Workbook

Sheet 首页
A1: 财税代理 · 多公司收支管理 ② 汇总报表（只看，不用录入）
A2: 💡 这本的数都取自【A065-1_流水发票导入.xlsx】（两本放同一个文件夹）。打开时 Excel/WPS 问「是否更新链接 / 启用内容」选「更新」，或者先打开 ① 那本再打开这本，数就是最新的。每张报表顶上的黄格子选公司（或全部）、年份、日期。这本里隐藏的「资金台帐 / 发票导入 / 基础资料 / 往来单位」是取数用的，别改。
A4: 数据到 | B4: =_辅助!$B$2 -> 46279 | C4: 资金台帐 | D4: =_辅助!$B$3&" 笔" -> 27 笔 | E4: 待处理（✗） | F4: =COUNTIF(资金台帐!$X$6:$X$6005,"✗*")&" 笔" -> 7 笔 | G4: 录入表校验 ✗ | H4: =_辅助!$B$1&" 项" -> 2 项
A6: 公司 | B6: 全部 | D6: 年份 | E6: 2026
A8: 本年收入 | B8: 变动利润 | C8: 利润 | D8: 本年新增客户 | E8: 资金余额（现在） | F8: 客户欠款＊ | G8: 欠供应商＊ | H8: 内部往来对不上
A9: =ROUND(SUMIFS(资金台帐!$AB$6:$AB$6005,资金台帐!$U$6:$U$6005,"收入",资金台帐!$O$6:$O$6005,IF($B$6="全部","?*",$B$6),资金台帐!$N$6:$N$6005,">="&DATE($E$6,1,1),资金台帐!$N$6:$N$6005,"<"&DATE($E$6+1,1,1))-SUMIFS(资金台帐!$AC$6:$AC$6005,资金台帐!$U$6:$U$6005,"收入",资金台帐!$O$6:$O$6005,IF($B$6="全部","?*",$B$6),资金台帐!$N$6:$N$6005,">="&DATE($E$6,1,1),资金台帐!$N$6:$N$6005,"<"&DATE($E$6+1,1,1)),2) -> 171000 | B9: =ROUND(SUMIFS(资金台帐!$AB$6:$AB$6005,资金台帐!$U$6:$U$6005,"收入",资金台帐!$O$6:$O$6005,IF($B$6="全部","?*",$B$6),资金台帐!$N$6:$N$6005,">="&DATE($E$6,1,1),资金台帐!$N$6:$N$6005,"<"&DATE($E$6+1,1,1))-SUMIFS(资金台帐!$AC$6:$AC$6005,资金台帐!$U$6:$U$6005,"收入",资金台帐!$O$6:$O$6005,IF($B$6="全部","?*",$B$6),资金台帐!$N$6:$N$6005,">="&DATE($E$6,1,1),资金台帐!$N$6:$N$6005,"<"&DATE($E$6+1,1,1))-(SUMIFS(资金台帐!$AC$6:$AC$6005,资金台帐!$U$6:$U$6005,"变动成本",资金台帐!$O$6:$O$6005,IF($B$6="全部","?*",$B$6),资金台帐!$N$6:$N$6005,">="&DATE($E$6,1,1),资金台帐!$N$6:$N$6005,"<"&DATE($E$6+1,1,1))-SUMIFS(资金台帐!$AB$6:$AB$6005,资金台帐!$U$6:$U$6005,"变动成本",资金台帐!$O$6:$O$6005,IF($B$6="全部","?*",$B$6),资金台帐!$N$6:$N$6005,">="&DATE($E$6,1,1),资金台帐!$N$6:$N$6005,"<"&DATE($E$6+1,1,1))),2) -> 148621.34 | C9: =ROUND(SUMIFS(资金台帐!$AB$6:$AB$6005,资金台帐!$U$6:$U$6005,"收入",资金台帐!$O$6:$O$6005,IF($B$6="全部","?*",$B$6),资金台帐!$N$6:$N$6005,">="&DATE($E$6,1,1),资金台帐!$N$6:$N$6005,"<"&DATE($E$6+1,1,1))-SUMIFS(资金台帐!$AC$6:$AC$6005,资金台帐!$U$6:$U$6005,"收入",资金台帐!$O$6:$O$6005,IF($B$6="全部","?*",$B$6),资金台帐!$N$6:$N$6005,">="&DATE($E$6,1,1),资金台帐!$N$6:$N$6005,"<"&DATE($E$6+1,1,1))-(SUMIFS(资金台帐!$AC$6:$AC$6005,资金台帐!$U$6:$U$6005,"变动成本",资金台帐!$O$6:$O$6005,IF($B$6="全部","?*",$B$6),资金台帐!$N$6:$N$6005,">="&DATE($E$6,1,1),资金台帐!$N$6:$N$6005,"<"&DATE($E$6+1,1,1))-SUMIFS(资金台帐!$AB$6:$AB$6005,资金台帐!$U$6:$U$6005,"变动成本",资金台帐!$O$6:$O$6005,IF($B$6="全部","?*",$B$6),资金台帐!$N$6:$N$6005,">="&DATE($E$6,1,1),资金台帐!$N$6:$N$6005,"<"&DATE($E$6+1,1,1)))-(SUMIFS(资金台帐!$AC$6:$AC$6005,资金台帐!$U$6:$U$6005,"固定成本",资金台帐!$O$6:$O$6005,IF($B$6="全部","?*",$B$6),资金台帐!$N$6:$N$6005,">="&DATE($E$6,1,1),资金台帐!$N$6:$N$6005,"<"&DATE($E$6+1,1,1))-SUMIFS(资金台帐!$AB$6:$AB$6005,资金台帐!$U$6:$U$6005,"固定成本",资金台帐!$O$6:$O$6005,IF($B$6="全部","?*",$B$6),资金台帐!$N$6:$N$6005,">="&DATE($E$6,1,1),资金台帐!$N$6:$N$6005,"<"&DATE($E$6+1,1,1))),2) -> 148621.34 | D9: =COUNTIFS(资金台帐!$T$6:$T$6005,"新增",资金台帐!$AB$6:$AB$6005,">0",资金台帐!$O$6:$O$6005,IF($B$6="全部","?*",$B$6),资金台帐!$N$6:$N$6005,">="&DATE($E$6,1,1),资金台帐!$N$6:$N$6005,"<"&DATE($E$6+1,1,1)) -> 13 | E9: =ROUND(SUMIFS(基础资料!$N$5:$N$24,基础资料!$J$5:$J$24,IF($B$6="全部","?*",$B$6))+SUMIFS(资金台帐!$AD$6:$AD$6005,资金台帐!$O$6:$O$6005,IF($B$6="全部","?*",$B$6)),2) -> 286034.11 | F9: =ROUND(SUMIF(应收应付汇总!$G$6:$G$606,">0"),2) -> 81300 | G9: =ROUND(SUMIF(应收应付汇总!$K$6:$K$606,">0"),2) -> 183.71 | H9: =COUNTIF(内部往来!$B$18:$I$25,"差*")/2+COUNTIF(内部往来!$C$39:$C$46,"✗*") -> 0
A10: 收入、利润、新增客户按上面选的公司和年份；资金余额是所选公司所有账户到现在；＊客户欠款、欠供应商按【应收应付汇总】里选的公司、年份（年底余额，只加正数）；内部往来对不上的看【内部往来】②和最下面。
A12: 表格导航（点表名直接跳过去）
A13: 表名 | B13: 干什么的 | F13: 你要做什么
A14: 收支汇总表 | B14: 「收支类型」× 1～12 月：收入、变动成本、变动利润、固定成本、利润 | F14: 选公司、年份看
A15: 简易现金流量表 | B15: 业务口径的简易现金流量表（经营 / 投资 / 筹资往来），跟账户余额核对 | F15: 选公司、年份看
A16: 资金余额表 | B16: 每个账户期初、收、支、期末，跟银行余额核对 | F16: 选公司、起止日期看
A17: 费用统计 | B17: 收入、各项费用按公司对比 | F17: 选年份、月份范围看
A18: 客户收入统计 | B18: 每月新增客户、新增/续费收入；每个客户首次来款、续费、应收 | F18: 选公司、年份看
A19: 应收应付汇总 | B19: 每个往来单位的应收、应付、其他往来（借款押金） | F19: 选公司、年份看
A20: 往来对账单 | B20: 给某个客户/供应商的对账单：发票、收付款逐笔带余额 | F20: 选公司、单位、起止日期
A21: 内部往来 | B21: 几家公司之间划转的钱谁欠谁、两边对不对得上；自家之间开的票 | F21: 选截止日看
A22: 发票汇总 | B22: 每月销项、进项发票金额，对照同月收付款 | F22: 选公司、年份看

Sheet 收支汇总表
A1: 收 支 汇 总 表（收支类型 × 1～12 月 · 按资金台帐实收实付）
A2: 💡 选公司、年份。行就是「收支类型」：收入 → 变动成本 → 变动利润 → 固定成本 → 利润，下面是其他支出、实收资本、投资、往来。收入类＝收进来减退出去；成本费用类＝付出去减退回来。账户互转、内部公司之间划转不算收入支出（最下面单列）。
B3: 公司 | C3: 全部 | E3: 年份 | F3: 2026
A4: 收支类型 | B4: 项目 | C4: 1月 | D4: 2月 | E4: 3月 | F4: 4月 | G4: 5月 | H4: 6月 | I4: 7月 | J4: 8月 | K4: 9月 | L4: 10月 | M4: 11月 | N4: 12月 | O4: 全年合计 | P4: 占收入 | Q4: 项目名
A5: 收入 | B5: =IF(基础资料!$W$5="",基础资料!$U$5&"",基础资料!$W$5&"") -> 项目 | C5: =ROUND(SUMIFS(资金台帐!$AB$6:$AB$6005,资金台帐!$T$6:$T$6005,$Q5,资金台帐!$U$6:$U$6005,"收入",资金台帐!$O$6:$O$6005,IF($C$3="全部","?*",$C$3),资金台帐!$N$6:$N$6005,">="&DATE($F$3,1,1),资金台帐!$N$6:$N$6005,"<"&DATE($F$3,1+1,1))-SUMIFS(资金台帐!$AC$6:$AC$6005,资金台帐!$T$6:$T$6005,$Q5,资金台帐!$U$6:$U$6005,"收入",资金台帐!$O$6:$O$6005,IF($C$3="全部","?*",$C$3),资金台帐!$N$6:$N$6005,">="&DATE($F$3,1,1),资金台帐!$N$6:$N$6005,"<"&DATE($F$3,1+1,1)),2) -> 0 | D5: =ROUND(SUMIFS(资金台帐!$AB$6:$AB$6005,资金台帐!$T$6:$T$6005,$Q5,资金台帐!$U$6:$U$6005,"收入",资金台帐!$O$6:$O$6005,IF($C$3="全部","?*",$C$3),资金台帐!$N$6:$N$6005,">="&DATE($F$3,2,1),资金台帐!$N$6:$N$6005,"<"&DATE($F$3,2+1,1))-SUMIFS(资金台帐!$AC$6:$AC$6005,资金台帐!$T$6:$T$6005,$Q5,资金台帐!$U$6:$U$6005,"收入",资金台帐!$O$6:$O$6005,IF($C$3="全部","?*",$C$3),资金台帐!$N$6:$N$6005,">="&DATE($F$3,2,1),资金台帐!$N$6:$N$6005,"<"&DATE($F$3,2+1,1)),2) -> 0 | E5: =ROUND(SUMIFS(资金台帐!$AB$6:$AB$6005,资金台帐!$T$6:$T$6005,$Q5,资金台帐!$U$6:$U$6005,"收入",资金台帐!$O$6:$O$6005,IF($C$3="全部","?*",$C$3),资金台帐!$N$6:$N$6005,">="&DATE($F$3,3,1),资金台帐!$N$6:$N$6005,"<"&DATE($F$3,3+1,1))-SUMIFS(资金台帐!$AC$6:$AC$6005,资金台帐!$T$6:$T$6005,$Q5,资金台帐!$U$6:$U$6005,"收入",资金台帐!$O$6:$O$6005,IF($C$3="全部","?*",$C$3),资金台帐!$N$6:$N$6005,">="&DATE($F$3,3,1),资金台帐!$N$6:$N$6005,"<"&DATE($F$3,3+1,1)),2) -> 0 | F5: =ROUND(SUMIFS(资金台帐!$AB$6:$AB$6005,资金台帐!$T$6:$T$6005,$Q5,资金台帐!$U$6:$U$6005,"收入",资金台帐!$O$6:$O$6005,IF($C$3="全部","?*",$C$3),资金台帐!$N$6:$N$6005,">="&DATE($F$3,4,1),资金台帐!$N$6:$N$6005,"<"&DATE($F$3,4+1,1))-SUMIFS(资金台帐!$AC$6:$AC$6005,资金台帐!$T$6:$T$6005,$Q5,资金台帐!$U$6:$U$6005,"收入",资金台帐!$O$6:$O$6005,IF($C$3="全部","?*",$C$3),资金台帐!$N$6:$N$6005,">="&DATE($F$3,4,1),资金台帐!$N$6:$N$6005,"<"&DATE($F$3,4+1,1)),2) -> 0 | G5: =ROUND(SUMIFS(资金台帐!$AB$6:$AB$6005,资金台帐!$T$6:$T$6005,$Q5,资金台帐!$U$6:$U$6005,"收入",资金台帐!$O$6:$O$6005,IF($C$3="全部","?*",$C$3),资金台帐!$N$6:$N$6005,">="&DATE($F$3,5,1),资金台帐!$N$6:$N$6005,"<"&DATE($F$3,5+1,1))-SUMIFS(资金台帐!$AC$6:$AC$6005,资金台帐!$T$6:$T$6005,$Q5,资金台帐!$U$6:$U$6005,"收入",资金台帐!$O$6:$O$6005,IF($C$3="全部","?*",$C$3),资金台帐!$N$6:$N$6005,">="&DATE($F$3,5,1),资金台帐!$N$6:$N$6005,"<"&DATE($F$3,5+1,1)),2) -> 0 | H5: =ROUND(SUMIFS(资金台帐!$AB$6:$AB$6005,资金台帐!$T$6:$T$6005,$Q5,资金台帐!$U$6:$U$6005,"收入",资金台帐!$O$6:$O$6005,IF($C$3="全部","?*",$C$3),资金台帐!$N$6:$N$6005,">="&DATE($F$3,6,1),资金台帐!$N$6:$N$6005,"<"&DATE($F$3,6+1,1))-SUMIFS(资金台帐!$AC$6:$AC$6005,资金台帐!$T$6:$T$6005,$Q5,资金台帐!$U$6:$U$6005,"收入",资金台帐!$O$6:$O$6005,IF($C$3="全部","?*",$C$3),资金台帐!$N$6:$N$6005,">="&DATE($F$3,6,1),资金台帐!$N$6:$N$6005,"<"&DATE($F$3,6+1,1)),2) -> 0 | I5: =ROUND(SUMIFS(资金台帐!$AB$6:$AB$6005,资金台帐!$T$6:$T$6005,$Q5,资金台帐!$U$6:$U$6005,"收入",资金台帐!$O$6:$O$6005,IF($C$3="全部","?*",$C$3),资金台帐!$N$6:$N$6005,">="&DATE($F$3,7,1),资金台帐!$N$6:$N$6005,"<"&DATE($F$3,7+1,1))-SUMIFS(资金台帐!$AC$6:$AC$6005,资金台帐!$T$6:$T$6005,$Q5,资金台帐!$U$6:$U$6005,"收入",资金台帐!$O$6:$O$6005,IF($C$3="全部","?*",$C$3),资金台帐!$N$6:$N$6005,">="&DATE($F$3,7,1),资金台帐!$N$6:$N$6005,"<"&DATE($F$3,7+1,1)),2) -> 0 | J5: =ROUND(SUMIFS(资金台帐!$AB$6:$AB$6005,资金台帐!$T$6:$T$6005,$Q5,资金台帐!$U$6:$U$6005,"收入",资金台帐!$O$6:$O$6005,IF($C$3="全部","?*",$C$3),资金台帐!$N$6:$N$6005,">="&DATE($F$3,8,1),资金台帐!$N$6:$N$6005,"<"&DATE($F$3,8+1,1))-SUMIFS(资金台帐!$AC$6:$AC$6005,资金台帐!$T$6:$T$6005,$Q5,资金台帐!$U$6:$U$6005,"收入",资金台帐!$O$6:$O$6005,IF($C$3="全部","?*",$C$3),资金台帐!$N$6:$N$6005,">="&DATE($F$3,8,1),资金台帐!$N$6:$N$6005,"<"&DATE($F$3,8+1,1)),2) -> 0 | K5: =ROUND(SUMIFS(资金台帐!$AB$6:$AB$6005,资金台帐!$T$6:$T$6005,$Q5,资金台帐!$U$6:$U$6005,"收入",资金台帐!$O$6:$O$6005,IF($C$3="全部","?*",$C$3),资金台帐!$N$6:$N$6005,">="&DATE($F$3,9,1),资金台帐!$N$6:$N$6005,"<"&DATE($F$3,9+1,1))-SUMIFS(资金台帐!$AC$6:$AC$6005,资金台帐!$T$6:$T$6005,$Q5,资金台帐!$U$6:$U$6005,"收入",资金台帐!$O$6:$O$6005,IF($C$3="全部","?*",$C$3),资金台帐!$N$6:$N$6005,">="&DATE($F$3,9,1),资金台帐!$N$6:$N$6005,"<"&DATE($F$3,9+1,1)),2) -> 0 | L5: =ROUND(SUMIFS(资金台帐!$AB$6:$AB$6005,资金台帐!$T$6:$T$6005,$Q5,资金台帐!$U$6:$U$6005,"收入",资金台帐!$O$6:$O$6005,IF($C$3="全部","?*",$C$3),资金台帐!$N$6:$N$6005,">="&DATE($F$3,10,1),资金台帐!$N$6:$N$6005,"<"&DATE($F$3,10+1,1))-SUMIFS(资金台帐!$AC$6:$AC$6005,资金台帐!$T$6:$T$6005,$Q5,资金台帐!$U$6:$U$6005,"收入",资金台帐!$O$6:$O$6005,IF($C$3="全部","?*",$C$3),资金台帐!$N$6:$N$6005,">="&DATE($F$3,10,1),资金台帐!$N$6:$N$6005,"<"&DATE($F$3,10+1,1)),2) -> 0 | M5: =ROUND(SUMIFS(资金台帐!$AB$6:$AB$6005,资金台帐!$T$6:$T$6005,$Q5,资金台帐!$U$6:$U$6005,"收入",资金台帐!$O$6:$O$6005,IF($C$3="全部","?*",$C$3),资金台帐!$N$6:$N$6005,">="&DATE($F$3,11,1),资金台帐!$N$6:$N$6005,"<"&DATE($F$3,11+1,1))-SUMIFS(资金台帐!$AC$6:$AC$6005,资金台帐!$T$6:$T$6005,$Q5,资金台帐!$U$6:$U$6005,"收入",资金台帐!$O$6:$O$6005,IF($C$3="全部","?*",$C$3),资金台帐!$N$6:$N$6005,">="&DATE($F$3,11,1),资金台帐!$N$6:$N$6005,"<"&DATE($F$3,11+1,1)),2) -> 0 | N5: =ROUND(SUMIFS(资金台帐!$AB$6:$AB$6005,资金台帐!$T$6:$T$6005,$Q5,资金台帐!$U$6:$U$6005,"收入",资金台帐!$O$6:$O$6005,IF($C$3="全部","?*",$C$3),资金台帐!$N$6:$N$6005,">="&DATE($F$3,12,1),资金台帐!$N$6:$N$6005,"<"&DATE($F$3,12+1,1))-SUMIFS(资金台帐!$AC$6:$AC$6005,资金台帐!$T$6:$T$6005,$Q5,资金台帐!$U$6:$U$6005,"收入",资金台帐!$O$6:$O$6005,IF($C$3="全部","?*",$C$3),资金台帐!$N$6:$N$6005,">="&DATE($F$3,12,1),资金台帐!$N$6:$N$6005,"<"&DATE($F$3,12+1,1)),2) -> 0 | O5: =ROUND(SUM(C5:N5),2) -> 0 | P5: =IF(N($O$16)=0,"",O5/$O$16) -> 0 | Q5: =基础资料!$U$5&"" -> 项目
B6: =IF(基础资料!$W$6="",基础资料!$U$6&"",基础资料!$W$6&"") -> 续费 | C6: =ROUND(SUMIFS(资金台帐!$AB$6:$AB$6005,资金台帐!$T$6:$T$6005,$Q6,资金台帐!$U$6:$U$6005,"收入",资金台帐!$O$6:$O$6005,IF($C$3="全部","?*",$C$3),资金台帐!$N$6:$N$6005,">="&DATE($F$3,1,1),资金台帐!$N$6:$N$6005,"<"&DATE($F$3,1+1,1))-SUMIFS(资金台帐!$AC$6:$AC$6005,资金台帐!$T$6:$T$6005,$Q6,资金台帐!$U$6:$U$6005,"收入",资金台帐!$O$6:$O$6005,IF($C$3="全部","?*",$C$3),资金台帐!$N$6:$N$6005,">="&DATE($F$3,1,1),资金台帐!$N$6:$N$6005,"<"&DATE($F$3,1+1,1)),2) -> 0 | D6: =ROUND(SUMIFS(资金台帐!$AB$6:$AB$6005,资金台帐!$T$6:$T$6005,$Q6,资金台帐!$U$6:$U$6005,"收入",资金台帐!$O$6:$O$6005,IF($C$3="全部","?*",$C$3),资金台帐!$N$6:$N$6005,">="&DATE($F$3,2,1),资金台帐!$N$6:$N$6005,"<"&DATE($F$3,2+1,1))-SUMIFS(资金台帐!$AC$6:$AC$6005,资金台帐!$T$6:$T$6005,$Q6,资金台帐!$U$6:$U$6005,"收入",资金台帐!$O$6:$O$6005,IF($C$3="全部","?*",$C$3),资金台帐!$N$6:$N$6005,">="&DATE($F$3,2,1),资金台帐!$N$6:$N$6005,"<"&DATE($F$3,2+1,1)),2) -> 0 | E6: =ROUND(SUMIFS(资金台帐!$AB$6:$AB$6005,资金台帐!$T$6:$T$6005,$Q6,资金台帐!$U$6:$U$6005,"收入",资金台帐!$O$6:$O$6005,IF($C$3="全部","?*",$C$3),资金台帐!$N$6:$N$6005,">="&DATE($F$3,3,1),资金台帐!$N$6:$N$6005,"<"&DATE($F$3,3+1,1))-SUMIFS(资金台帐!$AC$6:$AC$6005,资金台帐!$T$6:$T$6005,$Q6,资金台帐!$U$6:$U$6005,"收入",资金台帐!$O$6:$O$6005,IF($C$3="全部","?*",$C$3),资金台帐!$N$6:$N$6005,">="&DATE($F$3,3,1),资金台帐!$N$6:$N$6005,"<"&DATE($F$3,3+1,1)),2) -> 0 | F6: =ROUND(SUMIFS(资金台帐!$AB$6:$AB$6005,资金台帐!$T$6:$T$6005,$Q6,资金台帐!$U$6:$U$6005,"收入",资金台帐!$O$6:$O$6005,IF($C$3="全部","?*",$C$3),资金台帐!$N$6:$N$6005,">="&DATE($F$3,4,1),资金台帐!$N$6:$N$6005,"<"&DATE($F$3,4+1,1))-SUMIFS(资金台帐!$AC$6:$AC$6005,资金台帐!$T$6:$T$6005,$Q6,资金台帐!$U$6:$U$6005,"收入",资金台帐!$O$6:$O$6005,IF($C$3="全部","?*",$C$3),资金台帐!$N$6:$N$6005,">="&DATE($F$3,4,1),资金台帐!$N$6:$N$6005,"<"&DATE($F$3,4+1,1)),2) -> 0 | G6: =ROUND(SUMIFS(资金台帐!$AB$6:$AB$6005,资金台帐!$T$6:$T$6005,$Q6,资金台帐!$U$6:$U$6005,"收入",资金台帐!$O$6:$O$6005,IF($C$3="全部","?*",$C$3),资金台帐!$N$6:$N$6005,">="&DATE($F$3,5,1),资金台帐!$N$6:$N$6005,"<"&DATE($F$3,5+1,1))-SUMIFS(资金台帐!$AC$6:$AC$6005,资金台帐!$T$6:$T$6005,$Q6,资金台帐!$U$6:$U$6005,"收入",资金台帐!$O$6:$O$6005,IF($C$3="全部","?*",$C$3),资金台帐!$N$6:$N$6005,">="&DATE($F$3,5,1),资金台帐!$N$6:$N$6005,"<"&DATE($F$3,5+1,1)),2) -> 0 | H6: =ROUND(SUMIFS(资金台帐!$AB$6:$AB$6005,资金台帐!$T$6:$T$6005,$Q6,资金台帐!$U$6:$U$6005,"收入",资金台帐!$O$6:$O$6005,IF($C$3="全部","?*",$C$3),资金台帐!$N$6:$N$6005,">="&DATE($F$3,6,1),资金台帐!$N$6:$N$6005,"<"&DATE($F$3,6+1,1))-SUMIFS(资金台帐!$AC$6:$AC$6005,资金台帐!$T$6:$T$6005,$Q6,资金台帐!$U$6:$U$6005,"收入",资金台帐!$O$6:$O$6005,IF($C$3="全部","?*",$C$3),资金台帐!$N$6:$N$6005,">="&DATE($F$3,6,1),资金台帐!$N$6:$N$6005,"<"&DATE($F$3,6+1,1)),2) -> 0 | I6: =ROUND(SUMIFS(资金台帐!$AB$6:$AB$6005,资金台帐!$T$6:$T$6005,$Q6,资金台帐!$U$6:$U$6005,"收入",资金台帐!$O$6:$O$6005,IF($C$3="全部","?*",$C$3),资金台帐!$N$6:$N$6005,">="&DATE($F$3,7,1),资金台帐!$N$6:$N$6005,"<"&DATE($F$3,7+1,1))-SUMIFS(资金台帐!$AC$6:$AC$6005,资金台帐!$T$6:$T$6005,$Q6,资金台帐!$U$6:$U$6005,"收入",资金台帐!$O$6:$O$6005,IF($C$3="全部","?*",$C$3),资金台帐!$N$6:$N$6005,">="&DATE($F$3,7,1),资金台帐!$N$6:$N$6005,"<"&DATE($F$3,7+1,1)),2) -> 0 | J6: =ROUND(SUMIFS(资金台帐!$AB$6:$AB$6005,资金台帐!$T$6:$T$6005,$Q6,资金台帐!$U$6:$U$6005,"收入",资金台帐!$O$6:$O$6005,IF($C$3="全部","?*",$C$3),资金台帐!$N$6:$N$6005,">="&DATE($F$3,8,1),资金台帐!$N$6:$N$6005,"<"&DATE($F$3,8+1,1))-SUMIFS(资金台帐!$AC$6:$AC$6005,资金台帐!$T$6:$T$6005,$Q6,资金台帐!$U$6:$U$6005,"收入",资金台帐!$O$6:$O$6005,IF($C$3="全部","?*",$C$3),资金台帐!$N$6:$N$6005,">="&DATE($F$3,8,1),资金台帐!$N$6:$N$6005,"<"&DATE($F$3,8+1,1)),2) -> 0 | K6: =ROUND(SUMIFS(资金台帐!$AB$6:$AB$6005,资金台帐!$T$6:$T$6005,$Q6,资金台帐!$U$6:$U$6005,"收入",资金台帐!$O$6:$O$6005,IF($C$3="全部","?*",$C$3),资金台帐!$N$6:$N$6005,">="&DATE($F$3,9,1),资金台帐!$N$6:$N$6005,"<"&DATE($F$3,9+1,1))-SUMIFS(资金台帐!$AC$6:$AC$6005,资金台帐!$T$6:$T$6005,$Q6,资金台帐!$U$6:$U$6005,"收入",资金台帐!$O$6:$O$6005,IF($C$3="全部","?*",$C$3),资金台帐!$N$6:$N$6005,">="&DATE($F$3,9,1),资金台帐!$N$6:$N$6005,"<"&DATE($F$3,9+1,1)),2) -> 0 | L6: =ROUND(SUMIFS(资金台帐!$AB$6:$AB$6005,资金台帐!$T$6:$T$6005,$Q6,资金台帐!$U$6:$U$6005,"收入",资金台帐!$O$6:$O$6005,IF($C$3="全部","?*",$C$3),资金台帐!$N$6:$N$6005,">="&DATE($F$3,10,1),资金台帐!$N$6:$N$6005,"<"&DATE($F$3,10+1,1))-SUMIFS(资金台帐!$AC$6:$AC$6005,资金台帐!$T$6:$T$6005,$Q6,资金台帐!$U$6:$U$6005,"收入",资金台帐!$O$6:$O$6005,IF($C$3="全部","?*",$C$3),资金台帐!$N$6:$N$6005,">="&DATE($F$3,10,1),资金台帐!$N$6:$N$6005,"<"&DATE($F$3,10+1,1)),2) -> 0 | M6: =ROUND(SUMIFS(资金台帐!$AB$6:$AB$6005,资金台帐!$T$6:$T$6005,$Q6,资金台帐!$U$6:$U$6005,"收入",资金台帐!$O$6:$O$6005,IF($C$3="全部","?*",$C$3),资金台帐!$N$6:$N$6005,">="&DATE($F$3,11,1),资金台帐!$N$6:$N$6005,"<"&DATE($F$3,11+1,1))-SUMIFS(资金台帐!$AC$6:$AC$6005,资金台帐!$T$6:$T$6005,$Q6,资金台帐!$U$6:$U$6005,"收入",资金台帐!$O$6:$O$6005,IF($C$3="全部","?*",$C$3),资金台帐!$N$6:$N$6005,">="&DATE($F$3,11,1),资金台帐!$N$6:$N$6005,"<"&DATE($F$3,11+1,1)),2) -> 0 | N6: =ROUND(SUMIFS(资金台帐!$AB$6:$AB$6005,资金台帐!$T$6:$T$6005,$Q6,资金台帐!$U$6:$U$6005,"收入",资金台帐!$O$6:$O$6005,IF($C$3="全部","?*",$C$3),资金台帐!$N$6:$N$6005,">="&DATE($F$3,12,1),资金台帐!$N$6:$N$6005,"<"&DATE($F$3,12+1,1))-SUMIFS(资金台帐!$AC$6:$AC$6005,资金台帐!$T$6:$T$6005,$Q6,资金台帐!$U$6:$U$6005,"收入",资金台帐!$O$6:$O$6005,IF($C$3="全部","?*",$C$3),资金台帐!$N$6:$N$6005,">="&DATE($F$3,12,1),资金台帐!$N$6:$N$6005,"<"&DATE($F$3,12+1,1)),2) -> 0 | O6: =ROUND(SUM(C6:N6),2) -> 0 | P6: =IF(N($O$16)=0,"",O6/$O$16) -> 0 | Q6: =基础资料!$U$6&"" -> 续费
B7: =IF(基础资料!$W$7="",基础资料!$U$7&"",基础资料!$W$7&"") -> 新增 | C7: =ROUND(SUMIFS(资金台帐!$AB$6:$AB$6005,资金台帐!$T$6:$T$6005,$Q7,资金台帐!$U$6:$U$6005,"收入",资金台帐!$O$6:$O$6005,IF($C$3="全部","?*",$C$3),资金台帐!$N$6:$N$6005,">="&DATE($F$3,1,1),资金台帐!$N$6:$N$6005,"<"&DATE($F$3,1+1,1))-SUMIFS(资金台帐!$AC$6:$AC$6005,资金台帐!$T$6:$T$6005,$Q7,资金台帐!$U$6:$U$6005,"收入",资金台帐!$O$6:$O$6005,IF($C$3="全部","?*",$C$3),资金台帐!$N$6:$N$6005,">="&DATE($F$3,1,1),资金台帐!$N$6:$N$6005,"<"&DATE($F$3,1+1,1)),2) -> 0 | D7: =ROUND(SUMIFS(资金台帐!$AB$6:$AB$6005,资金台帐!$T$6:$T$6005,$Q7,资金台帐!$U$6:$U$6005,"收入",资金台帐!$O$6:$O$6005,IF($C$3="全部","?*",$C$3),资金台帐!$N$6:$N$6005,">="&DATE($F$3,2,1),资金台帐!$N$6:$N$6005,"<"&DATE($F$3,2+1,1))-SUMIFS(资金台帐!$AC$6:$AC$6005,资金台帐!$T$6:$T$6005,$Q7,资金台帐!$U$6:$U$6005,"收入",资金台帐!$O$6:$O$6005,IF($C$3="全部","?*",$C$3),资金台帐!$N$6:$N$6005,">="&DATE($F$3,2,1),资金台帐!$N$6:$N$6005,"<"&DATE($F$3,2+1,1)),2) -> 0 | E7: =ROUND(SUMIFS(资金台帐!$AB$6:$AB$6005,资金台帐!$T$6:$T$6005,$Q7,资金台帐!$U$6:$U$6005,"收入",资金台帐!$O$6:$O$6005,IF($C$3="全部","?*",$C$3),资金台帐!$N$6:$N$6005,">="&DATE($F$3,3,1),资金台帐!$N$6:$N$6005,"<"&DATE($F$3,3+1,1))-SUMIFS(资金台帐!$AC$6:$AC$6005,资金台帐!$T$6:$T$6005,$Q7,资金台帐!$U$6:$U$6005,"收入",资金台帐!$O$6:$O$6005,IF($C$3="全部","?*",$C$3),资金台帐!$N$6:$N$6005,">="&DATE($F$3,3,1),资金台帐!$N$6:$N$6005,"<"&DATE($F$3,3+1,1)),2) -> 0 | F7: =ROUND(SUMIFS(资金台帐!$AB$6:$AB$6005,资金台帐!$T$6:$T$6005,$Q7,资金台帐!$U$6:$U$6005,"收入",资金台帐!$O$6:$O$6005,IF($C$3="全部","?*",$C$3),资金台帐!$N$6:$N$6005,">="&DATE($F$3,4,1),资金台帐!$N$6:$N$6005,"<"&DATE($F$3,4+1,1))-SUMIFS(资金台帐!$AC$6:$AC$6005,资金台帐!$T$6:$T$6005,$Q7,资金台帐!$U$6:$U$6005,"收入",资金台帐!$O$6:$O$6005,IF($C$3="全部","?*",$C$3),资金台帐!$N$6:$N$6005,">="&DATE($F$3,4,1),资金台帐!$N$6:$N$6005,"<"&DATE($F$3,4+1,1)),2) -> 0 | G7: =ROUND(SUMIFS(资金台帐!$AB$6:$AB$6005,资金台帐!$T$6:$T$6005,$Q7,资金台帐!$U$6:$U$6005,"收入",资金台帐!$O$6:$O$6005,IF($C$3="全部","?*",$C$3),资金台帐!$N$6:$N$6005,">="&DATE($F$3,5,1),资金台帐!$N$6:$N$6005,"<"&DATE($F$3,5+1,1))-SUMIFS(资金台帐!$AC$6:$AC$6005,资金台帐!$T$6:$T$6005,$Q7,资金台帐!$U$6:$U$6005,"收入",资金台帐!$O$6:$O$6005,IF($C$3="全部","?*",$C$3),资金台帐!$N$6:$N$6005,">="&DATE($F$3,5,1),资金台帐!$N$6:$N$6005,"<"&DATE($F$3,5+1,1)),2) -> 0 | H7: =ROUND(SUMIFS(资金台帐!$AB$6:$AB$6005,资金台帐!$T$6:$T$6005,$Q7,资金台帐!$U$6:$U$6005,"收入",资金台帐!$O$6:$O$6005,IF($C$3="全部","?*",$C$3),资金台帐!$N$6:$N$6005,">="&DATE($F$3,6,1),资金台帐!$N$6:$N$6005,"<"&DATE($F$3,6+1,1))-SUMIFS(资金台帐!$AC$6:$AC$6005,资金台帐!$T$6:$T$6005,$Q7,资金台帐!$U$6:$U$6005,"收入",资金台帐!$O$6:$O$6005,IF($C$3="全部","?*",$C$3),资金台帐!$N$6:$N$6005,">="&DATE($F$3,6,1),资金台帐!$N$6:$N$6005,"<"&DATE($F$3,6+1,1)),2) -> 0 | I7: =ROUND(SUMIFS(资金台帐!$AB$6:$AB$6005,资金台帐!$T$6:$T$6005,$Q7,资金台帐!$U$6:$U$6005,"收入",资金台帐!$O$6:$O$6005,IF($C$3="全部","?*",$C$3),资金台帐!$N$6:$N$6005,">="&DATE($F$3,7,1),资金台帐!$N$6:$N$6005,"<"&DATE($F$3,7+1,1))-SUMIFS(资金台帐!$AC$6:$AC$6005,资金台帐!$T$6:$T$6005,$Q7,资金台帐!$U$6:$U$6005,"收入",资金台帐!$O$6:$O$6005,IF($C$3="全部","?*",$C$3),资金台帐!$N$6:$N$6005,">="&DATE($F$3,7,1),资金台帐!$N$6:$N$6005,"<"&DATE($F$3,7+1,1)),2) -> 0 | J7: =ROUND(SUMIFS(资金台帐!$AB$6:$AB$6005,资金台帐!$T$6:$T$6005,$Q7,资金台帐!$U$6:$U$6005,"收入",资金台帐!$O$6:$O$6005,IF($C$3="全部","?*",$C$3),资金台帐!$N$6:$N$6005,">="&DATE($F$3,8,1),资金台帐!$N$6:$N$6005,"<"&DATE($F$3,8+1,1))-SUMIFS(资金台帐!$AC$6:$AC$6005,资金台帐!$T$6:$T$6005,$Q7,资金台帐!$U$6:$U$6005,"收入",资金台帐!$O$6:$O$6005,IF($C$3="全部","?*",$C$3),资金台帐!$N$6:$N$6005,">="&DATE($F$3,8,1),资金台帐!$N$6:$N$6005,"<"&DATE($F$3,8+1,1)),2) -> 0 | K7: =ROUND(SUMIFS(资金台帐!$AB$6:$AB$6005,资金台帐!$T$6:$T$6005,$Q7,资金台帐!$U$6:$U$6005,"收入",资金台帐!$O$6:$O$6005,IF($C$3="全部","?*",$C$3),资金台帐!$N$6:$N$6005,">="&DATE($F$3,9,1),资金台帐!$N$6:$N$6005,"<"&DATE($F$3,9+1,1))-SUMIFS(资金台帐!$AC$6:$AC$6005,资金台帐!$T$6:$T$6005,$Q7,资金台帐!$U$6:$U$6005,"收入",资金台帐!$O$6:$O$6005,IF($C$3="全部","?*",$C$3),资金台帐!$N$6:$N$6005,">="&DATE($F$3,9,1),资金台帐!$N$6:$N$6005,"<"&DATE($F$3,9+1,1)),2) -> 171000 | L7: =ROUND(SUMIFS(资金台帐!$AB$6:$AB$6005,资金台帐!$T$6:$T$6005,$Q7,资金台帐!$U$6:$U$6005,"收入",资金台帐!$O$6:$O$6005,IF($C$3="全部","?*",$C$3),资金台帐!$N$6:$N$6005,">="&DATE($F$3,10,1),资金台帐!$N$6:$N$6005,"<"&DATE($F$3,10+1,1))-SUMIFS(资金台帐!$AC$6:$AC$6005,资金台帐!$T$6:$T$6005,$Q7,资金台帐!$U$6:$U$6005,"收入",资金台帐!$O$6:$O$6005,IF($C$3="全部","?*",$C$3),资金台帐!$N$6:$N$6005,">="&DATE($F$3,10,1),资金台帐!$N$6:$N$6005,"<"&DATE($F$3,10+1,1)),2) -> 0 | M7: =ROUND(SUMIFS(资金台帐!$AB$6:$AB$6005,资金台帐!$T$6:$T$6005,$Q7,资金台帐!$U$6:$U$6005,"收入",资金台帐!$O$6:$O$6005,IF($C$3="全部","?*",$C$3),资金台帐!$N$6:$N$6005,">="&DATE($F$3,11,1),资金台帐!$N$6:$N$6005,"<"&DATE($F$3,11+1,1))-SUMIFS(资金台帐!$AC$6:$AC$6005,资金台帐!$T$6:$T$6005,$Q7,资金台帐!$U$6:$U$6005,"收入",资金台帐!$O$6:$O$6005,IF($C$3="全部","?*",$C$3),资金台帐!$N$6:$N$6005,">="&DATE($F$3,11,1),资金台帐!$N$6:$N$6005,"<"&DATE($F$3,11+1,1)),2) -> 0 | N7: =ROUND(SUMIFS(资金台帐!$AB$6:$AB$6005,资金台帐!$T$6:$T$6005,$Q7,资金台帐!$U$6:$U$6005,"收入",资金台帐!$O$6:$O$6005,IF($C$3="全部","?*",$C$3),资金台帐!$N$6:$N$6005,">="&DATE($F$3,12,1),资金台帐!$N$6:$N$6005,"<"&DATE($F$3,12+1,1))-SUMIFS(资金台帐!$AC$6:$AC$6005,资金台帐!$T$6:$T$6005,$Q7,资金台帐!$U$6:$U$6005,"收入",资金台帐!$O$6:$O$6005,IF($C$3="全部","?*",$C$3),资金台帐!$N$6:$N$6005,">="&DATE($F$3,12,1),资金台帐!$N$6:$N$6005,"<"&DATE($F$3,12+1,1)),2) -> 0 | O7: =ROUND(SUM(C7:N7),2) -> 171000 | P7: =IF(N($O$16)=0,"",O7/$O$16) -> 1 | Q7: =基础资料!$U$7&"" -> 新增
B8: =IF(基础资料!$W$8="",基础资料!$U$8&"",基础资料!$W$8&"") -> 代办 | C8: =ROUND(SUMIFS(资金台帐!$AB$6:$AB$6005,资金台帐!$T$6:$T$6005,$Q8,资金台帐!$U$6:$U$6005,"收入",资金台帐!$O$6:$O$6005,IF($C$3="全部","?*",$C$3),资金台帐!$N$6:$N$6005,">="&DATE($F$3,1,1),资金台帐!$N$6:$N$6005,"<"&DATE($F$3,1+1,1))-SUMIFS(资金台帐!$AC$6:$AC$6005,资金台帐!$T$6:$T$6005,$Q8,资金台帐!$U$6:$U$6005,"收入",资金台帐!$O$6:$O$6005,IF($C$3="全部","?*",$C$3),资金台帐!$N$6:$N$6005,">="&DATE($F$3,1,1),资金台帐!$N$6:$N$6005,"<"&DATE($F$3,1+1,1)),2) -> 0 | D8: =ROUND(SUMIFS(资金台帐!$AB$6:$AB$6005,资金台帐!$T$6:$T$6005,$Q8,资金台帐!$U$6:$U$6005,"收入",资金台帐!$O$6:$O$6005,IF($C$3="全部","?*",$C$3),资金台帐!$N$6:$N$6005,">="&DATE($F$3,2,1),资金台帐!$N$6:$N$6005,"<"&DATE($F$3,2+1,1))-SUMIFS(资金台帐!$AC$6:$AC$6005,资金台帐!$T$6:$T$6005,$Q8,资金台帐!$U$6:$U$6005,"收入",资金台帐!$O$6:$O$6005,IF($C$3="全部","?*",$C$3),资金台帐!$N$6:$N$6005,">="&DATE($F$3,2,1),资金台帐!$N$6:$N$6005,"<"&DATE($F$3,2+1,1)),2) -> 0 | E8: =ROUND(SUMIFS(资金台帐!$AB$6:$AB$6005,资金台帐!$T$6:$T$6005,$Q8,资金台帐!$U$6:$U$6005,"收入",资金台帐!$O$6:$O$6005,IF($C$3="全部","?*",$C$3),资金台帐!$N$6:$N$6005,">="&DATE($F$3,3,1),资金台帐!$N$6:$N$6005,"<"&DATE($F$3,3+1,1))-SUMIFS(资金台帐!$AC$6:$AC$6005,资金台帐!$T$6:$T$6005,$Q8,资金台帐!$U$6:$U$6005,"收入",资金台帐!$O$6:$O$6005,IF($C$3="全部","?*",$C$3),资金台帐!$N$6:$N$6005,">="&DATE($F$3,3,1),资金台帐!$N$6:$N$6005,"<"&DATE($F$3,3+1,1)),2) -> 0 | F8: =ROUND(SUMIFS(资金台帐!$AB$6:$AB$6005,资金台帐!$T$6:$T$6005,$Q8,资金台帐!$U$6:$U$6005,"收入",资金台帐!$O$6:$O$6005,IF($C$3="全部","?*",$C$3),资金台帐!$N$6:$N$6005,">="&DATE($F$3,4,1),资金台帐!$N$6:$N$6005,"<"&DATE($F$3,4+1,1))-SUMIFS(资金台帐!$AC$6:$AC$6005,资金台帐!$T$6:$T$6005,$Q8,资金台帐!$U$6:$U$6005,"收入",资金台帐!$O$6:$O$6005,IF($C$3="全部","?*",$C$3),资金台帐!$N$6:$N$6005,">="&DATE($F$3,4,1),资金台帐!$N$6:$N$6005,"<"&DATE($F$3,4+1,1)),2) -> 0 | G8: =ROUND(SUMIFS(资金台帐!$AB$6:$AB$6005,资金台帐!$T$6:$T$6005,$Q8,资金台帐!$U$6:$U$6005,"收入",资金台帐!$O$6:$O$6005,IF($C$3="全部","?*",$C$3),资金台帐!$N$6:$N$6005,">="&DATE($F$3,5,1),资金台帐!$N$6:$N$6005,"<"&DATE($F$3,5+1,1))-SUMIFS(资金台帐!$AC$6:$AC$6005,资金台帐!$T$6:$T$6005,$Q8,资金台帐!$U$6:$U$6005,"收入",资金台帐!$O$6:$O$6005,IF($C$3="全部","?*",$C$3),资金台帐!$N$6:$N$6005,">="&DATE($F$3,5,1),资金台帐!$N$6:$N$6005,"<"&DATE($F$3,5+1,1)),2) -> 0 | H8: =ROUND(SUMIFS(资金台帐!$AB$6:$AB$6005,资金台帐!$T$6:$T$6005,$Q8,资金台帐!$U$6:$U$6005,"收入",资金台帐!$O$6:$O$6005,IF($C$3="全部","?*",$C$3),资金台帐!$N$6:$N$6005,">="&DATE($F$3,6,1),资金台帐!$N$6:$N$6005,"<"&DATE($F$3,6+1,1))-SUMIFS(资金台帐!$AC$6:$AC$6005,资金台帐!$T$6:$T$6005,$Q8,资金台帐!$U$6:$U$6005,"收入",资金台帐!$O$6:$O$6005,IF($C$3="全部","?*",$C$3),资金台帐!$N$6:$N$6005,">="&DATE($F$3,6,1),资金台帐!$N$6:$N$6005,"<"&DATE($F$3,6+1,1)),2) -> 0 | I8: =ROUND(SUMIFS(资金台帐!$AB$6:$AB$6005,资金台帐!$T$6:$T$6005,$Q8,资金台帐!$U$6:$U$6005,"收入",资金台帐!$O$6:$O$6005,IF($C$3="全部","?*",$C$3),资金台帐!$N$6:$N$6005,">="&DATE($F$3,7,1),资金台帐!$N$6:$N$6005,"<"&DATE($F$3,7+1,1))-SUMIFS(资金台帐!$AC$6:$AC$6005,资金台帐!$T$6:$T$6005,$Q8,资金台帐!$U$6:$U$6005,"收入",资金台帐!$O$6:$O$6005,IF($C$3="全部","?*",$C$3),资金台帐!$N$6:$N$6005,">="&DATE($F$3,7,1),资金台帐!$N$6:$N$6005,"<"&DATE($F$3,7+1,1)),2) -> 0 | J8: =ROUND(SUMIFS(资金台帐!$AB$6:$AB$6005,资金台帐!$T$6:$T$6005,$Q8,资金台帐!$U$6:$U$6005,"收入",资金台帐!$O$6:$O$6005,IF($C$3="全部","?*",$C$3),资金台帐!$N$6:$N$6005,">="&DATE($F$3,8,1),资金台帐!$N$6:$N$6005,"<"&DATE($F$3,8+1,1))-SUMIFS(资金台帐!$AC$6:$AC$6005,资金台帐!$T$6:$T$6005,$Q8,资金台帐!$U$6:$U$6005,"收入",资金台帐!$O$6:$O$6005,IF($C$3="全部","?*",$C$3),资金台帐!$N$6:$N$6005,">="&DATE($F$3,8,1),资金台帐!$N$6:$N$6005,"<"&DATE($F$3,8+1,1)),2) -> 0 | K8: =ROUND(SUMIFS(资金台帐!$AB$6:$AB$6005,资金台帐!$T$6:$T$6005,$Q8,资金台帐!$U$6:$U$6005,"收入",资金台帐!$O$6:$O$6005,IF($C$3="全部","?*",$C$3),资金台帐!$N$6:$N$6005,">="&DATE($F$3,9,1),资金台帐!$N$6:$N$6005,"<"&DATE($F$3,9+1,1))-SUMIFS(资金台帐!$AC$6:$AC$6005,资金台帐!$T$6:$T$6005,$Q8,资金台帐!$U$6:$U$6005,"收入",资金台帐!$O$6:$O$6005,IF($C$3="全部","?*",$C$3),资金台帐!$N$6:$N$6005,">="&DATE($F$3,9,1),资金台帐!$N$6:$N$6005,"<"&DATE($F$3,9+1,1)),2) -> 0 | L8: =ROUND(SUMIFS(资金台帐!$AB$6:$AB$6005,资金台帐!$T$6:$T$6005,$Q8,资金台帐!$U$6:$U$6005,"收入",资金台帐!$O$6:$O$6005,IF($C$3="全部","?*",$C$3),资金台帐!$N$6:$N$6005,">="&DATE($F$3,10,1),资金台帐!$N$6:$N$6005,"<"&DATE($F$3,10+1,1))-SUMIFS(资金台帐!$AC$6:$AC$6005,资金台帐!$T$6:$T$6005,$Q8,资金台帐!$U$6:$U$6005,"收入",资金台帐!$O$6:$O$6005,IF($C$3="全部","?*",$C$3),资金台帐!$N$6:$N$6005,">="&DATE($F$3,10,1),资金台帐!$N$6:$N$6005,"<"&DATE($F$3,10+1,1)),2) -> 0 | M8: =ROUND(SUMIFS(资金台帐!$AB$6:$AB$6005,资金台帐!$T$6:$T$6005,$Q8,资金台帐!$U$6:$U$6005,"收入",资金台帐!$O$6:$O$6005,IF($C$3="全部","?*",$C$3),资金台帐!$N$6:$N$6005,">="&DATE($F$3,11,1),资金台帐!$N$6:$N$6005,"<"&DATE($F$3,11+1,1))-SUMIFS(资金台帐!$AC$6:$AC$6005,资金台帐!$T$6:$T$6005,$Q8,资金台帐!$U$6:$U$6005,"收入",资金台帐!$O$6:$O$6005,IF($C$3="全部","?*",$C$3),资金台帐!$N$6:$N$6005,">="&DATE($F$3,11,1),资金台帐!$N$6:$N$6005,"<"&DATE($F$3,11+1,1)),2) -> 0 | N8: =ROUND(SUMIFS(资金台帐!$AB$6:$AB$6005,资金台帐!$T$6:$T$6005,$Q8,资金台帐!$U$6:$U$6005,"收入",资金台帐!$O$6:$O$6005,IF($C$3="全部","?*",$C$3),资金台帐!$N$6:$N$6005,">="&DATE($F$3,12,1),资金台帐!$N$6:$N$6005,"<"&DATE($F$3,12+1,1))-SUMIFS(资金台帐!$AC$6:$AC$6005,资金台帐!$T$6:$T$6005,$Q8,资金台帐!$U$6:$U$6005,"收入",资金台帐!$O$6:$O$6005,IF($C$3="全部","?*",$C$3),资金台帐!$N$6:$N$6005,">="&DATE($F$3,12,1),资金台帐!$N$6:$N$6005,"<"&DATE($F$3,12+1,1)),2) -> 0 | O8: =ROUND(SUM(C8:N8),2) -> 0 | P8: =IF(N($O$16)=0,"",O8/$O$16) -> 0 | Q8: =基础资料!$U$8&"" -> 代办
B9: =IF(基础资料!$W$9="",基础资料!$U$9&"",基础资料!$W$9&"") -> 刻章 | C9: =ROUND(SUMIFS(资金台帐!$AB$6:$AB$6005,资金台帐!$T$6:$T$6005,$Q9,资金台帐!$U$6:$U$6005,"收入",资金台帐!$O$6:$O$6005,IF($C$3="全部","?*",$C$3),资金台帐!$N$6:$N$6005,">="&DATE($F$3,1,1),资金台帐!$N$6:$N$6005,"<"&DATE($F$3,1+1,1))-SUMIFS(资金台帐!$AC$6:$AC$6005,资金台帐!$T$6:$T$6005,$Q9,资金台帐!$U$6:$U$6005,"收入",资金台帐!$O$6:$O$6005,IF($C$3="全部","?*",$C$3),资金台帐!$N$6:$N$6005,">="&DATE($F$3,1,1),资金台帐!$N$6:$N$6005,"<"&DATE($F$3,1+1,1)),2) -> 0 | D9: =ROUND(SUMIFS(资金台帐!$AB$6:$AB$6005,资金台帐!$T$6:$T$6005,$Q9,资金台帐!$U$6:$U$6005,"收入",资金台帐!$O$6:$O$6005,IF($C$3="全部","?*",$C$3),资金台帐!$N$6:$N$6005,">="&DATE($F$3,2,1),资金台帐!$N$6:$N$6005,"<"&DATE($F$3,2+1,1))-SUMIFS(资金台帐!$AC$6:$AC$6005,资金台帐!$T$6:$T$6005,$Q9,资金台帐!$U$6:$U$6005,"收入",资金台帐!$O$6:$O$6005,IF($C$3="全部","?*",$C$3),资金台帐!$N$6:$N$6005,">="&DATE($F$3,2,1),资金台帐!$N$6:$N$6005,"<"&DATE($F$3,2+1,1)),2) -> 0 | E9: =ROUND(SUMIFS(资金台帐!$AB$6:$AB$6005,资金台帐!$T$6:$T$6005,$Q9,资金台帐!$U$6:$U$6005,"收入",资金台帐!$O$6:$O$6005,IF($C$3="全部","?*",$C$3),资金台帐!$N$6:$N$6005,">="&DATE($F$3,3,1),资金台帐!$N$6:$N$6005,"<"&DATE($F$3,3+1,1))-SUMIFS(资金台帐!$AC$6:$AC$6005,资金台帐!$T$6:$T$6005,$Q9,资金台帐!$U$6:$U$6005,"收入",资金台帐!$O$6:$O$6005,IF($C$3="全部","?*",$C$3),资金台帐!$N$6:$N$6005,">="&DATE($F$3,3,1),资金台帐!$N$6:$N$6005,"<"&DATE($F$3,3+1,1)),2) -> 0 | F9: =ROUND(SUMIFS(资金台帐!$AB$6:$AB$6005,资金台帐!$T$6:$T$6005,$Q9,资金台帐!$U$6:$U$6005,"收入",资金台帐!$O$6:$O$6005,IF($C$3="全部","?*",$C$3),资金台帐!$N$6:$N$6005,">="&DATE($F$3,4,1),资金台帐!$N$6:$N$6005,"<"&DATE($F$3,4+1,1))-SUMIFS(资金台帐!$AC$6:$AC$6005,资金台帐!$T$6:$T$6005,$Q9,资金台帐!$U$6:$U$6005,"收入",资金台帐!$O$6:$O$6005,IF($C$3="全部","?*",$C$3),资金台帐!$N$6:$N$6005,">="&DATE($F$3,4,1),资金台帐!$N$6:$N$6005,"<"&DATE($F$3,4+1,1)),2) -> 0 | G9: =ROUND(SUMIFS(资金台帐!$AB$6:$AB$6005,资金台帐!$T$6:$T$6005,$Q9,资金台帐!$U$6:$U$6005,"收入",资金台帐!$O$6:$O$6005,IF($C$3="全部","?*",$C$3),资金台帐!$N$6:$N$6005,">="&DATE($F$3,5,1),资金台帐!$N$6:$N$6005,"<"&DATE($F$3,5+1,1))-SUMIFS(资金台帐!$AC$6:$AC$6005,资金台帐!$T$6:$T$6005,$Q9,资金台帐!$U$6:$U$6005,"收入",资金台帐!$O$6:$O$6005,IF($C$3="全部","?*",$C$3),资金台帐!$N$6:$N$6005,">="&DATE($F$3,5,1),资金台帐!$N$6:$N$6005,"<"&DATE($F$3,5+1,1)),2) -> 0 | H9: =ROUND(SUMIFS(资金台帐!$AB$6:$AB$6005,资金台帐!$T$6:$T$6005,$Q9,资金台帐!$U$6:$U$6005,"收入",资金台帐!$O$6:$O$6005,IF($C$3="全部","?*",$C$3),资金台帐!$N$6:$N$6005,">="&DATE($F$3,6,1),资金台帐!$N$6:$N$6005,"<"&DATE($F$3,6+1,1))-SUMIFS(资金台帐!$AC$6:$AC$6005,资金台帐!$T$6:$T$6005,$Q9,资金台帐!$U$6:$U$6005,"收入",资金台帐!$O$6:$O$6005,IF($C$3="全部","?*",$C$3),资金台帐!$N$6:$N$6005,">="&DATE($F$3,6,1),资金台帐!$N$6:$N$6005,"<"&DATE($F$3,6+1,1)),2) -> 0 | I9: =ROUND(SUMIFS(资金台帐!$AB$6:$AB$6005,资金台帐!$T$6:$T$6005,$Q9,资金台帐!$U$6:$U$6005,"收入",资金台帐!$O$6:$O$6005,IF($C$3="全部","?*",$C$3),资金台帐!$N$6:$N$6005,">="&DATE($F$3,7,1),资金台帐!$N$6:$N$6005,"<"&DATE($F$3,7+1,1))-SUMIFS(资金台帐!$AC$6:$AC$6005,资金台帐!$T$6:$T$6005,$Q9,资金台帐!$U$6:$U$6005,"收入",资金台帐!$O$6:$O$6005,IF($C$3="全部","?*",$C$3),资金台帐!$N$6:$N$6005,">="&DATE($F$3,7,1),资金台帐!$N$6:$N$6005,"<"&DATE($F$3,7+1,1)),2) -> 0 | J9: =ROUND(SUMIFS(资金台帐!$AB$6:$AB$6005,资金台帐!$T$6:$T$6005,$Q9,资金台帐!$U$6:$U$6005,"收入",资金台帐!$O$6:$O$6005,IF($C$3="全部","?*",$C$3),资金台帐!$N$6:$N$6005,">="&DATE($F$3,8,1),资金台帐!$N$6:$N$6005,"<"&DATE($F$3,8+1,1))-SUMIFS(资金台帐!$AC$6:$AC$6005,资金台帐!$T$6:$T$6005,$Q9,资金台帐!$U$6:$U$6005,"收入",资金台帐!$O$6:$O$6005,IF($C$3="全部","?*",$C$3),资金台帐!$N$6:$N$6005,">="&DATE($F$3,8,1),资金台帐!$N$6:$N$6005,"<"&DATE($F$3,8+1,1)),2) -> 0 | K9: =ROUND(SUMIFS(资金台帐!$AB$6:$AB$6005,资金台帐!$T$6:$T$6005,$Q9,资金台帐!$U$6:$U$6005,"收入",资金台帐!$O$6:$O$6005,IF($C$3="全部","?*",$C$3),资金台帐!$N$6:$N$6005,">="&DATE($F$3,9,1),资金台帐!$N$6:$N$6005,"<"&DATE($F$3,9+1,1))-SUMIFS(资金台帐!$AC$6:$AC$6005,资金台帐!$T$6:$T$6005,$Q9,资金台帐!$U$6:$U$6005,"收入",资金台帐!$O$6:$O$6005,IF($C$3="全部","?*",$C$3),资金台帐!$N$6:$N$6005,">="&DATE($F$3,9,1),资金台帐!$N$6:$N$6005,"<"&DATE($F$3,9+1,1)),2) -> 0 | L9: =ROUND(SUMIFS(资金台帐!$AB$6:$AB$6005,资金台帐!$T$6:$T$6005,$Q9,资金台帐!$U$6:$U$6005,"收入",资金台帐!$O$6:$O$6005,IF($C$3="全部","?*",$C$3),资金台帐!$N$6:$N$6005,">="&DATE($F$3,10,1),资金台帐!$N$6:$N$6005,"<"&DATE($F$3,10+1,1))-SUMIFS(资金台帐!$AC$6:$AC$6005,资金台帐!$T$6:$T$6005,$Q9,资金台帐!$U$6:$U$6005,"收入",资金台帐!$O$6:$O$6005,IF($C$3="全部","?*",$C$3),资金台帐!$N$6:$N$6005,">="&DATE($F$3,10,1),资金台帐!$N$6:$N$6005,"<"&DATE($F$3,10+1,1)),2) -> 0 | M9: =ROUND(SUMIFS(资金台帐!$AB$6:$AB$6005,资金台帐!$T$6:$T$6005,$Q9,资金台帐!$U$6:$U$6005,"收入",资金台帐!$O$6:$O$6005,IF($C$3="全部","?*",$C$3),资金台帐!$N$6:$N$6005,">="&DATE($F$3,11,1),资金台帐!$N$6:$N$6005,"<"&DATE($F$3,11+1,1))-SUMIFS(资金台帐!$AC$6:$AC$6005,资金台帐!$T$6:$T$6005,$Q9,资金台帐!$U$6:$U$6005,"收入",资金台帐!$O$6:$O$6005,IF($C$3="全部","?*",$C$3),资金台帐!$N$6:$N$6005,">="&DATE($F$3,11,1),资金台帐!$N$6:$N$6005,"<"&DATE($F$3,11+1,1)),2) -> 0 | N9: =ROUND(SUMIFS(资金台帐!$AB$6:$AB$6005,资金台帐!$T$6:$T$6005,$Q9,资金台帐!$U$6:$U$6005,"收入",资金台帐!$O$6:$O$6005,IF($C$3="全部","?*",$C$3),资金台帐!$N$6:$N$6005,">="&DATE($F$3,12,1),资金台帐!$N$6:$N$6005,"<"&DATE($F$3,12+1,1))-SUMIFS(资金台帐!$AC$6:$AC$6005,资金台帐!$T$6:$T$6005,$Q9,资金台帐!$U$6:$U$6005,"收入",资金台帐!$O$6:$O$6005,IF($C$3="全部","?*",$C$3),资金台帐!$N$6:$N$6005,">="&DATE($F$3,12,1),资金台帐!$N$6:$N$6005,"<"&DATE($F$3,12+1,1)),2) -> 0 | O9: =ROUND(SUM(C9:N9),2) -> 0 | P9: =IF(N($O$16)=0,"",O9/$O$16) -> 0 | Q9: =基础资料!$U$9&"" -> 刻章
B10: =IF(基础资料!$W$10="",基础资料!$U$10&"",基础资料!$W$10&"") -> 场地 | C10: =ROUND(SUMIFS(资金台帐!$AB$6:$AB$6005,资金台帐!$T$6:$T$6005,$Q10,资金台帐!$U$6:$U$6005,"收入",资金台帐!$O$6:$O$6005,IF($C$3="全部","?*",$C$3),资金台帐!$N$6:$N$6005,">="&DATE($F$3,1,1),资金台帐!$N$6:$N$6005,"<"&DATE($F$3,1+1,1))-SUMIFS(资金台帐!$AC$6:$AC$6005,资金台帐!$T$6:$T$6005,$Q10,资金台帐!$U$6:$U$6005,"收入",资金台帐!$O$6:$O$6005,IF($C$3="全部","?*",$C$3),资金台帐!$N$6:$N$6005,">="&DATE($F$3,1,1),资金台帐!$N$6:$N$6005,"<"&DATE($F$3,1+1,1)),2) -> 0 | D10: =ROUND(SUMIFS(资金台帐!$AB$6:$AB$6005,资金台帐!$T$6:$T$6005,$Q10,资金台帐!$U$6:$U$6005,"收入",资金台帐!$O$6:$O$6005,IF($C$3="全部","?*",$C$3),资金台帐!$N$6:$N$6005,">="&DATE($F$3,2,1),资金台帐!$N$6:$N$6005,"<"&DATE($F$3,2+1,1))-SUMIFS(资金台帐!$AC$6:$AC$6005,资金台帐!$T$6:$T$6005,$Q10,资金台帐!$U$6:$U$6005,"收入",资金台帐!$O$6:$O$6005,IF($C$3="全部","?*",$C$3),资金台帐!$N$6:$N$6005,">="&DATE($F$3,2,1),资金台帐!$N$6:$N$6005,"<"&DATE($F$3,2+1,1)),2) -> 0 | E10: =ROUND(SUMIFS(资金台帐!$AB$6:$AB$6005,资金台帐!$T$6:$T$6005,$Q10,资金台帐!$U$6:$U$6005,"收入",资金台帐!$O$6:$O$6005,IF($C$3="全部","?*",$C$3),资金台帐!$N$6:$N$6005,">="&DATE($F$3,3,1),资金台帐!$N$6:$N$6005,"<"&DATE($F$3,3+1,1))-SUMIFS(资金台帐!$AC$6:$AC$6005,资金台帐!$T$6:$T$6005,$Q10,资金台帐!$U$6:$U$6005,"收入",资金台帐!$O$6:$O$6005,IF($C$3="全部","?*",$C$3),资金台帐!$N$6:$N$6005,">="&DATE($F$3,3,1),资金台帐!$N$6:$N$6005,"<"&DATE($F$3,3+1,1)),2) -> 0 | F10: =ROUND(SUMIFS(资金台帐!$AB$6:$AB$6005,资金台帐!$T$6:$T$6005,$Q10,资金台帐!$U$6:$U$6005,"收入",资金台帐!$O$6:$O$6005,IF($C$3="全部","?*",$C$3),资金台帐!$N$6:$N$6005,">="&DATE($F$3,4,1),资金台帐!$N$6:$N$6005,"<"&DATE($F$3,4+1,1))-SUMIFS(资金台帐!$AC$6:$AC$6005,资金台帐!$T$6:$T$6005,$Q10,资金台帐!$U$6:$U$6005,"收入",资金台帐!$O$6:$O$6005,IF($C$3="全部","?*",$C$3),资金台帐!$N$6:$N$6005,">="&DATE($F$3,4,1),资金台帐!$N$6:$N$6005,"<"&DATE($F$3,4+1,1)),2) -> 0 | G10: =ROUND(SUMIFS(资金台帐!$AB$6:$AB$6005,资金台帐!$T$6:$T$6005,$Q10,资金台帐!$U$6:$U$6005,"收入",资金台帐!$O$6:$O$6005,IF($C$3="全部","?*",$C$3),资金台帐!$N$6:$N$6005,">="&DATE($F$3,5,1),资金台帐!$N$6:$N$6005,"<"&DATE($F$3,5+1,1))-SUMIFS(资金台帐!$AC$6:$AC$6005,资金台帐!$T$6:$T$6005,$Q10,资金台帐!$U$6:$U$6005,"收入",资金台帐!$O$6:$O$6005,IF($C$3="全部","?*",$C$3),资金台帐!$N$6:$N$6005,">="&DATE($F$3,5,1),资金台帐!$N$6:$N$6005,"<"&DATE($F$3,5+1,1)),2) -> 0 | H10: =ROUND(SUMIFS(资金台帐!$AB$6:$AB$6005,资金台帐!$T$6:$T$6005,$Q10,资金台帐!$U$6:$U$6005,"收入",资金台帐!$O$6:$O$6005,IF($C$3="全部","?*",$C$3),资金台帐!$N$6:$N$6005,">="&DATE($F$3,6,1),资金台帐!$N$6:$N$6005,"<"&DATE($F$3,6+1,1))-SUMIFS(资金台帐!$AC$6:$AC$6005,资金台帐!$T$6:$T$6005,$Q10,资金台帐!$U$6:$U$6005,"收入",资金台帐!$O$6:$O$6005,IF($C$3="全部","?*",$C$3),资金台帐!$N$6:$N$6005,">="&DATE($F$3,6,1),资金台帐!$N$6:$N$6005,"<"&DATE($F$3,6+1,1)),2) -> 0 | I10: =ROUND(SUMIFS(资金台帐!$AB$6:$AB$6005,资金台帐!$T$6:$T$6005,$Q10,资金台帐!$U$6:$U$6005,"收入",资金台帐!$O$6:$O$6005,IF($C$3="全部","?*",$C$3),资金台帐!$N$6:$N$6005,">="&DATE($F$3,7,1),资金台帐!$N$6:$N$6005,"<"&DATE($F$3,7+1,1))-SUMIFS(资金台帐!$AC$6:$AC$6005,资金台帐!$T$6:$T$6005,$Q10,资金台帐!$U$6:$U$6005,"收入",资金台帐!$O$6:$O$6005,IF($C$3="全部","?*",$C$3),资金台帐!$N$6:$N$6005,">="&DATE($F$3,7,1),资金台帐!$N$6:$N$6005,"<"&DATE($F$3,7+1,1)),2) -> 0 | J10: =ROUND(SUMIFS(资金台帐!$AB$6:$AB$6005,资金台帐!$T$6:$T$6005,$Q10,资金台帐!$U$6:$U$6005,"收入",资金台帐!$O$6:$O$6005,IF($C$3="全部","?*",$C$3),资金台帐!$N$6:$N$6005,">="&DATE($F$3,8,1),资金台帐!$N$6:$N$6005,"<"&DATE($F$3,8+1,1))-SUMIFS(资金台帐!$AC$6:$AC$6005,资金台帐!$T$6:$T$6005,$Q10,资金台帐!$U$6:$U$6005,"收入",资金台帐!$O$6:$O$6005,IF($C$3="全部","?*",$C$3),资金台帐!$N$6:$N$6005,">="&DATE($F$3,8,1),资金台帐!$N$6:$N$6005,"<"&DATE($F$3,8+1,1)),2) -> 0 | K10: =ROUND(SUMIFS(资金台帐!$AB$6:$AB$6005,资金台帐!$T$6:$T$6005,$Q10,资金台帐!$U$6:$U$6005,"收入",资金台帐!$O$6:$O$6005,IF($C$3="全部","?*",$C$3),资金台帐!$N$6:$N$6005,">="&DATE($F$3,9,1),资金台帐!$N$6:$N$6005,"<"&DATE($F$3,9+1,1))-SUMIFS(资金台帐!$AC$6:$AC$6005,资金台帐!$T$6:$T$6005,$Q10,资金台帐!$U$6:$U$6005,"收入",资金台帐!$O$6:$O$6005,IF($C$3="全部","?*",$C$3),资金台帐!$N$6:$N$6005,">="&DATE($F$3,9,1),资金台帐!$N$6:$N$6005,"<"&DATE($F$3,9+1,1)),2) -> 0 | L10: =ROUND(SUMIFS(资金台帐!$AB$6:$AB$6005,资金台帐!$T$6:$T$6005,$Q10,资金台帐!$U$6:$U$6005,"收入",资金台帐!$O$6:$O$6005,IF($C$3="全部","?*",$C$3),资金台帐!$N$6:$N$6005,">="&DATE($F$3,10,1),资金台帐!$N$6:$N$6005,"<"&DATE($F$3,10+1,1))-SUMIFS(资金台帐!$AC$6:$AC$6005,资金台帐!$T$6:$T$6005,$Q10,资金台帐!$U$6:$U$6005,"收入",资金台帐!$O$6:$O$6005,IF($C$3="全部","?*",$C$3),资金台帐!$N$6:$N$6005,">="&DATE($F$3,10,1),资金台帐!$N$6:$N$6005,"<"&DATE($F$3,10+1,1)),2) -> 0 | M10: =ROUND(SUMIFS(资金台帐!$AB$6:$AB$6005,资金台帐!$T$6:$T$6005,$Q10,资金台帐!$U$6:$U$6005,"收入",资金台帐!$O$6:$O$6005,IF($C$3="全部","?*",$C$3),资金台帐!$N$6:$N$6005,">="&DATE($F$3,11,1),资金台帐!$N$6:$N$6005,"<"&DATE($F$3,11+1,1))-SUMIFS(资金台帐!$AC$6:$AC$6005,资金台帐!$T$6:$T$6005,$Q10,资金台帐!$U$6:$U$6005,"收入",资金台帐!$O$6:$O$6005,IF($C$3="全部","?*",$C$3),资金台帐!$N$6:$N$6005,">="&DATE($F$3,11,1),资金台帐!$N$6:$N$6005,"<"&DATE($F$3,11+1,1)),2) -> 0 | N10: =ROUND(SUMIFS(资金台帐!$AB$6:$AB$6005,资金台帐!$T$6:$T$6005,$Q10,资金台帐!$U$6:$U$6005,"收入",资金台帐!$O$6:$O$6005,IF($C$3="全部","?*",$C$3),资金台帐!$N$6:$N$6005,">="&DATE($F$3,12,1),资金台帐!$N$6:$N$6005,"<"&DATE($F$3,12+1,1))-SUMIFS(资金台帐!$AC$6:$AC$6005,资金台帐!$T$6:$T$6005,$Q10,资金台帐!$U$6:$U$6005,"收入",资金台帐!$O$6:$O$6005,IF($C$3="全部","?*",$C$3),资金台帐!$N$6:$N$6005,">="&DATE($F$3,12,1),资金台帐!$N$6:$N$6005,"<"&DATE($F$3,12+1,1)),2) -> 0 | O10: =ROUND(SUM(C10:N10),2) -> 0 | P10: =IF(N($O$16)=0,"",O10/$O$16) -> 0 | Q10: =基础资料!$U$10&"" -> 场地
B11: =IF(基础资料!$W$11="",基础资料!$U$11&"",基础资料!$W$11&"") -> 办证 | C11: =ROUND(SUMIFS(资金台帐!$AB$6:$AB$6005,资金台帐!$T$6:$T$6005,$Q11,资金台帐!$U$6:$U$6005,"收入",资金台帐!$O$6:$O$6005,IF($C$3="全部","?*",$C$3),资金台帐!$N$6:$N$6005,">="&DATE($F$3,1,1),资金台帐!$N$6:$N$6005,"<"&DATE($F$3,1+1,1))-SUMIFS(资金台帐!$AC$6:$AC$6005,资金台帐!$T$6:$T$6005,$Q11,资金台帐!$U$6:$U$6005,"收入",资金台帐!$O$6:$O$6005,IF($C$3="全部","?*",$C$3),资金台帐!$N$6:$N$6005,">="&DATE($F$3,1,1),资金台帐!$N$6:$N$6005,"<"&DATE($F$3,1+1,1)),2) -> 0 | D11: =ROUND(SUMIFS(资金台帐!$AB$6:$AB$6005,资金台帐!$T$6:$T$6005,$Q11,资金台帐!$U$6:$U$6005,"收入",资金台帐!$O$6:$O$6005,IF($C$3="全部","?*",$C$3),资金台帐!$N$6:$N$6005,">="&DATE($F$3,2,1),资金台帐!$N$6:$N$6005,"<"&DATE($F$3,2+1,1))-SUMIFS(资金台帐!$AC$6:$AC$6005,资金台帐!$T$6:$T$6005,$Q11,资金台帐!$U$6:$U$6005,"收入",资金台帐!$O$6:$O$6005,IF($C$3="全部","?*",$C$3),资金台帐!$N$6:$N$6005,">="&DATE($F$3,2,1),资金台帐!$N$6:$N$6005,"<"&DATE($F$3,2+1,1)),2) -> 0 | E11: =ROUND(SUMIFS(资金台帐!$AB$6:$AB$6005,资金台帐!$T$6:$T$6005,$Q11,资金台帐!$U$6:$U$6005,"收入",资金台帐!$O$6:$O$6005,IF($C$3="全部","?*",$C$3),资金台帐!$N$6:$N$6005,">="&DATE($F$3,3,1),资金台帐!$N$6:$N$6005,"<"&DATE($F$3,3+1,1))-SUMIFS(资金台帐!$AC$6:$AC$6005,资金台帐!$T$6:$T$6005,$Q11,资金台帐!$U$6:$U$6005,"收入",资金台帐!$O$6:$O$6005,IF($C$3="全部","?*",$C$3),资金台帐!$N$6:$N$6005,">="&DATE($F$3,3,1),资金台帐!$N$6:$N$6005,"<"&DATE($F$3,3+1,1)),2) -> 0 | F11: =ROUND(SUMIFS(资金台帐!$AB$6:$AB$6005,资金台帐!$T$6:$T$6005,$Q11,资金台帐!$U$6:$U$6005,"收入",资金台帐!$O$6:$O$6005,IF($C$3="全部","?*",$C$3),资金台帐!$N$6:$N$6005,">="&DATE($F$3,4,1),资金台帐!$N$6:$N$6005,"<"&DATE($F$3,4+1,1))-SUMIFS(资金台帐!$AC$6:$AC$6005,资金台帐!$T$6:$T$6005,$Q11,资金台帐!$U$6:$U$6005,"收入",资金台帐!$O$6:$O$6005,IF($C$3="全部","?*",$C$3),资金台帐!$N$6:$N$6005,">="&DATE($F$3,4,1),资金台帐!$N$6:$N$6005,"<"&DATE($F$3,4+1,1)),2) -> 0 | G11: =ROUND(SUMIFS(资金台帐!$AB$6:$AB$6005,资金台帐!$T$6:$T$6005,$Q11,资金台帐!$U$6:$U$6005,"收入",资金台帐!$O$6:$O$6005,IF($C$3="全部","?*",$C$3),资金台帐!$N$6:$N$6005,">="&DATE($F$3,5,1),资金台帐!$N$6:$N$6005,"<"&DATE($F$3,5+1,1))-SUMIFS(资金台帐!$AC$6:$AC$6005,资金台帐!$T$6:$T$6005,$Q11,资金台帐!$U$6:$U$6005,"收入",资金台帐!$O$6:$O$6005,IF($C$3="全部","?*",$C$3),资金台帐!$N$6:$N$6005,">="&DATE($F$3,5,1),资金台帐!$N$6:$N$6005,"<"&DATE($F$3,5+1,1)),2) -> 0 | H11: =ROUND(SUMIFS(资金台帐!$AB$6:$AB$6005,资金台帐!$T$6:$T$6005,$Q11,资金台帐!$U$6:$U$6005,"收入",资金台帐!$O$6:$O$6005,IF($C$3="全部","?*",$C$3),资金台帐!$N$6:$N$6005,">="&DATE($F$3,6,1),资金台帐!$N$6:$N$6005,"<"&DATE($F$3,6+1,1))-SUMIFS(资金台帐!$AC$6:$AC$6005,资金台帐!$T$6:$T$6005,$Q11,资金台帐!$U$6:$U$6005,"收入",资金台帐!$O$6:$O$6005,IF($C$3="全部","?*",$C$3),资金台帐!$N$6:$N$6005,">="&DATE($F$3,6,1),资金台帐!$N$6:$N$6005,"<"&DATE($F$3,6+1,1)),2) -> 0 | I11: =ROUND(SUMIFS(资金台帐!$AB$6:$AB$6005,资金台帐!$T$6:$T$6005,$Q11,资金台帐!$U$6:$U$6005,"收入",资金台帐!$O$6:$O$6005,IF($C$3="全部","?*",$C$3),资金台帐!$N$6:$N$6005,">="&DATE($F$3,7,1),资金台帐!$N$6:$N$6005,"<"&DATE($F$3,7+1,1))-SUMIFS(资金台帐!$AC$6:$AC$6005,资金台帐!$T$6:$T$6005,$Q11,资金台帐!$U$6:$U$6005,"收入",资金台帐!$O$6:$O$6005,IF($C$3="全部","?*",$C$3),资金台帐!$N$6:$N$6005,">="&DATE($F$3,7,1),资金台帐!$N$6:$N$6005,"<"&DATE($F$3,7+1,1)),2) -> 0 | J11: =ROUND(SUMIFS(资金台帐!$AB$6:$AB$6005,资金台帐!$T$6:$T$6005,$Q11,资金台帐!$U$6:$U$6005,"收入",资金台帐!$O$6:$O$6005,IF($C$3="全部","?*",$C$3),资金台帐!$N$6:$N$6005,">="&DATE($F$3,8,1),资金台帐!$N$6:$N$6005,"<"&DATE($F$3,8+1,1))-SUMIFS(资金台帐!$AC$6:$AC$6005,资金台帐!$T$6:$T$6005,$Q11,资金台帐!$U$6:$U$6005,"收入",资金台帐!$O$6:$O$6005,IF($C$3="全部","?*",$C$3),资金台帐!$N$6:$N$6005,">="&DATE($F$3,8,1),资金台帐!$N$6:$N$6005,"<"&DATE($F$3,8+1,1)),2) -> 0 | K11: =ROUND(SUMIFS(资金台帐!$AB$6:$AB$6005,资金台帐!$T$6:$T$6005,$Q11,资金台帐!$U$6:$U$6005,"收入",资金台帐!$O$6:$O$6005,IF($C$3="全部","?*",$C$3),资金台帐!$N$6:$N$6005,">="&DATE($F$3,9,1),资金台帐!$N$6:$N$6005,"<"&DATE($F$3,9+1,1))-SUMIFS(资金台帐!$AC$6:$AC$6005,资金台帐!$T$6:$T$6005,$Q11,资金台帐!$U$6:$U$6005,"收入",资金台帐!$O$6:$O$6005,IF($C$3="全部","?*",$C$3),资金台帐!$N$6:$N$6005,">="&DATE($F$3,9,1),资金台帐!$N$6:$N$6005,"<"&DATE($F$3,9+1,1)),2) -> 0 | L11: =ROUND(SUMIFS(资金台帐!$AB$6:$AB$6005,资金台帐!$T$6:$T$6005,$Q11,资金台帐!$U$6:$U$6005,"收入",资金台帐!$O$6:$O$6005,IF($C$3="全部","?*",$C$3),资金台帐!$N$6:$N$6005,">="&DATE($F$3,10,1),资金台帐!$N$6:$N$6005,"<"&DATE($F$3,10+1,1))-SUMIFS(资金台帐!$AC$6:$AC$6005,资金台帐!$T$6:$T$6005,$Q11,资金台帐!$U$6:$U$6005,"收入",资金台帐!$O$6:$O$6005,IF($C$3="全部","?*",$C$3),资金台帐!$N$6:$N$6005,">="&DATE($F$3,10,1),资金台帐!$N$6:$N$6005,"<"&DATE($F$3,10+1,1)),2) -> 0 | M11: =ROUND(SUMIFS(资金台帐!$AB$6:$AB$6005,资金台帐!$T$6:$T$6005,$Q11,资金台帐!$U$6:$U$6005,"收入",资金台帐!$O$6:$O$6005,IF($C$3="全部","?*",$C$3),资金台帐!$N$6:$N$6005,">="&DATE($F$3,11,1),资金台帐!$N$6:$N$6005,"<"&DATE($F$3,11+1,1))-SUMIFS(资金台帐!$AC$6:$AC$6005,资金台帐!$T$6:$T$6005,$Q11,资金台帐!$U$6:$U$6005,"收入",资金台帐!$O$6:$O$6005,IF($C$3="全部","?*",$C$3),资金台帐!$N$6:$N$6005,">="&DATE($F$3,11,1),资金台帐!$N$6:$N$6005,"<"&DATE($F$3,11+1,1)),2) -> 0 | N11: =ROUND(SUMIFS(资金台帐!$AB$6:$AB$6005,资金台帐!$T$6:$T$6005,$Q11,资金台帐!$U$6:$U$6005,"收入",资金台帐!$O$6:$O$6005,IF($C$3="全部","?*",$C$3),资金台帐!$N$6:$N$6005,">="&DATE($F$3,12,1),资金台帐!$N$6:$N$6005,"<"&DATE($F$3,12+1,1))-SUMIFS(资金台帐!$AC$6:$AC$6005,资金台帐!$T$6:$T$6005,$Q11,资金台帐!$U$6:$U$6005,"收入",资金台帐!$O$6:$O$6005,IF($C$3="全部","?*",$C$3),资金台帐!$N$6:$N$6005,">="&DATE($F$3,12,1),资金台帐!$N$6:$N$6005,"<"&DATE($F$3,12+1,1)),2) -> 0 | O11: =ROUND(SUM(C11:N11),2) -> 0 | P11: =IF(N($O$16)=0,"",O11/$O$16) -> 0 | Q11: =基础资料!$U$11&"" -> 办证
B12: =IF(基础资料!$W$12="",基础资料!$U$12&"",基础资料!$W$12&"") -> 转介绍 | C12: =ROUND(SUMIFS(资金台帐!$AB$6:$AB$6005,资金台帐!$T$6:$T$6005,$Q12,资金台帐!$U$6:$U$6005,"收入",资金台帐!$O$6:$O$6005,IF($C$3="全部","?*",$C$3),资金台帐!$N$6:$N$6005,">="&DATE($F$3,1,1),资金台帐!$N$6:$N$6005,"<"&DATE($F$3,1+1,1))-SUMIFS(资金台帐!$AC$6:$AC$6005,资金台帐!$T$6:$T$6005,$Q12,资金台帐!$U$6:$U$6005,"收入",资金台帐!$O$6:$O$6005,IF($C$3="全部","?*",$C$3),资金台帐!$N$6:$N$6005,">="&DATE($F$3,1,1),资金台帐!$N$6:$N$6005,"<"&DATE($F$3,1+1,1)),2) -> 0 | D12: =ROUND(SUMIFS(资金台帐!$AB$6:$AB$6005,资金台帐!$T$6:$T$6005,$Q12,资金台帐!$U$6:$U$6005,"收入",资金台帐!$O$6:$O$6005,IF($C$3="全部","?*",$C$3),资金台帐!$N$6:$N$6005,">="&DATE($F$3,2,1),资金台帐!$N$6:$N$6005,"<"&DATE($F$3,2+1,1))-SUMIFS(资金台帐!$AC$6:$AC$6005,资金台帐!$T$6:$T$6005,$Q12,资金台帐!$U$6:$U$6005,"收入",资金台帐!$O$6:$O$6005,IF($C$3="全部","?*",$C$3),资金台帐!$N$6:$N$6005,">="&DATE($F$3,2,1),资金台帐!$N$6:$N$6005,"<"&DATE($F$3,2+1,1)),2) -> 0 | E12: =ROUND(SUMIFS(资金台帐!$AB$6:$AB$6005,资金台帐!$T$6:$T$6005,$Q12,资金台帐!$U$6:$U$6005,"收入",资金台帐!$O$6:$O$6005,IF($C$3="全部","?*",$C$3),资金台帐!$N$6:$N$6005,">="&DATE($F$3,3,1),资金台帐!$N$6:$N$6005,"<"&DATE($F$3,3+1,1))-SUMIFS(资金台帐!$AC$6:$AC$6005,资金台帐!$T$6:$T$6005,$Q12,资金台帐!$U$6:$U$6005,"收入",资金台帐!$O$6:$O$6005,IF($C$3="全部","?*",$C$3),资金台帐!$N$6:$N$6005,">="&DATE($F$3,3,1),资金台帐!$N$6:$N$6005,"<"&DATE($F$3,3+1,1)),2) -> 0 | F12: =ROUND(SUMIFS(资金台帐!$AB$6:$AB$6005,资金台帐!$T$6:$T$6005,$Q12,资金台帐!$U$6:$U$6005,"收入",资金台帐!$O$6:$O$6005,IF($C$3="全部","?*",$C$3),资金台帐!$N$6:$N$6005,">="&DATE($F$3,4,1),资金台帐!$N$6:$N$6005,"<"&DATE($F$3,4+1,1))-SUMIFS(资金台帐!$AC$6:$AC$6005,资金台帐!$T$6:$T$6005,$Q12,资金台帐!$U$6:$U$6005,"收入",资金台帐!$O$6:$O$6005,IF($C$3="全部","?*",$C$3),资金台帐!$N$6:$N$6005,">="&DATE($F$3,4,1),资金台帐!$N$6:$N$6005,"<"&DATE($F$3,4+1,1)),2) -> 0 | G12: =ROUND(SUMIFS(资金台帐!$AB$6:$AB$6005,资金台帐!$T$6:$T$6005,$Q12,资金台帐!$U$6:$U$6005,"收入",资金台帐!$O$6:$O$6005,IF($C$3="全部","?*",$C$3),资金台帐!$N$6:$N$6005,">="&DATE($F$3,5,1),资金台帐!$N$6:$N$6005,"<"&DATE($F$3,5+1,1))-SUMIFS(资金台帐!$AC$6:$AC$6005,资金台帐!$T$6:$T$6005,$Q12,资金台帐!$U$6:$U$6005,"收入",资金台帐!$O$6:$O$6005,IF($C$3="全部","?*",$C$3),资金台帐!$N$6:$N$6005,">="&DATE($F$3,5,1),资金台帐!$N$6:$N$6005,"<"&DATE($F$3,5+1,1)),2) -> 0 | H12: =ROUND(SUMIFS(资金台帐!$AB$6:$AB$6005,资金台帐!$T$6:$T$6005,$Q12,资金台帐!$U$6:$U$6005,"收入",资金台帐!$O$6:$O$6005,IF($C$3="全部","?*",$C$3),资金台帐!$N$6:$N$6005,">="&DATE($F$3,6,1),资金台帐!$N$6:$N$6005,"<"&DATE($F$3,6+1,1))-SUMIFS(资金台帐!$AC$6:$AC$6005,资金台帐!$T$6:$T$6005,$Q12,资金台帐!$U$6:$U$6005,"收入",资金台帐!$O$6:$O$6005,IF($C$3="全部","?*",$C$3),资金台帐!$N$6:$N$6005,">="&DATE($F$3,6,1),资金台帐!$N$6:$N$6005,"<"&DATE($F$3,6+1,1)),2) -> 0 | I12: =ROUND(SUMIFS(资金台帐!$AB$6:$AB$6005,资金台帐!$T$6:$T$6005,$Q12,资金台帐!$U$6:$U$6005,"收入",资金台帐!$O$6:$O$6005,IF($C$3="全部","?*",$C$3),资金台帐!$N$6:$N$6005,">="&DATE($F$3,7,1),资金台帐!$N$6:$N$6005,"<"&DATE($F$3,7+1,1))-SUMIFS(资金台帐!$AC$6:$AC$6005,资金台帐!$T$6:$T$6005,$Q12,资金台帐!$U$6:$U$6005,"收入",资金台帐!$O$6:$O$6005,IF($C$3="全部","?*",$C$3),资金台帐!$N$6:$N$6005,">="&DATE($F$3,7,1),资金台帐!$N$6:$N$6005,"<"&DATE($F$3,7+1,1)),2) -> 0 | J12: =ROUND(SUMIFS(资金台帐!$AB$6:$AB$6005,资金台帐!$T$6:$T$6005,$Q12,资金台帐!$U$6:$U$6005,"收入",资金台帐!$O$6:$O$6005,IF($C$3="全部","?*",$C$3),资金台帐!$N$6:$N$6005,">="&DATE($F$3,8,1),资金台帐!$N$6:$N$6005,"<"&DATE($F$3,8+1,1))-SUMIFS(资金台帐!$AC$6:$AC$6005,资金台帐!$T$6:$T$6005,$Q12,资金台帐!$U$6:$U$6005,"收入",资金台帐!$O$6:$O$6005,IF($C$3="全部","?*",$C$3),资金台帐!$N$6:$N$6005,">="&DATE($F$3,8,1),资金台帐!$N$6:$N$6005,"<"&DATE($F$3,8+1,1)),2) -> 0 | K12: =ROUND(SUMIFS(资金台帐!$AB$6:$AB$6005,资金台帐!$T$6:$T$6005,$Q12,资金台帐!$U$6:$U$6005,"收入",资金台帐!$O$6:$O$6005,IF($C$3="全部","?*",$C$3),资金台帐!$N$6:$N$6005,">="&DATE($F$3,9,1),资金台帐!$N$6:$N$6005,"<"&DATE($F$3,9+1,1))-SUMIFS(资金台帐!$AC$6:$AC$6005,资金台帐!$T$6:$T$6005,$Q12,资金台帐!$U$6:$U$6005,"收入",资金台帐!$O$6:$O$6005,IF($C$3="全部","?*",$C$3),资金台帐!$N$6:$N$6005,">="&DATE($F$3,9,1),资金台帐!$N$6:$N$6005,"<"&DATE($F$3,9+1,1)),2) -> 0 | L12: =ROUND(SUMIFS(资金台帐!$AB$6:$AB$6005,资金台帐!$T$6:$T$6005,$Q12,资金台帐!$U$6:$U$6005,"收入",资金台帐!$O$6:$O$6005,IF($C$3="全部","?*",$C$3),资金台帐!$N$6:$N$6005,">="&DATE($F$3,10,1),资金台帐!$N$6:$N$6005,"<"&DATE($F$3,10+1,1))-SUMIFS(资金台帐!$AC$6:$AC$6005,资金台帐!$T$6:$T$6005,$Q12,资金台帐!$U$6:$U$6005,"收入",资金台帐!$O$6:$O$6005,IF($C$3="全部","?*",$C$3),资金台帐!$N$6:$N$6005,">="&DATE($F$3,10,1),资金台帐!$N$6:$N$6005,"<"&DATE($F$3,10+1,1)),2) -> 0 | M12: =ROUND(SUMIFS(资金台帐!$AB$6:$AB$6005,资金台帐!$T$6:$T$6005,$Q12,资金台帐!$U$6:$U$6005,"收入",资金台帐!$O$6:$O$6005,IF($C$3="全部","?*",$C$3),资金台帐!$N$6:$N$6005,">="&DATE($F$3,11,1),资金台帐!$N$6:$N$6005,"<"&DATE($F$3,11+1,1))-SUMIFS(资金台帐!$AC$6:$AC$6005,资金台帐!$T$6:$T$6005,$Q12,资金台帐!$U$6:$U$6005,"收入",资金台帐!$O$6:$O$6005,IF($C$3="全部","?*",$C$3),资金台帐!$N$6:$N$6005,">="&DATE($F$3,11,1),资金台帐!$N$6:$N$6005,"<"&DATE($F$3,11+1,1)),2) -> 0 | N12: =ROUND(SUMIFS(资金台帐!$AB$6:$AB$6005,资金台帐!$T$6:$T$6005,$Q12,资金台帐!$U$6:$U$6005,"收入",资金台帐!$O$6:$O$6005,IF($C$3="全部","?*",$C$3),资金台帐!$N$6:$N$6005,">="&DATE($F$3,12,1),资金台帐!$N$6:$N$6005,"<"&DATE($F$3,12+1,1))-SUMIFS(资金台帐!$AC$6:$AC$6005,资金台帐!$T$6:$T$6005,$Q12,资金台帐!$U$6:$U$6005,"收入",资金台帐!$O$6:$O$6005,IF($C$3="全部","?*",$C$3),资金台帐!$N$6:$N$6005,">="&DATE($F$3,12,1),资金台帐!$N$6:$N$6005,"<"&DATE($F$3,12+1,1)),2) -> 0 | O12: =ROUND(SUM(C12:N12),2) -> 0 | P12: =IF(N($O$16)=0,"",O12/$O$16) -> 0 | Q12: =基础资料!$U$12&"" -> 转介绍
B13: =IF(基础资料!$W$13="",基础资料!$U$13&"",基础资料!$W$13&"") -> 园区返税 | C13: =ROUND(SUMIFS(资金台帐!$AB$6:$AB$6005,资金台帐!$T$6:$T$6005,$Q13,资金台帐!$U$6:$U$6005,"收入",资金台帐!$O$6:$O$6005,IF($C$3="全部","?*",$C$3),资金台帐!$N$6:$N$6005,">="&DATE($F$3,1,1),资金台帐!$N$6:$N$6005,"<"&DATE($F$3,1+1,1))-SUMIFS(资金台帐!$AC$6:$AC$6005,资金台帐!$T$6:$T$6005,$Q13,资金台帐!$U$6:$U$6005,"收入",资金台帐!$O$6:$O$6005,IF($C$3="全部","?*",$C$3),资金台帐!$N$6:$N$6005,">="&DATE($F$3,1,1),资金台帐!$N$6:$N$6005,"<"&DATE($F$3,1+1,1)),2) -> 0 | D13: =ROUND(SUMIFS(资金台帐!$AB$6:$AB$6005,资金台帐!$T$6:$T$6005,$Q13,资金台帐!$U$6:$U$6005,"收入",资金台帐!$O$6:$O$6005,IF($C$3="全部","?*",$C$3),资金台帐!$N$6:$N$6005,">="&DATE($F$3,2,1),资金台帐!$N$6:$N$6005,"<"&DATE($F$3,2+1,1))-SUMIFS(资金台帐!$AC$6:$AC$6005,资金台帐!$T$6:$T$6005,$Q13,资金台帐!$U$6:$U$6005,"收入",资金台帐!$O$6:$O$6005,IF($C$3="全部","?*",$C$3),资金台帐!$N$6:$N$6005,">="&DATE($F$3,2,1),资金台帐!$N$6:$N$6005,"<"&DATE($F$3,2+1,1)),2) -> 0 | E13: =ROUND(SUMIFS(资金台帐!$AB$6:$AB$6005,资金台帐!$T$6:$T$6005,$Q13,资金台帐!$U$6:$U$6005,"收入",资金台帐!$O$6:$O$6005,IF($C$3="全部","?*",$C$3),资金台帐!$N$6:$N$6005,">="&DATE($F$3,3,1),资金台帐!$N$6:$N$6005,"<"&DATE($F$3,3+1,1))-SUMIFS(资金台帐!$AC$6:$AC$6005,资金台帐!$T$6:$T$6005,$Q13,资金台帐!$U$6:$U$6005,"收入",资金台帐!$O$6:$O$6005,IF($C$3="全部","?*",$C$3),资金台帐!$N$6:$N$6005,">="&DATE($F$3,3,1),资金台帐!$N$6:$N$6005,"<"&DATE($F$3,3+1,1)),2) -> 0 | F13: =ROUND(SUMIFS(资金台帐!$AB$6:$AB$6005,资金台帐!$T$6:$T$6005,$Q13,资金台帐!$U$6:$U$6005,"收入",资金台帐!$O$6:$O$6005,IF($C$3="全部","?*",$C$3),资金台帐!$N$6:$N$6005,">="&DATE($F$3,4,1),资金台帐!$N$6:$N$6005,"<"&DATE($F$3,4+1,1))-SUMIFS(资金台帐!$AC$6:$AC$6005,资金台帐!$T$6:$T$6005,$Q13,资金台帐!$U$6:$U$6005,"收入",资金台帐!$O$6:$O$6005,IF($C$3="全部","?*",$C$3),资金台帐!$N$6:$N$6005,">="&DATE($F$3,4,1),资金台帐!$N$6:$N$6005,"<"&DATE($F$3,4+1,1)),2) -> 0 | G13: =ROUND(SUMIFS(资金台帐!$AB$6:$AB$6005,资金台帐!$T$6:$T$6005,$Q13,资金台帐!$U$6:$U$6005,"收入",资金台帐!$O$6:$O$6005,IF($C$3="全部","?*",$C$3),资金台帐!$N$6:$N$6005,">="&DATE($F$3,5,1),资金台帐!$N$6:$N$6005,"<"&DATE($F$3,5+1,1))-SUMIFS(资金台帐!$AC$6:$AC$6005,资金台帐!$T$6:$T$6005,$Q13,资金台帐!$U$6:$U$6005,"收入",资金台帐!$O$6:$O$6005,IF($C$3="全部","?*",$C$3),资金台帐!$N$6:$N$6005,">="&DATE($F$3,5,1),资金台帐!$N$6:$N$6005,"<"&DATE($F$3,5+1,1)),2) -> 0 | H13: =ROUND(SUMIFS(资金台帐!$AB$6:$AB$6005,资金台帐!$T$6:$T$6005,$Q13,资金台帐!$U$6:$U$6005,"收入",资金台帐!$O$6:$O$6005,IF($C$3="全部","?*",$C$3),资金台帐!$N$6:$N$6005,">="&DATE($F$3,6,1),资金台帐!$N$6:$N$6005,"<"&DATE($F$3,6+1,1))-SUMIFS(资金台帐!$AC$6:$AC$6005,资金台帐!$T$6:$T$6005,$Q13,资金台帐!$U$6:$U$6005,"收入",资金台帐!$O$6:$O$6005,IF($C$3="全部","?*",$C$3),资金台帐!$N$6:$N$6005,">="&DATE($F$3,6,1),资金台帐!$N$6:$N$6005,"<"&DATE($F$3,6+1,1)),2) -> 0 | I13: =ROUND(SUMIFS(资金台帐!$AB$6:$AB$6005,资金台帐!$T$6:$T$6005,$Q13,资金台帐!$U$6:$U$6005,"收入",资金台帐!$O$6:$O$6005,IF($C$3="全部","?*",$C$3),资金台帐!$N$6:$N$6005,">="&DATE($F$3,7,1),资金台帐!$N$6:$N$6005,"<"&DATE($F$3,7+1,1))-SUMIFS(资金台帐!$AC$6:$AC$6005,资金台帐!$T$6:$T$6005,$Q13,资金台帐!$U$6:$U$6005,"收入",资金台帐!$O$6:$O$6005,IF($C$3="全部","?*",$C$3),资金台帐!$N$6:$N$6005,">="&DATE($F$3,7,1),资金台帐!$N$6:$N$6005,"<"&DATE($F$3,7+1,1)),2) -> 0 | J13: =ROUND(SUMIFS(资金台帐!$AB$6:$AB$6005,资金台帐!$T$6:$T$6005,$Q13,资金台帐!$U$6:$U$6005,"收入",资金台帐!$O$6:$O$6005,IF($C$3="全部","?*",$C$3),资金台帐!$N$6:$N$6005,">="&DATE($F$3,8,1),资金台帐!$N$6:$N$6005,"<"&DATE($F$3,8+1,1))-SUMIFS(资金台帐!$AC$6:$AC$6005,资金台帐!$T$6:$T$6005,$Q13,资金台帐!$U$6:$U$6005,"收入",资金台帐!$O$6:$O$6005,IF($C$3="全部","?*",$C$3),资金台帐!$N$6:$N$6005,">="&DATE($F$3,8,1),资金台帐!$N$6:$N$6005,"<"&DATE($F$3,8+1,1)),2) -> 0 | K13: =ROUND(SUMIFS(资金台帐!$AB$6:$AB$6005,资金台帐!$T$6:$T$6005,$Q13,资金台帐!$U$6:$U$6005,"收入",资金台帐!$O$6:$O$6005,IF($C$3="全部","?*",$C$3),资金台帐!$N$6:$N$6005,">="&DATE($F$3,9,1),资金台帐!$N$6:$N$6005,"<"&DATE($F$3,9+1,1))-SUMIFS(资金台帐!$AC$6:$AC$6005,资金台帐!$T$6:$T$6005,$Q13,资金台帐!$U$6:$U$6005,"收入",资金台帐!$O$6:$O$6005,IF($C$3="全部","?*",$C$3),资金台帐!$N$6:$N$6005,">="&DATE($F$3,9,1),资金台帐!$N$6:$N$6005,"<"&DATE($F$3,9+1,1)),2) -> 0 | L13: =ROUND(SUMIFS(资金台帐!$AB$6:$AB$6005,资金台帐!$T$6:$T$6005,$Q13,资金台帐!$U$6:$U$6005,"收入",资金台帐!$O$6:$O$6005,IF($C$3="全部","?*",$C$3),资金台帐!$N$6:$N$6005,">="&DATE($F$3,10,1),资金台帐!$N$6:$N$6005,"<"&DATE($F$3,10+1,1))-SUMIFS(资金台帐!$AC$6:$AC$6005,资金台帐!$T$6:$T$6005,$Q13,资金台帐!$U$6:$U$6005,"收入",资金台帐!$O$6:$O$6005,IF($C$3="全部","?*",$C$3),资金台帐!$N$6:$N$6005,">="&DATE($F$3,10,1),资金台帐!$N$6:$N$6005,"<"&DATE($F$3,10+1,1)),2) -> 0 | M13: =ROUND(SUMIFS(资金台帐!$AB$6:$AB$6005,资金台帐!$T$6:$T$6005,$Q13,资金台帐!$U$6:$U$6005,"收入",资金台帐!$O$6:$O$6005,IF($C$3="全部","?*",$C$3),资金台帐!$N$6:$N$6005,">="&DATE($F$3,11,1),资金台帐!$N$6:$N$6005,"<"&DATE($F$3,11+1,1))-SUMIFS(资金台帐!$AC$6:$AC$6005,资金台帐!$T$6:$T$6005,$Q13,资金台帐!$U$6:$U$6005,"收入",资金台帐!$O$6:$O$6005,IF($C$3="全部","?*",$C$3),资金台帐!$N$6:$N$6005,">="&DATE($F$3,11,1),资金台帐!$N$6:$N$6005,"<"&DATE($F$3,11+1,1)),2) -> 0 | N13: =ROUND(SUMIFS(资金台帐!$AB$6:$AB$6005,资金台帐!$T$6:$T$6005,$Q13,资金台帐!$U$6:$U$6005,"收入",资金台帐!$O$6:$O$6005,IF($C$3="全部","?*",$C$3),资金台帐!$N$6:$N$6005,">="&DATE($F$3,12,1),资金台帐!$N$6:$N$6005,"<"&DATE($F$3,12+1,1))-SUMIFS(资金台帐!$AC$6:$AC$6005,资金台帐!$T$6:$T$6005,$Q13,资金台帐!$U$6:$U$6005,"收入",资金台帐!$O$6:$O$6005,IF($C$3="全部","?*",$C$3),资金台帐!$N$6:$N$6005,">="&DATE($F$3,12,1),资金台帐!$N$6:$N$6005,"<"&DATE($F$3,12+1,1)),2) -> 0 | O13: =ROUND(SUM(C13:N13),2) -> 0 | P13: =IF(N($O$16)=0,"",O13/$O$16) -> 0 | Q13: =基础资料!$U$13&"" -> 园区返税
B14: =IF(基础资料!$W$14="",基础资料!$U$14&"",基础资料!$W$14&"") -> 咨询服务 | C14: =ROUND(SUMIFS(资金台帐!$AB$6:$AB$6005,资金台帐!$T$6:$T$6005,$Q14,资金台帐!$U$6:$U$6005,"收入",资金台帐!$O$6:$O$6005,IF($C$3="全部","?*",$C$3),资金台帐!$N$6:$N$6005,">="&DATE($F$3,1,1),资金台帐!$N$6:$N$6005,"<"&DATE($F$3,1+1,1))-SUMIFS(资金台帐!$AC$6:$AC$6005,资金台帐!$T$6:$T$6005,$Q14,资金台帐!$U$6:$U$6005,"收入",资金台帐!$O$6:$O$6005,IF($C$3="全部","?*",$C$3),资金台帐!$N$6:$N$6005,">="&DATE($F$3,1,1),资金台帐!$N$6:$N$6005,"<"&DATE($F$3,1+1,1)),2) -> 0 | D14: =ROUND(SUMIFS(资金台帐!$AB$6:$AB$6005,资金台帐!$T$6:$T$6005,$Q14,资金台帐!$U$6:$U$6005,"收入",资金台帐!$O$6:$O$6005,IF($C$3="全部","?*",$C$3),资金台帐!$N$6:$N$6005,">="&DATE($F$3,2,1),资金台帐!$N$6:$N$6005,"<"&DATE($F$3,2+1,1))-SUMIFS(资金台帐!$AC$6:$AC$6005,资金台帐!$T$6:$T$6005,$Q14,资金台帐!$U$6:$U$6005,"收入",资金台帐!$O$6:$O$6005,IF($C$3="全部","?*",$C$3),资金台帐!$N$6:$N$6005,">="&DATE($F$3,2,1),资金台帐!$N$6:$N$6005,"<"&DATE($F$3,2+1,1)),2) -> 0 | E14: =ROUND(SUMIFS(资金台帐!$AB$6:$AB$6005,资金台帐!$T$6:$T$6005,$Q14,资金台帐!$U$6:$U$6005,"收入",资金台帐!$O$6:$O$6005,IF($C$3="全部","?*",$C$3),资金台帐!$N$6:$N$6005,">="&DATE($F$3,3,1),资金台帐!$N$6:$N$6005,"<"&DATE($F$3,3+1,1))-SUMIFS(资金台帐!$AC$6:$AC$6005,资金台帐!$T$6:$T$6005,$Q14,资金台帐!$U$6:$U$6005,"收入",资金台帐!$O$6:$O$6005,IF($C$3="全部","?*",$C$3),资金台帐!$N$6:$N$6005,">="&DATE($F$3,3,1),资金台帐!$N$6:$N$6005,"<"&DATE($F$3,3+1,1)),2) -> 0 | F14: =ROUND(SUMIFS(资金台帐!$AB$6:$AB$6005,资金台帐!$T$6:$T$6005,$Q14,资金台帐!$U$6:$U$6005,"收入",资金台帐!$O$6:$O$6005,IF($C$3="全部","?*",$C$3),资金台帐!$N$6:$N$6005,">="&DATE($F$3,4,1),资金台帐!$N$6:$N$6005,"<"&DATE($F$3,4+1,1))-SUMIFS(资金台帐!$AC$6:$AC$6005,资金台帐!$T$6:$T$6005,$Q14,资金台帐!$U$6:$U$6005,"收入",资金台帐!$O$6:$O$6005,IF($C$3="全部","?*",$C$3),资金台帐!$N$6:$N$6005,">="&DATE($F$3,4,1),资金台帐!$N$6:$N$6005,"<"&DATE($F$3,4+1,1)),2) -> 0 | G14: =ROUND(SUMIFS(资金台帐!$AB$6:$AB$6005,资金台帐!$T$6:$T$6005,$Q14,资金台帐!$U$6:$U$6005,"收入",资金台帐!$O$6:$O$6005,IF($C$3="全部","?*",$C$3),资金台帐!$N$6:$N$6005,">="&DATE($F$3,5,1),资金台帐!$N$6:$N$6005,"<"&DATE($F$3,5+1,1))-SUMIFS(资金台帐!$AC$6:$AC$6005,资金台帐!$T$6:$T$6005,$Q14,资金台帐!$U$6:$U$6005,"收入",资金台帐!$O$6:$O$6005,IF($C$3="全部","?*",$C$3),资金台帐!$N$6:$N$6005,">="&DATE($F$3,5,1),资金台帐!$N$6:$N$6005,"<"&DATE($F$3,5+1,1)),2) -> 0 | H14: =ROUND(SUMIFS(资金台帐!$AB$6:$AB$6005,资金台帐!$T$6:$T$6005,$Q14,资金台帐!$U$6:$U$6005,"收入",资金台帐!$O$6:$O$6005,IF($C$3="全部","?*",$C$3),资金台帐!$N$6:$N$6005,">="&DATE($F$3,6,1),资金台帐!$N$6:$N$6005,"<"&DATE($F$3,6+1,1))-SUMIFS(资金台帐!$AC$6:$AC$6005,资金台帐!$T$6:$T$6005,$Q14,资金台帐!$U$6:$U$6005,"收入",资金台帐!$O$6:$O$6005,IF($C$3="全部","?*",$C$3),资金台帐!$N$6:$N$6005,">="&DATE($F$3,6,1),资金台帐!$N$6:$N$6005,"<"&DATE($F$3,6+1,1)),2) -> 0 | I14: =ROUND(SUMIFS(资金台帐!$AB$6:$AB$6005,资金台帐!$T$6:$T$6005,$Q14,资金台帐!$U$6:$U$6005,"收入",资金台帐!$O$6:$O$6005,IF($C$3="全部","?*",$C$3),资金台帐!$N$6:$N$6005,">="&DATE($F$3,7,1),资金台帐!$N$6:$N$6005,"<"&DATE($F$3,7+1,1))-SUMIFS(资金台帐!$AC$6:$AC$6005,资金台帐!$T$6:$T$6005,$Q14,资金台帐!$U$6:$U$6005,"收入",资金台帐!$O$6:$O$6005,IF($C$3="全部","?*",$C$3),资金台帐!$N$6:$N$6005,">="&DATE($F$3,7,1),资金台帐!$N$6:$N$6005,"<"&DATE($F$3,7+1,1)),2) -> 0 | J14: =ROUND(SUMIFS(资金台帐!$AB$6:$AB$6005,资金台帐!$T$6:$T$6005,$Q14,资金台帐!$U$6:$U$6005,"收入",资金台帐!$O$6:$O$6005,IF($C$3="全部","?*",$C$3),资金台帐!$N$6:$N$6005,">="&DATE($F$3,8,1),资金台帐!$N$6:$N$6005,"<"&DATE($F$3,8+1,1))-SUMIFS(资金台帐!$AC$6:$AC$6005,资金台帐!$T$6:$T$6005,$Q14,资金台帐!$U$6:$U$6005,"收入",资金台帐!$O$6:$O$6005,IF($C$3="全部","?*",$C$3),资金台帐!$N$6:$N$6005,">="&DATE($F$3,8,1),资金台帐!$N$6:$N$6005,"<"&DATE($F$3,8+1,1)),2) -> 0 | K14: =ROUND(SUMIFS(资金台帐!$AB$6:$AB$6005,资金台帐!$T$6:$T$6005,$Q14,资金台帐!$U$6:$U$6005,"收入",资金台帐!$O$6:$O$6005,IF($C$3="全部","?*",$C$3),资金台帐!$N$6:$N$6005,">="&DATE($F$3,9,1),资金台帐!$N$6:$N$6005,"<"&DATE($F$3,9+1,1))-SUMIFS(资金台帐!$AC$6:$AC$6005,资金台帐!$T$6:$T$6005,$Q14,资金台帐!$U$6:$U$6005,"收入",资金台帐!$O$6:$O$6005,IF($C$3="全部","?*",$C$3),资金台帐!$N$6:$N$6005,">="&DATE($F$3,9,1),资金台帐!$N$6:$N$6005,"<"&DATE($F$3,9+1,1)),2) -> 0 | L14: =ROUND(SUMIFS(资金台帐!$AB$6:$AB$6005,资金台帐!$T$6:$T$6005,$Q14,资金台帐!$U$6:$U$6005,"收入",资金台帐!$O$6:$O$6005,IF($C$3="全部","?*",$C$3),资金台帐!$N$6:$N$6005,">="&DATE($F$3,10,1),资金台帐!$N$6:$N$6005,"<"&DATE($F$3,10+1,1))-SUMIFS(资金台帐!$AC$6:$AC$6005,资金台帐!$T$6:$T$6005,$Q14,资金台帐!$U$6:$U$6005,"收入",资金台帐!$O$6:$O$6005,IF($C$3="全部","?*",$C$3),资金台帐!$N$6:$N$6005,">="&DATE($F$3,10,1),资金台帐!$N$6:$N$6005,"<"&DATE($F$3,10+1,1)),2) -> 0 | M14: =ROUND(SUMIFS(资金台帐!$AB$6:$AB$6005,资金台帐!$T$6:$T$6005,$Q14,资金台帐!$U$6:$U$6005,"收入",资金台帐!$O$6:$O$6005,IF($C$3="全部","?*",$C$3),资金台帐!$N$6:$N$6005,">="&DATE($F$3,11,1),资金台帐!$N$6:$N$6005,"<"&DATE($F$3,11+1,1))-SUMIFS(资金台帐!$AC$6:$AC$6005,资金台帐!$T$6:$T$6005,$Q14,资金台帐!$U$6:$U$6005,"收入",资金台帐!$O$6:$O$6005,IF($C$3="全部","?*",$C$3),资金台帐!$N$6:$N$6005,">="&DATE($F$3,11,1),资金台帐!$N$6:$N$6005,"<"&DATE($F$3,11+1,1)),2) -> 0 | N14: =ROUND(SUMIFS(资金台帐!$AB$6:$AB$6005,资金台帐!$T$6:$T$6005,$Q14,资金台帐!$U$6:$U$6005,"收入",资金台帐!$O$6:$O$6005,IF($C$3="全部","?*",$C$3),资金台帐!$N$6:$N$6005,">="&DATE($F$3,12,1),资金台帐!$N$6:$N$6005,"<"&DATE($F$3,12+1,1))-SUMIFS(资金台帐!$AC$6:$AC$6005,资金台帐!$T$6:$T$6005,$Q14,资金台帐!$U$6:$U$6005,"收入",资金台帐!$O$6:$O$6005,IF($C$3="全部","?*",$C$3),资金台帐!$N$6:$N$6005,">="&DATE($F$3,12,1),资金台帐!$N$6:$N$6005,"<"&DATE($F$3,12+1,1)),2) -> 0 | O14: =ROUND(SUM(C14:N14),2) -> 0 | P14: =IF(N($O$16)=0,"",O14/$O$16) -> 0 | Q14: =基础资料!$U$14&"" -> 咨询服务
B15: =IF(COUNTIFS(基础资料!$V$5:$V$64,"收入",基础资料!$U$5:$U$64,"?*")>11,"其他（含新加项目）","其他") -> 其他 | C15: =ROUND(SUMIFS(资金台帐!$AB$6:$AB$6005,资金台帐!$U$6:$U$6005,"收入",资金台帐!$O$6:$O$6005,IF($C$3="全部","?*",$C$3),资金台帐!$N$6:$N$6005,">="&DATE($F$3,1,1),资金台帐!$N$6:$N$6005,"<"&DATE($F$3,1+1,1))-SUMIFS(资金台帐!$AC$6:$AC$6005,资金台帐!$U$6:$U$6005,"收入",资金台帐!$O$6:$O$6005,IF($C$3="全部","?*",$C$3),资金台帐!$N$6:$N$6005,">="&DATE($F$3,1,1),资金台帐!$N$6:$N$6005,"<"&DATE($F$3,1+1,1))-SUM(C5:C14),2) -> 0 | D15: =ROUND(SUMIFS(资金台帐!$AB$6:$AB$6005,资金台帐!$U$6:$U$6005,"收入",资金台帐!$O$6:$O$6005,IF($C$3="全部","?*",$C$3),资金台帐!$N$6:$N$6005,">="&DATE($F$3,2,1),资金台帐!$N$6:$N$6005,"<"&DATE($F$3,2+1,1))-SUMIFS(资金台帐!$AC$6:$AC$6005,资金台帐!$U$6:$U$6005,"收入",资金台帐!$O$6:$O$6005,IF($C$3="全部","?*",$C$3),资金台帐!$N$6:$N$6005,">="&DATE($F$3,2,1),资金台帐!$N$6:$N$6005,"<"&DATE($F$3,2+1,1))-SUM(D5:D14),2) -> 0 | E15: =ROUND(SUMIFS(资金台帐!$AB$6:$AB$6005,资金台帐!$U$6:$U$6005,"收入",资金台帐!$O$6:$O$6005,IF($C$3="全部","?*",$C$3),资金台帐!$N$6:$N$6005,">="&DATE($F$3,3,1),资金台帐!$N$6:$N$6005,"<"&DATE($F$3,3+1,1))-SUMIFS(资金台帐!$AC$6:$AC$6005,资金台帐!$U$6:$U$6005,"收入",资金台帐!$O$6:$O$6005,IF($C$3="全部","?*",$C$3),资金台帐!$N$6:$N$6005,">="&DATE($F$3,3,1),资金台帐!$N$6:$N$6005,"<"&DATE($F$3,3+1,1))-SUM(E5:E14),2) -> 0 | F15: =ROUND(SUMIFS(资金台帐!$AB$6:$AB$6005,资金台帐!$U$6:$U$6005,"收入",资金台帐!$O$6:$O$6005,IF($C$3="全部","?*",$C$3),资金台帐!$N$6:$N$6005,">="&DATE($F$3,4,1),资金台帐!$N$6:$N$6005,"<"&DATE($F$3,4+1,1))-SUMIFS(资金台帐!$AC$6:$AC$6005,资金台帐!$U$6:$U$6005,"收入",资金台帐!$O$6:$O$6005,IF($C$3="全部","?*",$C$3),资金台帐!$N$6:$N$6005,">="&DATE($F$3,4,1),资金台帐!$N$6:$N$6005,"<"&DATE($F$3,4+1,1))-SUM(F5:F14),2) -> 0 | G15: =ROUND(SUMIFS(资金台帐!$AB$6:$AB$6005,资金台帐!$U$6:$U$6005,"收入",资金台帐!$O$6:$O$6005,IF($C$3="全部","?*",$C$3),资金台帐!$N$6:$N$6005,">="&DATE($F$3,5,1),资金台帐!$N$6:$N$6005,"<"&DATE($F$3,5+1,1))-SUMIFS(资金台帐!$AC$6:$AC$6005,资金台帐!$U$6:$U$6005,"收入",资金台帐!$O$6:$O$6005,IF($C$3="全部","?*",$C$3),资金台帐!$N$6:$N$6005,">="&DATE($F$3,5,1),资金台帐!$N$6:$N$6005,"<"&DATE($F$3,5+1,1))-SUM(G5:G14),2) -> 0 | H15: =ROUND(SUMIFS(资金台帐!$AB$6:$AB$6005,资金台帐!$U$6:$U$6005,"收入",资金台帐!$O$6:$O$6005,IF($C$3="全部","?*",$C$3),资金台帐!$N$6:$N$6005,">="&DATE($F$3,6,1),资金台帐!$N$6:$N$6005,"<"&DATE($F$3,6+1,1))-SUMIFS(资金台帐!$AC$6:$AC$6005,资金台帐!$U$6:$U$6005,"收入",资金台帐!$O$6:$O$6005,IF($C$3="全部","?*",$C$3),资金台帐!$N$6:$N$6005,">="&DATE($F$3,6,1),资金台帐!$N$6:$N$6005,"<"&DATE($F$3,6+1,1))-SUM(H5:H14),2) -> 0 | I15: =ROUND(SUMIFS(资金台帐!$AB$6:$AB$6005,资金台帐!$U$6:$U$6005,"收入",资金台帐!$O$6:$O$6005,IF($C$3="全部","?*",$C$3),资金台帐!$N$6:$N$6005,">="&DATE($F$3,7,1),资金台帐!$N$6:$N$6005,"<"&DATE($F$3,7+1,1))-SUMIFS(资金台帐!$AC$6:$AC$6005,资金台帐!$U$6:$U$6005,"收入",资金台帐!$O$6:$O$6005,IF($C$3="全部","?*",$C$3),资金台帐!$N$6:$N$6005,">="&DATE($F$3,7,1),资金台帐!$N$6:$N$6005,"<"&DATE($F$3,7+1,1))-SUM(I5:I14),2) -> 0 | J15: =ROUND(SUMIFS(资金台帐!$AB$6:$AB$6005,资金台帐!$U$6:$U$6005,"收入",资金台帐!$O$6:$O$6005,IF($C$3="全部","?*",$C$3),资金台帐!$N$6:$N$6005,">="&DATE($F$3,8,1),资金台帐!$N$6:$N$6005,"<"&DATE($F$3,8+1,1))-SUMIFS(资金台帐!$AC$6:$AC$6005,资金台帐!$U$6:$U$6005,"收入",资金台帐!$O$6:$O$6005,IF($C$3="全部","?*",$C$3),资金台帐!$N$6:$N$6005,">="&DATE($F$3,8,1),资金台帐!$N$6:$N$6005,"<"&DATE($F$3,8+1,1))-SUM(J5:J14),2) -> 0 | K15: =ROUND(SUMIFS(资金台帐!$AB$6:$AB$6005,资金台帐!$U$6:$U$6005,"收入",资金台帐!$O$6:$O$6005,IF($C$3="全部","?*",$C$3),资金台帐!$N$6:$N$6005,">="&DATE($F$3,9,1),资金台帐!$N$6:$N$6005,"<"&DATE($F$3,9+1,1))-SUMIFS(资金台帐!$AC$6:$AC$6005,资金台帐!$U$6:$U$6005,"收入",资金台帐!$O$6:$O$6005,IF($C$3="全部","?*",$C$3),资金台帐!$N$6:$N$6005,">="&DATE($F$3,9,1),资金台帐!$N$6:$N$6005,"<"&DATE($F$3,9+1,1))-SUM(K5:K14),2) -> 0 | L15: =ROUND(SUMIFS(资金台帐!$AB$6:$AB$6005,资金台帐!$U$6:$U$6005,"收入",资金台帐!$O$6:$O$6005,IF($C$3="全部","?*",$C$3),资金台帐!$N$6:$N$6005,">="&DATE($F$3,10,1),资金台帐!$N$6:$N$6005,"<"&DATE($F$3,10+1,1))-SUMIFS(资金台帐!$AC$6:$AC$6005,资金台帐!$U$6:$U$6005,"收入",资金台帐!$O$6:$O$6005,IF($C$3="全部","?*",$C$3),资金台帐!$N$6:$N$6005,">="&DATE($F$3,10,1),资金台帐!$N$6:$N$6005,"<"&DATE($F$3,10+1,1))-SUM(L5:L14),2) -> 0 | M15: =ROUND(SUMIFS(资金台帐!$AB$6:$AB$6005,资金台帐!$U$6:$U$6005,"收入",资金台帐!$O$6:$O$6005,IF($C$3="全部","?*",$C$3),资金台帐!$N$6:$N$6005,">="&DATE($F$3,11,1),资金台帐!$N$6:$N$6005,"<"&DATE($F$3,11+1,1))-SUMIFS(资金台帐!$AC$6:$AC$6005,资金台帐!$U$6:$U$6005,"收入",资金台帐!$O$6:$O$6005,IF($C$3="全部","?*",$C$3),资金台帐!$N$6:$N$6005,">="&DATE($F$3,11,1),资金台帐!$N$6:$N$6005,"<"&DATE($F$3,11+1,1))-SUM(M5:M14),2) -> 0 | N15: =ROUND(SUMIFS(资金台帐!$AB$6:$AB$6005,资金台帐!$U$6:$U$6005,"收入",资金台帐!$O$6:$O$6005,IF($C$3="全部","?*",$C$3),资金台帐!$N$6:$N$6005,">="&DATE($F$3,12,1),资金台帐!$N$6:$N$6005,"<"&DATE($F$3,12+1,1))-SUMIFS(资金台帐!$AC$6:$AC$6005,资金台帐!$U$6:$U$6005,"收入",资金台帐!$O$6:$O$6005,IF($C$3="全部","?*",$C$3),资金台帐!$N$6:$N$6005,">="&DATE($F$3,12,1),资金台帐!$N$6:$N$6005,"<"&DATE($F$3,12+1,1))-SUM(N5:N14),2) -> 0 | O15: =ROUND(SUM(C15:N15),2) -> 0 | P15: =IF(N($O$16)=0,"",O15/$O$16) -> 0 | Q15: =基础资料!$U$15&"" -> 其他收入
B16: 小计 | C16: =ROUND(SUM(C5:C15),2) -> 0 | D16: =ROUND(SUM(D5:D15),2) -> 0 | E16: =ROUND(SUM(E5:E15),2) -> 0 | F16: =ROUND(SUM(F5:F15),2) -> 0 | G16: =ROUND(SUM(G5:G15),2) -> 0 | H16: =ROUND(SUM(H5:H15),2) -> 0 | I16: =ROUND(SUM(I5:I15),2) -> 0 | J16: =ROUND(SUM(J5:J15),2) -> 0 | ... O16: =ROUND(SUM(O5:O15),2) -> 171000 | P16: =IF(N($O$16)=0,"",O16/$O$16) -> 1
A17: 变动成本 | B17: =IF(基础资料!$W$16="",基础资料!$U$16&"",基础资料!$W$16&"") -> 人工-工资 | C17: =ROUND(SUMIFS(资金台帐!$AC$6:$AC$6005,资金台帐!$T$6:$T$6005,$Q17,资金台帐!$U$6:$U$6005,"变动成本",资金台帐!$O$6:$O$6005,IF($C$3="全部","?*",$C$3),资金台帐!$N$6:$N$6005,">="&DATE($F$3,1,1),资金台帐!$N$6:$N$6005,"<"&DATE($F$3,1+1,1))-SUMIFS(资金台帐!$AB$6:$AB$6005,资金台帐!$T$6:$T$6005,$Q17,资金台帐!$U$6:$U$6005,"变动成本",资金台帐!$O$6:$O$6005,IF($C$3="全部","?*",$C$3),资金台帐!$N$6:$N$6005,">="&DATE($F$3,1,1),资金台帐!$N$6:$N$6005,"<"&DATE($F$3,1+1,1)),2) -> 0 | D17: =ROUND(SUMIFS(资金台帐!$AC$6:$AC$6005,资金台帐!$T$6:$T$6005,$Q17,资金台帐!$U$6:$U$6005,"变动成本",资金台帐!$O$6:$O$6005,IF($C$3="全部","?*",$C$3),资金台帐!$N$6:$N$6005,">="&DATE($F$3,2,1),资金台帐!$N$6:$N$6005,"<"&DATE($F$3,2+1,1))-SUMIFS(资金台帐!$AB$6:$AB$6005,资金台帐!$T$6:$T$6005,$Q17,资金台帐!$U$6:$U$6005,"变动成本",资金台帐!$O$6:$O$6005,IF($C$3="全部","?*",$C$3),资金台帐!$N$6:$N$6005,">="&DATE($F$3,2,1),资金台帐!$N$6:$N$6005,"<"&DATE($F$3,2+1,1)),2) -> 0 | E17: =ROUND(SUMIFS(资金台帐!$AC$6:$AC$6005,资金台帐!$T$6:$T$6005,$Q17,资金台帐!$U$6:$U$6005,"变动成本",资金台帐!$O$6:$O$6005,IF($C$3="全部","?*",$C$3),资金台帐!$N$6:$N$6005,">="&DATE($F$3,3,1),资金台帐!$N$6:$N$6005,"<"&DATE($F$3,3+1,1))-SUMIFS(资金台帐!$AB$6:$AB$6005,资金台帐!$T$6:$T$6005,$Q17,资金台帐!$U$6:$U$6005,"变动成本",资金台帐!$O$6:$O$6005,IF($C$3="全部","?*",$C$3),资金台帐!$N$6:$N$6005,">="&DATE($F$3,3,1),资金台帐!$N$6:$N$6005,"<"&DATE($F$3,3+1,1)),2) -> 0 | F17: =ROUND(SUMIFS(资金台帐!$AC$6:$AC$6005,资金台帐!$T$6:$T$6005,$Q17,资金台帐!$U$6:$U$6005,"变动成本",资金台帐!$O$6:$O$6005,IF($C$3="全部","?*",$C$3),资金台帐!$N$6:$N$6005,">="&DATE($F$3,4,1),资金台帐!$N$6:$N$6005,"<"&DATE($F$3,4+1,1))-SUMIFS(资金台帐!$AB$6:$AB$6005,资金台帐!$T$6:$T$6005,$Q17,资金台帐!$U$6:$U$6005,"变动成本",资金台帐!$O$6:$O$6005,IF($C$3="全部","?*",$C$3),资金台帐!$N$6:$N$6005,">="&DATE($F$3,4,1),资金台帐!$N$6:$N$6005,"<"&DATE($F$3,4+1,1)),2) -> 0 | G17: =ROUND(SUMIFS(资金台帐!$AC$6:$AC$6005,资金台帐!$T$6:$T$6005,$Q17,资金台帐!$U$6:$U$6005,"变动成本",资金台帐!$O$6:$O$6005,IF($C$3="全部","?*",$C$3),资金台帐!$N$6:$N$6005,">="&DATE($F$3,5,1),资金台帐!$N$6:$N$6005,"<"&DATE($F$3,5+1,1))-SUMIFS(资金台帐!$AB$6:$AB$6005,资金台帐!$T$6:$T$6005,$Q17,资金台帐!$U$6:$U$6005,"变动成本",资金台帐!$O$6:$O$6005,IF($C$3="全部","?*",$C$3),资金台帐!$N$6:$N$6005,">="&DATE($F$3,5,1),资金台帐!$N$6:$N$6005,"<"&DATE($F$3,5+1,1)),2) -> 0 | H17: =ROUND(SUMIFS(资金台帐!$AC$6:$AC$6005,资金台帐!$T$6:$T$6005,$Q17,资金台帐!$U$6:$U$6005,"变动成本",资金台帐!$O$6:$O$6005,IF($C$3="全部","?*",$C$3),资金台帐!$N$6:$N$6005,">="&DATE($F$3,6,1),资金台帐!$N$6:$N$6005,"<"&DATE($F$3,6+1,1))-SUMIFS(资金台帐!$AB$6:$AB$6005,资金台帐!$T$6:$T$6005,$Q17,资金台帐!$U$6:$U$6005,"变动成本",资金台帐!$O$6:$O$6005,IF($C$3="全部","?*",$C$3),资金台帐!$N$6:$N$6005,">="&DATE($F$3,6,1),资金台帐!$N$6:$N$6005,"<"&DATE($F$3,6+1,1)),2) -> 0 | I17: =ROUND(SUMIFS(资金台帐!$AC$6:$AC$6005,资金台帐!$T$6:$T$6005,$Q17,资金台帐!$U$6:$U$6005,"变动成本",资金台帐!$O$6:$O$6005,IF($C$3="全部","?*",$C$3),资金台帐!$N$6:$N$6005,">="&DATE($F$3,7,1),资金台帐!$N$6:$N$6005,"<"&DATE($F$3,7+1,1))-SUMIFS(资金台帐!$AB$6:$AB$6005,资金台帐!$T$6:$T$6005,$Q17,资金台帐!$U$6:$U$6005,"变动成本",资金台帐!$O$6:$O$6005,IF($C$3="全部","?*",$C$3),资金台帐!$N$6:$N$6005,">="&DATE($F$3,7,1),资金台帐!$N$6:$N$6005,"<"&DATE($F$3,7+1,1)),2) -> 0 | J17: =ROUND(SUMIFS(资金台帐!$AC$6:$AC$6005,资金台帐!$T$6:$T$6005,$Q17,资金台帐!$U$6:$U$6005,"变动成本",资金台帐!$O$6:$O$6005,IF($C$3="全部","?*",$C$3),资金台帐!$N$6:$N$6005,">="&DATE($F$3,8,1),资金台帐!$N$6:$N$6005,"<"&DATE($F$3,8+1,1))-SUMIFS(资金台帐!$AB$6:$AB$6005,资金台帐!$T$6:$T$6005,$Q17,资金台帐!$U$6:$U$6005,"变动成本",资金台帐!$O$6:$O$6005,IF($C$3="全部","?*",$C$3),资金台帐!$N$6:$N$6005,">="&DATE($F$3,8,1),资金台帐!$N$6:$N$6005,"<"&DATE($F$3,8+1,1)),2) -> 0 | K17: =ROUND(SUMIFS(资金台帐!$AC$6:$AC$6005,资金台帐!$T$6:$T$6005,$Q17,资金台帐!$U$6:$U$6005,"变动成本",资金台帐!$O$6:$O$6005,IF($C$3="全部","?*",$C$3),资金台帐!$N$6:$N$6005,">="&DATE($F$3,9,1),资金台帐!$N$6:$N$6005,"<"&DATE($F$3,9+1,1))-SUMIFS(资金台帐!$AB$6:$AB$6005,资金台帐!$T$6:$T$6005,$Q17,资金台帐!$U$6:$U$6005,"变动成本",资金台帐!$O$6:$O$6005,IF($C$3="全部","?*",$C$3),资金台帐!$N$6:$N$6005,">="&DATE($F$3,9,1),资金台帐!$N$6:$N$6005,"<"&DATE($F$3,9+1,1)),2) -> 0 | L17: =ROUND(SUMIFS(资金台帐!$AC$6:$AC$6005,资金台帐!$T$6:$T$6005,$Q17,资金台帐!$U$6:$U$6005,"变动成本",资金台帐!$O$6:$O$6005,IF($C$3="全部","?*",$C$3),资金台帐!$N$6:$N$6005,">="&DATE($F$3,10,1),资金台帐!$N$6:$N$6005,"<"&DATE($F$3,10+1,1))-SUMIFS(资金台帐!$AB$6:$AB$6005,资金台帐!$T$6:$T$6005,$Q17,资金台帐!$U$6:$U$6005,"变动成本",资金台帐!$O$6:$O$6005,IF($C$3="全部","?*",$C$3),资金台帐!$N$6:$N$6005,">="&DATE($F$3,10,1),资金台帐!$N$6:$N$6005,"<"&DATE($F$3,10+1,1)),2) -> 0 | M17: =ROUND(SUMIFS(资金台帐!$AC$6:$AC$6005,资金台帐!$T$6:$T$6005,$Q17,资金台帐!$U$6:$U$6005,"变动成本",资金台帐!$O$6:$O$6005,IF($C$3="全部","?*",$C$3),资金台帐!$N$6:$N$6005,">="&DATE($F$3,11,1),资金台帐!$N$6:$N$6005,"<"&DATE($F$3,11+1,1))-SUMIFS(资金台帐!$AB$6:$AB$6005,资金台帐!$T$6:$T$6005,$Q17,资金台帐!$U$6:$U$6005,"变动成本",资金台帐!$O$6:$O$6005,IF($C$3="全部","?*",$C$3),资金台帐!$N$6:$N$6005,">="&DATE($F$3,11,1),资金台帐!$N$6:$N$6005,"<"&DATE($F$3,11+1,1)),2) -> 0 | N17: =ROUND(SUMIFS(资金台帐!$AC$6:$AC$6005,资金台帐!$T$6:$T$6005,$Q17,资金台帐!$U$6:$U$6005,"变动成本",资金台帐!$O$6:$O$6005,IF($C$3="全部","?*",$C$3),资金台帐!$N$6:$N$6005,">="&DATE($F$3,12,1),资金台帐!$N$6:$N$6005,"<"&DATE($F$3,12+1,1))-SUMIFS(资金台帐!$AB$6:$AB$6005,资金台帐!$T$6:$T$6005,$Q17,资金台帐!$U$6:$U$6005,"变动成本",资金台帐!$O$6:$O$6005,IF($C$3="全部","?*",$C$3),资金台帐!$N$6:$N$6005,">="&DATE($F$3,12,1),资金台帐!$N$6:$N$6005,"<"&DATE($F$3,12+1,1)),2) -> 0 | O17: =ROUND(SUM(C17:N17),2) -> 0 | P17: =IF(N($O$16)=0,"",O17/$O$16) -> 0 | Q17: =基础资料!$U$16&"" -> 人工-工资
B18: =IF(基础资料!$W$17="",基础资料!$U$17&"",基础资料!$W$17&"") -> 人工-社保 | C18: =ROUND(SUMIFS(资金台帐!$AC$6:$AC$6005,资金台帐!$T$6:$T$6005,$Q18,资金台帐!$U$6:$U$6005,"变动成本",资金台帐!$O$6:$O$6005,IF($C$3="全部","?*",$C$3),资金台帐!$N$6:$N$6005,">="&DATE($F$3,1,1),资金台帐!$N$6:$N$6005,"<"&DATE($F$3,1+1,1))-SUMIFS(资金台帐!$AB$6:$AB$6005,资金台帐!$T$6:$T$6005,$Q18,资金台帐!$U$6:$U$6005,"变动成本",资金台帐!$O$6:$O$6005,IF($C$3="全部","?*",$C$3),资金台帐!$N$6:$N$6005,">="&DATE($F$3,1,1),资金台帐!$N$6:$N$6005,"<"&DATE($F$3,1+1,1)),2) -> 0 | D18: =ROUND(SUMIFS(资金台帐!$AC$6:$AC$6005,资金台帐!$T$6:$T$6005,$Q18,资金台帐!$U$6:$U$6005,"变动成本",资金台帐!$O$6:$O$6005,IF($C$3="全部","?*",$C$3),资金台帐!$N$6:$N$6005,">="&DATE($F$3,2,1),资金台帐!$N$6:$N$6005,"<"&DATE($F$3,2+1,1))-SUMIFS(资金台帐!$AB$6:$AB$6005,资金台帐!$T$6:$T$6005,$Q18,资金台帐!$U$6:$U$6005,"变动成本",资金台帐!$O$6:$O$6005,IF($C$3="全部","?*",$C$3),资金台帐!$N$6:$N$6005,">="&DATE($F$3,2,1),资金台帐!$N$6:$N$6005,"<"&DATE($F$3,2+1,1)),2) -> 0 | E18: =ROUND(SUMIFS(资金台帐!$AC$6:$AC$6005,资金台帐!$T$6:$T$6005,$Q18,资金台帐!$U$6:$U$6005,"变动成本",资金台帐!$O$6:$O$6005,IF($C$3="全部","?*",$C$3),资金台帐!$N$6:$N$6005,">="&DATE($F$3,3,1),资金台帐!$N$6:$N$6005,"<"&DATE($F$3,3+1,1))-SUMIFS(资金台帐!$AB$6:$AB$6005,资金台帐!$T$6:$T$6005,$Q18,资金台帐!$U$6:$U$6005,"变动成本",资金台帐!$O$6:$O$6005,IF($C$3="全部","?*",$C$3),资金台帐!$N$6:$N$6005,">="&DATE($F$3,3,1),资金台帐!$N$6:$N$6005,"<"&DATE($F$3,3+1,1)),2) -> 0 | F18: =ROUND(SUMIFS(资金台帐!$AC$6:$AC$6005,资金台帐!$T$6:$T$6005,$Q18,资金台帐!$U$6:$U$6005,"变动成本",资金台帐!$O$6:$O$6005,IF($C$3="全部","?*",$C$3),资金台帐!$N$6:$N$6005,">="&DATE($F$3,4,1),资金台帐!$N$6:$N$6005,"<"&DATE($F$3,4+1,1))-SUMIFS(资金台帐!$AB$6:$AB$6005,资金台帐!$T$6:$T$6005,$Q18,资金台帐!$U$6:$U$6005,"变动成本",资金台帐!$O$6:$O$6005,IF($C$3="全部","?*",$C$3),资金台帐!$N$6:$N$6005,">="&DATE($F$3,4,1),资金台帐!$N$6:$N$6005,"<"&DATE($F$3,4+1,1)),2) -> 0 | G18: =ROUND(SUMIFS(资金台帐!$AC$6:$AC$6005,资金台帐!$T$6:$T$6005,$Q18,资金台帐!$U$6:$U$6005,"变动成本",资金台帐!$O$6:$O$6005,IF($C$3="全部","?*",$C$3),资金台帐!$N$6:$N$6005,">="&DATE($F$3,5,1),资金台帐!$N$6:$N$6005,"<"&DATE($F$3,5+1,1))-SUMIFS(资金台帐!$AB$6:$AB$6005,资金台帐!$T$6:$T$6005,$Q18,资金台帐!$U$6:$U$6005,"变动成本",资金台帐!$O$6:$O$6005,IF($C$3="全部","?*",$C$3),资金台帐!$N$6:$N$6005,">="&DATE($F$3,5,1),资金台帐!$N$6:$N$6005,"<"&DATE($F$3,5+1,1)),2) -> 0 | H18: =ROUND(SUMIFS(资金台帐!$AC$6:$AC$6005,资金台帐!$T$6:$T$6005,$Q18,资金台帐!$U$6:$U$6005,"变动成本",资金台帐!$O$6:$O$6005,IF($C$3="全部","?*",$C$3),资金台帐!$N$6:$N$6005,">="&DATE($F$3,6,1),资金台帐!$N$6:$N$6005,"<"&DATE($F$3,6+1,1))-SUMIFS(资金台帐!$AB$6:$AB$6005,资金台帐!$T$6:$T$6005,$Q18,资金台帐!$U$6:$U$6005,"变动成本",资金台帐!$O$6:$O$6005,IF($C$3="全部","?*",$C$3),资金台帐!$N$6:$N$6005,">="&DATE($F$3,6,1),资金台帐!$N$6:$N$6005,"<"&DATE($F$3,6+1,1)),2) -> 0 | I18: =ROUND(SUMIFS(资金台帐!$AC$6:$AC$6005,资金台帐!$T$6:$T$6005,$Q18,资金台帐!$U$6:$U$6005,"变动成本",资金台帐!$O$6:$O$6005,IF($C$3="全部","?*",$C$3),资金台帐!$N$6:$N$6005,">="&DATE($F$3,7,1),资金台帐!$N$6:$N$6005,"<"&DATE($F$3,7+1,1))-SUMIFS(资金台帐!$AB$6:$AB$6005,资金台帐!$T$6:$T$6005,$Q18,资金台帐!$U$6:$U$6005,"变动成本",资金台帐!$O$6:$O$6005,IF($C$3="全部","?*",$C$3),资金台帐!$N$6:$N$6005,">="&DATE($F$3,7,1),资金台帐!$N$6:$N$6005,"<"&DATE($F$3,7+1,1)),2) -> 0 | J18: =ROUND(SUMIFS(资金台帐!$AC$6:$AC$6005,资金台帐!$T$6:$T$6005,$Q18,资金台帐!$U$6:$U$6005,"变动成本",资金台帐!$O$6:$O$6005,IF($C$3="全部","?*",$C$3),资金台帐!$N$6:$N$6005,">="&DATE($F$3,8,1),资金台帐!$N$6:$N$6005,"<"&DATE($F$3,8+1,1))-SUMIFS(资金台帐!$AB$6:$AB$6005,资金台帐!$T$6:$T$6005,$Q18,资金台帐!$U$6:$U$6005,"变动成本",资金台帐!$O$6:$O$6005,IF($C$3="全部","?*",$C$3),资金台帐!$N$6:$N$6005,">="&DATE($F$3,8,1),资金台帐!$N$6:$N$6005,"<"&DATE($F$3,8+1,1)),2) -> 0 | K18: =ROUND(SUMIFS(资金台帐!$AC$6:$AC$6005,资金台帐!$T$6:$T$6005,$Q18,资金台帐!$U$6:$U$6005,"变动成本",资金台帐!$O$6:$O$6005,IF($C$3="全部","?*",$C$3),资金台帐!$N$6:$N$6005,">="&DATE($F$3,9,1),资金台帐!$N$6:$N$6005,"<"&DATE($F$3,9+1,1))-SUMIFS(资金台帐!$AB$6:$AB$6005,资金台帐!$T$6:$T$6005,$Q18,资金台帐!$U$6:$U$6005,"变动成本",资金台帐!$O$6:$O$6005,IF($C$3="全部","?*",$C$3),资金台帐!$N$6:$N$6005,">="&DATE($F$3,9,1),资金台帐!$N$6:$N$6005,"<"&DATE($F$3,9+1,1)),2) -> 0 | L18: =ROUND(SUMIFS(资金台帐!$AC$6:$AC$6005,资金台帐!$T$6:$T$6005,$Q18,资金台帐!$U$6:$U$6005,"变动成本",资金台帐!$O$6:$O$6005,IF($C$3="全部","?*",$C$3),资金台帐!$N$6:$N$6005,">="&DATE($F$3,10,1),资金台帐!$N$6:$N$6005,"<"&DATE($F$3,10+1,1))-SUMIFS(资金台帐!$AB$6:$AB$6005,资金台帐!$T$6:$T$6005,$Q18,资金台帐!$U$6:$U$6005,"变动成本",资金台帐!$O$6:$O$6005,IF($C$3="全部","?*",$C$3),资金台帐!$N$6:$N$6005,">="&DATE($F$3,10,1),资金台帐!$N$6:$N$6005,"<"&DATE($F$3,10+1,1)),2) -> 0 | M18: =ROUND(SUMIFS(资金台帐!$AC$6:$AC$6005,资金台帐!$T$6:$T$6005,$Q18,资金台帐!$U$6:$U$6005,"变动成本",资金台帐!$O$6:$O$6005,IF($C$3="全部","?*",$C$3),资金台帐!$N$6:$N$6005,">="&DATE($F$3,11,1),资金台帐!$N$6:$N$6005,"<"&DATE($F$3,11+1,1))-SUMIFS(资金台帐!$AB$6:$AB$6005,资金台帐!$T$6:$T$6005,$Q18,资金台帐!$U$6:$U$6005,"变动成本",资金台帐!$O$6:$O$6005,IF($C$3="全部","?*",$C$3),资金台帐!$N$6:$N$6005,">="&DATE($F$3,11,1),资金台帐!$N$6:$N$6005,"<"&DATE($F$3,11+1,1)),2) -> 0 | N18: =ROUND(SUMIFS(资金台帐!$AC$6:$AC$6005,资金台帐!$T$6:$T$6005,$Q18,资金台帐!$U$6:$U$6005,"变动成本",资金台帐!$O$6:$O$6005,IF($C$3="全部","?*",$C$3),资金台帐!$N$6:$N$6005,">="&DATE($F$3,12,1),资金台帐!$N$6:$N$6005,"<"&DATE($F$3,12+1,1))-SUMIFS(资金台帐!$AB$6:$AB$6005,资金台帐!$T$6:$T$6005,$Q18,资金台帐!$U$6:$U$6005,"变动成本",资金台帐!$O$6:$O$6005,IF($C$3="全部","?*",$C$3),资金台帐!$N$6:$N$6005,">="&DATE($F$3,12,1),资金台帐!$N$6:$N$6005,"<"&DATE($F$3,12+1,1)),2) -> 0 | O18: =ROUND(SUM(C18:N18),2) -> 0 | P18: =IF(N($O$16)=0,"",O18/$O$16) -> 0 | Q18: =基础资料!$U$17&"" -> 人工-社保
B19: =IF(基础资料!$W$18="",基础资料!$U$18&"",基础资料!$W$18&"") -> 人工-福利 | C19: =ROUND(SUMIFS(资金台帐!$AC$6:$AC$6005,资金台帐!$T$6:$T$6005,$Q19,资金台帐!$U$6:$U$6005,"变动成本",资金台帐!$O$6:$O$6005,IF($C$3="全部","?*",$C$3),资金台帐!$N$6:$N$6005,">="&DATE($F$3,1,1),资金台帐!$N$6:$N$6005,"<"&DATE($F$3,1+1,1))-SUMIFS(资金台帐!$AB$6:$AB$6005,资金台帐!$T$6:$T$6005,$Q19,资金台帐!$U$6:$U$6005,"变动成本",资金台帐!$O$6:$O$6005,IF($C$3="全部","?*",$C$3),资金台帐!$N$6:$N$6005,">="&DATE($F$3,1,1),资金台帐!$N$6:$N$6005,"<"&DATE($F$3,1+1,1)),2) -> 0 | D19: =ROUND(SUMIFS(资金台帐!$AC$6:$AC$6005,资金台帐!$T$6:$T$6005,$Q19,资金台帐!$U$6:$U$6005,"变动成本",资金台帐!$O$6:$O$6005,IF($C$3="全部","?*",$C$3),资金台帐!$N$6:$N$6005,">="&DATE($F$3,2,1),资金台帐!$N$6:$N$6005,"<"&DATE($F$3,2+1,1))-SUMIFS(资金台帐!$AB$6:$AB$6005,资金台帐!$T$6:$T$6005,$Q19,资金台帐!$U$6:$U$6005,"变动成本",资金台帐!$O$6:$O$6005,IF($C$3="全部","?*",$C$3),资金台帐!$N$6:$N$6005,">="&DATE($F$3,2,1),资金台帐!$N$6:$N$6005,"<"&DATE($F$3,2+1,1)),2) -> 0 | E19: =ROUND(SUMIFS(资金台帐!$AC$6:$AC$6005,资金台帐!$T$6:$T$6005,$Q19,资金台帐!$U$6:$U$6005,"变动成本",资金台帐!$O$6:$O$6005,IF($C$3="全部","?*",$C$3),资金台帐!$N$6:$N$6005,">="&DATE($F$3,3,1),资金台帐!$N$6:$N$6005,"<"&DATE($F$3,3+1,1))-SUMIFS(资金台帐!$AB$6:$AB$6005,资金台帐!$T$6:$T$6005,$Q19,资金台帐!$U$6:$U$6005,"变动成本",资金台帐!$O$6:$O$6005,IF($C$3="全部","?*",$C$3),资金台帐!$N$6:$N$6005,">="&DATE($F$3,3,1),资金台帐!$N$6:$N$6005,"<"&DATE($F$3,3+1,1)),2) -> 0 | F19: =ROUND(SUMIFS(资金台帐!$AC$6:$AC$6005,资金台帐!$T$6:$T$6005,$Q19,资金台帐!$U$6:$U$6005,"变动成本",资金台帐!$O$6:$O$6005,IF($C$3="全部","?*",$C$3),资金台帐!$N$6:$N$6005,">="&DATE($F$3,4,1),资金台帐!$N$6:$N$6005,"<"&DATE($F$3,4+1,1))-SUMIFS(资金台帐!$AB$6:$AB$6005,资金台帐!$T$6:$T$6005,$Q19,资金台帐!$U$6:$U$6005,"变动成本",资金台帐!$O$6:$O$6005,IF($C$3="全部","?*",$C$3),资金台帐!$N$6:$N$6005,">="&DATE($F$3,4,1),资金台帐!$N$6:$N$6005,"<"&DATE($F$3,4+1,1)),2) -> 0 | G19: =ROUND(SUMIFS(资金台帐!$AC$6:$AC$6005,资金台帐!$T$6:$T$6005,$Q19,资金台帐!$U$6:$U$6005,"变动成本",资金台帐!$O$6:$O$6005,IF($C$3="全部","?*",$C$3),资金台帐!$N$6:$N$6005,">="&DATE($F$3,5,1),资金台帐!$N$6:$N$6005,"<"&DATE($F$3,5+1,1))-SUMIFS(资金台帐!$AB$6:$AB$6005,资金台帐!$T$6:$T$6005,$Q19,资金台帐!$U$6:$U$6005,"变动成本",资金台帐!$O$6:$O$6005,IF($C$3="全部","?*",$C$3),资金台帐!$N$6:$N$6005,">="&DATE($F$3,5,1),资金台帐!$N$6:$N$6005,"<"&DATE($F$3,5+1,1)),2) -> 0 | H19: =ROUND(SUMIFS(资金台帐!$AC$6:$AC$6005,资金台帐!$T$6:$T$6005,$Q19,资金台帐!$U$6:$U$6005,"变动成本",资金台帐!$O$6:$O$6005,IF($C$3="全部","?*",$C$3),资金台帐!$N$6:$N$6005,">="&DATE($F$3,6,1),资金台帐!$N$6:$N$6005,"<"&DATE($F$3,6+1,1))-SUMIFS(资金台帐!$AB$6:$AB$6005,资金台帐!$T$6:$T$6005,$Q19,资金台帐!$U$6:$U$6005,"变动成本",资金台帐!$O$6:$O$6005,IF($C$3="全部","?*",$C$3),资金台帐!$N$6:$N$6005,">="&DATE($F$3,6,1),资金台帐!$N$6:$N$6005,"<"&DATE($F$3,6+1,1)),2) -> 0 | I19: =ROUND(SUMIFS(资金台帐!$AC$6:$AC$6005,资金台帐!$T$6:$T$6005,$Q19,资金台帐!$U$6:$U$6005,"变动成本",资金台帐!$O$6:$O$6005,IF($C$3="全部","?*",$C$3),资金台帐!$N$6:$N$6005,">="&DATE($F$3,7,1),资金台帐!$N$6:$N$6005,"<"&DATE($F$3,7+1,1))-SUMIFS(资金台帐!$AB$6:$AB$6005,资金台帐!$T$6:$T$6005,$Q19,资金台帐!$U$6:$U$6005,"变动成本",资金台帐!$O$6:$O$6005,IF($C$3="全部","?*",$C$3),资金台帐!$N$6:$N$6005,">="&DATE($F$3,7,1),资金台帐!$N$6:$N$6005,"<"&DATE($F$3,7+1,1)),2) -> 0 | J19: =ROUND(SUMIFS(资金台帐!$AC$6:$AC$6005,资金台帐!$T$6:$T$6005,$Q19,资金台帐!$U$6:$U$6005,"变动成本",资金台帐!$O$6:$O$6005,IF($C$3="全部","?*",$C$3),资金台帐!$N$6:$N$6005,">="&DATE($F$3,8,1),资金台帐!$N$6:$N$6005,"<"&DATE($F$3,8+1,1))-SUMIFS(资金台帐!$AB$6:$AB$6005,资金台帐!$T$6:$T$6005,$Q19,资金台帐!$U$6:$U$6005,"变动成本",资金台帐!$O$6:$O$6005,IF($C$3="全部","?*",$C$3),资金台帐!$N$6:$N$6005,">="&DATE($F$3,8,1),资金台帐!$N$6:$N$6005,"<"&DATE($F$3,8+1,1)),2) -> 0 | K19: =ROUND(SUMIFS(资金台帐!$AC$6:$AC$6005,资金台帐!$T$6:$T$6005,$Q19,资金台帐!$U$6:$U$6005,"变动成本",资金台帐!$O$6:$O$6005,IF($C$3="全部","?*",$C$3),资金台帐!$N$6:$N$6005,">="&DATE($F$3,9,1),资金台帐!$N$6:$N$6005,"<"&DATE($F$3,9+1,1))-SUMIFS(资金台帐!$AB$6:$AB$6005,资金台帐!$T$6:$T$6005,$Q19,资金台帐!$U$6:$U$6005,"变动成本",资金台帐!$O$6:$O$6005,IF($C$3="全部","?*",$C$3),资金台帐!$N$6:$N$6005,">="&DATE($F$3,9,1),资金台帐!$N$6:$N$6005,"<"&DATE($F$3,9+1,1)),2) -> 0 | L19: =ROUND(SUMIFS(资金台帐!$AC$6:$AC$6005,资金台帐!$T$6:$T$6005,$Q19,资金台帐!$U$6:$U$6005,"变动成本",资金台帐!$O$6:$O$6005,IF($C$3="全部","?*",$C$3),资金台帐!$N$6:$N$6005,">="&DATE($F$3,10,1),资金台帐!$N$6:$N$6005,"<"&DATE($F$3,10+1,1))-SUMIFS(资金台帐!$AB$6:$AB$6005,资金台帐!$T$6:$T$6005,$Q19,资金台帐!$U$6:$U$6005,"变动成本",资金台帐!$O$6:$O$6005,IF($C$3="全部","?*",$C$3),资金台帐!$N$6:$N$6005,">="&DATE($F$3,10,1),资金台帐!$N$6:$N$6005,"<"&DATE($F$3,10+1,1)),2) -> 0 | M19: =ROUND(SUMIFS(资金台帐!$AC$6:$AC$6005,资金台帐!$T$6:$T$6005,$Q19,资金台帐!$U$6:$U$6005,"变动成本",资金台帐!$O$6:$O$6005,IF($C$3="全部","?*",$C$3),资金台帐!$N$6:$N$6005,">="&DATE($F$3,11,1),资金台帐!$N$6:$N$6005,"<"&DATE($F$3,11+1,1))-SUMIFS(资金台帐!$AB$6:$AB$6005,资金台帐!$T$6:$T$6005,$Q19,资金台帐!$U$6:$U$6005,"变动成本",资金台帐!$O$6:$O$6005,IF($C$3="全部","?*",$C$3),资金台帐!$N$6:$N$6005,">="&DATE($F$3,11,1),资金台帐!$N$6:$N$6005,"<"&DATE($F$3,11+1,1)),2) -> 0 | N19: =ROUND(SUMIFS(资金台帐!$AC$6:$AC$6005,资金台帐!$T$6:$T$6005,$Q19,资金台帐!$U$6:$U$6005,"变动成本",资金台帐!$O$6:$O$6005,IF($C$3="全部","?*",$C$3),资金台帐!$N$6:$N$6005,">="&DATE($F$3,12,1),资金台帐!$N$6:$N$6005,"<"&DATE($F$3,12+1,1))-SUMIFS(资金台帐!$AB$6:$AB$6005,资金台帐!$T$6:$T$6005,$Q19,资金台帐!$U$6:$U$6005,"变动成本",资金台帐!$O$6:$O$6005,IF($C$3="全部","?*",$C$3),资金台帐!$N$6:$N$6005,">="&DATE($F$3,12,1),资金台帐!$N$6:$N$6005,"<"&DATE($F$3,12+1,1)),2) -> 0 | O19: =ROUND(SUM(C19:N19),2) -> 0 | P19: =IF(N($O$16)=0,"",O19/$O$16) -> 0 | Q19: =基础资料!$U$18&"" -> 人工-福利
B20: =IF(基础资料!$W$19="",基础资料!$U$19&"",基础资料!$W$19&"") -> 税金 | C20: =ROUND(SUMIFS(资金台帐!$AC$6:$AC$6005,资金台帐!$T$6:$T$6005,$Q20,资金台帐!$U$6:$U$6005,"变动成本",资金台帐!$O$6:$O$6005,IF($C$3="全部","?*",$C$3),资金台帐!$N$6:$N$6005,">="&DATE($F$3,1,1),资金台帐!$N$6:$N$6005,"<"&DATE($F$3,1+1,1))-SUMIFS(资金台帐!$AB$6:$AB$6005,资金台帐!$T$6:$T$6005,$Q20,资金台帐!$U$6:$U$6005,"变动成本",资金台帐!$O$6:$O$6005,IF($C$3="全部","?*",$C$3),资金台帐!$N$6:$N$6005,">="&DATE($F$3,1,1),资金台帐!$N$6:$N$6005,"<"&DATE($F$3,1+1,1)),2) -> 0 | D20: =ROUND(SUMIFS(资金台帐!$AC$6:$AC$6005,资金台帐!$T$6:$T$6005,$Q20,资金台帐!$U$6:$U$6005,"变动成本",资金台帐!$O$6:$O$6005,IF($C$3="全部","?*",$C$3),资金台帐!$N$6:$N$6005,">="&DATE($F$3,2,1),资金台帐!$N$6:$N$6005,"<"&DATE($F$3,2+1,1))-SUMIFS(资金台帐!$AB$6:$AB$6005,资金台帐!$T$6:$T$6005,$Q20,资金台帐!$U$6:$U$6005,"变动成本",资金台帐!$O$6:$O$6005,IF($C$3="全部","?*",$C$3),资金台帐!$N$6:$N$6005,">="&DATE($F$3,2,1),资金台帐!$N$6:$N$6005,"<"&DATE($F$3,2+1,1)),2) -> 0 | E20: =ROUND(SUMIFS(资金台帐!$AC$6:$AC$6005,资金台帐!$T$6:$T$6005,$Q20,资金台帐!$U$6:$U$6005,"变动成本",资金台帐!$O$6:$O$6005,IF($C$3="全部","?*",$C$3),资金台帐!$N$6:$N$6005,">="&DATE($F$3,3,1),资金台帐!$N$6:$N$6005,"<"&DATE($F$3,3+1,1))-SUMIFS(资金台帐!$AB$6:$AB$6005,资金台帐!$T$6:$T$6005,$Q20,资金台帐!$U$6:$U$6005,"变动成本",资金台帐!$O$6:$O$6005,IF($C$3="全部","?*",$C$3),资金台帐!$N$6:$N$6005,">="&DATE($F$3,3,1),资金台帐!$N$6:$N$6005,"<"&DATE($F$3,3+1,1)),2) -> 0 | F20: =ROUND(SUMIFS(资金台帐!$AC$6:$AC$6005,资金台帐!$T$6:$T$6005,$Q20,资金台帐!$U$6:$U$6005,"变动成本",资金台帐!$O$6:$O$6005,IF($C$3="全部","?*",$C$3),资金台帐!$N$6:$N$6005,">="&DATE($F$3,4,1),资金台帐!$N$6:$N$6005,"<"&DATE($F$3,4+1,1))-SUMIFS(资金台帐!$AB$6:$AB$6005,资金台帐!$T$6:$T$6005,$Q20,资金台帐!$U$6:$U$6005,"变动成本",资金台帐!$O$6:$O$6005,IF($C$3="全部","?*",$C$3),资金台帐!$N$6:$N$6005,">="&DATE($F$3,4,1),资金台帐!$N$6:$N$6005,"<"&DATE($F$3,4+1,1)),2) -> 0 | G20: =ROUND(SUMIFS(资金台帐!$AC$6:$AC$6005,资金台帐!$T$6:$T$6005,$Q20,资金台帐!$U$6:$U$6005,"变动成本",资金台帐!$O$6:$O$6005,IF($C$3="全部","?*",$C$3),资金台帐!$N$6:$N$6005,">="&DATE($F$3,5,1),资金台帐!$N$6:$N$6005,"<"&DATE($F$3,5+1,1))-SUMIFS(资金台帐!$AB$6:$AB$6005,资金台帐!$T$6:$T$6005,$Q20,资金台帐!$U$6:$U$6005,"变动成本",资金台帐!$O$6:$O$6005,IF($C$3="全部","?*",$C$3),资金台帐!$N$6:$N$6005,">="&DATE($F$3,5,1),资金台帐!$N$6:$N$6005,"<"&DATE($F$3,5+1,1)),2) -> 0 | H20: =ROUND(SUMIFS(资金台帐!$AC$6:$AC$6005,资金台帐!$T$6:$T$6005,$Q20,资金台帐!$U$6:$U$6005,"变动成本",资金台帐!$O$6:$O$6005,IF($C$3="全部","?*",$C$3),资金台帐!$N$6:$N$6005,">="&DATE($F$3,6,1),资金台帐!$N$6:$N$6005,"<"&DATE($F$3,6+1,1))-SUMIFS(资金台帐!$AB$6:$AB$6005,资金台帐!$T$6:$T$6005,$Q20,资金台帐!$U$6:$U$6005,"变动成本",资金台帐!$O$6:$O$6005,IF($C$3="全部","?*",$C$3),资金台帐!$N$6:$N$6005,">="&DATE($F$3,6,1),资金台帐!$N$6:$N$6005,"<"&DATE($F$3,6+1,1)),2) -> 0 | I20: =ROUND(SUMIFS(资金台帐!$AC$6:$AC$6005,资金台帐!$T$6:$T$6005,$Q20,资金台帐!$U$6:$U$6005,"变动成本",资金台帐!$O$6:$O$6005,IF($C$3="全部","?*",$C$3),资金台帐!$N$6:$N$6005,">="&DATE($F$3,7,1),资金台帐!$N$6:$N$6005,"<"&DATE($F$3,7+1,1))-SUMIFS(资金台帐!$AB$6:$AB$6005,资金台帐!$T$6:$T$6005,$Q20,资金台帐!$U$6:$U$6005,"变动成本",资金台帐!$O$6:$O$6005,IF($C$3="全部","?*",$C$3),资金台帐!$N$6:$N$6005,">="&DATE($F$3,7,1),资金台帐!$N$6:$N$6005,"<"&DATE($F$3,7+1,1)),2) -> 0 | J20: =ROUND(SUMIFS(资金台帐!$AC$6:$AC$6005,资金台帐!$T$6:$T$6005,$Q20,资金台帐!$U$6:$U$6005,"变动成本",资金台帐!$O$6:$O$6005,IF($C$3="全部","?*",$C$3),资金台帐!$N$6:$N$6005,">="&DATE($F$3,8,1),资金台帐!$N$6:$N$6005,"<"&DATE($F$3,8+1,1))-SUMIFS(资金台帐!$AB$6:$AB$6005,资金台帐!$T$6:$T$6005,$Q20,资金台帐!$U$6:$U$6005,"变动成本",资金台帐!$O$6:$O$6005,IF($C$3="全部","?*",$C$3),资金台帐!$N$6:$N$6005,">="&DATE($F$3,8,1),资金台帐!$N$6:$N$6005,"<"&DATE($F$3,8+1,1)),2) -> 0 | K20: =ROUND(SUMIFS(资金台帐!$AC$6:$AC$6005,资金台帐!$T$6:$T$6005,$Q20,资金台帐!$U$6:$U$6005,"变动成本",资金台帐!$O$6:$O$6005,IF($C$3="全部","?*",$C$3),资金台帐!$N$6:$N$6005,">="&DATE($F$3,9,1),资金台帐!$N$6:$N$6005,"<"&DATE($F$3,9+1,1))-SUMIFS(资金台帐!$AB$6:$AB$6005,资金台帐!$T$6:$T$6005,$Q20,资金台帐!$U$6:$U$6005,"变动成本",资金台帐!$O$6:$O$6005,IF($C$3="全部","?*",$C$3),资金台帐!$N$6:$N$6005,">="&DATE($F$3,9,1),资金台帐!$N$6:$N$6005,"<"&DATE($F$3,9+1,1)),2) -> 22160.77 | L20: =ROUND(SUMIFS(资金台帐!$AC$6:$AC$6005,资金台帐!$T$6:$T$6005,$Q20,资金台帐!$U$6:$U$6005,"变动成本",资金台帐!$O$6:$O$6005,IF($C$3="全部","?*",$C$3),资金台帐!$N$6:$N$6005,">="&DATE($F$3,10,1),资金台帐!$N$6:$N$6005,"<"&DATE($F$3,10+1,1))-SUMIFS(资金台帐!$AB$6:$AB$6005,资金台帐!$T$6:$T$6005,$Q20,资金台帐!$U$6:$U$6005,"变动成本",资金台帐!$O$6:$O$6005,IF($C$3="全部","?*",$C$3),资金台帐!$N$6:$N$6005,">="&DATE($F$3,10,1),资金台帐!$N$6:$N$6005,"<"&DATE($F$3,10+1,1)),2) -> 0 | M20: =ROUND(SUMIFS(资金台帐!$AC$6:$AC$6005,资金台帐!$T$6:$T$6005,$Q20,资金台帐!$U$6:$U$6005,"变动成本",资金台帐!$O$6:$O$6005,IF($C$3="全部","?*",$C$3),资金台帐!$N$6:$N$6005,">="&DATE($F$3,11,1),资金台帐!$N$6:$N$6005,"<"&DATE($F$3,11+1,1))-SUMIFS(资金台帐!$AB$6:$AB$6005,资金台帐!$T$6:$T$6005,$Q20,资金台帐!$U$6:$U$6005,"变动成本",资金台帐!$O$6:$O$6005,IF($C$3="全部","?*",$C$3),资金台帐!$N$6:$N$6005,">="&DATE($F$3,11,1),资金台帐!$N$6:$N$6005,"<"&DATE($F$3,11+1,1)),2) -> 0 | N20: =ROUND(SUMIFS(资金台帐!$AC$6:$AC$6005,资金台帐!$T$6:$T$6005,$Q20,资金台帐!$U$6:$U$6005,"变动成本",资金台帐!$O$6:$O$6005,IF($C$3="全部","?*",$C$3),资金台帐!$N$6:$N$6005,">="&DATE($F$3,12,1),资金台帐!$N$6:$N$6005,"<"&DATE($F$3,12+1,1))-SUMIFS(资金台帐!$AB$6:$AB$6005,资金台帐!$T$6:$T$6005,$Q20,资金台帐!$U$6:$U$6005,"变动成本",资金台帐!$O$6:$O$6005,IF($C$3="全部","?*",$C$3),资金台帐!$N$6:$N$6005,">="&DATE($F$3,12,1),资金台帐!$N$6:$N$6005,"<"&DATE($F$3,12+1,1)),2) -> 0 | O20: =ROUND(SUM(C20:N20),2) -> 22160.77 | P20: =IF(N($O$16)=0,"",O20/$O$16) -> 0.12959515 | Q20: =基础资料!$U$19&"" -> 税金
B21: =IF(基础资料!$W$20="",基础资料!$U$20&"",基础资料!$W$20&"") -> 差旅费 | C21: =ROUND(SUMIFS(资金台帐!$AC$6:$AC$6005,资金台帐!$T$6:$T$6005,$Q21,资金台帐!$U$6:$U$6005,"变动成本",资金台帐!$O$6:$O$6005,IF($C$3="全部","?*",$C$3),资金台帐!$N$6:$N$6005,">="&DATE($F$3,1,1),资金台帐!$N$6:$N$6005,"<"&DATE($F$3,1+1,1))-SUMIFS(资金台帐!$AB$6:$AB$6005,资金台帐!$T$6:$T$6005,$Q21,资金台帐!$U$6:$U$6005,"变动成本",资金台帐!$O$6:$O$6005,IF($C$3="全部","?*",$C$3),资金台帐!$N$6:$N$6005,">="&DATE($F$3,1,1),资金台帐!$N$6:$N$6005,"<"&DATE($F$3,1+1,1)),2) -> 0 | D21: =ROUND(SUMIFS(资金台帐!$AC$6:$AC$6005,资金台帐!$T$6:$T$6005,$Q21,资金台帐!$U$6:$U$6005,"变动成本",资金台帐!$O$6:$O$6005,IF($C$3="全部","?*",$C$3),资金台帐!$N$6:$N$6005,">="&DATE($F$3,2,1),资金台帐!$N$6:$N$6005,"<"&DATE($F$3,2+1,1))-SUMIFS(资金台帐!$AB$6:$AB$6005,资金台帐!$T$6:$T$6005,$Q21,资金台帐!$U$6:$U$6005,"变动成本",资金台帐!$O$6:$O$6005,IF($C$3="全部","?*",$C$3),资金台帐!$N$6:$N$6005,">="&DATE($F$3,2,1),资金台帐!$N$6:$N$6005,"<"&DATE($F$3,2+1,1)),2) -> 0 | E21: =ROUND(SUMIFS(资金台帐!$AC$6:$AC$6005,资金台帐!$T$6:$T$6005,$Q21,资金台帐!$U$6:$U$6005,"变动成本",资金台帐!$O$6:$O$6005,IF($C$3="全部","?*",$C$3),资金台帐!$N$6:$N$6005,">="&DATE($F$3,3,1),资金台帐!$N$6:$N$6005,"<"&DATE($F$3,3+1,1))-SUMIFS(资金台帐!$AB$6:$AB$6005,资金台帐!$T$6:$T$6005,$Q21,资金台帐!$U$6:$U$6005,"变动成本",资金台帐!$O$6:$O$6005,IF($C$3="全部","?*",$C$3),资金台帐!$N$6:$N$6005,">="&DATE($F$3,3,1),资金台帐!$N$6:$N$6005,"<"&DATE($F$3,3+1,1)),2) -> 0 | F21: =ROUND(SUMIFS(资金台帐!$AC$6:$AC$6005,资金台帐!$T$6:$T$6005,$Q21,资金台帐!$U$6:$U$6005,"变动成本",资金台帐!$O$6:$O$6005,IF($C$3="全部","?*",$C$3),资金台帐!$N$6:$N$6005,">="&DATE($F$3,4,1),资金台帐!$N$6:$N$6005,"<"&DATE($F$3,4+1,1))-SUMIFS(资金台帐!$AB$6:$AB$6005,资金台帐!$T$6:$T$6005,$Q21,资金台帐!$U$6:$U$6005,"变动成本",资金台帐!$O$6:$O$6005,IF($C$3="全部","?*",$C$3),资金台帐!$N$6:$N$6005,">="&DATE($F$3,4,1),资金台帐!$N$6:$N$6005,"<"&DATE($F$3,4+1,1)),2) -> 0 | G21: =ROUND(SUMIFS(资金台帐!$AC$6:$AC$6005,资金台帐!$T$6:$T$6005,$Q21,资金台帐!$U$6:$U$6005,"变动成本",资金台帐!$O$6:$O$6005,IF($C$3="全部","?*",$C$3),资金台帐!$N$6:$N$6005,">="&DATE($F$3,5,1),资金台帐!$N$6:$N$6005,"<"&DATE($F$3,5+1,1))-SUMIFS(资金台帐!$AB$6:$AB$6005,资金台帐!$T$6:$T$6005,$Q21,资金台帐!$U$6:$U$6005,"变动成本",资金台帐!$O$6:$O$6005,IF($C$3="全部","?*",$C$3),资金台帐!$N$6:$N$6005,">="&DATE($F$3,5,1),资金台帐!$N$6:$N$6005,"<"&DATE($F$3,5+1,1)),2) -> 0 | H21: =ROUND(SUMIFS(资金台帐!$AC$6:$AC$6005,资金台帐!$T$6:$T$6005,$Q21,资金台帐!$U$6:$U$6005,"变动成本",资金台帐!$O$6:$O$6005,IF($C$3="全部","?*",$C$3),资金台帐!$N$6:$N$6005,">="&DATE($F$3,6,1),资金台帐!$N$6:$N$6005,"<"&DATE($F$3,6+1,1))-SUMIFS(资金台帐!$AB$6:$AB$6005,资金台帐!$T$6:$T$6005,$Q21,资金台帐!$U$6:$U$6005,"变动成本",资金台帐!$O$6:$O$6005,IF($C$3="全部","?*",$C$3),资金台帐!$N$6:$N$6005,">="&DATE($F$3,6,1),资金台帐!$N$6:$N$6005,"<"&DATE($F$3,6+1,1)),2) -> 0 | I21: =ROUND(SUMIFS(资金台帐!$AC$6:$AC$6005,资金台帐!$T$6:$T$6005,$Q21,资金台帐!$U$6:$U$6005,"变动成本",资金台帐!$O$6:$O$6005,IF($C$3="全部","?*",$C$3),资金台帐!$N$6:$N$6005,">="&DATE($F$3,7,1),资金台帐!$N$6:$N$6005,"<"&DATE($F$3,7+1,1))-SUMIFS(资金台帐!$AB$6:$AB$6005,资金台帐!$T$6:$T$6005,$Q21,资金台帐!$U$6:$U$6005,"变动成本",资金台帐!$O$6:$O$6005,IF($C$3="全部","?*",$C$3),资金台帐!$N$6:$N$6005,">="&DATE($F$3,7,1),资金台帐!$N$6:$N$6005,"<"&DATE($F$3,7+1,1)),2) -> 0 | J21: =ROUND(SUMIFS(资金台帐!$AC$6:$AC$6005,资金台帐!$T$6:$T$6005,$Q21,资金台帐!$U$6:$U$6005,"变动成本",资金台帐!$O$6:$O$6005,IF($C$3="全部","?*",$C$3),资金台帐!$N$6:$N$6005,">="&DATE($F$3,8,1),资金台帐!$N$6:$N$6005,"<"&DATE($F$3,8+1,1))-SUMIFS(资金台帐!$AB$6:$AB$6005,资金台帐!$T$6:$T$6005,$Q21,资金台帐!$U$6:$U$6005,"变动成本",资金台帐!$O$6:$O$6005,IF($C$3="全部","?*",$C$3),资金台帐!$N$6:$N$6005,">="&DATE($F$3,8,1),资金台帐!$N$6:$N$6005,"<"&DATE($F$3,8+1,1)),2) -> 0 | K21: =ROUND(SUMIFS(资金台帐!$AC$6:$AC$6005,资金台帐!$T$6:$T$6005,$Q21,资金台帐!$U$6:$U$6005,"变动成本",资金台帐!$O$6:$O$6005,IF($C$3="全部","?*",$C$3),资金台帐!$N$6:$N$6005,">="&DATE($F$3,9,1),资金台帐!$N$6:$N$6005,"<"&DATE($F$3,9+1,1))-SUMIFS(资金台帐!$AB$6:$AB$6005,资金台帐!$T$6:$T$6005,$Q21,资金台帐!$U$6:$U$6005,"变动成本",资金台帐!$O$6:$O$6005,IF($C$3="全部","?*",$C$3),资金台帐!$N$6:$N$6005,">="&DATE($F$3,9,1),资金台帐!$N$6:$N$6005,"<"&DATE($F$3,9+1,1)),2) -> 0 | L21: =ROUND(SUMIFS(资金台帐!$AC$6:$AC$6005,资金台帐!$T$6:$T$6005,$Q21,资金台帐!$U$6:$U$6005,"变动成本",资金台帐!$O$6:$O$6005,IF($C$3="全部","?*",$C$3),资金台帐!$N$6:$N$6005,">="&DATE($F$3,10,1),资金台帐!$N$6:$N$6005,"<"&DATE($F$3,10+1,1))-SUMIFS(资金台帐!$AB$6:$AB$6005,资金台帐!$T$6:$T$6005,$Q21,资金台帐!$U$6:$U$6005,"变动成本",资金台帐!$O$6:$O$6005,IF($C$3="全部","?*",$C$3),资金台帐!$N$6:$N$6005,">="&DATE($F$3,10,1),资金台帐!$N$6:$N$6005,"<"&DATE($F$3,10+1,1)),2) -> 0 | M21: =ROUND(SUMIFS(资金台帐!$AC$6:$AC$6005,资金台帐!$T$6:$T$6005,$Q21,资金台帐!$U$6:$U$6005,"变动成本",资金台帐!$O$6:$O$6005,IF($C$3="全部","?*",$C$3),资金台帐!$N$6:$N$6005,">="&DATE($F$3,11,1),资金台帐!$N$6:$N$6005,"<"&DATE($F$3,11+1,1))-SUMIFS(资金台帐!$AB$6:$AB$6005,资金台帐!$T$6:$T$6005,$Q21,资金台帐!$U$6:$U$6005,"变动成本",资金台帐!$O$6:$O$6005,IF($C$3="全部","?*",$C$3),资金台帐!$N$6:$N$6005,">="&DATE($F$3,11,1),资金台帐!$N$6:$N$6005,"<"&DATE($F$3,11+1,1)),2) -> 0 | N21: =ROUND(SUMIFS(资金台帐!$AC$6:$AC$6005,资金台帐!$T$6:$T$6005,$Q21,资金台帐!$U$6:$U$6005,"变动成本",资金台帐!$O$6:$O$6005,IF($C$3="全部","?*",$C$3),资金台帐!$N$6:$N$6005,">="&DATE($F$3,12,1),资金台帐!$N$6:$N$6005,"<"&DATE($F$3,12+1,1))-SUMIFS(资金台帐!$AB$6:$AB$6005,资金台帐!$T$6:$T$6005,$Q21,资金台帐!$U$6:$U$6005,"变动成本",资金台帐!$O$6:$O$6005,IF($C$3="全部","?*",$C$3),资金台帐!$N$6:$N$6005,">="&DATE($F$3,12,1),资金台帐!$N$6:$N$6005,"<"&DATE($F$3,12+1,1)),2) -> 0 | O21: =ROUND(SUM(C21:N21),2) -> 0 | P21: =IF(N($O$16)=0,"",O21/$O$16) -> 0 | Q21: =基础资料!$U$20&"" -> 差旅费
B22: =IF(基础资料!$W$21="",基础资料!$U$21&"",基础资料!$W$21&"") -> 培训费 | C22: =ROUND(SUMIFS(资金台帐!$AC$6:$AC$6005,资金台帐!$T$6:$T$6005,$Q22,资金台帐!$U$6:$U$6005,"变动成本",资金台帐!$O$6:$O$6005,IF($C$3="全部","?*",$C$3),资金台帐!$N$6:$N$6005,">="&DATE($F$3,1,1),资金台帐!$N$6:$N$6005,"<"&DATE($F$3,1+1,1))-SUMIFS(资金台帐!$AB$6:$AB$6005,资金台帐!$T$6:$T$6005,$Q22,资金台帐!$U$6:$U$6005,"变动成本",资金台帐!$O$6:$O$6005,IF($C$3="全部","?*",$C$3),资金台帐!$N$6:$N$6005,">="&DATE($F$3,1,1),资金台帐!$N$6:$N$6005,"<"&DATE($F$3,1+1,1)),2) -> 0 | D22: =ROUND(SUMIFS(资金台帐!$AC$6:$AC$6005,资金台帐!$T$6:$T$6005,$Q22,资金台帐!$U$6:$U$6005,"变动成本",资金台帐!$O$6:$O$6005,IF($C$3="全部","?*",$C$3),资金台帐!$N$6:$N$6005,">="&DATE($F$3,2,1),资金台帐!$N$6:$N$6005,"<"&DATE($F$3,2+1,1))-SUMIFS(资金台帐!$AB$6:$AB$6005,资金台帐!$T$6:$T$6005,$Q22,资金台帐!$U$6:$U$6005,"变动成本",资金台帐!$O$6:$O$6005,IF($C$3="全部","?*",$C$3),资金台帐!$N$6:$N$6005,">="&DATE($F$3,2,1),资金台帐!$N$6:$N$6005,"<"&DATE($F$3,2+1,1)),2) -> 0 | E22: =ROUND(SUMIFS(资金台帐!$AC$6:$AC$6005,资金台帐!$T$6:$T$6005,$Q22,资金台帐!$U$6:$U$6005,"变动成本",资金台帐!$O$6:$O$6005,IF($C$3="全部","?*",$C$3),资金台帐!$N$6:$N$6005,">="&DATE($F$3,3,1),资金台帐!$N$6:$N$6005,"<"&DATE($F$3,3+1,1))-SUMIFS(资金台帐!$AB$6:$AB$6005,资金台帐!$T$6:$T$6005,$Q22,资金台帐!$U$6:$U$6005,"变动成本",资金台帐!$O$6:$O$6005,IF($C$3="全部","?*",$C$3),资金台帐!$N$6:$N$6005,">="&DATE($F$3,3,1),资金台帐!$N$6:$N$6005,"<"&DATE($F$3,3+1,1)),2) -> 0 | F22: =ROUND(SUMIFS(资金台帐!$AC$6:$AC$6005,资金台帐!$T$6:$T$6005,$Q22,资金台帐!$U$6:$U$6005,"变动成本",资金台帐!$O$6:$O$6005,IF($C$3="全部","?*",$C$3),资金台帐!$N$6:$N$6005,">="&DATE($F$3,4,1),资金台帐!$N$6:$N$6005,"<"&DATE($F$3,4+1,1))-SUMIFS(资金台帐!$AB$6:$AB$6005,资金台帐!$T$6:$T$6005,$Q22,资金台帐!$U$6:$U$6005,"变动成本",资金台帐!$O$6:$O$6005,IF($C$3="全部","?*",$C$3),资金台帐!$N$6:$N$6005,">="&DATE($F$3,4,1),资金台帐!$N$6:$N$6005,"<"&DATE($F$3,4+1,1)),2) -> 0 | G22: =ROUND(SUMIFS(资金台帐!$AC$6:$AC$6005,资金台帐!$T$6:$T$6005,$Q22,资金台帐!$U$6:$U$6005,"变动成本",资金台帐!$O$6:$O$6005,IF($C$3="全部","?*",$C$3),资金台帐!$N$6:$N$6005,">="&DATE($F$3,5,1),资金台帐!$N$6:$N$6005,"<"&DATE($F$3,5+1,1))-SUMIFS(资金台帐!$AB$6:$AB$6005,资金台帐!$T$6:$T$6005,$Q22,资金台帐!$U$6:$U$6005,"变动成本",资金台帐!$O$6:$O$6005,IF($C$3="全部","?*",$C$3),资金台帐!$N$6:$N$6005,">="&DATE($F$3,5,1),资金台帐!$N$6:$N$6005,"<"&DATE($F$3,5+1,1)),2) -> 0 | H22: =ROUND(SUMIFS(资金台帐!$AC$6:$AC$6005,资金台帐!$T$6:$T$6005,$Q22,资金台帐!$U$6:$U$6005,"变动成本",资金台帐!$O$6:$O$6005,IF($C$3="全部","?*",$C$3),资金台帐!$N$6:$N$6005,">="&DATE($F$3,6,1),资金台帐!$N$6:$N$6005,"<"&DATE($F$3,6+1,1))-SUMIFS(资金台帐!$AB$6:$AB$6005,资金台帐!$T$6:$T$6005,$Q22,资金台帐!$U$6:$U$6005,"变动成本",资金台帐!$O$6:$O$6005,IF($C$3="全部","?*",$C$3),资金台帐!$N$6:$N$6005,">="&DATE($F$3,6,1),资金台帐!$N$6:$N$6005,"<"&DATE($F$3,6+1,1)),2) -> 0 | I22: =ROUND(SUMIFS(资金台帐!$AC$6:$AC$6005,资金台帐!$T$6:$T$6005,$Q22,资金台帐!$U$6:$U$6005,"变动成本",资金台帐!$O$6:$O$6005,IF($C$3="全部","?*",$C$3),资金台帐!$N$6:$N$6005,">="&DATE($F$3,7,1),资金台帐!$N$6:$N$6005,"<"&DATE($F$3,7+1,1))-SUMIFS(资金台帐!$AB$6:$AB$6005,资金台帐!$T$6:$T$6005,$Q22,资金台帐!$U$6:$U$6005,"变动成本",资金台帐!$O$6:$O$6005,IF($C$3="全部","?*",$C$3),资金台帐!$N$6:$N$6005,">="&DATE($F$3,7,1),资金台帐!$N$6:$N$6005,"<"&DATE($F$3,7+1,1)),2) -> 0 | J22: =ROUND(SUMIFS(资金台帐!$AC$6:$AC$6005,资金台帐!$T$6:$T$6005,$Q22,资金台帐!$U$6:$U$6005,"变动成本",资金台帐!$O$6:$O$6005,IF($C$3="全部","?*",$C$3),资金台帐!$N$6:$N$6005,">="&DATE($F$3,8,1),资金台帐!$N$6:$N$6005,"<"&DATE($F$3,8+1,1))-SUMIFS(资金台帐!$AB$6:$AB$6005,资金台帐!$T$6:$T$6005,$Q22,资金台帐!$U$6:$U$6005,"变动成本",资金台帐!$O$6:$O$6005,IF($C$3="全部","?*",$C$3),资金台帐!$N$6:$N$6005,">="&DATE($F$3,8,1),资金台帐!$N$6:$N$6005,"<"&DATE($F$3,8+1,1)),2) -> 0 | K22: =ROUND(SUMIFS(资金台帐!$AC$6:$AC$6005,资金台帐!$T$6:$T$6005,$Q22,资金台帐!$U$6:$U$6005,"变动成本",资金台帐!$O$6:$O$6005,IF($C$3="全部","?*",$C$3),资金台帐!$N$6:$N$6005,">="&DATE($F$3,9,1),资金台帐!$N$6:$N$6005,"<"&DATE($F$3,9+1,1))-SUMIFS(资金台帐!$AB$6:$AB$6005,资金台帐!$T$6:$T$6005,$Q22,资金台帐!$U$6:$U$6005,"变动成本",资金台帐!$O$6:$O$6005,IF($C$3="全部","?*",$C$3),资金台帐!$N$6:$N$6005,">="&DATE($F$3,9,1),资金台帐!$N$6:$N$6005,"<"&DATE($F$3,9+1,1)),2) -> 0 | L22: =ROUND(SUMIFS(资金台帐!$AC$6:$AC$6005,资金台帐!$T$6:$T$6005,$Q22,资金台帐!$U$6:$U$6005,"变动成本",资金台帐!$O$6:$O$6005,IF($C$3="全部","?*",$C$3),资金台帐!$N$6:$N$6005,">="&DATE($F$3,10,1),资金台帐!$N$6:$N$6005,"<"&DATE($F$3,10+1,1))-SUMIFS(资金台帐!$AB$6:$AB$6005,资金台帐!$T$6:$T$6005,$Q22,资金台帐!$U$6:$U$6005,"变动成本",资金台帐!$O$6:$O$6005,IF($C$3="全部","?*",$C$3),资金台帐!$N$6:$N$6005,">="&DATE($F$3,10,1),资金台帐!$N$6:$N$6005,"<"&DATE($F$3,10+1,1)),2) -> 0 | M22: =ROUND(SUMIFS(资金台帐!$AC$6:$AC$6005,资金台帐!$T$6:$T$6005,$Q22,资金台帐!$U$6:$U$6005,"变动成本",资金台帐!$O$6:$O$6005,IF($C$3="全部","?*",$C$3),资金台帐!$N$6:$N$6005,">="&DATE($F$3,11,1),资金台帐!$N$6:$N$6005,"<"&DATE($F$3,11+1,1))-SUMIFS(资金台帐!$AB$6:$AB$6005,资金台帐!$T$6:$T$6005,$Q22,资金台帐!$U$6:$U$6005,"变动成本",资金台帐!$O$6:$O$6005,IF($C$3="全部","?*",$C$3),资金台帐!$N$6:$N$6005,">="&DATE($F$3,11,1),资金台帐!$N$6:$N$6005,"<"&DATE($F$3,11+1,1)),2) -> 0 | N22: =ROUND(SUMIFS(资金台帐!$AC$6:$AC$6005,资金台帐!$T$6:$T$6005,$Q22,资金台帐!$U$6:$U$6005,"变动成本",资金台帐!$O$6:$O$6005,IF($C$3="全部","?*",$C$3),资金台帐!$N$6:$N$6005,">="&DATE($F$3,12,1),资金台帐!$N$6:$N$6005,"<"&DATE($F$3,12+1,1))-SUMIFS(资金台帐!$AB$6:$AB$6005,资金台帐!$T$6:$T$6005,$Q22,资金台帐!$U$6:$U$6005,"变动成本",资金台帐!$O$6:$O$6005,IF($C$3="全部","?*",$C$3),资金台帐!$N$6:$N$6005,">="&DATE($F$3,12,1),资金台帐!$N$6:$N$6005,"<"&DATE($F$3,12+1,1)),2) -> 0 | O22: =ROUND(SUM(C22:N22),2) -> 0 | P22: =IF(N($O$16)=0,"",O22/$O$16) -> 0 | Q22: =基础资料!$U$21&"" -> 培训费
B23: =IF(基础资料!$W$22="",基础资料!$U$22&"",基础资料!$W$22&"") -> 银行手续费 | C23: =ROUND(SUMIFS(资金台帐!$AC$6:$AC$6005,资金台帐!$T$6:$T$6005,$Q23,资金台帐!$U$6:$U$6005,"变动成本",资金台帐!$O$6:$O$6005,IF($C$3="全部","?*",$C$3),资金台帐!$N$6:$N$6005,">="&DATE($F$3,1,1),资金台帐!$N$6:$N$6005,"<"&DATE($F$3,1+1,1))-SUMIFS(资金台帐!$AB$6:$AB$6005,资金台帐!$T$6:$T$6005,$Q23,资金台帐!$U$6:$U$6005,"变动成本",资金台帐!$O$6:$O$6005,IF($C$3="全部","?*",$C$3),资金台帐!$N$6:$N$6005,">="&DATE($F$3,1,1),资金台帐!$N$6:$N$6005,"<"&DATE($F$3,1+1,1)),2) -> 0 | D23: =ROUND(SUMIFS(资金台帐!$AC$6:$AC$6005,资金台帐!$T$6:$T$6005,$Q23,资金台帐!$U$6:$U$6005,"变动成本",资金台帐!$O$6:$O$6005,IF($C$3="全部","?*",$C$3),资金台帐!$N$6:$N$6005,">="&DATE($F$3,2,1),资金台帐!$N$6:$N$6005,"<"&DATE($F$3,2+1,1))-SUMIFS(资金台帐!$AB$6:$AB$6005,资金台帐!$T$6:$T$6005,$Q23,资金台帐!$U$6:$U$6005,"变动成本",资金台帐!$O$6:$O$6005,IF($C$3="全部","?*",$C$3),资金台帐!$N$6:$N$6005,">="&DATE($F$3,2,1),资金台帐!$N$6:$N$6005,"<"&DATE($F$3,2+1,1)),2) -> 0 | E23: =ROUND(SUMIFS(资金台帐!$AC$6:$AC$6005,资金台帐!$T$6:$T$6005,$Q23,资金台帐!$U$6:$U$6005,"变动成本",资金台帐!$O$6:$O$6005,IF($C$3="全部","?*",$C$3),资金台帐!$N$6:$N$6005,">="&DATE($F$3,3,1),资金台帐!$N$6:$N$6005,"<"&DATE($F$3,3+1,1))-SUMIFS(资金台帐!$AB$6:$AB$6005,资金台帐!$T$6:$T$6005,$Q23,资金台帐!$U$6:$U$6005,"变动成本",资金台帐!$O$6:$O$6005,IF($C$3="全部","?*",$C$3),资金台帐!$N$6:$N$6005,">="&DATE($F$3,3,1),资金台帐!$N$6:$N$6005,"<"&DATE($F$3,3+1,1)),2) -> 0 | F23: =ROUND(SUMIFS(资金台帐!$AC$6:$AC$6005,资金台帐!$T$6:$T$6005,$Q23,资金台帐!$U$6:$U$6005,"变动成本",资金台帐!$O$6:$O$6005,IF($C$3="全部","?*",$C$3),资金台帐!$N$6:$N$6005,">="&DATE($F$3,4,1),资金台帐!$N$6:$N$6005,"<"&DATE($F$3,4+1,1))-SUMIFS(资金台帐!$AB$6:$AB$6005,资金台帐!$T$6:$T$6005,$Q23,资金台帐!$U$6:$U$6005,"变动成本",资金台帐!$O$6:$O$6005,IF($C$3="全部","?*",$C$3),资金台帐!$N$6:$N$6005,">="&DATE($F$3,4,1),资金台帐!$N$6:$N$6005,"<"&DATE($F$3,4+1,1)),2) -> 0 | G23: =ROUND(SUMIFS(资金台帐!$AC$6:$AC$6005,资金台帐!$T$6:$T$6005,$Q23,资金台帐!$U$6:$U$6005,"变动成本",资金台帐!$O$6:$O$6005,IF($C$3="全部","?*",$C$3),资金台帐!$N$6:$N$6005,">="&DATE($F$3,5,1),资金台帐!$N$6:$N$6005,"<"&DATE($F$3,5+1,1))-SUMIFS(资金台帐!$AB$6:$AB$6005,资金台帐!$T$6:$T$6005,$Q23,资金台帐!$U$6:$U$6005,"变动成本",资金台帐!$O$6:$O$6005,IF($C$3="全部","?*",$C$3),资金台帐!$N$6:$N$6005,">="&DATE($F$3,5,1),资金台帐!$N$6:$N$6005,"<"&DATE($F$3,5+1,1)),2) -> 0 | H23: =ROUND(SUMIFS(资金台帐!$AC$6:$AC$6005,资金台帐!$T$6:$T$6005,$Q23,资金台帐!$U$6:$U$6005,"变动成本",资金台帐!$O$6:$O$6005,IF($C$3="全部","?*",$C$3),资金台帐!$N$6:$N$6005,">="&DATE($F$3,6,1),资金台帐!$N$6:$N$6005,"<"&DATE($F$3,6+1,1))-SUMIFS(资金台帐!$AB$6:$AB$6005,资金台帐!$T$6:$T$6005,$Q23,资金台帐!$U$6:$U$6005,"变动成本",资金台帐!$O$6:$O$6005,IF($C$3="全部","?*",$C$3),资金台帐!$N$6:$N$6005,">="&DATE($F$3,6,1),资金台帐!$N$6:$N$6005,"<"&DATE($F$3,6+1,1)),2) -> 0 | I23: =ROUND(SUMIFS(资金台帐!$AC$6:$AC$6005,资金台帐!$T$6:$T$6005,$Q23,资金台帐!$U$6:$U$6005,"变动成本",资金台帐!$O$6:$O$6005,IF($C$3="全部","?*",$C$3),资金台帐!$N$6:$N$6005,">="&DATE($F$3,7,1),资金台帐!$N$6:$N$6005,"<"&DATE($F$3,7+1,1))-SUMIFS(资金台帐!$AB$6:$AB$6005,资金台帐!$T$6:$T$6005,$Q23,资金台帐!$U$6:$U$6005,"变动成本",资金台帐!$O$6:$O$6005,IF($C$3="全部","?*",$C$3),资金台帐!$N$6:$N$6005,">="&DATE($F$3,7,1),资金台帐!$N$6:$N$6005,"<"&DATE($F$3,7+1,1)),2) -> 0 | J23: =ROUND(SUMIFS(资金台帐!$AC$6:$AC$6005,资金台帐!$T$6:$T$6005,$Q23,资金台帐!$U$6:$U$6005,"变动成本",资金台帐!$O$6:$O$6005,IF($C$3="全部","?*",$C$3),资金台帐!$N$6:$N$6005,">="&DATE($F$3,8,1),资金台帐!$N$6:$N$6005,"<"&DATE($F$3,8+1,1))-SUMIFS(资金台帐!$AB$6:$AB$6005,资金台帐!$T$6:$T$6005,$Q23,资金台帐!$U$6:$U$6005,"变动成本",资金台帐!$O$6:$O$6005,IF($C$3="全部","?*",$C$3),资金台帐!$N$6:$N$6005,">="&DATE($F$3,8,1),资金台帐!$N$6:$N$6005,"<"&DATE($F$3,8+1,1)),2) -> 0 | K23: =ROUND(SUMIFS(资金台帐!$AC$6:$AC$6005,资金台帐!$T$6:$T$6005,$Q23,资金台帐!$U$6:$U$6005,"变动成本",资金台帐!$O$6:$O$6005,IF($C$3="全部","?*",$C$3),资金台帐!$N$6:$N$6005,">="&DATE($F$3,9,1),资金台帐!$N$6:$N$6005,"<"&DATE($F$3,9+1,1))-SUMIFS(资金台帐!$AB$6:$AB$6005,资金台帐!$T$6:$T$6005,$Q23,资金台帐!$U$6:$U$6005,"变动成本",资金台帐!$O$6:$O$6005,IF($C$3="全部","?*",$C$3),资金台帐!$N$6:$N$6005,">="&DATE($F$3,9,1),资金台帐!$N$6:$N$6005,"<"&DATE($F$3,9+1,1)),2) -> 3.6 | L23: =ROUND(SUMIFS(资金台帐!$AC$6:$AC$6005,资金台帐!$T$6:$T$6005,$Q23,资金台帐!$U$6:$U$6005,"变动成本",资金台帐!$O$6:$O$6005,IF($C$3="全部","?*",$C$3),资金台帐!$N$6:$N$6005,">="&DATE($F$3,10,1),资金台帐!$N$6:$N$6005,"<"&DATE($F$3,10+1,1))-SUMIFS(资金台帐!$AB$6:$AB$6005,资金台帐!$T$6:$T$6005,$Q23,资金台帐!$U$6:$U$6005,"变动成本",资金台帐!$O$6:$O$6005,IF($C$3="全部","?*",$C$3),资金台帐!$N$6:$N$6005,">="&DATE($F$3,10,1),资金台帐!$N$6:$N$6005,"<"&DATE($F$3,10+1,1)),2) -> 0 | M23: =ROUND(SUMIFS(资金台帐!$AC$6:$AC$6005,资金台帐!$T$6:$T$6005,$Q23,资金台帐!$U$6:$U$6005,"变动成本",资金台帐!$O$6:$O$6005,IF($C$3="全部","?*",$C$3),资金台帐!$N$6:$N$6005,">="&DATE($F$3,11,1),资金台帐!$N$6:$N$6005,"<"&DATE($F$3,11+1,1))-SUMIFS(资金台帐!$AB$6:$AB$6005,资金台帐!$T$6:$T$6005,$Q23,资金台帐!$U$6:$U$6005,"变动成本",资金台帐!$O$6:$O$6005,IF($C$3="全部","?*",$C$3),资金台帐!$N$6:$N$6005,">="&DATE($F$3,11,1),资金台帐!$N$6:$N$6005,"<"&DATE($F$3,11+1,1)),2) -> 0 | N23: =ROUND(SUMIFS(资金台帐!$AC$6:$AC$6005,资金台帐!$T$6:$T$6005,$Q23,资金台帐!$U$6:$U$6005,"变动成本",资金台帐!$O$6:$O$6005,IF($C$3="全部","?*",$C$3),资金台帐!$N$6:$N$6005,">="&DATE($F$3,12,1),资金台帐!$N$6:$N$6005,"<"&DATE($F$3,12+1,1))-SUMIFS(资金台帐!$AB$6:$AB$6005,资金台帐!$T$6:$T$6005,$Q23,资金台帐!$U$6:$U$6005,"变动成本",资金台帐!$O$6:$O$6005,IF($C$3="全部","?*",$C$3),资金台帐!$N$6:$N$6005,">="&DATE($F$3,12,1),资金台帐!$N$6:$N$6005,"<"&DATE($F$3,12+1,1)),2) -> 0 | O23: =ROUND(SUM(C23:N23),2) -> 3.6 | P23: =IF(N($O$16)=0,"",O23/$O$16) -> 2.1052632e-05 | Q23: =基础资料!$U$22&"" -> 银行手续费
B24: =IF(基础资料!$W$23="",基础资料!$U$23&"",基础资料!$W$23&"") -> 刻章费用 | C24: =ROUND(SUMIFS(资金台帐!$AC$6:$AC$6005,资金台帐!$T$6:$T$6005,$Q24,资金台帐!$U$6:$U$6005,"变动成本",资金台帐!$O$6:$O$6005,IF($C$3="全部","?*",$C$3),资金台帐!$N$6:$N$6005,">="&DATE($F$3,1,1),资金台帐!$N$6:$N$6005,"<"&DATE($F$3,1+1,1))-SUMIFS(资金台帐!$AB$6:$AB$6005,资金台帐!$T$6:$T$6005,$Q24,资金台帐!$U$6:$U$6005,"变动成本",资金台帐!$O$6:$O$6005,IF($C$3="全部","?*",$C$3),资金台帐!$N$6:$N$6005,">="&DATE($F$3,1,1),资金台帐!$N$6:$N$6005,"<"&DATE($F$3,1+1,1)),2) -> 0 | D24: =ROUND(SUMIFS(资金台帐!$AC$6:$AC$6005,资金台帐!$T$6:$T$6005,$Q24,资金台帐!$U$6:$U$6005,"变动成本",资金台帐!$O$6:$O$6005,IF($C$3="全部","?*",$C$3),资金台帐!$N$6:$N$6005,">="&DATE($F$3,2,1),资金台帐!$N$6:$N$6005,"<"&DATE($F$3,2+1,1))-SUMIFS(资金台帐!$AB$6:$AB$6005,资金台帐!$T$6:$T$6005,$Q24,资金台帐!$U$6:$U$6005,"变动成本",资金台帐!$O$6:$O$6005,IF($C$3="全部","?*",$C$3),资金台帐!$N$6:$N$6005,">="&DATE($F$3,2,1),资金台帐!$N$6:$N$6005,"<"&DATE($F$3,2+1,1)),2) -> 0 | E24: =ROUND(SUMIFS(资金台帐!$AC$6:$AC$6005,资金台帐!$T$6:$T$6005,$Q24,资金台帐!$U$6:$U$6005,"变动成本",资金台帐!$O$6:$O$6005,IF($C$3="全部","?*",$C$3),资金台帐!$N$6:$N$6005,">="&DATE($F$3,3,1),资金台帐!$N$6:$N$6005,"<"&DATE($F$3,3+1,1))-SUMIFS(资金台帐!$AB$6:$AB$6005,资金台帐!$T$6:$T$6005,$Q24,资金台帐!$U$6:$U$6005,"变动成本",资金台帐!$O$6:$O$6005,IF($C$3="全部","?*",$C$3),资金台帐!$N$6:$N$6005,">="&DATE($F$3,3,1),资金台帐!$N$6:$N$6005,"<"&DATE($F$3,3+1,1)),2) -> 0 | F24: =ROUND(SUMIFS(资金台帐!$AC$6:$AC$6005,资金台帐!$T$6:$T$6005,$Q24,资金台帐!$U$6:$U$6005,"变动成本",资金台帐!$O$6:$O$6005,IF($C$3="全部","?*",$C$3),资金台帐!$N$6:$N$6005,">="&DATE($F$3,4,1),资金台帐!$N$6:$N$6005,"<"&DATE($F$3,4+1,1))-SUMIFS(资金台帐!$AB$6:$AB$6005,资金台帐!$T$6:$T$6005,$Q24,资金台帐!$U$6:$U$6005,"变动成本",资金台帐!$O$6:$O$6005,IF($C$3="全部","?*",$C$3),资金台帐!$N$6:$N$6005,">="&DATE($F$3,4,1),资金台帐!$N$6:$N$6005,"<"&DATE($F$3,4+1,1)),2) -> 0 | G24: =ROUND(SUMIFS(资金台帐!$AC$6:$AC$6005,资金台帐!$T$6:$T$6005,$Q24,资金台帐!$U$6:$U$6005,"变动成本",资金台帐!$O$6:$O$6005,IF($C$3="全部","?*",$C$3),资金台帐!$N$6:$N$6005,">="&DATE($F$3,5,1),资金台帐!$N$6:$N$6005,"<"&DATE($F$3,5+1,1))-SUMIFS(资金台帐!$AB$6:$AB$6005,资金台帐!$T$6:$T$6005,$Q24,资金台帐!$U$6:$U$6005,"变动成本",资金台帐!$O$6:$O$6005,IF($C$3="全部","?*",$C$3),资金台帐!$N$6:$N$6005,">="&DATE($F$3,5,1),资金台帐!$N$6:$N$6005,"<"&DATE($F$3,5+1,1)),2) -> 0 | H24: =ROUND(SUMIFS(资金台帐!$AC$6:$AC$6005,资金台帐!$T$6:$T$6005,$Q24,资金台帐!$U$6:$U$6005,"变动成本",资金台帐!$O$6:$O$6005,IF($C$3="全部","?*",$C$3),资金台帐!$N$6:$N$6005,">="&DATE($F$3,6,1),资金台帐!$N$6:$N$6005,"<"&DATE($F$3,6+1,1))-SUMIFS(资金台帐!$AB$6:$AB$6005,资金台帐!$T$6:$T$6005,$Q24,资金台帐!$U$6:$U$6005,"变动成本",资金台帐!$O$6:$O$6005,IF($C$3="全部","?*",$C$3),资金台帐!$N$6:$N$6005,">="&DATE($F$3,6,1),资金台帐!$N$6:$N$6005,"<"&DATE($F$3,6+1,1)),2) -> 0 | I24: =ROUND(SUMIFS(资金台帐!$AC$6:$AC$6005,资金台帐!$T$6:$T$6005,$Q24,资金台帐!$U$6:$U$6005,"变动成本",资金台帐!$O$6:$O$6005,IF($C$3="全部","?*",$C$3),资金台帐!$N$6:$N$6005,">="&DATE($F$3,7,1),资金台帐!$N$6:$N$6005,"<"&DATE($F$3,7+1,1))-SUMIFS(资金台帐!$AB$6:$AB$6005,资金台帐!$T$6:$T$6005,$Q24,资金台帐!$U$6:$U$6005,"变动成本",资金台帐!$O$6:$O$6005,IF($C$3="全部","?*",$C$3),资金台帐!$N$6:$N$6005,">="&DATE($F$3,7,1),资金台帐!$N$6:$N$6005,"<"&DATE($F$3,7+1,1)),2) -> 0 | J24: =ROUND(SUMIFS(资金台帐!$AC$6:$AC$6005,资金台帐!$T$6:$T$6005,$Q24,资金台帐!$U$6:$U$6005,"变动成本",资金台帐!$O$6:$O$6005,IF($C$3="全部","?*",$C$3),资金台帐!$N$6:$N$6005,">="&DATE($F$3,8,1),资金台帐!$N$6:$N$6005,"<"&DATE($F$3,8+1,1))-SUMIFS(资金台帐!$AB$6:$AB$6005,资金台帐!$T$6:$T$6005,$Q24,资金台帐!$U$6:$U$6005,"变动成本",资金台帐!$O$6:$O$6005,IF($C$3="全部","?*",$C$3),资金台帐!$N$6:$N$6005,">="&DATE($F$3,8,1),资金台帐!$N$6:$N$6005,"<"&DATE($F$3,8+1,1)),2) -> 0 | K24: =ROUND(SUMIFS(资金台帐!$AC$6:$AC$6005,资金台帐!$T$6:$T$6005,$Q24,资金台帐!$U$6:$U$6005,"变动成本",资金台帐!$O$6:$O$6005,IF($C$3="全部","?*",$C$3),资金台帐!$N$6:$N$6005,">="&DATE($F$3,9,1),资金台帐!$N$6:$N$6005,"<"&DATE($F$3,9+1,1))-SUMIFS(资金台帐!$AB$6:$AB$6005,资金台帐!$T$6:$T$6005,$Q24,资金台帐!$U$6:$U$6005,"变动成本",资金台帐!$O$6:$O$6005,IF($C$3="全部","?*",$C$3),资金台帐!$N$6:$N$6005,">="&DATE($F$3,9,1),资金台帐!$N$6:$N$6005,"<"&DATE($F$3,9+1,1)),2) -> 0 | L24: =ROUND(SUMIFS(资金台帐!$AC$6:$AC$6005,资金台帐!$T$6:$T$6005,$Q24,资金台帐!$U$6:$U$6005,"变动成本",资金台帐!$O$6:$O$6005,IF($C$3="全部","?*",$C$3),资金台帐!$N$6:$N$6005,">="&DATE($F$3,10,1),资金台帐!$N$6:$N$6005,"<"&DATE($F$3,10+1,1))-SUMIFS(资金台帐!$AB$6:$AB$6005,资金台帐!$T$6:$T$6005,$Q24,资金台帐!$U$6:$U$6005,"变动成本",资金台帐!$O$6:$O$6005,IF($C$3="全部","?*",$C$3),资金台帐!$N$6:$N$6005,">="&DATE($F$3,10,1),资金台帐!$N$6:$N$6005,"<"&DATE($F$3,10+1,1)),2) -> 0 | M24: =ROUND(SUMIFS(资金台帐!$AC$6:$AC$6005,资金台帐!$T$6:$T$6005,$Q24,资金台帐!$U$6:$U$6005,"变动成本",资金台帐!$O$6:$O$6005,IF($C$3="全部","?*",$C$3),资金台帐!$N$6:$N$6005,">="&DATE($F$3,11,1),资金台帐!$N$6:$N$6005,"<"&DATE($F$3,11+1,1))-SUMIFS(资金台帐!$AB$6:$AB$6005,资金台帐!$T$6:$T$6005,$Q24,资金台帐!$U$6:$U$6005,"变动成本",资金台帐!$O$6:$O$6005,IF($C$3="全部","?*",$C$3),资金台帐!$N$6:$N$6005,">="&DATE($F$3,11,1),资金台帐!$N$6:$N$6005,"<"&DATE($F$3,11+1,1)),2) -> 0 | N24: =ROUND(SUMIFS(资金台帐!$AC$6:$AC$6005,资金台帐!$T$6:$T$6005,$Q24,资金台帐!$U$6:$U$6005,"变动成本",资金台帐!$O$6:$O$6005,IF($C$3="全部","?*",$C$3),资金台帐!$N$6:$N$6005,">="&DATE($F$3,12,1),资金台帐!$N$6:$N$6005,"<"&DATE($F$3,12+1,1))-SUMIFS(资金台帐!$AB$6:$AB$6005,资金台帐!$T$6:$T$6005,$Q24,资金台帐!$U$6:$U$6005,"变动成本",资金台帐!$O$6:$O$6005,IF($C$3="全部","?*",$C$3),资金台帐!$N$6:$N$6005,">="&DATE($F$3,12,1),资金台帐!$N$6:$N$6005,"<"&DATE($F$3,12+1,1)),2) -> 0 | O24: =ROUND(SUM(C24:N24),2) -> 0 | P24: =IF(N($O$16)=0,"",O24/$O$16) -> 0 | Q24: =基础资料!$U$23&"" -> 刻章费用
B25: =IF(基础资料!$W$24="",基础资料!$U$24&"",基础资料!$W$24&"") -> 办公费用 | C25: =ROUND(SUMIFS(资金台帐!$AC$6:$AC$6005,资金台帐!$T$6:$T$6005,$Q25,资金台帐!$U$6:$U$6005,"变动成本",资金台帐!$O$6:$O$6005,IF($C$3="全部","?*",$C$3),资金台帐!$N$6:$N$6005,">="&DATE($F$3,1,1),资金台帐!$N$6:$N$6005,"<"&DATE($F$3,1+1,1))-SUMIFS(资金台帐!$AB$6:$AB$6005,资金台帐!$T$6:$T$6005,$Q25,资金台帐!$U$6:$U$6005,"变动成本",资金台帐!$O$6:$O$6005,IF($C$3="全部","?*",$C$3),资金台帐!$N$6:$N$6005,">="&DATE($F$3,1,1),资金台帐!$N$6:$N$6005,"<"&DATE($F$3,1+1,1)),2) -> 0 | D25: =ROUND(SUMIFS(资金台帐!$AC$6:$AC$6005,资金台帐!$T$6:$T$6005,$Q25,资金台帐!$U$6:$U$6005,"变动成本",资金台帐!$O$6:$O$6005,IF($C$3="全部","?*",$C$3),资金台帐!$N$6:$N$6005,">="&DATE($F$3,2,1),资金台帐!$N$6:$N$6005,"<"&DATE($F$3,2+1,1))-SUMIFS(资金台帐!$AB$6:$AB$6005,资金台帐!$T$6:$T$6005,$Q25,资金台帐!$U$6:$U$6005,"变动成本",资金台帐!$O$6:$O$6005,IF($C$3="全部","?*",$C$3),资金台帐!$N$6:$N$6005,">="&DATE($F$3,2,1),资金台帐!$N$6:$N$6005,"<"&DATE($F$3,2+1,1)),2) -> 0 | E25: =ROUND(SUMIFS(资金台帐!$AC$6:$AC$6005,资金台帐!$T$6:$T$6005,$Q25,资金台帐!$U$6:$U$6005,"变动成本",资金台帐!$O$6:$O$6005,IF($C$3="全部","?*",$C$3),资金台帐!$N$6:$N$6005,">="&DATE($F$3,3,1),资金台帐!$N$6:$N$6005,"<"&DATE($F$3,3+1,1))-SUMIFS(资金台帐!$AB$6:$AB$6005,资金台帐!$T$6:$T$6005,$Q25,资金台帐!$U$6:$U$6005,"变动成本",资金台帐!$O$6:$O$6005,IF($C$3="全部","?*",$C$3),资金台帐!$N$6:$N$6005,">="&DATE($F$3,3,1),资金台帐!$N$6:$N$6005,"<"&DATE($F$3,3+1,1)),2) -> 0 | F25: =ROUND(SUMIFS(资金台帐!$AC$6:$AC$6005,资金台帐!$T$6:$T$6005,$Q25,资金台帐!$U$6:$U$6005,"变动成本",资金台帐!$O$6:$O$6005,IF($C$3="全部","?*",$C$3),资金台帐!$N$6:$N$6005,">="&DATE($F$3,4,1),资金台帐!$N$6:$N$6005,"<"&DATE($F$3,4+1,1))-SUMIFS(资金台帐!$AB$6:$AB$6005,资金台帐!$T$6:$T$6005,$Q25,资金台帐!$U$6:$U$6005,"变动成本",资金台帐!$O$6:$O$6005,IF($C$3="全部","?*",$C$3),资金台帐!$N$6:$N$6005,">="&DATE($F$3,4,1),资金台帐!$N$6:$N$6005,"<"&DATE($F$3,4+1,1)),2) -> 0 | G25: =ROUND(SUMIFS(资金台帐!$AC$6:$AC$6005,资金台帐!$T$6:$T$6005,$Q25,资金台帐!$U$6:$U$6005,"变动成本",资金台帐!$O$6:$O$6005,IF($C$3="全部","?*",$C$3),资金台帐!$N$6:$N$6005,">="&DATE($F$3,5,1),资金台帐!$N$6:$N$6005,"<"&DATE($F$3,5+1,1))-SUMIFS(资金台帐!$AB$6:$AB$6005,资金台帐!$T$6:$T$6005,$Q25,资金台帐!$U$6:$U$6005,"变动成本",资金台帐!$O$6:$O$6005,IF($C$3="全部","?*",$C$3),资金台帐!$N$6:$N$6005,">="&DATE($F$3,5,1),资金台帐!$N$6:$N$6005,"<"&DATE($F$3,5+1,1)),2) -> 0 | H25: =ROUND(SUMIFS(资金台帐!$AC$6:$AC$6005,资金台帐!$T$6:$T$6005,$Q25,资金台帐!$U$6:$U$6005,"变动成本",资金台帐!$O$6:$O$6005,IF($C$3="全部","?*",$C$3),资金台帐!$N$6:$N$6005,">="&DATE($F$3,6,1),资金台帐!$N$6:$N$6005,"<"&DATE($F$3,6+1,1))-SUMIFS(资金台帐!$AB$6:$AB$6005,资金台帐!$T$6:$T$6005,$Q25,资金台帐!$U$6:$U$6005,"变动成本",资金台帐!$O$6:$O$6005,IF($C$3="全部","?*",$C$3),资金台帐!$N$6:$N$6005,">="&DATE($F$3,6,1),资金台帐!$N$6:$N$6005,"<"&DATE($F$3,6+1,1)),2) -> 0 | I25: =ROUND(SUMIFS(资金台帐!$AC$6:$AC$6005,资金台帐!$T$6:$T$6005,$Q25,资金台帐!$U$6:$U$6005,"变动成本",资金台帐!$O$6:$O$6005,IF($C$3="全部","?*",$C$3),资金台帐!$N$6:$N$6005,">="&DATE($F$3,7,1),资金台帐!$N$6:$N$6005,"<"&DATE($F$3,7+1,1))-SUMIFS(资金台帐!$AB$6:$AB$6005,资金台帐!$T$6:$T$6005,$Q25,资金台帐!$U$6:$U$6005,"变动成本",资金台帐!$O$6:$O$6005,IF($C$3="全部","?*",$C$3),资金台帐!$N$6:$N$6005,">="&DATE($F$3,7,1),资金台帐!$N$6:$N$6005,"<"&DATE($F$3,7+1,1)),2) -> 0 | J25: =ROUND(SUMIFS(资金台帐!$AC$6:$AC$6005,资金台帐!$T$6:$T$6005,$Q25,资金台帐!$U$6:$U$6005,"变动成本",资金台帐!$O$6:$O$6005,IF($C$3="全部","?*",$C$3),资金台帐!$N$6:$N$6005,">="&DATE($F$3,8,1),资金台帐!$N$6:$N$6005,"<"&DATE($F$3,8+1,1))-SUMIFS(资金台帐!$AB$6:$AB$6005,资金台帐!$T$6:$T$6005,$Q25,资金台帐!$U$6:$U$6005,"变动成本",资金台帐!$O$6:$O$6005,IF($C$3="全部","?*",$C$3),资金台帐!$N$6:$N$6005,">="&DATE($F$3,8,1),资金台帐!$N$6:$N$6005,"<"&DATE($F$3,8+1,1)),2) -> 0 | K25: =ROUND(SUMIFS(资金台帐!$AC$6:$AC$6005,资金台帐!$T$6:$T$6005,$Q25,资金台帐!$U$6:$U$6005,"变动成本",资金台帐!$O$6:$O$6005,IF($C$3="全部","?*",$C$3),资金台帐!$N$6:$N$6005,">="&DATE($F$3,9,1),资金台帐!$N$6:$N$6005,"<"&DATE($F$3,9+1,1))-SUMIFS(资金台帐!$AB$6:$AB$6005,资金台帐!$T$6:$T$6005,$Q25,资金台帐!$U$6:$U$6005,"变动成本",资金台帐!$O$6:$O$6005,IF($C$3="全部","?*",$C$3),资金台帐!$N$6:$N$6005,">="&DATE($F$3,9,1),资金台帐!$N$6:$N$6005,"<"&DATE($F$3,9+1,1)),2) -> 214.29 | L25: =ROUND(SUMIFS(资金台帐!$AC$6:$AC$6005,资金台帐!$T$6:$T$6005,$Q25,资金台帐!$U$6:$U$6005,"变动成本",资金台帐!$O$6:$O$6005,IF($C$3="全部","?*",$C$3),资金台帐!$N$6:$N$6005,">="&DATE($F$3,10,1),资金台帐!$N$6:$N$6005,"<"&DATE($F$3,10+1,1))-SUMIFS(资金台帐!$AB$6:$AB$6005,资金台帐!$T$6:$T$6005,$Q25,资金台帐!$U$6:$U$6005,"变动成本",资金台帐!$O$6:$O$6005,IF($C$3="全部","?*",$C$3),资金台帐!$N$6:$N$6005,">="&DATE($F$3,10,1),资金台帐!$N$6:$N$6005,"<"&DATE($F$3,10+1,1)),2) -> 0 | M25: =ROUND(SUMIFS(资金台帐!$AC$6:$AC$6005,资金台帐!$T$6:$T$6005,$Q25,资金台帐!$U$6:$U$6005,"变动成本",资金台帐!$O$6:$O$6005,IF($C$3="全部","?*",$C$3),资金台帐!$N$6:$N$6005,">="&DATE($F$3,11,1),资金台帐!$N$6:$N$6005,"<"&DATE($F$3,11+1,1))-SUMIFS(资金台帐!$AB$6:$AB$6005,资金台帐!$T$6:$T$6005,$Q25,资金台帐!$U$6:$U$6005,"变动成本",资金台帐!$O$6:$O$6005,IF($C$3="全部","?*",$C$3),资金台帐!$N$6:$N$6005,">="&DATE($F$3,11,1),资金台帐!$N$6:$N$6005,"<"&DATE($F$3,11+1,1)),2) -> 0 | N25: =ROUND(SUMIFS(资金台帐!$AC$6:$AC$6005,资金台帐!$T$6:$T$6005,$Q25,资金台帐!$U$6:$U$6005,"变动成本",资金台帐!$O$6:$O$6005,IF($C$3="全部","?*",$C$3),资金台帐!$N$6:$N$6005,">="&DATE($F$3,12,1),资金台帐!$N$6:$N$6005,"<"&DATE($F$3,12+1,1))-SUMIFS(资金台帐!$AB$6:$AB$6005,资金台帐!$T$6:$T$6005,$Q25,资金台帐!$U$6:$U$6005,"变动成本",资金台帐!$O$6:$O$6005,IF($C$3="全部","?*",$C$3),资金台帐!$N$6:$N$6005,">="&DATE($F$3,12,1),资金台帐!$N$6:$N$6005,"<"&DATE($F$3,12+1,1)),2) -> 0 | O25: =ROUND(SUM(C25:N25),2) -> 214.29 | P25: =IF(N($O$16)=0,"",O25/$O$16) -> 0.0012531579 | Q25: =基础资料!$U$24&"" -> 办公费用
B26: =IF(基础资料!$W$25="",基础资料!$U$25&"",基础资料!$W$25&"") -> 固定资产 | C26: =ROUND(SUMIFS(资金台帐!$AC$6:$AC$6005,资金台帐!$T$6:$T$6005,$Q26,资金台帐!$U$6:$U$6005,"变动成本",资金台帐!$O$6:$O$6005,IF($C$3="全部","?*",$C$3),资金台帐!$N$6:$N$6005,">="&DATE($F$3,1,1),资金台帐!$N$6:$N$6005,"<"&DATE($F$3,1+1,1))-SUMIFS(资金台帐!$AB$6:$AB$6005,资金台帐!$T$6:$T$6005,$Q26,资金台帐!$U$6:$U$6005,"变动成本",资金台帐!$O$6:$O$6005,IF($C$3="全部","?*",$C$3),资金台帐!$N$6:$N$6005,">="&DATE($F$3,1,1),资金台帐!$N$6:$N$6005,"<"&DATE($F$3,1+1,1)),2) -> 0 | D26: =ROUND(SUMIFS(资金台帐!$AC$6:$AC$6005,资金台帐!$T$6:$T$6005,$Q26,资金台帐!$U$6:$U$6005,"变动成本",资金台帐!$O$6:$O$6005,IF($C$3="全部","?*",$C$3),资金台帐!$N$6:$N$6005,">="&DATE($F$3,2,1),资金台帐!$N$6:$N$6005,"<"&DATE($F$3,2+1,1))-SUMIFS(资金台帐!$AB$6:$AB$6005,资金台帐!$T$6:$T$6005,$Q26,资金台帐!$U$6:$U$6005,"变动成本",资金台帐!$O$6:$O$6005,IF($C$3="全部","?*",$C$3),资金台帐!$N$6:$N$6005,">="&DATE($F$3,2,1),资金台帐!$N$6:$N$6005,"<"&DATE($F$3,2+1,1)),2) -> 0 | E26: =ROUND(SUMIFS(资金台帐!$AC$6:$AC$6005,资金台帐!$T$6:$T$6005,$Q26,资金台帐!$U$6:$U$6005,"变动成本",资金台帐!$O$6:$O$6005,IF($C$3="全部","?*",$C$3),资金台帐!$N$6:$N$6005,">="&DATE($F$3,3,1),资金台帐!$N$6:$N$6005,"<"&DATE($F$3,3+1,1))-SUMIFS(资金台帐!$AB$6:$AB$6005,资金台帐!$T$6:$T$6005,$Q26,资金台帐!$U$6:$U$6005,"变动成本",资金台帐!$O$6:$O$6005,IF($C$3="全部","?*",$C$3),资金台帐!$N$6:$N$6005,">="&DATE($F$3,3,1),资金台帐!$N$6:$N$6005,"<"&DATE($F$3,3+1,1)),2) -> 0 | F26: =ROUND(SUMIFS(资金台帐!$AC$6:$AC$6005,资金台帐!$T$6:$T$6005,$Q26,资金台帐!$U$6:$U$6005,"变动成本",资金台帐!$O$6:$O$6005,IF($C$3="全部","?*",$C$3),资金台帐!$N$6:$N$6005,">="&DATE($F$3,4,1),资金台帐!$N$6:$N$6005,"<"&DATE($F$3,4+1,1))-SUMIFS(资金台帐!$AB$6:$AB$6005,资金台帐!$T$6:$T$6005,$Q26,资金台帐!$U$6:$U$6005,"变动成本",资金台帐!$O$6:$O$6005,IF($C$3="全部","?*",$C$3),资金台帐!$N$6:$N$6005,">="&DATE($F$3,4,1),资金台帐!$N$6:$N$6005,"<"&DATE($F$3,4+1,1)),2) -> 0 | G26: =ROUND(SUMIFS(资金台帐!$AC$6:$AC$6005,资金台帐!$T$6:$T$6005,$Q26,资金台帐!$U$6:$U$6005,"变动成本",资金台帐!$O$6:$O$6005,IF($C$3="全部","?*",$C$3),资金台帐!$N$6:$N$6005,">="&DATE($F$3,5,1),资金台帐!$N$6:$N$6005,"<"&DATE($F$3,5+1,1))-SUMIFS(资金台帐!$AB$6:$AB$6005,资金台帐!$T$6:$T$6005,$Q26,资金台帐!$U$6:$U$6005,"变动成本",资金台帐!$O$6:$O$6005,IF($C$3="全部","?*",$C$3),资金台帐!$N$6:$N$6005,">="&DATE($F$3,5,1),资金台帐!$N$6:$N$6005,"<"&DATE($F$3,5+1,1)),2) -> 0 | H26: =ROUND(SUMIFS(资金台帐!$AC$6:$AC$6005,资金台帐!$T$6:$T$6005,$Q26,资金台帐!$U$6:$U$6005,"变动成本",资金台帐!$O$6:$O$6005,IF($C$3="全部","?*",$C$3),资金台帐!$N$6:$N$6005,">="&DATE($F$3,6,1),资金台帐!$N$6:$N$6005,"<"&DATE($F$3,6+1,1))-SUMIFS(资金台帐!$AB$6:$AB$6005,资金台帐!$T$6:$T$6005,$Q26,资金台帐!$U$6:$U$6005,"变动成本",资金台帐!$O$6:$O$6005,IF($C$3="全部","?*",$C$3),资金台帐!$N$6:$N$6005,">="&DATE($F$3,6,1),资金台帐!$N$6:$N$6005,"<"&DATE($F$3,6+1,1)),2) -> 0 | I26: =ROUND(SUMIFS(资金台帐!$AC$6:$AC$6005,资金台帐!$T$6:$T$6005,$Q26,资金台帐!$U$6:$U$6005,"变动成本",资金台帐!$O$6:$O$6005,IF($C$3="全部","?*",$C$3),资金台帐!$N$6:$N$6005,">="&DATE($F$3,7,1),资金台帐!$N$6:$N$6005,"<"&DATE($F$3,7+1,1))-SUMIFS(资金台帐!$AB$6:$AB$6005,资金台帐!$T$6:$T$6005,$Q26,资金台帐!$U$6:$U$6005,"变动成本",资金台帐!$O$6:$O$6005,IF($C$3="全部","?*",$C$3),资金台帐!$N$6:$N$6005,">="&DATE($F$3,7,1),资金台帐!$N$6:$N$6005,"<"&DATE($F$3,7+1,1)),2) -> 0 | J26: =ROUND(SUMIFS(资金台帐!$AC$6:$AC$6005,资金台帐!$T$6:$T$6005,$Q26,资金台帐!$U$6:$U$6005,"变动成本",资金台帐!$O$6:$O$6005,IF($C$3="全部","?*",$C$3),资金台帐!$N$6:$N$6005,">="&DATE($F$3,8,1),资金台帐!$N$6:$N$6005,"<"&DATE($F$3,8+1,1))-SUMIFS(资金台帐!$AB$6:$AB$6005,资金台帐!$T$6:$T$6005,$Q26,资金台帐!$U$6:$U$6005,"变动成本",资金台帐!$O$6:$O$6005,IF($C$3="全部","?*",$C$3),资金台帐!$N$6:$N$6005,">="&DATE($F$3,8,1),资金台帐!$N$6:$N$6005,"<"&DATE($F$3,8+1,1)),2) -> 0 | K26: =ROUND(SUMIFS(资金台帐!$AC$6:$AC$6005,资金台帐!$T$6:$T$6005,$Q26,资金台帐!$U$6:$U$6005,"变动成本",资金台帐!$O$6:$O$6005,IF($C$3="全部","?*",$C$3),资金台帐!$N$6:$N$6005,">="&DATE($F$3,9,1),资金台帐!$N$6:$N$6005,"<"&DATE($F$3,9+1,1))-SUMIFS(资金台帐!$AB$6:$AB$6005,资金台帐!$T$6:$T$6005,$Q26,资金台帐!$U$6:$U$6005,"变动成本",资金台帐!$O$6:$O$6005,IF($C$3="全部","?*",$C$3),资金台帐!$N$6:$N$6005,">="&DATE($F$3,9,1),资金台帐!$N$6:$N$6005,"<"&DATE($F$3,9+1,1)),2) -> 0 | L26: =ROUND(SUMIFS(资金台帐!$AC$6:$AC$6005,资金台帐!$T$6:$T$6005,$Q26,资金台帐!$U$6:$U$6005,"变动成本",资金台帐!$O$6:$O$6005,IF($C$3="全部","?*",$C$3),资金台帐!$N$6:$N$6005,">="&DATE($F$3,10,1),资金台帐!$N$6:$N$6005,"<"&DATE($F$3,10+1,1))-SUMIFS(资金台帐!$AB$6:$AB$6005,资金台帐!$T$6:$T$6005,$Q26,资金台帐!$U$6:$U$6005,"变动成本",资金台帐!$O$6:$O$6005,IF($C$3="全部","?*",$C$3),资金台帐!$N$6:$N$6005,">="&DATE($F$3,10,1),资金台帐!$N$6:$N$6005,"<"&DATE($F$3,10+1,1)),2) -> 0 | M26: =ROUND(SUMIFS(资金台帐!$AC$6:$AC$6005,资金台帐!$T$6:$T$6005,$Q26,资金台帐!$U$6:$U$6005,"变动成本",资金台帐!$O$6:$O$6005,IF($C$3="全部","?*",$C$3),资金台帐!$N$6:$N$6005,">="&DATE($F$3,11,1),资金台帐!$N$6:$N$6005,"<"&DATE($F$3,11+1,1))-SUMIFS(资金台帐!$AB$6:$AB$6005,资金台帐!$T$6:$T$6005,$Q26,资金台帐!$U$6:$U$6005,"变动成本",资金台帐!$O$6:$O$6005,IF($C$3="全部","?*",$C$3),资金台帐!$N$6:$N$6005,">="&DATE($F$3,11,1),资金台帐!$N$6:$N$6005,"<"&DATE($F$3,11+1,1)),2) -> 0 | N26: =ROUND(SUMIFS(资金台帐!$AC$6:$AC$6005,资金台帐!$T$6:$T$6005,$Q26,资金台帐!$U$6:$U$6005,"变动成本",资金台帐!$O$6:$O$6005,IF($C$3="全部","?*",$C$3),资金台帐!$N$6:$N$6005,">="&DATE($F$3,12,1),资金台帐!$N$6:$N$6005,"<"&DATE($F$3,12+1,1))-SUMIFS(资金台帐!$AB$6:$AB$6005,资金台帐!$T$6:$T$6005,$Q26,资金台帐!$U$6:$U$6005,"变动成本",资金台帐!$O$6:$O$6005,IF($C$3="全部","?*",$C$3),资金台帐!$N$6:$N$6005,">="&DATE($F$3,12,1),资金台帐!$N$6:$N$6005,"<"&DATE($F$3,12+1,1)),2) -> 0 | O26: =ROUND(SUM(C26:N26),2) -> 0 | P26: =IF(N($O$16)=0,"",O26/$O$16) -> 0 | Q26: =基础资料!$U$25&"" -> 固定资产
B27: =IF(基础资料!$W$26="",基础资料!$U$26&"",基础资料!$W$26&"") -> 汽车费用 | C27: =ROUND(SUMIFS(资金台帐!$AC$6:$AC$6005,资金台帐!$T$6:$T$6005,$Q27,资金台帐!$U$6:$U$6005,"变动成本",资金台帐!$O$6:$O$6005,IF($C$3="全部","?*",$C$3),资金台帐!$N$6:$N$6005,">="&DATE($F$3,1,1),资金台帐!$N$6:$N$6005,"<"&DATE($F$3,1+1,1))-SUMIFS(资金台帐!$AB$6:$AB$6005,资金台帐!$T$6:$T$6005,$Q27,资金台帐!$U$6:$U$6005,"变动成本",资金台帐!$O$6:$O$6005,IF($C$3="全部","?*",$C$3),资金台帐!$N$6:$N$6005,">="&DATE($F$3,1,1),资金台帐!$N$6:$N$6005,"<"&DATE($F$3,1+1,1)),2) -> 0 | D27: =ROUND(SUMIFS(资金台帐!$AC$6:$AC$6005,资金台帐!$T$6:$T$6005,$Q27,资金台帐!$U$6:$U$6005,"变动成本",资金台帐!$O$6:$O$6005,IF($C$3="全部","?*",$C$3),资金台帐!$N$6:$N$6005,">="&DATE($F$3,2,1),资金台帐!$N$6:$N$6005,"<"&DATE($F$3,2+1,1))-SUMIFS(资金台帐!$AB$6:$AB$6005,资金台帐!$T$6:$T$6005,$Q27,资金台帐!$U$6:$U$6005,"变动成本",资金台帐!$O$6:$O$6005,IF($C$3="全部","?*",$C$3),资金台帐!$N$6:$N$6005,">="&DATE($F$3,2,1),资金台帐!$N$6:$N$6005,"<"&DATE($F$3,2+1,1)),2) -> 0 | E27: =ROUND(SUMIFS(资金台帐!$AC$6:$AC$6005,资金台帐!$T$6:$T$6005,$Q27,资金台帐!$U$6:$U$6005,"变动成本",资金台帐!$O$6:$O$6005,IF($C$3="全部","?*",$C$3),资金台帐!$N$6:$N$6005,">="&DATE($F$3,3,1),资金台帐!$N$6:$N$6005,"<"&DATE($F$3,3+1,1))-SUMIFS(资金台帐!$AB$6:$AB$6005,资金台帐!$T$6:$T$6005,$Q27,资金台帐!$U$6:$U$6005,"变动成本",资金台帐!$O$6:$O$6005,IF($C$3="全部","?*",$C$3),资金台帐!$N$6:$N$6005,">="&DATE($F$3,3,1),资金台帐!$N$6:$N$6005,"<"&DATE($F$3,3+1,1)),2) -> 0 | F27: =ROUND(SUMIFS(资金台帐!$AC$6:$AC$6005,资金台帐!$T$6:$T$6005,$Q27,资金台帐!$U$6:$U$6005,"变动成本",资金台帐!$O$6:$O$6005,IF($C$3="全部","?*",$C$3),资金台帐!$N$6:$N$6005,">="&DATE($F$3,4,1),资金台帐!$N$6:$N$6005,"<"&DATE($F$3,4+1,1))-SUMIFS(资金台帐!$AB$6:$AB$6005,资金台帐!$T$6:$T$6005,$Q27,资金台帐!$U$6:$U$6005,"变动成本",资金台帐!$O$6:$O$6005,IF($C$3="全部","?*",$C$3),资金台帐!$N$6:$N$6005,">="&DATE($F$3,4,1),资金台帐!$N$6:$N$6005,"<"&DATE($F$3,4+1,1)),2) -> 0 | G27: =ROUND(SUMIFS(资金台帐!$AC$6:$AC$6005,资金台帐!$T$6:$T$6005,$Q27,资金台帐!$U$6:$U$6005,"变动成本",资金台帐!$O$6:$O$6005,IF($C$3="全部","?*",$C$3),资金台帐!$N$6:$N$6005,">="&DATE($F$3,5,1),资金台帐!$N$6:$N$6005,"<"&DATE($F$3,5+1,1))-SUMIFS(资金台帐!$AB$6:$AB$6005,资金台帐!$T$6:$T$6005,$Q27,资金台帐!$U$6:$U$6005,"变动成本",资金台帐!$O$6:$O$6005,IF($C$3="全部","?*",$C$3),资金台帐!$N$6:$N$6005,">="&DATE($F$3,5,1),资金台帐!$N$6:$N$6005,"<"&DATE($F$3,5+1,1)),2) -> 0 | H27: =ROUND(SUMIFS(资金台帐!$AC$6:$AC$6005,资金台帐!$T$6:$T$6005,$Q27,资金台帐!$U$6:$U$6005,"变动成本",资金台帐!$O$6:$O$6005,IF($C$3="全部","?*",$C$3),资金台帐!$N$6:$N$6005,">="&DATE($F$3,6,1),资金台帐!$N$6:$N$6005,"<"&DATE($F$3,6+1,1))-SUMIFS(资金台帐!$AB$6:$AB$6005,资金台帐!$T$6:$T$6005,$Q27,资金台帐!$U$6:$U$6005,"变动成本",资金台帐!$O$6:$O$6005,IF($C$3="全部","?*",$C$3),资金台帐!$N$6:$N$6005,">="&DATE($F$3,6,1),资金台帐!$N$6:$N$6005,"<"&DATE($F$3,6+1,1)),2) -> 0 | I27: =ROUND(SUMIFS(资金台帐!$AC$6:$AC$6005,资金台帐!$T$6:$T$6005,$Q27,资金台帐!$U$6:$U$6005,"变动成本",资金台帐!$O$6:$O$6005,IF($C$3="全部","?*",$C$3),资金台帐!$N$6:$N$6005,">="&DATE($F$3,7,1),资金台帐!$N$6:$N$6005,"<"&DATE($F$3,7+1,1))-SUMIFS(资金台帐!$AB$6:$AB$6005,资金台帐!$T$6:$T$6005,$Q27,资金台帐!$U$6:$U$6005,"变动成本",资金台帐!$O$6:$O$6005,IF($C$3="全部","?*",$C$3),资金台帐!$N$6:$N$6005,">="&DATE($F$3,7,1),资金台帐!$N$6:$N$6005,"<"&DATE($F$3,7+1,1)),2) -> 0 | J27: =ROUND(SUMIFS(资金台帐!$AC$6:$AC$6005,资金台帐!$T$6:$T$6005,$Q27,资金台帐!$U$6:$U$6005,"变动成本",资金台帐!$O$6:$O$6005,IF($C$3="全部","?*",$C$3),资金台帐!$N$6:$N$6005,">="&DATE($F$3,8,1),资金台帐!$N$6:$N$6005,"<"&DATE($F$3,8+1,1))-SUMIFS(资金台帐!$AB$6:$AB$6005,资金台帐!$T$6:$T$6005,$Q27,资金台帐!$U$6:$U$6005,"变动成本",资金台帐!$O$6:$O$6005,IF($C$3="全部","?*",$C$3),资金台帐!$N$6:$N$6005,">="&DATE($F$3,8,1),资金台帐!$N$6:$N$6005,"<"&DATE($F$3,8+1,1)),2) -> 0 | K27: =ROUND(SUMIFS(资金台帐!$AC$6:$AC$6005,资金台帐!$T$6:$T$6005,$Q27,资金台帐!$U$6:$U$6005,"变动成本",资金台帐!$O$6:$O$6005,IF($C$3="全部","?*",$C$3),资金台帐!$N$6:$N$6005,">="&DATE($F$3,9,1),资金台帐!$N$6:$N$6005,"<"&DATE($F$3,9+1,1))-SUMIFS(资金台帐!$AB$6:$AB$6005,资金台帐!$T$6:$T$6005,$Q27,资金台帐!$U$6:$U$6005,"变动成本",资金台帐!$O$6:$O$6005,IF($C$3="全部","?*",$C$3),资金台帐!$N$6:$N$6005,">="&DATE($F$3,9,1),资金台帐!$N$6:$N$6005,"<"&DATE($F$3,9+1,1)),2) -> 0 | L27: =ROUND(SUMIFS(资金台帐!$AC$6:$AC$6005,资金台帐!$T$6:$T$6005,$Q27,资金台帐!$U$6:$U$6005,"变动成本",资金台帐!$O$6:$O$6005,IF($C$3="全部","?*",$C$3),资金台帐!$N$6:$N$6005,">="&DATE($F$3,10,1),资金台帐!$N$6:$N$6005,"<"&DATE($F$3,10+1,1))-SUMIFS(资金台帐!$AB$6:$AB$6005,资金台帐!$T$6:$T$6005,$Q27,资金台帐!$U$6:$U$6005,"变动成本",资金台帐!$O$6:$O$6005,IF($C$3="全部","?*",$C$3),资金台帐!$N$6:$N$6005,">="&DATE($F$3,10,1),资金台帐!$N$6:$N$6005,"<"&DATE($F$3,10+1,1)),2) -> 0 | M27: =ROUND(SUMIFS(资金台帐!$AC$6:$AC$6005,资金台帐!$T$6:$T$6005,$Q27,资金台帐!$U$6:$U$6005,"变动成本",资金台帐!$O$6:$O$6005,IF($C$3="全部","?*",$C$3),资金台帐!$N$6:$N$6005,">="&DATE($F$3,11,1),资金台帐!$N$6:$N$6005,"<"&DATE($F$3,11+1,1))-SUMIFS(资金台帐!$AB$6:$AB$6005,资金台帐!$T$6:$T$6005,$Q27,资金台帐!$U$6:$U$6005,"变动成本",资金台帐!$O$6:$O$6005,IF($C$3="全部","?*",$C$3),资金台帐!$N$6:$N$6005,">="&DATE($F$3,11,1),资金台帐!$N$6:$N$6005,"<"&DATE($F$3,11+1,1)),2) -> 0 | N27: =ROUND(SUMIFS(资金台帐!$AC$6:$AC$6005,资金台帐!$T$6:$T$6005,$Q27,资金台帐!$U$6:$U$6005,"变动成本",资金台帐!$O$6:$O$6005,IF($C$3="全部","?*",$C$3),资金台帐!$N$6:$N$6005,">="&DATE($F$3,12,1),资金台帐!$N$6:$N$6005,"<"&DATE($F$3,12+1,1))-SUMIFS(资金台帐!$AB$6:$AB$6005,资金台帐!$T$6:$T$6005,$Q27,资金台帐!$U$6:$U$6005,"变动成本",资金台帐!$O$6:$O$6005,IF($C$3="全部","?*",$C$3),资金台帐!$N$6:$N$6005,">="&DATE($F$3,12,1),资金台帐!$N$6:$N$6005,"<"&DATE($F$3,12+1,1)),2) -> 0 | O27: =ROUND(SUM(C27:N27),2) -> 0 | P27: =IF(N($O$16)=0,"",O27/$O$16) -> 0 | Q27: =基础资料!$U$26&"" -> 汽车费用
B28: =IF(基础资料!$W$27="",基础资料!$U$27&"",基础资料!$W$27&"") -> 交际支出 | C28: =ROUND(SUMIFS(资金台帐!$AC$6:$AC$6005,资金台帐!$T$6:$T$6005,$Q28,资金台帐!$U$6:$U$6005,"变动成本",资金台帐!$O$6:$O$6005,IF($C$3="全部","?*",$C$3),资金台帐!$N$6:$N$6005,">="&DATE($F$3,1,1),资金台帐!$N$6:$N$6005,"<"&DATE($F$3,1+1,1))-SUMIFS(资金台帐!$AB$6:$AB$6005,资金台帐!$T$6:$T$6005,$Q28,资金台帐!$U$6:$U$6005,"变动成本",资金台帐!$O$6:$O$6005,IF($C$3="全部","?*",$C$3),资金台帐!$N$6:$N$6005,">="&DATE($F$3,1,1),资金台帐!$N$6:$N$6005,"<"&DATE($F$3,1+1,1)),2) -> 0 | D28: =ROUND(SUMIFS(资金台帐!$AC$6:$AC$6005,资金台帐!$T$6:$T$6005,$Q28,资金台帐!$U$6:$U$6005,"变动成本",资金台帐!$O$6:$O$6005,IF($C$3="全部","?*",$C$3),资金台帐!$N$6:$N$6005,">="&DATE($F$3,2,1),资金台帐!$N$6:$N$6005,"<"&DATE($F$3,2+1,1))-SUMIFS(资金台帐!$AB$6:$AB$6005,资金台帐!$T$6:$T$6005,$Q28,资金台帐!$U$6:$U$6005,"变动成本",资金台帐!$O$6:$O$6005,IF($C$3="全部","?*",$C$3),资金台帐!$N$6:$N$6005,">="&DATE($F$3,2,1),资金台帐!$N$6:$N$6005,"<"&DATE($F$3,2+1,1)),2) -> 0 | E28: =ROUND(SUMIFS(资金台帐!$AC$6:$AC$6005,资金台帐!$T$6:$T$6005,$Q28,资金台帐!$U$6:$U$6005,"变动成本",资金台帐!$O$6:$O$6005,IF($C$3="全部","?*",$C$3),资金台帐!$N$6:$N$6005,">="&DATE($F$3,3,1),资金台帐!$N$6:$N$6005,"<"&DATE($F$3,3+1,1))-SUMIFS(资金台帐!$AB$6:$AB$6005,资金台帐!$T$6:$T$6005,$Q28,资金台帐!$U$6:$U$6005,"变动成本",资金台帐!$O$6:$O$6005,IF($C$3="全部","?*",$C$3),资金台帐!$N$6:$N$6005,">="&DATE($F$3,3,1),资金台帐!$N$6:$N$6005,"<"&DATE($F$3,3+1,1)),2) -> 0 | F28: =ROUND(SUMIFS(资金台帐!$AC$6:$AC$6005,资金台帐!$T$6:$T$6005,$Q28,资金台帐!$U$6:$U$6005,"变动成本",资金台帐!$O$6:$O$6005,IF($C$3="全部","?*",$C$3),资金台帐!$N$6:$N$6005,">="&DATE($F$3,4,1),资金台帐!$N$6:$N$6005,"<"&DATE($F$3,4+1,1))-SUMIFS(资金台帐!$AB$6:$AB$6005,资金台帐!$T$6:$T$6005,$Q28,资金台帐!$U$6:$U$6005,"变动成本",资金台帐!$O$6:$O$6005,IF($C$3="全部","?*",$C$3),资金台帐!$N$6:$N$6005,">="&DATE($F$3,4,1),资金台帐!$N$6:$N$6005,"<"&DATE($F$3,4+1,1)),2) -> 0 | G28: =ROUND(SUMIFS(资金台帐!$AC$6:$AC$6005,资金台帐!$T$6:$T$6005,$Q28,资金台帐!$U$6:$U$6005,"变动成本",资金台帐!$O$6:$O$6005,IF($C$3="全部","?*",$C$3),资金台帐!$N$6:$N$6005,">="&DATE($F$3,5,1),资金台帐!$N$6:$N$6005,"<"&DATE($F$3,5+1,1))-SUMIFS(资金台帐!$AB$6:$AB$6005,资金台帐!$T$6:$T$6005,$Q28,资金台帐!$U$6:$U$6005,"变动成本",资金台帐!$O$6:$O$6005,IF($C$3="全部","?*",$C$3),资金台帐!$N$6:$N$6005,">="&DATE($F$3,5,1),资金台帐!$N$6:$N$6005,"<"&DATE($F$3,5+1,1)),2) -> 0 | H28: =ROUND(SUMIFS(资金台帐!$AC$6:$AC$6005,资金台帐!$T$6:$T$6005,$Q28,资金台帐!$U$6:$U$6005,"变动成本",资金台帐!$O$6:$O$6005,IF($C$3="全部","?*",$C$3),资金台帐!$N$6:$N$6005,">="&DATE($F$3,6,1),资金台帐!$N$6:$N$6005,"<"&DATE($F$3,6+1,1))-SUMIFS(资金台帐!$AB$6:$AB$6005,资金台帐!$T$6:$T$6005,$Q28,资金台帐!$U$6:$U$6005,"变动成本",资金台帐!$O$6:$O$6005,IF($C$3="全部","?*",$C$3),资金台帐!$N$6:$N$6005,">="&DATE($F$3,6,1),资金台帐!$N$6:$N$6005,"<"&DATE($F$3,6+1,1)),2) -> 0 | I28: =ROUND(SUMIFS(资金台帐!$AC$6:$AC$6005,资金台帐!$T$6:$T$6005,$Q28,资金台帐!$U$6:$U$6005,"变动成本",资金台帐!$O$6:$O$6005,IF($C$3="全部","?*",$C$3),资金台帐!$N$6:$N$6005,">="&DATE($F$3,7,1),资金台帐!$N$6:$N$6005,"<"&DATE($F$3,7+1,1))-SUMIFS(资金台帐!$AB$6:$AB$6005,资金台帐!$T$6:$T$6005,$Q28,资金台帐!$U$6:$U$6005,"变动成本",资金台帐!$O$6:$O$6005,IF($C$3="全部","?*",$C$3),资金台帐!$N$6:$N$6005,">="&DATE($F$3,7,1),资金台帐!$N$6:$N$6005,"<"&DATE($F$3,7+1,1)),2) -> 0 | J28: =ROUND(SUMIFS(资金台帐!$AC$6:$AC$6005,资金台帐!$T$6:$T$6005,$Q28,资金台帐!$U$6:$U$6005,"变动成本",资金台帐!$O$6:$O$6005,IF($C$3="全部","?*",$C$3),资金台帐!$N$6:$N$6005,">="&DATE($F$3,8,1),资金台帐!$N$6:$N$6005,"<"&DATE($F$3,8+1,1))-SUMIFS(资金台帐!$AB$6:$AB$6005,资金台帐!$T$6:$T$6005,$Q28,资金台帐!$U$6:$U$6005,"变动成本",资金台帐!$O$6:$O$6005,IF($C$3="全部","?*",$C$3),资金台帐!$N$6:$N$6005,">="&DATE($F$3,8,1),资金台帐!$N$6:$N$6005,"<"&DATE($F$3,8+1,1)),2) -> 0 | K28: =ROUND(SUMIFS(资金台帐!$AC$6:$AC$6005,资金台帐!$T$6:$T$6005,$Q28,资金台帐!$U$6:$U$6005,"变动成本",资金台帐!$O$6:$O$6005,IF($C$3="全部","?*",$C$3),资金台帐!$N$6:$N$6005,">="&DATE($F$3,9,1),资金台帐!$N$6:$N$6005,"<"&DATE($F$3,9+1,1))-SUMIFS(资金台帐!$AB$6:$AB$6005,资金台帐!$T$6:$T$6005,$Q28,资金台帐!$U$6:$U$6005,"变动成本",资金台帐!$O$6:$O$6005,IF($C$3="全部","?*",$C$3),资金台帐!$N$6:$N$6005,">="&DATE($F$3,9,1),资金台帐!$N$6:$N$6005,"<"&DATE($F$3,9+1,1)),2) -> 0 | L28: =ROUND(SUMIFS(资金台帐!$AC$6:$AC$6005,资金台帐!$T$6:$T$6005,$Q28,资金台帐!$U$6:$U$6005,"变动成本",资金台帐!$O$6:$O$6005,IF($C$3="全部","?*",$C$3),资金台帐!$N$6:$N$6005,">="&DATE($F$3,10,1),资金台帐!$N$6:$N$6005,"<"&DATE($F$3,10+1,1))-SUMIFS(资金台帐!$AB$6:$AB$6005,资金台帐!$T$6:$T$6005,$Q28,资金台帐!$U$6:$U$6005,"变动成本",资金台帐!$O$6:$O$6005,IF($C$3="全部","?*",$C$3),资金台帐!$N$6:$N$6005,">="&DATE($F$3,10,1),资金台帐!$N$6:$N$6005,"<"&DATE($F$3,10+1,1)),2) -> 0 | M28: =ROUND(SUMIFS(资金台帐!$AC$6:$AC$6005,资金台帐!$T$6:$T$6005,$Q28,资金台帐!$U$6:$U$6005,"变动成本",资金台帐!$O$6:$O$6005,IF($C$3="全部","?*",$C$3),资金台帐!$N$6:$N$6005,">="&DATE($F$3,11,1),资金台帐!$N$6:$N$6005,"<"&DATE($F$3,11+1,1))-SUMIFS(资金台帐!$AB$6:$AB$6005,资金台帐!$T$6:$T$6005,$Q28,资金台帐!$U$6:$U$6005,"变动成本",资金台帐!$O$6:$O$6005,IF($C$3="全部","?*",$C$3),资金台帐!$N$6:$N$6005,">="&DATE($F$3,11,1),资金台帐!$N$6:$N$6005,"<"&DATE($F$3,11+1,1)),2) -> 0 | N28: =ROUND(SUMIFS(资金台帐!$AC$6:$AC$6005,资金台帐!$T$6:$T$6005,$Q28,资金台帐!$U$6:$U$6005,"变动成本",资金台帐!$O$6:$O$6005,IF($C$3="全部","?*",$C$3),资金台帐!$N$6:$N$6005,">="&DATE($F$3,12,1),资金台帐!$N$6:$N$6005,"<"&DATE($F$3,12+1,1))-SUMIFS(资金台帐!$AB$6:$AB$6005,资金台帐!$T$6:$T$6005,$Q28,资金台帐!$U$6:$U$6005,"变动成本",资金台帐!$O$6:$O$6005,IF($C$3="全部","?*",$C$3),资金台帐!$N$6:$N$6005,">="&DATE($F$3,12,1),资金台帐!$N$6:$N$6005,"<"&DATE($F$3,12+1,1)),2) -> 0 | O28: =ROUND(SUM(C28:N28),2) -> 0 | P28: =IF(N($O$16)=0,"",O28/$O$16) -> 0 | Q28: =基础资料!$U$27&"" -> 交际支出
B29: =IF(基础资料!$W$28="",基础资料!$U$28&"",基础资料!$W$28&"") -> 佣金支出 | C29: =ROUND(SUMIFS(资金台帐!$AC$6:$AC$6005,资金台帐!$T$6:$T$6005,$Q29,资金台帐!$U$6:$U$6005,"变动成本",资金台帐!$O$6:$O$6005,IF($C$3="全部","?*",$C$3),资金台帐!$N$6:$N$6005,">="&DATE($F$3,1,1),资金台帐!$N$6:$N$6005,"<"&DATE($F$3,1+1,1))-SUMIFS(资金台帐!$AB$6:$AB$6005,资金台帐!$T$6:$T$6005,$Q29,资金台帐!$U$6:$U$6005,"变动成本",资金台帐!$O$6:$O$6005,IF($C$3="全部","?*",$C$3),资金台帐!$N$6:$N$6005,">="&DATE($F$3,1,1),资金台帐!$N$6:$N$6005,"<"&DATE($F$3,1+1,1)),2) -> 0 | D29: =ROUND(SUMIFS(资金台帐!$AC$6:$AC$6005,资金台帐!$T$6:$T$6005,$Q29,资金台帐!$U$6:$U$6005,"变动成本",资金台帐!$O$6:$O$6005,IF($C$3="全部","?*",$C$3),资金台帐!$N$6:$N$6005,">="&DATE($F$3,2,1),资金台帐!$N$6:$N$6005,"<"&DATE($F$3,2+1,1))-SUMIFS(资金台帐!$AB$6:$AB$6005,资金台帐!$T$6:$T$6005,$Q29,资金台帐!$U$6:$U$6005,"变动成本",资金台帐!$O$6:$O$6005,IF($C$3="全部","?*",$C$3),资金台帐!$N$6:$N$6005,">="&DATE($F$3,2,1),资金台帐!$N$6:$N$6005,"<"&DATE($F$3,2+1,1)),2) -> 0 | E29: =ROUND(SUMIFS(资金台帐!$AC$6:$AC$6005,资金台帐!$T$6:$T$6005,$Q29,资金台帐!$U$6:$U$6005,"变动成本",资金台帐!$O$6:$O$6005,IF($C$3="全部","?*",$C$3),资金台帐!$N$6:$N$6005,">="&DATE($F$3,3,1),资金台帐!$N$6:$N$6005,"<"&DATE($F$3,3+1,1))-SUMIFS(资金台帐!$AB$6:$AB$6005,资金台帐!$T$6:$T$6005,$Q29,资金台帐!$U$6:$U$6005,"变动成本",资金台帐!$O$6:$O$6005,IF($C$3="全部","?*",$C$3),资金台帐!$N$6:$N$6005,">="&DATE($F$3,3,1),资金台帐!$N$6:$N$6005,"<"&DATE($F$3,3+1,1)),2) -> 0 | F29: =ROUND(SUMIFS(资金台帐!$AC$6:$AC$6005,资金台帐!$T$6:$T$6005,$Q29,资金台帐!$U$6:$U$6005,"变动成本",资金台帐!$O$6:$O$6005,IF($C$3="全部","?*",$C$3),资金台帐!$N$6:$N$6005,">="&DATE($F$3,4,1),资金台帐!$N$6:$N$6005,"<"&DATE($F$3,4+1,1))-SUMIFS(资金台帐!$AB$6:$AB$6005,资金台帐!$T$6:$T$6005,$Q29,资金台帐!$U$6:$U$6005,"变动成本",资金台帐!$O$6:$O$6005,IF($C$3="全部","?*",$C$3),资金台帐!$N$6:$N$6005,">="&DATE($F$3,4,1),资金台帐!$N$6:$N$6005,"<"&DATE($F$3,4+1,1)),2) -> 0 | G29: =ROUND(SUMIFS(资金台帐!$AC$6:$AC$6005,资金台帐!$T$6:$T$6005,$Q29,资金台帐!$U$6:$U$6005,"变动成本",资金台帐!$O$6:$O$6005,IF($C$3="全部","?*",$C$3),资金台帐!$N$6:$N$6005,">="&DATE($F$3,5,1),资金台帐!$N$6:$N$6005,"<"&DATE($F$3,5+1,1))-SUMIFS(资金台帐!$AB$6:$AB$6005,资金台帐!$T$6:$T$6005,$Q29,资金台帐!$U$6:$U$6005,"变动成本",资金台帐!$O$6:$O$6005,IF($C$3="全部","?*",$C$3),资金台帐!$N$6:$N$6005,">="&DATE($F$3,5,1),资金台帐!$N$6:$N$6005,"<"&DATE($F$3,5+1,1)),2) -> 0 | H29: =ROUND(SUMIFS(资金台帐!$AC$6:$AC$6005,资金台帐!$T$6:$T$6005,$Q29,资金台帐!$U$6:$U$6005,"变动成本",资金台帐!$O$6:$O$6005,IF($C$3="全部","?*",$C$3),资金台帐!$N$6:$N$6005,">="&DATE($F$3,6,1),资金台帐!$N$6:$N$6005,"<"&DATE($F$3,6+1,1))-SUMIFS(资金台帐!$AB$6:$AB$6005,资金台帐!$T$6:$T$6005,$Q29,资金台帐!$U$6:$U$6005,"变动成本",资金台帐!$O$6:$O$6005,IF($C$3="全部","?*",$C$3),资金台帐!$N$6:$N$6005,">="&DATE($F$3,6,1),资金台帐!$N$6:$N$6005,"<"&DATE($F$3,6+1,1)),2) -> 0 | I29: =ROUND(SUMIFS(资金台帐!$AC$6:$AC$6005,资金台帐!$T$6:$T$6005,$Q29,资金台帐!$U$6:$U$6005,"变动成本",资金台帐!$O$6:$O$6005,IF($C$3="全部","?*",$C$3),资金台帐!$N$6:$N$6005,">="&DATE($F$3,7,1),资金台帐!$N$6:$N$6005,"<"&DATE($F$3,7+1,1))-SUMIFS(资金台帐!$AB$6:$AB$6005,资金台帐!$T$6:$T$6005,$Q29,资金台帐!$U$6:$U$6005,"变动成本",资金台帐!$O$6:$O$6005,IF($C$3="全部","?*",$C$3),资金台帐!$N$6:$N$6005,">="&DATE($F$3,7,1),资金台帐!$N$6:$N$6005,"<"&DATE($F$3,7+1,1)),2) -> 0 | J29: =ROUND(SUMIFS(资金台帐!$AC$6:$AC$6005,资金台帐!$T$6:$T$6005,$Q29,资金台帐!$U$6:$U$6005,"变动成本",资金台帐!$O$6:$O$6005,IF($C$3="全部","?*",$C$3),资金台帐!$N$6:$N$6005,">="&DATE($F$3,8,1),资金台帐!$N$6:$N$6005,"<"&DATE($F$3,8+1,1))-SUMIFS(资金台帐!$AB$6:$AB$6005,资金台帐!$T$6:$T$6005,$Q29,资金台帐!$U$6:$U$6005,"变动成本",资金台帐!$O$6:$O$6005,IF($C$3="全部","?*",$C$3),资金台帐!$N$6:$N$6005,">="&DATE($F$3,8,1),资金台帐!$N$6:$N$6005,"<"&DATE($F$3,8+1,1)),2) -> 0 | K29: =ROUND(SUMIFS(资金台帐!$AC$6:$AC$6005,资金台帐!$T$6:$T$6005,$Q29,资金台帐!$U$6:$U$6005,"变动成本",资金台帐!$O$6:$O$6005,IF($C$3="全部","?*",$C$3),资金台帐!$N$6:$N$6005,">="&DATE($F$3,9,1),资金台帐!$N$6:$N$6005,"<"&DATE($F$3,9+1,1))-SUMIFS(资金台帐!$AB$6:$AB$6005,资金台帐!$T$6:$T$6005,$Q29,资金台帐!$U$6:$U$6005,"变动成本",资金台帐!$O$6:$O$6005,IF($C$3="全部","?*",$C$3),资金台帐!$N$6:$N$6005,">="&DATE($F$3,9,1),资金台帐!$N$6:$N$6005,"<"&DATE($F$3,9+1,1)),2) -> 0 | L29: =ROUND(SUMIFS(资金台帐!$AC$6:$AC$6005,资金台帐!$T$6:$T$6005,$Q29,资金台帐!$U$6:$U$6005,"变动成本",资金台帐!$O$6:$O$6005,IF($C$3="全部","?*",$C$3),资金台帐!$N$6:$N$6005,">="&DATE($F$3,10,1),资金台帐!$N$6:$N$6005,"<"&DATE($F$3,10+1,1))-SUMIFS(资金台帐!$AB$6:$AB$6005,资金台帐!$T$6:$T$6005,$Q29,资金台帐!$U$6:$U$6005,"变动成本",资金台帐!$O$6:$O$6005,IF($C$3="全部","?*",$C$3),资金台帐!$N$6:$N$6005,">="&DATE($F$3,10,1),资金台帐!$N$6:$N$6005,"<"&DATE($F$3,10+1,1)),2) -> 0 | M29: =ROUND(SUMIFS(资金台帐!$AC$6:$AC$6005,资金台帐!$T$6:$T$6005,$Q29,资金台帐!$U$6:$U$6005,"变动成本",资金台帐!$O$6:$O$6005,IF($C$3="全部","?*",$C$3),资金台帐!$N$6:$N$6005,">="&DATE($F$3,11,1),资金台帐!$N$6:$N$6005,"<"&DATE($F$3,11+1,1))-SUMIFS(资金台帐!$AB$6:$AB$6005,资金台帐!$T$6:$T$6005,$Q29,资金台帐!$U$6:$U$6005,"变动成本",资金台帐!$O$6:$O$6005,IF($C$3="全部","?*",$C$3),资金台帐!$N$6:$N$6005,">="&DATE($F$3,11,1),资金台帐!$N$6:$N$6005,"<"&DATE($F$3,11+1,1)),2) -> 0 | N29: =ROUND(SUMIFS(资金台帐!$AC$6:$AC$6005,资金台帐!$T$6:$T$6005,$Q29,资金台帐!$U$6:$U$6005,"变动成本",资金台帐!$O$6:$O$6005,IF($C$3="全部","?*",$C$3),资金台帐!$N$6:$N$6005,">="&DATE($F$3,12,1),资金台帐!$N$6:$N$6005,"<"&DATE($F$3,12+1,1))-SUMIFS(资金台帐!$AB$6:$AB$6005,资金台帐!$T$6:$T$6005,$Q29,资金台帐!$U$6:$U$6005,"变动成本",资金台帐!$O$6:$O$6005,IF($C$3="全部","?*",$C$3),资金台帐!$N$6:$N$6005,">="&DATE($F$3,12,1),资金台帐!$N$6:$N$6005,"<"&DATE($F$3,12+1,1)),2) -> 0 | O29: =ROUND(SUM(C29:N29),2) -> 0 | P29: =IF(N($O$16)=0,"",O29/$O$16) -> 0 | Q29: =基础资料!$U$28&"" -> 佣金支出
B30: =IF(基础资料!$W$29="",基础资料!$U$29&"",基础资料!$W$29&"") -> 营销费用 | C30: =ROUND(SUMIFS(资金台帐!$AC$6:$AC$6005,资金台帐!$T$6:$T$6005,$Q30,资金台帐!$U$6:$U$6005,"变动成本",资金台帐!$O$6:$O$6005,IF($C$3="全部","?*",$C$3),资金台帐!$N$6:$N$6005,">="&DATE($F$3,1,1),资金台帐!$N$6:$N$6005,"<"&DATE($F$3,1+1,1))-SUMIFS(资金台帐!$AB$6:$AB$6005,资金台帐!$T$6:$T$6005,$Q30,资金台帐!$U$6:$U$6005,"变动成本",资金台帐!$O$6:$O$6005,IF($C$3="全部","?*",$C$3),资金台帐!$N$6:$N$6005,">="&DATE($F$3,1,1),资金台帐!$N$6:$N$6005,"<"&DATE($F$3,1+1,1)),2) -> 0 | D30: =ROUND(SUMIFS(资金台帐!$AC$6:$AC$6005,资金台帐!$T$6:$T$6005,$Q30,资金台帐!$U$6:$U$6005,"变动成本",资金台帐!$O$6:$O$6005,IF($C$3="全部","?*",$C$3),资金台帐!$N$6:$N$6005,">="&DATE($F$3,2,1),资金台帐!$N$6:$N$6005,"<"&DATE($F$3,2+1,1))-SUMIFS(资金台帐!$AB$6:$AB$6005,资金台帐!$T$6:$T$6005,$Q30,资金台帐!$U$6:$U$6005,"变动成本",资金台帐!$O$6:$O$6005,IF($C$3="全部","?*",$C$3),资金台帐!$N$6:$N$6005,">="&DATE($F$3,2,1),资金台帐!$N$6:$N$6005,"<"&DATE($F$3,2+1,1)),2) -> 0 | E30: =ROUND(SUMIFS(资金台帐!$AC$6:$AC$6005,资金台帐!$T$6:$T$6005,$Q30,资金台帐!$U$6:$U$6005,"变动成本",资金台帐!$O$6:$O$6005,IF($C$3="全部","?*",$C$3),资金台帐!$N$6:$N$6005,">="&DATE($F$3,3,1),资金台帐!$N$6:$N$6005,"<"&DATE($F$3,3+1,1))-SUMIFS(资金台帐!$AB$6:$AB$6005,资金台帐!$T$6:$T$6005,$Q30,资金台帐!$U$6:$U$6005,"变动成本",资金台帐!$O$6:$O$6005,IF($C$3="全部","?*",$C$3),资金台帐!$N$6:$N$6005,">="&DATE($F$3,3,1),资金台帐!$N$6:$N$6005,"<"&DATE($F$3,3+1,1)),2) -> 0 | F30: =ROUND(SUMIFS(资金台帐!$AC$6:$AC$6005,资金台帐!$T$6:$T$6005,$Q30,资金台帐!$U$6:$U$6005,"变动成本",资金台帐!$O$6:$O$6005,IF($C$3="全部","?*",$C$3),资金台帐!$N$6:$N$6005,">="&DATE($F$3,4,1),资金台帐!$N$6:$N$6005,"<"&DATE($F$3,4+1,1))-SUMIFS(资金台帐!$AB$6:$AB$6005,资金台帐!$T$6:$T$6005,$Q30,资金台帐!$U$6:$U$6005,"变动成本",资金台帐!$O$6:$O$6005,IF($C$3="全部","?*",$C$3),资金台帐!$N$6:$N$6005,">="&DATE($F$3,4,1),资金台帐!$N$6:$N$6005,"<"&DATE($F$3,4+1,1)),2) -> 0 | G30: =ROUND(SUMIFS(资金台帐!$AC$6:$AC$6005,资金台帐!$T$6:$T$6005,$Q30,资金台帐!$U$6:$U$6005,"变动成本",资金台帐!$O$6:$O$6005,IF($C$3="全部","?*",$C$3),资金台帐!$N$6:$N$6005,">="&DATE($F$3,5,1),资金台帐!$N$6:$N$6005,"<"&DATE($F$3,5+1,1))-SUMIFS(资金台帐!$AB$6:$AB$6005,资金台帐!$T$6:$T$6005,$Q30,资金台帐!$U$6:$U$6005,"变动成本",资金台帐!$O$6:$O$6005,IF($C$3="全部","?*",$C$3),资金台帐!$N$6:$N$6005,">="&DATE($F$3,5,1),资金台帐!$N$6:$N$6005,"<"&DATE($F$3,5+1,1)),2) -> 0 | H30: =ROUND(SUMIFS(资金台帐!$AC$6:$AC$6005,资金台帐!$T$6:$T$6005,$Q30,资金台帐!$U$6:$U$6005,"变动成本",资金台帐!$O$6:$O$6005,IF($C$3="全部","?*",$C$3),资金台帐!$N$6:$N$6005,">="&DATE($F$3,6,1),资金台帐!$N$6:$N$6005,"<"&DATE($F$3,6+1,1))-SUMIFS(资金台帐!$AB$6:$AB$6005,资金台帐!$T$6:$T$6005,$Q30,资金台帐!$U$6:$U$6005,"变动成本",资金台帐!$O$6:$O$6005,IF($C$3="全部","?*",$C$3),资金台帐!$N$6:$N$6005,">="&DATE($F$3,6,1),资金台帐!$N$6:$N$6005,"<"&DATE($F$3,6+1,1)),2) -> 0 | I30: =ROUND(SUMIFS(资金台帐!$AC$6:$AC$6005,资金台帐!$T$6:$T$6005,$Q30,资金台帐!$U$6:$U$6005,"变动成本",资金台帐!$O$6:$O$6005,IF($C$3="全部","?*",$C$3),资金台帐!$N$6:$N$6005,">="&DATE($F$3,7,1),资金台帐!$N$6:$N$6005,"<"&DATE($F$3,7+1,1))-SUMIFS(资金台帐!$AB$6:$AB$6005,资金台帐!$T$6:$T$6005,$Q30,资金台帐!$U$6:$U$6005,"变动成本",资金台帐!$O$6:$O$6005,IF($C$3="全部","?*",$C$3),资金台帐!$N$6:$N$6005,">="&DATE($F$3,7,1),资金台帐!$N$6:$N$6005,"<"&DATE($F$3,7+1,1)),2) -> 0 | J30: =ROUND(SUMIFS(资金台帐!$AC$6:$AC$6005,资金台帐!$T$6:$T$6005,$Q30,资金台帐!$U$6:$U$6005,"变动成本",资金台帐!$O$6:$O$6005,IF($C$3="全部","?*",$C$3),资金台帐!$N$6:$N$6005,">="&DATE($F$3,8,1),资金台帐!$N$6:$N$6005,"<"&DATE($F$3,8+1,1))-SUMIFS(资金台帐!$AB$6:$AB$6005,资金台帐!$T$6:$T$6005,$Q30,资金台帐!$U$6:$U$6005,"变动成本",资金台帐!$O$6:$O$6005,IF($C$3="全部","?*",$C$3),资金台帐!$N$6:$N$6005,">="&DATE($F$3,8,1),资金台帐!$N$6:$N$6005,"<"&DATE($F$3,8+1,1)),2) -> 0 | K30: =ROUND(SUMIFS(资金台帐!$AC$6:$AC$6005,资金台帐!$T$6:$T$6005,$Q30,资金台帐!$U$6:$U$6005,"变动成本",资金台帐!$O$6:$O$6005,IF($C$3="全部","?*",$C$3),资金台帐!$N$6:$N$6005,">="&DATE($F$3,9,1),资金台帐!$N$6:$N$6005,"<"&DATE($F$3,9+1,1))-SUMIFS(资金台帐!$AB$6:$AB$6005,资金台帐!$T$6:$T$6005,$Q30,资金台帐!$U$6:$U$6005,"变动成本",资金台帐!$O$6:$O$6005,IF($C$3="全部","?*",$C$3),资金台帐!$N$6:$N$6005,">="&DATE($F$3,9,1),资金台帐!$N$6:$N$6005,"<"&DATE($F$3,9+1,1)),2) -> 0 | L30: =ROUND(SUMIFS(资金台帐!$AC$6:$AC$6005,资金台帐!$T$6:$T$6005,$Q30,资金台帐!$U$6:$U$6005,"变动成本",资金台帐!$O$6:$O$6005,IF($C$3="全部","?*",$C$3),资金台帐!$N$6:$N$6005,">="&DATE($F$3,10,1),资金台帐!$N$6:$N$6005,"<"&DATE($F$3,10+1,1))-SUMIFS(资金台帐!$AB$6:$AB$6005,资金台帐!$T$6:$T$6005,$Q30,资金台帐!$U$6:$U$6005,"变动成本",资金台帐!$O$6:$O$6005,IF($C$3="全部","?*",$C$3),资金台帐!$N$6:$N$6005,">="&DATE($F$3,10,1),资金台帐!$N$6:$N$6005,"<"&DATE($F$3,10+1,1)),2) -> 0 | M30: =ROUND(SUMIFS(资金台帐!$AC$6:$AC$6005,资金台帐!$T$6:$T$6005,$Q30,资金台帐!$U$6:$U$6005,"变动成本",资金台帐!$O$6:$O$6005,IF($C$3="全部","?*",$C$3),资金台帐!$N$6:$N$6005,">="&DATE($F$3,11,1),资金台帐!$N$6:$N$6005,"<"&DATE($F$3,11+1,1))-SUMIFS(资金台帐!$AB$6:$AB$6005,资金台帐!$T$6:$T$6005,$Q30,资金台帐!$U$6:$U$6005,"变动成本",资金台帐!$O$6:$O$6005,IF($C$3="全部","?*",$C$3),资金台帐!$N$6:$N$6005,">="&DATE($F$3,11,1),资金台帐!$N$6:$N$6005,"<"&DATE($F$3,11+1,1)),2) -> 0 | N30: =ROUND(SUMIFS(资金台帐!$AC$6:$AC$6005,资金台帐!$T$6:$T$6005,$Q30,资金台帐!$U$6:$U$6005,"变动成本",资金台帐!$O$6:$O$6005,IF($C$3="全部","?*",$C$3),资金台帐!$N$6:$N$6005,">="&DATE($F$3,12,1),资金台帐!$N$6:$N$6005,"<"&DATE($F$3,12+1,1))-SUMIFS(资金台帐!$AB$6:$AB$6005,资金台帐!$T$6:$T$6005,$Q30,资金台帐!$U$6:$U$6005,"变动成本",资金台帐!$O$6:$O$6005,IF($C$3="全部","?*",$C$3),资金台帐!$N$6:$N$6005,">="&DATE($F$3,12,1),资金台帐!$N$6:$N$6005,"<"&DATE($F$3,12+1,1)),2) -> 0 | O30: =ROUND(SUM(C30:N30),2) -> 0 | P30: =IF(N($O$16)=0,"",O30/$O$16) -> 0 | Q30: =基础资料!$U$29&"" -> 营销费用
B31: =IF(基础资料!$W$30="",基础资料!$U$30&"",基础资料!$W$30&"") -> 地址成本 | C31: =ROUND(SUMIFS(资金台帐!$AC$6:$AC$6005,资金台帐!$T$6:$T$6005,$Q31,资金台帐!$U$6:$U$6005,"变动成本",资金台帐!$O$6:$O$6005,IF($C$3="全部","?*",$C$3),资金台帐!$N$6:$N$6005,">="&DATE($F$3,1,1),资金台帐!$N$6:$N$6005,"<"&DATE($F$3,1+1,1))-SUMIFS(资金台帐!$AB$6:$AB$6005,资金台帐!$T$6:$T$6005,$Q31,资金台帐!$U$6:$U$6005,"变动成本",资金台帐!$O$6:$O$6005,IF($C$3="全部","?*",$C$3),资金台帐!$N$6:$N$6005,">="&DATE($F$3,1,1),资金台帐!$N$6:$N$6005,"<"&DATE($F$3,1+1,1)),2) -> 0 | D31: =ROUND(SUMIFS(资金台帐!$AC$6:$AC$6005,资金台帐!$T$6:$T$6005,$Q31,资金台帐!$U$6:$U$6005,"变动成本",资金台帐!$O$6:$O$6005,IF($C$3="全部","?*",$C$3),资金台帐!$N$6:$N$6005,">="&DATE($F$3,2,1),资金台帐!$N$6:$N$6005,"<"&DATE($F$3,2+1,1))-SUMIFS(资金台帐!$AB$6:$AB$6005,资金台帐!$T$6:$T$6005,$Q31,资金台帐!$U$6:$U$6005,"变动成本",资金台帐!$O$6:$O$6005,IF($C$3="全部","?*",$C$3),资金台帐!$N$6:$N$6005,">="&DATE($F$3,2,1),资金台帐!$N$6:$N$6005,"<"&DATE($F$3,2+1,1)),2) -> 0 | E31: =ROUND(SUMIFS(资金台帐!$AC$6:$AC$6005,资金台帐!$T$6:$T$6005,$Q31,资金台帐!$U$6:$U$6005,"变动成本",资金台帐!$O$6:$O$6005,IF($C$3="全部","?*",$C$3),资金台帐!$N$6:$N$6005,">="&DATE($F$3,3,1),资金台帐!$N$6:$N$6005,"<"&DATE($F$3,3+1,1))-SUMIFS(资金台帐!$AB$6:$AB$6005,资金台帐!$T$6:$T$6005,$Q31,资金台帐!$U$6:$U$6005,"变动成本",资金台帐!$O$6:$O$6005,IF($C$3="全部","?*",$C$3),资金台帐!$N$6:$N$6005,">="&DATE($F$3,3,1),资金台帐!$N$6:$N$6005,"<"&DATE($F$3,3+1,1)),2) -> 0 | F31: =ROUND(SUMIFS(资金台帐!$AC$6:$AC$6005,资金台帐!$T$6:$T$6005,$Q31,资金台帐!$U$6:$U$6005,"变动成本",资金台帐!$O$6:$O$6005,IF($C$3="全部","?*",$C$3),资金台帐!$N$6:$N$6005,">="&DATE($F$3,4,1),资金台帐!$N$6:$N$6005,"<"&DATE($F$3,4+1,1))-SUMIFS(资金台帐!$AB$6:$AB$6005,资金台帐!$T$6:$T$6005,$Q31,资金台帐!$U$6:$U$6005,"变动成本",资金台帐!$O$6:$O$6005,IF($C$3="全部","?*",$C$3),资金台帐!$N$6:$N$6005,">="&DATE($F$3,4,1),资金台帐!$N$6:$N$6005,"<"&DATE($F$3,4+1,1)),2) -> 0 | G31: =ROUND(SUMIFS(资金台帐!$AC$6:$AC$6005,资金台帐!$T$6:$T$6005,$Q31,资金台帐!$U$6:$U$6005,"变动成本",资金台帐!$O$6:$O$6005,IF($C$3="全部","?*",$C$3),资金台帐!$N$6:$N$6005,">="&DATE($F$3,5,1),资金台帐!$N$6:$N$6005,"<"&DATE($F$3,5+1,1))-SUMIFS(资金台帐!$AB$6:$AB$6005,资金台帐!$T$6:$T$6005,$Q31,资金台帐!$U$6:$U$6005,"变动成本",资金台帐!$O$6:$O$6005,IF($C$3="全部","?*",$C$3),资金台帐!$N$6:$N$6005,">="&DATE($F$3,5,1),资金台帐!$N$6:$N$6005,"<"&DATE($F$3,5+1,1)),2) -> 0 | H31: =ROUND(SUMIFS(资金台帐!$AC$6:$AC$6005,资金台帐!$T$6:$T$6005,$Q31,资金台帐!$U$6:$U$6005,"变动成本",资金台帐!$O$6:$O$6005,IF($C$3="全部","?*",$C$3),资金台帐!$N$6:$N$6005,">="&DATE($F$3,6,1),资金台帐!$N$6:$N$6005,"<"&DATE($F$3,6+1,1))-SUMIFS(资金台帐!$AB$6:$AB$6005,资金台帐!$T$6:$T$6005,$Q31,资金台帐!$U$6:$U$6005,"变动成本",资金台帐!$O$6:$O$6005,IF($C$3="全部","?*",$C$3),资金台帐!$N$6:$N$6005,">="&DATE($F$3,6,1),资金台帐!$N$6:$N$6005,"<"&DATE($F$3,6+1,1)),2) -> 0 | I31: =ROUND(SUMIFS(资金台帐!$AC$6:$AC$6005,资金台帐!$T$6:$T$6005,$Q31,资金台帐!$U$6:$U$6005,"变动成本",资金台帐!$O$6:$O$6005,IF($C$3="全部","?*",$C$3),资金台帐!$N$6:$N$6005,">="&DATE($F$3,7,1),资金台帐!$N$6:$N$6005,"<"&DATE($F$3,7+1,1))-SUMIFS(资金台帐!$AB$6:$AB$6005,资金台帐!$T$6:$T$6005,$Q31,资金台帐!$U$6:$U$6005,"变动成本",资金台帐!$O$6:$O$6005,IF($C$3="全部","?*",$C$3),资金台帐!$N$6:$N$6005,">="&DATE($F$3,7,1),资金台帐!$N$6:$N$6005,"<"&DATE($F$3,7+1,1)),2) -> 0 | J31: =ROUND(SUMIFS(资金台帐!$AC$6:$AC$6005,资金台帐!$T$6:$T$6005,$Q31,资金台帐!$U$6:$U$6005,"变动成本",资金台帐!$O$6:$O$6005,IF($C$3="全部","?*",$C$3),资金台帐!$N$6:$N$6005,">="&DATE($F$3,8,1),资金台帐!$N$6:$N$6005,"<"&DATE($F$3,8+1,1))-SUMIFS(资金台帐!$AB$6:$AB$6005,资金台帐!$T$6:$T$6005,$Q31,资金台帐!$U$6:$U$6005,"变动成本",资金台帐!$O$6:$O$6005,IF($C$3="全部","?*",$C$3),资金台帐!$N$6:$N$6005,">="&DATE($F$3,8,1),资金台帐!$N$6:$N$6005,"<"&DATE($F$3,8+1,1)),2) -> 0 | K31: =ROUND(SUMIFS(资金台帐!$AC$6:$AC$6005,资金台帐!$T$6:$T$6005,$Q31,资金台帐!$U$6:$U$6005,"变动成本",资金台帐!$O$6:$O$6005,IF($C$3="全部","?*",$C$3),资金台帐!$N$6:$N$6005,">="&DATE($F$3,9,1),资金台帐!$N$6:$N$6005,"<"&DATE($F$3,9+1,1))-SUMIFS(资金台帐!$AB$6:$AB$6005,资金台帐!$T$6:$T$6005,$Q31,资金台帐!$U$6:$U$6005,"变动成本",资金台帐!$O$6:$O$6005,IF($C$3="全部","?*",$C$3),资金台帐!$N$6:$N$6005,">="&DATE($F$3,9,1),资金台帐!$N$6:$N$6005,"<"&DATE($F$3,9+1,1)),2) -> 0 | L31: =ROUND(SUMIFS(资金台帐!$AC$6:$AC$6005,资金台帐!$T$6:$T$6005,$Q31,资金台帐!$U$6:$U$6005,"变动成本",资金台帐!$O$6:$O$6005,IF($C$3="全部","?*",$C$3),资金台帐!$N$6:$N$6005,">="&DATE($F$3,10,1),资金台帐!$N$6:$N$6005,"<"&DATE($F$3,10+1,1))-SUMIFS(资金台帐!$AB$6:$AB$6005,资金台帐!$T$6:$T$6005,$Q31,资金台帐!$U$6:$U$6005,"变动成本",资金台帐!$O$6:$O$6005,IF($C$3="全部","?*",$C$3),资金台帐!$N$6:$N$6005,">="&DATE($F$3,10,1),资金台帐!$N$6:$N$6005,"<"&DATE($F$3,10+1,1)),2) -> 0 | M31: =ROUND(SUMIFS(资金台帐!$AC$6:$AC$6005,资金台帐!$T$6:$T$6005,$Q31,资金台帐!$U$6:$U$6005,"变动成本",资金台帐!$O$6:$O$6005,IF($C$3="全部","?*",$C$3),资金台帐!$N$6:$N$6005,">="&DATE($F$3,11,1),资金台帐!$N$6:$N$6005,"<"&DATE($F$3,11+1,1))-SUMIFS(资金台帐!$AB$6:$AB$6005,资金台帐!$T$6:$T$6005,$Q31,资金台帐!$U$6:$U$6005,"变动成本",资金台帐!$O$6:$O$6005,IF($C$3="全部","?*",$C$3),资金台帐!$N$6:$N$6005,">="&DATE($F$3,11,1),资金台帐!$N$6:$N$6005,"<"&DATE($F$3,11+1,1)),2) -> 0 | N31: =ROUND(SUMIFS(资金台帐!$AC$6:$AC$6005,资金台帐!$T$6:$T$6005,$Q31,资金台帐!$U$6:$U$6005,"变动成本",资金台帐!$O$6:$O$6005,IF($C$3="全部","?*",$C$3),资金台帐!$N$6:$N$6005,">="&DATE($F$3,12,1),资金台帐!$N$6:$N$6005,"<"&DATE($F$3,12+1,1))-SUMIFS(资金台帐!$AB$6:$AB$6005,资金台帐!$T$6:$T$6005,$Q31,资金台帐!$U$6:$U$6005,"变动成本",资金台帐!$O$6:$O$6005,IF($C$3="全部","?*",$C$3),资金台帐!$N$6:$N$6005,">="&DATE($F$3,12,1),资金台帐!$N$6:$N$6005,"<"&DATE($F$3,12+1,1)),2) -> 0 | O31: =ROUND(SUM(C31:N31),2) -> 0 | P31: =IF(N($O$16)=0,"",O31/$O$16) -> 0 | Q31: =基础资料!$U$30&"" -> 地址成本
B32: =IF(基础资料!$W$31="",基础资料!$U$31&"",基础资料!$W$31&"") -> 项目成本 | C32: =ROUND(SUMIFS(资金台帐!$AC$6:$AC$6005,资金台帐!$T$6:$T$6005,$Q32,资金台帐!$U$6:$U$6005,"变动成本",资金台帐!$O$6:$O$6005,IF($C$3="全部","?*",$C$3),资金台帐!$N$6:$N$6005,">="&DATE($F$3,1,1),资金台帐!$N$6:$N$6005,"<"&DATE($F$3,1+1,1))-SUMIFS(资金台帐!$AB$6:$AB$6005,资金台帐!$T$6:$T$6005,$Q32,资金台帐!$U$6:$U$6005,"变动成本",资金台帐!$O$6:$O$6005,IF($C$3="全部","?*",$C$3),资金台帐!$N$6:$N$6005,">="&DATE($F$3,1,1),资金台帐!$N$6:$N$6005,"<"&DATE($F$3,1+1,1)),2) -> 0 | D32: =ROUND(SUMIFS(资金台帐!$AC$6:$AC$6005,资金台帐!$T$6:$T$6005,$Q32,资金台帐!$U$6:$U$6005,"变动成本",资金台帐!$O$6:$O$6005,IF($C$3="全部","?*",$C$3),资金台帐!$N$6:$N$6005,">="&DATE($F$3,2,1),资金台帐!$N$6:$N$6005,"<"&DATE($F$3,2+1,1))-SUMIFS(资金台帐!$AB$6:$AB$6005,资金台帐!$T$6:$T$6005,$Q32,资金台帐!$U$6:$U$6005,"变动成本",资金台帐!$O$6:$O$6005,IF($C$3="全部","?*",$C$3),资金台帐!$N$6:$N$6005,">="&DATE($F$3,2,1),资金台帐!$N$6:$N$6005,"<"&DATE($F$3,2+1,1)),2) -> 0 | E32: =ROUND(SUMIFS(资金台帐!$AC$6:$AC$6005,资金台帐!$T$6:$T$6005,$Q32,资金台帐!$U$6:$U$6005,"变动成本",资金台帐!$O$6:$O$6005,IF($C$3="全部","?*",$C$3),资金台帐!$N$6:$N$6005,">="&DATE($F$3,3,1),资金台帐!$N$6:$N$6005,"<"&DATE($F$3,3+1,1))-SUMIFS(资金台帐!$AB$6:$AB$6005,资金台帐!$T$6:$T$6005,$Q32,资金台帐!$U$6:$U$6005,"变动成本",资金台帐!$O$6:$O$6005,IF($C$3="全部","?*",$C$3),资金台帐!$N$6:$N$6005,">="&DATE($F$3,3,1),资金台帐!$N$6:$N$6005,"<"&DATE($F$3,3+1,1)),2) -> 0 | F32: =ROUND(SUMIFS(资金台帐!$AC$6:$AC$6005,资金台帐!$T$6:$T$6005,$Q32,资金台帐!$U$6:$U$6005,"变动成本",资金台帐!$O$6:$O$6005,IF($C$3="全部","?*",$C$3),资金台帐!$N$6:$N$6005,">="&DATE($F$3,4,1),资金台帐!$N$6:$N$6005,"<"&DATE($F$3,4+1,1))-SUMIFS(资金台帐!$AB$6:$AB$6005,资金台帐!$T$6:$T$6005,$Q32,资金台帐!$U$6:$U$6005,"变动成本",资金台帐!$O$6:$O$6005,IF($C$3="全部","?*",$C$3),资金台帐!$N$6:$N$6005,">="&DATE($F$3,4,1),资金台帐!$N$6:$N$6005,"<"&DATE($F$3,4+1,1)),2) -> 0 | G32: =ROUND(SUMIFS(资金台帐!$AC$6:$AC$6005,资金台帐!$T$6:$T$6005,$Q32,资金台帐!$U$6:$U$6005,"变动成本",资金台帐!$O$6:$O$6005,IF($C$3="全部","?*",$C$3),资金台帐!$N$6:$N$6005,">="&DATE($F$3,5,1),资金台帐!$N$6:$N$6005,"<"&DATE($F$3,5+1,1))-SUMIFS(资金台帐!$AB$6:$AB$6005,资金台帐!$T$6:$T$6005,$Q32,资金台帐!$U$6:$U$6005,"变动成本",资金台帐!$O$6:$O$6005,IF($C$3="全部","?*",$C$3),资金台帐!$N$6:$N$6005,">="&DATE($F$3,5,1),资金台帐!$N$6:$N$6005,"<"&DATE($F$3,5+1,1)),2) -> 0 | H32: =ROUND(SUMIFS(资金台帐!$AC$6:$AC$6005,资金台帐!$T$6:$T$6005,$Q32,资金台帐!$U$6:$U$6005,"变动成本",资金台帐!$O$6:$O$6005,IF($C$3="全部","?*",$C$3),资金台帐!$N$6:$N$6005,">="&DATE($F$3,6,1),资金台帐!$N$6:$N$6005,"<"&DATE($F$3,6+1,1))-SUMIFS(资金台帐!$AB$6:$AB$6005,资金台帐!$T$6:$T$6005,$Q32,资金台帐!$U$6:$U$6005,"变动成本",资金台帐!$O$6:$O$6005,IF($C$3="全部","?*",$C$3),资金台帐!$N$6:$N$6005,">="&DATE($F$3,6,1),资金台帐!$N$6:$N$6005,"<"&DATE($F$3,6+1,1)),2) -> 0 | I32: =ROUND(SUMIFS(资金台帐!$AC$6:$AC$6005,资金台帐!$T$6:$T$6005,$Q32,资金台帐!$U$6:$U$6005,"变动成本",资金台帐!$O$6:$O$6005,IF($C$3="全部","?*",$C$3),资金台帐!$N$6:$N$6005,">="&DATE($F$3,7,1),资金台帐!$N$6:$N$6005,"<"&DATE($F$3,7+1,1))-SUMIFS(资金台帐!$AB$6:$AB$6005,资金台帐!$T$6:$T$6005,$Q32,资金台帐!$U$6:$U$6005,"变动成本",资金台帐!$O$6:$O$6005,IF($C$3="全部","?*",$C$3),资金台帐!$N$6:$N$6005,">="&DATE($F$3,7,1),资金台帐!$N$6:$N$6005,"<"&DATE($F$3,7+1,1)),2) -> 0 | J32: =ROUND(SUMIFS(资金台帐!$AC$6:$AC$6005,资金台帐!$T$6:$T$6005,$Q32,资金台帐!$U$6:$U$6005,"变动成本",资金台帐!$O$6:$O$6005,IF($C$3="全部","?*",$C$3),资金台帐!$N$6:$N$6005,">="&DATE($F$3,8,1),资金台帐!$N$6:$N$6005,"<"&DATE($F$3,8+1,1))-SUMIFS(资金台帐!$AB$6:$AB$6005,资金台帐!$T$6:$T$6005,$Q32,资金台帐!$U$6:$U$6005,"变动成本",资金台帐!$O$6:$O$6005,IF($C$3="全部","?*",$C$3),资金台帐!$N$6:$N$6005,">="&DATE($F$3,8,1),资金台帐!$N$6:$N$6005,"<"&DATE($F$3,8+1,1)),2) -> 0 | K32: =ROUND(SUMIFS(资金台帐!$AC$6:$AC$6005,资金台帐!$T$6:$T$6005,$Q32,资金台帐!$U$6:$U$6005,"变动成本",资金台帐!$O$6:$O$6005,IF($C$3="全部","?*",$C$3),资金台帐!$N$6:$N$6005,">="&DATE($F$3,9,1),资金台帐!$N$6:$N$6005,"<"&DATE($F$3,9+1,1))-SUMIFS(资金台帐!$AB$6:$AB$6005,资金台帐!$T$6:$T$6005,$Q32,资金台帐!$U$6:$U$6005,"变动成本",资金台帐!$O$6:$O$6005,IF($C$3="全部","?*",$C$3),资金台帐!$N$6:$N$6005,">="&DATE($F$3,9,1),资金台帐!$N$6:$N$6005,"<"&DATE($F$3,9+1,1)),2) -> 0 | L32: =ROUND(SUMIFS(资金台帐!$AC$6:$AC$6005,资金台帐!$T$6:$T$6005,$Q32,资金台帐!$U$6:$U$6005,"变动成本",资金台帐!$O$6:$O$6005,IF($C$3="全部","?*",$C$3),资金台帐!$N$6:$N$6005,">="&DATE($F$3,10,1),资金台帐!$N$6:$N$6005,"<"&DATE($F$3,10+1,1))-SUMIFS(资金台帐!$AB$6:$AB$6005,资金台帐!$T$6:$T$6005,$Q32,资金台帐!$U$6:$U$6005,"变动成本",资金台帐!$O$6:$O$6005,IF($C$3="全部","?*",$C$3),资金台帐!$N$6:$N$6005,">="&DATE($F$3,10,1),资金台帐!$N$6:$N$6005,"<"&DATE($F$3,10+1,1)),2) -> 0 | M32: =ROUND(SUMIFS(资金台帐!$AC$6:$AC$6005,资金台帐!$T$6:$T$6005,$Q32,资金台帐!$U$6:$U$6005,"变动成本",资金台帐!$O$6:$O$6005,IF($C$3="全部","?*",$C$3),资金台帐!$N$6:$N$6005,">="&DATE($F$3,11,1),资金台帐!$N$6:$N$6005,"<"&DATE($F$3,11+1,1))-SUMIFS(资金台帐!$AB$6:$AB$6005,资金台帐!$T$6:$T$6005,$Q32,资金台帐!$U$6:$U$6005,"变动成本",资金台帐!$O$6:$O$6005,IF($C$3="全部","?*",$C$3),资金台帐!$N$6:$N$6005,">="&DATE($F$3,11,1),资金台帐!$N$6:$N$6005,"<"&DATE($F$3,11+1,1)),2) -> 0 | N32: =ROUND(SUMIFS(资金台帐!$AC$6:$AC$6005,资金台帐!$T$6:$T$6005,$Q32,资金台帐!$U$6:$U$6005,"变动成本",资金台帐!$O$6:$O$6005,IF($C$3="全部","?*",$C$3),资金台帐!$N$6:$N$6005,">="&DATE($F$3,12,1),资金台帐!$N$6:$N$6005,"<"&DATE($F$3,12+1,1))-SUMIFS(资金台帐!$AB$6:$AB$6005,资金台帐!$T$6:$T$6005,$Q32,资金台帐!$U$6:$U$6005,"变动成本",资金台帐!$O$6:$O$6005,IF($C$3="全部","?*",$C$3),资金台帐!$N$6:$N$6005,">="&DATE($F$3,12,1),资金台帐!$N$6:$N$6005,"<"&DATE($F$3,12+1,1)),2) -> 0 | O32: =ROUND(SUM(C32:N32),2) -> 0 | P32: =IF(N($O$16)=0,"",O32/$O$16) -> 0 | Q32: =基础资料!$U$31&"" -> 项目成本
B33: =IF(COUNTIFS(基础资料!$V$5:$V$64,"变动成本",基础资料!$U$5:$U$64,"?*")>17,"其他（含新加项目）","其他") -> 其他 | C33: =ROUND(SUMIFS(资金台帐!$AC$6:$AC$6005,资金台帐!$U$6:$U$6005,"变动成本",资金台帐!$O$6:$O$6005,IF($C$3="全部","?*",$C$3),资金台帐!$N$6:$N$6005,">="&DATE($F$3,1,1),资金台帐!$N$6:$N$6005,"<"&DATE($F$3,1+1,1))-SUMIFS(资金台帐!$AB$6:$AB$6005,资金台帐!$U$6:$U$6005,"变动成本",资金台帐!$O$6:$O$6005,IF($C$3="全部","?*",$C$3),资金台帐!$N$6:$N$6005,">="&DATE($F$3,1,1),资金台帐!$N$6:$N$6005,"<"&DATE($F$3,1+1,1))-SUM(C17:C32),2) -> 0 | D33: =ROUND(SUMIFS(资金台帐!$AC$6:$AC$6005,资金台帐!$U$6:$U$6005,"变动成本",资金台帐!$O$6:$O$6005,IF($C$3="全部","?*",$C$3),资金台帐!$N$6:$N$6005,">="&DATE($F$3,2,1),资金台帐!$N$6:$N$6005,"<"&DATE($F$3,2+1,1))-SUMIFS(资金台帐!$AB$6:$AB$6005,资金台帐!$U$6:$U$6005,"变动成本",资金台帐!$O$6:$O$6005,IF($C$3="全部","?*",$C$3),资金台帐!$N$6:$N$6005,">="&DATE($F$3,2,1),资金台帐!$N$6:$N$6005,"<"&DATE($F$3,2+1,1))-SUM(D17:D32),2) -> 0 | E33: =ROUND(SUMIFS(资金台帐!$AC$6:$AC$6005,资金台帐!$U$6:$U$6005,"变动成本",资金台帐!$O$6:$O$6005,IF($C$3="全部","?*",$C$3),资金台帐!$N$6:$N$6005,">="&DATE($F$3,3,1),资金台帐!$N$6:$N$6005,"<"&DATE($F$3,3+1,1))-SUMIFS(资金台帐!$AB$6:$AB$6005,资金台帐!$U$6:$U$6005,"变动成本",资金台帐!$O$6:$O$6005,IF($C$3="全部","?*",$C$3),资金台帐!$N$6:$N$6005,">="&DATE($F$3,3,1),资金台帐!$N$6:$N$6005,"<"&DATE($F$3,3+1,1))-SUM(E17:E32),2) -> 0 | F33: =ROUND(SUMIFS(资金台帐!$AC$6:$AC$6005,资金台帐!$U$6:$U$6005,"变动成本",资金台帐!$O$6:$O$6005,IF($C$3="全部","?*",$C$3),资金台帐!$N$6:$N$6005,">="&DATE($F$3,4,1),资金台帐!$N$6:$N$6005,"<"&DATE($F$3,4+1,1))-SUMIFS(资金台帐!$AB$6:$AB$6005,资金台帐!$U$6:$U$6005,"变动成本",资金台帐!$O$6:$O$6005,IF($C$3="全部","?*",$C$3),资金台帐!$N$6:$N$6005,">="&DATE($F$3,4,1),资金台帐!$N$6:$N$6005,"<"&DATE($F$3,4+1,1))-SUM(F17:F32),2) -> 0 | G33: =ROUND(SUMIFS(资金台帐!$AC$6:$AC$6005,资金台帐!$U$6:$U$6005,"变动成本",资金台帐!$O$6:$O$6005,IF($C$3="全部","?*",$C$3),资金台帐!$N$6:$N$6005,">="&DATE($F$3,5,1),资金台帐!$N$6:$N$6005,"<"&DATE($F$3,5+1,1))-SUMIFS(资金台帐!$AB$6:$AB$6005,资金台帐!$U$6:$U$6005,"变动成本",资金台帐!$O$6:$O$6005,IF($C$3="全部","?*",$C$3),资金台帐!$N$6:$N$6005,">="&DATE($F$3,5,1),资金台帐!$N$6:$N$6005,"<"&DATE($F$3,5+1,1))-SUM(G17:G32),2) -> 0 | H33: =ROUND(SUMIFS(资金台帐!$AC$6:$AC$6005,资金台帐!$U$6:$U$6005,"变动成本",资金台帐!$O$6:$O$6005,IF($C$3="全部","?*",$C$3),资金台帐!$N$6:$N$6005,">="&DATE($F$3,6,1),资金台帐!$N$6:$N$6005,"<"&DATE($F$3,6+1,1))-SUMIFS(资金台帐!$AB$6:$AB$6005,资金台帐!$U$6:$U$6005,"变动成本",资金台帐!$O$6:$O$6005,IF($C$3="全部","?*",$C$3),资金台帐!$N$6:$N$6005,">="&DATE($F$3,6,1),资金台帐!$N$6:$N$6005,"<"&DATE($F$3,6+1,1))-SUM(H17:H32),2) -> 0 | I33: =ROUND(SUMIFS(资金台帐!$AC$6:$AC$6005,资金台帐!$U$6:$U$6005,"变动成本",资金台帐!$O$6:$O$6005,IF($C$3="全部","?*",$C$3),资金台帐!$N$6:$N$6005,">="&DATE($F$3,7,1),资金台帐!$N$6:$N$6005,"<"&DATE($F$3,7+1,1))-SUMIFS(资金台帐!$AB$6:$AB$6005,资金台帐!$U$6:$U$6005,"变动成本",资金台帐!$O$6:$O$6005,IF($C$3="全部","?*",$C$3),资金台帐!$N$6:$N$6005,">="&DATE($F$3,7,1),资金台帐!$N$6:$N$6005,"<"&DATE($F$3,7+1,1))-SUM(I17:I32),2) -> 0 | J33: =ROUND(SUMIFS(资金台帐!$AC$6:$AC$6005,资金台帐!$U$6:$U$6005,"变动成本",资金台帐!$O$6:$O$6005,IF($C$3="全部","?*",$C$3),资金台帐!$N$6:$N$6005,">="&DATE($F$3,8,1),资金台帐!$N$6:$N$6005,"<"&DATE($F$3,8+1,1))-SUMIFS(资金台帐!$AB$6:$AB$6005,资金台帐!$U$6:$U$6005,"变动成本",资金台帐!$O$6:$O$6005,IF($C$3="全部","?*",$C$3),资金台帐!$N$6:$N$6005,">="&DATE($F$3,8,1),资金台帐!$N$6:$N$6005,"<"&DATE($F$3,8+1,1))-SUM(J17:J32),2) -> 0 | K33: =ROUND(SUMIFS(资金台帐!$AC$6:$AC$6005,资金台帐!$U$6:$U$6005,"变动成本",资金台帐!$O$6:$O$6005,IF($C$3="全部","?*",$C$3),资金台帐!$N$6:$N$6005,">="&DATE($F$3,9,1),资金台帐!$N$6:$N$6005,"<"&DATE($F$3,9+1,1))-SUMIFS(资金台帐!$AB$6:$AB$6005,资金台帐!$U$6:$U$6005,"变动成本",资金台帐!$O$6:$O$6005,IF($C$3="全部","?*",$C$3),资金台帐!$N$6:$N$6005,">="&DATE($F$3,9,1),资金台帐!$N$6:$N$6005,"<"&DATE($F$3,9+1,1))-SUM(K17:K32),2) -> 0 | L33: =ROUND(SUMIFS(资金台帐!$AC$6:$AC$6005,资金台帐!$U$6:$U$6005,"变动成本",资金台帐!$O$6:$O$6005,IF($C$3="全部","?*",$C$3),资金台帐!$N$6:$N$6005,">="&DATE($F$3,10,1),资金台帐!$N$6:$N$6005,"<"&DATE($F$3,10+1,1))-SUMIFS(资金台帐!$AB$6:$AB$6005,资金台帐!$U$6:$U$6005,"变动成本",资金台帐!$O$6:$O$6005,IF($C$3="全部","?*",$C$3),资金台帐!$N$6:$N$6005,">="&DATE($F$3,10,1),资金台帐!$N$6:$N$6005,"<"&DATE($F$3,10+1,1))-SUM(L17:L32),2) -> 0 | M33: =ROUND(SUMIFS(资金台帐!$AC$6:$AC$6005,资金台帐!$U$6:$U$6005,"变动成本",资金台帐!$O$6:$O$6005,IF($C$3="全部","?*",$C$3),资金台帐!$N$6:$N$6005,">="&DATE($F$3,11,1),资金台帐!$N$6:$N$6005,"<"&DATE($F$3,11+1,1))-SUMIFS(资金台帐!$AB$6:$AB$6005,资金台帐!$U$6:$U$6005,"变动成本",资金台帐!$O$6:$O$6005,IF($C$3="全部","?*",$C$3),资金台帐!$N$6:$N$6005,">="&DATE($F$3,11,1),资金台帐!$N$6:$N$6005,"<"&DATE($F$3,11+1,1))-SUM(M17:M32),2) -> 0 | N33: =ROUND(SUMIFS(资金台帐!$AC$6:$AC$6005,资金台帐!$U$6:$U$6005,"变动成本",资金台帐!$O$6:$O$6005,IF($C$3="全部","?*",$C$3),资金台帐!$N$6:$N$6005,">="&DATE($F$3,12,1),资金台帐!$N$6:$N$6005,"<"&DATE($F$3,12+1,1))-SUMIFS(资金台帐!$AB$6:$AB$6005,资金台帐!$U$6:$U$6005,"变动成本",资金台帐!$O$6:$O$6005,IF($C$3="全部","?*",$C$3),资金台帐!$N$6:$N$6005,">="&DATE($F$3,12,1),资金台帐!$N$6:$N$6005,"<"&DATE($F$3,12+1,1))-SUM(N17:N32),2) -> 0 | O33: =ROUND(SUM(C33:N33),2) -> 0 | P33: =IF(N($O$16)=0,"",O33/$O$16) -> 0 | Q33: =基础资料!$U$32&"" -> 其他成本
B34: 变动成本小计 | C34: =ROUND(SUM(C17:C33),2) -> 0 | D34: =ROUND(SUM(D17:D33),2) -> 0 | E34: =ROUND(SUM(E17:E33),2) -> 0 | F34: =ROUND(SUM(F17:F33),2) -> 0 | G34: =ROUND(SUM(G17:G33),2) -> 0 | H34: =ROUND(SUM(H17:H33),2) -> 0 | I34: =ROUND(SUM(I17:I33),2) -> 0 | J34: =ROUND(SUM(J17:J33),2) -> 0 | ... O34: =ROUND(SUM(O17:O33),2) -> 22378.66 | P34: =IF(N($O$16)=0,"",O34/$O$16) -> 0.13086936
B35: 变动利润 | C35: =ROUND(C16-C34,2) -> 0 | D35: =ROUND(D16-D34,2) -> 0 | E35: =ROUND(E16-E34,2) -> 0 | F35: =ROUND(F16-F34,2) -> 0 | G35: =ROUND(G16-G34,2) -> 0 | H35: =ROUND(H16-H34,2) -> 0 | I35: =ROUND(I16-I34,2) -> 0 | J35: =ROUND(J16-J34,2) -> 0 | ... O35: =ROUND(O16-O34,2) -> 148621.34 | P35: =IF(N($O$16)=0,"",O35/$O$16) -> 0.86913064
A36: 固定成本 | B36: =IF(基础资料!$W$33="",基础资料!$U$33&"",基础资料!$W$33&"") -> 店面租金 | C36: =ROUND(SUMIFS(资金台帐!$AC$6:$AC$6005,资金台帐!$T$6:$T$6005,$Q36,资金台帐!$U$6:$U$6005,"固定成本",资金台帐!$O$6:$O$6005,IF($C$3="全部","?*",$C$3),资金台帐!$N$6:$N$6005,">="&DATE($F$3,1,1),资金台帐!$N$6:$N$6005,"<"&DATE($F$3,1+1,1))-SUMIFS(资金台帐!$AB$6:$AB$6005,资金台帐!$T$6:$T$6005,$Q36,资金台帐!$U$6:$U$6005,"固定成本",资金台帐!$O$6:$O$6005,IF($C$3="全部","?*",$C$3),资金台帐!$N$6:$N$6005,">="&DATE($F$3,1,1),资金台帐!$N$6:$N$6005,"<"&DATE($F$3,1+1,1)),2) -> 0 | D36: =ROUND(SUMIFS(资金台帐!$AC$6:$AC$6005,资金台帐!$T$6:$T$6005,$Q36,资金台帐!$U$6:$U$6005,"固定成本",资金台帐!$O$6:$O$6005,IF($C$3="全部","?*",$C$3),资金台帐!$N$6:$N$6005,">="&DATE($F$3,2,1),资金台帐!$N$6:$N$6005,"<"&DATE($F$3,2+1,1))-SUMIFS(资金台帐!$AB$6:$AB$6005,资金台帐!$T$6:$T$6005,$Q36,资金台帐!$U$6:$U$6005,"固定成本",资金台帐!$O$6:$O$6005,IF($C$3="全部","?*",$C$3),资金台帐!$N$6:$N$6005,">="&DATE($F$3,2,1),资金台帐!$N$6:$N$6005,"<"&DATE($F$3,2+1,1)),2) -> 0 | E36: =ROUND(SUMIFS(资金台帐!$AC$6:$AC$6005,资金台帐!$T$6:$T$6005,$Q36,资金台帐!$U$6:$U$6005,"固定成本",资金台帐!$O$6:$O$6005,IF($C$3="全部","?*",$C$3),资金台帐!$N$6:$N$6005,">="&DATE($F$3,3,1),资金台帐!$N$6:$N$6005,"<"&DATE($F$3,3+1,1))-SUMIFS(资金台帐!$AB$6:$AB$6005,资金台帐!$T$6:$T$6005,$Q36,资金台帐!$U$6:$U$6005,"固定成本",资金台帐!$O$6:$O$6005,IF($C$3="全部","?*",$C$3),资金台帐!$N$6:$N$6005,">="&DATE($F$3,3,1),资金台帐!$N$6:$N$6005,"<"&DATE($F$3,3+1,1)),2) -> 0 | F36: =ROUND(SUMIFS(资金台帐!$AC$6:$AC$6005,资金台帐!$T$6:$T$6005,$Q36,资金台帐!$U$6:$U$6005,"固定成本",资金台帐!$O$6:$O$6005,IF($C$3="全部","?*",$C$3),资金台帐!$N$6:$N$6005,">="&DATE($F$3,4,1),资金台帐!$N$6:$N$6005,"<"&DATE($F$3,4+1,1))-SUMIFS(资金台帐!$AB$6:$AB$6005,资金台帐!$T$6:$T$6005,$Q36,资金台帐!$U$6:$U$6005,"固定成本",资金台帐!$O$6:$O$6005,IF($C$3="全部","?*",$C$3),资金台帐!$N$6:$N$6005,">="&DATE($F$3,4,1),资金台帐!$N$6:$N$6005,"<"&DATE($F$3,4+1,1)),2) -> 0 | G36: =ROUND(SUMIFS(资金台帐!$AC$6:$AC$6005,资金台帐!$T$6:$T$6005,$Q36,资金台帐!$U$6:$U$6005,"固定成本",资金台帐!$O$6:$O$6005,IF($C$3="全部","?*",$C$3),资金台帐!$N$6:$N$6005,">="&DATE($F$3,5,1),资金台帐!$N$6:$N$6005,"<"&DATE($F$3,5+1,1))-SUMIFS(资金台帐!$AB$6:$AB$6005,资金台帐!$T$6:$T$6005,$Q36,资金台帐!$U$6:$U$6005,"固定成本",资金台帐!$O$6:$O$6005,IF($C$3="全部","?*",$C$3),资金台帐!$N$6:$N$6005,">="&DATE($F$3,5,1),资金台帐!$N$6:$N$6005,"<"&DATE($F$3,5+1,1)),2) -> 0 | H36: =ROUND(SUMIFS(资金台帐!$AC$6:$AC$6005,资金台帐!$T$6:$T$6005,$Q36,资金台帐!$U$6:$U$6005,"固定成本",资金台帐!$O$6:$O$6005,IF($C$3="全部","?*",$C$3),资金台帐!$N$6:$N$6005,">="&DATE($F$3,6,1),资金台帐!$N$6:$N$6005,"<"&DATE($F$3,6+1,1))-SUMIFS(资金台帐!$AB$6:$AB$6005,资金台帐!$T$6:$T$6005,$Q36,资金台帐!$U$6:$U$6005,"固定成本",资金台帐!$O$6:$O$6005,IF($C$3="全部","?*",$C$3),资金台帐!$N$6:$N$6005,">="&DATE($F$3,6,1),资金台帐!$N$6:$N$6005,"<"&DATE($F$3,6+1,1)),2) -> 0 | I36: =ROUND(SUMIFS(资金台帐!$AC$6:$AC$6005,资金台帐!$T$6:$T$6005,$Q36,资金台帐!$U$6:$U$6005,"固定成本",资金台帐!$O$6:$O$6005,IF($C$3="全部","?*",$C$3),资金台帐!$N$6:$N$6005,">="&DATE($F$3,7,1),资金台帐!$N$6:$N$6005,"<"&DATE($F$3,7+1,1))-SUMIFS(资金台帐!$AB$6:$AB$6005,资金台帐!$T$6:$T$6005,$Q36,资金台帐!$U$6:$U$6005,"固定成本",资金台帐!$O$6:$O$6005,IF($C$3="全部","?*",$C$3),资金台帐!$N$6:$N$6005,">="&DATE($F$3,7,1),资金台帐!$N$6:$N$6005,"<"&DATE($F$3,7+1,1)),2) -> 0 | J36: =ROUND(SUMIFS(资金台帐!$AC$6:$AC$6005,资金台帐!$T$6:$T$6005,$Q36,资金台帐!$U$6:$U$6005,"固定成本",资金台帐!$O$6:$O$6005,IF($C$3="全部","?*",$C$3),资金台帐!$N$6:$N$6005,">="&DATE($F$3,8,1),资金台帐!$N$6:$N$6005,"<"&DATE($F$3,8+1,1))-SUMIFS(资金台帐!$AB$6:$AB$6005,资金台帐!$T$6:$T$6005,$Q36,资金台帐!$U$6:$U$6005,"固定成本",资金台帐!$O$6:$O$6005,IF($C$3="全部","?*",$C$3),资金台帐!$N$6:$N$6005,">="&DATE($F$3,8,1),资金台帐!$N$6:$N$6005,"<"&DATE($F$3,8+1,1)),2) -> 0 | K36: =ROUND(SUMIFS(资金台帐!$AC$6:$AC$6005,资金台帐!$T$6:$T$6005,$Q36,资金台帐!$U$6:$U$6005,"固定成本",资金台帐!$O$6:$O$6005,IF($C$3="全部","?*",$C$3),资金台帐!$N$6:$N$6005,">="&DATE($F$3,9,1),资金台帐!$N$6:$N$6005,"<"&DATE($F$3,9+1,1))-SUMIFS(资金台帐!$AB$6:$AB$6005,资金台帐!$T$6:$T$6005,$Q36,资金台帐!$U$6:$U$6005,"固定成本",资金台帐!$O$6:$O$6005,IF($C$3="全部","?*",$C$3),资金台帐!$N$6:$N$6005,">="&DATE($F$3,9,1),资金台帐!$N$6:$N$6005,"<"&DATE($F$3,9+1,1)),2) -> 0 | L36: =ROUND(SUMIFS(资金台帐!$AC$6:$AC$6005,资金台帐!$T$6:$T$6005,$Q36,资金台帐!$U$6:$U$6005,"固定成本",资金台帐!$O$6:$O$6005,IF($C$3="全部","?*",$C$3),资金台帐!$N$6:$N$6005,">="&DATE($F$3,10,1),资金台帐!$N$6:$N$6005,"<"&DATE($F$3,10+1,1))-SUMIFS(资金台帐!$AB$6:$AB$6005,资金台帐!$T$6:$T$6005,$Q36,资金台帐!$U$6:$U$6005,"固定成本",资金台帐!$O$6:$O$6005,IF($C$3="全部","?*",$C$3),资金台帐!$N$6:$N$6005,">="&DATE($F$3,10,1),资金台帐!$N$6:$N$6005,"<"&DATE($F$3,10+1,1)),2) -> 0 | M36: =ROUND(SUMIFS(资金台帐!$AC$6:$AC$6005,资金台帐!$T$6:$T$6005,$Q36,资金台帐!$U$6:$U$6005,"固定成本",资金台帐!$O$6:$O$6005,IF($C$3="全部","?*",$C$3),资金台帐!$N$6:$N$6005,">="&DATE($F$3,11,1),资金台帐!$N$6:$N$6005,"<"&DATE($F$3,11+1,1))-SUMIFS(资金台帐!$AB$6:$AB$6005,资金台帐!$T$6:$T$6005,$Q36,资金台帐!$U$6:$U$6005,"固定成本",资金台帐!$O$6:$O$6005,IF($C$3="全部","?*",$C$3),资金台帐!$N$6:$N$6005,">="&DATE($F$3,11,1),资金台帐!$N$6:$N$6005,"<"&DATE($F$3,11+1,1)),2) -> 0 | N36: =ROUND(SUMIFS(资金台帐!$AC$6:$AC$6005,资金台帐!$T$6:$T$6005,$Q36,资金台帐!$U$6:$U$6005,"固定成本",资金台帐!$O$6:$O$6005,IF($C$3="全部","?*",$C$3),资金台帐!$N$6:$N$6005,">="&DATE($F$3,12,1),资金台帐!$N$6:$N$6005,"<"&DATE($F$3,12+1,1))-SUMIFS(资金台帐!$AB$6:$AB$6005,资金台帐!$T$6:$T$6005,$Q36,资金台帐!$U$6:$U$6005,"固定成本",资金台帐!$O$6:$O$6005,IF($C$3="全部","?*",$C$3),资金台帐!$N$6:$N$6005,">="&DATE($F$3,12,1),资金台帐!$N$6:$N$6005,"<"&DATE($F$3,12+1,1)),2) -> 0 | O36: =ROUND(SUM(C36:N36),2) -> 0 | P36: =IF(N($O$16)=0,"",O36/$O$16) -> 0 | Q36: =基础资料!$U$33&"" -> 店面租金
B37: =IF(基础资料!$W$34="",基础资料!$U$34&"",基础资料!$W$34&"") -> 装修成本 | C37: =ROUND(SUMIFS(资金台帐!$AC$6:$AC$6005,资金台帐!$T$6:$T$6005,$Q37,资金台帐!$U$6:$U$6005,"固定成本",资金台帐!$O$6:$O$6005,IF($C$3="全部","?*",$C$3),资金台帐!$N$6:$N$6005,">="&DATE($F$3,1,1),资金台帐!$N$6:$N$6005,"<"&DATE($F$3,1+1,1))-SUMIFS(资金台帐!$AB$6:$AB$6005,资金台帐!$T$6:$T$6005,$Q37,资金台帐!$U$6:$U$6005,"固定成本",资金台帐!$O$6:$O$6005,IF($C$3="全部","?*",$C$3),资金台帐!$N$6:$N$6005,">="&DATE($F$3,1,1),资金台帐!$N$6:$N$6005,"<"&DATE($F$3,1+1,1)),2) -> 0 | D37: =ROUND(SUMIFS(资金台帐!$AC$6:$AC$6005,资金台帐!$T$6:$T$6005,$Q37,资金台帐!$U$6:$U$6005,"固定成本",资金台帐!$O$6:$O$6005,IF($C$3="全部","?*",$C$3),资金台帐!$N$6:$N$6005,">="&DATE($F$3,2,1),资金台帐!$N$6:$N$6005,"<"&DATE($F$3,2+1,1))-SUMIFS(资金台帐!$AB$6:$AB$6005,资金台帐!$T$6:$T$6005,$Q37,资金台帐!$U$6:$U$6005,"固定成本",资金台帐!$O$6:$O$6005,IF($C$3="全部","?*",$C$3),资金台帐!$N$6:$N$6005,">="&DATE($F$3,2,1),资金台帐!$N$6:$N$6005,"<"&DATE($F$3,2+1,1)),2) -> 0 | E37: =ROUND(SUMIFS(资金台帐!$AC$6:$AC$6005,资金台帐!$T$6:$T$6005,$Q37,资金台帐!$U$6:$U$6005,"固定成本",资金台帐!$O$6:$O$6005,IF($C$3="全部","?*",$C$3),资金台帐!$N$6:$N$6005,">="&DATE($F$3,3,1),资金台帐!$N$6:$N$6005,"<"&DATE($F$3,3+1,1))-SUMIFS(资金台帐!$AB$6:$AB$6005,资金台帐!$T$6:$T$6005,$Q37,资金台帐!$U$6:$U$6005,"固定成本",资金台帐!$O$6:$O$6005,IF($C$3="全部","?*",$C$3),资金台帐!$N$6:$N$6005,">="&DATE($F$3,3,1),资金台帐!$N$6:$N$6005,"<"&DATE($F$3,3+1,1)),2) -> 0 | F37: =ROUND(SUMIFS(资金台帐!$AC$6:$AC$6005,资金台帐!$T$6:$T$6005,$Q37,资金台帐!$U$6:$U$6005,"固定成本",资金台帐!$O$6:$O$6005,IF($C$3="全部","?*",$C$3),资金台帐!$N$6:$N$6005,">="&DATE($F$3,4,1),资金台帐!$N$6:$N$6005,"<"&DATE($F$3,4+1,1))-SUMIFS(资金台帐!$AB$6:$AB$6005,资金台帐!$T$6:$T$6005,$Q37,资金台帐!$U$6:$U$6005,"固定成本",资金台帐!$O$6:$O$6005,IF($C$3="全部","?*",$C$3),资金台帐!$N$6:$N$6005,">="&DATE($F$3,4,1),资金台帐!$N$6:$N$6005,"<"&DATE($F$3,4+1,1)),2) -> 0 | G37: =ROUND(SUMIFS(资金台帐!$AC$6:$AC$6005,资金台帐!$T$6:$T$6005,$Q37,资金台帐!$U$6:$U$6005,"固定成本",资金台帐!$O$6:$O$6005,IF($C$3="全部","?*",$C$3),资金台帐!$N$6:$N$6005,">="&DATE($F$3,5,1),资金台帐!$N$6:$N$6005,"<"&DATE($F$3,5+1,1))-SUMIFS(资金台帐!$AB$6:$AB$6005,资金台帐!$T$6:$T$6005,$Q37,资金台帐!$U$6:$U$6005,"固定成本",资金台帐!$O$6:$O$6005,IF($C$3="全部","?*",$C$3),资金台帐!$N$6:$N$6005,">="&DATE($F$3,5,1),资金台帐!$N$6:$N$6005,"<"&DATE($F$3,5+1,1)),2) -> 0 | H37: =ROUND(SUMIFS(资金台帐!$AC$6:$AC$6005,资金台帐!$T$6:$T$6005,$Q37,资金台帐!$U$6:$U$6005,"固定成本",资金台帐!$O$6:$O$6005,IF($C$3="全部","?*",$C$3),资金台帐!$N$6:$N$6005,">="&DATE($F$3,6,1),资金台帐!$N$6:$N$6005,"<"&DATE($F$3,6+1,1))-SUMIFS(资金台帐!$AB$6:$AB$6005,资金台帐!$T$6:$T$6005,$Q37,资金台帐!$U$6:$U$6005,"固定成本",资金台帐!$O$6:$O$6005,IF($C$3="全部","?*",$C$3),资金台帐!$N$6:$N$6005,">="&DATE($F$3,6,1),资金台帐!$N$6:$N$6005,"<"&DATE($F$3,6+1,1)),2) -> 0 | I37: =ROUND(SUMIFS(资金台帐!$AC$6:$AC$6005,资金台帐!$T$6:$T$6005,$Q37,资金台帐!$U$6:$U$6005,"固定成本",资金台帐!$O$6:$O$6005,IF($C$3="全部","?*",$C$3),资金台帐!$N$6:$N$6005,">="&DATE($F$3,7,1),资金台帐!$N$6:$N$6005,"<"&DATE($F$3,7+1,1))-SUMIFS(资金台帐!$AB$6:$AB$6005,资金台帐!$T$6:$T$6005,$Q37,资金台帐!$U$6:$U$6005,"固定成本",资金台帐!$O$6:$O$6005,IF($C$3="全部","?*",$C$3),资金台帐!$N$6:$N$6005,">="&DATE($F$3,7,1),资金台帐!$N$6:$N$6005,"<"&DATE($F$3,7+1,1)),2) -> 0 | J37: =ROUND(SUMIFS(资金台帐!$AC$6:$AC$6005,资金台帐!$T$6:$T$6005,$Q37,资金台帐!$U$6:$U$6005,"固定成本",资金台帐!$O$6:$O$6005,IF($C$3="全部","?*",$C$3),资金台帐!$N$6:$N$6005,">="&DATE($F$3,8,1),资金台帐!$N$6:$N$6005,"<"&DATE($F$3,8+1,1))-SUMIFS(资金台帐!$AB$6:$AB$6005,资金台帐!$T$6:$T$6005,$Q37,资金台帐!$U$6:$U$6005,"固定成本",资金台帐!$O$6:$O$6005,IF($C$3="全部","?*",$C$3),资金台帐!$N$6:$N$6005,">="&DATE($F$3,8,1),资金台帐!$N$6:$N$6005,"<"&DATE($F$3,8+1,1)),2) -> 0 | K37: =ROUND(SUMIFS(资金台帐!$AC$6:$AC$6005,资金台帐!$T$6:$T$6005,$Q37,资金台帐!$U$6:$U$6005,"固定成本",资金台帐!$O$6:$O$6005,IF($C$3="全部","?*",$C$3),资金台帐!$N$6:$N$6005,">="&DATE($F$3,9,1),资金台帐!$N$6:$N$6005,"<"&DATE($F$3,9+1,1))-SUMIFS(资金台帐!$AB$6:$AB$6005,资金台帐!$T$6:$T$6005,$Q37,资金台帐!$U$6:$U$6005,"固定成本",资金台帐!$O$6:$O$6005,IF($C$3="全部","?*",$C$3),资金台帐!$N$6:$N$6005,">="&DATE($F$3,9,1),资金台帐!$N$6:$N$6005,"<"&DATE($F$3,9+1,1)),2) -> 0 | L37: =ROUND(SUMIFS(资金台帐!$AC$6:$AC$6005,资金台帐!$T$6:$T$6005,$Q37,资金台帐!$U$6:$U$6005,"固定成本",资金台帐!$O$6:$O$6005,IF($C$3="全部","?*",$C$3),资金台帐!$N$6:$N$6005,">="&DATE($F$3,10,1),资金台帐!$N$6:$N$6005,"<"&DATE($F$3,10+1,1))-SUMIFS(资金台帐!$AB$6:$AB$6005,资金台帐!$T$6:$T$6005,$Q37,资金台帐!$U$6:$U$6005,"固定成本",资金台帐!$O$6:$O$6005,IF($C$3="全部","?*",$C$3),资金台帐!$N$6:$N$6005,">="&DATE($F$3,10,1),资金台帐!$N$6:$N$6005,"<"&DATE($F$3,10+1,1)),2) -> 0 | M37: =ROUND(SUMIFS(资金台帐!$AC$6:$AC$6005,资金台帐!$T$6:$T$6005,$Q37,资金台帐!$U$6:$U$6005,"固定成本",资金台帐!$O$6:$O$6005,IF($C$3="全部","?*",$C$3),资金台帐!$N$6:$N$6005,">="&DATE($F$3,11,1),资金台帐!$N$6:$N$6005,"<"&DATE($F$3,11+1,1))-SUMIFS(资金台帐!$AB$6:$AB$6005,资金台帐!$T$6:$T$6005,$Q37,资金台帐!$U$6:$U$6005,"固定成本",资金台帐!$O$6:$O$6005,IF($C$3="全部","?*",$C$3),资金台帐!$N$6:$N$6005,">="&DATE($F$3,11,1),资金台帐!$N$6:$N$6005,"<"&DATE($F$3,11+1,1)),2) -> 0 | N37: =ROUND(SUMIFS(资金台帐!$AC$6:$AC$6005,资金台帐!$T$6:$T$6005,$Q37,资金台帐!$U$6:$U$6005,"固定成本",资金台帐!$O$6:$O$6005,IF($C$3="全部","?*",$C$3),资金台帐!$N$6:$N$6005,">="&DATE($F$3,12,1),资金台帐!$N$6:$N$6005,"<"&DATE($F$3,12+1,1))-SUMIFS(资金台帐!$AB$6:$AB$6005,资金台帐!$T$6:$T$6005,$Q37,资金台帐!$U$6:$U$6005,"固定成本",资金台帐!$O$6:$O$6005,IF($C$3="全部","?*",$C$3),资金台帐!$N$6:$N$6005,">="&DATE($F$3,12,1),资金台帐!$N$6:$N$6005,"<"&DATE($F$3,12+1,1)),2) -> 0 | O37: =ROUND(SUM(C37:N37),2) -> 0 | P37: =IF(N($O$16)=0,"",O37/$O$16) -> 0 | Q37: =基础资料!$U$34&"" -> 装修成本
B38: =IF(COUNTIFS(基础资料!$V$5:$V$64,"固定成本",基础资料!$U$5:$U$64,"?*")>2,"其他（含新加项目）","其他") -> 其他 | C38: =ROUND(SUMIFS(资金台帐!$AC$6:$AC$6005,资金台帐!$U$6:$U$6005,"固定成本",资金台帐!$O$6:$O$6005,IF($C$3="全部","?*",$C$3),资金台帐!$N$6:$N$6005,">="&DATE($F$3,1,1),资金台帐!$N$6:$N$6005,"<"&DATE($F$3,1+1,1))-SUMIFS(资金台帐!$AB$6:$AB$6005,资金台帐!$U$6:$U$6005,"固定成本",资金台帐!$O$6:$O$6005,IF($C$3="全部","?*",$C$3),资金台帐!$N$6:$N$6005,">="&DATE($F$3,1,1),资金台帐!$N$6:$N$6005,"<"&DATE($F$3,1+1,1))-SUM(C36:C37),2) -> 0 | D38: =ROUND(SUMIFS(资金台帐!$AC$6:$AC$6005,资金台帐!$U$6:$U$6005,"固定成本",资金台帐!$O$6:$O$6005,IF($C$3="全部","?*",$C$3),资金台帐!$N$6:$N$6005,">="&DATE($F$3,2,1),资金台帐!$N$6:$N$6005,"<"&DATE($F$3,2+1,1))-SUMIFS(资金台帐!$AB$6:$AB$6005,资金台帐!$U$6:$U$6005,"固定成本",资金台帐!$O$6:$O$6005,IF($C$3="全部","?*",$C$3),资金台帐!$N$6:$N$6005,">="&DATE($F$3,2,1),资金台帐!$N$6:$N$6005,"<"&DATE($F$3,2+1,1))-SUM(D36:D37),2) -> 0 | E38: =ROUND(SUMIFS(资金台帐!$AC$6:$AC$6005,资金台帐!$U$6:$U$6005,"固定成本",资金台帐!$O$6:$O$6005,IF($C$3="全部","?*",$C$3),资金台帐!$N$6:$N$6005,">="&DATE($F$3,3,1),资金台帐!$N$6:$N$6005,"<"&DATE($F$3,3+1,1))-SUMIFS(资金台帐!$AB$6:$AB$6005,资金台帐!$U$6:$U$6005,"固定成本",资金台帐!$O$6:$O$6005,IF($C$3="全部","?*",$C$3),资金台帐!$N$6:$N$6005,">="&DATE($F$3,3,1),资金台帐!$N$6:$N$6005,"<"&DATE($F$3,3+1,1))-SUM(E36:E37),2) -> 0 | F38: =ROUND(SUMIFS(资金台帐!$AC$6:$AC$6005,资金台帐!$U$6:$U$6005,"固定成本",资金台帐!$O$6:$O$6005,IF($C$3="全部","?*",$C$3),资金台帐!$N$6:$N$6005,">="&DATE($F$3,4,1),资金台帐!$N$6:$N$6005,"<"&DATE($F$3,4+1,1))-SUMIFS(资金台帐!$AB$6:$AB$6005,资金台帐!$U$6:$U$6005,"固定成本",资金台帐!$O$6:$O$6005,IF($C$3="全部","?*",$C$3),资金台帐!$N$6:$N$6005,">="&DATE($F$3,4,1),资金台帐!$N$6:$N$6005,"<"&DATE($F$3,4+1,1))-SUM(F36:F37),2) -> 0 | G38: =ROUND(SUMIFS(资金台帐!$AC$6:$AC$6005,资金台帐!$U$6:$U$6005,"固定成本",资金台帐!$O$6:$O$6005,IF($C$3="全部","?*",$C$3),资金台帐!$N$6:$N$6005,">="&DATE($F$3,5,1),资金台帐!$N$6:$N$6005,"<"&DATE($F$3,5+1,1))-SUMIFS(资金台帐!$AB$6:$AB$6005,资金台帐!$U$6:$U$6005,"固定成本",资金台帐!$O$6:$O$6005,IF($C$3="全部","?*",$C$3),资金台帐!$N$6:$N$6005,">="&DATE($F$3,5,1),资金台帐!$N$6:$N$6005,"<"&DATE($F$3,5+1,1))-SUM(G36:G37),2) -> 0 | H38: =ROUND(SUMIFS(资金台帐!$AC$6:$AC$6005,资金台帐!$U$6:$U$6005,"固定成本",资金台帐!$O$6:$O$6005,IF($C$3="全部","?*",$C$3),资金台帐!$N$6:$N$6005,">="&DATE($F$3,6,1),资金台帐!$N$6:$N$6005,"<"&DATE($F$3,6+1,1))-SUMIFS(资金台帐!$AB$6:$AB$6005,资金台帐!$U$6:$U$6005,"固定成本",资金台帐!$O$6:$O$6005,IF($C$3="全部","?*",$C$3),资金台帐!$N$6:$N$6005,">="&DATE($F$3,6,1),资金台帐!$N$6:$N$6005,"<"&DATE($F$3,6+1,1))-SUM(H36:H37),2) -> 0 | I38: =ROUND(SUMIFS(资金台帐!$AC$6:$AC$6005,资金台帐!$U$6:$U$6005,"固定成本",资金台帐!$O$6:$O$6005,IF($C$3="全部","?*",$C$3),资金台帐!$N$6:$N$6005,">="&DATE($F$3,7,1),资金台帐!$N$6:$N$6005,"<"&DATE($F$3,7+1,1))-SUMIFS(资金台帐!$AB$6:$AB$6005,资金台帐!$U$6:$U$6005,"固定成本",资金台帐!$O$6:$O$6005,IF($C$3="全部","?*",$C$3),资金台帐!$N$6:$N$6005,">="&DATE($F$3,7,1),资金台帐!$N$6:$N$6005,"<"&DATE($F$3,7+1,1))-SUM(I36:I37),2) -> 0 | J38: =ROUND(SUMIFS(资金台帐!$AC$6:$AC$6005,资金台帐!$U$6:$U$6005,"固定成本",资金台帐!$O$6:$O$6005,IF($C$3="全部","?*",$C$3),资金台帐!$N$6:$N$6005,">="&DATE($F$3,8,1),资金台帐!$N$6:$N$6005,"<"&DATE($F$3,8+1,1))-SUMIFS(资金台帐!$AB$6:$AB$6005,资金台帐!$U$6:$U$6005,"固定成本",资金台帐!$O$6:$O$6005,IF($C$3="全部","?*",$C$3),资金台帐!$N$6:$N$6005,">="&DATE($F$3,8,1),资金台帐!$N$6:$N$6005,"<"&DATE($F$3,8+1,1))-SUM(J36:J37),2) -> 0 | K38: =ROUND(SUMIFS(资金台帐!$AC$6:$AC$6005,资金台帐!$U$6:$U$6005,"固定成本",资金台帐!$O$6:$O$6005,IF($C$3="全部","?*",$C$3),资金台帐!$N$6:$N$6005,">="&DATE($F$3,9,1),资金台帐!$N$6:$N$6005,"<"&DATE($F$3,9+1,1))-SUMIFS(资金台帐!$AB$6:$AB$6005,资金台帐!$U$6:$U$6005,"固定成本",资金台帐!$O$6:$O$6005,IF($C$3="全部","?*",$C$3),资金台帐!$N$6:$N$6005,">="&DATE($F$3,9,1),资金台帐!$N$6:$N$6005,"<"&DATE($F$3,9+1,1))-SUM(K36:K37),2) -> 0 | L38: =ROUND(SUMIFS(资金台帐!$AC$6:$AC$6005,资金台帐!$U$6:$U$6005,"固定成本",资金台帐!$O$6:$O$6005,IF($C$3="全部","?*",$C$3),资金台帐!$N$6:$N$6005,">="&DATE($F$3,10,1),资金台帐!$N$6:$N$6005,"<"&DATE($F$3,10+1,1))-SUMIFS(资金台帐!$AB$6:$AB$6005,资金台帐!$U$6:$U$6005,"固定成本",资金台帐!$O$6:$O$6005,IF($C$3="全部","?*",$C$3),资金台帐!$N$6:$N$6005,">="&DATE($F$3,10,1),资金台帐!$N$6:$N$6005,"<"&DATE($F$3,10+1,1))-SUM(L36:L37),2) -> 0 | M38: =ROUND(SUMIFS(资金台帐!$AC$6:$AC$6005,资金台帐!$U$6:$U$6005,"固定成本",资金台帐!$O$6:$O$6005,IF($C$3="全部","?*",$C$3),资金台帐!$N$6:$N$6005,">="&DATE($F$3,11,1),资金台帐!$N$6:$N$6005,"<"&DATE($F$3,11+1,1))-SUMIFS(资金台帐!$AB$6:$AB$6005,资金台帐!$U$6:$U$6005,"固定成本",资金台帐!$O$6:$O$6005,IF($C$3="全部","?*",$C$3),资金台帐!$N$6:$N$6005,">="&DATE($F$3,11,1),资金台帐!$N$6:$N$6005,"<"&DATE($F$3,11+1,1))-SUM(M36:M37),2) -> 0 | N38: =ROUND(SUMIFS(资金台帐!$AC$6:$AC$6005,资金台帐!$U$6:$U$6005,"固定成本",资金台帐!$O$6:$O$6005,IF($C$3="全部","?*",$C$3),资金台帐!$N$6:$N$6005,">="&DATE($F$3,12,1),资金台帐!$N$6:$N$6005,"<"&DATE($F$3,12+1,1))-SUMIFS(资金台帐!$AB$6:$AB$6005,资金台帐!$U$6:$U$6005,"固定成本",资金台帐!$O$6:$O$6005,IF($C$3="全部","?*",$C$3),资金台帐!$N$6:$N$6005,">="&DATE($F$3,12,1),资金台帐!$N$6:$N$6005,"<"&DATE($F$3,12+1,1))-SUM(N36:N37),2) -> 0 | O38: =ROUND(SUM(C38:N38),2) -> 0 | P38: =IF(N($O$16)=0,"",O38/$O$16) -> 0
B39: 固定成本小计 | C39: =ROUND(SUM(C36:C38),2) -> 0 | D39: =ROUND(SUM(D36:D38),2) -> 0 | E39: =ROUND(SUM(E36:E38),2) -> 0 | F39: =ROUND(SUM(F36:F38),2) -> 0 | G39: =ROUND(SUM(G36:G38),2) -> 0 | H39: =ROUND(SUM(H36:H38),2) -> 0 | I39: =ROUND(SUM(I36:I38),2) -> 0 | J39: =ROUND(SUM(J36:J38),2) -> 0 | ... O39: =ROUND(SUM(O36:O38),2) -> 0 | P39: =IF(N($O$16)=0,"",O39/$O$16) -> 0
B40: 利润 | C40: =ROUND(C35-C39,2) -> 0 | D40: =ROUND(D35-D39,2) -> 0 | E40: =ROUND(E35-E39,2) -> 0 | F40: =ROUND(F35-F39,2) -> 0 | G40: =ROUND(G35-G39,2) -> 0 | H40: =ROUND(H35-H39,2) -> 0 | I40: =ROUND(I35-I39,2) -> 0 | J40: =ROUND(J35-J39,2) -> 0 | ... O40: =ROUND(O35-O39,2) -> 148621.34 | P40: =IF(N($O$16)=0,"",O40/$O$16) -> 0.86913064
A41: 其他支出 | B41: =IF(基础资料!$W$35="",基础资料!$U$35&"",基础资料!$W$35&"") -> 工资挂靠 | C41: =ROUND(SUMIFS(资金台帐!$AC$6:$AC$6005,资金台帐!$T$6:$T$6005,$Q41,资金台帐!$U$6:$U$6005,"其他支出",资金台帐!$O$6:$O$6005,IF($C$3="全部","?*",$C$3),资金台帐!$N$6:$N$6005,">="&DATE($F$3,1,1),资金台帐!$N$6:$N$6005,"<"&DATE($F$3,1+1,1))-SUMIFS(资金台帐!$AB$6:$AB$6005,资金台帐!$T$6:$T$6005,$Q41,资金台帐!$U$6:$U$6005,"其他支出",资金台帐!$O$6:$O$6005,IF($C$3="全部","?*",$C$3),资金台帐!$N$6:$N$6005,">="&DATE($F$3,1,1),资金台帐!$N$6:$N$6005,"<"&DATE($F$3,1+1,1)),2) -> 0 | D41: =ROUND(SUMIFS(资金台帐!$AC$6:$AC$6005,资金台帐!$T$6:$T$6005,$Q41,资金台帐!$U$6:$U$6005,"其他支出",资金台帐!$O$6:$O$6005,IF($C$3="全部","?*",$C$3),资金台帐!$N$6:$N$6005,">="&DATE($F$3,2,1),资金台帐!$N$6:$N$6005,"<"&DATE($F$3,2+1,1))-SUMIFS(资金台帐!$AB$6:$AB$6005,资金台帐!$T$6:$T$6005,$Q41,资金台帐!$U$6:$U$6005,"其他支出",资金台帐!$O$6:$O$6005,IF($C$3="全部","?*",$C$3),资金台帐!$N$6:$N$6005,">="&DATE($F$3,2,1),资金台帐!$N$6:$N$6005,"<"&DATE($F$3,2+1,1)),2) -> 0 | E41: =ROUND(SUMIFS(资金台帐!$AC$6:$AC$6005,资金台帐!$T$6:$T$6005,$Q41,资金台帐!$U$6:$U$6005,"其他支出",资金台帐!$O$6:$O$6005,IF($C$3="全部","?*",$C$3),资金台帐!$N$6:$N$6005,">="&DATE($F$3,3,1),资金台帐!$N$6:$N$6005,"<"&DATE($F$3,3+1,1))-SUMIFS(资金台帐!$AB$6:$AB$6005,资金台帐!$T$6:$T$6005,$Q41,资金台帐!$U$6:$U$6005,"其他支出",资金台帐!$O$6:$O$6005,IF($C$3="全部","?*",$C$3),资金台帐!$N$6:$N$6005,">="&DATE($F$3,3,1),资金台帐!$N$6:$N$6005,"<"&DATE($F$3,3+1,1)),2) -> 0 | F41: =ROUND(SUMIFS(资金台帐!$AC$6:$AC$6005,资金台帐!$T$6:$T$6005,$Q41,资金台帐!$U$6:$U$6005,"其他支出",资金台帐!$O$6:$O$6005,IF($C$3="全部","?*",$C$3),资金台帐!$N$6:$N$6005,">="&DATE($F$3,4,1),资金台帐!$N$6:$N$6005,"<"&DATE($F$3,4+1,1))-SUMIFS(资金台帐!$AB$6:$AB$6005,资金台帐!$T$6:$T$6005,$Q41,资金台帐!$U$6:$U$6005,"其他支出",资金台帐!$O$6:$O$6005,IF($C$3="全部","?*",$C$3),资金台帐!$N$6:$N$6005,">="&DATE($F$3,4,1),资金台帐!$N$6:$N$6005,"<"&DATE($F$3,4+1,1)),2) -> 0 | G41: =ROUND(SUMIFS(资金台帐!$AC$6:$AC$6005,资金台帐!$T$6:$T$6005,$Q41,资金台帐!$U$6:$U$6005,"其他支出",资金台帐!$O$6:$O$6005,IF($C$3="全部","?*",$C$3),资金台帐!$N$6:$N$6005,">="&DATE($F$3,5,1),资金台帐!$N$6:$N$6005,"<"&DATE($F$3,5+1,1))-SUMIFS(资金台帐!$AB$6:$AB$6005,资金台帐!$T$6:$T$6005,$Q41,资金台帐!$U$6:$U$6005,"其他支出",资金台帐!$O$6:$O$6005,IF($C$3="全部","?*",$C$3),资金台帐!$N$6:$N$6005,">="&DATE($F$3,5,1),资金台帐!$N$6:$N$6005,"<"&DATE($F$3,5+1,1)),2) -> 0 | H41: =ROUND(SUMIFS(资金台帐!$AC$6:$AC$6005,资金台帐!$T$6:$T$6005,$Q41,资金台帐!$U$6:$U$6005,"其他支出",资金台帐!$O$6:$O$6005,IF($C$3="全部","?*",$C$3),资金台帐!$N$6:$N$6005,">="&DATE($F$3,6,1),资金台帐!$N$6:$N$6005,"<"&DATE($F$3,6+1,1))-SUMIFS(资金台帐!$AB$6:$AB$6005,资金台帐!$T$6:$T$6005,$Q41,资金台帐!$U$6:$U$6005,"其他支出",资金台帐!$O$6:$O$6005,IF($C$3="全部","?*",$C$3),资金台帐!$N$6:$N$6005,">="&DATE($F$3,6,1),资金台帐!$N$6:$N$6005,"<"&DATE($F$3,6+1,1)),2) -> 0 | I41: =ROUND(SUMIFS(资金台帐!$AC$6:$AC$6005,资金台帐!$T$6:$T$6005,$Q41,资金台帐!$U$6:$U$6005,"其他支出",资金台帐!$O$6:$O$6005,IF($C$3="全部","?*",$C$3),资金台帐!$N$6:$N$6005,">="&DATE($F$3,7,1),资金台帐!$N$6:$N$6005,"<"&DATE($F$3,7+1,1))-SUMIFS(资金台帐!$AB$6:$AB$6005,资金台帐!$T$6:$T$6005,$Q41,资金台帐!$U$6:$U$6005,"其他支出",资金台帐!$O$6:$O$6005,IF($C$3="全部","?*",$C$3),资金台帐!$N$6:$N$6005,">="&DATE($F$3,7,1),资金台帐!$N$6:$N$6005,"<"&DATE($F$3,7+1,1)),2) -> 0 | J41: =ROUND(SUMIFS(资金台帐!$AC$6:$AC$6005,资金台帐!$T$6:$T$6005,$Q41,资金台帐!$U$6:$U$6005,"其他支出",资金台帐!$O$6:$O$6005,IF($C$3="全部","?*",$C$3),资金台帐!$N$6:$N$6005,">="&DATE($F$3,8,1),资金台帐!$N$6:$N$6005,"<"&DATE($F$3,8+1,1))-SUMIFS(资金台帐!$AB$6:$AB$6005,资金台帐!$T$6:$T$6005,$Q41,资金台帐!$U$6:$U$6005,"其他支出",资金台帐!$O$6:$O$6005,IF($C$3="全部","?*",$C$3),资金台帐!$N$6:$N$6005,">="&DATE($F$3,8,1),资金台帐!$N$6:$N$6005,"<"&DATE($F$3,8+1,1)),2) -> 0 | K41: =ROUND(SUMIFS(资金台帐!$AC$6:$AC$6005,资金台帐!$T$6:$T$6005,$Q41,资金台帐!$U$6:$U$6005,"其他支出",资金台帐!$O$6:$O$6005,IF($C$3="全部","?*",$C$3),资金台帐!$N$6:$N$6005,">="&DATE($F$3,9,1),资金台帐!$N$6:$N$6005,"<"&DATE($F$3,9+1,1))-SUMIFS(资金台帐!$AB$6:$AB$6005,资金台帐!$T$6:$T$6005,$Q41,资金台帐!$U$6:$U$6005,"其他支出",资金台帐!$O$6:$O$6005,IF($C$3="全部","?*",$C$3),资金台帐!$N$6:$N$6005,">="&DATE($F$3,9,1),资金台帐!$N$6:$N$6005,"<"&DATE($F$3,9+1,1)),2) -> 0 | L41: =ROUND(SUMIFS(资金台帐!$AC$6:$AC$6005,资金台帐!$T$6:$T$6005,$Q41,资金台帐!$U$6:$U$6005,"其他支出",资金台帐!$O$6:$O$6005,IF($C$3="全部","?*",$C$3),资金台帐!$N$6:$N$6005,">="&DATE($F$3,10,1),资金台帐!$N$6:$N$6005,"<"&DATE($F$3,10+1,1))-SUMIFS(资金台帐!$AB$6:$AB$6005,资金台帐!$T$6:$T$6005,$Q41,资金台帐!$U$6:$U$6005,"其他支出",资金台帐!$O$6:$O$6005,IF($C$3="全部","?*",$C$3),资金台帐!$N$6:$N$6005,">="&DATE($F$3,10,1),资金台帐!$N$6:$N$6005,"<"&DATE($F$3,10+1,1)),2) -> 0 | M41: =ROUND(SUMIFS(资金台帐!$AC$6:$AC$6005,资金台帐!$T$6:$T$6005,$Q41,资金台帐!$U$6:$U$6005,"其他支出",资金台帐!$O$6:$O$6005,IF($C$3="全部","?*",$C$3),资金台帐!$N$6:$N$6005,">="&DATE($F$3,11,1),资金台帐!$N$6:$N$6005,"<"&DATE($F$3,11+1,1))-SUMIFS(资金台帐!$AB$6:$AB$6005,资金台帐!$T$6:$T$6005,$Q41,资金台帐!$U$6:$U$6005,"其他支出",资金台帐!$O$6:$O$6005,IF($C$3="全部","?*",$C$3),资金台帐!$N$6:$N$6005,">="&DATE($F$3,11,1),资金台帐!$N$6:$N$6005,"<"&DATE($F$3,11+1,1)),2) -> 0 | N41: =ROUND(SUMIFS(资金台帐!$AC$6:$AC$6005,资金台帐!$T$6:$T$6005,$Q41,资金台帐!$U$6:$U$6005,"其他支出",资金台帐!$O$6:$O$6005,IF($C$3="全部","?*",$C$3),资金台帐!$N$6:$N$6005,">="&DATE($F$3,12,1),资金台帐!$N$6:$N$6005,"<"&DATE($F$3,12+1,1))-SUMIFS(资金台帐!$AB$6:$AB$6005,资金台帐!$T$6:$T$6005,$Q41,资金台帐!$U$6:$U$6005,"其他支出",资金台帐!$O$6:$O$6005,IF($C$3="全部","?*",$C$3),资金台帐!$N$6:$N$6005,">="&DATE($F$3,12,1),资金台帐!$N$6:$N$6005,"<"&DATE($F$3,12+1,1)),2) -> 0 | O41: =ROUND(SUM(C41:N41),2) -> 0 | P41: =IF(N($O$16)=0,"",O41/$O$16) -> 0 | Q41: =基础资料!$U$35&"" -> 工资挂靠
B42: =IF(基础资料!$W$36="",基础资料!$U$36&"",基础资料!$W$36&"") -> 社保挂靠 | C42: =ROUND(SUMIFS(资金台帐!$AC$6:$AC$6005,资金台帐!$T$6:$T$6005,$Q42,资金台帐!$U$6:$U$6005,"其他支出",资金台帐!$O$6:$O$6005,IF($C$3="全部","?*",$C$3),资金台帐!$N$6:$N$6005,">="&DATE($F$3,1,1),资金台帐!$N$6:$N$6005,"<"&DATE($F$3,1+1,1))-SUMIFS(资金台帐!$AB$6:$AB$6005,资金台帐!$T$6:$T$6005,$Q42,资金台帐!$U$6:$U$6005,"其他支出",资金台帐!$O$6:$O$6005,IF($C$3="全部","?*",$C$3),资金台帐!$N$6:$N$6005,">="&DATE($F$3,1,1),资金台帐!$N$6:$N$6005,"<"&DATE($F$3,1+1,1)),2) -> 0 | D42: =ROUND(SUMIFS(资金台帐!$AC$6:$AC$6005,资金台帐!$T$6:$T$6005,$Q42,资金台帐!$U$6:$U$6005,"其他支出",资金台帐!$O$6:$O$6005,IF($C$3="全部","?*",$C$3),资金台帐!$N$6:$N$6005,">="&DATE($F$3,2,1),资金台帐!$N$6:$N$6005,"<"&DATE($F$3,2+1,1))-SUMIFS(资金台帐!$AB$6:$AB$6005,资金台帐!$T$6:$T$6005,$Q42,资金台帐!$U$6:$U$6005,"其他支出",资金台帐!$O$6:$O$6005,IF($C$3="全部","?*",$C$3),资金台帐!$N$6:$N$6005,">="&DATE($F$3,2,1),资金台帐!$N$6:$N$6005,"<"&DATE($F$3,2+1,1)),2) -> 0 | E42: =ROUND(SUMIFS(资金台帐!$AC$6:$AC$6005,资金台帐!$T$6:$T$6005,$Q42,资金台帐!$U$6:$U$6005,"其他支出",资金台帐!$O$6:$O$6005,IF($C$3="全部","?*",$C$3),资金台帐!$N$6:$N$6005,">="&DATE($F$3,3,1),资金台帐!$N$6:$N$6005,"<"&DATE($F$3,3+1,1))-SUMIFS(资金台帐!$AB$6:$AB$6005,资金台帐!$T$6:$T$6005,$Q42,资金台帐!$U$6:$U$6005,"其他支出",资金台帐!$O$6:$O$6005,IF($C$3="全部","?*",$C$3),资金台帐!$N$6:$N$6005,">="&DATE($F$3,3,1),资金台帐!$N$6:$N$6005,"<"&DATE($F$3,3+1,1)),2) -> 0 | F42: =ROUND(SUMIFS(资金台帐!$AC$6:$AC$6005,资金台帐!$T$6:$T$6005,$Q42,资金台帐!$U$6:$U$6005,"其他支出",资金台帐!$O$6:$O$6005,IF($C$3="全部","?*",$C$3),资金台帐!$N$6:$N$6005,">="&DATE($F$3,4,1),资金台帐!$N$6:$N$6005,"<"&DATE($F$3,4+1,1))-SUMIFS(资金台帐!$AB$6:$AB$6005,资金台帐!$T$6:$T$6005,$Q42,资金台帐!$U$6:$U$6005,"其他支出",资金台帐!$O$6:$O$6005,IF($C$3="全部","?*",$C$3),资金台帐!$N$6:$N$6005,">="&DATE($F$3,4,1),资金台帐!$N$6:$N$6005,"<"&DATE($F$3,4+1,1)),2) -> 0 | G42: =ROUND(SUMIFS(资金台帐!$AC$6:$AC$6005,资金台帐!$T$6:$T$6005,$Q42,资金台帐!$U$6:$U$6005,"其他支出",资金台帐!$O$6:$O$6005,IF($C$3="全部","?*",$C$3),资金台帐!$N$6:$N$6005,">="&DATE($F$3,5,1),资金台帐!$N$6:$N$6005,"<"&DATE($F$3,5+1,1))-SUMIFS(资金台帐!$AB$6:$AB$6005,资金台帐!$T$6:$T$6005,$Q42,资金台帐!$U$6:$U$6005,"其他支出",资金台帐!$O$6:$O$6005,IF($C$3="全部","?*",$C$3),资金台帐!$N$6:$N$6005,">="&DATE($F$3,5,1),资金台帐!$N$6:$N$6005,"<"&DATE($F$3,5+1,1)),2) -> 0 | H42: =ROUND(SUMIFS(资金台帐!$AC$6:$AC$6005,资金台帐!$T$6:$T$6005,$Q42,资金台帐!$U$6:$U$6005,"其他支出",资金台帐!$O$6:$O$6005,IF($C$3="全部","?*",$C$3),资金台帐!$N$6:$N$6005,">="&DATE($F$3,6,1),资金台帐!$N$6:$N$6005,"<"&DATE($F$3,6+1,1))-SUMIFS(资金台帐!$AB$6:$AB$6005,资金台帐!$T$6:$T$6005,$Q42,资金台帐!$U$6:$U$6005,"其他支出",资金台帐!$O$6:$O$6005,IF($C$3="全部","?*",$C$3),资金台帐!$N$6:$N$6005,">="&DATE($F$3,6,1),资金台帐!$N$6:$N$6005,"<"&DATE($F$3,6+1,1)),2) -> 0 | I42: =ROUND(SUMIFS(资金台帐!$AC$6:$AC$6005,资金台帐!$T$6:$T$6005,$Q42,资金台帐!$U$6:$U$6005,"其他支出",资金台帐!$O$6:$O$6005,IF($C$3="全部","?*",$C$3),资金台帐!$N$6:$N$6005,">="&DATE($F$3,7,1),资金台帐!$N$6:$N$6005,"<"&DATE($F$3,7+1,1))-SUMIFS(资金台帐!$AB$6:$AB$6005,资金台帐!$T$6:$T$6005,$Q42,资金台帐!$U$6:$U$6005,"其他支出",资金台帐!$O$6:$O$6005,IF($C$3="全部","?*",$C$3),资金台帐!$N$6:$N$6005,">="&DATE($F$3,7,1),资金台帐!$N$6:$N$6005,"<"&DATE($F$3,7+1,1)),2) -> 0 | J42: =ROUND(SUMIFS(资金台帐!$AC$6:$AC$6005,资金台帐!$T$6:$T$6005,$Q42,资金台帐!$U$6:$U$6005,"其他支出",资金台帐!$O$6:$O$6005,IF($C$3="全部","?*",$C$3),资金台帐!$N$6:$N$6005,">="&DATE($F$3,8,1),资金台帐!$N$6:$N$6005,"<"&DATE($F$3,8+1,1))-SUMIFS(资金台帐!$AB$6:$AB$6005,资金台帐!$T$6:$T$6005,$Q42,资金台帐!$U$6:$U$6005,"其他支出",资金台帐!$O$6:$O$6005,IF($C$3="全部","?*",$C$3),资金台帐!$N$6:$N$6005,">="&DATE($F$3,8,1),资金台帐!$N$6:$N$6005,"<"&DATE($F$3,8+1,1)),2) -> 0 | K42: =ROUND(SUMIFS(资金台帐!$AC$6:$AC$6005,资金台帐!$T$6:$T$6005,$Q42,资金台帐!$U$6:$U$6005,"其他支出",资金台帐!$O$6:$O$6005,IF($C$3="全部","?*",$C$3),资金台帐!$N$6:$N$6005,">="&DATE($F$3,9,1),资金台帐!$N$6:$N$6005,"<"&DATE($F$3,9+1,1))-SUMIFS(资金台帐!$AB$6:$AB$6005,资金台帐!$T$6:$T$6005,$Q42,资金台帐!$U$6:$U$6005,"其他支出",资金台帐!$O$6:$O$6005,IF($C$3="全部","?*",$C$3),资金台帐!$N$6:$N$6005,">="&DATE($F$3,9,1),资金台帐!$N$6:$N$6005,"<"&DATE($F$3,9+1,1)),2) -> 0 | L42: =ROUND(SUMIFS(资金台帐!$AC$6:$AC$6005,资金台帐!$T$6:$T$6005,$Q42,资金台帐!$U$6:$U$6005,"其他支出",资金台帐!$O$6:$O$6005,IF($C$3="全部","?*",$C$3),资金台帐!$N$6:$N$6005,">="&DATE($F$3,10,1),资金台帐!$N$6:$N$6005,"<"&DATE($F$3,10+1,1))-SUMIFS(资金台帐!$AB$6:$AB$6005,资金台帐!$T$6:$T$6005,$Q42,资金台帐!$U$6:$U$6005,"其他支出",资金台帐!$O$6:$O$6005,IF($C$3="全部","?*",$C$3),资金台帐!$N$6:$N$6005,">="&DATE($F$3,10,1),资金台帐!$N$6:$N$6005,"<"&DATE($F$3,10+1,1)),2) -> 0 | M42: =ROUND(SUMIFS(资金台帐!$AC$6:$AC$6005,资金台帐!$T$6:$T$6005,$Q42,资金台帐!$U$6:$U$6005,"其他支出",资金台帐!$O$6:$O$6005,IF($C$3="全部","?*",$C$3),资金台帐!$N$6:$N$6005,">="&DATE($F$3,11,1),资金台帐!$N$6:$N$6005,"<"&DATE($F$3,11+1,1))-SUMIFS(资金台帐!$AB$6:$AB$6005,资金台帐!$T$6:$T$6005,$Q42,资金台帐!$U$6:$U$6005,"其他支出",资金台帐!$O$6:$O$6005,IF($C$3="全部","?*",$C$3),资金台帐!$N$6:$N$6005,">="&DATE($F$3,11,1),资金台帐!$N$6:$N$6005,"<"&DATE($F$3,11+1,1)),2) -> 0 | N42: =ROUND(SUMIFS(资金台帐!$AC$6:$AC$6005,资金台帐!$T$6:$T$6005,$Q42,资金台帐!$U$6:$U$6005,"其他支出",资金台帐!$O$6:$O$6005,IF($C$3="全部","?*",$C$3),资金台帐!$N$6:$N$6005,">="&DATE($F$3,12,1),资金台帐!$N$6:$N$6005,"<"&DATE($F$3,12+1,1))-SUMIFS(资金台帐!$AB$6:$AB$6005,资金台帐!$T$6:$T$6005,$Q42,资金台帐!$U$6:$U$6005,"其他支出",资金台帐!$O$6:$O$6005,IF($C$3="全部","?*",$C$3),资金台帐!$N$6:$N$6005,">="&DATE($F$3,12,1),资金台帐!$N$6:$N$6005,"<"&DATE($F$3,12+1,1)),2) -> 0 | O42: =ROUND(SUM(C42:N42),2) -> 0 | P42: =IF(N($O$16)=0,"",O42/$O$16) -> 0 | Q42: =基础资料!$U$36&"" -> 社保挂靠
B43: =IF(基础资料!$W$37="",基础资料!$U$37&"",基础资料!$W$37&"") -> 贷款利息 | C43: =ROUND(SUMIFS(资金台帐!$AC$6:$AC$6005,资金台帐!$T$6:$T$6005,$Q43,资金台帐!$U$6:$U$6005,"其他支出",资金台帐!$O$6:$O$6005,IF($C$3="全部","?*",$C$3),资金台帐!$N$6:$N$6005,">="&DATE($F$3,1,1),资金台帐!$N$6:$N$6005,"<"&DATE($F$3,1+1,1))-SUMIFS(资金台帐!$AB$6:$AB$6005,资金台帐!$T$6:$T$6005,$Q43,资金台帐!$U$6:$U$6005,"其他支出",资金台帐!$O$6:$O$6005,IF($C$3="全部","?*",$C$3),资金台帐!$N$6:$N$6005,">="&DATE($F$3,1,1),资金台帐!$N$6:$N$6005,"<"&DATE($F$3,1+1,1)),2) -> 0 | D43: =ROUND(SUMIFS(资金台帐!$AC$6:$AC$6005,资金台帐!$T$6:$T$6005,$Q43,资金台帐!$U$6:$U$6005,"其他支出",资金台帐!$O$6:$O$6005,IF($C$3="全部","?*",$C$3),资金台帐!$N$6:$N$6005,">="&DATE($F$3,2,1),资金台帐!$N$6:$N$6005,"<"&DATE($F$3,2+1,1))-SUMIFS(资金台帐!$AB$6:$AB$6005,资金台帐!$T$6:$T$6005,$Q43,资金台帐!$U$6:$U$6005,"其他支出",资金台帐!$O$6:$O$6005,IF($C$3="全部","?*",$C$3),资金台帐!$N$6:$N$6005,">="&DATE($F$3,2,1),资金台帐!$N$6:$N$6005,"<"&DATE($F$3,2+1,1)),2) -> 0 | E43: =ROUND(SUMIFS(资金台帐!$AC$6:$AC$6005,资金台帐!$T$6:$T$6005,$Q43,资金台帐!$U$6:$U$6005,"其他支出",资金台帐!$O$6:$O$6005,IF($C$3="全部","?*",$C$3),资金台帐!$N$6:$N$6005,">="&DATE($F$3,3,1),资金台帐!$N$6:$N$6005,"<"&DATE($F$3,3+1,1))-SUMIFS(资金台帐!$AB$6:$AB$6005,资金台帐!$T$6:$T$6005,$Q43,资金台帐!$U$6:$U$6005,"其他支出",资金台帐!$O$6:$O$6005,IF($C$3="全部","?*",$C$3),资金台帐!$N$6:$N$6005,">="&DATE($F$3,3,1),资金台帐!$N$6:$N$6005,"<"&DATE($F$3,3+1,1)),2) -> 0 | F43: =ROUND(SUMIFS(资金台帐!$AC$6:$AC$6005,资金台帐!$T$6:$T$6005,$Q43,资金台帐!$U$6:$U$6005,"其他支出",资金台帐!$O$6:$O$6005,IF($C$3="全部","?*",$C$3),资金台帐!$N$6:$N$6005,">="&DATE($F$3,4,1),资金台帐!$N$6:$N$6005,"<"&DATE($F$3,4+1,1))-SUMIFS(资金台帐!$AB$6:$AB$6005,资金台帐!$T$6:$T$6005,$Q43,资金台帐!$U$6:$U$6005,"其他支出",资金台帐!$O$6:$O$6005,IF($C$3="全部","?*",$C$3),资金台帐!$N$6:$N$6005,">="&DATE($F$3,4,1),资金台帐!$N$6:$N$6005,"<"&DATE($F$3,4+1,1)),2) -> 0 | G43: =ROUND(SUMIFS(资金台帐!$AC$6:$AC$6005,资金台帐!$T$6:$T$6005,$Q43,资金台帐!$U$6:$U$6005,"其他支出",资金台帐!$O$6:$O$6005,IF($C$3="全部","?*",$C$3),资金台帐!$N$6:$N$6005,">="&DATE($F$3,5,1),资金台帐!$N$6:$N$6005,"<"&DATE($F$3,5+1,1))-SUMIFS(资金台帐!$AB$6:$AB$6005,资金台帐!$T$6:$T$6005,$Q43,资金台帐!$U$6:$U$6005,"其他支出",资金台帐!$O$6:$O$6005,IF($C$3="全部","?*",$C$3),资金台帐!$N$6:$N$6005,">="&DATE($F$3,5,1),资金台帐!$N$6:$N$6005,"<"&DATE($F$3,5+1,1)),2) -> 0 | H43: =ROUND(SUMIFS(资金台帐!$AC$6:$AC$6005,资金台帐!$T$6:$T$6005,$Q43,资金台帐!$U$6:$U$6005,"其他支出",资金台帐!$O$6:$O$6005,IF($C$3="全部","?*",$C$3),资金台帐!$N$6:$N$6005,">="&DATE($F$3,6,1),资金台帐!$N$6:$N$6005,"<"&DATE($F$3,6+1,1))-SUMIFS(资金台帐!$AB$6:$AB$6005,资金台帐!$T$6:$T$6005,$Q43,资金台帐!$U$6:$U$6005,"其他支出",资金台帐!$O$6:$O$6005,IF($C$3="全部","?*",$C$3),资金台帐!$N$6:$N$6005,">="&DATE($F$3,6,1),资金台帐!$N$6:$N$6005,"<"&DATE($F$3,6+1,1)),2) -> 0 | I43: =ROUND(SUMIFS(资金台帐!$AC$6:$AC$6005,资金台帐!$T$6:$T$6005,$Q43,资金台帐!$U$6:$U$6005,"其他支出",资金台帐!$O$6:$O$6005,IF($C$3="全部","?*",$C$3),资金台帐!$N$6:$N$6005,">="&DATE($F$3,7,1),资金台帐!$N$6:$N$6005,"<"&DATE($F$3,7+1,1))-SUMIFS(资金台帐!$AB$6:$AB$6005,资金台帐!$T$6:$T$6005,$Q43,资金台帐!$U$6:$U$6005,"其他支出",资金台帐!$O$6:$O$6005,IF($C$3="全部","?*",$C$3),资金台帐!$N$6:$N$6005,">="&DATE($F$3,7,1),资金台帐!$N$6:$N$6005,"<"&DATE($F$3,7+1,1)),2) -> 0 | J43: =ROUND(SUMIFS(资金台帐!$AC$6:$AC$6005,资金台帐!$T$6:$T$6005,$Q43,资金台帐!$U$6:$U$6005,"其他支出",资金台帐!$O$6:$O$6005,IF($C$3="全部","?*",$C$3),资金台帐!$N$6:$N$6005,">="&DATE($F$3,8,1),资金台帐!$N$6:$N$6005,"<"&DATE($F$3,8+1,1))-SUMIFS(资金台帐!$AB$6:$AB$6005,资金台帐!$T$6:$T$6005,$Q43,资金台帐!$U$6:$U$6005,"其他支出",资金台帐!$O$6:$O$6005,IF($C$3="全部","?*",$C$3),资金台帐!$N$6:$N$6005,">="&DATE($F$3,8,1),资金台帐!$N$6:$N$6005,"<"&DATE($F$3,8+1,1)),2) -> 0 | K43: =ROUND(SUMIFS(资金台帐!$AC$6:$AC$6005,资金台帐!$T$6:$T$6005,$Q43,资金台帐!$U$6:$U$6005,"其他支出",资金台帐!$O$6:$O$6005,IF($C$3="全部","?*",$C$3),资金台帐!$N$6:$N$6005,">="&DATE($F$3,9,1),资金台帐!$N$6:$N$6005,"<"&DATE($F$3,9+1,1))-SUMIFS(资金台帐!$AB$6:$AB$6005,资金台帐!$T$6:$T$6005,$Q43,资金台帐!$U$6:$U$6005,"其他支出",资金台帐!$O$6:$O$6005,IF($C$3="全部","?*",$C$3),资金台帐!$N$6:$N$6005,">="&DATE($F$3,9,1),资金台帐!$N$6:$N$6005,"<"&DATE($F$3,9+1,1)),2) -> 0 | L43: =ROUND(SUMIFS(资金台帐!$AC$6:$AC$6005,资金台帐!$T$6:$T$6005,$Q43,资金台帐!$U$6:$U$6005,"其他支出",资金台帐!$O$6:$O$6005,IF($C$3="全部","?*",$C$3),资金台帐!$N$6:$N$6005,">="&DATE($F$3,10,1),资金台帐!$N$6:$N$6005,"<"&DATE($F$3,10+1,1))-SUMIFS(资金台帐!$AB$6:$AB$6005,资金台帐!$T$6:$T$6005,$Q43,资金台帐!$U$6:$U$6005,"其他支出",资金台帐!$O$6:$O$6005,IF($C$3="全部","?*",$C$3),资金台帐!$N$6:$N$6005,">="&DATE($F$3,10,1),资金台帐!$N$6:$N$6005,"<"&DATE($F$3,10+1,1)),2) -> 0 | M43: =ROUND(SUMIFS(资金台帐!$AC$6:$AC$6005,资金台帐!$T$6:$T$6005,$Q43,资金台帐!$U$6:$U$6005,"其他支出",资金台帐!$O$6:$O$6005,IF($C$3="全部","?*",$C$3),资金台帐!$N$6:$N$6005,">="&DATE($F$3,11,1),资金台帐!$N$6:$N$6005,"<"&DATE($F$3,11+1,1))-SUMIFS(资金台帐!$AB$6:$AB$6005,资金台帐!$T$6:$T$6005,$Q43,资金台帐!$U$6:$U$6005,"其他支出",资金台帐!$O$6:$O$6005,IF($C$3="全部","?*",$C$3),资金台帐!$N$6:$N$6005,">="&DATE($F$3,11,1),资金台帐!$N$6:$N$6005,"<"&DATE($F$3,11+1,1)),2) -> 0 | N43: =ROUND(SUMIFS(资金台帐!$AC$6:$AC$6005,资金台帐!$T$6:$T$6005,$Q43,资金台帐!$U$6:$U$6005,"其他支出",资金台帐!$O$6:$O$6005,IF($C$3="全部","?*",$C$3),资金台帐!$N$6:$N$6005,">="&DATE($F$3,12,1),资金台帐!$N$6:$N$6005,"<"&DATE($F$3,12+1,1))-SUMIFS(资金台帐!$AB$6:$AB$6005,资金台帐!$T$6:$T$6005,$Q43,资金台帐!$U$6:$U$6005,"其他支出",资金台帐!$O$6:$O$6005,IF($C$3="全部","?*",$C$3),资金台帐!$N$6:$N$6005,">="&DATE($F$3,12,1),资金台帐!$N$6:$N$6005,"<"&DATE($F$3,12+1,1)),2) -> 0 | O43: =ROUND(SUM(C43:N43),2) -> 0 | P43: =IF(N($O$16)=0,"",O43/$O$16) -> 0 | Q43: =基础资料!$U$37&"" -> 贷款利息
B44: =IF(COUNTIFS(基础资料!$V$5:$V$64,"其他支出",基础资料!$U$5:$U$64,"?*")>3,"其他（含新加项目）","其他") -> 其他 | C44: =ROUND(SUMIFS(资金台帐!$AC$6:$AC$6005,资金台帐!$U$6:$U$6005,"其他支出",资金台帐!$O$6:$O$6005,IF($C$3="全部","?*",$C$3),资金台帐!$N$6:$N$6005,">="&DATE($F$3,1,1),资金台帐!$N$6:$N$6005,"<"&DATE($F$3,1+1,1))-SUMIFS(资金台帐!$AB$6:$AB$6005,资金台帐!$U$6:$U$6005,"其他支出",资金台帐!$O$6:$O$6005,IF($C$3="全部","?*",$C$3),资金台帐!$N$6:$N$6005,">="&DATE($F$3,1,1),资金台帐!$N$6:$N$6005,"<"&DATE($F$3,1+1,1))-SUM(C41:C43),2) -> 0 | D44: =ROUND(SUMIFS(资金台帐!$AC$6:$AC$6005,资金台帐!$U$6:$U$6005,"其他支出",资金台帐!$O$6:$O$6005,IF($C$3="全部","?*",$C$3),资金台帐!$N$6:$N$6005,">="&DATE($F$3,2,1),资金台帐!$N$6:$N$6005,"<"&DATE($F$3,2+1,1))-SUMIFS(资金台帐!$AB$6:$AB$6005,资金台帐!$U$6:$U$6005,"其他支出",资金台帐!$O$6:$O$6005,IF($C$3="全部","?*",$C$3),资金台帐!$N$6:$N$6005,">="&DATE($F$3,2,1),资金台帐!$N$6:$N$6005,"<"&DATE($F$3,2+1,1))-SUM(D41:D43),2) -> 0 | E44: =ROUND(SUMIFS(资金台帐!$AC$6:$AC$6005,资金台帐!$U$6:$U$6005,"其他支出",资金台帐!$O$6:$O$6005,IF($C$3="全部","?*",$C$3),资金台帐!$N$6:$N$6005,">="&DATE($F$3,3,1),资金台帐!$N$6:$N$6005,"<"&DATE($F$3,3+1,1))-SUMIFS(资金台帐!$AB$6:$AB$6005,资金台帐!$U$6:$U$6005,"其他支出",资金台帐!$O$6:$O$6005,IF($C$3="全部","?*",$C$3),资金台帐!$N$6:$N$6005,">="&DATE($F$3,3,1),资金台帐!$N$6:$N$6005,"<"&DATE($F$3,3+1,1))-SUM(E41:E43),2) -> 0 | F44: =ROUND(SUMIFS(资金台帐!$AC$6:$AC$6005,资金台帐!$U$6:$U$6005,"其他支出",资金台帐!$O$6:$O$6005,IF($C$3="全部","?*",$C$3),资金台帐!$N$6:$N$6005,">="&DATE($F$3,4,1),资金台帐!$N$6:$N$6005,"<"&DATE($F$3,4+1,1))-SUMIFS(资金台帐!$AB$6:$AB$6005,资金台帐!$U$6:$U$6005,"其他支出",资金台帐!$O$6:$O$6005,IF($C$3="全部","?*",$C$3),资金台帐!$N$6:$N$6005,">="&DATE($F$3,4,1),资金台帐!$N$6:$N$6005,"<"&DATE($F$3,4+1,1))-SUM(F41:F43),2) -> 0 | G44: =ROUND(SUMIFS(资金台帐!$AC$6:$AC$6005,资金台帐!$U$6:$U$6005,"其他支出",资金台帐!$O$6:$O$6005,IF($C$3="全部","?*",$C$3),资金台帐!$N$6:$N$6005,">="&DATE($F$3,5,1),资金台帐!$N$6:$N$6005,"<"&DATE($F$3,5+1,1))-SUMIFS(资金台帐!$AB$6:$AB$6005,资金台帐!$U$6:$U$6005,"其他支出",资金台帐!$O$6:$O$6005,IF($C$3="全部","?*",$C$3),资金台帐!$N$6:$N$6005,">="&DATE($F$3,5,1),资金台帐!$N$6:$N$6005,"<"&DATE($F$3,5+1,1))-SUM(G41:G43),2) -> 0 | H44: =ROUND(SUMIFS(资金台帐!$AC$6:$AC$6005,资金台帐!$U$6:$U$6005,"其他支出",资金台帐!$O$6:$O$6005,IF($C$3="全部","?*",$C$3),资金台帐!$N$6:$N$6005,">="&DATE($F$3,6,1),资金台帐!$N$6:$N$6005,"<"&DATE($F$3,6+1,1))-SUMIFS(资金台帐!$AB$6:$AB$6005,资金台帐!$U$6:$U$6005,"其他支出",资金台帐!$O$6:$O$6005,IF($C$3="全部","?*",$C$3),资金台帐!$N$6:$N$6005,">="&DATE($F$3,6,1),资金台帐!$N$6:$N$6005,"<"&DATE($F$3,6+1,1))-SUM(H41:H43),2) -> 0 | I44: =ROUND(SUMIFS(资金台帐!$AC$6:$AC$6005,资金台帐!$U$6:$U$6005,"其他支出",资金台帐!$O$6:$O$6005,IF($C$3="全部","?*",$C$3),资金台帐!$N$6:$N$6005,">="&DATE($F$3,7,1),资金台帐!$N$6:$N$6005,"<"&DATE($F$3,7+1,1))-SUMIFS(资金台帐!$AB$6:$AB$6005,资金台帐!$U$6:$U$6005,"其他支出",资金台帐!$O$6:$O$6005,IF($C$3="全部","?*",$C$3),资金台帐!$N$6:$N$6005,">="&DATE($F$3,7,1),资金台帐!$N$6:$N$6005,"<"&DATE($F$3,7+1,1))-SUM(I41:I43),2) -> 0 | J44: =ROUND(SUMIFS(资金台帐!$AC$6:$AC$6005,资金台帐!$U$6:$U$6005,"其他支出",资金台帐!$O$6:$O$6005,IF($C$3="全部","?*",$C$3),资金台帐!$N$6:$N$6005,">="&DATE($F$3,8,1),资金台帐!$N$6:$N$6005,"<"&DATE($F$3,8+1,1))-SUMIFS(资金台帐!$AB$6:$AB$6005,资金台帐!$U$6:$U$6005,"其他支出",资金台帐!$O$6:$O$6005,IF($C$3="全部","?*",$C$3),资金台帐!$N$6:$N$6005,">="&DATE($F$3,8,1),资金台帐!$N$6:$N$6005,"<"&DATE($F$3,8+1,1))-SUM(J41:J43),2) -> 0 | K44: =ROUND(SUMIFS(资金台帐!$AC$6:$AC$6005,资金台帐!$U$6:$U$6005,"其他支出",资金台帐!$O$6:$O$6005,IF($C$3="全部","?*",$C$3),资金台帐!$N$6:$N$6005,">="&DATE($F$3,9,1),资金台帐!$N$6:$N$6005,"<"&DATE($F$3,9+1,1))-SUMIFS(资金台帐!$AB$6:$AB$6005,资金台帐!$U$6:$U$6005,"其他支出",资金台帐!$O$6:$O$6005,IF($C$3="全部","?*",$C$3),资金台帐!$N$6:$N$6005,">="&DATE($F$3,9,1),资金台帐!$N$6:$N$6005,"<"&DATE($F$3,9+1,1))-SUM(K41:K43),2) -> 0 | L44: =ROUND(SUMIFS(资金台帐!$AC$6:$AC$6005,资金台帐!$U$6:$U$6005,"其他支出",资金台帐!$O$6:$O$6005,IF($C$3="全部","?*",$C$3),资金台帐!$N$6:$N$6005,">="&DATE($F$3,10,1),资金台帐!$N$6:$N$6005,"<"&DATE($F$3,10+1,1))-SUMIFS(资金台帐!$AB$6:$AB$6005,资金台帐!$U$6:$U$6005,"其他支出",资金台帐!$O$6:$O$6005,IF($C$3="全部","?*",$C$3),资金台帐!$N$6:$N$6005,">="&DATE($F$3,10,1),资金台帐!$N$6:$N$6005,"<"&DATE($F$3,10+1,1))-SUM(L41:L43),2) -> 0 | M44: =ROUND(SUMIFS(资金台帐!$AC$6:$AC$6005,资金台帐!$U$6:$U$6005,"其他支出",资金台帐!$O$6:$O$6005,IF($C$3="全部","?*",$C$3),资金台帐!$N$6:$N$6005,">="&DATE($F$3,11,1),资金台帐!$N$6:$N$6005,"<"&DATE($F$3,11+1,1))-SUMIFS(资金台帐!$AB$6:$AB$6005,资金台帐!$U$6:$U$6005,"其他支出",资金台帐!$O$6:$O$6005,IF($C$3="全部","?*",$C$3),资金台帐!$N$6:$N$6005,">="&DATE($F$3,11,1),资金台帐!$N$6:$N$6005,"<"&DATE($F$3,11+1,1))-SUM(M41:M43),2) -> 0 | N44: =ROUND(SUMIFS(资金台帐!$AC$6:$AC$6005,资金台帐!$U$6:$U$6005,"其他支出",资金台帐!$O$6:$O$6005,IF($C$3="全部","?*",$C$3),资金台帐!$N$6:$N$6005,">="&DATE($F$3,12,1),资金台帐!$N$6:$N$6005,"<"&DATE($F$3,12+1,1))-SUMIFS(资金台帐!$AB$6:$AB$6005,资金台帐!$U$6:$U$6005,"其他支出",资金台帐!$O$6:$O$6005,IF($C$3="全部","?*",$C$3),资金台帐!$N$6:$N$6005,">="&DATE($F$3,12,1),资金台帐!$N$6:$N$6005,"<"&DATE($F$3,12+1,1))-SUM(N41:N43),2) -> 0 | O44: =ROUND(SUM(C44:N44),2) -> 0 | P44: =IF(N($O$16)=0,"",O44/$O$16) -> 0
B45: 其他支出小计 | C45: =ROUND(SUM(C41:C44),2) -> 0 | D45: =ROUND(SUM(D41:D44),2) -> 0 | E45: =ROUND(SUM(E41:E44),2) -> 0 | F45: =ROUND(SUM(F41:F44),2) -> 0 | G45: =ROUND(SUM(G41:G44),2) -> 0 | H45: =ROUND(SUM(H41:H44),2) -> 0 | I45: =ROUND(SUM(I41:I44),2) -> 0 | J45: =ROUND(SUM(J41:J44),2) -> 0 | ... O45: =ROUND(SUM(O41:O44),2) -> 0 | P45: =IF(N($O$16)=0,"",O45/$O$16) -> 0
A46: 收到为准 | B46: 实收资本 | C46: =ROUND(SUMIFS(资金台帐!$AB$6:$AB$6005,资金台帐!$U$6:$U$6005,"收到为准",资金台帐!$O$6:$O$6005,IF($C$3="全部","?*",$C$3),资金台帐!$N$6:$N$6005,">="&DATE($F$3,1,1),资金台帐!$N$6:$N$6005,"<"&DATE($F$3,1+1,1))-SUMIFS(资金台帐!$AC$6:$AC$6005,资金台帐!$U$6:$U$6005,"收到为准",资金台帐!$O$6:$O$6005,IF($C$3="全部","?*",$C$3),资金台帐!$N$6:$N$6005,">="&DATE($F$3,1,1),资金台帐!$N$6:$N$6005,"<"&DATE($F$3,1+1,1)),2) -> 0 | D46: =ROUND(SUMIFS(资金台帐!$AB$6:$AB$6005,资金台帐!$U$6:$U$6005,"收到为准",资金台帐!$O$6:$O$6005,IF($C$3="全部","?*",$C$3),资金台帐!$N$6:$N$6005,">="&DATE($F$3,2,1),资金台帐!$N$6:$N$6005,"<"&DATE($F$3,2+1,1))-SUMIFS(资金台帐!$AC$6:$AC$6005,资金台帐!$U$6:$U$6005,"收到为准",资金台帐!$O$6:$O$6005,IF($C$3="全部","?*",$C$3),资金台帐!$N$6:$N$6005,">="&DATE($F$3,2,1),资金台帐!$N$6:$N$6005,"<"&DATE($F$3,2+1,1)),2) -> 0 | E46: =ROUND(SUMIFS(资金台帐!$AB$6:$AB$6005,资金台帐!$U$6:$U$6005,"收到为准",资金台帐!$O$6:$O$6005,IF($C$3="全部","?*",$C$3),资金台帐!$N$6:$N$6005,">="&DATE($F$3,3,1),资金台帐!$N$6:$N$6005,"<"&DATE($F$3,3+1,1))-SUMIFS(资金台帐!$AC$6:$AC$6005,资金台帐!$U$6:$U$6005,"收到为准",资金台帐!$O$6:$O$6005,IF($C$3="全部","?*",$C$3),资金台帐!$N$6:$N$6005,">="&DATE($F$3,3,1),资金台帐!$N$6:$N$6005,"<"&DATE($F$3,3+1,1)),2) -> 0 | F46: =ROUND(SUMIFS(资金台帐!$AB$6:$AB$6005,资金台帐!$U$6:$U$6005,"收到为准",资金台帐!$O$6:$O$6005,IF($C$3="全部","?*",$C$3),资金台帐!$N$6:$N$6005,">="&DATE($F$3,4,1),资金台帐!$N$6:$N$6005,"<"&DATE($F$3,4+1,1))-SUMIFS(资金台帐!$AC$6:$AC$6005,资金台帐!$U$6:$U$6005,"收到为准",资金台帐!$O$6:$O$6005,IF($C$3="全部","?*",$C$3),资金台帐!$N$6:$N$6005,">="&DATE($F$3,4,1),资金台帐!$N$6:$N$6005,"<"&DATE($F$3,4+1,1)),2) -> 0 | G46: =ROUND(SUMIFS(资金台帐!$AB$6:$AB$6005,资金台帐!$U$6:$U$6005,"收到为准",资金台帐!$O$6:$O$6005,IF($C$3="全部","?*",$C$3),资金台帐!$N$6:$N$6005,">="&DATE($F$3,5,1),资金台帐!$N$6:$N$6005,"<"&DATE($F$3,5+1,1))-SUMIFS(资金台帐!$AC$6:$AC$6005,资金台帐!$U$6:$U$6005,"收到为准",资金台帐!$O$6:$O$6005,IF($C$3="全部","?*",$C$3),资金台帐!$N$6:$N$6005,">="&DATE($F$3,5,1),资金台帐!$N$6:$N$6005,"<"&DATE($F$3,5+1,1)),2) -> 0 | H46: =ROUND(SUMIFS(资金台帐!$AB$6:$AB$6005,资金台帐!$U$6:$U$6005,"收到为准",资金台帐!$O$6:$O$6005,IF($C$3="全部","?*",$C$3),资金台帐!$N$6:$N$6005,">="&DATE($F$3,6,1),资金台帐!$N$6:$N$6005,"<"&DATE($F$3,6+1,1))-SUMIFS(资金台帐!$AC$6:$AC$6005,资金台帐!$U$6:$U$6005,"收到为准",资金台帐!$O$6:$O$6005,IF($C$3="全部","?*",$C$3),资金台帐!$N$6:$N$6005,">="&DATE($F$3,6,1),资金台帐!$N$6:$N$6005,"<"&DATE($F$3,6+1,1)),2) -> 0 | I46: =ROUND(SUMIFS(资金台帐!$AB$6:$AB$6005,资金台帐!$U$6:$U$6005,"收到为准",资金台帐!$O$6:$O$6005,IF($C$3="全部","?*",$C$3),资金台帐!$N$6:$N$6005,">="&DATE($F$3,7,1),资金台帐!$N$6:$N$6005,"<"&DATE($F$3,7+1,1))-SUMIFS(资金台帐!$AC$6:$AC$6005,资金台帐!$U$6:$U$6005,"收到为准",资金台帐!$O$6:$O$6005,IF($C$3="全部","?*",$C$3),资金台帐!$N$6:$N$6005,">="&DATE($F$3,7,1),资金台帐!$N$6:$N$6005,"<"&DATE($F$3,7+1,1)),2) -> 0 | J46: =ROUND(SUMIFS(资金台帐!$AB$6:$AB$6005,资金台帐!$U$6:$U$6005,"收到为准",资金台帐!$O$6:$O$6005,IF($C$3="全部","?*",$C$3),资金台帐!$N$6:$N$6005,">="&DATE($F$3,8,1),资金台帐!$N$6:$N$6005,"<"&DATE($F$3,8+1,1))-SUMIFS(资金台帐!$AC$6:$AC$6005,资金台帐!$U$6:$U$6005,"收到为准",资金台帐!$O$6:$O$6005,IF($C$3="全部","?*",$C$3),资金台帐!$N$6:$N$6005,">="&DATE($F$3,8,1),资金台帐!$N$6:$N$6005,"<"&DATE($F$3,8+1,1)),2) -> 0 | K46: =ROUND(SUMIFS(资金台帐!$AB$6:$AB$6005,资金台帐!$U$6:$U$6005,"收到为准",资金台帐!$O$6:$O$6005,IF($C$3="全部","?*",$C$3),资金台帐!$N$6:$N$6005,">="&DATE($F$3,9,1),资金台帐!$N$6:$N$6005,"<"&DATE($F$3,9+1,1))-SUMIFS(资金台帐!$AC$6:$AC$6005,资金台帐!$U$6:$U$6005,"收到为准",资金台帐!$O$6:$O$6005,IF($C$3="全部","?*",$C$3),资金台帐!$N$6:$N$6005,">="&DATE($F$3,9,1),资金台帐!$N$6:$N$6005,"<"&DATE($F$3,9+1,1)),2) -> 0 | L46: =ROUND(SUMIFS(资金台帐!$AB$6:$AB$6005,资金台帐!$U$6:$U$6005,"收到为准",资金台帐!$O$6:$O$6005,IF($C$3="全部","?*",$C$3),资金台帐!$N$6:$N$6005,">="&DATE($F$3,10,1),资金台帐!$N$6:$N$6005,"<"&DATE($F$3,10+1,1))-SUMIFS(资金台帐!$AC$6:$AC$6005,资金台帐!$U$6:$U$6005,"收到为准",资金台帐!$O$6:$O$6005,IF($C$3="全部","?*",$C$3),资金台帐!$N$6:$N$6005,">="&DATE($F$3,10,1),资金台帐!$N$6:$N$6005,"<"&DATE($F$3,10+1,1)),2) -> 0 | M46: =ROUND(SUMIFS(资金台帐!$AB$6:$AB$6005,资金台帐!$U$6:$U$6005,"收到为准",资金台帐!$O$6:$O$6005,IF($C$3="全部","?*",$C$3),资金台帐!$N$6:$N$6005,">="&DATE($F$3,11,1),资金台帐!$N$6:$N$6005,"<"&DATE($F$3,11+1,1))-SUMIFS(资金台帐!$AC$6:$AC$6005,资金台帐!$U$6:$U$6005,"收到为准",资金台帐!$O$6:$O$6005,IF($C$3="全部","?*",$C$3),资金台帐!$N$6:$N$6005,">="&DATE($F$3,11,1),资金台帐!$N$6:$N$6005,"<"&DATE($F$3,11+1,1)),2) -> 0 | N46: =ROUND(SUMIFS(资金台帐!$AB$6:$AB$6005,资金台帐!$U$6:$U$6005,"收到为准",资金台帐!$O$6:$O$6005,IF($C$3="全部","?*",$C$3),资金台帐!$N$6:$N$6005,">="&DATE($F$3,12,1),资金台帐!$N$6:$N$6005,"<"&DATE($F$3,12+1,1))-SUMIFS(资金台帐!$AC$6:$AC$6005,资金台帐!$U$6:$U$6005,"收到为准",资金台帐!$O$6:$O$6005,IF($C$3="全部","?*",$C$3),资金台帐!$N$6:$N$6005,">="&DATE($F$3,12,1),资金台帐!$N$6:$N$6005,"<"&DATE($F$3,12+1,1)),2) -> 0 | O46: =ROUND(SUM(C46:N46),2) -> 0 | P46: =IF(N($O$16)=0,"",O46/$O$16) -> 0
A47: 支出为准 | B47: 投资 | C47: =ROUND(SUMIFS(资金台帐!$AC$6:$AC$6005,资金台帐!$U$6:$U$6005,"支出为准",资金台帐!$O$6:$O$6005,IF($C$3="全部","?*",$C$3),资金台帐!$N$6:$N$6005,">="&DATE($F$3,1,1),资金台帐!$N$6:$N$6005,"<"&DATE($F$3,1+1,1))-SUMIFS(资金台帐!$AB$6:$AB$6005,资金台帐!$U$6:$U$6005,"支出为准",资金台帐!$O$6:$O$6005,IF($C$3="全部","?*",$C$3),资金台帐!$N$6:$N$6005,">="&DATE($F$3,1,1),资金台帐!$N$6:$N$6005,"<"&DATE($F$3,1+1,1)),2) -> 0 | D47: =ROUND(SUMIFS(资金台帐!$AC$6:$AC$6005,资金台帐!$U$6:$U$6005,"支出为准",资金台帐!$O$6:$O$6005,IF($C$3="全部","?*",$C$3),资金台帐!$N$6:$N$6005,">="&DATE($F$3,2,1),资金台帐!$N$6:$N$6005,"<"&DATE($F$3,2+1,1))-SUMIFS(资金台帐!$AB$6:$AB$6005,资金台帐!$U$6:$U$6005,"支出为准",资金台帐!$O$6:$O$6005,IF($C$3="全部","?*",$C$3),资金台帐!$N$6:$N$6005,">="&DATE($F$3,2,1),资金台帐!$N$6:$N$6005,"<"&DATE($F$3,2+1,1)),2) -> 0 | E47: =ROUND(SUMIFS(资金台帐!$AC$6:$AC$6005,资金台帐!$U$6:$U$6005,"支出为准",资金台帐!$O$6:$O$6005,IF($C$3="全部","?*",$C$3),资金台帐!$N$6:$N$6005,">="&DATE($F$3,3,1),资金台帐!$N$6:$N$6005,"<"&DATE($F$3,3+1,1))-SUMIFS(资金台帐!$AB$6:$AB$6005,资金台帐!$U$6:$U$6005,"支出为准",资金台帐!$O$6:$O$6005,IF($C$3="全部","?*",$C$3),资金台帐!$N$6:$N$6005,">="&DATE($F$3,3,1),资金台帐!$N$6:$N$6005,"<"&DATE($F$3,3+1,1)),2) -> 0 | F47: =ROUND(SUMIFS(资金台帐!$AC$6:$AC$6005,资金台帐!$U$6:$U$6005,"支出为准",资金台帐!$O$6:$O$6005,IF($C$3="全部","?*",$C$3),资金台帐!$N$6:$N$6005,">="&DATE($F$3,4,1),资金台帐!$N$6:$N$6005,"<"&DATE($F$3,4+1,1))-SUMIFS(资金台帐!$AB$6:$AB$6005,资金台帐!$U$6:$U$6005,"支出为准",资金台帐!$O$6:$O$6005,IF($C$3="全部","?*",$C$3),资金台帐!$N$6:$N$6005,">="&DATE($F$3,4,1),资金台帐!$N$6:$N$6005,"<"&DATE($F$3,4+1,1)),2) -> 0 | G47: =ROUND(SUMIFS(资金台帐!$AC$6:$AC$6005,资金台帐!$U$6:$U$6005,"支出为准",资金台帐!$O$6:$O$6005,IF($C$3="全部","?*",$C$3),资金台帐!$N$6:$N$6005,">="&DATE($F$3,5,1),资金台帐!$N$6:$N$6005,"<"&DATE($F$3,5+1,1))-SUMIFS(资金台帐!$AB$6:$AB$6005,资金台帐!$U$6:$U$6005,"支出为准",资金台帐!$O$6:$O$6005,IF($C$3="全部","?*",$C$3),资金台帐!$N$6:$N$6005,">="&DATE($F$3,5,1),资金台帐!$N$6:$N$6005,"<"&DATE($F$3,5+1,1)),2) -> 0 | H47: =ROUND(SUMIFS(资金台帐!$AC$6:$AC$6005,资金台帐!$U$6:$U$6005,"支出为准",资金台帐!$O$6:$O$6005,IF($C$3="全部","?*",$C$3),资金台帐!$N$6:$N$6005,">="&DATE($F$3,6,1),资金台帐!$N$6:$N$6005,"<"&DATE($F$3,6+1,1))-SUMIFS(资金台帐!$AB$6:$AB$6005,资金台帐!$U$6:$U$6005,"支出为准",资金台帐!$O$6:$O$6005,IF($C$3="全部","?*",$C$3),资金台帐!$N$6:$N$6005,">="&DATE($F$3,6,1),资金台帐!$N$6:$N$6005,"<"&DATE($F$3,6+1,1)),2) -> 0 | I47: =ROUND(SUMIFS(资金台帐!$AC$6:$AC$6005,资金台帐!$U$6:$U$6005,"支出为准",资金台帐!$O$6:$O$6005,IF($C$3="全部","?*",$C$3),资金台帐!$N$6:$N$6005,">="&DATE($F$3,7,1),资金台帐!$N$6:$N$6005,"<"&DATE($F$3,7+1,1))-SUMIFS(资金台帐!$AB$6:$AB$6005,资金台帐!$U$6:$U$6005,"支出为准",资金台帐!$O$6:$O$6005,IF($C$3="全部","?*",$C$3),资金台帐!$N$6:$N$6005,">="&DATE($F$3,7,1),资金台帐!$N$6:$N$6005,"<"&DATE($F$3,7+1,1)),2) -> 0 | J47: =ROUND(SUMIFS(资金台帐!$AC$6:$AC$6005,资金台帐!$U$6:$U$6005,"支出为准",资金台帐!$O$6:$O$6005,IF($C$3="全部","?*",$C$3),资金台帐!$N$6:$N$6005,">="&DATE($F$3,8,1),资金台帐!$N$6:$N$6005,"<"&DATE($F$3,8+1,1))-SUMIFS(资金台帐!$AB$6:$AB$6005,资金台帐!$U$6:$U$6005,"支出为准",资金台帐!$O$6:$O$6005,IF($C$3="全部","?*",$C$3),资金台帐!$N$6:$N$6005,">="&DATE($F$3,8,1),资金台帐!$N$6:$N$6005,"<"&DATE($F$3,8+1,1)),2) -> 0 | K47: =ROUND(SUMIFS(资金台帐!$AC$6:$AC$6005,资金台帐!$U$6:$U$6005,"支出为准",资金台帐!$O$6:$O$6005,IF($C$3="全部","?*",$C$3),资金台帐!$N$6:$N$6005,">="&DATE($F$3,9,1),资金台帐!$N$6:$N$6005,"<"&DATE($F$3,9+1,1))-SUMIFS(资金台帐!$AB$6:$AB$6005,资金台帐!$U$6:$U$6005,"支出为准",资金台帐!$O$6:$O$6005,IF($C$3="全部","?*",$C$3),资金台帐!$N$6:$N$6005,">="&DATE($F$3,9,1),资金台帐!$N$6:$N$6005,"<"&DATE($F$3,9+1,1)),2) -> 0 | L47: =ROUND(SUMIFS(资金台帐!$AC$6:$AC$6005,资金台帐!$U$6:$U$6005,"支出为准",资金台帐!$O$6:$O$6005,IF($C$3="全部","?*",$C$3),资金台帐!$N$6:$N$6005,">="&DATE($F$3,10,1),资金台帐!$N$6:$N$6005,"<"&DATE($F$3,10+1,1))-SUMIFS(资金台帐!$AB$6:$AB$6005,资金台帐!$U$6:$U$6005,"支出为准",资金台帐!$O$6:$O$6005,IF($C$3="全部","?*",$C$3),资金台帐!$N$6:$N$6005,">="&DATE($F$3,10,1),资金台帐!$N$6:$N$6005,"<"&DATE($F$3,10+1,1)),2) -> 0 | M47: =ROUND(SUMIFS(资金台帐!$AC$6:$AC$6005,资金台帐!$U$6:$U$6005,"支出为准",资金台帐!$O$6:$O$6005,IF($C$3="全部","?*",$C$3),资金台帐!$N$6:$N$6005,">="&DATE($F$3,11,1),资金台帐!$N$6:$N$6005,"<"&DATE($F$3,11+1,1))-SUMIFS(资金台帐!$AB$6:$AB$6005,资金台帐!$U$6:$U$6005,"支出为准",资金台帐!$O$6:$O$6005,IF($C$3="全部","?*",$C$3),资金台帐!$N$6:$N$6005,">="&DATE($F$3,11,1),资金台帐!$N$6:$N$6005,"<"&DATE($F$3,11+1,1)),2) -> 0 | N47: =ROUND(SUMIFS(资金台帐!$AC$6:$AC$6005,资金台帐!$U$6:$U$6005,"支出为准",资金台帐!$O$6:$O$6005,IF($C$3="全部","?*",$C$3),资金台帐!$N$6:$N$6005,">="&DATE($F$3,12,1),资金台帐!$N$6:$N$6005,"<"&DATE($F$3,12+1,1))-SUMIFS(资金台帐!$AB$6:$AB$6005,资金台帐!$U$6:$U$6005,"支出为准",资金台帐!$O$6:$O$6005,IF($C$3="全部","?*",$C$3),资金台帐!$N$6:$N$6005,">="&DATE($F$3,12,1),资金台帐!$N$6:$N$6005,"<"&DATE($F$3,12+1,1)),2) -> 0 | O47: =ROUND(SUM(C47:N47),2) -> 0 | P47: =IF(N($O$16)=0,"",O47/$O$16) -> 0
B48: 往来（净收入） | C48: =ROUND(SUMIFS(资金台帐!$AB$6:$AB$6005,资金台帐!$U$6:$U$6005,"往来",资金台帐!$O$6:$O$6005,IF($C$3="全部","?*",$C$3),资金台帐!$N$6:$N$6005,">="&DATE($F$3,1,1),资金台帐!$N$6:$N$6005,"<"&DATE($F$3,1+1,1))-SUMIFS(资金台帐!$AC$6:$AC$6005,资金台帐!$U$6:$U$6005,"往来",资金台帐!$O$6:$O$6005,IF($C$3="全部","?*",$C$3),资金台帐!$N$6:$N$6005,">="&DATE($F$3,1,1),资金台帐!$N$6:$N$6005,"<"&DATE($F$3,1+1,1)),2) -> 0 | D48: =ROUND(SUMIFS(资金台帐!$AB$6:$AB$6005,资金台帐!$U$6:$U$6005,"往来",资金台帐!$O$6:$O$6005,IF($C$3="全部","?*",$C$3),资金台帐!$N$6:$N$6005,">="&DATE($F$3,2,1),资金台帐!$N$6:$N$6005,"<"&DATE($F$3,2+1,1))-SUMIFS(资金台帐!$AC$6:$AC$6005,资金台帐!$U$6:$U$6005,"往来",资金台帐!$O$6:$O$6005,IF($C$3="全部","?*",$C$3),资金台帐!$N$6:$N$6005,">="&DATE($F$3,2,1),资金台帐!$N$6:$N$6005,"<"&DATE($F$3,2+1,1)),2) -> 0 | E48: =ROUND(SUMIFS(资金台帐!$AB$6:$AB$6005,资金台帐!$U$6:$U$6005,"往来",资金台帐!$O$6:$O$6005,IF($C$3="全部","?*",$C$3),资金台帐!$N$6:$N$6005,">="&DATE($F$3,3,1),资金台帐!$N$6:$N$6005,"<"&DATE($F$3,3+1,1))-SUMIFS(资金台帐!$AC$6:$AC$6005,资金台帐!$U$6:$U$6005,"往来",资金台帐!$O$6:$O$6005,IF($C$3="全部","?*",$C$3),资金台帐!$N$6:$N$6005,">="&DATE($F$3,3,1),资金台帐!$N$6:$N$6005,"<"&DATE($F$3,3+1,1)),2) -> 0 | F48: =ROUND(SUMIFS(资金台帐!$AB$6:$AB$6005,资金台帐!$U$6:$U$6005,"往来",资金台帐!$O$6:$O$6005,IF($C$3="全部","?*",$C$3),资金台帐!$N$6:$N$6005,">="&DATE($F$3,4,1),资金台帐!$N$6:$N$6005,"<"&DATE($F$3,4+1,1))-SUMIFS(资金台帐!$AC$6:$AC$6005,资金台帐!$U$6:$U$6005,"往来",资金台帐!$O$6:$O$6005,IF($C$3="全部","?*",$C$3),资金台帐!$N$6:$N$6005,">="&DATE($F$3,4,1),资金台帐!$N$6:$N$6005,"<"&DATE($F$3,4+1,1)),2) -> 0 | G48: =ROUND(SUMIFS(资金台帐!$AB$6:$AB$6005,资金台帐!$U$6:$U$6005,"往来",资金台帐!$O$6:$O$6005,IF($C$3="全部","?*",$C$3),资金台帐!$N$6:$N$6005,">="&DATE($F$3,5,1),资金台帐!$N$6:$N$6005,"<"&DATE($F$3,5+1,1))-SUMIFS(资金台帐!$AC$6:$AC$6005,资金台帐!$U$6:$U$6005,"往来",资金台帐!$O$6:$O$6005,IF($C$3="全部","?*",$C$3),资金台帐!$N$6:$N$6005,">="&DATE($F$3,5,1),资金台帐!$N$6:$N$6005,"<"&DATE($F$3,5+1,1)),2) -> 0 | H48: =ROUND(SUMIFS(资金台帐!$AB$6:$AB$6005,资金台帐!$U$6:$U$6005,"往来",资金台帐!$O$6:$O$6005,IF($C$3="全部","?*",$C$3),资金台帐!$N$6:$N$6005,">="&DATE($F$3,6,1),资金台帐!$N$6:$N$6005,"<"&DATE($F$3,6+1,1))-SUMIFS(资金台帐!$AC$6:$AC$6005,资金台帐!$U$6:$U$6005,"往来",资金台帐!$O$6:$O$6005,IF($C$3="全部","?*",$C$3),资金台帐!$N$6:$N$6005,">="&DATE($F$3,6,1),资金台帐!$N$6:$N$6005,"<"&DATE($F$3,6+1,1)),2) -> 0 | I48: =ROUND(SUMIFS(资金台帐!$AB$6:$AB$6005,资金台帐!$U$6:$U$6005,"往来",资金台帐!$O$6:$O$6005,IF($C$3="全部","?*",$C$3),资金台帐!$N$6:$N$6005,">="&DATE($F$3,7,1),资金台帐!$N$6:$N$6005,"<"&DATE($F$3,7+1,1))-SUMIFS(资金台帐!$AC$6:$AC$6005,资金台帐!$U$6:$U$6005,"往来",资金台帐!$O$6:$O$6005,IF($C$3="全部","?*",$C$3),资金台帐!$N$6:$N$6005,">="&DATE($F$3,7,1),资金台帐!$N$6:$N$6005,"<"&DATE($F$3,7+1,1)),2) -> 0 | J48: =ROUND(SUMIFS(资金台帐!$AB$6:$AB$6005,资金台帐!$U$6:$U$6005,"往来",资金台帐!$O$6:$O$6005,IF($C$3="全部","?*",$C$3),资金台帐!$N$6:$N$6005,">="&DATE($F$3,8,1),资金台帐!$N$6:$N$6005,"<"&DATE($F$3,8+1,1))-SUMIFS(资金台帐!$AC$6:$AC$6005,资金台帐!$U$6:$U$6005,"往来",资金台帐!$O$6:$O$6005,IF($C$3="全部","?*",$C$3),资金台帐!$N$6:$N$6005,">="&DATE($F$3,8,1),资金台帐!$N$6:$N$6005,"<"&DATE($F$3,8+1,1)),2) -> 0 | K48: =ROUND(SUMIFS(资金台帐!$AB$6:$AB$6005,资金台帐!$U$6:$U$6005,"往来",资金台帐!$O$6:$O$6005,IF($C$3="全部","?*",$C$3),资金台帐!$N$6:$N$6005,">="&DATE($F$3,9,1),资金台帐!$N$6:$N$6005,"<"&DATE($F$3,9+1,1))-SUMIFS(资金台帐!$AC$6:$AC$6005,资金台帐!$U$6:$U$6005,"往来",资金台帐!$O$6:$O$6005,IF($C$3="全部","?*",$C$3),资金台帐!$N$6:$N$6005,">="&DATE($F$3,9,1),资金台帐!$N$6:$N$6005,"<"&DATE($F$3,9+1,1)),2) -> 0 | L48: =ROUND(SUMIFS(资金台帐!$AB$6:$AB$6005,资金台帐!$U$6:$U$6005,"往来",资金台帐!$O$6:$O$6005,IF($C$3="全部","?*",$C$3),资金台帐!$N$6:$N$6005,">="&DATE($F$3,10,1),资金台帐!$N$6:$N$6005,"<"&DATE($F$3,10+1,1))-SUMIFS(资金台帐!$AC$6:$AC$6005,资金台帐!$U$6:$U$6005,"往来",资金台帐!$O$6:$O$6005,IF($C$3="全部","?*",$C$3),资金台帐!$N$6:$N$6005,">="&DATE($F$3,10,1),资金台帐!$N$6:$N$6005,"<"&DATE($F$3,10+1,1)),2) -> 0 | M48: =ROUND(SUMIFS(资金台帐!$AB$6:$AB$6005,资金台帐!$U$6:$U$6005,"往来",资金台帐!$O$6:$O$6005,IF($C$3="全部","?*",$C$3),资金台帐!$N$6:$N$6005,">="&DATE($F$3,11,1),资金台帐!$N$6:$N$6005,"<"&DATE($F$3,11+1,1))-SUMIFS(资金台帐!$AC$6:$AC$6005,资金台帐!$U$6:$U$6005,"往来",资金台帐!$O$6:$O$6005,IF($C$3="全部","?*",$C$3),资金台帐!$N$6:$N$6005,">="&DATE($F$3,11,1),资金台帐!$N$6:$N$6005,"<"&DATE($F$3,11+1,1)),2) -> 0 | N48: =ROUND(SUMIFS(资金台帐!$AB$6:$AB$6005,资金台帐!$U$6:$U$6005,"往来",资金台帐!$O$6:$O$6005,IF($C$3="全部","?*",$C$3),资金台帐!$N$6:$N$6005,">="&DATE($F$3,12,1),资金台帐!$N$6:$N$6005,"<"&DATE($F$3,12+1,1))-SUMIFS(资金台帐!$AC$6:$AC$6005,资金台帐!$U$6:$U$6005,"往来",资金台帐!$O$6:$O$6005,IF($C$3="全部","?*",$C$3),资金台帐!$N$6:$N$6005,">="&DATE($F$3,12,1),资金台帐!$N$6:$N$6005,"<"&DATE($F$3,12+1,1)),2) -> 0 | O48: =ROUND(SUM(C48:N48),2) -> 0 | P48: =IF(N($O$16)=0,"",O48/$O$16) -> 0
