Workbook

Sheet Sheet1
A1: 多帐户收支登记表
F2: 收入总额 | G2: 支出总额 | H2: 账户余额
F3: 68868685 | G3: 67149704 | H3: 4429622.6
A4: 序号 | B4: 日期 | C4: 公司账户 | D4: 业务类别 | E4: 摘要内容 | F4: 收入 | G4: 支出 | H4: 账户余额 | I4: 公司 | J4: 电商平台 | K4: 会计科目 | L4: 收支所属月份 | M4: 返利名称 | N4: 月份 | O4: 员工
A5: 1 | B5: 46023 | C5: 邮政公户 | E5: 期初余额 | H5: 1674705.1 | N5: 202601
A6: 2 | B6: 46023 | C6: 农发行公户 | E6: 期初余额 | H6: 230615.22 | N6: 202601
A7: 3 | B7: 46023 | C7: 邢台银行公户 | E7: 期初余额 | H7: 61632.53 | N7: 202601
A8: 4 | B8: 46023 | C8: 农业银行公户 | E8: 期初余额 | H8: 81.65 | N8: 202601
A9: 5 | B9: 46023 | C9: 信用社公户 | E9: 期初余额 | H9: 57038.92
A10: 6 | B10: 46023 | C10: 建行公户 | E10: 期初余额 | H10: 81941.47 | N10: 202601
A11: 7 | B11: 46023 | C11: 沧州个人 | E11: 期初余额 | H11: 15.62 | N11: 202601
A12: 8 | B12: 46023 | C12: 信用社个人 | E12: 期初余额 | H12: 258118.28 | N12: 202601
A13: 9 | B13: 46023 | C13: 邮政个人 | E13: 期初余额 | H13: 292251.86 | N13: 202601
A14: 10 | B14: 46023 | C14: 建行个人 | E14: 期初余额 | H14: 51712.92 | N14: 202601
A15: 11 | B15: 46023 | C15: 现金 | E15: 期初余额 | H15: 2528.16 | N15: 202601
A16: 12 | B16: 46023 | C16: 五优68店邮政 | E16: 期初余额 | N16: 202601
A17: 13 | B17: 46023 | C17: 五优3店邮政 | E17: 期初余额 | N17: 202601
A18: 14 | B18: 46023 | C18: 五优43店邮政 | E18: 期初余额 | N18: 202601
A19: 15 | B19: 46023 | C19: 邮政个人 | D19: 营业款 | E19: 60店郭静钰 | F19: 350.68 | H19: 292602.54 | I19: 博景分店（60分店） | L19: 202512 | N19: 202601
A20: 16 | B20: 46023 | C20: 邮政个人 | D20: 营业款 | E20: 67店姜慧娟 | F20: 619.65 | H20: 293222.19 | I20: 博亮分店（67分店） | L20: 202512 | N20: 202601
A21: 17 | B21: 46023 | C21: 邮政个人 | D21: 营业款 | E21: 68店李国霞 | F21: 1837.2 | H21: 295059.39 | I21: 博山分店（68分店） | L21: 202512 | N21: 202601
A22: 18 | B22: 46023 | C22: 邮政个人 | D22: 营业款 | E22: 62店张彦 | F22: 1655.68 | H22: 296715.07 | I22: 西范村分店（62分店） | L22: 202512 | N22: 202601
A23: 19 | B23: 46023 | C23: 邮政个人 | D23: 营业款 | E23: 2店王玉彩 | F23: 31812.4 | H23: 328527.47 | I23: 新隆分店（2分店） | L23: 202512 | N23: 202601
A24: 20 | B24: 46023 | C24: 邮政个人 | D24: 营业款 | E24: 55店杨芳 | F24: 2336.46 | H24: 330863.93 | I24: 博魏分店（55分店） | L24: 202512 | N24: 202601
A25: 21 | B25: 46023 | C25: 邮政个人 | E25: 转入国燕岭工商银行 | G25: 300000 | H25: 30863.93 | I25: 股东借款 | L25: 202601 | N25: 202601
A26: 22 | B26: 46023 | C26: 邮政个人 | D26: 内部转账 | E26: 邮政公户转入邮政个人 | F26: 500000 | H26: 530863.93 | I26: 内部转款 | L26: 202601 | N26: 202601
A27: 23 | B27: 46024 | C27: 邮政个人 | E27: 转入国燕岭工商银行 | G27: 500000 | H27: 30863.93 | I27: 股东借款 | L27: 202601 | N27: 202601
A28: 24 | B28: 46024 | C28: 邮政个人 | D28: 营业款 | E28: 5店李永娜 | F28: 7465.09 | H28: 38329.02 | I28: 象城街分店（5店） | L28: 202512 | N28: 202601
A29: 25 | B29: 46024 | C29: 邮政个人 | D29: 营业款 | E29: 63店曹雪雪 | F29: 2972.05 | H29: 41301.07 | I29: 博医分店（63分店） | L29: 202512 | N29: 202601
A30: 26 | B30: 46024 | C30: 邮政个人 | D30: 营业款 | E30: 4店张彩红 | F30: 8103.01 | H30: 49404.08 | I30: 东关分店（4分店） | L30: 202512 | N30: 202601
A31: 27 | B31: 46024 | C31: 邮政个人 | D31: 营业款 | E31: 24店曹玉丽 | F31: 16033.13 | H31: 65437.21 | I31: 高村分店（24分店） | L31: 202512 | N31: 202601
A32: 28 | B32: 46024 | C32: 邮政个人 | D32: 营业款 | E32: 66店冯丽 | F32: 4593.28 | H32: 70030.49 | I32: 博实分店（66分店） | L32: 202512 | N32: 202601
A33: 29 | B33: 46024 | C33: 邮政个人 | D33: 营业款 | E33: 57店刘国华 | F33: 13343.62 | H33: 83374.11 | I33: 临城县博城分店（57分店） | L33: 202512 | N33: 202601
A34: 30 | B34: 46024 | C34: 邮政个人 | D34: 营业款 | E34: 23店田少芳 | F34: 3392.35 | H34: 86766.46 | I34: 尹村分店(23分店） | L34: 202512 | N34: 202601
A35: 31 | B35: 46025 | C35: 邮政个人 | D35: 营业款 | E35: 3店王惠娟 | F35: 5578.88 | H35: 92345.34 | I35: 康庄东路分店（3店） | L35: 202512 | N35: 202601
A36: 32 | B36: 46026 | C36: 邮政个人 | D36: 营业款 | E36: 2店王玉彩 | F36: 28189.83 | H36: 120535.17 | I36: 新隆分店（2分店） | L36: 202601 | N36: 202601
A37: 33 | B37: 46027 | C37: 邮政个人 | D37: 营业款 | E37: 5店李永娜 | F37: 6361.83 | H37: 126897 | I37: 象城街分店（5店） | L37: 202601 | N37: 202601
A38: 34 | B38: 46027 | C38: 邮政个人 | D38: 营业款 | E38: 5店李永娜 | F38: 2 | H38: 126899 | I38: 象城街分店（5店） | L38: 202512 | N38: 202601
A39: 35 | B39: 46028 | C39: 邮政个人 | D39: 营业款 | E39: 3店王惠娟 | F39: 5.8 | H39: 126904.8 | I39: 康庄东路分店（3店） | L39: 202512 | N39: 202601
... A41: 37 | B41: 46028 | C41: 邮政个人 | D41: 营业款 | E41: 3店王惠娟 | F41: 6566.62 | H41: 133513.12 | I41: 康庄东路分店（3店） | L41: 202601 | N41: 202601
A42: 38 | B42: 46028 | C42: 邮政个人 | E42: 支取现金 | G42: 12000 | H42: 121513.12 | I42: 内部转款 | L42: 202601 | N42: 202601
A43: 39 | B43: 46028 | C43: 邮政个人 | D43: 营业款 | E43: 4店张彩红 | F43: 33.69 | H43: 121546.81 | I43: 东关分店（4分店） | L43: 202612 | N43: 202601
A44: 40 | B44: 46028 | C44: 邮政个人 | D44: 营业款 | E44: 4店张彩红 | F44: 7842.54 | H44: 129389.35 | I44: 东关分店（4分店） | L44: 202601 | N44: 202601
A45: 41 | B45: 46028 | C45: 邮政个人 | D45: 营业款 | E45: 57店刘国华 | F45: 5412.85 | H45: 134802.2 | I45: 临城县博城分店（57分店） | L45: 202601 | N45: 202601
A46: 42 | B46: 46029 | C46: 邮政个人 | D46: 营业款 | E46: 68店李国霞 | F46: 2553.52 | H46: 137355.72 | I46: 博山分店（68分店） | L46: 202601 | N46: 202601
A47: 43 | B47: 46029 | C47: 邮政个人 | D47: 营业款 | E47: 67店姜慧娟 | F47: 1983.45 | H47: 139339.17 | I47: 博亮分店（67分店） | L47: 202601 | N47: 202601
A48: 44 | B48: 46029 | C48: 邮政个人 | D48: 营业款 | E48: 24店曹玉丽 | F48: 10202.92 | H48: 149542.09 | I48: 高村分店（24分店） | L48: 202601 | N48: 202601
A49: 45 | B49: 46029 | C49: 邮政个人 | D49: 营业款 | E49: 23店田少芳 | F49: 2566.35 | H49: 152108.44 | I49: 尹村分店(23分店） | L49: 202601 | N49: 202601
A50: 46 | B50: 46029 | C50: 邮政个人 | D50: 营业款 | E50: 60店郭静钰 | F50: 1405.7 | H50: 153514.14 | I50: 博景分店（60分店） | L50: 202601 | N50: 202601
A51: 47 | B51: 46029 | C51: 邮政个人 | D51: 营业款 | E51: 4店张彩红 | F51: 9155.02 | H51: 162669.16 | I51: 东关分店（4分店） | L51: 202601 | N51: 202601
A52: 48 | B52: 46029 | C52: 邮政个人 | D52: 营业款 | E52: 2店王玉彩 | F52: 30326.56 | H52: 192995.72 | I52: 新隆分店（2分店） | L52: 202601 | N52: 202601
A53: 49 | B53: 46029 | C53: 邮政个人 | D53: 营业款 | E53: 62店张彦 | F53: 1201.97 | H53: 194197.69 | I53: 西范村分店（62分店） | L53: 202601 | N53: 202601
A54: 50 | B54: 46030 | C54: 邮政个人 | D54: 营业款 | E54: 63店曹雪雪 | F54: 13899.89 | H54: 208097.58 | I54: 博医分店（63分店） | L54: 202601 | N54: 202601
... A64: 60 | B64: 46034 | C64: 邮政个人 | D64: 营业款 | E64: 57店刘国华 | F64: 3246.98 | H64: 265386.76 | I64: 临城县博城分店（57分店） | L64: 202601 | N64: 202601
A65: 61 | B65: 46034 | C65: 邮政个人 | D65: 内部转账 | E65: 支取现金 | G65: 5000 | H65: 260386.76 | I65: 内部转款 | L65: 202601 | N65: 202601
A66: 62 | B66: 46034 | C66: 邮政个人 | D66: 内部转账 | E66: 支取现金 | G66: 3600 | H66: 256786.76 | I66: 内部转款 | L66: 202601 | N66: 202601
A67: 63 | B67: 46034 | C67: 邮政个人 | D67: 营业款 | E67: 4店张彩红 | F67: 6140.01 | H67: 262926.77 | I67: 东关分店（4分店） | L67: 202601 | N67: 202601
A68: 64 | B68: 46035 | C68: 邮政个人 | D68: 营业款 | E68: 3店王惠娟 | F68: 4119.87 | H68: 267046.64 | I68: 康庄东路分店（3店） | L68: 202601 | N68: 202601
A69: 65 | B69: 46035 | C69: 邮政个人 | D69: 营业款 | E69: 2店王玉彩 | F69: 25249.7 | H69: 292296.34 | I69: 新隆分店（2分店） | L69: 202601 | N69: 202601
A70: 66 | B70: 46036 | C70: 邮政个人 | D70: 营业款 | E70: 60店郭静钰 | F70: 1153.71 | H70: 293450.05 | I70: 博景分店（60分店） | L70: 202601 | N70: 202601
A71: 67 | B71: 46036 | C71: 邮政个人 | D71: 营业款 | E71: 68店李国霞 | F71: 1589.19 | H71: 295039.24 | I71: 博山分店（68分店） | L71: 202601 | N71: 202601
A72: 68 | B72: 46036 | C72: 邮政个人 | D72: 营业款 | E72: 62店张彦 | F72: 1343.14 | H72: 296382.38 | I72: 西范村分店（62分店） | L72: 202601 | N72: 202601
A73: 69 | B73: 46036 | C73: 邮政个人 | D73: 营业款 | E73: 5店李永娜 | F73: 5644.87 | H73: 302027.25 | I73: 象城街分店（5店） | L73: 202601 | N73: 202601
A74: 70 | B74: 46036 | C74: 邮政个人 | D74: 营业款 | E74: 66店冯丽 | F74: 1776.02 | H74: 303803.27 | I74: 博实分店（66分店） | L74: 202601 | N74: 202601
A75: 71 | B75: 46036 | C75: 邮政个人 | D75: 内部转款 | E75: 邮政个人转入建行个人 | G75: 250000 | H75: 53803.27 | I75: 内部转款 | L75: 202601 | N75: 202601
A76: 72 | B76: 46036 | C76: 邮政个人 | D76: 营业款 | E76: 23店田少芳 | F76: 1595.6 | H76: 55398.87 | I76: 尹村分店(23分店） | L76: 202601 | N76: 202601
A77: 73 | B77: 46036 | C77: 邮政个人 | D77: 营业款 | E77: 63店曹雪雪 | F77: 9261.49 | H77: 64660.36 | I77: 博医分店（63分店） | L77: 202601 | N77: 202601
A78: 74 | B78: 46037 | C78: 邮政个人 | D78: 营业款 | E78: 67店姜慧娟 | F78: 1988.97 | H78: 66649.33 | I78: 博亮分店（67分店） | L78: 202601 | N78: 202601
A79: 75 | B79: 46037 | C79: 邮政个人 | D79: 营业款 | E79: 55店杨芳 | F79: 1299.38 | H79: 67948.71 | I79: 博魏分店（55分店） | L79: 202601 | N79: 202601
A80: 76 | B80: 46037 | C80: 邮政个人 | D80: 营业款 | E80: 24店曹玉丽 | F80: 9486.1 | H80: 77434.81 | I80: 高村分店（24分店） | L80: 202601 | N80: 202601
A81: 77 | B81: 46037 | C81: 邮政个人 | D81: 营业款 | E81: 3店王惠娟 | F81: 3533.45 | H81: 80968.26 | I81: 康庄东路分店（3店） | L81: 202601 | N81: 202601
A82: 78 | B82: 46038 | C82: 邮政个人 | D82: 营业款 | E82: 2店王玉彩 | F82: 31870.96 | H82: 112839.22 | I82: 新隆分店（2分店） | L82: 202601 | N82: 202601
A83: 79 | B83: 46039 | C83: 邮政个人 | D83: 营业款 | E83: 4店张彩红 | F83: 8560.25 | H83: 121399.47 | I83: 东关分店（4分店） | L83: 202601 | N83: 202601
A84: 80 | B84: 46040 | C84: 邮政个人 | D84: 营业款 | E84: 3店王惠娟 | F84: 4907.8 | H84: 126307.27 | I84: 康庄东路分店（3店） | L84: 202601 | N84: 202601
A85: 81 | B85: 46040 | C85: 邮政个人 | D85: 营业款 | E85: 5店李永娜 | F85: 8734.5 | H85: 135041.77 | I85: 象城街分店（5店） | L85: 202601 | N85: 202601
A86: 82 | B86: 46041 | C86: 邮政个人 | D86: 营业款 | E86: 2店王玉彩 | F86: 27380.41 | H86: 162422.18 | I86: 新隆分店（2分店） | L86: 202601 | N86: 202601
A87: 83 | B87: 46042 | C87: 邮政个人 | D87: 内部转款 | E87: 邮政个人转入建行个人 | G87: 100000 | H87: 62422.18 | I87: 内部转款 | L87: 202601 | N87: 202601
A88: 84 | B88: 46043 | C88: 邮政个人 | D88: 营业款 | E88: 67店姜慧娟 | F88: 813.45 | H88: 63235.63 | I88: 博亮分店（67分店） | L88: 202601 | N88: 202601
A89: 85 | B89: 46043 | C89: 邮政个人 | D89: 营业款 | E89: 3店王惠娟 | F89: 6051.2 | H89: 69286.83 | I89: 康庄东路分店（3店） | L89: 202601 | N89: 202601
A90: 86 | B90: 46036 | C90: 邮政个人 | D90: 营业款 | E90: 63店曹雪雪 | F90: 165.3 | H90: 69452.13 | I90: 博医分店（63分店） | L90: 202512 | N90: 202601
A91: 87 | B91: 46043 | C91: 邮政个人 | D91: 营业款 | E91: 63店曹雪雪 | F91: 12544.46 | H91: 81996.59 | I91: 博医分店（63分店） | L91: 202601 | N91: 202601
A92: 88 | B92: 46043 | C92: 邮政个人 | D92: 营业款 | E92: 62店张彦 | F92: 1458.14 | H92: 83454.73 | I92: 西范村分店（62分店） | L92: 202601 | N92: 202601
A93: 89 | B93: 46043 | C93: 邮政个人 | D93: 营业款 | E93: 68店李国霞 | F93: 1083.49 | H93: 84538.22 | I93: 博山分店（68分店） | L93: 202601 | N93: 202601
A94: 90 | B94: 46043 | C94: 邮政个人 | D94: 营业款 | E94: 23店田少芳 | F94: 2220.54 | H94: 86758.76 | I94: 尹村分店(23分店） | L94: 202601 | N94: 202601
A95: 91 | B95: 46044 | C95: 邮政个人 | D95: 营业款 | E95: 57店刘国华 | F95: 9195.39 | H95: 95954.15 | I95: 临城县博城分店（57分店） | L95: 202601 | N95: 202601
A96: 92 | B96: 46044 | C96: 邮政个人 | D96: 营业款 | E96: 60店郭静钰 | F96: 1468.5 | H96: 97422.65 | I96: 博景分店（60分店） | L96: 202601 | N96: 202601
A97: 93 | B97: 46044 | C97: 邮政个人 | D97: 营业款 | E97: 5店李永娜 | F97: 7413.57 | H97: 104836.22 | I97: 象城街分店（5店） | L97: 202601 | N97: 202601
A98: 94 | B98: 46044 | C98: 邮政个人 | D98: 营业款 | E98: 4店张彩红 | F98: 8461.36 | H98: 113297.58 | I98: 东关分店（4分店） | L98: 202601 | N98: 202601
A99: 95 | B99: 46044 | C99: 邮政个人 | D99: 营业款 | E99: 66店冯丽 | F99: 3861.44 | H99: 117159.02 | I99: 博实分店（66分店） | L99: 202601 | N99: 202601
... A148: 144 | B148: 46062 | C148: 邮政个人 | D148: 营业款 | E148: 3店王惠娟 | F148: 4433.38 | H148: 497336.13 | I148: 康庄东路分店（3店） | L148: 202602 | N148: 202602
A149: 145 | B149: 46063 | C149: 邮政个人 | D149: 营业款 | E149: 支取现金 | G149: 3000 | H149: 494336.13 | I149: 内部转款 | L149: 202601 | N149: 202602
A150: 146 | B150: 46064 | C150: 邮政个人 | D150: 营业款 | E150: 2店王玉彩 | F150: 31654.44 | H150: 525990.57 | I150: 新隆分店（2分店） | L150: 202602 | N150: 202602
A151: 147 | B151: 46064 | C151: 邮政个人 | D151: 营业款 | E151: 3店王惠娟 | F151: 6127.43 | H151: 532118 | I151: 康庄东路分店（3店） | L151: 202602 | N151: 202602
A152: 148 | B152: 46065 | C152: 邮政个人 | D152: 内部转款 | E152: 邮政个人转入建行个人 | G152: 250000 | H152: 282118 | I152: 内部转款 | L152: 202601 | N152: 202602
A153: 149 | B153: 46023 | C153: 建行个人 | D153: 预付款 | E153: 苏长习预付款 | G153: 11200 | H153: 40512.92 | I153: 配送 | L153: 202601 | N153: 202601
A154: 150 | B154: 46023 | C154: 建行个人 | D154: 营业款 | E154: 7店李红晓 | F154: 4001.85 | H154: 44514.77 | I154: 华鑫分店（7店） | L154: 202512 | N154: 202601
A155: 151 | B155: 46023 | C155: 建行个人 | D155: 营业款 | E155: 37店王娜娜 | F155: 1823.94 | H155: 46338.71 | I155: 新华路分店（37店） | L155: 202512 | N155: 202601
A156: 152 | B156: 46023 | C156: 建行个人 | D156: 营业款 | E156: 8店郭军平 | F156: 2277.11 | H156: 48615.82 | I156: 博昭分店（8分店） | L156: 202512 | N156: 202601
A157: 153 | B157: 46023 | C157: 建行个人 | D157: 营业款 | E157: 1店曹娇娇 | F157: 1510.46 | H157: 50126.28 | I157: 柏人商城分店（1店） | L157: 202512 | N157: 202601
A158: 154 | B158: 46023 | C158: 建行个人 | D158: 营业款 | E158: 50店张亚 | F158: 228.85 | H158: 50355.13 | I158: 博诺医药-临城县博尚分店（50分店） | L158: 202512 | N158: 202601
...

Sheet 月度汇总
A1: 月度门店收支汇总（按“收支所属月份”统计）
A2: 月份 | B2: 门店 | C2: 收入 / 收款分类 | AB2: 支出分类 | AL2: 净额
A3: 月份 | B3: 门店 | C3: 营业款 | D3: 医保即时拨付 | E3: 医保 | F3: 聚合 | G3: 24小时微信 | H3: 美团 | I3: 饿了么 | J3: 健E卡 | K3: 抖音 | L3: 医卡通 | M3: 企健网 | N3: 银联 | O3: 京东 | P3: 药机微信 | Q3: 亲情卡 | R3: 优惠券 | S3: 代金券 | T3: 其他收款 | U3: 调拨收入 | V3: 储值 | W3: 效期 | X3: 内部转入 | Y3: 其他收入 | Z3: 收入合计 | AA3: 工资 | AB3: 水费 | AC3: 电费 | AD3: 宽带费 | AE3: 办公费 | AF3: 话费 | AG3: 房租 | AH3: 调拨支出 | AI3: 内部转出 | AJ3: 其他支出 | AK3: 支出合计 | AL3: 净收支
A4: 202512 | B4: 东关分店（4分店） | C4: =SUMIFS(Sheet1!$F$5:$F$28252,Sheet1!$I$5:$I$28252,$B4,Sheet1!$L$5:$L$28252,$A4,Sheet1!$D$5:$D$28252,"营业款",Sheet1!$E$5:$E$28252,"<>*调拨*",Sheet1!$E$5:$E$28252,"<>*回款*",Sheet1!$E$5:$E$28252,"<>*收款*",Sheet1!$E$5:$E$28252,"<>*医保*",Sheet1!$E$5:$E$28252,"<>*聚合*",Sheet1!$E$5:$E$28252,"<>*24小时微信*",Sheet1!$E$5:$E$28252,"<>*美团*",Sheet1!$E$5:$E$28252,"<>*饿了么*",Sheet1!$E$5:$E$28252,"<>*健E卡*",Sheet1!$E$5:$E$28252,"<>*抖音*",Sheet1!$E$5:$E$28252,"<>*医卡通*",Sheet1!$E$5:$E$28252,"<>*企健网*",Sheet1!$E$5:$E$28252,"<>*银联*",Sheet1!$E$5:$E$28252,"<>*京东*",Sheet1!$E$5:$E$28252,"<>*药机微信*",Sheet1!$E$5:$E$28252,"<>*亲情卡*",Sheet1!$E$5:$E$28252,"<>*优惠券*",Sheet1!$E$5:$E$28252,"<>*代金券*",Sheet1!$E$5:$E$28252,"<>*储值*",Sheet1!$E$5:$E$28252,"<>*效期*") -> 8103.01 | D4: =SUMIFS(Sheet1!$F$5:$F$28252,Sheet1!$I$5:$I$28252,$B4,Sheet1!$L$5:$L$28252,$A4,Sheet1!$D$5:$D$28252,"医保即时拨付",Sheet1!$E$5:$E$28252,"<>*调拨*")+SUMIFS(Sheet1!$F$5:$F$28252,Sheet1!$I$5:$I$28252,$B4,Sheet1!$L$5:$L$28252,$A4,Sheet1!$E$5:$E$28252,"*医保即时拨付*",Sheet1!$D$5:$D$28252,"<>医保即时拨付",Sheet1!$D$5:$D$28252,"<>内部转款",Sheet1!$D$5:$D$28252,"<>内部转账",Sheet1!$E$5:$E$28252,"<>*调拨*") -> 0 | E4: =SUMIFS(Sheet1!$F$5:$F$28252,Sheet1!$I$5:$I$28252,$B4,Sheet1!$L$5:$L$28252,$A4,Sheet1!$D$5:$D$28252,"医保",Sheet1!$E$5:$E$28252,"<>*调拨*",Sheet1!$E$5:$E$28252,"<>*医保即时拨付*")+SUMIFS(Sheet1!$F$5:$F$28252,Sheet1!$I$5:$I$28252,$B4,Sheet1!$L$5:$L$28252,$A4,Sheet1!$E$5:$E$28252,"*医保*",Sheet1!$D$5:$D$28252,"<>医保",Sheet1!$D$5:$D$28252,"<>医保即时拨付",Sheet1!$D$5:$D$28252,"<>内部转款",Sheet1!$D$5:$D$28252,"<>内部转账",Sheet1!$E$5:$E$28252,"<>*医保即时拨付*",Sheet1!$E$5:$E$28252,"<>*调拨*") -> 0 | F4: =SUMIFS(Sheet1!$F$5:$F$28252,Sheet1!$I$5:$I$28252,$B4,Sheet1!$L$5:$L$28252,$A4,Sheet1!$D$5:$D$28252,"聚合",Sheet1!$E$5:$E$28252,"<>*调拨*")+SUMIFS(Sheet1!$F$5:$F$28252,Sheet1!$I$5:$I$28252,$B4,Sheet1!$L$5:$L$28252,$A4,Sheet1!$E$5:$E$28252,"*聚合*",Sheet1!$D$5:$D$28252,"<>聚合",Sheet1!$D$5:$D$28252,"<>内部转款",Sheet1!$D$5:$D$28252,"<>内部转账",Sheet1!$E$5:$E$28252,"<>*调拨*") -> 0 | G4: =SUMIFS(Sheet1!$F$5:$F$28252,Sheet1!$I$5:$I$28252,$B4,Sheet1!$L$5:$L$28252,$A4,Sheet1!$D$5:$D$28252,"24小时微信",Sheet1!$E$5:$E$28252,"<>*调拨*")+SUMIFS(Sheet1!$F$5:$F$28252,Sheet1!$I$5:$I$28252,$B4,Sheet1!$L$5:$L$28252,$A4,Sheet1!$E$5:$E$28252,"*24小时微信*",Sheet1!$D$5:$D$28252,"<>24小时微信",Sheet1!$D$5:$D$28252,"<>内部转款",Sheet1!$D$5:$D$28252,"<>内部转账",Sheet1!$E$5:$E$28252,"<>*调拨*") -> 0 | H4: =SUMIFS(Sheet1!$F$5:$F$28252,Sheet1!$I$5:$I$28252,$B4,Sheet1!$L$5:$L$28252,$A4,Sheet1!$D$5:$D$28252,"美团",Sheet1!$E$5:$E$28252,"<>*调拨*")+SUMIFS(Sheet1!$F$5:$F$28252,Sheet1!$I$5:$I$28252,$B4,Sheet1!$L$5:$L$28252,$A4,Sheet1!$E$5:$E$28252,"*美团*",Sheet1!$D$5:$D$28252,"<>美团",Sheet1!$D$5:$D$28252,"<>内部转款",Sheet1!$D$5:$D$28252,"<>内部转账",Sheet1!$E$5:$E$28252,"<>*调拨*") -> 0 | I4: =SUMIFS(Sheet1!$F$5:$F$28252,Sheet1!$I$5:$I$28252,$B4,Sheet1!$L$5:$L$28252,$A4,Sheet1!$D$5:$D$28252,"饿了么",Sheet1!$E$5:$E$28252,"<>*调拨*")+SUMIFS(Sheet1!$F$5:$F$28252,Sheet1!$I$5:$I$28252,$B4,Sheet1!$L$5:$L$28252,$A4,Sheet1!$E$5:$E$28252,"*饿了么*",Sheet1!$D$5:$D$28252,"<>饿了么",Sheet1!$D$5:$D$28252,"<>内部转款",Sheet1!$D$5:$D$28252,"<>内部转账",Sheet1!$E$5:$E$28252,"<>*调拨*") -> 0 | J4: =SUMIFS(Sheet1!$F$5:$F$28252,Sheet1!$I$5:$I$28252,$B4,Sheet1!$L$5:$L$28252,$A4,Sheet1!$D$5:$D$28252,"健E卡",Sheet1!$E$5:$E$28252,"<>*调拨*")+SUMIFS(Sheet1!$F$5:$F$28252,Sheet1!$I$5:$I$28252,$B4,Sheet1!$L$5:$L$28252,$A4,Sheet1!$E$5:$E$28252,"*健E卡*",Sheet1!$D$5:$D$28252,"<>健E卡",Sheet1!$D$5:$D$28252,"<>内部转款",Sheet1!$D$5:$D$28252,"<>内部转账",Sheet1!$E$5:$E$28252,"<>*调拨*") -> 0 | K4: =SUMIFS(Sheet1!$F$5:$F$28252,Sheet1!$I$5:$I$28252,$B4,Sheet1!$L$5:$L$28252,$A4,Sheet1!$D$5:$D$28252,"抖音",Sheet1!$E$5:$E$28252,"<>*调拨*")+SUMIFS(Sheet1!$F$5:$F$28252,Sheet1!$I$5:$I$28252,$B4,Sheet1!$L$5:$L$28252,$A4,Sheet1!$E$5:$E$28252,"*抖音*",Sheet1!$D$5:$D$28252,"<>抖音",Sheet1!$D$5:$D$28252,"<>内部转款",Sheet1!$D$5:$D$28252,"<>内部转账",Sheet1!$E$5:$E$28252,"<>*调拨*") -> 0 | L4: =SUMIFS(Sheet1!$F$5:$F$28252,Sheet1!$I$5:$I$28252,$B4,Sheet1!$L$5:$L$28252,$A4,Sheet1!$D$5:$D$28252,"医卡通",Sheet1!$E$5:$E$28252,"<>*调拨*")+SUMIFS(Sheet1!$F$5:$F$28252,Sheet1!$I$5:$I$28252,$B4,Sheet1!$L$5:$L$28252,$A4,Sheet1!$E$5:$E$28252,"*医卡通*",Sheet1!$D$5:$D$28252,"<>医卡通",Sheet1!$D$5:$D$28252,"<>内部转款",Sheet1!$D$5:$D$28252,"<>内部转账",Sheet1!$E$5:$E$28252,"<>*调拨*") -> 0 | M4: =SUMIFS(Sheet1!$F$5:$F$28252,Sheet1!$I$5:$I$28252,$B4,Sheet1!$L$5:$L$28252,$A4,Sheet1!$D$5:$D$28252,"企健网",Sheet1!$E$5:$E$28252,"<>*调拨*")+SUMIFS(Sheet1!$F$5:$F$28252,Sheet1!$I$5:$I$28252,$B4,Sheet1!$L$5:$L$28252,$A4,Sheet1!$E$5:$E$28252,"*企健网*",Sheet1!$D$5:$D$28252,"<>企健网",Sheet1!$D$5:$D$28252,"<>内部转款",Sheet1!$D$5:$D$28252,"<>内部转账",Sheet1!$E$5:$E$28252,"<>*调拨*") -> 0 | N4: =SUMIFS(Sheet1!$F$5:$F$28252,Sheet1!$I$5:$I$28252,$B4,Sheet1!$L$5:$L$28252,$A4,Sheet1!$D$5:$D$28252,"银联",Sheet1!$E$5:$E$28252,"<>*调拨*")+SUMIFS(Sheet1!$F$5:$F$28252,Sheet1!$I$5:$I$28252,$B4,Sheet1!$L$5:$L$28252,$A4,Sheet1!$E$5:$E$28252,"*银联*",Sheet1!$D$5:$D$28252,"<>银联",Sheet1!$D$5:$D$28252,"<>内部转款",Sheet1!$D$5:$D$28252,"<>内部转账",Sheet1!$E$5:$E$28252,"<>*调拨*") -> 0 | O4: =SUMIFS(Sheet1!$F$5:$F$28252,Sheet1!$I$5:$I$28252,$B4,Sheet1!$L$5:$L$28252,$A4,Sheet1!$D$5:$D$28252,"京东",Sheet1!$E$5:$E$28252,"<>*调拨*")+SUMIFS(Sheet1!$F$5:$F$28252,Sheet1!$I$5:$I$28252,$B4,Sheet1!$L$5:$L$28252,$A4,Sheet1!$E$5:$E$28252,"*京东*",Sheet1!$D$5:$D$28252,"<>京东",Sheet1!$D$5:$D$28252,"<>内部转款",Sheet1!$D$5:$D$28252,"<>内部转账",Sheet1!$E$5:$E$28252,"<>*调拨*") -> 0 | P4: =SUMIFS(Sheet1!$F$5:$F$28252,Sheet1!$I$5:$I$28252,$B4,Sheet1!$L$5:$L$28252,$A4,Sheet1!$D$5:$D$28252,"药机微信",Sheet1!$E$5:$E$28252,"<>*调拨*")+SUMIFS(Sheet1!$F$5:$F$28252,Sheet1!$I$5:$I$28252,$B4,Sheet1!$L$5:$L$28252,$A4,Sheet1!$E$5:$E$28252,"*药机微信*",Sheet1!$D$5:$D$28252,"<>药机微信",Sheet1!$D$5:$D$28252,"<>内部转款",Sheet1!$D$5:$D$28252,"<>内部转账",Sheet1!$E$5:$E$28252,"<>*调拨*") -> 0 | Q4: =SUMIFS(Sheet1!$F$5:$F$28252,Sheet1!$I$5:$I$28252,$B4,Sheet1!$L$5:$L$28252,$A4,Sheet1!$D$5:$D$28252,"亲情卡",Sheet1!$E$5:$E$28252,"<>*调拨*")+SUMIFS(Sheet1!$F$5:$F$28252,Sheet1!$I$5:$I$28252,$B4,Sheet1!$L$5:$L$28252,$A4,Sheet1!$E$5:$E$28252,"*亲情卡*",Sheet1!$D$5:$D$28252,"<>亲情卡",Sheet1!$D$5:$D$28252,"<>内部转款",Sheet1!$D$5:$D$28252,"<>内部转账",Sheet1!$E$5:$E$28252,"<>*调拨*") -> 0 | R4: =SUMIFS(Sheet1!$F$5:$F$28252,Sheet1!$I$5:$I$28252,$B4,Sheet1!$L$5:$L$28252,$A4,Sheet1!$D$5:$D$28252,"优惠券",Sheet1!$E$5:$E$28252,"<>*调拨*")+SUMIFS(Sheet1!$F$5:$F$28252,Sheet1!$I$5:$I$28252,$B4,Sheet1!$L$5:$L$28252,$A4,Sheet1!$E$5:$E$28252,"*优惠券*",Sheet1!$D$5:$D$28252,"<>优惠券",Sheet1!$D$5:$D$28252,"<>内部转款",Sheet1!$D$5:$D$28252,"<>内部转账",Sheet1!$E$5:$E$28252,"<>*调拨*") -> 0 | S4: =SUMIFS(Sheet1!$F$5:$F$28252,Sheet1!$I$5:$I$28252,$B4,Sheet1!$L$5:$L$28252,$A4,Sheet1!$D$5:$D$28252,"代金券",Sheet1!$E$5:$E$28252,"<>*调拨*")+SUMIFS(Sheet1!$F$5:$F$28252,Sheet1!$I$5:$I$28252,$B4,Sheet1!$L$5:$L$28252,$A4,Sheet1!$E$5:$E$28252,"*代金券*",Sheet1!$D$5:$D$28252,"<>代金券",Sheet1!$D$5:$D$28252,"<>内部转款",Sheet1!$D$5:$D$28252,"<>内部转账",Sheet1!$E$5:$E$28252,"<>*调拨*") -> 0 | T4: =SUMIFS(Sheet1!$F$5:$F$28252,Sheet1!$I$5:$I$28252,$B4,Sheet1!$L$5:$L$28252,$A4,Sheet1!$D$5:$D$28252,"回款",Sheet1!$E$5:$E$28252,"<>*调拨*",Sheet1!$E$5:$E$28252,"<>*医保*",Sheet1!$E$5:$E$28252,"<>*聚合*",Sheet1!$E$5:$E$28252,"<>*24小时微信*",Sheet1!$E$5:$E$28252,"<>*美团*",Sheet1!$E$5:$E$28252,"<>*饿了么*",Sheet1!$E$5:$E$28252,"<>*健E卡*",Sheet1!$E$5:$E$28252,"<>*抖音*",Sheet1!$E$5:$E$28252,"<>*医卡通*",Sheet1!$E$5:$E$28252,"<>*企健网*",Sheet1!$E$5:$E$28252,"<>*银联*",Sheet1!$E$5:$E$28252,"<>*京东*",Sheet1!$E$5:$E$28252,"<>*药机微信*",Sheet1!$E$5:$E$28252,"<>*亲情卡*",Sheet1!$E$5:$E$28252,"<>*优惠券*",Sheet1!$E$5:$E$28252,"<>*代金券*",Sheet1!$E$5:$E$28252,"<>*储值*",Sheet1!$E$5:$E$28252,"<>*效期*")+SUMIFS(Sheet1!$F$5:$F$28252,Sheet1!$I$5:$I$28252,$B4,Sheet1!$L$5:$L$28252,$A4,Sheet1!$D$5:$D$28252,"收款",Sheet1!$E$5:$E$28252,"<>*调拨*",Sheet1!$E$5:$E$28252,"<>*医保*",Sheet1!$E$5:$E$28252,"<>*聚合*",Sheet1!$E$5:$E$28252,"<>*24小时微信*",Sheet1!$E$5:$E$28252,"<>*美团*",Sheet1!$E$5:$E$28252,"<>*饿了么*",Sheet1!$E$5:$E$28252,"<>*健E卡*",Sheet1!$E$5:$E$28252,"<>*抖音*",Sheet1!$E$5:$E$28252,"<>*医卡通*",Sheet1!$E$5:$E$28252,"<>*企健网*",Sheet1!$E$5:$E$28252,"<>*银联*",Sheet1!$E$5:$E$28252,"<>*京东*",Sheet1!$E$5:$E$28252,"<>*药机微信*",Sheet1!$E$5:$E$28252,"<>*亲情卡*",Sheet1!$E$5:$E$28252,"<>*优惠券*",Sheet1!$E$5:$E$28252,"<>*代金券*",Sheet1!$E$5:$E$28252,"<>*储值*",Sheet1!$E$5:$E$28252,"<>*效期*")+SUMIFS(Sheet1!$F$5:$F$28252,Sheet1!$I$5:$I$28252,$B4,Sheet1!$L$5:$L$28252,$A4,Sheet1!$E$5:$E$28252,"*回款*",Sheet1!$D$5:$D$28252,"<>回款",Sheet1!$D$5:$D$28252,"<>收款",Sheet1!$D$5:$D$28252,"<>内部转款",Sheet1!$D$5:$D$28252,"<>内部转账",Sheet1!$E$5:$E$28252,"<>*调拨*",Sheet1!$E$5:$E$28252,"<>*医保*",Sheet1!$E$5:$E$28252,"<>*聚合*",Sheet1!$E$5:$E$28252,"<>*24小时微信*",Sheet1!$E$5:$E$28252,"<>*美团*",Sheet1!$E$5:$E$28252,"<>*饿了么*",Sheet1!$E$5:$E$28252,"<>*健E卡*",Sheet1!$E$5:$E$28252,"<>*抖音*",Sheet1!$E$5:$E$28252,"<>*医卡通*",Sheet1!$E$5:$E$28252,"<>*企健网*",Sheet1!$E$5:$E$28252,"<>*银联*",Sheet1!$E$5:$E$28252,"<>*京东*",Sheet1!$E$5:$E$28252,"<>*药机微信*",Sheet1!$E$5:$E$28252,"<>*亲情卡*",Sheet1!$E$5:$E$28252,"<>*优惠券*",Sheet1!$E$5:$E$28252,"<>*代金券*",Sheet1!$E$5:$E$28252,"<>*储值*",Sheet1!$E$5:$E$28252,"<>*效期*")+SUMIFS(Sheet1!$F$5:$F$28252,Sheet1!$I$5:$I$28252,$B4,Sheet1!$L$5:$L$28252,$A4,Sheet1!$E$5:$E$28252,"*收款*",Sheet1!$E$5:$E$28252,"<>*回款*",Sheet1!$D$5:$D$28252,"<>回款",Sheet1!$D$5:$D$28252,"<>收款",Sheet1!$D$5:$D$28252,"<>内部转款",Sheet1!$D$5:$D$28252,"<>内部转账",Sheet1!$E$5:$E$28252,"<>*调拨*",Sheet1!$E$5:$E$28252,"<>*医保*",Sheet1!$E$5:$E$28252,"<>*聚合*",Sheet1!$E$5:$E$28252,"<>*24小时微信*",Sheet1!$E$5:$E$28252,"<>*美团*",Sheet1!$E$5:$E$28252,"<>*饿了么*",Sheet1!$E$5:$E$28252,"<>*健E卡*",Sheet1!$E$5:$E$28252,"<>*抖音*",Sheet1!$E$5:$E$28252,"<>*医卡通*",Sheet1!$E$5:$E$28252,"<>*企健网*",Sheet1!$E$5:$E$28252,"<>*银联*",Sheet1!$E$5:$E$28252,"<>*京东*",Sheet1!$E$5:$E$28252,"<>*药机微信*",Sheet1!$E$5:$E$28252,"<>*亲情卡*",Sheet1!$E$5:$E$28252,"<>*优惠券*",Sheet1!$E$5:$E$28252,"<>*代金券*",Sheet1!$E$5:$E$28252,"<>*储值*",Sheet1!$E$5:$E$28252,"<>*效期*") -> 0 | U4: =SUMIFS(Sheet1!$F$5:$F$28252,Sheet1!$I$5:$I$28252,$B4,Sheet1!$L$5:$L$28252,$A4,Sheet1!$E$5:$E$28252,"*调拨*") -> 0 | V4: =SUMIFS(Sheet1!$F$5:$F$28252,Sheet1!$I$5:$I$28252,$B4,Sheet1!$L$5:$L$28252,$A4,Sheet1!$D$5:$D$28252,"储值",Sheet1!$E$5:$E$28252,"<>*调拨*")+SUMIFS(Sheet1!$F$5:$F$28252,Sheet1!$I$5:$I$28252,$B4,Sheet1!$L$5:$L$28252,$A4,Sheet1!$E$5:$E$28252,"*储值*",Sheet1!$D$5:$D$28252,"<>储值",Sheet1!$D$5:$D$28252,"<>内部转款",Sheet1!$D$5:$D$28252,"<>内部转账",Sheet1!$E$5:$E$28252,"<>*调拨*") -> 0 | W4: =SUMIFS(Sheet1!$F$5:$F$28252,Sheet1!$I$5:$I$28252,$B4,Sheet1!$L$5:$L$28252,$A4,Sheet1!$D$5:$D$28252,"效期",Sheet1!$E$5:$E$28252,"<>*调拨*")+SUMIFS(Sheet1!$F$5:$F$28252,Sheet1!$I$5:$I$28252,$B4,Sheet1!$L$5:$L$28252,$A4,Sheet1!$E$5:$E$28252,"*效期*",Sheet1!$D$5:$D$28252,"<>效期",Sheet1!$D$5:$D$28252,"<>内部转款",Sheet1!$D$5:$D$28252,"<>内部转账",Sheet1!$E$5:$E$28252,"<>*调拨*") -> 0 | X4: =SUMIFS(Sheet1!$F$5:$F$28252,Sheet1!$I$5:$I$28252,$B4,Sheet1!$L$5:$L$28252,$A4,Sheet1!$D$5:$D$28252,"内部转款",Sheet1!$E$5:$E$28252,"<>*调拨*")+SUMIFS(Sheet1!$F$5:$F$28252,Sheet1!$I$5:$I$28252,$B4,Sheet1!$L$5:$L$28252,$A4,Sheet1!$D$5:$D$28252,"内部转账",Sheet1!$E$5:$E$28252,"<>*调拨*") -> 0 | Y4: =Z4-SUM(C4:X4) -> 0 | Z4: =SUMIFS(Sheet1!$F$5:$F$28252,Sheet1!$I$5:$I$28252,$B4,Sheet1!$L$5:$L$28252,$A4) -> 8103.01 | AA4: =SUMIFS(Sheet1!$G$5:$G$28252,Sheet1!$I$5:$I$28252,$B4,Sheet1!$L$5:$L$28252,$A4,Sheet1!$D$5:$D$28252,"工资",Sheet1!$E$5:$E$28252,"<>*调拨*")+SUMIFS(Sheet1!$G$5:$G$28252,Sheet1!$I$5:$I$28252,$B4,Sheet1!$L$5:$L$28252,$A4,Sheet1!$E$5:$E$28252,"*工资*",Sheet1!$E$5:$E$28252,"<>*调拨*",Sheet1!$D$5:$D$28252,"<>内部转款",Sheet1!$D$5:$D$28252,"<>内部转账",Sheet1!$D$5:$D$28252,"<>工资",Sheet1!$D$5:$D$28252,"<>水费",Sheet1!$D$5:$D$28252,"<>电费",Sheet1!$D$5:$D$28252,"<>宽带费",Sheet1!$D$5:$D$28252,"<>办公费",Sheet1!$D$5:$D$28252,"<>话费",Sheet1!$D$5:$D$28252,"<>房租") -> 0 | AB4: =SUMIFS(Sheet1!$G$5:$G$28252,Sheet1!$I$5:$I$28252,$B4,Sheet1!$L$5:$L$28252,$A4,Sheet1!$D$5:$D$28252,"水费",Sheet1!$E$5:$E$28252,"<>*调拨*")+SUMIFS(Sheet1!$G$5:$G$28252,Sheet1!$I$5:$I$28252,$B4,Sheet1!$L$5:$L$28252,$A4,Sheet1!$E$5:$E$28252,"*水费*",Sheet1!$E$5:$E$28252,"<>*调拨*",Sheet1!$D$5:$D$28252,"<>内部转款",Sheet1!$D$5:$D$28252,"<>内部转账",Sheet1!$D$5:$D$28252,"<>工资",Sheet1!$D$5:$D$28252,"<>水费",Sheet1!$D$5:$D$28252,"<>电费",Sheet1!$D$5:$D$28252,"<>宽带费",Sheet1!$D$5:$D$28252,"<>办公费",Sheet1!$D$5:$D$28252,"<>话费",Sheet1!$D$5:$D$28252,"<>房租",Sheet1!$E$5:$E$28252,"<>*工资*") -> 0 | AC4: =SUMIFS(Sheet1!$G$5:$G$28252,Sheet1!$I$5:$I$28252,$B4,Sheet1!$L$5:$L$28252,$A4,Sheet1!$D$5:$D$28252,"电费",Sheet1!$E$5:$E$28252,"<>*调拨*")+SUMIFS(Sheet1!$G$5:$G$28252,Sheet1!$I$5:$I$28252,$B4,Sheet1!$L$5:$L$28252,$A4,Sheet1!$E$5:$E$28252,"*电费*",Sheet1!$E$5:$E$28252,"<>*调拨*",Sheet1!$D$5:$D$28252,"<>内部转款",Sheet1!$D$5:$D$28252,"<>内部转账",Sheet1!$D$5:$D$28252,"<>工资",Sheet1!$D$5:$D$28252,"<>水费",Sheet1!$D$5:$D$28252,"<>电费",Sheet1!$D$5:$D$28252,"<>宽带费",Sheet1!$D$5:$D$28252,"<>办公费",Sheet1!$D$5:$D$28252,"<>话费",Sheet1!$D$5:$D$28252,"<>房租",Sheet1!$E$5:$E$28252,"<>*工资*",Sheet1!$E$5:$E$28252,"<>*水费*") -> 0 | AD4: =SUMIFS(Sheet1!$G$5:$G$28252,Sheet1!$I$5:$I$28252,$B4,Sheet1!$L$5:$L$28252,$A4,Sheet1!$D$5:$D$28252,"宽带费",Sheet1!$E$5:$E$28252,"<>*调拨*")+SUMIFS(Sheet1!$G$5:$G$28252,Sheet1!$I$5:$I$28252,$B4,Sheet1!$L$5:$L$28252,$A4,Sheet1!$E$5:$E$28252,"*宽带*",Sheet1!$E$5:$E$28252,"<>*调拨*",Sheet1!$D$5:$D$28252,"<>内部转款",Sheet1!$D$5:$D$28252,"<>内部转账",Sheet1!$D$5:$D$28252,"<>工资",Sheet1!$D$5:$D$28252,"<>水费",Sheet1!$D$5:$D$28252,"<>电费",Sheet1!$D$5:$D$28252,"<>宽带费",Sheet1!$D$5:$D$28252,"<>办公费",Sheet1!$D$5:$D$28252,"<>话费",Sheet1!$D$5:$D$28252,"<>房租",Sheet1!$E$5:$E$28252,"<>*工资*",Sheet1!$E$5:$E$28252,"<>*水费*",Sheet1!$E$5:$E$28252,"<>*电费*") -> 0 | AE4: =SUMIFS(Sheet1!$G$5:$G$28252,Sheet1!$I$5:$I$28252,$B4,Sheet1!$L$5:$L$28252,$A4,Sheet1!$D$5:$D$28252,"办公费",Sheet1!$E$5:$E$28252,"<>*调拨*")+SUMIFS(Sheet1!$G$5:$G$28252,Sheet1!$I$5:$I$28252,$B4,Sheet1!$L$5:$L$28252,$A4,Sheet1!$E$5:$E$28252,"*办公*",Sheet1!$E$5:$E$28252,"<>*调拨*",Sheet1!$D$5:$D$28252,"<>内部转款",Sheet1!$D$5:$D$28252,"<>内部转账",Sheet1!$D$5:$D$28252,"<>工资",Sheet1!$D$5:$D$28252,"<>水费",Sheet1!$D$5:$D$28252,"<>电费",Sheet1!$D$5:$D$28252,"<>宽带费",Sheet1!$D$5:$D$28252,"<>办公费",Sheet1!$D$5:$D$28252,"<>话费",Sheet1!$D$5:$D$28252,"<>房租",Sheet1!$E$5:$E$28252,"<>*工资*",Sheet1!$E$5:$E$28252,"<>*水费*",Sheet1!$E$5:$E$28252,"<>*电费*",Sheet1!$E$5:$E$28252,"<>*宽带*") -> 0 | AF4: =SUMIFS(Sheet1!$G$5:$G$28252,Sheet1!$I$5:$I$28252,$B4,Sheet1!$L$5:$L$28252,$A4,Sheet1!$D$5:$D$28252,"话费",Sheet1!$E$5:$E$28252,"<>*调拨*")+SUMIFS(Sheet1!$G$5:$G$28252,Sheet1!$I$5:$I$28252,$B4,Sheet1!$L$5:$L$28252,$A4,Sheet1!$E$5:$E$28252,"*话费*",Sheet1!$E$5:$E$28252,"<>*调拨*",Sheet1!$D$5:$D$28252,"<>内部转款",Sheet1!$D$5:$D$28252,"<>内部转账",Sheet1!$D$5:$D$28252,"<>工资",Sheet1!$D$5:$D$28252,"<>水费",Sheet1!$D$5:$D$28252,"<>电费",Sheet1!$D$5:$D$28252,"<>宽带费",Sheet1!$D$5:$D$28252,"<>办公费",Sheet1!$D$5:$D$28252,"<>话费",Sheet1!$D$5:$D$28252,"<>房租",Sheet1!$E$5:$E$28252,"<>*工资*",Sheet1!$E$5:$E$28252,"<>*水费*",Sheet1!$E$5:$E$28252,"<>*电费*",Sheet1!$E$5:$E$28252,"<>*宽带*",Sheet1!$E$5:$E$28252,"<>*办公*") -> 0 | AG4: =SUMIFS(Sheet1!$G$5:$G$28252,Sheet1!$I$5:$I$28252,$B4,Sheet1!$L$5:$L$28252,$A4,Sheet1!$D$5:$D$28252,"房租",Sheet1!$E$5:$E$28252,"<>*调拨*")+SUMIFS(Sheet1!$G$5:$G$28252,Sheet1!$I$5:$I$28252,$B4,Sheet1!$L$5:$L$28252,$A4,Sheet1!$E$5:$E$28252,"*房租*",Sheet1!$E$5:$E$28252,"<>*调拨*",Sheet1!$D$5:$D$28252,"<>内部转款",Sheet1!$D$5:$D$28252,"<>内部转账",Sheet1!$D$5:$D$28252,"<>工资",Sheet1!$D$5:$D$28252,"<>水费",Sheet1!$D$5:$D$28252,"<>电费",Sheet1!$D$5:$D$28252,"<>宽带费",Sheet1!$D$5:$D$28252,"<>办公费",Sheet1!$D$5:$D$28252,"<>话费",Sheet1!$D$5:$D$28252,"<>房租",Sheet1!$E$5:$E$28252,"<>*工资*",Sheet1!$E$5:$E$28252,"<>*水费*",Sheet1!$E$5:$E$28252,"<>*电费*",Sheet1!$E$5:$E$28252,"<>*宽带*",Sheet1!$E$5:$E$28252,"<>*办公*",Sheet1!$E$5:$E$28252,"<>*话费*") -> 0 | AH4: =SUMIFS(Sheet1!$G$5:$G$28252,Sheet1!$I$5:$I$28252,$B4,Sheet1!$L$5:$L$28252,$A4,Sheet1!$E$5:$E$28252,"*调拨*") -> 0 | AI4: =SUMIFS(Sheet1!$G$5:$G$28252,Sheet1!$I$5:$I$28252,$B4,Sheet1!$L$5:$L$28252,$A4,Sheet1!$D$5:$D$28252,"内部转款",Sheet1!$E$5:$E$28252,"<>*调拨*")+SUMIFS(Sheet1!$G$5:$G$28252,Sheet1!$I$5:$I$28252,$B4,Sheet1!$L$5:$L$28252,$A4,Sheet1!$D$5:$D$28252,"内部转账",Sheet1!$E$5:$E$28252,"<>*调拨*") -> 0 | AJ4: =AK4-SUM(AA4:AI4) -> 0 | AK4: =SUMIFS(Sheet1!$G$5:$G$28252,Sheet1!$I$5:$I$28252,$B4,Sheet1!$L$5:$L$28252,$A4) -> 0 | AL4: =Z4-AK4 -> 8103.01
A5: 202512 | B5: 临城县博城分店（57分店） | C5: =SUMIFS(Sheet1!$F$5:$F$28252,Sheet1!$I$5:$I$28252,$B5,Sheet1!$L$5:$L$28252,$A5,Sheet1!$D$5:$D$28252,"营业款",Sheet1!$E$5:$E$28252,"<>*调拨*",Sheet1!$E$5:$E$28252,"<>*回款*",Sheet1!$E$5:$E$28252,"<>*收款*",Sheet1!$E$5:$E$28252,"<>*医保*",Sheet1!$E$5:$E$28252,"<>*聚合*",Sheet1!$E$5:$E$28252,"<>*24小时微信*",Sheet1!$E$5:$E$28252,"<>*美团*",Sheet1!$E$5:$E$28252,"<>*饿了么*",Sheet1!$E$5:$E$28252,"<>*健E卡*",Sheet1!$E$5:$E$28252,"<>*抖音*",Sheet1!$E$5:$E$28252,"<>*医卡通*",Sheet1!$E$5:$E$28252,"<>*企健网*",Sheet1!$E$5:$E$28252,"<>*银联*",Sheet1!$E$5:$E$28252,"<>*京东*",Sheet1!$E$5:$E$28252,"<>*药机微信*",Sheet1!$E$5:$E$28252,"<>*亲情卡*",Sheet1!$E$5:$E$28252,"<>*优惠券*",Sheet1!$E$5:$E$28252,"<>*代金券*",Sheet1!$E$5:$E$28252,"<>*储值*",Sheet1!$E$5:$E$28252,"<>*效期*") -> 13343.62 | D5: =SUMIFS(Sheet1!$F$5:$F$28252,Sheet1!$I$5:$I$28252,$B5,Sheet1!$L$5:$L$28252,$A5,Sheet1!$D$5:$D$28252,"医保即时拨付",Sheet1!$E$5:$E$28252,"<>*调拨*")+SUMIFS(Sheet1!$F$5:$F$28252,Sheet1!$I$5:$I$28252,$B5,Sheet1!$L$5:$L$28252,$A5,Sheet1!$E$5:$E$28252,"*医保即时拨付*",Sheet1!$D$5:$D$28252,"<>医保即时拨付",Sheet1!$D$5:$D$28252,"<>内部转款",Sheet1!$D$5:$D$28252,"<>内部转账",Sheet1!$E$5:$E$28252,"<>*调拨*") -> 0 | E5: =SUMIFS(Sheet1!$F$5:$F$28252,Sheet1!$I$5:$I$28252,$B5,Sheet1!$L$5:$L$28252,$A5,Sheet1!$D$5:$D$28252,"医保",Sheet1!$E$5:$E$28252,"<>*调拨*",Sheet1!$E$5:$E$28252,"<>*医保即时拨付*")+SUMIFS(Sheet1!$F$5:$F$28252,Sheet1!$I$5:$I$28252,$B5,Sheet1!$L$5:$L$28252,$A5,Sheet1!$E$5:$E$28252,"*医保*",Sheet1!$D$5:$D$28252,"<>医保",Sheet1!$D$5:$D$28252,"<>医保即时拨付",Sheet1!$D$5:$D$28252,"<>内部转款",Sheet1!$D$5:$D$28252,"<>内部转账",Sheet1!$E$5:$E$28252,"<>*医保即时拨付*",Sheet1!$E$5:$E$28252,"<>*调拨*") -> 0 | F5: =SUMIFS(Sheet1!$F$5:$F$28252,Sheet1!$I$5:$I$28252,$B5,Sheet1!$L$5:$L$28252,$A5,Sheet1!$D$5:$D$28252,"聚合",Sheet1!$E$5:$E$28252,"<>*调拨*")+SUMIFS(Sheet1!$F$5:$F$28252,Sheet1!$I$5:$I$28252,$B5,Sheet1!$L$5:$L$28252,$A5,Sheet1!$E$5:$E$28252,"*聚合*",Sheet1!$D$5:$D$28252,"<>聚合",Sheet1!$D$5:$D$28252,"<>内部转款",Sheet1!$D$5:$D$28252,"<>内部转账",Sheet1!$E$5:$E$28252,"<>*调拨*") -> 0 | G5: =SUMIFS(Sheet1!$F$5:$F$28252,Sheet1!$I$5:$I$28252,$B5,Sheet1!$L$5:$L$28252,$A5,Sheet1!$D$5:$D$28252,"24小时微信",Sheet1!$E$5:$E$28252,"<>*调拨*")+SUMIFS(Sheet1!$F$5:$F$28252,Sheet1!$I$5:$I$28252,$B5,Sheet1!$L$5:$L$28252,$A5,Sheet1!$E$5:$E$28252,"*24小时微信*",Sheet1!$D$5:$D$28252,"<>24小时微信",Sheet1!$D$5:$D$28252,"<>内部转款",Sheet1!$D$5:$D$28252,"<>内部转账",Sheet1!$E$5:$E$28252,"<>*调拨*") -> 0 | H5: =SUMIFS(Sheet1!$F$5:$F$28252,Sheet1!$I$5:$I$28252,$B5,Sheet1!$L$5:$L$28252,$A5,Sheet1!$D$5:$D$28252,"美团",Sheet1!$E$5:$E$28252,"<>*调拨*")+SUMIFS(Sheet1!$F$5:$F$28252,Sheet1!$I$5:$I$28252,$B5,Sheet1!$L$5:$L$28252,$A5,Sheet1!$E$5:$E$28252,"*美团*",Sheet1!$D$5:$D$28252,"<>美团",Sheet1!$D$5:$D$28252,"<>内部转款",Sheet1!$D$5:$D$28252,"<>内部转账",Sheet1!$E$5:$E$28252,"<>*调拨*") -> 0 | I5: =SUMIFS(Sheet1!$F$5:$F$28252,Sheet1!$I$5:$I$28252,$B5,Sheet1!$L$5:$L$28252,$A5,Sheet1!$D$5:$D$28252,"饿了么",Sheet1!$E$5:$E$28252,"<>*调拨*")+SUMIFS(Sheet1!$F$5:$F$28252,Sheet1!$I$5:$I$28252,$B5,Sheet1!$L$5:$L$28252,$A5,Sheet1!$E$5:$E$28252,"*饿了么*",Sheet1!$D$5:$D$28252,"<>饿了么",Sheet1!$D$5:$D$28252,"<>内部转款",Sheet1!$D$5:$D$28252,"<>内部转账",Sheet1!$E$5:$E$28252,"<>*调拨*") -> 0 | J5: =SUMIFS(Sheet1!$F$5:$F$28252,Sheet1!$I$5:$I$28252,$B5,Sheet1!$L$5:$L$28252,$A5,Sheet1!$D$5:$D$28252,"健E卡",Sheet1!$E$5:$E$28252,"<>*调拨*")+SUMIFS(Sheet1!$F$5:$F$28252,Sheet1!$I$5:$I$28252,$B5,Sheet1!$L$5:$L$28252,$A5,Sheet1!$E$5:$E$28252,"*健E卡*",Sheet1!$D$5:$D$28252,"<>健E卡",Sheet1!$D$5:$D$28252,"<>内部转款",Sheet1!$D$5:$D$28252,"<>内部转账",Sheet1!$E$5:$E$28252,"<>*调拨*") -> 0 | K5: =SUMIFS(Sheet1!$F$5:$F$28252,Sheet1!$I$5:$I$28252,$B5,Sheet1!$L$5:$L$28252,$A5,Sheet1!$D$5:$D$28252,"抖音",Sheet1!$E$5:$E$28252,"<>*调拨*")+SUMIFS(Sheet1!$F$5:$F$28252,Sheet1!$I$5:$I$28252,$B5,Sheet1!$L$5:$L$28252,$A5,Sheet1!$E$5:$E$28252,"*抖音*",Sheet1!$D$5:$D$28252,"<>抖音",Sheet1!$D$5:$D$28252,"<>内部转款",Sheet1!$D$5:$D$28252,"<>内部转账",Sheet1!$E$5:$E$28252,"<>*调拨*") -> 0 | L5: =SUMIFS(Sheet1!$F$5:$F$28252,Sheet1!$I$5:$I$28252,$B5,Sheet1!$L$5:$L$28252,$A5,Sheet1!$D$5:$D$28252,"医卡通",Sheet1!$E$5:$E$28252,"<>*调拨*")+SUMIFS(Sheet1!$F$5:$F$28252,Sheet1!$I$5:$I$28252,$B5,Sheet1!$L$5:$L$28252,$A5,Sheet1!$E$5:$E$28252,"*医卡通*",Sheet1!$D$5:$D$28252,"<>医卡通",Sheet1!$D$5:$D$28252,"<>内部转款",Sheet1!$D$5:$D$28252,"<>内部转账",Sheet1!$E$5:$E$28252,"<>*调拨*") -> 0 | M5: =SUMIFS(Sheet1!$F$5:$F$28252,Sheet1!$I$5:$I$28252,$B5,Sheet1!$L$5:$L$28252,$A5,Sheet1!$D$5:$D$28252,"企健网",Sheet1!$E$5:$E$28252,"<>*调拨*")+SUMIFS(Sheet1!$F$5:$F$28252,Sheet1!$I$5:$I$28252,$B5,Sheet1!$L$5:$L$28252,$A5,Sheet1!$E$5:$E$28252,"*企健网*",Sheet1!$D$5:$D$28252,"<>企健网",Sheet1!$D$5:$D$28252,"<>内部转款",Sheet1!$D$5:$D$28252,"<>内部转账",Sheet1!$E$5:$E$28252,"<>*调拨*") -> 0 | N5: =SUMIFS(Sheet1!$F$5:$F$28252,Sheet1!$I$5:$I$28252,$B5,Sheet1!$L$5:$L$28252,$A5,Sheet1!$D$5:$D$28252,"银联",Sheet1!$E$5:$E$28252,"<>*调拨*")+SUMIFS(Sheet1!$F$5:$F$28252,Sheet1!$I$5:$I$28252,$B5,Sheet1!$L$5:$L$28252,$A5,Sheet1!$E$5:$E$28252,"*银联*",Sheet1!$D$5:$D$28252,"<>银联",Sheet1!$D$5:$D$28252,"<>内部转款",Sheet1!$D$5:$D$28252,"<>内部转账",Sheet1!$E$5:$E$28252,"<>*调拨*") -> 0 | O5: =SUMIFS(Sheet1!$F$5:$F$28252,Sheet1!$I$5:$I$28252,$B5,Sheet1!$L$5:$L$28252,$A5,Sheet1!$D$5:$D$28252,"京东",Sheet1!$E$5:$E$28252,"<>*调拨*")+SUMIFS(Sheet1!$F$5:$F$28252,Sheet1!$I$5:$I$28252,$B5,Sheet1!$L$5:$L$28252,$A5,Sheet1!$E$5:$E$28252,"*京东*",Sheet1!$D$5:$D$28252,"<>京东",Sheet1!$D$5:$D$28252,"<>内部转款",Sheet1!$D$5:$D$28252,"<>内部转账",Sheet1!$E$5:$E$28252,"<>*调拨*") -> 0 | P5: =SUMIFS(Sheet1!$F$5:$F$28252,Sheet1!$I$5:$I$28252,$B5,Sheet1!$L$5:$L$28252,$A5,Sheet1!$D$5:$D$28252,"药机微信",Sheet1!$E$5:$E$28252,"<>*调拨*")+SUMIFS(Sheet1!$F$5:$F$28252,Sheet1!$I$5:$I$28252,$B5,Sheet1!$L$5:$L$28252,$A5,Sheet1!$E$5:$E$28252,"*药机微信*",Sheet1!$D$5:$D$28252,"<>药机微信",Sheet1!$D$5:$D$28252,"<>内部转款",Sheet1!$D$5:$D$28252,"<>内部转账",Sheet1!$E$5:$E$28252,"<>*调拨*") -> 0 | Q5: =SUMIFS(Sheet1!$F$5:$F$28252,Sheet1!$I$5:$I$28252,$B5,Sheet1!$L$5:$L$28252,$A5,Sheet1!$D$5:$D$28252,"亲情卡",Sheet1!$E$5:$E$28252,"<>*调拨*")+SUMIFS(Sheet1!$F$5:$F$28252,Sheet1!$I$5:$I$28252,$B5,Sheet1!$L$5:$L$28252,$A5,Sheet1!$E$5:$E$28252,"*亲情卡*",Sheet1!$D$5:$D$28252,"<>亲情卡",Sheet1!$D$5:$D$28252,"<>内部转款",Sheet1!$D$5:$D$28252,"<>内部转账",Sheet1!$E$5:$E$28252,"<>*调拨*") -> 0 | R5: =SUMIFS(Sheet1!$F$5:$F$28252,Sheet1!$I$5:$I$28252,$B5,Sheet1!$L$5:$L$28252,$A5,Sheet1!$D$5:$D$28252,"优惠券",Sheet1!$E$5:$E$28252,"<>*调拨*")+SUMIFS(Sheet1!$F$5:$F$28252,Sheet1!$I$5:$I$28252,$B5,Sheet1!$L$5:$L$28252,$A5,Sheet1!$E$5:$E$28252,"*优惠券*",Sheet1!$D$5:$D$28252,"<>优惠券",Sheet1!$D$5:$D$28252,"<>内部转款",Sheet1!$D$5:$D$28252,"<>内部转账",Sheet1!$E$5:$E$28252,"<>*调拨*") -> 0 | S5: =SUMIFS(Sheet1!$F$5:$F$28252,Sheet1!$I$5:$I$28252,$B5,Sheet1!$L$5:$L$28252,$A5,Sheet1!$D$5:$D$28252,"代金券",Sheet1!$E$5:$E$28252,"<>*调拨*")+SUMIFS(Sheet1!$F$5:$F$28252,Sheet1!$I$5:$I$28252,$B5,Sheet1!$L$5:$L$28252,$A5,Sheet1!$E$5:$E$28252,"*代金券*",Sheet1!$D$5:$D$28252,"<>代金券",Sheet1!$D$5:$D$28252,"<>内部转款",Sheet1!$D$5:$D$28252,"<>内部转账",Sheet1!$E$5:$E$28252,"<>*调拨*") -> 0 | T5: =SUMIFS(Sheet1!$F$5:$F$28252,Sheet1!$I$5:$I$28252,$B5,Sheet1!$L$5:$L$28252,$A5,Sheet1!$D$5:$D$28252,"回款",Sheet1!$E$5:$E$28252,"<>*调拨*",Sheet1!$E$5:$E$28252,"<>*医保*",Sheet1!$E$5:$E$28252,"<>*聚合*",Sheet1!$E$5:$E$28252,"<>*24小时微信*",Sheet1!$E$5:$E$28252,"<>*美团*",Sheet1!$E$5:$E$28252,"<>*饿了么*",Sheet1!$E$5:$E$28252,"<>*健E卡*",Sheet1!$E$5:$E$28252,"<>*抖音*",Sheet1!$E$5:$E$28252,"<>*医卡通*",Sheet1!$E$5:$E$28252,"<>*企健网*",Sheet1!$E$5:$E$28252,"<>*银联*",Sheet1!$E$5:$E$28252,"<>*京东*",Sheet1!$E$5:$E$28252,"<>*药机微信*",Sheet1!$E$5:$E$28252,"<>*亲情卡*",Sheet1!$E$5:$E$28252,"<>*优惠券*",Sheet1!$E$5:$E$28252,"<>*代金券*",Sheet1!$E$5:$E$28252,"<>*储值*",Sheet1!$E$5:$E$28252,"<>*效期*")+SUMIFS(Sheet1!$F$5:$F$28252,Sheet1!$I$5:$I$28252,$B5,Sheet1!$L$5:$L$28252,$A5,Sheet1!$D$5:$D$28252,"收款",Sheet1!$E$5:$E$28252,"<>*调拨*",Sheet1!$E$5:$E$28252,"<>*医保*",Sheet1!$E$5:$E$28252,"<>*聚合*",Sheet1!$E$5:$E$28252,"<>*24小时微信*",Sheet1!$E$5:$E$28252,"<>*美团*",Sheet1!$E$5:$E$28252,"<>*饿了么*",Sheet1!$E$5:$E$28252,"<>*健E卡*",Sheet1!$E$5:$E$28252,"<>*抖音*",Sheet1!$E$5:$E$28252,"<>*医卡通*",Sheet1!$E$5:$E$28252,"<>*企健网*",Sheet1!$E$5:$E$28252,"<>*银联*",Sheet1!$E$5:$E$28252,"<>*京东*",Sheet1!$E$5:$E$28252,"<>*药机微信*",Sheet1!$E$5:$E$28252,"<>*亲情卡*",Sheet1!$E$5:$E$28252,"<>*优惠券*",Sheet1!$E$5:$E$28252,"<>*代金券*",Sheet1!$E$5:$E$28252,"<>*储值*",Sheet1!$E$5:$E$28252,"<>*效期*")+SUMIFS(Sheet1!$F$5:$F$28252,Sheet1!$I$5:$I$28252,$B5,Sheet1!$L$5:$L$28252,$A5,Sheet1!$E$5:$E$28252,"*回款*",Sheet1!$D$5:$D$28252,"<>回款",Sheet1!$D$5:$D$28252,"<>收款",Sheet1!$D$5:$D$28252,"<>内部转款",Sheet1!$D$5:$D$28252,"<>内部转账",Sheet1!$E$5:$E$28252,"<>*调拨*",Sheet1!$E$5:$E$28252,"<>*医保*",Sheet1!$E$5:$E$28252,"<>*聚合*",Sheet1!$E$5:$E$28252,"<>*24小时微信*",Sheet1!$E$5:$E$28252,"<>*美团*",Sheet1!$E$5:$E$28252,"<>*饿了么*",Sheet1!$E$5:$E$28252,"<>*健E卡*",Sheet1!$E$5:$E$28252,"<>*抖音*",Sheet1!$E$5:$E$28252,"<>*医卡通*",Sheet1!$E$5:$E$28252,"<>*企健网*",Sheet1!$E$5:$E$28252,"<>*银联*",Sheet1!$E$5:$E$28252,"<>*京东*",Sheet1!$E$5:$E$28252,"<>*药机微信*",Sheet1!$E$5:$E$28252,"<>*亲情卡*",Sheet1!$E$5:$E$28252,"<>*优惠券*",Sheet1!$E$5:$E$28252,"<>*代金券*",Sheet1!$E$5:$E$28252,"<>*储值*",Sheet1!$E$5:$E$28252,"<>*效期*")+SUMIFS(Sheet1!$F$5:$F$28252,Sheet1!$I$5:$I$28252,$B5,Sheet1!$L$5:$L$28252,$A5,Sheet1!$E$5:$E$28252,"*收款*",Sheet1!$E$5:$E$28252,"<>*回款*",Sheet1!$D$5:$D$28252,"<>回款",Sheet1!$D$5:$D$28252,"<>收款",Sheet1!$D$5:$D$28252,"<>内部转款",Sheet1!$D$5:$D$28252,"<>内部转账",Sheet1!$E$5:$E$28252,"<>*调拨*",Sheet1!$E$5:$E$28252,"<>*医保*",Sheet1!$E$5:$E$28252,"<>*聚合*",Sheet1!$E$5:$E$28252,"<>*24小时微信*",Sheet1!$E$5:$E$28252,"<>*美团*",Sheet1!$E$5:$E$28252,"<>*饿了么*",Sheet1!$E$5:$E$28252,"<>*健E卡*",Sheet1!$E$5:$E$28252,"<>*抖音*",Sheet1!$E$5:$E$28252,"<>*医卡通*",Sheet1!$E$5:$E$28252,"<>*企健网*",Sheet1!$E$5:$E$28252,"<>*银联*",Sheet1!$E$5:$E$28252,"<>*京东*",Sheet1!$E$5:$E$28252,"<>*药机微信*",Sheet1!$E$5:$E$28252,"<>*亲情卡*",Sheet1!$E$5:$E$28252,"<>*优惠券*",Sheet1!$E$5:$E$28252,"<>*代金券*",Sheet1!$E$5:$E$28252,"<>*储值*",Sheet1!$E$5:$E$28252,"<>*效期*") -> 0 | U5: =SUMIFS(Sheet1!$F$5:$F$28252,Sheet1!$I$5:$I$28252,$B5,Sheet1!$L$5:$L$28252,$A5,Sheet1!$E$5:$E$28252,"*调拨*") -> 0 | V5: =SUMIFS(Sheet1!$F$5:$F$28252,Sheet1!$I$5:$I$28252,$B5,Sheet1!$L$5:$L$28252,$A5,Sheet1!$D$5:$D$28252,"储值",Sheet1!$E$5:$E$28252,"<>*调拨*")+SUMIFS(Sheet1!$F$5:$F$28252,Sheet1!$I$5:$I$28252,$B5,Sheet1!$L$5:$L$28252,$A5,Sheet1!$E$5:$E$28252,"*储值*",Sheet1!$D$5:$D$28252,"<>储值",Sheet1!$D$5:$D$28252,"<>内部转款",Sheet1!$D$5:$D$28252,"<>内部转账",Sheet1!$E$5:$E$28252,"<>*调拨*") -> 0 | W5: =SUMIFS(Sheet1!$F$5:$F$28252,Sheet1!$I$5:$I$28252,$B5,Sheet1!$L$5:$L$28252,$A5,Sheet1!$D$5:$D$28252,"效期",Sheet1!$E$5:$E$28252,"<>*调拨*")+SUMIFS(Sheet1!$F$5:$F$28252,Sheet1!$I$5:$I$28252,$B5,Sheet1!$L$5:$L$28252,$A5,Sheet1!$E$5:$E$28252,"*效期*",Sheet1!$D$5:$D$28252,"<>效期",Sheet1!$D$5:$D$28252,"<>内部转款",Sheet1!$D$5:$D$28252,"<>内部转账",Sheet1!$E$5:$E$28252,"<>*调拨*") -> 0 | X5: =SUMIFS(Sheet1!$F$5:$F$28252,Sheet1!$I$5:$I$28252,$B5,Sheet1!$L$5:$L$28252,$A5,Sheet1!$D$5:$D$28252,"内部转款",Sheet1!$E$5:$E$28252,"<>*调拨*")+SUMIFS(Sheet1!$F$5:$F$28252,Sheet1!$I$5:$I$28252,$B5,Sheet1!$L$5:$L$28252,$A5,Sheet1!$D$5:$D$28252,"内部转账",Sheet1!$E$5:$E$28252,"<>*调拨*") -> 0 | Y5: =Z5-SUM(C5:X5) -> 0 | Z5: =SUMIFS(Sheet1!$F$5:$F$28252,Sheet1!$I$5:$I$28252,$B5,Sheet1!$L$5:$L$28252,$A5) -> 13343.62 | AA5: =SUMIFS(Sheet1!$G$5:$G$28252,Sheet1!$I$5:$I$28252,$B5,Sheet1!$L$5:$L$28252,$A5,Sheet1!$D$5:$D$28252,"工资",Sheet1!$E$5:$E$28252,"<>*调拨*")+SUMIFS(Sheet1!$G$5:$G$28252,Sheet1!$I$5:$I$28252,$B5,Sheet1!$L$5:$L$28252,$A5,Sheet1!$E$5:$E$28252,"*工资*",Sheet1!$E$5:$E$28252,"<>*调拨*",Sheet1!$D$5:$D$28252,"<>内部转款",Sheet1!$D$5:$D$28252,"<>内部转账",Sheet1!$D$5:$D$28252,"<>工资",Sheet1!$D$5:$D$28252,"<>水费",Sheet1!$D$5:$D$28252,"<>电费",Sheet1!$D$5:$D$28252,"<>宽带费",Sheet1!$D$5:$D$28252,"<>办公费",Sheet1!$D$5:$D$28252,"<>话费",Sheet1!$D$5:$D$28252,"<>房租") -> 0 | AB5: =SUMIFS(Sheet1!$G$5:$G$28252,Sheet1!$I$5:$I$28252,$B5,Sheet1!$L$5:$L$28252,$A5,Sheet1!$D$5:$D$28252,"水费",Sheet1!$E$5:$E$28252,"<>*调拨*")+SUMIFS(Sheet1!$G$5:$G$28252,Sheet1!$I$5:$I$28252,$B5,Sheet1!$L$5:$L$28252,$A5,Sheet1!$E$5:$E$28252,"*水费*",Sheet1!$E$5:$E$28252,"<>*调拨*",Sheet1!$D$5:$D$28252,"<>内部转款",Sheet1!$D$5:$D$28252,"<>内部转账",Sheet1!$D$5:$D$28252,"<>工资",Sheet1!$D$5:$D$28252,"<>水费",Sheet1!$D$5:$D$28252,"<>电费",Sheet1!$D$5:$D$28252,"<>宽带费",Sheet1!$D$5:$D$28252,"<>办公费",Sheet1!$D$5:$D$28252,"<>话费",Sheet1!$D$5:$D$28252,"<>房租",Sheet1!$E$5:$E$28252,"<>*工资*") -> 0 | AC5: =SUMIFS(Sheet1!$G$5:$G$28252,Sheet1!$I$5:$I$28252,$B5,Sheet1!$L$5:$L$28252,$A5,Sheet1!$D$5:$D$28252,"电费",Sheet1!$E$5:$E$28252,"<>*调拨*")+SUMIFS(Sheet1!$G$5:$G$28252,Sheet1!$I$5:$I$28252,$B5,Sheet1!$L$5:$L$28252,$A5,Sheet1!$E$5:$E$28252,"*电费*",Sheet1!$E$5:$E$28252,"<>*调拨*",Sheet1!$D$5:$D$28252,"<>内部转款",Sheet1!$D$5:$D$28252,"<>内部转账",Sheet1!$D$5:$D$28252,"<>工资",Sheet1!$D$5:$D$28252,"<>水费",Sheet1!$D$5:$D$28252,"<>电费",Sheet1!$D$5:$D$28252,"<>宽带费",Sheet1!$D$5:$D$28252,"<>办公费",Sheet1!$D$5:$D$28252,"<>话费",Sheet1!$D$5:$D$28252,"<>房租",Sheet1!$E$5:$E$28252,"<>*工资*",Sheet1!$E$5:$E$28252,"<>*水费*") -> 0 | AD5: =SUMIFS(Sheet1!$G$5:$G$28252,Sheet1!$I$5:$I$28252,$B5,Sheet1!$L$5:$L$28252,$A5,Sheet1!$D$5:$D$28252,"宽带费",Sheet1!$E$5:$E$28252,"<>*调拨*")+SUMIFS(Sheet1!$G$5:$G$28252,Sheet1!$I$5:$I$28252,$B5,Sheet1!$L$5:$L$28252,$A5,Sheet1!$E$5:$E$28252,"*宽带*",Sheet1!$E$5:$E$28252,"<>*调拨*",Sheet1!$D$5:$D$28252,"<>内部转款",Sheet1!$D$5:$D$28252,"<>内部转账",Sheet1!$D$5:$D$28252,"<>工资",Sheet1!$D$5:$D$28252,"<>水费",Sheet1!$D$5:$D$28252,"<>电费",Sheet1!$D$5:$D$28252,"<>宽带费",Sheet1!$D$5:$D$28252,"<>办公费",Sheet1!$D$5:$D$28252,"<>话费",Sheet1!$D$5:$D$28252,"<>房租",Sheet1!$E$5:$E$28252,"<>*工资*",Sheet1!$E$5:$E$28252,"<>*水费*",Sheet1!$E$5:$E$28252,"<>*电费*") -> 0 | AE5: =SUMIFS(Sheet1!$G$5:$G$28252,Sheet1!$I$5:$I$28252,$B5,Sheet1!$L$5:$L$28252,$A5,Sheet1!$D$5:$D$28252,"办公费",Sheet1!$E$5:$E$28252,"<>*调拨*")+SUMIFS(Sheet1!$G$5:$G$28252,Sheet1!$I$5:$I$28252,$B5,Sheet1!$L$5:$L$28252,$A5,Sheet1!$E$5:$E$28252,"*办公*",Sheet1!$E$5:$E$28252,"<>*调拨*",Sheet1!$D$5:$D$28252,"<>内部转款",Sheet1!$D$5:$D$28252,"<>内部转账",Sheet1!$D$5:$D$28252,"<>工资",Sheet1!$D$5:$D$28252,"<>水费",Sheet1!$D$5:$D$28252,"<>电费",Sheet1!$D$5:$D$28252,"<>宽带费",Sheet1!$D$5:$D$28252,"<>办公费",Sheet1!$D$5:$D$28252,"<>话费",Sheet1!$D$5:$D$28252,"<>房租",Sheet1!$E$5:$E$28252,"<>*工资*",Sheet1!$E$5:$E$28252,"<>*水费*",Sheet1!$E$5:$E$28252,"<>*电费*",Sheet1!$E$5:$E$28252,"<>*宽带*") -> 0 | AF5: =SUMIFS(Sheet1!$G$5:$G$28252,Sheet1!$I$5:$I$28252,$B5,Sheet1!$L$5:$L$28252,$A5,Sheet1!$D$5:$D$28252,"话费",Sheet1!$E$5:$E$28252,"<>*调拨*")+SUMIFS(Sheet1!$G$5:$G$28252,Sheet1!$I$5:$I$28252,$B5,Sheet1!$L$5:$L$28252,$A5,Sheet1!$E$5:$E$28252,"*话费*",Sheet1!$E$5:$E$28252,"<>*调拨*",Sheet1!$D$5:$D$28252,"<>内部转款",Sheet1!$D$5:$D$28252,"<>内部转账",Sheet1!$D$5:$D$28252,"<>工资",Sheet1!$D$5:$D$28252,"<>水费",Sheet1!$D$5:$D$28252,"<>电费",Sheet1!$D$5:$D$28252,"<>宽带费",Sheet1!$D$5:$D$28252,"<>办公费",Sheet1!$D$5:$D$28252,"<>话费",Sheet1!$D$5:$D$28252,"<>房租",Sheet1!$E$5:$E$28252,"<>*工资*",Sheet1!$E$5:$E$28252,"<>*水费*",Sheet1!$E$5:$E$28252,"<>*电费*",Sheet1!$E$5:$E$28252,"<>*宽带*",Sheet1!$E$5:$E$28252,"<>*办公*") -> 0 | AG5: =SUMIFS(Sheet1!$G$5:$G$28252,Sheet1!$I$5:$I$28252,$B5,Sheet1!$L$5:$L$28252,$A5,Sheet1!$D$5:$D$28252,"房租",Sheet1!$E$5:$E$28252,"<>*调拨*")+SUMIFS(Sheet1!$G$5:$G$28252,Sheet1!$I$5:$I$28252,$B5,Sheet1!$L$5:$L$28252,$A5,Sheet1!$E$5:$E$28252,"*房租*",Sheet1!$E$5:$E$28252,"<>*调拨*",Sheet1!$D$5:$D$28252,"<>内部转款",Sheet1!$D$5:$D$28252,"<>内部转账",Sheet1!$D$5:$D$28252,"<>工资",Sheet1!$D$5:$D$28252,"<>水费",Sheet1!$D$5:$D$28252,"<>电费",Sheet1!$D$5:$D$28252,"<>宽带费",Sheet1!$D$5:$D$28252,"<>办公费",Sheet1!$D$5:$D$28252,"<>话费",Sheet1!$D$5:$D$28252,"<>房租",Sheet1!$E$5:$E$28252,"<>*工资*",Sheet1!$E$5:$E$28252,"<>*水费*",Sheet1!$E$5:$E$28252,"<>*电费*",Sheet1!$E$5:$E$28252,"<>*宽带*",Sheet1!$E$5:$E$28252,"<>*办公*",Sheet1!$E$5:$E$28252,"<>*话费*") -> 0 | AH5: =SUMIFS(Sheet1!$G$5:$G$28252,Sheet1!$I$5:$I$28252,$B5,Sheet1!$L$5:$L$28252,$A5,Sheet1!$E$5:$E$28252,"*调拨*") -> 0 | AI5: =SUMIFS(Sheet1!$G$5:$G$28252,Sheet1!$I$5:$I$28252,$B5,Sheet1!$L$5:$L$28252,$A5,Sheet1!$D$5:$D$28252,"内部转款",Sheet1!$E$5:$E$28252,"<>*调拨*")+SUMIFS(Sheet1!$G$5:$G$28252,Sheet1!$I$5:$I$28252,$B5,Sheet1!$L$5:$L$28252,$A5,Sheet1!$D$5:$D$28252,"内部转账",Sheet1!$E$5:$E$28252,"<>*调拨*") -> 0 | AJ5: =AK5-SUM(AA5:AI5) -> 0 | AK5: =SUMIFS(Sheet1!$G$5:$G$28252,Sheet1!$I$5:$I$28252,$B5,Sheet1!$L$5:$L$28252,$A5) -> 0 | AL5: =Z5-AK5 -> 13343.62
A6: 202512 | B6: 临城县博康分店（46分店） | C6: =SUMIFS(Sheet1!$F$5:$F$28252,Sheet1!$I$5:$I$28252,$B6,Sheet1!$L$5:$L$28252,$A6,Sheet1!$D$5:$D$28252,"营业款",Sheet1!$E$5:$E$28252,"<>*调拨*",Sheet1!$E$5:$E$28252,"<>*回款*",Sheet1!$E$5:$E$28252,"<>*收款*",Sheet1!$E$5:$E$28252,"<>*医保*",Sheet1!$E$5:$E$28252,"<>*聚合*",Sheet1!$E$5:$E$28252,"<>*24小时微信*",Sheet1!$E$5:$E$28252,"<>*美团*",Sheet1!$E$5:$E$28252,"<>*饿了么*",Sheet1!$E$5:$E$28252,"<>*健E卡*",Sheet1!$E$5:$E$28252,"<>*抖音*",Sheet1!$E$5:$E$28252,"<>*医卡通*",Sheet1!$E$5:$E$28252,"<>*企健网*",Sheet1!$E$5:$E$28252,"<>*银联*",Sheet1!$E$5:$E$28252,"<>*京东*",Sheet1!$E$5:$E$28252,"<>*药机微信*",Sheet1!$E$5:$E$28252,"<>*亲情卡*",Sheet1!$E$5:$E$28252,"<>*优惠券*",Sheet1!$E$5:$E$28252,"<>*代金券*",Sheet1!$E$5:$E$28252,"<>*储值*",Sheet1!$E$5:$E$28252,"<>*效期*") -> 0 | D6: =SUMIFS(Sheet1!$F$5:$F$28252,Sheet1!$I$5:$I$28252,$B6,Sheet1!$L$5:$L$28252,$A6,Sheet1!$D$5:$D$28252,"医保即时拨付",Sheet1!$E$5:$E$28252,"<>*调拨*")+SUMIFS(Sheet1!$F$5:$F$28252,Sheet1!$I$5:$I$28252,$B6,Sheet1!$L$5:$L$28252,$A6,Sheet1!$E$5:$E$28252,"*医保即时拨付*",Sheet1!$D$5:$D$28252,"<>医保即时拨付",Sheet1!$D$5:$D$28252,"<>内部转款",Sheet1!$D$5:$D$28252,"<>内部转账",Sheet1!$E$5:$E$28252,"<>*调拨*") -> 0 | E6: =SUMIFS(Sheet1!$F$5:$F$28252,Sheet1!$I$5:$I$28252,$B6,Sheet1!$L$5:$L$28252,$A6,Sheet1!$D$5:$D$28252,"医保",Sheet1!$E$5:$E$28252,"<>*调拨*",Sheet1!$E$5:$E$28252,"<>*医保即时拨付*")+SUMIFS(Sheet1!$F$5:$F$28252,Sheet1!$I$5:$I$28252,$B6,Sheet1!$L$5:$L$28252,$A6,Sheet1!$E$5:$E$28252,"*医保*",Sheet1!$D$5:$D$28252,"<>医保",Sheet1!$D$5:$D$28252,"<>医保即时拨付",Sheet1!$D$5:$D$28252,"<>内部转款",Sheet1!$D$5:$D$28252,"<>内部转账",Sheet1!$E$5:$E$28252,"<>*医保即时拨付*",Sheet1!$E$5:$E$28252,"<>*调拨*") -> 0 | F6: =SUMIFS(Sheet1!$F$5:$F$28252,Sheet1!$I$5:$I$28252,$B6,Sheet1!$L$5:$L$28252,$A6,Sheet1!$D$5:$D$28252,"聚合",Sheet1!$E$5:$E$28252,"<>*调拨*")+SUMIFS(Sheet1!$F$5:$F$28252,Sheet1!$I$5:$I$28252,$B6,Sheet1!$L$5:$L$28252,$A6,Sheet1!$E$5:$E$28252,"*聚合*",Sheet1!$D$5:$D$28252,"<>聚合",Sheet1!$D$5:$D$28252,"<>内部转款",Sheet1!$D$5:$D$28252,"<>内部转账",Sheet1!$E$5:$E$28252,"<>*调拨*") -> 0 | G6: =SUMIFS(Sheet1!$F$5:$F$28252,Sheet1!$I$5:$I$28252,$B6,Sheet1!$L$5:$L$28252,$A6,Sheet1!$D$5:$D$28252,"24小时微信",Sheet1!$E$5:$E$28252,"<>*调拨*")+SUMIFS(Sheet1!$F$5:$F$28252,Sheet1!$I$5:$I$28252,$B6,Sheet1!$L$5:$L$28252,$A6,Sheet1!$E$5:$E$28252,"*24小时微信*",Sheet1!$D$5:$D$28252,"<>24小时微信",Sheet1!$D$5:$D$28252,"<>内部转款",Sheet1!$D$5:$D$28252,"<>内部转账",Sheet1!$E$5:$E$28252,"<>*调拨*") -> 0 | H6: =SUMIFS(Sheet1!$F$5:$F$28252,Sheet1!$I$5:$I$28252,$B6,Sheet1!$L$5:$L$28252,$A6,Sheet1!$D$5:$D$28252,"美团",Sheet1!$E$5:$E$28252,"<>*调拨*")+SUMIFS(Sheet1!$F$5:$F$28252,Sheet1!$I$5:$I$28252,$B6,Sheet1!$L$5:$L$28252,$A6,Sheet1!$E$5:$E$28252,"*美团*",Sheet1!$D$5:$D$28252,"<>美团",Sheet1!$D$5:$D$28252,"<>内部转款",Sheet1!$D$5:$D$28252,"<>内部转账",Sheet1!$E$5:$E$28252,"<>*调拨*") -> 0 | I6: =SUMIFS(Sheet1!$F$5:$F$28252,Sheet1!$I$5:$I$28252,$B6,Sheet1!$L$5:$L$28252,$A6,Sheet1!$D$5:$D$28252,"饿了么",Sheet1!$E$5:$E$28252,"<>*调拨*")+SUMIFS(Sheet1!$F$5:$F$28252,Sheet1!$I$5:$I$28252,$B6,Sheet1!$L$5:$L$28252,$A6,Sheet1!$E$5:$E$28252,"*饿了么*",Sheet1!$D$5:$D$28252,"<>饿了么",Sheet1!$D$5:$D$28252,"<>内部转款",Sheet1!$D$5:$D$28252,"<>内部转账",Sheet1!$E$5:$E$28252,"<>*调拨*") -> 0 | J6: =SUMIFS(Sheet1!$F$5:$F$28252,Sheet1!$I$5:$I$28252,$B6,Sheet1!$L$5:$L$28252,$A6,Sheet1!$D$5:$D$28252,"健E卡",Sheet1!$E$5:$E$28252,"<>*调拨*")+SUMIFS(Sheet1!$F$5:$F$28252,Sheet1!$I$5:$I$28252,$B6,Sheet1!$L$5:$L$28252,$A6,Sheet1!$E$5:$E$28252,"*健E卡*",Sheet1!$D$5:$D$28252,"<>健E卡",Sheet1!$D$5:$D$28252,"<>内部转款",Sheet1!$D$5:$D$28252,"<>内部转账",Sheet1!$E$5:$E$28252,"<>*调拨*") -> 0 | K6: =SUMIFS(Sheet1!$F$5:$F$28252,Sheet1!$I$5:$I$28252,$B6,Sheet1!$L$5:$L$28252,$A6,Sheet1!$D$5:$D$28252,"抖音",Sheet1!$E$5:$E$28252,"<>*调拨*")+SUMIFS(Sheet1!$F$5:$F$28252,Sheet1!$I$5:$I$28252,$B6,Sheet1!$L$5:$L$28252,$A6,Sheet1!$E$5:$E$28252,"*抖音*",Sheet1!$D$5:$D$28252,"<>抖音",Sheet1!$D$5:$D$28252,"<>内部转款",Sheet1!$D$5:$D$28252,"<>内部转账",Sheet1!$E$5:$E$28252,"<>*调拨*") -> 0 | L6: =SUMIFS(Sheet1!$F$5:$F$28252,Sheet1!$I$5:$I$28252,$B6,Sheet1!$L$5:$L$28252,$A6,Sheet1!$D$5:$D$28252,"医卡通",Sheet1!$E$5:$E$28252,"<>*调拨*")+SUMIFS(Sheet1!$F$5:$F$28252,Sheet1!$I$5:$I$28252,$B6,Sheet1!$L$5:$L$28252,$A6,Sheet1!$E$5:$E$28252,"*医卡通*",Sheet1!$D$5:$D$28252,"<>医卡通",Sheet1!$D$5:$D$28252,"<>内部转款",Sheet1!$D$5:$D$28252,"<>内部转账",Sheet1!$E$5:$E$28252,"<>*调拨*") -> 0 | M6: =SUMIFS(Sheet1!$F$5:$F$28252,Sheet1!$I$5:$I$28252,$B6,Sheet1!$L$5:$L$28252,$A6,Sheet1!$D$5:$D$28252,"企健网",Sheet1!$E$5:$E$28252,"<>*调拨*")+SUMIFS(Sheet1!$F$5:$F$28252,Sheet1!$I$5:$I$28252,$B6,Sheet1!$L$5:$L$28252,$A6,Sheet1!$E$5:$E$28252,"*企健网*",Sheet1!$D$5:$D$28252,"<>企健网",Sheet1!$D$5:$D$28252,"<>内部转款",Sheet1!$D$5:$D$28252,"<>内部转账",Sheet1!$E$5:$E$28252,"<>*调拨*") -> 0 | N6: =SUMIFS(Sheet1!$F$5:$F$28252,Sheet1!$I$5:$I$28252,$B6,Sheet1!$L$5:$L$28252,$A6,Sheet1!$D$5:$D$28252,"银联",Sheet1!$E$5:$E$28252,"<>*调拨*")+SUMIFS(Sheet1!$F$5:$F$28252,Sheet1!$I$5:$I$28252,$B6,Sheet1!$L$5:$L$28252,$A6,Sheet1!$E$5:$E$28252,"*银联*",Sheet1!$D$5:$D$28252,"<>银联",Sheet1!$D$5:$D$28252,"<>内部转款",Sheet1!$D$5:$D$28252,"<>内部转账",Sheet1!$E$5:$E$28252,"<>*调拨*") -> 0 | O6: =SUMIFS(Sheet1!$F$5:$F$28252,Sheet1!$I$5:$I$28252,$B6,Sheet1!$L$5:$L$28252,$A6,Sheet1!$D$5:$D$28252,"京东",Sheet1!$E$5:$E$28252,"<>*调拨*")+SUMIFS(Sheet1!$F$5:$F$28252,Sheet1!$I$5:$I$28252,$B6,Sheet1!$L$5:$L$28252,$A6,Sheet1!$E$5:$E$28252,"*京东*",Sheet1!$D$5:$D$28252,"<>京东",Sheet1!$D$5:$D$28252,"<>内部转款",Sheet1!$D$5:$D$28252,"<>内部转账",Sheet1!$E$5:$E$28252,"<>*调拨*") -> 0 | P6: =SUMIFS(Sheet1!$F$5:$F$28252,Sheet1!$I$5:$I$28252,$B6,Sheet1!$L$5:$L$28252,$A6,Sheet1!$D$5:$D$28252,"药机微信",Sheet1!$E$5:$E$28252,"<>*调拨*")+SUMIFS(Sheet1!$F$5:$F$28252,Sheet1!$I$5:$I$28252,$B6,Sheet1!$L$5:$L$28252,$A6,Sheet1!$E$5:$E$28252,"*药机微信*",Sheet1!$D$5:$D$28252,"<>药机微信",Sheet1!$D$5:$D$28252,"<>内部转款",Sheet1!$D$5:$D$28252,"<>内部转账",Sheet1!$E$5:$E$28252,"<>*调拨*") -> 0 | Q6: =SUMIFS(Sheet1!$F$5:$F$28252,Sheet1!$I$5:$I$28252,$B6,Sheet1!$L$5:$L$28252,$A6,Sheet1!$D$5:$D$28252,"亲情卡",Sheet1!$E$5:$E$28252,"<>*调拨*")+SUMIFS(Sheet1!$F$5:$F$28252,Sheet1!$I$5:$I$28252,$B6,Sheet1!$L$5:$L$28252,$A6,Sheet1!$E$5:$E$28252,"*亲情卡*",Sheet1!$D$5:$D$28252,"<>亲情卡",Sheet1!$D$5:$D$28252,"<>内部转款",Sheet1!$D$5:$D$28252,"<>内部转账",Sheet1!$E$5:$E$28252,"<>*调拨*") -> 0 | R6: =SUMIFS(Sheet1!$F$5:$F$28252,Sheet1!$I$5:$I$28252,$B6,Sheet1!$L$5:$L$28252,$A6,Sheet1!$D$5:$D$28252,"优惠券",Sheet1!$E$5:$E$28252,"<>*调拨*")+SUMIFS(Sheet1!$F$5:$F$28252,Sheet1!$I$5:$I$28252,$B6,Sheet1!$L$5:$L$28252,$A6,Sheet1!$E$5:$E$28252,"*优惠券*",Sheet1!$D$5:$D$28252,"<>优惠券",Sheet1!$D$5:$D$28252,"<>内部转款",Sheet1!$D$5:$D$28252,"<>内部转账",Sheet1!$E$5:$E$28252,"<>*调拨*") -> 0 | S6: =SUMIFS(Sheet1!$F$5:$F$28252,Sheet1!$I$5:$I$28252,$B6,Sheet1!$L$5:$L$28252,$A6,Sheet1!$D$5:$D$28252,"代金券",Sheet1!$E$5:$E$28252,"<>*调拨*")+SUMIFS(Sheet1!$F$5:$F$28252,Sheet1!$I$5:$I$28252,$B6,Sheet1!$L$5:$L$28252,$A6,Sheet1!$E$5:$E$28252,"*代金券*",Sheet1!$D$5:$D$28252,"<>代金券",Sheet1!$D$5:$D$28252,"<>内部转款",Sheet1!$D$5:$D$28252,"<>内部转账",Sheet1!$E$5:$E$28252,"<>*调拨*") -> 0 | T6: =SUMIFS(Sheet1!$F$5:$F$28252,Sheet1!$I$5:$I$28252,$B6,Sheet1!$L$5:$L$28252,$A6,Sheet1!$D$5:$D$28252,"回款",Sheet1!$E$5:$E$28252,"<>*调拨*",Sheet1!$E$5:$E$28252,"<>*医保*",Sheet1!$E$5:$E$28252,"<>*聚合*",Sheet1!$E$5:$E$28252,"<>*24小时微信*",Sheet1!$E$5:$E$28252,"<>*美团*",Sheet1!$E$5:$E$28252,"<>*饿了么*",Sheet1!$E$5:$E$28252,"<>*健E卡*",Sheet1!$E$5:$E$28252,"<>*抖音*",Sheet1!$E$5:$E$28252,"<>*医卡通*",Sheet1!$E$5:$E$28252,"<>*企健网*",Sheet1!$E$5:$E$28252,"<>*银联*",Sheet1!$E$5:$E$28252,"<>*京东*",Sheet1!$E$5:$E$28252,"<>*药机微信*",Sheet1!$E$5:$E$28252,"<>*亲情卡*",Sheet1!$E$5:$E$28252,"<>*优惠券*",Sheet1!$E$5:$E$28252,"<>*代金券*",Sheet1!$E$5:$E$28252,"<>*储值*",Sheet1!$E$5:$E$28252,"<>*效期*")+SUMIFS(Sheet1!$F$5:$F$28252,Sheet1!$I$5:$I$28252,$B6,Sheet1!$L$5:$L$28252,$A6,Sheet1!$D$5:$D$28252,"收款",Sheet1!$E$5:$E$28252,"<>*调拨*",Sheet1!$E$5:$E$28252,"<>*医保*",Sheet1!$E$5:$E$28252,"<>*聚合*",Sheet1!$E$5:$E$28252,"<>*24小时微信*",Sheet1!$E$5:$E$28252,"<>*美团*",Sheet1!$E$5:$E$28252,"<>*饿了么*",Sheet1!$E$5:$E$28252,"<>*健E卡*",Sheet1!$E$5:$E$28252,"<>*抖音*",Sheet1!$E$5:$E$28252,"<>*医卡通*",Sheet1!$E$5:$E$28252,"<>*企健网*",Sheet1!$E$5:$E$28252,"<>*银联*",Sheet1!$E$5:$E$28252,"<>*京东*",Sheet1!$E$5:$E$28252,"<>*药机微信*",Sheet1!$E$5:$E$28252,"<>*亲情卡*",Sheet1!$E$5:$E$28252,"<>*优惠券*",Sheet1!$E$5:$E$28252,"<>*代金券*",Sheet1!$E$5:$E$28252,"<>*储值*",Sheet1!$E$5:$E$28252,"<>*效期*")+SUMIFS(Sheet1!$F$5:$F$28252,Sheet1!$I$5:$I$28252,$B6,Sheet1!$L$5:$L$28252,$A6,Sheet1!$E$5:$E$28252,"*回款*",Sheet1!$D$5:$D$28252,"<>回款",Sheet1!$D$5:$D$28252,"<>收款",Sheet1!$D$5:$D$28252,"<>内部转款",Sheet1!$D$5:$D$28252,"<>内部转账",Sheet1!$E$5:$E$28252,"<>*调拨*",Sheet1!$E$5:$E$28252,"<>*医保*",Sheet1!$E$5:$E$28252,"<>*聚合*",Sheet1!$E$5:$E$28252,"<>*24小时微信*",Sheet1!$E$5:$E$28252,"<>*美团*",Sheet1!$E$5:$E$28252,"<>*饿了么*",Sheet1!$E$5:$E$28252,"<>*健E卡*",Sheet1!$E$5:$E$28252,"<>*抖音*",Sheet1!$E$5:$E$28252,"<>*医卡通*",Sheet1!$E$5:$E$28252,"<>*企健网*",Sheet1!$E$5:$E$28252,"<>*银联*",Sheet1!$E$5:$E$28252,"<>*京东*",Sheet1!$E$5:$E$28252,"<>*药机微信*",Sheet1!$E$5:$E$28252,"<>*亲情卡*",Sheet1!$E$5:$E$28252,"<>*优惠券*",Sheet1!$E$5:$E$28252,"<>*代金券*",Sheet1!$E$5:$E$28252,"<>*储值*",Sheet1!$E$5:$E$28252,"<>*效期*")+SUMIFS(Sheet1!$F$5:$F$28252,Sheet1!$I$5:$I$28252,$B6,Sheet1!$L$5:$L$28252,$A6,Sheet1!$E$5:$E$28252,"*收款*",Sheet1!$E$5:$E$28252,"<>*回款*",Sheet1!$D$5:$D$28252,"<>回款",Sheet1!$D$5:$D$28252,"<>收款",Sheet1!$D$5:$D$28252,"<>内部转款",Sheet1!$D$5:$D$28252,"<>内部转账",Sheet1!$E$5:$E$28252,"<>*调拨*",Sheet1!$E$5:$E$28252,"<>*医保*",Sheet1!$E$5:$E$28252,"<>*聚合*",Sheet1!$E$5:$E$28252,"<>*24小时微信*",Sheet1!$E$5:$E$28252,"<>*美团*",Sheet1!$E$5:$E$28252,"<>*饿了么*",Sheet1!$E$5:$E$28252,"<>*健E卡*",Sheet1!$E$5:$E$28252,"<>*抖音*",Sheet1!$E$5:$E$28252,"<>*医卡通*",Sheet1!$E$5:$E$28252,"<>*企健网*",Sheet1!$E$5:$E$28252,"<>*银联*",Sheet1!$E$5:$E$28252,"<>*京东*",Sheet1!$E$5:$E$28252,"<>*药机微信*",Sheet1!$E$5:$E$28252,"<>*亲情卡*",Sheet1!$E$5:$E$28252,"<>*优惠券*",Sheet1!$E$5:$E$28252,"<>*代金券*",Sheet1!$E$5:$E$28252,"<>*储值*",Sheet1!$E$5:$E$28252,"<>*效期*") -> 0 | U6: =SUMIFS(Sheet1!$F$5:$F$28252,Sheet1!$I$5:$I$28252,$B6,Sheet1!$L$5:$L$28252,$A6,Sheet1!$E$5:$E$28252,"*调拨*") -> 0 | V6: =SUMIFS(Sheet1!$F$5:$F$28252,Sheet1!$I$5:$I$28252,$B6,Sheet1!$L$5:$L$28252,$A6,Sheet1!$D$5:$D$28252,"储值",Sheet1!$E$5:$E$28252,"<>*调拨*")+SUMIFS(Sheet1!$F$5:$F$28252,Sheet1!$I$5:$I$28252,$B6,Sheet1!$L$5:$L$28252,$A6,Sheet1!$E$5:$E$28252,"*储值*",Sheet1!$D$5:$D$28252,"<>储值",Sheet1!$D$5:$D$28252,"<>内部转款",Sheet1!$D$5:$D$28252,"<>内部转账",Sheet1!$E$5:$E$28252,"<>*调拨*") -> 0 | W6: =SUMIFS(Sheet1!$F$5:$F$28252,Sheet1!$I$5:$I$28252,$B6,Sheet1!$L$5:$L$28252,$A6,Sheet1!$D$5:$D$28252,"效期",Sheet1!$E$5:$E$28252,"<>*调拨*")+SUMIFS(Sheet1!$F$5:$F$28252,Sheet1!$I$5:$I$28252,$B6,Sheet1!$L$5:$L$28252,$A6,Sheet1!$E$5:$E$28252,"*效期*",Sheet1!$D$5:$D$28252,"<>效期",Sheet1!$D$5:$D$28252,"<>内部转款",Sheet1!$D$5:$D$28252,"<>内部转账",Sheet1!$E$5:$E$28252,"<>*调拨*") -> 0 | X6: =SUMIFS(Sheet1!$F$5:$F$28252,Sheet1!$I$5:$I$28252,$B6,Sheet1!$L$5:$L$28252,$A6,Sheet1!$D$5:$D$28252,"内部转款",Sheet1!$E$5:$E$28252,"<>*调拨*")+SUMIFS(Sheet1!$F$5:$F$28252,Sheet1!$I$5:$I$28252,$B6,Sheet1!$L$5:$L$28252,$A6,Sheet1!$D$5:$D$28252,"内部转账",Sheet1!$E$5:$E$28252,"<>*调拨*") -> 0 | Y6: =Z6-SUM(C6:X6) -> 0 | Z6: =SUMIFS(Sheet1!$F$5:$F$28252,Sheet1!$I$5:$I$28252,$B6,Sheet1!$L$5:$L$28252,$A6) -> 0 | AA6: =SUMIFS(Sheet1!$G$5:$G$28252,Sheet1!$I$5:$I$28252,$B6,Sheet1!$L$5:$L$28252,$A6,Sheet1!$D$5:$D$28252,"工资",Sheet1!$E$5:$E$28252,"<>*调拨*")+SUMIFS(Sheet1!$G$5:$G$28252,Sheet1!$I$5:$I$28252,$B6,Sheet1!$L$5:$L$28252,$A6,Sheet1!$E$5:$E$28252,"*工资*",Sheet1!$E$5:$E$28252,"<>*调拨*",Sheet1!$D$5:$D$28252,"<>内部转款",Sheet1!$D$5:$D$28252,"<>内部转账",Sheet1!$D$5:$D$28252,"<>工资",Sheet1!$D$5:$D$28252,"<>水费",Sheet1!$D$5:$D$28252,"<>电费",Sheet1!$D$5:$D$28252,"<>宽带费",Sheet1!$D$5:$D$28252,"<>办公费",Sheet1!$D$5:$D$28252,"<>话费",Sheet1!$D$5:$D$28252,"<>房租") -> 0 | AB6: =SUMIFS(Sheet1!$G$5:$G$28252,Sheet1!$I$5:$I$28252,$B6,Sheet1!$L$5:$L$28252,$A6,Sheet1!$D$5:$D$28252,"水费",Sheet1!$E$5:$E$28252,"<>*调拨*")+SUMIFS(Sheet1!$G$5:$G$28252,Sheet1!$I$5:$I$28252,$B6,Sheet1!$L$5:$L$28252,$A6,Sheet1!$E$5:$E$28252,"*水费*",Sheet1!$E$5:$E$28252,"<>*调拨*",Sheet1!$D$5:$D$28252,"<>内部转款",Sheet1!$D$5:$D$28252,"<>内部转账",Sheet1!$D$5:$D$28252,"<>工资",Sheet1!$D$5:$D$28252,"<>水费",Sheet1!$D$5:$D$28252,"<>电费",Sheet1!$D$5:$D$28252,"<>宽带费",Sheet1!$D$5:$D$28252,"<>办公费",Sheet1!$D$5:$D$28252,"<>话费",Sheet1!$D$5:$D$28252,"<>房租",Sheet1!$E$5:$E$28252,"<>*工资*") -> 0 | AC6: =SUMIFS(Sheet1!$G$5:$G$28252,Sheet1!$I$5:$I$28252,$B6,Sheet1!$L$5:$L$28252,$A6,Sheet1!$D$5:$D$28252,"电费",Sheet1!$E$5:$E$28252,"<>*调拨*")+SUMIFS(Sheet1!$G$5:$G$28252,Sheet1!$I$5:$I$28252,$B6,Sheet1!$L$5:$L$28252,$A6,Sheet1!$E$5:$E$28252,"*电费*",Sheet1!$E$5:$E$28252,"<>*调拨*",Sheet1!$D$5:$D$28252,"<>内部转款",Sheet1!$D$5:$D$28252,"<>内部转账",Sheet1!$D$5:$D$28252,"<>工资",Sheet1!$D$5:$D$28252,"<>水费",Sheet1!$D$5:$D$28252,"<>电费",Sheet1!$D$5:$D$28252,"<>宽带费",Sheet1!$D$5:$D$28252,"<>办公费",Sheet1!$D$5:$D$28252,"<>话费",Sheet1!$D$5:$D$28252,"<>房租",Sheet1!$E$5:$E$28252,"<>*工资*",Sheet1!$E$5:$E$28252,"<>*水费*") -> 0 | AD6: =SUMIFS(Sheet1!$G$5:$G$28252,Sheet1!$I$5:$I$28252,$B6,Sheet1!$L$5:$L$28252,$A6,Sheet1!$D$5:$D$28252,"宽带费",Sheet1!$E$5:$E$28252,"<>*调拨*")+SUMIFS(Sheet1!$G$5:$G$28252,Sheet1!$I$5:$I$28252,$B6,Sheet1!$L$5:$L$28252,$A6,Sheet1!$E$5:$E$28252,"*宽带*",Sheet1!$E$5:$E$28252,"<>*调拨*",Sheet1!$D$5:$D$28252,"<>内部转款",Sheet1!$D$5:$D$28252,"<>内部转账",Sheet1!$D$5:$D$28252,"<>工资",Sheet1!$D$5:$D$28252,"<>水费",Sheet1!$D$5:$D$28252,"<>电费",Sheet1!$D$5:$D$28252,"<>宽带费",Sheet1!$D$5:$D$28252,"<>办公费",Sheet1!$D$5:$D$28252,"<>话费",Sheet1!$D$5:$D$28252,"<>房租",Sheet1!$E$5:$E$28252,"<>*工资*",Sheet1!$E$5:$E$28252,"<>*水费*",Sheet1!$E$5:$E$28252,"<>*电费*") -> 0 | AE6: =SUMIFS(Sheet1!$G$5:$G$28252,Sheet1!$I$5:$I$28252,$B6,Sheet1!$L$5:$L$28252,$A6,Sheet1!$D$5:$D$28252,"办公费",Sheet1!$E$5:$E$28252,"<>*调拨*")+SUMIFS(Sheet1!$G$5:$G$28252,Sheet1!$I$5:$I$28252,$B6,Sheet1!$L$5:$L$28252,$A6,Sheet1!$E$5:$E$28252,"*办公*",Sheet1!$E$5:$E$28252,"<>*调拨*",Sheet1!$D$5:$D$28252,"<>内部转款",Sheet1!$D$5:$D$28252,"<>内部转账",Sheet1!$D$5:$D$28252,"<>工资",Sheet1!$D$5:$D$28252,"<>水费",Sheet1!$D$5:$D$28252,"<>电费",Sheet1!$D$5:$D$28252,"<>宽带费",Sheet1!$D$5:$D$28252,"<>办公费",Sheet1!$D$5:$D$28252,"<>话费",Sheet1!$D$5:$D$28252,"<>房租",Sheet1!$E$5:$E$28252,"<>*工资*",Sheet1!$E$5:$E$28252,"<>*水费*",Sheet1!$E$5:$E$28252,"<>*电费*",Sheet1!$E$5:$E$28252,"<>*宽带*") -> 0 | AF6: =SUMIFS(Sheet1!$G$5:$G$28252,Sheet1!$I$5:$I$28252,$B6,Sheet1!$L$5:$L$28252,$A6,Sheet1!$D$5:$D$28252,"话费",Sheet1!$E$5:$E$28252,"<>*调拨*")+SUMIFS(Sheet1!$G$5:$G$28252,Sheet1!$I$5:$I$28252,$B6,Sheet1!$L$5:$L$28252,$A6,Sheet1!$E$5:$E$28252,"*话费*",Sheet1!$E$5:$E$28252,"<>*调拨*",Sheet1!$D$5:$D$28252,"<>内部转款",Sheet1!$D$5:$D$28252,"<>内部转账",Sheet1!$D$5:$D$28252,"<>工资",Sheet1!$D$5:$D$28252,"<>水费",Sheet1!$D$5:$D$28252,"<>电费",Sheet1!$D$5:$D$28252,"<>宽带费",Sheet1!$D$5:$D$28252,"<>办公费",Sheet1!$D$5:$D$28252,"<>话费",Sheet1!$D$5:$D$28252,"<>房租",Sheet1!$E$5:$E$28252,"<>*工资*",Sheet1!$E$5:$E$28252,"<>*水费*",Sheet1!$E$5:$E$28252,"<>*电费*",Sheet1!$E$5:$E$28252,"<>*宽带*",Sheet1!$E$5:$E$28252,"<>*办公*") -> 0 | AG6: =SUMIFS(Sheet1!$G$5:$G$28252,Sheet1!$I$5:$I$28252,$B6,Sheet1!$L$5:$L$28252,$A6,Sheet1!$D$5:$D$28252,"房租",Sheet1!$E$5:$E$28252,"<>*调拨*")+SUMIFS(Sheet1!$G$5:$G$28252,Sheet1!$I$5:$I$28252,$B6,Sheet1!$L$5:$L$28252,$A6,Sheet1!$E$5:$E$28252,"*房租*",Sheet1!$E$5:$E$28252,"<>*调拨*",Sheet1!$D$5:$D$28252,"<>内部转款",Sheet1!$D$5:$D$28252,"<>内部转账",Sheet1!$D$5:$D$28252,"<>工资",Sheet1!$D$5:$D$28252,"<>水费",Sheet1!$D$5:$D$28252,"<>电费",Sheet1!$D$5:$D$28252,"<>宽带费",Sheet1!$D$5:$D$28252,"<>办公费",Sheet1!$D$5:$D$28252,"<>话费",Sheet1!$D$5:$D$28252,"<>房租",Sheet1!$E$5:$E$28252,"<>*工资*",Sheet1!$E$5:$E$28252,"<>*水费*",Sheet1!$E$5:$E$28252,"<>*电费*",Sheet1!$E$5:$E$28252,"<>*宽带*",Sheet1!$E$5:$E$28252,"<>*办公*",Sheet1!$E$5:$E$28252,"<>*话费*") -> 0 | AH6: =SUMIFS(Sheet1!$G$5:$G$28252,Sheet1!$I$5:$I$28252,$B6,Sheet1!$L$5:$L$28252,$A6,Sheet1!$E$5:$E$28252,"*调拨*") -> 0 | AI6: =SUMIFS(Sheet1!$G$5:$G$28252,Sheet1!$I$5:$I$28252,$B6,Sheet1!$L$5:$L$28252,$A6,Sheet1!$D$5:$D$28252,"内部转款",Sheet1!$E$5:$E$28252,"<>*调拨*")+SUMIFS(Sheet1!$G$5:$G$28252,Sheet1!$I$5:$I$28252,$B6,Sheet1!$L$5:$L$28252,$A6,Sheet1!$D$5:$D$28252,"内部转账",Sheet1!$E$5:$E$28252,"<>*调拨*") -> 0 | AJ6: =AK6-SUM(AA6:AI6) -> 0 | AK6: =SUMIFS(Sheet1!$G$5:$G$28252,Sheet1!$I$5:$I$28252,$B6,Sheet1!$L$5:$L$28252,$A6) -> 0 | AL6: =Z6-AK6 -> 0
A7: 202512 | B7: 临城县博福分店43店 | C7: =SUMIFS(Sheet1!$F$5:$F$28252,Sheet1!$I$5:$I$28252,$B7,Sheet1!$L$5:$L$28252,$A7,Sheet1!$D$5:$D$28252,"营业款",Sheet1!$E$5:$E$28252,"<>*调拨*",Sheet1!$E$5:$E$28252,"<>*回款*",Sheet1!$E$5:$E$28252,"<>*收款*",Sheet1!$E$5:$E$28252,"<>*医保*",Sheet1!$E$5:$E$28252,"<>*聚合*",Sheet1!$E$5:$E$28252,"<>*24小时微信*",Sheet1!$E$5:$E$28252,"<>*美团*",Sheet1!$E$5:$E$28252,"<>*饿了么*",Sheet1!$E$5:$E$28252,"<>*健E卡*",Sheet1!$E$5:$E$28252,"<>*抖音*",Sheet1!$E$5:$E$28252,"<>*医卡通*",Sheet1!$E$5:$E$28252,"<>*企健网*",Sheet1!$E$5:$E$28252,"<>*银联*",Sheet1!$E$5:$E$28252,"<>*京东*",Sheet1!$E$5:$E$28252,"<>*药机微信*",Sheet1!$E$5:$E$28252,"<>*亲情卡*",Sheet1!$E$5:$E$28252,"<>*优惠券*",Sheet1!$E$5:$E$28252,"<>*代金券*",Sheet1!$E$5:$E$28252,"<>*储值*",Sheet1!$E$5:$E$28252,"<>*效期*") -> 0 | D7: =SUMIFS(Sheet1!$F$5:$F$28252,Sheet1!$I$5:$I$28252,$B7,Sheet1!$L$5:$L$28252,$A7,Sheet1!$D$5:$D$28252,"医保即时拨付",Sheet1!$E$5:$E$28252,"<>*调拨*")+SUMIFS(Sheet1!$F$5:$F$28252,Sheet1!$I$5:$I$28252,$B7,Sheet1!$L$5:$L$28252,$A7,Sheet1!$E$5:$E$28252,"*医保即时拨付*",Sheet1!$D$5:$D$28252,"<>医保即时拨付",Sheet1!$D$5:$D$28252,"<>内部转款",Sheet1!$D$5:$D$28252,"<>内部转账",Sheet1!$E$5:$E$28252,"<>*调拨*") -> 0 | E7: =SUMIFS(Sheet1!$F$5:$F$28252,Sheet1!$I$5:$I$28252,$B7,Sheet1!$L$5:$L$28252,$A7,Sheet1!$D$5:$D$28252,"医保",Sheet1!$E$5:$E$28252,"<>*调拨*",Sheet1!$E$5:$E$28252,"<>*医保即时拨付*")+SUMIFS(Sheet1!$F$5:$F$28252,Sheet1!$I$5:$I$28252,$B7,Sheet1!$L$5:$L$28252,$A7,Sheet1!$E$5:$E$28252,"*医保*",Sheet1!$D$5:$D$28252,"<>医保",Sheet1!$D$5:$D$28252,"<>医保即时拨付",Sheet1!$D$5:$D$28252,"<>内部转款",Sheet1!$D$5:$D$28252,"<>内部转账",Sheet1!$E$5:$E$28252,"<>*医保即时拨付*",Sheet1!$E$5:$E$28252,"<>*调拨*") -> 0 | F7: =SUMIFS(Sheet1!$F$5:$F$28252,Sheet1!$I$5:$I$28252,$B7,Sheet1!$L$5:$L$28252,$A7,Sheet1!$D$5:$D$28252,"聚合",Sheet1!$E$5:$E$28252,"<>*调拨*")+SUMIFS(Sheet1!$F$5:$F$28252,Sheet1!$I$5:$I$28252,$B7,Sheet1!$L$5:$L$28252,$A7,Sheet1!$E$5:$E$28252,"*聚合*",Sheet1!$D$5:$D$28252,"<>聚合",Sheet1!$D$5:$D$28252,"<>内部转款",Sheet1!$D$5:$D$28252,"<>内部转账",Sheet1!$E$5:$E$28252,"<>*调拨*") -> 0 | G7: =SUMIFS(Sheet1!$F$5:$F$28252,Sheet1!$I$5:$I$28252,$B7,Sheet1!$L$5:$L$28252,$A7,Sheet1!$D$5:$D$28252,"24小时微信",Sheet1!$E$5:$E$28252,"<>*调拨*")+SUMIFS(Sheet1!$F$5:$F$28252,Sheet1!$I$5:$I$28252,$B7,Sheet1!$L$5:$L$28252,$A7,Sheet1!$E$5:$E$28252,"*24小时微信*",Sheet1!$D$5:$D$28252,"<>24小时微信",Sheet1!$D$5:$D$28252,"<>内部转款",Sheet1!$D$5:$D$28252,"<>内部转账",Sheet1!$E$5:$E$28252,"<>*调拨*") -> 0 | H7: =SUMIFS(Sheet1!$F$5:$F$28252,Sheet1!$I$5:$I$28252,$B7,Sheet1!$L$5:$L$28252,$A7,Sheet1!$D$5:$D$28252,"美团",Sheet1!$E$5:$E$28252,"<>*调拨*")+SUMIFS(Sheet1!$F$5:$F$28252,Sheet1!$I$5:$I$28252,$B7,Sheet1!$L$5:$L$28252,$A7,Sheet1!$E$5:$E$28252,"*美团*",Sheet1!$D$5:$D$28252,"<>美团",Sheet1!$D$5:$D$28252,"<>内部转款",Sheet1!$D$5:$D$28252,"<>内部转账",Sheet1!$E$5:$E$28252,"<>*调拨*") -> 0 | I7: =SUMIFS(Sheet1!$F$5:$F$28252,Sheet1!$I$5:$I$28252,$B7,Sheet1!$L$5:$L$28252,$A7,Sheet1!$D$5:$D$28252,"饿了么",Sheet1!$E$5:$E$28252,"<>*调拨*")+SUMIFS(Sheet1!$F$5:$F$28252,Sheet1!$I$5:$I$28252,$B7,Sheet1!$L$5:$L$28252,$A7,Sheet1!$E$5:$E$28252,"*饿了么*",Sheet1!$D$5:$D$28252,"<>饿了么",Sheet1!$D$5:$D$28252,"<>内部转款",Sheet1!$D$5:$D$28252,"<>内部转账",Sheet1!$E$5:$E$28252,"<>*调拨*") -> 0 | J7: =SUMIFS(Sheet1!$F$5:$F$28252,Sheet1!$I$5:$I$28252,$B7,Sheet1!$L$5:$L$28252,$A7,Sheet1!$D$5:$D$28252,"健E卡",Sheet1!$E$5:$E$28252,"<>*调拨*")+SUMIFS(Sheet1!$F$5:$F$28252,Sheet1!$I$5:$I$28252,$B7,Sheet1!$L$5:$L$28252,$A7,Sheet1!$E$5:$E$28252,"*健E卡*",Sheet1!$D$5:$D$28252,"<>健E卡",Sheet1!$D$5:$D$28252,"<>内部转款",Sheet1!$D$5:$D$28252,"<>内部转账",Sheet1!$E$5:$E$28252,"<>*调拨*") -> 0 | K7: =SUMIFS(Sheet1!$F$5:$F$28252,Sheet1!$I$5:$I$28252,$B7,Sheet1!$L$5:$L$28252,$A7,Sheet1!$D$5:$D$28252,"抖音",Sheet1!$E$5:$E$28252,"<>*调拨*")+SUMIFS(Sheet1!$F$5:$F$28252,Sheet1!$I$5:$I$28252,$B7,Sheet1!$L$5:$L$28252,$A7,Sheet1!$E$5:$E$28252,"*抖音*",Sheet1!$D$5:$D$28252,"<>抖音",Sheet1!$D$5:$D$28252,"<>内部转款",Sheet1!$D$5:$D$28252,"<>内部转账",Sheet1!$E$5:$E$28252,"<>*调拨*") -> 0 | L7: =SUMIFS(Sheet1!$F$5:$F$28252,Sheet1!$I$5:$I$28252,$B7,Sheet1!$L$5:$L$28252,$A7,Sheet1!$D$5:$D$28252,"医卡通",Sheet1!$E$5:$E$28252,"<>*调拨*")+SUMIFS(Sheet1!$F$5:$F$28252,Sheet1!$I$5:$I$28252,$B7,Sheet1!$L$5:$L$28252,$A7,Sheet1!$E$5:$E$28252,"*医卡通*",Sheet1!$D$5:$D$28252,"<>医卡通",Sheet1!$D$5:$D$28252,"<>内部转款",Sheet1!$D$5:$D$28252,"<>内部转账",Sheet1!$E$5:$E$28252,"<>*调拨*") -> 0 | M7: =SUMIFS(Sheet1!$F$5:$F$28252,Sheet1!$I$5:$I$28252,$B7,Sheet1!$L$5:$L$28252,$A7,Sheet1!$D$5:$D$28252,"企健网",Sheet1!$E$5:$E$28252,"<>*调拨*")+SUMIFS(Sheet1!$F$5:$F$28252,Sheet1!$I$5:$I$28252,$B7,Sheet1!$L$5:$L$28252,$A7,Sheet1!$E$5:$E$28252,"*企健网*",Sheet1!$D$5:$D$28252,"<>企健网",Sheet1!$D$5:$D$28252,"<>内部转款",Sheet1!$D$5:$D$28252,"<>内部转账",Sheet1!$E$5:$E$28252,"<>*调拨*") -> 0 | N7: =SUMIFS(Sheet1!$F$5:$F$28252,Sheet1!$I$5:$I$28252,$B7,Sheet1!$L$5:$L$28252,$A7,Sheet1!$D$5:$D$28252,"银联",Sheet1!$E$5:$E$28252,"<>*调拨*")+SUMIFS(Sheet1!$F$5:$F$28252,Sheet1!$I$5:$I$28252,$B7,Sheet1!$L$5:$L$28252,$A7,Sheet1!$E$5:$E$28252,"*银联*",Sheet1!$D$5:$D$28252,"<>银联",Sheet1!$D$5:$D$28252,"<>内部转款",Sheet1!$D$5:$D$28252,"<>内部转账",Sheet1!$E$5:$E$28252,"<>*调拨*") -> 0 | O7: =SUMIFS(Sheet1!$F$5:$F$28252,Sheet1!$I$5:$I$28252,$B7,Sheet1!$L$5:$L$28252,$A7,Sheet1!$D$5:$D$28252,"京东",Sheet1!$E$5:$E$28252,"<>*调拨*")+SUMIFS(Sheet1!$F$5:$F$28252,Sheet1!$I$5:$I$28252,$B7,Sheet1!$L$5:$L$28252,$A7,Sheet1!$E$5:$E$28252,"*京东*",Sheet1!$D$5:$D$28252,"<>京东",Sheet1!$D$5:$D$28252,"<>内部转款",Sheet1!$D$5:$D$28252,"<>内部转账",Sheet1!$E$5:$E$28252,"<>*调拨*") -> 0 | P7: =SUMIFS(Sheet1!$F$5:$F$28252,Sheet1!$I$5:$I$28252,$B7,Sheet1!$L$5:$L$28252,$A7,Sheet1!$D$5:$D$28252,"药机微信",Sheet1!$E$5:$E$28252,"<>*调拨*")+SUMIFS(Sheet1!$F$5:$F$28252,Sheet1!$I$5:$I$28252,$B7,Sheet1!$L$5:$L$28252,$A7,Sheet1!$E$5:$E$28252,"*药机微信*",Sheet1!$D$5:$D$28252,"<>药机微信",Sheet1!$D$5:$D$28252,"<>内部转款",Sheet1!$D$5:$D$28252,"<>内部转账",Sheet1!$E$5:$E$28252,"<>*调拨*") -> 0 | Q7: =SUMIFS(Sheet1!$F$5:$F$28252,Sheet1!$I$5:$I$28252,$B7,Sheet1!$L$5:$L$28252,$A7,Sheet1!$D$5:$D$28252,"亲情卡",Sheet1!$E$5:$E$28252,"<>*调拨*")+SUMIFS(Sheet1!$F$5:$F$28252,Sheet1!$I$5:$I$28252,$B7,Sheet1!$L$5:$L$28252,$A7,Sheet1!$E$5:$E$28252,"*亲情卡*",Sheet1!$D$5:$D$28252,"<>亲情卡",Sheet1!$D$5:$D$28252,"<>内部转款",Sheet1!$D$5:$D$28252,"<>内部转账",Sheet1!$E$5:$E$28252,"<>*调拨*") -> 0 | R7: =SUMIFS(Sheet1!$F$5:$F$28252,Sheet1!$I$5:$I$28252,$B7,Sheet1!$L$5:$L$28252,$A7,Sheet1!$D$5:$D$28252,"优惠券",Sheet1!$E$5:$E$28252,"<>*调拨*")+SUMIFS(Sheet1!$F$5:$F$28252,Sheet1!$I$5:$I$28252,$B7,Sheet1!$L$5:$L$28252,$A7,Sheet1!$E$5:$E$28252,"*优惠券*",Sheet1!$D$5:$D$28252,"<>优惠券",Sheet1!$D$5:$D$28252,"<>内部转款",Sheet1!$D$5:$D$28252,"<>内部转账",Sheet1!$E$5:$E$28252,"<>*调拨*") -> 0 | S7: =SUMIFS(Sheet1!$F$5:$F$28252,Sheet1!$I$5:$I$28252,$B7,Sheet1!$L$5:$L$28252,$A7,Sheet1!$D$5:$D$28252,"代金券",Sheet1!$E$5:$E$28252,"<>*调拨*")+SUMIFS(Sheet1!$F$5:$F$28252,Sheet1!$I$5:$I$28252,$B7,Sheet1!$L$5:$L$28252,$A7,Sheet1!$E$5:$E$28252,"*代金券*",Sheet1!$D$5:$D$28252,"<>代金券",Sheet1!$D$5:$D$28252,"<>内部转款",Sheet1!$D$5:$D$28252,"<>内部转账",Sheet1!$E$5:$E$28252,"<>*调拨*") -> 0 | T7: =SUMIFS(Sheet1!$F$5:$F$28252,Sheet1!$I$5:$I$28252,$B7,Sheet1!$L$5:$L$28252,$A7,Sheet1!$D$5:$D$28252,"回款",Sheet1!$E$5:$E$28252,"<>*调拨*",Sheet1!$E$5:$E$28252,"<>*医保*",Sheet1!$E$5:$E$28252,"<>*聚合*",Sheet1!$E$5:$E$28252,"<>*24小时微信*",Sheet1!$E$5:$E$28252,"<>*美团*",Sheet1!$E$5:$E$28252,"<>*饿了么*",Sheet1!$E$5:$E$28252,"<>*健E卡*",Sheet1!$E$5:$E$28252,"<>*抖音*",Sheet1!$E$5:$E$28252,"<>*医卡通*",Sheet1!$E$5:$E$28252,"<>*企健网*",Sheet1!$E$5:$E$28252,"<>*银联*",Sheet1!$E$5:$E$28252,"<>*京东*",Sheet1!$E$5:$E$28252,"<>*药机微信*",Sheet1!$E$5:$E$28252,"<>*亲情卡*",Sheet1!$E$5:$E$28252,"<>*优惠券*",Sheet1!$E$5:$E$28252,"<>*代金券*",Sheet1!$E$5:$E$28252,"<>*储值*",Sheet1!$E$5:$E$28252,"<>*效期*")+SUMIFS(Sheet1!$F$5:$F$28252,Sheet1!$I$5:$I$28252,$B7,Sheet1!$L$5:$L$28252,$A7,Sheet1!$D$5:$D$28252,"收款",Sheet1!$E$5:$E$28252,"<>*调拨*",Sheet1!$E$5:$E$28252,"<>*医保*",Sheet1!$E$5:$E$28252,"<>*聚合*",Sheet1!$E$5:$E$28252,"<>*24小时微信*",Sheet1!$E$5:$E$28252,"<>*美团*",Sheet1!$E$5:$E$28252,"<>*饿了么*",Sheet1!$E$5:$E$28252,"<>*健E卡*",Sheet1!$E$5:$E$28252,"<>*抖音*",Sheet1!$E$5:$E$28252,"<>*医卡通*",Sheet1!$E$5:$E$28252,"<>*企健网*",Sheet1!$E$5:$E$28252,"<>*银联*",Sheet1!$E$5:$E$28252,"<>*京东*",Sheet1!$E$5:$E$28252,"<>*药机微信*",Sheet1!$E$5:$E$28252,"<>*亲情卡*",Sheet1!$E$5:$E$28252,"<>*优惠券*",Sheet1!$E$5:$E$28252,"<>*代金券*",Sheet1!$E$5:$E$28252,"<>*储值*",Sheet1!$E$5:$E$28252,"<>*效期*")+SUMIFS(Sheet1!$F$5:$F$28252,Sheet1!$I$5:$I$28252,$B7,Sheet1!$L$5:$L$28252,$A7,Sheet1!$E$5:$E$28252,"*回款*",Sheet1!$D$5:$D$28252,"<>回款",Sheet1!$D$5:$D$28252,"<>收款",Sheet1!$D$5:$D$28252,"<>内部转款",Sheet1!$D$5:$D$28252,"<>内部转账",Sheet1!$E$5:$E$28252,"<>*调拨*",Sheet1!$E$5:$E$28252,"<>*医保*",Sheet1!$E$5:$E$28252,"<>*聚合*",Sheet1!$E$5:$E$28252,"<>*24小时微信*",Sheet1!$E$5:$E$28252,"<>*美团*",Sheet1!$E$5:$E$28252,"<>*饿了么*",Sheet1!$E$5:$E$28252,"<>*健E卡*",Sheet1!$E$5:$E$28252,"<>*抖音*",Sheet1!$E$5:$E$28252,"<>*医卡通*",Sheet1!$E$5:$E$28252,"<>*企健网*",Sheet1!$E$5:$E$28252,"<>*银联*",Sheet1!$E$5:$E$28252,"<>*京东*",Sheet1!$E$5:$E$28252,"<>*药机微信*",Sheet1!$E$5:$E$28252,"<>*亲情卡*",Sheet1!$E$5:$E$28252,"<>*优惠券*",Sheet1!$E$5:$E$28252,"<>*代金券*",Sheet1!$E$5:$E$28252,"<>*储值*",Sheet1!$E$5:$E$28252,"<>*效期*")+SUMIFS(Sheet1!$F$5:$F$28252,Sheet1!$I$5:$I$28252,$B7,Sheet1!$L$5:$L$28252,$A7,Sheet1!$E$5:$E$28252,"*收款*",Sheet1!$E$5:$E$28252,"<>*回款*",Sheet1!$D$5:$D$28252,"<>回款",Sheet1!$D$5:$D$28252,"<>收款",Sheet1!$D$5:$D$28252,"<>内部转款",Sheet1!$D$5:$D$28252,"<>内部转账",Sheet1!$E$5:$E$28252,"<>*调拨*",Sheet1!$E$5:$E$28252,"<>*医保*",Sheet1!$E$5:$E$28252,"<>*聚合*",Sheet1!$E$5:$E$28252,"<>*24小时微信*",Sheet1!$E$5:$E$28252,"<>*美团*",Sheet1!$E$5:$E$28252,"<>*饿了么*",Sheet1!$E$5:$E$28252,"<>*健E卡*",Sheet1!$E$5:$E$28252,"<>*抖音*",Sheet1!$E$5:$E$28252,"<>*医卡通*",Sheet1!$E$5:$E$28252,"<>*企健网*",Sheet1!$E$5:$E$28252,"<>*银联*",Sheet1!$E$5:$E$28252,"<>*京东*",Sheet1!$E$5:$E$28252,"<>*药机微信*",Sheet1!$E$5:$E$28252,"<>*亲情卡*",Sheet1!$E$5:$E$28252,"<>*优惠券*",Sheet1!$E$5:$E$28252,"<>*代金券*",Sheet1!$E$5:$E$28252,"<>*储值*",Sheet1!$E$5:$E$28252,"<>*效期*") -> 0 | U7: =SUMIFS(Sheet1!$F$5:$F$28252,Sheet1!$I$5:$I$28252,$B7,Sheet1!$L$5:$L$28252,$A7,Sheet1!$E$5:$E$28252,"*调拨*") -> 0 | V7: =SUMIFS(Sheet1!$F$5:$F$28252,Sheet1!$I$5:$I$28252,$B7,Sheet1!$L$5:$L$28252,$A7,Sheet1!$D$5:$D$28252,"储值",Sheet1!$E$5:$E$28252,"<>*调拨*")+SUMIFS(Sheet1!$F$5:$F$28252,Sheet1!$I$5:$I$28252,$B7,Sheet1!$L$5:$L$28252,$A7,Sheet1!$E$5:$E$28252,"*储值*",Sheet1!$D$5:$D$28252,"<>储值",Sheet1!$D$5:$D$28252,"<>内部转款",Sheet1!$D$5:$D$28252,"<>内部转账",Sheet1!$E$5:$E$28252,"<>*调拨*") -> 0 | W7: =SUMIFS(Sheet1!$F$5:$F$28252,Sheet1!$I$5:$I$28252,$B7,Sheet1!$L$5:$L$28252,$A7,Sheet1!$D$5:$D$28252,"效期",Sheet1!$E$5:$E$28252,"<>*调拨*")+SUMIFS(Sheet1!$F$5:$F$28252,Sheet1!$I$5:$I$28252,$B7,Sheet1!$L$5:$L$28252,$A7,Sheet1!$E$5:$E$28252,"*效期*",Sheet1!$D$5:$D$28252,"<>效期",Sheet1!$D$5:$D$28252,"<>内部转款",Sheet1!$D$5:$D$28252,"<>内部转账",Sheet1!$E$5:$E$28252,"<>*调拨*") -> 0 | X7: =SUMIFS(Sheet1!$F$5:$F$28252,Sheet1!$I$5:$I$28252,$B7,Sheet1!$L$5:$L$28252,$A7,Sheet1!$D$5:$D$28252,"内部转款",Sheet1!$E$5:$E$28252,"<>*调拨*")+SUMIFS(Sheet1!$F$5:$F$28252,Sheet1!$I$5:$I$28252,$B7,Sheet1!$L$5:$L$28252,$A7,Sheet1!$D$5:$D$28252,"内部转账",Sheet1!$E$5:$E$28252,"<>*调拨*") -> 0 | Y7: =Z7-SUM(C7:X7) -> 0 | Z7: =SUMIFS(Sheet1!$F$5:$F$28252,Sheet1!$I$5:$I$28252,$B7,Sheet1!$L$5:$L$28252,$A7) -> 0 | AA7: =SUMIFS(Sheet1!$G$5:$G$28252,Sheet1!$I$5:$I$28252,$B7,Sheet1!$L$5:$L$28252,$A7,Sheet1!$D$5:$D$28252,"工资",Sheet1!$E$5:$E$28252,"<>*调拨*")+SUMIFS(Sheet1!$G$5:$G$28252,Sheet1!$I$5:$I$28252,$B7,Sheet1!$L$5:$L$28252,$A7,Sheet1!$E$5:$E$28252,"*工资*",Sheet1!$E$5:$E$28252,"<>*调拨*",Sheet1!$D$5:$D$28252,"<>内部转款",Sheet1!$D$5:$D$28252,"<>内部转账",Sheet1!$D$5:$D$28252,"<>工资",Sheet1!$D$5:$D$28252,"<>水费",Sheet1!$D$5:$D$28252,"<>电费",Sheet1!$D$5:$D$28252,"<>宽带费",Sheet1!$D$5:$D$28252,"<>办公费",Sheet1!$D$5:$D$28252,"<>话费",Sheet1!$D$5:$D$28252,"<>房租") -> 0 | AB7: =SUMIFS(Sheet1!$G$5:$G$28252,Sheet1!$I$5:$I$28252,$B7,Sheet1!$L$5:$L$28252,$A7,Sheet1!$D$5:$D$28252,"水费",Sheet1!$E$5:$E$28252,"<>*调拨*")+SUMIFS(Sheet1!$G$5:$G$28252,Sheet1!$I$5:$I$28252,$B7,Sheet1!$L$5:$L$28252,$A7,Sheet1!$E$5:$E$28252,"*水费*",Sheet1!$E$5:$E$28252,"<>*调拨*",Sheet1!$D$5:$D$28252,"<>内部转款",Sheet1!$D$5:$D$28252,"<>内部转账",Sheet1!$D$5:$D$28252,"<>工资",Sheet1!$D$5:$D$28252,"<>水费",Sheet1!$D$5:$D$28252,"<>电费",Sheet1!$D$5:$D$28252,"<>宽带费",Sheet1!$D$5:$D$28252,"<>办公费",Sheet1!$D$5:$D$28252,"<>话费",Sheet1!$D$5:$D$28252,"<>房租",Sheet1!$E$5:$E$28252,"<>*工资*") -> 0 | AC7: =SUMIFS(Sheet1!$G$5:$G$28252,Sheet1!$I$5:$I$28252,$B7,Sheet1!$L$5:$L$28252,$A7,Sheet1!$D$5:$D$28252,"电费",Sheet1!$E$5:$E$28252,"<>*调拨*")+SUMIFS(Sheet1!$G$5:$G$28252,Sheet1!$I$5:$I$28252,$B7,Sheet1!$L$5:$L$28252,$A7,Sheet1!$E$5:$E$28252,"*电费*",Sheet1!$E$5:$E$28252,"<>*调拨*",Sheet1!$D$5:$D$28252,"<>内部转款",Sheet1!$D$5:$D$28252,"<>内部转账",Sheet1!$D$5:$D$28252,"<>工资",Sheet1!$D$5:$D$28252,"<>水费",Sheet1!$D$5:$D$28252,"<>电费",Sheet1!$D$5:$D$28252,"<>宽带费",Sheet1!$D$5:$D$28252,"<>办公费",Sheet1!$D$5:$D$28252,"<>话费",Sheet1!$D$5:$D$28252,"<>房租",Sheet1!$E$5:$E$28252,"<>*工资*",Sheet1!$E$5:$E$28252,"<>*水费*") -> 0 | AD7: =SUMIFS(Sheet1!$G$5:$G$28252,Sheet1!$I$5:$I$28252,$B7,Sheet1!$L$5:$L$28252,$A7,Sheet1!$D$5:$D$28252,"宽带费",Sheet1!$E$5:$E$28252,"<>*调拨*")+SUMIFS(Sheet1!$G$5:$G$28252,Sheet1!$I$5:$I$28252,$B7,Sheet1!$L$5:$L$28252,$A7,Sheet1!$E$5:$E$28252,"*宽带*",Sheet1!$E$5:$E$28252,"<>*调拨*",Sheet1!$D$5:$D$28252,"<>内部转款",Sheet1!$D$5:$D$28252,"<>内部转账",Sheet1!$D$5:$D$28252,"<>工资",Sheet1!$D$5:$D$28252,"<>水费",Sheet1!$D$5:$D$28252,"<>电费",Sheet1!$D$5:$D$28252,"<>宽带费",Sheet1!$D$5:$D$28252,"<>办公费",Sheet1!$D$5:$D$28252,"<>话费",Sheet1!$D$5:$D$28252,"<>房租",Sheet1!$E$5:$E$28252,"<>*工资*",Sheet1!$E$5:$E$28252,"<>*水费*",Sheet1!$E$5:$E$28252,"<>*电费*") -> 0 | AE7: =SUMIFS(Sheet1!$G$5:$G$28252,Sheet1!$I$5:$I$28252,$B7,Sheet1!$L$5:$L$28252,$A7,Sheet1!$D$5:$D$28252,"办公费",Sheet1!$E$5:$E$28252,"<>*调拨*")+SUMIFS(Sheet1!$G$5:$G$28252,Sheet1!$I$5:$I$28252,$B7,Sheet1!$L$5:$L$28252,$A7,Sheet1!$E$5:$E$28252,"*办公*",Sheet1!$E$5:$E$28252,"<>*调拨*",Sheet1!$D$5:$D$28252,"<>内部转款",Sheet1!$D$5:$D$28252,"<>内部转账",Sheet1!$D$5:$D$28252,"<>工资",Sheet1!$D$5:$D$28252,"<>水费",Sheet1!$D$5:$D$28252,"<>电费",Sheet1!$D$5:$D$28252,"<>宽带费",Sheet1!$D$5:$D$28252,"<>办公费",Sheet1!$D$5:$D$28252,"<>话费",Sheet1!$D$5:$D$28252,"<>房租",Sheet1!$E$5:$E$28252,"<>*工资*",Sheet1!$E$5:$E$28252,"<>*水费*",Sheet1!$E$5:$E$28252,"<>*电费*",Sheet1!$E$5:$E$28252,"<>*宽带*") -> 3930 | AF7: =SUMIFS(Sheet1!$G$5:$G$28252,Sheet1!$I$5:$I$28252,$B7,Sheet1!$L$5:$L$28252,$A7,Sheet1!$D$5:$D$28252,"话费",Sheet1!$E$5:$E$28252,"<>*调拨*")+SUMIFS(Sheet1!$G$5:$G$28252,Sheet1!$I$5:$I$28252,$B7,Sheet1!$L$5:$L$28252,$A7,Sheet1!$E$5:$E$28252,"*话费*",Sheet1!$E$5:$E$28252,"<>*调拨*",Sheet1!$D$5:$D$28252,"<>内部转款",Sheet1!$D$5:$D$28252,"<>内部转账",Sheet1!$D$5:$D$28252,"<>工资",Sheet1!$D$5:$D$28252,"<>水费",Sheet1!$D$5:$D$28252,"<>电费",Sheet1!$D$5:$D$28252,"<>宽带费",Sheet1!$D$5:$D$28252,"<>办公费",Sheet1!$D$5:$D$28252,"<>话费",Sheet1!$D$5:$D$28252,"<>房租",Sheet1!$E$5:$E$28252,"<>*工资*",Sheet1!$E$5:$E$28252,"<>*水费*",Sheet1!$E$5:$E$28252,"<>*电费*",Sheet1!$E$5:$E$28252,"<>*宽带*",Sheet1!$E$5:$E$28252,"<>*办公*") -> 0 | AG7: =SUMIFS(Sheet1!$G$5:$G$28252,Sheet1!$I$5:$I$28252,$B7,Sheet1!$L$5:$L$28252,$A7,Sheet1!$D$5:$D$28252,"房租",Sheet1!$E$5:$E$28252,"<>*调拨*")+SUMIFS(Sheet1!$G$5:$G$28252,Sheet1!$I$5:$I$28252,$B7,Sheet1!$L$5:$L$28252,$A7,Sheet1!$E$5:$E$28252,"*房租*",Sheet1!$E$5:$E$28252,"<>*调拨*",Sheet1!$D$5:$D$28252,"<>内部转款",Sheet1!$D$5:$D$28252,"<>内部转账",Sheet1!$D$5:$D$28252,"<>工资",Sheet1!$D$5:$D$28252,"<>水费",Sheet1!$D$5:$D$28252,"<>电费",Sheet1!$D$5:$D$28252,"<>宽带费",Sheet1!$D$5:$D$28252,"<>办公费",Sheet1!$D$5:$D$28252,"<>话费",Sheet1!$D$5:$D$28252,"<>房租",Sheet1!$E$5:$E$28252,"<>*工资*",Sheet1!$E$5:$E$28252,"<>*水费*",Sheet1!$E$5:$E$28252,"<>*电费*",Sheet1!$E$5:$E$28252,"<>*宽带*",Sheet1!$E$5:$E$28252,"<>*办公*",Sheet1!$E$5:$E$28252,"<>*话费*") -> 0 | AH7: =SUMIFS(Sheet1!$G$5:$G$28252,Sheet1!$I$5:$I$28252,$B7,Sheet1!$L$5:$L$28252,$A7,Sheet1!$E$5:$E$28252,"*调拨*") -> 0 | AI7: =SUMIFS(Sheet1!$G$5:$G$28252,Sheet1!$I$5:$I$28252,$B7,Sheet1!$L$5:$L$28252,$A7,Sheet1!$D$5:$D$28252,"内部转款",Sheet1!$E$5:$E$28252,"<>*调拨*")+SUMIFS(Sheet1!$G$5:$G$28252,Sheet1!$I$5:$I$28252,$B7,Sheet1!$L$5:$L$28252,$A7,Sheet1!$D$5:$D$28252,"内部转账",Sheet1!$E$5:$E$28252,"<>*调拨*") -> 0 | AJ7: =AK7-SUM(AA7:AI7) -> 0 | AK7: =SUMIFS(Sheet1!$G$5:$G$28252,Sheet1!$I$5:$I$28252,$B7,Sheet1!$L$5:$L$28252,$A7) -> 3930 | AL7: =Z7-AK7 -> -3930
A8: 202512 | B8: 临城县博营分店（44分店） | C8: =SUMIFS(Sheet1!$F$5:$F$28252,Sheet1!$I$5:$I$28252,$B8,Sheet1!$L$5:$L$28252,$A8,Sheet1!$D$5:$D$28252,"营业款",Sheet1!$E$5:$E$28252,"<>*调拨*",Sheet1!$E$5:$E$28252,"<>*回款*",Sheet1!$E$5:$E$28252,"<>*收款*",Sheet1!$E$5:$E$28252,"<>*医保*",Sheet1!$E$5:$E$28252,"<>*聚合*",Sheet1!$E$5:$E$28252,"<>*24小时微信*",Sheet1!$E$5:$E$28252,"<>*美团*",Sheet1!$E$5:$E$28252,"<>*饿了么*",Sheet1!$E$5:$E$28252,"<>*健E卡*",Sheet1!$E$5:$E$28252,"<>*抖音*",Sheet1!$E$5:$E$28252,"<>*医卡通*",Sheet1!$E$5:$E$28252,"<>*企健网*",Sheet1!$E$5:$E$28252,"<>*银联*",Sheet1!$E$5:$E$28252,"<>*京东*",Sheet1!$E$5:$E$28252,"<>*药机微信*",Sheet1!$E$5:$E$28252,"<>*亲情卡*",Sheet1!$E$5:$E$28252,"<>*优惠券*",Sheet1!$E$5:$E$28252,"<>*代金券*",Sheet1!$E$5:$E$28252,"<>*储值*",Sheet1!$E$5:$E$28252,"<>*效期*") -> 3498.1 | D8: =SUMIFS(Sheet1!$F$5:$F$28252,Sheet1!$I$5:$I$28252,$B8,Sheet1!$L$5:$L$28252,$A8,Sheet1!$D$5:$D$28252,"医保即时拨付",Sheet1!$E$5:$E$28252,"<>*调拨*")+SUMIFS(Sheet1!$F$5:$F$28252,Sheet1!$I$5:$I$28252,$B8,Sheet1!$L$5:$L$28252,$A8,Sheet1!$E$5:$E$28252,"*医保即时拨付*",Sheet1!$D$5:$D$28252,"<>医保即时拨付",Sheet1!$D$5:$D$28252,"<>内部转款",Sheet1!$D$5:$D$28252,"<>内部转账",Sheet1!$E$5:$E$28252,"<>*调拨*") -> 0 | E8: =SUMIFS(Sheet1!$F$5:$F$28252,Sheet1!$I$5:$I$28252,$B8,Sheet1!$L$5:$L$28252,$A8,Sheet1!$D$5:$D$28252,"医保",Sheet1!$E$5:$E$28252,"<>*调拨*",Sheet1!$E$5:$E$28252,"<>*医保即时拨付*")+SUMIFS(Sheet1!$F$5:$F$28252,Sheet1!$I$5:$I$28252,$B8,Sheet1!$L$5:$L$28252,$A8,Sheet1!$E$5:$E$28252,"*医保*",Sheet1!$D$5:$D$28252,"<>医保",Sheet1!$D$5:$D$28252,"<>医保即时拨付",Sheet1!$D$5:$D$28252,"<>内部转款",Sheet1!$D$5:$D$28252,"<>内部转账",Sheet1!$E$5:$E$28252,"<>*医保即时拨付*",Sheet1!$E$5:$E$28252,"<>*调拨*") -> 0 | F8: =SUMIFS(Sheet1!$F$5:$F$28252,Sheet1!$I$5:$I$28252,$B8,Sheet1!$L$5:$L$28252,$A8,Sheet1!$D$5:$D$28252,"聚合",Sheet1!$E$5:$E$28252,"<>*调拨*")+SUMIFS(Sheet1!$F$5:$F$28252,Sheet1!$I$5:$I$28252,$B8,Sheet1!$L$5:$L$28252,$A8,Sheet1!$E$5:$E$28252,"*聚合*",Sheet1!$D$5:$D$28252,"<>聚合",Sheet1!$D$5:$D$28252,"<>内部转款",Sheet1!$D$5:$D$28252,"<>内部转账",Sheet1!$E$5:$E$28252,"<>*调拨*") -> 0 | G8: =SUMIFS(Sheet1!$F$5:$F$28252,Sheet1!$I$5:$I$28252,$B8,Sheet1!$L$5:$L$28252,$A8,Sheet1!$D$5:$D$28252,"24小时微信",Sheet1!$E$5:$E$28252,"<>*调拨*")+SUMIFS(Sheet1!$F$5:$F$28252,Sheet1!$I$5:$I$28252,$B8,Sheet1!$L$5:$L$28252,$A8,Sheet1!$E$5:$E$28252,"*24小时微信*",Sheet1!$D$5:$D$28252,"<>24小时微信",Sheet1!$D$5:$D$28252,"<>内部转款",Sheet1!$D$5:$D$28252,"<>内部转账",Sheet1!$E$5:$E$28252,"<>*调拨*") -> 0 | H8: =SUMIFS(Sheet1!$F$5:$F$28252,Sheet1!$I$5:$I$28252,$B8,Sheet1!$L$5:$L$28252,$A8,Sheet1!$D$5:$D$28252,"美团",Sheet1!$E$5:$E$28252,"<>*调拨*")+SUMIFS(Sheet1!$F$5:$F$28252,Sheet1!$I$5:$I$28252,$B8,Sheet1!$L$5:$L$28252,$A8,Sheet1!$E$5:$E$28252,"*美团*",Sheet1!$D$5:$D$28252,"<>美团",Sheet1!$D$5:$D$28252,"<>内部转款",Sheet1!$D$5:$D$28252,"<>内部转账",Sheet1!$E$5:$E$28252,"<>*调拨*") -> 0 | I8: =SUMIFS(Sheet1!$F$5:$F$28252,Sheet1!$I$5:$I$28252,$B8,Sheet1!$L$5:$L$28252,$A8,Sheet1!$D$5:$D$28252,"饿了么",Sheet1!$E$5:$E$28252,"<>*调拨*")+SUMIFS(Sheet1!$F$5:$F$28252,Sheet1!$I$5:$I$28252,$B8,Sheet1!$L$5:$L$28252,$A8,Sheet1!$E$5:$E$28252,"*饿了么*",Sheet1!$D$5:$D$28252,"<>饿了么",Sheet1!$D$5:$D$28252,"<>内部转款",Sheet1!$D$5:$D$28252,"<>内部转账",Sheet1!$E$5:$E$28252,"<>*调拨*") -> 0 | J8: =SUMIFS(Sheet1!$F$5:$F$28252,Sheet1!$I$5:$I$28252,$B8,Sheet1!$L$5:$L$28252,$A8,Sheet1!$D$5:$D$28252,"健E卡",Sheet1!$E$5:$E$28252,"<>*调拨*")+SUMIFS(Sheet1!$F$5:$F$28252,Sheet1!$I$5:$I$28252,$B8,Sheet1!$L$5:$L$28252,$A8,Sheet1!$E$5:$E$28252,"*健E卡*",Sheet1!$D$5:$D$28252,"<>健E卡",Sheet1!$D$5:$D$28252,"<>内部转款",Sheet1!$D$5:$D$28252,"<>内部转账",Sheet1!$E$5:$E$28252,"<>*调拨*") -> 0 | K8: =SUMIFS(Sheet1!$F$5:$F$28252,Sheet1!$I$5:$I$28252,$B8,Sheet1!$L$5:$L$28252,$A8,Sheet1!$D$5:$D$28252,"抖音",Sheet1!$E$5:$E$28252,"<>*调拨*")+SUMIFS(Sheet1!$F$5:$F$28252,Sheet1!$I$5:$I$28252,$B8,Sheet1!$L$5:$L$28252,$A8,Sheet1!$E$5:$E$28252,"*抖音*",Sheet1!$D$5:$D$28252,"<>抖音",Sheet1!$D$5:$D$28252,"<>内部转款",Sheet1!$D$5:$D$28252,"<>内部转账",Sheet1!$E$5:$E$28252,"<>*调拨*") -> 0 | L8: =SUMIFS(Sheet1!$F$5:$F$28252,Sheet1!$I$5:$I$28252,$B8,Sheet1!$L$5:$L$28252,$A8,Sheet1!$D$5:$D$28252,"医卡通",Sheet1!$E$5:$E$28252,"<>*调拨*")+SUMIFS(Sheet1!$F$5:$F$28252,Sheet1!$I$5:$I$28252,$B8,Sheet1!$L$5:$L$28252,$A8,Sheet1!$E$5:$E$28252,"*医卡通*",Sheet1!$D$5:$D$28252,"<>医卡通",Sheet1!$D$5:$D$28252,"<>内部转款",Sheet1!$D$5:$D$28252,"<>内部转账",Sheet1!$E$5:$E$28252,"<>*调拨*") -> 0 | M8: =SUMIFS(Sheet1!$F$5:$F$28252,Sheet1!$I$5:$I$28252,$B8,Sheet1!$L$5:$L$28252,$A8,Sheet1!$D$5:$D$28252,"企健网",Sheet1!$E$5:$E$28252,"<>*调拨*")+SUMIFS(Sheet1!$F$5:$F$28252,Sheet1!$I$5:$I$28252,$B8,Sheet1!$L$5:$L$28252,$A8,Sheet1!$E$5:$E$28252,"*企健网*",Sheet1!$D$5:$D$28252,"<>企健网",Sheet1!$D$5:$D$28252,"<>内部转款",Sheet1!$D$5:$D$28252,"<>内部转账",Sheet1!$E$5:$E$28252,"<>*调拨*") -> 0 | N8: =SUMIFS(Sheet1!$F$5:$F$28252,Sheet1!$I$5:$I$28252,$B8,Sheet1!$L$5:$L$28252,$A8,Sheet1!$D$5:$D$28252,"银联",Sheet1!$E$5:$E$28252,"<>*调拨*")+SUMIFS(Sheet1!$F$5:$F$28252,Sheet1!$I$5:$I$28252,$B8,Sheet1!$L$5:$L$28252,$A8,Sheet1!$E$5:$E$28252,"*银联*",Sheet1!$D$5:$D$28252,"<>银联",Sheet1!$D$5:$D$28252,"<>内部转款",Sheet1!$D$5:$D$28252,"<>内部转账",Sheet1!$E$5:$E$28252,"<>*调拨*") -> 0 | O8: =SUMIFS(Sheet1!$F$5:$F$28252,Sheet1!$I$5:$I$28252,$B8,Sheet1!$L$5:$L$28252,$A8,Sheet1!$D$5:$D$28252,"京东",Sheet1!$E$5:$E$28252,"<>*调拨*")+SUMIFS(Sheet1!$F$5:$F$28252,Sheet1!$I$5:$I$28252,$B8,Sheet1!$L$5:$L$28252,$A8,Sheet1!$E$5:$E$28252,"*京东*",Sheet1!$D$5:$D$28252,"<>京东",Sheet1!$D$5:$D$28252,"<>内部转款",Sheet1!$D$5:$D$28252,"<>内部转账",Sheet1!$E$5:$E$28252,"<>*调拨*") -> 0 | P8: =SUMIFS(Sheet1!$F$5:$F$28252,Sheet1!$I$5:$I$28252,$B8,Sheet1!$L$5:$L$28252,$A8,Sheet1!$D$5:$D$28252,"药机微信",Sheet1!$E$5:$E$28252,"<>*调拨*")+SUMIFS(Sheet1!$F$5:$F$28252,Sheet1!$I$5:$I$28252,$B8,Sheet1!$L$5:$L$28252,$A8,Sheet1!$E$5:$E$28252,"*药机微信*",Sheet1!$D$5:$D$28252,"<>药机微信",Sheet1!$D$5:$D$28252,"<>内部转款",Sheet1!$D$5:$D$28252,"<>内部转账",Sheet1!$E$5:$E$28252,"<>*调拨*") -> 0 | Q8: =SUMIFS(Sheet1!$F$5:$F$28252,Sheet1!$I$5:$I$28252,$B8,Sheet1!$L$5:$L$28252,$A8,Sheet1!$D$5:$D$28252,"亲情卡",Sheet1!$E$5:$E$28252,"<>*调拨*")+SUMIFS(Sheet1!$F$5:$F$28252,Sheet1!$I$5:$I$28252,$B8,Sheet1!$L$5:$L$28252,$A8,Sheet1!$E$5:$E$28252,"*亲情卡*",Sheet1!$D$5:$D$28252,"<>亲情卡",Sheet1!$D$5:$D$28252,"<>内部转款",Sheet1!$D$5:$D$28252,"<>内部转账",Sheet1!$E$5:$E$28252,"<>*调拨*") -> 0 | R8: =SUMIFS(Sheet1!$F$5:$F$28252,Sheet1!$I$5:$I$28252,$B8,Sheet1!$L$5:$L$28252,$A8,Sheet1!$D$5:$D$28252,"优惠券",Sheet1!$E$5:$E$28252,"<>*调拨*")+SUMIFS(Sheet1!$F$5:$F$28252,Sheet1!$I$5:$I$28252,$B8,Sheet1!$L$5:$L$28252,$A8,Sheet1!$E$5:$E$28252,"*优惠券*",Sheet1!$D$5:$D$28252,"<>优惠券",Sheet1!$D$5:$D$28252,"<>内部转款",Sheet1!$D$5:$D$28252,"<>内部转账",Sheet1!$E$5:$E$28252,"<>*调拨*") -> 0 | S8: =SUMIFS(Sheet1!$F$5:$F$28252,Sheet1!$I$5:$I$28252,$B8,Sheet1!$L$5:$L$28252,$A8,Sheet1!$D$5:$D$28252,"代金券",Sheet1!$E$5:$E$28252,"<>*调拨*")+SUMIFS(Sheet1!$F$5:$F$28252,Sheet1!$I$5:$I$28252,$B8,Sheet1!$L$5:$L$28252,$A8,Sheet1!$E$5:$E$28252,"*代金券*",Sheet1!$D$5:$D$28252,"<>代金券",Sheet1!$D$5:$D$28252,"<>内部转款",Sheet1!$D$5:$D$28252,"<>内部转账",Sheet1!$E$5:$E$28252,"<>*调拨*") -> 0 | T8: =SUMIFS(Sheet1!$F$5:$F$28252,Sheet1!$I$5:$I$28252,$B8,Sheet1!$L$5:$L$28252,$A8,Sheet1!$D$5:$D$28252,"回款",Sheet1!$E$5:$E$28252,"<>*调拨*",Sheet1!$E$5:$E$28252,"<>*医保*",Sheet1!$E$5:$E$28252,"<>*聚合*",Sheet1!$E$5:$E$28252,"<>*24小时微信*",Sheet1!$E$5:$E$28252,"<>*美团*",Sheet1!$E$5:$E$28252,"<>*饿了么*",Sheet1!$E$5:$E$28252,"<>*健E卡*",Sheet1!$E$5:$E$28252,"<>*抖音*",Sheet1!$E$5:$E$28252,"<>*医卡通*",Sheet1!$E$5:$E$28252,"<>*企健网*",Sheet1!$E$5:$E$28252,"<>*银联*",Sheet1!$E$5:$E$28252,"<>*京东*",Sheet1!$E$5:$E$28252,"<>*药机微信*",Sheet1!$E$5:$E$28252,"<>*亲情卡*",Sheet1!$E$5:$E$28252,"<>*优惠券*",Sheet1!$E$5:$E$28252,"<>*代金券*",Sheet1!$E$5:$E$28252,"<>*储值*",Sheet1!$E$5:$E$28252,"<>*效期*")+SUMIFS(Sheet1!$F$5:$F$28252,Sheet1!$I$5:$I$28252,$B8,Sheet1!$L$5:$L$28252,$A8,Sheet1!$D$5:$D$28252,"收款",Sheet1!$E$5:$E$28252,"<>*调拨*",Sheet1!$E$5:$E$28252,"<>*医保*",Sheet1!$E$5:$E$28252,"<>*聚合*",Sheet1!$E$5:$E$28252,"<>*24小时微信*",Sheet1!$E$5:$E$28252,"<>*美团*",Sheet1!$E$5:$E$28252,"<>*饿了么*",Sheet1!$E$5:$E$28252,"<>*健E卡*",Sheet1!$E$5:$E$28252,"<>*抖音*",Sheet1!$E$5:$E$28252,"<>*医卡通*",Sheet1!$E$5:$E$28252,"<>*企健网*",Sheet1!$E$5:$E$28252,"<>*银联*",Sheet1!$E$5:$E$28252,"<>*京东*",Sheet1!$E$5:$E$28252,"<>*药机微信*",Sheet1!$E$5:$E$28252,"<>*亲情卡*",Sheet1!$E$5:$E$28252,"<>*优惠券*",Sheet1!$E$5:$E$28252,"<>*代金券*",Sheet1!$E$5:$E$28252,"<>*储值*",Sheet1!$E$5:$E$28252,"<>*效期*")+SUMIFS(Sheet1!$F$5:$F$28252,Sheet1!$I$5:$I$28252,$B8,Sheet1!$L$5:$L$28252,$A8,Sheet1!$E$5:$E$28252,"*回款*",Sheet1!$D$5:$D$28252,"<>回款",Sheet1!$D$5:$D$28252,"<>收款",Sheet1!$D$5:$D$28252,"<>内部转款",Sheet1!$D$5:$D$28252,"<>内部转账",Sheet1!$E$5:$E$28252,"<>*调拨*",Sheet1!$E$5:$E$28252,"<>*医保*",Sheet1!$E$5:$E$28252,"<>*聚合*",Sheet1!$E$5:$E$28252,"<>*24小时微信*",Sheet1!$E$5:$E$28252,"<>*美团*",Sheet1!$E$5:$E$28252,"<>*饿了么*",Sheet1!$E$5:$E$28252,"<>*健E卡*",Sheet1!$E$5:$E$28252,"<>*抖音*",Sheet1!$E$5:$E$28252,"<>*医卡通*",Sheet1!$E$5:$E$28252,"<>*企健网*",Sheet1!$E$5:$E$28252,"<>*银联*",Sheet1!$E$5:$E$28252,"<>*京东*",Sheet1!$E$5:$E$28252,"<>*药机微信*",Sheet1!$E$5:$E$28252,"<>*亲情卡*",Sheet1!$E$5:$E$28252,"<>*优惠券*",Sheet1!$E$5:$E$28252,"<>*代金券*",Sheet1!$E$5:$E$28252,"<>*储值*",Sheet1!$E$5:$E$28252,"<>*效期*")+SUMIFS(Sheet1!$F$5:$F$28252,Sheet1!$I$5:$I$28252,$B8,Sheet1!$L$5:$L$28252,$A8,Sheet1!$E$5:$E$28252,"*收款*",Sheet1!$E$5:$E$28252,"<>*回款*",Sheet1!$D$5:$D$28252,"<>回款",Sheet1!$D$5:$D$28252,"<>收款",Sheet1!$D$5:$D$28252,"<>内部转款",Sheet1!$D$5:$D$28252,"<>内部转账",Sheet1!$E$5:$E$28252,"<>*调拨*",Sheet1!$E$5:$E$28252,"<>*医保*",Sheet1!$E$5:$E$28252,"<>*聚合*",Sheet1!$E$5:$E$28252,"<>*24小时微信*",Sheet1!$E$5:$E$28252,"<>*美团*",Sheet1!$E$5:$E$28252,"<>*饿了么*",Sheet1!$E$5:$E$28252,"<>*健E卡*",Sheet1!$E$5:$E$28252,"<>*抖音*",Sheet1!$E$5:$E$28252,"<>*医卡通*",Sheet1!$E$5:$E$28252,"<>*企健网*",Sheet1!$E$5:$E$28252,"<>*银联*",Sheet1!$E$5:$E$28252,"<>*京东*",Sheet1!$E$5:$E$28252,"<>*药机微信*",Sheet1!$E$5:$E$28252,"<>*亲情卡*",Sheet1!$E$5:$E$28252,"<>*优惠券*",Sheet1!$E$5:$E$28252,"<>*代金券*",Sheet1!$E$5:$E$28252,"<>*储值*",Sheet1!$E$5:$E$28252,"<>*效期*") -> 0 | U8: =SUMIFS(Sheet1!$F$5:$F$28252,Sheet1!$I$5:$I$28252,$B8,Sheet1!$L$5:$L$28252,$A8,Sheet1!$E$5:$E$28252,"*调拨*") -> 0 | V8: =SUMIFS(Sheet1!$F$5:$F$28252,Sheet1!$I$5:$I$28252,$B8,Sheet1!$L$5:$L$28252,$A8,Sheet1!$D$5:$D$28252,"储值",Sheet1!$E$5:$E$28252,"<>*调拨*")+SUMIFS(Sheet1!$F$5:$F$28252,Sheet1!$I$5:$I$28252,$B8,Sheet1!$L$5:$L$28252,$A8,Sheet1!$E$5:$E$28252,"*储值*",Sheet1!$D$5:$D$28252,"<>储值",Sheet1!$D$5:$D$28252,"<>内部转款",Sheet1!$D$5:$D$28252,"<>内部转账",Sheet1!$E$5:$E$28252,"<>*调拨*") -> 0 | W8: =SUMIFS(Sheet1!$F$5:$F$28252,Sheet1!$I$5:$I$28252,$B8,Sheet1!$L$5:$L$28252,$A8,Sheet1!$D$5:$D$28252,"效期",Sheet1!$E$5:$E$28252,"<>*调拨*")+SUMIFS(Sheet1!$F$5:$F$28252,Sheet1!$I$5:$I$28252,$B8,Sheet1!$L$5:$L$28252,$A8,Sheet1!$E$5:$E$28252,"*效期*",Sheet1!$D$5:$D$28252,"<>效期",Sheet1!$D$5:$D$28252,"<>内部转款",Sheet1!$D$5:$D$28252,"<>内部转账",Sheet1!$E$5:$E$28252,"<>*调拨*") -> 0 | X8: =SUMIFS(Sheet1!$F$5:$F$28252,Sheet1!$I$5:$I$28252,$B8,Sheet1!$L$5:$L$28252,$A8,Sheet1!$D$5:$D$28252,"内部转款",Sheet1!$E$5:$E$28252,"<>*调拨*")+SUMIFS(Sheet1!$F$5:$F$28252,Sheet1!$I$5:$I$28252,$B8,Sheet1!$L$5:$L$28252,$A8,Sheet1!$D$5:$D$28252,"内部转账",Sheet1!$E$5:$E$28252,"<>*调拨*") -> 0 | Y8: =Z8-SUM(C8:X8) -> 0 | Z8: =SUMIFS(Sheet1!$F$5:$F$28252,Sheet1!$I$5:$I$28252,$B8,Sheet1!$L$5:$L$28252,$A8) -> 3498.1 | AA8: =SUMIFS(Sheet1!$G$5:$G$28252,Sheet1!$I$5:$I$28252,$B8,Sheet1!$L$5:$L$28252,$A8,Sheet1!$D$5:$D$28252,"工资",Sheet1!$E$5:$E$28252,"<>*调拨*")+SUMIFS(Sheet1!$G$5:$G$28252,Sheet1!$I$5:$I$28252,$B8,Sheet1!$L$5:$L$28252,$A8,Sheet1!$E$5:$E$28252,"*工资*",Sheet1!$E$5:$E$28252,"<>*调拨*",Sheet1!$D$5:$D$28252,"<>内部转款",Sheet1!$D$5:$D$28252,"<>内部转账",Sheet1!$D$5:$D$28252,"<>工资",Sheet1!$D$5:$D$28252,"<>水费",Sheet1!$D$5:$D$28252,"<>电费",Sheet1!$D$5:$D$28252,"<>宽带费",Sheet1!$D$5:$D$28252,"<>办公费",Sheet1!$D$5:$D$28252,"<>话费",Sheet1!$D$5:$D$28252,"<>房租") -> 0 | AB8: =SUMIFS(Sheet1!$G$5:$G$28252,Sheet1!$I$5:$I$28252,$B8,Sheet1!$L$5:$L$28252,$A8,Sheet1!$D$5:$D$28252,"水费",Sheet1!$E$5:$E$28252,"<>*调拨*")+SUMIFS(Sheet1!$G$5:$G$28252,Sheet1!$I$5:$I$28252,$B8,Sheet1!$L$5:$L$28252,$A8,Sheet1!$E$5:$E$28252,"*水费*",Sheet1!$E$5:$E$28252,"<>*调拨*",Sheet1!$D$5:$D$28252,"<>内部转款",Sheet1!$D$5:$D$28252,"<>内部转账",Sheet1!$D$5:$D$28252,"<>工资",Sheet1!$D$5:$D$28252,"<>水费",Sheet1!$D$5:$D$28252,"<>电费",Sheet1!$D$5:$D$28252,"<>宽带费",Sheet1!$D$5:$D$28252,"<>办公费",Sheet1!$D$5:$D$28252,"<>话费",Sheet1!$D$5:$D$28252,"<>房租",Sheet1!$E$5:$E$28252,"<>*工资*") -> 0 | AC8: =SUMIFS(Sheet1!$G$5:$G$28252,Sheet1!$I$5:$I$28252,$B8,Sheet1!$L$5:$L$28252,$A8,Sheet1!$D$5:$D$28252,"电费",Sheet1!$E$5:$E$28252,"<>*调拨*")+SUMIFS(Sheet1!$G$5:$G$28252,Sheet1!$I$5:$I$28252,$B8,Sheet1!$L$5:$L$28252,$A8,Sheet1!$E$5:$E$28252,"*电费*",Sheet1!$E$5:$E$28252,"<>*调拨*",Sheet1!$D$5:$D$28252,"<>内部转款",Sheet1!$D$5:$D$28252,"<>内部转账",Sheet1!$D$5:$D$28252,"<>工资",Sheet1!$D$5:$D$28252,"<>水费",Sheet1!$D$5:$D$28252,"<>电费",Sheet1!$D$5:$D$28252,"<>宽带费",Sheet1!$D$5:$D$28252,"<>办公费",Sheet1!$D$5:$D$28252,"<>话费",Sheet1!$D$5:$D$28252,"<>房租",Sheet1!$E$5:$E$28252,"<>*工资*",Sheet1!$E$5:$E$28252,"<>*水费*") -> 0 | AD8: =SUMIFS(Sheet1!$G$5:$G$28252,Sheet1!$I$5:$I$28252,$B8,Sheet1!$L$5:$L$28252,$A8,Sheet1!$D$5:$D$28252,"宽带费",Sheet1!$E$5:$E$28252,"<>*调拨*")+SUMIFS(Sheet1!$G$5:$G$28252,Sheet1!$I$5:$I$28252,$B8,Sheet1!$L$5:$L$28252,$A8,Sheet1!$E$5:$E$28252,"*宽带*",Sheet1!$E$5:$E$28252,"<>*调拨*",Sheet1!$D$5:$D$28252,"<>内部转款",Sheet1!$D$5:$D$28252,"<>内部转账",Sheet1!$D$5:$D$28252,"<>工资",Sheet1!$D$5:$D$28252,"<>水费",Sheet1!$D$5:$D$28252,"<>电费",Sheet1!$D$5:$D$28252,"<>宽带费",Sheet1!$D$5:$D$28252,"<>办公费",Sheet1!$D$5:$D$28252,"<>话费",Sheet1!$D$5:$D$28252,"<>房租",Sheet1!$E$5:$E$28252,"<>*工资*",Sheet1!$E$5:$E$28252,"<>*水费*",Sheet1!$E$5:$E$28252,"<>*电费*") -> 0 | AE8: =SUMIFS(Sheet1!$G$5:$G$28252,Sheet1!$I$5:$I$28252,$B8,Sheet1!$L$5:$L$28252,$A8,Sheet1!$D$5:$D$28252,"办公费",Sheet1!$E$5:$E$28252,"<>*调拨*")+SUMIFS(Sheet1!$G$5:$G$28252,Sheet1!$I$5:$I$28252,$B8,Sheet1!$L$5:$L$28252,$A8,Sheet1!$E$5:$E$28252,"*办公*",Sheet1!$E$5:$E$28252,"<>*调拨*",Sheet1!$D$5:$D$28252,"<>内部转款",Sheet1!$D$5:$D$28252,"<>内部转账",Sheet1!$D$5:$D$28252,"<>工资",Sheet1!$D$5:$D$28252,"<>水费",Sheet1!$D$5:$D$28252,"<>电费",Sheet1!$D$5:$D$28252,"<>宽带费",Sheet1!$D$5:$D$28252,"<>办公费",Sheet1!$D$5:$D$28252,"<>话费",Sheet1!$D$5:$D$28252,"<>房租",Sheet1!$E$5:$E$28252,"<>*工资*",Sheet1!$E$5:$E$28252,"<>*水费*",Sheet1!$E$5:$E$28252,"<>*电费*",Sheet1!$E$5:$E$28252,"<>*宽带*") -> 0 | AF8: =SUMIFS(Sheet1!$G$5:$G$28252,Sheet1!$I$5:$I$28252,$B8,Sheet1!$L$5:$L$28252,$A8,Sheet1!$D$5:$D$28252,"话费",Sheet1!$E$5:$E$28252,"<>*调拨*")+SUMIFS(Sheet1!$G$5:$G$28252,Sheet1!$I$5:$I$28252,$B8,Sheet1!$L$5:$L$28252,$A8,Sheet1!$E$5:$E$28252,"*话费*",Sheet1!$E$5:$E$28252,"<>*调拨*",Sheet1!$D$5:$D$28252,"<>内部转款",Sheet1!$D$5:$D$28252,"<>内部转账",Sheet1!$D$5:$D$28252,"<>工资",Sheet1!$D$5:$D$28252,"<>水费",Sheet1!$D$5:$D$28252,"<>电费",Sheet1!$D$5:$D$28252,"<>宽带费",Sheet1!$D$5:$D$28252,"<>办公费",Sheet1!$D$5:$D$28252,"<>话费",Sheet1!$D$5:$D$28252,"<>房租",Sheet1!$E$5:$E$28252,"<>*工资*",Sheet1!$E$5:$E$28252,"<>*水费*",Sheet1!$E$5:$E$28252,"<>*电费*",Sheet1!$E$5:$E$28252,"<>*宽带*",Sheet1!$E$5:$E$28252,"<>*办公*") -> 0 | AG8: =SUMIFS(Sheet1!$G$5:$G$28252,Sheet1!$I$5:$I$28252,$B8,Sheet1!$L$5:$L$28252,$A8,Sheet1!$D$5:$D$28252,"房租",Sheet1!$E$5:$E$28252,"<>*调拨*")+SUMIFS(Sheet1!$G$5:$G$28252,Sheet1!$I$5:$I$28252,$B8,Sheet1!$L$5:$L$28252,$A8,Sheet1!$E$5:$E$28252,"*房租*",Sheet1!$E$5:$E$28252,"<>*调拨*",Sheet1!$D$5:$D$28252,"<>内部转款",Sheet1!$D$5:$D$28252,"<>内部转账",Sheet1!$D$5:$D$28252,"<>工资",Sheet1!$D$5:$D$28252,"<>水费",Sheet1!$D$5:$D$28252,"<>电费",Sheet1!$D$5:$D$28252,"<>宽带费",Sheet1!$D$5:$D$28252,"<>办公费",Sheet1!$D$5:$D$28252,"<>话费",Sheet1!$D$5:$D$28252,"<>房租",Sheet1!$E$5:$E$28252,"<>*工资*",Sheet1!$E$5:$E$28252,"<>*水费*",Sheet1!$E$5:$E$28252,"<>*电费*",Sheet1!$E$5:$E$28252,"<>*宽带*",Sheet1!$E$5:$E$28252,"<>*办公*",Sheet1!$E$5:$E$28252,"<>*话费*") -> 0 | AH8: =SUMIFS(Sheet1!$G$5:$G$28252,Sheet1!$I$5:$I$28252,$B8,Sheet1!$L$5:$L$28252,$A8,Sheet1!$E$5:$E$28252,"*调拨*") -> 0 | AI8: =SUMIFS(Sheet1!$G$5:$G$28252,Sheet1!$I$5:$I$28252,$B8,Sheet1!$L$5:$L$28252,$A8,Sheet1!$D$5:$D$28252,"内部转款",Sheet1!$E$5:$E$28252,"<>*调拨*")+SUMIFS(Sheet1!$G$5:$G$28252,Sheet1!$I$5:$I$28252,$B8,Sheet1!$L$5:$L$28252,$A8,Sheet1!$D$5:$D$28252,"内部转账",Sheet1!$E$5:$E$28252,"<>*调拨*") -> 0 | AJ8: =AK8-SUM(AA8:AI8) -> 0 | AK8: =SUMIFS(Sheet1!$G$5:$G$28252,Sheet1!$I$5:$I$28252,$B8,Sheet1!$L$5:$L$28252,$A8) -> 0 | AL8: =Z8-AK8 -> 3498.1
A9: 202512 | B9: 北楼分店（22分店） | C9: =SUMIFS(Sheet1!$F$5:$F$28252,Sheet1!$I$5:$I$28252,$B9,Sheet1!$L$5:$L$28252,$A9,Sheet1!$D$5:$D$28252,"营业款",Sheet1!$E$5:$E$28252,"<>*调拨*",Sheet1!$E$5:$E$28252,"<>*回款*",Sheet1!$E$5:$E$28252,"<>*收款*",Sheet1!$E$5:$E$28252,"<>*医保*",Sheet1!$E$5:$E$28252,"<>*聚合*",Sheet1!$E$5:$E$28252,"<>*24小时微信*",Sheet1!$E$5:$E$28252,"<>*美团*",Sheet1!$E$5:$E$28252,"<>*饿了么*",Sheet1!$E$5:$E$28252,"<>*健E卡*",Sheet1!$E$5:$E$28252,"<>*抖音*",Sheet1!$E$5:$E$28252,"<>*医卡通*",Sheet1!$E$5:$E$28252,"<>*企健网*",Sheet1!$E$5:$E$28252,"<>*银联*",Sheet1!$E$5:$E$28252,"<>*京东*",Sheet1!$E$5:$E$28252,"<>*药机微信*",Sheet1!$E$5:$E$28252,"<>*亲情卡*",Sheet1!$E$5:$E$28252,"<>*优惠券*",Sheet1!$E$5:$E$28252,"<>*代金券*",Sheet1!$E$5:$E$28252,"<>*储值*",Sheet1!$E$5:$E$28252,"<>*效期*") -> 0 | D9: =SUMIFS(Sheet1!$F$5:$F$28252,Sheet1!$I$5:$I$28252,$B9,Sheet1!$L$5:$L$28252,$A9,Sheet1!$D$5:$D$28252,"医保即时拨付",Sheet1!$E$5:$E$28252,"<>*调拨*")+SUMIFS(Sheet1!$F$5:$F$28252,Sheet1!$I$5:$I$28252,$B9,Sheet1!$L$5:$L$28252,$A9,Sheet1!$E$5:$E$28252,"*医保即时拨付*",Sheet1!$D$5:$D$28252,"<>医保即时拨付",Sheet1!$D$5:$D$28252,"<>内部转款",Sheet1!$D$5:$D$28252,"<>内部转账",Sheet1!$E$5:$E$28252,"<>*调拨*") -> 0 | E9: =SUMIFS(Sheet1!$F$5:$F$28252,Sheet1!$I$5:$I$28252,$B9,Sheet1!$L$5:$L$28252,$A9,Sheet1!$D$5:$D$28252,"医保",Sheet1!$E$5:$E$28252,"<>*调拨*",Sheet1!$E$5:$E$28252,"<>*医保即时拨付*")+SUMIFS(Sheet1!$F$5:$F$28252,Sheet1!$I$5:$I$28252,$B9,Sheet1!$L$5:$L$28252,$A9,Sheet1!$E$5:$E$28252,"*医保*",Sheet1!$D$5:$D$28252,"<>医保",Sheet1!$D$5:$D$28252,"<>医保即时拨付",Sheet1!$D$5:$D$28252,"<>内部转款",Sheet1!$D$5:$D$28252,"<>内部转账",Sheet1!$E$5:$E$28252,"<>*医保即时拨付*",Sheet1!$E$5:$E$28252,"<>*调拨*") -> 0 | F9: =SUMIFS(Sheet1!$F$5:$F$28252,Sheet1!$I$5:$I$28252,$B9,Sheet1!$L$5:$L$28252,$A9,Sheet1!$D$5:$D$28252,"聚合",Sheet1!$E$5:$E$28252,"<>*调拨*")+SUMIFS(Sheet1!$F$5:$F$28252,Sheet1!$I$5:$I$28252,$B9,Sheet1!$L$5:$L$28252,$A9,Sheet1!$E$5:$E$28252,"*聚合*",Sheet1!$D$5:$D$28252,"<>聚合",Sheet1!$D$5:$D$28252,"<>内部转款",Sheet1!$D$5:$D$28252,"<>内部转账",Sheet1!$E$5:$E$28252,"<>*调拨*") -> 0 | G9: =SUMIFS(Sheet1!$F$5:$F$28252,Sheet1!$I$5:$I$28252,$B9,Sheet1!$L$5:$L$28252,$A9,Sheet1!$D$5:$D$28252,"24小时微信",Sheet1!$E$5:$E$28252,"<>*调拨*")+SUMIFS(Sheet1!$F$5:$F$28252,Sheet1!$I$5:$I$28252,$B9,Sheet1!$L$5:$L$28252,$A9,Sheet1!$E$5:$E$28252,"*24小时微信*",Sheet1!$D$5:$D$28252,"<>24小时微信",Sheet1!$D$5:$D$28252,"<>内部转款",Sheet1!$D$5:$D$28252,"<>内部转账",Sheet1!$E$5:$E$28252,"<>*调拨*") -> 0 | H9: =SUMIFS(Sheet1!$F$5:$F$28252,Sheet1!$I$5:$I$28252,$B9,Sheet1!$L$5:$L$28252,$A9,Sheet1!$D$5:$D$28252,"美团",Sheet1!$E$5:$E$28252,"<>*调拨*")+SUMIFS(Sheet1!$F$5:$F$28252,Sheet1!$I$5:$I$28252,$B9,Sheet1!$L$5:$L$28252,$A9,Sheet1!$E$5:$E$28252,"*美团*",Sheet1!$D$5:$D$28252,"<>美团",Sheet1!$D$5:$D$28252,"<>内部转款",Sheet1!$D$5:$D$28252,"<>内部转账",Sheet1!$E$5:$E$28252,"<>*调拨*") -> 0 | I9: =SUMIFS(Sheet1!$F$5:$F$28252,Sheet1!$I$5:$I$28252,$B9,Sheet1!$L$5:$L$28252,$A9,Sheet1!$D$5:$D$28252,"饿了么",Sheet1!$E$5:$E$28252,"<>*调拨*")+SUMIFS(Sheet1!$F$5:$F$28252,Sheet1!$I$5:$I$28252,$B9,Sheet1!$L$5:$L$28252,$A9,Sheet1!$E$5:$E$28252,"*饿了么*",Sheet1!$D$5:$D$28252,"<>饿了么",Sheet1!$D$5:$D$28252,"<>内部转款",Sheet1!$D$5:$D$28252,"<>内部转账",Sheet1!$E$5:$E$28252,"<>*调拨*") -> 0 | J9: =SUMIFS(Sheet1!$F$5:$F$28252,Sheet1!$I$5:$I$28252,$B9,Sheet1!$L$5:$L$28252,$A9,Sheet1!$D$5:$D$28252,"健E卡",Sheet1!$E$5:$E$28252,"<>*调拨*")+SUMIFS(Sheet1!$F$5:$F$28252,Sheet1!$I$5:$I$28252,$B9,Sheet1!$L$5:$L$28252,$A9,Sheet1!$E$5:$E$28252,"*健E卡*",Sheet1!$D$5:$D$28252,"<>健E卡",Sheet1!$D$5:$D$28252,"<>内部转款",Sheet1!$D$5:$D$28252,"<>内部转账",Sheet1!$E$5:$E$28252,"<>*调拨*") -> 0 | K9: =SUMIFS(Sheet1!$F$5:$F$28252,Sheet1!$I$5:$I$28252,$B9,Sheet1!$L$5:$L$28252,$A9,Sheet1!$D$5:$D$28252,"抖音",Sheet1!$E$5:$E$28252,"<>*调拨*")+SUMIFS(Sheet1!$F$5:$F$28252,Sheet1!$I$5:$I$28252,$B9,Sheet1!$L$5:$L$28252,$A9,Sheet1!$E$5:$E$28252,"*抖音*",Sheet1!$D$5:$D$28252,"<>抖音",Sheet1!$D$5:$D$28252,"<>内部转款",Sheet1!$D$5:$D$28252,"<>内部转账",Sheet1!$E$5:$E$28252,"<>*调拨*") -> 0 | L9: =SUMIFS(Sheet1!$F$5:$F$28252,Sheet1!$I$5:$I$28252,$B9,Sheet1!$L$5:$L$28252,$A9,Sheet1!$D$5:$D$28252,"医卡通",Sheet1!$E$5:$E$28252,"<>*调拨*")+SUMIFS(Sheet1!$F$5:$F$28252,Sheet1!$I$5:$I$28252,$B9,Sheet1!$L$5:$L$28252,$A9,Sheet1!$E$5:$E$28252,"*医卡通*",Sheet1!$D$5:$D$28252,"<>医卡通",Sheet1!$D$5:$D$28252,"<>内部转款",Sheet1!$D$5:$D$28252,"<>内部转账",Sheet1!$E$5:$E$28252,"<>*调拨*") -> 0 | M9: =SUMIFS(Sheet1!$F$5:$F$28252,Sheet1!$I$5:$I$28252,$B9,Sheet1!$L$5:$L$28252,$A9,Sheet1!$D$5:$D$28252,"企健网",Sheet1!$E$5:$E$28252,"<>*调拨*")+SUMIFS(Sheet1!$F$5:$F$28252,Sheet1!$I$5:$I$28252,$B9,Sheet1!$L$5:$L$28252,$A9,Sheet1!$E$5:$E$28252,"*企健网*",Sheet1!$D$5:$D$28252,"<>企健网",Sheet1!$D$5:$D$28252,"<>内部转款",Sheet1!$D$5:$D$28252,"<>内部转账",Sheet1!$E$5:$E$28252,"<>*调拨*") -> 0 | N9: =SUMIFS(Sheet1!$F$5:$F$28252,Sheet1!$I$5:$I$28252,$B9,Sheet1!$L$5:$L$28252,$A9,Sheet1!$D$5:$D$28252,"银联",Sheet1!$E$5:$E$28252,"<>*调拨*")+SUMIFS(Sheet1!$F$5:$F$28252,Sheet1!$I$5:$I$28252,$B9,Sheet1!$L$5:$L$28252,$A9,Sheet1!$E$5:$E$28252,"*银联*",Sheet1!$D$5:$D$28252,"<>银联",Sheet1!$D$5:$D$28252,"<>内部转款",Sheet1!$D$5:$D$28252,"<>内部转账",Sheet1!$E$5:$E$28252,"<>*调拨*") -> 0 | O9: =SUMIFS(Sheet1!$F$5:$F$28252,Sheet1!$I$5:$I$28252,$B9,Sheet1!$L$5:$L$28252,$A9,Sheet1!$D$5:$D$28252,"京东",Sheet1!$E$5:$E$28252,"<>*调拨*")+SUMIFS(Sheet1!$F$5:$F$28252,Sheet1!$I$5:$I$28252,$B9,Sheet1!$L$5:$L$28252,$A9,Sheet1!$E$5:$E$28252,"*京东*",Sheet1!$D$5:$D$28252,"<>京东",Sheet1!$D$5:$D$28252,"<>内部转款",Sheet1!$D$5:$D$28252,"<>内部转账",Sheet1!$E$5:$E$28252,"<>*调拨*") -> 0 | P9: =SUMIFS(Sheet1!$F$5:$F$28252,Sheet1!$I$5:$I$28252,$B9,Sheet1!$L$5:$L$28252,$A9,Sheet1!$D$5:$D$28252,"药机微信",Sheet1!$E$5:$E$28252,"<>*调拨*")+SUMIFS(Sheet1!$F$5:$F$28252,Sheet1!$I$5:$I$28252,$B9,Sheet1!$L$5:$L$28252,$A9,Sheet1!$E$5:$E$28252,"*药机微信*",Sheet1!$D$5:$D$28252,"<>药机微信",Sheet1!$D$5:$D$28252,"<>内部转款",Sheet1!$D$5:$D$28252,"<>内部转账",Sheet1!$E$5:$E$28252,"<>*调拨*") -> 0 | Q9: =SUMIFS(Sheet1!$F$5:$F$28252,Sheet1!$I$5:$I$28252,$B9,Sheet1!$L$5:$L$28252,$A9,Sheet1!$D$5:$D$28252,"亲情卡",Sheet1!$E$5:$E$28252,"<>*调拨*")+SUMIFS(Sheet1!$F$5:$F$28252,Sheet1!$I$5:$I$28252,$B9,Sheet1!$L$5:$L$28252,$A9,Sheet1!$E$5:$E$28252,"*亲情卡*",Sheet1!$D$5:$D$28252,"<>亲情卡",Sheet1!$D$5:$D$28252,"<>内部转款",Sheet1!$D$5:$D$28252,"<>内部转账",Sheet1!$E$5:$E$28252,"<>*调拨*") -> 0 | R9: =SUMIFS(Sheet1!$F$5:$F$28252,Sheet1!$I$5:$I$28252,$B9,Sheet1!$L$5:$L$28252,$A9,Sheet1!$D$5:$D$28252,"优惠券",Sheet1!$E$5:$E$28252,"<>*调拨*")+SUMIFS(Sheet1!$F$5:$F$28252,Sheet1!$I$5:$I$28252,$B9,Sheet1!$L$5:$L$28252,$A9,Sheet1!$E$5:$E$28252,"*优惠券*",Sheet1!$D$5:$D$28252,"<>优惠券",Sheet1!$D$5:$D$28252,"<>内部转款",Sheet1!$D$5:$D$28252,"<>内部转账",Sheet1!$E$5:$E$28252,"<>*调拨*") -> 0 | S9: =SUMIFS(Sheet1!$F$5:$F$28252,Sheet1!$I$5:$I$28252,$B9,Sheet1!$L$5:$L$28252,$A9,Sheet1!$D$5:$D$28252,"代金券",Sheet1!$E$5:$E$28252,"<>*调拨*")+SUMIFS(Sheet1!$F$5:$F$28252,Sheet1!$I$5:$I$28252,$B9,Sheet1!$L$5:$L$28252,$A9,Sheet1!$E$5:$E$28252,"*代金券*",Sheet1!$D$5:$D$28252,"<>代金券",Sheet1!$D$5:$D$28252,"<>内部转款",Sheet1!$D$5:$D$28252,"<>内部转账",Sheet1!$E$5:$E$28252,"<>*调拨*") -> 0 | T9: =SUMIFS(Sheet1!$F$5:$F$28252,Sheet1!$I$5:$I$28252,$B9,Sheet1!$L$5:$L$28252,$A9,Sheet1!$D$5:$D$28252,"回款",Sheet1!$E$5:$E$28252,"<>*调拨*",Sheet1!$E$5:$E$28252,"<>*医保*",Sheet1!$E$5:$E$28252,"<>*聚合*",Sheet1!$E$5:$E$28252,"<>*24小时微信*",Sheet1!$E$5:$E$28252,"<>*美团*",Sheet1!$E$5:$E$28252,"<>*饿了么*",Sheet1!$E$5:$E$28252,"<>*健E卡*",Sheet1!$E$5:$E$28252,"<>*抖音*",Sheet1!$E$5:$E$28252,"<>*医卡通*",Sheet1!$E$5:$E$28252,"<>*企健网*",Sheet1!$E$5:$E$28252,"<>*银联*",Sheet1!$E$5:$E$28252,"<>*京东*",Sheet1!$E$5:$E$28252,"<>*药机微信*",Sheet1!$E$5:$E$28252,"<>*亲情卡*",Sheet1!$E$5:$E$28252,"<>*优惠券*",Sheet1!$E$5:$E$28252,"<>*代金券*",Sheet1!$E$5:$E$28252,"<>*储值*",Sheet1!$E$5:$E$28252,"<>*效期*")+SUMIFS(Sheet1!$F$5:$F$28252,Sheet1!$I$5:$I$28252,$B9,Sheet1!$L$5:$L$28252,$A9,Sheet1!$D$5:$D$28252,"收款",Sheet1!$E$5:$E$28252,"<>*调拨*",Sheet1!$E$5:$E$28252,"<>*医保*",Sheet1!$E$5:$E$28252,"<>*聚合*",Sheet1!$E$5:$E$28252,"<>*24小时微信*",Sheet1!$E$5:$E$28252,"<>*美团*",Sheet1!$E$5:$E$28252,"<>*饿了么*",Sheet1!$E$5:$E$28252,"<>*健E卡*",Sheet1!$E$5:$E$28252,"<>*抖音*",Sheet1!$E$5:$E$28252,"<>*医卡通*",Sheet1!$E$5:$E$28252,"<>*企健网*",Sheet1!$E$5:$E$28252,"<>*银联*",Sheet1!$E$5:$E$28252,"<>*京东*",Sheet1!$E$5:$E$28252,"<>*药机微信*",Sheet1!$E$5:$E$28252,"<>*亲情卡*",Sheet1!$E$5:$E$28252,"<>*优惠券*",Sheet1!$E$5:$E$28252,"<>*代金券*",Sheet1!$E$5:$E$28252,"<>*储值*",Sheet1!$E$5:$E$28252,"<>*效期*")+SUMIFS(Sheet1!$F$5:$F$28252,Sheet1!$I$5:$I$28252,$B9,Sheet1!$L$5:$L$28252,$A9,Sheet1!$E$5:$E$28252,"*回款*",Sheet1!$D$5:$D$28252,"<>回款",Sheet1!$D$5:$D$28252,"<>收款",Sheet1!$D$5:$D$28252,"<>内部转款",Sheet1!$D$5:$D$28252,"<>内部转账",Sheet1!$E$5:$E$28252,"<>*调拨*",Sheet1!$E$5:$E$28252,"<>*医保*",Sheet1!$E$5:$E$28252,"<>*聚合*",Sheet1!$E$5:$E$28252,"<>*24小时微信*",Sheet1!$E$5:$E$28252,"<>*美团*",Sheet1!$E$5:$E$28252,"<>*饿了么*",Sheet1!$E$5:$E$28252,"<>*健E卡*",Sheet1!$E$5:$E$28252,"<>*抖音*",Sheet1!$E$5:$E$28252,"<>*医卡通*",Sheet1!$E$5:$E$28252,"<>*企健网*",Sheet1!$E$5:$E$28252,"<>*银联*",Sheet1!$E$5:$E$28252,"<>*京东*",Sheet1!$E$5:$E$28252,"<>*药机微信*",Sheet1!$E$5:$E$28252,"<>*亲情卡*",Sheet1!$E$5:$E$28252,"<>*优惠券*",Sheet1!$E$5:$E$28252,"<>*代金券*",Sheet1!$E$5:$E$28252,"<>*储值*",Sheet1!$E$5:$E$28252,"<>*效期*")+SUMIFS(Sheet1!$F$5:$F$28252,Sheet1!$I$5:$I$28252,$B9,Sheet1!$L$5:$L$28252,$A9,Sheet1!$E$5:$E$28252,"*收款*",Sheet1!$E$5:$E$28252,"<>*回款*",Sheet1!$D$5:$D$28252,"<>回款",Sheet1!$D$5:$D$28252,"<>收款",Sheet1!$D$5:$D$28252,"<>内部转款",Sheet1!$D$5:$D$28252,"<>内部转账",Sheet1!$E$5:$E$28252,"<>*调拨*",Sheet1!$E$5:$E$28252,"<>*医保*",Sheet1!$E$5:$E$28252,"<>*聚合*",Sheet1!$E$5:$E$28252,"<>*24小时微信*",Sheet1!$E$5:$E$28252,"<>*美团*",Sheet1!$E$5:$E$28252,"<>*饿了么*",Sheet1!$E$5:$E$28252,"<>*健E卡*",Sheet1!$E$5:$E$28252,"<>*抖音*",Sheet1!$E$5:$E$28252,"<>*医卡通*",Sheet1!$E$5:$E$28252,"<>*企健网*",Sheet1!$E$5:$E$28252,"<>*银联*",Sheet1!$E$5:$E$28252,"<>*京东*",Sheet1!$E$5:$E$28252,"<>*药机微信*",Sheet1!$E$5:$E$28252,"<>*亲情卡*",Sheet1!$E$5:$E$28252,"<>*优惠券*",Sheet1!$E$5:$E$28252,"<>*代金券*",Sheet1!$E$5:$E$28252,"<>*储值*",Sheet1!$E$5:$E$28252,"<>*效期*") -> 0 | U9: =SUMIFS(Sheet1!$F$5:$F$28252,Sheet1!$I$5:$I$28252,$B9,Sheet1!$L$5:$L$28252,$A9,Sheet1!$E$5:$E$28252,"*调拨*") -> 0 | V9: =SUMIFS(Sheet1!$F$5:$F$28252,Sheet1!$I$5:$I$28252,$B9,Sheet1!$L$5:$L$28252,$A9,Sheet1!$D$5:$D$28252,"储值",Sheet1!$E$5:$E$28252,"<>*调拨*")+SUMIFS(Sheet1!$F$5:$F$28252,Sheet1!$I$5:$I$28252,$B9,Sheet1!$L$5:$L$28252,$A9,Sheet1!$E$5:$E$28252,"*储值*",Sheet1!$D$5:$D$28252,"<>储值",Sheet1!$D$5:$D$28252,"<>内部转款",Sheet1!$D$5:$D$28252,"<>内部转账",Sheet1!$E$5:$E$28252,"<>*调拨*") -> 0 | W9: =SUMIFS(Sheet1!$F$5:$F$28252,Sheet1!$I$5:$I$28252,$B9,Sheet1!$L$5:$L$28252,$A9,Sheet1!$D$5:$D$28252,"效期",Sheet1!$E$5:$E$28252,"<>*调拨*")+SUMIFS(Sheet1!$F$5:$F$28252,Sheet1!$I$5:$I$28252,$B9,Sheet1!$L$5:$L$28252,$A9,Sheet1!$E$5:$E$28252,"*效期*",Sheet1!$D$5:$D$28252,"<>效期",Sheet1!$D$5:$D$28252,"<>内部转款",Sheet1!$D$5:$D$28252,"<>内部转账",Sheet1!$E$5:$E$28252,"<>*调拨*") -> 0 | X9: =SUMIFS(Sheet1!$F$5:$F$28252,Sheet1!$I$5:$I$28252,$B9,Sheet1!$L$5:$L$28252,$A9,Sheet1!$D$5:$D$28252,"内部转款",Sheet1!$E$5:$E$28252,"<>*调拨*")+SUMIFS(Sheet1!$F$5:$F$28252,Sheet1!$I$5:$I$28252,$B9,Sheet1!$L$5:$L$28252,$A9,Sheet1!$D$5:$D$28252,"内部转账",Sheet1!$E$5:$E$28252,"<>*调拨*") -> 0 | Y9: =Z9-SUM(C9:X9) -> 0 | Z9: =SUMIFS(Sheet1!$F$5:$F$28252,Sheet1!$I$5:$I$28252,$B9,Sheet1!$L$5:$L$28252,$A9) -> 0 | AA9: =SUMIFS(Sheet1!$G$5:$G$28252,Sheet1!$I$5:$I$28252,$B9,Sheet1!$L$5:$L$28252,$A9,Sheet1!$D$5:$D$28252,"工资",Sheet1!$E$5:$E$28252,"<>*调拨*")+SUMIFS(Sheet1!$G$5:$G$28252,Sheet1!$I$5:$I$28252,$B9,Sheet1!$L$5:$L$28252,$A9,Sheet1!$E$5:$E$28252,"*工资*",Sheet1!$E$5:$E$28252,"<>*调拨*",Sheet1!$D$5:$D$28252,"<>内部转款",Sheet1!$D$5:$D$28252,"<>内部转账",Sheet1!$D$5:$D$28252,"<>工资",Sheet1!$D$5:$D$28252,"<>水费",Sheet1!$D$5:$D$28252,"<>电费",Sheet1!$D$5:$D$28252,"<>宽带费",Sheet1!$D$5:$D$28252,"<>办公费",Sheet1!$D$5:$D$28252,"<>话费",Sheet1!$D$5:$D$28252,"<>房租") -> 0 | AB9: =SUMIFS(Sheet1!$G$5:$G$28252,Sheet1!$I$5:$I$28252,$B9,Sheet1!$L$5:$L$28252,$A9,Sheet1!$D$5:$D$28252,"水费",Sheet1!$E$5:$E$28252,"<>*调拨*")+SUMIFS(Sheet1!$G$5:$G$28252,Sheet1!$I$5:$I$28252,$B9,Sheet1!$L$5:$L$28252,$A9,Sheet1!$E$5:$E$28252,"*水费*",Sheet1!$E$5:$E$28252,"<>*调拨*",Sheet1!$D$5:$D$28252,"<>内部转款",Sheet1!$D$5:$D$28252,"<>内部转账",Sheet1!$D$5:$D$28252,"<>工资",Sheet1!$D$5:$D$28252,"<>水费",Sheet1!$D$5:$D$28252,"<>电费",Sheet1!$D$5:$D$28252,"<>宽带费",Sheet1!$D$5:$D$28252,"<>办公费",Sheet1!$D$5:$D$28252,"<>话费",Sheet1!$D$5:$D$28252,"<>房租",Sheet1!$E$5:$E$28252,"<>*工资*") -> 0 | AC9: =SUMIFS(Sheet1!$G$5:$G$28252,Sheet1!$I$5:$I$28252,$B9,Sheet1!$L$5:$L$28252,$A9,Sheet1!$D$5:$D$28252,"电费",Sheet1!$E$5:$E$28252,"<>*调拨*")+SUMIFS(Sheet1!$G$5:$G$28252,Sheet1!$I$5:$I$28252,$B9,Sheet1!$L$5:$L$28252,$A9,Sheet1!$E$5:$E$28252,"*电费*",Sheet1!$E$5:$E$28252,"<>*调拨*",Sheet1!$D$5:$D$28252,"<>内部转款",Sheet1!$D$5:$D$28252,"<>内部转账",Sheet1!$D$5:$D$28252,"<>工资",Sheet1!$D$5:$D$28252,"<>水费",Sheet1!$D$5:$D$28252,"<>电费",Sheet1!$D$5:$D$28252,"<>宽带费",Sheet1!$D$5:$D$28252,"<>办公费",Sheet1!$D$5:$D$28252,"<>话费",Sheet1!$D$5:$D$28252,"<>房租",Sheet1!$E$5:$E$28252,"<>*工资*",Sheet1!$E$5:$E$28252,"<>*水费*") -> 0 | AD9: =SUMIFS(Sheet1!$G$5:$G$28252,Sheet1!$I$5:$I$28252,$B9,Sheet1!$L$5:$L$28252,$A9,Sheet1!$D$5:$D$28252,"宽带费",Sheet1!$E$5:$E$28252,"<>*调拨*")+SUMIFS(Sheet1!$G$5:$G$28252,Sheet1!$I$5:$I$28252,$B9,Sheet1!$L$5:$L$28252,$A9,Sheet1!$E$5:$E$28252,"*宽带*",Sheet1!$E$5:$E$28252,"<>*调拨*",Sheet1!$D$5:$D$28252,"<>内部转款",Sheet1!$D$5:$D$28252,"<>内部转账",Sheet1!$D$5:$D$28252,"<>工资",Sheet1!$D$5:$D$28252,"<>水费",Sheet1!$D$5:$D$28252,"<>电费",Sheet1!$D$5:$D$28252,"<>宽带费",Sheet1!$D$5:$D$28252,"<>办公费",Sheet1!$D$5:$D$28252,"<>话费",Sheet1!$D$5:$D$28252,"<>房租",Sheet1!$E$5:$E$28252,"<>*工资*",Sheet1!$E$5:$E$28252,"<>*水费*",Sheet1!$E$5:$E$28252,"<>*电费*") -> 0 | AE9: =SUMIFS(Sheet1!$G$5:$G$28252,Sheet1!$I$5:$I$28252,$B9,Sheet1!$L$5:$L$28252,$A9,Sheet1!$D$5:$D$28252,"办公费",Sheet1!$E$5:$E$28252,"<>*调拨*")+SUMIFS(Sheet1!$G$5:$G$28252,Sheet1!$I$5:$I$28252,$B9,Sheet1!$L$5:$L$28252,$A9,Sheet1!$E$5:$E$28252,"*办公*",Sheet1!$E$5:$E$28252,"<>*调拨*",Sheet1!$D$5:$D$28252,"<>内部转款",Sheet1!$D$5:$D$28252,"<>内部转账",Sheet1!$D$5:$D$28252,"<>工资",Sheet1!$D$5:$D$28252,"<>水费",Sheet1!$D$5:$D$28252,"<>电费",Sheet1!$D$5:$D$28252,"<>宽带费",Sheet1!$D$5:$D$28252,"<>办公费",Sheet1!$D$5:$D$28252,"<>话费",Sheet1!$D$5:$D$28252,"<>房租",Sheet1!$E$5:$E$28252,"<>*工资*",Sheet1!$E$5:$E$28252,"<>*水费*",Sheet1!$E$5:$E$28252,"<>*电费*",Sheet1!$E$5:$E$28252,"<>*宽带*") -> 0 | AF9: =SUMIFS(Sheet1!$G$5:$G$28252,Sheet1!$I$5:$I$28252,$B9,Sheet1!$L$5:$L$28252,$A9,Sheet1!$D$5:$D$28252,"话费",Sheet1!$E$5:$E$28252,"<>*调拨*")+SUMIFS(Sheet1!$G$5:$G$28252,Sheet1!$I$5:$I$28252,$B9,Sheet1!$L$5:$L$28252,$A9,Sheet1!$E$5:$E$28252,"*话费*",Sheet1!$E$5:$E$28252,"<>*调拨*",Sheet1!$D$5:$D$28252,"<>内部转款",Sheet1!$D$5:$D$28252,"<>内部转账",Sheet1!$D$5:$D$28252,"<>工资",Sheet1!$D$5:$D$28252,"<>水费",Sheet1!$D$5:$D$28252,"<>电费",Sheet1!$D$5:$D$28252,"<>宽带费",Sheet1!$D$5:$D$28252,"<>办公费",Sheet1!$D$5:$D$28252,"<>话费",Sheet1!$D$5:$D$28252,"<>房租",Sheet1!$E$5:$E$28252,"<>*工资*",Sheet1!$E$5:$E$28252,"<>*水费*",Sheet1!$E$5:$E$28252,"<>*电费*",Sheet1!$E$5:$E$28252,"<>*宽带*",Sheet1!$E$5:$E$28252,"<>*办公*") -> 0 | AG9: =SUMIFS(Sheet1!$G$5:$G$28252,Sheet1!$I$5:$I$28252,$B9,Sheet1!$L$5:$L$28252,$A9,Sheet1!$D$5:$D$28252,"房租",Sheet1!$E$5:$E$28252,"<>*调拨*")+SUMIFS(Sheet1!$G$5:$G$28252,Sheet1!$I$5:$I$28252,$B9,Sheet1!$L$5:$L$28252,$A9,Sheet1!$E$5:$E$28252,"*房租*",Sheet1!$E$5:$E$28252,"<>*调拨*",Sheet1!$D$5:$D$28252,"<>内部转款",Sheet1!$D$5:$D$28252,"<>内部转账",Sheet1!$D$5:$D$28252,"<>工资",Sheet1!$D$5:$D$28252,"<>水费",Sheet1!$D$5:$D$28252,"<>电费",Sheet1!$D$5:$D$28252,"<>宽带费",Sheet1!$D$5:$D$28252,"<>办公费",Sheet1!$D$5:$D$28252,"<>话费",Sheet1!$D$5:$D$28252,"<>房租",Sheet1!$E$5:$E$28252,"<>*工资*",Sheet1!$E$5:$E$28252,"<>*水费*",Sheet1!$E$5:$E$28252,"<>*电费*",Sheet1!$E$5:$E$28252,"<>*宽带*",Sheet1!$E$5:$E$28252,"<>*办公*",Sheet1!$E$5:$E$28252,"<>*话费*") -> 0 | AH9: =SUMIFS(Sheet1!$G$5:$G$28252,Sheet1!$I$5:$I$28252,$B9,Sheet1!$L$5:$L$28252,$A9,Sheet1!$E$5:$E$28252,"*调拨*") -> 0 | AI9: =SUMIFS(Sheet1!$G$5:$G$28252,Sheet1!$I$5:$I$28252,$B9,Sheet1!$L$5:$L$28252,$A9,Sheet1!$D$5:$D$28252,"内部转款",Sheet1!$E$5:$E$28252,"<>*调拨*")+SUMIFS(Sheet1!$G$5:$G$28252,Sheet1!$I$5:$I$28252,$B9,Sheet1!$L$5:$L$28252,$A9,Sheet1!$D$5:$D$28252,"内部转账",Sheet1!$E$5:$E$28252,"<>*调拨*") -> 0 | AJ9: =AK9-SUM(AA9:AI9) -> 0 | AK9: =SUMIFS(Sheet1!$G$5:$G$28252,Sheet1!$I$5:$I$28252,$B9,Sheet1!$L$5:$L$28252,$A9) -> 0 | AL9: =Z9-AK9 -> 0
A10: 202512 | B10: 千户营滏阳分店（39分店） | C10: =SUMIFS(Sheet1!$F$5:$F$28252,Sheet1!$I$5:$I$28252,$B10,Sheet1!$L$5:$L$28252,$A10,Sheet1!$D$5:$D$28252,"营业款",Sheet1!$E$5:$E$28252,"<>*调拨*",Sheet1!$E$5:$E$28252,"<>*回款*",Sheet1!$E$5:$E$28252,"<>*收款*",Sheet1!$E$5:$E$28252,"<>*医保*",Sheet1!$E$5:$E$28252,"<>*聚合*",Sheet1!$E$5:$E$28252,"<>*24小时微信*",Sheet1!$E$5:$E$28252,"<>*美团*",Sheet1!$E$5:$E$28252,"<>*饿了么*",Sheet1!$E$5:$E$28252,"<>*健E卡*",Sheet1!$E$5:$E$28252,"<>*抖音*",Sheet1!$E$5:$E$28252,"<>*医卡通*",Sheet1!$E$5:$E$28252,"<>*企健网*",Sheet1!$E$5:$E$28252,"<>*银联*",Sheet1!$E$5:$E$28252,"<>*京东*",Sheet1!$E$5:$E$28252,"<>*药机微信*",Sheet1!$E$5:$E$28252,"<>*亲情卡*",Sheet1!$E$5:$E$28252,"<>*优惠券*",Sheet1!$E$5:$E$28252,"<>*代金券*",Sheet1!$E$5:$E$28252,"<>*储值*",Sheet1!$E$5:$E$28252,"<>*效期*") -> 0 | D10: =SUMIFS(Sheet1!$F$5:$F$28252,Sheet1!$I$5:$I$28252,$B10,Sheet1!$L$5:$L$28252,$A10,Sheet1!$D$5:$D$28252,"医保即时拨付",Sheet1!$E$5:$E$28252,"<>*调拨*")+SUMIFS(Sheet1!$F$5:$F$28252,Sheet1!$I$5:$I$28252,$B10,Sheet1!$L$5:$L$28252,$A10,Sheet1!$E$5:$E$28252,"*医保即时拨付*",Sheet1!$D$5:$D$28252,"<>医保即时拨付",Sheet1!$D$5:$D$28252,"<>内部转款",Sheet1!$D$5:$D$28252,"<>内部转账",Sheet1!$E$5:$E$28252,"<>*调拨*") -> 0 | E10: =SUMIFS(Sheet1!$F$5:$F$28252,Sheet1!$I$5:$I$28252,$B10,Sheet1!$L$5:$L$28252,$A10,Sheet1!$D$5:$D$28252,"医保",Sheet1!$E$5:$E$28252,"<>*调拨*",Sheet1!$E$5:$E$28252,"<>*医保即时拨付*")+SUMIFS(Sheet1!$F$5:$F$28252,Sheet1!$I$5:$I$28252,$B10,Sheet1!$L$5:$L$28252,$A10,Sheet1!$E$5:$E$28252,"*医保*",Sheet1!$D$5:$D$28252,"<>医保",Sheet1!$D$5:$D$28252,"<>医保即时拨付",Sheet1!$D$5:$D$28252,"<>内部转款",Sheet1!$D$5:$D$28252,"<>内部转账",Sheet1!$E$5:$E$28252,"<>*医保即时拨付*",Sheet1!$E$5:$E$28252,"<>*调拨*") -> 0 | F10: =SUMIFS(Sheet1!$F$5:$F$28252,Sheet1!$I$5:$I$28252,$B10,Sheet1!$L$5:$L$28252,$A10,Sheet1!$D$5:$D$28252,"聚合",Sheet1!$E$5:$E$28252,"<>*调拨*")+SUMIFS(Sheet1!$F$5:$F$28252,Sheet1!$I$5:$I$28252,$B10,Sheet1!$L$5:$L$28252,$A10,Sheet1!$E$5:$E$28252,"*聚合*",Sheet1!$D$5:$D$28252,"<>聚合",Sheet1!$D$5:$D$28252,"<>内部转款",Sheet1!$D$5:$D$28252,"<>内部转账",Sheet1!$E$5:$E$28252,"<>*调拨*") -> 0 | G10: =SUMIFS(Sheet1!$F$5:$F$28252,Sheet1!$I$5:$I$28252,$B10,Sheet1!$L$5:$L$28252,$A10,Sheet1!$D$5:$D$28252,"24小时微信",Sheet1!$E$5:$E$28252,"<>*调拨*")+SUMIFS(Sheet1!$F$5:$F$28252,Sheet1!$I$5:$I$28252,$B10,Sheet1!$L$5:$L$28252,$A10,Sheet1!$E$5:$E$28252,"*24小时微信*",Sheet1!$D$5:$D$28252,"<>24小时微信",Sheet1!$D$5:$D$28252,"<>内部转款",Sheet1!$D$5:$D$28252,"<>内部转账",Sheet1!$E$5:$E$28252,"<>*调拨*") -> 0 | H10: =SUMIFS(Sheet1!$F$5:$F$28252,Sheet1!$I$5:$I$28252,$B10,Sheet1!$L$5:$L$28252,$A10,Sheet1!$D$5:$D$28252,"美团",Sheet1!$E$5:$E$28252,"<>*调拨*")+SUMIFS(Sheet1!$F$5:$F$28252,Sheet1!$I$5:$I$28252,$B10,Sheet1!$L$5:$L$28252,$A10,Sheet1!$E$5:$E$28252,"*美团*",Sheet1!$D$5:$D$28252,"<>美团",Sheet1!$D$5:$D$28252,"<>内部转款",Sheet1!$D$5:$D$28252,"<>内部转账",Sheet1!$E$5:$E$28252,"<>*调拨*") -> 0 | I10: =SUMIFS(Sheet1!$F$5:$F$28252,Sheet1!$I$5:$I$28252,$B10,Sheet1!$L$5:$L$28252,$A10,Sheet1!$D$5:$D$28252,"饿了么",Sheet1!$E$5:$E$28252,"<>*调拨*")+SUMIFS(Sheet1!$F$5:$F$28252,Sheet1!$I$5:$I$28252,$B10,Sheet1!$L$5:$L$28252,$A10,Sheet1!$E$5:$E$28252,"*饿了么*",Sheet1!$D$5:$D$28252,"<>饿了么",Sheet1!$D$5:$D$28252,"<>内部转款",Sheet1!$D$5:$D$28252,"<>内部转账",Sheet1!$E$5:$E$28252,"<>*调拨*") -> 0 | J10: =SUMIFS(Sheet1!$F$5:$F$28252,Sheet1!$I$5:$I$28252,$B10,Sheet1!$L$5:$L$28252,$A10,Sheet1!$D$5:$D$28252,"健E卡",Sheet1!$E$5:$E$28252,"<>*调拨*")+SUMIFS(Sheet1!$F$5:$F$28252,Sheet1!$I$5:$I$28252,$B10,Sheet1!$L$5:$L$28252,$A10,Sheet1!$E$5:$E$28252,"*健E卡*",Sheet1!$D$5:$D$28252,"<>健E卡",Sheet1!$D$5:$D$28252,"<>内部转款",Sheet1!$D$5:$D$28252,"<>内部转账",Sheet1!$E$5:$E$28252,"<>*调拨*") -> 0 | K10: =SUMIFS(Sheet1!$F$5:$F$28252,Sheet1!$I$5:$I$28252,$B10,Sheet1!$L$5:$L$28252,$A10,Sheet1!$D$5:$D$28252,"抖音",Sheet1!$E$5:$E$28252,"<>*调拨*")+SUMIFS(Sheet1!$F$5:$F$28252,Sheet1!$I$5:$I$28252,$B10,Sheet1!$L$5:$L$28252,$A10,Sheet1!$E$5:$E$28252,"*抖音*",Sheet1!$D$5:$D$28252,"<>抖音",Sheet1!$D$5:$D$28252,"<>内部转款",Sheet1!$D$5:$D$28252,"<>内部转账",Sheet1!$E$5:$E$28252,"<>*调拨*") -> 0 | L10: =SUMIFS(Sheet1!$F$5:$F$28252,Sheet1!$I$5:$I$28252,$B10,Sheet1!$L$5:$L$28252,$A10,Sheet1!$D$5:$D$28252,"医卡通",Sheet1!$E$5:$E$28252,"<>*调拨*")+SUMIFS(Sheet1!$F$5:$F$28252,Sheet1!$I$5:$I$28252,$B10,Sheet1!$L$5:$L$28252,$A10,Sheet1!$E$5:$E$28252,"*医卡通*",Sheet1!$D$5:$D$28252,"<>医卡通",Sheet1!$D$5:$D$28252,"<>内部转款",Sheet1!$D$5:$D$28252,"<>内部转账",Sheet1!$E$5:$E$28252,"<>*调拨*") -> 0 | M10: =SUMIFS(Sheet1!$F$5:$F$28252,Sheet1!$I$5:$I$28252,$B10,Sheet1!$L$5:$L$28252,$A10,Sheet1!$D$5:$D$28252,"企健网",Sheet1!$E$5:$E$28252,"<>*调拨*")+SUMIFS(Sheet1!$F$5:$F$28252,Sheet1!$I$5:$I$28252,$B10,Sheet1!$L$5:$L$28252,$A10,Sheet1!$E$5:$E$28252,"*企健网*",Sheet1!$D$5:$D$28252,"<>企健网",Sheet1!$D$5:$D$28252,"<>内部转款",Sheet1!$D$5:$D$28252,"<>内部转账",Sheet1!$E$5:$E$28252,"<>*调拨*") -> 0 | N10: =SUMIFS(Sheet1!$F$5:$F$28252,Sheet1!$I$5:$I$28252,$B10,Sheet1!$L$5:$L$28252,$A10,Sheet1!$D$5:$D$28252,"银联",Sheet1!$E$5:$E$28252,"<>*调拨*")+SUMIFS(Sheet1!$F$5:$F$28252,Sheet1!$I$5:$I$28252,$B10,Sheet1!$L$5:$L$28252,$A10,Sheet1!$E$5:$E$28252,"*银联*",Sheet1!$D$5:$D$28252,"<>银联",Sheet1!$D$5:$D$28252,"<>内部转款",Sheet1!$D$5:$D$28252,"<>内部转账",Sheet1!$E$5:$E$28252,"<>*调拨*") -> 0 | O10: =SUMIFS(Sheet1!$F$5:$F$28252,Sheet1!$I$5:$I$28252,$B10,Sheet1!$L$5:$L$28252,$A10,Sheet1!$D$5:$D$28252,"京东",Sheet1!$E$5:$E$28252,"<>*调拨*")+SUMIFS(Sheet1!$F$5:$F$28252,Sheet1!$I$5:$I$28252,$B10,Sheet1!$L$5:$L$28252,$A10,Sheet1!$E$5:$E$28252,"*京东*",Sheet1!$D$5:$D$28252,"<>京东",Sheet1!$D$5:$D$28252,"<>内部转款",Sheet1!$D$5:$D$28252,"<>内部转账",Sheet1!$E$5:$E$28252,"<>*调拨*") -> 0 | P10: =SUMIFS(Sheet1!$F$5:$F$28252,Sheet1!$I$5:$I$28252,$B10,Sheet1!$L$5:$L$28252,$A10,Sheet1!$D$5:$D$28252,"药机微信",Sheet1!$E$5:$E$28252,"<>*调拨*")+SUMIFS(Sheet1!$F$5:$F$28252,Sheet1!$I$5:$I$28252,$B10,Sheet1!$L$5:$L$28252,$A10,Sheet1!$E$5:$E$28252,"*药机微信*",Sheet1!$D$5:$D$28252,"<>药机微信",Sheet1!$D$5:$D$28252,"<>内部转款",Sheet1!$D$5:$D$28252,"<>内部转账",Sheet1!$E$5:$E$28252,"<>*调拨*") -> 0 | Q10: =SUMIFS(Sheet1!$F$5:$F$28252,Sheet1!$I$5:$I$28252,$B10,Sheet1!$L$5:$L$28252,$A10,Sheet1!$D$5:$D$28252,"亲情卡",Sheet1!$E$5:$E$28252,"<>*调拨*")+SUMIFS(Sheet1!$F$5:$F$28252,Sheet1!$I$5:$I$28252,$B10,Sheet1!$L$5:$L$28252,$A10,Sheet1!$E$5:$E$28252,"*亲情卡*",Sheet1!$D$5:$D$28252,"<>亲情卡",Sheet1!$D$5:$D$28252,"<>内部转款",Sheet1!$D$5:$D$28252,"<>内部转账",Sheet1!$E$5:$E$28252,"<>*调拨*") -> 0 | R10: =SUMIFS(Sheet1!$F$5:$F$28252,Sheet1!$I$5:$I$28252,$B10,Sheet1!$L$5:$L$28252,$A10,Sheet1!$D$5:$D$28252,"优惠券",Sheet1!$E$5:$E$28252,"<>*调拨*")+SUMIFS(Sheet1!$F$5:$F$28252,Sheet1!$I$5:$I$28252,$B10,Sheet1!$L$5:$L$28252,$A10,Sheet1!$E$5:$E$28252,"*优惠券*",Sheet1!$D$5:$D$28252,"<>优惠券",Sheet1!$D$5:$D$28252,"<>内部转款",Sheet1!$D$5:$D$28252,"<>内部转账",Sheet1!$E$5:$E$28252,"<>*调拨*") -> 0 | S10: =SUMIFS(Sheet1!$F$5:$F$28252,Sheet1!$I$5:$I$28252,$B10,Sheet1!$L$5:$L$28252,$A10,Sheet1!$D$5:$D$28252,"代金券",Sheet1!$E$5:$E$28252,"<>*调拨*")+SUMIFS(Sheet1!$F$5:$F$28252,Sheet1!$I$5:$I$28252,$B10,Sheet1!$L$5:$L$28252,$A10,Sheet1!$E$5:$E$28252,"*代金券*",Sheet1!$D$5:$D$28252,"<>代金券",Sheet1!$D$5:$D$28252,"<>内部转款",Sheet1!$D$5:$D$28252,"<>内部转账",Sheet1!$E$5:$E$28252,"<>*调拨*") -> 0 | T10: =SUMIFS(Sheet1!$F$5:$F$28252,Sheet1!$I$5:$I$28252,$B10,Sheet1!$L$5:$L$28252,$A10,Sheet1!$D$5:$D$28252,"回款",Sheet1!$E$5:$E$28252,"<>*调拨*",Sheet1!$E$5:$E$28252,"<>*医保*",Sheet1!$E$5:$E$28252,"<>*聚合*",Sheet1!$E$5:$E$28252,"<>*24小时微信*",Sheet1!$E$5:$E$28252,"<>*美团*",Sheet1!$E$5:$E$28252,"<>*饿了么*",Sheet1!$E$5:$E$28252,"<>*健E卡*",Sheet1!$E$5:$E$28252,"<>*抖音*",Sheet1!$E$5:$E$28252,"<>*医卡通*",Sheet1!$E$5:$E$28252,"<>*企健网*",Sheet1!$E$5:$E$28252,"<>*银联*",Sheet1!$E$5:$E$28252,"<>*京东*",Sheet1!$E$5:$E$28252,"<>*药机微信*",Sheet1!$E$5:$E$28252,"<>*亲情卡*",Sheet1!$E$5:$E$28252,"<>*优惠券*",Sheet1!$E$5:$E$28252,"<>*代金券*",Sheet1!$E$5:$E$28252,"<>*储值*",Sheet1!$E$5:$E$28252,"<>*效期*")+SUMIFS(Sheet1!$F$5:$F$28252,Sheet1!$I$5:$I$28252,$B10,Sheet1!$L$5:$L$28252,$A10,Sheet1!$D$5:$D$28252,"收款",Sheet1!$E$5:$E$28252,"<>*调拨*",Sheet1!$E$5:$E$28252,"<>*医保*",Sheet1!$E$5:$E$28252,"<>*聚合*",Sheet1!$E$5:$E$28252,"<>*24小时微信*",Sheet1!$E$5:$E$28252,"<>*美团*",Sheet1!$E$5:$E$28252,"<>*饿了么*",Sheet1!$E$5:$E$28252,"<>*健E卡*",Sheet1!$E$5:$E$28252,"<>*抖音*",Sheet1!$E$5:$E$28252,"<>*医卡通*",Sheet1!$E$5:$E$28252,"<>*企健网*",Sheet1!$E$5:$E$28252,"<>*银联*",Sheet1!$E$5:$E$28252,"<>*京东*",Sheet1!$E$5:$E$28252,"<>*药机微信*",Sheet1!$E$5:$E$28252,"<>*亲情卡*",Sheet1!$E$5:$E$28252,"<>*优惠券*",Sheet1!$E$5:$E$28252,"<>*代金券*",Sheet1!$E$5:$E$28252,"<>*储值*",Sheet1!$E$5:$E$28252,"<>*效期*")+SUMIFS(Sheet1!$F$5:$F$28252,Sheet1!$I$5:$I$28252,$B10,Sheet1!$L$5:$L$28252,$A10,Sheet1!$E$5:$E$28252,"*回款*",Sheet1!$D$5:$D$28252,"<>回款",Sheet1!$D$5:$D$28252,"<>收款",Sheet1!$D$5:$D$28252,"<>内部转款",Sheet1!$D$5:$D$28252,"<>内部转账",Sheet1!$E$5:$E$28252,"<>*调拨*",Sheet1!$E$5:$E$28252,"<>*医保*",Sheet1!$E$5:$E$28252,"<>*聚合*",Sheet1!$E$5:$E$28252,"<>*24小时微信*",Sheet1!$E$5:$E$28252,"<>*美团*",Sheet1!$E$5:$E$28252,"<>*饿了么*",Sheet1!$E$5:$E$28252,"<>*健E卡*",Sheet1!$E$5:$E$28252,"<>*抖音*",Sheet1!$E$5:$E$28252,"<>*医卡通*",Sheet1!$E$5:$E$28252,"<>*企健网*",Sheet1!$E$5:$E$28252,"<>*银联*",Sheet1!$E$5:$E$28252,"<>*京东*",Sheet1!$E$5:$E$28252,"<>*药机微信*",Sheet1!$E$5:$E$28252,"<>*亲情卡*",Sheet1!$E$5:$E$28252,"<>*优惠券*",Sheet1!$E$5:$E$28252,"<>*代金券*",Sheet1!$E$5:$E$28252,"<>*储值*",Sheet1!$E$5:$E$28252,"<>*效期*")+SUMIFS(Sheet1!$F$5:$F$28252,Sheet1!$I$5:$I$28252,$B10,Sheet1!$L$5:$L$28252,$A10,Sheet1!$E$5:$E$28252,"*收款*",Sheet1!$E$5:$E$28252,"<>*回款*",Sheet1!$D$5:$D$28252,"<>回款",Sheet1!$D$5:$D$28252,"<>收款",Sheet1!$D$5:$D$28252,"<>内部转款",Sheet1!$D$5:$D$28252,"<>内部转账",Sheet1!$E$5:$E$28252,"<>*调拨*",Sheet1!$E$5:$E$28252,"<>*医保*",Sheet1!$E$5:$E$28252,"<>*聚合*",Sheet1!$E$5:$E$28252,"<>*24小时微信*",Sheet1!$E$5:$E$28252,"<>*美团*",Sheet1!$E$5:$E$28252,"<>*饿了么*",Sheet1!$E$5:$E$28252,"<>*健E卡*",Sheet1!$E$5:$E$28252,"<>*抖音*",Sheet1!$E$5:$E$28252,"<>*医卡通*",Sheet1!$E$5:$E$28252,"<>*企健网*",Sheet1!$E$5:$E$28252,"<>*银联*",Sheet1!$E$5:$E$28252,"<>*京东*",Sheet1!$E$5:$E$28252,"<>*药机微信*",Sheet1!$E$5:$E$28252,"<>*亲情卡*",Sheet1!$E$5:$E$28252,"<>*优惠券*",Sheet1!$E$5:$E$28252,"<>*代金券*",Sheet1!$E$5:$E$28252,"<>*储值*",Sheet1!$E$5:$E$28252,"<>*效期*") -> 0 | U10: =SUMIFS(Sheet1!$F$5:$F$28252,Sheet1!$I$5:$I$28252,$B10,Sheet1!$L$5:$L$28252,$A10,Sheet1!$E$5:$E$28252,"*调拨*") -> 0 | V10: =SUMIFS(Sheet1!$F$5:$F$28252,Sheet1!$I$5:$I$28252,$B10,Sheet1!$L$5:$L$28252,$A10,Sheet1!$D$5:$D$28252,"储值",Sheet1!$E$5:$E$28252,"<>*调拨*")+SUMIFS(Sheet1!$F$5:$F$28252,Sheet1!$I$5:$I$28252,$B10,Sheet1!$L$5:$L$28252,$A10,Sheet1!$E$5:$E$28252,"*储值*",Sheet1!$D$5:$D$28252,"<>储值",Sheet1!$D$5:$D$28252,"<>内部转款",Sheet1!$D$5:$D$28252,"<>内部转账",Sheet1!$E$5:$E$28252,"<>*调拨*") -> 0 | W10: =SUMIFS(Sheet1!$F$5:$F$28252,Sheet1!$I$5:$I$28252,$B10,Sheet1!$L$5:$L$28252,$A10,Sheet1!$D$5:$D$28252,"效期",Sheet1!$E$5:$E$28252,"<>*调拨*")+SUMIFS(Sheet1!$F$5:$F$28252,Sheet1!$I$5:$I$28252,$B10,Sheet1!$L$5:$L$28252,$A10,Sheet1!$E$5:$E$28252,"*效期*",Sheet1!$D$5:$D$28252,"<>效期",Sheet1!$D$5:$D$28252,"<>内部转款",Sheet1!$D$5:$D$28252,"<>内部转账",Sheet1!$E$5:$E$28252,"<>*调拨*") -> 0 | X10: =SUMIFS(Sheet1!$F$5:$F$28252,Sheet1!$I$5:$I$28252,$B10,Sheet1!$L$5:$L$28252,$A10,Sheet1!$D$5:$D$28252,"内部转款",Sheet1!$E$5:$E$28252,"<>*调拨*")+SUMIFS(Sheet1!$F$5:$F$28252,Sheet1!$I$5:$I$28252,$B10,Sheet1!$L$5:$L$28252,$A10,Sheet1!$D$5:$D$28252,"内部转账",Sheet1!$E$5:$E$28252,"<>*调拨*") -> 0 | Y10: =Z10-SUM(C10:X10) -> 0 | Z10: =SUMIFS(Sheet1!$F$5:$F$28252,Sheet1!$I$5:$I$28252,$B10,Sheet1!$L$5:$L$28252,$A10) -> 0 | AA10: =SUMIFS(Sheet1!$G$5:$G$28252,Sheet1!$I$5:$I$28252,$B10,Sheet1!$L$5:$L$28252,$A10,Sheet1!$D$5:$D$28252,"工资",Sheet1!$E$5:$E$28252,"<>*调拨*")+SUMIFS(Sheet1!$G$5:$G$28252,Sheet1!$I$5:$I$28252,$B10,Sheet1!$L$5:$L$28252,$A10,Sheet1!$E$5:$E$28252,"*工资*",Sheet1!$E$5:$E$28252,"<>*调拨*",Sheet1!$D$5:$D$28252,"<>内部转款",Sheet1!$D$5:$D$28252,"<>内部转账",Sheet1!$D$5:$D$28252,"<>工资",Sheet1!$D$5:$D$28252,"<>水费",Sheet1!$D$5:$D$28252,"<>电费",Sheet1!$D$5:$D$28252,"<>宽带费",Sheet1!$D$5:$D$28252,"<>办公费",Sheet1!$D$5:$D$28252,"<>话费",Sheet1!$D$5:$D$28252,"<>房租") -> 0 | AB10: =SUMIFS(Sheet1!$G$5:$G$28252,Sheet1!$I$5:$I$28252,$B10,Sheet1!$L$5:$L$28252,$A10,Sheet1!$D$5:$D$28252,"水费",Sheet1!$E$5:$E$28252,"<>*调拨*")+SUMIFS(Sheet1!$G$5:$G$28252,Sheet1!$I$5:$I$28252,$B10,Sheet1!$L$5:$L$28252,$A10,Sheet1!$E$5:$E$28252,"*水费*",Sheet1!$E$5:$E$28252,"<>*调拨*",Sheet1!$D$5:$D$28252,"<>内部转款",Sheet1!$D$5:$D$28252,"<>内部转账",Sheet1!$D$5:$D$28252,"<>工资",Sheet1!$D$5:$D$28252,"<>水费",Sheet1!$D$5:$D$28252,"<>电费",Sheet1!$D$5:$D$28252,"<>宽带费",Sheet1!$D$5:$D$28252,"<>办公费",Sheet1!$D$5:$D$28252,"<>话费",Sheet1!$D$5:$D$28252,"<>房租",Sheet1!$E$5:$E$28252,"<>*工资*") -> 0 | AC10: =SUMIFS(Sheet1!$G$5:$G$28252,Sheet1!$I$5:$I$28252,$B10,Sheet1!$L$5:$L$28252,$A10,Sheet1!$D$5:$D$28252,"电费",Sheet1!$E$5:$E$28252,"<>*调拨*")+SUMIFS(Sheet1!$G$5:$G$28252,Sheet1!$I$5:$I$28252,$B10,Sheet1!$L$5:$L$28252,$A10,Sheet1!$E$5:$E$28252,"*电费*",Sheet1!$E$5:$E$28252,"<>*调拨*",Sheet1!$D$5:$D$28252,"<>内部转款",Sheet1!$D$5:$D$28252,"<>内部转账",Sheet1!$D$5:$D$28252,"<>工资",Sheet1!$D$5:$D$28252,"<>水费",Sheet1!$D$5:$D$28252,"<>电费",Sheet1!$D$5:$D$28252,"<>宽带费",Sheet1!$D$5:$D$28252,"<>办公费",Sheet1!$D$5:$D$28252,"<>话费",Sheet1!$D$5:$D$28252,"<>房租",Sheet1!$E$5:$E$28252,"<>*工资*",Sheet1!$E$5:$E$28252,"<>*水费*") -> 0 | AD10: =SUMIFS(Sheet1!$G$5:$G$28252,Sheet1!$I$5:$I$28252,$B10,Sheet1!$L$5:$L$28252,$A10,Sheet1!$D$5:$D$28252,"宽带费",Sheet1!$E$5:$E$28252,"<>*调拨*")+SUMIFS(Sheet1!$G$5:$G$28252,Sheet1!$I$5:$I$28252,$B10,Sheet1!$L$5:$L$28252,$A10,Sheet1!$E$5:$E$28252,"*宽带*",Sheet1!$E$5:$E$28252,"<>*调拨*",Sheet1!$D$5:$D$28252,"<>内部转款",Sheet1!$D$5:$D$28252,"<>内部转账",Sheet1!$D$5:$D$28252,"<>工资",Sheet1!$D$5:$D$28252,"<>水费",Sheet1!$D$5:$D$28252,"<>电费",Sheet1!$D$5:$D$28252,"<>宽带费",Sheet1!$D$5:$D$28252,"<>办公费",Sheet1!$D$5:$D$28252,"<>话费",Sheet1!$D$5:$D$28252,"<>房租",Sheet1!$E$5:$E$28252,"<>*工资*",Sheet1!$E$5:$E$28252,"<>*水费*",Sheet1!$E$5:$E$28252,"<>*电费*") -> 0 | AE10: =SUMIFS(Sheet1!$G$5:$G$28252,Sheet1!$I$5:$I$28252,$B10,Sheet1!$L$5:$L$28252,$A10,Sheet1!$D$5:$D$28252,"办公费",Sheet1!$E$5:$E$28252,"<>*调拨*")+SUMIFS(Sheet1!$G$5:$G$28252,Sheet1!$I$5:$I$28252,$B10,Sheet1!$L$5:$L$28252,$A10,Sheet1!$E$5:$E$28252,"*办公*",Sheet1!$E$5:$E$28252,"<>*调拨*",Sheet1!$D$5:$D$28252,"<>内部转款",Sheet1!$D$5:$D$28252,"<>内部转账",Sheet1!$D$5:$D$28252,"<>工资",Sheet1!$D$5:$D$28252,"<>水费",Sheet1!$D$5:$D$28252,"<>电费",Sheet1!$D$5:$D$28252,"<>宽带费",Sheet1!$D$5:$D$28252,"<>办公费",Sheet1!$D$5:$D$28252,"<>话费",Sheet1!$D$5:$D$28252,"<>房租",Sheet1!$E$5:$E$28252,"<>*工资*",Sheet1!$E$5:$E$28252,"<>*水费*",Sheet1!$E$5:$E$28252,"<>*电费*",Sheet1!$E$5:$E$28252,"<>*宽带*") -> 0 | AF10: =SUMIFS(Sheet1!$G$5:$G$28252,Sheet1!$I$5:$I$28252,$B10,Sheet1!$L$5:$L$28252,$A10,Sheet1!$D$5:$D$28252,"话费",Sheet1!$E$5:$E$28252,"<>*调拨*")+SUMIFS(Sheet1!$G$5:$G$28252,Sheet1!$I$5:$I$28252,$B10,Sheet1!$L$5:$L$28252,$A10,Sheet1!$E$5:$E$28252,"*话费*",Sheet1!$E$5:$E$28252,"<>*调拨*",Sheet1!$D$5:$D$28252,"<>内部转款",Sheet1!$D$5:$D$28252,"<>内部转账",Sheet1!$D$5:$D$28252,"<>工资",Sheet1!$D$5:$D$28252,"<>水费",Sheet1!$D$5:$D$28252,"<>电费",Sheet1!$D$5:$D$28252,"<>宽带费",Sheet1!$D$5:$D$28252,"<>办公费",Sheet1!$D$5:$D$28252,"<>话费",Sheet1!$D$5:$D$28252,"<>房租",Sheet1!$E$5:$E$28252,"<>*工资*",Sheet1!$E$5:$E$28252,"<>*水费*",Sheet1!$E$5:$E$28252,"<>*电费*",Sheet1!$E$5:$E$28252,"<>*宽带*",Sheet1!$E$5:$E$28252,"<>*办公*") -> 0 | AG10: =SUMIFS(Sheet1!$G$5:$G$28252,Sheet1!$I$5:$I$28252,$B10,Sheet1!$L$5:$L$28252,$A10,Sheet1!$D$5:$D$28252,"房租",Sheet1!$E$5:$E$28252,"<>*调拨*")+SUMIFS(Sheet1!$G$5:$G$28252,Sheet1!$I$5:$I$28252,$B10,Sheet1!$L$5:$L$28252,$A10,Sheet1!$E$5:$E$28252,"*房租*",Sheet1!$E$5:$E$28252,"<>*调拨*",Sheet1!$D$5:$D$28252,"<>内部转款",Sheet1!$D$5:$D$28252,"<>内部转账",Sheet1!$D$5:$D$28252,"<>工资",Sheet1!$D$5:$D$28252,"<>水费",Sheet1!$D$5:$D$28252,"<>电费",Sheet1!$D$5:$D$28252,"<>宽带费",Sheet1!$D$5:$D$28252,"<>办公费",Sheet1!$D$5:$D$28252,"<>话费",Sheet1!$D$5:$D$28252,"<>房租",Sheet1!$E$5:$E$28252,"<>*工资*",Sheet1!$E$5:$E$28252,"<>*水费*",Sheet1!$E$5:$E$28252,"<>*电费*",Sheet1!$E$5:$E$28252,"<>*宽带*",Sheet1!$E$5:$E$28252,"<>*办公*",Sheet1!$E$5:$E$28252,"<>*话费*") -> 0 | AH10: =SUMIFS(Sheet1!$G$5:$G$28252,Sheet1!$I$5:$I$28252,$B10,Sheet1!$L$5:$L$28252,$A10,Sheet1!$E$5:$E$28252,"*调拨*") -> 0 | AI10: =SUMIFS(Sheet1!$G$5:$G$28252,Sheet1!$I$5:$I$28252,$B10,Sheet1!$L$5:$L$28252,$A10,Sheet1!$D$5:$D$28252,"内部转款",Sheet1!$E$5:$E$28252,"<>*调拨*")+SUMIFS(Sheet1!$G$5:$G$28252,Sheet1!$I$5:$I$28252,$B10,Sheet1!$L$5:$L$28252,$A10,Sheet1!$D$5:$D$28252,"内部转账",Sheet1!$E$5:$E$28252,"<>*调拨*") -> 0 | AJ10: =AK10-SUM(AA10:AI10) -> 0 | AK10: =SUMIFS(Sheet1!$G$5:$G$28252,Sheet1!$I$5:$I$28252,$B10,Sheet1!$L$5:$L$28252,$A10) -> 0 | AL10: =Z10-AK10 -> 0
A11: 202512 | B11: 华联五优临城 | C11: =SUMIFS(Sheet1!$F$5:$F$28252,Sheet1!$I$5:$I$28252,$B11,Sheet1!$L$5:$L$28252,$A11,Sheet1!$D$5:$D$28252,"营业款",Sheet1!$E$5:$E$28252,"<>*调拨*",Sheet1!$E$5:$E$28252,"<>*回款*",Sheet1!$E$5:$E$28252,"<>*收款*",Sheet1!$E$5:$E$28252,"<>*医保*",Sheet1!$E$5:$E$28252,"<>*聚合*",Sheet1!$E$5:$E$28252,"<>*24小时微信*",Sheet1!$E$5:$E$28252,"<>*美团*",Sheet1!$E$5:$E$28252,"<>*饿了么*",Sheet1!$E$5:$E$28252,"<>*健E卡*",Sheet1!$E$5:$E$28252,"<>*抖音*",Sheet1!$E$5:$E$28252,"<>*医卡通*",Sheet1!$E$5:$E$28252,"<>*企健网*",Sheet1!$E$5:$E$28252,"<>*银联*",Sheet1!$E$5:$E$28252,"<>*京东*",Sheet1!$E$5:$E$28252,"<>*药机微信*",Sheet1!$E$5:$E$28252,"<>*亲情卡*",Sheet1!$E$5:$E$28252,"<>*优惠券*",Sheet1!$E$5:$E$28252,"<>*代金券*",Sheet1!$E$5:$E$28252,"<>*储值*",Sheet1!$E$5:$E$28252,"<>*效期*") -> 0 | D11: =SUMIFS(Sheet1!$F$5:$F$28252,Sheet1!$I$5:$I$28252,$B11,Sheet1!$L$5:$L$28252,$A11,Sheet1!$D$5:$D$28252,"医保即时拨付",Sheet1!$E$5:$E$28252,"<>*调拨*")+SUMIFS(Sheet1!$F$5:$F$28252,Sheet1!$I$5:$I$28252,$B11,Sheet1!$L$5:$L$28252,$A11,Sheet1!$E$5:$E$28252,"*医保即时拨付*",Sheet1!$D$5:$D$28252,"<>医保即时拨付",Sheet1!$D$5:$D$28252,"<>内部转款",Sheet1!$D$5:$D$28252,"<>内部转账",Sheet1!$E$5:$E$28252,"<>*调拨*") -> 0 | E11: =SUMIFS(Sheet1!$F$5:$F$28252,Sheet1!$I$5:$I$28252,$B11,Sheet1!$L$5:$L$28252,$A11,Sheet1!$D$5:$D$28252,"医保",Sheet1!$E$5:$E$28252,"<>*调拨*",Sheet1!$E$5:$E$28252,"<>*医保即时拨付*")+SUMIFS(Sheet1!$F$5:$F$28252,Sheet1!$I$5:$I$28252,$B11,Sheet1!$L$5:$L$28252,$A11,Sheet1!$E$5:$E$28252,"*医保*",Sheet1!$D$5:$D$28252,"<>医保",Sheet1!$D$5:$D$28252,"<>医保即时拨付",Sheet1!$D$5:$D$28252,"<>内部转款",Sheet1!$D$5:$D$28252,"<>内部转账",Sheet1!$E$5:$E$28252,"<>*医保即时拨付*",Sheet1!$E$5:$E$28252,"<>*调拨*") -> 0 | F11: =SUMIFS(Sheet1!$F$5:$F$28252,Sheet1!$I$5:$I$28252,$B11,Sheet1!$L$5:$L$28252,$A11,Sheet1!$D$5:$D$28252,"聚合",Sheet1!$E$5:$E$28252,"<>*调拨*")+SUMIFS(Sheet1!$F$5:$F$28252,Sheet1!$I$5:$I$28252,$B11,Sheet1!$L$5:$L$28252,$A11,Sheet1!$E$5:$E$28252,"*聚合*",Sheet1!$D$5:$D$28252,"<>聚合",Sheet1!$D$5:$D$28252,"<>内部转款",Sheet1!$D$5:$D$28252,"<>内部转账",Sheet1!$E$5:$E$28252,"<>*调拨*") -> 0 | G11: =SUMIFS(Sheet1!$F$5:$F$28252,Sheet1!$I$5:$I$28252,$B11,Sheet1!$L$5:$L$28252,$A11,Sheet1!$D$5:$D$28252,"24小时微信",Sheet1!$E$5:$E$28252,"<>*调拨*")+SUMIFS(Sheet1!$F$5:$F$28252,Sheet1!$I$5:$I$28252,$B11,Sheet1!$L$5:$L$28252,$A11,Sheet1!$E$5:$E$28252,"*24小时微信*",Sheet1!$D$5:$D$28252,"<>24小时微信",Sheet1!$D$5:$D$28252,"<>内部转款",Sheet1!$D$5:$D$28252,"<>内部转账",Sheet1!$E$5:$E$28252,"<>*调拨*") -> 0 | H11: =SUMIFS(Sheet1!$F$5:$F$28252,Sheet1!$I$5:$I$28252,$B11,Sheet1!$L$5:$L$28252,$A11,Sheet1!$D$5:$D$28252,"美团",Sheet1!$E$5:$E$28252,"<>*调拨*")+SUMIFS(Sheet1!$F$5:$F$28252,Sheet1!$I$5:$I$28252,$B11,Sheet1!$L$5:$L$28252,$A11,Sheet1!$E$5:$E$28252,"*美团*",Sheet1!$D$5:$D$28252,"<>美团",Sheet1!$D$5:$D$28252,"<>内部转款",Sheet1!$D$5:$D$28252,"<>内部转账",Sheet1!$E$5:$E$28252,"<>*调拨*") -> 0 | I11: =SUMIFS(Sheet1!$F$5:$F$28252,Sheet1!$I$5:$I$28252,$B11,Sheet1!$L$5:$L$28252,$A11,Sheet1!$D$5:$D$28252,"饿了么",Sheet1!$E$5:$E$28252,"<>*调拨*")+SUMIFS(Sheet1!$F$5:$F$28252,Sheet1!$I$5:$I$28252,$B11,Sheet1!$L$5:$L$28252,$A11,Sheet1!$E$5:$E$28252,"*饿了么*",Sheet1!$D$5:$D$28252,"<>饿了么",Sheet1!$D$5:$D$28252,"<>内部转款",Sheet1!$D$5:$D$28252,"<>内部转账",Sheet1!$E$5:$E$28252,"<>*调拨*") -> 0 | J11: =SUMIFS(Sheet1!$F$5:$F$28252,Sheet1!$I$5:$I$28252,$B11,Sheet1!$L$5:$L$28252,$A11,Sheet1!$D$5:$D$28252,"健E卡",Sheet1!$E$5:$E$28252,"<>*调拨*")+SUMIFS(Sheet1!$F$5:$F$28252,Sheet1!$I$5:$I$28252,$B11,Sheet1!$L$5:$L$28252,$A11,Sheet1!$E$5:$E$28252,"*健E卡*",Sheet1!$D$5:$D$28252,"<>健E卡",Sheet1!$D$5:$D$28252,"<>内部转款",Sheet1!$D$5:$D$28252,"<>内部转账",Sheet1!$E$5:$E$28252,"<>*调拨*") -> 0 | K11: =SUMIFS(Sheet1!$F$5:$F$28252,Sheet1!$I$5:$I$28252,$B11,Sheet1!$L$5:$L$28252,$A11,Sheet1!$D$5:$D$28252,"抖音",Sheet1!$E$5:$E$28252,"<>*调拨*")+SUMIFS(Sheet1!$F$5:$F$28252,Sheet1!$I$5:$I$28252,$B11,Sheet1!$L$5:$L$28252,$A11,Sheet1!$E$5:$E$28252,"*抖音*",Sheet1!$D$5:$D$28252,"<>抖音",Sheet1!$D$5:$D$28252,"<>内部转款",Sheet1!$D$5:$D$28252,"<>内部转账",Sheet1!$E$5:$E$28252,"<>*调拨*") -> 0 | L11: =SUMIFS(Sheet1!$F$5:$F$28252,Sheet1!$I$5:$I$28252,$B11,Sheet1!$L$5:$L$28252,$A11,Sheet1!$D$5:$D$28252,"医卡通",Sheet1!$E$5:$E$28252,"<>*调拨*")+SUMIFS(Sheet1!$F$5:$F$28252,Sheet1!$I$5:$I$28252,$B11,Sheet1!$L$5:$L$28252,$A11,Sheet1!$E$5:$E$28252,"*医卡通*",Sheet1!$D$5:$D$28252,"<>医卡通",Sheet1!$D$5:$D$28252,"<>内部转款",Sheet1!$D$5:$D$28252,"<>内部转账",Sheet1!$E$5:$E$28252,"<>*调拨*") -> 0 | M11: =SUMIFS(Sheet1!$F$5:$F$28252,Sheet1!$I$5:$I$28252,$B11,Sheet1!$L$5:$L$28252,$A11,Sheet1!$D$5:$D$28252,"企健网",Sheet1!$E$5:$E$28252,"<>*调拨*")+SUMIFS(Sheet1!$F$5:$F$28252,Sheet1!$I$5:$I$28252,$B11,Sheet1!$L$5:$L$28252,$A11,Sheet1!$E$5:$E$28252,"*企健网*",Sheet1!$D$5:$D$28252,"<>企健网",Sheet1!$D$5:$D$28252,"<>内部转款",Sheet1!$D$5:$D$28252,"<>内部转账",Sheet1!$E$5:$E$28252,"<>*调拨*") -> 0 | N11: =SUMIFS(Sheet1!$F$5:$F$28252,Sheet1!$I$5:$I$28252,$B11,Sheet1!$L$5:$L$28252,$A11,Sheet1!$D$5:$D$28252,"银联",Sheet1!$E$5:$E$28252,"<>*调拨*")+SUMIFS(Sheet1!$F$5:$F$28252,Sheet1!$I$5:$I$28252,$B11,Sheet1!$L$5:$L$28252,$A11,Sheet1!$E$5:$E$28252,"*银联*",Sheet1!$D$5:$D$28252,"<>银联",Sheet1!$D$5:$D$28252,"<>内部转款",Sheet1!$D$5:$D$28252,"<>内部转账",Sheet1!$E$5:$E$28252,"<>*调拨*") -> 0 | O11: =SUMIFS(Sheet1!$F$5:$F$28252,Sheet1!$I$5:$I$28252,$B11,Sheet1!$L$5:$L$28252,$A11,Sheet1!$D$5:$D$28252,"京东",Sheet1!$E$5:$E$28252,"<>*调拨*")+SUMIFS(Sheet1!$F$5:$F$28252,Sheet1!$I$5:$I$28252,$B11,Sheet1!$L$5:$L$28252,$A11,Sheet1!$E$5:$E$28252,"*京东*",Sheet1!$D$5:$D$28252,"<>京东",Sheet1!$D$5:$D$28252,"<>内部转款",Sheet1!$D$5:$D$28252,"<>内部转账",Sheet1!$E$5:$E$28252,"<>*调拨*") -> 0 | P11: =SUMIFS(Sheet1!$F$5:$F$28252,Sheet1!$I$5:$I$28252,$B11,Sheet1!$L$5:$L$28252,$A11,Sheet1!$D$5:$D$28252,"药机微信",Sheet1!$E$5:$E$28252,"<>*调拨*")+SUMIFS(Sheet1!$F$5:$F$28252,Sheet1!$I$5:$I$28252,$B11,Sheet1!$L$5:$L$28252,$A11,Sheet1!$E$5:$E$28252,"*药机微信*",Sheet1!$D$5:$D$28252,"<>药机微信",Sheet1!$D$5:$D$28252,"<>内部转款",Sheet1!$D$5:$D$28252,"<>内部转账",Sheet1!$E$5:$E$28252,"<>*调拨*") -> 0 | Q11: =SUMIFS(Sheet1!$F$5:$F$28252,Sheet1!$I$5:$I$28252,$B11,Sheet1!$L$5:$L$28252,$A11,Sheet1!$D$5:$D$28252,"亲情卡",Sheet1!$E$5:$E$28252,"<>*调拨*")+SUMIFS(Sheet1!$F$5:$F$28252,Sheet1!$I$5:$I$28252,$B11,Sheet1!$L$5:$L$28252,$A11,Sheet1!$E$5:$E$28252,"*亲情卡*",Sheet1!$D$5:$D$28252,"<>亲情卡",Sheet1!$D$5:$D$28252,"<>内部转款",Sheet1!$D$5:$D$28252,"<>内部转账",Sheet1!$E$5:$E$28252,"<>*调拨*") -> 0 | R11: =SUMIFS(Sheet1!$F$5:$F$28252,Sheet1!$I$5:$I$28252,$B11,Sheet1!$L$5:$L$28252,$A11,Sheet1!$D$5:$D$28252,"优惠券",Sheet1!$E$5:$E$28252,"<>*调拨*")+SUMIFS(Sheet1!$F$5:$F$28252,Sheet1!$I$5:$I$28252,$B11,Sheet1!$L$5:$L$28252,$A11,Sheet1!$E$5:$E$28252,"*优惠券*",Sheet1!$D$5:$D$28252,"<>优惠券",Sheet1!$D$5:$D$28252,"<>内部转款",Sheet1!$D$5:$D$28252,"<>内部转账",Sheet1!$E$5:$E$28252,"<>*调拨*") -> 0 | S11: =SUMIFS(Sheet1!$F$5:$F$28252,Sheet1!$I$5:$I$28252,$B11,Sheet1!$L$5:$L$28252,$A11,Sheet1!$D$5:$D$28252,"代金券",Sheet1!$E$5:$E$28252,"<>*调拨*")+SUMIFS(Sheet1!$F$5:$F$28252,Sheet1!$I$5:$I$28252,$B11,Sheet1!$L$5:$L$28252,$A11,Sheet1!$E$5:$E$28252,"*代金券*",Sheet1!$D$5:$D$28252,"<>代金券",Sheet1!$D$5:$D$28252,"<>内部转款",Sheet1!$D$5:$D$28252,"<>内部转账",Sheet1!$E$5:$E$28252,"<>*调拨*") -> 0 | T11: =SUMIFS(Sheet1!$F$5:$F$28252,Sheet1!$I$5:$I$28252,$B11,Sheet1!$L$5:$L$28252,$A11,Sheet1!$D$5:$D$28252,"回款",Sheet1!$E$5:$E$28252,"<>*调拨*",Sheet1!$E$5:$E$28252,"<>*医保*",Sheet1!$E$5:$E$28252,"<>*聚合*",Sheet1!$E$5:$E$28252,"<>*24小时微信*",Sheet1!$E$5:$E$28252,"<>*美团*",Sheet1!$E$5:$E$28252,"<>*饿了么*",Sheet1!$E$5:$E$28252,"<>*健E卡*",Sheet1!$E$5:$E$28252,"<>*抖音*",Sheet1!$E$5:$E$28252,"<>*医卡通*",Sheet1!$E$5:$E$28252,"<>*企健网*",Sheet1!$E$5:$E$28252,"<>*银联*",Sheet1!$E$5:$E$28252,"<>*京东*",Sheet1!$E$5:$E$28252,"<>*药机微信*",Sheet1!$E$5:$E$28252,"<>*亲情卡*",Sheet1!$E$5:$E$28252,"<>*优惠券*",Sheet1!$E$5:$E$28252,"<>*代金券*",Sheet1!$E$5:$E$28252,"<>*储值*",Sheet1!$E$5:$E$28252,"<>*效期*")+SUMIFS(Sheet1!$F$5:$F$28252,Sheet1!$I$5:$I$28252,$B11,Sheet1!$L$5:$L$28252,$A11,Sheet1!$D$5:$D$28252,"收款",Sheet1!$E$5:$E$28252,"<>*调拨*",Sheet1!$E$5:$E$28252,"<>*医保*",Sheet1!$E$5:$E$28252,"<>*聚合*",Sheet1!$E$5:$E$28252,"<>*24小时微信*",Sheet1!$E$5:$E$28252,"<>*美团*",Sheet1!$E$5:$E$28252,"<>*饿了么*",Sheet1!$E$5:$E$28252,"<>*健E卡*",Sheet1!$E$5:$E$28252,"<>*抖音*",Sheet1!$E$5:$E$28252,"<>*医卡通*",Sheet1!$E$5:$E$28252,"<>*企健网*",Sheet1!$E$5:$E$28252,"<>*银联*",Sheet1!$E$5:$E$28252,"<>*京东*",Sheet1!$E$5:$E$28252,"<>*药机微信*",Sheet1!$E$5:$E$28252,"<>*亲情卡*",Sheet1!$E$5:$E$28252,"<>*优惠券*",Sheet1!$E$5:$E$28252,"<>*代金券*",Sheet1!$E$5:$E$28252,"<>*储值*",Sheet1!$E$5:$E$28252,"<>*效期*")+SUMIFS(Sheet1!$F$5:$F$28252,Sheet1!$I$5:$I$28252,$B11,Sheet1!$L$5:$L$28252,$A11,Sheet1!$E$5:$E$28252,"*回款*",Sheet1!$D$5:$D$28252,"<>回款",Sheet1!$D$5:$D$28252,"<>收款",Sheet1!$D$5:$D$28252,"<>内部转款",Sheet1!$D$5:$D$28252,"<>内部转账",Sheet1!$E$5:$E$28252,"<>*调拨*",Sheet1!$E$5:$E$28252,"<>*医保*",Sheet1!$E$5:$E$28252,"<>*聚合*",Sheet1!$E$5:$E$28252,"<>*24小时微信*",Sheet1!$E$5:$E$28252,"<>*美团*",Sheet1!$E$5:$E$28252,"<>*饿了么*",Sheet1!$E$5:$E$28252,"<>*健E卡*",Sheet1!$E$5:$E$28252,"<>*抖音*",Sheet1!$E$5:$E$28252,"<>*医卡通*",Sheet1!$E$5:$E$28252,"<>*企健网*",Sheet1!$E$5:$E$28252,"<>*银联*",Sheet1!$E$5:$E$28252,"<>*京东*",Sheet1!$E$5:$E$28252,"<>*药机微信*",Sheet1!$E$5:$E$28252,"<>*亲情卡*",Sheet1!$E$5:$E$28252,"<>*优惠券*",Sheet1!$E$5:$E$28252,"<>*代金券*",Sheet1!$E$5:$E$28252,"<>*储值*",Sheet1!$E$5:$E$28252,"<>*效期*")+SUMIFS(Sheet1!$F$5:$F$28252,Sheet1!$I$5:$I$28252,$B11,Sheet1!$L$5:$L$28252,$A11,Sheet1!$E$5:$E$28252,"*收款*",Sheet1!$E$5:$E$28252,"<>*回款*",Sheet1!$D$5:$D$28252,"<>回款",Sheet1!$D$5:$D$28252,"<>收款",Sheet1!$D$5:$D$28252,"<>内部转款",Sheet1!$D$5:$D$28252,"<>内部转账",Sheet1!$E$5:$E$28252,"<>*调拨*",Sheet1!$E$5:$E$28252,"<>*医保*",Sheet1!$E$5:$E$28252,"<>*聚合*",Sheet1!$E$5:$E$28252,"<>*24小时微信*",Sheet1!$E$5:$E$28252,"<>*美团*",Sheet1!$E$5:$E$28252,"<>*饿了么*",Sheet1!$E$5:$E$28252,"<>*健E卡*",Sheet1!$E$5:$E$28252,"<>*抖音*",Sheet1!$E$5:$E$28252,"<>*医卡通*",Sheet1!$E$5:$E$28252,"<>*企健网*",Sheet1!$E$5:$E$28252,"<>*银联*",Sheet1!$E$5:$E$28252,"<>*京东*",Sheet1!$E$5:$E$28252,"<>*药机微信*",Sheet1!$E$5:$E$28252,"<>*亲情卡*",Sheet1!$E$5:$E$28252,"<>*优惠券*",Sheet1!$E$5:$E$28252,"<>*代金券*",Sheet1!$E$5:$E$28252,"<>*储值*",Sheet1!$E$5:$E$28252,"<>*效期*") -> 0 | U11: =SUMIFS(Sheet1!$F$5:$F$28252,Sheet1!$I$5:$I$28252,$B11,Sheet1!$L$5:$L$28252,$A11,Sheet1!$E$5:$E$28252,"*调拨*") -> 0 | V11: =SUMIFS(Sheet1!$F$5:$F$28252,Sheet1!$I$5:$I$28252,$B11,Sheet1!$L$5:$L$28252,$A11,Sheet1!$D$5:$D$28252,"储值",Sheet1!$E$5:$E$28252,"<>*调拨*")+SUMIFS(Sheet1!$F$5:$F$28252,Sheet1!$I$5:$I$28252,$B11,Sheet1!$L$5:$L$28252,$A11,Sheet1!$E$5:$E$28252,"*储值*",Sheet1!$D$5:$D$28252,"<>储值",Sheet1!$D$5:$D$28252,"<>内部转款",Sheet1!$D$5:$D$28252,"<>内部转账",Sheet1!$E$5:$E$28252,"<>*调拨*") -> 0 | W11: =SUMIFS(Sheet1!$F$5:$F$28252,Sheet1!$I$5:$I$28252,$B11,Sheet1!$L$5:$L$28252,$A11,Sheet1!$D$5:$D$28252,"效期",Sheet1!$E$5:$E$28252,"<>*调拨*")+SUMIFS(Sheet1!$F$5:$F$28252,Sheet1!$I$5:$I$28252,$B11,Sheet1!$L$5:$L$28252,$A11,Sheet1!$E$5:$E$28252,"*效期*",Sheet1!$D$5:$D$28252,"<>效期",Sheet1!$D$5:$D$28252,"<>内部转款",Sheet1!$D$5:$D$28252,"<>内部转账",Sheet1!$E$5:$E$28252,"<>*调拨*") -> 0 | X11: =SUMIFS(Sheet1!$F$5:$F$28252,Sheet1!$I$5:$I$28252,$B11,Sheet1!$L$5:$L$28252,$A11,Sheet1!$D$5:$D$28252,"内部转款",Sheet1!$E$5:$E$28252,"<>*调拨*")+SUMIFS(Sheet1!$F$5:$F$28252,Sheet1!$I$5:$I$28252,$B11,Sheet1!$L$5:$L$28252,$A11,Sheet1!$D$5:$D$28252,"内部转账",Sheet1!$E$5:$E$28252,"<>*调拨*") -> 0 | Y11: =Z11-SUM(C11:X11) -> 0 | Z11: =SUMIFS(Sheet1!$F$5:$F$28252,Sheet1!$I$5:$I$28252,$B11,Sheet1!$L$5:$L$28252,$A11) -> 0 | AA11: =SUMIFS(Sheet1!$G$5:$G$28252,Sheet1!$I$5:$I$28252,$B11,Sheet1!$L$5:$L$28252,$A11,Sheet1!$D$5:$D$28252,"工资",Sheet1!$E$5:$E$28252,"<>*调拨*")+SUMIFS(Sheet1!$G$5:$G$28252,Sheet1!$I$5:$I$28252,$B11,Sheet1!$L$5:$L$28252,$A11,Sheet1!$E$5:$E$28252,"*工资*",Sheet1!$E$5:$E$28252,"<>*调拨*",Sheet1!$D$5:$D$28252,"<>内部转款",Sheet1!$D$5:$D$28252,"<>内部转账",Sheet1!$D$5:$D$28252,"<>工资",Sheet1!$D$5:$D$28252,"<>水费",Sheet1!$D$5:$D$28252,"<>电费",Sheet1!$D$5:$D$28252,"<>宽带费",Sheet1!$D$5:$D$28252,"<>办公费",Sheet1!$D$5:$D$28252,"<>话费",Sheet1!$D$5:$D$28252,"<>房租") -> 0 | AB11: =SUMIFS(Sheet1!$G$5:$G$28252,Sheet1!$I$5:$I$28252,$B11,Sheet1!$L$5:$L$28252,$A11,Sheet1!$D$5:$D$28252,"水费",Sheet1!$E$5:$E$28252,"<>*调拨*")+SUMIFS(Sheet1!$G$5:$G$28252,Sheet1!$I$5:$I$28252,$B11,Sheet1!$L$5:$L$28252,$A11,Sheet1!$E$5:$E$28252,"*水费*",Sheet1!$E$5:$E$28252,"<>*调拨*",Sheet1!$D$5:$D$28252,"<>内部转款",Sheet1!$D$5:$D$28252,"<>内部转账",Sheet1!$D$5:$D$28252,"<>工资",Sheet1!$D$5:$D$28252,"<>水费",Sheet1!$D$5:$D$28252,"<>电费",Sheet1!$D$5:$D$28252,"<>宽带费",Sheet1!$D$5:$D$28252,"<>办公费",Sheet1!$D$5:$D$28252,"<>话费",Sheet1!$D$5:$D$28252,"<>房租",Sheet1!$E$5:$E$28252,"<>*工资*") -> 0 | AC11: =SUMIFS(Sheet1!$G$5:$G$28252,Sheet1!$I$5:$I$28252,$B11,Sheet1!$L$5:$L$28252,$A11,Sheet1!$D$5:$D$28252,"电费",Sheet1!$E$5:$E$28252,"<>*调拨*")+SUMIFS(Sheet1!$G$5:$G$28252,Sheet1!$I$5:$I$28252,$B11,Sheet1!$L$5:$L$28252,$A11,Sheet1!$E$5:$E$28252,"*电费*",Sheet1!$E$5:$E$28252,"<>*调拨*",Sheet1!$D$5:$D$28252,"<>内部转款",Sheet1!$D$5:$D$28252,"<>内部转账",Sheet1!$D$5:$D$28252,"<>工资",Sheet1!$D$5:$D$28252,"<>水费",Sheet1!$D$5:$D$28252,"<>电费",Sheet1!$D$5:$D$28252,"<>宽带费",Sheet1!$D$5:$D$28252,"<>办公费",Sheet1!$D$5:$D$28252,"<>话费",Sheet1!$D$5:$D$28252,"<>房租",Sheet1!$E$5:$E$28252,"<>*工资*",Sheet1!$E$5:$E$28252,"<>*水费*") -> 0 | AD11: =SUMIFS(Sheet1!$G$5:$G$28252,Sheet1!$I$5:$I$28252,$B11,Sheet1!$L$5:$L$28252,$A11,Sheet1!$D$5:$D$28252,"宽带费",Sheet1!$E$5:$E$28252,"<>*调拨*")+SUMIFS(Sheet1!$G$5:$G$28252,Sheet1!$I$5:$I$28252,$B11,Sheet1!$L$5:$L$28252,$A11,Sheet1!$E$5:$E$28252,"*宽带*",Sheet1!$E$5:$E$28252,"<>*调拨*",Sheet1!$D$5:$D$28252,"<>内部转款",Sheet1!$D$5:$D$28252,"<>内部转账",Sheet1!$D$5:$D$28252,"<>工资",Sheet1!$D$5:$D$28252,"<>水费",Sheet1!$D$5:$D$28252,"<>电费",Sheet1!$D$5:$D$28252,"<>宽带费",Sheet1!$D$5:$D$28252,"<>办公费",Sheet1!$D$5:$D$28252,"<>话费",Sheet1!$D$5:$D$28252,"<>房租",Sheet1!$E$5:$E$28252,"<>*工资*",Sheet1!$E$5:$E$28252,"<>*水费*",Sheet1!$E$5:$E$28252,"<>*电费*") -> 0 | AE11: =SUMIFS(Sheet1!$G$5:$G$28252,Sheet1!$I$5:$I$28252,$B11,Sheet1!$L$5:$L$28252,$A11,Sheet1!$D$5:$D$28252,"办公费",Sheet1!$E$5:$E$28252,"<>*调拨*")+SUMIFS(Sheet1!$G$5:$G$28252,Sheet1!$I$5:$I$28252,$B11,Sheet1!$L$5:$L$28252,$A11,Sheet1!$E$5:$E$28252,"*办公*",Sheet1!$E$5:$E$28252,"<>*调拨*",Sheet1!$D$5:$D$28252,"<>内部转款",Sheet1!$D$5:$D$28252,"<>内部转账",Sheet1!$D$5:$D$28252,"<>工资",Sheet1!$D$5:$D$28252,"<>水费",Sheet1!$D$5:$D$28252,"<>电费",Sheet1!$D$5:$D$28252,"<>宽带费",Sheet1!$D$5:$D$28252,"<>办公费",Sheet1!$D$5:$D$28252,"<>话费",Sheet1!$D$5:$D$28252,"<>房租",Sheet1!$E$5:$E$28252,"<>*工资*",Sheet1!$E$5:$E$28252,"<>*水费*",Sheet1!$E$5:$E$28252,"<>*电费*",Sheet1!$E$5:$E$28252,"<>*宽带*") -> 0 | AF11: =SUMIFS(Sheet1!$G$5:$G$28252,Sheet1!$I$5:$I$28252,$B11,Sheet1!$L$5:$L$28252,$A11,Sheet1!$D$5:$D$28252,"话费",Sheet1!$E$5:$E$28252,"<>*调拨*")+SUMIFS(Sheet1!$G$5:$G$28252,Sheet1!$I$5:$I$28252,$B11,Sheet1!$L$5:$L$28252,$A11,Sheet1!$E$5:$E$28252,"*话费*",Sheet1!$E$5:$E$28252,"<>*调拨*",Sheet1!$D$5:$D$28252,"<>内部转款",Sheet1!$D$5:$D$28252,"<>内部转账",Sheet1!$D$5:$D$28252,"<>工资",Sheet1!$D$5:$D$28252,"<>水费",Sheet1!$D$5:$D$28252,"<>电费",Sheet1!$D$5:$D$28252,"<>宽带费",Sheet1!$D$5:$D$28252,"<>办公费",Sheet1!$D$5:$D$28252,"<>话费",Sheet1!$D$5:$D$28252,"<>房租",Sheet1!$E$5:$E$28252,"<>*工资*",Sheet1!$E$5:$E$28252,"<>*水费*",Sheet1!$E$5:$E$28252,"<>*电费*",Sheet1!$E$5:$E$28252,"<>*宽带*",Sheet1!$E$5:$E$28252,"<>*办公*") -> 0 | AG11: =SUMIFS(Sheet1!$G$5:$G$28252,Sheet1!$I$5:$I$28252,$B11,Sheet1!$L$5:$L$28252,$A11,Sheet1!$D$5:$D$28252,"房租",Sheet1!$E$5:$E$28252,"<>*调拨*")+SUMIFS(Sheet1!$G$5:$G$28252,Sheet1!$I$5:$I$28252,$B11,Sheet1!$L$5:$L$28252,$A11,Sheet1!$E$5:$E$28252,"*房租*",Sheet1!$E$5:$E$28252,"<>*调拨*",Sheet1!$D$5:$D$28252,"<>内部转款",Sheet1!$D$5:$D$28252,"<>内部转账",Sheet1!$D$5:$D$28252,"<>工资",Sheet1!$D$5:$D$28252,"<>水费",Sheet1!$D$5:$D$28252,"<>电费",Sheet1!$D$5:$D$28252,"<>宽带费",Sheet1!$D$5:$D$28252,"<>办公费",Sheet1!$D$5:$D$28252,"<>话费",Sheet1!$D$5:$D$28252,"<>房租",Sheet1!$E$5:$E$28252,"<>*工资*",Sheet1!$E$5:$E$28252,"<>*水费*",Sheet1!$E$5:$E$28252,"<>*电费*",Sheet1!$E$5:$E$28252,"<>*宽带*",Sheet1!$E$5:$E$28252,"<>*办公*",Sheet1!$E$5:$E$28252,"<>*话费*") -> 0 | AH11: =SUMIFS(Sheet1!$G$5:$G$28252,Sheet1!$I$5:$I$28252,$B11,Sheet1!$L$5:$L$28252,$A11,Sheet1!$E$5:$E$28252,"*调拨*") -> 0 | AI11: =SUMIFS(Sheet1!$G$5:$G$28252,Sheet1!$I$5:$I$28252,$B11,Sheet1!$L$5:$L$28252,$A11,Sheet1!$D$5:$D$28252,"内部转款",Sheet1!$E$5:$E$28252,"<>*调拨*")+SUMIFS(Sheet1!$G$5:$G$28252,Sheet1!$I$5:$I$28252,$B11,Sheet1!$L$5:$L$28252,$A11,Sheet1!$D$5:$D$28252,"内部转账",Sheet1!$E$5:$E$28252,"<>*调拨*") -> 0 | AJ11: =AK11-SUM(AA11:AI11) -> 0 | AK11: =SUMIFS(Sheet1!$G$5:$G$28252,Sheet1!$I$5:$I$28252,$B11,Sheet1!$L$5:$L$28252,$A11) -> 0 | AL11: =Z11-AK11 -> 0
A12: 202512 | B12: 华联五优康庄路 | C12: =SUMIFS(Sheet1!$F$5:$F$28252,Sheet1!$I$5:$I$28252,$B12,Sheet1!$L$5:$L$28252,$A12,Sheet1!$D$5:$D$28252,"营业款",Sheet1!$E$5:$E$28252,"<>*调拨*",Sheet1!$E$5:$E$28252,"<>*回款*",Sheet1!$E$5:$E$28252,"<>*收款*",Sheet1!$E$5:$E$28252,"<>*医保*",Sheet1!$E$5:$E$28252,"<>*聚合*",Sheet1!$E$5:$E$28252,"<>*24小时微信*",Sheet1!$E$5:$E$28252,"<>*美团*",Sheet1!$E$5:$E$28252,"<>*饿了么*",Sheet1!$E$5:$E$28252,"<>*健E卡*",Sheet1!$E$5:$E$28252,"<>*抖音*",Sheet1!$E$5:$E$28252,"<>*医卡通*",Sheet1!$E$5:$E$28252,"<>*企健网*",Sheet1!$E$5:$E$28252,"<>*银联*",Sheet1!$E$5:$E$28252,"<>*京东*",Sheet1!$E$5:$E$28252,"<>*药机微信*",Sheet1!$E$5:$E$28252,"<>*亲情卡*",Sheet1!$E$5:$E$28252,"<>*优惠券*",Sheet1!$E$5:$E$28252,"<>*代金券*",Sheet1!$E$5:$E$28252,"<>*储值*",Sheet1!$E$5:$E$28252,"<>*效期*") -> 0 | D12: =SUMIFS(Sheet1!$F$5:$F$28252,Sheet1!$I$5:$I$28252,$B12,Sheet1!$L$5:$L$28252,$A12,Sheet1!$D$5:$D$28252,"医保即时拨付",Sheet1!$E$5:$E$28252,"<>*调拨*")+SUMIFS(Sheet1!$F$5:$F$28252,Sheet1!$I$5:$I$28252,$B12,Sheet1!$L$5:$L$28252,$A12,Sheet1!$E$5:$E$28252,"*医保即时拨付*",Sheet1!$D$5:$D$28252,"<>医保即时拨付",Sheet1!$D$5:$D$28252,"<>内部转款",Sheet1!$D$5:$D$28252,"<>内部转账",Sheet1!$E$5:$E$28252,"<>*调拨*") -> 0 | E12: =SUMIFS(Sheet1!$F$5:$F$28252,Sheet1!$I$5:$I$28252,$B12,Sheet1!$L$5:$L$28252,$A12,Sheet1!$D$5:$D$28252,"医保",Sheet1!$E$5:$E$28252,"<>*调拨*",Sheet1!$E$5:$E$28252,"<>*医保即时拨付*")+SUMIFS(Sheet1!$F$5:$F$28252,Sheet1!$I$5:$I$28252,$B12,Sheet1!$L$5:$L$28252,$A12,Sheet1!$E$5:$E$28252,"*医保*",Sheet1!$D$5:$D$28252,"<>医保",Sheet1!$D$5:$D$28252,"<>医保即时拨付",Sheet1!$D$5:$D$28252,"<>内部转款",Sheet1!$D$5:$D$28252,"<>内部转账",Sheet1!$E$5:$E$28252,"<>*医保即时拨付*",Sheet1!$E$5:$E$28252,"<>*调拨*") -> 0 | F12: =SUMIFS(Sheet1!$F$5:$F$28252,Sheet1!$I$5:$I$28252,$B12,Sheet1!$L$5:$L$28252,$A12,Sheet1!$D$5:$D$28252,"聚合",Sheet1!$E$5:$E$28252,"<>*调拨*")+SUMIFS(Sheet1!$F$5:$F$28252,Sheet1!$I$5:$I$28252,$B12,Sheet1!$L$5:$L$28252,$A12,Sheet1!$E$5:$E$28252,"*聚合*",Sheet1!$D$5:$D$28252,"<>聚合",Sheet1!$D$5:$D$28252,"<>内部转款",Sheet1!$D$5:$D$28252,"<>内部转账",Sheet1!$E$5:$E$28252,"<>*调拨*") -> 0 | G12: =SUMIFS(Sheet1!$F$5:$F$28252,Sheet1!$I$5:$I$28252,$B12,Sheet1!$L$5:$L$28252,$A12,Sheet1!$D$5:$D$28252,"24小时微信",Sheet1!$E$5:$E$28252,"<>*调拨*")+SUMIFS(Sheet1!$F$5:$F$28252,Sheet1!$I$5:$I$28252,$B12,Sheet1!$L$5:$L$28252,$A12,Sheet1!$E$5:$E$28252,"*24小时微信*",Sheet1!$D$5:$D$28252,"<>24小时微信",Sheet1!$D$5:$D$28252,"<>内部转款",Sheet1!$D$5:$D$28252,"<>内部转账",Sheet1!$E$5:$E$28252,"<>*调拨*") -> 0 | H12: =SUMIFS(Sheet1!$F$5:$F$28252,Sheet1!$I$5:$I$28252,$B12,Sheet1!$L$5:$L$28252,$A12,Sheet1!$D$5:$D$28252,"美团",Sheet1!$E$5:$E$28252,"<>*调拨*")+SUMIFS(Sheet1!$F$5:$F$28252,Sheet1!$I$5:$I$28252,$B12,Sheet1!$L$5:$L$28252,$A12,Sheet1!$E$5:$E$28252,"*美团*",Sheet1!$D$5:$D$28252,"<>美团",Sheet1!$D$5:$D$28252,"<>内部转款",Sheet1!$D$5:$D$28252,"<>内部转账",Sheet1!$E$5:$E$28252,"<>*调拨*") -> 0 | I12: =SUMIFS(Sheet1!$F$5:$F$28252,Sheet1!$I$5:$I$28252,$B12,Sheet1!$L$5:$L$28252,$A12,Sheet1!$D$5:$D$28252,"饿了么",Sheet1!$E$5:$E$28252,"<>*调拨*")+SUMIFS(Sheet1!$F$5:$F$28252,Sheet1!$I$5:$I$28252,$B12,Sheet1!$L$5:$L$28252,$A12,Sheet1!$E$5:$E$28252,"*饿了么*",Sheet1!$D$5:$D$28252,"<>饿了么",Sheet1!$D$5:$D$28252,"<>内部转款",Sheet1!$D$5:$D$28252,"<>内部转账",Sheet1!$E$5:$E$28252,"<>*调拨*") -> 0 | J12: =SUMIFS(Sheet1!$F$5:$F$28252,Sheet1!$I$5:$I$28252,$B12,Sheet1!$L$5:$L$28252,$A12,Sheet1!$D$5:$D$28252,"健E卡",Sheet1!$E$5:$E$28252,"<>*调拨*")+SUMIFS(Sheet1!$F$5:$F$28252,Sheet1!$I$5:$I$28252,$B12,Sheet1!$L$5:$L$28252,$A12,Sheet1!$E$5:$E$28252,"*健E卡*",Sheet1!$D$5:$D$28252,"<>健E卡",Sheet1!$D$5:$D$28252,"<>内部转款",Sheet1!$D$5:$D$28252,"<>内部转账",Sheet1!$E$5:$E$28252,"<>*调拨*") -> 0 | K12: =SUMIFS(Sheet1!$F$5:$F$28252,Sheet1!$I$5:$I$28252,$B12,Sheet1!$L$5:$L$28252,$A12,Sheet1!$D$5:$D$28252,"抖音",Sheet1!$E$5:$E$28252,"<>*调拨*")+SUMIFS(Sheet1!$F$5:$F$28252,Sheet1!$I$5:$I$28252,$B12,Sheet1!$L$5:$L$28252,$A12,Sheet1!$E$5:$E$28252,"*抖音*",Sheet1!$D$5:$D$28252,"<>抖音",Sheet1!$D$5:$D$28252,"<>内部转款",Sheet1!$D$5:$D$28252,"<>内部转账",Sheet1!$E$5:$E$28252,"<>*调拨*") -> 0 | L12: =SUMIFS(Sheet1!$F$5:$F$28252,Sheet1!$I$5:$I$28252,$B12,Sheet1!$L$5:$L$28252,$A12,Sheet1!$D$5:$D$28252,"医卡通",Sheet1!$E$5:$E$28252,"<>*调拨*")+SUMIFS(Sheet1!$F$5:$F$28252,Sheet1!$I$5:$I$28252,$B12,Sheet1!$L$5:$L$28252,$A12,Sheet1!$E$5:$E$28252,"*医卡通*",Sheet1!$D$5:$D$28252,"<>医卡通",Sheet1!$D$5:$D$28252,"<>内部转款",Sheet1!$D$5:$D$28252,"<>内部转账",Sheet1!$E$5:$E$28252,"<>*调拨*") -> 0 | M12: =SUMIFS(Sheet1!$F$5:$F$28252,Sheet1!$I$5:$I$28252,$B12,Sheet1!$L$5:$L$28252,$A12,Sheet1!$D$5:$D$28252,"企健网",Sheet1!$E$5:$E$28252,"<>*调拨*")+SUMIFS(Sheet1!$F$5:$F$28252,Sheet1!$I$5:$I$28252,$B12,Sheet1!$L$5:$L$28252,$A12,Sheet1!$E$5:$E$28252,"*企健网*",Sheet1!$D$5:$D$28252,"<>企健网",Sheet1!$D$5:$D$28252,"<>内部转款",Sheet1!$D$5:$D$28252,"<>内部转账",Sheet1!$E$5:$E$28252,"<>*调拨*") -> 0 | N12: =SUMIFS(Sheet1!$F$5:$F$28252,Sheet1!$I$5:$I$28252,$B12,Sheet1!$L$5:$L$28252,$A12,Sheet1!$D$5:$D$28252,"银联",Sheet1!$E$5:$E$28252,"<>*调拨*")+SUMIFS(Sheet1!$F$5:$F$28252,Sheet1!$I$5:$I$28252,$B12,Sheet1!$L$5:$L$28252,$A12,Sheet1!$E$5:$E$28252,"*银联*",Sheet1!$D$5:$D$28252,"<>银联",Sheet1!$D$5:$D$28252,"<>内部转款",Sheet1!$D$5:$D$28252,"<>内部转账",Sheet1!$E$5:$E$28252,"<>*调拨*") -> 0 | O12: =SUMIFS(Sheet1!$F$5:$F$28252,Sheet1!$I$5:$I$28252,$B12,Sheet1!$L$5:$L$28252,$A12,Sheet1!$D$5:$D$28252,"京东",Sheet1!$E$5:$E$28252,"<>*调拨*")+SUMIFS(Sheet1!$F$5:$F$28252,Sheet1!$I$5:$I$28252,$B12,Sheet1!$L$5:$L$28252,$A12,Sheet1!$E$5:$E$28252,"*京东*",Sheet1!$D$5:$D$28252,"<>京东",Sheet1!$D$5:$D$28252,"<>内部转款",Sheet1!$D$5:$D$28252,"<>内部转账",Sheet1!$E$5:$E$28252,"<>*调拨*") -> 0 | P12: =SUMIFS(Sheet1!$F$5:$F$28252,Sheet1!$I$5:$I$28252,$B12,Sheet1!$L$5:$L$28252,$A12,Sheet1!$D$5:$D$28252,"药机微信",Sheet1!$E$5:$E$28252,"<>*调拨*")+SUMIFS(Sheet1!$F$5:$F$28252,Sheet1!$I$5:$I$28252,$B12,Sheet1!$L$5:$L$28252,$A12,Sheet1!$E$5:$E$28252,"*药机微信*",Sheet1!$D$5:$D$28252,"<>药机微信",Sheet1!$D$5:$D$28252,"<>内部转款",Sheet1!$D$5:$D$28252,"<>内部转账",Sheet1!$E$5:$E$28252,"<>*调拨*") -> 0 | Q12: =SUMIFS(Sheet1!$F$5:$F$28252,Sheet1!$I$5:$I$28252,$B12,Sheet1!$L$5:$L$28252,$A12,Sheet1!$D$5:$D$28252,"亲情卡",Sheet1!$E$5:$E$28252,"<>*调拨*")+SUMIFS(Sheet1!$F$5:$F$28252,Sheet1!$I$5:$I$28252,$B12,Sheet1!$L$5:$L$28252,$A12,Sheet1!$E$5:$E$28252,"*亲情卡*",Sheet1!$D$5:$D$28252,"<>亲情卡",Sheet1!$D$5:$D$28252,"<>内部转款",Sheet1!$D$5:$D$28252,"<>内部转账",Sheet1!$E$5:$E$28252,"<>*调拨*") -> 0 | R12: =SUMIFS(Sheet1!$F$5:$F$28252,Sheet1!$I$5:$I$28252,$B12,Sheet1!$L$5:$L$28252,$A12,Sheet1!$D$5:$D$28252,"优惠券",Sheet1!$E$5:$E$28252,"<>*调拨*")+SUMIFS(Sheet1!$F$5:$F$28252,Sheet1!$I$5:$I$28252,$B12,Sheet1!$L$5:$L$28252,$A12,Sheet1!$E$5:$E$28252,"*优惠券*",Sheet1!$D$5:$D$28252,"<>优惠券",Sheet1!$D$5:$D$28252,"<>内部转款",Sheet1!$D$5:$D$28252,"<>内部转账",Sheet1!$E$5:$E$28252,"<>*调拨*") -> 0 | S12: =SUMIFS(Sheet1!$F$5:$F$28252,Sheet1!$I$5:$I$28252,$B12,Sheet1!$L$5:$L$28252,$A12,Sheet1!$D$5:$D$28252,"代金券",Sheet1!$E$5:$E$28252,"<>*调拨*")+SUMIFS(Sheet1!$F$5:$F$28252,Sheet1!$I$5:$I$28252,$B12,Sheet1!$L$5:$L$28252,$A12,Sheet1!$E$5:$E$28252,"*代金券*",Sheet1!$D$5:$D$28252,"<>代金券",Sheet1!$D$5:$D$28252,"<>内部转款",Sheet1!$D$5:$D$28252,"<>内部转账",Sheet1!$E$5:$E$28252,"<>*调拨*") -> 0 | T12: =SUMIFS(Sheet1!$F$5:$F$28252,Sheet1!$I$5:$I$28252,$B12,Sheet1!$L$5:$L$28252,$A12,Sheet1!$D$5:$D$28252,"回款",Sheet1!$E$5:$E$28252,"<>*调拨*",Sheet1!$E$5:$E$28252,"<>*医保*",Sheet1!$E$5:$E$28252,"<>*聚合*",Sheet1!$E$5:$E$28252,"<>*24小时微信*",Sheet1!$E$5:$E$28252,"<>*美团*",Sheet1!$E$5:$E$28252,"<>*饿了么*",Sheet1!$E$5:$E$28252,"<>*健E卡*",Sheet1!$E$5:$E$28252,"<>*抖音*",Sheet1!$E$5:$E$28252,"<>*医卡通*",Sheet1!$E$5:$E$28252,"<>*企健网*",Sheet1!$E$5:$E$28252,"<>*银联*",Sheet1!$E$5:$E$28252,"<>*京东*",Sheet1!$E$5:$E$28252,"<>*药机微信*",Sheet1!$E$5:$E$28252,"<>*亲情卡*",Sheet1!$E$5:$E$28252,"<>*优惠券*",Sheet1!$E$5:$E$28252,"<>*代金券*",Sheet1!$E$5:$E$28252,"<>*储值*",Sheet1!$E$5:$E$28252,"<>*效期*")+SUMIFS(Sheet1!$F$5:$F$28252,Sheet1!$I$5:$I$28252,$B12,Sheet1!$L$5:$L$28252,$A12,Sheet1!$D$5:$D$28252,"收款",Sheet1!$E$5:$E$28252,"<>*调拨*",Sheet1!$E$5:$E$28252,"<>*医保*",Sheet1!$E$5:$E$28252,"<>*聚合*",Sheet1!$E$5:$E$28252,"<>*24小时微信*",Sheet1!$E$5:$E$28252,"<>*美团*",Sheet1!$E$5:$E$28252,"<>*饿了么*",Sheet1!$E$5:$E$28252,"<>*健E卡*",Sheet1!$E$5:$E$28252,"<>*抖音*",Sheet1!$E$5:$E$28252,"<>*医卡通*",Sheet1!$E$5:$E$28252,"<>*企健网*",Sheet1!$E$5:$E$28252,"<>*银联*",Sheet1!$E$5:$E$28252,"<>*京东*",Sheet1!$E$5:$E$28252,"<>*药机微信*",Sheet1!$E$5:$E$28252,"<>*亲情卡*",Sheet1!$E$5:$E$28252,"<>*优惠券*",Sheet1!$E$5:$E$28252,"<>*代金券*",Sheet1!$E$5:$E$28252,"<>*储值*",Sheet1!$E$5:$E$28252,"<>*效期*")+SUMIFS(Sheet1!$F$5:$F$28252,Sheet1!$I$5:$I$28252,$B12,Sheet1!$L$5:$L$28252,$A12,Sheet1!$E$5:$E$28252,"*回款*",Sheet1!$D$5:$D$28252,"<>回款",Sheet1!$D$5:$D$28252,"<>收款",Sheet1!$D$5:$D$28252,"<>内部转款",Sheet1!$D$5:$D$28252,"<>内部转账",Sheet1!$E$5:$E$28252,"<>*调拨*",Sheet1!$E$5:$E$28252,"<>*医保*",Sheet1!$E$5:$E$28252,"<>*聚合*",Sheet1!$E$5:$E$28252,"<>*24小时微信*",Sheet1!$E$5:$E$28252,"<>*美团*",Sheet1!$E$5:$E$28252,"<>*饿了么*",Sheet1!$E$5:$E$28252,"<>*健E卡*",Sheet1!$E$5:$E$28252,"<>*抖音*",Sheet1!$E$5:$E$28252,"<>*医卡通*",Sheet1!$E$5:$E$28252,"<>*企健网*",Sheet1!$E$5:$E$28252,"<>*银联*",Sheet1!$E$5:$E$28252,"<>*京东*",Sheet1!$E$5:$E$28252,"<>*药机微信*",Sheet1!$E$5:$E$28252,"<>*亲情卡*",Sheet1!$E$5:$E$28252,"<>*优惠券*",Sheet1!$E$5:$E$28252,"<>*代金券*",Sheet1!$E$5:$E$28252,"<>*储值*",Sheet1!$E$5:$E$28252,"<>*效期*")+SUMIFS(Sheet1!$F$5:$F$28252,Sheet1!$I$5:$I$28252,$B12,Sheet1!$L$5:$L$28252,$A12,Sheet1!$E$5:$E$28252,"*收款*",Sheet1!$E$5:$E$28252,"<>*回款*",Sheet1!$D$5:$D$28252,"<>回款",Sheet1!$D$5:$D$28252,"<>收款",Sheet1!$D$5:$D$28252,"<>内部转款",Sheet1!$D$5:$D$28252,"<>内部转账",Sheet1!$E$5:$E$28252,"<>*调拨*",Sheet1!$E$5:$E$28252,"<>*医保*",Sheet1!$E$5:$E$28252,"<>*聚合*",Sheet1!$E$5:$E$28252,"<>*24小时微信*",Sheet1!$E$5:$E$28252,"<>*美团*",Sheet1!$E$5:$E$28252,"<>*饿了么*",Sheet1!$E$5:$E$28252,"<>*健E卡*",Sheet1!$E$5:$E$28252,"<>*抖音*",Sheet1!$E$5:$E$28252,"<>*医卡通*",Sheet1!$E$5:$E$28252,"<>*企健网*",Sheet1!$E$5:$E$28252,"<>*银联*",Sheet1!$E$5:$E$28252,"<>*京东*",Sheet1!$E$5:$E$28252,"<>*药机微信*",Sheet1!$E$5:$E$28252,"<>*亲情卡*",Sheet1!$E$5:$E$28252,"<>*优惠券*",Sheet1!$E$5:$E$28252,"<>*代金券*",Sheet1!$E$5:$E$28252,"<>*储值*",Sheet1!$E$5:$E$28252,"<>*效期*") -> 0 | U12: =SUMIFS(Sheet1!$F$5:$F$28252,Sheet1!$I$5:$I$28252,$B12,Sheet1!$L$5:$L$28252,$A12,Sheet1!$E$5:$E$28252,"*调拨*") -> 0 | V12: =SUMIFS(Sheet1!$F$5:$F$28252,Sheet1!$I$5:$I$28252,$B12,Sheet1!$L$5:$L$28252,$A12,Sheet1!$D$5:$D$28252,"储值",Sheet1!$E$5:$E$28252,"<>*调拨*")+SUMIFS(Sheet1!$F$5:$F$28252,Sheet1!$I$5:$I$28252,$B12,Sheet1!$L$5:$L$28252,$A12,Sheet1!$E$5:$E$28252,"*储值*",Sheet1!$D$5:$D$28252,"<>储值",Sheet1!$D$5:$D$28252,"<>内部转款",Sheet1!$D$5:$D$28252,"<>内部转账",Sheet1!$E$5:$E$28252,"<>*调拨*") -> 0 | W12: =SUMIFS(Sheet1!$F$5:$F$28252,Sheet1!$I$5:$I$28252,$B12,Sheet1!$L$5:$L$28252,$A12,Sheet1!$D$5:$D$28252,"效期",Sheet1!$E$5:$E$28252,"<>*调拨*")+SUMIFS(Sheet1!$F$5:$F$28252,Sheet1!$I$5:$I$28252,$B12,Sheet1!$L$5:$L$28252,$A12,Sheet1!$E$5:$E$28252,"*效期*",Sheet1!$D$5:$D$28252,"<>效期",Sheet1!$D$5:$D$28252,"<>内部转款",Sheet1!$D$5:$D$28252,"<>内部转账",Sheet1!$E$5:$E$28252,"<>*调拨*") -> 0 | X12: =SUMIFS(Sheet1!$F$5:$F$28252,Sheet1!$I$5:$I$28252,$B12,Sheet1!$L$5:$L$28252,$A12,Sheet1!$D$5:$D$28252,"内部转款",Sheet1!$E$5:$E$28252,"<>*调拨*")+SUMIFS(Sheet1!$F$5:$F$28252,Sheet1!$I$5:$I$28252,$B12,Sheet1!$L$5:$L$28252,$A12,Sheet1!$D$5:$D$28252,"内部转账",Sheet1!$E$5:$E$28252,"<>*调拨*") -> 0 | Y12: =Z12-SUM(C12:X12) -> 0 | Z12: =SUMIFS(Sheet1!$F$5:$F$28252,Sheet1!$I$5:$I$28252,$B12,Sheet1!$L$5:$L$28252,$A12) -> 0 | AA12: =SUMIFS(Sheet1!$G$5:$G$28252,Sheet1!$I$5:$I$28252,$B12,Sheet1!$L$5:$L$28252,$A12,Sheet1!$D$5:$D$28252,"工资",Sheet1!$E$5:$E$28252,"<>*调拨*")+SUMIFS(Sheet1!$G$5:$G$28252,Sheet1!$I$5:$I$28252,$B12,Sheet1!$L$5:$L$28252,$A12,Sheet1!$E$5:$E$28252,"*工资*",Sheet1!$E$5:$E$28252,"<>*调拨*",Sheet1!$D$5:$D$28252,"<>内部转款",Sheet1!$D$5:$D$28252,"<>内部转账",Sheet1!$D$5:$D$28252,"<>工资",Sheet1!$D$5:$D$28252,"<>水费",Sheet1!$D$5:$D$28252,"<>电费",Sheet1!$D$5:$D$28252,"<>宽带费",Sheet1!$D$5:$D$28252,"<>办公费",Sheet1!$D$5:$D$28252,"<>话费",Sheet1!$D$5:$D$28252,"<>房租") -> 0 | AB12: =SUMIFS(Sheet1!$G$5:$G$28252,Sheet1!$I$5:$I$28252,$B12,Sheet1!$L$5:$L$28252,$A12,Sheet1!$D$5:$D$28252,"水费",Sheet1!$E$5:$E$28252,"<>*调拨*")+SUMIFS(Sheet1!$G$5:$G$28252,Sheet1!$I$5:$I$28252,$B12,Sheet1!$L$5:$L$28252,$A12,Sheet1!$E$5:$E$28252,"*水费*",Sheet1!$E$5:$E$28252,"<>*调拨*",Sheet1!$D$5:$D$28252,"<>内部转款",Sheet1!$D$5:$D$28252,"<>内部转账",Sheet1!$D$5:$D$28252,"<>工资",Sheet1!$D$5:$D$28252,"<>水费",Sheet1!$D$5:$D$28252,"<>电费",Sheet1!$D$5:$D$28252,"<>宽带费",Sheet1!$D$5:$D$28252,"<>办公费",Sheet1!$D$5:$D$28252,"<>话费",Sheet1!$D$5:$D$28252,"<>房租",Sheet1!$E$5:$E$28252,"<>*工资*") -> 0 | AC12: =SUMIFS(Sheet1!$G$5:$G$28252,Sheet1!$I$5:$I$28252,$B12,Sheet1!$L$5:$L$28252,$A12,Sheet1!$D$5:$D$28252,"电费",Sheet1!$E$5:$E$28252,"<>*调拨*")+SUMIFS(Sheet1!$G$5:$G$28252,Sheet1!$I$5:$I$28252,$B12,Sheet1!$L$5:$L$28252,$A12,Sheet1!$E$5:$E$28252,"*电费*",Sheet1!$E$5:$E$28252,"<>*调拨*",Sheet1!$D$5:$D$28252,"<>内部转款",Sheet1!$D$5:$D$28252,"<>内部转账",Sheet1!$D$5:$D$28252,"<>工资",Sheet1!$D$5:$D$28252,"<>水费",Sheet1!$D$5:$D$28252,"<>电费",Sheet1!$D$5:$D$28252,"<>宽带费",Sheet1!$D$5:$D$28252,"<>办公费",Sheet1!$D$5:$D$28252,"<>话费",Sheet1!$D$5:$D$28252,"<>房租",Sheet1!$E$5:$E$28252,"<>*工资*",Sheet1!$E$5:$E$28252,"<>*水费*") -> 0 | AD12: =SUMIFS(Sheet1!$G$5:$G$28252,Sheet1!$I$5:$I$28252,$B12,Sheet1!$L$5:$L$28252,$A12,Sheet1!$D$5:$D$28252,"宽带费",Sheet1!$E$5:$E$28252,"<>*调拨*")+SUMIFS(Sheet1!$G$5:$G$28252,Sheet1!$I$5:$I$28252,$B12,Sheet1!$L$5:$L$28252,$A12,Sheet1!$E$5:$E$28252,"*宽带*",Sheet1!$E$5:$E$28252,"<>*调拨*",Sheet1!$D$5:$D$28252,"<>内部转款",Sheet1!$D$5:$D$28252,"<>内部转账",Sheet1!$D$5:$D$28252,"<>工资",Sheet1!$D$5:$D$28252,"<>水费",Sheet1!$D$5:$D$28252,"<>电费",Sheet1!$D$5:$D$28252,"<>宽带费",Sheet1!$D$5:$D$28252,"<>办公费",Sheet1!$D$5:$D$28252,"<>话费",Sheet1!$D$5:$D$28252,"<>房租",Sheet1!$E$5:$E$28252,"<>*工资*",Sheet1!$E$5:$E$28252,"<>*水费*",Sheet1!$E$5:$E$28252,"<>*电费*") -> 0 | AE12: =SUMIFS(Sheet1!$G$5:$G$28252,Sheet1!$I$5:$I$28252,$B12,Sheet1!$L$5:$L$28252,$A12,Sheet1!$D$5:$D$28252,"办公费",Sheet1!$E$5:$E$28252,"<>*调拨*")+SUMIFS(Sheet1!$G$5:$G$28252,Sheet1!$I$5:$I$28252,$B12,Sheet1!$L$5:$L$28252,$A12,Sheet1!$E$5:$E$28252,"*办公*",Sheet1!$E$5:$E$28252,"<>*调拨*",Sheet1!$D$5:$D$28252,"<>内部转款",Sheet1!$D$5:$D$28252,"<>内部转账",Sheet1!$D$5:$D$28252,"<>工资",Sheet1!$D$5:$D$28252,"<>水费",Sheet1!$D$5:$D$28252,"<>电费",Sheet1!$D$5:$D$28252,"<>宽带费",Sheet1!$D$5:$D$28252,"<>办公费",Sheet1!$D$5:$D$28252,"<>话费",Sheet1!$D$5:$D$28252,"<>房租",Sheet1!$E$5:$E$28252,"<>*工资*",Sheet1!$E$5:$E$28252,"<>*水费*",Sheet1!$E$5:$E$28252,"<>*电费*",Sheet1!$E$5:$E$28252,"<>*宽带*") -> 0 | AF12: =SUMIFS(Sheet1!$G$5:$G$28252,Sheet1!$I$5:$I$28252,$B12,Sheet1!$L$5:$L$28252,$A12,Sheet1!$D$5:$D$28252,"话费",Sheet1!$E$5:$E$28252,"<>*调拨*")+SUMIFS(Sheet1!$G$5:$G$28252,Sheet1!$I$5:$I$28252,$B12,Sheet1!$L$5:$L$28252,$A12,Sheet1!$E$5:$E$28252,"*话费*",Sheet1!$E$5:$E$28252,"<>*调拨*",Sheet1!$D$5:$D$28252,"<>内部转款",Sheet1!$D$5:$D$28252,"<>内部转账",Sheet1!$D$5:$D$28252,"<>工资",Sheet1!$D$5:$D$28252,"<>水费",Sheet1!$D$5:$D$28252,"<>电费",Sheet1!$D$5:$D$28252,"<>宽带费",Sheet1!$D$5:$D$28252,"<>办公费",Sheet1!$D$5:$D$28252,"<>话费",Sheet1!$D$5:$D$28252,"<>房租",Sheet1!$E$5:$E$28252,"<>*工资*",Sheet1!$E$5:$E$28252,"<>*水费*",Sheet1!$E$5:$E$28252,"<>*电费*",Sheet1!$E$5:$E$28252,"<>*宽带*",Sheet1!$E$5:$E$28252,"<>*办公*") -> 0 | AG12: =SUMIFS(Sheet1!$G$5:$G$28252,Sheet1!$I$5:$I$28252,$B12,Sheet1!$L$5:$L$28252,$A12,Sheet1!$D$5:$D$28252,"房租",Sheet1!$E$5:$E$28252,"<>*调拨*")+SUMIFS(Sheet1!$G$5:$G$28252,Sheet1!$I$5:$I$28252,$B12,Sheet1!$L$5:$L$28252,$A12,Sheet1!$E$5:$E$28252,"*房租*",Sheet1!$E$5:$E$28252,"<>*调拨*",Sheet1!$D$5:$D$28252,"<>内部转款",Sheet1!$D$5:$D$28252,"<>内部转账",Sheet1!$D$5:$D$28252,"<>工资",Sheet1!$D$5:$D$28252,"<>水费",Sheet1!$D$5:$D$28252,"<>电费",Sheet1!$D$5:$D$28252,"<>宽带费",Sheet1!$D$5:$D$28252,"<>办公费",Sheet1!$D$5:$D$28252,"<>话费",Sheet1!$D$5:$D$28252,"<>房租",Sheet1!$E$5:$E$28252,"<>*工资*",Sheet1!$E$5:$E$28252,"<>*水费*",Sheet1!$E$5:$E$28252,"<>*电费*",Sheet1!$E$5:$E$28252,"<>*宽带*",Sheet1!$E$5:$E$28252,"<>*办公*",Sheet1!$E$5:$E$28252,"<>*话费*") -> 0 | AH12: =SUMIFS(Sheet1!$G$5:$G$28252,Sheet1!$I$5:$I$28252,$B12,Sheet1!$L$5:$L$28252,$A12,Sheet1!$E$5:$E$28252,"*调拨*") -> 0 | AI12: =SUMIFS(Sheet1!$G$5:$G$28252,Sheet1!$I$5:$I$28252,$B12,Sheet1!$L$5:$L$28252,$A12,Sheet1!$D$5:$D$28252,"内部转款",Sheet1!$E$5:$E$28252,"<>*调拨*")+SUMIFS(Sheet1!$G$5:$G$28252,Sheet1!$I$5:$I$28252,$B12,Sheet1!$L$5:$L$28252,$A12,Sheet1!$D$5:$D$28252,"内部转账",Sheet1!$E$5:$E$28252,"<>*调拨*") -> 0 | AJ12: =AK12-SUM(AA12:AI12) -> 0 | AK12: =SUMIFS(Sheet1!$G$5:$G$28252,Sheet1!$I$5:$I$28252,$B12,Sheet1!$L$5:$L$28252,$A12) -> 0 | AL12: =Z12-AK12 -> 0
A13: 202512 | B13: 华联五优新华路 | C13: =SUMIFS(Sheet1!$F$5:$F$28252,Sheet1!$I$5:$I$28252,$B13,Sheet1!$L$5:$L$28252,$A13,Sheet1!$D$5:$D$28252,"营业款",Sheet1!$E$5:$E$28252,"<>*调拨*",Sheet1!$E$5:$E$28252,"<>*回款*",Sheet1!$E$5:$E$28252,"<>*收款*",Sheet1!$E$5:$E$28252,"<>*医保*",Sheet1!$E$5:$E$28252,"<>*聚合*",Sheet1!$E$5:$E$28252,"<>*24小时微信*",Sheet1!$E$5:$E$28252,"<>*美团*",Sheet1!$E$5:$E$28252,"<>*饿了么*",Sheet1!$E$5:$E$28252,"<>*健E卡*",Sheet1!$E$5:$E$28252,"<>*抖音*",Sheet1!$E$5:$E$28252,"<>*医卡通*",Sheet1!$E$5:$E$28252,"<>*企健网*",Sheet1!$E$5:$E$28252,"<>*银联*",Sheet1!$E$5:$E$28252,"<>*京东*",Sheet1!$E$5:$E$28252,"<>*药机微信*",Sheet1!$E$5:$E$28252,"<>*亲情卡*",Sheet1!$E$5:$E$28252,"<>*优惠券*",Sheet1!$E$5:$E$28252,"<>*代金券*",Sheet1!$E$5:$E$28252,"<>*储值*",Sheet1!$E$5:$E$28252,"<>*效期*") -> 0 | D13: =SUMIFS(Sheet1!$F$5:$F$28252,Sheet1!$I$5:$I$28252,$B13,Sheet1!$L$5:$L$28252,$A13,Sheet1!$D$5:$D$28252,"医保即时拨付",Sheet1!$E$5:$E$28252,"<>*调拨*")+SUMIFS(Sheet1!$F$5:$F$28252,Sheet1!$I$5:$I$28252,$B13,Sheet1!$L$5:$L$28252,$A13,Sheet1!$E$5:$E$28252,"*医保即时拨付*",Sheet1!$D$5:$D$28252,"<>医保即时拨付",Sheet1!$D$5:$D$28252,"<>内部转款",Sheet1!$D$5:$D$28252,"<>内部转账",Sheet1!$E$5:$E$28252,"<>*调拨*") -> 0 | E13: =SUMIFS(Sheet1!$F$5:$F$28252,Sheet1!$I$5:$I$28252,$B13,Sheet1!$L$5:$L$28252,$A13,Sheet1!$D$5:$D$28252,"医保",Sheet1!$E$5:$E$28252,"<>*调拨*",Sheet1!$E$5:$E$28252,"<>*医保即时拨付*")+SUMIFS(Sheet1!$F$5:$F$28252,Sheet1!$I$5:$I$28252,$B13,Sheet1!$L$5:$L$28252,$A13,Sheet1!$E$5:$E$28252,"*医保*",Sheet1!$D$5:$D$28252,"<>医保",Sheet1!$D$5:$D$28252,"<>医保即时拨付",Sheet1!$D$5:$D$28252,"<>内部转款",Sheet1!$D$5:$D$28252,"<>内部转账",Sheet1!$E$5:$E$28252,"<>*医保即时拨付*",Sheet1!$E$5:$E$28252,"<>*调拨*") -> 0 | F13: =SUMIFS(Sheet1!$F$5:$F$28252,Sheet1!$I$5:$I$28252,$B13,Sheet1!$L$5:$L$28252,$A13,Sheet1!$D$5:$D$28252,"聚合",Sheet1!$E$5:$E$28252,"<>*调拨*")+SUMIFS(Sheet1!$F$5:$F$28252,Sheet1!$I$5:$I$28252,$B13,Sheet1!$L$5:$L$28252,$A13,Sheet1!$E$5:$E$28252,"*聚合*",Sheet1!$D$5:$D$28252,"<>聚合",Sheet1!$D$5:$D$28252,"<>内部转款",Sheet1!$D$5:$D$28252,"<>内部转账",Sheet1!$E$5:$E$28252,"<>*调拨*") -> 0 | G13: =SUMIFS(Sheet1!$F$5:$F$28252,Sheet1!$I$5:$I$28252,$B13,Sheet1!$L$5:$L$28252,$A13,Sheet1!$D$5:$D$28252,"24小时微信",Sheet1!$E$5:$E$28252,"<>*调拨*")+SUMIFS(Sheet1!$F$5:$F$28252,Sheet1!$I$5:$I$28252,$B13,Sheet1!$L$5:$L$28252,$A13,Sheet1!$E$5:$E$28252,"*24小时微信*",Sheet1!$D$5:$D$28252,"<>24小时微信",Sheet1!$D$5:$D$28252,"<>内部转款",Sheet1!$D$5:$D$28252,"<>内部转账",Sheet1!$E$5:$E$28252,"<>*调拨*") -> 0 | H13: =SUMIFS(Sheet1!$F$5:$F$28252,Sheet1!$I$5:$I$28252,$B13,Sheet1!$L$5:$L$28252,$A13,Sheet1!$D$5:$D$28252,"美团",Sheet1!$E$5:$E$28252,"<>*调拨*")+SUMIFS(Sheet1!$F$5:$F$28252,Sheet1!$I$5:$I$28252,$B13,Sheet1!$L$5:$L$28252,$A13,Sheet1!$E$5:$E$28252,"*美团*",Sheet1!$D$5:$D$28252,"<>美团",Sheet1!$D$5:$D$28252,"<>内部转款",Sheet1!$D$5:$D$28252,"<>内部转账",Sheet1!$E$5:$E$28252,"<>*调拨*") -> 0 | I13: =SUMIFS(Sheet1!$F$5:$F$28252,Sheet1!$I$5:$I$28252,$B13,Sheet1!$L$5:$L$28252,$A13,Sheet1!$D$5:$D$28252,"饿了么",Sheet1!$E$5:$E$28252,"<>*调拨*")+SUMIFS(Sheet1!$F$5:$F$28252,Sheet1!$I$5:$I$28252,$B13,Sheet1!$L$5:$L$28252,$A13,Sheet1!$E$5:$E$28252,"*饿了么*",Sheet1!$D$5:$D$28252,"<>饿了么",Sheet1!$D$5:$D$28252,"<>内部转款",Sheet1!$D$5:$D$28252,"<>内部转账",Sheet1!$E$5:$E$28252,"<>*调拨*") -> 0 | J13: =SUMIFS(Sheet1!$F$5:$F$28252,Sheet1!$I$5:$I$28252,$B13,Sheet1!$L$5:$L$28252,$A13,Sheet1!$D$5:$D$28252,"健E卡",Sheet1!$E$5:$E$28252,"<>*调拨*")+SUMIFS(Sheet1!$F$5:$F$28252,Sheet1!$I$5:$I$28252,$B13,Sheet1!$L$5:$L$28252,$A13,Sheet1!$E$5:$E$28252,"*健E卡*",Sheet1!$D$5:$D$28252,"<>健E卡",Sheet1!$D$5:$D$28252,"<>内部转款",Sheet1!$D$5:$D$28252,"<>内部转账",Sheet1!$E$5:$E$28252,"<>*调拨*") -> 0 | K13: =SUMIFS(Sheet1!$F$5:$F$28252,Sheet1!$I$5:$I$28252,$B13,Sheet1!$L$5:$L$28252,$A13,Sheet1!$D$5:$D$28252,"抖音",Sheet1!$E$5:$E$28252,"<>*调拨*")+SUMIFS(Sheet1!$F$5:$F$28252,Sheet1!$I$5:$I$28252,$B13,Sheet1!$L$5:$L$28252,$A13,Sheet1!$E$5:$E$28252,"*抖音*",Sheet1!$D$5:$D$28252,"<>抖音",Sheet1!$D$5:$D$28252,"<>内部转款",Sheet1!$D$5:$D$28252,"<>内部转账",Sheet1!$E$5:$E$28252,"<>*调拨*") -> 0 | L13: =SUMIFS(Sheet1!$F$5:$F$28252,Sheet1!$I$5:$I$28252,$B13,Sheet1!$L$5:$L$28252,$A13,Sheet1!$D$5:$D$28252,"医卡通",Sheet1!$E$5:$E$28252,"<>*调拨*")+SUMIFS(Sheet1!$F$5:$F$28252,Sheet1!$I$5:$I$28252,$B13,Sheet1!$L$5:$L$28252,$A13,Sheet1!$E$5:$E$28252,"*医卡通*",Sheet1!$D$5:$D$28252,"<>医卡通",Sheet1!$D$5:$D$28252,"<>内部转款",Sheet1!$D$5:$D$28252,"<>内部转账",Sheet1!$E$5:$E$28252,"<>*调拨*") -> 0 | M13: =SUMIFS(Sheet1!$F$5:$F$28252,Sheet1!$I$5:$I$28252,$B13,Sheet1!$L$5:$L$28252,$A13,Sheet1!$D$5:$D$28252,"企健网",Sheet1!$E$5:$E$28252,"<>*调拨*")+SUMIFS(Sheet1!$F$5:$F$28252,Sheet1!$I$5:$I$28252,$B13,Sheet1!$L$5:$L$28252,$A13,Sheet1!$E$5:$E$28252,"*企健网*",Sheet1!$D$5:$D$28252,"<>企健网",Sheet1!$D$5:$D$28252,"<>内部转款",Sheet1!$D$5:$D$28252,"<>内部转账",Sheet1!$E$5:$E$28252,"<>*调拨*") -> 0 | N13: =SUMIFS(Sheet1!$F$5:$F$28252,Sheet1!$I$5:$I$28252,$B13,Sheet1!$L$5:$L$28252,$A13,Sheet1!$D$5:$D$28252,"银联",Sheet1!$E$5:$E$28252,"<>*调拨*")+SUMIFS(Sheet1!$F$5:$F$28252,Sheet1!$I$5:$I$28252,$B13,Sheet1!$L$5:$L$28252,$A13,Sheet1!$E$5:$E$28252,"*银联*",Sheet1!$D$5:$D$28252,"<>银联",Sheet1!$D$5:$D$28252,"<>内部转款",Sheet1!$D$5:$D$28252,"<>内部转账",Sheet1!$E$5:$E$28252,"<>*调拨*") -> 0 | O13: =SUMIFS(Sheet1!$F$5:$F$28252,Sheet1!$I$5:$I$28252,$B13,Sheet1!$L$5:$L$28252,$A13,Sheet1!$D$5:$D$28252,"京东",Sheet1!$E$5:$E$28252,"<>*调拨*")+SUMIFS(Sheet1!$F$5:$F$28252,Sheet1!$I$5:$I$28252,$B13,Sheet1!$L$5:$L$28252,$A13,Sheet1!$E$5:$E$28252,"*京东*",Sheet1!$D$5:$D$28252,"<>京东",Sheet1!$D$5:$D$28252,"<>内部转款",Sheet1!$D$5:$D$28252,"<>内部转账",Sheet1!$E$5:$E$28252,"<>*调拨*") -> 0 | P13: =SUMIFS(Sheet1!$F$5:$F$28252,Sheet1!$I$5:$I$28252,$B13,Sheet1!$L$5:$L$28252,$A13,Sheet1!$D$5:$D$28252,"药机微信",Sheet1!$E$5:$E$28252,"<>*调拨*")+SUMIFS(Sheet1!$F$5:$F$28252,Sheet1!$I$5:$I$28252,$B13,Sheet1!$L$5:$L$28252,$A13,Sheet1!$E$5:$E$28252,"*药机微信*",Sheet1!$D$5:$D$28252,"<>药机微信",Sheet1!$D$5:$D$28252,"<>内部转款",Sheet1!$D$5:$D$28252,"<>内部转账",Sheet1!$E$5:$E$28252,"<>*调拨*") -> 0 | Q13: =SUMIFS(Sheet1!$F$5:$F$28252,Sheet1!$I$5:$I$28252,$B13,Sheet1!$L$5:$L$28252,$A13,Sheet1!$D$5:$D$28252,"亲情卡",Sheet1!$E$5:$E$28252,"<>*调拨*")+SUMIFS(Sheet1!$F$5:$F$28252,Sheet1!$I$5:$I$28252,$B13,Sheet1!$L$5:$L$28252,$A13,Sheet1!$E$5:$E$28252,"*亲情卡*",Sheet1!$D$5:$D$28252,"<>亲情卡",Sheet1!$D$5:$D$28252,"<>内部转款",Sheet1!$D$5:$D$28252,"<>内部转账",Sheet1!$E$5:$E$28252,"<>*调拨*") -> 0 | R13: =SUMIFS(Sheet1!$F$5:$F$28252,Sheet1!$I$5:$I$28252,$B13,Sheet1!$L$5:$L$28252,$A13,Sheet1!$D$5:$D$28252,"优惠券",Sheet1!$E$5:$E$28252,"<>*调拨*")+SUMIFS(Sheet1!$F$5:$F$28252,Sheet1!$I$5:$I$28252,$B13,Sheet1!$L$5:$L$28252,$A13,Sheet1!$E$5:$E$28252,"*优惠券*",Sheet1!$D$5:$D$28252,"<>优惠券",Sheet1!$D$5:$D$28252,"<>内部转款",Sheet1!$D$5:$D$28252,"<>内部转账",Sheet1!$E$5:$E$28252,"<>*调拨*") -> 0 | S13: =SUMIFS(Sheet1!$F$5:$F$28252,Sheet1!$I$5:$I$28252,$B13,Sheet1!$L$5:$L$28252,$A13,Sheet1!$D$5:$D$28252,"代金券",Sheet1!$E$5:$E$28252,"<>*调拨*")+SUMIFS(Sheet1!$F$5:$F$28252,Sheet1!$I$5:$I$28252,$B13,Sheet1!$L$5:$L$28252,$A13,Sheet1!$E$5:$E$28252,"*代金券*",Sheet1!$D$5:$D$28252,"<>代金券",Sheet1!$D$5:$D$28252,"<>内部转款",Sheet1!$D$5:$D$28252,"<>内部转账",Sheet1!$E$5:$E$28252,"<>*调拨*") -> 0 | T13: =SUMIFS(Sheet1!$F$5:$F$28252,Sheet1!$I$5:$I$28252,$B13,Sheet1!$L$5:$L$28252,$A13,Sheet1!$D$5:$D$28252,"回款",Sheet1!$E$5:$E$28252,"<>*调拨*",Sheet1!$E$5:$E$28252,"<>*医保*",Sheet1!$E$5:$E$28252,"<>*聚合*",Sheet1!$E$5:$E$28252,"<>*24小时微信*",Sheet1!$E$5:$E$28252,"<>*美团*",Sheet1!$E$5:$E$28252,"<>*饿了么*",Sheet1!$E$5:$E$28252,"<>*健E卡*",Sheet1!$E$5:$E$28252,"<>*抖音*",Sheet1!$E$5:$E$28252,"<>*医卡通*",Sheet1!$E$5:$E$28252,"<>*企健网*",Sheet1!$E$5:$E$28252,"<>*银联*",Sheet1!$E$5:$E$28252,"<>*京东*",Sheet1!$E$5:$E$28252,"<>*药机微信*",Sheet1!$E$5:$E$28252,"<>*亲情卡*",Sheet1!$E$5:$E$28252,"<>*优惠券*",Sheet1!$E$5:$E$28252,"<>*代金券*",Sheet1!$E$5:$E$28252,"<>*储值*",Sheet1!$E$5:$E$28252,"<>*效期*")+SUMIFS(Sheet1!$F$5:$F$28252,Sheet1!$I$5:$I$28252,$B13,Sheet1!$L$5:$L$28252,$A13,Sheet1!$D$5:$D$28252,"收款",Sheet1!$E$5:$E$28252,"<>*调拨*",Sheet1!$E$5:$E$28252,"<>*医保*",Sheet1!$E$5:$E$28252,"<>*聚合*",Sheet1!$E$5:$E$28252,"<>*24小时微信*",Sheet1!$E$5:$E$28252,"<>*美团*",Sheet1!$E$5:$E$28252,"<>*饿了么*",Sheet1!$E$5:$E$28252,"<>*健E卡*",Sheet1!$E$5:$E$28252,"<>*抖音*",Sheet1!$E$5:$E$28252,"<>*医卡通*",Sheet1!$E$5:$E$28252,"<>*企健网*",Sheet1!$E$5:$E$28252,"<>*银联*",Sheet1!$E$5:$E$28252,"<>*京东*",Sheet1!$E$5:$E$28252,"<>*药机微信*",Sheet1!$E$5:$E$28252,"<>*亲情卡*",Sheet1!$E$5:$E$28252,"<>*优惠券*",Sheet1!$E$5:$E$28252,"<>*代金券*",Sheet1!$E$5:$E$28252,"<>*储值*",Sheet1!$E$5:$E$28252,"<>*效期*")+SUMIFS(Sheet1!$F$5:$F$28252,Sheet1!$I$5:$I$28252,$B13,Sheet1!$L$5:$L$28252,$A13,Sheet1!$E$5:$E$28252,"*回款*",Sheet1!$D$5:$D$28252,"<>回款",Sheet1!$D$5:$D$28252,"<>收款",Sheet1!$D$5:$D$28252,"<>内部转款",Sheet1!$D$5:$D$28252,"<>内部转账",Sheet1!$E$5:$E$28252,"<>*调拨*",Sheet1!$E$5:$E$28252,"<>*医保*",Sheet1!$E$5:$E$28252,"<>*聚合*",Sheet1!$E$5:$E$28252,"<>*24小时微信*",Sheet1!$E$5:$E$28252,"<>*美团*",Sheet1!$E$5:$E$28252,"<>*饿了么*",Sheet1!$E$5:$E$28252,"<>*健E卡*",Sheet1!$E$5:$E$28252,"<>*抖音*",Sheet1!$E$5:$E$28252,"<>*医卡通*",Sheet1!$E$5:$E$28252,"<>*企健网*",Sheet1!$E$5:$E$28252,"<>*银联*",Sheet1!$E$5:$E$28252,"<>*京东*",Sheet1!$E$5:$E$28252,"<>*药机微信*",Sheet1!$E$5:$E$28252,"<>*亲情卡*",Sheet1!$E$5:$E$28252,"<>*优惠券*",Sheet1!$E$5:$E$28252,"<>*代金券*",Sheet1!$E$5:$E$28252,"<>*储值*",Sheet1!$E$5:$E$28252,"<>*效期*")+SUMIFS(Sheet1!$F$5:$F$28252,Sheet1!$I$5:$I$28252,$B13,Sheet1!$L$5:$L$28252,$A13,Sheet1!$E$5:$E$28252,"*收款*",Sheet1!$E$5:$E$28252,"<>*回款*",Sheet1!$D$5:$D$28252,"<>回款",Sheet1!$D$5:$D$28252,"<>收款",Sheet1!$D$5:$D$28252,"<>内部转款",Sheet1!$D$5:$D$28252,"<>内部转账",Sheet1!$E$5:$E$28252,"<>*调拨*",Sheet1!$E$5:$E$28252,"<>*医保*",Sheet1!$E$5:$E$28252,"<>*聚合*",Sheet1!$E$5:$E$28252,"<>*24小时微信*",Sheet1!$E$5:$E$28252,"<>*美团*",Sheet1!$E$5:$E$28252,"<>*饿了么*",Sheet1!$E$5:$E$28252,"<>*健E卡*",Sheet1!$E$5:$E$28252,"<>*抖音*",Sheet1!$E$5:$E$28252,"<>*医卡通*",Sheet1!$E$5:$E$28252,"<>*企健网*",Sheet1!$E$5:$E$28252,"<>*银联*",Sheet1!$E$5:$E$28252,"<>*京东*",Sheet1!$E$5:$E$28252,"<>*药机微信*",Sheet1!$E$5:$E$28252,"<>*亲情卡*",Sheet1!$E$5:$E$28252,"<>*优惠券*",Sheet1!$E$5:$E$28252,"<>*代金券*",Sheet1!$E$5:$E$28252,"<>*储值*",Sheet1!$E$5:$E$28252,"<>*效期*") -> 0 | U13: =SUMIFS(Sheet1!$F$5:$F$28252,Sheet1!$I$5:$I$28252,$B13,Sheet1!$L$5:$L$28252,$A13,Sheet1!$E$5:$E$28252,"*调拨*") -> 0 | V13: =SUMIFS(Sheet1!$F$5:$F$28252,Sheet1!$I$5:$I$28252,$B13,Sheet1!$L$5:$L$28252,$A13,Sheet1!$D$5:$D$28252,"储值",Sheet1!$E$5:$E$28252,"<>*调拨*")+SUMIFS(Sheet1!$F$5:$F$28252,Sheet1!$I$5:$I$28252,$B13,Sheet1!$L$5:$L$28252,$A13,Sheet1!$E$5:$E$28252,"*储值*",Sheet1!$D$5:$D$28252,"<>储值",Sheet1!$D$5:$D$28252,"<>内部转款",Sheet1!$D$5:$D$28252,"<>内部转账",Sheet1!$E$5:$E$28252,"<>*调拨*") -> 0 | W13: =SUMIFS(Sheet1!$F$5:$F$28252,Sheet1!$I$5:$I$28252,$B13,Sheet1!$L$5:$L$28252,$A13,Sheet1!$D$5:$D$28252,"效期",Sheet1!$E$5:$E$28252,"<>*调拨*")+SUMIFS(Sheet1!$F$5:$F$28252,Sheet1!$I$5:$I$28252,$B13,Sheet1!$L$5:$L$28252,$A13,Sheet1!$E$5:$E$28252,"*效期*",Sheet1!$D$5:$D$28252,"<>效期",Sheet1!$D$5:$D$28252,"<>内部转款",Sheet1!$D$5:$D$28252,"<>内部转账",Sheet1!$E$5:$E$28252,"<>*调拨*") -> 0 | X13: =SUMIFS(Sheet1!$F$5:$F$28252,Sheet1!$I$5:$I$28252,$B13,Sheet1!$L$5:$L$28252,$A13,Sheet1!$D$5:$D$28252,"内部转款",Sheet1!$E$5:$E$28252,"<>*调拨*")+SUMIFS(Sheet1!$F$5:$F$28252,Sheet1!$I$5:$I$28252,$B13,Sheet1!$L$5:$L$28252,$A13,Sheet1!$D$5:$D$28252,"内部转账",Sheet1!$E$5:$E$28252,"<>*调拨*") -> 0 | Y13: =Z13-SUM(C13:X13) -> 0 | Z13: =SUMIFS(Sheet1!$F$5:$F$28252,Sheet1!$I$5:$I$28252,$B13,Sheet1!$L$5:$L$28252,$A13) -> 0 | AA13: =SUMIFS(Sheet1!$G$5:$G$28252,Sheet1!$I$5:$I$28252,$B13,Sheet1!$L$5:$L$28252,$A13,Sheet1!$D$5:$D$28252,"工资",Sheet1!$E$5:$E$28252,"<>*调拨*")+SUMIFS(Sheet1!$G$5:$G$28252,Sheet1!$I$5:$I$28252,$B13,Sheet1!$L$5:$L$28252,$A13,Sheet1!$E$5:$E$28252,"*工资*",Sheet1!$E$5:$E$28252,"<>*调拨*",Sheet1!$D$5:$D$28252,"<>内部转款",Sheet1!$D$5:$D$28252,"<>内部转账",Sheet1!$D$5:$D$28252,"<>工资",Sheet1!$D$5:$D$28252,"<>水费",Sheet1!$D$5:$D$28252,"<>电费",Sheet1!$D$5:$D$28252,"<>宽带费",Sheet1!$D$5:$D$28252,"<>办公费",Sheet1!$D$5:$D$28252,"<>话费",Sheet1!$D$5:$D$28252,"<>房租") -> 0 | AB13: =SUMIFS(Sheet1!$G$5:$G$28252,Sheet1!$I$5:$I$28252,$B13,Sheet1!$L$5:$L$28252,$A13,Sheet1!$D$5:$D$28252,"水费",Sheet1!$E$5:$E$28252,"<>*调拨*")+SUMIFS(Sheet1!$G$5:$G$28252,Sheet1!$I$5:$I$28252,$B13,Sheet1!$L$5:$L$28252,$A13,Sheet1!$E$5:$E$28252,"*水费*",Sheet1!$E$5:$E$28252,"<>*调拨*",Sheet1!$D$5:$D$28252,"<>内部转款",Sheet1!$D$5:$D$28252,"<>内部转账",Sheet1!$D$5:$D$28252,"<>工资",Sheet1!$D$5:$D$28252,"<>水费",Sheet1!$D$5:$D$28252,"<>电费",Sheet1!$D$5:$D$28252,"<>宽带费",Sheet1!$D$5:$D$28252,"<>办公费",Sheet1!$D$5:$D$28252,"<>话费",Sheet1!$D$5:$D$28252,"<>房租",Sheet1!$E$5:$E$28252,"<>*工资*") -> 0 | AC13: =SUMIFS(Sheet1!$G$5:$G$28252,Sheet1!$I$5:$I$28252,$B13,Sheet1!$L$5:$L$28252,$A13,Sheet1!$D$5:$D$28252,"电费",Sheet1!$E$5:$E$28252,"<>*调拨*")+SUMIFS(Sheet1!$G$5:$G$28252,Sheet1!$I$5:$I$28252,$B13,Sheet1!$L$5:$L$28252,$A13,Sheet1!$E$5:$E$28252,"*电费*",Sheet1!$E$5:$E$28252,"<>*调拨*",Sheet1!$D$5:$D$28252,"<>内部转款",Sheet1!$D$5:$D$28252,"<>内部转账",Sheet1!$D$5:$D$28252,"<>工资",Sheet1!$D$5:$D$28252,"<>水费",Sheet1!$D$5:$D$28252,"<>电费",Sheet1!$D$5:$D$28252,"<>宽带费",Sheet1!$D$5:$D$28252,"<>办公费",Sheet1!$D$5:$D$28252,"<>话费",Sheet1!$D$5:$D$28252,"<>房租",Sheet1!$E$5:$E$28252,"<>*工资*",Sheet1!$E$5:$E$28252,"<>*水费*") -> 0 | AD13: =SUMIFS(Sheet1!$G$5:$G$28252,Sheet1!$I$5:$I$28252,$B13,Sheet1!$L$5:$L$28252,$A13,Sheet1!$D$5:$D$28252,"宽带费",Sheet1!$E$5:$E$28252,"<>*调拨*")+SUMIFS(Sheet1!$G$5:$G$28252,Sheet1!$I$5:$I$28252,$B13,Sheet1!$L$5:$L$28252,$A13,Sheet1!$E$5:$E$28252,"*宽带*",Sheet1!$E$5:$E$28252,"<>*调拨*",Sheet1!$D$5:$D$28252,"<>内部转款",Sheet1!$D$5:$D$28252,"<>内部转账",Sheet1!$D$5:$D$28252,"<>工资",Sheet1!$D$5:$D$28252,"<>水费",Sheet1!$D$5:$D$28252,"<>电费",Sheet1!$D$5:$D$28252,"<>宽带费",Sheet1!$D$5:$D$28252,"<>办公费",Sheet1!$D$5:$D$28252,"<>话费",Sheet1!$D$5:$D$28252,"<>房租",Sheet1!$E$5:$E$28252,"<>*工资*",Sheet1!$E$5:$E$28252,"<>*水费*",Sheet1!$E$5:$E$28252,"<>*电费*") -> 0 | AE13: =SUMIFS(Sheet1!$G$5:$G$28252,Sheet1!$I$5:$I$28252,$B13,Sheet1!$L$5:$L$28252,$A13,Sheet1!$D$5:$D$28252,"办公费",Sheet1!$E$5:$E$28252,"<>*调拨*")+SUMIFS(Sheet1!$G$5:$G$28252,Sheet1!$I$5:$I$28252,$B13,Sheet1!$L$5:$L$28252,$A13,Sheet1!$E$5:$E$28252,"*办公*",Sheet1!$E$5:$E$28252,"<>*调拨*",Sheet1!$D$5:$D$28252,"<>内部转款",Sheet1!$D$5:$D$28252,"<>内部转账",Sheet1!$D$5:$D$28252,"<>工资",Sheet1!$D$5:$D$28252,"<>水费",Sheet1!$D$5:$D$28252,"<>电费",Sheet1!$D$5:$D$28252,"<>宽带费",Sheet1!$D$5:$D$28252,"<>办公费",Sheet1!$D$5:$D$28252,"<>话费",Sheet1!$D$5:$D$28252,"<>房租",Sheet1!$E$5:$E$28252,"<>*工资*",Sheet1!$E$5:$E$28252,"<>*水费*",Sheet1!$E$5:$E$28252,"<>*电费*",Sheet1!$E$5:$E$28252,"<>*宽带*") -> 0 | AF13: =SUMIFS(Sheet1!$G$5:$G$28252,Sheet1!$I$5:$I$28252,$B13,Sheet1!$L$5:$L$28252,$A13,Sheet1!$D$5:$D$28252,"话费",Sheet1!$E$5:$E$28252,"<>*调拨*")+SUMIFS(Sheet1!$G$5:$G$28252,Sheet1!$I$5:$I$28252,$B13,Sheet1!$L$5:$L$28252,$A13,Sheet1!$E$5:$E$28252,"*话费*",Sheet1!$E$5:$E$28252,"<>*调拨*",Sheet1!$D$5:$D$28252,"<>内部转款",Sheet1!$D$5:$D$28252,"<>内部转账",Sheet1!$D$5:$D$28252,"<>工资",Sheet1!$D$5:$D$28252,"<>水费",Sheet1!$D$5:$D$28252,"<>电费",Sheet1!$D$5:$D$28252,"<>宽带费",Sheet1!$D$5:$D$28252,"<>办公费",Sheet1!$D$5:$D$28252,"<>话费",Sheet1!$D$5:$D$28252,"<>房租",Sheet1!$E$5:$E$28252,"<>*工资*",Sheet1!$E$5:$E$28252,"<>*水费*",Sheet1!$E$5:$E$28252,"<>*电费*",Sheet1!$E$5:$E$28252,"<>*宽带*",Sheet1!$E$5:$E$28252,"<>*办公*") -> 0 | AG13: =SUMIFS(Sheet1!$G$5:$G$28252,Sheet1!$I$5:$I$28252,$B13,Sheet1!$L$5:$L$28252,$A13,Sheet1!$D$5:$D$28252,"房租",Sheet1!$E$5:$E$28252,"<>*调拨*")+SUMIFS(Sheet1!$G$5:$G$28252,Sheet1!$I$5:$I$28252,$B13,Sheet1!$L$5:$L$28252,$A13,Sheet1!$E$5:$E$28252,"*房租*",Sheet1!$E$5:$E$28252,"<>*调拨*",Sheet1!$D$5:$D$28252,"<>内部转款",Sheet1!$D$5:$D$28252,"<>内部转账",Sheet1!$D$5:$D$28252,"<>工资",Sheet1!$D$5:$D$28252,"<>水费",Sheet1!$D$5:$D$28252,"<>电费",Sheet1!$D$5:$D$28252,"<>宽带费",Sheet1!$D$5:$D$28252,"<>办公费",Sheet1!$D$5:$D$28252,"<>话费",Sheet1!$D$5:$D$28252,"<>房租",Sheet1!$E$5:$E$28252,"<>*工资*",Sheet1!$E$5:$E$28252,"<>*水费*",Sheet1!$E$5:$E$28252,"<>*电费*",Sheet1!$E$5:$E$28252,"<>*宽带*",Sheet1!$E$5:$E$28252,"<>*办公*",Sheet1!$E$5:$E$28252,"<>*话费*") -> 0 | AH13: =SUMIFS(Sheet1!$G$5:$G$28252,Sheet1!$I$5:$I$28252,$B13,Sheet1!$L$5:$L$28252,$A13,Sheet1!$E$5:$E$28252,"*调拨*") -> 0 | AI13: =SUMIFS(Sheet1!$G$5:$G$28252,Sheet1!$I$5:$I$28252,$B13,Sheet1!$L$5:$L$28252,$A13,Sheet1!$D$5:$D$28252,"内部转款",Sheet1!$E$5:$E$28252,"<>*调拨*")+SUMIFS(Sheet1!$G$5:$G$28252,Sheet1!$I$5:$I$28252,$B13,Sheet1!$L$5:$L$28252,$A13,Sheet1!$D$5:$D$28252,"内部转账",Sheet1!$E$5:$E$28252,"<>*调拨*") -> 0 | AJ13: =AK13-SUM(AA13:AI13) -> 0 | AK13: =SUMIFS(Sheet1!$G$5:$G$28252,Sheet1!$I$5:$I$28252,$B13,Sheet1!$L$5:$L$28252,$A13) -> 0 | AL13: =Z13-AK13 -> 0
A14: 202512 | B14: 华鑫分店（7店） | C14: =SUMIFS(Sheet1!$F$5:$F$28252,Sheet1!$I$5:$I$28252,$B14,Sheet1!$L$5:$L$28252,$A14,Sheet1!$D$5:$D$28252,"营业款",Sheet1!$E$5:$E$28252,"<>*调拨*",Sheet1!$E$5:$E$28252,"<>*回款*",Sheet1!$E$5:$E$28252,"<>*收款*",Sheet1!$E$5:$E$28252,"<>*医保*",Sheet1!$E$5:$E$28252,"<>*聚合*",Sheet1!$E$5:$E$28252,"<>*24小时微信*",Sheet1!$E$5:$E$28252,"<>*美团*",Sheet1!$E$5:$E$28252,"<>*饿了么*",Sheet1!$E$5:$E$28252,"<>*健E卡*",Sheet1!$E$5:$E$28252,"<>*抖音*",Sheet1!$E$5:$E$28252,"<>*医卡通*",Sheet1!$E$5:$E$28252,"<>*企健网*",Sheet1!$E$5:$E$28252,"<>*银联*",Sheet1!$E$5:$E$28252,"<>*京东*",Sheet1!$E$5:$E$28252,"<>*药机微信*",Sheet1!$E$5:$E$28252,"<>*亲情卡*",Sheet1!$E$5:$E$28252,"<>*优惠券*",Sheet1!$E$5:$E$28252,"<>*代金券*",Sheet1!$E$5:$E$28252,"<>*储值*",Sheet1!$E$5:$E$28252,"<>*效期*") -> 4001.85 | D14: =SUMIFS(Sheet1!$F$5:$F$28252,Sheet1!$I$5:$I$28252,$B14,Sheet1!$L$5:$L$28252,$A14,Sheet1!$D$5:$D$28252,"医保即时拨付",Sheet1!$E$5:$E$28252,"<>*调拨*")+SUMIFS(Sheet1!$F$5:$F$28252,Sheet1!$I$5:$I$28252,$B14,Sheet1!$L$5:$L$28252,$A14,Sheet1!$E$5:$E$28252,"*医保即时拨付*",Sheet1!$D$5:$D$28252,"<>医保即时拨付",Sheet1!$D$5:$D$28252,"<>内部转款",Sheet1!$D$5:$D$28252,"<>内部转账",Sheet1!$E$5:$E$28252,"<>*调拨*") -> 0 | E14: =SUMIFS(Sheet1!$F$5:$F$28252,Sheet1!$I$5:$I$28252,$B14,Sheet1!$L$5:$L$28252,$A14,Sheet1!$D$5:$D$28252,"医保",Sheet1!$E$5:$E$28252,"<>*调拨*",Sheet1!$E$5:$E$28252,"<>*医保即时拨付*")+SUMIFS(Sheet1!$F$5:$F$28252,Sheet1!$I$5:$I$28252,$B14,Sheet1!$L$5:$L$28252,$A14,Sheet1!$E$5:$E$28252,"*医保*",Sheet1!$D$5:$D$28252,"<>医保",Sheet1!$D$5:$D$28252,"<>医保即时拨付",Sheet1!$D$5:$D$28252,"<>内部转款",Sheet1!$D$5:$D$28252,"<>内部转账",Sheet1!$E$5:$E$28252,"<>*医保即时拨付*",Sheet1!$E$5:$E$28252,"<>*调拨*") -> 0 | F14: =SUMIFS(Sheet1!$F$5:$F$28252,Sheet1!$I$5:$I$28252,$B14,Sheet1!$L$5:$L$28252,$A14,Sheet1!$D$5:$D$28252,"聚合",Sheet1!$E$5:$E$28252,"<>*调拨*")+SUMIFS(Sheet1!$F$5:$F$28252,Sheet1!$I$5:$I$28252,$B14,Sheet1!$L$5:$L$28252,$A14,Sheet1!$E$5:$E$28252,"*聚合*",Sheet1!$D$5:$D$28252,"<>聚合",Sheet1!$D$5:$D$28252,"<>内部转款",Sheet1!$D$5:$D$28252,"<>内部转账",Sheet1!$E$5:$E$28252,"<>*调拨*") -> 0 | G14: =SUMIFS(Sheet1!$F$5:$F$28252,Sheet1!$I$5:$I$28252,$B14,Sheet1!$L$5:$L$28252,$A14,Sheet1!$D$5:$D$28252,"24小时微信",Sheet1!$E$5:$E$28252,"<>*调拨*")+SUMIFS(Sheet1!$F$5:$F$28252,Sheet1!$I$5:$I$28252,$B14,Sheet1!$L$5:$L$28252,$A14,Sheet1!$E$5:$E$28252,"*24小时微信*",Sheet1!$D$5:$D$28252,"<>24小时微信",Sheet1!$D$5:$D$28252,"<>内部转款",Sheet1!$D$5:$D$28252,"<>内部转账",Sheet1!$E$5:$E$28252,"<>*调拨*") -> 0 | H14: =SUMIFS(Sheet1!$F$5:$F$28252,Sheet1!$I$5:$I$28252,$B14,Sheet1!$L$5:$L$28252,$A14,Sheet1!$D$5:$D$28252,"美团",Sheet1!$E$5:$E$28252,"<>*调拨*")+SUMIFS(Sheet1!$F$5:$F$28252,Sheet1!$I$5:$I$28252,$B14,Sheet1!$L$5:$L$28252,$A14,Sheet1!$E$5:$E$28252,"*美团*",Sheet1!$D$5:$D$28252,"<>美团",Sheet1!$D$5:$D$28252,"<>内部转款",Sheet1!$D$5:$D$28252,"<>内部转账",Sheet1!$E$5:$E$28252,"<>*调拨*") -> 0 | I14: =SUMIFS(Sheet1!$F$5:$F$28252,Sheet1!$I$5:$I$28252,$B14,Sheet1!$L$5:$L$28252,$A14,Sheet1!$D$5:$D$28252,"饿了么",Sheet1!$E$5:$E$28252,"<>*调拨*")+SUMIFS(Sheet1!$F$5:$F$28252,Sheet1!$I$5:$I$28252,$B14,Sheet1!$L$5:$L$28252,$A14,Sheet1!$E$5:$E$28252,"*饿了么*",Sheet1!$D$5:$D$28252,"<>饿了么",Sheet1!$D$5:$D$28252,"<>内部转款",Sheet1!$D$5:$D$28252,"<>内部转账",Sheet1!$E$5:$E$28252,"<>*调拨*") -> 0 | J14: =SUMIFS(Sheet1!$F$5:$F$28252,Sheet1!$I$5:$I$28252,$B14,Sheet1!$L$5:$L$28252,$A14,Sheet1!$D$5:$D$28252,"健E卡",Sheet1!$E$5:$E$28252,"<>*调拨*")+SUMIFS(Sheet1!$F$5:$F$28252,Sheet1!$I$5:$I$28252,$B14,Sheet1!$L$5:$L$28252,$A14,Sheet1!$E$5:$E$28252,"*健E卡*",Sheet1!$D$5:$D$28252,"<>健E卡",Sheet1!$D$5:$D$28252,"<>内部转款",Sheet1!$D$5:$D$28252,"<>内部转账",Sheet1!$E$5:$E$28252,"<>*调拨*") -> 0 | K14: =SUMIFS(Sheet1!$F$5:$F$28252,Sheet1!$I$5:$I$28252,$B14,Sheet1!$L$5:$L$28252,$A14,Sheet1!$D$5:$D$28252,"抖音",Sheet1!$E$5:$E$28252,"<>*调拨*")+SUMIFS(Sheet1!$F$5:$F$28252,Sheet1!$I$5:$I$28252,$B14,Sheet1!$L$5:$L$28252,$A14,Sheet1!$E$5:$E$28252,"*抖音*",Sheet1!$D$5:$D$28252,"<>抖音",Sheet1!$D$5:$D$28252,"<>内部转款",Sheet1!$D$5:$D$28252,"<>内部转账",Sheet1!$E$5:$E$28252,"<>*调拨*") -> 0 | L14: =SUMIFS(Sheet1!$F$5:$F$28252,Sheet1!$I$5:$I$28252,$B14,Sheet1!$L$5:$L$28252,$A14,Sheet1!$D$5:$D$28252,"医卡通",Sheet1!$E$5:$E$28252,"<>*调拨*")+SUMIFS(Sheet1!$F$5:$F$28252,Sheet1!$I$5:$I$28252,$B14,Sheet1!$L$5:$L$28252,$A14,Sheet1!$E$5:$E$28252,"*医卡通*",Sheet1!$D$5:$D$28252,"<>医卡通",Sheet1!$D$5:$D$28252,"<>内部转款",Sheet1!$D$5:$D$28252,"<>内部转账",Sheet1!$E$5:$E$28252,"<>*调拨*") -> 0 | M14: =SUMIFS(Sheet1!$F$5:$F$28252,Sheet1!$I$5:$I$28252,$B14,Sheet1!$L$5:$L$28252,$A14,Sheet1!$D$5:$D$28252,"企健网",Sheet1!$E$5:$E$28252,"<>*调拨*")+SUMIFS(Sheet1!$F$5:$F$28252,Sheet1!$I$5:$I$28252,$B14,Sheet1!$L$5:$L$28252,$A14,Sheet1!$E$5:$E$28252,"*企健网*",Sheet1!$D$5:$D$28252,"<>企健网",Sheet1!$D$5:$D$28252,"<>内部转款",Sheet1!$D$5:$D$28252,"<>内部转账",Sheet1!$E$5:$E$28252,"<>*调拨*") -> 0 | N14: =SUMIFS(Sheet1!$F$5:$F$28252,Sheet1!$I$5:$I$28252,$B14,Sheet1!$L$5:$L$28252,$A14,Sheet1!$D$5:$D$28252,"银联",Sheet1!$E$5:$E$28252,"<>*调拨*")+SUMIFS(Sheet1!$F$5:$F$28252,Sheet1!$I$5:$I$28252,$B14,Sheet1!$L$5:$L$28252,$A14,Sheet1!$E$5:$E$28252,"*银联*",Sheet1!$D$5:$D$28252,"<>银联",Sheet1!$D$5:$D$28252,"<>内部转款",Sheet1!$D$5:$D$28252,"<>内部转账",Sheet1!$E$5:$E$28252,"<>*调拨*") -> 0 | O14: =SUMIFS(Sheet1!$F$5:$F$28252,Sheet1!$I$5:$I$28252,$B14,Sheet1!$L$5:$L$28252,$A14,Sheet1!$D$5:$D$28252,"京东",Sheet1!$E$5:$E$28252,"<>*调拨*")+SUMIFS(Sheet1!$F$5:$F$28252,Sheet1!$I$5:$I$28252,$B14,Sheet1!$L$5:$L$28252,$A14,Sheet1!$E$5:$E$28252,"*京东*",Sheet1!$D$5:$D$28252,"<>京东",Sheet1!$D$5:$D$28252,"<>内部转款",Sheet1!$D$5:$D$28252,"<>内部转账",Sheet1!$E$5:$E$28252,"<>*调拨*") -> 0 | P14: =SUMIFS(Sheet1!$F$5:$F$28252,Sheet1!$I$5:$I$28252,$B14,Sheet1!$L$5:$L$28252,$A14,Sheet1!$D$5:$D$28252,"药机微信",Sheet1!$E$5:$E$28252,"<>*调拨*")+SUMIFS(Sheet1!$F$5:$F$28252,Sheet1!$I$5:$I$28252,$B14,Sheet1!$L$5:$L$28252,$A14,Sheet1!$E$5:$E$28252,"*药机微信*",Sheet1!$D$5:$D$28252,"<>药机微信",Sheet1!$D$5:$D$28252,"<>内部转款",Sheet1!$D$5:$D$28252,"<>内部转账",Sheet1!$E$5:$E$28252,"<>*调拨*") -> 0 | Q14: =SUMIFS(Sheet1!$F$5:$F$28252,Sheet1!$I$5:$I$28252,$B14,Sheet1!$L$5:$L$28252,$A14,Sheet1!$D$5:$D$28252,"亲情卡",Sheet1!$E$5:$E$28252,"<>*调拨*")+SUMIFS(Sheet1!$F$5:$F$28252,Sheet1!$I$5:$I$28252,$B14,Sheet1!$L$5:$L$28252,$A14,Sheet1!$E$5:$E$28252,"*亲情卡*",Sheet1!$D$5:$D$28252,"<>亲情卡",Sheet1!$D$5:$D$28252,"<>内部转款",Sheet1!$D$5:$D$28252,"<>内部转账",Sheet1!$E$5:$E$28252,"<>*调拨*") -> 0 | R14: =SUMIFS(Sheet1!$F$5:$F$28252,Sheet1!$I$5:$I$28252,$B14,Sheet1!$L$5:$L$28252,$A14,Sheet1!$D$5:$D$28252,"优惠券",Sheet1!$E$5:$E$28252,"<>*调拨*")+SUMIFS(Sheet1!$F$5:$F$28252,Sheet1!$I$5:$I$28252,$B14,Sheet1!$L$5:$L$28252,$A14,Sheet1!$E$5:$E$28252,"*优惠券*",Sheet1!$D$5:$D$28252,"<>优惠券",Sheet1!$D$5:$D$28252,"<>内部转款",Sheet1!$D$5:$D$28252,"<>内部转账",Sheet1!$E$5:$E$28252,"<>*调拨*") -> 0 | S14: =SUMIFS(Sheet1!$F$5:$F$28252,Sheet1!$I$5:$I$28252,$B14,Sheet1!$L$5:$L$28252,$A14,Sheet1!$D$5:$D$28252,"代金券",Sheet1!$E$5:$E$28252,"<>*调拨*")+SUMIFS(Sheet1!$F$5:$F$28252,Sheet1!$I$5:$I$28252,$B14,Sheet1!$L$5:$L$28252,$A14,Sheet1!$E$5:$E$28252,"*代金券*",Sheet1!$D$5:$D$28252,"<>代金券",Sheet1!$D$5:$D$28252,"<>内部转款",Sheet1!$D$5:$D$28252,"<>内部转账",Sheet1!$E$5:$E$28252,"<>*调拨*") -> 0 | T14: =SUMIFS(Sheet1!$F$5:$F$28252,Sheet1!$I$5:$I$28252,$B14,Sheet1!$L$5:$L$28252,$A14,Sheet1!$D$5:$D$28252,"回款",Sheet1!$E$5:$E$28252,"<>*调拨*",Sheet1!$E$5:$E$28252,"<>*医保*",Sheet1!$E$5:$E$28252,"<>*聚合*",Sheet1!$E$5:$E$28252,"<>*24小时微信*",Sheet1!$E$5:$E$28252,"<>*美团*",Sheet1!$E$5:$E$28252,"<>*饿了么*",Sheet1!$E$5:$E$28252,"<>*健E卡*",Sheet1!$E$5:$E$28252,"<>*抖音*",Sheet1!$E$5:$E$28252,"<>*医卡通*",Sheet1!$E$5:$E$28252,"<>*企健网*",Sheet1!$E$5:$E$28252,"<>*银联*",Sheet1!$E$5:$E$28252,"<>*京东*",Sheet1!$E$5:$E$28252,"<>*药机微信*",Sheet1!$E$5:$E$28252,"<>*亲情卡*",Sheet1!$E$5:$E$28252,"<>*优惠券*",Sheet1!$E$5:$E$28252,"<>*代金券*",Sheet1!$E$5:$E$28252,"<>*储值*",Sheet1!$E$5:$E$28252,"<>*效期*")+SUMIFS(Sheet1!$F$5:$F$28252,Sheet1!$I$5:$I$28252,$B14,Sheet1!$L$5:$L$28252,$A14,Sheet1!$D$5:$D$28252,"收款",Sheet1!$E$5:$E$28252,"<>*调拨*",Sheet1!$E$5:$E$28252,"<>*医保*",Sheet1!$E$5:$E$28252,"<>*聚合*",Sheet1!$E$5:$E$28252,"<>*24小时微信*",Sheet1!$E$5:$E$28252,"<>*美团*",Sheet1!$E$5:$E$28252,"<>*饿了么*",Sheet1!$E$5:$E$28252,"<>*健E卡*",Sheet1!$E$5:$E$28252,"<>*抖音*",Sheet1!$E$5:$E$28252,"<>*医卡通*",Sheet1!$E$5:$E$28252,"<>*企健网*",Sheet1!$E$5:$E$28252,"<>*银联*",Sheet1!$E$5:$E$28252,"<>*京东*",Sheet1!$E$5:$E$28252,"<>*药机微信*",Sheet1!$E$5:$E$28252,"<>*亲情卡*",Sheet1!$E$5:$E$28252,"<>*优惠券*",Sheet1!$E$5:$E$28252,"<>*代金券*",Sheet1!$E$5:$E$28252,"<>*储值*",Sheet1!$E$5:$E$28252,"<>*效期*")+SUMIFS(Sheet1!$F$5:$F$28252,Sheet1!$I$5:$I$28252,$B14,Sheet1!$L$5:$L$28252,$A14,Sheet1!$E$5:$E$28252,"*回款*",Sheet1!$D$5:$D$28252,"<>回款",Sheet1!$D$5:$D$28252,"<>收款",Sheet1!$D$5:$D$28252,"<>内部转款",Sheet1!$D$5:$D$28252,"<>内部转账",Sheet1!$E$5:$E$28252,"<>*调拨*",Sheet1!$E$5:$E$28252,"<>*医保*",Sheet1!$E$5:$E$28252,"<>*聚合*",Sheet1!$E$5:$E$28252,"<>*24小时微信*",Sheet1!$E$5:$E$28252,"<>*美团*",Sheet1!$E$5:$E$28252,"<>*饿了么*",Sheet1!$E$5:$E$28252,"<>*健E卡*",Sheet1!$E$5:$E$28252,"<>*抖音*",Sheet1!$E$5:$E$28252,"<>*医卡通*",Sheet1!$E$5:$E$28252,"<>*企健网*",Sheet1!$E$5:$E$28252,"<>*银联*",Sheet1!$E$5:$E$28252,"<>*京东*",Sheet1!$E$5:$E$28252,"<>*药机微信*",Sheet1!$E$5:$E$28252,"<>*亲情卡*",Sheet1!$E$5:$E$28252,"<>*优惠券*",Sheet1!$E$5:$E$28252,"<>*代金券*",Sheet1!$E$5:$E$28252,"<>*储值*",Sheet1!$E$5:$E$28252,"<>*效期*")+SUMIFS(Sheet1!$F$5:$F$28252,Sheet1!$I$5:$I$28252,$B14,Sheet1!$L$5:$L$28252,$A14,Sheet1!$E$5:$E$28252,"*收款*",Sheet1!$E$5:$E$28252,"<>*回款*",Sheet1!$D$5:$D$28252,"<>回款",Sheet1!$D$5:$D$28252,"<>收款",Sheet1!$D$5:$D$28252,"<>内部转款",Sheet1!$D$5:$D$28252,"<>内部转账",Sheet1!$E$5:$E$28252,"<>*调拨*",Sheet1!$E$5:$E$28252,"<>*医保*",Sheet1!$E$5:$E$28252,"<>*聚合*",Sheet1!$E$5:$E$28252,"<>*24小时微信*",Sheet1!$E$5:$E$28252,"<>*美团*",Sheet1!$E$5:$E$28252,"<>*饿了么*",Sheet1!$E$5:$E$28252,"<>*健E卡*",Sheet1!$E$5:$E$28252,"<>*抖音*",Sheet1!$E$5:$E$28252,"<>*医卡通*",Sheet1!$E$5:$E$28252,"<>*企健网*",Sheet1!$E$5:$E$28252,"<>*银联*",Sheet1!$E$5:$E$28252,"<>*京东*",Sheet1!$E$5:$E$28252,"<>*药机微信*",Sheet1!$E$5:$E$28252,"<>*亲情卡*",Sheet1!$E$5:$E$28252,"<>*优惠券*",Sheet1!$E$5:$E$28252,"<>*代金券*",Sheet1!$E$5:$E$28252,"<>*储值*",Sheet1!$E$5:$E$28252,"<>*效期*") -> 0 | U14: =SUMIFS(Sheet1!$F$5:$F$28252,Sheet1!$I$5:$I$28252,$B14,Sheet1!$L$5:$L$28252,$A14,Sheet1!$E$5:$E$28252,"*调拨*") -> 0 | V14: =SUMIFS(Sheet1!$F$5:$F$28252,Sheet1!$I$5:$I$28252,$B14,Sheet1!$L$5:$L$28252,$A14,Sheet1!$D$5:$D$28252,"储值",Sheet1!$E$5:$E$28252,"<>*调拨*")+SUMIFS(Sheet1!$F$5:$F$28252,Sheet1!$I$5:$I$28252,$B14,Sheet1!$L$5:$L$28252,$A14,Sheet1!$E$5:$E$28252,"*储值*",Sheet1!$D$5:$D$28252,"<>储值",Sheet1!$D$5:$D$28252,"<>内部转款",Sheet1!$D$5:$D$28252,"<>内部转账",Sheet1!$E$5:$E$28252,"<>*调拨*") -> 0 | W14: =SUMIFS(Sheet1!$F$5:$F$28252,Sheet1!$I$5:$I$28252,$B14,Sheet1!$L$5:$L$28252,$A14,Sheet1!$D$5:$D$28252,"效期",Sheet1!$E$5:$E$28252,"<>*调拨*")+SUMIFS(Sheet1!$F$5:$F$28252,Sheet1!$I$5:$I$28252,$B14,Sheet1!$L$5:$L$28252,$A14,Sheet1!$E$5:$E$28252,"*效期*",Sheet1!$D$5:$D$28252,"<>效期",Sheet1!$D$5:$D$28252,"<>内部转款",Sheet1!$D$5:$D$28252,"<>内部转账",Sheet1!$E$5:$E$28252,"<>*调拨*") -> 0 | X14: =SUMIFS(Sheet1!$F$5:$F$28252,Sheet1!$I$5:$I$28252,$B14,Sheet1!$L$5:$L$28252,$A14,Sheet1!$D$5:$D$28252,"内部转款",Sheet1!$E$5:$E$28252,"<>*调拨*")+SUMIFS(Sheet1!$F$5:$F$28252,Sheet1!$I$5:$I$28252,$B14,Sheet1!$L$5:$L$28252,$A14,Sheet1!$D$5:$D$28252,"内部转账",Sheet1!$E$5:$E$28252,"<>*调拨*") -> 0 | Y14: =Z14-SUM(C14:X14) -> 0 | Z14: =SUMIFS(Sheet1!$F$5:$F$28252,Sheet1!$I$5:$I$28252,$B14,Sheet1!$L$5:$L$28252,$A14) -> 4001.85 | AA14: =SUMIFS(Sheet1!$G$5:$G$28252,Sheet1!$I$5:$I$28252,$B14,Sheet1!$L$5:$L$28252,$A14,Sheet1!$D$5:$D$28252,"工资",Sheet1!$E$5:$E$28252,"<>*调拨*")+SUMIFS(Sheet1!$G$5:$G$28252,Sheet1!$I$5:$I$28252,$B14,Sheet1!$L$5:$L$28252,$A14,Sheet1!$E$5:$E$28252,"*工资*",Sheet1!$E$5:$E$28252,"<>*调拨*",Sheet1!$D$5:$D$28252,"<>内部转款",Sheet1!$D$5:$D$28252,"<>内部转账",Sheet1!$D$5:$D$28252,"<>工资",Sheet1!$D$5:$D$28252,"<>水费",Sheet1!$D$5:$D$28252,"<>电费",Sheet1!$D$5:$D$28252,"<>宽带费",Sheet1!$D$5:$D$28252,"<>办公费",Sheet1!$D$5:$D$28252,"<>话费",Sheet1!$D$5:$D$28252,"<>房租") -> 0 | AB14: =SUMIFS(Sheet1!$G$5:$G$28252,Sheet1!$I$5:$I$28252,$B14,Sheet1!$L$5:$L$28252,$A14,Sheet1!$D$5:$D$28252,"水费",Sheet1!$E$5:$E$28252,"<>*调拨*")+SUMIFS(Sheet1!$G$5:$G$28252,Sheet1!$I$5:$I$28252,$B14,Sheet1!$L$5:$L$28252,$A14,Sheet1!$E$5:$E$28252,"*水费*",Sheet1!$E$5:$E$28252,"<>*调拨*",Sheet1!$D$5:$D$28252,"<>内部转款",Sheet1!$D$5:$D$28252,"<>内部转账",Sheet1!$D$5:$D$28252,"<>工资",Sheet1!$D$5:$D$28252,"<>水费",Sheet1!$D$5:$D$28252,"<>电费",Sheet1!$D$5:$D$28252,"<>宽带费",Sheet1!$D$5:$D$28252,"<>办公费",Sheet1!$D$5:$D$28252,"<>话费",Sheet1!$D$5:$D$28252,"<>房租",Sheet1!$E$5:$E$28252,"<>*工资*") -> 0 | AC14: =SUMIFS(Sheet1!$G$5:$G$28252,Sheet1!$I$5:$I$28252,$B14,Sheet1!$L$5:$L$28252,$A14,Sheet1!$D$5:$D$28252,"电费",Sheet1!$E$5:$E$28252,"<>*调拨*")+SUMIFS(Sheet1!$G$5:$G$28252,Sheet1!$I$5:$I$28252,$B14,Sheet1!$L$5:$L$28252,$A14,Sheet1!$E$5:$E$28252,"*电费*",Sheet1!$E$5:$E$28252,"<>*调拨*",Sheet1!$D$5:$D$28252,"<>内部转款",Sheet1!$D$5:$D$28252,"<>内部转账",Sheet1!$D$5:$D$28252,"<>工资",Sheet1!$D$5:$D$28252,"<>水费",Sheet1!$D$5:$D$28252,"<>电费",Sheet1!$D$5:$D$28252,"<>宽带费",Sheet1!$D$5:$D$28252,"<>办公费",Sheet1!$D$5:$D$28252,"<>话费",Sheet1!$D$5:$D$28252,"<>房租",Sheet1!$E$5:$E$28252,"<>*工资*",Sheet1!$E$5:$E$28252,"<>*水费*") -> 0 | AD14: =SUMIFS(Sheet1!$G$5:$G$28252,Sheet1!$I$5:$I$28252,$B14,Sheet1!$L$5:$L$28252,$A14,Sheet1!$D$5:$D$28252,"宽带费",Sheet1!$E$5:$E$28252,"<>*调拨*")+SUMIFS(Sheet1!$G$5:$G$28252,Sheet1!$I$5:$I$28252,$B14,Sheet1!$L$5:$L$28252,$A14,Sheet1!$E$5:$E$28252,"*宽带*",Sheet1!$E$5:$E$28252,"<>*调拨*",Sheet1!$D$5:$D$28252,"<>内部转款",Sheet1!$D$5:$D$28252,"<>内部转账",Sheet1!$D$5:$D$28252,"<>工资",Sheet1!$D$5:$D$28252,"<>水费",Sheet1!$D$5:$D$28252,"<>电费",Sheet1!$D$5:$D$28252,"<>宽带费",Sheet1!$D$5:$D$28252,"<>办公费",Sheet1!$D$5:$D$28252,"<>话费",Sheet1!$D$5:$D$28252,"<>房租",Sheet1!$E$5:$E$28252,"<>*工资*",Sheet1!$E$5:$E$28252,"<>*水费*",Sheet1!$E$5:$E$28252,"<>*电费*") -> 0 | AE14: =SUMIFS(Sheet1!$G$5:$G$28252,Sheet1!$I$5:$I$28252,$B14,Sheet1!$L$5:$L$28252,$A14,Sheet1!$D$5:$D$28252,"办公费",Sheet1!$E$5:$E$28252,"<>*调拨*")+SUMIFS(Sheet1!$G$5:$G$28252,Sheet1!$I$5:$I$28252,$B14,Sheet1!$L$5:$L$28252,$A14,Sheet1!$E$5:$E$28252,"*办公*",Sheet1!$E$5:$E$28252,"<>*调拨*",Sheet1!$D$5:$D$28252,"<>内部转款",Sheet1!$D$5:$D$28252,"<>内部转账",Sheet1!$D$5:$D$28252,"<>工资",Sheet1!$D$5:$D$28252,"<>水费",Sheet1!$D$5:$D$28252,"<>电费",Sheet1!$D$5:$D$28252,"<>宽带费",Sheet1!$D$5:$D$28252,"<>办公费",Sheet1!$D$5:$D$28252,"<>话费",Sheet1!$D$5:$D$28252,"<>房租",Sheet1!$E$5:$E$28252,"<>*工资*",Sheet1!$E$5:$E$28252,"<>*水费*",Sheet1!$E$5:$E$28252,"<>*电费*",Sheet1!$E$5:$E$28252,"<>*宽带*") -> 0 | AF14: =SUMIFS(Sheet1!$G$5:$G$28252,Sheet1!$I$5:$I$28252,$B14,Sheet1!$L$5:$L$28252,$A14,Sheet1!$D$5:$D$28252,"话费",Sheet1!$E$5:$E$28252,"<>*调拨*")+SUMIFS(Sheet1!$G$5:$G$28252,Sheet1!$I$5:$I$28252,$B14,Sheet1!$L$5:$L$28252,$A14,Sheet1!$E$5:$E$28252,"*话费*",Sheet1!$E$5:$E$28252,"<>*调拨*",Sheet1!$D$5:$D$28252,"<>内部转款",Sheet1!$D$5:$D$28252,"<>内部转账",Sheet1!$D$5:$D$28252,"<>工资",Sheet1!$D$5:$D$28252,"<>水费",Sheet1!$D$5:$D$28252,"<>电费",Sheet1!$D$5:$D$28252,"<>宽带费",Sheet1!$D$5:$D$28252,"<>办公费",Sheet1!$D$5:$D$28252,"<>话费",Sheet1!$D$5:$D$28252,"<>房租",Sheet1!$E$5:$E$28252,"<>*工资*",Sheet1!$E$5:$E$28252,"<>*水费*",Sheet1!$E$5:$E$28252,"<>*电费*",Sheet1!$E$5:$E$28252,"<>*宽带*",Sheet1!$E$5:$E$28252,"<>*办公*") -> 0 | AG14: =SUMIFS(Sheet1!$G$5:$G$28252,Sheet1!$I$5:$I$28252,$B14,Sheet1!$L$5:$L$28252,$A14,Sheet1!$D$5:$D$28252,"房租",Sheet1!$E$5:$E$28252,"<>*调拨*")+SUMIFS(Sheet1!$G$5:$G$28252,Sheet1!$I$5:$I$28252,$B14,Sheet1!$L$5:$L$28252,$A14,Sheet1!$E$5:$E$28252,"*房租*",Sheet1!$E$5:$E$28252,"<>*调拨*",Sheet1!$D$5:$D$28252,"<>内部转款",Sheet1!$D$5:$D$28252,"<>内部转账",Sheet1!$D$5:$D$28252,"<>工资",Sheet1!$D$5:$D$28252,"<>水费",Sheet1!$D$5:$D$28252,"<>电费",Sheet1!$D$5:$D$28252,"<>宽带费",Sheet1!$D$5:$D$28252,"<>办公费",Sheet1!$D$5:$D$28252,"<>话费",Sheet1!$D$5:$D$28252,"<>房租",Sheet1!$E$5:$E$28252,"<>*工资*",Sheet1!$E$5:$E$28252,"<>*水费*",Sheet1!$E$5:$E$28252,"<>*电费*",Sheet1!$E$5:$E$28252,"<>*宽带*",Sheet1!$E$5:$E$28252,"<>*办公*",Sheet1!$E$5:$E$28252,"<>*话费*") -> 0 | AH14: =SUMIFS(Sheet1!$G$5:$G$28252,Sheet1!$I$5:$I$28252,$B14,Sheet1!$L$5:$L$28252,$A14,Sheet1!$E$5:$E$28252,"*调拨*") -> 0 | AI14: =SUMIFS(Sheet1!$G$5:$G$28252,Sheet1!$I$5:$I$28252,$B14,Sheet1!$L$5:$L$28252,$A14,Sheet1!$D$5:$D$28252,"内部转款",Sheet1!$E$5:$E$28252,"<>*调拨*")+SUMIFS(Sheet1!$G$5:$G$28252,Sheet1!$I$5:$I$28252,$B14,Sheet1!$L$5:$L$28252,$A14,Sheet1!$D$5:$D$28252,"内部转账",Sheet1!$E$5:$E$28252,"<>*调拨*") -> 0 | AJ14: =AK14-SUM(AA14:AI14) -> 0 | AK14: =SUMIFS(Sheet1!$G$5:$G$28252,Sheet1!$I$5:$I$28252,$B14,Sheet1!$L$5:$L$28252,$A14) -> 0 | AL14: =Z14-AK14 -> 4001.85
