Workbook
Name 差旅费: [1]名称!$B$21
Name 费用类别: #REF!
Name 明细科目编码: [2]会计科目表!$A$3:$A$70
Name 明细科目名称: [2]会计科目表!$B$3:$B$70
Name 日期: #REF!
Name 收费项: [3]名称!$B$2:$B$40
Name 收入现金: #REF!
Name 薪资福利: [3]名称!$B$2:$B$45
Name 月份: #REF!
Name 支出现金: #REF!
Name 总账科目名称: [2]总账科目!$B$3:$B$40

Sheet 目录
B1: 目录 | C1: 跳转链接
B2: {=_wpsfn.SHEETSNAME(,1,1)} -> 汇总 | C2: =HYPERLINK("#"&B2&"!a1","跳转链接") -> 跳转链接
B3: 付费项 | C3: =HYPERLINK("#"&B3&"!a1","跳转链接") -> 跳转链接
B4: 力喆实业中国银行 | C4: =HYPERLINK("#"&B4&"!a1","跳转链接") -> 跳转链接
B5: 力喆产业农商银行 | C5: =HYPERLINK("#"&B5&"!a1","跳转链接") -> 跳转链接
B6: 元生万物建设银行 | C6: =HYPERLINK("#"&B6&"!a1","跳转链接") -> 跳转链接
B7: 言吾言中国银行 | C7: =HYPERLINK("#"&B7&"!a1","跳转链接") -> 跳转链接
B8: 力喆传媒海峡银行 | C8: =HYPERLINK("#"&B8&"!a1","跳转链接") -> 跳转链接
B9: 徐洁招商银行 | C9: =HYPERLINK("#"&B9&"!a1","跳转链接") -> 跳转链接 | M9: SHEETSNAME(,1,1)
B10: 力喆贸易建设银行 | C10: =HYPERLINK("#"&B10&"!a1","跳转链接") -> 跳转链接 | M10: HYPERLINK("#"&B2&"!a1","跳转链接")
B11: 古玩城农商银行 | C11: =HYPERLINK("#"&B11&"!a1","跳转链接") -> 跳转链接 | M11: HYPERLINK("#目录!a1","返回目录")
B12: 古玩城现金 | C12: =HYPERLINK("#"&B12&"!a1","跳转链接") -> 跳转链接
B13: 艾泊烨海峡银行 | C13: =HYPERLINK("#"&B13&"!a1","跳转链接") -> 跳转链接
B14: 艾泊烨招商银行 | C14: =HYPERLINK("#"&B14&"!a1","跳转链接") -> 跳转链接
B15: 艾泊烨农商银行 | C15: =HYPERLINK("#"&B15&"!a1","跳转链接") -> 跳转链接
B16: 艾泊烨私户银行 | C16: =HYPERLINK("#"&B16&"!a1","跳转链接") -> 跳转链接
B17: 博烨体育农商银行 | C17: =HYPERLINK("#"&B17&"!a1","跳转链接") -> 跳转链接
B18: 博烨私户 | C18: =HYPERLINK("#"&B18&"!a1","跳转链接") -> 跳转链接
B19: 博烨篮球馆 | C19: =HYPERLINK("#"&B19&"!a1","跳转链接") -> 跳转链接
B20: 博烨羽毛球 | C20: =HYPERLINK("#"&B20&"!a1","跳转链接") -> 跳转链接
B21: 博烨健身房 | C21: =HYPERLINK("#"&B21&"!a1","跳转链接") -> 跳转链接
B22: 博烨匹克球 | C22: =HYPERLINK("#"&B22&"!a1","跳转链接") -> 跳转链接
B23: Sheet1 | C23: =HYPERLINK("#"&B23&"!a1","跳转链接") -> 跳转链接
... B29: 易佰兴农商银行外 | C29: =HYPERLINK("#"&B29&"!a1","跳转链接") -> 跳转链接
C30: =HYPERLINK("#"&B30&"!a1","跳转链接") -> 跳转链接
C31: =HYPERLINK("#"&B31&"!a1","跳转链接") -> 跳转链接
C32: =HYPERLINK("#"&B32&"!a1","跳转链接") -> 跳转链接
C33: =HYPERLINK("#"&B33&"!a1","跳转链接") -> 跳转链接
C34: =HYPERLINK("#"&B34&"!a1","跳转链接") -> 跳转链接

Sheet 中策管理海峡银行
A1: =HYPERLINK("#目录!a1","返回目录") -> 返回目录 | B1: 银行日记账--海峡银行
B3: 月 | C3: 日 | D3: 收费项 | E3: 收付人 | F3: 摘要 | G3: 收入 | H3: 支出 | I3: 余额 | J3: 备注
F4: 期初余额 | I4: 176530.77
B5: 1 | C5: 5 | D5: 银行手续费 | E5: 福建海峡银行股份有限公司福州金城支行 | F5: 支付短信通服务费 | H5: 10 | I5: =I4+G5-H5 -> 176520.77
B6: 1 | C6: 11 | E6: 福建海峡银行股份有限公司福州金城支行 | F6: 自助回单打印机服务费 | H6: 60 | I6: =I5+G6-H6 -> 176460.77
B7: 1 | C7: 15 | E7: 徐洁 | F7: 收徐洁服务费 | G7: 4000 | I7: =I6+G7-H7 -> 180460.77
F8: 本月合计 | G8: =SUM(G5:G7) -> 4000 | H8: =SUM(H5:H7) -> 70 | I8: =I4+G8-H8 -> 180460.77
B9: 2 | C9: 2 | E9: 福建悟空游国际旅行社有限公司 | F9: 旅游费用 | H9: 21320 | I9: =I8+G9-H9 -> 159140.77
B10: 2 | C10: 5 | D10: 银行手续费 | E10: 福建海峡银行股份有限公司福州金城支行 | F10: 支付短信通服务费 | H10: 10 | I10: =I9+G10-H10 -> 159130.77
B11: 2 | C11: 13 | E11: 徐洁 | F11: 收徐洁服务费 | G11: 4000 | I11: =I10+G11-H11 -> 163130.77
B12: 2 | C12: 26 | E12: 福州晋安中策管理咨询有限公司 | F12: 提取备用金 | H12: 48000 | I12: =I11+G12-H12 -> 115130.77
B13: 2 | C13: 28 | E13: 福建悟空游国际旅行社有限公司 | F13: 退回旅游费用 | G13: 800 | I13: =I12+G13-H13 -> 115930.77
F14: 本月合计 | G14: =SUM(G9:G13) -> 4800 | H14: =SUM(H9:H13) -> 69330 | I14: =I8+G14-H14 -> 115930.77
B15: 3 | C15: 5 | D15: 银行手续费 | E15: 福建海峡银行股份有限公司福州金城支行 | F15: 支付短信通服务费 | H15: 10 | I15: =I14+G15-H15 -> 115920.77
B16: 3 | C16: 16 | E16: 徐洁 | F16: 收徐洁服务费 | G16: 4000 | I16: =I15+G16-H16 -> 119920.77
B17: 3 | C17: 21 | E17: 银行 | F17: 利息收入 | G17: 19.75 | I17: =I16+G17-H17 -> 119940.52
F18: 本月合计 | G18: =SUM(G15:G17) -> 4019.75 | H18: =SUM(H15:H17) -> 10 | I18: =I14+G18-H18 -> 119940.52
I19: =I18+G19-H19 -> 119940.52
I20: =I19+G20-H20 -> 119940.52
I21: =I20+G21-H21 -> 119940.52
I22: =I21+G22-H22 -> 119940.52
I23: =I22+G23-H23 -> 119940.52
I24: =I23+G24-H24 -> 119940.52
I25: =I24+G25-H25 -> 119940.52
I26: =I25+G26-H26 -> 119940.52
I27: =I26+G27-H27 -> 119940.52
I28: =I27+G28-H28 -> 119940.52
I29: =I28+G29-H29 -> 119940.52
I30: =I29+G30-H30 -> 119940.52
... I65: =I64+G65-H65 -> 119940.52

Sheet 四季快安兴业银行
A1: =HYPERLINK("#目录!a1","返回目录") -> 返回目录 | B1: 银行日记账--兴业银行
B3: 月 | C3: 日 | D3: 收费项 | E3: 收付人 | F3: 摘要 | G3: 收入 | H3: 支出 | I3: 余额 | J3: 备注
F4: 期初余额 | I4: 125.51
B5: 1 | C5: 15 | E5: 福建省健坤德行资产管理有限责任公司 | F5: 收到福建省健坤德行资产管理有限责任公司借款 | G5: 35000 | I5: =I4+G5-H5 -> 35125.51
B6: 1 | C6: 15 | E6: 福建丰华智能停车场管理有限公司 | F6: 支付福建丰华智能停车场管理有限公司借款 | H6: 35000 | I6: =I5+G6-H6 -> 125.51
B7: 1 | C7: 15 | F7: 支付银行手续费 | H7: 0.5 | I7: =I6+G7-H7 -> 125.01
F8: 本月合计 | G8: =SUM(G5:G7) -> 35000 | H8: =SUM(H5:H7) -> 35000.5 | I8: =I4+G8-H8 -> 125.01
B9: 2 | C9: 12 | E9: 福建省健坤德行资产管理有限责任公司 | F9: 收到福建省健坤德行资产管理有限责任公司借款 | G9: 85000 | I9: =I8+G9-H9 -> 85125.01
B10: 2 | C10: 12 | E10: 福建丰华智能停车场管理有限公司 | F10: 支付福建丰华智能停车场管理有限公司借款 | H10: 85000 | I10: =I9+G10-H10 -> 125.01
B11: 2 | C11: 12 | F11: 支付银行手续费 | H11: 0.5 | I11: =I10+G11-H11 -> 124.51
F12: 本月合计 | G12: =SUM(G9:G11) -> 85000 | H12: =SUM(H9:H11) -> 85000.5 | I12: =I8+G12-H12 -> 124.51
B13: 3 | C13: 16 | E13: 福建省健坤德行资产管理有限责任公司 | F13: 收到福建省健坤德行资产管理有限责任公司借款 | G13: 30000 | I13: =I12+G13-H13 -> 30124.51
B14: 3 | C14: 16 | E14: 福建丰华智能停车场管理有限公司 | F14: 支付福建丰华智能停车场管理有限公司借款 | H14: 30000 | I14: =I13+G14-H14 -> 124.51
B15: 3 | C15: 16 | F15: 支付银行手续费 | H15: 0.5 | I15: =I14+G15-H15 -> 124.01
B16: 3 | C16: 21 | E16: 银行 | F16: 利息收入 | G16: 0.02 | I16: =I15+G16-H16 -> 124.03
F17: 本月合计 | G17: =SUM(G13:G16) -> 30000.02 | H17: =SUM(H13:H16) -> 30000.5 | I17: =I12+G17-H17 -> 124.03
B18: 4 | C18: 14 | F18: 支付银行手续费 | H18: 0.5 | I18: =I17+G18-H18 -> 123.53
B19: 4 | C19: 14 | E19: 福建省健坤德行资产管理有限责任公司 | F19: 收到福建省健坤德行资产管理有限责任公司借款 | G19: 55000 | I19: =I18+G19-H19 -> 55123.53
B20: 4 | C20: 14 | E20: 福建丰华智能停车场管理有限公司 | F20: 支付福建丰华智能停车场管理有限公司借款 | H20: 55000 | I20: =I19+G20-H20 -> 123.53
B21: 4 | C21: 14 | F21: 支付银行手续费 | H21: 0.5 | I21: =I20+G21-H21 -> 123.03
B22: 4 | C22: 16 | E22: 福建省健坤德行资产管理有限责任公司 | F22: 收到福建省健坤德行资产管理有限责任公司借款 | G22: 120000 | I22: =I21+G22-H22 -> 120123.03
B23: 4 | C23: 16 | E23: 福建丰华智能停车场管理有限公司 | F23: 支付福建丰华智能停车场管理有限公司借款 | H23: 120000 | I23: =I22+G23-H23 -> 123.03
B24: 4 | C24: 16 | F24: 支付银行手续费 | H24: 0.5 | I24: =I23+G24-H24 -> 122.53
I25: =I24+G25-H25 -> 122.53
I26: =I25+G26-H26 -> 122.53
I27: =I26+G27-H27 -> 122.53
I28: =I27+G28-H28 -> 122.53
I29: =I28+G29-H29 -> 122.53
I30: =I29+G30-H30 -> 122.53
I31: =I30+G31-H31 -> 122.53
I32: =I31+G32-H32 -> 122.53
I33: =I32+G33-H33 -> 122.53
I34: =I33+G34-H34 -> 122.53
I35: =I34+G35-H35 -> 122.53
I36: =I35+G36-H36 -> 122.53
... I65: =I64+G65-H65 -> 122.53

Sheet 汇总
B1: 2026 | C1: 年各公司收支明细表
A2: =HYPERLINK("#目录!a1","返回目录") -> 返回目录 | B2: 年份 | C2: 2026 | D2: 月份 | E2: 5
E3: 力喆中国银行 | F3: 力喆农商银行 | G3: 力喆私户 | H3: 力喆贸易建行 | I3: 元生万物建行 | J3: 言吾言中行 | K3: 传媒海峡银行 | L3: 古玩城农商银行 | M3: 古玩城现金 | N3: 艾泊烨海峡银行 | O3: 艾泊烨招商银行 | P3: 艾泊烨农商银行 | Q3: 艾泊烨私户 | R3: 易佰兴建行 | S3: 易佰兴私户 | T3: 易佰兴现金 | U3: 易佰兴基本户
A4: 收入明细表 | B4: 月份 | C4: 收入明细 | D4: 青翼创 | E4: 力喆实业 | F4: 力喆实业 | G4: 力喆实业 | H4: 力喆贸易 | I4: 元生万物 | J4: 言吾言 | K4: 力喆传媒 | L4: 古玩城 | M4: 古玩城 | N4: 艾泊烨 | O4: 艾泊烨 | P4: 艾泊烨 | Q4: 艾泊烨 | R4: 易佰兴 | S4: 易佰兴 | T4: 易佰兴 | U4: 易佰兴
C5: 银行期初余额 | D5: =SUMIFS(Sheet1!$L:$L,Sheet1!$A:$A,"="&$E$2) -> 17724.83 | E5: =SUMIFS(Sheet1!$M:$M,Sheet1!$A:$A,"="&$E$2) -> 0 | F5: =SUMIFS(Sheet1!$N:$N,Sheet1!$A:$A,"="&$E$2) -> 6814.57 | G5: =SUMIFS(Sheet1!$R:$R,Sheet1!$A:$A,"="&$E$2) -> 12055.05 | H5: =SUMIFS(Sheet1!$S:$S,Sheet1!$A:$A,"="&$E$2) -> 11156.41 | I5: =SUMIFS(Sheet1!$O:$O,Sheet1!$A:$A,"="&$E$2) -> 35003.97 | J5: =SUMIFS(Sheet1!$P:$P,Sheet1!$A:$A,"="&$E$2) -> 4419.25 | K5: =SUMIFS(Sheet1!$Q:$Q,Sheet1!$A:$A,"="&$E$2) -> 0 | L5: =SUMIFS(Sheet1!$B:$B,Sheet1!$A:$A,"="&$E$2) -> 155258.06 | M5: =SUMIFS(Sheet1!$C:$C,Sheet1!$A:$A,"="&$E$2) -> 0 | N5: =SUMIFS(Sheet1!$D:$D,Sheet1!$A:$A,"="&$E$2) -> 118439.59 | O5: =SUMIFS(Sheet1!$E:$E,Sheet1!$A:$A,"="&$E$2) -> 30536.78 | P5: =SUMIFS(Sheet1!$F:$F,Sheet1!$A:$A,"="&$E$2) -> 3279.77 | Q5: =SUMIFS(Sheet1!$G:$G,Sheet1!$A:$A,"="&$E$2) -> 28831.41 | R5: =SUMIFS(Sheet1!$H:$H,Sheet1!$A:$A,"="&$E$2) -> 8822.26 | S5: =SUMIFS(Sheet1!$I:$I,Sheet1!$A:$A,"="&$E$2) -> 127662.01 | T5: =SUMIFS(Sheet1!$J:$J,Sheet1!$A:$A,"="&$E$2) -> 0 | U5: =SUMIFS(Sheet1!$K:$K,Sheet1!$A:$A,"="&$E$2) -> 1352.1
B6: =E2 -> 5 | C6: 押金 | D6: =SUMIFS(#REF!,#REF!,"="&$E$2,#REF!,"="&$C6) -> #REF! | E6: =SUMIFS(力喆实业中国银行!$G:$G,力喆实业中国银行!$B:$B,"="&$E$2,力喆实业中国银行!$D:$D,"="&$C6) -> 0 | F6: =SUMIFS(力喆产业农商银行!$G:$G,力喆产业农商银行!$B:$B,"="&$E$2,力喆产业农商银行!$D:$D,"="&$C6) -> 0 | G6: =SUMIFS(徐洁招商银行!$G:$G,徐洁招商银行!$B:$B,"="&$E$2,徐洁招商银行!$D:$D,"="&$C6) -> 0 | H6: =SUMIFS(力喆贸易建设银行!$G:$G,力喆贸易建设银行!$B:$B,"="&$E$2,力喆贸易建设银行!$D:$D,"="&$C6) -> 0 | I6: =SUMIFS(元生万物建设银行!$G:$G,元生万物建设银行!$B:$B,"="&$E$2,元生万物建设银行!$D:$D,"="&$C6) -> 0 | J6: =SUMIFS(言吾言中国银行!$G:$G,言吾言中国银行!$B:$B,"="&$E$2,言吾言中国银行!$D:$D,"="&$C6) -> 0 | K6: =SUMIFS(力喆传媒海峡银行!$G:$G,力喆传媒海峡银行!$B:$B,"="&$E$2,力喆传媒海峡银行!$D:$D,"="&$C6) -> 0 | L6: =SUMIFS(古玩城农商银行!$J:$J,古玩城农商银行!$B:$B,"="&$E$2) -> 22200 | M6: =SUMIFS(古玩城现金!$J:$J,古玩城现金!$B:$B,"="&$E$2) -> 0 | N6: =SUMIFS(艾泊烨海峡银行!$G:$G,艾泊烨海峡银行!$B:$B,"="&$E$2,艾泊烨海峡银行!$D:$D,"="&$C6) -> 0 | O6: 0 | P6: =SUMIFS(艾泊烨农商银行!$I:$I,艾泊烨农商银行!$B:$B,"="&$E$2,艾泊烨农商银行!$D:$D,"="&$C6) -> 0 | Q6: =SUMIFS(艾泊烨私户银行!$G:$G,艾泊烨私户银行!$B:$B,"="&$E$2,艾泊烨私户银行!$D:$D,"="&$C6) -> 27380 | R6: =SUMIFS(易佰兴建行!$J:$J,易佰兴建行!$B:$B,"="&$E$2) -> 41422 | S6: =SUMIFS(易佰兴私户!$J:$J,易佰兴私户!$B:$B,"="&$E$2) -> 0 | T6: =SUMIFS(易佰兴现金!$J:$J,易佰兴现金!$B:$B,"="&$E$2) -> 0 | U6: =SUMIFS(易佰兴基本户!$J:$J,易佰兴基本户!$B:$B,"="&$E$2) -> 0
B7: =B6 -> 5 | C7: 往来款 | D7: =SUMIFS(#REF!,#REF!,"="&$E$2,#REF!,"="&$C7) -> #REF! | E7: =SUMIFS(力喆实业中国银行!$G:$G,力喆实业中国银行!$B:$B,"="&$E$2,力喆实业中国银行!$D:$D,"="&$C7) -> 0 | F7: =SUMIFS(力喆产业农商银行!$G:$G,力喆产业农商银行!$B:$B,"="&$E$2,力喆产业农商银行!$D:$D,"="&$C7) -> 47832.11 | G7: =SUMIFS(徐洁招商银行!$G:$G,徐洁招商银行!$B:$B,"="&$E$2,徐洁招商银行!$D:$D,"="&$C7) -> 25000 | H7: =SUMIFS(力喆贸易建设银行!$G:$G,力喆贸易建设银行!$B:$B,"="&$E$2,力喆贸易建设银行!$D:$D,"="&$C7) -> 0 | I7: =SUMIFS(元生万物建设银行!$G:$G,元生万物建设银行!$B:$B,"="&$E$2,元生万物建设银行!$D:$D,"="&$C7) -> 30098.25 | J7: =SUMIFS(言吾言中国银行!$G:$G,言吾言中国银行!$B:$B,"="&$E$2,言吾言中国银行!$D:$D,"="&$C7) -> 0 | K7: =SUMIFS(力喆传媒海峡银行!$G:$G,力喆传媒海峡银行!$B:$B,"="&$E$2,力喆传媒海峡银行!$D:$D,"="&$C7) -> 0 | M7: =SUMIFS(古玩城现金!$D:$D,古玩城现金!$B:$B,"="&$E$2) -> 0 | N7: =SUMIFS(艾泊烨海峡银行!$G:$G,艾泊烨海峡银行!$B:$B,"="&$E$2,艾泊烨海峡银行!$D:$D,"="&$C7) -> 0 | O7: 0 | P7: =SUMIFS(艾泊烨农商银行!$I:$I,艾泊烨农商银行!$B:$B,"="&$E$2,艾泊烨农商银行!$D:$D,"="&$C7) -> 16000 | Q7: =SUMIFS(艾泊烨私户银行!$G:$G,艾泊烨私户银行!$B:$B,"="&$E$2,艾泊烨私户银行!$D:$D,"="&$C7) -> 0 | R7: =SUMIFS(易佰兴建行!$O:$O,易佰兴建行!$B:$B,"="&$E$2,易佰兴建行!D:D,"="&$C7) -> 0 | S7: 0 | T7: =SUMIFS(易佰兴现金!$J:$J,易佰兴现金!$B:$B,"="&$E$2) -> 0 | U7: =SUMIFS(易佰兴基本户!$O:$O,易佰兴基本户!$B:$B,"="&$E$2,易佰兴基本户!$D:$D,"="&$C7) -> 24300
B8: =B24 -> 5 | C8: 场地租金收入 | E8: =SUMIFS(力喆实业中国银行!$G:$G,力喆实业中国银行!$B:$B,"="&$E$2,力喆实业中国银行!$D:$D,"="&$C8) -> 0 | F8: =SUMIFS(力喆产业农商银行!$G:$G,力喆产业农商银行!$B:$B,"="&$E$2,力喆产业农商银行!$D:$D,"="&$C8) -> 0 | G8: =SUMIFS(徐洁招商银行!$G:$G,徐洁招商银行!$B:$B,"="&$E$2,徐洁招商银行!$D:$D,"="&$C8) -> 0 | H8: =SUMIFS(力喆贸易建设银行!$G:$G,力喆贸易建设银行!$B:$B,"="&$E$2,力喆贸易建设银行!$D:$D,"="&$C8) -> 0 | J8: =SUMIFS(言吾言中国银行!$G:$G,言吾言中国银行!$B:$B,"="&$E$2,言吾言中国银行!$D:$D,"="&$C8) -> 0 | M8: =SUMIFS(古玩城现金!$J:$J,古玩城现金!$B:$B,"="&$E$2) -> 0 | N8: =SUMIFS(艾泊烨海峡银行!$G:$G,艾泊烨海峡银行!$B:$B,"="&$E$2,艾泊烨海峡银行!$D:$D,"="&$C8) -> 14000 | O8: 0 | P8: =SUMIFS(艾泊烨农商银行!$I:$I,艾泊烨农商银行!$B:$B,"="&$E$2,艾泊烨农商银行!$D:$D,"="&$C8) -> 0 | Q8: =SUMIFS(艾泊烨私户银行!$G:$G,艾泊烨私户银行!$B:$B,"="&$E$2,艾泊烨私户银行!$D:$D,"="&$C8) -> 9600 | R8: 0 | S8: 0 | T8: =SUMIFS(易佰兴现金!$J:$J,易佰兴现金!$B:$B,"="&$E$2) -> 0 | U8: 0
B9: =B24 -> 5 | C9: 月卡收入 | E9: =SUMIFS(力喆实业中国银行!$G:$G,力喆实业中国银行!$B:$B,"="&$E$2,力喆实业中国银行!$D:$D,"="&$C9) -> 0 | F9: =SUMIFS(力喆产业农商银行!$G:$G,力喆产业农商银行!$B:$B,"="&$E$2,力喆产业农商银行!$D:$D,"="&$C9) -> 0 | G9: =SUMIFS(徐洁招商银行!$G:$G,徐洁招商银行!$B:$B,"="&$E$2,徐洁招商银行!$D:$D,"="&$C9) -> 0 | H9: =SUMIFS(力喆贸易建设银行!$G:$G,力喆贸易建设银行!$B:$B,"="&$E$2,力喆贸易建设银行!$D:$D,"="&$C9) -> 0 | J9: =SUMIFS(言吾言中国银行!$G:$G,言吾言中国银行!$B:$B,"="&$E$2,言吾言中国银行!$D:$D,"="&$C9) -> 0 | L9: 0 | M9: =SUMIFS(古玩城现金!$J:$J,古玩城现金!$B:$B,"="&$E$2) -> 0 | N9: =SUMIFS(艾泊烨海峡银行!$G:$G,艾泊烨海峡银行!$B:$B,"="&$E$2,艾泊烨海峡银行!$D:$D,"="&$C9) -> 350 | O9: 0 | P9: =SUMIFS(艾泊烨农商银行!$I:$I,艾泊烨农商银行!$B:$B,"="&$E$2,艾泊烨农商银行!$D:$D,"="&$C9) -> 0 | Q9: =SUMIFS(艾泊烨私户银行!$G:$G,艾泊烨私户银行!$B:$B,"="&$E$2,艾泊烨私户银行!$D:$D,"="&$C9) -> 27222.77 | R9: 0 | S9: 0 | T9: =SUMIFS(易佰兴现金!$J:$J,易佰兴现金!$B:$B,"="&$E$2) -> 0 | U9: 0
B10: =B15 -> 5 | C10: 营业分成收入 | E10: =SUMIFS(力喆实业中国银行!$G:$G,力喆实业中国银行!$B:$B,"="&$E$2,力喆实业中国银行!$D:$D,"="&$C10) -> 0 | F10: =SUMIFS(力喆产业农商银行!$G:$G,力喆产业农商银行!$B:$B,"="&$E$2,力喆产业农商银行!$D:$D,"="&$C10) -> 0 | G10: =SUMIFS(徐洁招商银行!$G:$G,徐洁招商银行!$B:$B,"="&$E$2,徐洁招商银行!$D:$D,"="&$C10) -> 0 | H10: =SUMIFS(力喆贸易建设银行!$G:$G,力喆贸易建设银行!$B:$B,"="&$E$2,力喆贸易建设银行!$D:$D,"="&$C10) -> 0 | J10: =SUMIFS(言吾言中国银行!$G:$G,言吾言中国银行!$B:$B,"="&$E$2,言吾言中国银行!$D:$D,"="&$C10) -> 0 | L10: 0 | M10: =SUMIFS(古玩城现金!$J:$J,古玩城现金!$B:$B,"="&$E$2) -> 0 | N10: =SUMIFS(艾泊烨海峡银行!$G:$G,艾泊烨海峡银行!$B:$B,"="&$E$2,艾泊烨海峡银行!$D:$D,"="&$C10) -> 2000 | O10: 0 | P10: =SUMIFS(艾泊烨农商银行!$I:$I,艾泊烨农商银行!$B:$B,"="&$E$2,艾泊烨农商银行!$D:$D,"="&$C10) -> 0 | Q10: =SUMIFS(艾泊烨私户银行!$G:$G,艾泊烨私户银行!$B:$B,"="&$E$2,艾泊烨私户银行!$D:$D,"="&$C10) -> 0 | R10: 0 | S10: 0 | T10: =SUMIFS(易佰兴现金!$J:$J,易佰兴现金!$B:$B,"="&$E$2) -> 0 | U10: 0
B11: =B8 -> 5 | C11: 超出部分80%收入 | E11: =SUMIFS(力喆实业中国银行!$G:$G,力喆实业中国银行!$B:$B,"="&$E$2,力喆实业中国银行!$D:$D,"="&$C11) -> 0 | F11: =SUMIFS(力喆产业农商银行!$G:$G,力喆产业农商银行!$B:$B,"="&$E$2,力喆产业农商银行!$D:$D,"="&$C11) -> 0 | G11: =SUMIFS(徐洁招商银行!$G:$G,徐洁招商银行!$B:$B,"="&$E$2,徐洁招商银行!$D:$D,"="&$C11) -> 0 | H11: =SUMIFS(力喆贸易建设银行!$G:$G,力喆贸易建设银行!$B:$B,"="&$E$2,力喆贸易建设银行!$D:$D,"="&$C11) -> 0 | J11: =SUMIFS(言吾言中国银行!$G:$G,言吾言中国银行!$B:$B,"="&$E$2,言吾言中国银行!$D:$D,"="&$C11) -> 0 | M11: =SUMIFS(古玩城现金!$J:$J,古玩城现金!$B:$B,"="&$E$2) -> 0 | N11: =SUMIFS(艾泊烨海峡银行!$G:$G,艾泊烨海峡银行!$B:$B,"="&$E$2,艾泊烨海峡银行!$D:$D,"="&$C11) -> 118449.07 | O11: 0 | P11: =SUMIFS(艾泊烨农商银行!$I:$I,艾泊烨农商银行!$B:$B,"="&$E$2,艾泊烨农商银行!$D:$D,"="&$C11) -> 0 | Q11: =SUMIFS(艾泊烨私户银行!$G:$G,艾泊烨私户银行!$B:$B,"="&$E$2,艾泊烨私户银行!$D:$D,"="&$C11) -> 0 | R11: 0 | S11: 0 | T11: =SUMIFS(易佰兴现金!$J:$J,易佰兴现金!$B:$B,"="&$E$2) -> 0 | U11: 0
B12: =B10 -> 5 | C12: 道闸服务费收入 | E12: =SUMIFS(力喆实业中国银行!$G:$G,力喆实业中国银行!$B:$B,"="&$E$2,力喆实业中国银行!$D:$D,"="&$C12) -> 0 | F12: =SUMIFS(力喆产业农商银行!$G:$G,力喆产业农商银行!$B:$B,"="&$E$2,力喆产业农商银行!$D:$D,"="&$C12) -> 0 | G12: =SUMIFS(徐洁招商银行!$G:$G,徐洁招商银行!$B:$B,"="&$E$2,徐洁招商银行!$D:$D,"="&$C12) -> 0 | H12: =SUMIFS(力喆贸易建设银行!$G:$G,力喆贸易建设银行!$B:$B,"="&$E$2,力喆贸易建设银行!$D:$D,"="&$C12) -> 0 | J12: =SUMIFS(言吾言中国银行!$G:$G,言吾言中国银行!$B:$B,"="&$E$2,言吾言中国银行!$D:$D,"="&$C12) -> 0 | L12: 0 | M12: =SUMIFS(古玩城现金!$J:$J,古玩城现金!$B:$B,"="&$E$2) -> 0 | N12: =SUMIFS(艾泊烨海峡银行!$G:$G,艾泊烨海峡银行!$B:$B,"="&$E$2,艾泊烨海峡银行!$D:$D,"="&$C12) -> 16800 | O12: 0 | P12: =SUMIFS(艾泊烨农商银行!$I:$I,艾泊烨农商银行!$B:$B,"="&$E$2,艾泊烨农商银行!$D:$D,"="&$C12) -> 0 | Q12: =SUMIFS(艾泊烨私户银行!$G:$G,艾泊烨私户银行!$B:$B,"="&$E$2,艾泊烨私户银行!$D:$D,"="&$C12) -> 0 | R12: 0 | S12: 0 | T12: =SUMIFS(易佰兴现金!$J:$J,易佰兴现金!$B:$B,"="&$E$2) -> 0 | U12: 0
B13: =B12 -> 5 | C13: 充电桩收入 | E13: =SUMIFS(力喆实业中国银行!$G:$G,力喆实业中国银行!$B:$B,"="&$E$2,力喆实业中国银行!$D:$D,"="&$C13) -> 0 | F13: =SUMIFS(力喆产业农商银行!$G:$G,力喆产业农商银行!$B:$B,"="&$E$2,力喆产业农商银行!$D:$D,"="&$C13) -> 0 | G13: =SUMIFS(徐洁招商银行!$G:$G,徐洁招商银行!$B:$B,"="&$E$2,徐洁招商银行!$D:$D,"="&$C13) -> 0 | H13: =SUMIFS(力喆贸易建设银行!$G:$G,力喆贸易建设银行!$B:$B,"="&$E$2,力喆贸易建设银行!$D:$D,"="&$C13) -> 0 | J13: =SUMIFS(言吾言中国银行!$G:$G,言吾言中国银行!$B:$B,"="&$E$2,言吾言中国银行!$D:$D,"="&$C13) -> 0 | M13: =SUMIFS(古玩城现金!$J:$J,古玩城现金!$B:$B,"="&$E$2) -> 0 | N13: =SUMIFS(艾泊烨海峡银行!$G:$G,艾泊烨海峡银行!$B:$B,"="&$E$2,艾泊烨海峡银行!$D:$D,"="&$C13) -> 0 | O13: 0 | P13: =SUMIFS(艾泊烨农商银行!$I:$I,艾泊烨农商银行!$B:$B,"="&$E$2,艾泊烨农商银行!$D:$D,"="&$C13) -> 0 | Q13: =SUMIFS(艾泊烨私户银行!$G:$G,艾泊烨私户银行!$B:$B,"="&$E$2,艾泊烨私户银行!$D:$D,"="&$C13) -> 0 | R13: 0 | S13: 0 | T13: =SUMIFS(易佰兴现金!$J:$J,易佰兴现金!$B:$B,"="&$E$2) -> 0 | U13: 0
B14: =B13 -> 5 | C14: 利达大厦租金收入 | E14: =SUMIFS(力喆实业中国银行!$G:$G,力喆实业中国银行!$B:$B,"="&$E$2,力喆实业中国银行!$D:$D,"="&$C14) -> 0 | F14: =SUMIFS(力喆产业农商银行!$G:$G,力喆产业农商银行!$B:$B,"="&$E$2,力喆产业农商银行!$D:$D,"="&$C14) -> 0 | G14: =SUMIFS(徐洁招商银行!$G:$G,徐洁招商银行!$B:$B,"="&$E$2,徐洁招商银行!$D:$D,"="&$C14) -> 73824.8 | H14: =SUMIFS(力喆贸易建设银行!$G:$G,力喆贸易建设银行!$B:$B,"="&$E$2,力喆贸易建设银行!$D:$D,"="&$C14) -> 0 | T14: =SUMIFS(易佰兴现金!$J:$J,易佰兴现金!$B:$B,"="&$E$2) -> 0
B15: =B7 -> 5 | C15: 房租收入 | D15: =SUMIFS(#REF!,#REF!,"="&$E$2,#REF!,"="&$C15) -> #REF! | E15: =SUMIFS(力喆实业中国银行!$G:$G,力喆实业中国银行!$B:$B,"="&$E$2,力喆实业中国银行!$D:$D,"="&$C15) -> 0 | F15: =SUMIFS(力喆产业农商银行!$G:$G,力喆产业农商银行!$B:$B,"="&$E$2,力喆产业农商银行!$D:$D,"="&$C15) -> 0 | G15: =SUMIFS(徐洁招商银行!$G:$G,徐洁招商银行!$B:$B,"="&$E$2,徐洁招商银行!$D:$D,"="&$C15) -> 57832.11 | H15: =SUMIFS(力喆贸易建设银行!$G:$G,力喆贸易建设银行!$B:$B,"="&$E$2,力喆贸易建设银行!$D:$D,"="&$C15) -> 73229.1 | I15: =SUMIFS(元生万物建设银行!$G:$G,元生万物建设银行!$B:$B,"="&$E$2,元生万物建设银行!$D:$D,"="&$C15) -> 0 | J15: =SUMIFS(言吾言中国银行!$G:$G,言吾言中国银行!$B:$B,"="&$E$2,言吾言中国银行!$D:$D,"="&$C15) -> 0 | K15: =SUMIFS(力喆传媒海峡银行!$G:$G,力喆传媒海峡银行!$B:$B,"="&$E$2,力喆传媒海峡银行!$D:$D,"="&$C15) -> 0 | L15: =SUMIFS(古玩城农商银行!$G:$G,古玩城农商银行!$B:$B,"="&$E$2) -> 290765 | M15: =SUMIFS(古玩城现金!$G:$G,古玩城现金!$B:$B,"="&$E$2) -> 10864 | N15: =SUMIFS(艾泊烨海峡银行!$G:$G,艾泊烨海峡银行!$B:$B,"="&$E$2,艾泊烨海峡银行!$D:$D,"="&$C15) -> 0 | O15: 0 | P15: =SUMIFS(艾泊烨农商银行!$I:$I,艾泊烨农商银行!$B:$B,"="&$E$2,艾泊烨农商银行!$D:$D,"="&$C15) -> 0 | Q15: =SUMIFS(艾泊烨私户银行!$G:$G,艾泊烨私户银行!$B:$B,"="&$E$2,艾泊烨私户银行!$D:$D,"="&$C15) -> 0 | R15: =SUMIFS(易佰兴建行!$G:$G,易佰兴建行!$B:$B,"="&$E$2) -> 278302.83 | S15: =SUMIFS(易佰兴私户!$G:$G,易佰兴私户!$B:$B,"="&$E$2) -> 79195 | T15: =SUMIFS(易佰兴现金!$G:$G,易佰兴现金!$B:$B,"="&$E$2) -> 0 | U15: =SUMIFS(易佰兴基本户!$G:$G,易佰兴基本户!$B:$B,"="&$E$2) -> 0
B16: =B15 -> 5 | C16: 物业收入 | D16: =SUMIFS(#REF!,#REF!,"="&$E$2,#REF!,"="&$C16) -> #REF! | E16: =SUMIFS(力喆实业中国银行!$G:$G,力喆实业中国银行!$B:$B,"="&$E$2,力喆实业中国银行!$D:$D,"="&$C16) -> 0 | F16: =SUMIFS(力喆产业农商银行!$G:$G,力喆产业农商银行!$B:$B,"="&$E$2,力喆产业农商银行!$D:$D,"="&$C16) -> 0 | G16: =SUMIFS(徐洁招商银行!$G:$G,徐洁招商银行!$B:$B,"="&$E$2,徐洁招商银行!$D:$D,"="&$C16) -> 0 | H16: =SUMIFS(力喆贸易建设银行!$G:$G,力喆贸易建设银行!$B:$B,"="&$E$2,力喆贸易建设银行!$D:$D,"="&$C16) -> 0 | I16: =SUMIFS(元生万物建设银行!$G:$G,元生万物建设银行!$B:$B,"="&$E$2,元生万物建设银行!$D:$D,"="&$C16) -> 0 | J16: =SUMIFS(言吾言中国银行!$G:$G,言吾言中国银行!$B:$B,"="&$E$2,言吾言中国银行!$D:$D,"="&$C16) -> 0 | K16: =SUMIFS(力喆传媒海峡银行!$G:$G,力喆传媒海峡银行!$B:$B,"="&$E$2,力喆传媒海峡银行!$D:$D,"="&$C16) -> 0 | L16: =SUMIFS(古玩城农商银行!H:H,古玩城农商银行!B:B,"="&$E$2) -> 12400 | M16: =SUMIFS(古玩城现金!$H:$H,古玩城现金!$B:$B,"="&$E$2) -> 600 | N16: =SUMIFS(艾泊烨海峡银行!$G:$G,艾泊烨海峡银行!$B:$B,"="&$E$2,艾泊烨海峡银行!$D:$D,"="&$C16) -> 0 | O16: 0 | P16: =SUMIFS(艾泊烨农商银行!$I:$I,艾泊烨农商银行!$B:$B,"="&$E$2,艾泊烨农商银行!$D:$D,"="&$C16) -> 0 | Q16: =SUMIFS(艾泊烨私户银行!$G:$G,艾泊烨私户银行!$B:$B,"="&$E$2,艾泊烨私户银行!$D:$D,"="&$C16) -> 0 | R16: =SUMIFS(易佰兴建行!$H:$H,易佰兴建行!$B:$B,"="&$E$2) -> 25142.7 | S16: =SUMIFS(易佰兴私户!$H:$H,易佰兴私户!B:B,"="&$E$2) -> 7862.4 | T16: =SUMIFS(易佰兴现金!$H:$H,易佰兴现金!$B:$B,"="&$E$2) -> 0 | U16: =SUMIFS(易佰兴基本户!$H:$H,易佰兴基本户!$B:$B,"="&$E$2) -> 0
B17: =B16 -> 5 | C17: 水电收入 | D17: =SUMIFS(#REF!,#REF!,"="&$E$2,#REF!,"="&$C17) -> #REF! | E17: =SUMIFS(力喆实业中国银行!$G:$G,力喆实业中国银行!$B:$B,"="&$E$2,力喆实业中国银行!$D:$D,"="&$C17) -> 0 | F17: =SUMIFS(力喆产业农商银行!$G:$G,力喆产业农商银行!$B:$B,"="&$E$2,力喆产业农商银行!$D:$D,"="&$C17) -> 0 | G17: =SUMIFS(徐洁招商银行!$G:$G,徐洁招商银行!$B:$B,"="&$E$2,徐洁招商银行!$D:$D,"="&$C17) -> 0 | H17: =SUMIFS(力喆贸易建设银行!$G:$G,力喆贸易建设银行!$B:$B,"="&$E$2,力喆贸易建设银行!$D:$D,"="&$C17) -> 0 | I17: =SUMIFS(元生万物建设银行!$G:$G,元生万物建设银行!$B:$B,"="&$E$2,元生万物建设银行!$D:$D,"="&$C17) -> 0 | J17: =SUMIFS(言吾言中国银行!$G:$G,言吾言中国银行!$B:$B,"="&$E$2,言吾言中国银行!$D:$D,"="&$C17) -> 0 | K17: =SUMIFS(力喆传媒海峡银行!$G:$G,力喆传媒海峡银行!$B:$B,"="&$E$2,力喆传媒海峡银行!$D:$D,"="&$C17) -> 0 | L17: =SUMIFS(古玩城农商银行!$I:$I,古玩城农商银行!$B:$B,"="&$E$2) -> 20631.2 | M17: =SUMIFS(古玩城现金!$I:$I,古玩城现金!$B:$B,"="&$E$2) -> 656 | N17: =SUMIFS(艾泊烨海峡银行!$G:$G,艾泊烨海峡银行!$B:$B,"="&$E$2,艾泊烨海峡银行!$D:$D,"="&$C17) -> 2756.25 | O17: 0 | P17: =SUMIFS(艾泊烨农商银行!$I:$I,艾泊烨农商银行!$B:$B,"="&$E$2,艾泊烨农商银行!$D:$D,"="&$C17) -> 0 | Q17: =SUMIFS(艾泊烨私户银行!$G:$G,艾泊烨私户银行!$B:$B,"="&$E$2,艾泊烨私户银行!$D:$D,"="&$C17) -> 4250.05 | R17: =SUMIFS(易佰兴建行!$I:$I,易佰兴建行!$B:$B,"="&$E$2) -> 188 | S17: =SUMIFS(易佰兴私户!$I:$I,易佰兴私户!B:B,"="&$E$2) -> 25305.83 | T17: =SUMIFS(易佰兴现金!$I:$I,易佰兴现金!$B:$B,"="&$E$2) -> 0 | U17: =SUMIFS(易佰兴基本户!$I:$I,易佰兴基本户!$B:$B,"="&$E$2) -> 0
B18: =B17 -> 5 | C18: 摊位收入 | D18: =SUMIFS(#REF!,#REF!,"="&$E$2,#REF!,"="&$C18) -> #REF! | E18: =SUMIFS(力喆实业中国银行!$G:$G,力喆实业中国银行!$B:$B,"="&$E$2,力喆实业中国银行!$D:$D,"="&$C18) -> 0 | F18: =SUMIFS(力喆产业农商银行!$G:$G,力喆产业农商银行!$B:$B,"="&$E$2,力喆产业农商银行!$D:$D,"="&$C18) -> 0 | G18: =SUMIFS(徐洁招商银行!$G:$G,徐洁招商银行!$B:$B,"="&$E$2,徐洁招商银行!$D:$D,"="&$C18) -> 0 | H18: =SUMIFS(力喆贸易建设银行!$G:$G,力喆贸易建设银行!$B:$B,"="&$E$2,力喆贸易建设银行!$D:$D,"="&$C18) -> 0 | I18: =SUMIFS(元生万物建设银行!$G:$G,元生万物建设银行!$B:$B,"="&$E$2,元生万物建设银行!$D:$D,"="&$C18) -> 0 | J18: =SUMIFS(言吾言中国银行!$G:$G,言吾言中国银行!$B:$B,"="&$E$2,言吾言中国银行!$D:$D,"="&$C18) -> 0 | K18: =SUMIFS(力喆传媒海峡银行!$G:$G,力喆传媒海峡银行!$B:$B,"="&$E$2,力喆传媒海峡银行!$D:$D,"="&$C18) -> 0 | L18: =SUMIFS(古玩城农商银行!$K:$K,古玩城农商银行!$B:$B,"="&$E$2) -> 25185 | M18: =SUMIFS(古玩城现金!$K:$K,古玩城现金!$B:$B,"="&$E$2) -> 4080 | N18: =SUMIFS(艾泊烨海峡银行!$G:$G,艾泊烨海峡银行!$B:$B,"="&$E$2,艾泊烨海峡银行!$D:$D,"="&$C18) -> 0 | O18: 0 | P18: =SUMIFS(艾泊烨农商银行!$I:$I,艾泊烨农商银行!$B:$B,"="&$E$2,艾泊烨农商银行!$D:$D,"="&$C18) -> 0 | Q18: =SUMIFS(艾泊烨私户银行!$G:$G,艾泊烨私户银行!$B:$B,"="&$E$2,艾泊烨私户银行!$D:$D,"="&$C18) -> 0 | R18: 0 | S18: 0 | T18: =SUMIFS(易佰兴现金!$J:$J,易佰兴现金!$B:$B,"="&$E$2) -> 0 | U18: 0
B19: =B18 -> 5 | C19: 停车费收入 | E19: =SUMIFS(力喆实业中国银行!$G:$G,力喆实业中国银行!$B:$B,"="&$E$2,力喆实业中国银行!$D:$D,"="&$C19) -> 0 | F19: =SUMIFS(力喆产业农商银行!$G:$G,力喆产业农商银行!$B:$B,"="&$E$2,力喆产业农商银行!$D:$D,"="&$C19) -> 0 | G19: =SUMIFS(徐洁招商银行!$G:$G,徐洁招商银行!$B:$B,"="&$E$2,徐洁招商银行!$D:$D,"="&$C19) -> 0 | H19: =SUMIFS(力喆贸易建设银行!$G:$G,力喆贸易建设银行!$B:$B,"="&$E$2,力喆贸易建设银行!$D:$D,"="&$C19) -> 0 | J19: =SUMIFS(言吾言中国银行!$G:$G,言吾言中国银行!$B:$B,"="&$E$2,言吾言中国银行!$D:$D,"="&$C19) -> 0 | R19: =SUMIFS(易佰兴建行!$K:$K,易佰兴建行!$B:$B,"="&$E$2) -> 300 | S19: =SUMIFS(易佰兴私户!$K:$K,易佰兴私户!$B:$B,"="&$E$2) -> 6580 | T19: =SUMIFS(易佰兴现金!$K:$K,易佰兴现金!$B:$B,"="&$E$2) -> 240 | U19: =SUMIFS(易佰兴基本户!$K:$K,易佰兴基本户!$B:$B,"="&$E$2) -> 0
B20: =B19 -> 5 | C20: 广告费收入 | E20: =SUMIFS(力喆实业中国银行!$G:$G,力喆实业中国银行!$B:$B,"="&$E$2,力喆实业中国银行!$D:$D,"="&$C20) -> 0 | F20: =SUMIFS(力喆产业农商银行!$G:$G,力喆产业农商银行!$B:$B,"="&$E$2,力喆产业农商银行!$D:$D,"="&$C20) -> 0 | G20: =SUMIFS(徐洁招商银行!$G:$G,徐洁招商银行!$B:$B,"="&$E$2,徐洁招商银行!$D:$D,"="&$C20) -> 0 | H20: =SUMIFS(力喆贸易建设银行!$G:$G,力喆贸易建设银行!$B:$B,"="&$E$2,力喆贸易建设银行!$D:$D,"="&$C20) -> 0 | J20: =SUMIFS(言吾言中国银行!$G:$G,言吾言中国银行!$B:$B,"="&$E$2,言吾言中国银行!$D:$D,"="&$C20) -> 0 | R20: =SUMIFS(易佰兴建行!$L:$L,易佰兴建行!$B:$B,"="&$E$2) -> 500 | S20: 0 | T20: =SUMIFS(易佰兴现金!$J:$J,易佰兴现金!$B:$B,"="&$E$2) -> 0 | U20: =SUMIFS(易佰兴基本户!$L:$L,易佰兴基本户!$B:$B,"="&$E$2) -> 0
B21: =B18 -> 5 | C21: 股东分红 | D21: =SUMIFS(#REF!,#REF!,"="&$E$2,#REF!,"="&$C21) -> #REF! | E21: =SUMIFS(力喆实业中国银行!$G:$G,力喆实业中国银行!$B:$B,"="&$E$2,力喆实业中国银行!$D:$D,"="&$C21) -> 0 | F21: =SUMIFS(力喆产业农商银行!$G:$G,力喆产业农商银行!$B:$B,"="&$E$2,力喆产业农商银行!$D:$D,"="&$C21) -> 0 | G21: =SUMIFS(徐洁招商银行!$G:$G,徐洁招商银行!$B:$B,"="&$E$2,徐洁招商银行!$D:$D,"="&$C21) -> 0 | H21: =SUMIFS(力喆贸易建设银行!$G:$G,力喆贸易建设银行!$B:$B,"="&$E$2,力喆贸易建设银行!$D:$D,"="&$C21) -> 0 | I21: =SUMIFS(元生万物建设银行!$G:$G,元生万物建设银行!$B:$B,"="&$E$2,元生万物建设银行!$D:$D,"="&$C21) -> 0 | J21: =SUMIFS(言吾言中国银行!$G:$G,言吾言中国银行!$B:$B,"="&$E$2,言吾言中国银行!$D:$D,"="&$C21) -> 0 | K21: =SUMIFS(力喆传媒海峡银行!$G:$G,力喆传媒海峡银行!$B:$B,"="&$E$2,力喆传媒海峡银行!$D:$D,"="&$C21) -> 0 | L21: =SUMIFS(古玩城农商银行!$G:$G,古玩城农商银行!$B:$B,"="&$E$2,古玩城农商银行!$D:$D,"="&$C21) -> 0 | M21: =SUMIFS(古玩城现金!$J:$J,古玩城现金!$B:$B,"="&$E$2) -> 0 | N21: =SUMIFS(艾泊烨海峡银行!$G:$G,艾泊烨海峡银行!$B:$B,"="&$E$2,艾泊烨海峡银行!$D:$D,"="&$C21) -> 0 | O21: 0 | P21: =SUMIFS(艾泊烨农商银行!$I:$I,艾泊烨农商银行!$B:$B,"="&$E$2,艾泊烨农商银行!$D:$D,"="&$C21) -> 0 | Q21: =SUMIFS(艾泊烨私户银行!$G:$G,艾泊烨私户银行!$B:$B,"="&$E$2,艾泊烨私户银行!$D:$D,"="&$C21) -> 0 | R21: 0 | S21: 0 | T21: =SUMIFS(易佰兴现金!$J:$J,易佰兴现金!$B:$B,"="&$E$2) -> 0 | U21: 0
B22: =B21 -> 5 | C22: 其他收入 | D22: =SUMIFS(#REF!,#REF!,"="&$E$2,#REF!,"="&$C22) -> #REF! | E22: =SUMIFS(力喆实业中国银行!$G:$G,力喆实业中国银行!$B:$B,"="&$E$2,力喆实业中国银行!$D:$D,"="&$C22) -> 0 | F22: =SUMIFS(力喆产业农商银行!$G:$G,力喆产业农商银行!$B:$B,"="&$E$2,力喆产业农商银行!$D:$D,"="&$C22) -> 0 | G22: =SUMIFS(徐洁招商银行!$G:$G,徐洁招商银行!$B:$B,"="&$E$2,徐洁招商银行!$D:$D,"="&$C22) -> 0 | H22: =SUMIFS(力喆贸易建设银行!$G:$G,力喆贸易建设银行!$B:$B,"="&$E$2,力喆贸易建设银行!$D:$D,"="&$C22) -> 0 | I22: =SUMIFS(元生万物建设银行!$G:$G,元生万物建设银行!$B:$B,"="&$E$2,元生万物建设银行!$D:$D,"="&$C22) -> 0 | J22: =SUMIFS(言吾言中国银行!$G:$G,言吾言中国银行!$B:$B,"="&$E$2,言吾言中国银行!$D:$D,"="&$C22) -> 0 | K22: =SUMIFS(力喆传媒海峡银行!$G:$G,力喆传媒海峡银行!$B:$B,"="&$E$2,力喆传媒海峡银行!$D:$D,"="&$C22) -> 0 | L22: =SUMIFS(古玩城农商银行!$G:$G,古玩城农商银行!$B:$B,"="&$E$2,古玩城农商银行!$D:$D,"="&$C22) -> 0 | M22: =SUMIFS(古玩城现金!$J:$J,古玩城现金!$B:$B,"="&$E$2) -> 0 | N22: =SUMIFS(艾泊烨海峡银行!$G:$G,艾泊烨海峡银行!$B:$B,"="&$E$2,艾泊烨海峡银行!$D:$D,"="&$C22) -> 0 | O22: 0 | P22: =SUMIFS(艾泊烨农商银行!$I:$I,艾泊烨农商银行!$B:$B,"="&$E$2,艾泊烨农商银行!$D:$D,"="&$C22) -> 0 | Q22: =SUMIFS(艾泊烨私户银行!$G:$G,艾泊烨私户银行!$B:$B,"="&$E$2,艾泊烨私户银行!$D:$D,"="&$C22) -> 0 | R22: 0 | S22: 0 | T22: =SUMIFS(易佰兴现金!$J:$J,易佰兴现金!$B:$B,"="&$E$2) -> 0 | U22: 0
B23: =B22 -> 5 | C23: 利息收入 | D23: =SUMIFS(#REF!,#REF!,"="&$E$2,#REF!,"="&$C23) -> #REF! | E23: =SUMIFS(力喆实业中国银行!$G:$G,力喆实业中国银行!$B:$B,"="&$E$2,力喆实业中国银行!$D:$D,"="&$C23) -> 0 | F23: =SUMIFS(力喆产业农商银行!$G:$G,力喆产业农商银行!$B:$B,"="&$E$2,力喆产业农商银行!$D:$D,"="&$C23) -> 0 | G23: =SUMIFS(徐洁招商银行!$G:$G,徐洁招商银行!$B:$B,"="&$E$2,徐洁招商银行!$D:$D,"="&$C23) -> 0 | H23: =SUMIFS(力喆贸易建设银行!$G:$G,力喆贸易建设银行!$B:$B,"="&$E$2,力喆贸易建设银行!$D:$D,"="&$C23) -> 0 | I23: =SUMIFS(元生万物建设银行!$G:$G,元生万物建设银行!$B:$B,"="&$E$2,元生万物建设银行!$D:$D,"="&$C23) -> 0 | J23: =SUMIFS(言吾言中国银行!$G:$G,言吾言中国银行!$B:$B,"="&$E$2,言吾言中国银行!$D:$D,"="&$C23) -> 0 | K23: =SUMIFS(力喆传媒海峡银行!$G:$G,力喆传媒海峡银行!$B:$B,"="&$E$2,力喆传媒海峡银行!$D:$D,"="&$C23) -> 0 | L23: =SUMIFS(古玩城农商银行!$L:$L,古玩城农商银行!$B:$B,"="&$E$2) -> 0 | M23: =SUMIFS(古玩城现金!$J:$J,古玩城现金!$B:$B,"="&$E$2) -> 0 | N23: =SUMIFS(艾泊烨海峡银行!$G:$G,艾泊烨海峡银行!$B:$B,"="&$E$2,艾泊烨海峡银行!$D:$D,"="&$C23) -> 0 | O23: =SUMIFS(艾泊烨招商银行!$G:$G,艾泊烨招商银行!$B:$B,"="&$E$2,艾泊烨招商银行!$D:$D,"="&$C23) -> 0 | P23: =SUMIFS(艾泊烨农商银行!$I:$I,艾泊烨农商银行!$B:$B,"="&$E$2,艾泊烨农商银行!$D:$D,"="&$C23) -> 0 | Q23: =SUMIFS(艾泊烨私户银行!$G:$G,艾泊烨私户银行!$B:$B,"="&$E$2,艾泊烨私户银行!$D:$D,"="&$C23) -> 0 | R23: =SUMIFS(易佰兴建行!$M:$M,易佰兴建行!$B:$B,"="&$E$2) -> 0 | S23: =SUMIFS(易佰兴私户!$M:$M,易佰兴私户!B:B,"="&$E$2) -> 0 | T23: =SUMIFS(易佰兴现金!$J:$J,易佰兴现金!$B:$B,"="&$E$2) -> 0 | U23: =SUMIFS(易佰兴基本户!$M:$M,易佰兴基本户!$B:$B,"="&$E$2) -> 0
B24: =B23 -> 5 | C24: 贷款转入 | E24: =SUMIFS(力喆实业中国银行!$G:$G,力喆实业中国银行!$B:$B,"="&$E$2,力喆实业中国银行!$D:$D,"="&$C24) -> 0 | F24: =SUMIFS(力喆产业农商银行!$G:$G,力喆产业农商银行!$B:$B,"="&$E$2,力喆产业农商银行!$D:$D,"="&$C24) -> 0 | G24: =SUMIFS(徐洁招商银行!$G:$G,徐洁招商银行!$B:$B,"="&$E$2,徐洁招商银行!$D:$D,"="&$C24) -> 0 | H24: =SUMIFS(力喆贸易建设银行!$G:$G,力喆贸易建设银行!$B:$B,"="&$E$2,力喆贸易建设银行!$D:$D,"="&$C24) -> 0 | J24: =SUMIFS(言吾言中国银行!$G:$G,言吾言中国银行!$B:$B,"="&$E$2,言吾言中国银行!$D:$D,"="&$C24) -> 0 | L24: 0 | M24: =SUMIFS(古玩城现金!$J:$J,古玩城现金!$B:$B,"="&$E$2) -> 0 | N24: =SUMIFS(艾泊烨海峡银行!$G:$G,艾泊烨海峡银行!$B:$B,"="&$E$2,艾泊烨海峡银行!$D:$D,"="&$C24) -> 650000 | O24: 0 | P24: =SUMIFS(艾泊烨农商银行!$I:$I,艾泊烨农商银行!$B:$B,"="&$E$2,艾泊烨农商银行!$D:$D,"="&$C24) -> 0 | Q24: =SUMIFS(艾泊烨私户银行!$G:$G,艾泊烨私户银行!$B:$B,"="&$E$2,艾泊烨私户银行!$D:$D,"="&$C24) -> 0 | R24: 0 | S24: 0 | T24: =SUMIFS(易佰兴现金!$J:$J,易佰兴现金!$B:$B,"="&$E$2) -> 0 | U24: 0
B25: =B9 -> 5 | C25: 借款转入 | E25: =SUMIFS(力喆实业中国银行!$G:$G,力喆实业中国银行!$B:$B,"="&$E$2,力喆实业中国银行!$D:$D,"="&$C25) -> 0 | F25: =SUMIFS(力喆产业农商银行!$G:$G,力喆产业农商银行!$B:$B,"="&$E$2,力喆产业农商银行!$D:$D,"="&$C25) -> 0 | G25: =SUMIFS(徐洁招商银行!$G:$G,徐洁招商银行!$B:$B,"="&$E$2,徐洁招商银行!$D:$D,"="&$C25) -> 0 | H25: =SUMIFS(力喆贸易建设银行!$G:$G,力喆贸易建设银行!$B:$B,"="&$E$2,力喆贸易建设银行!$D:$D,"="&$C25) -> 0 | J25: =SUMIFS(言吾言中国银行!$G:$G,言吾言中国银行!$B:$B,"="&$E$2,言吾言中国银行!$D:$D,"="&$C25) -> 0 | L25: =SUMIFS(古玩城农商银行!$N:$N,古玩城农商银行!$B:$B,"="&$E$2,古玩城农商银行!$D:$D,"="&$C25) -> 0 | M25: =SUMIFS(古玩城现金!$J:$J,古玩城现金!$B:$B,"="&$E$2) -> 0 | N25: =SUMIFS(艾泊烨海峡银行!$G:$G,艾泊烨海峡银行!$B:$B,"="&$E$2,艾泊烨海峡银行!$D:$D,"="&$C25) -> 95000 | O25: 0 | P25: =SUMIFS(艾泊烨农商银行!$I:$I,艾泊烨农商银行!$B:$B,"="&$E$2,艾泊烨农商银行!$D:$D,"="&$C25) -> 0 | Q25: =SUMIFS(艾泊烨私户银行!$G:$G,艾泊烨私户银行!$B:$B,"="&$E$2,艾泊烨私户银行!$D:$D,"="&$C25) -> 0 | R25: 0 | S25: 0 | T25: =SUMIFS(易佰兴现金!$J:$J,易佰兴现金!$B:$B,"="&$E$2) -> 0 | U25: 0
B26: =B25 -> 5 | C26: 收回借款 | E26: =SUMIFS(力喆实业中国银行!$G:$G,力喆实业中国银行!$B:$B,"="&$E$2,力喆实业中国银行!$D:$D,"="&$C26) -> 0 | F26: =SUMIFS(力喆产业农商银行!$G:$G,力喆产业农商银行!$B:$B,"="&$E$2,力喆产业农商银行!$D:$D,"="&$C26) -> 0 | G26: =SUMIFS(徐洁招商银行!$G:$G,徐洁招商银行!$B:$B,"="&$E$2,徐洁招商银行!$D:$D,"="&$C26) -> 0 | H26: =SUMIFS(力喆贸易建设银行!$G:$G,力喆贸易建设银行!$B:$B,"="&$E$2,力喆贸易建设银行!$D:$D,"="&$C26) -> 0 | J26: =SUMIFS(言吾言中国银行!$G:$G,言吾言中国银行!$B:$B,"="&$E$2,言吾言中国银行!$D:$D,"="&$C26) -> 0 | L26: =SUMIFS(古玩城农商银行!$N:$N,古玩城农商银行!$B:$B,"="&$E$2,古玩城农商银行!$D:$D,"="&$C26) -> 0 | M26: =SUMIFS(古玩城现金!$J:$J,古玩城现金!$B:$B,"="&$E$2) -> 0 | N26: =SUMIFS(艾泊烨海峡银行!$G:$G,艾泊烨海峡银行!$B:$B,"="&$E$2,艾泊烨海峡银行!$D:$D,"="&$C26) -> 0 | O26: 0 | P26: =SUMIFS(艾泊烨农商银行!$I:$I,艾泊烨农商银行!$B:$B,"="&$E$2,艾泊烨农商银行!$D:$D,"="&$C26) -> 0 | Q26: =SUMIFS(艾泊烨私户银行!$G:$G,艾泊烨私户银行!$B:$B,"="&$E$2,艾泊烨私户银行!$D:$D,"="&$C26) -> 0 | R26: 0 | S26: 0 | T26: =SUMIFS(易佰兴现金!$J:$J,易佰兴现金!$B:$B,"="&$E$2) -> 0 | U26: 0
B27: =B26 -> 5 | C27: 薪资、社医保 | E27: =SUMIFS(力喆实业中国银行!$G:$G,力喆实业中国银行!$B:$B,"="&$E$2,力喆实业中国银行!$D:$D,"="&$C27) -> 0 | F27: =SUMIFS(力喆产业农商银行!$G:$G,力喆产业农商银行!$B:$B,"="&$E$2,力喆产业农商银行!$D:$D,"="&$C27) -> 0 | G27: =SUMIFS(徐洁招商银行!$G:$G,徐洁招商银行!$B:$B,"="&$E$2,徐洁招商银行!$D:$D,"="&$C27) -> 0 | H27: =SUMIFS(力喆贸易建设银行!$G:$G,力喆贸易建设银行!$B:$B,"="&$E$2,力喆贸易建设银行!$D:$D,"="&$C27) -> 0 | J27: =SUMIFS(言吾言中国银行!$G:$G,言吾言中国银行!$B:$B,"="&$E$2,言吾言中国银行!$D:$D,"="&$C27) -> 0 | L27: 0 | M27: =SUMIFS(古玩城现金!$J:$J,古玩城现金!$B:$B,"="&$E$2) -> 0 | N27: =SUMIFS(艾泊烨海峡银行!$G:$G,艾泊烨海峡银行!$B:$B,"="&$E$2,艾泊烨海峡银行!$D:$D,"="&$C27) -> 19844.24 | O27: 0 | P27: =SUMIFS(艾泊烨农商银行!$I:$I,艾泊烨农商银行!$B:$B,"="&$E$2,艾泊烨农商银行!$D:$D,"="&$C27) -> 0 | Q27: =SUMIFS(艾泊烨私户银行!$G:$G,艾泊烨私户银行!$B:$B,"="&$E$2,艾泊烨私户银行!$D:$D,"="&$C27) -> 19745.39 | R27: 0 | S27: 0 | T27: =SUMIFS(易佰兴现金!$J:$J,易佰兴现金!$B:$B,"="&$E$2) -> 0 | U27: 0
B28: 合计 | D28: =SUBTOTAL(109,D6:D27) -> #REF! | E28: =SUBTOTAL(109,E6:E27) -> 0 | F28: =SUBTOTAL(109,F6:F27) -> 47832.11 | G28: =SUBTOTAL(109,G6:G27) -> 156656.91 | H28: =SUBTOTAL(109,H6:H27) -> 73229.1 | I28: =SUBTOTAL(109,I6:I27) -> 30098.25 | J28: =SUBTOTAL(109,J6:J27) -> 0 | K28: =SUBTOTAL(109,K6:K27) -> 0 | ... U28: =SUBTOTAL(109,U6:U27) -> 24300
D29: =D28-SUMIFS(#REF!,#REF!,汇总!$B$17) -> #REF! | E29: =E28-SUMIFS(力喆实业中国银行!$G:$G,力喆实业中国银行!$B:$B,"="&$E$2)-SUMIFS(力喆产业农商银行!$G:$G,力喆产业农商银行!$B:$B,"="&$E$2) -> -47832.11 | F29: =F28-SUMIFS(力喆实业中国银行!$G:$G,力喆实业中国银行!$B:$B,"="&$E$2)-SUMIFS(力喆产业农商银行!$G:$G,力喆产业农商银行!$B:$B,"="&$E$2) -> 0 | G29: =G28-SUMIFS(徐洁招商银行!$G:$G,徐洁招商银行!$B:$B,"="&$E$2) -> 0 | H29: =H28-SUMIFS(力喆贸易建设银行!$G:$G,力喆贸易建设银行!$B:$B,"="&$E$2) -> 0 | I29: =I28-SUMIFS(元生万物建设银行!$G:$G,元生万物建设银行!$B:$B,"="&$E$2) -> 0 | J29: =J28-SUMIFS(言吾言中国银行!$G:$G,言吾言中国银行!$B:$B,"="&$E$2) -> 0 | K29: =K28-SUMIFS(力喆传媒海峡银行!$G:$G,力喆传媒海峡银行!$B:$B,"="&$E$2) -> 0 | L29: =L28-SUMIFS(古玩城农商银行!$N:$N,古玩城农商银行!$B:$B,"="&$E$2) -> -24819.23 | M29: =M28-SUMIFS(古玩城农商银行!$N:$N,古玩城农商银行!$B:$B,"="&$E$2) -> -379800.43 | N29: =N28-SUMIFS(古玩城农商银行!$N:$N,古玩城农商银行!$B:$B,"="&$E$2) -> 523199.13 | O29: =O28-SUMIFS(古玩城农商银行!$N:$N,古玩城农商银行!$B:$B,"="&$E$2) -> -396000.43 | P29: =P28-SUMIFS(古玩城农商银行!$N:$N,古玩城农商银行!$B:$B,"="&$E$2) -> -380000.43 | Q29: =Q28-SUMIFS(古玩城农商银行!$N:$N,古玩城农商银行!$B:$B,"="&$E$2) -> -307802.22 | R29: =R28-SUMIFS(古玩城农商银行!$N:$N,古玩城农商银行!$B:$B,"="&$E$2) -> -50144.9 | S29: =S28-SUMIFS(古玩城农商银行!$N:$N,古玩城农商银行!$B:$B,"="&$E$2) -> -277057.2 | ... U29: =U28-SUMIFS(古玩城农商银行!$N:$N,古玩城农商银行!$B:$B,"="&$E$2) -> -371700.43
A31: 支出明细汇总表 | B31: 月份 | C31: 支出明细 | D31: =D4 -> 青翼创 | E31: =E4 -> 力喆实业 | F31: =F4 -> 力喆实业 | G31: =G4 -> 力喆实业 | H31: =H4 -> 力喆贸易 | I31: =I4 -> 元生万物 | J31: =J4 -> 言吾言 | K31: =K4 -> 力喆传媒 | L31: 古玩城 | M31: 古玩城 | N31: 艾泊烨 | O31: 艾泊烨 | P31: 艾泊烨 | Q31: 艾泊烨 | R31: 易佰兴 | S31: 易佰兴 | T31: 易佰兴 | U31: 易佰兴
B32: =B21 -> 5 | C32: 薪资 | D32: =SUMIFS(#REF!,#REF!,"="&$E$2,#REF!,"="&$C32) -> #REF! | E32: =SUMIFS(力喆实业中国银行!$H:$H,力喆实业中国银行!$B:$B,"="&$E$2,力喆实业中国银行!$D:$D,"="&$C32) -> 0 | F32: =SUMIFS(力喆产业农商银行!$H:$H,力喆产业农商银行!$B:$B,"="&$E$2,力喆产业农商银行!$D:$D,"="&$C32) -> 0 | G32: =SUMIFS(徐洁招商银行!$H:$H,徐洁招商银行!$B:$B,"="&$E$2,徐洁招商银行!$D:$D,"="&$C32) -> 26000 | H32: =SUMIFS(力喆贸易建设银行!$H:$H,力喆贸易建设银行!$B:$B,"="&$E$2,力喆贸易建设银行!$D:$D,"="&$C32) -> 25121.34 | I32: =SUMIFS(元生万物建设银行!$H:$H,元生万物建设银行!$B:$B,"="&$E$2,元生万物建设银行!$D:$D,"="&$C32) -> 0 | J32: =SUMIFS(言吾言中国银行!$H:$H,言吾言中国银行!$B:$B,"="&$E$2,言吾言中国银行!$D:$D,"="&$C32) -> 0 | K32: =SUMIFS(力喆传媒海峡银行!$H:$H,力喆传媒海峡银行!$B:$B,"="&$E$2,力喆传媒海峡银行!$D:$D,"="&$C32) -> 0 | L32: =SUMIFS(古玩城农商银行!$O:$O,古玩城农商银行!$B:$B,"="&$E$2,古玩城农商银行!$D:$D,"="&$C32) -> 34100 | M32: 0 | N32: =SUMIFS(艾泊烨海峡银行!$H:$H,艾泊烨海峡银行!$B:$B,"="&$E$2,艾泊烨海峡银行!$D:$D,"="&$C32) -> 59293.95 | O32: 0 | P32: =SUMIFS(艾泊烨农商银行!$J:$J,艾泊烨农商银行!$B:$B,"="&$E$2,艾泊烨农商银行!D:D,"="&$C32) -> 0 | Q32: =SUMIFS(艾泊烨私户银行!$H:$H,艾泊烨私户银行!$B:$B,"="&$E$2,艾泊烨私户银行!$D:$D,"="&$C32) -> 0 | R32: =SUMIFS(易佰兴建行!$P:$P,易佰兴建行!$B:$B,"="&$E$2,易佰兴建行!$D:$D,"="&$C32) -> 0 | S32: =SUMIFS(易佰兴私户!$P:$P,易佰兴私户!$B:$B,"="&$E$2,易佰兴私户!$D:$D,"="&$C32)+SUMIFS(易佰兴趋势民生银行!$H:$H,易佰兴趋势民生银行!$B:$B,"="&$E$2,易佰兴趋势民生银行!D:D,"="&$C32) -> 19001.01 | T32: =SUMIFS(易佰兴现金!$O:$O,易佰兴现金!$B:$B,"="&$E$2,易佰兴现金!D:D,"="&$C32) -> 0 | U32: =SUMIFS(易佰兴基本户!$P:$P,易佰兴基本户!$B:$B,"="&$E$2,易佰兴基本户!D:D,"="&$C32) -> 26370.73
B33: =B32 -> 5 | C33: 五险一金 | D33: =SUMIFS(#REF!,#REF!,"="&$E$2,#REF!,"="&$C33) -> #REF! | E33: =SUMIFS(力喆实业中国银行!$H:$H,力喆实业中国银行!$B:$B,"="&$E$2,力喆实业中国银行!$D:$D,"="&$C33) -> 0 | F33: =SUMIFS(力喆产业农商银行!$H:$H,力喆产业农商银行!$B:$B,"="&$E$2,力喆产业农商银行!$D:$D,"="&$C33) -> 2987.84 | G33: =SUMIFS(徐洁招商银行!$H:$H,徐洁招商银行!$B:$B,"="&$E$2,徐洁招商银行!$D:$D,"="&$C33) -> 0 | H33: =SUMIFS(力喆贸易建设银行!$H:$H,力喆贸易建设银行!$B:$B,"="&$E$2,力喆贸易建设银行!$D:$D,"="&$C33) -> 6853.33 | I33: =SUMIFS(元生万物建设银行!$H:$H,元生万物建设银行!$B:$B,"="&$E$2,元生万物建设银行!$D:$D,"="&$C33) -> 0 | J33: =SUMIFS(言吾言中国银行!$H:$H,言吾言中国银行!$B:$B,"="&$E$2,言吾言中国银行!$D:$D,"="&$C33) -> 0 | K33: =SUMIFS(力喆传媒海峡银行!$H:$H,力喆传媒海峡银行!$B:$B,"="&$E$2,力喆传媒海峡银行!$D:$D,"="&$C33) -> 0 | L33: =SUMIFS(古玩城农商银行!$O:$O,古玩城农商银行!$B:$B,"="&$E$2,古玩城农商银行!$D:$D,"="&$C33) -> 0 | M33: 0 | N33: =SUMIFS(艾泊烨海峡银行!$H:$H,艾泊烨海峡银行!$B:$B,"="&$E$2,艾泊烨海峡银行!$D:$D,"="&$C33) -> 20682.24 | O33: 0 | P33: =SUMIFS(艾泊烨农商银行!$J:$J,艾泊烨农商银行!$B:$B,"="&$E$2,艾泊烨农商银行!D:D,"="&$C33) -> 0 | Q33: =SUMIFS(艾泊烨私户银行!$H:$H,艾泊烨私户银行!$B:$B,"="&$E$2,艾泊烨私户银行!$D:$D,"="&$C33) -> 0 | R33: =SUMIFS(易佰兴建行!$P:$P,易佰兴建行!$B:$B,"="&$E$2,易佰兴建行!$D:$D,"="&$C33) -> 0 | S33: =SUMIFS(易佰兴私户!$P:$P,易佰兴私户!$B:$B,"="&$E$2,易佰兴私户!$D:$D,"="&$C33) -> 3244.38 | T33: =SUMIFS(易佰兴现金!$O:$O,易佰兴现金!$B:$B,"="&$E$2,易佰兴现金!D:D,"="&$C33) -> 0 | U33: =SUMIFS(易佰兴基本户!$P:$P,易佰兴基本户!$B:$B,"="&$E$2,易佰兴基本户!D:D,"="&$C33) -> 0
B34: =B33 -> 5 | C34: 吴华云账户 | E34: =SUMIFS(力喆实业中国银行!$H:$H,力喆实业中国银行!$B:$B,"="&$E$2,力喆实业中国银行!$D:$D,"="&$C34) -> 0 | F34: =SUMIFS(力喆产业农商银行!$H:$H,力喆产业农商银行!$B:$B,"="&$E$2,力喆产业农商银行!$D:$D,"="&$C34) -> 0 | G34: =SUMIFS(徐洁招商银行!$H:$H,徐洁招商银行!$B:$B,"="&$E$2,徐洁招商银行!$D:$D,"="&$C34) -> 0 | H34: =SUMIFS(力喆贸易建设银行!$H:$H,力喆贸易建设银行!$B:$B,"="&$E$2,力喆贸易建设银行!$D:$D,"="&$C34) -> 0 | T34: =SUMIFS(易佰兴现金!$O:$O,易佰兴现金!$B:$B,"="&$E$2,易佰兴现金!D:D,"="&$C34) -> 0
B35: =B33 -> 5 | C35: 员工保险 | D35: =SUMIFS(#REF!,#REF!,"="&$E$2,#REF!,"="&$C35) -> #REF! | E35: =SUMIFS(力喆实业中国银行!$H:$H,力喆实业中国银行!$B:$B,"="&$E$2,力喆实业中国银行!$D:$D,"="&$C35) -> 0 | F35: =SUMIFS(力喆产业农商银行!$H:$H,力喆产业农商银行!$B:$B,"="&$E$2,力喆产业农商银行!$D:$D,"="&$C35) -> 0 | G35: =SUMIFS(徐洁招商银行!$H:$H,徐洁招商银行!$B:$B,"="&$E$2,徐洁招商银行!$D:$D,"="&$C35) -> 0 | H35: =SUMIFS(力喆贸易建设银行!$H:$H,力喆贸易建设银行!$B:$B,"="&$E$2,力喆贸易建设银行!$D:$D,"="&$C35) -> 0 | I35: =SUMIFS(元生万物建设银行!$H:$H,元生万物建设银行!$B:$B,"="&$E$2,元生万物建设银行!$D:$D,"="&$C35) -> 0 | J35: =SUMIFS(言吾言中国银行!$H:$H,言吾言中国银行!$B:$B,"="&$E$2,言吾言中国银行!$D:$D,"="&$C35) -> 0 | K35: =SUMIFS(力喆传媒海峡银行!$H:$H,力喆传媒海峡银行!$B:$B,"="&$E$2,力喆传媒海峡银行!$D:$D,"="&$C35) -> 0 | L35: =SUMIFS(古玩城农商银行!$O:$O,古玩城农商银行!$B:$B,"="&$E$2,古玩城农商银行!$D:$D,"="&$C35) -> 0 | M35: 0 | N35: =SUMIFS(艾泊烨海峡银行!$H:$H,艾泊烨海峡银行!$B:$B,"="&$E$2,艾泊烨海峡银行!$D:$D,"="&$C35) -> 0 | O35: 0 | P35: =SUMIFS(艾泊烨农商银行!$J:$J,艾泊烨农商银行!$B:$B,"="&$E$2,艾泊烨农商银行!D:D,"="&$C35) -> 0 | Q35: =SUMIFS(艾泊烨私户银行!$H:$H,艾泊烨私户银行!$B:$B,"="&$E$2,艾泊烨私户银行!$D:$D,"="&$C35) -> 0 | R35: =SUMIFS(易佰兴建行!$P:$P,易佰兴建行!$B:$B,"="&$E$2,易佰兴建行!$D:$D,"="&$C35) -> 0 | S35: =SUMIFS(易佰兴私户!$P:$P,易佰兴私户!$B:$B,"="&$E$2,易佰兴私户!$D:$D,"="&$C35) -> 0 | T35: =SUMIFS(易佰兴现金!$O:$O,易佰兴现金!$B:$B,"="&$E$2,易佰兴现金!D:D,"="&$C35) -> 0 | U35: =SUMIFS(易佰兴基本户!$P:$P,易佰兴基本户!$B:$B,"="&$E$2,易佰兴基本户!D:D,"="&$C35) -> 0
B36: =B35 -> 5 | C36: 福利费 | D36: =SUMIFS(#REF!,#REF!,"="&$E$2,#REF!,"="&$C36) -> #REF! | E36: =SUMIFS(力喆实业中国银行!$H:$H,力喆实业中国银行!$B:$B,"="&$E$2,力喆实业中国银行!$D:$D,"="&$C36) -> 0 | F36: =SUMIFS(力喆产业农商银行!$H:$H,力喆产业农商银行!$B:$B,"="&$E$2,力喆产业农商银行!$D:$D,"="&$C36) -> 0 | G36: =SUMIFS(徐洁招商银行!$H:$H,徐洁招商银行!$B:$B,"="&$E$2,徐洁招商银行!$D:$D,"="&$C36) -> 0 | H36: =SUMIFS(力喆贸易建设银行!$H:$H,力喆贸易建设银行!$B:$B,"="&$E$2,力喆贸易建设银行!$D:$D,"="&$C36) -> 0 | I36: =SUMIFS(元生万物建设银行!$H:$H,元生万物建设银行!$B:$B,"="&$E$2,元生万物建设银行!$D:$D,"="&$C36) -> 0 | J36: =SUMIFS(言吾言中国银行!$H:$H,言吾言中国银行!$B:$B,"="&$E$2,言吾言中国银行!$D:$D,"="&$C36) -> 0 | K36: =SUMIFS(力喆传媒海峡银行!$H:$H,力喆传媒海峡银行!$B:$B,"="&$E$2,力喆传媒海峡银行!$D:$D,"="&$C36) -> 0 | L36: =SUMIFS(古玩城农商银行!$O:$O,古玩城农商银行!$B:$B,"="&$E$2,古玩城农商银行!$D:$D,"="&$C36) -> 0 | M36: 0 | N36: =SUMIFS(艾泊烨海峡银行!$H:$H,艾泊烨海峡银行!$B:$B,"="&$E$2,艾泊烨海峡银行!$D:$D,"="&$C36) -> 0 | O36: 0 | P36: =SUMIFS(艾泊烨农商银行!$J:$J,艾泊烨农商银行!$B:$B,"="&$E$2,艾泊烨农商银行!D:D,"="&$C36) -> 0 | Q36: =SUMIFS(艾泊烨私户银行!$H:$H,艾泊烨私户银行!$B:$B,"="&$E$2,艾泊烨私户银行!$D:$D,"="&$C36) -> 0 | R36: =SUMIFS(易佰兴建行!$P:$P,易佰兴建行!$B:$B,"="&$E$2,易佰兴建行!$D:$D,"="&$C36) -> 0 | S36: =SUMIFS(易佰兴私户!$P:$P,易佰兴私户!$B:$B,"="&$E$2,易佰兴私户!$D:$D,"="&$C36) -> 0 | T36: =SUMIFS(易佰兴现金!$O:$O,易佰兴现金!$B:$B,"="&$E$2,易佰兴现金!D:D,"="&$C36) -> 0 | U36: =SUMIFS(易佰兴基本户!$P:$P,易佰兴基本户!$B:$B,"="&$E$2,易佰兴基本户!D:D,"="&$C36) -> 0
B37: =B36 -> 5 | C37: 招待费 | D37: =SUMIFS(#REF!,#REF!,"="&$E$2,#REF!,"="&$C37) -> #REF! | E37: =SUMIFS(力喆实业中国银行!$H:$H,力喆实业中国银行!$B:$B,"="&$E$2,力喆实业中国银行!$D:$D,"="&$C37) -> 0 | F37: =SUMIFS(力喆产业农商银行!$H:$H,力喆产业农商银行!$B:$B,"="&$E$2,力喆产业农商银行!$D:$D,"="&$C37) -> 0 | G37: =SUMIFS(徐洁招商银行!$H:$H,徐洁招商银行!$B:$B,"="&$E$2,徐洁招商银行!$D:$D,"="&$C37) -> 0 | H37: =SUMIFS(力喆贸易建设银行!$H:$H,力喆贸易建设银行!$B:$B,"="&$E$2,力喆贸易建设银行!$D:$D,"="&$C37) -> 0 | I37: =SUMIFS(元生万物建设银行!$H:$H,元生万物建设银行!$B:$B,"="&$E$2,元生万物建设银行!$D:$D,"="&$C37) -> 0 | J37: =SUMIFS(言吾言中国银行!$H:$H,言吾言中国银行!$B:$B,"="&$E$2,言吾言中国银行!$D:$D,"="&$C37) -> 0 | K37: =SUMIFS(力喆传媒海峡银行!$H:$H,力喆传媒海峡银行!$B:$B,"="&$E$2,力喆传媒海峡银行!$D:$D,"="&$C37) -> 0 | L37: =SUMIFS(古玩城农商银行!$O:$O,古玩城农商银行!$B:$B,"="&$E$2,古玩城农商银行!$D:$D,"="&$C37) -> 0 | M37: 0 | N37: =SUMIFS(艾泊烨海峡银行!$H:$H,艾泊烨海峡银行!$B:$B,"="&$E$2,艾泊烨海峡银行!$D:$D,"="&$C37) -> 0 | O37: 0 | P37: =SUMIFS(艾泊烨农商银行!$J:$J,艾泊烨农商银行!$B:$B,"="&$E$2,艾泊烨农商银行!D:D,"="&$C37) -> 0 | Q37: =SUMIFS(艾泊烨私户银行!$H:$H,艾泊烨私户银行!$B:$B,"="&$E$2,艾泊烨私户银行!$D:$D,"="&$C37) -> 0 | R37: =SUMIFS(易佰兴建行!$P:$P,易佰兴建行!$B:$B,"="&$E$2,易佰兴建行!$D:$D,"="&$C37) -> 0 | S37: =SUMIFS(易佰兴私户!$P:$P,易佰兴私户!$B:$B,"="&$E$2,易佰兴私户!$D:$D,"="&$C37) -> 0 | T37: =SUMIFS(易佰兴现金!$O:$O,易佰兴现金!$B:$B,"="&$E$2,易佰兴现金!D:D,"="&$C37) -> 0 | U37: =SUMIFS(易佰兴基本户!$P:$P,易佰兴基本户!$B:$B,"="&$E$2,易佰兴基本户!D:D,"="&$C37) -> 0
B38: =B37 -> 5 | C38: 酒水费 | D38: =SUMIFS(#REF!,#REF!,"="&$E$2,#REF!,"="&$C38) -> #REF! | E38: =SUMIFS(力喆实业中国银行!$H:$H,力喆实业中国银行!$B:$B,"="&$E$2,力喆实业中国银行!$D:$D,"="&$C38) -> 0 | F38: =SUMIFS(力喆产业农商银行!$H:$H,力喆产业农商银行!$B:$B,"="&$E$2,力喆产业农商银行!$D:$D,"="&$C38) -> 0 | G38: =SUMIFS(徐洁招商银行!$H:$H,徐洁招商银行!$B:$B,"="&$E$2,徐洁招商银行!$D:$D,"="&$C38) -> 0 | H38: =SUMIFS(力喆贸易建设银行!$H:$H,力喆贸易建设银行!$B:$B,"="&$E$2,力喆贸易建设银行!$D:$D,"="&$C38) -> 0 | I38: =SUMIFS(元生万物建设银行!$H:$H,元生万物建设银行!$B:$B,"="&$E$2,元生万物建设银行!$D:$D,"="&$C38) -> 0 | J38: =SUMIFS(言吾言中国银行!$H:$H,言吾言中国银行!$B:$B,"="&$E$2,言吾言中国银行!$D:$D,"="&$C38) -> 0 | K38: =SUMIFS(力喆传媒海峡银行!$H:$H,力喆传媒海峡银行!$B:$B,"="&$E$2,力喆传媒海峡银行!$D:$D,"="&$C38) -> 0 | L38: =SUMIFS(古玩城农商银行!$O:$O,古玩城农商银行!$B:$B,"="&$E$2,古玩城农商银行!$D:$D,"="&$C38) -> 0 | M38: 0 | N38: =SUMIFS(艾泊烨海峡银行!$H:$H,艾泊烨海峡银行!$B:$B,"="&$E$2,艾泊烨海峡银行!$D:$D,"="&$C38) -> 0 | O38: 0 | P38: =SUMIFS(艾泊烨农商银行!$J:$J,艾泊烨农商银行!$B:$B,"="&$E$2,艾泊烨农商银行!D:D,"="&$C38) -> 0 | Q38: =SUMIFS(艾泊烨私户银行!$H:$H,艾泊烨私户银行!$B:$B,"="&$E$2,艾泊烨私户银行!$D:$D,"="&$C38) -> 0 | R38: =SUMIFS(易佰兴建行!$P:$P,易佰兴建行!$B:$B,"="&$E$2,易佰兴建行!$D:$D,"="&$C38) -> 0 | S38: =SUMIFS(易佰兴私户!$P:$P,易佰兴私户!$B:$B,"="&$E$2,易佰兴私户!$D:$D,"="&$C38) -> 0 | T38: =SUMIFS(易佰兴现金!$O:$O,易佰兴现金!$B:$B,"="&$E$2,易佰兴现金!D:D,"="&$C38) -> 0 | U38: =SUMIFS(易佰兴基本户!$P:$P,易佰兴基本户!$B:$B,"="&$E$2,易佰兴基本户!D:D,"="&$C38) -> 0
B39: =B38 -> 5 | C39: 公共关系费用 | D39: =SUMIFS(#REF!,#REF!,"="&$E$2,#REF!,"="&$C39) -> #REF! | E39: =SUMIFS(力喆实业中国银行!$H:$H,力喆实业中国银行!$B:$B,"="&$E$2,力喆实业中国银行!$D:$D,"="&$C39) -> 0 | F39: =SUMIFS(力喆产业农商银行!$H:$H,力喆产业农商银行!$B:$B,"="&$E$2,力喆产业农商银行!$D:$D,"="&$C39) -> 0 | G39: =SUMIFS(徐洁招商银行!$H:$H,徐洁招商银行!$B:$B,"="&$E$2,徐洁招商银行!$D:$D,"="&$C39) -> 0 | H39: =SUMIFS(力喆贸易建设银行!$H:$H,力喆贸易建设银行!$B:$B,"="&$E$2,力喆贸易建设银行!$D:$D,"="&$C39) -> 0 | I39: =SUMIFS(元生万物建设银行!$H:$H,元生万物建设银行!$B:$B,"="&$E$2,元生万物建设银行!$D:$D,"="&$C39) -> 0 | J39: =SUMIFS(言吾言中国银行!$H:$H,言吾言中国银行!$B:$B,"="&$E$2,言吾言中国银行!$D:$D,"="&$C39) -> 0 | K39: =SUMIFS(力喆传媒海峡银行!$H:$H,力喆传媒海峡银行!$B:$B,"="&$E$2,力喆传媒海峡银行!$D:$D,"="&$C39) -> 0 | L39: =SUMIFS(古玩城农商银行!$O:$O,古玩城农商银行!$B:$B,"="&$E$2,古玩城农商银行!$D:$D,"="&$C39) -> 0 | M39: 0 | N39: =SUMIFS(艾泊烨海峡银行!$H:$H,艾泊烨海峡银行!$B:$B,"="&$E$2,艾泊烨海峡银行!$D:$D,"="&$C39) -> 0 | O39: 0 | P39: =SUMIFS(艾泊烨农商银行!$J:$J,艾泊烨农商银行!$B:$B,"="&$E$2,艾泊烨农商银行!D:D,"="&$C39) -> 0 | Q39: =SUMIFS(艾泊烨私户银行!$H:$H,艾泊烨私户银行!$B:$B,"="&$E$2,艾泊烨私户银行!$D:$D,"="&$C39) -> 0 | R39: =SUMIFS(易佰兴建行!$P:$P,易佰兴建行!$B:$B,"="&$E$2,易佰兴建行!$D:$D,"="&$C39) -> 0 | S39: =SUMIFS(易佰兴私户!$P:$P,易佰兴私户!$B:$B,"="&$E$2,易佰兴私户!$D:$D,"="&$C39) -> 0 | T39: =SUMIFS(易佰兴现金!$O:$O,易佰兴现金!$B:$B,"="&$E$2,易佰兴现金!D:D,"="&$C39) -> 0 | U39: =SUMIFS(易佰兴基本户!$P:$P,易佰兴基本户!$B:$B,"="&$E$2,易佰兴基本户!D:D,"="&$C39) -> 0
B40: =B39 -> 5 | C40: 办公费 | D40: =SUMIFS(#REF!,#REF!,"="&$E$2,#REF!,"="&$C40) -> #REF! | E40: =SUMIFS(力喆实业中国银行!$H:$H,力喆实业中国银行!$B:$B,"="&$E$2,力喆实业中国银行!$D:$D,"="&$C40) -> 0 | F40: =SUMIFS(力喆产业农商银行!$H:$H,力喆产业农商银行!$B:$B,"="&$E$2,力喆产业农商银行!$D:$D,"="&$C40) -> 0 | G40: =SUMIFS(徐洁招商银行!$H:$H,徐洁招商银行!$B:$B,"="&$E$2,徐洁招商银行!$D:$D,"="&$C40) -> 0 | H40: =SUMIFS(力喆贸易建设银行!$H:$H,力喆贸易建设银行!$B:$B,"="&$E$2,力喆贸易建设银行!$D:$D,"="&$C40) -> 0 | I40: =SUMIFS(元生万物建设银行!$H:$H,元生万物建设银行!$B:$B,"="&$E$2,元生万物建设银行!$D:$D,"="&$C40) -> 0 | J40: =SUMIFS(言吾言中国银行!$H:$H,言吾言中国银行!$B:$B,"="&$E$2,言吾言中国银行!$D:$D,"="&$C40) -> 0 | K40: =SUMIFS(力喆传媒海峡银行!$H:$H,力喆传媒海峡银行!$B:$B,"="&$E$2,力喆传媒海峡银行!$D:$D,"="&$C40) -> 0 | L40: =SUMIFS(古玩城农商银行!$O:$O,古玩城农商银行!$B:$B,"="&$E$2,古玩城农商银行!$D:$D,"="&$C40) -> 731.8 | M40: 0 | N40: =SUMIFS(艾泊烨海峡银行!$H:$H,艾泊烨海峡银行!$B:$B,"="&$E$2,艾泊烨海峡银行!$D:$D,"="&$C40) -> 0 | O40: 0 | P40: =SUMIFS(艾泊烨农商银行!$J:$J,艾泊烨农商银行!$B:$B,"="&$E$2,艾泊烨农商银行!D:D,"="&$C40) -> 0 | Q40: =SUMIFS(艾泊烨私户银行!$H:$H,艾泊烨私户银行!$B:$B,"="&$E$2,艾泊烨私户银行!$D:$D,"="&$C40) -> 0 | R40: =SUMIFS(易佰兴建行!$P:$P,易佰兴建行!$B:$B,"="&$E$2,易佰兴建行!$D:$D,"="&$C40) -> 449 | S40: =SUMIFS(易佰兴私户!$P:$P,易佰兴私户!$B:$B,"="&$E$2,易佰兴私户!$D:$D,"="&$C40) -> 350 | T40: =SUMIFS(易佰兴现金!$O:$O,易佰兴现金!$B:$B,"="&$E$2,易佰兴现金!D:D,"="&$C40) -> 0 | U40: =SUMIFS(易佰兴基本户!$P:$P,易佰兴基本户!$B:$B,"="&$E$2,易佰兴基本户!D:D,"="&$C40) -> 0
B41: =B40 -> 5 | C41: 低值易耗品 | D41: =SUMIFS(#REF!,#REF!,"="&$E$2,#REF!,"="&$C41) -> #REF! | E41: =SUMIFS(力喆实业中国银行!$H:$H,力喆实业中国银行!$B:$B,"="&$E$2,力喆实业中国银行!$D:$D,"="&$C41) -> 0 | F41: =SUMIFS(力喆产业农商银行!$H:$H,力喆产业农商银行!$B:$B,"="&$E$2,力喆产业农商银行!$D:$D,"="&$C41) -> 0 | G41: =SUMIFS(徐洁招商银行!$H:$H,徐洁招商银行!$B:$B,"="&$E$2,徐洁招商银行!$D:$D,"="&$C41) -> 0 | H41: =SUMIFS(力喆贸易建设银行!$H:$H,力喆贸易建设银行!$B:$B,"="&$E$2,力喆贸易建设银行!$D:$D,"="&$C41) -> 0 | I41: =SUMIFS(元生万物建设银行!$H:$H,元生万物建设银行!$B:$B,"="&$E$2,元生万物建设银行!$D:$D,"="&$C41) -> 0 | J41: =SUMIFS(言吾言中国银行!$H:$H,言吾言中国银行!$B:$B,"="&$E$2,言吾言中国银行!$D:$D,"="&$C41) -> 0 | K41: =SUMIFS(力喆传媒海峡银行!$H:$H,力喆传媒海峡银行!$B:$B,"="&$E$2,力喆传媒海峡银行!$D:$D,"="&$C41) -> 0 | L41: =SUMIFS(古玩城农商银行!$O:$O,古玩城农商银行!$B:$B,"="&$E$2,古玩城农商银行!$D:$D,"="&$C41) -> 0 | M41: 0 | N41: =SUMIFS(艾泊烨海峡银行!$H:$H,艾泊烨海峡银行!$B:$B,"="&$E$2,艾泊烨海峡银行!$D:$D,"="&$C41) -> 0 | O41: 0 | P41: =SUMIFS(艾泊烨农商银行!$J:$J,艾泊烨农商银行!$B:$B,"="&$E$2,艾泊烨农商银行!D:D,"="&$C41) -> 0 | Q41: =SUMIFS(艾泊烨私户银行!$H:$H,艾泊烨私户银行!$B:$B,"="&$E$2,艾泊烨私户银行!$D:$D,"="&$C41) -> 0 | R41: =SUMIFS(易佰兴建行!$P:$P,易佰兴建行!$B:$B,"="&$E$2,易佰兴建行!$D:$D,"="&$C41) -> 0 | S41: =SUMIFS(易佰兴私户!$P:$P,易佰兴私户!$B:$B,"="&$E$2,易佰兴私户!$D:$D,"="&$C41) -> 139 | T41: =SUMIFS(易佰兴现金!$O:$O,易佰兴现金!$B:$B,"="&$E$2,易佰兴现金!D:D,"="&$C41) -> 0 | U41: =SUMIFS(易佰兴基本户!$P:$P,易佰兴基本户!$B:$B,"="&$E$2,易佰兴基本户!D:D,"="&$C41) -> 0
B42: =B41 -> 5 | C42: 快递邮电费 | D42: =SUMIFS(#REF!,#REF!,"="&$E$2,#REF!,"="&$C42) -> #REF! | E42: =SUMIFS(力喆实业中国银行!$H:$H,力喆实业中国银行!$B:$B,"="&$E$2,力喆实业中国银行!$D:$D,"="&$C42) -> 0 | F42: =SUMIFS(力喆产业农商银行!$H:$H,力喆产业农商银行!$B:$B,"="&$E$2,力喆产业农商银行!$D:$D,"="&$C42) -> 0 | G42: =SUMIFS(徐洁招商银行!$H:$H,徐洁招商银行!$B:$B,"="&$E$2,徐洁招商银行!$D:$D,"="&$C42) -> 0 | H42: =SUMIFS(力喆贸易建设银行!$H:$H,力喆贸易建设银行!$B:$B,"="&$E$2,力喆贸易建设银行!$D:$D,"="&$C42) -> 0 | I42: =SUMIFS(元生万物建设银行!$H:$H,元生万物建设银行!$B:$B,"="&$E$2,元生万物建设银行!$D:$D,"="&$C42) -> 0 | J42: =SUMIFS(言吾言中国银行!$H:$H,言吾言中国银行!$B:$B,"="&$E$2,言吾言中国银行!$D:$D,"="&$C42) -> 0 | K42: =SUMIFS(力喆传媒海峡银行!$H:$H,力喆传媒海峡银行!$B:$B,"="&$E$2,力喆传媒海峡银行!$D:$D,"="&$C42) -> 0 | L42: =SUMIFS(古玩城农商银行!$O:$O,古玩城农商银行!$B:$B,"="&$E$2,古玩城农商银行!$D:$D,"="&$C42) -> 0 | M42: 0 | N42: =SUMIFS(艾泊烨海峡银行!$H:$H,艾泊烨海峡银行!$B:$B,"="&$E$2,艾泊烨海峡银行!$D:$D,"="&$C42) -> 0 | O42: 0 | P42: =SUMIFS(艾泊烨农商银行!$J:$J,艾泊烨农商银行!$B:$B,"="&$E$2,艾泊烨农商银行!D:D,"="&$C42) -> 0 | Q42: =SUMIFS(艾泊烨私户银行!$H:$H,艾泊烨私户银行!$B:$B,"="&$E$2,艾泊烨私户银行!$D:$D,"="&$C42) -> 0 | R42: =SUMIFS(易佰兴建行!$P:$P,易佰兴建行!$B:$B,"="&$E$2,易佰兴建行!$D:$D,"="&$C42) -> 53 | S42: =SUMIFS(易佰兴私户!$P:$P,易佰兴私户!$B:$B,"="&$E$2,易佰兴私户!$D:$D,"="&$C42) -> 0 | T42: =SUMIFS(易佰兴现金!$O:$O,易佰兴现金!$B:$B,"="&$E$2,易佰兴现金!D:D,"="&$C42) -> 0 | U42: =SUMIFS(易佰兴基本户!$P:$P,易佰兴基本户!$B:$B,"="&$E$2,易佰兴基本户!D:D,"="&$C42) -> 0
B43: =B42 -> 5 | C43: 通讯、宽带费 | D43: =SUMIFS(#REF!,#REF!,"="&$E$2,#REF!,"="&$C43) -> #REF! | E43: =SUMIFS(力喆实业中国银行!$H:$H,力喆实业中国银行!$B:$B,"="&$E$2,力喆实业中国银行!$D:$D,"="&$C43) -> 0 | F43: =SUMIFS(力喆产业农商银行!$H:$H,力喆产业农商银行!$B:$B,"="&$E$2,力喆产业农商银行!$D:$D,"="&$C43) -> 249 | G43: =SUMIFS(徐洁招商银行!$H:$H,徐洁招商银行!$B:$B,"="&$E$2,徐洁招商银行!$D:$D,"="&$C43) -> 0 | H43: =SUMIFS(力喆贸易建设银行!$H:$H,力喆贸易建设银行!$B:$B,"="&$E$2,力喆贸易建设银行!$D:$D,"="&$C43) -> 0 | I43: =SUMIFS(元生万物建设银行!$H:$H,元生万物建设银行!$B:$B,"="&$E$2,元生万物建设银行!$D:$D,"="&$C43) -> 0 | J43: =SUMIFS(言吾言中国银行!$H:$H,言吾言中国银行!$B:$B,"="&$E$2,言吾言中国银行!$D:$D,"="&$C43) -> 0 | K43: =SUMIFS(力喆传媒海峡银行!$H:$H,力喆传媒海峡银行!$B:$B,"="&$E$2,力喆传媒海峡银行!$D:$D,"="&$C43) -> 0 | L43: =SUMIFS(古玩城农商银行!$O:$O,古玩城农商银行!$B:$B,"="&$E$2,古玩城农商银行!$D:$D,"="&$C43) -> 50 | M43: 0 | N43: =SUMIFS(艾泊烨海峡银行!$H:$H,艾泊烨海峡银行!$B:$B,"="&$E$2,艾泊烨海峡银行!$D:$D,"="&$C43) -> 0 | O43: 0 | P43: =SUMIFS(艾泊烨农商银行!$J:$J,艾泊烨农商银行!$B:$B,"="&$E$2,艾泊烨农商银行!D:D,"="&$C43) -> 0 | Q43: =SUMIFS(艾泊烨私户银行!$H:$H,艾泊烨私户银行!$B:$B,"="&$E$2,艾泊烨私户银行!$D:$D,"="&$C43) -> 100 | R43: =SUMIFS(易佰兴建行!$P:$P,易佰兴建行!$B:$B,"="&$E$2,易佰兴建行!$D:$D,"="&$C43) -> 0 | S43: =SUMIFS(易佰兴私户!$P:$P,易佰兴私户!$B:$B,"="&$E$2,易佰兴私户!$D:$D,"="&$C43) -> 0 | T43: =SUMIFS(易佰兴现金!$O:$O,易佰兴现金!$B:$B,"="&$E$2,易佰兴现金!D:D,"="&$C43) -> 0 | U43: =SUMIFS(易佰兴基本户!$P:$P,易佰兴基本户!$B:$B,"="&$E$2,易佰兴基本户!D:D,"="&$C43) -> 415
B44: =B43 -> 5 | C44: 营销费用 | E44: =SUMIFS(力喆实业中国银行!$H:$H,力喆实业中国银行!$B:$B,"="&$E$2,力喆实业中国银行!$D:$D,"="&$C44) -> 0 | F44: =SUMIFS(力喆产业农商银行!$H:$H,力喆产业农商银行!$B:$B,"="&$E$2,力喆产业农商银行!$D:$D,"="&$C44) -> 0 | G44: =SUMIFS(徐洁招商银行!$H:$H,徐洁招商银行!$B:$B,"="&$E$2,徐洁招商银行!$D:$D,"="&$C44) -> 0 | H44: =SUMIFS(力喆贸易建设银行!$H:$H,力喆贸易建设银行!$B:$B,"="&$E$2,力喆贸易建设银行!$D:$D,"="&$C44) -> 0 | L44: =SUMIFS(古玩城农商银行!$O:$O,古玩城农商银行!$B:$B,"="&$E$2,古玩城农商银行!$D:$D,"="&$C44) -> 0 | M44: 0 | N44: =SUMIFS(艾泊烨海峡银行!$H:$H,艾泊烨海峡银行!$B:$B,"="&$E$2,艾泊烨海峡银行!$D:$D,"="&$C44) -> 0 | O44: 0 | P44: =SUMIFS(艾泊烨农商银行!$J:$J,艾泊烨农商银行!$B:$B,"="&$E$2,艾泊烨农商银行!D:D,"="&$C44) -> 0 | Q44: =SUMIFS(艾泊烨私户银行!$H:$H,艾泊烨私户银行!$B:$B,"="&$E$2,艾泊烨私户银行!$D:$D,"="&$C44) -> 0 | R44: =SUMIFS(易佰兴建行!$P:$P,易佰兴建行!$B:$B,"="&$E$2,易佰兴建行!$D:$D,"="&$C44) -> 0 | S44: =SUMIFS(易佰兴私户!$P:$P,易佰兴私户!$B:$B,"="&$E$2,易佰兴私户!$D:$D,"="&$C44) -> 0 | T44: =SUMIFS(易佰兴现金!$O:$O,易佰兴现金!$B:$B,"="&$E$2,易佰兴现金!D:D,"="&$C44) -> 0 | U44: =SUMIFS(易佰兴基本户!$P:$P,易佰兴基本户!$B:$B,"="&$E$2,易佰兴基本户!D:D,"="&$C44) -> 0
B45: =B43 -> 5 | C45: 差旅费 | D45: =SUMIFS(#REF!,#REF!,"="&$E$2,#REF!,"="&$C45) -> #REF! | E45: =SUMIFS(力喆实业中国银行!$H:$H,力喆实业中国银行!$B:$B,"="&$E$2,力喆实业中国银行!$D:$D,"="&$C45) -> 0 | F45: =SUMIFS(力喆产业农商银行!$H:$H,力喆产业农商银行!$B:$B,"="&$E$2,力喆产业农商银行!$D:$D,"="&$C45) -> 0 | G45: =SUMIFS(徐洁招商银行!$H:$H,徐洁招商银行!$B:$B,"="&$E$2,徐洁招商银行!$D:$D,"="&$C45) -> 0 | H45: =SUMIFS(力喆贸易建设银行!$H:$H,力喆贸易建设银行!$B:$B,"="&$E$2,力喆贸易建设银行!$D:$D,"="&$C45) -> 0 | I45: =SUMIFS(元生万物建设银行!$H:$H,元生万物建设银行!$B:$B,"="&$E$2,元生万物建设银行!$D:$D,"="&$C45) -> 0 | J45: =SUMIFS(言吾言中国银行!$H:$H,言吾言中国银行!$B:$B,"="&$E$2,言吾言中国银行!$D:$D,"="&$C45) -> 0 | K45: =SUMIFS(力喆传媒海峡银行!$H:$H,力喆传媒海峡银行!$B:$B,"="&$E$2,力喆传媒海峡银行!$D:$D,"="&$C45) -> 0 | L45: =SUMIFS(古玩城农商银行!$O:$O,古玩城农商银行!$B:$B,"="&$E$2,古玩城农商银行!$D:$D,"="&$C45) -> 0 | M45: 0 | N45: =SUMIFS(艾泊烨海峡银行!$H:$H,艾泊烨海峡银行!$B:$B,"="&$E$2,艾泊烨海峡银行!$D:$D,"="&$C45) -> 0 | O45: 0 | P45: =SUMIFS(艾泊烨农商银行!$J:$J,艾泊烨农商银行!$B:$B,"="&$E$2,艾泊烨农商银行!D:D,"="&$C45) -> 0 | Q45: =SUMIFS(艾泊烨私户银行!$H:$H,艾泊烨私户银行!$B:$B,"="&$E$2,艾泊烨私户银行!$D:$D,"="&$C45) -> 0 | R45: =SUMIFS(易佰兴建行!$P:$P,易佰兴建行!$B:$B,"="&$E$2,易佰兴建行!$D:$D,"="&$C45) -> 0 | S45: =SUMIFS(易佰兴私户!$P:$P,易佰兴私户!$B:$B,"="&$E$2,易佰兴私户!$D:$D,"="&$C45) -> 0 | T45: =SUMIFS(易佰兴现金!$O:$O,易佰兴现金!$B:$B,"="&$E$2,易佰兴现金!D:D,"="&$C45) -> 0 | U45: =SUMIFS(易佰兴基本户!$P:$P,易佰兴基本户!$B:$B,"="&$E$2,易佰兴基本户!D:D,"="&$C45) -> 0
B46: =B44 -> 5 | C46: 退押金 | D46: =SUMIFS(#REF!,#REF!,"="&$E$2,#REF!,"="&$C46) -> #REF! | E46: =SUMIFS(力喆实业中国银行!$H:$H,力喆实业中国银行!$B:$B,"="&$E$2,力喆实业中国银行!$D:$D,"="&$C46) -> 0 | F46: =SUMIFS(力喆产业农商银行!$H:$H,力喆产业农商银行!$B:$B,"="&$E$2,力喆产业农商银行!$D:$D,"="&$C46) -> 0 | G46: =SUMIFS(徐洁招商银行!$H:$H,徐洁招商银行!$B:$B,"="&$E$2,徐洁招商银行!$D:$D,"="&$C46) -> 0 | H46: =SUMIFS(力喆贸易建设银行!$H:$H,力喆贸易建设银行!$B:$B,"="&$E$2,力喆贸易建设银行!$D:$D,"="&$C46) -> 0 | L46: =SUMIFS(古玩城农商银行!$O:$O,古玩城农商银行!$B:$B,"="&$E$2,古玩城农商银行!$D:$D,"="&$C46) -> 9000 | M46: 0 | N46: =SUMIFS(艾泊烨海峡银行!$H:$H,艾泊烨海峡银行!$B:$B,"="&$E$2,艾泊烨海峡银行!$D:$D,"="&$C46) -> 0 | O46: 0 | P46: =SUMIFS(艾泊烨农商银行!$J:$J,艾泊烨农商银行!$B:$B,"="&$E$2,艾泊烨农商银行!D:D,"="&$C46) -> 0 | Q46: =SUMIFS(艾泊烨私户银行!$H:$H,艾泊烨私户银行!$B:$B,"="&$E$2,艾泊烨私户银行!$D:$D,"="&$C46) -> 0 | R46: =SUMIFS(易佰兴建行!$P:$P,易佰兴建行!$B:$B,"="&$E$2,易佰兴建行!$D:$D,"="&$C46) -> 770.78 | S46: =SUMIFS(易佰兴私户!$P:$P,易佰兴私户!$B:$B,"="&$E$2,易佰兴私户!$D:$D,"="&$C46) -> 0 | T46: =SUMIFS(易佰兴现金!$O:$O,易佰兴现金!$B:$B,"="&$E$2,易佰兴现金!D:D,"="&$C46) -> 0 | U46: =SUMIFS(易佰兴基本户!$P:$P,易佰兴基本户!$B:$B,"="&$E$2,易佰兴基本户!D:D,"="&$C46) -> 0
B47: =B45 -> 5 | C47: 油费 | D47: =SUMIFS(#REF!,#REF!,"="&$E$2,#REF!,"="&$C47) -> #REF! | E47: =SUMIFS(力喆实业中国银行!$H:$H,力喆实业中国银行!$B:$B,"="&$E$2,力喆实业中国银行!$D:$D,"="&$C47) -> 0 | F47: =SUMIFS(力喆产业农商银行!$H:$H,力喆产业农商银行!$B:$B,"="&$E$2,力喆产业农商银行!$D:$D,"="&$C47) -> 0 | G47: =SUMIFS(徐洁招商银行!$H:$H,徐洁招商银行!$B:$B,"="&$E$2,徐洁招商银行!$D:$D,"="&$C47) -> 0 | H47: =SUMIFS(力喆贸易建设银行!$H:$H,力喆贸易建设银行!$B:$B,"="&$E$2,力喆贸易建设银行!$D:$D,"="&$C47) -> 0 | I47: =SUMIFS(元生万物建设银行!$H:$H,元生万物建设银行!$B:$B,"="&$E$2,元生万物建设银行!$D:$D,"="&$C47) -> 0 | J47: =SUMIFS(言吾言中国银行!$H:$H,言吾言中国银行!$B:$B,"="&$E$2,言吾言中国银行!$D:$D,"="&$C47) -> 0 | K47: =SUMIFS(力喆传媒海峡银行!$H:$H,力喆传媒海峡银行!$B:$B,"="&$E$2,力喆传媒海峡银行!$D:$D,"="&$C47) -> 0 | L47: =SUMIFS(古玩城农商银行!$O:$O,古玩城农商银行!$B:$B,"="&$E$2,古玩城农商银行!$D:$D,"="&$C47) -> 0 | M47: 0 | N47: =SUMIFS(艾泊烨海峡银行!$H:$H,艾泊烨海峡银行!$B:$B,"="&$E$2,艾泊烨海峡银行!$D:$D,"="&$C47) -> 0 | O47: 0 | P47: =SUMIFS(艾泊烨农商银行!$J:$J,艾泊烨农商银行!$B:$B,"="&$E$2,艾泊烨农商银行!D:D,"="&$C47) -> 0 | Q47: =SUMIFS(艾泊烨私户银行!$H:$H,艾泊烨私户银行!$B:$B,"="&$E$2,艾泊烨私户银行!$D:$D,"="&$C47) -> 0 | R47: =SUMIFS(易佰兴建行!$P:$P,易佰兴建行!$B:$B,"="&$E$2,易佰兴建行!$D:$D,"="&$C47) -> 0 | S47: =SUMIFS(易佰兴私户!$P:$P,易佰兴私户!$B:$B,"="&$E$2,易佰兴私户!$D:$D,"="&$C47) -> 0 | T47: =SUMIFS(易佰兴现金!$O:$O,易佰兴现金!$B:$B,"="&$E$2,易佰兴现金!D:D,"="&$C47) -> 0 | U47: =SUMIFS(易佰兴基本户!$P:$P,易佰兴基本户!$B:$B,"="&$E$2,易佰兴基本户!D:D,"="&$C47) -> 0
B48: =B47 -> 5 | C48: 油费（闽A013LZ） | D48: =SUMIFS(#REF!,#REF!,"="&$E$2,#REF!,"="&$C48) -> #REF! | E48: =SUMIFS(力喆实业中国银行!$H:$H,力喆实业中国银行!$B:$B,"="&$E$2,力喆实业中国银行!$D:$D,"="&$C48) -> 0 | F48: =SUMIFS(力喆产业农商银行!$H:$H,力喆产业农商银行!$B:$B,"="&$E$2,力喆产业农商银行!$D:$D,"="&$C48) -> 0 | G48: =SUMIFS(徐洁招商银行!$H:$H,徐洁招商银行!$B:$B,"="&$E$2,徐洁招商银行!$D:$D,"="&$C48) -> 0 | H48: =SUMIFS(力喆贸易建设银行!$H:$H,力喆贸易建设银行!$B:$B,"="&$E$2,力喆贸易建设银行!$D:$D,"="&$C48) -> 0 | I48: =SUMIFS(元生万物建设银行!$H:$H,元生万物建设银行!$B:$B,"="&$E$2,元生万物建设银行!$D:$D,"="&$C48) -> 0 | J48: =SUMIFS(言吾言中国银行!$H:$H,言吾言中国银行!$B:$B,"="&$E$2,言吾言中国银行!$D:$D,"="&$C48) -> 0 | K48: =SUMIFS(力喆传媒海峡银行!$H:$H,力喆传媒海峡银行!$B:$B,"="&$E$2,力喆传媒海峡银行!$D:$D,"="&$C48) -> 0 | L48: =SUMIFS(古玩城农商银行!$O:$O,古玩城农商银行!$B:$B,"="&$E$2,古玩城农商银行!$D:$D,"="&$C48) -> 0 | M48: 0 | N48: =SUMIFS(艾泊烨海峡银行!$H:$H,艾泊烨海峡银行!$B:$B,"="&$E$2,艾泊烨海峡银行!$D:$D,"="&$C48) -> 0 | O48: 0 | P48: =SUMIFS(艾泊烨农商银行!$J:$J,艾泊烨农商银行!$B:$B,"="&$E$2,艾泊烨农商银行!D:D,"="&$C48) -> 0 | Q48: =SUMIFS(艾泊烨私户银行!$H:$H,艾泊烨私户银行!$B:$B,"="&$E$2,艾泊烨私户银行!$D:$D,"="&$C48) -> 0 | R48: =SUMIFS(易佰兴建行!$P:$P,易佰兴建行!$B:$B,"="&$E$2,易佰兴建行!$D:$D,"="&$C48) -> 0 | S48: =SUMIFS(易佰兴私户!$P:$P,易佰兴私户!$B:$B,"="&$E$2,易佰兴私户!$D:$D,"="&$C48) -> 0 | T48: =SUMIFS(易佰兴现金!$O:$O,易佰兴现金!$B:$B,"="&$E$2,易佰兴现金!D:D,"="&$C48) -> 0 | U48: =SUMIFS(易佰兴基本户!$P:$P,易佰兴基本户!$B:$B,"="&$E$2,易佰兴基本户!D:D,"="&$C48) -> 0
B49: =B48 -> 5 | C49: 油费（闽AD10200） | D49: =SUMIFS(#REF!,#REF!,"="&$E$2,#REF!,"="&$C49) -> #REF! | E49: =SUMIFS(力喆实业中国银行!$H:$H,力喆实业中国银行!$B:$B,"="&$E$2,力喆实业中国银行!$D:$D,"="&$C49) -> 0 | F49: =SUMIFS(力喆产业农商银行!$H:$H,力喆产业农商银行!$B:$B,"="&$E$2,力喆产业农商银行!$D:$D,"="&$C49) -> 0 | G49: =SUMIFS(徐洁招商银行!$H:$H,徐洁招商银行!$B:$B,"="&$E$2,徐洁招商银行!$D:$D,"="&$C49) -> 0 | H49: =SUMIFS(力喆贸易建设银行!$H:$H,力喆贸易建设银行!$B:$B,"="&$E$2,力喆贸易建设银行!$D:$D,"="&$C49) -> 0 | I49: =SUMIFS(元生万物建设银行!$H:$H,元生万物建设银行!$B:$B,"="&$E$2,元生万物建设银行!$D:$D,"="&$C49) -> 0 | J49: =SUMIFS(言吾言中国银行!$H:$H,言吾言中国银行!$B:$B,"="&$E$2,言吾言中国银行!$D:$D,"="&$C49) -> 0 | K49: =SUMIFS(力喆传媒海峡银行!$H:$H,力喆传媒海峡银行!$B:$B,"="&$E$2,力喆传媒海峡银行!$D:$D,"="&$C49) -> 0 | L49: =SUMIFS(古玩城农商银行!$O:$O,古玩城农商银行!$B:$B,"="&$E$2,古玩城农商银行!$D:$D,"="&$C49) -> 0 | M49: 0 | N49: =SUMIFS(艾泊烨海峡银行!$H:$H,艾泊烨海峡银行!$B:$B,"="&$E$2,艾泊烨海峡银行!$D:$D,"="&$C49) -> 0 | O49: 0 | P49: =SUMIFS(艾泊烨农商银行!$J:$J,艾泊烨农商银行!$B:$B,"="&$E$2,艾泊烨农商银行!D:D,"="&$C49) -> 0 | Q49: =SUMIFS(艾泊烨私户银行!$H:$H,艾泊烨私户银行!$B:$B,"="&$E$2,艾泊烨私户银行!$D:$D,"="&$C49) -> 0 | R49: =SUMIFS(易佰兴建行!$P:$P,易佰兴建行!$B:$B,"="&$E$2,易佰兴建行!$D:$D,"="&$C49) -> 0 | S49: =SUMIFS(易佰兴私户!$P:$P,易佰兴私户!$B:$B,"="&$E$2,易佰兴私户!$D:$D,"="&$C49) -> 0 | T49: =SUMIFS(易佰兴现金!$O:$O,易佰兴现金!$B:$B,"="&$E$2,易佰兴现金!D:D,"="&$C49) -> 0 | U49: =SUMIFS(易佰兴基本户!$P:$P,易佰兴基本户!$B:$B,"="&$E$2,易佰兴基本户!D:D,"="&$C49) -> 0
B50: =B49 -> 5 | C50: 车辆保险费 | D50: =SUMIFS(#REF!,#REF!,"="&$E$2,#REF!,"="&$C50) -> #REF! | E50: =SUMIFS(力喆实业中国银行!$H:$H,力喆实业中国银行!$B:$B,"="&$E$2,力喆实业中国银行!$D:$D,"="&$C50) -> 0 | F50: =SUMIFS(力喆产业农商银行!$H:$H,力喆产业农商银行!$B:$B,"="&$E$2,力喆产业农商银行!$D:$D,"="&$C50) -> 0 | G50: =SUMIFS(徐洁招商银行!$H:$H,徐洁招商银行!$B:$B,"="&$E$2,徐洁招商银行!$D:$D,"="&$C50) -> 5898.84 | H50: =SUMIFS(力喆贸易建设银行!$H:$H,力喆贸易建设银行!$B:$B,"="&$E$2,力喆贸易建设银行!$D:$D,"="&$C50) -> 0 | I50: =SUMIFS(元生万物建设银行!$H:$H,元生万物建设银行!$B:$B,"="&$E$2,元生万物建设银行!$D:$D,"="&$C50) -> 0 | J50: =SUMIFS(言吾言中国银行!$H:$H,言吾言中国银行!$B:$B,"="&$E$2,言吾言中国银行!$D:$D,"="&$C50) -> 0 | K50: =SUMIFS(力喆传媒海峡银行!$H:$H,力喆传媒海峡银行!$B:$B,"="&$E$2,力喆传媒海峡银行!$D:$D,"="&$C50) -> 0 | L50: =SUMIFS(古玩城农商银行!$O:$O,古玩城农商银行!$B:$B,"="&$E$2,古玩城农商银行!$D:$D,"="&$C50) -> 0 | M50: 0 | N50: =SUMIFS(艾泊烨海峡银行!$H:$H,艾泊烨海峡银行!$B:$B,"="&$E$2,艾泊烨海峡银行!$D:$D,"="&$C50) -> 0 | O50: 0 | P50: =SUMIFS(艾泊烨农商银行!$J:$J,艾泊烨农商银行!$B:$B,"="&$E$2,艾泊烨农商银行!D:D,"="&$C50) -> 0 | Q50: =SUMIFS(艾泊烨私户银行!$H:$H,艾泊烨私户银行!$B:$B,"="&$E$2,艾泊烨私户银行!$D:$D,"="&$C50) -> 0 | R50: =SUMIFS(易佰兴建行!$P:$P,易佰兴建行!$B:$B,"="&$E$2,易佰兴建行!$D:$D,"="&$C50) -> 0 | S50: =SUMIFS(易佰兴私户!$P:$P,易佰兴私户!$B:$B,"="&$E$2,易佰兴私户!$D:$D,"="&$C50) -> 0 | T50: =SUMIFS(易佰兴现金!$O:$O,易佰兴现金!$B:$B,"="&$E$2,易佰兴现金!D:D,"="&$C50) -> 0 | U50: =SUMIFS(易佰兴基本户!$P:$P,易佰兴基本户!$B:$B,"="&$E$2,易佰兴基本户!D:D,"="&$C50) -> 0
B51: =B50 -> 5 | C51: 车辆维修费 | D51: =SUMIFS(#REF!,#REF!,"="&$E$2,#REF!,"="&$C51) -> #REF! | E51: =SUMIFS(力喆实业中国银行!$H:$H,力喆实业中国银行!$B:$B,"="&$E$2,力喆实业中国银行!$D:$D,"="&$C51) -> 0 | F51: =SUMIFS(力喆产业农商银行!$H:$H,力喆产业农商银行!$B:$B,"="&$E$2,力喆产业农商银行!$D:$D,"="&$C51) -> 0 | G51: =SUMIFS(徐洁招商银行!$H:$H,徐洁招商银行!$B:$B,"="&$E$2,徐洁招商银行!$D:$D,"="&$C51) -> 0 | H51: =SUMIFS(力喆贸易建设银行!$H:$H,力喆贸易建设银行!$B:$B,"="&$E$2,力喆贸易建设银行!$D:$D,"="&$C51) -> 0 | I51: =SUMIFS(元生万物建设银行!$H:$H,元生万物建设银行!$B:$B,"="&$E$2,元生万物建设银行!$D:$D,"="&$C51) -> 0 | J51: =SUMIFS(言吾言中国银行!$H:$H,言吾言中国银行!$B:$B,"="&$E$2,言吾言中国银行!$D:$D,"="&$C51) -> 0 | K51: =SUMIFS(力喆传媒海峡银行!$H:$H,力喆传媒海峡银行!$B:$B,"="&$E$2,力喆传媒海峡银行!$D:$D,"="&$C51) -> 0 | L51: =SUMIFS(古玩城农商银行!$O:$O,古玩城农商银行!$B:$B,"="&$E$2,古玩城农商银行!$D:$D,"="&$C51) -> 0 | M51: 0 | N51: =SUMIFS(艾泊烨海峡银行!$H:$H,艾泊烨海峡银行!$B:$B,"="&$E$2,艾泊烨海峡银行!$D:$D,"="&$C51) -> 0 | O51: 0 | P51: =SUMIFS(艾泊烨农商银行!$J:$J,艾泊烨农商银行!$B:$B,"="&$E$2,艾泊烨农商银行!D:D,"="&$C51) -> 0 | Q51: =SUMIFS(艾泊烨私户银行!$H:$H,艾泊烨私户银行!$B:$B,"="&$E$2,艾泊烨私户银行!$D:$D,"="&$C51) -> 0 | R51: =SUMIFS(易佰兴建行!$P:$P,易佰兴建行!$B:$B,"="&$E$2,易佰兴建行!$D:$D,"="&$C51) -> 0 | S51: =SUMIFS(易佰兴私户!$P:$P,易佰兴私户!$B:$B,"="&$E$2,易佰兴私户!$D:$D,"="&$C51) -> 0 | T51: =SUMIFS(易佰兴现金!$O:$O,易佰兴现金!$B:$B,"="&$E$2,易佰兴现金!D:D,"="&$C51) -> 0 | U51: =SUMIFS(易佰兴基本户!$P:$P,易佰兴基本户!$B:$B,"="&$E$2,易佰兴基本户!D:D,"="&$C51) -> 0
B52: =B51 -> 5 | C52: 车辆保养费 | D52: =SUMIFS(#REF!,#REF!,"="&$E$2,#REF!,"="&$C52) -> #REF! | E52: =SUMIFS(力喆实业中国银行!$H:$H,力喆实业中国银行!$B:$B,"="&$E$2,力喆实业中国银行!$D:$D,"="&$C52) -> 0 | F52: =SUMIFS(力喆产业农商银行!$H:$H,力喆产业农商银行!$B:$B,"="&$E$2,力喆产业农商银行!$D:$D,"="&$C52) -> 0 | G52: =SUMIFS(徐洁招商银行!$H:$H,徐洁招商银行!$B:$B,"="&$E$2,徐洁招商银行!$D:$D,"="&$C52) -> 0 | H52: =SUMIFS(力喆贸易建设银行!$H:$H,力喆贸易建设银行!$B:$B,"="&$E$2,力喆贸易建设银行!$D:$D,"="&$C52) -> 0 | I52: =SUMIFS(元生万物建设银行!$H:$H,元生万物建设银行!$B:$B,"="&$E$2,元生万物建设银行!$D:$D,"="&$C52) -> 0 | J52: =SUMIFS(言吾言中国银行!$H:$H,言吾言中国银行!$B:$B,"="&$E$2,言吾言中国银行!$D:$D,"="&$C52) -> 0 | K52: =SUMIFS(力喆传媒海峡银行!$H:$H,力喆传媒海峡银行!$B:$B,"="&$E$2,力喆传媒海峡银行!$D:$D,"="&$C52) -> 0 | L52: =SUMIFS(古玩城农商银行!$O:$O,古玩城农商银行!$B:$B,"="&$E$2,古玩城农商银行!$D:$D,"="&$C52) -> 0 | M52: 0 | N52: =SUMIFS(艾泊烨海峡银行!$H:$H,艾泊烨海峡银行!$B:$B,"="&$E$2,艾泊烨海峡银行!$D:$D,"="&$C52) -> 0 | O52: 0 | P52: =SUMIFS(艾泊烨农商银行!$J:$J,艾泊烨农商银行!$B:$B,"="&$E$2,艾泊烨农商银行!D:D,"="&$C52) -> 0 | Q52: =SUMIFS(艾泊烨私户银行!$H:$H,艾泊烨私户银行!$B:$B,"="&$E$2,艾泊烨私户银行!$D:$D,"="&$C52) -> 0 | R52: =SUMIFS(易佰兴建行!$P:$P,易佰兴建行!$B:$B,"="&$E$2,易佰兴建行!$D:$D,"="&$C52) -> 0 | S52: =SUMIFS(易佰兴私户!$P:$P,易佰兴私户!$B:$B,"="&$E$2,易佰兴私户!$D:$D,"="&$C52) -> 0 | T52: =SUMIFS(易佰兴现金!$O:$O,易佰兴现金!$B:$B,"="&$E$2,易佰兴现金!D:D,"="&$C52) -> 0 | U52: =SUMIFS(易佰兴基本户!$P:$P,易佰兴基本户!$B:$B,"="&$E$2,易佰兴基本户!D:D,"="&$C52) -> 0
B53: =B52 -> 5 | C53: ETC（闽A6896D） | D53: =SUMIFS(#REF!,#REF!,"="&$E$2,#REF!,"="&$C53) -> #REF! | E53: =SUMIFS(力喆实业中国银行!$H:$H,力喆实业中国银行!$B:$B,"="&$E$2,力喆实业中国银行!$D:$D,"="&$C53) -> 0 | F53: =SUMIFS(力喆产业农商银行!$H:$H,力喆产业农商银行!$B:$B,"="&$E$2,力喆产业农商银行!$D:$D,"="&$C53) -> 0 | G53: =SUMIFS(徐洁招商银行!$H:$H,徐洁招商银行!$B:$B,"="&$E$2,徐洁招商银行!$D:$D,"="&$C53) -> 0 | H53: =SUMIFS(力喆贸易建设银行!$H:$H,力喆贸易建设银行!$B:$B,"="&$E$2,力喆贸易建设银行!$D:$D,"="&$C53) -> 0 | I53: =SUMIFS(元生万物建设银行!$H:$H,元生万物建设银行!$B:$B,"="&$E$2,元生万物建设银行!$D:$D,"="&$C53) -> 0 | J53: =SUMIFS(言吾言中国银行!$H:$H,言吾言中国银行!$B:$B,"="&$E$2,言吾言中国银行!$D:$D,"="&$C53) -> 114 | K53: =SUMIFS(力喆传媒海峡银行!$H:$H,力喆传媒海峡银行!$B:$B,"="&$E$2,力喆传媒海峡银行!$D:$D,"="&$C53) -> 0 | L53: =SUMIFS(古玩城农商银行!$O:$O,古玩城农商银行!$B:$B,"="&$E$2,古玩城农商银行!$D:$D,"="&$C53) -> 0 | M53: 0 | N53: =SUMIFS(艾泊烨海峡银行!$H:$H,艾泊烨海峡银行!$B:$B,"="&$E$2,艾泊烨海峡银行!$D:$D,"="&$C53) -> 0 | O53: 0 | P53: =SUMIFS(艾泊烨农商银行!$J:$J,艾泊烨农商银行!$B:$B,"="&$E$2,艾泊烨农商银行!D:D,"="&$C53) -> 0 | Q53: =SUMIFS(艾泊烨私户银行!$H:$H,艾泊烨私户银行!$B:$B,"="&$E$2,艾泊烨私户银行!$D:$D,"="&$C53) -> 0 | R53: =SUMIFS(易佰兴建行!$P:$P,易佰兴建行!$B:$B,"="&$E$2,易佰兴建行!$D:$D,"="&$C53) -> 0 | S53: =SUMIFS(易佰兴私户!$P:$P,易佰兴私户!$B:$B,"="&$E$2,易佰兴私户!$D:$D,"="&$C53) -> 0 | T53: =SUMIFS(易佰兴现金!$O:$O,易佰兴现金!$B:$B,"="&$E$2,易佰兴现金!D:D,"="&$C53) -> 0 | U53: =SUMIFS(易佰兴基本户!$P:$P,易佰兴基本户!$B:$B,"="&$E$2,易佰兴基本户!D:D,"="&$C53) -> 0
B54: =B53 -> 5 | C54: ETC（闽A013LZ） | D54: =SUMIFS(#REF!,#REF!,"="&$E$2,#REF!,"="&$C54) -> #REF! | E54: =SUMIFS(力喆实业中国银行!$H:$H,力喆实业中国银行!$B:$B,"="&$E$2,力喆实业中国银行!$D:$D,"="&$C54) -> 0 | F54: =SUMIFS(力喆产业农商银行!$H:$H,力喆产业农商银行!$B:$B,"="&$E$2,力喆产业农商银行!$D:$D,"="&$C54) -> 0 | G54: =SUMIFS(徐洁招商银行!$H:$H,徐洁招商银行!$B:$B,"="&$E$2,徐洁招商银行!$D:$D,"="&$C54) -> 0 | H54: =SUMIFS(力喆贸易建设银行!$H:$H,力喆贸易建设银行!$B:$B,"="&$E$2,力喆贸易建设银行!$D:$D,"="&$C54) -> 0 | I54: =SUMIFS(元生万物建设银行!$H:$H,元生万物建设银行!$B:$B,"="&$E$2,元生万物建设银行!$D:$D,"="&$C54) -> 0 | J54: =SUMIFS(言吾言中国银行!$H:$H,言吾言中国银行!$B:$B,"="&$E$2,言吾言中国银行!$D:$D,"="&$C54) -> 0 | K54: =SUMIFS(力喆传媒海峡银行!$H:$H,力喆传媒海峡银行!$B:$B,"="&$E$2,力喆传媒海峡银行!$D:$D,"="&$C54) -> 0 | L54: =SUMIFS(古玩城农商银行!$O:$O,古玩城农商银行!$B:$B,"="&$E$2,古玩城农商银行!$D:$D,"="&$C54) -> 0 | M54: 0 | N54: =SUMIFS(艾泊烨海峡银行!$H:$H,艾泊烨海峡银行!$B:$B,"="&$E$2,艾泊烨海峡银行!$D:$D,"="&$C54) -> 0 | O54: 0 | P54: =SUMIFS(艾泊烨农商银行!$J:$J,艾泊烨农商银行!$B:$B,"="&$E$2,艾泊烨农商银行!D:D,"="&$C54) -> 0 | Q54: =SUMIFS(艾泊烨私户银行!$H:$H,艾泊烨私户银行!$B:$B,"="&$E$2,艾泊烨私户银行!$D:$D,"="&$C54) -> 0 | R54: =SUMIFS(易佰兴建行!$P:$P,易佰兴建行!$B:$B,"="&$E$2,易佰兴建行!$D:$D,"="&$C54) -> 0 | S54: =SUMIFS(易佰兴私户!$P:$P,易佰兴私户!$B:$B,"="&$E$2,易佰兴私户!$D:$D,"="&$C54) -> 0 | T54: =SUMIFS(易佰兴现金!$O:$O,易佰兴现金!$B:$B,"="&$E$2,易佰兴现金!D:D,"="&$C54) -> 0 | U54: =SUMIFS(易佰兴基本户!$P:$P,易佰兴基本户!$B:$B,"="&$E$2,易佰兴基本户!D:D,"="&$C54) -> 0
B55: =B54 -> 5 | C55: ETC（闽AD10200） | D55: =SUMIFS(#REF!,#REF!,"="&$E$2,#REF!,"="&$C55) -> #REF! | E55: =SUMIFS(力喆实业中国银行!$H:$H,力喆实业中国银行!$B:$B,"="&$E$2,力喆实业中国银行!$D:$D,"="&$C55) -> 0 | F55: =SUMIFS(力喆产业农商银行!$H:$H,力喆产业农商银行!$B:$B,"="&$E$2,力喆产业农商银行!$D:$D,"="&$C55) -> 0 | G55: =SUMIFS(徐洁招商银行!$H:$H,徐洁招商银行!$B:$B,"="&$E$2,徐洁招商银行!$D:$D,"="&$C55) -> 0 | H55: =SUMIFS(力喆贸易建设银行!$H:$H,力喆贸易建设银行!$B:$B,"="&$E$2,力喆贸易建设银行!$D:$D,"="&$C55) -> 0 | I55: =SUMIFS(元生万物建设银行!$H:$H,元生万物建设银行!$B:$B,"="&$E$2,元生万物建设银行!$D:$D,"="&$C55) -> 0 | J55: =SUMIFS(言吾言中国银行!$H:$H,言吾言中国银行!$B:$B,"="&$E$2,言吾言中国银行!$D:$D,"="&$C55) -> 0 | K55: =SUMIFS(力喆传媒海峡银行!$H:$H,力喆传媒海峡银行!$B:$B,"="&$E$2,力喆传媒海峡银行!$D:$D,"="&$C55) -> 0 | L55: =SUMIFS(古玩城农商银行!$O:$O,古玩城农商银行!$B:$B,"="&$E$2,古玩城农商银行!$D:$D,"="&$C55) -> 0 | M55: 0 | N55: =SUMIFS(艾泊烨海峡银行!$H:$H,艾泊烨海峡银行!$B:$B,"="&$E$2,艾泊烨海峡银行!$D:$D,"="&$C55) -> 0 | O55: 0 | P55: =SUMIFS(艾泊烨农商银行!$J:$J,艾泊烨农商银行!$B:$B,"="&$E$2,艾泊烨农商银行!D:D,"="&$C55) -> 0 | Q55: =SUMIFS(艾泊烨私户银行!$H:$H,艾泊烨私户银行!$B:$B,"="&$E$2,艾泊烨私户银行!$D:$D,"="&$C55) -> 0 | R55: =SUMIFS(易佰兴建行!$P:$P,易佰兴建行!$B:$B,"="&$E$2,易佰兴建行!$D:$D,"="&$C55) -> 0 | S55: =SUMIFS(易佰兴私户!$P:$P,易佰兴私户!$B:$B,"="&$E$2,易佰兴私户!$D:$D,"="&$C55) -> 0 | T55: =SUMIFS(易佰兴现金!$O:$O,易佰兴现金!$B:$B,"="&$E$2,易佰兴现金!D:D,"="&$C55) -> 0 | U55: =SUMIFS(易佰兴基本户!$P:$P,易佰兴基本户!$B:$B,"="&$E$2,易佰兴基本户!D:D,"="&$C55) -> 0
B56: =B55 -> 5 | C56: 停车费 | D56: =SUMIFS(#REF!,#REF!,"="&$E$2,#REF!,"="&$C56) -> #REF! | E56: =SUMIFS(力喆实业中国银行!$H:$H,力喆实业中国银行!$B:$B,"="&$E$2,力喆实业中国银行!$D:$D,"="&$C56) -> 0 | F56: =SUMIFS(力喆产业农商银行!$H:$H,力喆产业农商银行!$B:$B,"="&$E$2,力喆产业农商银行!$D:$D,"="&$C56) -> 0 | G56: =SUMIFS(徐洁招商银行!$H:$H,徐洁招商银行!$B:$B,"="&$E$2,徐洁招商银行!$D:$D,"="&$C56) -> 0 | H56: =SUMIFS(力喆贸易建设银行!$H:$H,力喆贸易建设银行!$B:$B,"="&$E$2,力喆贸易建设银行!$D:$D,"="&$C56) -> 0 | I56: =SUMIFS(元生万物建设银行!$H:$H,元生万物建设银行!$B:$B,"="&$E$2,元生万物建设银行!$D:$D,"="&$C56) -> 0 | J56: =SUMIFS(言吾言中国银行!$H:$H,言吾言中国银行!$B:$B,"="&$E$2,言吾言中国银行!$D:$D,"="&$C56) -> 0 | K56: =SUMIFS(力喆传媒海峡银行!$H:$H,力喆传媒海峡银行!$B:$B,"="&$E$2,力喆传媒海峡银行!$D:$D,"="&$C56) -> 0 | L56: =SUMIFS(古玩城农商银行!$O:$O,古玩城农商银行!$B:$B,"="&$E$2,古玩城农商银行!$D:$D,"="&$C56) -> 0 | M56: 0 | N56: =SUMIFS(艾泊烨海峡银行!$H:$H,艾泊烨海峡银行!$B:$B,"="&$E$2,艾泊烨海峡银行!$D:$D,"="&$C56) -> 0 | O56: 0 | P56: =SUMIFS(艾泊烨农商银行!$J:$J,艾泊烨农商银行!$B:$B,"="&$E$2,艾泊烨农商银行!D:D,"="&$C56) -> 0 | Q56: =SUMIFS(艾泊烨私户银行!$H:$H,艾泊烨私户银行!$B:$B,"="&$E$2,艾泊烨私户银行!$D:$D,"="&$C56) -> 0 | R56: =SUMIFS(易佰兴建行!$P:$P,易佰兴建行!$B:$B,"="&$E$2,易佰兴建行!$D:$D,"="&$C56) -> 0 | S56: =SUMIFS(易佰兴私户!$P:$P,易佰兴私户!$B:$B,"="&$E$2,易佰兴私户!$D:$D,"="&$C56) -> 0 | T56: =SUMIFS(易佰兴现金!$O:$O,易佰兴现金!$B:$B,"="&$E$2,易佰兴现金!D:D,"="&$C56) -> 0 | U56: =SUMIFS(易佰兴基本户!$P:$P,易佰兴基本户!$B:$B,"="&$E$2,易佰兴基本户!D:D,"="&$C56) -> 0
B57: =B56 -> 5 | C57: 车辆使用费 | D57: =SUMIFS(#REF!,#REF!,"="&$E$2,#REF!,"="&$C57) -> #REF! | E57: =SUMIFS(力喆实业中国银行!$H:$H,力喆实业中国银行!$B:$B,"="&$E$2,力喆实业中国银行!$D:$D,"="&$C57) -> 0 | F57: =SUMIFS(力喆产业农商银行!$H:$H,力喆产业农商银行!$B:$B,"="&$E$2,力喆产业农商银行!$D:$D,"="&$C57) -> 0 | G57: =SUMIFS(徐洁招商银行!$H:$H,徐洁招商银行!$B:$B,"="&$E$2,徐洁招商银行!$D:$D,"="&$C57) -> 0 | H57: =SUMIFS(力喆贸易建设银行!$H:$H,力喆贸易建设银行!$B:$B,"="&$E$2,力喆贸易建设银行!$D:$D,"="&$C57) -> 0 | I57: =SUMIFS(元生万物建设银行!$H:$H,元生万物建设银行!$B:$B,"="&$E$2,元生万物建设银行!$D:$D,"="&$C57) -> 0 | J57: =SUMIFS(言吾言中国银行!$H:$H,言吾言中国银行!$B:$B,"="&$E$2,言吾言中国银行!$D:$D,"="&$C57) -> 0 | K57: =SUMIFS(力喆传媒海峡银行!$H:$H,力喆传媒海峡银行!$B:$B,"="&$E$2,力喆传媒海峡银行!$D:$D,"="&$C57) -> 0 | L57: =SUMIFS(古玩城农商银行!$O:$O,古玩城农商银行!$B:$B,"="&$E$2,古玩城农商银行!$D:$D,"="&$C57) -> 0 | M57: 0 | N57: =SUMIFS(艾泊烨海峡银行!$H:$H,艾泊烨海峡银行!$B:$B,"="&$E$2,艾泊烨海峡银行!$D:$D,"="&$C57) -> 0 | O57: 0 | P57: =SUMIFS(艾泊烨农商银行!$J:$J,艾泊烨农商银行!$B:$B,"="&$E$2,艾泊烨农商银行!D:D,"="&$C57) -> 0 | Q57: =SUMIFS(艾泊烨私户银行!$H:$H,艾泊烨私户银行!$B:$B,"="&$E$2,艾泊烨私户银行!$D:$D,"="&$C57) -> 0 | R57: =SUMIFS(易佰兴建行!$P:$P,易佰兴建行!$B:$B,"="&$E$2,易佰兴建行!$D:$D,"="&$C57) -> 0 | S57: =SUMIFS(易佰兴私户!$P:$P,易佰兴私户!$B:$B,"="&$E$2,易佰兴私户!$D:$D,"="&$C57) -> 0 | T57: =SUMIFS(易佰兴现金!$O:$O,易佰兴现金!$B:$B,"="&$E$2,易佰兴现金!D:D,"="&$C57) -> 0 | U57: =SUMIFS(易佰兴基本户!$P:$P,易佰兴基本户!$B:$B,"="&$E$2,易佰兴基本户!D:D,"="&$C57) -> 0
B58: =B57 -> 5 | C58: 市内交通费 | D58: =SUMIFS(#REF!,#REF!,"="&$E$2,#REF!,"="&$C58) -> #REF! | E58: =SUMIFS(力喆实业中国银行!$H:$H,力喆实业中国银行!$B:$B,"="&$E$2,力喆实业中国银行!$D:$D,"="&$C58) -> 0 | F58: =SUMIFS(力喆产业农商银行!$H:$H,力喆产业农商银行!$B:$B,"="&$E$2,力喆产业农商银行!$D:$D,"="&$C58) -> 0 | G58: =SUMIFS(徐洁招商银行!$H:$H,徐洁招商银行!$B:$B,"="&$E$2,徐洁招商银行!$D:$D,"="&$C58) -> 0 | H58: =SUMIFS(力喆贸易建设银行!$H:$H,力喆贸易建设银行!$B:$B,"="&$E$2,力喆贸易建设银行!$D:$D,"="&$C58) -> 0 | I58: =SUMIFS(元生万物建设银行!$H:$H,元生万物建设银行!$B:$B,"="&$E$2,元生万物建设银行!$D:$D,"="&$C58) -> 0 | J58: =SUMIFS(言吾言中国银行!$H:$H,言吾言中国银行!$B:$B,"="&$E$2,言吾言中国银行!$D:$D,"="&$C58) -> 0 | K58: =SUMIFS(力喆传媒海峡银行!$H:$H,力喆传媒海峡银行!$B:$B,"="&$E$2,力喆传媒海峡银行!$D:$D,"="&$C58) -> 0 | L58: =SUMIFS(古玩城农商银行!$O:$O,古玩城农商银行!$B:$B,"="&$E$2,古玩城农商银行!$D:$D,"="&$C58) -> 0 | M58: 0 | N58: =SUMIFS(艾泊烨海峡银行!$H:$H,艾泊烨海峡银行!$B:$B,"="&$E$2,艾泊烨海峡银行!$D:$D,"="&$C58) -> 0 | O58: 0 | P58: =SUMIFS(艾泊烨农商银行!$J:$J,艾泊烨农商银行!$B:$B,"="&$E$2,艾泊烨农商银行!D:D,"="&$C58) -> 0 | Q58: =SUMIFS(艾泊烨私户银行!$H:$H,艾泊烨私户银行!$B:$B,"="&$E$2,艾泊烨私户银行!$D:$D,"="&$C58) -> 0 | R58: =SUMIFS(易佰兴建行!$P:$P,易佰兴建行!$B:$B,"="&$E$2,易佰兴建行!$D:$D,"="&$C58) -> 0 | S58: =SUMIFS(易佰兴私户!$P:$P,易佰兴私户!$B:$B,"="&$E$2,易佰兴私户!$D:$D,"="&$C58) -> 0 | T58: =SUMIFS(易佰兴现金!$O:$O,易佰兴现金!$B:$B,"="&$E$2,易佰兴现金!D:D,"="&$C58) -> 0 | U58: =SUMIFS(易佰兴基本户!$P:$P,易佰兴基本户!$B:$B,"="&$E$2,易佰兴基本户!D:D,"="&$C58) -> 0
B59: =B58 -> 5 | C59: 银行手续费 | D59: =SUMIFS(#REF!,#REF!,"="&$E$2,#REF!,"="&$C59) -> #REF! | E59: =SUMIFS(力喆实业中国银行!$H:$H,力喆实业中国银行!$B:$B,"="&$E$2,力喆实业中国银行!$D:$D,"="&$C59) -> 0 | F59: =SUMIFS(力喆产业农商银行!$H:$H,力喆产业农商银行!$B:$B,"="&$E$2,力喆产业农商银行!$D:$D,"="&$C59) -> 10 | G59: =SUMIFS(徐洁招商银行!$H:$H,徐洁招商银行!$B:$B,"="&$E$2,徐洁招商银行!$D:$D,"="&$C59) -> 0 | H59: =SUMIFS(力喆贸易建设银行!$H:$H,力喆贸易建设银行!$B:$B,"="&$E$2,力喆贸易建设银行!$D:$D,"="&$C59) -> 33 | I59: =SUMIFS(元生万物建设银行!$H:$H,元生万物建设银行!$B:$B,"="&$E$2,元生万物建设银行!$D:$D,"="&$C59) -> 30 | J59: =SUMIFS(言吾言中国银行!$H:$H,言吾言中国银行!$B:$B,"="&$E$2,言吾言中国银行!$D:$D,"="&$C59) -> 20 | K59: =SUMIFS(力喆传媒海峡银行!$H:$H,力喆传媒海峡银行!$B:$B,"="&$E$2,力喆传媒海峡银行!$D:$D,"="&$C59) -> 0 | L59: =SUMIFS(古玩城农商银行!$M:$M,古玩城农商银行!$B:$B,"="&$E$2) -> 180.77 | M59: 0 | N59: =SUMIFS(艾泊烨海峡银行!$H:$H,艾泊烨海峡银行!$B:$B,"="&$E$2,艾泊烨海峡银行!$D:$D,"="&$C59) -> 52 | O59: =SUMIFS(艾泊烨招商银行!$H:$H,艾泊烨招商银行!$B:$B,"="&$E$2,艾泊烨招商银行!$D:$D,"="&$C59) -> 25 | P59: =SUMIFS(艾泊烨农商银行!$J:$J,艾泊烨农商银行!$B:$B,"="&$E$2,艾泊烨农商银行!D:D,"="&$C59) -> 0 | Q59: =SUMIFS(艾泊烨私户银行!$H:$H,艾泊烨私户银行!$B:$B,"="&$E$2,艾泊烨私户银行!$D:$D,"="&$C59) -> 0 | R59: =SUMIFS(易佰兴建行!$P:$P,易佰兴建行!$B:$B,"="&$E$2,易佰兴建行!$D:$D,"="&$C59) -> 19 | S59: =SUMIFS(易佰兴私户!$N:$N,易佰兴私户!$B:$B,"="&$E$2) -> 130.37 | T59: =SUMIFS(易佰兴现金!$O:$O,易佰兴现金!$B:$B,"="&$E$2,易佰兴现金!D:D,"="&$C59) -> 0 | U59: =SUMIFS(易佰兴基本户!$N:$N,易佰兴基本户!B:B,"="&$E$2) -> 0
B60: =B59 -> 5 | C60: 税费 | D60: =SUMIFS(#REF!,#REF!,"="&$E$2,#REF!,"="&$C60) -> #REF! | E60: =SUMIFS(力喆实业中国银行!$H:$H,力喆实业中国银行!$B:$B,"="&$E$2,力喆实业中国银行!$D:$D,"="&$C60) -> 0 | F60: =SUMIFS(力喆产业农商银行!$H:$H,力喆产业农商银行!$B:$B,"="&$E$2,力喆产业农商银行!$D:$D,"="&$C60) -> 0 | G60: =SUMIFS(徐洁招商银行!$H:$H,徐洁招商银行!$B:$B,"="&$E$2,徐洁招商银行!$D:$D,"="&$C60) -> 0 | H60: =SUMIFS(力喆贸易建设银行!$H:$H,力喆贸易建设银行!$B:$B,"="&$E$2,力喆贸易建设银行!$D:$D,"="&$C60) -> 6397.46 | I60: =SUMIFS(元生万物建设银行!$H:$H,元生万物建设银行!$B:$B,"="&$E$2,元生万物建设银行!$D:$D,"="&$C60) -> 0 | J60: =SUMIFS(言吾言中国银行!$H:$H,言吾言中国银行!$B:$B,"="&$E$2,言吾言中国银行!$D:$D,"="&$C60) -> 0 | K60: =SUMIFS(力喆传媒海峡银行!$H:$H,力喆传媒海峡银行!$B:$B,"="&$E$2,力喆传媒海峡银行!$D:$D,"="&$C60) -> 0 | L60: =SUMIFS(古玩城农商银行!$O:$O,古玩城农商银行!$B:$B,"="&$E$2,古玩城农商银行!$D:$D,"="&$C60) -> 0 | M60: 0 | N60: =SUMIFS(艾泊烨海峡银行!$H:$H,艾泊烨海峡银行!$B:$B,"="&$E$2,艾泊烨海峡银行!$D:$D,"="&$C60) -> 17.8 | O60: 0 | P60: =SUMIFS(艾泊烨农商银行!$J:$J,艾泊烨农商银行!$B:$B,"="&$E$2,艾泊烨农商银行!D:D,"="&$C60) -> 0 | Q60: =SUMIFS(艾泊烨私户银行!$H:$H,艾泊烨私户银行!$B:$B,"="&$E$2,艾泊烨私户银行!$D:$D,"="&$C60) -> 0 | R60: =SUMIFS(易佰兴建行!$P:$P,易佰兴建行!$B:$B,"="&$E$2,易佰兴建行!D:D,"="&$C60) -> 15.5 | S60: =SUMIFS(易佰兴私户!$P:$P,易佰兴私户!$B:$B,"="&$E$2,易佰兴私户!$D:$D,"="&$C60) -> 0 | T60: =SUMIFS(易佰兴现金!$O:$O,易佰兴现金!$B:$B,"="&$E$2,易佰兴现金!D:D,"="&$C60) -> 0 | U60: =SUMIFS(易佰兴基本户!$P:$P,易佰兴基本户!$B:$B,"="&$E$2,易佰兴基本户!D:D,"="&$C60) -> 0
B61: =B60 -> 5 | C61: 贷款利息 | D61: =SUMIFS(#REF!,#REF!,"="&$E$2,#REF!,"="&$C61) -> #REF! | E61: =SUMIFS(力喆实业中国银行!$H:$H,力喆实业中国银行!$B:$B,"="&$E$2,力喆实业中国银行!$D:$D,"="&$C61) -> 0 | F61: =SUMIFS(力喆产业农商银行!$H:$H,力喆产业农商银行!$B:$B,"="&$E$2,力喆产业农商银行!$D:$D,"="&$C61) -> 34931.25 | G61: =SUMIFS(徐洁招商银行!$H:$H,徐洁招商银行!$B:$B,"="&$E$2,徐洁招商银行!$D:$D,"="&$C61) -> 0 | H61: =SUMIFS(力喆贸易建设银行!$H:$H,力喆贸易建设银行!$B:$B,"="&$E$2,力喆贸易建设银行!$D:$D,"="&$C61) -> 0 | I61: =SUMIFS(元生万物建设银行!$H:$H,元生万物建设银行!$B:$B,"="&$E$2,元生万物建设银行!$D:$D,"="&$C61) -> 0 | J61: =SUMIFS(言吾言中国银行!$H:$H,言吾言中国银行!$B:$B,"="&$E$2,言吾言中国银行!$D:$D,"="&$C61) -> 0 | K61: =SUMIFS(力喆传媒海峡银行!$H:$H,力喆传媒海峡银行!$B:$B,"="&$E$2,力喆传媒海峡银行!$D:$D,"="&$C61) -> 0 | L61: =SUMIFS(古玩城农商银行!$O:$O,古玩城农商银行!$B:$B,"="&$E$2,古玩城农商银行!$D:$D,"="&$C61) -> 0 | M61: 0 | N61: =SUMIFS(艾泊烨海峡银行!$H:$H,艾泊烨海峡银行!$B:$B,"="&$E$2,艾泊烨海峡银行!$D:$D,"="&$C61) -> 0 | O61: 0 | P61: =SUMIFS(艾泊烨农商银行!$J:$J,艾泊烨农商银行!$B:$B,"="&$E$2,艾泊烨农商银行!D:D,"="&$C61) -> 15179.17 | Q61: =SUMIFS(艾泊烨私户银行!$H:$H,艾泊烨私户银行!$B:$B,"="&$E$2,艾泊烨私户银行!$D:$D,"="&$C61) -> 3195.83 | R61: =SUMIFS(易佰兴建行!$P:$P,易佰兴建行!$B:$B,"="&$E$2,易佰兴建行!D:D,"="&$C61) -> 0 | S61: =SUMIFS(易佰兴私户!$P:$P,易佰兴私户!$B:$B,"="&$E$2,易佰兴私户!$D:$D,"="&$C61) -> 0 | T61: =SUMIFS(易佰兴现金!$O:$O,易佰兴现金!$B:$B,"="&$E$2,易佰兴现金!D:D,"="&$C61) -> 0 | U61: =SUMIFS(易佰兴基本户!$P:$P,易佰兴基本户!$B:$B,"="&$E$2,易佰兴基本户!D:D,"="&$C61) -> 0
B62: =B61 -> 5 | C62: 房租 | D62: =SUMIFS(#REF!,#REF!,"="&$E$2,#REF!,"="&$C62) -> #REF! | E62: =SUMIFS(力喆实业中国银行!$H:$H,力喆实业中国银行!$B:$B,"="&$E$2,力喆实业中国银行!$D:$D,"="&$C62) -> 0 | F62: =SUMIFS(力喆产业农商银行!$H:$H,力喆产业农商银行!$B:$B,"="&$E$2,力喆产业农商银行!$D:$D,"="&$C62) -> 12832.11 | G62: =SUMIFS(徐洁招商银行!$H:$H,徐洁招商银行!$B:$B,"="&$E$2,徐洁招商银行!$D:$D,"="&$C62) -> 0 | H62: =SUMIFS(力喆贸易建设银行!$H:$H,力喆贸易建设银行!$B:$B,"="&$E$2,力喆贸易建设银行!$D:$D,"="&$C62) -> 0 | I62: =SUMIFS(元生万物建设银行!$H:$H,元生万物建设银行!$B:$B,"="&$E$2,元生万物建设银行!$D:$D,"="&$C62) -> 0 | J62: =SUMIFS(言吾言中国银行!$H:$H,言吾言中国银行!$B:$B,"="&$E$2,言吾言中国银行!$D:$D,"="&$C62) -> 0 | K62: =SUMIFS(力喆传媒海峡银行!$H:$H,力喆传媒海峡银行!$B:$B,"="&$E$2,力喆传媒海峡银行!$D:$D,"="&$C62) -> 0 | L62: =SUMIFS(古玩城农商银行!$O:$O,古玩城农商银行!$B:$B,"="&$E$2,古玩城农商银行!$D:$D,"="&$C62) -> 130000 | M62: 0 | N62: =SUMIFS(艾泊烨海峡银行!$H:$H,艾泊烨海峡银行!$B:$B,"="&$E$2,艾泊烨海峡银行!$D:$D,"="&$C62) -> 0 | O62: 0 | P62: =SUMIFS(艾泊烨农商银行!$J:$J,艾泊烨农商银行!$B:$B,"="&$E$2,艾泊烨农商银行!D:D,"="&$C62) -> 0 | Q62: =SUMIFS(艾泊烨私户银行!$H:$H,艾泊烨私户银行!$B:$B,"="&$E$2,艾泊烨私户银行!$D:$D,"="&$C62) -> 0 | R62: =SUMIFS(易佰兴建行!$P:$P,易佰兴建行!$B:$B,"="&$E$2,易佰兴建行!D:D,"="&$C62) -> 207266.2 | S62: =SUMIFS(易佰兴私户!$P:$P,易佰兴私户!$B:$B,"="&$E$2,易佰兴私户!$D:$D,"="&$C62) -> 0 | T62: =SUMIFS(易佰兴现金!$O:$O,易佰兴现金!$B:$B,"="&$E$2,易佰兴现金!D:D,"="&$C62) -> 0 | U62: =SUMIFS(易佰兴基本户!$P:$P,易佰兴基本户!$B:$B,"="&$E$2,易佰兴基本户!D:D,"="&$C62) -> 0
B63: =B62 -> 5 | C63: 衣锦坊52号一进房租 | D63: =SUMIFS(#REF!,#REF!,"="&$E$2,#REF!,"="&$C63) -> #REF! | E63: =SUMIFS(力喆实业中国银行!$H:$H,力喆实业中国银行!$B:$B,"="&$E$2,力喆实业中国银行!$D:$D,"="&$C63) -> 0 | F63: =SUMIFS(力喆产业农商银行!$H:$H,力喆产业农商银行!$B:$B,"="&$E$2,力喆产业农商银行!$D:$D,"="&$C63) -> 0 | G63: =SUMIFS(徐洁招商银行!$H:$H,徐洁招商银行!$B:$B,"="&$E$2,徐洁招商银行!$D:$D,"="&$C63) -> 0 | H63: =SUMIFS(力喆贸易建设银行!$H:$H,力喆贸易建设银行!$B:$B,"="&$E$2,力喆贸易建设银行!$D:$D,"="&$C63) -> 0 | I63: =SUMIFS(元生万物建设银行!$H:$H,元生万物建设银行!$B:$B,"="&$E$2,元生万物建设银行!$D:$D,"="&$C63) -> 0 | J63: =SUMIFS(言吾言中国银行!$H:$H,言吾言中国银行!$B:$B,"="&$E$2,言吾言中国银行!$D:$D,"="&$C63) -> 0 | K63: =SUMIFS(力喆传媒海峡银行!$H:$H,力喆传媒海峡银行!$B:$B,"="&$E$2,力喆传媒海峡银行!$D:$D,"="&$C63) -> 0 | L63: =SUMIFS(古玩城农商银行!$O:$O,古玩城农商银行!$B:$B,"="&$E$2,古玩城农商银行!$D:$D,"="&$C63) -> 0 | M63: 0 | N63: =SUMIFS(艾泊烨海峡银行!$H:$H,艾泊烨海峡银行!$B:$B,"="&$E$2,艾泊烨海峡银行!$D:$D,"="&$C63) -> 0 | O63: 0 | P63: =SUMIFS(艾泊烨农商银行!$J:$J,艾泊烨农商银行!$B:$B,"="&$E$2,艾泊烨农商银行!D:D,"="&$C63) -> 0 | Q63: =SUMIFS(艾泊烨私户银行!$H:$H,艾泊烨私户银行!$B:$B,"="&$E$2,艾泊烨私户银行!$D:$D,"="&$C63) -> 0 | R63: =SUMIFS(易佰兴建行!$P:$P,易佰兴建行!$B:$B,"="&$E$2,易佰兴建行!D:D,"="&$C63) -> 0 | S63: =SUMIFS(易佰兴私户!$P:$P,易佰兴私户!$B:$B,"="&$E$2,易佰兴私户!$D:$D,"="&$C63) -> 0 | T63: =SUMIFS(易佰兴现金!$O:$O,易佰兴现金!$B:$B,"="&$E$2,易佰兴现金!D:D,"="&$C63) -> 0 | U63: =SUMIFS(易佰兴基本户!$P:$P,易佰兴基本户!$B:$B,"="&$E$2,易佰兴基本户!D:D,"="&$C63) -> 0
B64: =B63 -> 5 | C64: 物业费 | D64: =SUMIFS(#REF!,#REF!,"="&$E$2,#REF!,"="&$C64) -> #REF! | E64: =SUMIFS(力喆实业中国银行!$H:$H,力喆实业中国银行!$B:$B,"="&$E$2,力喆实业中国银行!$D:$D,"="&$C64) -> 0 | F64: =SUMIFS(力喆产业农商银行!$H:$H,力喆产业农商银行!$B:$B,"="&$E$2,力喆产业农商银行!$D:$D,"="&$C64) -> 0 | G64: =SUMIFS(徐洁招商银行!$H:$H,徐洁招商银行!$B:$B,"="&$E$2,徐洁招商银行!$D:$D,"="&$C64) -> 0 | H64: =SUMIFS(力喆贸易建设银行!$H:$H,力喆贸易建设银行!$B:$B,"="&$E$2,力喆贸易建设银行!$D:$D,"="&$C64) -> 0 | I64: =SUMIFS(元生万物建设银行!$H:$H,元生万物建设银行!$B:$B,"="&$E$2,元生万物建设银行!$D:$D,"="&$C64) -> 0 | J64: =SUMIFS(言吾言中国银行!$H:$H,言吾言中国银行!$B:$B,"="&$E$2,言吾言中国银行!$D:$D,"="&$C64) -> 0 | K64: =SUMIFS(力喆传媒海峡银行!$H:$H,力喆传媒海峡银行!$B:$B,"="&$E$2,力喆传媒海峡银行!$D:$D,"="&$C64) -> 0 | L64: =SUMIFS(古玩城农商银行!$O:$O,古玩城农商银行!$B:$B,"="&$E$2,古玩城农商银行!$D:$D,"="&$C64) -> 0 | M64: 0 | N64: =SUMIFS(艾泊烨海峡银行!$H:$H,艾泊烨海峡银行!$B:$B,"="&$E$2,艾泊烨海峡银行!$D:$D,"="&$C64) -> 0 | O64: 0 | P64: =SUMIFS(艾泊烨农商银行!$J:$J,艾泊烨农商银行!$B:$B,"="&$E$2,艾泊烨农商银行!D:D,"="&$C64) -> 0 | Q64: =SUMIFS(艾泊烨私户银行!$H:$H,艾泊烨私户银行!$B:$B,"="&$E$2,艾泊烨私户银行!$D:$D,"="&$C64) -> 0 | R64: =SUMIFS(易佰兴建行!$P:$P,易佰兴建行!$B:$B,"="&$E$2,易佰兴建行!D:D,"="&$C64) -> 0 | S64: =SUMIFS(易佰兴私户!$P:$P,易佰兴私户!$B:$B,"="&$E$2,易佰兴私户!$D:$D,"="&$C64) -> 0 | T64: =SUMIFS(易佰兴现金!$O:$O,易佰兴现金!$B:$B,"="&$E$2,易佰兴现金!D:D,"="&$C64) -> 0 | U64: =SUMIFS(易佰兴基本户!$P:$P,易佰兴基本户!$B:$B,"="&$E$2,易佰兴基本户!D:D,"="&$C64) -> 0
B65: =B64 -> 5 | C65: 水电费 | D65: =SUMIFS(#REF!,#REF!,"="&$E$2,#REF!,"="&$C65) -> #REF! | E65: =SUMIFS(力喆实业中国银行!$H:$H,力喆实业中国银行!$B:$B,"="&$E$2,力喆实业中国银行!$D:$D,"="&$C65) -> 0 | F65: =SUMIFS(力喆产业农商银行!$H:$H,力喆产业农商银行!$B:$B,"="&$E$2,力喆产业农商银行!$D:$D,"="&$C65) -> 0 | G65: =SUMIFS(徐洁招商银行!$H:$H,徐洁招商银行!$B:$B,"="&$E$2,徐洁招商银行!$D:$D,"="&$C65) -> 0 | H65: =SUMIFS(力喆贸易建设银行!$H:$H,力喆贸易建设银行!$B:$B,"="&$E$2,力喆贸易建设银行!$D:$D,"="&$C65) -> 0 | I65: =SUMIFS(元生万物建设银行!$H:$H,元生万物建设银行!$B:$B,"="&$E$2,元生万物建设银行!$D:$D,"="&$C65) -> 0 | J65: =SUMIFS(言吾言中国银行!$H:$H,言吾言中国银行!$B:$B,"="&$E$2,言吾言中国银行!$D:$D,"="&$C65) -> 0 | K65: =SUMIFS(力喆传媒海峡银行!$H:$H,力喆传媒海峡银行!$B:$B,"="&$E$2,力喆传媒海峡银行!$D:$D,"="&$C65) -> 0 | L65: =SUMIFS(古玩城农商银行!$O:$O,古玩城农商银行!$B:$B,"="&$E$2,古玩城农商银行!$D:$D,"="&$C65) -> 17141.16 | M65: 0 | N65: =SUMIFS(艾泊烨海峡银行!$H:$H,艾泊烨海峡银行!$B:$B,"="&$E$2,艾泊烨海峡银行!$D:$D,"="&$C65) -> 0 | O65: 0 | P65: =SUMIFS(艾泊烨农商银行!$J:$J,艾泊烨农商银行!$B:$B,"="&$E$2,艾泊烨农商银行!D:D,"="&$C65) -> 0 | Q65: =SUMIFS(艾泊烨私户银行!$H:$H,艾泊烨私户银行!$B:$B,"="&$E$2,艾泊烨私户银行!$D:$D,"="&$C65) -> 0 | R65: =SUMIFS(易佰兴建行!$P:$P,易佰兴建行!$B:$B,"="&$E$2,易佰兴建行!D:D,"="&$C65) -> 15281.38 | S65: =SUMIFS(易佰兴私户!$P:$P,易佰兴私户!$B:$B,"="&$E$2,易佰兴私户!$D:$D,"="&$C65) -> 0 | T65: =SUMIFS(易佰兴现金!$O:$O,易佰兴现金!$B:$B,"="&$E$2,易佰兴现金!D:D,"="&$C65) -> 0 | U65: =SUMIFS(易佰兴基本户!$P:$P,易佰兴基本户!$B:$B,"="&$E$2,易佰兴基本户!D:D,"="&$C65) -> 0
B66: =B65 -> 5 | C66: 光伏电费 | D66: 0 | E66: =SUMIFS(力喆实业中国银行!$H:$H,力喆实业中国银行!$B:$B,"="&$E$2,力喆实业中国银行!$D:$D,"="&$C66) -> 0 | F66: =SUMIFS(力喆产业农商银行!$H:$H,力喆产业农商银行!$B:$B,"="&$E$2,力喆产业农商银行!$D:$D,"="&$C66) -> 0 | G66: =SUMIFS(徐洁招商银行!$H:$H,徐洁招商银行!$B:$B,"="&$E$2,徐洁招商银行!$D:$D,"="&$C66) -> 0 | H66: =SUMIFS(力喆贸易建设银行!$H:$H,力喆贸易建设银行!$B:$B,"="&$E$2,力喆贸易建设银行!$D:$D,"="&$C66) -> 0 | I66: 0 | J66: 0 | K66: 0 | L66: 0 | M66: 0 | N66: 0 | O66: 0 | P66: 0 | Q66: =SUMIFS(艾泊烨私户银行!$H:$H,艾泊烨私户银行!$B:$B,"="&$E$2,艾泊烨私户银行!$D:$D,"="&$C66) -> 0 | R66: =SUMIFS(易佰兴建行!$P:$P,易佰兴建行!$B:$B,"="&$E$2,易佰兴建行!D:D,"="&$C66) -> 0 | S66: =SUMIFS(易佰兴私户!$P:$P,易佰兴私户!$B:$B,"="&$E$2,易佰兴私户!$D:$D,"="&$C66) -> 0 | T66: =SUMIFS(易佰兴现金!$O:$O,易佰兴现金!$B:$B,"="&$E$2,易佰兴现金!D:D,"="&$C66) -> 0 | U66: =SUMIFS(易佰兴基本户!$P:$P,易佰兴基本户!$B:$B,"="&$E$2,易佰兴基本户!D:D,"="&$C66) -> 0
B67: =B64 -> 5 | C67: 上下杭房租 | D67: =SUMIFS(#REF!,#REF!,"="&$E$2,#REF!,"="&$C67) -> #REF! | E67: =SUMIFS(力喆实业中国银行!$H:$H,力喆实业中国银行!$B:$B,"="&$E$2,力喆实业中国银行!$D:$D,"="&$C67) -> 0 | F67: =SUMIFS(力喆产业农商银行!$H:$H,力喆产业农商银行!$B:$B,"="&$E$2,力喆产业农商银行!$D:$D,"="&$C67) -> 0 | G67: =SUMIFS(徐洁招商银行!$H:$H,徐洁招商银行!$B:$B,"="&$E$2,徐洁招商银行!$D:$D,"="&$C67) -> 0 | H67: =SUMIFS(力喆贸易建设银行!$H:$H,力喆贸易建设银行!$B:$B,"="&$E$2,力喆贸易建设银行!$D:$D,"="&$C67) -> 0 | I67: =SUMIFS(元生万物建设银行!$H:$H,元生万物建设银行!$B:$B,"="&$E$2,元生万物建设银行!$D:$D,"="&$C67) -> 0 | J67: =SUMIFS(言吾言中国银行!$H:$H,言吾言中国银行!$B:$B,"="&$E$2,言吾言中国银行!$D:$D,"="&$C67) -> 0 | K67: =SUMIFS(力喆传媒海峡银行!$H:$H,力喆传媒海峡银行!$B:$B,"="&$E$2,力喆传媒海峡银行!$D:$D,"="&$C67) -> 0 | L67: =SUMIFS(古玩城农商银行!$O:$O,古玩城农商银行!$B:$B,"="&$E$2,古玩城农商银行!$D:$D,"="&$C67) -> 0 | M67: 0 | N67: =SUMIFS(艾泊烨海峡银行!$H:$H,艾泊烨海峡银行!$B:$B,"="&$E$2,艾泊烨海峡银行!$D:$D,"="&$C67) -> 0 | O67: 0 | P67: =SUMIFS(艾泊烨农商银行!$J:$J,艾泊烨农商银行!$B:$B,"="&$E$2,艾泊烨农商银行!D:D,"="&$C67) -> 0 | Q67: =SUMIFS(艾泊烨私户银行!$H:$H,艾泊烨私户银行!$B:$B,"="&$E$2,艾泊烨私户银行!$D:$D,"="&$C67) -> 0 | R67: =SUMIFS(易佰兴建行!$P:$P,易佰兴建行!$B:$B,"="&$E$2,易佰兴建行!D:D,"="&$C67) -> 0 | S67: =SUMIFS(易佰兴私户!$P:$P,易佰兴私户!$B:$B,"="&$E$2,易佰兴私户!$D:$D,"="&$C67) -> 0 | T67: =SUMIFS(易佰兴现金!$O:$O,易佰兴现金!$B:$B,"="&$E$2,易佰兴现金!D:D,"="&$C67) -> 0 | U67: =SUMIFS(易佰兴基本户!$P:$P,易佰兴基本户!$B:$B,"="&$E$2,易佰兴基本户!D:D,"="&$C67) -> 0
B68: =B65 -> 5 | C68: 徐总费用 | D68: =SUMIFS(#REF!,#REF!,"="&$E$2,#REF!,"="&$C68) -> #REF! | E68: =SUMIFS(力喆实业中国银行!$H:$H,力喆实业中国银行!$B:$B,"="&$E$2,力喆实业中国银行!$D:$D,"="&$C68) -> 0 | F68: =SUMIFS(力喆产业农商银行!$H:$H,力喆产业农商银行!$B:$B,"="&$E$2,力喆产业农商银行!$D:$D,"="&$C68) -> 0 | G68: =SUMIFS(徐洁招商银行!$H:$H,徐洁招商银行!$B:$B,"="&$E$2,徐洁招商银行!$D:$D,"="&$C68) -> 63409.14 | H68: =SUMIFS(力喆贸易建设银行!$H:$H,力喆贸易建设银行!$B:$B,"="&$E$2,力喆贸易建设银行!$D:$D,"="&$C68) -> 0 | I68: =SUMIFS(元生万物建设银行!$H:$H,元生万物建设银行!$B:$B,"="&$E$2,元生万物建设银行!$D:$D,"="&$C68) -> 0 | J68: =SUMIFS(言吾言中国银行!$H:$H,言吾言中国银行!$B:$B,"="&$E$2,言吾言中国银行!$D:$D,"="&$C68) -> 0 | K68: =SUMIFS(力喆传媒海峡银行!$H:$H,力喆传媒海峡银行!$B:$B,"="&$E$2,力喆传媒海峡银行!$D:$D,"="&$C68) -> 0 | L68: =SUMIFS(古玩城农商银行!$O:$O,古玩城农商银行!$B:$B,"="&$E$2,古玩城农商银行!$D:$D,"="&$C68) -> 0 | M68: 0 | N68: =SUMIFS(艾泊烨海峡银行!$H:$H,艾泊烨海峡银行!$B:$B,"="&$E$2,艾泊烨海峡银行!$D:$D,"="&$C68) -> 0 | O68: 0 | P68: =SUMIFS(艾泊烨农商银行!$J:$J,艾泊烨农商银行!$B:$B,"="&$E$2,艾泊烨农商银行!D:D,"="&$C68) -> 0 | Q68: =SUMIFS(艾泊烨私户银行!$H:$H,艾泊烨私户银行!$B:$B,"="&$E$2,艾泊烨私户银行!$D:$D,"="&$C68) -> 0 | R68: =SUMIFS(易佰兴建行!$P:$P,易佰兴建行!$B:$B,"="&$E$2,易佰兴建行!D:D,"="&$C68) -> 0 | S68: =SUMIFS(易佰兴私户!$P:$P,易佰兴私户!$B:$B,"="&$E$2,易佰兴私户!$D:$D,"="&$C68) -> 0 | T68: =SUMIFS(易佰兴现金!$O:$O,易佰兴现金!$B:$B,"="&$E$2,易佰兴现金!D:D,"="&$C68) -> 0 | U68: =SUMIFS(易佰兴基本户!$P:$P,易佰兴基本户!$B:$B,"="&$E$2,易佰兴基本户!D:D,"="&$C68) -> 0
B69: =B67 -> 5 | C69: 营业外支出-赔偿款 | D69: =SUMIFS(#REF!,#REF!,"="&$E$2,#REF!,"="&$C69) -> #REF! | E69: =SUMIFS(力喆实业中国银行!$H:$H,力喆实业中国银行!$B:$B,"="&$E$2,力喆实业中国银行!$D:$D,"="&$C69) -> 0 | F69: =SUMIFS(力喆产业农商银行!$H:$H,力喆产业农商银行!$B:$B,"="&$E$2,力喆产业农商银行!$D:$D,"="&$C69) -> 0 | G69: =SUMIFS(徐洁招商银行!$H:$H,徐洁招商银行!$B:$B,"="&$E$2,徐洁招商银行!$D:$D,"="&$C69) -> 0 | H69: =SUMIFS(力喆贸易建设银行!$H:$H,力喆贸易建设银行!$B:$B,"="&$E$2,力喆贸易建设银行!$D:$D,"="&$C69) -> 0 | I69: =SUMIFS(元生万物建设银行!$H:$H,元生万物建设银行!$B:$B,"="&$E$2,元生万物建设银行!$D:$D,"="&$C69) -> 0 | J69: =SUMIFS(言吾言中国银行!$H:$H,言吾言中国银行!$B:$B,"="&$E$2,言吾言中国银行!$D:$D,"="&$C69) -> 0 | K69: =SUMIFS(力喆传媒海峡银行!$H:$H,力喆传媒海峡银行!$B:$B,"="&$E$2,力喆传媒海峡银行!$D:$D,"="&$C69) -> 0 | L69: =SUMIFS(古玩城农商银行!$O:$O,古玩城农商银行!$B:$B,"="&$E$2,古玩城农商银行!$D:$D,"="&$C69) -> 0 | M69: 0 | N69: =SUMIFS(艾泊烨海峡银行!$H:$H,艾泊烨海峡银行!$B:$B,"="&$E$2,艾泊烨海峡银行!$D:$D,"="&$C69) -> 0 | O69: 0 | P69: =SUMIFS(艾泊烨农商银行!$J:$J,艾泊烨农商银行!$B:$B,"="&$E$2,艾泊烨农商银行!D:D,"="&$C69) -> 0 | Q69: =SUMIFS(艾泊烨私户银行!$H:$H,艾泊烨私户银行!$B:$B,"="&$E$2,艾泊烨私户银行!$D:$D,"="&$C69) -> 0 | R69: =SUMIFS(易佰兴建行!$P:$P,易佰兴建行!$B:$B,"="&$E$2,易佰兴建行!D:D,"="&$C69) -> 0 | S69: =SUMIFS(易佰兴私户!$P:$P,易佰兴私户!$B:$B,"="&$E$2,易佰兴私户!$D:$D,"="&$C69) -> 0 | T69: =SUMIFS(易佰兴现金!$O:$O,易佰兴现金!$B:$B,"="&$E$2,易佰兴现金!D:D,"="&$C69) -> 0 | U69: =SUMIFS(易佰兴基本户!$P:$P,易佰兴基本户!$B:$B,"="&$E$2,易佰兴基本户!D:D,"="&$C69) -> 0
B70: =B68 -> 5 | C70: 物业修缮费 | D70: =SUMIFS(#REF!,#REF!,"="&$E$2,#REF!,"="&$C70) -> #REF! | E70: =SUMIFS(力喆实业中国银行!$H:$H,力喆实业中国银行!$B:$B,"="&$E$2,力喆实业中国银行!$D:$D,"="&$C70) -> 0 | F70: =SUMIFS(力喆产业农商银行!$H:$H,力喆产业农商银行!$B:$B,"="&$E$2,力喆产业农商银行!$D:$D,"="&$C70) -> 0 | G70: =SUMIFS(徐洁招商银行!$H:$H,徐洁招商银行!$B:$B,"="&$E$2,徐洁招商银行!$D:$D,"="&$C70) -> 0 | H70: =SUMIFS(力喆贸易建设银行!$H:$H,力喆贸易建设银行!$B:$B,"="&$E$2,力喆贸易建设银行!$D:$D,"="&$C70) -> 0 | I70: =SUMIFS(元生万物建设银行!$H:$H,元生万物建设银行!$B:$B,"="&$E$2,元生万物建设银行!$D:$D,"="&$C70) -> 0 | J70: =SUMIFS(言吾言中国银行!$H:$H,言吾言中国银行!$B:$B,"="&$E$2,言吾言中国银行!$D:$D,"="&$C70) -> 0 | K70: =SUMIFS(力喆传媒海峡银行!$H:$H,力喆传媒海峡银行!$B:$B,"="&$E$2,力喆传媒海峡银行!$D:$D,"="&$C70) -> 0 | L70: =SUMIFS(古玩城农商银行!$O:$O,古玩城农商银行!$B:$B,"="&$E$2,古玩城农商银行!$D:$D,"="&$C70) -> 215.24 | M70: 0 | N70: =SUMIFS(艾泊烨海峡银行!$H:$H,艾泊烨海峡银行!$B:$B,"="&$E$2,艾泊烨海峡银行!$D:$D,"="&$C70) -> 0 | O70: 0 | P70: =SUMIFS(艾泊烨农商银行!$J:$J,艾泊烨农商银行!$B:$B,"="&$E$2,艾泊烨农商银行!D:D,"="&$C70) -> 0 | Q70: =SUMIFS(艾泊烨私户银行!$H:$H,艾泊烨私户银行!$B:$B,"="&$E$2,艾泊烨私户银行!$D:$D,"="&$C70) -> 0 | R70: =SUMIFS(易佰兴建行!$P:$P,易佰兴建行!$B:$B,"="&$E$2,易佰兴建行!D:D,"="&$C70) -> 0 | S70: =SUMIFS(易佰兴私户!$P:$P,易佰兴私户!$B:$B,"="&$E$2,易佰兴私户!$D:$D,"="&$C70) -> 0 | T70: =SUMIFS(易佰兴现金!$O:$O,易佰兴现金!$B:$B,"="&$E$2,易佰兴现金!D:D,"="&$C70) -> 0 | U70: =SUMIFS(易佰兴基本户!$P:$P,易佰兴基本户!$B:$B,"="&$E$2,易佰兴基本户!D:D,"="&$C70) -> 0
B71: =B69 -> 5 | C71: 利息支出 | D71: =SUMIFS(#REF!,#REF!,"="&$E$2,#REF!,"="&$C71) -> #REF! | E71: =SUMIFS(力喆实业中国银行!$H:$H,力喆实业中国银行!$B:$B,"="&$E$2,力喆实业中国银行!$D:$D,"="&$C71) -> 0 | F71: =SUMIFS(力喆产业农商银行!$H:$H,力喆产业农商银行!$B:$B,"="&$E$2,力喆产业农商银行!$D:$D,"="&$C71) -> 0 | G71: =SUMIFS(徐洁招商银行!$H:$H,徐洁招商银行!$B:$B,"="&$E$2,徐洁招商银行!$D:$D,"="&$C71) -> 0 | H71: =SUMIFS(力喆贸易建设银行!$H:$H,力喆贸易建设银行!$B:$B,"="&$E$2,力喆贸易建设银行!$D:$D,"="&$C71) -> 0 | I71: =SUMIFS(元生万物建设银行!$H:$H,元生万物建设银行!$B:$B,"="&$E$2,元生万物建设银行!$D:$D,"="&$C71) -> 0 | J71: =SUMIFS(言吾言中国银行!$H:$H,言吾言中国银行!$B:$B,"="&$E$2,言吾言中国银行!$D:$D,"="&$C71) -> 0 | K71: =SUMIFS(力喆传媒海峡银行!$H:$H,力喆传媒海峡银行!$B:$B,"="&$E$2,力喆传媒海峡银行!$D:$D,"="&$C71) -> 0 | L71: =SUMIFS(古玩城农商银行!$O:$O,古玩城农商银行!$B:$B,"="&$E$2,古玩城农商银行!$D:$D,"="&$C71) -> 3438.71 | M71: 0 | N71: =SUMIFS(艾泊烨海峡银行!$H:$H,艾泊烨海峡银行!$B:$B,"="&$E$2,艾泊烨海峡银行!$D:$D,"="&$C71) -> 0 | O71: 0 | P71: =SUMIFS(艾泊烨农商银行!$J:$J,艾泊烨农商银行!$B:$B,"="&$E$2,艾泊烨农商银行!D:D,"="&$C71) -> 0 | Q71: =SUMIFS(艾泊烨私户银行!$H:$H,艾泊烨私户银行!$B:$B,"="&$E$2,艾泊烨私户银行!$D:$D,"="&$C71) -> 0 | R71: =SUMIFS(易佰兴建行!$P:$P,易佰兴建行!$B:$B,"="&$E$2,易佰兴建行!D:D,"="&$C71) -> 0 | S71: =SUMIFS(易佰兴私户!$P:$P,易佰兴私户!$B:$B,"="&$E$2,易佰兴私户!$D:$D,"="&$C71) -> 0 | T71: =SUMIFS(易佰兴现金!$O:$O,易佰兴现金!$B:$B,"="&$E$2,易佰兴现金!D:D,"="&$C71) -> 0 | U71: =SUMIFS(易佰兴基本户!$P:$P,易佰兴基本户!$B:$B,"="&$E$2,易佰兴基本户!D:D,"="&$C71) -> 0
B72: =B70 -> 5 | C72: 还贷款本金 | E72: =SUMIFS(力喆实业中国银行!$H:$H,力喆实业中国银行!$B:$B,"="&$E$2,力喆实业中国银行!$D:$D,"="&$C72) -> 0 | F72: =SUMIFS(力喆产业农商银行!$H:$H,力喆产业农商银行!$B:$B,"="&$E$2,力喆产业农商银行!$D:$D,"="&$C72) -> 0 | G72: =SUMIFS(徐洁招商银行!$H:$H,徐洁招商银行!$B:$B,"="&$E$2,徐洁招商银行!$D:$D,"="&$C72) -> 0 | H72: =SUMIFS(力喆贸易建设银行!$H:$H,力喆贸易建设银行!$B:$B,"="&$E$2,力喆贸易建设银行!$D:$D,"="&$C72) -> 0 | P72: =SUMIFS(艾泊烨农商银行!$J:$J,艾泊烨农商银行!$B:$B,"="&$E$2,艾泊烨农商银行!D:D,"="&$C72) -> 0 | Q72: =SUMIFS(艾泊烨私户银行!$H:$H,艾泊烨私户银行!$B:$B,"="&$E$2,艾泊烨私户银行!$D:$D,"="&$C72) -> 0 | R72: =SUMIFS(易佰兴建行!$P:$P,易佰兴建行!$B:$B,"="&$E$2,易佰兴建行!D:D,"="&$C72) -> 0 | S72: =SUMIFS(易佰兴私户!$P:$P,易佰兴私户!$B:$B,"="&$E$2,易佰兴私户!$D:$D,"="&$C72) -> 0 | T72: =SUMIFS(易佰兴现金!$O:$O,易佰兴现金!$B:$B,"="&$E$2,易佰兴现金!D:D,"="&$C72) -> 0 | U72: =SUMIFS(易佰兴基本户!$P:$P,易佰兴基本户!$B:$B,"="&$E$2,易佰兴基本户!D:D,"="&$C72) -> 0
B73: =B70 -> 5 | C73: 股东分红 | D73: =SUMIFS(#REF!,#REF!,"="&$E$2,#REF!,"="&$C73) -> #REF! | E73: =SUMIFS(力喆实业中国银行!$H:$H,力喆实业中国银行!$B:$B,"="&$E$2,力喆实业中国银行!$D:$D,"="&$C73) -> 0 | F73: =SUMIFS(力喆产业农商银行!$H:$H,力喆产业农商银行!$B:$B,"="&$E$2,力喆产业农商银行!$D:$D,"="&$C73) -> 0 | G73: =SUMIFS(徐洁招商银行!$H:$H,徐洁招商银行!$B:$B,"="&$E$2,徐洁招商银行!$D:$D,"="&$C73) -> 0 | H73: =SUMIFS(力喆贸易建设银行!$H:$H,力喆贸易建设银行!$B:$B,"="&$E$2,力喆贸易建设银行!$D:$D,"="&$C73) -> 0 | I73: =SUMIFS(元生万物建设银行!$H:$H,元生万物建设银行!$B:$B,"="&$E$2,元生万物建设银行!$D:$D,"="&$C73) -> 0 | J73: =SUMIFS(言吾言中国银行!$H:$H,言吾言中国银行!$B:$B,"="&$E$2,言吾言中国银行!$D:$D,"="&$C73) -> 0 | K73: =SUMIFS(力喆传媒海峡银行!$H:$H,力喆传媒海峡银行!$B:$B,"="&$E$2,力喆传媒海峡银行!$D:$D,"="&$C73) -> 0 | L73: =SUMIFS(古玩城农商银行!$O:$O,古玩城农商银行!$B:$B,"="&$E$2,古玩城农商银行!$D:$D,"="&$C73) -> 0 | M73: 0 | N73: =SUMIFS(艾泊烨海峡银行!$H:$H,艾泊烨海峡银行!$B:$B,"="&$E$2,艾泊烨海峡银行!$D:$D,"="&$C73) -> 0 | O73: 0 | P73: =SUMIFS(艾泊烨农商银行!$J:$J,艾泊烨农商银行!$B:$B,"="&$E$2,艾泊烨农商银行!D:D,"="&$C73) -> 0 | Q73: =SUMIFS(艾泊烨私户银行!$H:$H,艾泊烨私户银行!$B:$B,"="&$E$2,艾泊烨私户银行!$D:$D,"="&$C73) -> 0 | R73: =SUMIFS(易佰兴建行!$P:$P,易佰兴建行!$B:$B,"="&$E$2,易佰兴建行!D:D,"="&$C73) -> 0 | S73: =SUMIFS(易佰兴私户!$P:$P,易佰兴私户!$B:$B,"="&$E$2,易佰兴私户!$D:$D,"="&$C73) -> 0 | T73: =SUMIFS(易佰兴现金!$O:$O,易佰兴现金!$B:$B,"="&$E$2,易佰兴现金!D:D,"="&$C73) -> 0 | U73: =SUMIFS(易佰兴基本户!$P:$P,易佰兴基本户!$B:$B,"="&$E$2,易佰兴基本户!D:D,"="&$C73) -> 0
B74: =B73 -> 5 | C74: 股权投资款 | D74: =SUMIFS(#REF!,#REF!,"="&$E$2,#REF!,"="&$C74) -> #REF! | E74: =SUMIFS(力喆实业中国银行!$H:$H,力喆实业中国银行!$B:$B,"="&$E$2,力喆实业中国银行!$D:$D,"="&$C74) -> 0 | F74: =SUMIFS(力喆产业农商银行!$H:$H,力喆产业农商银行!$B:$B,"="&$E$2,力喆产业农商银行!$D:$D,"="&$C74) -> 0 | G74: =SUMIFS(徐洁招商银行!$H:$H,徐洁招商银行!$B:$B,"="&$E$2,徐洁招商银行!$D:$D,"="&$C74) -> 0 | H74: =SUMIFS(力喆贸易建设银行!$H:$H,力喆贸易建设银行!$B:$B,"="&$E$2,力喆贸易建设银行!$D:$D,"="&$C74) -> 0 | I74: =SUMIFS(元生万物建设银行!$H:$H,元生万物建设银行!$B:$B,"="&$E$2,元生万物建设银行!$D:$D,"="&$C74) -> 0 | J74: =SUMIFS(言吾言中国银行!$H:$H,言吾言中国银行!$B:$B,"="&$E$2,言吾言中国银行!$D:$D,"="&$C74) -> 0 | K74: =SUMIFS(力喆传媒海峡银行!$H:$H,力喆传媒海峡银行!$B:$B,"="&$E$2,力喆传媒海峡银行!$D:$D,"="&$C74) -> 0 | L74: =SUMIFS(古玩城农商银行!$O:$O,古玩城农商银行!$B:$B,"="&$E$2,古玩城农商银行!$D:$D,"="&$C74) -> 0 | M74: 0 | N74: =SUMIFS(艾泊烨海峡银行!$H:$H,艾泊烨海峡银行!$B:$B,"="&$E$2,艾泊烨海峡银行!$D:$D,"="&$C74) -> 0 | O74: 0 | P74: =SUMIFS(艾泊烨农商银行!$J:$J,艾泊烨农商银行!$B:$B,"="&$E$2,艾泊烨农商银行!D:D,"="&$C74) -> 0 | Q74: =SUMIFS(艾泊烨私户银行!$H:$H,艾泊烨私户银行!$B:$B,"="&$E$2,艾泊烨私户银行!$D:$D,"="&$C74) -> 0 | R74: =SUMIFS(易佰兴建行!$P:$P,易佰兴建行!$B:$B,"="&$E$2,易佰兴建行!D:D,"="&$C74) -> 0 | S74: =SUMIFS(易佰兴私户!$P:$P,易佰兴私户!$B:$B,"="&$E$2,易佰兴私户!$D:$D,"="&$C74) -> 0 | T74: =SUMIFS(易佰兴现金!$O:$O,易佰兴现金!$B:$B,"="&$E$2,易佰兴现金!D:D,"="&$C74) -> 0 | U74: =SUMIFS(易佰兴基本户!$P:$P,易佰兴基本户!$B:$B,"="&$E$2,易佰兴基本户!D:D,"="&$C74) -> 0
B75: =B74 -> 5 | C75: 往来款 | D75: =SUMIFS(#REF!,#REF!,"="&$E$2,#REF!,"="&$C75) -> #REF! | E75: =SUMIFS(力喆实业中国银行!$H:$H,力喆实业中国银行!$B:$B,"="&$E$2,力喆实业中国银行!$D:$D,"="&$C75) -> 0 | F75: =SUMIFS(力喆产业农商银行!$H:$H,力喆产业农商银行!$B:$B,"="&$E$2,力喆产业农商银行!$D:$D,"="&$C75) -> 0 | G75: =SUMIFS(徐洁招商银行!$H:$H,徐洁招商银行!$B:$B,"="&$E$2,徐洁招商银行!$D:$D,"="&$C75) -> 47930.36 | H75: =SUMIFS(力喆贸易建设银行!$H:$H,力喆贸易建设银行!$B:$B,"="&$E$2,力喆贸易建设银行!$D:$D,"="&$C75) -> 30000 | I75: =SUMIFS(元生万物建设银行!$H:$H,元生万物建设银行!$B:$B,"="&$E$2,元生万物建设银行!$D:$D,"="&$C75) -> 0 | J75: =SUMIFS(言吾言中国银行!$H:$H,言吾言中国银行!$B:$B,"="&$E$2,言吾言中国银行!$D:$D,"="&$C75) -> 0 | K75: =SUMIFS(力喆传媒海峡银行!$H:$H,力喆传媒海峡银行!$B:$B,"="&$E$2,力喆传媒海峡银行!$D:$D,"="&$C75) -> 0 | L75: =SUMIFS(古玩城农商银行!$O:$O,古玩城农商银行!$B:$B,"="&$E$2,古玩城农商银行!$D:$D,"="&$C75) -> 25000 | M75: 0 | N75: =SUMIFS(艾泊烨海峡银行!$H:$H,艾泊烨海峡银行!$B:$B,"="&$E$2,艾泊烨海峡银行!$D:$D,"="&$C75) -> 16000 | O75: 0 | P75: =SUMIFS(艾泊烨农商银行!$J:$J,艾泊烨农商银行!$B:$B,"="&$E$2,艾泊烨农商银行!D:D,"="&$C75) -> 0 | Q75: =SUMIFS(艾泊烨私户银行!$H:$H,艾泊烨私户银行!$B:$B,"="&$E$2,艾泊烨私户银行!$D:$D,"="&$C75) -> 19844.24 | R75: =SUMIFS(易佰兴建行!$P:$P,易佰兴建行!$B:$B,"="&$E$2,易佰兴建行!D:D,"="&$C75) -> 0 | S75: =SUMIFS(易佰兴私户!$P:$P,易佰兴私户!$B:$B,"="&$E$2,易佰兴私户!$D:$D,"="&$C75) -> 24300 | T75: =SUMIFS(易佰兴现金!$O:$O,易佰兴现金!$B:$B,"="&$E$2,易佰兴现金!D:D,"="&$C75) -> 0 | U75: =SUMIFS(易佰兴基本户!$P:$P,易佰兴基本户!$B:$B,"="&$E$2,易佰兴基本户!D:D,"="&$C75) -> 0
B76: =B75 -> 5 | C76: 借款支出 | E76: =SUMIFS(力喆实业中国银行!$H:$H,力喆实业中国银行!$B:$B,"="&$E$2,力喆实业中国银行!$D:$D,"="&$C76) -> 0 | F76: =SUMIFS(力喆产业农商银行!$H:$H,力喆产业农商银行!$B:$B,"="&$E$2,力喆产业农商银行!$D:$D,"="&$C76) -> 0 | G76: =SUMIFS(徐洁招商银行!$H:$H,徐洁招商银行!$B:$B,"="&$E$2,徐洁招商银行!$D:$D,"="&$C76) -> 0 | H76: =SUMIFS(力喆贸易建设银行!$H:$H,力喆贸易建设银行!$B:$B,"="&$E$2,力喆贸易建设银行!$D:$D,"="&$C76) -> 0 | L76: =SUMIFS(古玩城农商银行!$O:$O,古玩城农商银行!$B:$B,"="&$E$2,古玩城农商银行!$D:$D,"="&$C76) -> 0 | M76: 0 | N76: =SUMIFS(艾泊烨海峡银行!$H:$H,艾泊烨海峡银行!$B:$B,"="&$E$2,艾泊烨海峡银行!$D:$D,"="&$C76) -> 0 | O76: 0 | P76: =SUMIFS(艾泊烨农商银行!$J:$J,艾泊烨农商银行!$B:$B,"="&$E$2,艾泊烨农商银行!D:D,"="&$C76) -> 0 | Q76: =SUMIFS(艾泊烨私户银行!$H:$H,艾泊烨私户银行!$B:$B,"="&$E$2,艾泊烨私户银行!$D:$D,"="&$C76) -> 0 | R76: =SUMIFS(易佰兴建行!$P:$P,易佰兴建行!$B:$B,"="&$E$2,易佰兴建行!D:D,"="&$C76) -> 0 | S76: =SUMIFS(易佰兴私户!$P:$P,易佰兴私户!$B:$B,"="&$E$2,易佰兴私户!$D:$D,"="&$C76) -> 0 | T76: =SUMIFS(易佰兴现金!$O:$O,易佰兴现金!$B:$B,"="&$E$2,易佰兴现金!D:D,"="&$C76) -> 0 | U76: =SUMIFS(易佰兴基本户!$P:$P,易佰兴基本户!$B:$B,"="&$E$2,易佰兴基本户!D:D,"="&$C76) -> 0
B77: =B76 -> 5 | C77: 拆除费用 | E77: =SUMIFS(力喆实业中国银行!$H:$H,力喆实业中国银行!$B:$B,"="&$E$2,力喆实业中国银行!$D:$D,"="&$C77) -> 0 | F77: =SUMIFS(力喆产业农商银行!$H:$H,力喆产业农商银行!$B:$B,"="&$E$2,力喆产业农商银行!$D:$D,"="&$C77) -> 0 | G77: =SUMIFS(徐洁招商银行!$H:$H,徐洁招商银行!$B:$B,"="&$E$2,徐洁招商银行!$D:$D,"="&$C77) -> 0 | H77: =SUMIFS(力喆贸易建设银行!$H:$H,力喆贸易建设银行!$B:$B,"="&$E$2,力喆贸易建设银行!$D:$D,"="&$C77) -> 0 | L77: =SUMIFS(古玩城农商银行!$O:$O,古玩城农商银行!$B:$B,"="&$E$2,古玩城农商银行!$D:$D,"="&$C77) -> 0 | M77: 0 | N77: =SUMIFS(艾泊烨海峡银行!$H:$H,艾泊烨海峡银行!$B:$B,"="&$E$2,艾泊烨海峡银行!$D:$D,"="&$C77) -> 0 | O77: 0 | P77: =SUMIFS(艾泊烨农商银行!$J:$J,艾泊烨农商银行!$B:$B,"="&$E$2,艾泊烨农商银行!D:D,"="&$C77) -> 0 | Q77: =SUMIFS(艾泊烨私户银行!$H:$H,艾泊烨私户银行!$B:$B,"="&$E$2,艾泊烨私户银行!$D:$D,"="&$C77) -> 0 | R77: =SUMIFS(易佰兴建行!$P:$P,易佰兴建行!$B:$B,"="&$E$2,易佰兴建行!D:D,"="&$C77) -> 0 | S77: =SUMIFS(易佰兴私户!$P:$P,易佰兴私户!$B:$B,"="&$E$2,易佰兴私户!$D:$D,"="&$C77) -> 0 | T77: =SUMIFS(易佰兴现金!$O:$O,易佰兴现金!$B:$B,"="&$E$2,易佰兴现金!D:D,"="&$C77) -> 0 | U77: =SUMIFS(易佰兴基本户!$P:$P,易佰兴基本户!$B:$B,"="&$E$2,易佰兴基本户!D:D,"="&$C77) -> 0
B78: =B77 -> 5 | C78: 丝绸厂遮阳篷安装费 | E78: =SUMIFS(力喆实业中国银行!$H:$H,力喆实业中国银行!$B:$B,"="&$E$2,力喆实业中国银行!$D:$D,"="&$C78) -> 0 | F78: =SUMIFS(力喆产业农商银行!$H:$H,力喆产业农商银行!$B:$B,"="&$E$2,力喆产业农商银行!$D:$D,"="&$C78) -> 0 | G78: =SUMIFS(徐洁招商银行!$H:$H,徐洁招商银行!$B:$B,"="&$E$2,徐洁招商银行!$D:$D,"="&$C78) -> 0 | H78: =SUMIFS(力喆贸易建设银行!$H:$H,力喆贸易建设银行!$B:$B,"="&$E$2,力喆贸易建设银行!$D:$D,"="&$C78) -> 0 | L78: =SUMIFS(古玩城农商银行!$O:$O,古玩城农商银行!$B:$B,"="&$E$2,古玩城农商银行!$D:$D,"="&$C78) -> 0 | M78: 0 | N78: =SUMIFS(艾泊烨海峡银行!$H:$H,艾泊烨海峡银行!$B:$B,"="&$E$2,艾泊烨海峡银行!$D:$D,"="&$C78) -> 150000 | O78: 0 | P78: =SUMIFS(艾泊烨农商银行!$J:$J,艾泊烨农商银行!$B:$B,"="&$E$2,艾泊烨农商银行!D:D,"="&$C78) -> 0 | Q78: =SUMIFS(艾泊烨私户银行!$H:$H,艾泊烨私户银行!$B:$B,"="&$E$2,艾泊烨私户银行!$D:$D,"="&$C78) -> 0 | R78: =SUMIFS(易佰兴建行!$P:$P,易佰兴建行!$B:$B,"="&$E$2,易佰兴建行!D:D,"="&$C78) -> 0 | S78: =SUMIFS(易佰兴私户!$P:$P,易佰兴私户!$B:$B,"="&$E$2,易佰兴私户!$D:$D,"="&$C78) -> 0 | T78: =SUMIFS(易佰兴现金!$O:$O,易佰兴现金!$B:$B,"="&$E$2,易佰兴现金!D:D,"="&$C78) -> 0 | U78: =SUMIFS(易佰兴基本户!$P:$P,易佰兴基本户!$B:$B,"="&$E$2,易佰兴基本户!D:D,"="&$C78) -> 0
B79: =B78 -> 5 | C79: 丝绸厂土建工程款 | E79: =SUMIFS(力喆实业中国银行!$H:$H,力喆实业中国银行!$B:$B,"="&$E$2,力喆实业中国银行!$D:$D,"="&$C79) -> 0 | F79: =SUMIFS(力喆产业农商银行!$H:$H,力喆产业农商银行!$B:$B,"="&$E$2,力喆产业农商银行!$D:$D,"="&$C79) -> 0 | G79: =SUMIFS(徐洁招商银行!$H:$H,徐洁招商银行!$B:$B,"="&$E$2,徐洁招商银行!$D:$D,"="&$C79) -> 0 | H79: =SUMIFS(力喆贸易建设银行!$H:$H,力喆贸易建设银行!$B:$B,"="&$E$2,力喆贸易建设银行!$D:$D,"="&$C79) -> 0 | L79: =SUMIFS(古玩城农商银行!$O:$O,古玩城农商银行!$B:$B,"="&$E$2,古玩城农商银行!$D:$D,"="&$C79) -> 0 | M79: 0 | N79: =SUMIFS(艾泊烨海峡银行!$H:$H,艾泊烨海峡银行!$B:$B,"="&$E$2,艾泊烨海峡银行!$D:$D,"="&$C79) -> 400000 | O79: 0 | P79: =SUMIFS(艾泊烨农商银行!$J:$J,艾泊烨农商银行!$B:$B,"="&$E$2,艾泊烨农商银行!D:D,"="&$C79) -> 0 | Q79: =SUMIFS(艾泊烨私户银行!$H:$H,艾泊烨私户银行!$B:$B,"="&$E$2,艾泊烨私户银行!$D:$D,"="&$C79) -> 0 | R79: =SUMIFS(易佰兴建行!$P:$P,易佰兴建行!$B:$B,"="&$E$2,易佰兴建行!D:D,"="&$C79) -> 0 | S79: =SUMIFS(易佰兴私户!$P:$P,易佰兴私户!$B:$B,"="&$E$2,易佰兴私户!$D:$D,"="&$C79) -> 0 | T79: =SUMIFS(易佰兴现金!$O:$O,易佰兴现金!$B:$B,"="&$E$2,易佰兴现金!D:D,"="&$C79) -> 0 | U79: =SUMIFS(易佰兴基本户!$P:$P,易佰兴基本户!$B:$B,"="&$E$2,易佰兴基本户!D:D,"="&$C79) -> 0
B80: =B79 -> 5 | C80: 丝绸厂车库机械设备
B81: =B80 -> 5 | C81: 王庄篮球馆
B82: =B81 -> 5 | C82: 丝绸厂电力工程
B83: =B79 -> 5 | C83: 道闸服务费 | E83: =SUMIFS(力喆实业中国银行!$H:$H,力喆实业中国银行!$B:$B,"="&$E$2,力喆实业中国银行!$D:$D,"="&$C83) -> 0 | F83: =SUMIFS(力喆产业农商银行!$H:$H,力喆产业农商银行!$B:$B,"="&$E$2,力喆产业农商银行!$D:$D,"="&$C83) -> 0 | G83: =SUMIFS(徐洁招商银行!$H:$H,徐洁招商银行!$B:$B,"="&$E$2,徐洁招商银行!$D:$D,"="&$C83) -> 0 | H83: =SUMIFS(力喆贸易建设银行!$H:$H,力喆贸易建设银行!$B:$B,"="&$E$2,力喆贸易建设银行!$D:$D,"="&$C83) -> 0 | L83: =SUMIFS(古玩城农商银行!$O:$O,古玩城农商银行!$B:$B,"="&$E$2,古玩城农商银行!$D:$D,"="&$C83) -> 0 | M83: 0 | N83: =SUMIFS(艾泊烨海峡银行!$H:$H,艾泊烨海峡银行!$B:$B,"="&$E$2,艾泊烨海峡银行!$D:$D,"="&$C83) -> 33600 | O83: 0 | P83: =SUMIFS(艾泊烨农商银行!$J:$J,艾泊烨农商银行!$B:$B,"="&$E$2,艾泊烨农商银行!D:D,"="&$C83) -> 0 | Q83: =SUMIFS(艾泊烨私户银行!$H:$H,艾泊烨私户银行!$B:$B,"="&$E$2,艾泊烨私户银行!$D:$D,"="&$C83) -> 0 | R83: =SUMIFS(易佰兴建行!$P:$P,易佰兴建行!$B:$B,"="&$E$2,易佰兴建行!D:D,"="&$C83) -> 0 | S83: =SUMIFS(易佰兴私户!$P:$P,易佰兴私户!$B:$B,"="&$E$2,易佰兴私户!$D:$D,"="&$C83) -> 0 | T83: =SUMIFS(易佰兴现金!$O:$O,易佰兴现金!$B:$B,"="&$E$2,易佰兴现金!D:D,"="&$C83) -> 0 | U83: =SUMIFS(易佰兴基本户!$P:$P,易佰兴基本户!$B:$B,"="&$E$2,易佰兴基本户!D:D,"="&$C83) -> 0
B84: =B83 -> 5 | C84: 场地租金 | E84: =SUMIFS(力喆实业中国银行!$H:$H,力喆实业中国银行!$B:$B,"="&$E$2,力喆实业中国银行!$D:$D,"="&$C84) -> 0 | F84: =SUMIFS(力喆产业农商银行!$H:$H,力喆产业农商银行!$B:$B,"="&$E$2,力喆产业农商银行!$D:$D,"="&$C84) -> 0 | G84: =SUMIFS(徐洁招商银行!$H:$H,徐洁招商银行!$B:$B,"="&$E$2,徐洁招商银行!$D:$D,"="&$C84) -> 0 | H84: =SUMIFS(力喆贸易建设银行!$H:$H,力喆贸易建设银行!$B:$B,"="&$E$2,力喆贸易建设银行!$D:$D,"="&$C84) -> 0 | L84: =SUMIFS(古玩城农商银行!$O:$O,古玩城农商银行!$B:$B,"="&$E$2,古玩城农商银行!$D:$D,"="&$C84) -> 0 | M84: 0 | N84: =SUMIFS(艾泊烨海峡银行!$H:$H,艾泊烨海峡银行!$B:$B,"="&$E$2,艾泊烨海峡银行!$D:$D,"="&$C84) -> 301300 | O84: 0 | P84: =SUMIFS(艾泊烨农商银行!$J:$J,艾泊烨农商银行!$B:$B,"="&$E$2,艾泊烨农商银行!D:D,"="&$C84) -> 0 | Q84: =SUMIFS(艾泊烨私户银行!$H:$H,艾泊烨私户银行!$B:$B,"="&$E$2,艾泊烨私户银行!$D:$D,"="&$C84) -> 0 | R84: =SUMIFS(易佰兴建行!$P:$P,易佰兴建行!$B:$B,"="&$E$2,易佰兴建行!D:D,"="&$C84) -> 0 | S84: =SUMIFS(易佰兴私户!$P:$P,易佰兴私户!$B:$B,"="&$E$2,易佰兴私户!$D:$D,"="&$C84) -> 0 | T84: =SUMIFS(易佰兴现金!$O:$O,易佰兴现金!$B:$B,"="&$E$2,易佰兴现金!D:D,"="&$C84) -> 0 | U84: =SUMIFS(易佰兴基本户!$P:$P,易佰兴基本户!$B:$B,"="&$E$2,易佰兴基本户!D:D,"="&$C84) -> 0
B85: =B84 -> 5 | C85: 垃圾清运费 | E85: =SUMIFS(力喆实业中国银行!$H:$H,力喆实业中国银行!$B:$B,"="&$E$2,力喆实业中国银行!$D:$D,"="&$C85) -> 0 | F85: =SUMIFS(力喆产业农商银行!$H:$H,力喆产业农商银行!$B:$B,"="&$E$2,力喆产业农商银行!$D:$D,"="&$C85) -> 0 | G85: =SUMIFS(徐洁招商银行!$H:$H,徐洁招商银行!$B:$B,"="&$E$2,徐洁招商银行!$D:$D,"="&$C85) -> 0 | H85: =SUMIFS(力喆贸易建设银行!$H:$H,力喆贸易建设银行!$B:$B,"="&$E$2,力喆贸易建设银行!$D:$D,"="&$C85) -> 0 | L85: =SUMIFS(古玩城农商银行!$O:$O,古玩城农商银行!$B:$B,"="&$E$2,古玩城农商银行!$D:$D,"="&$C85) -> 0 | N85: =SUMIFS(艾泊烨海峡银行!$H:$H,艾泊烨海峡银行!$B:$B,"="&$E$2,艾泊烨海峡银行!$D:$D,"="&$C85) -> 0 | R85: =SUMIFS(易佰兴建行!$P:$P,易佰兴建行!$B:$B,"="&$E$2,易佰兴建行!D:D,"="&$C85) -> 0 | S85: =SUMIFS(易佰兴私户!$P:$P,易佰兴私户!$B:$B,"="&$E$2,易佰兴私户!$D:$D,"="&$C85) -> 0 | T85: =SUMIFS(易佰兴现金!$O:$O,易佰兴现金!$B:$B,"="&$E$2,易佰兴现金!D:D,"="&$C85) -> 0 | U85: =SUMIFS(易佰兴基本户!$P:$P,易佰兴基本户!$B:$B,"="&$E$2,易佰兴基本户!D:D,"="&$C85) -> 0
B86: =B85 -> 5 | C86: 中介介绍费 | E86: =SUMIFS(力喆实业中国银行!$H:$H,力喆实业中国银行!$B:$B,"="&$E$2,力喆实业中国银行!$D:$D,"="&$C86) -> 0 | F86: =SUMIFS(力喆产业农商银行!$H:$H,力喆产业农商银行!$B:$B,"="&$E$2,力喆产业农商银行!$D:$D,"="&$C86) -> 0 | G86: =SUMIFS(徐洁招商银行!$H:$H,徐洁招商银行!$B:$B,"="&$E$2,徐洁招商银行!$D:$D,"="&$C86) -> 0 | H86: =SUMIFS(力喆贸易建设银行!$H:$H,力喆贸易建设银行!$B:$B,"="&$E$2,力喆贸易建设银行!$D:$D,"="&$C86) -> 0 | L86: =SUMIFS(古玩城农商银行!$O:$O,古玩城农商银行!$B:$B,"="&$E$2,古玩城农商银行!$D:$D,"="&$C86) -> 0 | N86: =SUMIFS(艾泊烨海峡银行!$H:$H,艾泊烨海峡银行!$B:$B,"="&$E$2,艾泊烨海峡银行!$D:$D,"="&$C86) -> 0 | R86: =SUMIFS(易佰兴建行!$P:$P,易佰兴建行!$B:$B,"="&$E$2,易佰兴建行!D:D,"="&$C86) -> 0 | S86: =SUMIFS(易佰兴私户!$P:$P,易佰兴私户!$B:$B,"="&$E$2,易佰兴私户!$D:$D,"="&$C86) -> 0 | T86: =SUMIFS(易佰兴现金!$O:$O,易佰兴现金!$B:$B,"="&$E$2,易佰兴现金!D:D,"="&$C86) -> 0 | U86: =SUMIFS(易佰兴基本户!$P:$P,易佰兴基本户!$B:$B,"="&$E$2,易佰兴基本户!D:D,"="&$C86) -> 0
B87: =B86 -> 5 | C87: 佣金 | E87: =SUMIFS(力喆实业中国银行!$H:$H,力喆实业中国银行!$B:$B,"="&$E$2,力喆实业中国银行!$D:$D,"="&$C87) -> 0 | F87: =SUMIFS(力喆产业农商银行!$H:$H,力喆产业农商银行!$B:$B,"="&$E$2,力喆产业农商银行!$D:$D,"="&$C87) -> 0 | G87: =SUMIFS(徐洁招商银行!$H:$H,徐洁招商银行!$B:$B,"="&$E$2,徐洁招商银行!$D:$D,"="&$C87) -> 0 | H87: =SUMIFS(力喆贸易建设银行!$H:$H,力喆贸易建设银行!$B:$B,"="&$E$2,力喆贸易建设银行!$D:$D,"="&$C87) -> 0 | L87: =SUMIFS(古玩城农商银行!$O:$O,古玩城农商银行!$B:$B,"="&$E$2,古玩城农商银行!$D:$D,"="&$C87) -> 0 | N87: =SUMIFS(艾泊烨海峡银行!$H:$H,艾泊烨海峡银行!$B:$B,"="&$E$2,艾泊烨海峡银行!$D:$D,"="&$C87) -> 0 | R87: =SUMIFS(易佰兴建行!$P:$P,易佰兴建行!$B:$B,"="&$E$2,易佰兴建行!D:D,"="&$C87) -> 0 | S87: =SUMIFS(易佰兴私户!$P:$P,易佰兴私户!$B:$B,"="&$E$2,易佰兴私户!$D:$D,"="&$C87) -> 28137 | T87: =SUMIFS(易佰兴现金!$O:$O,易佰兴现金!$B:$B,"="&$E$2,易佰兴现金!D:D,"="&$C87) -> 0 | U87: =SUMIFS(易佰兴基本户!$P:$P,易佰兴基本户!$B:$B,"="&$E$2,易佰兴基本户!D:D,"="&$C87) -> 0
B88: =B87 -> 5 | C88: 还款 | E88: =SUMIFS(力喆实业中国银行!$H:$H,力喆实业中国银行!$B:$B,"="&$E$2,力喆实业中国银行!$D:$D,"="&$C88) -> 0 | F88: =SUMIFS(力喆产业农商银行!$H:$H,力喆产业农商银行!$B:$B,"="&$E$2,力喆产业农商银行!$D:$D,"="&$C88) -> 0 | G88: =SUMIFS(徐洁招商银行!$H:$H,徐洁招商银行!$B:$B,"="&$E$2,徐洁招商银行!$D:$D,"="&$C88) -> 0 | H88: =SUMIFS(力喆贸易建设银行!$H:$H,力喆贸易建设银行!$B:$B,"="&$E$2,力喆贸易建设银行!$D:$D,"="&$C88) -> 0 | L88: =SUMIFS(古玩城农商银行!$O:$O,古玩城农商银行!$B:$B,"="&$E$2,古玩城农商银行!$D:$D,"="&$C88) -> 130000 | N88: =SUMIFS(艾泊烨海峡银行!$H:$H,艾泊烨海峡银行!$B:$B,"="&$E$2,艾泊烨海峡银行!$D:$D,"="&$C88) -> 0 | T88: =SUMIFS(易佰兴现金!$O:$O,易佰兴现金!$B:$B,"="&$E$2,易佰兴现金!D:D,"="&$C88) -> 0
B89: 合计 | D89: =SUBTOTAL(109,D32:D88) -> #REF! | E89: =SUBTOTAL(109,E32:E88) -> 0 | F89: =SUBTOTAL(109,F32:F88) -> 51010.2 | G89: =SUBTOTAL(109,G32:G88) -> 143238.34 | H89: =SUBTOTAL(109,H32:H88) -> 68405.13 | I89: =SUBTOTAL(109,I32:I88) -> 30 | J89: =SUBTOTAL(109,J32:J88) -> 134 | K89: =SUBTOTAL(109,K32:K88) -> 0 | ... U89: =SUBTOTAL(109,U32:U88) -> 26785.73
B90: 校验 | D90: =D89-SUMIFS(#REF!,#REF!,汇总!$B$17) -> #REF! | E90: =E89-SUMIFS(力喆实业中国银行!$H:$H,力喆实业中国银行!$B:$B,"="&$E$2)-SUMIFS(力喆产业农商银行!$H:$H,力喆产业农商银行!$B:$B,"="&$E$2) -> -51010.2 | F90: =F89-SUMIFS(力喆实业中国银行!$H:$H,力喆实业中国银行!$B:$B,"="&$E$2)-SUMIFS(力喆产业农商银行!$H:$H,力喆产业农商银行!$B:$B,"="&$E$2) -> 0 | G90: =G89-SUMIFS(徐洁招商银行!$H:$H,徐洁招商银行!$B:$B,"="&$E$2) -> 0 | H90: =H89-SUMIFS(力喆贸易建设银行!$H:$H,力喆贸易建设银行!$B:$B,"="&$E$2) -> 0 | I90: =I89-SUMIFS(元生万物建设银行!$H:$H,元生万物建设银行!$B:$B,"="&$E$2) -> 0 | J90: =J89-SUMIFS(言吾言中国银行!$H:$H,言吾言中国银行!$B:$B,"="&$E$2) -> 0 | K90: =K89-SUMIFS(力喆传媒海峡银行!$H:$H,力喆传媒海峡银行!$B:$B,"="&$E$2) -> 0
B91: 银行余额 | D91: =D5+D28-D89 -> #REF! | E91: =E5+E28-E89 -> 0 | F91: =F5+F28-F89 -> 3636.48 | G91: =G5+G28-G89 -> 25473.62 | H91: =H5+H28-H89 -> 15980.38 | I91: =I5+I28-I89 -> 65072.22 | J91: =J5+J28-J89 -> 4285.25 | K91: =K5+K28-K89 -> 0 | ... U91: =U5+U28-U89 -> -1133.63

Sheet 付费项
B1: 收费项 | C1: 收入类型
B2: 薪资 | C2: 往来款 | D2: =VLOOKUP(收费名称[[#This Row],[收费项]],汇总!C:C,1,0) -> 薪资
B3: 五险一金 | C3: 房租 | D3: =VLOOKUP(收费名称[[#This Row],[收费项]],汇总!C:C,1,0) -> 五险一金
B4: 员工保险 | C4: 物业费 | D4: =VLOOKUP(收费名称[[#This Row],[收费项]],汇总!C:C,1,0) -> 员工保险
B5: 福利费 | D5: =VLOOKUP(收费名称[[#This Row],[收费项]],汇总!C:C,1,0) -> 福利费
B6: 招待费 | D6: =VLOOKUP(收费名称[[#This Row],[收费项]],汇总!C:C,1,0) -> 招待费
B7: 酒水费 | D7: =VLOOKUP(收费名称[[#This Row],[收费项]],汇总!C:C,1,0) -> 酒水费
B8: 公共关系费用 | D8: =VLOOKUP(收费名称[[#This Row],[收费项]],汇总!C:C,1,0) -> 公共关系费用
B9: 办公费 | D9: =VLOOKUP(收费名称[[#This Row],[收费项]],汇总!C:C,1,0) -> 办公费
B10: 低值易耗品 | D10: =VLOOKUP(收费名称[[#This Row],[收费项]],汇总!C:C,1,0) -> 低值易耗品
B11: 快递邮电费 | D11: =VLOOKUP(收费名称[[#This Row],[收费项]],汇总!C:C,1,0) -> 快递邮电费
B12: 通讯、宽带费 | D12: =VLOOKUP(收费名称[[#This Row],[收费项]],汇总!C:C,1,0) -> 通讯、宽带费
B13: 差旅费 | D13: =VLOOKUP(收费名称[[#This Row],[收费项]],汇总!C:C,1,0) -> 差旅费
B14: 退押金 | D14: =VLOOKUP(收费名称[[#This Row],[收费项]],汇总!C:C,1,0) -> 退押金
B15: 营销费用 | D15: =VLOOKUP(收费名称[[#This Row],[收费项]],汇总!C:C,1,0) -> 营销费用
B16: 油费 | D16: =VLOOKUP(收费名称[[#This Row],[收费项]],汇总!C:C,1,0) -> 油费
... B40: 车辆使用费 | D40: =VLOOKUP(收费名称[[#This Row],[收费项]],汇总!C:C,1,0) -> 车辆使用费
B41: 拆除费用
B42: 丝绸厂遮阳篷安装费
B43: 丝绸厂土建工程款
B44: 道闸服务费
B45: 场地租金
B46: 还贷款本金
B47: 光伏电费
B48: 垃圾清运费
B49: 中介介绍费
B50: 房租
B51: 佣金
B52: 借款支出
... B57: 丝绸厂电力工程
A58: 收入 | B58: 押金
A59: 收入 | B59: 往来款
B60: 借款转入
A61: 收入 | B61: 房租收入
A62: 收入 | B62: 物业收入
A63: 收入 | B63: 水电收入
A64: 收入 | B64: 摊位收入
A65: 收入 | B65: 其他收入
B66: 利息收入
B67: 贷款转入
B68: 月卡收入
B69: 营业分成收入
B70: 薪资、社医保
B71: 收回借款
B72: 充电桩收入
B73: 道闸服务费收入
B74: 场地租金收入
B75: 超出部分80%收入
B76: 停车费收入
B77: 广告费收入
B78: 利达大厦租金收入
K132: 19535.5

Sheet 力喆实业中国银行
A1: =HYPERLINK("#目录!a1","返回目录") -> 返回目录 | B1: 力喆产业银行日记账--中国银行
B3: 月 | C3: 日 | D3: 收费项 | E3: 收付人 | F3: 摘要 | G3: 收入 | H3: 支出 | I3: 余额 | J3: 备注
F4: 期初余额 | I4: 20187.05
B5: 3 | C5: 6 | D5: 银行手续费 | E5: 银行 | F5: 回单箱服务年费 | H5: 400 | I5: =I4+G5-H5 -> 19787.05
B6: 3 | C6: 20 | D6: 利息收入 | E6: 银行 | F6: 利息收入 | G6: 2.52 | I6: =I5+G6-H6 -> 19789.57
F7: 本月合计 | G7: =SUM(G5:G6) -> 2.52 | H7: =SUM(H5:H6) -> 400 | I7: =I4+G7-H7 -> 19789.57
B8: 6 | C8: 20 | D8: 利息收入 | E8: 银行 | F8: 利息收入 | G8: 2.53 | I8: =I7+G8-H8 -> 19792.1
F9: 本月合计 | G9: =SUM(G8) -> 2.53 | H9: =SUM(H8) -> 0 | I9: =I6+G9-H9 -> 19792.1
I10: =I9+G10-H10 -> 19792.1
I11: =I10+G11-H11 -> 19792.1
I12: =I11+G12-H12 -> 19792.1
I13: =I12+G13-H13 -> 19792.1
I14: =I13+G14-H14 -> 19792.1
I15: =I14+G15-H15 -> 19792.1
I16: =I15+G16-H16 -> 19792.1
I17: =I16+G17-H17 -> 19792.1
I18: =I17+G18-H18 -> 19792.1
I19: =I18+G19-H19 -> 19792.1
I20: =I19+G20-H20 -> 19792.1
I21: =I20+G21-H21 -> 19792.1
... I65: =I64+G65-H65 -> 19792.1

Sheet 力喆产业农商银行
A1: =HYPERLINK("#目录!a1","返回目录") -> 返回目录 | B1: 力喆产业银行日记账--农商银行
B3: 月 | C3: 日 | D3: 收费项 | E3: 收付人 | F3: 摘要 | G3: 收入 | H3: 支出 | I3: 余额 | J3: 备注
F4: 期初余额 | I4: 20301.19
B5: 1 | C5: 8 | D5: 银行手续费 | F5: 支付短信服务费 | H5: 10 | I5: =I4+G5-H5 -> 20291.19
B6: 1 | C6: 13 | D6: 税费 | E6: 国家税务总局福州市晋安区税务局 | F6: 工会经费（20251001-20251231） | H6: 24 | I6: =I5+G6-H6 -> 20267.19
B7: 1 | C7: 13 | D7: 税费 | E7: 国家税务总局福州市晋安区税务局 | F7: 支付印花税（20251001-20251231） | H7: 6.68 | I7: =I6+G7-H7 -> 20260.51
B8: 1 | C8: 16 | D8: 往来款 | E8: 徐洁 | F8: 收雅道巷63-1租金（2025.12.22-2026.3.21） | G8: 12832.11 | I8: =I7+G8-H8 -> 33092.62
B9: 1 | C9: 16 | D9: 房租 | E9: 福州名城保护开发有限公司 | F9: 支付雅道巷63-1租金（2025.12.22-2026.3.21） | H9: 12832.11 | I9: =I8+G9-H9 -> 20260.51
B10: 1 | C10: 16 | D10: 往来款 | E10: 福建力喆贸易有限公司 | F10: 收回力喆贸易借款 | G10: 50000 | I10: =I9+G10-H10 -> 70260.51
B11: 1 | C11: 21 | D11: 贷款利息 | E11: 农商银行 | F11: 支付900万贷款利息 | H11: 24189.3 | I11: =I10+G11-H11 -> 46071.21
B12: 1 | C12: 21 | D12: 贷款利息 | E12: 农商银行 | F12: 支付900万贷款利息 | H12: 12115.58 | I12: =I11+G12-H12 -> 33955.63
B13: 1 | C13: 21 | D13: 五险一金 | E13: 国家税务总局福州市晋安区税务局 | F13: 企业职工基本养老保险费 20260101-20260131 1940.64 失业保险费 20260101-20260131 80.88 工伤保险费 20260101-20260131 35.32 基本医疗保险费 20260101-20260131 886.6 生育保险 20260101-20260131 62.06 | H13: 3005.5 | I13: =I12+G13-H13 -> 30950.13
B14: 1 | C14: 25 | D14: 通讯、宽带费 | E14: 中国电信股份有限公司福州分公司 | F14: 12月电信宽带费 | H14: 249 | I14: =I13+G14-H14 -> 30701.13
B15: 1 | C15: 27 | D15: 房租收入 | E15: 福州心上造物网络科技有限公司 | F15: 收汤房巷3号26年1月租金4100元、1月物业及12月水费500元、电费119.91元、税费47.2元 | G15: 4767.11 | I15: =I14+G15-H15 -> 35468.24
B16: 1 | C16: 27 | D16: 房租收入 | E16: 福州心上造物网络科技有限公司 | F16: 收汤房巷1号26年1月租金4663.8元、1月物业886.4元、12月水费200元、电费120.75元、税费58.71元 | G16: 5929.66 | I16: =I15+G16-H16 -> 41397.9
F17: 本月合计 | G17: =SUM(G5:G16) -> 73528.88 | H17: =SUM(H5:H16) -> 52432.17 | I17: =I4+G17-H17 -> 41397.9
B18: 2 | C18: 8 | D18: 银行手续费 | E18: 银行 | F18: 支付短信服务费 | H18: 10 | I18: =I17+G18-H18 -> 41387.9
B19: 2 | C19: 10 | D19: ETC（闽AD10200） | E19: 福建省高速公路集团有限公司电子收费管理中心 | F19: 高速ETC记账卡批量扣款 | H19: 6.18 | I19: =I18+G19-H19 -> 41381.72
B20: 2 | C20: 13 | D20: 往来款 | E20: 福建力喆贸易有限公司 | F20: 收回力喆贸易借款 | G20: 20000 | I20: =I19+G20-H20 -> 61381.72
B21: 2 | C21: 13 | D21: 往来款 | E21: 徐洁 | F21: 一般户转入徐洁招行账户 | H21: 16000 | I21: =I20+G21-H21 -> 45381.72
B22: 2 | C22: 17 | D22: 通讯、宽带费 | E22: 中国电信股份有限公司福州分公司 | F22: 1月电信宽带费 | H22: 249 | I22: =I21+G22-H22 -> 45132.72
B23: 2 | C23: 21 | D23: 贷款利息 | E23: 农商银行 | F23: 支付900万贷款利息 | H23: 24189.3 | I23: =I22+G23-H23 -> 20943.42
B24: 2 | C24: 21 | D24: 贷款利息 | E24: 农商银行 | F24: 支付900万贷款利息 | H24: 12115.58 | I24: =I23+G24-H24 -> 8827.84
B25: 2 | C25: 24 | D25: 五险一金 | E25: 国家税务总局福州市晋安区税务局 | F25: 企业职工基本养老保险费 20260201-20260228 1940.64 失业保险费 20260201-20260228 80.88 工伤保险费 20260201-20260228 35.32 基本医疗保险费 20260201-20260228 886.6 生育保险 20260201-20260228 62.06 | H25: 3005.5 | I25: =I24+G25-H25 -> 5822.34
F26: 本月合计 | G26: =SUM(G18:G25) -> 20000 | H26: =SUM(H18:H25) -> 55575.56 | I26: =I17+G26-H26 -> 5822.34
B27: 3 | C27: 8 | D27: 银行手续费 | E27: 银行 | F27: 支付短信服务费 | H27: 10 | I27: =I26+G27-H27 -> 5812.34
B28: 3 | C28: 16 | D28: 通讯、宽带费 | E28: 中国电信股份有限公司福州分公司 | F28: 2月电信宽带费 | H28: 249.2 | I28: =I27+G28-H28 -> 5563.14
B29: 3 | C29: 16 | D29: 往来款 | E29: 福建力喆贸易有限公司 | F29: 收回力喆贸易借款 | G29: 32000 | I29: =I28+G29-H29 -> 37563.14
B30: 3 | C30: 21 | D30: 利息收入 | E30: 银行 | F30: 利息收入 | G30: 3.42 | I30: =I29+G30-H30 -> 37566.56
B31: 3 | C31: 21 | D31: 贷款利息 | E31: 农商银行 | F31: 支付900万贷款利息 | H31: 21848.4 | I31: =I30+G31-H31 -> 15718.16
B32: 3 | C32: 21 | D32: 贷款利息 | E32: 农商银行 | F32: 支付900万贷款利息 | H32: 10943.1 | I32: =I31+G32-H32 -> 4775.06
B33: 3 | C33: 23 | D33: 五险一金 | E33: 国家税务总局福州市晋安区税务局 | F33: 企业职工基本养老保险费 20260301-20260331 1940.64 失业保险费 20260301-20260331 80.88 工伤保险费 20260301-20260331 17.66 基本医疗保险费 20260301-20260331 886.6 生育保险 20260301-20260331 62.06 | H33: 2987.84 | I33: =I32+G33-H33 -> 1787.22
F34: 本月合计 | G34: =SUM(G27:G33) -> 32003.42 | H34: =SUM(H27:H33) -> 36038.54 | I34: =I26+G34-H34 -> 1787.22
B35: 4 | C35: 8 | D35: 银行手续费 | E35: 银行 | F35: 支付短信服务费 | H35: 10 | I35: =I34+G35-H35 -> 1777.22
B36: 4 | C36: 14 | D36: 通讯、宽带费 | E36: 中国电信股份有限公司福州分公司 | F36: 3月电信宽带费，宽带迁移服务费 | H36: 357 | I36: =I35+G36-H36 -> 1420.22
B37: 4 | C37: 15 | D37: 往来款 | E37: 徐洁 | F37: 徐洁转入一般户 | G37: 50000 | I37: =I36+G37-H37 -> 51420.22
B38: 4 | C38: 15 | D38: 往来款 | E38: 福建力喆贸易有限公司 | F38: 收回力喆贸易借款 | G38: 35000 | I38: =I37+G38-H38 -> 86420.22
B39: 4 | C39: 15 | D39: 快递邮电费 | E39: 刘桢颖 | F39: 顺丰快递费 | H39: 16.8 | I39: =I38+G39-H39 -> 86403.42
B40: 4 | C40: 16 | D40: 税费 | E40: 国家税务总局福州市晋安区税务局 | F40: 支付印花税（20260101-20260331） | H40: 11.65 | I40: =I39+G40-H40 -> 86391.77
B41: 4 | C41: 16 | D41: 税费 | E41: 国家税务总局福州市晋安区税务局 | F41: 工会经费（20260101-20260331） | H41: 24 | I41: =I40+G41-H41 -> 86367.77
B42: 4 | C42: 17 | D42: 往来款 | E42: 徐洁 | F42: 徐洁转入一般户 | G42: 10000 | I42: =I41+G42-H42 -> 96367.77
B43: 4 | C43: 17 | D43: 快递邮电费 | E43: 刘桢颖 | F43: 顺丰快递费71.64，货拉拉188.84 | H43: 260.48 | I43: =I42+G43-H43 -> 96107.29
B44: 4 | C44: 21 | D44: 贷款利息 | E44: 农商银行 | F44: 支付900万贷款利息 | H44: 24189.3 | I44: =I43+G44-H44 -> 71917.99
B45: 4 | C45: 21 | D45: 还贷款本金 | E45: 农商银行 | F45: 支付900万贷款本金 | H45: 50000 | I45: =I44+G45-H45 -> 21917.99
B46: 4 | C46: 21 | D46: 贷款利息 | E46: 农商银行 | F46: 支付900万贷款利息 | H46: 12115.58 | I46: =I45+G46-H46 -> 9802.41
B47: 4 | C47: 22 | D47: 五险一金 | E47: 国家税务总局福州市晋安区税务局 | F47: 企业职工基本养老保险费 20260401-20260430 1940.64 失业保险费 20260401-20260430 80.88 工伤保险费 20260401-20260430 17.66 基本医疗保险费 20260401-20260430 886.6 生育保险 20260401-20260430 62.06 | H47: 2987.84 | I47: =I46+G47-H47 -> 6814.57
F48: 本月合计 | G48: =SUM(G35:G47) -> 95000 | H48: =SUM(H35:H47) -> 89972.65 | I48: =I34+G48-H48 -> 6814.57
B49: 5 | C49: 8 | D49: 银行手续费 | E49: 银行 | F49: 支付短信服务费 | H49: 10 | I49: =I47+G49-H49 -> 6804.57
B50: 5 | C50: 15 | D50: 往来款 | E50: 徐洁 | F50: 徐洁转入一般户 | G50: 5000 | I50: =I49+G50-H50 -> 11804.57
B51: 5 | C51: 15 | D51: 往来款 | E51: 福建力喆贸易有限公司 | F51: 收回力喆贸易借款 | G51: 30000 | I51: =I50+G51-H51 -> 41804.57
B52: 5 | C52: 15 | D52: 通讯、宽带费 | E52: 中国电信股份有限公司福州分公司 | F52: 4月电信宽带费 | H52: 249 | I52: =I51+G52-H52 -> 41555.57
B53: 5 | C53: 21 | D53: 贷款利息 | E53: 农商银行 | F53: 支付900万贷款利息 | H53: 23267.25 | I53: =I52+G53-H53 -> 18288.32
B54: 5 | C54: 21 | D54: 贷款利息 | E54: 农商银行 | F54: 支付900万贷款利息 | H54: 11664 | I54: =I53+G54-H54 -> 6624.32
B55: 5 | C55: 25 | D55: 五险一金 | E55: 国家税务总局福州市晋安区税务局 | F55: 企业职工基本养老保险费 20260501-20260531 1940.64 失业保险费 20260501-20260531 80.88 工伤保险费 20260501-20260531 17.66 基本医疗保险费 20260501-20260531 886.6 生育保险 20260501-20260531 62.06 | H55: 2987.84 | I55: =I54+G55-H55 -> 3636.48
B56: 5 | C56: 25 | D56: 往来款 | E56: 徐洁 | F56: 收雅道巷63-1租金（2026.3.22-2026.6.21） | G56: 12832.11 | I56: =I55+G56-H56 -> 16468.59
B57: 5 | C57: 25 | D57: 房租 | E57: 福州名城保护开发有限公司 | F57: 支付雅道巷63-1租金（2026.3.22-2026.6.21） | H57: 12832.11 | I57: =I56+G57-H57 -> 3636.48
F58: 本月合计 | G58: =SUM(G49:G57) -> 47832.11 | H58: =SUM(H49:H57) -> 51010.2 | I58: =I48+G58-H58 -> 3636.48
B59: 6 | C59: 8 | D59: 银行手续费 | E59: 银行 | F59: 支付短信服务费 | H59: 10 | I59: =I58+G59-H59 -> 3626.48
B60: 6 | C60: 14 | D60: 通讯、宽带费 | E60: 中国电信股份有限公司福州分公司 | F60: 5月电信宽带费 | H60: 249 | I60: =I59+G60-H60 -> 3377.48
B61: 6 | C61: 15 | D61: 往来款 | E61: 福建力喆贸易有限公司 | F61: 收回力喆贸易借款 | G61: 33000 | I61: =I60+G61-H61 -> 36377.48
B62: 6 | C62: 21 | D62: 利息收入 | E62: 银行 | F62: 利息收入 | G62: 1.87 | I62: =I61+G62-H62 -> 36379.35
B63: 6 | C63: 21 | D63: 贷款利息 | E63: 农商银行 | F63: 支付900万贷款利息 | H63: 24042.83 | I63: =I62+G63-H63 -> 12336.52
B64: 6 | C64: 21 | D64: 贷款利息 | E64: 农商银行 | F64: 支付900万贷款利息 | H64: 12052.8 | I64: =I63+G64-H64 -> 283.72
B65: 6 | C65: 22 | D65: 往来款 | E65: 徐洁 | F65: 徐洁转入一般户 | G65: 10000 | I65: =I64+G65-H65 -> 10283.72
B66: 6 | C66: 22 | D66: 五险一金 | E66: 国家税务总局福州市晋安区税务局 | F66: 企业职工基本养老保险费 20260601-20260630 1940.64 失业保险费 20260601-20260630 80.88 工伤保险费 20260601-20260630 17.66 基本医疗保险费 20260601-20260630 886.6 生育保险 20260601-20260630 62.06 | H66: 2987.84 | I66: =I65+G66-H66 -> 7295.88
F67: 本月合计 | G67: =SUM(G59:G66) -> 43001.87 | H67: =SUM(H59:H66) -> 39342.47 | I67: =I58+G67-H67 -> 7295.88
B68: 7 | C68: 8 | D68: 银行手续费 | E68: 银行 | F68: 支付短信服务费 | H68: 10 | I68: =I67+G68-H68 -> 7285.88
B69: 7 | C69: 13 | D69: 税费 | E69: 国家税务总局福州市晋安区税务局 | F69: 工会经费（20260401-20260630） | H69: 24 | I69: =I68+G69-H69 -> 7261.88
B70: 7 | C70: 13 | D70: 税费 | E70: 国家税务总局福州市晋安区税务局 | F70: 支付印花税（20260401-20260630） | H70: 6.35 | I70: =I69+G70-H70 -> 7255.53
B71: 7 | C71: 14 | D71: ETC（闽AD10200） | E71: 福建省高速公路集团有限公司电子收费管理中心 | F71: 高速ETC记账卡批量扣款 | H71: 138.6 | I71: =I70+G71-H71 -> 7116.93
B72: 7 | C72: 15 | D72: 往来款 | E72: 福建力喆贸易有限公司 | F72: 收回力喆贸易借款 | G72: 33000 | I72: =I71+G72-H72 -> 40116.93
B73: 7 | C73: 15 | D73: 通讯、宽带费 | E73: 中国电信股份有限公司福州分公司 | F73: 6月电信宽带费 | H73: 249 | I73: =I72+G73-H73 -> 39867.93
B74: 7 | C74: 17 | D74: ETC（闽AD10200） | E74: 福建省高速公路集团有限公司电子收费管理中心 | F74: 高速ETC记账卡批量扣款 | H74: 132.84 | I74: =I73+G74-H74 -> 39735.09
B75: 7 | C75: 21 | D75: 贷款利息 | E75: 农商银行 | F75: 支付900万贷款利息 | H75: 23267.25 | I75: =I74+G75-H75 -> 16467.84
B76: 7 | C76: 21 | D76: 贷款利息 | E76: 农商银行 | F76: 支付900万贷款利息 | H76: 11664 | I76: =I75+G76-H76 -> 4803.84
B77: 7 | C77: 21 | D77: 五险一金 | E77: 国家税务总局福州市晋安区税务局 | F77: 企业职工基本养老保险费 20260701-20260731 1940.64 失业保险费 20260701-20260731 80.88 工伤保险费 20260701-20260731 17.66 基本医疗保险费 20260701-20260731 915.8 生育保险 20260701-20260731 64.1 | H77: 3019.08 | I77: =I76+G77-H77 -> 1784.76
B78: 7 | C78: 23 | D78: 往来款 | E78: 徐洁 | F78: 收雅道巷63-1租金（2026.6.22-2026.9.21） | G78: 12832.11 | I78: =I77+G78-H78 -> 14616.87
B79: 7 | C79: 24 | D79: 房租 | E79: 福州名城保护开发有限公司 | F79: 支付雅道巷63-1租金（2026.6.22-2026.9.21） | H79: 12832.11 | I79: =I78+G79-H79 -> 1784.76
F80: 本月合计 | G80: =SUM(G68:G79) -> 45832.11 | H80: =SUM(H68:H79) -> 51343.23 | I80: =I67+G80-H80 -> 1784.76
B81: 8 | C81: 4 | D81: 其他收入 | E81: 曾在国 | F81: 乐棋公司代理服务费 | G81: 1920 | I81: =I80+G81-H81 -> 3704.76
B82: 8 | C82: 8 | D82: 银行手续费 | E82: 银行 | F82: 支付短信服务费 | H82: 10 | I82: =I81+G82-H82 -> 3694.76
B83: 8 | C83: 12 | D83: 通讯、宽带费 | E83: 中国电信股份有限公司福州分公司 | F83: 7月电信宽带费 | H83: 249 | I83: =I82+G83-H83 -> 3445.76
B84: 8 | C84: 17 | D84: 往来款 | E84: 福建力喆贸易有限公司 | F84: 收回力喆贸易借款 | G84: 37000 | I84: =I83+G84-H84 -> 40445.76
B85: 8 | C85: 20 | D85: 五险一金 | E85: 国家税务总局福州市晋安区税务局 | F85: 企业职工基本养老保险费 20260801-20260831 1940.64 失业保险费 20260801-20260831 80.88 工伤保险费 20260801-20260831 18.32 基本医疗保险费 20260801-20260831 915.8 生育保险 20260801-20260831 64.1 | H85: 3019.74 | I85: =I84+G85-H85 -> 37426.02
B86: 8 | C86: 21 | D86: 贷款利息 | E86: 农商银行 | F86: 支付900万贷款利息 | H86: 24042.83 | I86: =I85+G86-H86 -> 13383.19
B87: 8 | C87: 21 | D87: 贷款利息 | E87: 农商银行 | F87: 支付900万贷款利息 | H87: 12052.8 | I87: =I86+G87-H87 -> 1330.39
F88: 本月合计 | G88: =SUM(G81:G87) -> 38920 | H88: =SUM(H81:H87) -> 39374.37 | I88: =I80+G88-H88 -> 1330.39
B89: 9 | C89: 3 | D89: 其他收入 | E89: 北森云计算有限公司 | G89: 3838 | I89: =I88+G89-H89 -> 5168.39
B90: 9 | C90: 8 | D90: 银行手续费 | E90: 银行 | F90: 支付短信服务费 | H90: 10 | I90: =I89+G90-H90 -> 5158.39
B91: 9 | C91: 13 | D91: 通讯、宽带费 | E91: 中国电信股份有限公司福州分公司 | F91: 8月电信宽带费 | H91: 249 | I91: =I90+G91-H91 -> 4909.39
B92: 9 | C92: 15 | D92: 往来款 | E92: 福建力喆贸易有限公司 | F92: 收回力喆贸易借款 | G92: 36000 | I92: =I91+G92-H92 -> 40909.39
B93: 9 | C93: 21 | D93: 利息收入 | E93: 农商银行 | F93: 利息收入 | G93: 1.35 | I93: =I92+G93-H93 -> 40910.74
B94: 9 | C94: 21 | D94: 贷款利息 | E94: 农商银行 | F94: 支付900万贷款利息 | H94: 24042.83 | I94: =I93+G94-H94 -> 16867.91
B95: 9 | C95: 21 | D95: 贷款利息 | E95: 农商银行 | F95: 支付900万贷款利息 | H95: 12052.8 | I95: =I94+G95-H95 -> 4815.11
B96: 9 | C96: 23 | D96: 五险一金 | E96: 国家税务总局福州市晋安区税务局 | F96: 企业职工基本养老保险费 20260901-20260930 1940.64 失业保险费 20260901-20260930 80.88 工伤保险费 20260901-20260930 18.32 基本医疗保险费 20260901-20260930 915.8 生育保险 20260901-20260930 64.1 | H96: 3019.74 | I96: =I95+G96-H96 -> 1795.37
B97: 9 | C97: 29 | D97: 办公费 | E97: 林焓欣 | F97: 顺丰2026年1-6月快递费 | H97: 235 | I97: =I96+G97-H97 -> 1560.37
B98: 9 | C98: 29 | D98: 差旅费 | E98: 何福顺 | F98: 打车：216.18、住宿：459 | H98: 675.18 | I98: =I97+G98-H98 -> 885.19
F99: 本月合计 | G99: =SUM(G89:G98) -> 39839.35 | H99: =SUM(H89:H98) -> 40284.55 | I99: =I88+G99-H99 -> 885.19
B100: 10 | C100: 8 | D100: 银行手续费 | E100: 银行 | F100: 支付短信服务费 | H100: 10 | I100: =I99+G100-H100 -> 875.19
B101: 10 | C101: 9 | D101: 往来款 | E101: 徐洁 | F101: 收雅道巷63-1租金（2026.9.22-2026.11.21） | G101: 8554.74 | I101: =I100+G101-H101 -> 9429.93
...

Sheet 元生万物建设银行
A1: =HYPERLINK("#目录!a1","返回目录") -> 返回目录 | B1: 元生万物银行日记账--建设银行
B3: 月 | C3: 日 | D3: 收费项 | E3: 收付人 | F3: 摘要 | G3: 收入 | H3: 支出 | I3: 余额 | J3: 备注
F4: 期初余额 | I4: 36305.74
B5: 1 | C5: 8 | D5: 银行手续费 | E5: 建行广达支行 | F5: 支付手续费 | H5: 1 | I5: =I4+G5-H5 -> 36304.74
B6: 1 | C6: 10 | D6: 银行手续费 | E6: 建行广达支行 | F6: 自助设备使用费 | H6: 30 | I6: =I5+G6-H6 -> 36274.74
B7: 1 | C7: 13 | D7: 税费 | E7: 待报解预算收入（财库联网集中户） | F7: 20251001-20251231印花税 | H7: 42.57 | I7: =I6+G7-H7 -> 36232.17
F8: 本月合计 | H8: =SUM(H5:H7) -> 73.57 | I8: =I4+G8-H8 -> 36232.17
B9: 2 | C9: 10 | D9: 银行手续费 | E9: 建行广达支行 | F9: 自助设备使用费 | H9: 30 | I9: =I8+G9-H9 -> 36202.17
F10: 本月合计 | H10: =SUM(H9:H9) -> 30 | I10: =I8+G10-H10 -> 36202.17
B11: 3 | C11: 4 | D11: 往来款 | E11: 徐洁 | F11: 收衣锦坊52号及衣锦坊54号一进部分租金2026.2.16-2026.3.15 | G11: 30098.25 | I11: =I10+G11-H11 -> 66300.42
B12: 3 | C12: 10 | D12: 银行手续费 | E12: 建行广达支行 | F12: 自助设备使用费 | H12: 30 | I12: =I11+G12-H12 -> 66270.42
B13: 3 | C13: 21 | D13: 利息收入 | E13: 银行 | F13: 利息收入 | G13: 6.03 | I13: =I12+G13-H13 -> 66276.45
B14: 3 | C14: 23 | D14: 往来款 | E14: 徐洁 | F14: 收衣锦坊52号及衣锦坊54号一进部分租金2026.3.16-2026.4.15 | G14: 30098.25 | I14: =I13+G14-H14 -> 96374.7
B15: 3 | C15: 24 | D15: 衣锦坊52号一进房租 | E15: 福州名城保护开发有限公司 | F15: 衣锦坊52号及衣锦坊54号一进部分租金2026.2.16-2026.5.15 | H15: 89536.65 | I15: =I14+G15-H15 -> 6838.05
F16: 本月合计 | G16: =SUM(G11:G15) -> 60202.53 | H16: =SUM(H11:H15) -> 89566.65 | I16: =I10+G16-H16 -> 6838.05
B17: 4 | C17: 2 | D17: 往来款 | E17: 徐洁 | F17: 收衣锦坊52号及衣锦坊54号一进部分租金2026.4.16-2026.5.15 | G17: 30098.25 | I17: =I16+G17-H17 -> 36936.3
B18: 4 | C18: 7 | D18: 银行手续费 | E18: 建行广达支行 | F18: 企业网银服务费 | H18: 600 | I18: =I17+G18-H18 -> 36336.3
B19: 4 | C19: 8 | D19: 银行手续费 | E19: 建行广达支行 | F19: 支付手续费 | H19: 1 | I19: =I18+G19-H19 -> 36335.3
B20: 4 | C20: 10 | D20: 银行手续费 | E20: 建行广达支行 | F20: 自助设备使用费 | H20: 30 | I20: =I19+G20-H20 -> 36305.3
B21: 4 | C21: 17 | D21: 福利费 | E21: 刘桢颖 | F21: 2025年会费用（餐费） | H21: 1301.33 | I21: =I20+G21-H21 -> 35003.97
F22: 本月合计 | G22: =SUM(G17:G21) -> 30098.25 | H22: =SUM(H17:H21) -> 1932.33 | I22: =I16+G22-H22 -> 35003.97
B23: 5 | C23: 6 | D23: 往来款 | E23: 徐洁 | F23: 收衣锦坊52号及衣锦坊54号一进部分租金2026.5.16-2026.6.15 | G23: 30098.25 | I23: =I21+G23-H23 -> 65102.22
B24: 5 | C24: 10 | D24: 银行手续费 | E24: 建行广达支行 | F24: 自助设备使用费 | H24: 30 | I24: =I23+G24-H24 -> 65072.22
F25: 本月合计 | G25: =SUM(G23:G24) -> 30098.25 | H25: =SUM(H23:H24) -> 30 | I25: =I22+G25-H25 -> 65072.22
B26: 6 | C26: 3 | D26: 往来款 | E26: 徐洁 | F26: 收衣锦坊52号及衣锦坊54号一进部分租金2026.6.16-2026.7.15 | G26: 30098.25 | I26: =I24+G26-H26 -> 95170.47
B27: 6 | C27: 10 | D27: 银行手续费 | E27: 建行广达支行 | F27: 自助设备使用费 | H27: 30 | I27: =I26+G27-H27 -> 95140.47
B28: 6 | C28: 21 | D28: 利息收入 | E28: 银行 | F28: 利息收入 | G28: 7 | I28: =I27+G28-H28 -> 95147.47
B29: 6 | C29: 29 | D29: 税费 | E29: 周月平 | F29: 吴海萍徐莺股权转让印花税扣款 | H29: 1881.58 | I29: =I28+G29-H29 -> 93265.89
F30: 本月合计 | G30: =SUM(G26:G29) -> 30105.25 | H30: =SUM(H26:H29) -> 1911.58 | I30: =I25+G30-H30 -> 93265.89
B31: 7 | C31: 10 | D31: 银行手续费 | E31: 建行广达支行 | F31: 自助设备使用费 | H31: 30 | I31: =I29+G31-H31 -> 93235.89
B32: 7 | C32: 13 | D32: 税费 | E32: 待报解预算收入（财库联网集中户） | F32: 20260401-20260630印花税 | H32: 44.7 | I32: =I31+G32-H32 -> 93191.19
B33: 7 | C33: 26 | D33: 银行手续费 | E33: 建行广达支行 | F33: 企业网银服务费 | H33: 600 | I33: =I32+G33-H33 -> 92591.19
B34: 7 | C34: 28 | D34: 衣锦坊52号一进房租 | E34: 福州名城保护开发有限公司 | F34: 衣锦坊52号及衣锦坊54号一进部分租金2026.5.16-2026.8.15 | H34: 89536.65 | I34: =I33+G34-H34 -> 3054.54
B35: 7 | C35: 31 | D35: 往来款 | E35: 徐洁 | F35: 收衣锦坊52号及衣锦坊54号一进部分租金2026.6.16-2026.7.15 | G35: 30098.25 | I35: =I34+G35-H35 -> 33152.79
F36: 本月合计 | G36: =SUM(G31:G35) -> 30098.25 | H36: =SUM(H31:H35) -> 90211.35 | I36: =I30+G36-H36 -> 33152.79
B37: 8 | C37: 3 | D37: 往来款 | E37: 徐洁 | F37: 收衣锦坊52号及衣锦坊54号一进部分租金2026.7.16-2026.8.15 | G37: 30098.25 | I37: =I35+G37-H37 -> 63251.04
B38: 8 | C38: 8 | D38: 银行手续费 | E38: 建行广达支行 | F38: 支付手续费 | H38: 1 | I38: =I37+G38-H38 -> 63250.04
B39: 8 | C39: 10 | D39: 银行手续费 | E39: 建行广达支行 | F39: 自助设备使用费 | H39: 30 | I39: =I38+G39-H39 -> 63220.04
F40: 本月合计 | G40: =SUM(G37:G39) -> 30098.25 | H40: =SUM(H37:H39) -> 31 | I40: =I36+G40-H40 -> 63220.04
B41: 9 | C41: 10 | D41: 银行手续费 | E41: 建行广达支行 | F41: 自助设备使用费 | H41: 30 | I41: =I40+G41-H41 -> 63190.04
B42: 9 | C42: 21 | D42: 利息收入 | E42: 银行 | F42: 利息收入 | G42: 9.26 | I42: =I41+G42-H42 -> 63199.3
F43: 本月合计 | G43: =SUM(G41:G42) -> 9.26 | H43: =SUM(H41:H42) -> 30 | I43: =I40+G43-H43 -> 63199.3
B44: 10 | C44: 9 | D44: 税费 | E44: 待报解预算收入（财库联网集中户） | F44: 2026701-20260930印花税 | H44: 29.8 | I44: =I43+G44-H44 -> 63169.5
B45: 10 | C45: 9 | D45: 往来款 | E45: 徐洁 | F45: 收衣锦坊52号及衣锦坊54号一进部分租金2026.8.16-2026.9.15 | G45: 30098.25 | I45: =I44+G45-H45 -> 93267.75
B46: 10 | C46: 10 | D46: 银行手续费 | E46: 建行广达支行 | F46: 自助设备使用费 | H46: 30 | I46: =I45+G46-H46 -> 93237.75
I47: =I46+G47-H47 -> 93237.75
I48: =I47+G48-H48 -> 93237.75
I49: =I48+G49-H49 -> 93237.75
I50: =I49+G50-H50 -> 93237.75
I51: =I50+G51-H51 -> 93237.75
I52: =I51+G52-H52 -> 93237.75
I53: =I52+G53-H53 -> 93237.75
I54: =I53+G54-H54 -> 93237.75
I55: =I54+G55-H55 -> 93237.75
I56: =I55+G56-H56 -> 93237.75
I57: =I56+G57-H57 -> 93237.75
I58: =I57+G58-H58 -> 93237.75
... I67: =I66+G67-H67 -> 93237.75

Sheet 言吾言中国银行
A1: =HYPERLINK("#目录!a1","返回目录") -> 返回目录 | B1: 言吾言银行日记账--中国银行
B3: 月 | C3: 日 | D3: 收费项 | E3: 收付人 | F3: 摘要 | G3: 收入 | H3: 支出 | I3: 余额 | J3: 备注
F4: 期初余额 | I4: 3045.39
B5: 1 | C5: 1 | D5: ETC（闽A6896D） | E5: 福建省高速公路集团有限公司 | F5: 支付ETC费用 | H5: 77.7 | I5: =I4+G5-H5 -> 2967.69
B6: 1 | C6: 2 | D6: ETC（闽A6896D） | E6: 福建省高速公路集团有限公司 | F6: 支付ETC费用 | H6: 24.7 | I6: =I5+G6-H6 -> 2942.99
B7: 1 | C7: 7 | D7: 银行手续费 | E7: 中国银行福州中亭街支行 | F7: 支付短信服务费 | H7: 20 | I7: =I6+G7-H7 -> 2922.99
B8: 1 | C8: 10 | D8: ETC（闽A6896D） | E8: 福建省高速公路集团有限公司 | F8: 支付ETC费用 | H8: 55.1 | I8: =I7+G8-H8 -> 2867.89
B9: 1 | C9: 27 | D9: 油费 | E9: 中石化森美（福建）石油有限公司 | F9: 充值油卡 | H9: 2000 | I9: =I8+G9-H9 -> 867.89
B10: 1 | C10: 27 | D10: 银行手续费 | E10: 中国银行福州中亭街支行 | F10: 转账手续费 | H10: 4.5 | I10: =I9+G10-H10 -> 863.39
B11: 1 | C11: 31 | D11: 银行手续费 | E11: 中国银行福州中亭街支行 | F11: 网银服务费 | H11: 500 | I11: =I10+G11-H11 -> 363.39
F12: 本月合计 | G12: =SUM(G5:G11) -> 0 | H12: =SUM(H5:H11) -> 2682 | I12: =I4+G12-H12 -> 363.39
B13: 2 | C13: 2 | D13: ETC（闽A6896D） | E13: 福建省高速公路集团有限公司 | F13: 支付ETC费用 | H13: 27.43 | I13: =I12+G13-H13 -> 335.96
B14: 2 | C14: 3 | D14: ETC（闽A6896D） | E14: 福建省高速公路集团有限公司 | F14: 支付ETC费用 | H14: 236.92 | I14: =I13+G14-H14 -> 99.04
B15: 2 | C15: 7 | D15: 银行手续费 | E15: 中国银行福州中亭街支行 | F15: 支付短信服务费 | H15: 20 | I15: =I14+G15-H15 -> 79.04
B16: 2 | C16: 9 | D16: 往来款 | E16: 吴海萍 | F16: 转入投资款 | G16: 1000 | I16: =I15+G16-H16 -> 1079.04
B17: 2 | C17: 28 | D17: 往来款 | E17: 吴海萍 | F17: 转入投资款 | G17: 5000 | I17: =I16+G17-H17 -> 6079.04
B18: 2 | C18: 28 | D18: 油费 | E18: 中石化森美（福建）石油有限公司 | F18: 充值油卡 | H18: 2000 | I18: =I17+G18-H18 -> 4079.04
B19: 2 | C19: 28 | D19: ETC（闽A6896D） | E19: 福建省高速公路集团有限公司 | F19: 转账手续费 | H19: 4.5 | I19: =I18+G19-H19 -> 4074.54
B20: 2 | C20: 28 | D20: 往来款 | E20: 福建言吾言物业管理有限公司 | F20: 转入投资款 | G20: 5000 | I20: =I19+G20-H20 -> 9074.54
F21: 本月合计 | G21: =SUM(G13:G20) -> 11000 | H21: =SUM(H13:H20) -> 2288.85 | I21: =I12+G21-H21 -> 9074.54
B22: 3 | C22: 2 | D22: ETC（闽A6896D） | E22: 福建省高速公路集团有限公司 | F22: 支付ETC费用 | H22: 48.94 | I22: =I21+G22-H22 -> 9025.6
B23: 3 | C23: 6 | D23: 银行手续费 | E23: 中国银行福州中亭街支行 | F23: 回单箱网银服务费 | H23: 400 | I23: =I22+G23-H23 -> 8625.6
B24: 3 | C24: 7 | D24: 银行手续费 | E24: 中国银行福州中亭街支行 | F24: 支付短信服务费 | H24: 20 | I24: =I23+G24-H24 -> 8605.6
B25: 3 | C25: 20 | D25: 利息收入 | E25: 中国银行福州中亭街支行 | F25: 利息收入 | G25: 0.45 | I25: =I24+G25-H25 -> 8606.05
B26: 3 | C26: 22 | D26: ETC（闽A6896D） | E26: 福建省高速公路集团有限公司 | F26: 支付ETC费用 | H26: 100.3 | I26: =I25+G26-H26 -> 8505.75
B27: 3 | C27: 24 | D27: 油费 | E27: 中石化森美（福建）石油有限公司 | F27: 充值油卡 | H27: 2000 | I27: =I26+G27-H27 -> 6505.75
B28: 3 | C28: 24 | D28: 银行手续费 | E28: 中国银行福州中亭街支行 | F28: 转账手续费 | H28: 4.5 | I28: =I27+G28-H28 -> 6501.25
F29: 本月合计 | G29: =SUM(G22:G28) -> 0.45 | H29: =SUM(H22:H28) -> 2573.74 | I29: =I20+G29-H29 -> 6501.25
B30: 4 | C30: 7 | D30: 银行手续费 | E30: 中国银行福州中亭街支行 | F30: 支付短信服务费 | H30: 20 | I30: =I28+G30-H30 -> 6481.25
B31: 4 | C31: 21 | D31: ETC（闽A6896D） | E31: 福建省高速公路集团有限公司 | F31: 支付ETC费用 | H31: 28.5 | I31: =I30+G31-H31 -> 6452.75
B32: 4 | C32: 26 | D32: ETC（闽A6896D） | E32: 福建省高速公路集团有限公司 | F32: 支付ETC费用 | H32: 28.5 | I32: =I31+G32-H32 -> 6424.25
B33: 4 | C33: 30 | D33: 油费 | E33: 中石化森美（福建）石油有限公司 | F33: 充值油卡 | H33: 2000 | I33: =I32+G33-H33 -> 4424.25
B34: 4 | C34: 30 | D34: 银行手续费 | E34: 中国银行福州中亭街支行 | F34: 转账手续费 | H34: 4.5 | I34: =I33+G34-H34 -> 4419.75
F35: 本月合计 | G35: =SUM(G30:G34) -> 0 | H35: =SUM(H30:H34) -> 2081.5 | I35: =I29+G35-H35 -> 4419.75
B36: 5 | C36: 7 | D36: 银行手续费 | E36: 中国银行福州中亭街支行 | F36: 支付短信服务费 | H36: 20 | I36: =I34+G36-H36 -> 4399.75
B37: 5 | C37: 9 | D37: ETC（闽A6896D） | E37: 福建省高速公路集团有限公司 | F37: 支付ETC费用 | H37: 28.5 | I37: =I36+G37-H37 -> 4371.25
B38: 5 | C38: 14 | D38: ETC（闽A6896D） | E38: 福建省高速公路集团有限公司 | F38: 支付ETC费用 | H38: 57 | I38: =I37+G38-H38 -> 4314.25
B39: 5 | C39: 30 | D39: ETC（闽A6896D） | E39: 福建省高速公路集团有限公司 | F39: 支付ETC费用 | H39: 28.5 | I39: =I38+G39-H39 -> 4285.75
F40: 本月合计 | G40: =SUM(G36:G39) -> 0 | H40: =SUM(H36:H39) -> 134 | I40: =I34+G40-H40 -> 4285.75
B41: 6 | C41: 2 | D41: 油费 | E41: 中石化森美（福建）石油有限公司 | F41: 充值油卡 | H41: 2000 | I41: =I39+G41-H41 -> 2285.75
B42: 6 | C42: 2 | D42: 银行手续费 | E42: 中国银行福州中亭街支行 | F42: 转账手续费 | H42: 4.5 | I42: =I41+G42-H42 -> 2281.25
B43: 6 | C43: 3 | D43: ETC（闽A6896D） | E43: 福建省高速公路集团有限公司 | F43: 支付ETC费用 | H43: 22.68 | I43: =I42+G43-H43 -> 2258.57
B44: 6 | C44: 7 | D44: 银行手续费 | E44: 中国银行福州中亭街支行 | F44: 支付短信服务费 | H44: 20 | I44: =I43+G44-H44 -> 2238.57
B45: 6 | C45: 17 | D45: 往来款 | E45: 吴海萍 | F45: 转入投资款 | G45: 10000 | I45: =I44+G45-H45 -> 12238.57
B46: 6 | C46: 17 | D46: ETC（闽A6896D） | E46: 福州晋安区隆升汽修厂 | F46: 车辆保养维修费用 | H46: 2675 | I46: =I45+G46-H46 -> 9563.57
B47: 6 | C47: 17 | D47: 银行手续费 | E47: 中国银行福州中亭街支行 | F47: 支付短信服务费 | H47: 4.5 | I47: =I46+G47-H47 -> 9559.07
B48: 6 | C48: 21 | D48: 利息收入 | E48: 中国银行福州中亭街支行 | F48: 利息收入 | G48: 0.67 | I48: =I47+G48-H48 -> 9559.74
B49: 6 | C49: 25 | D49: 油费 | E49: 中石化森美（福建）石油有限公司 | F49: 充值油卡 | H49: 2000 | I49: =I48+G49-H49 -> 7559.74
B50: 6 | C50: 25 | D50: 银行手续费 | E50: 中国银行福州中亭街支行 | F50: 转账手续费 | H50: 4.5 | I50: =I49+G50-H50 -> 7555.24
F51: 本月合计 | G51: =SUM(G41:G50) -> 10000.67 | H51: =SUM(H41:H50) -> 6731.18 | I51: =I40+G51-H51 -> 7555.24
B52: 7 | C52: 7 | D52: 银行手续费 | E52: 中国银行福州中亭街支行 | F52: 支付短信服务费 | H52: 20 | I52: =I50+G52-H52 -> 7535.24
B53: 7 | C53: 10 | D53: 押金 | E53: 福州市新东方培训学校有限公司 | F53: 履约保证金 | G53: 84854 | I53: =I52+G53-H53 -> 92389.24
B54: 7 | C54: 14 | D54: 往来款 | E54: 徐洁 | F54: 往来款 | H54: 50000 | I54: =I53+G54-H54 -> 42389.24
B55: 7 | C55: 14 | D55: 银行手续费 | E55: 中国银行福州中亭街支行 | F55: 支付短信服务费 | H55: 9 | I55: =I54+G55-H55 -> 42380.24
B56: 7 | C56: 16 | D56: 房租收入 | E56: 福州市新东方培训学校有限公司 | F56: 收新东方房租（2026.8.10-2026.9.9） | G56: 42427.14 | I56: =I55+G56-H56 -> 84807.38
B57: 7 | C57: 22 | D57: ETC（闽A6896D） | E57: 福建省高速公路集团有限公司 | F57: 支付ETC费用 | H57: 47.5 | I57: =I56+G57-H57 -> 84759.88
B58: 7 | C58: 23 | D58: 油费 | E58: 中石化森美（福建）石油有限公司 | F58: 充值油卡 | H58: 2000 | I58: =I57+G58-H58 -> 82759.88
B59: 7 | C59: 23 | D59: 银行手续费 | E59: 中国银行福州中亭街支行 | F59: 转账手续费 | H59: 4.5 | I59: =I58+G59-H59 -> 82755.38
B60: 7 | C60: 24 | D60: ETC（闽A6896D） | E60: 福建省高速公路集团有限公司 | F60: 支付ETC费用 | H60: 145.48 | I60: =I59+G60-H60 -> 82609.9
B61: 7 | C61: 25 | D61: ETC（闽A6896D） | E61: 福建省高速公路集团有限公司 | F61: 支付ETC费用 | H61: 43.27 | I61: =I60+G61-H61 -> 82566.63
B62: 7 | C62: 29 | D62: ETC（闽A6896D） | E62: 福建省高速公路集团有限公司 | F62: 支付ETC费用 | H62: 42.75 | I62: =I60+G62-H62 -> 82567.15
F63: 本月合计 | G63: =SUM(G52:G62) -> 127281.14 | H63: =SUM(H52:H62) -> 52312.5 | I63: =I51+G63-H63 -> 82523.88
B64: 8 | C64: 3 | D64: ETC（闽A6896D） | E64: 福建省高速公路集团有限公司 | F64: 支付ETC费用 | H64: 28.5 | I64: =I63+G64-H64 -> 82495.38
B65: 8 | C65: 5 | D65: ETC（闽A6896D） | E65: 福建省高速公路集团有限公司 | F65: 支付ETC费用 | H65: 193.54 | I65: =I64+G65-H65 -> 82301.84
B66: 8 | C66: 7 | D66: 银行手续费 | E66: 中国银行福州中亭街支行 | F66: 支付短信服务费 | H66: 20 | I66: =I65+G66-H66 -> 82281.84
B67: 8 | C67: 7 | D67: 油费 | E67: 中石化森美（福建）石油有限公司 | F67: 充值油卡 | H67: 2000 | I67: =I66+G67-H67 -> 80281.84
B68: 8 | C68: 7 | D68: 银行手续费 | E68: 中国银行福州中亭街支行 | F68: 转账手续费 | H68: 4.5 | I68: =I67+G68-H68 -> 80277.34
B69: 8 | C69: 9 | D69: ETC（闽A6896D） | E69: 福建省高速公路集团有限公司 | F69: 支付ETC费用 | H69: 36.1 | I69: =I68+G69-H69 -> 80241.24
B70: 8 | C70: 10 | D70: ETC（闽A6896D） | E70: 福建省高速公路集团有限公司 | F70: 支付ETC费用 | H70: 36.1 | I70: =I69+G70-H70 -> 80205.14
B71: 8 | C71: 11 | D71: ETC（闽A6896D） | E71: 福建省高速公路集团有限公司 | F71: 支付ETC费用 | H71: 24.7 | I71: =I70+G71-H71 -> 80180.44
B72: 8 | C72: 13 | D72: ETC（闽A6896D） | E72: 福建省高速公路集团有限公司 | F72: 支付ETC费用 | H72: 24.7 | I72: =I71+G72-H72 -> 80155.74
B73: 8 | C73: 27 | D73: ETC（闽A6896D） | E73: 福州晋安区隆升汽修厂 | F73: 更换AGM电瓶，前杠喷漆，全车抛光 | H73: 1630 | I73: =I72+G73-H73 -> 78525.74
B74: 8 | C74: 27 | D74: 银行手续费 | E74: 中国银行福州中亭街支行 | F74: 转账手续费 | H74: 4.5 | I74: =I73+G74-H74 -> 78521.24
B75: 8 | C75: 28 | D75: 房租收入 | E75: 福州市新东方培训学校有限公司 | F75: 收新东方房租（2026.9.10-2026.10.9） | G75: 42427.14 | I75: =I74+G75-H75 -> 120948.38
B76: 8 | C76: 31 | D76: 往来款 | E76: 徐洁 | F76: 学费 | H76: 50000 | I76: =I75+G76-H76 -> 70948.38
B77: 8 | C77: 31 | D77: 银行手续费 | E77: 中国银行福州中亭街支行 | F77: 支付短信服务费 | H77: 9 | I77: =I76+G77-H77 -> 70939.38
F78: 本月合计 | G78: =SUM(G64:G77) -> 42427.14 | H78: =SUM(H64:H77) -> 54011.64 | I78: =I63+G78-H78 -> 70939.38
B79: 9 | C79: 2 | D79: ETC（闽A6896D） | E79: 福建省高速公路集团有限公司 | F79: 支付ETC费用 | H79: 55.57 | I79: =I78+G79-H79 -> 70883.81
B80: 9 | C80: 2 | D80: 油费 | E80: 中石化森美（福建）石油有限公司 | F80: 充值油卡 | H80: 2000 | I80: =I79+G80-H80 -> 68883.81
B81: 9 | C81: 2 | D81: 银行手续费 | E81: 中国银行福州中亭街支行 | F81: 转账手续费 | H81: 4.5 | I81: =I80+G81-H81 -> 68879.31
B82: 9 | C82: 6 | D82: 银行手续费 | E82: 中国银行福州中亭街支行 | F82: 支付短信服务费 | H82: 20 | I82: =I81+G82-H82 -> 68859.31
B83: 9 | C83: 7 | D83: 车辆保险费 | E83: 王晓华 | F83: 闽A6896D车辆报险（2026.9.15-2026.9.14） | H83: 6412.06 | I83: =I82+G83-H83 -> 62447.25
B84: 9 | C84: 7 | D84: 银行手续费 | E84: 中国银行福州中亭街支行 | F84: 转账手续费 | H84: 4.5 | I84: =I83+G84-H84 -> 62442.75
B85: 9 | C85: 10 | D85: ETC（闽A6896D） | E85: 福建省高速公路集团有限公司 | F85: 支付ETC费用 | H85: 9.5 | I85: =I84+G85-H85 -> 62433.25
B86: 9 | C86: 20 | D86: ETC（闽A6896D） | E86: 福建省高速公路集团有限公司 | F86: 支付ETC费用 | H86: 8.11 | I86: =I85+G86-H86 -> 62425.14
B87: 9 | C87: 24 | D87: 油费 | E87: 中石化森美（福建）石油有限公司 | F87: 充值油卡 | H87: 2000 | I87: =I86+G87-H87 -> 60425.14
B88: 9 | C88: 24 | D88: 银行手续费 | E88: 中国银行福州中亭街支行 | F88: 转账手续费 | H88: 4.5 | I88: =I87+G88-H88 -> 60420.64
B89: 9 | C89: 29 | D89: 房租 | E89: 徐洁 | F89: 利达大厦（2026.7.10-2026.9.9） | H89: 22000 | I89: =I88+G89-H89 -> 38420.64
F90: 本月合计 | G90: =SUM(G79:G89) -> 0 | H90: =SUM(H79:H89) -> 32518.74 | I90: =I78+G90-H90 -> 38420.64
I91: =I90+G91-H91 -> 38420.64
I92: =I91+G92-H92 -> 38420.64
I93: =I92+G93-H93 -> 38420.64
I94: =I93+G94-H94 -> 38420.64
I95: =I94+G95-H95 -> 38420.64
I96: =I95+G96-H96 -> 38420.64
I97: =I96+G97-H97 -> 38420.64
I98: =I97+G98-H98 -> 38420.64
I99: =I98+G99-H99 -> 38420.64
I100: =I99+G100-H100 -> 38420.64
I101: =I100+G101-H101 -> 38420.64
...

Sheet 力喆传媒海峡银行
A1: =HYPERLINK("#目录!a1","返回目录") -> 返回目录 | B1: 力喆传媒银行日记账--海峡银行
B3: 月 | C3: 日 | D3: 收费项 | E3: 收付人 | F3: 摘要 | G3: 收入 | H3: 支出 | I3: 余额 | J3: 备注
F4: 期初余额 | I4: 10337.35
B5: 1 | C5: 11 | D5: 银行手续费 | E5: 银行 | F5: 回单打印费 | H5: 60 | I5: =I4+G5-H5 -> 10277.35
F6: 本月合计 | G6: =SUM(G5:G5) -> 0 | H6: =SUM(H5:H5) -> 60 | I6: =I4+G6-H6 -> 10277.35
B7: 2 | C7: 27 | D7: 往来款 | E7: 往来款 | F7: 转入吴海萍 | H7: 5000 | I7: =I6+G7-H7 -> 5277.35
B8: 2 | C8: 27 | D8: 银行手续费 | E8: 银行 | F8: 转账手续费 | H8: 4 | I8: =I7+G8-H8 -> 5273.35
B9: 2 | C9: 28 | D9: 往来款 | E9: 往来款 | F9: 转入吴海萍 | H9: 5000 | I9: =I8+G9-H9 -> 273.35
B10: 2 | C10: 28 | D10: 银行手续费 | E10: 银行 | F10: 转账手续费 | H10: 4 | I10: =I9+G10-H10 -> 269.35
F11: 本月合计 | G11: =SUM(G7:G10) -> 0 | H11: =SUM(H7:H10) -> 10008 | I11: =I6+G11-H11 -> 269.35
B12: 3 | C12: 21 | D12: 利息收入 | E12: 银行 | F12: 利息收入 | G12: 0.99 | I12: =I11+G12-H12 -> 270.34
F13: 本月合计 | G13: =SUM(G12) -> 0.99 | H13: =SUM(H12) -> 0 | I13: =I11+G13-H13 -> 270.34
B14: 6 | C14: 21 | D14: 利息收入 | E14: 银行 | F14: 利息收入 | G14: 0.03 | I14: 270.37
F15: 本月合计 | G15: =SUM(G14) -> 0.03 | H15: 0 | I15: 270.37
B16: 9 | C16: 21 | D16: 利息收入 | E16: 银行 | F16: 利息收入 | G16: 0.03 | I16: =I15+G16-H16 -> 270.4
F17: 本月合计 | G17: =SUM(G16) -> 0.03 | H17: 0 | I17: =I16+G17-H17 -> 270.43
I18: =I17+G18-H18 -> 270.43
I19: =I18+G19-H19 -> 270.43
I20: =I19+G20-H20 -> 270.43
I21: =I20+G21-H21 -> 270.43
I22: =I21+G22-H22 -> 270.43
I23: =I22+G23-H23 -> 270.43
I24: =I23+G24-H24 -> 270.43
I25: =I24+G25-H25 -> 270.43
I26: =I25+G26-H26 -> 270.43
I27: =I26+G27-H27 -> 270.43
I28: =I27+G28-H28 -> 270.43
I29: =I28+G29-H29 -> 270.43
... I65: =I64+G65-H65 -> 270.43

Sheet 徐洁招商银行
A1: =HYPERLINK("#目录!a1","返回目录") -> 返回目录 | B1: 力喆产业银行日记账--徐洁招商银行
B3: 月 | C3: 日 | D3: 收费项 | E3: 收付人 | F3: 摘要 | G3: 收入 | H3: 支出 | I3: 余额 | J3: 备注
F4: 期初余额 | I4: 227902.83
B5: 1 | C5: 10 | D5: 利达大厦租金收入 | E5: 庄巧婷（蔡加强） | F5: 金豆豆3楼利达大厦房租 | G5: 10530 | I5: =I4+G5-H5 -> 238432.83
B6: 1 | C6: 12 | D6: 徐总费用 | E6: 周月平 | F6: 代付福州院子房贷 | H6: 8259.6 | I6: =I5+G6-H6 -> 230173.23 | J6: 力喆实业
B7: 1 | C7: 12 | D7: 徐总费用 | E7: 周月平 | F7: 代付华润万象城房贷 | H7: 1042.65 | I7: =I6+G7-H7 -> 229130.58 | J7: 力喆实业
B8: 1 | C8: 12 | D8: 徐总费用 | E8: 徐洁 | F8: 代付世茂云顶房贷 | H8: 6000 | I8: =I7+G8-H8 -> 223130.58 | J8: 力喆实业
B9: 1 | C9: 12 | D9: 徐总费用 | E9: 徐洁 | F9: 还海峡银行贷款本金及利息 | H9: 14014.58 | I9: =I8+G9-H9 -> 209116 | J9: 力喆实业
B10: 1 | C10: 12 | D10: 徐总费用 | E10: 徐洁 | F10: 转入徐洁工行2426账户 | H10: 2000 | I10: =I9+G10-H10 -> 207116 | J10: 力喆实业
B11: 1 | C11: 13 | D11: 吴华云账户 | E11: 吴华云 | F11: 金豆豆3楼利达大厦房租转给吴华云 | H11: 10530 | I11: =I10+G11-H11 -> 196586
B12: 1 | C12: 14 | D12: 往来款 | E12: 王晓华 | F12: 转入王晓华建行（用于力喆应急使用，艾泊烨贷款） | H12: 130000 | I12: =I11+G12-H12 -> 66586 | J12: 力喆实业
B13: 1 | C13: 15 | D13: 徐总费用 | E13: 徐洁 | F13: 支付招行个贷 | H13: 21502.11 | I13: =I12+G13-H13 -> 45083.89 | J13: 力喆实业
B14: 1 | C14: 15 | D14: 往来款 | E14: 福州力喆贸易有限公司 | F14: 转入力喆贸易对公账户 | H14: 20000 | I14: =I13+G14-H14 -> 25083.89 | J14: 力喆实业
B15: 1 | C15: 15 | D15: 薪资 | E15: 个人 | F15: 支付力喆实业2025年12月工资 | H15: 25000 | I15: =I14+G15-H15 -> 83.89 | J15: 力喆实业
B16: 1 | C16: 16 | D16: 房租收入 | E16: 汪亮 | F16: 收1：雅道巷63-1租金（2025.12.22-2026.3.21） | G16: 12832.11 | I16: =I15+G16-H16 -> 12916 | J16: 力喆实业
B17: 1 | C17: 16 | D17: 往来款 | E17: 福建力喆实业发展有限公司 | F17: 雅道巷63-1租金（2025.12.22-2026.3.21）转入力喆实业一般户 | H17: 12832.11 | I17: =I16+G17-H17 -> 83.89 | J17: 力喆实业
B18: 1 | C18: 17 | D18: 利达大厦租金收入 | E18: 福州市鼓楼区爱而丽新医疗美容诊所有限公司 | F18: 3 楼利达大厦房租 | G18: 11000 | I18: =I17+G18-H18 -> 11083.89
B19: 1 | C19: 23 | D19: 利达大厦租金收入 | E19: 黄玲丹 | F19: 3 楼利达大厦房租 | G19: 29406.8 | I19: =I18+G19-H19 -> 40490.69
B20: 1 | C20: 26 | D20: 吴华云账户 | E20: 吴华云 | F20: 3 楼利达大厦房租 | H20: 40406.8 | I20: =I19+G20-H20 -> 83.89
B21: 1 | C21: 26 | D21: 往来款 | E21: 吴海萍 | F21: 吴海萍转入徐洁账户 | G21: 1000 | I21: =I20+G21-H21 -> 1083.89 | J21: 古玩城
B22: 1 | C22: 26 | D22: 薪资 | E22: 林婷招 | F22: 支付12月财务顾问费 | H22: 1000 | I22: =I21+G22-H22 -> 83.89 | J22: 力喆实业
F23: 本月合计 | G23: =SUM(G5:G22) -> 64768.91 | H23: =SUM(H5:H22) -> 292587.85 | I23: =I4+G23-H23 -> 83.89
B24: 2 | C24: 5 | D24: 往来款 | E24: 吴海萍 | F24: 吴海萍转入徐洁账户 | G24: 96000 | I24: =I23+G24-H24 -> 96083.89 | J24: 古玩城
B25: 2 | C25: 5 | D25: 拆除费用 | E25: 陈正光 | F25: 利达大厦拆除费用、搬家费用 | H25: 21600 | I25: =I24+G25-H25 -> 74483.89 | J25: 力喆实业
B26: 2 | C26: 5 | D26: 股东分红 | E26: 林炜、徐莺、吴华云、高海瑜 | F26: 支付力喆贸易202601月分红 | H26: 65000 | I26: =I25+G26-H26 -> 9483.89 | J26: 力喆实业
B27: 2 | C27: 5 | D27: 办公费 | E27: 郭春星 | F27: 上下杭搬家费用 | H27: 8500 | I27: =I26+G27-H27 -> 983.89 | J27: 力喆实业
B28: 2 | C28: 9 | D28: 往来款 | E28: 吴海萍 | F28: 吴海萍转入徐洁账户 | G28: 2000 | I28: =I27+G28-H28 -> 2983.89 | J28: 古玩城
B29: 2 | C29: 9 | D29: 车辆维修费 | E29: 福州晋安区隆升汽修厂 | F29: 别克车辆维修费 | H29: 1278 | I29: =I28+G29-H29 -> 1705.89 | J29: 力喆实业
B30: 2 | C30: 9 | D30: 往来款 | E30: 福建言吾言物业管理有限公司 | F30: 转入吴海萍招行账户-转入言吾言对公（投资款） | H30: 1000 | I30: =I29+G30-H30 -> 705.89 | J30: 力喆实业
B31: 2 | C31: 10 | D31: 往来款 | E31: 吴海萍 | F31: 吴海萍转入徐洁账户 | G31: 10000 | I31: =I30+G31-H31 -> 10705.89 | J31: 古玩城
B32: 2 | C32: 10 | D32: 徐总费用 | E32: 林丰 | F32: 转入林丰账户-转林焓欣微信（徐总购买购物卡） | H32: 10000 | I32: =I31+G32-H32 -> 705.89 | J32: 力喆实业
B33: 2 | C33: 10 | D33: 利达大厦租金收入 | E33: 庄巧婷（蔡加强） | F33: 金豆豆3楼利达大厦房租 | G33: 10530 | I33: =I32+G33-H33 -> 11235.89
B34: 2 | C34: 11 | D34: 往来款 | E34: 吴海萍 | F34: 吴海萍转入徐洁账户 | G34: 60000 | I34: =I33+G34-H34 -> 71235.89 | J34: 古玩城
B35: 2 | C35: 11 | D35: 徐总费用 | E35: 周月平 | F35: 代付福州院子房贷 | H35: 8115.89 | I35: =I34+G35-H35 -> 63120 | J35: 力喆实业
B36: 2 | C36: 11 | D36: 徐总费用 | E36: 周月平 | F36: 代付华润万象城房贷 | H36: 1035.86 | I36: =I35+G36-H36 -> 62084.14 | J36: 力喆实业
B37: 2 | C37: 11 | D37: 徐总费用 | E37: 徐洁 | F37: 代付世茂云顶房贷 | H37: 6000 | I37: =I36+G37-H37 -> 56084.14 | J37: 力喆实业
B38: 2 | C38: 11 | D38: 徐总费用 | E38: 徐洁 | F38: 还海峡银行贷款本金及利息 | H38: 14014.58 | I38: =I37+G38-H38 -> 42069.56 | J38: 力喆实业
B39: 2 | C39: 11 | D39: 徐总费用 | E39: 徐洁 | F39: 转入徐洁工行2426账户 | H39: 2000 | I39: =I38+G39-H39 -> 40069.56 | J39: 力喆实业
B40: 2 | C40: 13 | D40: 往来款 | E40: 福州市青翼创创业投资有限公司 | F40: 青翼创转入徐洁招行账户 | G40: 26000 | I40: =I39+G40-H40 -> 66069.56 | J40: 力喆实业
B41: 2 | C41: 13 | D41: 往来款 | E41: 福建力喆产业投资集团有限公司 | F41: 力喆产业转入徐洁招行账户 | G41: 16000 | I41: =I40+G41-H41 -> 82069.56 | J41: 力喆实业
B42: 2 | C42: 13 | D42: 吴华云账户 | E42: 吴华云 | F42: 金豆豆3楼利达大厦房租转给吴华云 | H42: 10530 | I42: =I41+G42-H42 -> 71539.56
B43: 2 | C43: 13 | D43: 薪资 | E43: 个人 | F43: 支付力喆实业2026年1月工资 | H43: 25000 | I43: =I42+G43-H43 -> 46539.56 | J43: 力喆实业
B44: 2 | C44: 13 | D44: 薪资 | E44: 个人 | F44: 支付力喆实业2025年终奖 | H44: 17000 | I44: =I43+G44-H44 -> 29539.56 | J44: 力喆实业
B45: 2 | C45: 14 | D45: 往来款 | E45: 吴海萍 | F45: 吴海萍转入徐洁账户 | G45: 10000 | I45: =I44+G45-H45 -> 39539.56 | J45: 古玩城
B46: 2 | C46: 14 | D46: 徐总费用 | E46: 刘桢颖 | F46: 华润万象物业费556.22元、世欧5202物业费2746.87元 | H46: 3303.09 | I46: =I45+G46-H46 -> 36236.47 | J46: 力喆实业
B47: 2 | C47: 14 | D47: 徐总费用 | E47: 刘桢颖 | F47: 餐费 | H47: 2807 | I47: =I46+G47-H47 -> 33429.47 | J47: 力喆实业
B48: 2 | C48: 14 | D48: 酒水费 | E48: 刘桢颖 | F48: 购十四代-瓶2600元 | H48: 2600 | I48: =I47+G48-H48 -> 30829.47 | J48: 力喆实业
B49: 2 | C49: 14 | D49: 车辆使用费 | E49: 刘桢颖 | F49: 车牌转移.车辆过户代办费1000元、购十四代-瓶2600元 | H49: 1000 | I49: =I48+G49-H49 -> 29829.47 | J49: 力喆实业
B50: 2 | C50: 15 | D50: 徐总费用 | E50: 徐洁 | F50: 支付招行个贷 | H50: 21502.11 | I50: =I49+G50-H50 -> 8327.36 | J50: 力喆实业
B51: 2 | C51: 27 | D51: 利达大厦租金收入 | E51: 福州市鼓楼区爱而丽新医疗美容诊所有限公司 | F51: 3 楼利达大厦房租 | G51: 11000 | I51: =I50+G51-H51 -> 19327.36
B52: 2 | C52: 27 | D52: 利达大厦租金收入 | E52: 黄玲丹 | F52: 3 楼利达大厦房租 | G52: 29406.8 | I52: =I51+G52-H52 -> 48734.16
B53: 2 | C53: 28 | D53: 房租收入 | E53: 汪亮 | F53: 普朗姆租金（2025.12.1-2025.12.31） | G53: 45000 | I53: =I52+G53-H53 -> 93734.16 | J53: 力喆实业
F54: 本月合计 | G54: =SUM(G24:G53) -> 315936.8 | H54: =SUM(H24:H53) -> 222286.53 | I54: =I23+G54-H54 -> 93734.16
B55: 3 | C55: 4 | D55: 吴华云账户 | E55: 吴华云 | F55: 3 楼利达大厦房租 | H55: 40406.8 | I55: =I53+G55-H55 -> 53327.36
B56: 3 | C56: 4 | D56: 往来款 | E56: 福州市元生万物投资有限公司 | F56: 衣锦坊52号及54号一进部分租金2025.12.16-2026.1.15 | H56: 30098.25 | I56: =I55+G56-H56 -> 23229.11 | J56: 力喆实业
B57: 3 | C57: 4 | D57: 薪资 | E57: 林婷招 | F57: 支付1月财务顾问费 | H57: 1000 | I57: =I56+G57-H57 -> 22229.11 | J57: 力喆实业
B58: 3 | C58: 10 | D58: 徐总费用 | E58: 徐洁 | F58: 信用卡扣款 | H58: 278.4 | I58: =I57+G58-H58 -> 21950.71 | J58: 力喆实业
B59: 3 | C59: 10 | D59: 利达大厦租金收入 | E59: 庄巧婷（蔡加强） | F59: 金豆豆3楼利达大厦房租 | G59: 10530 | I59: =I58+G59-H59 -> 32480.71
B60: 3 | C60: 11 | D60: 往来款 | E60: 吴海萍 | F60: 吴海萍转入徐洁账户 | G60: 50000 | I60: =I59+G60-H60 -> 82480.71 | J60: 古玩城
B61: 3 | C61: 11 | D61: 往来款 | E61: 吴海萍 | F61: 吴海萍转入徐洁账户 | G61: 10000 | I61: =I60+G61-H61 -> 92480.71 | J61: 古玩城
B62: 3 | C62: 11 | D62: 吴华云账户 | E62: 吴华云 | F62: 金豆豆3楼利达大厦房租转给吴华云 | H62: 10530 | I62: =I61+G62-H62 -> 81950.71
B63: 3 | C63: 11 | D63: 徐总费用 | E63: 徐洁 | F63: 转入徐洁工行2426账户 | H63: 2000 | I63: =I62+G63-H63 -> 79950.71 | J63: 力喆实业
B64: 3 | C64: 11 | D64: 徐总费用 | E64: 周月平 | F64: 代付福州院子房贷 | H64: 8115.89 | I64: =I63+G64-H64 -> 71834.82 | J64: 力喆实业
B65: 3 | C65: 11 | D65: 徐总费用 | E65: 周月平 | F65: 代付华润万象城房贷 | H65: 1035.86 | I65: =I64+G65-H65 -> 70798.96 | J65: 力喆实业
B66: 3 | C66: 11 | D66: 徐总费用 | E66: 徐洁 | F66: 代付世茂云顶房贷 | H66: 6000 | I66: =I65+G66-H66 -> 64798.96 | J66: 力喆实业
B67: 3 | C67: 11 | D67: 徐总费用 | E67: 徐洁 | F67: 还海峡银行贷款本金及利息 | H67: 12658.33 | I67: =I66+G67-H67 -> 52140.63 | J67: 力喆实业
B68: 3 | C68: 11 | D68: 往来款 | E68: 吴海萍 | F68: 吴海萍转入徐洁账户 | G68: 50000 | I68: =I67+G68-H68 -> 102140.63 | J68: 古玩城
B69: 3 | C69: 11 | D69: 往来款 | E69: 吴海萍 | F69: 吴海萍转入徐洁账户 | G69: 30000 | I69: =I68+G69-H69 -> 132140.63 | J69: 古玩城
B70: 3 | C70: 11 | D70: 利息支出 | E70: 庄秀平 | F70: 庄秀平50万借款-利息费用 | H70: 15000 | I70: =I69+G70-H70 -> 117140.63 | J70: 力喆实业
B71: 3 | C71: 11 | D71: 股东分红 | E71: 林炜、徐莺、吴华云、高海瑜 | F71: 支付力喆贸易202602月分红 | H71: 65000 | I71: =I70+G71-H71 -> 52140.63 | J71: 力喆实业
B72: 3 | C72: 15 | D72: 徐总费用 | E72: 徐洁 | F72: 支付招行个贷 | H72: 21502.11 | I72: =I71+G72-H72 -> 30638.52 | J72: 力喆实业
B73: 3 | C73: 16 | D73: 薪资 | E73: 个人 | F73: 支付力喆实业2026年2月工资 | H73: 25000 | I73: =I72+G73-H73 -> 5638.52 | J73: 力喆实业
B74: 3 | C74: 17 | D74: 利达大厦租金收入 | E74: 福州市鼓楼区爱而丽新医疗美容诊所有限公司 | F74: 3 楼利达大厦房租 | G74: 11000 | I74: =I73+G74-H74 -> 16638.52
B75: 3 | C75: 19 | D75: 房租收入 | E75: 汪亮 | F75: 普朗姆租金（2026.1.1-2026.1.31） | G75: 45000 | I75: =I74+G75-H75 -> 61638.52 | J75: 力喆实业
B76: 3 | C76: 21 | D76: 利息收入 | E76: 招商银行 | F76: 利息收入 | G76: 9.56 | I76: =I75+G76-H76 -> 61648.08 | J76: 力喆实业
B77: 3 | C77: 23 | D77: 往来款 | E77: 福州市元生万物投资有限公司 | F77: 衣锦坊52号及54号一进部分租金2026.1.16-2026.2.15 | H77: 30098.25 | I77: =I76+G77-H77 -> 31549.83 | J77: 力喆实业
B78: 3 | C78: 23 | D78: 往来款 | E78: 徐洁 | F78: 徐洁海峡银行1796转入 | G78: 30000 | I78: =I77+G78-H78 -> 61549.83 | J78: 力喆实业
B79: 3 | C79: 24 | D79: 垃圾清运费 | E79: 林圳钞 | F79: 上杭路87、89、2号垃圾清理费用 | H79: 17500 | I79: =I78+G79-H79 -> 44049.83 | J79: 力喆实业
B80: 3 | C80: 26 | D80: 薪资 | E80: 林婷招 | F80: 支付2月财务顾问费 | H80: 1000 | I80: =I79+G80-H80 -> 43049.83 | J80: 力喆实业
B81: 3 | C81: 26 | D81: 往来款 | E81: 陈正光 | F81: 银联代付，银联转账（云闪付）-陈正光 | G81: 15000 | I81: =I80+G81-H81 -> 58049.83 | J81: 力喆实业
B82: 3 | C82: 31 | D82: 房租收入 | E82: 汪亮 | F82: 普朗姆租金（2026.2.1-2026.2.28） | G82: 45000 | I82: =I81+G82-H82 -> 103049.83 | J82: 力喆实业
F83: 本月合计 | G83: =SUM(G55:G82) -> 296539.56 | H83: =SUM(H55:H82) -> 287223.89 | I83: =I54+G83-H83 -> 103049.83
B84: 4 | C84: 2 | D84: 利达大厦租金收入 | E84: 福州市鼓楼区七色光艺术培训有限公司（张丽萍） | F84: 利达大厦三楼的租金（2026.4.8-2026.5.7） | G84: 24588 | I84: =I83+G84-H84 -> 127637.83 | J84: 力喆实业
B85: 4 | C85: 2 | D85: 往来款 | E85: 福州市元生万物投资有限公司 | F85: 衣锦坊52号及54号一进部分租金2026.2.16-2026.3.15 | H85: 30098.25 | I85: =I84+G85-H85 -> 97539.58 | J85: 力喆实业
B86: 4 | C86: 2 | D86: 徐总费用 | E86: 福建利达物业管现有限公司 | F86: 利达大厦4月-12月物业费 | H86: 26555.04 | I86: =I85+G86-H86 -> 70984.54 | J86: 力喆实业
B87: 4 | C87: 2 | D87: 办公费 | E87: 刘桢颖 | F87: 上下杭第二次搬家费用 | H87: 6200 | I87: =I86+G87-H87 -> 64784.54 | J87: 力喆实业
B88: 4 | C88: 2 | D88: 徐总费用 | E88: 何福顺 | F88: 餐费2131.59元、买烟、，水，纸743.86元 | H88: 2875.44 | I88: =I87+G88-H88 -> 61909.1 | J88: 力喆实业
B89: 4 | C89: 2 | D89: 车辆使用费 | E89: 何福顺 | F89: 加油费1268.4元、高速过路费118元 | H89: 1386.4 | I89: =I88+G89-H89 -> 60522.7 | J89: 力喆实业
B90: 4 | C90: 2 | D90: 车辆使用费 | E90: 何福顺 | F90: 洗车 | H90: 1240 | I90: =I89+G90-H90 -> 59282.7 | J90: 力喆实业
B91: 4 | C91: 2 | D91: 徐总费用 | E91: 何福顺 | F91: 购文具24.9元、香蕉176.11元、住宿费360元 | H91: 561.01 | I91: =I90+G91-H91 -> 58721.69 | J91: 力喆实业
B92: 4 | C92: 2 | D92: 停车费 | E92: 何福顺 | F92: 停车费 | H92: 1412 | I92: =I91+G92-H92 -> 57309.69 | J92: 力喆实业
B93: 4 | C93: 2 | D93: 市内交通费 | E93: 何福顺 | F93: 市内交通费724.1 | H93: 724.1 | I93: =I92+G93-H93 -> 56585.59 | J93: 力喆实业
B94: 4 | C94: 2 | D94: 徐总费用 | E94: 何福顺 | F94: 住宿费 | H94: 548 | I94: =I93+G94-H94 -> 56037.59 | J94: 力喆实业
B95: 4 | C95: 7 | D95: 徐总费用 | E95: 徐洁 | F95: 信用卡快速还款 | H95: 202.1 | I95: =I94+G95-H95 -> 55835.49 | J95: 力喆实业
B96: 4 | C96: 9 | D96: 往来款 | E96: 吴海萍 | F96: 吴海萍转入徐洁账户 | G96: 10000 | I96: =I95+G96-H96 -> 65835.49 | J96: 古玩城
B97: 4 | C97: 9 | D97: 徐总费用 | E97: 徐洁 | F97: 转入徐洁工行2426账户 | H97: 2000 | I97: =I96+G97-H97 -> 63835.49 | J97: 力喆实业
B98: 4 | C98: 9 | D98: 徐总费用 | E98: 周月平 | F98: 代付福州院子房贷 | H98: 8115.89 | I98: =I97+G98-H98 -> 55719.6 | J98: 力喆实业
B99: 4 | C99: 9 | D99: 徐总费用 | E99: 周月平 | F99: 代付华润万象城房贷 | H99: 1035.86 | I99: =I98+G99-H99 -> 54683.74 | J99: 力喆实业
B100: 4 | C100: 9 | D100: 徐总费用 | E100: 徐洁 | F100: 代付世茂云顶房贷 | H100: 6000 | I100: =I99+G100-H100 -> 48683.74 | J100: 力喆实业
B101: 4 | C101: 9 | D101: 徐总费用 | E101: 徐洁 | F101: 还海峡银行贷款本金及利息 | H101: 14014.58 | I101: =I100+G101-H101 -> 34669.16 | J101: 力喆实业
...

Sheet 力喆贸易建设银行
A1: =HYPERLINK("#目录!a1","返回目录") -> 返回目录 | B1: 力喆贸易银行日记账--建设银行
B3: 月 | C3: 日 | D3: 收费项 | E3: 收付人 | F3: 摘要 | G3: 收入 | H3: 支出 | I3: 余额 | J3: 备注
F4: 期初余额 | I4: 14300.72
B5: 1 | C5: 2 | D5: 银行手续费 | E5: 建设银行 | F5: 支付对公自助设备使用费 | H5: 30 | I5: =I4+G5-H5 -> 14270.72
B6: 1 | C6: 4 | D6: 税费 | E6: 待报解预算收入（财库联网集中户 | F6: 代收代付个人所得税 | H6: 353.79 | I6: =I5+G6-H6 -> 13916.93
B7: 1 | C7: 13 | D7: 税费 | E7: 待报解预算收入（财库联网集中户 | F7: 支付20251001-20251231增值税2046.07元、城建税71.61元 | H7: 2117.68 | I7: =I6+G7-H7 -> 11799.25
B8: 1 | C8: 13 | D8: 税费 | E8: 待报解预算收入（财库联网集中户 | F8: 支付20251001-20251231房产税540元、城镇土地使用税201.42元、印花税4.5元 | H8: 745.92 | I8: =I7+G8-H8 -> 11053.33
B9: 1 | C9: 15 | D9: 五险一金 | E9: 福州住房公积金中心 | F9: 支付26年1月住房公积金 | H9: 2230 | I9: =I8+G9-H9 -> 8823.33
B10: 1 | C10: 15 | D10: 往来款 | E10: 徐洁 | F10: 徐洁转入往来款 | G10: 20000 | I10: =I9+G10-H10 -> 28823.33
B11: 1 | C11: 15 | D11: 薪资 | E11: 个人 | F11: 支付2025年12月工资 | H11: 25715.81 | I11: =I10+G11-H11 -> 3107.52
B12: 1 | C12: 15 | D12: 房租收入 | E12: 福州朴朴电子商务有限公司 | F12: 收朴朴商务公司1月房租 | G12: 73229.1 | I12: =I11+G12-H12 -> 76336.62
B13: 1 | C13: 16 | D13: 往来款 | E13: 福建力喆产业投资集团有限公司 | F13: 还力喆实业暂借款 | H13: 50000 | I13: =I12+G13-H13 -> 26336.62
B14: 1 | C14: 21 | D14: 五险一金 | E14: 待报解预算收入（财库联网集中户 | F14: 企业职工基本养老保险费 20260101-20260131 3020.64 失业保险费 20260101-20260131 125.88 工伤保险费 20260101-20260131 93.3 基本医疗保险费 20260101-20260131 1336.6 生育保险费 20260101-20260131 93.56 | H14: 4669.98 | I14: =I13+G14-H14 -> 21666.64
B15: 1 | C15: 29 | D15: 银行手续费 | E15: 建设银行 | F15: 银行手续费 | H15: 3 | I15: =I14+G15-H15 -> 21663.64
F16: 本月合计 | G16: =SUM(G5:G15) -> 93229.1 | H16: =SUM(H5:H15) -> 85866.18 | I16: =I4+G16-H16 -> 21663.64
B17: 2 | C17: 2 | D17: 银行手续费 | E17: 建设银行 | F17: 支付对公自助设备使用费 | H17: 30 | I17: =I16+G17-H17 -> 21633.64
B18: 2 | C18: 3 | D18: 税费 | E18: 待报解预算收入（财库联网集中户 | F18: 支付20260101-20260131增值税 | H18: 6046.44 | I18: =I17+G18-H18 -> 15587.2
B19: 2 | C19: 3 | D19: 税费 | E19: 待报解预算收入（财库联网集中户 | F19: 支付20260101-20260131城建税 | H19: 211.62 | I19: =I18+G19-H19 -> 15375.58
B20: 2 | C20: 6 | D20: 税费 | E20: 待报解预算收入（财库联网集中户 | F20: 代收代付个人所得税 | H20: 152.46 | I20: =I19+G20-H20 -> 15223.12
B21: 2 | C21: 9 | D21: 房租收入 | E21: 福州朴朴电子商务有限公司 | F21: 收朴朴商务公司2月房租 | G21: 73229.1 | I21: =I20+G21-H21 -> 88452.22
B22: 2 | C22: 13 | D22: 薪资 | E22: 个人 | F22: 支付2026年1月工资 | H22: 25140 | I22: =I21+G22-H22 -> 63312.22
B23: 2 | C23: 13 | D23: 薪资 | E23: 个人 | F23: 支付2025年年终奖 | H23: 21300 | I23: =I22+G23-H23 -> 42012.22
B24: 2 | C24: 13 | D24: 往来款 | E24: 福建力喆产业投资集团有限公司 | F24: 还力喆实业暂借款 | H24: 20000 | I24: =I23+G24-H24 -> 22012.22
B25: 2 | C25: 14 | D25: 薪资 | E25: 个人 | F25: 支付2025年年终奖 | H25: 6500 | I25: =I24+G25-H25 -> 15512.22
B26: 2 | C26: 15 | D26: 五险一金 | E26: 福州住房公积金中心 | F26: 支付26年2月住房公积金 | H26: 2230 | I26: =I25+G26-H26 -> 13282.22
B27: 2 | C27: 24 | D27: 五险一金 | E27: 待报解预算收入（财库联网集中户 | F27: 企业职工基本养老保险费 20260201-20260228 3020.64 失业保险费 20260201-20260228 125.88 工伤保险费 20260201-20260228 93.3 基本医疗保险费 20260201-20260228 1336.6 生育保险费 20260201-20260228 93.56 | H27: 4669.98 | I27: =I26+G27-H27 -> 8612.24
F28: 本月合计 | G28: =SUM(G17:G27) -> 73229.1 | H28: =SUM(H17:H27) -> 86280.5 | I28: =I16+G28-H28 -> 8612.24
B29: 3 | C29: 1 | D29: 银行手续费 | E29: 建设银行 | F29: 支付对公自助设备使用费 | H29: 35 | I29: =I28+G29-H29 -> 8577.24
B30: 3 | C30: 5 | D30: 税费 | E30: 待报解预算收入（财库联网集中户 | F30: 支付20260201-20260228增值税 | H30: 6046.44 | I30: =I29+G30-H30 -> 2530.8
B31: 3 | C31: 5 | D31: 税费 | E31: 待报解预算收入（财库联网集中户 | F31: 支付20260201-20260228城建税 | H31: 211.62 | I31: =I30+G31-H31 -> 2319.18
B32: 3 | C32: 9 | D32: 税费 | E32: 待报解预算收入（财库联网集中户 | F32: 代收代付个人所得税 | H32: 828.15 | I32: =I31+G32-H32 -> 1491.03
B33: 3 | C33: 9 | D33: 房租收入 | E33: 福州朴朴电子商务有限公司 | F33: 收朴朴商务公司3月房租 | G33: 73229.1 | I33: =I32+G33-H33 -> 74720.13
B34: 3 | C34: 15 | D34: 五险一金 | E34: 福州住房公积金中心 | F34: 支付26年3月住房公积金 | H34: 2230 | I34: =I33+G34-H34 -> 72490.13
B35: 3 | C35: 16 | D35: 薪资 | E35: 个人 | F35: 支付2026年2月工资 | H35: 23141.45 | I35: =I34+G35-H35 -> 49348.68
B36: 3 | C36: 16 | D36: 往来款 | E36: 福建力喆产业投资集团有限公司 | F36: 还力喆实业暂借款 | H36: 32000 | I36: =I35+G36-H36 -> 17348.68
B37: 3 | C37: 21 | D37: 利息收入 | E37: 建设银行 | F37: 利息收入 | G37: 2.97 | I37: =I36+G37-H37 -> 17351.65
B38: 3 | C38: 23 | D38: 五险一金 | E38: 待报解预算收入（财库联网集中户 | F38: 企业职工基本养老保险费 20260301-20260331 3020.64 失业保险费 20260301-20260331 125.88 工伤保险费 20260301-20260331 46.65 基本医疗保险费 20260301-20260331 1336.6 生育保险费 20260301-20260331 93.56 | H38: 4623.33 | I38: =I37+G38-H38 -> 12728.32
B39: 3 | C39: 29 | D39: 银行手续费 | E39: 建设银行 | F39: 银行手续费 | H39: 3 | I39: =I38+G39-H39 -> 12725.32
F40: 本月合计 | G40: =SUM(G29:G39) -> 73232.07 | H40: =SUM(H29:H39) -> 69118.99 | I40: =I28+G40-H40 -> 12725.32
B41: 4 | C41: 2 | D41: 银行手续费 | E41: 建设银行 | F41: 支付对公自助设备使用费 | H41: 30 | I41: =I39+G41-H41 -> 12695.32
B42: 4 | C42: 8 | D42: 税费 | E42: 待报解预算收入（财库联网集中户 | F42: 支付20260101-20260331增值税6046.44元、城建税211.62元 | H42: 6258.06 | I42: =I41+G42-H42 -> 6437.26
B43: 4 | C43: 8 | D43: 税费 | E43: 待报解预算收入（财库联网集中户 | F43: 支付20260101-20260331房产税540元、城镇土地使用税201.42元、印花税4.5元 | H43: 745.92 | I43: =I42+G43-H43 -> 5691.34
B44: 4 | C44: 8 | D44: 税费 | E44: 待报解预算收入（财库联网集中户 | F44: 代收代付个人所得税 | H44: 97.67 | I44: =I43+G44-H44 -> 5593.67
B45: 4 | C45: 11 | D45: 房租收入 | E45: 福州朴朴电子商务有限公司 | F45: 收朴朴商务公司4月房租 | G45: 73229.1 | I45: =I44+G45-H45 -> 78822.77
B46: 4 | C46: 15 | D46: 五险一金 | E46: 福州住房公积金中心 | F46: 支付2026年4月住房公积金 | H46: 2230 | I46: =I45+G46-H46 -> 76592.77
B47: 4 | C47: 15 | D47: 薪资 | E47: 个人 | F47: 支付2026年3月工资 | H47: 25810.03 | I47: =I46+G47-H47 -> 50782.74
B48: 4 | C48: 15 | D48: 往来款 | E48: 福建力喆产业投资集团有限公司 | F48: 还力喆实业暂借款 | H48: 35000 | I48: =I47+G48-H48 -> 15782.74
B49: 4 | C49: 22 | D49: 五险一金 | E49: 待报解预算收入（财库联网集中户 | F49: 企业职工基本养老保险费 20260401-20260430 3020.64 失业保险费 20260401-20260430 125.88 工伤保险费 20260401-20260430 46.65 基本医疗保险费 20260401-20260430 1336.6 生育保险费 20260401-20260430 93.56 | H49: 4623.33 | I49: =I48+G49-H49 -> 11159.41
B50: 4 | C50: 29 | D50: 银行手续费 | E50: 建设银行 | F50: 银行手续费 | H50: 3 | I50: =I49+G50-H50 -> 11156.41
F51: 本月合计 | G51: =SUM(G41:G50) -> 73229.1 | H51: =SUM(H41:H50) -> 74798.01 | I51: =I39+G51-H51 -> 11156.41
B52: 5 | C52: 2 | D52: 银行手续费 | E52: 建设银行 | F52: 支付对公自助设备使用费 | H52: 30 | I52: =I50+G52-H52 -> 11126.41
B53: 5 | C53: 6 | D53: 税费 | E53: 待报解预算收入（财库联网集中户 | F53: 支付20260401-20260430增值税6046.44元、城建税211.62元 | H53: 6258.06 | I53: =I52+G53-H53 -> 4868.35
B54: 5 | C54: 11 | D54: 税费 | E54: 待报解预算收入（财库联网集中户 | F54: 代收代付个人所得税 | H54: 139.4 | I54: =I53+G54-H54 -> 4728.95
B55: 5 | C55: 11 | D55: 房租收入 | E55: 福州朴朴电子商务有限公司 | F55: 收朴朴商务公司房租（20260515-20260614） | G55: 73229.1 | I55: =I54+G55-H55 -> 77958.05
B56: 5 | C56: 15 | D56: 五险一金 | E56: 福州住房公积金中心 | F56: 支付2026年5月住房公积金 | H56: 2230 | I56: =I55+G56-H56 -> 75728.05
B57: 5 | C57: 15 | D57: 薪资 | E57: 个人 | F57: 支付2026年4月工资 | H57: 25121.34 | I57: =I56+G57-H57 -> 50606.71
B58: 5 | C58: 15 | D58: 往来款 | E58: 福建力喆产业投资集团有限公司 | F58: 还力喆实业暂借款 | H58: 30000 | I58: =I57+G58-H58 -> 20606.71
B59: 5 | C59: 25 | D59: 五险一金 | E59: 待报解预算收入（财库联网集中户 | F59: 企业职工基本养老保险费 20260501-20260531 3020.64 失业保险费 20260501-20260531 125.88 工伤保险费 20260501-20260531 46.65 基本医疗保险费 20260501-20260531 1336.6 生育保险费 20260501-20260531 93.56 | H59: 4623.33 | I59: =I58+G59-H59 -> 15983.38
B60: 5 | C60: 29 | D60: 银行手续费 | E60: 建设银行 | F60: 银行手续费 | H60: 3 | I60: =I59+G60-H60 -> 15980.38
F61: 本月合计 | G61: =SUM(G52:G60) -> 73229.1 | H61: =SUM(H52:H60) -> 68405.13 | I61: =I51+G61-H61 -> 15980.38
B62: 6 | C62: 2 | D62: 银行手续费 | E62: 建设银行 | F62: 支付对公自助设备使用费 | H62: 30 | I62: =I60+G62-H62 -> 15950.38
B63: 6 | C63: 3 | D63: 税费 | E63: 待报解预算收入（财库联网集中户 | F63: 支付20260501-20260531增值税6046.44元、城建税211.62元 | H63: 6258.06 | I63: =I62+G63-H63 -> 9692.32
B64: 6 | C64: 5 | D64: 税费 | E64: 待报解预算收入（财库联网集中户 | F64: 代收代付个人所得税 | H64: 128.2 | I64: =I63+G64-H64 -> 9564.12
B65: 6 | C65: 9 | D65: 房租收入 | E65: 福州朴朴电子商务有限公司 | F65: 收朴朴商务公司房租（20260615-20260714） | G65: 73229.1 | I65: =I64+G65-H65 -> 82793.22
B66: 6 | C66: 15 | D66: 五险一金 | E66: 福州住房公积金中心 | F66: 支付2026年6月住房公积金 | H66: 2230 | I66: =I65+G66-H66 -> 80563.22
B67: 6 | C67: 15 | D67: 薪资 | E67: 个人 | F67: 支付2026年5月工资 | H67: 25465.6 | I67: =I66+G67-H67 -> 55097.62
B68: 6 | C68: 15 | D68: 往来款 | E68: 福建力喆产业投资集团有限公司 | F68: 还力喆实业暂借款 | H68: 33000 | I68: =I67+G68-H68 -> 22097.62
B69: 6 | C69: 21 | D69: 利息收入 | E69: 建设银行 | F69: 利息收入 | G69: 3.07 | I69: =I68+G69-H69 -> 22100.69
B70: 6 | C70: 29 | D70: 银行手续费 | E70: 建设银行 | F70: 银行手续费 | H70: 3 | I70: =I69+G70-H70 -> 22097.69
B71: 6 | C71: 30 | D71: 五险一金 | E71: 待报解预算收入（财库联网集中户 | F71: 企业职工基本养老保险费 20260601-20260630 3020.64 失业保险费 20260601-20260630 125.88 工伤保险费 20260601-20260630 46.65 基本医疗保险费 20260601-20260630 1336.6 生育保险费 20260601-20260630 93.56 | H71: 4623.33 | I71: =I70+G71-H71 -> 17474.36
F72: 本月合计 | G72: =SUM(G62:G71) -> 73232.17 | H72: =SUM(H62:H71) -> 71738.19 | I72: =I61+G72-H72 -> 17474.36
B73: 7 | C73: 2 | D73: 银行手续费 | E73: 建设银行 | F73: 支付对公自助设备使用费 | H73: 30 | I73: =I71+G73-H73 -> 17444.36
B74: 7 | C74: 3 | D74: 税费 | E74: 待报解预算收入（财库联网集中户 | F74: 代收代付个人所得税 | H74: 138.18 | I74: =I73+G74-H74 -> 17306.18
B75: 7 | C75: 3 | D75: 税费 | E75: 待报解预算收入（财库联网集中户 | F75: 支付20260601-20260630增值税6046.44元、城建税211.62元 | H75: 6258.06 | I75: =I74+G75-H75 -> 11048.12
B76: 7 | C76: 3 | D76: 税费 | E76: 待报解预算收入（财库联网集中户 | F76: 支付20260401-20260630房产税540元、城镇土地使用税201.42元、印花税4.5元 | H76: 745.92 | I76: =I75+G76-H76 -> 10302.2
B77: 7 | C77: 14 | D77: 房租收入 | E77: 福州朴朴电子商务有限公司 | F77: 收朴朴商务公司房租（20260715-20260814） | G77: 73229.1 | I77: =I76+G77-H77 -> 83531.3
B78: 7 | C78: 15 | D78: 五险一金 | E78: 福州住房公积金中心 | F78: 支付2026年7月住房公积金 | H78: 2230 | I78: =I77+G78-H78 -> 81301.3
B79: 7 | C79: 15 | D79: 薪资 | E79: 个人 | F79: 支付2026年6月工资 | H79: 25312.88 | I79: =I78+G79-H79 -> 55988.42
B80: 7 | C80: 15 | D80: 往来款 | E80: 福建力喆产业投资集团有限公司 | F80: 还力喆实业暂借款 | H80: 33000 | I80: =I79+G80-H80 -> 22988.42
B81: 7 | C81: 21 | D81: 五险一金 | E81: 待报解预算收入（财库联网集中户 | F81: 企业职工基本养老保险费 20260701-20260731 3020.64 失业保险费 20260701-20260731 125.88 工伤保险费 20260701-20260731 46.65 基本医疗保险费 20260701-20260731 1373.7 生育保险费 20260701-20260731 96.15 | H81: 4663.02 | I81: =I80+G81-H81 -> 18325.4
B82: 7 | C82: 29 | D82: 银行手续费 | E82: 建设银行 | F82: 银行手续费 | H82: 3 | I82: =I81+G82-H82 -> 18322.4
F83: 本月合计 | G83: =SUM(G73:G82) -> 73229.1 | H83: =SUM(H73:H82) -> 72381.06 | I83: =I72+G83-H83 -> 18322.4
B84: 8 | C84: 2 | D84: 银行手续费 | E84: 建设银行 | F84: 支付对公自助设备使用费 | H84: 30 | I84: =I83+G84-H84 -> 18292.4
B85: 8 | C85: 3 | D85: 税费 | E85: 待报解预算收入（财库联网集中户 | F85: 支付20260701-20260731增值税6046.44元、城建税211.62元 | H85: 6258.06 | I85: =I84+G85-H85 -> 12034.34
B86: 8 | C86: 5 | D86: 税费 | E86: 待报解预算收入（财库联网集中户 | F86: 代收代付个人所得税 | H86: 133.91 | I86: =I85+G86-H86 -> 11900.43
B87: 8 | C87: 13 | D87: 房租收入 | E87: 福州朴朴电子商务有限公司 | F87: 收朴朴商务公司房租（20260815-20260914） | G87: 73229.1 | I87: =I86+G87-H87 -> 85129.53
B88: 8 | C88: 15 | D88: 五险一金 | E88: 福州住房公积金中心 | F88: 支付2026年8月住房公积金 | H88: 2230 | I88: =I87+G88-H88 -> 82899.53
B89: 8 | C89: 17 | D89: 薪资 | E89: 个人 | F89: 支付2026年7月工资 | H89: 25826.77 | I89: =I88+G89-H89 -> 57072.76
B90: 8 | C90: 17 | D90: 往来款 | E90: 福建力喆产业投资集团有限公司 | F90: 还力喆实业暂借款 | H90: 37000 | I90: =I89+G90-H90 -> 20072.76
B91: 8 | C91: 20 | D91: 五险一金 | E91: 待报解预算收入（财库联网集中户 | F91: 企业职工基本养老保险费 20260801-20260831 3020.64 失业保险费 20260801-20260831 125.88 工伤保险费 20260801-20260831 48.09 基本医疗保险费 20260801-20260831 1373.7 生育保险费 20260801-20260831 96.15 | H91: 4664.46 | I91: =I90+G91-H91 -> 15408.3
B92: 8 | C92: 29 | D92: 银行手续费 | E92: 建设银行 | F92: 银行手续费 | H92: 3 | I92: =I91+G92-H92 -> 15405.3
F93: 本月合计 | G93: =SUM(G84:G92) -> 73229.1 | H93: =SUM(H84:H92) -> 76146.2 | I93: =I83+G93-H93 -> 15405.3
B94: 9 | C94: 1 | D94: 税费 | E94: 待报解预算收入（财库联网集中户 | F94: 代收代付个人所得税 | H94: 149.25 | I94: =I92+G94-H94 -> 15256.05
B95: 9 | C95: 2 | D95: 银行手续费 | E95: 建设银行 | F95: 支付对公自助设备使用费 | H95: 30 | I95: =I94+G95-H95 -> 15226.05
B96: 9 | C96: 3 | D96: 税费 | E96: 待报解预算收入（财库联网集中户 | F96: 支付20260801-20260831增值税6046.44元、城建税211.62元 | H96: 6258.06 | I96: =I95+G96-H96 -> 8967.99
B97: 9 | C97: 14 | D97: 房租收入 | E97: 福州朴朴电子商务有限公司 | F97: 收朴朴商务公司房租（20260915-20261014） | G97: 73229.1 | I97: =I96+G97-H97 -> 82197.09
B98: 9 | C98: 15 | D98: 五险一金 | E98: 福州住房公积金中心 | F98: 支付2026年9月住房公积金 | H98: 2230 | I98: =I97+G98-H98 -> 79967.09
B99: 9 | C99: 15 | D99: 薪资 | E99: 个人 | F99: 支付2026年8月工资 | H99: 24802.73 | I99: =I98+G99-H99 -> 55164.36
B100: 9 | C100: 15 | D100: 往来款 | E100: 福建力喆产业投资集团有限公司 | F100: 还力喆实业暂借款 | H100: 36000 | I100: =I99+G100-H100 -> 19164.36
B101: 9 | C101: 20 | D101: 五险一金 | E101: 待报解预算收入（财库联网集中户 | F101: 企业职工基本养老保险费 20260901-20260930 3020.64 失业保险费 20260901-20260930 125.88 工伤保险费 20260901-20260930 48.09 基本医疗保险费 20260901-20260930 1373.7 生育保险费 20260901-20260930 96.15 | H101: 4664.46 | I101: =I100+G101-H101 -> 14499.9
...

Sheet 古玩城农商银行
A1: =HYPERLINK("#目录!a1","返回目录") -> 返回目录 | B1: 银行日记账--吴海萍农商银行
A3: =HYPERLINK("#目录!a1","返回目录") -> 返回目录 | G3: 收入 | O3: 支出 | P3: 余额
B4: 月 | C4: 日 | D4: 收费项 | E4: 收付人 | F4: 摘要 | G4: 租金 | H4: 物业 | I4: 水电费 | J4: 押金 | K4: 地摊费 | L4: 利息 | M4: 手续费 | N4: 收入 | Q4: 备注
F5: 期初余额 | N5: =SUM(G5:L5)-M5 -> 0 | P5: 7552829.5 | Q5: 吴海萍 | R5: 262273.1
B6: 1 | C6: 1 | E6: 陈文 | F6: A105 1月租金 | G6: 7247 | N6: =SUM(G6:L6)-M6 -> 7247 | P6: =P5+N6-O6 -> 7560076.5
B7: 1 | C7: 4 | F7: 广场92号 固定摊位费（2026.1.3-2026.4.2） | K7: 600 | M7: 17.23 | N7: =SUM(G7:L7)-M7 -> 582.77 | P7: =P6+N7-O7 -> 7560659.3
B8: 1 | C8: 4 | F8: 广场86号 固定摊位费（2026.1.5-2026.4.5） | K8: 500 | N8: =SUM(G8:L8)-M8 -> 500 | P8: =P7+N8-O8 -> 7561159.3
B9: 1 | C9: 4 | F9: 1月3-74号临时摊位费 | K9: 5790 | N9: =SUM(G9:L9)-M9 -> 5790 | P9: =P8+N9-O9 -> 7566949.3
B10: 1 | C10: 4 | E10: 黄月红 | F10: A122 年缴租金（2025.8.1-2026.7.31） | G10: 10360 | N10: =SUM(G10:L10)-M10 -> 10360 | P10: =P9+N10-O10 -> 7577309.3 | Q10: 吴海萍 | R10: =SUM(N6:N10)+R5 -> 286752.87
B11: 1 | C11: 6 | D11: 水电费 | E11: 林淑琴 | F11: 古玩城电费（2025.12.20-2025.12.31） | N11: =SUM(G11:L11)-M11 -> 0 | O11: 5511.88 | P11: =P10+N11-O11 -> 7571797.4
B12: 1 | C12: 6 | D12: 办公费 | E12: 林淑琴 | F12: 购买办公室抽纸 | N12: =SUM(G12:L12)-M12 -> 0 | O12: 75.6 | P12: =P11+N12-O12 -> 7571721.8
B13: 1 | C13: 5 | E13: 林威 | F13: C126 季度租金（2025.11.1-2026.1.31） | G13: 6000 | N13: =SUM(G13:L13)-M13 -> 6000 | P13: =P12+N13-O13 -> 7577721.8
B14: 1 | C14: 5 | E14: 周廷仕 | F14: A103 104 12月租金及11月水电费 | G14: 16445 | I14: 338 | N14: =SUM(G14:L14)-M14 -> 16783 | P14: =P13+N14-O14 -> 7594504.8
B15: 1 | C15: 10 | E15: 林烈爱 | F15: A110 1月租金物业及12月水电费 | G15: 7221 | H15: 200 | I15: 486.2 | N15: =SUM(G15:L15)-M15 -> 7907.2 | P15: =P14+N15-O15 -> 7602412
B16: 1 | C16: 10 | E16: 詹春其 | F16: A107 1月租金物业及12月水电费 | G16: 6655 | H16: 200 | I16: 616.8 | N16: =SUM(G16:L16)-M16 -> 7471.8 | P16: =P15+N16-O16 -> 7609883.8
B17: 1 | C17: 10 | E17: 朱耀梨 | F17: C132 1月租金物业及12月水电费 | G17: 1300 | H17: 150 | I17: 63.6 | N17: =SUM(G17:L17)-M17 -> 1513.6 | P17: =P16+N17-O17 -> 7611397.4
B18: 1 | C18: 10 | E18: 李小林 | F18: B117 12月水电费 | I18: 75.6 | N18: =SUM(G18:L18)-M18 -> 75.6 | P18: =P17+N18-O18 -> 7611473
B19: 1 | C19: 10 | E19: 陈裕国 | F19: C121 1月租金物业及12月水电费 | G19: 1500 | H19: 150 | I19: 93 | N19: =SUM(G19:L19)-M19 -> 1743 | P19: =P18+N19-O19 -> 7613216
B20: 1 | C20: 10 | E20: 徐常彪 | F20: C111 1月租金物业及12月水电费 | G20: 1400 | H20: 150 | I20: 66 | N20: =SUM(G20:L20)-M20 -> 1616 | P20: =P19+N20-O20 -> 7614832
B21: 1 | C21: 10 | E21: 陈文 | F21: A105 1月物业及12月水电费 | H21: 200 | I21: 633.8 | N21: =SUM(G21:L21)-M21 -> 833.8 | P21: =P20+N21-O21 -> 7615665.8
B22: 1 | C22: 10 | E22: 廖三妹 | F22: A106 1月租金物业及12月水电费 | G22: 7274 | H22: 200 | I22: 409.6 | N22: =SUM(G22:L22)-M22 -> 7883.6 | P22: =P21+N22-O22 -> 7623549.4
B23: 1 | C23: 11 | E23: 张泳光 | F23: A108 1月租金物业及12月水电费 | G23: 6946 | H23: 200 | I23: 535.8 | N23: =SUM(G23:L23)-M23 -> 7681.8 | P23: =P22+N23-O23 -> 7631231.2
B24: 1 | C24: 11 | E24: 黄美姜 | F24: B120-1 1月租金物业及12月水电费 | G24: 1700 | H24: 150 | I24: 136.8 | N24: =SUM(G24:L24)-M24 -> 1986.8 | P24: =P23+N24-O24 -> 7633218
B25: 1 | C25: 12 | E25: 郭在炎 | F25: A121 1月物业及12月水电费 | H25: 200 | I25: 164.4 | N25: =SUM(G25:L25)-M25 -> 364.4 | P25: =P24+N25-O25 -> 7633582.4
B26: 1 | C26: 12 | E26: 潘少榕 | F26: A114 1月租金物业及12月水电费 | G26: 7715 | H26: 200 | I26: 659.8 | N26: =SUM(G26:L26)-M26 -> 8574.8 | P26: =P25+N26-O26 -> 7642157.2
B27: 1 | C27: 12 | F27: 大厅1号固定摊位费（2026.1.11-2026.4.10） | K27: 700 | M27: 87.4 | N27: =SUM(G27:L27)-M27 -> 612.6 | P27: =P26+N27-O27 -> 7642769.8
B28: 1 | C28: 12 | F28: 1.10-11号地摊5290 | K28: 5290 | N28: =SUM(G28:L28)-M28 -> 5290 | P28: =P27+N28-O28 -> 7648059.8
B29: 1 | C29: 12 | E29: 江其棉 | F29: B106 年缴租金（2025.8.6-2026.8.5） | G29: 12000 | N29: =SUM(G29:L29)-M29 -> 12000 | P29: =P28+N29-O29 -> 7660059.8
B30: 1 | C30: 12 | E30: 周文光 | F30: C122 11月水电费 | I30: 47 | N30: =SUM(G30:L30)-M30 -> 47 | P30: =P29+N30-O30 -> 7660106.8
B31: 1 | C31: 12 | E31: 林木建 | F31: B108 12月租金物业及11月水电费 | G31: 1500 | H31: 150 | I31: 61 | N31: =SUM(G31:L31)-M31 -> 1711 | P31: =P30+N31-O31 -> 7661817.8
B32: 1 | C32: 12 | E32: 施传灿 | F32: A137 12月租金及11月水电费 | G32: 2900 | I32: 210 | N32: =SUM(G32:L32)-M32 -> 3110 | P32: =P31+N32-O32 -> 7664927.8
B33: 1 | C33: 12 | E33: 施传灿 | F33: B103 11月水电费 | I33: 163 | N33: =SUM(G33:L33)-M33 -> 163 | P33: =P32+N33-O33 -> 7665090.8
B34: 1 | C34: 12 | E34: 郑国朝 | F34: C128 年缴租金（2025.12.15-2026.12.14） | G34: 24000 | N34: =SUM(G34:L34)-M34 -> 24000 | P34: =P33+N34-O34 -> 7689090.8
B35: 1 | C35: 12 | E35: 刘瑞琴 | F35: A120 12月租金物业及11月水电费 | G35: 3646 | H35: 150 | I35: 190 | N35: =SUM(G35:L35)-M35 -> 3986 | P35: =P34+N35-O35 -> 7693076.8
B36: 1 | C36: 12 | E36: 张依妹 | F36: B127 1月物业及12月水电费 | H36: 150 | I36: 60 | N36: =SUM(G36:L36)-M36 -> 210 | P36: =P35+N36-O36 -> 7693286.8
B37: 1 | C37: 12 | E37: 陈昭祥 | F37: C120 1月物业及12月水电费 | H37: 150 | I37: 50.4 | N37: =SUM(G37:L37)-M37 -> 200.4 | P37: =P36+N37-O37 -> 7693487.2
B38: 1 | C38: 12 | E38: 吴国俤 | F38: C106 1月租金物业及12月水电费 | G38: 1400 | H38: 150 | I38: 187.2 | N38: =SUM(G38:L38)-M38 -> 1737.2 | P38: =P37+N38-O38 -> 7695224.4
B39: 1 | C39: 12 | E39: 吕小英 | F39: C110 1月物业及12月水电费 | H39: 150 | I39: 100.8 | N39: =SUM(G39:L39)-M39 -> 250.8 | P39: =P38+N39-O39 -> 7695475.2
B40: 1 | C40: 12 | E40: 刘增东 | F40: C113 1月物业及12月水电费 | H40: 150 | I40: 61.2 | N40: =SUM(G40:L40)-M40 -> 211.2 | P40: =P39+N40-O40 -> 7695686.4
B41: 1 | C41: 12 | E41: 王志云 | F41: C114 115 1月物业及12月水电费 | H41: 150 | I41: 102 | N41: =SUM(G41:L41)-M41 -> 252 | P41: =P40+N41-O41 -> 7695938.4
B42: 1 | C42: 12 | E42: 黄娇芳 | F42: C105 12月水电费 | I42: 62.4 | N42: =SUM(G42:L42)-M42 -> 62.4 | P42: =P41+N42-O42 -> 7696000.8
B43: 1 | C43: 12 | E43: 朱清 | F43: C120 1月租金物业及12月水电费 | G43: 1500 | H43: 150 | I43: 76.8 | N43: =SUM(G43:L43)-M43 -> 1726.8 | P43: =P42+N43-O43 -> 7697727.6
B44: 1 | C44: 12 | E44: 周文光 | F44: C122 12月水电费 | I44: 40.8 | N44: =SUM(G44:L44)-M44 -> 40.8 | P44: =P43+N44-O44 -> 7697768.4
B45: 1 | C45: 12 | E45: 徐陈威 | F45: A138 1月租金物业及12月水电费 | G45: 1700 | H45: 150 | I45: 89 | N45: =SUM(G45:L45)-M45 -> 1939 | P45: =P44+N45-O45 -> 7699707.4
B46: 1 | C46: 12 | E46: 吴伟绩 | F46: A130 1月物业及12月水电费 | H46: 150 | I46: 106 | N46: =SUM(G46:L46)-M46 -> 256 | P46: =P45+N46-O46 -> 7699963.4
B47: 1 | C47: 12 | E47: 李耀明 | F47: A101-102 1月租金及12月水电费 | G47: 7590 | I47: 165 | N47: =SUM(G47:L47)-M47 -> 7755 | P47: =P46+N47-O47 -> 7707718.4
B48: 1 | C48: 12 | E48: 姬志力 | F48: B114 1月物业及12月水电费 | H48: 150 | I48: 162 | N48: =SUM(G48:L48)-M48 -> 312 | P48: =P47+N48-O48 -> 7708030.4
B49: 1 | C49: 12 | E49: 郑飞霞 | F49: B112 1月租金物业及12月水电费 | G49: 2500 | H49: 150 | I49: 54 | N49: =SUM(G49:L49)-M49 -> 2704 | P49: =P48+N49-O49 -> 7710734.4
B50: 1 | C50: 12 | E50: 赵守辉 | F50: C101 1月租金物业及12月水电费 | G50: 1400 | H50: 150 | I50: 70.8 | N50: =SUM(G50:L50)-M50 -> 1620.8 | P50: =P49+N50-O50 -> 7712355.2
B51: 1 | C51: 12 | E51: 吴贵舜 | F51: B111 1月租金物业及12月水电费 | G51: 2400 | H51: 150 | I51: 79.2 | N51: =SUM(G51:L51)-M51 -> 2629.2 | P51: =P50+N51-O51 -> 7714984.4
B52: 1 | C52: 12 | E52: 张玉女 | F52: B120-2 12月水电费 | I52: 97.2 | N52: =SUM(G52:L52)-M52 -> 97.2 | P52: =P51+N52-O52 -> 7715081.6
B53: 1 | C53: 12 | E53: 林勇 | F53: B124 12月水电费 | I53: 277.2 | N53: =SUM(G53:L53)-M53 -> 277.2 | P53: =P52+N53-O53 -> 7715358.8
B54: 1 | C54: 12 | E54: 刘长福 | F54: B125 1月物业及12月水电费 | H54: 150 | I54: 103.2 | N54: =SUM(G54:L54)-M54 -> 253.2 | P54: =P53+N54-O54 -> 7715612
B55: 1 | C55: 12 | E55: 潘仲才 | F55: A128 1月租金物业及12月水电费 | G55: 2500 | H55: 150 | I55: 108 | N55: =SUM(G55:L55)-M55 -> 2758 | P55: =P54+N55-O55 -> 7718370
B56: 1 | C56: 12 | E56: 卢允诺 | F56: C118 1月租金物业及12月水电费 | G56: 1500 | H56: 150 | I56: 105.6 | N56: =SUM(G56:L56)-M56 -> 1755.6 | P56: =P55+N56-O56 -> 7720125.6
B57: 1 | C57: 12 | E57: 郑用辉 | F57: C134 12月租金物业及11月水电费 | G57: 544 | H57: 150 | I57: 526 | N57: =SUM(G57:L57)-M57 -> 1220 | P57: =P56+N57-O57 -> 7721345.6
B58: 1 | C58: 12 | E58: 陈媄媄 | F58: A112 1月租金物业及12月水电费 | G58: 7043 | H58: 200 | I58: 649 | N58: =SUM(G58:L58)-M58 -> 7892 | P58: =P57+N58-O58 -> 7729237.6
B59: 1 | C59: 12 | E59: 黄月红 | F59: A122 1月物业及12月水电费 | H59: 200 | I59: 112.8 | N59: =SUM(G59:L59)-M59 -> 312.8 | P59: =P58+N59-O59 -> 7729550.4
B60: 1 | C60: 13 | D60: 水电费 | E60: 林淑琴 | F60: 古玩城2025.12.10-2026.1.9水费 | N60: =SUM(G60:L60)-M60 -> 0 | O60: 2864.63 | P60: =P59+N60-O60 -> 7726685.8
B61: 1 | C61: 13 | D61: 办公费 | E61: 林淑琴 | F61: 古玩城办公室水票 | N61: =SUM(G61:L61)-M61 -> 0 | O61: 300 | P61: =P60+N61-O61 -> 7726385.8
B62: 1 | C62: 14 | E62: 翁启恩 | F62: A117-1 1月租金物业及12月水电费 | G62: 5959 | H62: 200 | I62: 2532.2 | N62: =SUM(G62:L62)-M62 -> 8691.2 | P62: =P61+N62-O62 -> 7735077
B63: 1 | C63: 15 | E63: 薛世仁 | F63: B113 C125 10月租金物业及9月水电费 | G63: 4200 | H63: 150 | I63: 769 | N63: =SUM(G63:L63)-M63 -> 5119 | P63: =P62+N63-O63 -> 7740196
B64: 1 | C64: 15 | E64: 王秀娟 | F64: A111 12月租金物业及11月水电费 | G64: 6708 | H64: 200 | I64: 276 | N64: =SUM(G64:L64)-M64 -> 7184 | P64: =P63+N64-O64 -> 7747380
B65: 1 | C65: 15 | E65: 林金芳 | F65: A131 1月租金物业及12月水电费 | G65: 3000 | H65: 150 | I65: 183.6 | N65: =SUM(G65:L65)-M65 -> 3333.6 | P65: =P64+N65-O65 -> 7750713.6
B66: 1 | C66: 15 | D66: 薪资 | E66: 个人 | F66: 古玩城2025年12月工资 | N66: =SUM(G66:L66)-M66 -> 0 | O66: 31190 | P66: =P65+N66-O66 -> 7719523.6
B67: 1 | C67: 15 | D67: 通讯、宽带费 | E67: 刘桢颖 | F67: 古玩城宽带费用 | N67: =SUM(G67:L67)-M67 -> 0 | O67: 1090 | P67: =P66+N67-O67 -> 7718433.6
B68: 1 | C68: 15 | F68: 吴海萍招行利息收入 | L68: 0.22 | N68: =SUM(G68:L68)-M68 -> 0.22 | P68: =P67+N68-O68 -> 7718433.8 | Q68: 吴海萍 | R68: =SUM(N11:N68)-SUM(O11:O67)+R10 -> 427877.38
B69: 1 | C69: 16 | E69: 陈明东 | F69: A110-2 1月租金物业及12月水电费 | G69: 1000 | H69: 150 | I69: 30 | N69: =SUM(G69:L69)-M69 -> 1180 | P69: =P68+N69-O69 -> 7719613.8
B70: 1 | C70: 18 | E70: 陈庆存 | F70: A118 1月租金物业及12月水电费 | G70: 2700 | H70: 200 | I70: 124.8 | N70: =SUM(G70:L70)-M70 -> 3024.8 | P70: =P69+N70-O70 -> 7722638.6
B71: 1 | C71: 19 | F71: 1.17-18号地摊5976 | K71: 5976 | M71: 8.43 | N71: =SUM(G71:L71)-M71 -> 5967.57 | P71: =P70+N71-O71 -> 7728606.2
B72: 1 | C72: 19 | E72: 郑国潮 | F72: C128 1月物业及12月水电费 | H72: 150 | I72: 66 | N72: =SUM(G72:L72)-M72 -> 216 | P72: =P71+N72-O72 -> 7728822.2
B73: 1 | C73: 19 | E73: 李军州 | F73: C123 12月水电费 | I73: 91.2 | N73: =SUM(G73:L73)-M73 -> 91.2 | P73: =P72+N73-O73 -> 7728913.3
B74: 1 | C74: 19 | E74: 刘祖锣 | F74: B129 1月物业及12月水电费 | H74: 150 | I74: 117 | N74: =SUM(G74:L74)-M74 -> 267 | P74: =P73+N74-O74 -> 7729180.3
B75: 1 | C75: 19 | E75: 刘祖锣 | F75: B130 1月物业及12月水电费 | H75: 150 | I75: 151.2 | N75: =SUM(G75:L75)-M75 -> 301.2 | P75: =P74+N75-O75 -> 7729481.5
B76: 1 | C76: 19 | E76: 郑元麟 | F76: C112 12月租金物业及11月水电费 | G76: 1350 | H76: 150 | I76: 83 | N76: =SUM(G76:L76)-M76 -> 1583 | P76: =P75+N76-O76 -> 7731064.5
B77: 1 | C77: 20 | E77: 吴仕茂 | F77: A113 1月租金物业及12月水电费 | G77: 7355 | H77: 200 | I77: 338.4 | N77: =SUM(G77:L77)-M77 -> 7893.4 | P77: =P76+N77-O77 -> 7738958
B78: 1 | C78: 22 | E78: 陈小龙 | F78: A12G 12租金 | G78: 10333 | M78: 28.95 | N78: =SUM(G78:L78)-M78 -> 10304.05 | P78: =P77+N78-O78 -> 7749262
B79: 1 | C79: 22 | E79: 张凯 | F79: C108 1月租金物业及12月水电费 | G79: 1200 | H79: 150 | I79: 79.2 | N79: =SUM(G79:L79)-M79 -> 1429.2 | P79: =P78+N79-O79 -> 7750691.2
B80: 1 | C80: 22 | E80: 郑用辉 | F80: C133 12月租金 | G80: 1000 | N80: =SUM(G80:L80)-M80 -> 1000 | P80: =P79+N80-O80 -> 7751691.2
B81: 1 | C81: 22 | E81: 苏清治 | F81: A136 12月物业及11月水电费 | H81: 200 | I81: 377 | N81: =SUM(G81:L81)-M81 -> 577 | P81: =P80+N81-O81 -> 7752268.2
B82: 1 | C82: 22 | E82: 苏定福 | F82: A119 12月物业及11月水电费 | H82: 200 | I82: 254 | N82: =SUM(G82:L82)-M82 -> 454 | P82: =P81+N82-O82 -> 7752722.2
B83: 1 | C83: 22 | E83: 薛德文 | F83: C119 年缴租金（2025.8.1-2026.7.31） | G83: 6200 | N83: =SUM(G83:L83)-M83 -> 6200 | P83: =P82+N83-O83 -> 7758922.2
B84: 1 | C84: 22 | E84: 陈明东 | F84: A110-2 12月物业及11月水电费 | H84: 150 | I84: 30 | N84: =SUM(G84:L84)-M84 -> 180 | P84: =P83+N84-O84 -> 7759102.2
B85: 1 | C85: 22 | E85: 后英英 | F85: A109 1月租金物业及12月水电费 | G85: 7707 | H85: 200 | I85: 885.4 | N85: =SUM(G85:L85)-M85 -> 8792.4 | P85: =P84+N85-O85 -> 7767894.6
B86: 1 | C86: 22 | D86: 物业修缮费 | E86: 李忠华 | F86: 古玩城外围花圃拆填费用 | N86: =SUM(G86:L86)-M86 -> 0 | O86: 795 | P86: =P85+N86-O86 -> 7767099.6
B87: 1 | C87: 22 | D87: 薪资 | E87: 林淑琴 | F87: 社区警务室治安费用（2026.1-2月） | N87: =SUM(G87:L87)-M87 -> 0 | O87: 1000 | P87: =P86+N87-O87 -> 7766099.6
B88: 1 | C88: 23 | E88: 黄济超 | F88: A127 1月物业及12月水电费 | H88: 300 | I88: 388.8 | N88: =SUM(G88:L88)-M88 -> 688.8 | P88: =P87+N88-O88 -> 7766788.4 | Q88: 吴海萍 | R88: =SUM(N69:N88)-SUM(O69:O88)+R68 -> 476232
B89: 1 | C89: 24 | E89: 江其棉 | F89: B106 1月物业及12月水电费 | H89: 150 | I89: 97 | N89: =SUM(G89:L89)-M89 -> 247 | P89: =P88+N89-O89 -> 7767035.4
B90: 1 | C90: 24 | E90: 陈群 | F90: C107 1月租金物业及12月水电费 | G90: 1400 | H90: 150 | I90: 45.6 | N90: =SUM(G90:L90)-M90 -> 1595.6 | P90: =P89+N90-O90 -> 7768631
B91: 1 | C91: 26 | E91: 张文华 | F91: A116 1月租金物业及12月水电费 | G91: 6090 | H91: 200 | I91: 349 | N91: =SUM(G91:L91)-M91 -> 6639 | P91: =P90+N91-O91 -> 7775270
B92: 1 | C92: 28 | E92: 周廷仕 | F92: A103 104 1月租金及12月水电费 | G92: 16445 | I92: 65.6 | N92: =SUM(G92:L92)-M92 -> 16510.6 | P92: =P91+N92-O92 -> 7791780.6
B93: 1 | C93: 26 | D93: 水电费 | E93: 林淑琴 | F93: 古玩城电费（2026.1.1-1.20） | N93: =SUM(G93:L93)-M93 -> 0 | O93: 9142.55 | P93: =P92+N93-O93 -> 7782638
B94: 1 | C94: 26 | D94: 营销费用 | E94: 李忠华 | F94: 古玩城外围地摊画线费用 | N94: =SUM(G94:L94)-M94 -> 0 | O94: 1300 | P94: =P93+N94-O94 -> 7781338
B95: 1 | C95: 26 | D95: 退押金 | E95: 詹善长 | F95: 退古玩城B104商户押金 | N95: =SUM(G95:L95)-M95 -> 0 | O95: 4800 | P95: =P94+N95-O95 -> 7776538
B96: 1 | C96: 26 | D96: 退押金 | E96: 赵伟 | F96: 退古玩城B104商户押金7800元-1月物业150、12月水电费204 | N96: =SUM(G96:L96)-M96 -> 0 | O96: 7446 | P96: =P95+N96-O96 -> 7769092
B97: 1 | D97: 往来款 | E97: 徐洁 | F97: 吴海萍转入徐洁账户 | N97: 1000 | O97: 1000 | P97: =P96+N97-O97 -> 7769092
B98: 1 | F98: 1.24-25号地摊5370 | K98: 5370 | M98: 12.22 | N98: =SUM(G98:L98)-M98 -> 5357.78 | P98: =P97+N98-O98 -> 7774449.8
B99: 1 | C99: 30 | E99: 郑用辉 | F99: C133 12月租金物业及11月水电费 | G99: 100 | H99: 150 | I99: 110 | N99: =SUM(G99:L99)-M99 -> 360 | P99: =P98+N99-O99 -> 7774809.8
B100: 1 | C100: 30 | E100: 郑用辉 | F100: C134 1月租金 | G100: 640 | N100: =SUM(G100:L100)-M100 -> 640 | P100: =P99+N100-O100 -> 7775449.8
B101: 1 | C101: 30 | E101: 陈学 | F101: B133 1月物业及12月水电费 | H101: 150 | I101: 30 | N101: =SUM(G101:L101)-M101 -> 180 | P101: =P100+N101-O101 -> 7775629.8
...

Sheet 古玩城现金
A1: =HYPERLINK("#目录!a1","返回目录") -> 返回目录 | B1: 银行日记账--吴海萍农商银行
A3: =HYPERLINK("#目录!a1","返回目录") -> 返回目录 | G3: 收入 | O3: 支出 | P3: 余额
B4: 月 | C4: 日 | D4: 收费项 | E4: 收付人 | F4: 摘要 | G4: 租金 | H4: 物业 | I4: 水电费 | J4: 押金 | K4: 地摊费 | L4: 利息 | M4: 手续费 | N4: 收入 | Q4: 备注
F5: 期初余额 | N5: =SUM(G5:L5)-M5 -> 0 | P5: 0
B6: 5 | C6: 11 | F6: 2026.5.9-5.10地摊费740 | K6: 740 | N6: =SUM(G6:L6)-M6 -> 740 | P6: =P5+N6-O6 -> 740
B7: 5 | C7: 11 | E7: 姬志力 | F7: B114 5月物业及4月水电费 | H7: 150 | I7: 170 | N7: =SUM(G7:L7)-M7 -> 320 | P7: =P6+N7-O7 -> 1060
B8: 5 | C8: 19 | F8: 2026.5.16-5.17地摊费1110 | K8: 1110 | N8: =SUM(G8:L8)-M8 -> 1110 | P8: =P7+N8-O8 -> 2170
B9: 5 | C9: 22 | E9: 郑用辉 | F9: C133 C134 4月租金 | G9: 2000 | N9: =SUM(G9:L9)-M9 -> 2000 | P9: =P8+N9-O9 -> 4170
B10: 5 | C10: 25 | F10: 2026.5.23-5.24地摊费550 | K10: 550 | N10: =SUM(G10:L10)-M10 -> 550 | P10: =P9+N10-O10 -> 4720
B11: 5 | C11: 31 | F11: 2026.5.30-5.31地摊费1680 | K11: 1680 | N11: =SUM(G11:L11)-M11 -> 1680 | P11: =P10+N11-O11 -> 6400
B12: 5 | C12: 31 | E12: 薛熙伟 | F12: A129 3月租金 | G12: 2373 | N12: =SUM(G12:L12)-M12 -> 2373 | P12: =P11+N12-O12 -> 8773
B13: 5 | C13: 31 | E13: 薛熙伟 | F13: A129 4月租金物业及3月水电费 | G13: 2500 | H13: 150 | I13: 186 | N13: =SUM(G13:L13)-M13 -> 2836 | P13: =P12+N13-O13 -> 11609
B14: 5 | C14: 31 | E14: 薛熙伟 | F14: A129 5月租金 | G14: 591 | N14: =SUM(G14:L14)-M14 -> 591 | P14: =P13+N14-O14 -> 12200
B15: 5 | C15: 31 | E15: 段锦亮 | F15: B116 4月租金物业及3月水电费 | G15: 1700 | H15: 150 | I15: 274 | N15: =SUM(G15:L15)-M15 -> 2124 | P15: =P14+N15-O15 -> 14324
B16: 5 | C16: 31 | E16: 段锦亮 | F16: B116 5月租金物业及4月水电费 | G16: 1700 | H16: 150 | I16: 26 | N16: =SUM(G16:L16)-M16 -> 1876 | P16: =P15+N16-O16 -> 16200
F17: 本月合计 | G17: =SUM(G6:G16) -> 10864 | H17: =SUM(H6:H16) -> 600 | I17: =SUM(I6:I16) -> 656 | J17: =SUM(J6:J16) -> 0 | K17: =SUM(K6:K16) -> 4080 | L17: =SUM(L6:L16) -> 0 | M17: =SUM(M6:M16) -> 0 | N17: =SUM(N6:N16) -> 16200 | O17: =SUM(O6:O16) -> 0 | P17: =P5+N17-O17 -> 16200
B18: 6 | C18: 8 | F18: 2026.6.6-6.7地摊费660 | K18: 660 | N18: =SUM(G18:L18)-M18 -> 660 | P18: =P17+N18-O18 -> 16860
B19: 6 | C19: 13 | E19: 刘长福 | F19: B125 6月租金及5月水电费 | G19: 2400 | I19: 112 | N19: =SUM(G19:L19)-M19 -> 2512 | P19: =P18+N19-O19 -> 19372
B20: 6 | C20: 15 | F20: 2026.6.13地摊费640 | K20: 640 | N20: =SUM(G20:L20)-M20 -> 640 | P20: =P19+N20-O20 -> 20012
B21: 6 | C21: 22 | F21: 2026.6.20-6.21地摊费200 | K21: 200 | N21: =SUM(G21:L21)-M21 -> 200 | P21: =P20+N21-O21 -> 20212
B22: 6 | C22: 29 | E22: 姬志力 | F22: B114 6月物业及5月水电费 | H22: 150 | I22: 192 | N22: =SUM(G22:L22)-M22 -> 342 | P22: =P21+N22-O22 -> 20554
B23: 6 | C23: 29 | E23: 宋少波 | F23: B129 8月租金 | G23: 2000 | N23: =SUM(G23:L23)-M23 -> 2000 | P23: =P22+N23-O23 -> 22554
F24: 本月合计 | G24: =SUM(G18:G23) -> 4400 | H24: =SUM(H18:H23) -> 150 | I24: =SUM(I18:I23) -> 304 | J24: =SUM(J18:J23) -> 0 | K24: =SUM(K18:K23) -> 1500 | L24: =SUM(L18:L23) -> 0 | M24: =SUM(M18:M23) -> 0 | N24: =SUM(N18:N23) -> 6354 | O24: =SUM(O18:O23) -> 0 | P24: =P17+N24-O24 -> 22554
B25: 7 | C25: 3 | E25: 郑用辉 | F25: C133 C134 5月租金及4月水电费 | G25: 572 | I25: 428 | N25: =SUM(G25:L25)-M25 -> 1000 | P25: =P23+N25-O25 -> 23554
B26: 7 | C26: 5 | F26: 2026.7.4-7.5地摊费 | K26: 345 | N26: =SUM(G26:L26)-M26 -> 345 | P26: =P25+N26-O26 -> 23899
B27: 7 | C27: 16 | E27: 姬志力 | F27: B114 7月物业及6月水电费 | H27: 150 | I27: 107 | N27: =SUM(G27:L27)-M27 -> 257 | P27: =P26+N27-O27 -> 24156
B28: 7 | C28: 18 | E28: 刘增东 | F28: C113 押金 | J28: 6900 | N28: =SUM(G28:L28)-M28 -> 6900 | P28: =P27+N28-O28 -> 31056
B29: 7 | C29: 21 | F29: 2026.7.18-7.19地摊费 | K29: 310 | N29: =SUM(G29:L29)-M29 -> 310 | P29: =P28+N29-O29 -> 31366
B30: 7 | C30: 27 | F30: 2026.7.25-7.26地摊费 | K30: 190 | N30: =SUM(G30:L30)-M30 -> 190 | P30: =P29+N30-O30 -> 31556
F31: 本月合计 | G31: =SUM(G25:G30) -> 572 | H31: =SUM(H25:H30) -> 150 | I31: =SUM(I25:I30) -> 535 | J31: =SUM(J25:J30) -> 6900 | K31: =SUM(K25:K30) -> 845 | L31: =SUM(L25:L30) -> 0 | M31: =SUM(M25:M30) -> 0 | N31: =SUM(N25:N30) -> 9002 | O31: =SUM(O25:O30) -> 0 | P31: =P24+N31-O31 -> 31556
B32: 8 | C32: 3 | F32: 2026.8.1-8.2地摊费 | K32: 170 | N32: =SUM(G32:L32)-M32 -> 170 | P32: =P31+N32-O32 -> 31726
B33: 8 | C33: 10 | F33: 2026.8.8-8.9地摊费 | K33: 220 | N33: =SUM(G33:L33)-M33 -> 220 | P33: =P32+N33-O33 -> 31946
B34: 8 | C34: 10 | E34: 林静 | F34: A12G 7月租金及6月水电费 | G34: 1800 | I34: 52 | N34: =SUM(G34:L34)-M34 -> 1852 | P34: =P33+N34-O34 -> 33798
B35: 8 | C35: 10 | E35: 吴国俤 | F35: C106 8月租金物业及6月水电费 | G35: 1400 | H35: 150 | I35: 121 | N35: =SUM(G35:L35)-M35 -> 1671 | P35: =P34+N35-O35 -> 35469
B36: 8 | C36: 10 | E36: 潘仲才 | F36: A128 8月租金 | G36: 1000 | N36: =SUM(G36:L36)-M36 -> 1000 | P36: =P35+N36-O36 -> 36469
B37: 8 | C37: 10 | E37: 陈志坚 | F37: C104 半年租金（2026.8.1-2027.1.31） | G37: 4050 | N37: =SUM(G37:L37)-M37 -> 4050 | P37: =P36+N37-O37 -> 40519
B38: 8 | C38: 15 | F38: 8.15地摊收入310 | K38: 310 | N38: =SUM(G38:L38)-M38 -> 310 | P38: =P37+N38-O38 -> 40829
B39: 8 | C39: 18 | E39: 姬志力 | F39: B114 8月物业及7月水电费 | H39: 150 | I39: 354 | N39: =SUM(G39:L39)-M39 -> 504 | P39: =P38+N39-O39 -> 41333
B40: 8 | C40: 22 | F40: 8.22地摊收入 | K40: 120 | N40: =SUM(G40:L40)-M40 -> 120 | P40: =P39+N40-O40 -> 41453
B41: 8 | C41: 31 | F41: 8.29地摊收入 | K41: 110 | N41: =SUM(G41:L41)-M41 -> 110 | P41: =P40+N41-O41 -> 41563
F42: 本月合计 | G42: =SUM(G32:G41) -> 8250 | H42: =SUM(H32:H41) -> 300 | I42: =SUM(I32:I41) -> 527 | J42: =SUM(J32:J41) -> 0 | K42: =SUM(K32:K41) -> 930 | L42: =SUM(L32:L41) -> 0 | M42: =SUM(M32:M41) -> 0 | N42: =SUM(N32:N41) -> 10007 | O42: =SUM(O32:O41) -> 0 | P42: =P31+N42-O42 -> 41563
B43: 9 | C43: 7 | F43: 9.5地摊收入 | K43: 600 | N43: =SUM(G43:L43)-M43 -> 600 | P43: =P41+N43-O43 -> 42163
B44: 9 | C44: 10 | E44: 姬志力 | F44: B114 年缴租金（2026.9.3-2027..9.2） | G44: 18000 | N44: =SUM(G44:L44)-M44 -> 18000 | P44: =P43+N44-O44 -> 60163
B45: 9 | C45: 10 | E45: 江其棉 | F45: B106 半年缴租金（2026.8.6-2027.2.5） | G45: 9000 | N45: =SUM(G45:L45)-M45 -> 9000 | P45: =P44+N45-O45 -> 69163
B46: 9 | C46: 10 | E46: 潘仲才 | F46: A128 9月租金 | G46: 1000 | N46: =SUM(G46:L46)-M46 -> 1000 | P46: =P45+N46-O46 -> 70163
B47: 9 | C47: 10 | E47: 吴国俤 | F47: C106 9月租金物业及8月水电费 | G47: 1400 | H47: 150 | I47: 125 | N47: =SUM(G47:L47)-M47 -> 1675 | P47: =P46+N47-O47 -> 71838
B48: 9 | C48: 14 | E48: 姬志力 | F48: B114 9月物业及8月水电费 | H48: 150 | I48: 455 | N48: =SUM(G48:L48)-M48 -> 605 | P48: =P47+N48-O48 -> 72443
B49: 9 | C49: 14 | F49: 9.12地摊收入 | K49: 60 | N49: =SUM(G49:L49)-M49 -> 60 | P49: =P48+N49-O49 -> 72503
B50: 9 | C50: 21 | F50: 9.19-9.20地摊收入380 | K50: 380 | N50: =SUM(G50:L50)-M50 -> 380 | P50: =P49+N50-O50 -> 72883
B51: 9 | F51: 9.26-9.27地摊收入280 | K51: 280 | N51: =SUM(G51:L51)-M51 -> 280 | P51: =P50+N51-O51 -> 73163
F52: 本月合计 | G52: =SUM(G42:G51) -> 37650 | H52: =SUM(H42:H51) -> 600 | I52: =SUM(I42:I51) -> 1107 | J52: =SUM(J42:J51) -> 0 | K52: =SUM(K42:K51) -> 2250 | L52: =SUM(L42:L51) -> 0 | M52: =SUM(M42:M51) -> 0 | N52: =SUM(N42:N51) -> 41607 | O52: =SUM(O42:O51) -> 0 | P52: =P41+N52-O52 -> 83170
B53: 10 | C53: 8 | F53: 10.3-10.4地摊收入230 | K53: 230 | N53: =SUM(G53:L53)-M53 -> 230 | P53: =P51+N53-O53 -> 73393
B54: 10 | N54: =SUM(G54:L54)-M54 -> 0 | P54: =P53+N54-O54 -> 73393
B55: 10 | N55: =SUM(G55:L55)-M55 -> 0 | P55: =P54+N55-O55 -> 73393
B56: 10 | N56: =SUM(G56:L56)-M56 -> 0 | P56: =P55+N56-O56 -> 73393
B57: 10 | N57: =SUM(G57:L57)-M57 -> 0 | P57: =P56+N57-O57 -> 73393
B58: 10 | N58: =SUM(G58:L58)-M58 -> 0 | P58: =P57+N58-O58 -> 73393
N59: =SUM(G59:L59)-M59 -> 0 | P59: =P58+N59-O59 -> 73393
N60: =SUM(G60:L60)-M60 -> 0 | P60: =P59+N60-O60 -> 73393
N61: =SUM(G61:L61)-M61 -> 0 | P61: =P60+N61-O61 -> 73393
N62: =SUM(G62:L62)-M62 -> 0 | P62: =P61+N62-O62 -> 73393
N63: =SUM(G63:L63)-M63 -> 0 | P63: =P62+N63-O63 -> 73393
N64: =SUM(G64:L64)-M64 -> 0 | P64: =P63+N64-O64 -> 73393
N65: =SUM(G65:L65)-M65 -> 0 | P65: =P64+N65-O65 -> 73393
N66: =SUM(G66:L66)-M66 -> 0 | P66: =P65+N66-O66 -> 73393
N67: =SUM(G67:L67)-M67 -> 0 | P67: =P66+N67-O67 -> 73393
N68: =SUM(G68:L68)-M68 -> 0 | P68: =P67+N68-O68 -> 73393
N69: =SUM(G69:L69)-M69 -> 0 | P69: =P68+N69-O69 -> 73393
N70: =SUM(G70:L70)-M70 -> 0 | P70: =P69+N70-O70 -> 73393
G275: =SUBTOTAL(9,#REF!) -> #REF! | H275: =SUBTOTAL(9,#REF!) -> #REF! | I275: =SUBTOTAL(9,#REF!) -> #REF! | J275: =SUBTOTAL(9,#REF!) -> #REF! | K275: =SUBTOTAL(9,#REF!) -> #REF! | L275: =SUBTOTAL(9,#REF!) -> #REF! | M275: =SUBTOTAL(9,#REF!) -> #REF! | N275: =SUBTOTAL(9,#REF!) -> #REF!
H276: 150
K277: =#REF!+#REF!+#REF! -> #REF!
K278: =K275-K277 -> #REF!
K279: 1078.33
H280: =H275+H276 -> #REF! | K280: =K278+K279 -> #REF!

Sheet 艾泊烨海峡银行
A1: =HYPERLINK("#目录!a1","返回目录") -> 返回目录 | B1: 银行日记账--海峡银行
B3: 月 | C3: 日 | D3: 收费项 | E3: 收付人 | F3: 摘要 | G3: 收入 | H3: 支出 | I3: 余额 | J3: 备注
F4: 期初余额 | I4: 4588.64
B5: 1 | C5: 2 | D5: 水电费 | E5: 电力项目归集专户 | F5: 灵响路26号12月电费 | H5: 27.49 | I5: =I4+G5-H5 -> 4561.15
B6: 1 | C6: 5 | D6: 贷款转入 | E6: 福州艾泊烨停车科技有限公司 | F6: 王晓华建行转入投资款（支付丝绸厂场工程款） | G6: 200000 | I6: =I5+G6-H6 -> 204561.15
B7: 1 | C7: 5 | D7: 股权投资款 | E7: 福州市博烨体育发展有限公司 | F7: 博烨体育投资款 | H7: 200000 | I7: =I6+G7-H7 -> 4561.15
B8: 1 | C8: 11 | D8: 银行手续费 | E8: 福建海峡银行 | F8: 自助回单打印机服务费 | H8: 60 | I8: =I7+G8-H8 -> 4501.15
B9: 1 | C9: 12 | D9: 税费 | E9: 待报解预算收入（财库联网集中户） | F9: 缴纳个人所得税 | H9: 15.77 | I9: =I8+G9-H9 -> 4485.38
B10: 1 | C10: 12 | D10: 税费 | E10: 待报解预算收入（财库联网集中户） | F10: 增值税20251001-20251231 | H10: 3061.18 | I10: =I9+G10-H10 -> 1424.2
B11: 1 | C11: 12 | D11: 税费 | E11: 待报解预算收入（财库联网集中户） | F11: 城市维护建设税20251001-20251231 | H11: 107.14 | I11: =I10+G11-H11 -> 1317.06
B12: 1 | C12: 12 | D12: 税费 | E12: 待报解预算收入（财库联网集中户） | F12: 教育费附加20251001-20251231 | H12: 45.92 | I12: =I11+G12-H12 -> 1271.14
B13: 1 | C13: 12 | D13: 税费 | E13: 待报解预算收入（财库联网集中户） | F13: 地方教育附加20251001-20251231 | H13: 30.61 | I13: =I12+G13-H13 -> 1240.53
B14: 1 | C14: 12 | D14: 税费 | E14: 待报解预算收入（财库联网集中户） | F14: 印花税20251001-20251231 | H14: 45.92 | I14: =I13+G14-H14 -> 1194.61
B15: 1 | C15: 12 | D15: 月卡收入 | E15: 张丽君 | F15: 闽A670CS停车费 | G15: 350 | I15: =I14+G15-H15 -> 1544.61
B16: 1 | C16: 14 | D16: 贷款转入 | E16: 王晓华 | F16: 建行银行转入（贷款） | G16: 130000 | I16: =I15+G16-H16 -> 131544.61
B17: 1 | C17: 15 | D17: 五险一金 | E17: 福州住房公积金中心 | F17: 支付2026年1月公积金 | H17: 3984 | I17: =I16+G17-H17 -> 127560.61
B18: 1 | C18: 15 | D18: 快递邮电费 | E18: 刘桢颖 | F18: 顺丰快递费 | H18: 16.2 | I18: =I17+G18-H18 -> 127544.41
B19: 1 | C19: 15 | D19: 往来款 | E19: 福州艾泊烨停车科技有限公司 | F19: 对公户转入农商银行一般户（支付本金、贷款利息） | H19: 60000 | I19: =I18+G19-H19 -> 67544.41
B20: 1 | C20: 15 | D20: 薪资 | E20: 招商银行应付代发业务清算款（福州艾泊烨停车科技有限公司 | F20: 代发工资（2025年12月工资） | H20: 57531.85 | I20: =I19+G20-H20 -> 10012.56
B21: 1 | C21: 15 | D21: 银行手续费 | E21: 福建海峡银行 | F21: 转账手续费 | H21: 8 | I21: =I20+G21-H21 -> 10004.56
B22: 1 | C22: 20 | D22: 月卡收入 | E22: 郑国瑞 | F22: 闽AV9Y15,停车费1.22-2.22 | G22: 600 | I22: =I21+G22-H22 -> 10604.56
B23: 1 | C23: 23 | D23: 水电收入 | E23: 福州万泊烨体育发展有限公司 | F23: 收元帅路（2025.7.1-2025.8.1）运动场地电费16798.32、水费168 | G23: 16966.32 | I23: =I22+G23-H23 -> 27570.88 | K23: 已开票
B24: 1 | C24: 26 | D24: 五险一金 | E24: 国家税务总局福州市台江区税务局 | F24: 企业职工基本养老保险费 20260101-20260131 9682.56 失业保险费 20260101-20260131 403.52 工伤保险费 20260101-20260131 563.04 基本医疗保险费 20260101-20260131 3903.1 生育保险费 20260101-20260131 273.21 | H24: 14825.43 | I24: =I23+G24-H24 -> 12745.45
B25: 1 | C25: 26 | D25: 月卡收入 | E25: 米长峰 | F25: 月卡停车费 | G25: 600 | I25: =I24+G25-H25 -> 13345.45
B26: 1 | C26: 28 | D26: 贷款转入 | E26: 福州艾泊烨停车科技有限公司 | F26: 王晓华建行转入投资款（支付丝绸厂场工程款） | G26: 108670 | I26: =I25+G26-H26 -> 122015.45
B27: 1 | C27: 28 | D27: 股权投资款 | E27: 福州市博烨体育发展有限公司 | F27: 博烨体育投资款 | H27: 108670 | I27: =I26+G27-H27 -> 13345.45
F28: 本月合计 | G28: =SUM(G5:G27) -> 457186.32 | H28: =SUM(H5:H27) -> 448429.51 | I28: =I4+G28-H28 -> 13345.45
B29: 2 | C29: 2 | D29: 水电费 | E29: 电力项目归集专户 | F29: 灵响路26号1月电费 | H29: 28.91 | I29: =I28+G29-H29 -> 13316.54
B30: 2 | C30: 4 | D30: 往来款 | E30: 王晓华 | F30: 王晓华农商银行转入艾泊烨对公账户 | G30: 50000 | I30: =I29+G30-H30 -> 63316.54
B31: 2 | C31: 5 | D31: 借款转入 | E31: 王晓华（古玩城） | F31: 古玩城吴海萍农商行转入王晓华账户再转入艾泊烨对公账户（借款用于支付博烨体育工程款） | G31: 45000 | I31: =I30+G31-H31 -> 108316.54
B32: 2 | C32: 5 | D32: 股权投资款 | E32: 福州市博烨体育发展有限公司 | F32: 博烨体育投资款 | H32: 106838.3 | I32: =I31+G32-H32 -> 1478.24
B33: 2 | C33: 9 | D33: 税费 | E33: 待报解预算收入（财库联网集中户） | F33: 缴纳个人所得税 | H33: 20.46 | I33: =I32+G33-H33 -> 1457.78
B34: 2 | C34: 9 | D34: 往来款 | E34: 福建省卓正能源科技有限公司 | F34: 代开发票5500元扣款税点275元，剩余5225元由私户转出(王晓华农商银行） | G34: 5500 | I34: =I33+G34-H34 -> 6957.78
B35: 2 | C35: 9 | D35: 退押金 | E35: 金昶晟 | F35: 退还小肥猪冰浆押金 | H35: 1000 | I35: =I34+G35-H35 -> 5957.78
B36: 2 | C36: 9 | D36: 银行手续费 | E36: 福建海峡银行 | F36: 转账手续费 | H36: 4 | I36: =I35+G36-H36 -> 5953.78
B37: 2 | C37: 9 | D37: 月卡收入 | E37: 福州潭榕食品贸易有限公司 | F37: 月卡停车费 | G37: 7200 | I37: =I36+G37-H37 -> 13153.78
B38: 2 | C38: 13 | D38: 借款转入 | E38: 王晓华（古玩城） | F38: 古玩城转入王晓华账户转入艾泊烨对公账户（借款用于支付艾泊烨1月工资及年终奖） | G38: 80000 | I38: =I37+G38-H38 -> 93153.78
B39: 2 | C39: 13 | D39: 往来款 | E39: 福州艾泊烨停车科技有限公司 | F39: 对公户转入农商银行一般户（用于支付贷款利息） | H39: 10000 | I39: =I38+G39-H39 -> 83153.78
B40: 2 | C40: 13 | D40: 薪资 | E40: 招商银行应付代发业务清算款（福州艾泊烨停车科技有限公司 | F40: 代发工资（2026年1月工资46408.08元、年终奖27243元） | H40: 73651.08 | I40: =I39+G40-H40 -> 9502.7
B41: 2 | C41: 13 | D41: 银行手续费 | E41: 福建海峡银行 | F41: 转账手续费 | H41: 8 | I41: =I40+G41-H41 -> 9494.7
B42: 2 | C42: 14 | D42: 借款转入 | E42: 福建泊易安智慧停车管理有限公司 | F42: 借款转入（用于支付灵响路拆除清理费用及博烨体育工程款） | G42: 55000 | I42: =I41+G42-H42 -> 64494.7
B43: 2 | C43: 14 | D43: 拆除费用 | E43: 福州市凯江科技工程有限公司 | F43: 灵响路地基拆除清理，土方外运至丝绸厂地块费用 | H43: 20000 | I43: =I42+G43-H43 -> 44494.7 | J43: 未开票 | M43: 王庄项目
B44: 2 | C44: 14 | D44: 银行手续费 | E44: 福建海峡银行 | F44: 转账手续费 | H44: 8 | I44: =I43+G44-H44 -> 44486.7
B45: 2 | C45: 14 | D45: 借款转入 | E45: 王晓华 | F45: 王晓华借款转入（用于支付博烨体育工程款） | G45: 26000 | I45: =I44+G45-H45 -> 70486.7
B46: 2 | C46: 14 | D46: 往来款 | E46: 王晓华 | F46: 王晓华农商银行转入艾泊烨对公账户 | G46: 45000 | I46: =I45+G46-H46 -> 115486.7
B47: 2 | C47: 14 | D47: 股权投资款 | E47: 福州市博烨体育发展有限公司 | F47: 博烨体育投资款 | H47: 106838.3 | I47: =I46+G47-H47 -> 8648.4
B48: 2 | C48: 15 | D48: 五险一金 | E48: 福州住房公积金中心 | F48: 支付2026年2月公积金 | H48: 5664 | I48: =I47+G48-H48 -> 2984.4
B49: 2 | C49: 15 | D49: 场地租金收入 | E49: 福建立行科技有限公司 | F49: 哎呦飞金包银租金2025.12.29-2026.1.28 | G49: 6000 | I49: =I48+G49-H49 -> 8984.4
B50: 2 | C50: 15 | D50: 营业分成收入 | E50: 福建立行科技有限公司 | F50: 哎呦飞金包银租金2025.11.29-2025.12.21营业分成1% | G50: 1000 | I50: =I49+G50-H50 -> 9984.4
B51: 2 | C51: 15 | D51: 水电收入 | E51: 福建立行科技有限公司 | F51: 哎呦飞金包银（2025.12.1-2026.1.1）电费833.7元、水费4.2元 | G51: 837.9 | I51: =I50+G51-H51 -> 10822.3
B52: 2 | C52: 23 | D52: 月卡收入 | E52: 张丽君 | F52: 闽A670CS停车费 | G52: 350 | I52: =I51+G52-H52 -> 11172.3
B53: 2 | C53: 25 | D53: 借款转入 | E53: 王晓华 | F53: 王晓华借款转入 | G53: 5000 | I53: =I52+G53-H53 -> 16172.3
B54: 2 | C54: 27 | D54: 薪资、社医保 | E54: 王晓华 | F54: 王晓华转入（易佰兴员工1月工资、2025年终奖、社医保费用） | G54: 22231 | I54: =I53+G54-H54 -> 38403.3
B55: 2 | C55: 27 | D55: 五险一金 | E55: 国家税务总局福州市台江区税务局 | F55: 企业职工基本养老保险费 20260201-20260228 10652.88 失业保险费 20260201-20260228 443.96 工伤保险费 20260201-20260228 620.42 基本医疗保险费 20260201-20260228 4789.7 生育保险费 20260201-20260228 335.27 | H55: 16842.23 | I55: =I54+G55-H55 -> 21561.07
B56: 2 | C56: 27 | D56: 薪资 | E56: 个人 | F56: 易佰兴1月工资16130.67元、2025年终奖1900元 | H56: 18030.67 | I56: =I55+G56-H56 -> 3530.4
B57: 2 | C57: 27 | D57: 银行手续费 | E57: 福建海峡银行 | F57: 转账手续费 | H57: 8 | I57: =I56+G57-H57 -> 3522.4
B58: 2 | C58: 28 | D58: 月卡收入 | E58: 福建省隆君定慧设计工程有限公司 | F58: 停车费 | G58: 600 | I58: =I57+G58-H58 -> 4122.4
F59: 本月合计 | G59: =SUM(G29:G58) -> 349718.9 | H59: =SUM(H29:H58) -> 358941.95 | I59: =I28+G59-H59 -> 4122.4
B60: 3 | C60: 2 | D60: 往来款 | E60: 王晓华 | F60: 农商银行私户转入艾泊烨对公账户 | G60: 5000 | I60: =I59+G60-H60 -> 9122.4
B61: 3 | C61: 2 | D61: 还款 | E61: 王晓华 | F61: 还款转入王晓华建行账户 | H61: 5000 | I61: =I60+G61-H61 -> 4122.4
B62: 3 | C62: 9 | D62: 税费 | E62: 待报解预算收入（财库联网集中户） | F62: 缴纳个人所得税 | H62: 539.8 | I62: =I61+G62-H62 -> 3582.6
B63: 3 | C63: 16 | D63: 往来款 | E63: 王晓华 | F63: 农商银行私户转入艾泊烨对公账户 | G63: 50000 | I63: =I62+G63-H63 -> 53582.6
B64: 3 | C64: 16 | D64: 五险一金 | E64: 福州住房公积金中心 | F64: 支付2026年3月公积金 | H64: 5664 | I64: =I63+G64-H64 -> 47918.6
B65: 3 | C65: 16 | D65: 往来款 | E65: 王晓华（古玩城） | F65: 吴海萍转入王晓华账户转入艾泊烨对公账户（借款用于支付艾泊烨2月工资） | G65: 17000 | I65: =I64+G65-H65 -> 64918.6
B66: 3 | C66: 16 | D66: 薪资、社医保 | E66: 王晓华 | F66: 王晓华转入（易佰兴员工2月工资15665.01元、社医保费用4599.99元） | G66: 20265 | I66: =I65+G66-H66 -> 85183.6
B67: 3 | C67: 16 | D67: 往来款 | E67: 福州艾泊烨停车科技有限公司 | F67: 对公户转入农商银行一般户（用于支付贷款利息） | H67: 3000 | I67: =I66+G67-H67 -> 82183.6
B68: 3 | C68: 16 | D68: 薪资 | E68: 招商银行应付代发业务清算款（福州艾泊烨停车科技有限公司 | F68: 代发工资2026年2月工资 | H68: 66362.32 | I68: =I67+G68-H68 -> 15821.28
B69: 3 | C69: 16 | D69: 银行手续费 | E69: 福建海峡银行 | F69: 转账手续费 | H69: 16 | I69: =I68+G69-H69 -> 15805.28
B70: 3 | C70: 18 | D70: 借款转入 | E70: 王晓华（古玩城） | F70: 吴海萍转入王晓华建行账户转入艾泊烨对公账户（借款用于支付博烨体育投资款） | G70: 50000 | I70: =I69+G70-H70 -> 65805.28
B71: 3 | C71: 18 | D71: 股权投资款 | E71: 福州市博烨体育发展有限公司 | F71: 博烨体育投资款 | H71: 50000 | I71: =I70+G71-H71 -> 15805.28
B72: 3 | C72: 21 | D72: 利息收入 | E72: 福建海峡银行 | F72: 利息收入 | G72: 1.42 | I72: =I71+G72-H72 -> 15806.7
B73: 3 | C73: 26 | D73: 月卡收入 | E73: 张丽君 | F73: 闽A670CS停车费 | G73: 350 | I73: =I72+G73-H73 -> 16156.7
B74: 3 | C74: 26 | D74: 场地租金收入 | E74: 福建立行科技有限公司 | F74: 哎呦飞金包银租金2026.2.28-2026.3.28 | G74: 6000 | I74: =I73+G74-H74 -> 22156.7
B75: 3 | C75: 26 | D75: 营业分成收入 | E75: 福建立行科技有限公司 | F75: 哎呦飞金包银租金2026.1.29-2026.2.28营业分成1% | G75: 1000 | I75: =I74+G75-H75 -> 23156.7
B76: 3 | C76: 26 | D76: 水电收入 | E76: 福建立行科技有限公司 | F76: 哎呦飞金包银（2026.2.1-2026.3.1）电费783.3元、水费2.8元 | G76: 786.1 | I76: =I75+G76-H76 -> 23942.8
B77: 3 | C77: 30 | D77: 五险一金 | E77: 国家税务总局福州市台江区税务局 | F77: 企业职工基本养老保险费 20260301-20260331 10652.88 失业保险费 20260301-20260331 443.96 工伤保险费 20260301-20260331 310.21 基本医疗保险费 20260301-20260331 4789.7 生育保险费 20260301-20260331 335.27 | H77: 16532.02 | I77: =I76+G77-H77 -> 7410.78
B78: 3 | C78: 31 | D78: 借款转入 | E78: 王晓华（王晓东） | F78: 王晓东转入王晓华建行账户转入艾泊烨对公账户（借款用于支付丝绸厂项目遮阳篷安装费用） | G78: 350000 | I78: =I77+G78-H78 -> 357410.78 | J78: 借款1分利息(2026年4月10日用160万贷款归还本金+利息351283.33元
B79: 3 | C79: 31 | D79: 丝绸厂遮阳篷安装费 | E79: 上海良哥装饰工程有限公司福州分公司 | F79: 1、遮阳篷安装费用预付款5万元，第二笔：30万元（其中博烨体育已支付25万元） 2、（总价150万，支付方式：合同签订预付20%：30万元， 第二笔：材料进场后支付20%：30万元， 第三笔：弧形大梁吊装2套支付20%：30万元， 第四笔：验收合格支付35%：525000元， 尾款：质保期结束后支付5%：75000元 ） | H79: 350000 | I79: =I78+G79-H79 -> 7410.78 | J79: 未开票 | M79: 王庄项目
B80: 3 | C80: 31 | D80: 银行手续费 | E80: 福建海峡银行 | F80: 转账手续费 | H80: 12 | I80: =I79+G80-H80 -> 7398.78
F81: 本月合计 | G81: =SUM(G60:G80) -> 500402.52 | H81: =SUM(H60:H80) -> 497126.14 | I81: =I59+G81-H81 -> 7398.78
B82: 4 | C82: 2 | D82: 充电桩收入 | E82: 福州尚豚电子商务有限公司 | F82: 元帅路停车场售货机费用结算营业收入 | G82: 144.7 | I82: =I80+G82-H82 -> 7543.48
B83: 4 | C83: 7 | D83: 月卡收入 | E83: 福建省隆君定慧设计工程有限公司 | F83: 停车费 | G83: 600 | I83: =I82+G83-H83 -> 8143.48
B84: 4 | C84: 8 | D84: 税费 | E84: 待报解预算收入（财库联网集中户） | F84: 20260101-20260331印花税 | H84: 11.76 | I84: =I83+G84-H84 -> 8131.72
B85: 4 | C85: 8 | D85: 税费 | E85: 待报解预算收入（财库联网集中户） | F85: 缴纳个人所得税 | H85: 17.8 | I85: =I84+G85-H85 -> 8113.92
B86: 4 | C86: 9 | D86: 场地租金收入 | E86: 福建立行科技有限公司 | F86: 哎呦飞金包银租金2026.1.29-2026.2.28 | G86: 6000 | I86: =I85+G86-H86 -> 14113.92
B87: 4 | C87: 9 | D87: 营业分成收入 | E87: 福建立行科技有限公司 | F87: 哎呦飞金包银租金2025.12.29-2026.1.28营业分成1% | G87: 1000 | I87: =I86+G87-H87 -> 15113.92
B88: 4 | C88: 9 | D88: 水电收入 | E88: 福建立行科技有限公司 | F88: 哎呦飞金包银（2026.1.1-2026.2.1）电费1166.55元、水费3.5元 | G88: 1170.05 | I88: =I87+G88-H88 -> 16283.97
B89: 4 | C89: 9 | E89: 福州万象会发展有限公司 | F89: 2025.8-2026.3水电费和2025.11-2026.3服务费 | G89: 225103 | I89: =I88+G89-H89 -> 241386.97
B90: 4 | C90: 10 | E90: 福州万象会发展有限公司 | F90: 退回2025.8-2026.3水电费和2025.11-2026.3服务费 | H90: 225103 | I90: =I89+G90-H90 -> 16283.97
B91: 4 | C91: 10 | D91: 水电收入 | E91: 福州万泊烨体育发展有限公司 | F91: 收元帅路（2025.8.1-2025.9.1）运动场地电费17923.5元、水费203元 | G91: 18126.5 | I91: =I90+G91-H91 -> 34410.47
B92: 4 | C92: 10 | D92: 水电收入 | E92: 福州万泊烨体育发展有限公司 | F92: 收元帅路（2025.9.1-2025.10.1）运动场地电费17684.68元、水费217元 | G92: 17901.68 | I92: =I91+G92-H92 -> 52312.15
B93: 4 | C93: 10 | D93: 场地租金收入 | E93: 福州万泊烨体育发展有限公司 | F93: 收元帅路运动场地服务费（2025.10.29-2025.11.28） | G93: 31900 | I93: =I92+G93-H93 -> 84212.15
B94: 4 | C94: 10 | D94: 水电收入 | E94: 福州万泊烨体育发展有限公司 | F94: 收元帅路（2025.10.1-2025.11.1）运动场地电费8585.32元、水费147元 | G94: 8732.32 | I94: =I93+G94-H94 -> 92944.47
B95: 4 | C95: 10 | D95: 场地租金收入 | E95: 福州万泊烨体育发展有限公司 | F95: 收元帅路运动场地服务费（2025.11.29-2025.12.28） | G95: 31900 | I95: =I94+G95-H95 -> 124844.47
B96: 4 | C96: 10 | D96: 水电收入 | E96: 福州万泊烨体育发展有限公司 | F96: 收元帅路（2025.11.1-2025.12.1）运动场地电费4000.5元、水费315元 | G96: 4315.5 | I96: =I95+G96-H96 -> 129159.97
B97: 4 | C97: 10 | D97: 场地租金收入 | E97: 福州万泊烨体育发展有限公司 | F97: 收元帅路运动场地服务费（2025.12.29-2026.1.28） | G97: 31900 | I97: =I96+G97-H97 -> 161059.97
B98: 4 | C98: 10 | D98: 水电收入 | E98: 福州万泊烨体育发展有限公司 | F98: 收元帅路（2025.12.1-2026.1.1）运动场地电费3528元、水费196元 | G98: 3724 | I98: =I97+G98-H98 -> 164783.97
B99: 4 | C99: 10 | D99: 场地租金收入 | E99: 福州万泊烨体育发展有限公司 | F99: 收元帅路运动场地服务费（2026.1.29-2026.2.28） | G99: 31900 | I99: =I98+G99-H99 -> 196683.97
B100: 4 | C100: 10 | D100: 水电收入 | E100: 福州万泊烨体育发展有限公司 | F100: 收元帅路（2026.1.1-2026.2.1）运动场地电费3907.89元、水费224元 | G100: 4131.89 | I100: =I99+G100-H100 -> 200815.86
B101: 4 | C101: 10 | D101: 场地租金收入 | E101: 福州万泊烨体育发展有限公司 | F101: 收元帅路运动场地服务费（2026.3.1-2026.3.28） | G101: 31900 | I101: =I100+G101-H101 -> 232715.86
...

Sheet 艾泊烨招商银行
A1: =HYPERLINK("#目录!a1","返回目录") -> 返回目录 | B1: 银行日记账--招商银行（一般户）
B3: 月 | C3: 日 | D3: 收费项 | E3: 收付人 | F3: 摘要 | G3: 收入 | H3: 支出 | I3: 余额 | J3: 备注
F4: 期初余额 | I4: 30632.96
B5: 1 | C5: 2 | D5: 银行手续费 | E5: 招商银行福州南台支行 | F5: 网上企业银行-网上企业银行服务费 | H5: 25 | I5: =I4+G5-H5 -> 30607.96
F6: 本月合计 | G6: =SUM(G5) -> 0 | H6: =SUM(H5) -> 25 | I6: =I4+G6-H6 -> 30607.96
B7: 2 | C7: 2 | D7: 银行手续费 | E7: 招商银行福州南台支行 | F7: 网上企业银行-网上企业银行服务费 | H7: 25 | I7: =I6+G7-H7 -> 30582.96
F8: 本月合计 | G8: =SUM(G7) -> 0 | H8: =SUM(H7) -> 25 | I8: =I6+G8-H8 -> 30582.96
B9: 3 | C9: 2 | D9: 银行手续费 | E9: 招商银行福州南台支行 | F9: 网上企业银行-网上企业银行服务费 | H9: 25 | I9: =I7+G9-H9 -> 30557.96
B10: 3 | C10: 21 | D10: 利息收入 | E10: 招商银行福州南台支行 | F10: 利息收入 | G10: 3.82 | I10: =I9+G10-H10 -> 30561.78
F11: 本月合计 | G11: =SUM(G9:G10) -> 3.82 | H11: =SUM(H9:H10) -> 25 | I11: =I8+G11-H11 -> 30561.78
B12: 4 | C12: 2 | D12: 银行手续费 | E12: 招商银行福州南台支行 | F12: 网上企业银行-网上企业银行服务费 | H12: 25 | I12: =I10+G12-H12 -> 30536.78
F13: 本月合计 | G13: =SUM(G12:G12) -> 0 | H13: =SUM(H12:H12) -> 25 | I13: =I10+G13-H13 -> 30536.78
B14: 5 | C14: 2 | D14: 银行手续费 | E14: 招商银行福州南台支行 | F14: 网上企业银行-网上企业银行服务费 | H14: 25 | I14: =I12+G14-H14 -> 30511.78
F15: 本月合计 | G15: =SUM(G14:G14) -> 0 | H15: =SUM(H14:H14) -> 25 | I15: =I12+G15-H15 -> 30511.78
B16: 6 | C16: 2 | D16: 银行手续费 | E16: 招商银行福州南台支行 | F16: 网上企业银行-网上企业银行服务费 | H16: 25 | I16: =I15+G16-H16 -> 30486.78
B17: 6 | C17: 15 | D17: 往来款 | E17: 福州艾泊烨停车科技有限公司 | F17: 转入艾泊烨农商银行一般户（还利息） | H17: 17000 | I17: =I16+G17-H17 -> 13486.78
B18: 6 | C18: 21 | D18: 利息收入 | E18: 招商银行福州南台支行 | F18: 利息收入 | G18: 3.76 | I18: =I17+G18-H18 -> 13490.54
B19: 6 | C19: 22 | D19: 往来款 | E19: 福州艾泊烨停车科技有限公司 | F19: 转入艾泊烨基本户 | H19: 10000 | I19: =I18+G19-H19 -> 3490.54
F20: 本月合计 | G20: =SUM(G16:G19) -> 3.76 | H20: =SUM(H16:H19) -> 27025 | I20: =I15+G20-H20 -> 3490.54
B21: 7 | C21: 2 | D21: 银行手续费 | E21: 招商银行福州南台支行 | F21: 银行手续费 | H21: 1.06 | I21: =I19+G21-H21 -> 3489.48
B22: 7 | C22: 2 | D22: 银行手续费 | E22: 招商银行福州南台支行 | F22: 网上企业银行-网上企业银行服务费 | H22: 25 | I22: =I21+G22-H22 -> 3464.48
F23: 本月合计 | G23: =SUM(G21:G22) -> 0 | H23: =SUM(H21:H22) -> 26.06 | I23: =I20+G23-H23 -> 3464.48
B24: 8 | C24: 2 | D24: 银行手续费 | E24: 招商银行福州南台支行 | F24: 网上企业银行-网上企业银行服务费 | H24: 25 | I24: =I22+G24-H24 -> 3439.48
F25: 本月合计 | G25: =SUM(G23:G24) -> 0 | H25: =SUM(H24:H24) -> 25 | I25: =I23+G25-H25 -> 3439.48
B26: 9 | C26: 2 | D26: 银行手续费 | E26: 招商银行福州南台支行 | F26: 网上企业银行-网上企业银行服务费 | H26: 25 | I26: =I24+G26-H26 -> 3414.48
B27: 9 | C27: 21 | D27: 利息收入 | E27: 招商银行福州南台支行 | F27: 利息收入 | G27: 0.45 | I27: =I26+G27-H27 -> 3414.93
B28: 9 | C28: 30 | D28: 往来款 | E28: 福州市博烨体育发展有限公司 | F28: 归还博烨体育借款 | H28: 2500 | I28: =I27+G28-H28 -> 914.93
F29: 本月合计 | G29: =SUM(G26:G28) -> 0.45 | H29: =SUM(H26:H28) -> 2525 | I29: =I25+G29-H29 -> 914.93
I30: =I28+G30-H30 -> 914.93
I31: =I30+G31-H31 -> 914.93
I32: =I31+G32-H32 -> 914.93
I33: =I32+G33-H33 -> 914.93
I34: =I33+G34-H34 -> 914.93
I35: =I34+G35-H35 -> 914.93
I36: =I35+G36-H36 -> 914.93
I37: =I36+G37-H37 -> 914.93
I38: =I37+G38-H38 -> 914.93
I39: =I38+G39-H39 -> 914.93
I40: =I39+G40-H40 -> 914.93
I41: =I40+G41-H41 -> 914.93
I42: =I41+G42-H42 -> 914.93
... I73: =I72+G73-H73 -> 914.93

Sheet 艾泊烨农商银行
A1: =HYPERLINK("#目录!a1","返回目录") -> 返回目录 | B1: 银行日记账--农商银行（一般户）
B3: 月 | C3: 日 | D3: 收费项 | E3: 收付人 | F3: 摘要 | G3: 停车收入 | H3: 手续费 | I3: 收入 | J3: 支出 | K3: 余额 | L3: 备注
F4: 期初余额 | K4: 3219.26
B5: 1 | C5: 15 | D5: 往来款 | E5: 福州艾泊烨停车科技有限公司 | F5: 艾泊烨基本户转入一般户（还利息及本金） | I5: 60000 | K5: =K4+I5-J5 -> 63219.26
B6: 1 | C6: 21 | D6: 贷款利息 | E6: 福州艾泊烨停车科技有限公司 | F6: 贷款利息 | J6: 9151.46 | K6: =K5+I6-J6 -> 54067.8
B7: 1 | C7: 21 | D7: 还贷款本金 | E7: 福州艾泊烨停车科技有限公司 | F7: 归还贷款本金 | J7: 50000 | K7: =K6+I7-J7 -> 4067.8
F8: 本月合计 | I8: =SUM(I5:I7) -> 60000 | J8: =SUM(J5:J7) -> 59151.46 | K8: =K4+I8-J8 -> 4067.8
B9: 2 | C9: 13 | D9: 往来款 | E9: 福州艾泊烨停车科技有限公司 | F9: 艾泊烨基本户转入一般户（还利息） | I9: 10000 | K9: =K8+I9-J9 -> 14067.8
B10: 2 | C10: 21 | D10: 贷款利息 | E10: 福州艾泊烨停车科技有限公司 | F10: 贷款利息 | J10: 8916.81 | K10: =K9+I10-J10 -> 5150.99
F11: 本月合计 | I11: =SUM(I9:I10) -> 10000 | J11: =SUM(J9:J10) -> 8916.81 | K11: =K7+I11-J11 -> 5150.99
B12: 3 | C12: 16 | D12: 往来款 | E12: 福州艾泊烨停车科技有限公司 | F12: 艾泊烨基本户转入一般户（还利息） | I12: 3000 | K12: =K10+I12-J12 -> 8150.99
B13: 3 | C13: 21 | D13: 利息收入 | E13: 农商银行营业部 | F13: 利息收入 | I13: 1.15 | K13: =K12+I13-J13 -> 8152.14
B14: 3 | C14: 21 | D14: 贷款利息 | E14: 福州艾泊烨停车科技有限公司 | F14: 贷款利息 | J14: 8053.89 | K14: =K13+I14-J14 -> 98.25
F15: 本月合计 | I15: =SUM(I12:I14) -> 3001.15 | J15: =SUM(J12:J14) -> 8053.89 | K15: =K11+I15-J15 -> 98.25
B16: 4 | C16: 8 | E16: 农商银行营业部 | F16: 收到发放贷款 | I16: 1600000 | K16: =K14+I16-J16 -> 1600098.2
B17: 4 | C17: 8 | E17: 厦门市鑫创达科技有限公司 | F17: 预付账款 | J17: 1600000 | K17: =K16+I17-J17 -> 98.25
B18: 4 | C18: 16 | D18: 往来款 | E18: 福州艾泊烨停车科技有限公司 | F18: 艾泊烨基本户转入一般户（还利息） | I18: 15000 | K18: =K17+I18-J18 -> 15098.25
B19: 4 | C19: 21 | D19: 贷款利息 | E19: 福州艾泊烨停车科技有限公司 | F19: 200万贷款利息 | J19: 8842.92 | K19: =K18+I19-J19 -> 6255.33
B20: 4 | C20: 21 | D20: 贷款利息 | E20: 福州艾泊烨停车科技有限公司 | F20: 160万贷款利息 | J20: 2975.56 | K20: =K19+I20-J20 -> 3279.77
F21: 本月合计 | I21: =SUM(I16:I20) -> 1615000 | J21: =SUM(J16:J20) -> 1611818.5 | K21: =K17+I21-J21 -> 3279.77
B22: 5 | C22: 15 | D22: 往来款 | E22: 福州艾泊烨停车科技有限公司 | F22: 艾泊烨基本户转入一般户（还利息） | I22: 16000 | K22: =K20+I22-J22 -> 19279.77
B23: 5 | C23: 21 | D23: 贷款利息 | E23: 福州艾泊烨停车科技有限公司 | F23: 200万贷款利息 | J23: 8312.5 | K23: =K22+I23-J23 -> 10967.27
B24: 5 | C24: 21 | D24: 贷款利息 | E24: 福州艾泊烨停车科技有限公司 | F24: 160万贷款利息 | J24: 6866.67 | K24: =K23+I24-J24 -> 4100.6
F25: 本月合计 | I25: =SUM(I22:I24) -> 16000 | J25: =SUM(J22:J24) -> 15179.17 | K25: =K21+I25-J25 -> 4100.6
B26: 6 | C26: 15 | D26: 往来款 | E26: 福州艾泊烨停车科技有限公司 | F26: 基本户转入艾泊烨农商银行一般户（还利息） | I26: 17000 | K26: =K24+I26-J26 -> 21100.6
B27: 6 | C27: 21 | D27: 利息收入 | E27: 农商银行营业部 | F27: 利息收入 | I27: 0.7 | K27: =K26+I27-J27 -> 21101.3
B28: 6 | C28: 21 | D28: 贷款利息 | E28: 福州艾泊烨停车科技有限公司 | F28: 200万贷款利息 | J28: 8589.58 | K28: =K27+I28-J28 -> 12511.72
B29: 6 | C29: 21 | D29: 贷款利息 | E29: 福州艾泊烨停车科技有限公司 | F29: 160万贷款利息 | J29: 7095.56 | K29: =K28+I29-J29 -> 5416.16
F30: 本月合计 | I30: =SUM(I26:I29) -> 17000.7 | J30: =SUM(J26:J29) -> 15685.14 | K30: =K25+I30-J30 -> 5416.16
B31: 7 | C31: 17 | D31: 往来款 | E31: 福州艾泊烨停车科技有限公司 | F31: 转入艾泊烨农商银行一般户（还本金及利息） | I31: 66000 | K31: =K29+I31-J31 -> 71416.16
B32: 7 | C32: 21 | D32: 还贷款本金 | E32: 福州艾泊烨停车科技有限公司 | J32: 50000 | K32: =K31+I32-J32 -> 21416.16
B33: 7 | C33: 21 | D33: 贷款利息 | E33: 福州艾泊烨停车科技有限公司 | F33: 200万贷款利息 | J33: 8312.5 | K33: =K32+I33-J33 -> 13103.66
B34: 7 | C34: 21 | D34: 贷款利息 | E34: 福州艾泊烨停车科技有限公司 | F34: 160万贷款利息 | J34: 6866.67 | K34: =K33+I34-J34 -> 6236.99
F35: 本月合计 | I35: =SUM(I31:I34) -> 66000 | J35: =SUM(J31:J34) -> 65179.17 | K35: =K30+I35-J35 -> 6236.99
B36: 8 | C36: 17 | D36: 往来款 | E36: 福州艾泊烨停车科技有限公司 | F36: 基本户转入艾泊烨农商银行一般户（还利息） | I36: 16000 | K36: =K34+I36-J36 -> 22236.99
B37: 8 | C37: 17 | E37: 财付通支付科技有限公司 | F37: 微信支付认证 | I37: 0.01 | K37: =K36+I37-J37 -> 22237
B38: 8 | C38: 21 | D38: 贷款利息 | E38: 福州艾泊烨停车科技有限公司 | F38: 200万贷款利息 | J38: 8363.54 | K38: =K37+I38-J38 -> 13873.46
B39: 8 | C39: 21 | D39: 贷款利息 | E39: 福州艾泊烨停车科技有限公司 | F39: 160万贷款利息 | J39: 7095.56 | K39: =K38+I39-J39 -> 6777.9
B40: 8 | C40: 23 | E40: 财付通支付科技有限公司 | F40: 鼓西派出所停车场收入（2026.8.22） | G40: 40 | H40: 0.21 | I40: =G40-H40 -> 39.79 | K40: =K39+I40-J40 -> 6817.69
B41: 8 | C41: 24 | E41: 财付通支付科技有限公司 | F41: 鼓西派出所停车场收入（2026.8.23） | G41: 270 | H41: 1.44 | I41: =G41-H41 -> 268.56 | K41: =K40+I41-J41 -> 7086.25
B42: 8 | C42: 25 | E42: 财付通支付科技有限公司 | F42: 鼓西派出所停车场收入（2026.8.24） | G42: 130 | H42: 0.69 | I42: =G42-H42 -> 129.31 | K42: =K41+I42-J42 -> 7215.56
B43: 8 | C43: 26 | E43: 财付通支付科技有限公司 | F43: 鼓西派出所停车场收入（2026.8.25） | G43: 180 | H43: 0.95 | I43: =G43-H43 -> 179.05 | K43: =K42+I43-J43 -> 7394.61
B44: 8 | C44: 27 | E44: 财付通支付科技有限公司 | F44: 鼓西派出所停车场收入（2026.8.26） | G44: 250 | H44: 1.32 | I44: =G44-H44 -> 248.68 | K44: =K43+I44-J44 -> 7643.29
B45: 8 | C45: 28 | E45: 财付通支付科技有限公司 | F45: 鼓西派出所停车场收入（2026.8.27） | G45: 155 | H45: 0.82 | I45: =G45-H45 -> 154.18 | K45: =K44+I45-J45 -> 7797.47
B46: 8 | C46: 29 | E46: 财付通支付科技有限公司 | F46: 鼓西派出所停车场收入（2026.8.28） | G46: 110 | H46: 0.58 | I46: =G46-H46 -> 109.42 | K46: =K45+I46-J46 -> 7906.89
B47: 8 | C47: 30 | E47: 财付通支付科技有限公司 | F47: 鼓西派出所停车场收入（2026.8.29） | G47: 240 | H47: 1.27 | I47: =G47-H47 -> 238.73 | K47: =K46+I47-J47 -> 8145.62
B48: 8 | C48: 31 | E48: 财付通支付科技有限公司 | F48: 鼓西派出所停车场收入（2026.8.30） | G48: 215 | H48: 1.13 | I48: =G48-H48 -> 213.87 | K48: =K47+I48-J48 -> 8359.49
F49: 本月合计 | G49: =SUM(G36:G48) -> 1590 | H49: =SUM(H36:H48) -> 8.41 | I49: =SUM(I36:I48) -> 17581.6 | J49: =SUM(J36:J48) -> 15459.1 | K49: =K35+I49-J49 -> 8359.49
B50: 9 | C50: 1 | E50: 财付通支付科技有限公司 | F50: 鼓西派出所停车场收入（2026.8.31） | G50: 155 | H50: 0.81 | I50: =G50-H50 -> 154.19 | K50: =K49+I50-J50 -> 8513.68
B51: 9 | C51: 2 | E51: 财付通支付科技有限公司 | F51: 鼓西派出所停车场收入（2026.9.1） | G51: 200 | H51: 1.05 | I51: =G51-H51 -> 198.95 | K51: =K50+I51-J51 -> 8712.63
B52: 9 | C52: 3 | E52: 财付通支付科技有限公司 | F52: 鼓西派出所停车场收入（2026.9.2） | G52: 265 | H52: 1.43 | I52: =G52-H52 -> 263.57 | K52: =K51+I52-J52 -> 8976.2
B53: 9 | C53: 4 | E53: 财付通支付科技有限公司 | F53: 鼓西派出所停车场收入（2026.9.3） | G53: 385 | H53: 2.08 | I53: =G53-H53 -> 382.92 | K53: =K52+I53-J53 -> 9359.12
B54: 9 | C54: 5 | E54: 财付通支付科技有限公司 | F54: 鼓西派出所停车场收入（2026.9.4） | G54: 195 | H54: 1.04 | I54: =G54-H54 -> 193.96 | K54: =K53+I54-J54 -> 9553.08
B55: 9 | C55: 6 | E55: 财付通支付科技有限公司 | F55: 鼓西派出所停车场收入（2026.9.5） | G55: 215 | H55: 1.15 | I55: =G55-H55 -> 213.85 | K55: =K54+I55-J55 -> 9766.93
B56: 9 | C56: 7 | E56: 财付通支付科技有限公司 | F56: 鼓西派出所停车场收入（2026.9.6） | G56: 190 | H56: 1.01 | I56: =G56-H56 -> 188.99 | K56: =K55+I56-J56 -> 9955.92
B57: 9 | C57: 8 | E57: 财付通支付科技有限公司 | F57: 鼓西派出所停车场收入（2026.9.7） | G57: 115 | H57: 0.6 | I57: =G57-H57 -> 114.4 | K57: =K56+I57-J57 -> 10070.32
B58: 9 | C58: 9 | E58: 财付通支付科技有限公司 | F58: 鼓西派出所停车场收入（2026.9.8） | G58: 295 | H58: 1.59 | I58: =G58-H58 -> 293.41 | K58: =K57+I58-J58 -> 10363.73
B59: 9 | C59: 10 | E59: 财付通支付科技有限公司 | F59: 鼓西派出所停车场收入（2026.9.9） | G59: 160 | H59: 0.84 | I59: =G59-H59 -> 159.16 | K59: =K58+I59-J59 -> 10522.89
B60: 9 | C60: 11 | E60: 财付通支付科技有限公司 | F60: 鼓西派出所停车场收入（2026.9.10） | G60: 130 | H60: 0.7 | I60: =G60-H60 -> 129.3 | K60: =K59+I60-J60 -> 10652.19
B61: 9 | C61: 12 | E61: 财付通支付科技有限公司 | F61: 鼓西派出所停车场收入（2026.9.11） | G61: 15 | H61: 0.08 | I61: =G61-H61 -> 14.92 | K61: =K60+I61-J61 -> 10667.11
... B64: 9 | C64: 15 | E64: 财付通支付科技有限公司 | F64: 鼓西派出所停车场收入（2026.9.14） | G64: 215 | H64: 1.16 | I64: =G64-H64 -> 213.84 | K64: =K63+I64-J64 -> 11199.23
B65: 9 | C65: 15 | D65: 往来款 | E65: 福州艾泊烨停车科技有限公司 | F65: 基本户转入艾泊烨农商银行一般户（还利息） | I65: 7000 | K65: =K64+I65-J65 -> 18199.23
B66: 9 | C66: 16 | E66: 财付通支付科技有限公司 | F66: 鼓西派出所停车场收入（2026.9.15） | G66: 220 | H66: 1.16 | I66: =G66-H66 -> 218.84 | K66: =K65+I66-J66 -> 18418.07
B67: 9 | C67: 17 | E67: 财付通支付科技有限公司 | F67: 鼓西派出所停车场收入（2026.9.16） | G67: 125 | H67: 0.66 | I67: =G67-H67 -> 124.34 | K67: =K66+I67-J67 -> 18542.41
B68: 9 | C68: 18 | E68: 财付通支付科技有限公司 | F68: 鼓西派出所停车场收入（2026.9.17） | G68: 275 | H68: 1.45 | I68: =G68-H68 -> 273.55 | K68: =K67+I68-J68 -> 18815.96
B69: 9 | C69: 19 | E69: 财付通支付科技有限公司 | F69: 鼓西派出所停车场收入（2026.9.18） | G69: 185 | H69: 0.98 | I69: =G69-H69 -> 184.02 | K69: =K68+I69-J69 -> 18999.98
B70: 9 | C70: 20 | E70: 财付通支付科技有限公司 | F70: 鼓西派出所停车场收入（2026.9.19） | G70: 500 | H70: 2.68 | I70: =G70-H70 -> 497.32 | K70: =K69+I70-J70 -> 19497.3
B71: 9 | C71: 20 | D71: 往来款 | E71: 福州市博烨体育发展有限公司 | F71: 归还博烨体育借款 | I71: =G71-H71 -> 0 | J71: 1500 | K71: =K70+I71-J71 -> 17997.3
B72: 9 | C72: 21 | D72: 利息收入 | E72: 农商银行营业部 | F72: 利息收入 | I72: 1.41 | K72: =K71+I72-J72 -> 17998.71
B73: 9 | C73: 21 | D73: 贷款利息 | E73: 福州艾泊烨停车科技有限公司 | F73: 200万贷款利息 | J73: 8363.54 | K73: =K72+I73-J73 -> 9635.17
B74: 9 | C74: 21 | D74: 贷款利息 | E74: 福州艾泊烨停车科技有限公司 | F74: 160万贷款利息 | J74: 7095.56 | K74: =K73+I74-J74 -> 2539.61
B75: 9 | C75: 21 | E75: 财付通支付科技有限公司 | F75: 鼓西派出所停车场收入（2026.9.20） | G75: 120 | H75: 0.63 | I75: =G75-H75 -> 119.37 | K75: =K74+I75-J75 -> 2658.98
B76: 9 | C76: 22 | E76: 财付通支付科技有限公司 | F76: 鼓西派出所停车场收入（2026.9.21） | G76: 35 | H76: 0.18 | I76: =G76-H76 -> 34.82 | K76: =K75+I76-J76 -> 2693.8
B77: 9 | C77: 23 | E77: 财付通支付科技有限公司 | F77: 鼓西派出所停车场收入（2026.9.22） | G77: 145 | H77: 0.77 | I77: =G77-H77 -> 144.23 | K77: =K76+I77-J77 -> 2838.03
B78: 9 | C78: 24 | E78: 财付通支付科技有限公司 | F78: 鼓西派出所停车场收入（2026.9.23） | G78: 220 | H78: 1.18 | I78: =G78-H78 -> 218.82 | K78: =K77+I78-J78 -> 3056.85
B79: 9 | C79: 25 | E79: 财付通支付科技有限公司 | F79: 鼓西派出所停车场收入（2026.9.24） | G79: 130 | H79: 0.69 | I79: =G79-H79 -> 129.31 | K79: =K78+I79-J79 -> 3186.16
B80: 9 | C80: 26 | E80: 财付通支付科技有限公司 | F80: 鼓西派出所停车场收入（2026.9.25） | G80: 235 | H80: 1.26 | I80: =G80-H80 -> 233.74 | K80: =K79+I80-J80 -> 3419.9
B81: 9 | C81: 27 | E81: 财付通支付科技有限公司 | F81: 鼓西派出所停车场收入（2026.9.26） | G81: 345 | H81: 1.84 | I81: =G81-H81 -> 343.16 | K81: =K80+I81-J81 -> 3763.06
