Workbook
Name 采购合同号: OFFSET([1]采购合同!$E$6,,,COUNTA([1]采购合同!$E$6:$E$2000))
Name 发票: OFFSET([1]基础信息!$W$6,,,COUNTA([1]基础信息!$W$4:$W$50))
Name 工程项目: OFFSET([1]基础信息!$Q$6,,,COUNTA([1]基础信息!$Q$6:$Q$1000))
Name 供应商: OFFSET([1]基础信息!$U$6,,,COUNTA([1]基础信息!$U$4:$U$2000))
Name 客户: OFFSET([1]基础信息!$T$6,,,COUNTA([1]基础信息!$T$4:$T$2000))
Name 日期: OFFSET(收支登记表!$D$8,,,COUNTA(收支登记表!$D:$D))
Name 收入: [1]基础信息!$G$6:$G$100
Name 税率: [1]基础信息!$Y$6:$Y$20
Name 销售合同号: OFFSET([1]销售合同!$E$6,,,COUNTA([1]销售合同!$E$6:$E$2000))
Name 员工: OFFSET([1]基础信息!$N$6,,,COUNTA([1]基础信息!$N$4:$N$2000))
Name 账户: OFFSET([1]基础信息!$B$6,,,COUNTA([1]基础信息!$B$4:$B$100))
Name 支出: [1]基础信息!$I$6:$I$100

Sheet 收支登记表
D5: 收支登记 | J5: 收入总金额 | K5: 支出总金额 | L5: 收支盈亏 | N5: 客户查询 | O5: 王先生 | P5: 收款金额 | Q5: =SUMIF($O$8:$O$5161,O5,$J$8:$J$5161) -> 0
J6: =SUBTOTAL(9,J8:J5161) -> 8908368.2 | K6: =SUBTOTAL(9,K8:K5161) -> 8744363.7 | L6: =J6-K6 -> 164004.51 | N6: 供应商查询 | O6: 宁波凯瑞 | P6: 付款金额 | Q6: =SUMIF($P$8:$P$5161,$O$6,$K$8:$K$5161) -> 0
D7: 日期 | E7: 凭证号 | F7: 类别 | G7: 账户 | H7: 收支项目 | I7: 业务摘要 | J7: 收入金额 | K7: 支出金额 | L7: 账户结余 | M7: 项目名称 | N7: 负责人 | O7: 客户名称 | P7: 供应商名称 | Q7: 销售合同 | R7: 采购合同 | S7: 备注
D8: 45271 | F8: 支出 | G8: 九江银行 | H8: 个人借款-聂辉 | I8: 聂辉个人借款 | K8: -1668 | L8: =IFERROR(IF(G8="","",VLOOKUP($G8,[1]基础信息!$B:$C,2,FALSE)+SUMIF(G$8:G8,G8,J$8:J8)-SUMIF(G$8:G8,G8,K$8:K8)+SUMIFS([1]内部转账!$G:$G,[1]内部转账!$C:$C,"<="&$D8,[1]内部转账!$E:$E,$G8)-SUMIFS([1]内部转账!$G:$G,[1]内部转账!$C:$C,"<="&$D8,[1]内部转账!$F:$F,$G8)),"") -> 1668 | M8: 个人借款 | N8: 聂辉 | P8: 聂辉
D9: 45271 | F9: 支出 | G9: 九江银行 | K9: 240 | L9: =IFERROR(IF(G9="","",VLOOKUP($G9,[1]基础信息!$B:$C,2,FALSE)+SUMIF(G$8:G9,G9,J$8:J9)-SUMIF(G$8:G9,G9,K$8:K9)+SUMIFS([1]内部转账!$G:$G,[1]内部转账!$C:$C,"<="&$D9,[1]内部转账!$E:$E,$G9)-SUMIFS([1]内部转账!$G:$G,[1]内部转账!$C:$C,"<="&$D9,[1]内部转账!$F:$F,$G9)),"") -> 1428 | P9: 江西省城市建设高级技术学校
D10: 45281 | F10: 支出 | G10: 九江银行 | H10: 办公室-办公费 | I10: 入息 | K10: -0.08 | L10: =IFERROR(IF(G10="","",VLOOKUP($G10,[1]基础信息!$B:$C,2,FALSE)+SUMIF(G$8:G10,G10,J$8:J10)-SUMIF(G$8:G10,G10,K$8:K10)+SUMIFS([1]内部转账!$G:$G,[1]内部转账!$C:$C,"<="&$D10,[1]内部转账!$E:$E,$G10)-SUMIFS([1]内部转账!$G:$G,[1]内部转账!$C:$C,"<="&$D10,[1]内部转账!$F:$F,$G10)),"") -> 1428.08 | M10: 办公室
D11: 45308 | F11: 支出 | G11: 九江银行 | H11: 个人借款-聂辉 | I11: 聂辉交项目保证金 | K11: -500000 | L11: =IFERROR(IF(G11="","",VLOOKUP($G11,[1]基础信息!$B:$C,2,FALSE)+SUMIF(G$8:G11,G11,J$8:J11)-SUMIF(G$8:G11,G11,K$8:K11)+SUMIFS([1]内部转账!$G:$G,[1]内部转账!$C:$C,"<="&$D11,[1]内部转账!$E:$E,$G11)-SUMIFS([1]内部转账!$G:$G,[1]内部转账!$C:$C,"<="&$D11,[1]内部转账!$F:$F,$G11)),"") -> 501428.08 | M11: 个人借款 | N11: 聂辉 | P11: 聂辉
D12: 45308 | F12: 支出 | G12: 九江银行 | H12: 项目-保证金 | I12: 保证金 | K12: 500000 | L12: =IFERROR(IF(G12="","",VLOOKUP($G12,[1]基础信息!$B:$C,2,FALSE)+SUMIF(G$8:G12,G12,J$8:J12)-SUMIF(G$8:G12,G12,K$8:K12)+SUMIFS([1]内部转账!$G:$G,[1]内部转账!$C:$C,"<="&$D12,[1]内部转账!$E:$E,$G12)-SUMIFS([1]内部转账!$G:$G,[1]内部转账!$C:$C,"<="&$D12,[1]内部转账!$F:$F,$G12)),"") -> 1428.08 | M12: 九江欣埠置业有限公司
D13: 45308 | F13: 支出 | G13: 九江银行 | H13: 办公室-办公费 | I13: 对公跨行汇款费 | K13: 15 | L13: =IFERROR(IF(G13="","",VLOOKUP($G13,[1]基础信息!$B:$C,2,FALSE)+SUMIF(G$8:G13,G13,J$8:J13)-SUMIF(G$8:G13,G13,K$8:K13)+SUMIFS([1]内部转账!$G:$G,[1]内部转账!$C:$C,"<="&$D13,[1]内部转账!$E:$E,$G13)-SUMIFS([1]内部转账!$G:$G,[1]内部转账!$C:$C,"<="&$D13,[1]内部转账!$F:$F,$G13)),"") -> 1413.08 | M13: 隆世光伏/共青办公楼/德祥工地
D14: 45310 | F14: 支出 | G14: 九江银行 | H14: 个人借款-聂辉 | I14: 聂辉交项目保证金 | K14: -500000 | L14: =IFERROR(IF(G14="","",VLOOKUP($G14,[1]基础信息!$B:$C,2,FALSE)+SUMIF(G$8:G14,G14,J$8:J14)-SUMIF(G$8:G14,G14,K$8:K14)+SUMIFS([1]内部转账!$G:$G,[1]内部转账!$C:$C,"<="&$D14,[1]内部转账!$E:$E,$G14)-SUMIFS([1]内部转账!$G:$G,[1]内部转账!$C:$C,"<="&$D14,[1]内部转账!$F:$F,$G14)),"") -> 501413.08 | M14: 个人借款 | N14: 聂辉 | P14: 聂辉
D15: 45310 | F15: 支出 | G15: 九江银行 | H15: 项目-保证金 | I15: 保证金 | K15: 500000 | L15: =IFERROR(IF(G15="","",VLOOKUP($G15,[1]基础信息!$B:$C,2,FALSE)+SUMIF(G$8:G15,G15,J$8:J15)-SUMIF(G$8:G15,G15,K$8:K15)+SUMIFS([1]内部转账!$G:$G,[1]内部转账!$C:$C,"<="&$D15,[1]内部转账!$E:$E,$G15)-SUMIFS([1]内部转账!$G:$G,[1]内部转账!$C:$C,"<="&$D15,[1]内部转账!$F:$F,$G15)),"") -> 1413.08 | M15: 九江欣埠置业有限公司
D16: 45324 | F16: 收入 | G16: 九江银行 | H16: 工程款 | I16: 收到劳务费 | J16: 71000 | L16: =IFERROR(IF(G16="","",VLOOKUP($G16,[1]基础信息!$B:$C,2,FALSE)+SUMIF(G$8:G16,G16,J$8:J16)-SUMIF(G$8:G16,G16,K$8:K16)+SUMIFS([1]内部转账!$G:$G,[1]内部转账!$C:$C,"<="&$D16,[1]内部转账!$E:$E,$G16)-SUMIFS([1]内部转账!$G:$G,[1]内部转账!$C:$C,"<="&$D16,[1]内部转账!$F:$F,$G16)),"") -> 72413.08 | M16: 温州盛为装饰工程有限公司 | O16: 温州盛为装饰工程有限公司
D17: 45329 | F17: 支出 | G17: 九江银行 | H17: 项目-劳务费 | I17: 张小朋 | K17: 5000 | L17: =IFERROR(IF(G17="","",VLOOKUP($G17,[1]基础信息!$B:$C,2,FALSE)+SUMIF(G$8:G17,G17,J$8:J17)-SUMIF(G$8:G17,G17,K$8:K17)+SUMIFS([1]内部转账!$G:$G,[1]内部转账!$C:$C,"<="&$D17,[1]内部转账!$E:$E,$G17)-SUMIFS([1]内部转账!$G:$G,[1]内部转账!$C:$C,"<="&$D17,[1]内部转账!$F:$F,$G17)),"") -> 67413.08 | M17: 温州盛为装饰工程有限公司 | P17: 张小朋
D18: 45329 | F18: 支出 | G18: 九江银行 | H18: 项目-劳务费 | I18: 张亮亮 | K18: 10000 | L18: =IFERROR(IF(G18="","",VLOOKUP($G18,[1]基础信息!$B:$C,2,FALSE)+SUMIF(G$8:G18,G18,J$8:J18)-SUMIF(G$8:G18,G18,K$8:K18)+SUMIFS([1]内部转账!$G:$G,[1]内部转账!$C:$C,"<="&$D18,[1]内部转账!$E:$E,$G18)-SUMIFS([1]内部转账!$G:$G,[1]内部转账!$C:$C,"<="&$D18,[1]内部转账!$F:$F,$G18)),"") -> 57413.08 | M18: 温州盛为装饰工程有限公司
D19: 45329 | F19: 支出 | G19: 九江银行 | H19: 项目-劳务费 | I19: 刘洪文 | K19: 7000 | L19: =IFERROR(IF(G19="","",VLOOKUP($G19,[1]基础信息!$B:$C,2,FALSE)+SUMIF(G$8:G19,G19,J$8:J19)-SUMIF(G$8:G19,G19,K$8:K19)+SUMIFS([1]内部转账!$G:$G,[1]内部转账!$C:$C,"<="&$D19,[1]内部转账!$E:$E,$G19)-SUMIFS([1]内部转账!$G:$G,[1]内部转账!$C:$C,"<="&$D19,[1]内部转账!$F:$F,$G19)),"") -> 50413.08 | M19: 温州盛为装饰工程有限公司
D20: 45329 | F20: 支出 | G20: 九江银行 | H20: 项目-劳务费 | I20: 张国平 | K20: 10000 | L20: =IFERROR(IF(G20="","",VLOOKUP($G20,[1]基础信息!$B:$C,2,FALSE)+SUMIF(G$8:G20,G20,J$8:J20)-SUMIF(G$8:G20,G20,K$8:K20)+SUMIFS([1]内部转账!$G:$G,[1]内部转账!$C:$C,"<="&$D20,[1]内部转账!$E:$E,$G20)-SUMIFS([1]内部转账!$G:$G,[1]内部转账!$C:$C,"<="&$D20,[1]内部转账!$F:$F,$G20)),"") -> 40413.08 | M20: 温州盛为装饰工程有限公司
D21: 45329 | F21: 支出 | G21: 九江银行 | H21: 项目-劳务费 | I21: 彭雪亮 | K21: 5000 | L21: =IFERROR(IF(G21="","",VLOOKUP($G21,[1]基础信息!$B:$C,2,FALSE)+SUMIF(G$8:G21,G21,J$8:J21)-SUMIF(G$8:G21,G21,K$8:K21)+SUMIFS([1]内部转账!$G:$G,[1]内部转账!$C:$C,"<="&$D21,[1]内部转账!$E:$E,$G21)-SUMIFS([1]内部转账!$G:$G,[1]内部转账!$C:$C,"<="&$D21,[1]内部转账!$F:$F,$G21)),"") -> 35413.08 | M21: 温州盛为装饰工程有限公司
D22: 45329 | F22: 支出 | G22: 九江银行 | H22: 项目-劳务费 | I22: 张启红 | K22: 7000 | L22: =IFERROR(IF(G22="","",VLOOKUP($G22,[1]基础信息!$B:$C,2,FALSE)+SUMIF(G$8:G22,G22,J$8:J22)-SUMIF(G$8:G22,G22,K$8:K22)+SUMIFS([1]内部转账!$G:$G,[1]内部转账!$C:$C,"<="&$D22,[1]内部转账!$E:$E,$G22)-SUMIFS([1]内部转账!$G:$G,[1]内部转账!$C:$C,"<="&$D22,[1]内部转账!$F:$F,$G22)),"") -> 28413.08 | M22: 温州盛为装饰工程有限公司
D23: 45329 | F23: 支出 | G23: 九江银行 | H23: 办公室-工资 | I23: 聂辉 | K23: 10000 | L23: =IFERROR(IF(G23="","",VLOOKUP($G23,[1]基础信息!$B:$C,2,FALSE)+SUMIF(G$8:G23,G23,J$8:J23)-SUMIF(G$8:G23,G23,K$8:K23)+SUMIFS([1]内部转账!$G:$G,[1]内部转账!$C:$C,"<="&$D23,[1]内部转账!$E:$E,$G23)-SUMIFS([1]内部转账!$G:$G,[1]内部转账!$C:$C,"<="&$D23,[1]内部转账!$F:$F,$G23)),"") -> 18413.08 | M23: 温州盛为装饰工程有限公司 | N23: 聂辉
D24: 45372 | F24: 支出 | G24: 九江银行 | H24: 办公室-办公费 | I24: 入息 | K24: -5.15 | L24: =IFERROR(IF(G24="","",VLOOKUP($G24,[1]基础信息!$B:$C,2,FALSE)+SUMIF(G$8:G24,G24,J$8:J24)-SUMIF(G$8:G24,G24,K$8:K24)+SUMIFS([1]内部转账!$G:$G,[1]内部转账!$C:$C,"<="&$D24,[1]内部转账!$E:$E,$G24)-SUMIFS([1]内部转账!$G:$G,[1]内部转账!$C:$C,"<="&$D24,[1]内部转账!$F:$F,$G24)),"") -> 18418.23 | M24: 办公室
D25: 45404 | F25: 支出 | G25: 九江银行 | H25: 办公室-办公费 | I25: 解伟康的赔款 | K25: -4000 | L25: =IFERROR(IF(G25="","",VLOOKUP($G25,[1]基础信息!$B:$C,2,FALSE)+SUMIF(G$8:G25,G25,J$8:J25)-SUMIF(G$8:G25,G25,K$8:K25)+SUMIFS([1]内部转账!$G:$G,[1]内部转账!$C:$C,"<="&$D25,[1]内部转账!$E:$E,$G25)-SUMIFS([1]内部转账!$G:$G,[1]内部转账!$C:$C,"<="&$D25,[1]内部转账!$F:$F,$G25)),"") -> 22418.23 | M25: 温州盛为装饰工程有限公司 | P25: 中国平安财产保险股份有限公司广东分公司
D26: 45426 | F26: 支出 | G26: 九江银行 | H26: 项目-劳务费 | I26: 张传喜奖金 | K26: 9200 | L26: =IFERROR(IF(G26="","",VLOOKUP($G26,[1]基础信息!$B:$C,2,FALSE)+SUMIF(G$8:G26,G26,J$8:J26)-SUMIF(G$8:G26,G26,K$8:K26)+SUMIFS([1]内部转账!$G:$G,[1]内部转账!$C:$C,"<="&$D26,[1]内部转账!$E:$E,$G26)-SUMIFS([1]内部转账!$G:$G,[1]内部转账!$C:$C,"<="&$D26,[1]内部转账!$F:$F,$G26)),"") -> 13218.23 | M26: 温州盛为装饰工程有限公司
D27: 45426 | F27: 支出 | G27: 九江银行 | H27: 项目-劳务费 | I27: 张小朋奖金 | K27: 9500 | L27: =IFERROR(IF(G27="","",VLOOKUP($G27,[1]基础信息!$B:$C,2,FALSE)+SUMIF(G$8:G27,G27,J$8:J27)-SUMIF(G$8:G27,G27,K$8:K27)+SUMIFS([1]内部转账!$G:$G,[1]内部转账!$C:$C,"<="&$D27,[1]内部转账!$E:$E,$G27)-SUMIFS([1]内部转账!$G:$G,[1]内部转账!$C:$C,"<="&$D27,[1]内部转账!$F:$F,$G27)),"") -> 3718.23 | M27: 温州盛为装饰工程有限公司 | P27: 张小朋
D28: 45429 | F28: 支出 | G28: 九江银行 | H28: 项目-期间费 | I28: 支付保险费 | K28: 2310 | L28: =IFERROR(IF(G28="","",VLOOKUP($G28,[1]基础信息!$B:$C,2,FALSE)+SUMIF(G$8:G28,G28,J$8:J28)-SUMIF(G$8:G28,G28,K$8:K28)+SUMIFS([1]内部转账!$G:$G,[1]内部转账!$C:$C,"<="&$D28,[1]内部转账!$E:$E,$G28)-SUMIFS([1]内部转账!$G:$G,[1]内部转账!$C:$C,"<="&$D28,[1]内部转账!$F:$F,$G28)),"") -> 1408.23 | M28: 隆世光伏/共青办公楼/德祥工地 | P28: 中国平安财产保险股份有限公司广东分公司
D29: 45449 | F29: 收入 | G29: 九江银行 | H29: 工程款 | I29: 隆世光伏/共青办公楼/德祥工地工程款 | J29: 300000 | L29: =IFERROR(IF(G29="","",VLOOKUP($G29,[1]基础信息!$B:$C,2,FALSE)+SUMIF(G$8:G29,G29,J$8:J29)-SUMIF(G$8:G29,G29,K$8:K29)+SUMIFS([1]内部转账!$G:$G,[1]内部转账!$C:$C,"<="&$D29,[1]内部转账!$E:$E,$G29)-SUMIFS([1]内部转账!$G:$G,[1]内部转账!$C:$C,"<="&$D29,[1]内部转账!$F:$F,$G29)),"") -> 301408.23 | M29: 隆世光伏/共青办公楼/德祥工地 | O29: 共青农商行
D30: 45449 | F30: 支出 | G30: 九江银行 | H30: 项目-材料费 | I30: 付熊总材料费 | K30: 5146 | L30: =IFERROR(IF(G30="","",VLOOKUP($G30,[1]基础信息!$B:$C,2,FALSE)+SUMIF(G$8:G30,G30,J$8:J30)-SUMIF(G$8:G30,G30,K$8:K30)+SUMIFS([1]内部转账!$G:$G,[1]内部转账!$C:$C,"<="&$D30,[1]内部转账!$E:$E,$G30)-SUMIFS([1]内部转账!$G:$G,[1]内部转账!$C:$C,"<="&$D30,[1]内部转账!$F:$F,$G30)),"") -> 296262.23 | M30: 隆世光伏/共青办公楼/德祥工地 | P30: 德安小熊平价钢材店
D31: 45449 | F31: 支出 | G31: 九江银行 | H31: 项目-材料费 | I31: 付熊总材料费 | K31: -5146 | L31: =IFERROR(IF(G31="","",VLOOKUP($G31,[1]基础信息!$B:$C,2,FALSE)+SUMIF(G$8:G31,G31,J$8:J31)-SUMIF(G$8:G31,G31,K$8:K31)+SUMIFS([1]内部转账!$G:$G,[1]内部转账!$C:$C,"<="&$D31,[1]内部转账!$E:$E,$G31)-SUMIFS([1]内部转账!$G:$G,[1]内部转账!$C:$C,"<="&$D31,[1]内部转账!$F:$F,$G31)),"") -> 301408.23 | M31: 隆世光伏/共青办公楼/德祥工地 | P31: 德安小熊平价钢材店
D32: 45449 | F32: 支出 | G32: 九江银行 | H32: 项目-材料费 | I32: 付熊总材料费 | K32: 5146 | L32: =IFERROR(IF(G32="","",VLOOKUP($G32,[1]基础信息!$B:$C,2,FALSE)+SUMIF(G$8:G32,G32,J$8:J32)-SUMIF(G$8:G32,G32,K$8:K32)+SUMIFS([1]内部转账!$G:$G,[1]内部转账!$C:$C,"<="&$D32,[1]内部转账!$E:$E,$G32)-SUMIFS([1]内部转账!$G:$G,[1]内部转账!$C:$C,"<="&$D32,[1]内部转账!$F:$F,$G32)),"") -> 296262.23 | M32: 隆世光伏/共青办公楼/德祥工地 | P32: 德安小熊平价钢材店
D33: 45449 | F33: 支出 | G33: 九江银行 | H33: 项目-材料费 | I33: 付熊总材料费 | K33: 130000 | L33: =IFERROR(IF(G33="","",VLOOKUP($G33,[1]基础信息!$B:$C,2,FALSE)+SUMIF(G$8:G33,G33,J$8:J33)-SUMIF(G$8:G33,G33,K$8:K33)+SUMIFS([1]内部转账!$G:$G,[1]内部转账!$C:$C,"<="&$D33,[1]内部转账!$E:$E,$G33)-SUMIFS([1]内部转账!$G:$G,[1]内部转账!$C:$C,"<="&$D33,[1]内部转账!$F:$F,$G33)),"") -> 166262.23 | M33: 隆世光伏/共青办公楼/德祥工地 | P33: 德安小熊平价钢材店
D34: 45449 | F34: 支出 | G34: 九江银行 | H34: 项目-材料费 | I34: 付熊总材料费 | K34: 20000 | L34: =IFERROR(IF(G34="","",VLOOKUP($G34,[1]基础信息!$B:$C,2,FALSE)+SUMIF(G$8:G34,G34,J$8:J34)-SUMIF(G$8:G34,G34,K$8:K34)+SUMIFS([1]内部转账!$G:$G,[1]内部转账!$C:$C,"<="&$D34,[1]内部转账!$E:$E,$G34)-SUMIFS([1]内部转账!$G:$G,[1]内部转账!$C:$C,"<="&$D34,[1]内部转账!$F:$F,$G34)),"") -> 146262.23 | M34: 隆世光伏/共青办公楼/德祥工地 | P34: 德安小熊平价钢材店
D35: 45451 | F35: 支出 | G35: 九江银行 | H35: 项目-劳务费 | I35: 叶焰平 | K35: 5000 | L35: =IFERROR(IF(G35="","",VLOOKUP($G35,[1]基础信息!$B:$C,2,FALSE)+SUMIF(G$8:G35,G35,J$8:J35)-SUMIF(G$8:G35,G35,K$8:K35)+SUMIFS([1]内部转账!$G:$G,[1]内部转账!$C:$C,"<="&$D35,[1]内部转账!$E:$E,$G35)-SUMIFS([1]内部转账!$G:$G,[1]内部转账!$C:$C,"<="&$D35,[1]内部转账!$F:$F,$G35)),"") -> 141262.23 | M35: 隆世光伏/共青办公楼/德祥工地
D36: 45451 | F36: 支出 | G36: 九江银行 | H36: 项目-劳务费 | I36: 何正拥 | K36: 5000 | L36: =IFERROR(IF(G36="","",VLOOKUP($G36,[1]基础信息!$B:$C,2,FALSE)+SUMIF(G$8:G36,G36,J$8:J36)-SUMIF(G$8:G36,G36,K$8:K36)+SUMIFS([1]内部转账!$G:$G,[1]内部转账!$C:$C,"<="&$D36,[1]内部转账!$E:$E,$G36)-SUMIFS([1]内部转账!$G:$G,[1]内部转账!$C:$C,"<="&$D36,[1]内部转账!$F:$F,$G36)),"") -> 136262.23 | M36: 隆世光伏/共青办公楼/德祥工地
D37: 45451 | F37: 支出 | G37: 九江银行 | H37: 项目-劳务费 | I37: 李金平 | K37: 5000 | L37: =IFERROR(IF(G37="","",VLOOKUP($G37,[1]基础信息!$B:$C,2,FALSE)+SUMIF(G$8:G37,G37,J$8:J37)-SUMIF(G$8:G37,G37,K$8:K37)+SUMIFS([1]内部转账!$G:$G,[1]内部转账!$C:$C,"<="&$D37,[1]内部转账!$E:$E,$G37)-SUMIFS([1]内部转账!$G:$G,[1]内部转账!$C:$C,"<="&$D37,[1]内部转账!$F:$F,$G37)),"") -> 131262.23 | M37: 隆世光伏/共青办公楼/德祥工地
D38: 45451 | F38: 支出 | G38: 九江银行 | H38: 项目-劳务费 | I38: 李金平 | K38: -5000 | L38: =IFERROR(IF(G38="","",VLOOKUP($G38,[1]基础信息!$B:$C,2,FALSE)+SUMIF(G$8:G38,G38,J$8:J38)-SUMIF(G$8:G38,G38,K$8:K38)+SUMIFS([1]内部转账!$G:$G,[1]内部转账!$C:$C,"<="&$D38,[1]内部转账!$E:$E,$G38)-SUMIFS([1]内部转账!$G:$G,[1]内部转账!$C:$C,"<="&$D38,[1]内部转账!$F:$F,$G38)),"") -> 136262.23 | M38: 隆世光伏/共青办公楼/德祥工地
D39: 45451 | F39: 支出 | G39: 九江银行 | H39: 项目-劳务费 | I39: 吴志刚 | K39: 5000 | L39: =IFERROR(IF(G39="","",VLOOKUP($G39,[1]基础信息!$B:$C,2,FALSE)+SUMIF(G$8:G39,G39,J$8:J39)-SUMIF(G$8:G39,G39,K$8:K39)+SUMIFS([1]内部转账!$G:$G,[1]内部转账!$C:$C,"<="&$D39,[1]内部转账!$E:$E,$G39)-SUMIFS([1]内部转账!$G:$G,[1]内部转账!$C:$C,"<="&$D39,[1]内部转账!$F:$F,$G39)),"") -> 131262.23 | M39: 隆世光伏/共青办公楼/德祥工地
D40: 45451 | F40: 支出 | G40: 九江银行 | H40: 项目-劳务费 | I40: 成峰 | K40: 5000 | L40: =IFERROR(IF(G40="","",VLOOKUP($G40,[1]基础信息!$B:$C,2,FALSE)+SUMIF(G$8:G40,G40,J$8:J40)-SUMIF(G$8:G40,G40,K$8:K40)+SUMIFS([1]内部转账!$G:$G,[1]内部转账!$C:$C,"<="&$D40,[1]内部转账!$E:$E,$G40)-SUMIFS([1]内部转账!$G:$G,[1]内部转账!$C:$C,"<="&$D40,[1]内部转账!$F:$F,$G40)),"") -> 126262.23 | M40: 隆世光伏/共青办公楼/德祥工地
D41: 45451 | F41: 支出 | G41: 九江银行 | H41: 项目-劳务费 | I41: 何正辉 | K41: 5000 | L41: =IFERROR(IF(G41="","",VLOOKUP($G41,[1]基础信息!$B:$C,2,FALSE)+SUMIF(G$8:G41,G41,J$8:J41)-SUMIF(G$8:G41,G41,K$8:K41)+SUMIFS([1]内部转账!$G:$G,[1]内部转账!$C:$C,"<="&$D41,[1]内部转账!$E:$E,$G41)-SUMIFS([1]内部转账!$G:$G,[1]内部转账!$C:$C,"<="&$D41,[1]内部转账!$F:$F,$G41)),"") -> 121262.23 | M41: 隆世光伏/共青办公楼/德祥工地
D42: 45451 | F42: 支出 | G42: 九江银行 | H42: 项目-劳务费 | I42: 梅时金 | K42: 5000 | L42: =IFERROR(IF(G42="","",VLOOKUP($G42,[1]基础信息!$B:$C,2,FALSE)+SUMIF(G$8:G42,G42,J$8:J42)-SUMIF(G$8:G42,G42,K$8:K42)+SUMIFS([1]内部转账!$G:$G,[1]内部转账!$C:$C,"<="&$D42,[1]内部转账!$E:$E,$G42)-SUMIFS([1]内部转账!$G:$G,[1]内部转账!$C:$C,"<="&$D42,[1]内部转账!$F:$F,$G42)),"") -> 116262.23 | M42: 隆世光伏/共青办公楼/德祥工地
D43: 45451 | F43: 支出 | G43: 九江银行 | H43: 项目-劳务费 | I43: 余水明 | K43: 1500 | L43: =IFERROR(IF(G43="","",VLOOKUP($G43,[1]基础信息!$B:$C,2,FALSE)+SUMIF(G$8:G43,G43,J$8:J43)-SUMIF(G$8:G43,G43,K$8:K43)+SUMIFS([1]内部转账!$G:$G,[1]内部转账!$C:$C,"<="&$D43,[1]内部转账!$E:$E,$G43)-SUMIFS([1]内部转账!$G:$G,[1]内部转账!$C:$C,"<="&$D43,[1]内部转账!$F:$F,$G43)),"") -> 114762.23 | M43: 隆世光伏/共青办公楼/德祥工地
D44: 45451 | F44: 支出 | G44: 九江银行 | H44: 项目-劳务费 | I44: 李银华 | K44: 5000 | L44: =IFERROR(IF(G44="","",VLOOKUP($G44,[1]基础信息!$B:$C,2,FALSE)+SUMIF(G$8:G44,G44,J$8:J44)-SUMIF(G$8:G44,G44,K$8:K44)+SUMIFS([1]内部转账!$G:$G,[1]内部转账!$C:$C,"<="&$D44,[1]内部转账!$E:$E,$G44)-SUMIFS([1]内部转账!$G:$G,[1]内部转账!$C:$C,"<="&$D44,[1]内部转账!$F:$F,$G44)),"") -> 109762.23 | M44: 隆世光伏/共青办公楼/德祥工地
D45: 45451 | F45: 支出 | G45: 九江银行 | H45: 项目-劳务费 | I45: 张小朋 | K45: 5000 | L45: =IFERROR(IF(G45="","",VLOOKUP($G45,[1]基础信息!$B:$C,2,FALSE)+SUMIF(G$8:G45,G45,J$8:J45)-SUMIF(G$8:G45,G45,K$8:K45)+SUMIFS([1]内部转账!$G:$G,[1]内部转账!$C:$C,"<="&$D45,[1]内部转账!$E:$E,$G45)-SUMIFS([1]内部转账!$G:$G,[1]内部转账!$C:$C,"<="&$D45,[1]内部转账!$F:$F,$G45)),"") -> 104762.23 | M45: 隆世光伏/共青办公楼/德祥工地 | P45: 张小朋
D46: 45451 | F46: 支出 | G46: 九江银行 | H46: 项目-劳务费 | I46: 邓付贞 | K46: 5000 | L46: =IFERROR(IF(G46="","",VLOOKUP($G46,[1]基础信息!$B:$C,2,FALSE)+SUMIF(G$8:G46,G46,J$8:J46)-SUMIF(G$8:G46,G46,K$8:K46)+SUMIFS([1]内部转账!$G:$G,[1]内部转账!$C:$C,"<="&$D46,[1]内部转账!$E:$E,$G46)-SUMIFS([1]内部转账!$G:$G,[1]内部转账!$C:$C,"<="&$D46,[1]内部转账!$F:$F,$G46)),"") -> 99762.23 | M46: 隆世光伏/共青办公楼/德祥工地
D47: 45451 | F47: 支出 | G47: 九江银行 | H47: 项目-劳务费 | I47: 邓石平 | K47: 5000 | L47: =IFERROR(IF(G47="","",VLOOKUP($G47,[1]基础信息!$B:$C,2,FALSE)+SUMIF(G$8:G47,G47,J$8:J47)-SUMIF(G$8:G47,G47,K$8:K47)+SUMIFS([1]内部转账!$G:$G,[1]内部转账!$C:$C,"<="&$D47,[1]内部转账!$E:$E,$G47)-SUMIFS([1]内部转账!$G:$G,[1]内部转账!$C:$C,"<="&$D47,[1]内部转账!$F:$F,$G47)),"") -> 94762.23 | M47: 隆世光伏/共青办公楼/德祥工地
D48: 45451 | F48: 支出 | G48: 九江银行 | H48: 项目-劳务费 | I48: 雷有才 | K48: 5000 | L48: =IFERROR(IF(G48="","",VLOOKUP($G48,[1]基础信息!$B:$C,2,FALSE)+SUMIF(G$8:G48,G48,J$8:J48)-SUMIF(G$8:G48,G48,K$8:K48)+SUMIFS([1]内部转账!$G:$G,[1]内部转账!$C:$C,"<="&$D48,[1]内部转账!$E:$E,$G48)-SUMIFS([1]内部转账!$G:$G,[1]内部转账!$C:$C,"<="&$D48,[1]内部转账!$F:$F,$G48)),"") -> 89762.23 | M48: 隆世光伏/共青办公楼/德祥工地
D49: 45451 | F49: 支出 | G49: 九江银行 | H49: 项目-劳务费 | I49: 雷有才 | K49: -5000 | L49: =IFERROR(IF(G49="","",VLOOKUP($G49,[1]基础信息!$B:$C,2,FALSE)+SUMIF(G$8:G49,G49,J$8:J49)-SUMIF(G$8:G49,G49,K$8:K49)+SUMIFS([1]内部转账!$G:$G,[1]内部转账!$C:$C,"<="&$D49,[1]内部转账!$E:$E,$G49)-SUMIFS([1]内部转账!$G:$G,[1]内部转账!$C:$C,"<="&$D49,[1]内部转账!$F:$F,$G49)),"") -> 94762.23 | M49: 隆世光伏/共青办公楼/德祥工地
D50: 45451 | F50: 支出 | G50: 九江银行 | H50: 项目-劳务费 | I50: 王刚 | K50: 3000 | L50: =IFERROR(IF(G50="","",VLOOKUP($G50,[1]基础信息!$B:$C,2,FALSE)+SUMIF(G$8:G50,G50,J$8:J50)-SUMIF(G$8:G50,G50,K$8:K50)+SUMIFS([1]内部转账!$G:$G,[1]内部转账!$C:$C,"<="&$D50,[1]内部转账!$E:$E,$G50)-SUMIFS([1]内部转账!$G:$G,[1]内部转账!$C:$C,"<="&$D50,[1]内部转账!$F:$F,$G50)),"") -> 91762.23 | M50: 隆世光伏/共青办公楼/德祥工地
D51: 45451 | F51: 支出 | G51: 九江银行 | H51: 项目-劳务费 | I51: 金李平 | K51: 5000 | L51: =IFERROR(IF(G51="","",VLOOKUP($G51,[1]基础信息!$B:$C,2,FALSE)+SUMIF(G$8:G51,G51,J$8:J51)-SUMIF(G$8:G51,G51,K$8:K51)+SUMIFS([1]内部转账!$G:$G,[1]内部转账!$C:$C,"<="&$D51,[1]内部转账!$E:$E,$G51)-SUMIFS([1]内部转账!$G:$G,[1]内部转账!$C:$C,"<="&$D51,[1]内部转账!$F:$F,$G51)),"") -> 86762.23 | M51: 隆世光伏/共青办公楼/德祥工地
D52: 45454 | F52: 支出 | G52: 九江银行 | H52: 项目-材料费 | I52: 消防材料款 | K52: 21926 | L52: =IFERROR(IF(G52="","",VLOOKUP($G52,[1]基础信息!$B:$C,2,FALSE)+SUMIF(G$8:G52,G52,J$8:J52)-SUMIF(G$8:G52,G52,K$8:K52)+SUMIFS([1]内部转账!$G:$G,[1]内部转账!$C:$C,"<="&$D52,[1]内部转账!$E:$E,$G52)-SUMIFS([1]内部转账!$G:$G,[1]内部转账!$C:$C,"<="&$D52,[1]内部转账!$F:$F,$G52)),"") -> 64836.23 | M52: 隆世光伏/共青办公楼/德祥工地 | P52: 四川久远智能消防设备有限责任公司
D53: 45455 | F53: 支出 | G53: 九江银行 | H53: 项目-材料费 | I53: 付熊总材料费 | K53: 17500 | L53: =IFERROR(IF(G53="","",VLOOKUP($G53,[1]基础信息!$B:$C,2,FALSE)+SUMIF(G$8:G53,G53,J$8:J53)-SUMIF(G$8:G53,G53,K$8:K53)+SUMIFS([1]内部转账!$G:$G,[1]内部转账!$C:$C,"<="&$D53,[1]内部转账!$E:$E,$G53)-SUMIFS([1]内部转账!$G:$G,[1]内部转账!$C:$C,"<="&$D53,[1]内部转账!$F:$F,$G53)),"") -> 47336.23 | M53: 隆世光伏/共青办公楼/德祥工地 | P53: 德安小熊平价钢材店
D54: 45457 | F54: 支出 | G54: 九江银行 | H54: 项目-劳务费 | I54: 余水明 | K54: 15000 | L54: =IFERROR(IF(G54="","",VLOOKUP($G54,[1]基础信息!$B:$C,2,FALSE)+SUMIF(G$8:G54,G54,J$8:J54)-SUMIF(G$8:G54,G54,K$8:K54)+SUMIFS([1]内部转账!$G:$G,[1]内部转账!$C:$C,"<="&$D54,[1]内部转账!$E:$E,$G54)-SUMIFS([1]内部转账!$G:$G,[1]内部转账!$C:$C,"<="&$D54,[1]内部转账!$F:$F,$G54)),"") -> 32336.23 | M54: 隆世光伏/共青办公楼/德祥工地
D55: 45458 | F55: 支出 | G55: 九江银行 | H55: 项目-材料费 | I55: 付熊总材料费 | K55: 3432 | L55: =IFERROR(IF(G55="","",VLOOKUP($G55,[1]基础信息!$B:$C,2,FALSE)+SUMIF(G$8:G55,G55,J$8:J55)-SUMIF(G$8:G55,G55,K$8:K55)+SUMIFS([1]内部转账!$G:$G,[1]内部转账!$C:$C,"<="&$D55,[1]内部转账!$E:$E,$G55)-SUMIFS([1]内部转账!$G:$G,[1]内部转账!$C:$C,"<="&$D55,[1]内部转账!$F:$F,$G55)),"") -> 28904.23 | M55: 隆世光伏/共青办公楼/德祥工地 | P55: 德安小熊平价钢材店
D56: 45462 | F56: 支出 | G56: 九江银行 | H56: 项目-材料费 | I56: 付熊总材料费 | K56: 2850 | L56: =IFERROR(IF(G56="","",VLOOKUP($G56,[1]基础信息!$B:$C,2,FALSE)+SUMIF(G$8:G56,G56,J$8:J56)-SUMIF(G$8:G56,G56,K$8:K56)+SUMIFS([1]内部转账!$G:$G,[1]内部转账!$C:$C,"<="&$D56,[1]内部转账!$E:$E,$G56)-SUMIFS([1]内部转账!$G:$G,[1]内部转账!$C:$C,"<="&$D56,[1]内部转账!$F:$F,$G56)),"") -> 26054.23 | M56: 隆世光伏/共青办公楼/德祥工地 | P56: 德安小熊平价钢材店
D57: 45464 | F57: 支出 | G57: 九江银行 | H57: 办公室-办公费 | I57: 入息 | K57: -8.48 | L57: =IFERROR(IF(G57="","",VLOOKUP($G57,[1]基础信息!$B:$C,2,FALSE)+SUMIF(G$8:G57,G57,J$8:J57)-SUMIF(G$8:G57,G57,K$8:K57)+SUMIFS([1]内部转账!$G:$G,[1]内部转账!$C:$C,"<="&$D57,[1]内部转账!$E:$E,$G57)-SUMIFS([1]内部转账!$G:$G,[1]内部转账!$C:$C,"<="&$D57,[1]内部转账!$F:$F,$G57)),"") -> 26062.71 | M57: 办公室
D58: 45464 | F58: 支出 | G58: 九江银行 | H58: 项目-期间费 | I58: 员工培训费 | K58: 3500 | L58: =IFERROR(IF(G58="","",VLOOKUP($G58,[1]基础信息!$B:$C,2,FALSE)+SUMIF(G$8:G58,G58,J$8:J58)-SUMIF(G$8:G58,G58,K$8:K58)+SUMIFS([1]内部转账!$G:$G,[1]内部转账!$C:$C,"<="&$D58,[1]内部转账!$E:$E,$G58)-SUMIFS([1]内部转账!$G:$G,[1]内部转账!$C:$C,"<="&$D58,[1]内部转账!$F:$F,$G58)),"") -> 22562.71 | M58: 隆世光伏/共青办公楼/德祥工地 | P58: 江西省建安企服通商务咨询有限公司
D59: 45464 | F59: 支出 | G59: 九江银行 | H59: 项目-期间费 | I59: 员工培训费 | K59: -3500 | L59: =IFERROR(IF(G59="","",VLOOKUP($G59,[1]基础信息!$B:$C,2,FALSE)+SUMIF(G$8:G59,G59,J$8:J59)-SUMIF(G$8:G59,G59,K$8:K59)+SUMIFS([1]内部转账!$G:$G,[1]内部转账!$C:$C,"<="&$D59,[1]内部转账!$E:$E,$G59)-SUMIFS([1]内部转账!$G:$G,[1]内部转账!$C:$C,"<="&$D59,[1]内部转账!$F:$F,$G59)),"") -> 26062.71 | M59: 隆世光伏/共青办公楼/德祥工地 | P59: 江西省建安企服通商务咨询有限公司
D60: 45464 | F60: 支出 | G60: 九江银行 | H60: 项目-材料费 | I60: 付熊总材料费 | K60: 4818 | L60: =IFERROR(IF(G60="","",VLOOKUP($G60,[1]基础信息!$B:$C,2,FALSE)+SUMIF(G$8:G60,G60,J$8:J60)-SUMIF(G$8:G60,G60,K$8:K60)+SUMIFS([1]内部转账!$G:$G,[1]内部转账!$C:$C,"<="&$D60,[1]内部转账!$E:$E,$G60)-SUMIFS([1]内部转账!$G:$G,[1]内部转账!$C:$C,"<="&$D60,[1]内部转账!$F:$F,$G60)),"") -> 21244.71 | M60: 隆世光伏/共青办公楼/德祥工地 | P60: 德安小熊平价钢材店
D61: 45464 | F61: 支出 | G61: 九江银行 | H61: 项目-期间费 | I61: 员工培训费 | K61: 3500 | L61: =IFERROR(IF(G61="","",VLOOKUP($G61,[1]基础信息!$B:$C,2,FALSE)+SUMIF(G$8:G61,G61,J$8:J61)-SUMIF(G$8:G61,G61,K$8:K61)+SUMIFS([1]内部转账!$G:$G,[1]内部转账!$C:$C,"<="&$D61,[1]内部转账!$E:$E,$G61)-SUMIFS([1]内部转账!$G:$G,[1]内部转账!$C:$C,"<="&$D61,[1]内部转账!$F:$F,$G61)),"") -> 17744.71 | M61: 隆世光伏/共青办公楼/德祥工地 | P61: 江西省建安企服通商务咨询有限公司
D62: 45471 | F62: 支出 | G62: 九江银行 | H62: 项目-劳务费 | I62: 雷有才 | K62: 6000 | L62: =IFERROR(IF(G62="","",VLOOKUP($G62,[1]基础信息!$B:$C,2,FALSE)+SUMIF(G$8:G62,G62,J$8:J62)-SUMIF(G$8:G62,G62,K$8:K62)+SUMIFS([1]内部转账!$G:$G,[1]内部转账!$C:$C,"<="&$D62,[1]内部转账!$E:$E,$G62)-SUMIFS([1]内部转账!$G:$G,[1]内部转账!$C:$C,"<="&$D62,[1]内部转账!$F:$F,$G62)),"") -> 11744.71 | M62: 隆世光伏/共青办公楼/德祥工地
D63: 45471 | F63: 支出 | G63: 九江银行 | H63: 项目-劳务费 | I63: 雷有才 | K63: -6000 | L63: =IFERROR(IF(G63="","",VLOOKUP($G63,[1]基础信息!$B:$C,2,FALSE)+SUMIF(G$8:G63,G63,J$8:J63)-SUMIF(G$8:G63,G63,K$8:K63)+SUMIFS([1]内部转账!$G:$G,[1]内部转账!$C:$C,"<="&$D63,[1]内部转账!$E:$E,$G63)-SUMIFS([1]内部转账!$G:$G,[1]内部转账!$C:$C,"<="&$D63,[1]内部转账!$F:$F,$G63)),"") -> 17744.71 | M63: 隆世光伏/共青办公楼/德祥工地
D64: 45471 | F64: 支出 | G64: 九江银行 | H64: 项目-劳务费 | I64: 雷有才 | K64: 5000 | L64: =IFERROR(IF(G64="","",VLOOKUP($G64,[1]基础信息!$B:$C,2,FALSE)+SUMIF(G$8:G64,G64,J$8:J64)-SUMIF(G$8:G64,G64,K$8:K64)+SUMIFS([1]内部转账!$G:$G,[1]内部转账!$C:$C,"<="&$D64,[1]内部转账!$E:$E,$G64)-SUMIFS([1]内部转账!$G:$G,[1]内部转账!$C:$C,"<="&$D64,[1]内部转账!$F:$F,$G64)),"") -> 12744.71 | M64: 隆世光伏/共青办公楼/德祥工地
D65: 45473 | F65: 支出 | G65: 九江银行 | H65: 项目-材料费 | I65: 付熊总材料费 | K65: 5990 | L65: =IFERROR(IF(G65="","",VLOOKUP($G65,[1]基础信息!$B:$C,2,FALSE)+SUMIF(G$8:G65,G65,J$8:J65)-SUMIF(G$8:G65,G65,K$8:K65)+SUMIFS([1]内部转账!$G:$G,[1]内部转账!$C:$C,"<="&$D65,[1]内部转账!$E:$E,$G65)-SUMIFS([1]内部转账!$G:$G,[1]内部转账!$C:$C,"<="&$D65,[1]内部转账!$F:$F,$G65)),"") -> 6754.71 | M65: 隆世光伏/共青办公楼/德祥工地 | P65: 德安小熊平价钢材店
D66: 45484 | F66: 支出 | G66: 九江银行 | H66: 税款 | I66: 缴税款 | K66: 971.01 | L66: =IFERROR(IF(G66="","",VLOOKUP($G66,[1]基础信息!$B:$C,2,FALSE)+SUMIF(G$8:G66,G66,J$8:J66)-SUMIF(G$8:G66,G66,K$8:K66)+SUMIFS([1]内部转账!$G:$G,[1]内部转账!$C:$C,"<="&$D66,[1]内部转账!$E:$E,$G66)-SUMIFS([1]内部转账!$G:$G,[1]内部转账!$C:$C,"<="&$D66,[1]内部转账!$F:$F,$G66)),"") -> 5783.7 | M66: 隆世光伏/共青办公楼/德祥工地
D67: 45485 | F67: 支出 | G67: 九江银行 | H67: 项目-材料费 | I67: 付熊总材料费 | K67: 4700 | L67: =IFERROR(IF(G67="","",VLOOKUP($G67,[1]基础信息!$B:$C,2,FALSE)+SUMIF(G$8:G67,G67,J$8:J67)-SUMIF(G$8:G67,G67,K$8:K67)+SUMIFS([1]内部转账!$G:$G,[1]内部转账!$C:$C,"<="&$D67,[1]内部转账!$E:$E,$G67)-SUMIFS([1]内部转账!$G:$G,[1]内部转账!$C:$C,"<="&$D67,[1]内部转账!$F:$F,$G67)),"") -> 1083.7 | M67: 隆世光伏/共青办公楼/德祥工地 | P67: 德安小熊平价钢材店
D68: 45485 | F68: 支出 | G68: 九江银行 | H68: 项目-劳务费 | I68: 刘海 | K68: 1000 | L68: =IFERROR(IF(G68="","",VLOOKUP($G68,[1]基础信息!$B:$C,2,FALSE)+SUMIF(G$8:G68,G68,J$8:J68)-SUMIF(G$8:G68,G68,K$8:K68)+SUMIFS([1]内部转账!$G:$G,[1]内部转账!$C:$C,"<="&$D68,[1]内部转账!$E:$E,$G68)-SUMIFS([1]内部转账!$G:$G,[1]内部转账!$C:$C,"<="&$D68,[1]内部转账!$F:$F,$G68)),"") -> 83.7 | M68: 隆世光伏/共青办公楼/德祥工地
D69: 45509 | F69: 支出 | G69: 九江银行 | H69: 个人借款-聂辉 | I69: 聂辉个人借款 | K69: -5000 | L69: =IFERROR(IF(G69="","",VLOOKUP($G69,[1]基础信息!$B:$C,2,FALSE)+SUMIF(G$8:G69,G69,J$8:J69)-SUMIF(G$8:G69,G69,K$8:K69)+SUMIFS([1]内部转账!$G:$G,[1]内部转账!$C:$C,"<="&$D69,[1]内部转账!$E:$E,$G69)-SUMIFS([1]内部转账!$G:$G,[1]内部转账!$C:$C,"<="&$D69,[1]内部转账!$F:$F,$G69)),"") -> 5083.7 | M69: 个人借款 | N69: 聂辉 | P69: 聂辉
D70: 45509 | F70: 支出 | G70: 九江银行 | H70: 项目-劳务费 | I70: 王小刚 | K70: 2800 | L70: =IFERROR(IF(G70="","",VLOOKUP($G70,[1]基础信息!$B:$C,2,FALSE)+SUMIF(G$8:G70,G70,J$8:J70)-SUMIF(G$8:G70,G70,K$8:K70)+SUMIFS([1]内部转账!$G:$G,[1]内部转账!$C:$C,"<="&$D70,[1]内部转账!$E:$E,$G70)-SUMIFS([1]内部转账!$G:$G,[1]内部转账!$C:$C,"<="&$D70,[1]内部转账!$F:$F,$G70)),"") -> 2283.7 | M70: 隆世光伏/共青办公楼/德祥工地
D71: 45523 | F71: 支出 | G71: 九江银行 | H71: 项目-保证金 | I71: 退回保证金 | K71: -1000000 | L71: =IFERROR(IF(G71="","",VLOOKUP($G71,[1]基础信息!$B:$C,2,FALSE)+SUMIF(G$8:G71,G71,J$8:J71)-SUMIF(G$8:G71,G71,K$8:K71)+SUMIFS([1]内部转账!$G:$G,[1]内部转账!$C:$C,"<="&$D71,[1]内部转账!$E:$E,$G71)-SUMIFS([1]内部转账!$G:$G,[1]内部转账!$C:$C,"<="&$D71,[1]内部转账!$F:$F,$G71)),"") -> 1002283.7 | M71: 九江欣埠置业有限公司
D72: 45523 | F72: 支出 | G72: 九江银行 | H72: 个人借款-聂辉 | I72: 还聂辉个人借款（剩余800000） | K72: 200000 | L72: =IFERROR(IF(G72="","",VLOOKUP($G72,[1]基础信息!$B:$C,2,FALSE)+SUMIF(G$8:G72,G72,J$8:J72)-SUMIF(G$8:G72,G72,K$8:K72)+SUMIFS([1]内部转账!$G:$G,[1]内部转账!$C:$C,"<="&$D72,[1]内部转账!$E:$E,$G72)-SUMIFS([1]内部转账!$G:$G,[1]内部转账!$C:$C,"<="&$D72,[1]内部转账!$F:$F,$G72)),"") -> 802283.7 | M72: 个人借款 | N72: 聂辉 | P72: 聂辉
D73: 45524 | F73: 支出 | G73: 九江银行 | H73: 项目-材料费 | I73: 消防材料款 | K73: 1789 | L73: =IFERROR(IF(G73="","",VLOOKUP($G73,[1]基础信息!$B:$C,2,FALSE)+SUMIF(G$8:G73,G73,J$8:J73)-SUMIF(G$8:G73,G73,K$8:K73)+SUMIFS([1]内部转账!$G:$G,[1]内部转账!$C:$C,"<="&$D73,[1]内部转账!$E:$E,$G73)-SUMIFS([1]内部转账!$G:$G,[1]内部转账!$C:$C,"<="&$D73,[1]内部转账!$F:$F,$G73)),"") -> 800494.7 | M73: 隆世光伏/共青办公楼/德祥工地 | P73: 四川久远智能消防设备有限责任公司
D74: 45524 | F74: 支出 | G74: 九江银行 | H74: 个人借款-聂辉 | I74: 还聂辉个人借款（剩余310000） | K74: 490000 | L74: =IFERROR(IF(G74="","",VLOOKUP($G74,[1]基础信息!$B:$C,2,FALSE)+SUMIF(G$8:G74,G74,J$8:J74)-SUMIF(G$8:G74,G74,K$8:K74)+SUMIFS([1]内部转账!$G:$G,[1]内部转账!$C:$C,"<="&$D74,[1]内部转账!$E:$E,$G74)-SUMIFS([1]内部转账!$G:$G,[1]内部转账!$C:$C,"<="&$D74,[1]内部转账!$F:$F,$G74)),"") -> 310494.7 | M74: 个人借款 | N74: 聂辉 | P74: 聂辉
D75: 45530 | F75: 支出 | G75: 九江银行 | H75: 项目-材料费 | I75: 消防材料款 | K75: 15000 | L75: =IFERROR(IF(G75="","",VLOOKUP($G75,[1]基础信息!$B:$C,2,FALSE)+SUMIF(G$8:G75,G75,J$8:J75)-SUMIF(G$8:G75,G75,K$8:K75)+SUMIFS([1]内部转账!$G:$G,[1]内部转账!$C:$C,"<="&$D75,[1]内部转账!$E:$E,$G75)-SUMIFS([1]内部转账!$G:$G,[1]内部转账!$C:$C,"<="&$D75,[1]内部转账!$F:$F,$G75)),"") -> 295494.7 | M75: 隆世光伏/共青办公楼/德祥工地 | P75: 西湖区荣晟消防设备营销中心
D76: 45530 | F76: 支出 | G76: 九江银行 | H76: 个人借款-聂辉 | I76: 还聂辉个人借款（剩余215000） | K76: 95000 | L76: =IFERROR(IF(G76="","",VLOOKUP($G76,[1]基础信息!$B:$C,2,FALSE)+SUMIF(G$8:G76,G76,J$8:J76)-SUMIF(G$8:G76,G76,K$8:K76)+SUMIFS([1]内部转账!$G:$G,[1]内部转账!$C:$C,"<="&$D76,[1]内部转账!$E:$E,$G76)-SUMIFS([1]内部转账!$G:$G,[1]内部转账!$C:$C,"<="&$D76,[1]内部转账!$F:$F,$G76)),"") -> 200494.7 | M76: 个人借款 | N76: 聂辉 | P76: 聂辉
D77: 45531 | F77: 支出 | G77: 九江银行 | H77: 项目-劳务费 | I77: 吴志刚 | K77: 10000 | L77: =IFERROR(IF(G77="","",VLOOKUP($G77,[1]基础信息!$B:$C,2,FALSE)+SUMIF(G$8:G77,G77,J$8:J77)-SUMIF(G$8:G77,G77,K$8:K77)+SUMIFS([1]内部转账!$G:$G,[1]内部转账!$C:$C,"<="&$D77,[1]内部转账!$E:$E,$G77)-SUMIFS([1]内部转账!$G:$G,[1]内部转账!$C:$C,"<="&$D77,[1]内部转账!$F:$F,$G77)),"") -> 190494.7 | M77: 隆世光伏/共青办公楼/德祥工地
D78: 45531 | F78: 支出 | G78: 九江银行 | H78: 项目-劳务费 | I78: 叶焰平 | K78: 10000 | L78: =IFERROR(IF(G78="","",VLOOKUP($G78,[1]基础信息!$B:$C,2,FALSE)+SUMIF(G$8:G78,G78,J$8:J78)-SUMIF(G$8:G78,G78,K$8:K78)+SUMIFS([1]内部转账!$G:$G,[1]内部转账!$C:$C,"<="&$D78,[1]内部转账!$E:$E,$G78)-SUMIFS([1]内部转账!$G:$G,[1]内部转账!$C:$C,"<="&$D78,[1]内部转账!$F:$F,$G78)),"") -> 180494.7 | M78: 隆世光伏/共青办公楼/德祥工地
D79: 45531 | F79: 支出 | G79: 九江银行 | H79: 项目-劳务费 | I79: 李银华 | K79: 10000 | L79: =IFERROR(IF(G79="","",VLOOKUP($G79,[1]基础信息!$B:$C,2,FALSE)+SUMIF(G$8:G79,G79,J$8:J79)-SUMIF(G$8:G79,G79,K$8:K79)+SUMIFS([1]内部转账!$G:$G,[1]内部转账!$C:$C,"<="&$D79,[1]内部转账!$E:$E,$G79)-SUMIFS([1]内部转账!$G:$G,[1]内部转账!$C:$C,"<="&$D79,[1]内部转账!$F:$F,$G79)),"") -> 170494.7 | M79: 隆世光伏/共青办公楼/德祥工地
D80: 45531 | F80: 支出 | G80: 九江银行 | H80: 项目-劳务费 | I80: 雷有才 | K80: 5000 | L80: =IFERROR(IF(G80="","",VLOOKUP($G80,[1]基础信息!$B:$C,2,FALSE)+SUMIF(G$8:G80,G80,J$8:J80)-SUMIF(G$8:G80,G80,K$8:K80)+SUMIFS([1]内部转账!$G:$G,[1]内部转账!$C:$C,"<="&$D80,[1]内部转账!$E:$E,$G80)-SUMIFS([1]内部转账!$G:$G,[1]内部转账!$C:$C,"<="&$D80,[1]内部转账!$F:$F,$G80)),"") -> 165494.7 | M80: 隆世光伏/共青办公楼/德祥工地
D81: 45531 | F81: 支出 | G81: 九江银行 | H81: 项目-劳务费 | I81: 张小朋 | K81: 10000 | L81: =IFERROR(IF(G81="","",VLOOKUP($G81,[1]基础信息!$B:$C,2,FALSE)+SUMIF(G$8:G81,G81,J$8:J81)-SUMIF(G$8:G81,G81,K$8:K81)+SUMIFS([1]内部转账!$G:$G,[1]内部转账!$C:$C,"<="&$D81,[1]内部转账!$E:$E,$G81)-SUMIFS([1]内部转账!$G:$G,[1]内部转账!$C:$C,"<="&$D81,[1]内部转账!$F:$F,$G81)),"") -> 155494.7 | M81: 隆世光伏/共青办公楼/德祥工地 | P81: 张小朋
D82: 45531 | F82: 支出 | G82: 九江银行 | H82: 项目-劳务费 | I82: 成峰 | K82: 10000 | L82: =IFERROR(IF(G82="","",VLOOKUP($G82,[1]基础信息!$B:$C,2,FALSE)+SUMIF(G$8:G82,G82,J$8:J82)-SUMIF(G$8:G82,G82,K$8:K82)+SUMIFS([1]内部转账!$G:$G,[1]内部转账!$C:$C,"<="&$D82,[1]内部转账!$E:$E,$G82)-SUMIFS([1]内部转账!$G:$G,[1]内部转账!$C:$C,"<="&$D82,[1]内部转账!$F:$F,$G82)),"") -> 145494.7 | M82: 隆世光伏/共青办公楼/德祥工地
D83: 45531 | F83: 支出 | G83: 九江银行 | H83: 项目-劳务费 | I83: 邓付贞 | K83: 10000 | L83: =IFERROR(IF(G83="","",VLOOKUP($G83,[1]基础信息!$B:$C,2,FALSE)+SUMIF(G$8:G83,G83,J$8:J83)-SUMIF(G$8:G83,G83,K$8:K83)+SUMIFS([1]内部转账!$G:$G,[1]内部转账!$C:$C,"<="&$D83,[1]内部转账!$E:$E,$G83)-SUMIFS([1]内部转账!$G:$G,[1]内部转账!$C:$C,"<="&$D83,[1]内部转账!$F:$F,$G83)),"") -> 135494.7 | M83: 隆世光伏/共青办公楼/德祥工地
D84: 45531 | F84: 支出 | G84: 九江银行 | H84: 项目-劳务费 | I84: 何正拥 | K84: 5000 | L84: =IFERROR(IF(G84="","",VLOOKUP($G84,[1]基础信息!$B:$C,2,FALSE)+SUMIF(G$8:G84,G84,J$8:J84)-SUMIF(G$8:G84,G84,K$8:K84)+SUMIFS([1]内部转账!$G:$G,[1]内部转账!$C:$C,"<="&$D84,[1]内部转账!$E:$E,$G84)-SUMIFS([1]内部转账!$G:$G,[1]内部转账!$C:$C,"<="&$D84,[1]内部转账!$F:$F,$G84)),"") -> 130494.7 | M84: 隆世光伏/共青办公楼/德祥工地
D85: 45531 | F85: 支出 | G85: 九江银行 | H85: 项目-劳务费 | I85: 金李平 | K85: 5000 | L85: =IFERROR(IF(G85="","",VLOOKUP($G85,[1]基础信息!$B:$C,2,FALSE)+SUMIF(G$8:G85,G85,J$8:J85)-SUMIF(G$8:G85,G85,K$8:K85)+SUMIFS([1]内部转账!$G:$G,[1]内部转账!$C:$C,"<="&$D85,[1]内部转账!$E:$E,$G85)-SUMIFS([1]内部转账!$G:$G,[1]内部转账!$C:$C,"<="&$D85,[1]内部转账!$F:$F,$G85)),"") -> 125494.7 | M85: 隆世光伏/共青办公楼/德祥工地
D86: 45531 | F86: 支出 | G86: 九江银行 | H86: 项目-劳务费 | I86: 王伟 | K86: 30000 | L86: =IFERROR(IF(G86="","",VLOOKUP($G86,[1]基础信息!$B:$C,2,FALSE)+SUMIF(G$8:G86,G86,J$8:J86)-SUMIF(G$8:G86,G86,K$8:K86)+SUMIFS([1]内部转账!$G:$G,[1]内部转账!$C:$C,"<="&$D86,[1]内部转账!$E:$E,$G86)-SUMIFS([1]内部转账!$G:$G,[1]内部转账!$C:$C,"<="&$D86,[1]内部转账!$F:$F,$G86)),"") -> 95494.7 | M86: 隆世光伏/共青办公楼/德祥工地 | N86: 王伟
D87: 45532 | F87: 支出 | G87: 九江银行 | H87: 项目-劳务费 | I87: 刘海 | K87: 5000 | L87: =IFERROR(IF(G87="","",VLOOKUP($G87,[1]基础信息!$B:$C,2,FALSE)+SUMIF(G$8:G87,G87,J$8:J87)-SUMIF(G$8:G87,G87,K$8:K87)+SUMIFS([1]内部转账!$G:$G,[1]内部转账!$C:$C,"<="&$D87,[1]内部转账!$E:$E,$G87)-SUMIFS([1]内部转账!$G:$G,[1]内部转账!$C:$C,"<="&$D87,[1]内部转账!$F:$F,$G87)),"") -> 90494.7 | M87: 隆世光伏/共青办公楼/德祥工地
D88: 45532 | F88: 支出 | G88: 九江银行 | H88: 项目-劳务费 | I88: 何正辉 | K88: 8000 | L88: =IFERROR(IF(G88="","",VLOOKUP($G88,[1]基础信息!$B:$C,2,FALSE)+SUMIF(G$8:G88,G88,J$8:J88)-SUMIF(G$8:G88,G88,K$8:K88)+SUMIFS([1]内部转账!$G:$G,[1]内部转账!$C:$C,"<="&$D88,[1]内部转账!$E:$E,$G88)-SUMIFS([1]内部转账!$G:$G,[1]内部转账!$C:$C,"<="&$D88,[1]内部转账!$F:$F,$G88)),"") -> 82494.7 | M88: 隆世光伏/共青办公楼/德祥工地
D89: 45532 | F89: 支出 | G89: 九江银行 | H89: 项目-劳务费 | I89: 袁健冬 | K89: 5890 | L89: =IFERROR(IF(G89="","",VLOOKUP($G89,[1]基础信息!$B:$C,2,FALSE)+SUMIF(G$8:G89,G89,J$8:J89)-SUMIF(G$8:G89,G89,K$8:K89)+SUMIFS([1]内部转账!$G:$G,[1]内部转账!$C:$C,"<="&$D89,[1]内部转账!$E:$E,$G89)-SUMIFS([1]内部转账!$G:$G,[1]内部转账!$C:$C,"<="&$D89,[1]内部转账!$F:$F,$G89)),"") -> 76604.7 | M89: 隆世光伏/共青办公楼/德祥工地
D90: 45532 | F90: 支出 | G90: 九江银行 | H90: 项目-劳务费 | I90: 叶炳南 | K90: 10000 | L90: =IFERROR(IF(G90="","",VLOOKUP($G90,[1]基础信息!$B:$C,2,FALSE)+SUMIF(G$8:G90,G90,J$8:J90)-SUMIF(G$8:G90,G90,K$8:K90)+SUMIFS([1]内部转账!$G:$G,[1]内部转账!$C:$C,"<="&$D90,[1]内部转账!$E:$E,$G90)-SUMIFS([1]内部转账!$G:$G,[1]内部转账!$C:$C,"<="&$D90,[1]内部转账!$F:$F,$G90)),"") -> 66604.7 | M90: 隆世光伏/共青办公楼/德祥工地
D91: 45532 | F91: 支出 | G91: 九江银行 | H91: 项目-劳务费 | I91: 杨贤 | K91: 4400 | L91: =IFERROR(IF(G91="","",VLOOKUP($G91,[1]基础信息!$B:$C,2,FALSE)+SUMIF(G$8:G91,G91,J$8:J91)-SUMIF(G$8:G91,G91,K$8:K91)+SUMIFS([1]内部转账!$G:$G,[1]内部转账!$C:$C,"<="&$D91,[1]内部转账!$E:$E,$G91)-SUMIFS([1]内部转账!$G:$G,[1]内部转账!$C:$C,"<="&$D91,[1]内部转账!$F:$F,$G91)),"") -> 62204.7 | M91: 隆世光伏/共青办公楼/德祥工地
D92: 45532 | F92: 支出 | G92: 九江银行 | H92: 项目-劳务费 | I92: 梅时金 | K92: 10000 | L92: =IFERROR(IF(G92="","",VLOOKUP($G92,[1]基础信息!$B:$C,2,FALSE)+SUMIF(G$8:G92,G92,J$8:J92)-SUMIF(G$8:G92,G92,K$8:K92)+SUMIFS([1]内部转账!$G:$G,[1]内部转账!$C:$C,"<="&$D92,[1]内部转账!$E:$E,$G92)-SUMIFS([1]内部转账!$G:$G,[1]内部转账!$C:$C,"<="&$D92,[1]内部转账!$F:$F,$G92)),"") -> 52204.7 | M92: 隆世光伏/共青办公楼/德祥工地
D93: 45532 | F93: 支出 | G93: 九江银行 | H93: 项目-劳务费 | I93: 金李平 | K93: 5000 | L93: =IFERROR(IF(G93="","",VLOOKUP($G93,[1]基础信息!$B:$C,2,FALSE)+SUMIF(G$8:G93,G93,J$8:J93)-SUMIF(G$8:G93,G93,K$8:K93)+SUMIFS([1]内部转账!$G:$G,[1]内部转账!$C:$C,"<="&$D93,[1]内部转账!$E:$E,$G93)-SUMIFS([1]内部转账!$G:$G,[1]内部转账!$C:$C,"<="&$D93,[1]内部转账!$F:$F,$G93)),"") -> 47204.7 | M93: 隆世光伏/共青办公楼/德祥工地
D94: 45532 | F94: 支出 | G94: 九江银行 | H94: 办公室-工资 | I94: 聂辉 | K94: 20000 | L94: =IFERROR(IF(G94="","",VLOOKUP($G94,[1]基础信息!$B:$C,2,FALSE)+SUMIF(G$8:G94,G94,J$8:J94)-SUMIF(G$8:G94,G94,K$8:K94)+SUMIFS([1]内部转账!$G:$G,[1]内部转账!$C:$C,"<="&$D94,[1]内部转账!$E:$E,$G94)-SUMIFS([1]内部转账!$G:$G,[1]内部转账!$C:$C,"<="&$D94,[1]内部转账!$F:$F,$G94)),"") -> 27204.7 | M94: 隆世光伏/共青办公楼/德祥工地 | N94: 聂辉
D95: 45534 | F95: 支出 | G95: 九江银行 | H95: 项目-劳务费 | I95: 吴长友 | K95: 8000 | L95: =IFERROR(IF(G95="","",VLOOKUP($G95,[1]基础信息!$B:$C,2,FALSE)+SUMIF(G$8:G95,G95,J$8:J95)-SUMIF(G$8:G95,G95,K$8:K95)+SUMIFS([1]内部转账!$G:$G,[1]内部转账!$C:$C,"<="&$D95,[1]内部转账!$E:$E,$G95)-SUMIFS([1]内部转账!$G:$G,[1]内部转账!$C:$C,"<="&$D95,[1]内部转账!$F:$F,$G95)),"") -> 19204.7 | M95: 隆世光伏/共青办公楼/德祥工地
D96: 45534 | F96: 支出 | G96: 九江银行 | H96: 项目-劳务费 | I96: 吴长友 | K96: -8000 | L96: =IFERROR(IF(G96="","",VLOOKUP($G96,[1]基础信息!$B:$C,2,FALSE)+SUMIF(G$8:G96,G96,J$8:J96)-SUMIF(G$8:G96,G96,K$8:K96)+SUMIFS([1]内部转账!$G:$G,[1]内部转账!$C:$C,"<="&$D96,[1]内部转账!$E:$E,$G96)-SUMIFS([1]内部转账!$G:$G,[1]内部转账!$C:$C,"<="&$D96,[1]内部转账!$F:$F,$G96)),"") -> 27204.7 | M96: 隆世光伏/共青办公楼/德祥工地
D97: 45534 | F97: 支出 | G97: 九江银行 | H97: 项目-劳务费 | I97: 吴璇 | K97: 8000 | L97: =IFERROR(IF(G97="","",VLOOKUP($G97,[1]基础信息!$B:$C,2,FALSE)+SUMIF(G$8:G97,G97,J$8:J97)-SUMIF(G$8:G97,G97,K$8:K97)+SUMIFS([1]内部转账!$G:$G,[1]内部转账!$C:$C,"<="&$D97,[1]内部转账!$E:$E,$G97)-SUMIFS([1]内部转账!$G:$G,[1]内部转账!$C:$C,"<="&$D97,[1]内部转账!$F:$F,$G97)),"") -> 19204.7 | M97: 隆世光伏/共青办公楼/德祥工地
D98: 45534 | F98: 支出 | G98: 九江银行 | H98: 项目-劳务费 | I98: 吴长友 | K98: 8000 | L98: =IFERROR(IF(G98="","",VLOOKUP($G98,[1]基础信息!$B:$C,2,FALSE)+SUMIF(G$8:G98,G98,J$8:J98)-SUMIF(G$8:G98,G98,K$8:K98)+SUMIFS([1]内部转账!$G:$G,[1]内部转账!$C:$C,"<="&$D98,[1]内部转账!$E:$E,$G98)-SUMIFS([1]内部转账!$G:$G,[1]内部转账!$C:$C,"<="&$D98,[1]内部转账!$F:$F,$G98)),"") -> 11204.7 | M98: 隆世光伏/共青办公楼/德祥工地
D99: 45534 | F99: 支出 | G99: 九江银行 | H99: 项目-劳务费 | I99: 何正拥 | K99: 5000 | L99: =IFERROR(IF(G99="","",VLOOKUP($G99,[1]基础信息!$B:$C,2,FALSE)+SUMIF(G$8:G99,G99,J$8:J99)-SUMIF(G$8:G99,G99,K$8:K99)+SUMIFS([1]内部转账!$G:$G,[1]内部转账!$C:$C,"<="&$D99,[1]内部转账!$E:$E,$G99)-SUMIFS([1]内部转账!$G:$G,[1]内部转账!$C:$C,"<="&$D99,[1]内部转账!$F:$F,$G99)),"") -> 6204.7 | M99: 隆世光伏/共青办公楼/德祥工地
D100: 45534 | F100: 支出 | G100: 九江银行 | H100: 项目-劳务费 | I100: 雷有才 | K100: 3000 | L100: =IFERROR(IF(G100="","",VLOOKUP($G100,[1]基础信息!$B:$C,2,FALSE)+SUMIF(G$8:G100,G100,J$8:J100)-SUMIF(G$8:G100,G100,K$8:K100)+SUMIFS([1]内部转账!$G:$G,[1]内部转账!$C:$C,"<="&$D100,[1]内部转账!$E:$E,$G100)-SUMIFS([1]内部转账!$G:$G,[1]内部转账!$C:$C,"<="&$D100,[1]内部转账!$F:$F,$G100)),"") -> 3204.7 | M100: 隆世光伏/共青办公楼/德祥工地
D101: 45541 | F101: 支出 | G101: 九江银行 | H101: 项目-劳务费 | I101: 雷有才 | K101: 2000 | L101: =IFERROR(IF(G101="","",VLOOKUP($G101,[1]基础信息!$B:$C,2,FALSE)+SUMIF(G$8:G101,G101,J$8:J101)-SUMIF(G$8:G101,G101,K$8:K101)+SUMIFS([1]内部转账!$G:$G,[1]内部转账!$C:$C,"<="&$D101,[1]内部转账!$E:$E,$G101)-SUMIFS([1]内部转账!$G:$G,[1]内部转账!$C:$C,"<="&$D101,[1]内部转账!$F:$F,$G101)),"") -> 1204.7 | M101: 隆世光伏/共青办公楼/德祥工地
D102: 45556 | F102: 支出 | G102: 九江银行 | H102: 办公室-办公费 | I102: 入息 | K102: -13.83 | L102: =IFERROR(IF(G102="","",VLOOKUP($G102,[1]基础信息!$B:$C,2,FALSE)+SUMIF(G$8:G102,G102,J$8:J102)-SUMIF(G$8:G102,G102,K$8:K102)+SUMIFS([1]内部转账!$G:$G,[1]内部转账!$C:$C,"<="&$D102,[1]内部转账!$E:$E,$G102)-SUMIFS([1]内部转账!$G:$G,[1]内部转账!$C:$C,"<="&$D102,[1]内部转账!$F:$F,$G102)),"") -> 1218.53 | M102: 办公室
D103: 45567 | F103: 支出 | G103: 九江银行 | H103: 个人借款-聂辉 | I103: 聂辉个人借款 | K103: -10000 | L103: =IFERROR(IF(G103="","",VLOOKUP($G103,[1]基础信息!$B:$C,2,FALSE)+SUMIF(G$8:G103,G103,J$8:J103)-SUMIF(G$8:G103,G103,K$8:K103)+SUMIFS([1]内部转账!$G:$G,[1]内部转账!$C:$C,"<="&$D103,[1]内部转账!$E:$E,$G103)-SUMIFS([1]内部转账!$G:$G,[1]内部转账!$C:$C,"<="&$D103,[1]内部转账!$F:$F,$G103)),"") -> 11218.53 | M103: 个人借款 | N103: 聂辉 | P103: 聂辉
D104: 45567 | F104: 支出 | G104: 九江银行 | H104: 办公室-工资 | I104: 张滨 | K104: 10000 | L104: =IFERROR(IF(G104="","",VLOOKUP($G104,[1]基础信息!$B:$C,2,FALSE)+SUMIF(G$8:G104,G104,J$8:J104)-SUMIF(G$8:G104,G104,K$8:K104)+SUMIFS([1]内部转账!$G:$G,[1]内部转账!$C:$C,"<="&$D104,[1]内部转账!$E:$E,$G104)-SUMIFS([1]内部转账!$G:$G,[1]内部转账!$C:$C,"<="&$D104,[1]内部转账!$F:$F,$G104)),"") -> 1218.53 | M104: 隆世光伏/共青办公楼/德祥工地 | N104: 张滨
...
