Workbook

Sheet 基本信息表
A1: 机械工种 | B1: 单价
A2: 轮挖斗 | B2: 150
A3: 炮头 | B3: 250

Sheet Sheet1
A1: 机械工作费用明细表 | T1: 应付金额 | U1: 已付金额 | V1: 剩余金额
A2: 日期 | B2: 项目名称 | C2: 供应商名称 | D2: 机械种类 | E2: 单价 | F2: 上午时间 | G2: 下午时间 | H2: 工作时长 （时间） | I2: 工作时长 （小时） | J2: 应付金额 （元） | K2: 已付金额 （元） | L2: 付款日期 | M2: 付款账户 | N2: 已开票金额 | O2: 税率 | P2: 税额 | Q2: 备注2 | T2: =SUBTOTAL(9,J:J) -> 105775 | U2: =SUBTOTAL(9,K:K) -> 35000 | V2: =T2-U2 -> 70775
A3: 45942 | B3: 科创中心 | C3: 杨工轮挖 | D3: 轮挖斗 | E3: {=IFERROR(VLOOKUP(D3,基本信息表!A:B,{2},FALSE),"")} -> 150 | G3: 13:00-17:30 | H3: {=NPV(-2,--_xlfn.TEXTSPLIT(_xlfn.TEXTJOIN("-",,F3:G3),"-"))} -> 0.1875 | I3: =H3*24 -> 4.5 | J3: =E3*I3 -> 675 | K3: 5000 | L3: 45971 | M3: 九江银行 | N3: 5000 | O3: 0.01 | P3: =N3/(1+O3)*O3 -> 49.50495 | R3: 0.13
A4: 45943 | B4: 科创中心 | C4: 杨工轮挖 | D4: 轮挖斗 | E4: {=IFERROR(VLOOKUP(D4,基本信息表!A:B,{2},FALSE),"")} -> 150 | F4: 7:00-11:30 | G4: 13:00-17:30 | H4: {=NPV(-2,--_xlfn.TEXTSPLIT(_xlfn.TEXTJOIN("-",,F4:G4),"-"))} -> 0.375 | I4: =H4*24 -> 9 | J4: =E4*I4 -> 1350 | K4: 30000 | M4: 王伟垫付 | P4: =N4/(1+O4)*O4 -> 0 | R4: 0.09 | T4: 杨工 | U4: =T2-U5 -> 98875
A5: 45944 | B5: 科创中心 | C5: 杨工轮挖 | D5: 轮挖斗 | E5: {=IFERROR(VLOOKUP(D5,基本信息表!A:B,{2},FALSE),"")} -> 150 | F5: 7:00-11:30 | H5: {=NPV(-2,--_xlfn.TEXTSPLIT(_xlfn.TEXTJOIN("-",,F5:G5),"-"))} -> 0.1875 | I5: =H5*24 -> 4.5 | J5: =E5*I5 -> 675 | P5: =N5/(1+O5)*O5 -> 0 | R5: 0.06 | T5: 徐工 | U5: 6900
A6: 45946 | B6: 科创中心 | C6: 杨工轮挖 | D6: 轮挖斗 | E6: {=IFERROR(VLOOKUP(D6,基本信息表!A:B,{2},FALSE),"")} -> 150 | G6: 13:00-17:30 | H6: {=NPV(-2,--_xlfn.TEXTSPLIT(_xlfn.TEXTJOIN("-",,F6:G6),"-"))} -> 0.1875 | I6: =H6*24 -> 4.5 | J6: =E6*I6 -> 675 | P6: =N6/(1+O6)*O6 -> 0 | R6: 0.03
A7: 45947 | B7: 科创中心 | C7: 杨工轮挖 | D7: 轮挖斗 | E7: {=IFERROR(VLOOKUP(D7,基本信息表!A:B,{2},FALSE),"")} -> 150 | F7: 7:00-11:30 | G7: 13:00-17:30 | H7: {=NPV(-2,--_xlfn.TEXTSPLIT(_xlfn.TEXTJOIN("-",,F7:G7),"-"))} -> 0.375 | I7: =H7*24 -> 9 | J7: =E7*I7 -> 1350 | P7: =N7/(1+O7)*O7 -> 0 | R7: 0.01
A8: 45948 | B8: 科创中心 | C8: 杨工轮挖 | D8: 轮挖斗 | E8: {=IFERROR(VLOOKUP(D8,基本信息表!A:B,{2},FALSE),"")} -> 150 | F8: 7:00-11:30 | G8: 13:00-17:30 | H8: {=NPV(-2,--_xlfn.TEXTSPLIT(_xlfn.TEXTJOIN("-",,F8:G8),"-"))} -> 0.375 | I8: =H8*24 -> 9 | J8: =E8*I8 -> 1350 | P8: =N8/(1+O8)*O8 -> 0
A9: 45949 | B9: 科创中心 | C9: 杨工轮挖 | D9: 轮挖斗 | E9: {=IFERROR(VLOOKUP(D9,基本信息表!A:B,{2},FALSE),"")} -> 150 | F9: 7:00-11:30 | H9: {=NPV(-2,--_xlfn.TEXTSPLIT(_xlfn.TEXTJOIN("-",,F9:G9),"-"))} -> 0.1875 | I9: =H9*24 -> 4.5 | J9: =E9*I9 -> 675 | P9: =N9/(1+O9)*O9 -> 0
A10: 45950 | B10: 科创中心 | C10: 杨工轮挖 | D10: 轮挖斗 | E10: {=IFERROR(VLOOKUP(D10,基本信息表!A:B,{2},FALSE),"")} -> 150 | F10: 7:00-11:30 | G10: 13:00-17:30 | H10: {=NPV(-2,--_xlfn.TEXTSPLIT(_xlfn.TEXTJOIN("-",,F10:G10),"-"))} -> 0.375 | I10: =H10*24 -> 9 | J10: =E10*I10 -> 1350 | P10: =N10/(1+O10)*O10 -> 0
A11: 45951 | B11: 科创中心 | C11: 杨工轮挖 | D11: 轮挖斗 | E11: {=IFERROR(VLOOKUP(D11,基本信息表!A:B,{2},FALSE),"")} -> 150 | F11: 7:00-11:30 | G11: 13:00-17:30 | H11: {=NPV(-2,--_xlfn.TEXTSPLIT(_xlfn.TEXTJOIN("-",,F11:G11),"-"))} -> 0.375 | I11: =H11*24 -> 9 | J11: =E11*I11 -> 1350 | P11: =N11/(1+O11)*O11 -> 0
A12: 45952 | B12: 科创中心 | C12: 杨工轮挖 | D12: 轮挖斗 | E12: {=IFERROR(VLOOKUP(D12,基本信息表!A:B,{2},FALSE),"")} -> 150 | F12: 7:00-11:30 | G12: 13:00-17:30 | H12: {=NPV(-2,--_xlfn.TEXTSPLIT(_xlfn.TEXTJOIN("-",,F12:G12),"-"))} -> 0.375 | I12: =H12*24 -> 9 | J12: =E12*I12 -> 1350 | P12: =N12/(1+O12)*O12 -> 0
A13: 45953 | B13: 科创中心 | C13: 杨工轮挖 | D13: 轮挖斗 | E13: {=IFERROR(VLOOKUP(D13,基本信息表!A:B,{2},FALSE),"")} -> 150 | F13: 7:00-11:30 | G13: 13:00-17:30 | H13: {=NPV(-2,--_xlfn.TEXTSPLIT(_xlfn.TEXTJOIN("-",,F13:G13),"-"))} -> 0.375 | I13: =H13*24 -> 9 | J13: =E13*I13 -> 1350 | P13: =N13/(1+O13)*O13 -> 0
A14: 45954 | B14: 科创中心 | C14: 杨工轮挖 | D14: 轮挖斗 | E14: {=IFERROR(VLOOKUP(D14,基本信息表!A:B,{2},FALSE),"")} -> 150 | F14: 7:00-11:30 | G14: 13:00-17:30 | H14: {=NPV(-2,--_xlfn.TEXTSPLIT(_xlfn.TEXTJOIN("-",,F14:G14),"-"))} -> 0.375 | I14: =H14*24 -> 9 | J14: =E14*I14 -> 1350 | P14: =N14/(1+O14)*O14 -> 0
A15: 45955 | B15: 科创中心 | C15: 杨工轮挖 | D15: 轮挖斗 | E15: {=IFERROR(VLOOKUP(D15,基本信息表!A:B,{2},FALSE),"")} -> 150 | F15: 7:00-11:30 | G15: 13:00-17:30 | H15: {=NPV(-2,--_xlfn.TEXTSPLIT(_xlfn.TEXTJOIN("-",,F15:G15),"-"))} -> 0.375 | I15: =H15*24 -> 9 | J15: =E15*I15 -> 1350 | P15: =N15/(1+O15)*O15 -> 0
A16: 45956 | B16: 科创中心 | C16: 杨工轮挖 | D16: 轮挖斗 | E16: {=IFERROR(VLOOKUP(D16,基本信息表!A:B,{2},FALSE),"")} -> 150 | F16: 7:00-11:30 | G16: 13:00-17:30 | H16: {=NPV(-2,--_xlfn.TEXTSPLIT(_xlfn.TEXTJOIN("-",,F16:G16),"-"))} -> 0.375 | I16: =H16*24 -> 9 | J16: =E16*I16 -> 1350 | P16: =N16/(1+O16)*O16 -> 0
A17: 45957 | B17: 科创中心 | C17: 杨工轮挖 | D17: 轮挖斗 | E17: {=IFERROR(VLOOKUP(D17,基本信息表!A:B,{2},FALSE),"")} -> 150 | F17: 7:00-11:30 | G17: 13:00-17:30 | H17: {=NPV(-2,--_xlfn.TEXTSPLIT(_xlfn.TEXTJOIN("-",,F17:G17),"-"))} -> 0.375 | I17: =H17*24 -> 9 | J17: =E17*I17 -> 1350 | P17: =N17/(1+O17)*O17 -> 0
A18: 45958 | B18: 科创中心 | C18: 杨工轮挖 | D18: 轮挖斗 | E18: {=IFERROR(VLOOKUP(D18,基本信息表!A:B,{2},FALSE),"")} -> 150 | F18: 7:00-11:30 | G18: 13:00-17:30 | H18: {=NPV(-2,--_xlfn.TEXTSPLIT(_xlfn.TEXTJOIN("-",,F18:G18),"-"))} -> 0.375 | I18: =H18*24 -> 9 | J18: =E18*I18 -> 1350 | P18: =N18/(1+O18)*O18 -> 0
A19: 45959 | B19: 科创中心 | C19: 杨工轮挖 | D19: 轮挖斗 | E19: {=IFERROR(VLOOKUP(D19,基本信息表!A:B,{2},FALSE),"")} -> 150 | F19: 7:00-11:30 | G19: 13:00-17:30 | H19: {=NPV(-2,--_xlfn.TEXTSPLIT(_xlfn.TEXTJOIN("-",,F19:G19),"-"))} -> 0.375 | I19: =H19*24 -> 9 | J19: =E19*I19 -> 1350 | P19: =N19/(1+O19)*O19 -> 0
A20: 45961 | B20: 科创中心 | C20: 杨工轮挖 | D20: 轮挖斗 | E20: {=IFERROR(VLOOKUP(D20,基本信息表!A:B,{2},FALSE),"")} -> 150 | F20: 7:00-11:30 | G20: 13:00-17:30 | H20: {=NPV(-2,--_xlfn.TEXTSPLIT(_xlfn.TEXTJOIN("-",,F20:G20),"-"))} -> 0.375 | I20: =H20*24 -> 9 | J20: =E20*I20 -> 1350 | P20: =N20/(1+O20)*O20 -> 0
A21: 45962 | B21: 科创中心 | C21: 杨工轮挖 | D21: 轮挖斗 | E21: {=IFERROR(VLOOKUP(D21,基本信息表!A:B,{2},FALSE),"")} -> 150 | F21: 7:00-11:30 | G21: 13:00-17:30 | H21: {=NPV(-2,--_xlfn.TEXTSPLIT(_xlfn.TEXTJOIN("-",,F21:G21),"-"))} -> 0.375 | I21: =H21*24 -> 9 | J21: =E21*I21 -> 1350 | P21: =N21/(1+O21)*O21 -> 0
... A24: 45965 | B24: 科创中心 | C24: 杨工轮挖 | D24: 轮挖斗 | E24: {=IFERROR(VLOOKUP(D24,基本信息表!A:B,{2},FALSE),"")} -> 150 | F24: 7:00-11:30 | G24: 13:00-17:30 | H24: {=NPV(-2,--_xlfn.TEXTSPLIT(_xlfn.TEXTJOIN("-",,F24:G24),"-"))} -> 0.375 | I24: =H24*24 -> 9 | J24: =E24*I24 -> 1350 | P24: =N24/(1+O24)*O24 -> 0
A25: 45966 | B25: 科创中心 | C25: 杨工轮挖 | D25: 轮挖斗 | E25: {=IFERROR(VLOOKUP(D25,基本信息表!A:B,{2},FALSE),"")} -> 150 | F25: 7:00-10:00 | H25: {=NPV(-2,--_xlfn.TEXTSPLIT(_xlfn.TEXTJOIN("-",,F25:G25),"-"))} -> 0.125 | I25: =H25*24 -> 3 | J25: =E25*I25 -> 450 | P25: =N25/(1+O25)*O25 -> 0
A26: 45973 | B26: 科创中心 | C26: 杨工轮挖 | D26: 轮挖斗 | E26: {=IFERROR(VLOOKUP(D26,基本信息表!A:B,{2},FALSE),"")} -> 150 | F26: 9:30-11:30 | G26: 13:00-17:30 | H26: {=NPV(-2,--_xlfn.TEXTSPLIT(_xlfn.TEXTJOIN("-",,F26:G26),"-"))} -> 0.27083333 | I26: =H26*24 -> 6.5 | J26: =E26*I26 -> 975 | P26: =N26/(1+O26)*O26 -> 0
A27: 45974 | B27: 科创中心 | C27: 杨工轮挖 | D27: 轮挖斗 | E27: {=IFERROR(VLOOKUP(D27,基本信息表!A:B,{2},FALSE),"")} -> 150 | F27: 7:00-11:30 | G27: 13:00-17:30 | H27: {=NPV(-2,--_xlfn.TEXTSPLIT(_xlfn.TEXTJOIN("-",,F27:G27),"-"))} -> 0.375 | I27: =H27*24 -> 9 | J27: =E27*I27 -> 1350 | P27: =N27/(1+O27)*O27 -> 0
A28: 45975 | B28: 科创中心 | C28: 杨工轮挖 | D28: 轮挖斗 | E28: {=IFERROR(VLOOKUP(D28,基本信息表!A:B,{2},FALSE),"")} -> 150 | F28: 7:00-11:30 | G28: 13:00-17:30 | H28: {=NPV(-2,--_xlfn.TEXTSPLIT(_xlfn.TEXTJOIN("-",,F28:G28),"-"))} -> 0.375 | I28: =H28*24 -> 9 | J28: =E28*I28 -> 1350 | P28: =N28/(1+O28)*O28 -> 0
A29: 45976 | B29: 科创中心 | C29: 杨工轮挖 | D29: 轮挖斗 | E29: {=IFERROR(VLOOKUP(D29,基本信息表!A:B,{2},FALSE),"")} -> 150 | F29: 7:00-11:30 | G29: 13:00-17:30 | H29: {=NPV(-2,--_xlfn.TEXTSPLIT(_xlfn.TEXTJOIN("-",,F29:G29),"-"))} -> 0.375 | I29: =H29*24 -> 9 | J29: =E29*I29 -> 1350 | P29: =N29/(1+O29)*O29 -> 0
A30: 45977 | B30: 科创中心 | C30: 杨工轮挖 | D30: 轮挖斗 | E30: {=IFERROR(VLOOKUP(D30,基本信息表!A:B,{2},FALSE),"")} -> 150 | F30: 7:00-11:30 | G30: 13:00-17:30 | H30: {=NPV(-2,--_xlfn.TEXTSPLIT(_xlfn.TEXTJOIN("-",,F30:G30),"-"))} -> 0.375 | I30: =H30*24 -> 9 | J30: =E30*I30 -> 1350 | P30: =N30/(1+O30)*O30 -> 0
A31: 45978 | B31: 科创中心 | C31: 杨工轮挖 | D31: 轮挖斗 | E31: {=IFERROR(VLOOKUP(D31,基本信息表!A:B,{2},FALSE),"")} -> 150 | F31: 7:00-11:30 | G31: 13:00-17:30 | H31: {=NPV(-2,--_xlfn.TEXTSPLIT(_xlfn.TEXTJOIN("-",,F31:G31),"-"))} -> 0.375 | I31: =H31*24 -> 9 | J31: =E31*I31 -> 1350 | P31: =N31/(1+O31)*O31 -> 0
A32: 45979 | B32: 科创中心 | C32: 杨工轮挖 | D32: 轮挖斗 | E32: {=IFERROR(VLOOKUP(D32,基本信息表!A:B,{2},FALSE),"")} -> 150 | F32: 7:00-11:30 | G32: 13:00-17:30 | H32: {=NPV(-2,--_xlfn.TEXTSPLIT(_xlfn.TEXTJOIN("-",,F32:G32),"-"))} -> 0.375 | I32: =H32*24 -> 9 | J32: =E32*I32 -> 1350 | P32: =N32/(1+O32)*O32 -> 0
A33: 45980 | B33: 科创中心 | C33: 杨工轮挖 | D33: 轮挖斗 | E33: {=IFERROR(VLOOKUP(D33,基本信息表!A:B,{2},FALSE),"")} -> 150 | F33: 7:00-11:30 | G33: 13:00-17:00 | H33: {=NPV(-2,--_xlfn.TEXTSPLIT(_xlfn.TEXTJOIN("-",,F33:G33),"-"))} -> 0.35416667 | I33: =H33*24 -> 8.5 | J33: =E33*I33 -> 1275 | P33: =N33/(1+O33)*O33 -> 0
A34: 45982 | B34: 科创中心 | C34: 杨工轮挖 | D34: 轮挖斗 | E34: {=IFERROR(VLOOKUP(D34,基本信息表!A:B,{2},FALSE),"")} -> 150 | F34: 7:00-11:30 | G34: 13:00-17:30 | H34: {=NPV(-2,--_xlfn.TEXTSPLIT(_xlfn.TEXTJOIN("-",,F34:G34),"-"))} -> 0.375 | I34: =H34*24 -> 9 | J34: =E34*I34 -> 1350 | P34: =N34/(1+O34)*O34 -> 0
A35: 45984 | B35: 科创中心 | C35: 杨工轮挖 | D35: 轮挖斗 | E35: {=IFERROR(VLOOKUP(D35,基本信息表!A:B,{2},FALSE),"")} -> 150 | F35: 7:00-11:30 | H35: {=NPV(-2,--_xlfn.TEXTSPLIT(_xlfn.TEXTJOIN("-",,F35:G35),"-"))} -> 0.1875 | I35: =H35*24 -> 4.5 | J35: =E35*I35 -> 675 | P35: =N35/(1+O35)*O35 -> 0
A36: 45985 | B36: 科创中心 | C36: 杨工轮挖 | D36: 轮挖斗 | E36: {=IFERROR(VLOOKUP(D36,基本信息表!A:B,{2},FALSE),"")} -> 150 | G36: 13:00-17:30 | H36: {=NPV(-2,--_xlfn.TEXTSPLIT(_xlfn.TEXTJOIN("-",,F36:G36),"-"))} -> 0.1875 | I36: =H36*24 -> 4.5 | J36: =E36*I36 -> 675 | P36: =N36/(1+O36)*O36 -> 0
A37: 45986 | B37: 科创中心 | C37: 杨工轮挖 | D37: 轮挖斗 | E37: {=IFERROR(VLOOKUP(D37,基本信息表!A:B,{2},FALSE),"")} -> 150 | F37: 7:00-11:30 | G37: 13:00-17:30 | H37: {=NPV(-2,--_xlfn.TEXTSPLIT(_xlfn.TEXTJOIN("-",,F37:G37),"-"))} -> 0.375 | I37: =H37*24 -> 9 | J37: =E37*I37 -> 1350 | P37: =N37/(1+O37)*O37 -> 0
A38: 45987 | B38: 科创中心 | C38: 杨工轮挖 | D38: 轮挖斗 | E38: {=IFERROR(VLOOKUP(D38,基本信息表!A:B,{2},FALSE),"")} -> 150 | F38: 7:00-11:30 | G38: 13:00-17:30 | H38: {=NPV(-2,--_xlfn.TEXTSPLIT(_xlfn.TEXTJOIN("-",,F38:G38),"-"))} -> 0.375 | I38: =H38*24 -> 9 | J38: =E38*I38 -> 1350 | P38: =N38/(1+O38)*O38 -> 0
A39: 45988 | B39: 科创中心 | C39: 杨工轮挖 | D39: 轮挖斗 | E39: {=IFERROR(VLOOKUP(D39,基本信息表!A:B,{2},FALSE),"")} -> 150 | F39: 7:00-11:30 | G39: 13:00-17:30 | H39: {=NPV(-2,--_xlfn.TEXTSPLIT(_xlfn.TEXTJOIN("-",,F39:G39),"-"))} -> 0.375 | I39: =H39*24 -> 9 | J39: =E39*I39 -> 1350 | P39: =N39/(1+O39)*O39 -> 0
A40: 45989 | B40: 科创中心 | C40: 杨工轮挖 | D40: 轮挖斗 | E40: {=IFERROR(VLOOKUP(D40,基本信息表!A:B,{2},FALSE),"")} -> 150 | F40: 7:00-10:00 | H40: {=NPV(-2,--_xlfn.TEXTSPLIT(_xlfn.TEXTJOIN("-",,F40:G40),"-"))} -> 0.125 | I40: =H40*24 -> 3 | J40: =E40*I40 -> 450 | P40: =N40/(1+O40)*O40 -> 0
A41: 45991 | B41: 科创中心 | C41: 杨工轮挖 | D41: 轮挖斗 | E41: {=IFERROR(VLOOKUP(D41,基本信息表!A:B,{2},FALSE),"")} -> 150 | F41: 7:00-11:30 | G41: 13:30-17:30 | H41: {=NPV(-2,--_xlfn.TEXTSPLIT(_xlfn.TEXTJOIN("-",,F41:G41),"-"))} -> 0.35416667 | I41: =H41*24 -> 8.5 | J41: =E41*I41 -> 1275 | P41: =N41/(1+O41)*O41 -> 0
A42: 45992 | B42: 科创中心 | C42: 杨工轮挖 | D42: 轮挖斗 | E42: {=IFERROR(VLOOKUP(D42,基本信息表!A:B,{2},FALSE),"")} -> 150 | F42: 7:00-11:30 | G42: 13:00-16:00 | H42: {=NPV(-2,--_xlfn.TEXTSPLIT(_xlfn.TEXTJOIN("-",,F42:G42),"-"))} -> 0.3125 | I42: =H42*24 -> 7.5 | J42: =E42*I42 -> 1125 | P42: =N42/(1+O42)*O42 -> 0
A43: 45994 | B43: 科创中心 | C43: 杨工轮挖 | D43: 轮挖斗 | E43: {=IFERROR(VLOOKUP(D43,基本信息表!A:B,{2},FALSE),"")} -> 150 | F43: 7:00-11:30 | H43: {=NPV(-2,--_xlfn.TEXTSPLIT(_xlfn.TEXTJOIN("-",,F43:G43),"-"))} -> 0.1875 | I43: =H43*24 -> 4.5 | J43: =E43*I43 -> 675 | P43: =N43/(1+O43)*O43 -> 0
A44: 45997 | B44: 科创中心 | C44: 杨工轮挖 | D44: 轮挖斗 | E44: {=IFERROR(VLOOKUP(D44,基本信息表!A:B,{2},FALSE),"")} -> 150 | F44: 7:00-11:30 | G44: 13:00-17:30 | H44: {=NPV(-2,--_xlfn.TEXTSPLIT(_xlfn.TEXTJOIN("-",,F44:G44),"-"))} -> 0.375 | I44: =H44*24 -> 9 | J44: =E44*I44 -> 1350 | P44: =N44/(1+O44)*O44 -> 0
A45: 45999 | B45: 科创中心 | C45: 杨工轮挖 | D45: 轮挖斗 | E45: {=IFERROR(VLOOKUP(D45,基本信息表!A:B,{2},FALSE),"")} -> 150 | G45: 15:30-17:30 | H45: {=NPV(-2,--_xlfn.TEXTSPLIT(_xlfn.TEXTJOIN("-",,F45:G45),"-"))} -> 0.083333333 | I45: =H45*24 -> 2 | J45: =E45*I45 -> 300 | P45: =N45/(1+O45)*O45 -> 0
A46: 46000 | B46: 科创中心 | C46: 杨工轮挖 | D46: 轮挖斗 | E46: {=IFERROR(VLOOKUP(D46,基本信息表!A:B,{2},FALSE),"")} -> 150 | F46: 7:00-11:30 | G46: 13:00-17:30 | H46: {=NPV(-2,--_xlfn.TEXTSPLIT(_xlfn.TEXTJOIN("-",,F46:G46),"-"))} -> 0.375 | I46: =H46*24 -> 9 | J46: =E46*I46 -> 1350 | P46: =N46/(1+O46)*O46 -> 0
A47: 46001 | B47: 科创中心 | C47: 杨工轮挖 | D47: 轮挖斗 | E47: {=IFERROR(VLOOKUP(D47,基本信息表!A:B,{2},FALSE),"")} -> 150 | F47: 7:00-11:30 | H47: {=NPV(-2,--_xlfn.TEXTSPLIT(_xlfn.TEXTJOIN("-",,F47:G47),"-"))} -> 0.1875 | I47: =H47*24 -> 4.5 | J47: =E47*I47 -> 675 | P47: =N47/(1+O47)*O47 -> 0
A48: 46004 | B48: 科创中心 | C48: 杨工轮挖 | D48: 轮挖斗 | E48: {=IFERROR(VLOOKUP(D48,基本信息表!A:B,{2},FALSE),"")} -> 150 | F48: 7:00-11:30 | G48: 13:00-17:30 | H48: {=NPV(-2,--_xlfn.TEXTSPLIT(_xlfn.TEXTJOIN("-",,F48:G48),"-"))} -> 0.375 | I48: =H48*24 -> 9 | J48: =E48*I48 -> 1350 | P48: =N48/(1+O48)*O48 -> 0
A49: 46005 | B49: 科创中心 | C49: 杨工轮挖 | D49: 轮挖斗 | E49: {=IFERROR(VLOOKUP(D49,基本信息表!A:B,{2},FALSE),"")} -> 150 | F49: 7:00-11:30 | G49: 13:00-17:30 | H49: {=NPV(-2,--_xlfn.TEXTSPLIT(_xlfn.TEXTJOIN("-",,F49:G49),"-"))} -> 0.375 | I49: =H49*24 -> 9 | J49: =E49*I49 -> 1350 | P49: =N49/(1+O49)*O49 -> 0
A50: 46006 | B50: 科创中心 | C50: 杨工轮挖 | D50: 轮挖斗 | E50: {=IFERROR(VLOOKUP(D50,基本信息表!A:B,{2},FALSE),"")} -> 150 | F50: 10:00-11:30 | G50: 13:00-17:30 | H50: {=NPV(-2,--_xlfn.TEXTSPLIT(_xlfn.TEXTJOIN("-",,F50:G50),"-"))} -> 0.25 | I50: =H50*24 -> 6 | J50: =E50*I50 -> 900 | P50: =N50/(1+O50)*O50 -> 0
A51: 46007 | B51: 科创中心 | C51: 杨工轮挖 | D51: 轮挖斗 | E51: {=IFERROR(VLOOKUP(D51,基本信息表!A:B,{2},FALSE),"")} -> 150 | F51: 7:00-9:00 | H51: {=NPV(-2,--_xlfn.TEXTSPLIT(_xlfn.TEXTJOIN("-",,F51:G51),"-"))} -> 0.083333333 | I51: =H51*24 -> 2 | J51: =E51*I51 -> 300 | P51: =N51/(1+O51)*O51 -> 0
A52: 46008 | B52: 科创中心 | C52: 杨工轮挖 | D52: 轮挖斗 | E52: {=IFERROR(VLOOKUP(D52,基本信息表!A:B,{2},FALSE),"")} -> 150 | F52: 7:30-11:30 | G52: 13:00-17:30 | H52: {=NPV(-2,--_xlfn.TEXTSPLIT(_xlfn.TEXTJOIN("-",,F52:G52),"-"))} -> 0.35416667 | I52: =H52*24 -> 8.5 | J52: =E52*I52 -> 1275 | P52: =N52/(1+O52)*O52 -> 0
A53: 46009 | B53: 科创中心 | C53: 杨工轮挖 | D53: 轮挖斗 | E53: {=IFERROR(VLOOKUP(D53,基本信息表!A:B,{2},FALSE),"")} -> 150 | F53: 7:00-11:30 | G53: 13:00-17:30 | H53: {=NPV(-2,--_xlfn.TEXTSPLIT(_xlfn.TEXTJOIN("-",,F53:G53),"-"))} -> 0.375 | I53: =H53*24 -> 9 | J53: =E53*I53 -> 1350 | P53: =N53/(1+O53)*O53 -> 0
A54: 46010 | B54: 科创中心 | C54: 杨工轮挖 | D54: 轮挖斗 | E54: {=IFERROR(VLOOKUP(D54,基本信息表!A:B,{2},FALSE),"")} -> 150 | F54: 7:00-11:30 | G54: 13:00-17:30 | H54: {=NPV(-2,--_xlfn.TEXTSPLIT(_xlfn.TEXTJOIN("-",,F54:G54),"-"))} -> 0.375 | I54: =H54*24 -> 9 | J54: =E54*I54 -> 1350 | P54: =N54/(1+O54)*O54 -> 0
A55: 46011 | B55: 科创中心 | C55: 杨工轮挖 | D55: 轮挖斗 | E55: {=IFERROR(VLOOKUP(D55,基本信息表!A:B,{2},FALSE),"")} -> 150 | F55: 7:00-11:30 | G55: 13:00-17:30 | H55: {=NPV(-2,--_xlfn.TEXTSPLIT(_xlfn.TEXTJOIN("-",,F55:G55),"-"))} -> 0.375 | I55: =H55*24 -> 9 | J55: =E55*I55 -> 1350 | P55: =N55/(1+O55)*O55 -> 0
A56: 46013 | B56: 科创中心 | C56: 杨工轮挖 | D56: 轮挖斗 | E56: {=IFERROR(VLOOKUP(D56,基本信息表!A:B,{2},FALSE),"")} -> 150 | F56: 7:00-11:30 | G56: 13:00-17:30 | H56: {=NPV(-2,--_xlfn.TEXTSPLIT(_xlfn.TEXTJOIN("-",,F56:G56),"-"))} -> 0.375 | I56: =H56*24 -> 9 | J56: =E56*I56 -> 1350 | P56: =N56/(1+O56)*O56 -> 0
A57: 46014 | B57: 科创中心 | C57: 杨工轮挖 | D57: 轮挖斗 | E57: {=IFERROR(VLOOKUP(D57,基本信息表!A:B,{2},FALSE),"")} -> 150 | F57: 7:00-11:30 | G57: 14:00-17:30 | H57: {=NPV(-2,--_xlfn.TEXTSPLIT(_xlfn.TEXTJOIN("-",,F57:G57),"-"))} -> 0.33333333 | I57: =H57*24 -> 8 | J57: =E57*I57 -> 1200 | P57: =N57/(1+O57)*O57 -> 0
A58: 46016 | B58: 科创中心 | C58: 杨工轮挖 | D58: 轮挖斗 | E58: {=IFERROR(VLOOKUP(D58,基本信息表!A:B,{2},FALSE),"")} -> 150 | F58: 8:30-11:30 | G58: 13:00-16:30 | H58: {=NPV(-2,--_xlfn.TEXTSPLIT(_xlfn.TEXTJOIN("-",,F58:G58),"-"))} -> 0.27083333 | I58: =H58*24 -> 6.5 | J58: =E58*I58 -> 975 | P58: =N58/(1+O58)*O58 -> 0
A59: 46017 | B59: 科创中心 | C59: 杨工轮挖 | D59: 轮挖斗 | E59: {=IFERROR(VLOOKUP(D59,基本信息表!A:B,{2},FALSE),"")} -> 150 | F59: 7:00-11:30 | G59: 13:00-17:30 | H59: {=NPV(-2,--_xlfn.TEXTSPLIT(_xlfn.TEXTJOIN("-",,F59:G59),"-"))} -> 0.375 | I59: =H59*24 -> 9 | J59: =E59*I59 -> 1350 | P59: =N59/(1+O59)*O59 -> 0
A60: 46018 | B60: 科创中心 | C60: 杨工轮挖 | D60: 轮挖斗 | E60: {=IFERROR(VLOOKUP(D60,基本信息表!A:B,{2},FALSE),"")} -> 150 | F60: 7:00-11:30 | G60: 13:00-17:30 | H60: {=NPV(-2,--_xlfn.TEXTSPLIT(_xlfn.TEXTJOIN("-",,F60:G60),"-"))} -> 0.375 | I60: =H60*24 -> 9 | J60: =E60*I60 -> 1350 | P60: =N60/(1+O60)*O60 -> 0
A61: 46019 | B61: 科创中心 | C61: 杨工轮挖 | D61: 轮挖斗 | E61: {=IFERROR(VLOOKUP(D61,基本信息表!A:B,{2},FALSE),"")} -> 150 | F61: 7:00-11:30 | G61: 13:00-17:30 | H61: {=NPV(-2,--_xlfn.TEXTSPLIT(_xlfn.TEXTJOIN("-",,F61:G61),"-"))} -> 0.375 | I61: =H61*24 -> 9 | J61: =E61*I61 -> 1350 | P61: =N61/(1+O61)*O61 -> 0
A62: 46020 | B62: 科创中心 | C62: 杨工轮挖 | D62: 轮挖斗 | E62: {=IFERROR(VLOOKUP(D62,基本信息表!A:B,{2},FALSE),"")} -> 150 | F62: 7:00-11:30 | G62: 13:00-17:30 | H62: {=NPV(-2,--_xlfn.TEXTSPLIT(_xlfn.TEXTJOIN("-",,F62:G62),"-"))} -> 0.375 | I62: =H62*24 -> 9 | J62: =E62*I62 -> 1350 | P62: =N62/(1+O62)*O62 -> 0
A63: 46021 | B63: 科创中心 | C63: 杨工轮挖 | D63: 轮挖斗 | E63: {=IFERROR(VLOOKUP(D63,基本信息表!A:B,{2},FALSE),"")} -> 150 | F63: 7:00-11:30 | G63: 13:00-17:30 | H63: {=NPV(-2,--_xlfn.TEXTSPLIT(_xlfn.TEXTJOIN("-",,F63:G63),"-"))} -> 0.375 | I63: =H63*24 -> 9 | J63: =E63*I63 -> 1350 | P63: =N63/(1+O63)*O63 -> 0
... A75: 45968 | B75: 科创中心 | C75: 杨工轮挖 | D75: 炮头 | E75: {=IFERROR(VLOOKUP(D75,基本信息表!A:B,{2},FALSE),"")} -> 250 | F75: 7:00-11:30 | G75: 13:00-17:30 | H75: {=NPV(-2,--_xlfn.TEXTSPLIT(_xlfn.TEXTJOIN("-",,F75:G75),"-"))} -> 0.375 | I75: =H75*24 -> 9 | J75: =E75*I75 -> 2250 | P75: =N75/(1+O75)*O75 -> 0
A76: 45969 | B76: 科创中心 | C76: 杨工轮挖 | D76: 炮头 | E76: {=IFERROR(VLOOKUP(D76,基本信息表!A:B,{2},FALSE),"")} -> 250 | F76: 7:00-11:30 | H76: {=NPV(-2,--_xlfn.TEXTSPLIT(_xlfn.TEXTJOIN("-",,F76:G76),"-"))} -> 0.1875 | I76: =H76*24 -> 4.5 | J76: =E76*I76 -> 1125 | P76: =N76/(1+O76)*O76 -> 0
A77: 45971 | B77: 科创中心 | C77: 杨工轮挖 | D77: 炮头 | E77: {=IFERROR(VLOOKUP(D77,基本信息表!A:B,{2},FALSE),"")} -> 250 | F77: 7:00-11:30 | G77: 13:00-17:30 | H77: {=NPV(-2,--_xlfn.TEXTSPLIT(_xlfn.TEXTJOIN("-",,F77:G77),"-"))} -> 0.375 | I77: =H77*24 -> 9 | J77: =E77*I77 -> 2250 | P77: =N77/(1+O77)*O77 -> 0
A78: 45972 | B78: 科创中心 | C78: 杨工轮挖 | D78: 炮头 | E78: {=IFERROR(VLOOKUP(D78,基本信息表!A:B,{2},FALSE),"")} -> 250 | F78: 7:00-11:30 | G78: 13:00-17:30 | H78: {=NPV(-2,--_xlfn.TEXTSPLIT(_xlfn.TEXTJOIN("-",,F78:G78),"-"))} -> 0.375 | I78: =H78*24 -> 9 | J78: =E78*I78 -> 2250 | P78: =N78/(1+O78)*O78 -> 0
A79: 45973 | B79: 科创中心 | C79: 杨工轮挖 | D79: 炮头 | E79: {=IFERROR(VLOOKUP(D79,基本信息表!A:B,{2},FALSE),"")} -> 250 | F79: 7:00-9:30 | H79: {=NPV(-2,--_xlfn.TEXTSPLIT(_xlfn.TEXTJOIN("-",,F79:G79),"-"))} -> 0.10416667 | I79: =H79*24 -> 2.5 | J79: =E79*I79 -> 625 | P79: =N79/(1+O79)*O79 -> 0
A80: 46001 | B80: 科创中心 | C80: 杨工轮挖 | D80: 炮头 | E80: {=IFERROR(VLOOKUP(D80,基本信息表!A:B,{2},FALSE),"")} -> 250 | G80: 13:00-15:00 | H80: {=NPV(-2,--_xlfn.TEXTSPLIT(_xlfn.TEXTJOIN("-",,F80:G80),"-"))} -> 0.083333333 | I80: =H80*24 -> 2 | J80: =E80*I80 -> 500 | P80: =N80/(1+O80)*O80 -> 0
A81: 46006 | B81: 科创中心 | C81: 杨工轮挖 | D81: 炮头 | E81: {=IFERROR(VLOOKUP(D81,基本信息表!A:B,{2},FALSE),"")} -> 250 | F81: 7:00-10:00 | H81: {=NPV(-2,--_xlfn.TEXTSPLIT(_xlfn.TEXTJOIN("-",,F81:G81),"-"))} -> 0.125 | I81: =H81*24 -> 3 | J81: =E81*I81 -> 750 | P81: =N81/(1+O81)*O81 -> 0
A82: 46007 | B82: 科创中心 | C82: 杨工轮挖 | D82: 炮头 | E82: {=IFERROR(VLOOKUP(D82,基本信息表!A:B,{2},FALSE),"")} -> 250 | F82: 9:00-11:30 | G82: 13:00-17:30 | H82: {=NPV(-2,--_xlfn.TEXTSPLIT(_xlfn.TEXTJOIN("-",,F82:G82),"-"))} -> 0.29166667 | I82: =H82*24 -> 7 | J82: =E82*I82 -> 1750 | P82: =N82/(1+O82)*O82 -> 0
A83: 46008 | B83: 科创中心 | C83: 杨工轮挖 | D83: 炮头 | E83: {=IFERROR(VLOOKUP(D83,基本信息表!A:B,{2},FALSE),"")} -> 250 | F83: 6:00-7:30 | H83: {=NPV(-2,--_xlfn.TEXTSPLIT(_xlfn.TEXTJOIN("-",,F83:G83),"-"))} -> 0.0625 | I83: =H83*24 -> 1.5 | J83: =E83*I83 -> 375 | P83: =N83/(1+O83)*O83 -> 0
A84: 46021 | B84: 科创中心 | C84: 徐工轮挖 | D84: 轮挖斗 | E84: {=IFERROR(VLOOKUP(D84,基本信息表!A:B,{2},FALSE),"")} -> 150 | G84: 13:00-17:30 | H84: {=NPV(-2,--_xlfn.TEXTSPLIT(_xlfn.TEXTJOIN("-",,F84:G84),"-"))} -> 0.1875 | I84: =H84*24 -> 4.5 | J84: =E84*I84 -> 675 | P84: =N84/(1+O84)*O84 -> 0
A85: 46022 | B85: 科创中心 | C85: 徐工轮挖 | D85: 轮挖斗 | E85: {=IFERROR(VLOOKUP(D85,基本信息表!A:B,{2},FALSE),"")} -> 150 | F85: 7:00-11:30 | G85: 13:00-17:30 | H85: {=NPV(-2,--_xlfn.TEXTSPLIT(_xlfn.TEXTJOIN("-",,F85:G85),"-"))} -> 0.375 | I85: =H85*24 -> 9 | J85: =E85*I85 -> 1350 | P85: =N85/(1+O85)*O85 -> 0
A86: 45659 | B86: 科创中心 | C86: 徐工轮挖 | D86: 轮挖斗 | E86: {=IFERROR(VLOOKUP(D86,基本信息表!A:B,{2},FALSE),"")} -> 150 | F86: 7:00-11:30 | G86: 13:00-17:30 | H86: {=NPV(-2,--_xlfn.TEXTSPLIT(_xlfn.TEXTJOIN("-",,F86:G86),"-"))} -> 0.375 | I86: =H86*24 -> 9 | J86: =E86*I86 -> 1350 | P86: =N86/(1+O86)*O86 -> 0
A87: 45660 | B87: 科创中心 | C87: 徐工轮挖 | D87: 轮挖斗 | E87: {=IFERROR(VLOOKUP(D87,基本信息表!A:B,{2},FALSE),"")} -> 150 | F87: 7:30-11:30 | G87: 13:00-17:30 | H87: {=NPV(-2,--_xlfn.TEXTSPLIT(_xlfn.TEXTJOIN("-",,F87:G87),"-"))} -> 0.35416667 | I87: =H87*24 -> 8.5 | J87: =E87*I87 -> 1275 | P87: =N87/(1+O87)*O87 -> 0
A88: 45661 | B88: 科创中心 | C88: 徐工轮挖 | D88: 轮挖斗 | E88: {=IFERROR(VLOOKUP(D88,基本信息表!A:B,{2},FALSE),"")} -> 150 | F88: 7:00-11:30 | G88: 13:00-17:30 | H88: {=NPV(-2,--_xlfn.TEXTSPLIT(_xlfn.TEXTJOIN("-",,F88:G88),"-"))} -> 0.375 | I88: =H88*24 -> 9 | J88: =E88*I88 -> 1350 | P88: =N88/(1+O88)*O88 -> 0
A89: 45662 | B89: 科创中心 | C89: 徐工轮挖 | D89: 轮挖斗 | E89: {=IFERROR(VLOOKUP(D89,基本信息表!A:B,{2},FALSE),"")} -> 150 | F89: 7:00-11:30 | G89: 13:00-14:30 | H89: {=NPV(-2,--_xlfn.TEXTSPLIT(_xlfn.TEXTJOIN("-",,F89:G89),"-"))} -> 0.25 | I89: =H89*24 -> 6 | J89: =E89*I89 -> 900 | P89: =N89/(1+O89)*O89 -> 0

Sheet Sheet3
A1: 机械费汇总表 | B1: 机械+运输费用汇总表 | O1: {=_xlfn.PIVOTBY(_xlfn._TRO_TRAILING(C2:C999),,_xlfn._TRO_TRAILING(D2:E999),_xleta.SUM,3)} -> 项目名称 | P1: 应付金额 | Q1: 已付金额 | R1: 未付金额
A2: 日期 | B2: 挖机班组/（运输）名称 | C2: 项目名称 | D2: 应付金额 | E2: 已付金额 | F2: 付款日期 | G2: 付款账户 | H2: 收款账户 | I2: 已开票金额 | J2: 开票日期 | K2: 税率 | L2: 税额 | M2: 备注2 | O2: 德安农商行总部 | P2: 800 | Q2: 800 | R2: =P2-Q2 -> 0
A3: 25/11-26/1 | B3: 杨工 | C3: 科创中心 | D3: 98875 | E3: 30000 | G3: 王伟垫付 | O3: 科创中心 | P3: 105775 | Q3: 35000 | R3: =P3-Q3 -> 70775
A4: 25/11-26/1 | B4: 徐工 | C4: 科创中心 | D4: 6900 | E4: 5000 | F4: 45971 | G4: 九江银行 | H4: 九江翌年行建筑工程劳务有限公司 | I4: 5000 | K4: 0.01 | O4: 邹桥派出所 | P4: 1280 | Q4: 1280 | R4: =P4-Q4 -> 0
A5: 46174 | B5: 德安县恒建工程部 | C5: 德安农商行总部 | D5: 800 | E5: 800 | F5: 46205 | G5: 九江银行 | H5: 舒文龙 | I5: 800 | K5: 0.01 | O5: 总计 | P5: 107855 | Q5: 37080
A6: 46173 | B6: 航帆增辉 | C6: 邹桥派出所 | D6: 1000 | E6: 1000 | F6: 46173 | G6: 王伟垫付 | H6: 航帆增辉
A7: 46172 | B7: 章德吉货运 | C7: 邹桥派出所 | D7: 280 | E7: 280 | F7: 46172 | G7: 王伟垫付 | H7: 章德吉货运
