Workbook

Sheet 首页
A1: =基础资料!$C$5&" · 建筑安装财务模板（消防改造 · 水电安装 · 强弱电）" -> 竣辉 · 建筑安装财务模板（消防改造 · 水电安装 · 强弱电） | Z1: =IF(AND(项目利润表!$B$7<>"",OR(N(项目利润表!$Q$7)<>0,N(项目利润表!$R$7)+N(项目利润表!$S$7)+N(项目利润表!$T$7)+N(项目利润表!$U$7)+N(项目利润表!$V$7)<>0)),N(项目利润表!$Z$7)+(61-1)/10000000,"") -> 504646.35
A2: 💡 平时只录蓝色那几张（资金流水、应付登记、考勤工资、发票、收入确认、代发抵账），其余全是自动的。下面黄格子选报表年度和截止月份（选那个月任意一天，报表都算到月底；空着＝最后一笔流水那个月），所有报表跟着变。 | Z2: =IF(AND(项目利润表!$B$8<>"",OR(N(项目利润表!$Q$8)<>0,N(项目利润表!$R$8)+N(项目利润表!$S$8)+N(项目利润表!$T$8)+N(项目利润表!$U$8)+N(项目利润表!$V$8)<>0)),N(项目利润表!$Z$8)+(61-2)/10000000,"") -> 522827.04
Z3: =IF(AND(项目利润表!$B$9<>"",OR(N(项目利润表!$Q$9)<>0,N(项目利润表!$R$9)+N(项目利润表!$S$9)+N(项目利润表!$T$9)+N(项目利润表!$U$9)+N(项目利润表!$V$9)<>0)),N(项目利润表!$Z$9)+(61-3)/10000000,"") -> 1099488.6
B4: 报表年度 | C4: 2026 | E4: 截止月份 | H4: =IF(N(C4)<_辅助!$J$6,"⚠ 早于建账年（"&_辅助!$J$6&"），没有数","报表到："&TEXT(_辅助!$J$9,"yyyy年m月d日")&"（截止日所在月的月底；最后一笔流水 "&TEXT(_辅助!$J$10,"m月d日")&"）") -> 报表到：2026年8月31日（截止日所在月的月底；最后一笔流水 8月28日） | Z4: =IF(AND(项目利润表!$B$10<>"",OR(N(项目利润表!$Q$10)<>0,N(项目利润表!$R$10)+N(项目利润表!$S$10)+N(项目利润表!$T$10)+N(项目利润表!$U$10)+N(项目利润表!$V$10)<>0)),N(项目利润表!$Z$10)+(61-4)/10000000,"") -> 211042.55
B5: ⚠ 现在表里是你原表的数（演示用）：原表只有「累计」数，建账日定在 2026-03-01，以前的都当期初；2026 年只有德安农商行总部录了产值确认，其他项目 3 月以后的产值确认、5～8 月的考勤都还没录，所以本年利润表只有成本、收入很少，工人显示「多发了」。补录【收入确认】【考勤工资】后就准了。正式用之前，看说明里「开始用自己的账」清空这几张表。 | Z5: =IF(AND(项目利润表!$B$11<>"",OR(N(项目利润表!$Q$11)<>0,N(项目利润表!$R$11)+N(项目利润表!$S$11)+N(项目利润表!$T$11)+N(项目利润表!$U$11)+N(项目利润表!$V$11)<>0)),N(项目利润表!$Z$11)+(61-5)/10000000,"") -> 1084.41
B6: 关键数（到截止月底） | Z6: =IF(AND(项目利润表!$B$12<>"",OR(N(项目利润表!$Q$12)<>0,N(项目利润表!$R$12)+N(项目利润表!$S$12)+N(项目利润表!$T$12)+N(项目利润表!$U$12)+N(项目利润表!$V$12)<>0)),N(项目利润表!$Z$12)+(61-6)/10000000,"") -> 111782.44
B7: =HYPERLINK("#'利润表'!A1","本年确认产值") -> 本年确认产值 | E7: =HYPERLINK("#'利润表'!A1","本年净利润") -> 本年净利润 | H7: =HYPERLINK("#'资金报表'!A1","银行＋现金余额") -> 银行＋现金余额 | K7: =HYPERLINK("#'应收账款总表'!A1","甲方还欠（应收净额）") -> 甲方还欠（应收净额） | Z7: =IF(AND(项目利润表!$B$13<>"",OR(N(项目利润表!$Q$13)<>0,N(项目利润表!$R$13)+N(项目利润表!$S$13)+N(项目利润表!$T$13)+N(项目利润表!$U$13)+N(项目利润表!$V$13)<>0)),N(项目利润表!$Z$13)+(61-7)/10000000,"") -> 241332.28
B8: =_月汇总!$O$3 -> 8992 | E8: =_月汇总!$O$3+_月汇总!$O$22-(_月汇总!$O$4+_月汇总!$O$5+_月汇总!$O$6+_月汇总!$O$7+_月汇总!$O$8+_月汇总!$O$9+_月汇总!$O$10+_月汇总!$O$11+_月汇总!$O$12+_月汇总!$O$13+_月汇总!$O$14+_月汇总!$O$15+_月汇总!$O$16+_月汇总!$O$17+_月汇总!$O$18+_月汇总!$O$19+_月汇总!$O$20+_月汇总!$O$21+_月汇总!$O$23+_月汇总!$O$24+_月汇总!$O$25) -> -506604.59 | H8: =资产负债表!$B$6 -> 690444.46 | K8: =SUM(_项目汇总!$AV$3:$AV$62) -> 3327665.1 | Z8: =IF(AND(项目利润表!$B$14<>"",OR(N(项目利润表!$Q$14)<>0,N(项目利润表!$R$14)+N(项目利润表!$S$14)+N(项目利润表!$T$14)+N(项目利润表!$U$14)+N(项目利润表!$V$14)<>0)),N(项目利润表!$Z$14)+(61-8)/10000000,"") -> 62175.08
B9: =HYPERLINK("#'应付账款总表'!A1","欠材料分包机械（应付净额）") -> 欠材料分包机械（应付净额） | E9: =HYPERLINK("#'工资汇总'!A1","欠工资（净额，含管理人员）") -> 欠工资（净额，含管理人员） | H9: =HYPERLINK("#'个人往来'!A1","公司欠老板/负责人（个人户）") -> 公司欠老板/负责人（个人户） | K9: =HYPERLINK("#'盈亏平衡表'!A1","全年保本产值") -> 全年保本产值 | Z9: =IF(AND(项目利润表!$B$15<>"",OR(N(项目利润表!$Q$15)<>0,N(项目利润表!$R$15)+N(项目利润表!$S$15)+N(项目利润表!$T$15)+N(项目利润表!$U$15)+N(项目利润表!$V$15)<>0)),N(项目利润表!$Z$15)+(61-9)/10000000,"") -> 510758.96
B10: =SUM(_余额!$C$3:$C$302) -> 403773.38 | E10: =SUM(_余额!$E$3:$E$302) -> 5312.59 | H10: =-SUMIFS(_余额!$S$3:$S$22,_余额!$Q$3:$Q$22,"个人户") -> 283527.6 | K10: =盈亏平衡表!$C$16 -> 526119.2 | Z10: =IF(AND(项目利润表!$B$16<>"",OR(N(项目利润表!$Q$16)<>0,N(项目利润表!$R$16)+N(项目利润表!$S$16)+N(项目利润表!$T$16)+N(项目利润表!$U$16)+N(项目利润表!$V$16)<>0)),N(项目利润表!$Z$16)+(61-10)/10000000,"") -> 5965.21
B11: ="安全边际："&IF(ISNUMBER(盈亏平衡表!$C$22),TEXT(盈亏平衡表!$C$22,"0%"),"-")&" "&盈亏平衡表!$C$24 -> 安全边际：-2825% 照现在的速度，今年产值约 2 万，还差 51 万产值才保本 | Z11: =IF(AND(项目利润表!$B$17<>"",OR(N(项目利润表!$Q$17)<>0,N(项目利润表!$R$17)+N(项目利润表!$S$17)+N(项目利润表!$T$17)+N(项目利润表!$U$17)+N(项目利润表!$V$17)<>0)),N(项目利润表!$Z$17)+(61-11)/10000000,"") -> -9493.87
Z12: =IF(AND(项目利润表!$B$18<>"",OR(N(项目利润表!$Q$18)<>0,N(项目利润表!$R$18)+N(项目利润表!$S$18)+N(项目利润表!$T$18)+N(项目利润表!$U$18)+N(项目利润表!$V$18)<>0)),N(项目利润表!$Z$18)+(61-12)/10000000,"")
B13: 赚得最多的 5 个项目（开工至今） | H13: 亏得最多 / 赚得最少的 5 个项目 | Z13: =IF(AND(项目利润表!$B$19<>"",OR(N(项目利润表!$Q$19)<>0,N(项目利润表!$R$19)+N(项目利润表!$S$19)+N(项目利润表!$T$19)+N(项目利润表!$U$19)+N(项目利润表!$V$19)<>0)),N(项目利润表!$Z$19)+(61-13)/10000000,"")
B14: 项目 | C14: 净利 | E14: 确认产值 | F14: 净利率 | H14: 项目 | I14: 净利 | K14: 确认产值 | L14: 净利率 | Z14: =IF(AND(项目利润表!$B$20<>"",OR(N(项目利润表!$Q$20)<>0,N(项目利润表!$R$20)+N(项目利润表!$S$20)+N(项目利润表!$T$20)+N(项目利润表!$U$20)+N(项目利润表!$V$20)<>0)),N(项目利润表!$Z$20)+(61-14)/10000000,"") -> -2500
B15: =IF(IFERROR(MATCH(LARGE($Z$1:$Z$60,1),$Z$1:$Z$60,0),0)=0,"",INDEX(项目利润表!$B$7:$B$66,IFERROR(MATCH(LARGE($Z$1:$Z$60,1),$Z$1:$Z$60,0),0))) -> 九安架空层 | C15: =IF(IFERROR(MATCH(LARGE($Z$1:$Z$60,1),$Z$1:$Z$60,0),0)=0,"",INDEX(项目利润表!$Z$7:$Z$66,IFERROR(MATCH(LARGE($Z$1:$Z$60,1),$Z$1:$Z$60,0),0))) -> 1099488.6 | E15: =IF(IFERROR(MATCH(LARGE($Z$1:$Z$60,1),$Z$1:$Z$60,0),0)=0,"",INDEX(项目利润表!$Q$7:$Q$66,IFERROR(MATCH(LARGE($Z$1:$Z$60,1),$Z$1:$Z$60,0),0))) -> 1500000 | F15: =IF(IFERROR(MATCH(LARGE($Z$1:$Z$60,1),$Z$1:$Z$60,0),0)=0,"",INDEX(项目利润表!$AA$7:$AA$66,IFERROR(MATCH(LARGE($Z$1:$Z$60,1),$Z$1:$Z$60,0),0))) -> 0.73299237 | H15: =IF(IF(1>COUNT($Z$1:$Z$60)-5,0,IFERROR(MATCH(SMALL($Z$1:$Z$60,1),$Z$1:$Z$60,0),0))=0,"",INDEX(项目利润表!$B$7:$B$66,IF(1>COUNT($Z$1:$Z$60)-5,0,IFERROR(MATCH(SMALL($Z$1:$Z$60,1),$Z$1:$Z$60,0),0)))) -> 吴山政府项目 | I15: =IF(IF(1>COUNT($Z$1:$Z$60)-5,0,IFERROR(MATCH(SMALL($Z$1:$Z$60,1),$Z$1:$Z$60,0),0))=0,"",INDEX(项目利润表!$Z$7:$Z$66,IF(1>COUNT($Z$1:$Z$60)-5,0,IFERROR(MATCH(SMALL($Z$1:$Z$60,1),$Z$1:$Z$60,0),0)))) -> -56647.98 | K15: =IF(IF(1>COUNT($Z$1:$Z$60)-5,0,IFERROR(MATCH(SMALL($Z$1:$Z$60,1),$Z$1:$Z$60,0),0))=0,"",INDEX(项目利润表!$Q$7:$Q$66,IF(1>COUNT($Z$1:$Z$60)-5,0,IFERROR(MATCH(SMALL($Z$1:$Z$60,1),$Z$1:$Z$60,0),0)))) -> 0 | L15: =IF(IF(1>COUNT($Z$1:$Z$60)-5,0,IFERROR(MATCH(SMALL($Z$1:$Z$60,1),$Z$1:$Z$60,0),0))=0,"",INDEX(项目利润表!$AA$7:$AA$66,IF(1>COUNT($Z$1:$Z$60)-5,0,IFERROR(MATCH(SMALL($Z$1:$Z$60,1),$Z$1:$Z$60,0),0)))) | Z15: =IF(AND(项目利润表!$B$21<>"",OR(N(项目利润表!$Q$21)<>0,N(项目利润表!$R$21)+N(项目利润表!$S$21)+N(项目利润表!$T$21)+N(项目利润表!$U$21)+N(项目利润表!$V$21)<>0)),N(项目利润表!$Z$21)+(61-15)/10000000,"")
B16: =IF(IFERROR(MATCH(LARGE($Z$1:$Z$60,2),$Z$1:$Z$60,0),0)=0,"",INDEX(项目利润表!$B$7:$B$66,IFERROR(MATCH(LARGE($Z$1:$Z$60,2),$Z$1:$Z$60,0),0))) -> 科创中心 | C16: =IF(IFERROR(MATCH(LARGE($Z$1:$Z$60,2),$Z$1:$Z$60,0),0)=0,"",INDEX(项目利润表!$Z$7:$Z$66,IFERROR(MATCH(LARGE($Z$1:$Z$60,2),$Z$1:$Z$60,0),0))) -> 522827.04 | E16: =IF(IFERROR(MATCH(LARGE($Z$1:$Z$60,2),$Z$1:$Z$60,0),0)=0,"",INDEX(项目利润表!$Q$7:$Q$66,IFERROR(MATCH(LARGE($Z$1:$Z$60,2),$Z$1:$Z$60,0),0))) -> 1641809 | F16: =IF(IFERROR(MATCH(LARGE($Z$1:$Z$60,2),$Z$1:$Z$60,0),0)=0,"",INDEX(项目利润表!$AA$7:$AA$66,IFERROR(MATCH(LARGE($Z$1:$Z$60,2),$Z$1:$Z$60,0),0))) -> 0.31844571 | H16: =IF(IF(2>COUNT($Z$1:$Z$60)-5,0,IFERROR(MATCH(SMALL($Z$1:$Z$60,2),$Z$1:$Z$60,0),0))=0,"",INDEX(项目利润表!$B$7:$B$66,IF(2>COUNT($Z$1:$Z$60)-5,0,IFERROR(MATCH(SMALL($Z$1:$Z$60,2),$Z$1:$Z$60,0),0)))) -> 示范园 | I16: =IF(IF(2>COUNT($Z$1:$Z$60)-5,0,IFERROR(MATCH(SMALL($Z$1:$Z$60,2),$Z$1:$Z$60,0),0))=0,"",INDEX(项目利润表!$Z$7:$Z$66,IF(2>COUNT($Z$1:$Z$60)-5,0,IFERROR(MATCH(SMALL($Z$1:$Z$60,2),$Z$1:$Z$60,0),0)))) -> -9493.87 | K16: =IF(IF(2>COUNT($Z$1:$Z$60)-5,0,IFERROR(MATCH(SMALL($Z$1:$Z$60,2),$Z$1:$Z$60,0),0))=0,"",INDEX(项目利润表!$Q$7:$Q$66,IF(2>COUNT($Z$1:$Z$60)-5,0,IFERROR(MATCH(SMALL($Z$1:$Z$60,2),$Z$1:$Z$60,0),0)))) -> 0 | L16: =IF(IF(2>COUNT($Z$1:$Z$60)-5,0,IFERROR(MATCH(SMALL($Z$1:$Z$60,2),$Z$1:$Z$60,0),0))=0,"",INDEX(项目利润表!$AA$7:$AA$66,IF(2>COUNT($Z$1:$Z$60)-5,0,IFERROR(MATCH(SMALL($Z$1:$Z$60,2),$Z$1:$Z$60,0),0)))) | Z16: =IF(AND(项目利润表!$B$22<>"",OR(N(项目利润表!$Q$22)<>0,N(项目利润表!$R$22)+N(项目利润表!$S$22)+N(项目利润表!$T$22)+N(项目利润表!$U$22)+N(项目利润表!$V$22)<>0)),N(项目利润表!$Z$22)+(61-16)/10000000,"") -> -56647.98
B17: =IF(IFERROR(MATCH(LARGE($Z$1:$Z$60,3),$Z$1:$Z$60,0),0)=0,"",INDEX(项目利润表!$B$7:$B$66,IFERROR(MATCH(LARGE($Z$1:$Z$60,3),$Z$1:$Z$60,0),0))) -> 博河科创中心 | C17: =IF(IFERROR(MATCH(LARGE($Z$1:$Z$60,3),$Z$1:$Z$60,0),0)=0,"",INDEX(项目利润表!$Z$7:$Z$66,IFERROR(MATCH(LARGE($Z$1:$Z$60,3),$Z$1:$Z$60,0),0))) -> 510758.96 | E17: =IF(IFERROR(MATCH(LARGE($Z$1:$Z$60,3),$Z$1:$Z$60,0),0)=0,"",INDEX(项目利润表!$Q$7:$Q$66,IFERROR(MATCH(LARGE($Z$1:$Z$60,3),$Z$1:$Z$60,0),0))) -> 510758.96 | F17: =IF(IFERROR(MATCH(LARGE($Z$1:$Z$60,3),$Z$1:$Z$60,0),0)=0,"",INDEX(项目利润表!$AA$7:$AA$66,IFERROR(MATCH(LARGE($Z$1:$Z$60,3),$Z$1:$Z$60,0),0))) -> 1 | H17: =IF(IF(3>COUNT($Z$1:$Z$60)-5,0,IFERROR(MATCH(SMALL($Z$1:$Z$60,3),$Z$1:$Z$60,0),0))=0,"",INDEX(项目利润表!$B$7:$B$66,IF(3>COUNT($Z$1:$Z$60)-5,0,IFERROR(MATCH(SMALL($Z$1:$Z$60,3),$Z$1:$Z$60,0),0)))) -> 隆世光伏 | I17: =IF(IF(3>COUNT($Z$1:$Z$60)-5,0,IFERROR(MATCH(SMALL($Z$1:$Z$60,3),$Z$1:$Z$60,0),0))=0,"",INDEX(项目利润表!$Z$7:$Z$66,IF(3>COUNT($Z$1:$Z$60)-5,0,IFERROR(MATCH(SMALL($Z$1:$Z$60,3),$Z$1:$Z$60,0),0)))) -> -2500 | K17: =IF(IF(3>COUNT($Z$1:$Z$60)-5,0,IFERROR(MATCH(SMALL($Z$1:$Z$60,3),$Z$1:$Z$60,0),0))=0,"",INDEX(项目利润表!$Q$7:$Q$66,IF(3>COUNT($Z$1:$Z$60)-5,0,IFERROR(MATCH(SMALL($Z$1:$Z$60,3),$Z$1:$Z$60,0),0)))) -> 0 | L17: =IF(IF(3>COUNT($Z$1:$Z$60)-5,0,IFERROR(MATCH(SMALL($Z$1:$Z$60,3),$Z$1:$Z$60,0),0))=0,"",INDEX(项目利润表!$AA$7:$AA$66,IF(3>COUNT($Z$1:$Z$60)-5,0,IFERROR(MATCH(SMALL($Z$1:$Z$60,3),$Z$1:$Z$60,0),0)))) | Z17: =IF(AND(项目利润表!$B$23<>"",OR(N(项目利润表!$Q$23)<>0,N(项目利润表!$R$23)+N(项目利润表!$S$23)+N(项目利润表!$T$23)+N(项目利润表!$U$23)+N(项目利润表!$V$23)<>0)),N(项目利润表!$Z$23)+(61-17)/10000000,"")
B18: =IF(IFERROR(MATCH(LARGE($Z$1:$Z$60,4),$Z$1:$Z$60,0),0)=0,"",INDEX(项目利润表!$B$7:$B$66,IFERROR(MATCH(LARGE($Z$1:$Z$60,4),$Z$1:$Z$60,0),0))) -> 德安养老中心 | C18: =IF(IFERROR(MATCH(LARGE($Z$1:$Z$60,4),$Z$1:$Z$60,0),0)=0,"",INDEX(项目利润表!$Z$7:$Z$66,IFERROR(MATCH(LARGE($Z$1:$Z$60,4),$Z$1:$Z$60,0),0))) -> 504646.35 | E18: =IF(IFERROR(MATCH(LARGE($Z$1:$Z$60,4),$Z$1:$Z$60,0),0)=0,"",INDEX(项目利润表!$Q$7:$Q$66,IFERROR(MATCH(LARGE($Z$1:$Z$60,4),$Z$1:$Z$60,0),0))) -> 4362576.5 | F18: =IF(IFERROR(MATCH(LARGE($Z$1:$Z$60,4),$Z$1:$Z$60,0),0)=0,"",INDEX(项目利润表!$AA$7:$AA$66,IFERROR(MATCH(LARGE($Z$1:$Z$60,4),$Z$1:$Z$60,0),0))) -> 0.11567622 | H18: =IF(IF(4>COUNT($Z$1:$Z$60)-5,0,IFERROR(MATCH(SMALL($Z$1:$Z$60,4),$Z$1:$Z$60,0),0))=0,"",INDEX(项目利润表!$B$7:$B$66,IF(4>COUNT($Z$1:$Z$60)-5,0,IFERROR(MATCH(SMALL($Z$1:$Z$60,4),$Z$1:$Z$60,0),0)))) -> 邹桥派出所 | I18: =IF(IF(4>COUNT($Z$1:$Z$60)-5,0,IFERROR(MATCH(SMALL($Z$1:$Z$60,4),$Z$1:$Z$60,0),0))=0,"",INDEX(项目利润表!$Z$7:$Z$66,IF(4>COUNT($Z$1:$Z$60)-5,0,IFERROR(MATCH(SMALL($Z$1:$Z$60,4),$Z$1:$Z$60,0),0)))) -> 1084.41 | K18: =IF(IF(4>COUNT($Z$1:$Z$60)-5,0,IFERROR(MATCH(SMALL($Z$1:$Z$60,4),$Z$1:$Z$60,0),0))=0,"",INDEX(项目利润表!$Q$7:$Q$66,IF(4>COUNT($Z$1:$Z$60)-5,0,IFERROR(MATCH(SMALL($Z$1:$Z$60,4),$Z$1:$Z$60,0),0)))) -> 95560.56 | L18: =IF(IF(4>COUNT($Z$1:$Z$60)-5,0,IFERROR(MATCH(SMALL($Z$1:$Z$60,4),$Z$1:$Z$60,0),0))=0,"",INDEX(项目利润表!$AA$7:$AA$66,IF(4>COUNT($Z$1:$Z$60)-5,0,IFERROR(MATCH(SMALL($Z$1:$Z$60,4),$Z$1:$Z$60,0),0)))) -> 0.011347882 | Z18: =IF(AND(项目利润表!$B$24<>"",OR(N(项目利润表!$Q$24)<>0,N(项目利润表!$R$24)+N(项目利润表!$S$24)+N(项目利润表!$T$24)+N(项目利润表!$U$24)+N(项目利润表!$V$24)<>0)),N(项目利润表!$Z$24)+(61-18)/10000000,"")
B19: =IF(IFERROR(MATCH(LARGE($Z$1:$Z$60,5),$Z$1:$Z$60,0),0)=0,"",INDEX(项目利润表!$B$7:$B$66,IFERROR(MATCH(LARGE($Z$1:$Z$60,5),$Z$1:$Z$60,0),0))) -> 抚州8号楼 | C19: =IF(IFERROR(MATCH(LARGE($Z$1:$Z$60,5),$Z$1:$Z$60,0),0)=0,"",INDEX(项目利润表!$Z$7:$Z$66,IFERROR(MATCH(LARGE($Z$1:$Z$60,5),$Z$1:$Z$60,0),0))) -> 241332.28 | E19: =IF(IFERROR(MATCH(LARGE($Z$1:$Z$60,5),$Z$1:$Z$60,0),0)=0,"",INDEX(项目利润表!$Q$7:$Q$66,IFERROR(MATCH(LARGE($Z$1:$Z$60,5),$Z$1:$Z$60,0),0))) -> 960000 | F19: =IF(IFERROR(MATCH(LARGE($Z$1:$Z$60,5),$Z$1:$Z$60,0),0)=0,"",INDEX(项目利润表!$AA$7:$AA$66,IFERROR(MATCH(LARGE($Z$1:$Z$60,5),$Z$1:$Z$60,0),0))) -> 0.25138779 | H19: =IF(IF(5>COUNT($Z$1:$Z$60)-5,0,IFERROR(MATCH(SMALL($Z$1:$Z$60,5),$Z$1:$Z$60,0),0))=0,"",INDEX(项目利润表!$B$7:$B$66,IF(5>COUNT($Z$1:$Z$60)-5,0,IFERROR(MATCH(SMALL($Z$1:$Z$60,5),$Z$1:$Z$60,0),0)))) -> 德安农商行总部 | I19: =IF(IF(5>COUNT($Z$1:$Z$60)-5,0,IFERROR(MATCH(SMALL($Z$1:$Z$60,5),$Z$1:$Z$60,0),0))=0,"",INDEX(项目利润表!$Z$7:$Z$66,IF(5>COUNT($Z$1:$Z$60)-5,0,IFERROR(MATCH(SMALL($Z$1:$Z$60,5),$Z$1:$Z$60,0),0)))) -> 5965.21 | K19: =IF(IF(5>COUNT($Z$1:$Z$60)-5,0,IFERROR(MATCH(SMALL($Z$1:$Z$60,5),$Z$1:$Z$60,0),0))=0,"",INDEX(项目利润表!$Q$7:$Q$66,IF(5>COUNT($Z$1:$Z$60)-5,0,IFERROR(MATCH(SMALL($Z$1:$Z$60,5),$Z$1:$Z$60,0),0)))) -> 8992 | L19: =IF(IF(5>COUNT($Z$1:$Z$60)-5,0,IFERROR(MATCH(SMALL($Z$1:$Z$60,5),$Z$1:$Z$60,0),0))=0,"",INDEX(项目利润表!$AA$7:$AA$66,IF(5>COUNT($Z$1:$Z$60)-5,0,IFERROR(MATCH(SMALL($Z$1:$Z$60,5),$Z$1:$Z$60,0),0)))) -> 0.66339079 | Z19: =IF(AND(项目利润表!$B$25<>"",OR(N(项目利润表!$Q$25)<>0,N(项目利润表!$R$25)+N(项目利润表!$S$25)+N(项目利润表!$T$25)+N(项目利润表!$U$25)+N(项目利润表!$V$25)<>0)),N(项目利润表!$Z$25)+(61-19)/10000000,"")
Z20: =IF(AND(项目利润表!$B$26<>"",OR(N(项目利润表!$Q$26)<>0,N(项目利润表!$R$26)+N(项目利润表!$S$26)+N(项目利润表!$T$26)+N(项目利润表!$U$26)+N(项目利润表!$V$26)<>0)),N(项目利润表!$Z$26)+(61-20)/10000000,"")
B21: 提醒 | Z21: =IF(AND(项目利润表!$B$27<>"",OR(N(项目利润表!$Q$27)<>0,N(项目利润表!$R$27)+N(项目利润表!$S$27)+N(项目利润表!$T$27)+N(项目利润表!$U$27)+N(项目利润表!$V$27)<>0)),N(项目利润表!$Z$27)+(61-21)/10000000,"")
B22: ="数据校验：要改 "&COUNTIF(数据校验!$D$5:$D$45,"✗")&" 项、要看 "&COUNTIF(数据校验!$D$5:$D$45,"⚠")&" 项"&IF(COUNTIF(数据校验!$D$5:$D$45,"✗")+COUNTIF(数据校验!$D$5:$D$45,"⚠")=0,"，都没问题 √"," → 点这里去看") -> 数据校验：要改 1 项、要看 4 项 → 点这里去看 | Z22: =IF(AND(项目利润表!$B$28<>"",OR(N(项目利润表!$Q$28)<>0,N(项目利润表!$R$28)+N(项目利润表!$S$28)+N(项目利润表!$T$28)+N(项目利润表!$U$28)+N(项目利润表!$V$28)<>0)),N(项目利润表!$Z$28)+(61-22)/10000000,"")
B23: =IF(N(数据校验!$C$5)>0,"资金流水有 "&数据校验!$C$5&" 行要改（没认出类别、项目或单位）","资金流水都认出来了 √") -> 资金流水有 7 行要改（没认出类别、项目或单位） | Z23: =IF(AND(项目利润表!$B$29<>"",OR(N(项目利润表!$Q$29)<>0,N(项目利润表!$R$29)+N(项目利润表!$S$29)+N(项目利润表!$T$29)+N(项目利润表!$U$29)+N(项目利润表!$V$29)<>0)),N(项目利润表!$Z$29)+(61-23)/10000000,"")
B24: =IF(N(数据校验!$C$26)>0,数据校验!$C$26&" 个项目要注意：成本花得多产值确认得少（该找甲方报量）、完工没结算或亏损 → 看【项目利润表】提示","") -> 7 个项目要注意：成本花得多产值确认得少（该找甲方报量）、完工没结算或亏损 → 看【项目利润表】提示 | Z24: =IF(AND(项目利润表!$B$30<>"",OR(N(项目利润表!$Q$30)<>0,N(项目利润表!$R$30)+N(项目利润表!$S$30)+N(项目利润表!$T$30)+N(项目利润表!$U$30)+N(项目利润表!$V$30)<>0)),N(项目利润表!$Z$30)+(61-24)/10000000,"")
B25: =IF(COUNTIF(应收账款总表!$Y$6:$Y$65,"质保金*")>0,COUNTIF(应收账款总表!$Y$6:$Y$65,"质保金*")&" 个项目质保金到期可以催了","")&IF(N(应收账款总表!$L$4)>0," 开了票没回款的 "&TEXT(应收账款总表!$L$4,"#,##0")&" 元","") -> 开了票没回款的 135,732 元 | Z25: =IF(AND(项目利润表!$B$31<>"",OR(N(项目利润表!$Q$31)<>0,N(项目利润表!$R$31)+N(项目利润表!$S$31)+N(项目利润表!$T$31)+N(项目利润表!$U$31)+N(项目利润表!$V$31)<>0)),N(项目利润表!$Z$31)+(61-25)/10000000,"")
B26: =IF(N(数据校验!$C$15)>0,数据校验!$C$15&" 个管理人员有月份没录考勤（管理费会少算）","") -> 5 个管理人员有月份没录考勤（管理费会少算） | Z26: =IF(AND(项目利润表!$B$32<>"",OR(N(项目利润表!$Q$32)<>0,N(项目利润表!$R$32)+N(项目利润表!$S$32)+N(项目利润表!$T$32)+N(项目利润表!$U$32)+N(项目利润表!$V$32)<>0)),N(项目利润表!$Z$32)+(61-26)/10000000,"")
B27: =IF(ABS(N(数据校验!$C$17))>0.01,"账户余额跟银行 App 对不上，差 "&TEXT(数据校验!$C$17,"#,##0.00"),"") | Z27: =IF(AND(项目利润表!$B$33<>"",OR(N(项目利润表!$Q$33)<>0,N(项目利润表!$R$33)+N(项目利润表!$S$33)+N(项目利润表!$T$33)+N(项目利润表!$U$33)+N(项目利润表!$V$33)<>0)),N(项目利润表!$Z$33)+(61-27)/10000000,"")
Z28: =IF(AND(项目利润表!$B$34<>"",OR(N(项目利润表!$Q$34)<>0,N(项目利润表!$R$34)+N(项目利润表!$S$34)+N(项目利润表!$T$34)+N(项目利润表!$U$34)+N(项目利润表!$V$34)<>0)),N(项目利润表!$Z$34)+(61-28)/10000000,"")
B29: 各张表（点名字跳过去；每张表右上角有「← 回首页」） | Z29: =IF(AND(项目利润表!$B$35<>"",OR(N(项目利润表!$Q$35)<>0,N(项目利润表!$R$35)+N(项目利润表!$S$35)+N(项目利润表!$T$35)+N(项目利润表!$U$35)+N(项目利润表!$V$35)<>0)),N(项目利润表!$Z$35)+(61-29)/10000000,"")
B30: 每天 / 每笔录 | Z30: =IF(AND(项目利润表!$B$36<>"",OR(N(项目利润表!$Q$36)<>0,N(项目利润表!$R$36)+N(项目利润表!$S$36)+N(项目利润表!$T$36)+N(项目利润表!$U$36)+N(项目利润表!$V$36)<>0)),N(项目利润表!$Z$36)+(61-30)/10000000,"")
B31: 资金流水 | C31: 银行、现金、老板个人户的每一笔收支（摘要里的项目、单位、类别自动认） | H31: 应付登记 | I31: 跟材料商、分包、机械对了账就登记应付（付款在流水里记） | Z31: =IF(AND(项目利润表!$B$37<>"",OR(N(项目利润表!$Q$37)<>0,N(项目利润表!$R$37)+N(项目利润表!$S$37)+N(项目利润表!$T$37)+N(项目利润表!$U$37)+N(项目利润表!$V$37)<>0)),N(项目利润表!$Z$37)+(61-31)/10000000,"")
B32: 考勤工资 | C32: 每人每月一行：在哪个工地干了几天，工资自动算 | H32: 发票登记 | I32: 电子税务局导出的发票整块粘进来 | Z32: =IF(AND(项目利润表!$B$38<>"",OR(N(项目利润表!$Q$38)<>0,N(项目利润表!$R$38)+N(项目利润表!$S$38)+N(项目利润表!$T$38)+N(项目利润表!$U$38)+N(项目利润表!$V$38)<>0)),N(项目利润表!$Z$38)+(61-32)/10000000,"")
B33: 收入确认 | C33: 甲方/总包确认的产值、结算（收入按这里算） | H33: 代发抵账 | I33: 总包代发工资、代付款、甲供材、甲方扣款 | Z33: =IF(AND(项目利润表!$B$39<>"",OR(N(项目利润表!$Q$39)<>0,N(项目利润表!$R$39)+N(项目利润表!$S$39)+N(项目利润表!$T$39)+N(项目利润表!$U$39)+N(项目利润表!$V$39)<>0)),N(项目利润表!$Z$39)+(61-33)/10000000,"")
B34: 档案（偶尔改） | Z34: =IF(AND(项目利润表!$B$40<>"",OR(N(项目利润表!$Q$40)<>0,N(项目利润表!$R$40)+N(项目利润表!$S$40)+N(项目利润表!$T$40)+N(项目利润表!$U$40)+N(项目利润表!$V$40)<>0)),N(项目利润表!$Z$40)+(61-34)/10000000,"")
B35: 项目档案 | C35: 一个工地一行：合同额、甲方、开工完工、摘要关键词 | H35: 往来单位 | I35: 甲方、材料商、分包、机械、工人、老板都在这一张 | Z35: =IF(AND(项目利润表!$B$41<>"",OR(N(项目利润表!$Q$41)<>0,N(项目利润表!$R$41)+N(项目利润表!$S$41)+N(项目利润表!$T$41)+N(项目利润表!$U$41)+N(项目利润表!$V$41)<>0)),N(项目利润表!$Z$41)+(61-35)/10000000,"")
B36: 工资标准 | C36: 日工资、月薪；涨工资加一行 | H36: 期初余额 | I36: 建账日以前的数，只填一次 | Z36: =IF(AND(项目利润表!$B$42<>"",OR(N(项目利润表!$Q$42)<>0,N(项目利润表!$R$42)+N(项目利润表!$S$42)+N(项目利润表!$T$42)+N(项目利润表!$U$42)+N(项目利润表!$V$42)<>0)),N(项目利润表!$Z$42)+(61-36)/10000000,"")
B37: 基础资料 | C37: 公司、资金账户、收支类别、关键词、税率、固定资产 | Z37: =IF(AND(项目利润表!$B$43<>"",OR(N(项目利润表!$Q$43)<>0,N(项目利润表!$R$43)+N(项目利润表!$S$43)+N(项目利润表!$T$43)+N(项目利润表!$U$43)+N(项目利润表!$V$43)<>0)),N(项目利润表!$Z$43)+(61-37)/10000000,"")
B38: 查看（自动） | Z38: =IF(AND(项目利润表!$B$44<>"",OR(N(项目利润表!$Q$44)<>0,N(项目利润表!$R$44)+N(项目利润表!$S$44)+N(项目利润表!$T$44)+N(项目利润表!$U$44)+N(项目利润表!$V$44)<>0)),N(项目利润表!$Z$44)+(61-38)/10000000,"")
B39: 账户明细 | C39: 选一个账户看每一笔和余额 | H39: 资金报表 | I39: 资金周报 / 月报 | Z39: =IF(AND(项目利润表!$B$45<>"",OR(N(项目利润表!$Q$45)<>0,N(项目利润表!$R$45)+N(项目利润表!$S$45)+N(项目利润表!$T$45)+N(项目利润表!$U$45)+N(项目利润表!$V$45)<>0)),N(项目利润表!$Z$45)+(61-39)/10000000,"")
B40: 应收账款总表 | C40: 每个项目甲方还欠多少、欠了多久 | H40: 应付账款总表 | I40: 欠材料商、分包、机械多少，对账单 | Z40: =IF(AND(项目利润表!$B$46<>"",OR(N(项目利润表!$Q$46)<>0,N(项目利润表!$R$46)+N(项目利润表!$S$46)+N(项目利润表!$T$46)+N(项目利润表!$U$46)+N(项目利润表!$V$46)<>0)),N(项目利润表!$Z$46)+(61-40)/10000000,"")
B41: 个人往来 | C41: 老板、负责人垫了多少、公司欠他多少；保证金押金台账 | H41: 工资表 | I41: 选月份出工资表 | Z41: =IF(AND(项目利润表!$B$47<>"",OR(N(项目利润表!$Q$47)<>0,N(项目利润表!$R$47)+N(项目利润表!$S$47)+N(项目利润表!$T$47)+N(项目利润表!$U$47)+N(项目利润表!$V$47)<>0)),N(项目利润表!$Z$47)+(61-41)/10000000,"")
B42: 工资汇总 | C42: 每人本年应发、已发、欠薪 | H42: 用工成本表 | I42: 各项目每月人工 | Z42: =IF(AND(项目利润表!$B$48<>"",OR(N(项目利润表!$Q$48)<>0,N(项目利润表!$R$48)+N(项目利润表!$S$48)+N(项目利润表!$T$48)+N(项目利润表!$U$48)+N(项目利润表!$V$48)<>0)),N(项目利润表!$Z$48)+(61-42)/10000000,"")
B43: 发票统计 | C43: 开票、收票、欠票 | Z43: =IF(AND(项目利润表!$B$49<>"",OR(N(项目利润表!$Q$49)<>0,N(项目利润表!$R$49)+N(项目利润表!$S$49)+N(项目利润表!$T$49)+N(项目利润表!$U$49)+N(项目利润表!$V$49)<>0)),N(项目利润表!$Z$49)+(61-43)/10000000,"")
B44: 项目（自动） | Z44: =IF(AND(项目利润表!$B$50<>"",OR(N(项目利润表!$Q$50)<>0,N(项目利润表!$R$50)+N(项目利润表!$S$50)+N(项目利润表!$T$50)+N(项目利润表!$U$50)+N(项目利润表!$V$50)<>0)),N(项目利润表!$Z$50)+(61-44)/10000000,"")
B45: 项目账 | C45: 选一个项目看全部明细（不用每个项目做一张表） | H45: 项目利润表 | I45: 全部项目本年和开工至今的利润 | Z45: =IF(AND(项目利润表!$B$51<>"",OR(N(项目利润表!$Q$51)<>0,N(项目利润表!$R$51)+N(项目利润表!$S$51)+N(项目利润表!$T$51)+N(项目利润表!$U$51)+N(项目利润表!$V$51)<>0)),N(项目利润表!$Z$51)+(61-45)/10000000,"")
B46: 费用分摊 | C46: 老板工资、公司开支怎么摊到项目 | Z46: =IF(AND(项目利润表!$B$52<>"",OR(N(项目利润表!$Q$52)<>0,N(项目利润表!$R$52)+N(项目利润表!$S$52)+N(项目利润表!$T$52)+N(项目利润表!$U$52)+N(项目利润表!$V$52)<>0)),N(项目利润表!$Z$52)+(61-46)/10000000,"")
B47: 老板报表（自动） | Z47: =IF(AND(项目利润表!$B$53<>"",OR(N(项目利润表!$Q$53)<>0,N(项目利润表!$R$53)+N(项目利润表!$S$53)+N(项目利润表!$T$53)+N(项目利润表!$U$53)+N(项目利润表!$V$53)<>0)),N(项目利润表!$Z$53)+(61-47)/10000000,"")
B48: 利润表 | C48: 按月的利润表 | H48: 资产负债表 | I48: 资产负债表 | Z48: =IF(AND(项目利润表!$B$54<>"",OR(N(项目利润表!$Q$54)<>0,N(项目利润表!$R$54)+N(项目利润表!$S$54)+N(项目利润表!$T$54)+N(项目利润表!$U$54)+N(项目利润表!$V$54)<>0)),N(项目利润表!$Z$54)+(61-48)/10000000,"")
B49: 盈亏平衡表 | C49: 保本产值、项目还能花多少、报价计算器 | H49: 数据校验 | I49: 哪里录错了、漏了 | Z49: =IF(AND(项目利润表!$B$55<>"",OR(N(项目利润表!$Q$55)<>0,N(项目利润表!$R$55)+N(项目利润表!$S$55)+N(项目利润表!$T$55)+N(项目利润表!$U$55)+N(项目利润表!$V$55)<>0)),N(项目利润表!$Z$55)+(61-49)/10000000,"")
Z50: =IF(AND(项目利润表!$B$56<>"",OR(N(项目利润表!$Q$56)<>0,N(项目利润表!$R$56)+N(项目利润表!$S$56)+N(项目利润表!$T$56)+N(项目利润表!$U$56)+N(项目利润表!$V$56)<>0)),N(项目利润表!$Z$56)+(61-50)/10000000,"")
B51: 怎么用（第一次看这里） | Z51: =IF(AND(项目利润表!$B$57<>"",OR(N(项目利润表!$Q$57)<>0,N(项目利润表!$R$57)+N(项目利润表!$S$57)+N(项目利润表!$T$57)+N(项目利润表!$U$57)+N(项目利润表!$V$57)<>0)),N(项目利润表!$Z$57)+(61-51)/10000000,"")
B52: ① 先填档案：【基础资料】公司全称、建账日期、资金账户（每个老板/负责人一个「个人户」）；【项目档案】每个工地一行；【往来单位】甲方、材料商、分包、机械、工人、老板；【工资标准】每人日工资/月薪。 | Z52: =IF(AND(项目利润表!$B$58<>"",OR(N(项目利润表!$Q$58)<>0,N(项目利润表!$R$58)+N(项目利润表!$S$58)+N(项目利润表!$T$58)+N(项目利润表!$U$58)+N(项目利润表!$V$58)<>0)),N(项目利润表!$Z$58)+(61-52)/10000000,"")
B53: ② 建账日以前的账：在【期初余额】填一次——每个老项目累计确认的产值、收款、成本；每家材料商/分包每个项目累计应付、已付；银行期初余额在【基础资料】②。 | Z53: =IF(AND(项目利润表!$B$59<>"",OR(N(项目利润表!$Q$59)<>0,N(项目利润表!$R$59)+N(项目利润表!$S$59)+N(项目利润表!$T$59)+N(项目利润表!$U$59)+N(项目利润表!$V$59)<>0)),N(项目利润表!$Z$59)+(61-53)/10000000,"")
B54: ③ 平时：每笔钱进出记【资金流水】（摘要写清楚项目和对象，类别自动认；认不出的在「改类别」选）；跟材料商/分包对了账记【应付登记】；每月月底录【考勤工资】。 | Z54: =IF(AND(项目利润表!$B$60<>"",OR(N(项目利润表!$Q$60)<>0,N(项目利润表!$R$60)+N(项目利润表!$S$60)+N(项目利润表!$T$60)+N(项目利润表!$U$60)+N(项目利润表!$V$60)<>0)),N(项目利润表!$Z$60)+(61-54)/10000000,"")
B55: ④ 甲方/总包确认了产值（报量批了、结算了）就记【收入确认】——利润按这个算，不按收钱算。总包代发工资、甲方扣款记【代发抵账】。发票每月从电子税务局导出粘到【发票登记】。 | Z55: =IF(AND(项目利润表!$B$61<>"",OR(N(项目利润表!$Q$61)<>0,N(项目利润表!$R$61)+N(项目利润表!$S$61)+N(项目利润表!$T$61)+N(项目利润表!$U$61)+N(项目利润表!$V$61)<>0)),N(项目利润表!$Z$61)+(61-55)/10000000,"")
B56: ⑤ 看报表：首页选年度；【项目账】选项目看明细；【项目利润表】看哪个项目赚哪个亏；【利润表】【资产负债表】【盈亏平衡表】给老板看。每年年底在【费用分摊】填定稿费率。 | Z56: =IF(AND(项目利润表!$B$62<>"",OR(N(项目利润表!$Q$62)<>0,N(项目利润表!$R$62)+N(项目利润表!$S$62)+N(项目利润表!$T$62)+N(项目利润表!$U$62)+N(项目利润表!$V$62)<>0)),N(项目利润表!$Z$62)+(61-56)/10000000,"")
B57: ⑥ 每月对一次账：【基础资料】② 填银行 App 上的实际余额，差额是 0 就对了；再看一眼【数据校验】有没有 ✗。 | Z57: =IF(AND(项目利润表!$B$63<>"",OR(N(项目利润表!$Q$63)<>0,N(项目利润表!$R$63)+N(项目利润表!$S$63)+N(项目利润表!$T$63)+N(项目利润表!$U$63)+N(项目利润表!$V$63)<>0)),N(项目利润表!$Z$63)+(61-57)/10000000,"")
B58: ⑦ 注意：记错了就清空那几格，不要删整行、插行（别的表按行取数，删行公式会出错）；灰色格子是公式，不要往里打字。 | Z58: =IF(AND(项目利润表!$B$64<>"",OR(N(项目利润表!$Q$64)<>0,N(项目利润表!$R$64)+N(项目利润表!$S$64)+N(项目利润表!$T$64)+N(项目利润表!$U$64)+N(项目利润表!$V$64)<>0)),N(项目利润表!$Z$64)+(61-58)/10000000,"")
Z59: =IF(AND(项目利润表!$B$65<>"",OR(N(项目利润表!$Q$65)<>0,N(项目利润表!$R$65)+N(项目利润表!$S$65)+N(项目利润表!$T$65)+N(项目利润表!$U$65)+N(项目利润表!$V$65)<>0)),N(项目利润表!$Z$65)+(61-59)/10000000,"")
Z60: =IF(AND(项目利润表!$B$66<>"",OR(N(项目利润表!$Q$66)<>0,N(项目利润表!$R$66)+N(项目利润表!$S$66)+N(项目利润表!$T$66)+N(项目利润表!$U$66)+N(项目利润表!$V$66)<>0)),N(项目利润表!$Z$66)+(61-60)/10000000,"")

Sheet 资金流水
A1: 资 金 流 水（所有账户一张表 · 每天录 · 自动认项目、类别、单位） | Q1: ← 回首页
A2: 💡 左边照原来录：日期、账户、摘要、收入、支出（收款记「收入」，付款记「支出」；银行退回来的钱在支出栏记负数也行，自动当冲回）。中间灰色是按摘要自动认出的 项目 / 收支类别 / 单位或人，看一眼对不对；不对或认不出，在右边黄格「改项目、改类别、改单位」选（改的优先）。几条规矩：①「代X付」（代老叶付佩力材料款）：单位是 X（冲 X 的账），真正收钱的写备注；② 一笔钱是几个项目的（隆世光伏/共青办公楼/德祥工地工程款），拆成几行分别记；③ 自己账户之间转钱（银行↔银行、银行↔老板个人户：借款、还款、报销、备用金）类别是「账户互转」，只记一边，对方账户自动认或在 O 列选；④ 老板、负责人替公司花的钱，记在他的个人户里（账户选他的个人户）。G 列是这个账户记到这一笔为止的余额。⑤ 记错的行清空内容就行，不要删整行、也不要插行（别的表按行取数）。
A3: 笔数 | B3: =COUNT(资金流水!$B$6:$B$2005) -> 217 | C3: 收入合计 | D3: =SUMIFS(资金流水!$R$6:$R$2005,资金流水!$AH$6:$AH$2005,"收",资金流水!$I$6:$I$2005,"<>账户互转") -> 1673903.2 | E3: 支出合计 | F3: =-SUMIFS(资金流水!$R$6:$R$2005,资金流水!$AH$6:$AH$2005,"支",资金流水!$I$6:$I$2005,"<>账户互转") -> 839466.34 | G3: 待处理 | H3: =COUNTIF(资金流水!$K$6:$K$2005,"✗*")&" 笔" -> 7 笔 | I3: 提醒 | J3: =COUNTIF(资金流水!$K$6:$K$2005,"⚠*")&" 笔" -> 0 笔 | K3: ="收支不含账户互转；容量 "&TEXT(B3/2000,"0%") -> 收支不含账户互转；容量 11%
A4: ① 照原来录 | G4: ② 自动认的（看对不对） | L4: ③ 不对才改（改的优先）
A5: 序号 | B5: 日期 | C5: 账户 | D5: 摘要 | E5: 收入 | F5: 支出 | G5: 结存 （本账户） | H5: 项目 | I5: 收支类别 | J5: 单位 / 人 | K5: 校验 | L5: 改项目 | M5: 改类别 | N5: 改单位/人 | O5: 对方账户 （互转） | P5: 备注 | R5: 净额 | S5: 年月 | T5: 认项目 | U5: 认类别 | V5: 认单位 | W5: 分摊归类 | X5: 报表项目 | Y5: 有应付 | Z5: 单位类型 | AA5: 走考勤的人 | AB5: 代X付 | AC5: 认对方账户 | AD5: 对方账户 | AE5: 账户类型 | AF5: 对方类型 | AG5: 关键词类别 | AH5: 收支 | AI5: 项目命中词 | AJ5: 别的项目 | AK5: 项目码 | AL5: 单位码 | AM5: 代付单位码 | AN5: 日期数 | AO5: 收款排号 | AP5: 付款排号 | AQ5: 押金排号
A6: =IF(AND(B6="",D6="",E6="",F6=""),"",ROW()-5) -> 1 | B6: 46143 | C6: 九江银行 | D6: 代吴群付向勇工资 | F6: 15000 | G6: =IF(C6="","",ROUND(IFERROR(INDEX(基础资料!$K$5:$K$24,MATCH(C6,基础资料!$G$5:$G$24,0)),0)+SUMIFS($R$6:R6,$C$6:C6,C6)-SUMIFS($R$6:R6,$AD$6:AD6,C6,$X$6:X6,"账户互转"),2)) -> -15000 | H6: =IF(L6<>"",L6,T6) | I6: =IF(M6<>"",M6,U6) -> 付应付款 | J6: =IF(N6<>"",N6,V6) -> 吴群 | K6: =IF(AND(B6="",D6="",E6="",F6=""),"",IF(C6="","✗ 没选账户",IF(AE6="","✗ 账户不在【基础资料】② 里",IF(NOT(ISNUMBER(B6)),"✗ 日期要填成日期（2026/5/1）",IF(AND(ISNUMBER(B6),B6<基础资料!$C$9),"✗ 日期早于建账日期（建账前的放【期初余额】）",IF(AND(N(E6)<>0,N(F6)<>0),"✗ 收入、支出只填一边",IF(R6=0,"✗ 没有金额",IF(I6="","✗ 认不出收支类别：在「改类别」选",IF(W6="？","✗ 收支类别不在【基础资料】③ 里",IF(OR(I6="管理人员工资",I6="折旧费"),"✗ 这一类是自动算的，流水里不能选（发工资选「工资」，买设备选「固定资产购置」）",IF(AND(OR(X6="材料费",X6="人工费",X6="分包费",X6="机械运输费",X6="其他直接费",X6="票据贴息",X6="应收账款"),H6=""),"✗ 这一笔要选项目（摘要里的项目没在【项目档案】的话先去加上）",IF(AND(H6<>"",COUNTIF(项目档案!$B$4:$B$63,H6)=0),"✗ 项目不在【项目档案】里",IF(AND(OR(IFERROR(INDEX(基础资料!$W$5:$W$64,MATCH(I6,基础资料!$S$5:$S$64,0))&"","")="人",IFERROR(INDEX(基础资料!$W$5:$W$64,MATCH(I6,基础资料!$S$5:$S$64,0))&"","")="单位"),J6=""),"✗ 这一笔要选是谁（改单位/人）",IF(AND(I6="付应付款",NOT(OR(Z6="材料供应商",Z6="分包",Z6="机械运输",Z6="其他"))),"✗ 付应付款要选材料商、分包或机械单位",IF(AND(I6="付应付款",Y6=0),"✗ 这家没有应付：先在【应付登记】登记（现买现付的选材料费等）",IF(AND(OR(I6="工资",I6="工资退回"),AA6=0),"✗ 工资要选管理人员或工人（临时工选「临时工工资」）",IF(AND(I6="账户互转",AD6=""),"✗ 账户互转要在「对方账户」选（借款、报销选那个人的个人户）",IF(AND(I6="账户互转",AF6=""),"✗ 对方账户不在【基础资料】② 里",IF(AND(I6="账户互转",AD6=C6),"✗ 对方账户不能是自己",IF(IF(I6="账户互转",COUNTIFS(资金流水!$C$6:$C$2005,AD6,资金流水!$AD$6:$AD$2005,C6,资金流水!$I$6:$I$2005,"账户互转",资金流水!$R$6:$R$2005,-R6)>0,FALSE),"✗ 对方账户那边也记了这笔互转（只记一边：清空其中一行的内容）",IF(AJ6>0,"⚠ 摘要里有两个项目：拆成几行，或在「改项目」选",IF(AND(I6<>"账户互转",O6<>""),"⚠ 填了对方账户但类别不是账户互转（对方账户不起作用）",IF(AND(J6<>"",Z6=""),"⚠ 单位/人没在【往来单位】登记",IF(AND(N(F6)<0,AH6="收"),"⚠ 这是收款，以后请记在收入栏",IF(N(E6)<0,"⚠ 收入填了负数，已按支出算",IF(N(F6)<0,"↩ 冲回（退款）",IF(AND(R6<0,I6<>"固定资产购置",I6<>"付应付款",ISNUMBER(B6),IFERROR(SUMPRODUCT(ISNUMBER(SEARCH(基础资料!$AJ$5:$AJ$34,D6))*(基础资料!$AJ$5:$AJ$34<>"")*((AN6-基础资料!$AK$5:$AK$34)<=30)*((AN6-基础资料!$AK$5:$AK$34)>=-30)),0)>0),"⚠ 像是在买【基础资料】⑥ 登记的车/设备：类别改成「固定资产购置」，不然成本算两遍",IF(AND(OR(I6="材料费",I6="分包费",I6="机械运输费",I6="其他直接费"),J6="",H6<>"",COUNTIFS(应付登记!$E$5:$E$1004,H6,应付登记!$G$5:$G$1004,-R6)>0),"⚠ 这个项目有同样金额的应付登记：是付那家的，改类别选「付应付款」、改单位选那家（不然成本算两遍）","√")))))))))))))))))))))))))))) -> √ | R6: =ROUND(N(E6)-N(F6),2) -> -15000 | S6: =IF(ISNUMBER(B6),YEAR(B6)*100+MONTH(B6),"") -> 202605 | T6: =IF(N(AK6)=0,"",INDEX(_辅助!$S$1:$S$240,AK6)) | U6: =IF(OR(D6="",R6=0),"",IF(AND(Z6="临时工",R6<0),"临时工工资",IF(AG6="",IF(AA6=1,"工资",IF(Z6="临时工","临时工工资",IF(Z6="甲方/总包","工程款",IF(AND(OR(Z6="材料供应商",Z6="分包",Z6="机械运输"),Y6=1),"付应付款","")))),IF(AND(Y6=1,OR(Z6="材料供应商",Z6="分包",Z6="机械运输",Z6="其他"),OR(AG6="材料费",AG6="分包费",AG6="机械运输费",AG6="其他直接费",AG6="工资",AG6="临时工工资")),"付应付款",AG6)))) -> 付应付款 | V6: =IF(D6="","",IF(N(AM6)>0,IF(N(AM6)=0,"",INDEX(_辅助!$W$1:$W$900,AM6)),IF(N(AL6)=0,"",INDEX(_辅助!$W$1:$W$900,AL6)))) -> 吴群 | W6: =IF(I6="","",IFERROR(INDEX(基础资料!$V$5:$V$64,MATCH(I6,基础资料!$S$5:$S$64,0))&"","？")) -> 不进利润 | X6: =IF(R6=0,"",IF(OR(I6="",IFERROR(INDEX(基础资料!$U$5:$U$64,MATCH(I6,基础资料!$S$5:$S$64,0))&"","")=""),"待分类",IF(OR(I6="付应付款",IFERROR(INDEX(基础资料!$U$5:$U$64,MATCH(I6,基础资料!$S$5:$S$64,0))&"","")="应付款"),IF(Z6="材料供应商","应付材料款",IF(Z6="分包","应付分包款",IF(Z6="机械运输","应付机械运输费","应付其他款"))),IFERROR(INDEX(基础资料!$U$5:$U$64,MATCH(I6,基础资料!$S$5:$S$64,0))&"","")))) -> 应付分包款 | Y6: =IF(J6="",0,IF(COUNTIF(应付登记!$D$5:$D$1004,J6)+COUNTIF(期初余额!$P$5:$P$204,J6)>0,1,0)) -> 1 | Z6: =IF(J6="","",IFERROR(INDEX(往来单位!$C$4:$C$303,MATCH(J6,往来单位!$B$4:$B$303,0))&"","")) -> 分包 | AA6: =IF(OR(Z6="管理人员",Z6="工人"),1,0) -> 0 | AB6: =IF(ISERROR(FIND("代",D6)),"",IFERROR(MID(D6,FIND("代",D6)+1,FIND("付",D6,FIND("代",D6))-FIND("代",D6)-1),"")) -> 吴群 | AC6: =IF(I6<>"账户互转","",IF(J6<>"",IFERROR(INDEX(_辅助!$G$1:$G$40,MATCH(J6,_辅助!$F$1:$F$40,0)),IF(IFERROR(MATCH(1,INDEX(ISNUMBER(SEARCH(_辅助!$Z$1:$Z$40,D6))*(_辅助!$Z$1:$Z$40<>""),0),0),0)=0,"",INDEX(_辅助!$AA$1:$AA$40,IFERROR(MATCH(1,INDEX(ISNUMBER(SEARCH(_辅助!$Z$1:$Z$40,D6))*(_辅助!$Z$1:$Z$40<>""),0),0),0)))),IF(IFERROR(MATCH(1,INDEX(ISNUMBER(SEARCH(_辅助!$Z$1:$Z$40,D6))*(_辅助!$Z$1:$Z$40<>""),0),0),0)=0,"",INDEX(_辅助!$AA$1:$AA$40,IFERROR(MATCH(1,INDEX(ISNUMBER(SEARCH(_辅助!$Z$1:$Z$40,D6))*(_辅助!$Z$1:$Z$40<>""),0),0),0))))) | AD6: =IF(O6<>"",O6,AC6) | AE6: =IF(C6="","",IFERROR(INDEX(基础资料!$H$5:$H$24,MATCH(C6,基础资料!$G$5:$G$24,0))&"","")) -> 银行 | AF6: =IF(AD6="","",IFERROR(INDEX(基础资料!$H$5:$H$24,MATCH(AD6,基础资料!$G$5:$G$24,0))&"","")) | AG6: =IF(OR(D6="",R6=0),"",IFERROR(INDEX(基础资料!$AC$5:$AC$164,IF(IF(F6<>"","支","收")="收",MATCH(1,INDEX(ISNUMBER(SEARCH(_辅助!$AB$1:$AB$160,D6))*(_辅助!$AB$1:$AB$160<>""),0),0),MATCH(1,INDEX(ISNUMBER(SEARCH(_辅助!$AC$1:$AC$160,D6))*(_辅助!$AC$1:$AC$160<>""),0),0)))&"","")) -> 工资 | AH6: =IF(R6=0,"",IF(OR(IFERROR(INDEX(基础资料!$T$5:$T$64,MATCH(I6,基础资料!$S$5:$S$64,0))&"","")="收",IFERROR(INDEX(基础资料!$T$5:$T$64,MATCH(I6,基础资料!$S$5:$S$64,0))&"","")="支"),IFERROR(INDEX(基础资料!$T$5:$T$64,MATCH(I6,基础资料!$S$5:$S$64,0))&"",""),IF(R6>0,"收","支"))) -> 支 | AI6: =IF(N(AK6)=0,"",INDEX(_辅助!$R$1:$R$240,AK6)) | AJ6: =IF(OR(AI6="",L6<>""),0,SUMPRODUCT(ISNUMBER(SEARCH(_辅助!$R$1:$R$240,D6))*(_辅助!$R$1:$R$240<>"")*(1-ISNUMBER(SEARCH(_辅助!$R$1:$R$240,AI6)))*(_辅助!$S$1:$S$240<>T6))) -> 0 | AK6: =IF(D6="",0,IFERROR(MATCH(1,INDEX(ISNUMBER(SEARCH(_辅助!$R$1:$R$240,D6))*(_辅助!$R$1:$R$240<>""),0),0),0)) -> 0 | AL6: =IF(D6="",0,IFERROR(MATCH(1,INDEX(ISNUMBER(SEARCH(_辅助!$V$1:$V$900,D6))*(_辅助!$V$1:$V$900<>""),0),0),0)) -> 99 | AM6: =IF(AB6="",0,IFERROR(MATCH(1,INDEX(ISNUMBER(SEARCH(_辅助!$V$1:$V$900,AB6))*(_辅助!$V$1:$V$900<>""),0),0),0)) -> 99 | AN6: =IF(ISNUMBER(B6),INT(B6),0) -> 46143 | AO6: =IF(AND(X6="应收账款",R6>0,AN6>0,H6<>""),H6&"|"&COUNTIFS(资金流水!$H$6:$H$2005,H6,资金流水!$X$6:$X$2005,"应收账款",资金流水!$R$6:$R$2005,">0",资金流水!$AN$6:$AN$2005,">0",资金流水!$AN$6:$AN$2005,"<="&AN6),"") | AP6: =IF(AND(J6<>"",R6<0,AN6>0),J6&"|"&COUNTIFS(资金流水!$J$6:$J$2005,J6,资金流水!$R$6:$R$2005,"<0",资金流水!$AN$6:$AN$2005,">0",资金流水!$AN$6:$AN$2005,"<="&AN6),"") -> 吴群|1 | AQ6: =IF(AND(X6="其他应收款",AN6>0,J6<>""),J6&"|"&(COUNTIFS(资金流水!$J$6:$J$2005,J6,资金流水!$X$6:$X$2005,"其他应收款",资金流水!$AN$6:$AN$2005,">0",资金流水!$AN$6:$AN$2005,"<"&AN6)+COUNTIFS($J$6:J6,J6,$X$6:X6,"其他应收款",$AN$6:AN6,AN6)),"")
A7: =IF(AND(B7="",D7="",E7="",F7=""),"",ROW()-5) -> 2 | B7: 46144 | C7: 九江银行 | D7: 付邓泽贵工资 | F7: 3000 | G7: =IF(C7="","",ROUND(IFERROR(INDEX(基础资料!$K$5:$K$24,MATCH(C7,基础资料!$G$5:$G$24,0)),0)+SUMIFS($R$6:R7,$C$6:C7,C7)-SUMIFS($R$6:R7,$AD$6:AD7,C7,$X$6:X7,"账户互转"),2)) -> -18000 | H7: =IF(L7<>"",L7,T7) | I7: =IF(M7<>"",M7,U7) -> 工资 | J7: =IF(N7<>"",N7,V7) -> 邓泽贵 | K7: =IF(AND(B7="",D7="",E7="",F7=""),"",IF(C7="","✗ 没选账户",IF(AE7="","✗ 账户不在【基础资料】② 里",IF(NOT(ISNUMBER(B7)),"✗ 日期要填成日期（2026/5/1）",IF(AND(ISNUMBER(B7),B7<基础资料!$C$9),"✗ 日期早于建账日期（建账前的放【期初余额】）",IF(AND(N(E7)<>0,N(F7)<>0),"✗ 收入、支出只填一边",IF(R7=0,"✗ 没有金额",IF(I7="","✗ 认不出收支类别：在「改类别」选",IF(W7="？","✗ 收支类别不在【基础资料】③ 里",IF(OR(I7="管理人员工资",I7="折旧费"),"✗ 这一类是自动算的，流水里不能选（发工资选「工资」，买设备选「固定资产购置」）",IF(AND(OR(X7="材料费",X7="人工费",X7="分包费",X7="机械运输费",X7="其他直接费",X7="票据贴息",X7="应收账款"),H7=""),"✗ 这一笔要选项目（摘要里的项目没在【项目档案】的话先去加上）",IF(AND(H7<>"",COUNTIF(项目档案!$B$4:$B$63,H7)=0),"✗ 项目不在【项目档案】里",IF(AND(OR(IFERROR(INDEX(基础资料!$W$5:$W$64,MATCH(I7,基础资料!$S$5:$S$64,0))&"","")="人",IFERROR(INDEX(基础资料!$W$5:$W$64,MATCH(I7,基础资料!$S$5:$S$64,0))&"","")="单位"),J7=""),"✗ 这一笔要选是谁（改单位/人）",IF(AND(I7="付应付款",NOT(OR(Z7="材料供应商",Z7="分包",Z7="机械运输",Z7="其他"))),"✗ 付应付款要选材料商、分包或机械单位",IF(AND(I7="付应付款",Y7=0),"✗ 这家没有应付：先在【应付登记】登记（现买现付的选材料费等）",IF(AND(OR(I7="工资",I7="工资退回"),AA7=0),"✗ 工资要选管理人员或工人（临时工选「临时工工资」）",IF(AND(I7="账户互转",AD7=""),"✗ 账户互转要在「对方账户」选（借款、报销选那个人的个人户）",IF(AND(I7="账户互转",AF7=""),"✗ 对方账户不在【基础资料】② 里",IF(AND(I7="账户互转",AD7=C7),"✗ 对方账户不能是自己",IF(IF(I7="账户互转",COUNTIFS(资金流水!$C$6:$C$2005,AD7,资金流水!$AD$6:$AD$2005,C7,资金流水!$I$6:$I$2005,"账户互转",资金流水!$R$6:$R$2005,-R7)>0,FALSE),"✗ 对方账户那边也记了这笔互转（只记一边：清空其中一行的内容）",IF(AJ7>0,"⚠ 摘要里有两个项目：拆成几行，或在「改项目」选",IF(AND(I7<>"账户互转",O7<>""),"⚠ 填了对方账户但类别不是账户互转（对方账户不起作用）",IF(AND(J7<>"",Z7=""),"⚠ 单位/人没在【往来单位】登记",IF(AND(N(F7)<0,AH7="收"),"⚠ 这是收款，以后请记在收入栏",IF(N(E7)<0,"⚠ 收入填了负数，已按支出算",IF(N(F7)<0,"↩ 冲回（退款）",IF(AND(R7<0,I7<>"固定资产购置",I7<>"付应付款",ISNUMBER(B7),IFERROR(SUMPRODUCT(ISNUMBER(SEARCH(基础资料!$AJ$5:$AJ$34,D7))*(基础资料!$AJ$5:$AJ$34<>"")*((AN7-基础资料!$AK$5:$AK$34)<=30)*((AN7-基础资料!$AK$5:$AK$34)>=-30)),0)>0),"⚠ 像是在买【基础资料】⑥ 登记的车/设备：类别改成「固定资产购置」，不然成本算两遍",IF(AND(OR(I7="材料费",I7="分包费",I7="机械运输费",I7="其他直接费"),J7="",H7<>"",COUNTIFS(应付登记!$E$5:$E$1004,H7,应付登记!$G$5:$G$1004,-R7)>0),"⚠ 这个项目有同样金额的应付登记：是付那家的，改类别选「付应付款」、改单位选那家（不然成本算两遍）","√")))))))))))))))))))))))))))) -> √ | R7: =ROUND(N(E7)-N(F7),2) -> -3000 | S7: =IF(ISNUMBER(B7),YEAR(B7)*100+MONTH(B7),"") -> 202605 | T7: =IF(N(AK7)=0,"",INDEX(_辅助!$S$1:$S$240,AK7)) | U7: =IF(OR(D7="",R7=0),"",IF(AND(Z7="临时工",R7<0),"临时工工资",IF(AG7="",IF(AA7=1,"工资",IF(Z7="临时工","临时工工资",IF(Z7="甲方/总包","工程款",IF(AND(OR(Z7="材料供应商",Z7="分包",Z7="机械运输"),Y7=1),"付应付款","")))),IF(AND(Y7=1,OR(Z7="材料供应商",Z7="分包",Z7="机械运输",Z7="其他"),OR(AG7="材料费",AG7="分包费",AG7="机械运输费",AG7="其他直接费",AG7="工资",AG7="临时工工资")),"付应付款",AG7)))) -> 工资 | V7: =IF(D7="","",IF(N(AM7)>0,IF(N(AM7)=0,"",INDEX(_辅助!$W$1:$W$900,AM7)),IF(N(AL7)=0,"",INDEX(_辅助!$W$1:$W$900,AL7)))) -> 邓泽贵 | W7: =IF(I7="","",IFERROR(INDEX(基础资料!$V$5:$V$64,MATCH(I7,基础资料!$S$5:$S$64,0))&"","？")) -> 不进利润 | X7: =IF(R7=0,"",IF(OR(I7="",IFERROR(INDEX(基础资料!$U$5:$U$64,MATCH(I7,基础资料!$S$5:$S$64,0))&"","")=""),"待分类",IF(OR(I7="付应付款",IFERROR(INDEX(基础资料!$U$5:$U$64,MATCH(I7,基础资料!$S$5:$S$64,0))&"","")="应付款"),IF(Z7="材料供应商","应付材料款",IF(Z7="分包","应付分包款",IF(Z7="机械运输","应付机械运输费","应付其他款"))),IFERROR(INDEX(基础资料!$U$5:$U$64,MATCH(I7,基础资料!$S$5:$S$64,0))&"","")))) -> 应付职工薪酬 | Y7: =IF(J7="",0,IF(COUNTIF(应付登记!$D$5:$D$1004,J7)+COUNTIF(期初余额!$P$5:$P$204,J7)>0,1,0)) -> 0 | Z7: =IF(J7="","",IFERROR(INDEX(往来单位!$C$4:$C$303,MATCH(J7,往来单位!$B$4:$B$303,0))&"","")) -> 工人 | AA7: =IF(OR(Z7="管理人员",Z7="工人"),1,0) -> 1 | AB7: =IF(ISERROR(FIND("代",D7)),"",IFERROR(MID(D7,FIND("代",D7)+1,FIND("付",D7,FIND("代",D7))-FIND("代",D7)-1),"")) | AC7: =IF(I7<>"账户互转","",IF(J7<>"",IFERROR(INDEX(_辅助!$G$1:$G$40,MATCH(J7,_辅助!$F$1:$F$40,0)),IF(IFERROR(MATCH(1,INDEX(ISNUMBER(SEARCH(_辅助!$Z$1:$Z$40,D7))*(_辅助!$Z$1:$Z$40<>""),0),0),0)=0,"",INDEX(_辅助!$AA$1:$AA$40,IFERROR(MATCH(1,INDEX(ISNUMBER(SEARCH(_辅助!$Z$1:$Z$40,D7))*(_辅助!$Z$1:$Z$40<>""),0),0),0)))),IF(IFERROR(MATCH(1,INDEX(ISNUMBER(SEARCH(_辅助!$Z$1:$Z$40,D7))*(_辅助!$Z$1:$Z$40<>""),0),0),0)=0,"",INDEX(_辅助!$AA$1:$AA$40,IFERROR(MATCH(1,INDEX(ISNUMBER(SEARCH(_辅助!$Z$1:$Z$40,D7))*(_辅助!$Z$1:$Z$40<>""),0),0),0))))) | AD7: =IF(O7<>"",O7,AC7) | AE7: =IF(C7="","",IFERROR(INDEX(基础资料!$H$5:$H$24,MATCH(C7,基础资料!$G$5:$G$24,0))&"","")) -> 银行 | AF7: =IF(AD7="","",IFERROR(INDEX(基础资料!$H$5:$H$24,MATCH(AD7,基础资料!$G$5:$G$24,0))&"","")) | AG7: =IF(OR(D7="",R7=0),"",IFERROR(INDEX(基础资料!$AC$5:$AC$164,IF(IF(F7<>"","支","收")="收",MATCH(1,INDEX(ISNUMBER(SEARCH(_辅助!$AB$1:$AB$160,D7))*(_辅助!$AB$1:$AB$160<>""),0),0),MATCH(1,INDEX(ISNUMBER(SEARCH(_辅助!$AC$1:$AC$160,D7))*(_辅助!$AC$1:$AC$160<>""),0),0)))&"","")) -> 工资 | AH7: =IF(R7=0,"",IF(OR(IFERROR(INDEX(基础资料!$T$5:$T$64,MATCH(I7,基础资料!$S$5:$S$64,0))&"","")="收",IFERROR(INDEX(基础资料!$T$5:$T$64,MATCH(I7,基础资料!$S$5:$S$64,0))&"","")="支"),IFERROR(INDEX(基础资料!$T$5:$T$64,MATCH(I7,基础资料!$S$5:$S$64,0))&"",""),IF(R7>0,"收","支"))) -> 支 | AI7: =IF(N(AK7)=0,"",INDEX(_辅助!$R$1:$R$240,AK7)) | AJ7: =IF(OR(AI7="",L7<>""),0,SUMPRODUCT(ISNUMBER(SEARCH(_辅助!$R$1:$R$240,D7))*(_辅助!$R$1:$R$240<>"")*(1-ISNUMBER(SEARCH(_辅助!$R$1:$R$240,AI7)))*(_辅助!$S$1:$S$240<>T7))) -> 0 | AK7: =IF(D7="",0,IFERROR(MATCH(1,INDEX(ISNUMBER(SEARCH(_辅助!$R$1:$R$240,D7))*(_辅助!$R$1:$R$240<>""),0),0),0)) -> 0 | AL7: =IF(D7="",0,IFERROR(MATCH(1,INDEX(ISNUMBER(SEARCH(_辅助!$V$1:$V$900,D7))*(_辅助!$V$1:$V$900<>""),0),0),0)) -> 52 | AM7: =IF(AB7="",0,IFERROR(MATCH(1,INDEX(ISNUMBER(SEARCH(_辅助!$V$1:$V$900,AB7))*(_辅助!$V$1:$V$900<>""),0),0),0)) -> 0 | AN7: =IF(ISNUMBER(B7),INT(B7),0) -> 46144 | AO7: =IF(AND(X7="应收账款",R7>0,AN7>0,H7<>""),H7&"|"&COUNTIFS(资金流水!$H$6:$H$2005,H7,资金流水!$X$6:$X$2005,"应收账款",资金流水!$R$6:$R$2005,">0",资金流水!$AN$6:$AN$2005,">0",资金流水!$AN$6:$AN$2005,"<="&AN7),"") | AP7: =IF(AND(J7<>"",R7<0,AN7>0),J7&"|"&COUNTIFS(资金流水!$J$6:$J$2005,J7,资金流水!$R$6:$R$2005,"<0",资金流水!$AN$6:$AN$2005,">0",资金流水!$AN$6:$AN$2005,"<="&AN7),"") -> 邓泽贵|1 | AQ7: =IF(AND(X7="其他应收款",AN7>0,J7<>""),J7&"|"&(COUNTIFS(资金流水!$J$6:$J$2005,J7,资金流水!$X$6:$X$2005,"其他应收款",资金流水!$AN$6:$AN$2005,">0",资金流水!$AN$6:$AN$2005,"<"&AN7)+COUNTIFS($J$6:J7,J7,$X$6:X7,"其他应收款",$AN$6:AN7,AN7)),"")
A8: =IF(AND(B8="",D8="",E8="",F8=""),"",ROW()-5) -> 3 | B8: 46144 | C8: 九江银行 | D8: 付吴志刚工资 | F8: 3000 | G8: =IF(C8="","",ROUND(IFERROR(INDEX(基础资料!$K$5:$K$24,MATCH(C8,基础资料!$G$5:$G$24,0)),0)+SUMIFS($R$6:R8,$C$6:C8,C8)-SUMIFS($R$6:R8,$AD$6:AD8,C8,$X$6:X8,"账户互转"),2)) -> -21000 | H8: =IF(L8<>"",L8,T8) | I8: =IF(M8<>"",M8,U8) -> 工资 | J8: =IF(N8<>"",N8,V8) -> 吴志刚 | K8: =IF(AND(B8="",D8="",E8="",F8=""),"",IF(C8="","✗ 没选账户",IF(AE8="","✗ 账户不在【基础资料】② 里",IF(NOT(ISNUMBER(B8)),"✗ 日期要填成日期（2026/5/1）",IF(AND(ISNUMBER(B8),B8<基础资料!$C$9),"✗ 日期早于建账日期（建账前的放【期初余额】）",IF(AND(N(E8)<>0,N(F8)<>0),"✗ 收入、支出只填一边",IF(R8=0,"✗ 没有金额",IF(I8="","✗ 认不出收支类别：在「改类别」选",IF(W8="？","✗ 收支类别不在【基础资料】③ 里",IF(OR(I8="管理人员工资",I8="折旧费"),"✗ 这一类是自动算的，流水里不能选（发工资选「工资」，买设备选「固定资产购置」）",IF(AND(OR(X8="材料费",X8="人工费",X8="分包费",X8="机械运输费",X8="其他直接费",X8="票据贴息",X8="应收账款"),H8=""),"✗ 这一笔要选项目（摘要里的项目没在【项目档案】的话先去加上）",IF(AND(H8<>"",COUNTIF(项目档案!$B$4:$B$63,H8)=0),"✗ 项目不在【项目档案】里",IF(AND(OR(IFERROR(INDEX(基础资料!$W$5:$W$64,MATCH(I8,基础资料!$S$5:$S$64,0))&"","")="人",IFERROR(INDEX(基础资料!$W$5:$W$64,MATCH(I8,基础资料!$S$5:$S$64,0))&"","")="单位"),J8=""),"✗ 这一笔要选是谁（改单位/人）",IF(AND(I8="付应付款",NOT(OR(Z8="材料供应商",Z8="分包",Z8="机械运输",Z8="其他"))),"✗ 付应付款要选材料商、分包或机械单位",IF(AND(I8="付应付款",Y8=0),"✗ 这家没有应付：先在【应付登记】登记（现买现付的选材料费等）",IF(AND(OR(I8="工资",I8="工资退回"),AA8=0),"✗ 工资要选管理人员或工人（临时工选「临时工工资」）",IF(AND(I8="账户互转",AD8=""),"✗ 账户互转要在「对方账户」选（借款、报销选那个人的个人户）",IF(AND(I8="账户互转",AF8=""),"✗ 对方账户不在【基础资料】② 里",IF(AND(I8="账户互转",AD8=C8),"✗ 对方账户不能是自己",IF(IF(I8="账户互转",COUNTIFS(资金流水!$C$6:$C$2005,AD8,资金流水!$AD$6:$AD$2005,C8,资金流水!$I$6:$I$2005,"账户互转",资金流水!$R$6:$R$2005,-R8)>0,FALSE),"✗ 对方账户那边也记了这笔互转（只记一边：清空其中一行的内容）",IF(AJ8>0,"⚠ 摘要里有两个项目：拆成几行，或在「改项目」选",IF(AND(I8<>"账户互转",O8<>""),"⚠ 填了对方账户但类别不是账户互转（对方账户不起作用）",IF(AND(J8<>"",Z8=""),"⚠ 单位/人没在【往来单位】登记",IF(AND(N(F8)<0,AH8="收"),"⚠ 这是收款，以后请记在收入栏",IF(N(E8)<0,"⚠ 收入填了负数，已按支出算",IF(N(F8)<0,"↩ 冲回（退款）",IF(AND(R8<0,I8<>"固定资产购置",I8<>"付应付款",ISNUMBER(B8),IFERROR(SUMPRODUCT(ISNUMBER(SEARCH(基础资料!$AJ$5:$AJ$34,D8))*(基础资料!$AJ$5:$AJ$34<>"")*((AN8-基础资料!$AK$5:$AK$34)<=30)*((AN8-基础资料!$AK$5:$AK$34)>=-30)),0)>0),"⚠ 像是在买【基础资料】⑥ 登记的车/设备：类别改成「固定资产购置」，不然成本算两遍",IF(AND(OR(I8="材料费",I8="分包费",I8="机械运输费",I8="其他直接费"),J8="",H8<>"",COUNTIFS(应付登记!$E$5:$E$1004,H8,应付登记!$G$5:$G$1004,-R8)>0),"⚠ 这个项目有同样金额的应付登记：是付那家的，改类别选「付应付款」、改单位选那家（不然成本算两遍）","√")))))))))))))))))))))))))))) -> √ | R8: =ROUND(N(E8)-N(F8),2) -> -3000 | S8: =IF(ISNUMBER(B8),YEAR(B8)*100+MONTH(B8),"") -> 202605 | T8: =IF(N(AK8)=0,"",INDEX(_辅助!$S$1:$S$240,AK8)) | U8: =IF(OR(D8="",R8=0),"",IF(AND(Z8="临时工",R8<0),"临时工工资",IF(AG8="",IF(AA8=1,"工资",IF(Z8="临时工","临时工工资",IF(Z8="甲方/总包","工程款",IF(AND(OR(Z8="材料供应商",Z8="分包",Z8="机械运输"),Y8=1),"付应付款","")))),IF(AND(Y8=1,OR(Z8="材料供应商",Z8="分包",Z8="机械运输",Z8="其他"),OR(AG8="材料费",AG8="分包费",AG8="机械运输费",AG8="其他直接费",AG8="工资",AG8="临时工工资")),"付应付款",AG8)))) -> 工资 | V8: =IF(D8="","",IF(N(AM8)>0,IF(N(AM8)=0,"",INDEX(_辅助!$W$1:$W$900,AM8)),IF(N(AL8)=0,"",INDEX(_辅助!$W$1:$W$900,AL8)))) -> 吴志刚 | W8: =IF(I8="","",IFERROR(INDEX(基础资料!$V$5:$V$64,MATCH(I8,基础资料!$S$5:$S$64,0))&"","？")) -> 不进利润 | X8: =IF(R8=0,"",IF(OR(I8="",IFERROR(INDEX(基础资料!$U$5:$U$64,MATCH(I8,基础资料!$S$5:$S$64,0))&"","")=""),"待分类",IF(OR(I8="付应付款",IFERROR(INDEX(基础资料!$U$5:$U$64,MATCH(I8,基础资料!$S$5:$S$64,0))&"","")="应付款"),IF(Z8="材料供应商","应付材料款",IF(Z8="分包","应付分包款",IF(Z8="机械运输","应付机械运输费","应付其他款"))),IFERROR(INDEX(基础资料!$U$5:$U$64,MATCH(I8,基础资料!$S$5:$S$64,0))&"","")))) -> 应付职工薪酬 | Y8: =IF(J8="",0,IF(COUNTIF(应付登记!$D$5:$D$1004,J8)+COUNTIF(期初余额!$P$5:$P$204,J8)>0,1,0)) -> 0 | Z8: =IF(J8="","",IFERROR(INDEX(往来单位!$C$4:$C$303,MATCH(J8,往来单位!$B$4:$B$303,0))&"","")) -> 工人 | AA8: =IF(OR(Z8="管理人员",Z8="工人"),1,0) -> 1 | AB8: =IF(ISERROR(FIND("代",D8)),"",IFERROR(MID(D8,FIND("代",D8)+1,FIND("付",D8,FIND("代",D8))-FIND("代",D8)-1),"")) | AC8: =IF(I8<>"账户互转","",IF(J8<>"",IFERROR(INDEX(_辅助!$G$1:$G$40,MATCH(J8,_辅助!$F$1:$F$40,0)),IF(IFERROR(MATCH(1,INDEX(ISNUMBER(SEARCH(_辅助!$Z$1:$Z$40,D8))*(_辅助!$Z$1:$Z$40<>""),0),0),0)=0,"",INDEX(_辅助!$AA$1:$AA$40,IFERROR(MATCH(1,INDEX(ISNUMBER(SEARCH(_辅助!$Z$1:$Z$40,D8))*(_辅助!$Z$1:$Z$40<>""),0),0),0)))),IF(IFERROR(MATCH(1,INDEX(ISNUMBER(SEARCH(_辅助!$Z$1:$Z$40,D8))*(_辅助!$Z$1:$Z$40<>""),0),0),0)=0,"",INDEX(_辅助!$AA$1:$AA$40,IFERROR(MATCH(1,INDEX(ISNUMBER(SEARCH(_辅助!$Z$1:$Z$40,D8))*(_辅助!$Z$1:$Z$40<>""),0),0),0))))) | AD8: =IF(O8<>"",O8,AC8) | AE8: =IF(C8="","",IFERROR(INDEX(基础资料!$H$5:$H$24,MATCH(C8,基础资料!$G$5:$G$24,0))&"","")) -> 银行 | AF8: =IF(AD8="","",IFERROR(INDEX(基础资料!$H$5:$H$24,MATCH(AD8,基础资料!$G$5:$G$24,0))&"","")) | AG8: =IF(OR(D8="",R8=0),"",IFERROR(INDEX(基础资料!$AC$5:$AC$164,IF(IF(F8<>"","支","收")="收",MATCH(1,INDEX(ISNUMBER(SEARCH(_辅助!$AB$1:$AB$160,D8))*(_辅助!$AB$1:$AB$160<>""),0),0),MATCH(1,INDEX(ISNUMBER(SEARCH(_辅助!$AC$1:$AC$160,D8))*(_辅助!$AC$1:$AC$160<>""),0),0)))&"","")) -> 工资 | AH8: =IF(R8=0,"",IF(OR(IFERROR(INDEX(基础资料!$T$5:$T$64,MATCH(I8,基础资料!$S$5:$S$64,0))&"","")="收",IFERROR(INDEX(基础资料!$T$5:$T$64,MATCH(I8,基础资料!$S$5:$S$64,0))&"","")="支"),IFERROR(INDEX(基础资料!$T$5:$T$64,MATCH(I8,基础资料!$S$5:$S$64,0))&"",""),IF(R8>0,"收","支"))) -> 支 | AI8: =IF(N(AK8)=0,"",INDEX(_辅助!$R$1:$R$240,AK8)) | AJ8: =IF(OR(AI8="",L8<>""),0,SUMPRODUCT(ISNUMBER(SEARCH(_辅助!$R$1:$R$240,D8))*(_辅助!$R$1:$R$240<>"")*(1-ISNUMBER(SEARCH(_辅助!$R$1:$R$240,AI8)))*(_辅助!$S$1:$S$240<>T8))) -> 0 | AK8: =IF(D8="",0,IFERROR(MATCH(1,INDEX(ISNUMBER(SEARCH(_辅助!$R$1:$R$240,D8))*(_辅助!$R$1:$R$240<>""),0),0),0)) -> 0 | AL8: =IF(D8="",0,IFERROR(MATCH(1,INDEX(ISNUMBER(SEARCH(_辅助!$V$1:$V$900,D8))*(_辅助!$V$1:$V$900<>""),0),0),0)) -> 65 | AM8: =IF(AB8="",0,IFERROR(MATCH(1,INDEX(ISNUMBER(SEARCH(_辅助!$V$1:$V$900,AB8))*(_辅助!$V$1:$V$900<>""),0),0),0)) -> 0 | AN8: =IF(ISNUMBER(B8),INT(B8),0) -> 46144 | AO8: =IF(AND(X8="应收账款",R8>0,AN8>0,H8<>""),H8&"|"&COUNTIFS(资金流水!$H$6:$H$2005,H8,资金流水!$X$6:$X$2005,"应收账款",资金流水!$R$6:$R$2005,">0",资金流水!$AN$6:$AN$2005,">0",资金流水!$AN$6:$AN$2005,"<="&AN8),"") | AP8: =IF(AND(J8<>"",R8<0,AN8>0),J8&"|"&COUNTIFS(资金流水!$J$6:$J$2005,J8,资金流水!$R$6:$R$2005,"<0",资金流水!$AN$6:$AN$2005,">0",资金流水!$AN$6:$AN$2005,"<="&AN8),"") -> 吴志刚|1 | AQ8: =IF(AND(X8="其他应收款",AN8>0,J8<>""),J8&"|"&(COUNTIFS(资金流水!$J$6:$J$2005,J8,资金流水!$X$6:$X$2005,"其他应收款",资金流水!$AN$6:$AN$2005,">0",资金流水!$AN$6:$AN$2005,"<"&AN8)+COUNTIFS($J$6:J8,J8,$X$6:X8,"其他应收款",$AN$6:AN8,AN8)),"")
A9: =IF(AND(B9="",D9="",E9="",F9=""),"",ROW()-5) -> 4 | B9: 46144 | C9: 九江银行 | D9: 付金南水工资 | F9: 3000 | G9: =IF(C9="","",ROUND(IFERROR(INDEX(基础资料!$K$5:$K$24,MATCH(C9,基础资料!$G$5:$G$24,0)),0)+SUMIFS($R$6:R9,$C$6:C9,C9)-SUMIFS($R$6:R9,$AD$6:AD9,C9,$X$6:X9,"账户互转"),2)) -> -24000 | H9: =IF(L9<>"",L9,T9) | I9: =IF(M9<>"",M9,U9) -> 工资 | J9: =IF(N9<>"",N9,V9) -> 金南水 | K9: =IF(AND(B9="",D9="",E9="",F9=""),"",IF(C9="","✗ 没选账户",IF(AE9="","✗ 账户不在【基础资料】② 里",IF(NOT(ISNUMBER(B9)),"✗ 日期要填成日期（2026/5/1）",IF(AND(ISNUMBER(B9),B9<基础资料!$C$9),"✗ 日期早于建账日期（建账前的放【期初余额】）",IF(AND(N(E9)<>0,N(F9)<>0),"✗ 收入、支出只填一边",IF(R9=0,"✗ 没有金额",IF(I9="","✗ 认不出收支类别：在「改类别」选",IF(W9="？","✗ 收支类别不在【基础资料】③ 里",IF(OR(I9="管理人员工资",I9="折旧费"),"✗ 这一类是自动算的，流水里不能选（发工资选「工资」，买设备选「固定资产购置」）",IF(AND(OR(X9="材料费",X9="人工费",X9="分包费",X9="机械运输费",X9="其他直接费",X9="票据贴息",X9="应收账款"),H9=""),"✗ 这一笔要选项目（摘要里的项目没在【项目档案】的话先去加上）",IF(AND(H9<>"",COUNTIF(项目档案!$B$4:$B$63,H9)=0),"✗ 项目不在【项目档案】里",IF(AND(OR(IFERROR(INDEX(基础资料!$W$5:$W$64,MATCH(I9,基础资料!$S$5:$S$64,0))&"","")="人",IFERROR(INDEX(基础资料!$W$5:$W$64,MATCH(I9,基础资料!$S$5:$S$64,0))&"","")="单位"),J9=""),"✗ 这一笔要选是谁（改单位/人）",IF(AND(I9="付应付款",NOT(OR(Z9="材料供应商",Z9="分包",Z9="机械运输",Z9="其他"))),"✗ 付应付款要选材料商、分包或机械单位",IF(AND(I9="付应付款",Y9=0),"✗ 这家没有应付：先在【应付登记】登记（现买现付的选材料费等）",IF(AND(OR(I9="工资",I9="工资退回"),AA9=0),"✗ 工资要选管理人员或工人（临时工选「临时工工资」）",IF(AND(I9="账户互转",AD9=""),"✗ 账户互转要在「对方账户」选（借款、报销选那个人的个人户）",IF(AND(I9="账户互转",AF9=""),"✗ 对方账户不在【基础资料】② 里",IF(AND(I9="账户互转",AD9=C9),"✗ 对方账户不能是自己",IF(IF(I9="账户互转",COUNTIFS(资金流水!$C$6:$C$2005,AD9,资金流水!$AD$6:$AD$2005,C9,资金流水!$I$6:$I$2005,"账户互转",资金流水!$R$6:$R$2005,-R9)>0,FALSE),"✗ 对方账户那边也记了这笔互转（只记一边：清空其中一行的内容）",IF(AJ9>0,"⚠ 摘要里有两个项目：拆成几行，或在「改项目」选",IF(AND(I9<>"账户互转",O9<>""),"⚠ 填了对方账户但类别不是账户互转（对方账户不起作用）",IF(AND(J9<>"",Z9=""),"⚠ 单位/人没在【往来单位】登记",IF(AND(N(F9)<0,AH9="收"),"⚠ 这是收款，以后请记在收入栏",IF(N(E9)<0,"⚠ 收入填了负数，已按支出算",IF(N(F9)<0,"↩ 冲回（退款）",IF(AND(R9<0,I9<>"固定资产购置",I9<>"付应付款",ISNUMBER(B9),IFERROR(SUMPRODUCT(ISNUMBER(SEARCH(基础资料!$AJ$5:$AJ$34,D9))*(基础资料!$AJ$5:$AJ$34<>"")*((AN9-基础资料!$AK$5:$AK$34)<=30)*((AN9-基础资料!$AK$5:$AK$34)>=-30)),0)>0),"⚠ 像是在买【基础资料】⑥ 登记的车/设备：类别改成「固定资产购置」，不然成本算两遍",IF(AND(OR(I9="材料费",I9="分包费",I9="机械运输费",I9="其他直接费"),J9="",H9<>"",COUNTIFS(应付登记!$E$5:$E$1004,H9,应付登记!$G$5:$G$1004,-R9)>0),"⚠ 这个项目有同样金额的应付登记：是付那家的，改类别选「付应付款」、改单位选那家（不然成本算两遍）","√")))))))))))))))))))))))))))) -> √ | R9: =ROUND(N(E9)-N(F9),2) -> -3000 | S9: =IF(ISNUMBER(B9),YEAR(B9)*100+MONTH(B9),"") -> 202605 | T9: =IF(N(AK9)=0,"",INDEX(_辅助!$S$1:$S$240,AK9)) | U9: =IF(OR(D9="",R9=0),"",IF(AND(Z9="临时工",R9<0),"临时工工资",IF(AG9="",IF(AA9=1,"工资",IF(Z9="临时工","临时工工资",IF(Z9="甲方/总包","工程款",IF(AND(OR(Z9="材料供应商",Z9="分包",Z9="机械运输"),Y9=1),"付应付款","")))),IF(AND(Y9=1,OR(Z9="材料供应商",Z9="分包",Z9="机械运输",Z9="其他"),OR(AG9="材料费",AG9="分包费",AG9="机械运输费",AG9="其他直接费",AG9="工资",AG9="临时工工资")),"付应付款",AG9)))) -> 工资 | V9: =IF(D9="","",IF(N(AM9)>0,IF(N(AM9)=0,"",INDEX(_辅助!$W$1:$W$900,AM9)),IF(N(AL9)=0,"",INDEX(_辅助!$W$1:$W$900,AL9)))) -> 金南水 | W9: =IF(I9="","",IFERROR(INDEX(基础资料!$V$5:$V$64,MATCH(I9,基础资料!$S$5:$S$64,0))&"","？")) -> 不进利润 | X9: =IF(R9=0,"",IF(OR(I9="",IFERROR(INDEX(基础资料!$U$5:$U$64,MATCH(I9,基础资料!$S$5:$S$64,0))&"","")=""),"待分类",IF(OR(I9="付应付款",IFERROR(INDEX(基础资料!$U$5:$U$64,MATCH(I9,基础资料!$S$5:$S$64,0))&"","")="应付款"),IF(Z9="材料供应商","应付材料款",IF(Z9="分包","应付分包款",IF(Z9="机械运输","应付机械运输费","应付其他款"))),IFERROR(INDEX(基础资料!$U$5:$U$64,MATCH(I9,基础资料!$S$5:$S$64,0))&"","")))) -> 应付职工薪酬 | Y9: =IF(J9="",0,IF(COUNTIF(应付登记!$D$5:$D$1004,J9)+COUNTIF(期初余额!$P$5:$P$204,J9)>0,1,0)) -> 0 | Z9: =IF(J9="","",IFERROR(INDEX(往来单位!$C$4:$C$303,MATCH(J9,往来单位!$B$4:$B$303,0))&"","")) -> 工人 | AA9: =IF(OR(Z9="管理人员",Z9="工人"),1,0) -> 1 | AB9: =IF(ISERROR(FIND("代",D9)),"",IFERROR(MID(D9,FIND("代",D9)+1,FIND("付",D9,FIND("代",D9))-FIND("代",D9)-1),"")) | AC9: =IF(I9<>"账户互转","",IF(J9<>"",IFERROR(INDEX(_辅助!$G$1:$G$40,MATCH(J9,_辅助!$F$1:$F$40,0)),IF(IFERROR(MATCH(1,INDEX(ISNUMBER(SEARCH(_辅助!$Z$1:$Z$40,D9))*(_辅助!$Z$1:$Z$40<>""),0),0),0)=0,"",INDEX(_辅助!$AA$1:$AA$40,IFERROR(MATCH(1,INDEX(ISNUMBER(SEARCH(_辅助!$Z$1:$Z$40,D9))*(_辅助!$Z$1:$Z$40<>""),0),0),0)))),IF(IFERROR(MATCH(1,INDEX(ISNUMBER(SEARCH(_辅助!$Z$1:$Z$40,D9))*(_辅助!$Z$1:$Z$40<>""),0),0),0)=0,"",INDEX(_辅助!$AA$1:$AA$40,IFERROR(MATCH(1,INDEX(ISNUMBER(SEARCH(_辅助!$Z$1:$Z$40,D9))*(_辅助!$Z$1:$Z$40<>""),0),0),0))))) | AD9: =IF(O9<>"",O9,AC9) | AE9: =IF(C9="","",IFERROR(INDEX(基础资料!$H$5:$H$24,MATCH(C9,基础资料!$G$5:$G$24,0))&"","")) -> 银行 | AF9: =IF(AD9="","",IFERROR(INDEX(基础资料!$H$5:$H$24,MATCH(AD9,基础资料!$G$5:$G$24,0))&"","")) | AG9: =IF(OR(D9="",R9=0),"",IFERROR(INDEX(基础资料!$AC$5:$AC$164,IF(IF(F9<>"","支","收")="收",MATCH(1,INDEX(ISNUMBER(SEARCH(_辅助!$AB$1:$AB$160,D9))*(_辅助!$AB$1:$AB$160<>""),0),0),MATCH(1,INDEX(ISNUMBER(SEARCH(_辅助!$AC$1:$AC$160,D9))*(_辅助!$AC$1:$AC$160<>""),0),0)))&"","")) -> 工资 | AH9: =IF(R9=0,"",IF(OR(IFERROR(INDEX(基础资料!$T$5:$T$64,MATCH(I9,基础资料!$S$5:$S$64,0))&"","")="收",IFERROR(INDEX(基础资料!$T$5:$T$64,MATCH(I9,基础资料!$S$5:$S$64,0))&"","")="支"),IFERROR(INDEX(基础资料!$T$5:$T$64,MATCH(I9,基础资料!$S$5:$S$64,0))&"",""),IF(R9>0,"收","支"))) -> 支 | AI9: =IF(N(AK9)=0,"",INDEX(_辅助!$R$1:$R$240,AK9)) | AJ9: =IF(OR(AI9="",L9<>""),0,SUMPRODUCT(ISNUMBER(SEARCH(_辅助!$R$1:$R$240,D9))*(_辅助!$R$1:$R$240<>"")*(1-ISNUMBER(SEARCH(_辅助!$R$1:$R$240,AI9)))*(_辅助!$S$1:$S$240<>T9))) -> 0 | AK9: =IF(D9="",0,IFERROR(MATCH(1,INDEX(ISNUMBER(SEARCH(_辅助!$R$1:$R$240,D9))*(_辅助!$R$1:$R$240<>""),0),0),0)) -> 0 | AL9: =IF(D9="",0,IFERROR(MATCH(1,INDEX(ISNUMBER(SEARCH(_辅助!$V$1:$V$900,D9))*(_辅助!$V$1:$V$900<>""),0),0),0)) -> 57 | AM9: =IF(AB9="",0,IFERROR(MATCH(1,INDEX(ISNUMBER(SEARCH(_辅助!$V$1:$V$900,AB9))*(_辅助!$V$1:$V$900<>""),0),0),0)) -> 0 | AN9: =IF(ISNUMBER(B9),INT(B9),0) -> 46144 | AO9: =IF(AND(X9="应收账款",R9>0,AN9>0,H9<>""),H9&"|"&COUNTIFS(资金流水!$H$6:$H$2005,H9,资金流水!$X$6:$X$2005,"应收账款",资金流水!$R$6:$R$2005,">0",资金流水!$AN$6:$AN$2005,">0",资金流水!$AN$6:$AN$2005,"<="&AN9),"") | AP9: =IF(AND(J9<>"",R9<0,AN9>0),J9&"|"&COUNTIFS(资金流水!$J$6:$J$2005,J9,资金流水!$R$6:$R$2005,"<0",资金流水!$AN$6:$AN$2005,">0",资金流水!$AN$6:$AN$2005,"<="&AN9),"") -> 金南水|1 | AQ9: =IF(AND(X9="其他应收款",AN9>0,J9<>""),J9&"|"&(COUNTIFS(资金流水!$J$6:$J$2005,J9,资金流水!$X$6:$X$2005,"其他应收款",资金流水!$AN$6:$AN$2005,">0",资金流水!$AN$6:$AN$2005,"<"&AN9)+COUNTIFS($J$6:J9,J9,$X$6:X9,"其他应收款",$AN$6:AN9,AN9)),"")
A10: =IF(AND(B10="",D10="",E10="",F10=""),"",ROW()-5) -> 5 | B10: 46145 | C10: 九江银行 | D10: 付张亮亮工资 | F10: 4000 | G10: =IF(C10="","",ROUND(IFERROR(INDEX(基础资料!$K$5:$K$24,MATCH(C10,基础资料!$G$5:$G$24,0)),0)+SUMIFS($R$6:R10,$C$6:C10,C10)-SUMIFS($R$6:R10,$AD$6:AD10,C10,$X$6:X10,"账户互转"),2)) -> -28000 | H10: =IF(L10<>"",L10,T10) | I10: =IF(M10<>"",M10,U10) -> 工资 | J10: =IF(N10<>"",N10,V10) -> 张亮亮 | K10: =IF(AND(B10="",D10="",E10="",F10=""),"",IF(C10="","✗ 没选账户",IF(AE10="","✗ 账户不在【基础资料】② 里",IF(NOT(ISNUMBER(B10)),"✗ 日期要填成日期（2026/5/1）",IF(AND(ISNUMBER(B10),B10<基础资料!$C$9),"✗ 日期早于建账日期（建账前的放【期初余额】）",IF(AND(N(E10)<>0,N(F10)<>0),"✗ 收入、支出只填一边",IF(R10=0,"✗ 没有金额",IF(I10="","✗ 认不出收支类别：在「改类别」选",IF(W10="？","✗ 收支类别不在【基础资料】③ 里",IF(OR(I10="管理人员工资",I10="折旧费"),"✗ 这一类是自动算的，流水里不能选（发工资选「工资」，买设备选「固定资产购置」）",IF(AND(OR(X10="材料费",X10="人工费",X10="分包费",X10="机械运输费",X10="其他直接费",X10="票据贴息",X10="应收账款"),H10=""),"✗ 这一笔要选项目（摘要里的项目没在【项目档案】的话先去加上）",IF(AND(H10<>"",COUNTIF(项目档案!$B$4:$B$63,H10)=0),"✗ 项目不在【项目档案】里",IF(AND(OR(IFERROR(INDEX(基础资料!$W$5:$W$64,MATCH(I10,基础资料!$S$5:$S$64,0))&"","")="人",IFERROR(INDEX(基础资料!$W$5:$W$64,MATCH(I10,基础资料!$S$5:$S$64,0))&"","")="单位"),J10=""),"✗ 这一笔要选是谁（改单位/人）",IF(AND(I10="付应付款",NOT(OR(Z10="材料供应商",Z10="分包",Z10="机械运输",Z10="其他"))),"✗ 付应付款要选材料商、分包或机械单位",IF(AND(I10="付应付款",Y10=0),"✗ 这家没有应付：先在【应付登记】登记（现买现付的选材料费等）",IF(AND(OR(I10="工资",I10="工资退回"),AA10=0),"✗ 工资要选管理人员或工人（临时工选「临时工工资」）",IF(AND(I10="账户互转",AD10=""),"✗ 账户互转要在「对方账户」选（借款、报销选那个人的个人户）",IF(AND(I10="账户互转",AF10=""),"✗ 对方账户不在【基础资料】② 里",IF(AND(I10="账户互转",AD10=C10),"✗ 对方账户不能是自己",IF(IF(I10="账户互转",COUNTIFS(资金流水!$C$6:$C$2005,AD10,资金流水!$AD$6:$AD$2005,C10,资金流水!$I$6:$I$2005,"账户互转",资金流水!$R$6:$R$2005,-R10)>0,FALSE),"✗ 对方账户那边也记了这笔互转（只记一边：清空其中一行的内容）",IF(AJ10>0,"⚠ 摘要里有两个项目：拆成几行，或在「改项目」选",IF(AND(I10<>"账户互转",O10<>""),"⚠ 填了对方账户但类别不是账户互转（对方账户不起作用）",IF(AND(J10<>"",Z10=""),"⚠ 单位/人没在【往来单位】登记",IF(AND(N(F10)<0,AH10="收"),"⚠ 这是收款，以后请记在收入栏",IF(N(E10)<0,"⚠ 收入填了负数，已按支出算",IF(N(F10)<0,"↩ 冲回（退款）",IF(AND(R10<0,I10<>"固定资产购置",I10<>"付应付款",ISNUMBER(B10),IFERROR(SUMPRODUCT(ISNUMBER(SEARCH(基础资料!$AJ$5:$AJ$34,D10))*(基础资料!$AJ$5:$AJ$34<>"")*((AN10-基础资料!$AK$5:$AK$34)<=30)*((AN10-基础资料!$AK$5:$AK$34)>=-30)),0)>0),"⚠ 像是在买【基础资料】⑥ 登记的车/设备：类别改成「固定资产购置」，不然成本算两遍",IF(AND(OR(I10="材料费",I10="分包费",I10="机械运输费",I10="其他直接费"),J10="",H10<>"",COUNTIFS(应付登记!$E$5:$E$1004,H10,应付登记!$G$5:$G$1004,-R10)>0),"⚠ 这个项目有同样金额的应付登记：是付那家的，改类别选「付应付款」、改单位选那家（不然成本算两遍）","√")))))))))))))))))))))))))))) -> √ | R10: =ROUND(N(E10)-N(F10),2) -> -4000 | S10: =IF(ISNUMBER(B10),YEAR(B10)*100+MONTH(B10),"") -> 202605 | T10: =IF(N(AK10)=0,"",INDEX(_辅助!$S$1:$S$240,AK10)) | U10: =IF(OR(D10="",R10=0),"",IF(AND(Z10="临时工",R10<0),"临时工工资",IF(AG10="",IF(AA10=1,"工资",IF(Z10="临时工","临时工工资",IF(Z10="甲方/总包","工程款",IF(AND(OR(Z10="材料供应商",Z10="分包",Z10="机械运输"),Y10=1),"付应付款","")))),IF(AND(Y10=1,OR(Z10="材料供应商",Z10="分包",Z10="机械运输",Z10="其他"),OR(AG10="材料费",AG10="分包费",AG10="机械运输费",AG10="其他直接费",AG10="工资",AG10="临时工工资")),"付应付款",AG10)))) -> 工资 | V10: =IF(D10="","",IF(N(AM10)>0,IF(N(AM10)=0,"",INDEX(_辅助!$W$1:$W$900,AM10)),IF(N(AL10)=0,"",INDEX(_辅助!$W$1:$W$900,AL10)))) -> 张亮亮 | W10: =IF(I10="","",IFERROR(INDEX(基础资料!$V$5:$V$64,MATCH(I10,基础资料!$S$5:$S$64,0))&"","？")) -> 不进利润 | X10: =IF(R10=0,"",IF(OR(I10="",IFERROR(INDEX(基础资料!$U$5:$U$64,MATCH(I10,基础资料!$S$5:$S$64,0))&"","")=""),"待分类",IF(OR(I10="付应付款",IFERROR(INDEX(基础资料!$U$5:$U$64,MATCH(I10,基础资料!$S$5:$S$64,0))&"","")="应付款"),IF(Z10="材料供应商","应付材料款",IF(Z10="分包","应付分包款",IF(Z10="机械运输","应付机械运输费","应付其他款"))),IFERROR(INDEX(基础资料!$U$5:$U$64,MATCH(I10,基础资料!$S$5:$S$64,0))&"","")))) -> 应付职工薪酬 | Y10: =IF(J10="",0,IF(COUNTIF(应付登记!$D$5:$D$1004,J10)+COUNTIF(期初余额!$P$5:$P$204,J10)>0,1,0)) -> 0 | Z10: =IF(J10="","",IFERROR(INDEX(往来单位!$C$4:$C$303,MATCH(J10,往来单位!$B$4:$B$303,0))&"","")) -> 工人 | AA10: =IF(OR(Z10="管理人员",Z10="工人"),1,0) -> 1 | AB10: =IF(ISERROR(FIND("代",D10)),"",IFERROR(MID(D10,FIND("代",D10)+1,FIND("付",D10,FIND("代",D10))-FIND("代",D10)-1),"")) | AC10: =IF(I10<>"账户互转","",IF(J10<>"",IFERROR(INDEX(_辅助!$G$1:$G$40,MATCH(J10,_辅助!$F$1:$F$40,0)),IF(IFERROR(MATCH(1,INDEX(ISNUMBER(SEARCH(_辅助!$Z$1:$Z$40,D10))*(_辅助!$Z$1:$Z$40<>""),0),0),0)=0,"",INDEX(_辅助!$AA$1:$AA$40,IFERROR(MATCH(1,INDEX(ISNUMBER(SEARCH(_辅助!$Z$1:$Z$40,D10))*(_辅助!$Z$1:$Z$40<>""),0),0),0)))),IF(IFERROR(MATCH(1,INDEX(ISNUMBER(SEARCH(_辅助!$Z$1:$Z$40,D10))*(_辅助!$Z$1:$Z$40<>""),0),0),0)=0,"",INDEX(_辅助!$AA$1:$AA$40,IFERROR(MATCH(1,INDEX(ISNUMBER(SEARCH(_辅助!$Z$1:$Z$40,D10))*(_辅助!$Z$1:$Z$40<>""),0),0),0))))) | AD10: =IF(O10<>"",O10,AC10) | AE10: =IF(C10="","",IFERROR(INDEX(基础资料!$H$5:$H$24,MATCH(C10,基础资料!$G$5:$G$24,0))&"","")) -> 银行 | AF10: =IF(AD10="","",IFERROR(INDEX(基础资料!$H$5:$H$24,MATCH(AD10,基础资料!$G$5:$G$24,0))&"","")) | AG10: =IF(OR(D10="",R10=0),"",IFERROR(INDEX(基础资料!$AC$5:$AC$164,IF(IF(F10<>"","支","收")="收",MATCH(1,INDEX(ISNUMBER(SEARCH(_辅助!$AB$1:$AB$160,D10))*(_辅助!$AB$1:$AB$160<>""),0),0),MATCH(1,INDEX(ISNUMBER(SEARCH(_辅助!$AC$1:$AC$160,D10))*(_辅助!$AC$1:$AC$160<>""),0),0)))&"","")) -> 工资 | AH10: =IF(R10=0,"",IF(OR(IFERROR(INDEX(基础资料!$T$5:$T$64,MATCH(I10,基础资料!$S$5:$S$64,0))&"","")="收",IFERROR(INDEX(基础资料!$T$5:$T$64,MATCH(I10,基础资料!$S$5:$S$64,0))&"","")="支"),IFERROR(INDEX(基础资料!$T$5:$T$64,MATCH(I10,基础资料!$S$5:$S$64,0))&"",""),IF(R10>0,"收","支"))) -> 支 | AI10: =IF(N(AK10)=0,"",INDEX(_辅助!$R$1:$R$240,AK10)) | AJ10: =IF(OR(AI10="",L10<>""),0,SUMPRODUCT(ISNUMBER(SEARCH(_辅助!$R$1:$R$240,D10))*(_辅助!$R$1:$R$240<>"")*(1-ISNUMBER(SEARCH(_辅助!$R$1:$R$240,AI10)))*(_辅助!$S$1:$S$240<>T10))) -> 0 | AK10: =IF(D10="",0,IFERROR(MATCH(1,INDEX(ISNUMBER(SEARCH(_辅助!$R$1:$R$240,D10))*(_辅助!$R$1:$R$240<>""),0),0),0)) -> 0 | AL10: =IF(D10="",0,IFERROR(MATCH(1,INDEX(ISNUMBER(SEARCH(_辅助!$V$1:$V$900,D10))*(_辅助!$V$1:$V$900<>""),0),0),0)) -> 63 | AM10: =IF(AB10="",0,IFERROR(MATCH(1,INDEX(ISNUMBER(SEARCH(_辅助!$V$1:$V$900,AB10))*(_辅助!$V$1:$V$900<>""),0),0),0)) -> 0 | AN10: =IF(ISNUMBER(B10),INT(B10),0) -> 46145 | AO10: =IF(AND(X10="应收账款",R10>0,AN10>0,H10<>""),H10&"|"&COUNTIFS(资金流水!$H$6:$H$2005,H10,资金流水!$X$6:$X$2005,"应收账款",资金流水!$R$6:$R$2005,">0",资金流水!$AN$6:$AN$2005,">0",资金流水!$AN$6:$AN$2005,"<="&AN10),"") | AP10: =IF(AND(J10<>"",R10<0,AN10>0),J10&"|"&COUNTIFS(资金流水!$J$6:$J$2005,J10,资金流水!$R$6:$R$2005,"<0",资金流水!$AN$6:$AN$2005,">0",资金流水!$AN$6:$AN$2005,"<="&AN10),"") -> 张亮亮|1 | AQ10: =IF(AND(X10="其他应收款",AN10>0,J10<>""),J10&"|"&(COUNTIFS(资金流水!$J$6:$J$2005,J10,资金流水!$X$6:$X$2005,"其他应收款",资金流水!$AN$6:$AN$2005,">0",资金流水!$AN$6:$AN$2005,"<"&AN10)+COUNTIFS($J$6:J10,J10,$X$6:X10,"其他应收款",$AN$6:AN10,AN10)),"")
A11: =IF(AND(B11="",D11="",E11="",F11=""),"",ROW()-5) -> 6 | B11: 46148 | C11: 九江银行 | D11: 付共安门业材料款 | F11: 4940 | G11: =IF(C11="","",ROUND(IFERROR(INDEX(基础资料!$K$5:$K$24,MATCH(C11,基础资料!$G$5:$G$24,0)),0)+SUMIFS($R$6:R11,$C$6:C11,C11)-SUMIFS($R$6:R11,$AD$6:AD11,C11,$X$6:X11,"账户互转"),2)) -> -32940 | H11: =IF(L11<>"",L11,T11) | I11: =IF(M11<>"",M11,U11) -> 付应付款 | J11: =IF(N11<>"",N11,V11) -> 共安门业 | K11: =IF(AND(B11="",D11="",E11="",F11=""),"",IF(C11="","✗ 没选账户",IF(AE11="","✗ 账户不在【基础资料】② 里",IF(NOT(ISNUMBER(B11)),"✗ 日期要填成日期（2026/5/1）",IF(AND(ISNUMBER(B11),B11<基础资料!$C$9),"✗ 日期早于建账日期（建账前的放【期初余额】）",IF(AND(N(E11)<>0,N(F11)<>0),"✗ 收入、支出只填一边",IF(R11=0,"✗ 没有金额",IF(I11="","✗ 认不出收支类别：在「改类别」选",IF(W11="？","✗ 收支类别不在【基础资料】③ 里",IF(OR(I11="管理人员工资",I11="折旧费"),"✗ 这一类是自动算的，流水里不能选（发工资选「工资」，买设备选「固定资产购置」）",IF(AND(OR(X11="材料费",X11="人工费",X11="分包费",X11="机械运输费",X11="其他直接费",X11="票据贴息",X11="应收账款"),H11=""),"✗ 这一笔要选项目（摘要里的项目没在【项目档案】的话先去加上）",IF(AND(H11<>"",COUNTIF(项目档案!$B$4:$B$63,H11)=0),"✗ 项目不在【项目档案】里",IF(AND(OR(IFERROR(INDEX(基础资料!$W$5:$W$64,MATCH(I11,基础资料!$S$5:$S$64,0))&"","")="人",IFERROR(INDEX(基础资料!$W$5:$W$64,MATCH(I11,基础资料!$S$5:$S$64,0))&"","")="单位"),J11=""),"✗ 这一笔要选是谁（改单位/人）",IF(AND(I11="付应付款",NOT(OR(Z11="材料供应商",Z11="分包",Z11="机械运输",Z11="其他"))),"✗ 付应付款要选材料商、分包或机械单位",IF(AND(I11="付应付款",Y11=0),"✗ 这家没有应付：先在【应付登记】登记（现买现付的选材料费等）",IF(AND(OR(I11="工资",I11="工资退回"),AA11=0),"✗ 工资要选管理人员或工人（临时工选「临时工工资」）",IF(AND(I11="账户互转",AD11=""),"✗ 账户互转要在「对方账户」选（借款、报销选那个人的个人户）",IF(AND(I11="账户互转",AF11=""),"✗ 对方账户不在【基础资料】② 里",IF(AND(I11="账户互转",AD11=C11),"✗ 对方账户不能是自己",IF(IF(I11="账户互转",COUNTIFS(资金流水!$C$6:$C$2005,AD11,资金流水!$AD$6:$AD$2005,C11,资金流水!$I$6:$I$2005,"账户互转",资金流水!$R$6:$R$2005,-R11)>0,FALSE),"✗ 对方账户那边也记了这笔互转（只记一边：清空其中一行的内容）",IF(AJ11>0,"⚠ 摘要里有两个项目：拆成几行，或在「改项目」选",IF(AND(I11<>"账户互转",O11<>""),"⚠ 填了对方账户但类别不是账户互转（对方账户不起作用）",IF(AND(J11<>"",Z11=""),"⚠ 单位/人没在【往来单位】登记",IF(AND(N(F11)<0,AH11="收"),"⚠ 这是收款，以后请记在收入栏",IF(N(E11)<0,"⚠ 收入填了负数，已按支出算",IF(N(F11)<0,"↩ 冲回（退款）",IF(AND(R11<0,I11<>"固定资产购置",I11<>"付应付款",ISNUMBER(B11),IFERROR(SUMPRODUCT(ISNUMBER(SEARCH(基础资料!$AJ$5:$AJ$34,D11))*(基础资料!$AJ$5:$AJ$34<>"")*((AN11-基础资料!$AK$5:$AK$34)<=30)*((AN11-基础资料!$AK$5:$AK$34)>=-30)),0)>0),"⚠ 像是在买【基础资料】⑥ 登记的车/设备：类别改成「固定资产购置」，不然成本算两遍",IF(AND(OR(I11="材料费",I11="分包费",I11="机械运输费",I11="其他直接费"),J11="",H11<>"",COUNTIFS(应付登记!$E$5:$E$1004,H11,应付登记!$G$5:$G$1004,-R11)>0),"⚠ 这个项目有同样金额的应付登记：是付那家的，改类别选「付应付款」、改单位选那家（不然成本算两遍）","√")))))))))))))))))))))))))))) -> √ | R11: =ROUND(N(E11)-N(F11),2) -> -4940 | S11: =IF(ISNUMBER(B11),YEAR(B11)*100+MONTH(B11),"") -> 202605 | T11: =IF(N(AK11)=0,"",INDEX(_辅助!$S$1:$S$240,AK11)) | U11: =IF(OR(D11="",R11=0),"",IF(AND(Z11="临时工",R11<0),"临时工工资",IF(AG11="",IF(AA11=1,"工资",IF(Z11="临时工","临时工工资",IF(Z11="甲方/总包","工程款",IF(AND(OR(Z11="材料供应商",Z11="分包",Z11="机械运输"),Y11=1),"付应付款","")))),IF(AND(Y11=1,OR(Z11="材料供应商",Z11="分包",Z11="机械运输",Z11="其他"),OR(AG11="材料费",AG11="分包费",AG11="机械运输费",AG11="其他直接费",AG11="工资",AG11="临时工工资")),"付应付款",AG11)))) -> 付应付款 | V11: =IF(D11="","",IF(N(AM11)>0,IF(N(AM11)=0,"",INDEX(_辅助!$W$1:$W$900,AM11)),IF(N(AL11)=0,"",INDEX(_辅助!$W$1:$W$900,AL11)))) -> 共安门业 | W11: =IF(I11="","",IFERROR(INDEX(基础资料!$V$5:$V$64,MATCH(I11,基础资料!$S$5:$S$64,0))&"","？")) -> 不进利润 | X11: =IF(R11=0,"",IF(OR(I11="",IFERROR(INDEX(基础资料!$U$5:$U$64,MATCH(I11,基础资料!$S$5:$S$64,0))&"","")=""),"待分类",IF(OR(I11="付应付款",IFERROR(INDEX(基础资料!$U$5:$U$64,MATCH(I11,基础资料!$S$5:$S$64,0))&"","")="应付款"),IF(Z11="材料供应商","应付材料款",IF(Z11="分包","应付分包款",IF(Z11="机械运输","应付机械运输费","应付其他款"))),IFERROR(INDEX(基础资料!$U$5:$U$64,MATCH(I11,基础资料!$S$5:$S$64,0))&"","")))) -> 应付分包款 | Y11: =IF(J11="",0,IF(COUNTIF(应付登记!$D$5:$D$1004,J11)+COUNTIF(期初余额!$P$5:$P$204,J11)>0,1,0)) -> 1 | Z11: =IF(J11="","",IFERROR(INDEX(往来单位!$C$4:$C$303,MATCH(J11,往来单位!$B$4:$B$303,0))&"","")) -> 分包 | AA11: =IF(OR(Z11="管理人员",Z11="工人"),1,0) -> 0 | AB11: =IF(ISERROR(FIND("代",D11)),"",IFERROR(MID(D11,FIND("代",D11)+1,FIND("付",D11,FIND("代",D11))-FIND("代",D11)-1),"")) | AC11: =IF(I11<>"账户互转","",IF(J11<>"",IFERROR(INDEX(_辅助!$G$1:$G$40,MATCH(J11,_辅助!$F$1:$F$40,0)),IF(IFERROR(MATCH(1,INDEX(ISNUMBER(SEARCH(_辅助!$Z$1:$Z$40,D11))*(_辅助!$Z$1:$Z$40<>""),0),0),0)=0,"",INDEX(_辅助!$AA$1:$AA$40,IFERROR(MATCH(1,INDEX(ISNUMBER(SEARCH(_辅助!$Z$1:$Z$40,D11))*(_辅助!$Z$1:$Z$40<>""),0),0),0)))),IF(IFERROR(MATCH(1,INDEX(ISNUMBER(SEARCH(_辅助!$Z$1:$Z$40,D11))*(_辅助!$Z$1:$Z$40<>""),0),0),0)=0,"",INDEX(_辅助!$AA$1:$AA$40,IFERROR(MATCH(1,INDEX(ISNUMBER(SEARCH(_辅助!$Z$1:$Z$40,D11))*(_辅助!$Z$1:$Z$40<>""),0),0),0))))) | AD11: =IF(O11<>"",O11,AC11) | AE11: =IF(C11="","",IFERROR(INDEX(基础资料!$H$5:$H$24,MATCH(C11,基础资料!$G$5:$G$24,0))&"","")) -> 银行 | AF11: =IF(AD11="","",IFERROR(INDEX(基础资料!$H$5:$H$24,MATCH(AD11,基础资料!$G$5:$G$24,0))&"","")) | AG11: =IF(OR(D11="",R11=0),"",IFERROR(INDEX(基础资料!$AC$5:$AC$164,IF(IF(F11<>"","支","收")="收",MATCH(1,INDEX(ISNUMBER(SEARCH(_辅助!$AB$1:$AB$160,D11))*(_辅助!$AB$1:$AB$160<>""),0),0),MATCH(1,INDEX(ISNUMBER(SEARCH(_辅助!$AC$1:$AC$160,D11))*(_辅助!$AC$1:$AC$160<>""),0),0)))&"","")) -> 材料费 | AH11: =IF(R11=0,"",IF(OR(IFERROR(INDEX(基础资料!$T$5:$T$64,MATCH(I11,基础资料!$S$5:$S$64,0))&"","")="收",IFERROR(INDEX(基础资料!$T$5:$T$64,MATCH(I11,基础资料!$S$5:$S$64,0))&"","")="支"),IFERROR(INDEX(基础资料!$T$5:$T$64,MATCH(I11,基础资料!$S$5:$S$64,0))&"",""),IF(R11>0,"收","支"))) -> 支 | AI11: =IF(N(AK11)=0,"",INDEX(_辅助!$R$1:$R$240,AK11)) | AJ11: =IF(OR(AI11="",L11<>""),0,SUMPRODUCT(ISNUMBER(SEARCH(_辅助!$R$1:$R$240,D11))*(_辅助!$R$1:$R$240<>"")*(1-ISNUMBER(SEARCH(_辅助!$R$1:$R$240,AI11)))*(_辅助!$S$1:$S$240<>T11))) -> 0 | AK11: =IF(D11="",0,IFERROR(MATCH(1,INDEX(ISNUMBER(SEARCH(_辅助!$R$1:$R$240,D11))*(_辅助!$R$1:$R$240<>""),0),0),0)) -> 0 | AL11: =IF(D11="",0,IFERROR(MATCH(1,INDEX(ISNUMBER(SEARCH(_辅助!$V$1:$V$900,D11))*(_辅助!$V$1:$V$900<>""),0),0),0)) -> 38 | AM11: =IF(AB11="",0,IFERROR(MATCH(1,INDEX(ISNUMBER(SEARCH(_辅助!$V$1:$V$900,AB11))*(_辅助!$V$1:$V$900<>""),0),0),0)) -> 0 | AN11: =IF(ISNUMBER(B11),INT(B11),0) -> 46148 | AO11: =IF(AND(X11="应收账款",R11>0,AN11>0,H11<>""),H11&"|"&COUNTIFS(资金流水!$H$6:$H$2005,H11,资金流水!$X$6:$X$2005,"应收账款",资金流水!$R$6:$R$2005,">0",资金流水!$AN$6:$AN$2005,">0",资金流水!$AN$6:$AN$2005,"<="&AN11),"") | AP11: =IF(AND(J11<>"",R11<0,AN11>0),J11&"|"&COUNTIFS(资金流水!$J$6:$J$2005,J11,资金流水!$R$6:$R$2005,"<0",资金流水!$AN$6:$AN$2005,">0",资金流水!$AN$6:$AN$2005,"<="&AN11),"") -> 共安门业|2 | AQ11: =IF(AND(X11="其他应收款",AN11>0,J11<>""),J11&"|"&(COUNTIFS(资金流水!$J$6:$J$2005,J11,资金流水!$X$6:$X$2005,"其他应收款",资金流水!$AN$6:$AN$2005,">0",资金流水!$AN$6:$AN$2005,"<"&AN11)+COUNTIFS($J$6:J11,J11,$X$6:X11,"其他应收款",$AN$6:AN11,AN11)),"")
A12: =IF(AND(B12="",D12="",E12="",F12=""),"",ROW()-5) -> 7 | B12: 46150 | C12: 九江银行 | D12: 收到股东借款-聂辉 | E12: 10000 | G12: =IF(C12="","",ROUND(IFERROR(INDEX(基础资料!$K$5:$K$24,MATCH(C12,基础资料!$G$5:$G$24,0)),0)+SUMIFS($R$6:R12,$C$6:C12,C12)-SUMIFS($R$6:R12,$AD$6:AD12,C12,$X$6:X12,"账户互转"),2)) -> -22940 | H12: =IF(L12<>"",L12,T12) | I12: =IF(M12<>"",M12,U12) -> 账户互转 | J12: =IF(N12<>"",N12,V12) -> 聂辉 | K12: =IF(AND(B12="",D12="",E12="",F12=""),"",IF(C12="","✗ 没选账户",IF(AE12="","✗ 账户不在【基础资料】② 里",IF(NOT(ISNUMBER(B12)),"✗ 日期要填成日期（2026/5/1）",IF(AND(ISNUMBER(B12),B12<基础资料!$C$9),"✗ 日期早于建账日期（建账前的放【期初余额】）",IF(AND(N(E12)<>0,N(F12)<>0),"✗ 收入、支出只填一边",IF(R12=0,"✗ 没有金额",IF(I12="","✗ 认不出收支类别：在「改类别」选",IF(W12="？","✗ 收支类别不在【基础资料】③ 里",IF(OR(I12="管理人员工资",I12="折旧费"),"✗ 这一类是自动算的，流水里不能选（发工资选「工资」，买设备选「固定资产购置」）",IF(AND(OR(X12="材料费",X12="人工费",X12="分包费",X12="机械运输费",X12="其他直接费",X12="票据贴息",X12="应收账款"),H12=""),"✗ 这一笔要选项目（摘要里的项目没在【项目档案】的话先去加上）",IF(AND(H12<>"",COUNTIF(项目档案!$B$4:$B$63,H12)=0),"✗ 项目不在【项目档案】里",IF(AND(OR(IFERROR(INDEX(基础资料!$W$5:$W$64,MATCH(I12,基础资料!$S$5:$S$64,0))&"","")="人",IFERROR(INDEX(基础资料!$W$5:$W$64,MATCH(I12,基础资料!$S$5:$S$64,0))&"","")="单位"),J12=""),"✗ 这一笔要选是谁（改单位/人）",IF(AND(I12="付应付款",NOT(OR(Z12="材料供应商",Z12="分包",Z12="机械运输",Z12="其他"))),"✗ 付应付款要选材料商、分包或机械单位",IF(AND(I12="付应付款",Y12=0),"✗ 这家没有应付：先在【应付登记】登记（现买现付的选材料费等）",IF(AND(OR(I12="工资",I12="工资退回"),AA12=0),"✗ 工资要选管理人员或工人（临时工选「临时工工资」）",IF(AND(I12="账户互转",AD12=""),"✗ 账户互转要在「对方账户」选（借款、报销选那个人的个人户）",IF(AND(I12="账户互转",AF12=""),"✗ 对方账户不在【基础资料】② 里",IF(AND(I12="账户互转",AD12=C12),"✗ 对方账户不能是自己",IF(IF(I12="账户互转",COUNTIFS(资金流水!$C$6:$C$2005,AD12,资金流水!$AD$6:$AD$2005,C12,资金流水!$I$6:$I$2005,"账户互转",资金流水!$R$6:$R$2005,-R12)>0,FALSE),"✗ 对方账户那边也记了这笔互转（只记一边：清空其中一行的内容）",IF(AJ12>0,"⚠ 摘要里有两个项目：拆成几行，或在「改项目」选",IF(AND(I12<>"账户互转",O12<>""),"⚠ 填了对方账户但类别不是账户互转（对方账户不起作用）",IF(AND(J12<>"",Z12=""),"⚠ 单位/人没在【往来单位】登记",IF(AND(N(F12)<0,AH12="收"),"⚠ 这是收款，以后请记在收入栏",IF(N(E12)<0,"⚠ 收入填了负数，已按支出算",IF(N(F12)<0,"↩ 冲回（退款）",IF(AND(R12<0,I12<>"固定资产购置",I12<>"付应付款",ISNUMBER(B12),IFERROR(SUMPRODUCT(ISNUMBER(SEARCH(基础资料!$AJ$5:$AJ$34,D12))*(基础资料!$AJ$5:$AJ$34<>"")*((AN12-基础资料!$AK$5:$AK$34)<=30)*((AN12-基础资料!$AK$5:$AK$34)>=-30)),0)>0),"⚠ 像是在买【基础资料】⑥ 登记的车/设备：类别改成「固定资产购置」，不然成本算两遍",IF(AND(OR(I12="材料费",I12="分包费",I12="机械运输费",I12="其他直接费"),J12="",H12<>"",COUNTIFS(应付登记!$E$5:$E$1004,H12,应付登记!$G$5:$G$1004,-R12)>0),"⚠ 这个项目有同样金额的应付登记：是付那家的，改类别选「付应付款」、改单位选那家（不然成本算两遍）","√")))))))))))))))))))))))))))) -> √ | R12: =ROUND(N(E12)-N(F12),2) -> 10000 | S12: =IF(ISNUMBER(B12),YEAR(B12)*100+MONTH(B12),"") -> 202605 | T12: =IF(N(AK12)=0,"",INDEX(_辅助!$S$1:$S$240,AK12)) | U12: =IF(OR(D12="",R12=0),"",IF(AND(Z12="临时工",R12<0),"临时工工资",IF(AG12="",IF(AA12=1,"工资",IF(Z12="临时工","临时工工资",IF(Z12="甲方/总包","工程款",IF(AND(OR(Z12="材料供应商",Z12="分包",Z12="机械运输"),Y12=1),"付应付款","")))),IF(AND(Y12=1,OR(Z12="材料供应商",Z12="分包",Z12="机械运输",Z12="其他"),OR(AG12="材料费",AG12="分包费",AG12="机械运输费",AG12="其他直接费",AG12="工资",AG12="临时工工资")),"付应付款",AG12)))) -> 账户互转 | V12: =IF(D12="","",IF(N(AM12)>0,IF(N(AM12)=0,"",INDEX(_辅助!$W$1:$W$900,AM12)),IF(N(AL12)=0,"",INDEX(_辅助!$W$1:$W$900,AL12)))) -> 聂辉 | W12: =IF(I12="","",IFERROR(INDEX(基础资料!$V$5:$V$64,MATCH(I12,基础资料!$S$5:$S$64,0))&"","？")) -> 不进利润 | X12: =IF(R12=0,"",IF(OR(I12="",IFERROR(INDEX(基础资料!$U$5:$U$64,MATCH(I12,基础资料!$S$5:$S$64,0))&"","")=""),"待分类",IF(OR(I12="付应付款",IFERROR(INDEX(基础资料!$U$5:$U$64,MATCH(I12,基础资料!$S$5:$S$64,0))&"","")="应付款"),IF(Z12="材料供应商","应付材料款",IF(Z12="分包","应付分包款",IF(Z12="机械运输","应付机械运输费","应付其他款"))),IFERROR(INDEX(基础资料!$U$5:$U$64,MATCH(I12,基础资料!$S$5:$S$64,0))&"","")))) -> 账户互转 | Y12: =IF(J12="",0,IF(COUNTIF(应付登记!$D$5:$D$1004,J12)+COUNTIF(期初余额!$P$5:$P$204,J12)>0,1,0)) -> 0 | Z12: =IF(J12="","",IFERROR(INDEX(往来单位!$C$4:$C$303,MATCH(J12,往来单位!$B$4:$B$303,0))&"","")) -> 管理人员 | AA12: =IF(OR(Z12="管理人员",Z12="工人"),1,0) -> 1 | AB12: =IF(ISERROR(FIND("代",D12)),"",IFERROR(MID(D12,FIND("代",D12)+1,FIND("付",D12,FIND("代",D12))-FIND("代",D12)-1),"")) | AC12: =IF(I12<>"账户互转","",IF(J12<>"",IFERROR(INDEX(_辅助!$G$1:$G$40,MATCH(J12,_辅助!$F$1:$F$40,0)),IF(IFERROR(MATCH(1,INDEX(ISNUMBER(SEARCH(_辅助!$Z$1:$Z$40,D12))*(_辅助!$Z$1:$Z$40<>""),0),0),0)=0,"",INDEX(_辅助!$AA$1:$AA$40,IFERROR(MATCH(1,INDEX(ISNUMBER(SEARCH(_辅助!$Z$1:$Z$40,D12))*(_辅助!$Z$1:$Z$40<>""),0),0),0)))),IF(IFERROR(MATCH(1,INDEX(ISNUMBER(SEARCH(_辅助!$Z$1:$Z$40,D12))*(_辅助!$Z$1:$Z$40<>""),0),0),0)=0,"",INDEX(_辅助!$AA$1:$AA$40,IFERROR(MATCH(1,INDEX(ISNUMBER(SEARCH(_辅助!$Z$1:$Z$40,D12))*(_辅助!$Z$1:$Z$40<>""),0),0),0))))) -> 聂辉个人户 | AD12: =IF(O12<>"",O12,AC12) -> 聂辉个人户 | AE12: =IF(C12="","",IFERROR(INDEX(基础资料!$H$5:$H$24,MATCH(C12,基础资料!$G$5:$G$24,0))&"","")) -> 银行 | AF12: =IF(AD12="","",IFERROR(INDEX(基础资料!$H$5:$H$24,MATCH(AD12,基础资料!$G$5:$G$24,0))&"","")) -> 个人户 | AG12: =IF(OR(D12="",R12=0),"",IFERROR(INDEX(基础资料!$AC$5:$AC$164,IF(IF(F12<>"","支","收")="收",MATCH(1,INDEX(ISNUMBER(SEARCH(_辅助!$AB$1:$AB$160,D12))*(_辅助!$AB$1:$AB$160<>""),0),0),MATCH(1,INDEX(ISNUMBER(SEARCH(_辅助!$AC$1:$AC$160,D12))*(_辅助!$AC$1:$AC$160<>""),0),0)))&"","")) -> 账户互转 | AH12: =IF(R12=0,"",IF(OR(IFERROR(INDEX(基础资料!$T$5:$T$64,MATCH(I12,基础资料!$S$5:$S$64,0))&"","")="收",IFERROR(INDEX(基础资料!$T$5:$T$64,MATCH(I12,基础资料!$S$5:$S$64,0))&"","")="支"),IFERROR(INDEX(基础资料!$T$5:$T$64,MATCH(I12,基础资料!$S$5:$S$64,0))&"",""),IF(R12>0,"收","支"))) -> 收 | AI12: =IF(N(AK12)=0,"",INDEX(_辅助!$R$1:$R$240,AK12)) | AJ12: =IF(OR(AI12="",L12<>""),0,SUMPRODUCT(ISNUMBER(SEARCH(_辅助!$R$1:$R$240,D12))*(_辅助!$R$1:$R$240<>"")*(1-ISNUMBER(SEARCH(_辅助!$R$1:$R$240,AI12)))*(_辅助!$S$1:$S$240<>T12))) -> 0 | AK12: =IF(D12="",0,IFERROR(MATCH(1,INDEX(ISNUMBER(SEARCH(_辅助!$R$1:$R$240,D12))*(_辅助!$R$1:$R$240<>""),0),0),0)) -> 0 | AL12: =IF(D12="",0,IFERROR(MATCH(1,INDEX(ISNUMBER(SEARCH(_辅助!$V$1:$V$900,D12))*(_辅助!$V$1:$V$900<>""),0),0),0)) -> 111 | AM12: =IF(AB12="",0,IFERROR(MATCH(1,INDEX(ISNUMBER(SEARCH(_辅助!$V$1:$V$900,AB12))*(_辅助!$V$1:$V$900<>""),0),0),0)) -> 0 | AN12: =IF(ISNUMBER(B12),INT(B12),0) -> 46150 | AO12: =IF(AND(X12="应收账款",R12>0,AN12>0,H12<>""),H12&"|"&COUNTIFS(资金流水!$H$6:$H$2005,H12,资金流水!$X$6:$X$2005,"应收账款",资金流水!$R$6:$R$2005,">0",资金流水!$AN$6:$AN$2005,">0",资金流水!$AN$6:$AN$2005,"<="&AN12),"") | AP12: =IF(AND(J12<>"",R12<0,AN12>0),J12&"|"&COUNTIFS(资金流水!$J$6:$J$2005,J12,资金流水!$R$6:$R$2005,"<0",资金流水!$AN$6:$AN$2005,">0",资金流水!$AN$6:$AN$2005,"<="&AN12),"") | AQ12: =IF(AND(X12="其他应收款",AN12>0,J12<>""),J12&"|"&(COUNTIFS(资金流水!$J$6:$J$2005,J12,资金流水!$X$6:$X$2005,"其他应收款",资金流水!$AN$6:$AN$2005,">0",资金流水!$AN$6:$AN$2005,"<"&AN12)+COUNTIFS($J$6:J12,J12,$X$6:X12,"其他应收款",$AN$6:AN12,AN12)),"")
A13: =IF(AND(B13="",D13="",E13="",F13=""),"",ROW()-5) -> 8 | B13: 46150 | C13: 九江银行 | D13: 收到股东借款-聂辉 | E13: 2000 | G13: =IF(C13="","",ROUND(IFERROR(INDEX(基础资料!$K$5:$K$24,MATCH(C13,基础资料!$G$5:$G$24,0)),0)+SUMIFS($R$6:R13,$C$6:C13,C13)-SUMIFS($R$6:R13,$AD$6:AD13,C13,$X$6:X13,"账户互转"),2)) -> -20940 | H13: =IF(L13<>"",L13,T13) | I13: =IF(M13<>"",M13,U13) -> 账户互转 | J13: =IF(N13<>"",N13,V13) -> 聂辉 | K13: =IF(AND(B13="",D13="",E13="",F13=""),"",IF(C13="","✗ 没选账户",IF(AE13="","✗ 账户不在【基础资料】② 里",IF(NOT(ISNUMBER(B13)),"✗ 日期要填成日期（2026/5/1）",IF(AND(ISNUMBER(B13),B13<基础资料!$C$9),"✗ 日期早于建账日期（建账前的放【期初余额】）",IF(AND(N(E13)<>0,N(F13)<>0),"✗ 收入、支出只填一边",IF(R13=0,"✗ 没有金额",IF(I13="","✗ 认不出收支类别：在「改类别」选",IF(W13="？","✗ 收支类别不在【基础资料】③ 里",IF(OR(I13="管理人员工资",I13="折旧费"),"✗ 这一类是自动算的，流水里不能选（发工资选「工资」，买设备选「固定资产购置」）",IF(AND(OR(X13="材料费",X13="人工费",X13="分包费",X13="机械运输费",X13="其他直接费",X13="票据贴息",X13="应收账款"),H13=""),"✗ 这一笔要选项目（摘要里的项目没在【项目档案】的话先去加上）",IF(AND(H13<>"",COUNTIF(项目档案!$B$4:$B$63,H13)=0),"✗ 项目不在【项目档案】里",IF(AND(OR(IFERROR(INDEX(基础资料!$W$5:$W$64,MATCH(I13,基础资料!$S$5:$S$64,0))&"","")="人",IFERROR(INDEX(基础资料!$W$5:$W$64,MATCH(I13,基础资料!$S$5:$S$64,0))&"","")="单位"),J13=""),"✗ 这一笔要选是谁（改单位/人）",IF(AND(I13="付应付款",NOT(OR(Z13="材料供应商",Z13="分包",Z13="机械运输",Z13="其他"))),"✗ 付应付款要选材料商、分包或机械单位",IF(AND(I13="付应付款",Y13=0),"✗ 这家没有应付：先在【应付登记】登记（现买现付的选材料费等）",IF(AND(OR(I13="工资",I13="工资退回"),AA13=0),"✗ 工资要选管理人员或工人（临时工选「临时工工资」）",IF(AND(I13="账户互转",AD13=""),"✗ 账户互转要在「对方账户」选（借款、报销选那个人的个人户）",IF(AND(I13="账户互转",AF13=""),"✗ 对方账户不在【基础资料】② 里",IF(AND(I13="账户互转",AD13=C13),"✗ 对方账户不能是自己",IF(IF(I13="账户互转",COUNTIFS(资金流水!$C$6:$C$2005,AD13,资金流水!$AD$6:$AD$2005,C13,资金流水!$I$6:$I$2005,"账户互转",资金流水!$R$6:$R$2005,-R13)>0,FALSE),"✗ 对方账户那边也记了这笔互转（只记一边：清空其中一行的内容）",IF(AJ13>0,"⚠ 摘要里有两个项目：拆成几行，或在「改项目」选",IF(AND(I13<>"账户互转",O13<>""),"⚠ 填了对方账户但类别不是账户互转（对方账户不起作用）",IF(AND(J13<>"",Z13=""),"⚠ 单位/人没在【往来单位】登记",IF(AND(N(F13)<0,AH13="收"),"⚠ 这是收款，以后请记在收入栏",IF(N(E13)<0,"⚠ 收入填了负数，已按支出算",IF(N(F13)<0,"↩ 冲回（退款）",IF(AND(R13<0,I13<>"固定资产购置",I13<>"付应付款",ISNUMBER(B13),IFERROR(SUMPRODUCT(ISNUMBER(SEARCH(基础资料!$AJ$5:$AJ$34,D13))*(基础资料!$AJ$5:$AJ$34<>"")*((AN13-基础资料!$AK$5:$AK$34)<=30)*((AN13-基础资料!$AK$5:$AK$34)>=-30)),0)>0),"⚠ 像是在买【基础资料】⑥ 登记的车/设备：类别改成「固定资产购置」，不然成本算两遍",IF(AND(OR(I13="材料费",I13="分包费",I13="机械运输费",I13="其他直接费"),J13="",H13<>"",COUNTIFS(应付登记!$E$5:$E$1004,H13,应付登记!$G$5:$G$1004,-R13)>0),"⚠ 这个项目有同样金额的应付登记：是付那家的，改类别选「付应付款」、改单位选那家（不然成本算两遍）","√")))))))))))))))))))))))))))) -> √ | R13: =ROUND(N(E13)-N(F13),2) -> 2000 | S13: =IF(ISNUMBER(B13),YEAR(B13)*100+MONTH(B13),"") -> 202605 | T13: =IF(N(AK13)=0,"",INDEX(_辅助!$S$1:$S$240,AK13)) | U13: =IF(OR(D13="",R13=0),"",IF(AND(Z13="临时工",R13<0),"临时工工资",IF(AG13="",IF(AA13=1,"工资",IF(Z13="临时工","临时工工资",IF(Z13="甲方/总包","工程款",IF(AND(OR(Z13="材料供应商",Z13="分包",Z13="机械运输"),Y13=1),"付应付款","")))),IF(AND(Y13=1,OR(Z13="材料供应商",Z13="分包",Z13="机械运输",Z13="其他"),OR(AG13="材料费",AG13="分包费",AG13="机械运输费",AG13="其他直接费",AG13="工资",AG13="临时工工资")),"付应付款",AG13)))) -> 账户互转 | V13: =IF(D13="","",IF(N(AM13)>0,IF(N(AM13)=0,"",INDEX(_辅助!$W$1:$W$900,AM13)),IF(N(AL13)=0,"",INDEX(_辅助!$W$1:$W$900,AL13)))) -> 聂辉 | W13: =IF(I13="","",IFERROR(INDEX(基础资料!$V$5:$V$64,MATCH(I13,基础资料!$S$5:$S$64,0))&"","？")) -> 不进利润 | X13: =IF(R13=0,"",IF(OR(I13="",IFERROR(INDEX(基础资料!$U$5:$U$64,MATCH(I13,基础资料!$S$5:$S$64,0))&"","")=""),"待分类",IF(OR(I13="付应付款",IFERROR(INDEX(基础资料!$U$5:$U$64,MATCH(I13,基础资料!$S$5:$S$64,0))&"","")="应付款"),IF(Z13="材料供应商","应付材料款",IF(Z13="分包","应付分包款",IF(Z13="机械运输","应付机械运输费","应付其他款"))),IFERROR(INDEX(基础资料!$U$5:$U$64,MATCH(I13,基础资料!$S$5:$S$64,0))&"","")))) -> 账户互转 | Y13: =IF(J13="",0,IF(COUNTIF(应付登记!$D$5:$D$1004,J13)+COUNTIF(期初余额!$P$5:$P$204,J13)>0,1,0)) -> 0 | Z13: =IF(J13="","",IFERROR(INDEX(往来单位!$C$4:$C$303,MATCH(J13,往来单位!$B$4:$B$303,0))&"","")) -> 管理人员 | AA13: =IF(OR(Z13="管理人员",Z13="工人"),1,0) -> 1 | AB13: =IF(ISERROR(FIND("代",D13)),"",IFERROR(MID(D13,FIND("代",D13)+1,FIND("付",D13,FIND("代",D13))-FIND("代",D13)-1),"")) | AC13: =IF(I13<>"账户互转","",IF(J13<>"",IFERROR(INDEX(_辅助!$G$1:$G$40,MATCH(J13,_辅助!$F$1:$F$40,0)),IF(IFERROR(MATCH(1,INDEX(ISNUMBER(SEARCH(_辅助!$Z$1:$Z$40,D13))*(_辅助!$Z$1:$Z$40<>""),0),0),0)=0,"",INDEX(_辅助!$AA$1:$AA$40,IFERROR(MATCH(1,INDEX(ISNUMBER(SEARCH(_辅助!$Z$1:$Z$40,D13))*(_辅助!$Z$1:$Z$40<>""),0),0),0)))),IF(IFERROR(MATCH(1,INDEX(ISNUMBER(SEARCH(_辅助!$Z$1:$Z$40,D13))*(_辅助!$Z$1:$Z$40<>""),0),0),0)=0,"",INDEX(_辅助!$AA$1:$AA$40,IFERROR(MATCH(1,INDEX(ISNUMBER(SEARCH(_辅助!$Z$1:$Z$40,D13))*(_辅助!$Z$1:$Z$40<>""),0),0),0))))) -> 聂辉个人户 | AD13: =IF(O13<>"",O13,AC13) -> 聂辉个人户 | AE13: =IF(C13="","",IFERROR(INDEX(基础资料!$H$5:$H$24,MATCH(C13,基础资料!$G$5:$G$24,0))&"","")) -> 银行 | AF13: =IF(AD13="","",IFERROR(INDEX(基础资料!$H$5:$H$24,MATCH(AD13,基础资料!$G$5:$G$24,0))&"","")) -> 个人户 | AG13: =IF(OR(D13="",R13=0),"",IFERROR(INDEX(基础资料!$AC$5:$AC$164,IF(IF(F13<>"","支","收")="收",MATCH(1,INDEX(ISNUMBER(SEARCH(_辅助!$AB$1:$AB$160,D13))*(_辅助!$AB$1:$AB$160<>""),0),0),MATCH(1,INDEX(ISNUMBER(SEARCH(_辅助!$AC$1:$AC$160,D13))*(_辅助!$AC$1:$AC$160<>""),0),0)))&"","")) -> 账户互转 | AH13: =IF(R13=0,"",IF(OR(IFERROR(INDEX(基础资料!$T$5:$T$64,MATCH(I13,基础资料!$S$5:$S$64,0))&"","")="收",IFERROR(INDEX(基础资料!$T$5:$T$64,MATCH(I13,基础资料!$S$5:$S$64,0))&"","")="支"),IFERROR(INDEX(基础资料!$T$5:$T$64,MATCH(I13,基础资料!$S$5:$S$64,0))&"",""),IF(R13>0,"收","支"))) -> 收 | AI13: =IF(N(AK13)=0,"",INDEX(_辅助!$R$1:$R$240,AK13)) | AJ13: =IF(OR(AI13="",L13<>""),0,SUMPRODUCT(ISNUMBER(SEARCH(_辅助!$R$1:$R$240,D13))*(_辅助!$R$1:$R$240<>"")*(1-ISNUMBER(SEARCH(_辅助!$R$1:$R$240,AI13)))*(_辅助!$S$1:$S$240<>T13))) -> 0 | AK13: =IF(D13="",0,IFERROR(MATCH(1,INDEX(ISNUMBER(SEARCH(_辅助!$R$1:$R$240,D13))*(_辅助!$R$1:$R$240<>""),0),0),0)) -> 0 | AL13: =IF(D13="",0,IFERROR(MATCH(1,INDEX(ISNUMBER(SEARCH(_辅助!$V$1:$V$900,D13))*(_辅助!$V$1:$V$900<>""),0),0),0)) -> 111 | AM13: =IF(AB13="",0,IFERROR(MATCH(1,INDEX(ISNUMBER(SEARCH(_辅助!$V$1:$V$900,AB13))*(_辅助!$V$1:$V$900<>""),0),0),0)) -> 0 | AN13: =IF(ISNUMBER(B13),INT(B13),0) -> 46150 | AO13: =IF(AND(X13="应收账款",R13>0,AN13>0,H13<>""),H13&"|"&COUNTIFS(资金流水!$H$6:$H$2005,H13,资金流水!$X$6:$X$2005,"应收账款",资金流水!$R$6:$R$2005,">0",资金流水!$AN$6:$AN$2005,">0",资金流水!$AN$6:$AN$2005,"<="&AN13),"") | AP13: =IF(AND(J13<>"",R13<0,AN13>0),J13&"|"&COUNTIFS(资金流水!$J$6:$J$2005,J13,资金流水!$R$6:$R$2005,"<0",资金流水!$AN$6:$AN$2005,">0",资金流水!$AN$6:$AN$2005,"<="&AN13),"") | AQ13: =IF(AND(X13="其他应收款",AN13>0,J13<>""),J13&"|"&(COUNTIFS(资金流水!$J$6:$J$2005,J13,资金流水!$X$6:$X$2005,"其他应收款",资金流水!$AN$6:$AN$2005,">0",资金流水!$AN$6:$AN$2005,"<"&AN13)+COUNTIFS($J$6:J13,J13,$X$6:X13,"其他应收款",$AN$6:AN13,AN13)),"")
A14: =IF(AND(B14="",D14="",E14="",F14=""),"",ROW()-5) -> 9 | B14: 46150 | C14: 九江银行 | D14: 支付酒款 | F14: 20000 | G14: =IF(C14="","",ROUND(IFERROR(INDEX(基础资料!$K$5:$K$24,MATCH(C14,基础资料!$G$5:$G$24,0)),0)+SUMIFS($R$6:R14,$C$6:C14,C14)-SUMIFS($R$6:R14,$AD$6:AD14,C14,$X$6:X14,"账户互转"),2)) -> -40940 | H14: =IF(L14<>"",L14,T14) | I14: =IF(M14<>"",M14,U14) -> 业务招待费 | J14: =IF(N14<>"",N14,V14) | K14: =IF(AND(B14="",D14="",E14="",F14=""),"",IF(C14="","✗ 没选账户",IF(AE14="","✗ 账户不在【基础资料】② 里",IF(NOT(ISNUMBER(B14)),"✗ 日期要填成日期（2026/5/1）",IF(AND(ISNUMBER(B14),B14<基础资料!$C$9),"✗ 日期早于建账日期（建账前的放【期初余额】）",IF(AND(N(E14)<>0,N(F14)<>0),"✗ 收入、支出只填一边",IF(R14=0,"✗ 没有金额",IF(I14="","✗ 认不出收支类别：在「改类别」选",IF(W14="？","✗ 收支类别不在【基础资料】③ 里",IF(OR(I14="管理人员工资",I14="折旧费"),"✗ 这一类是自动算的，流水里不能选（发工资选「工资」，买设备选「固定资产购置」）",IF(AND(OR(X14="材料费",X14="人工费",X14="分包费",X14="机械运输费",X14="其他直接费",X14="票据贴息",X14="应收账款"),H14=""),"✗ 这一笔要选项目（摘要里的项目没在【项目档案】的话先去加上）",IF(AND(H14<>"",COUNTIF(项目档案!$B$4:$B$63,H14)=0),"✗ 项目不在【项目档案】里",IF(AND(OR(IFERROR(INDEX(基础资料!$W$5:$W$64,MATCH(I14,基础资料!$S$5:$S$64,0))&"","")="人",IFERROR(INDEX(基础资料!$W$5:$W$64,MATCH(I14,基础资料!$S$5:$S$64,0))&"","")="单位"),J14=""),"✗ 这一笔要选是谁（改单位/人）",IF(AND(I14="付应付款",NOT(OR(Z14="材料供应商",Z14="分包",Z14="机械运输",Z14="其他"))),"✗ 付应付款要选材料商、分包或机械单位",IF(AND(I14="付应付款",Y14=0),"✗ 这家没有应付：先在【应付登记】登记（现买现付的选材料费等）",IF(AND(OR(I14="工资",I14="工资退回"),AA14=0),"✗ 工资要选管理人员或工人（临时工选「临时工工资」）",IF(AND(I14="账户互转",AD14=""),"✗ 账户互转要在「对方账户」选（借款、报销选那个人的个人户）",IF(AND(I14="账户互转",AF14=""),"✗ 对方账户不在【基础资料】② 里",IF(AND(I14="账户互转",AD14=C14),"✗ 对方账户不能是自己",IF(IF(I14="账户互转",COUNTIFS(资金流水!$C$6:$C$2005,AD14,资金流水!$AD$6:$AD$2005,C14,资金流水!$I$6:$I$2005,"账户互转",资金流水!$R$6:$R$2005,-R14)>0,FALSE),"✗ 对方账户那边也记了这笔互转（只记一边：清空其中一行的内容）",IF(AJ14>0,"⚠ 摘要里有两个项目：拆成几行，或在「改项目」选",IF(AND(I14<>"账户互转",O14<>""),"⚠ 填了对方账户但类别不是账户互转（对方账户不起作用）",IF(AND(J14<>"",Z14=""),"⚠ 单位/人没在【往来单位】登记",IF(AND(N(F14)<0,AH14="收"),"⚠ 这是收款，以后请记在收入栏",IF(N(E14)<0,"⚠ 收入填了负数，已按支出算",IF(N(F14)<0,"↩ 冲回（退款）",IF(AND(R14<0,I14<>"固定资产购置",I14<>"付应付款",ISNUMBER(B14),IFERROR(SUMPRODUCT(ISNUMBER(SEARCH(基础资料!$AJ$5:$AJ$34,D14))*(基础资料!$AJ$5:$AJ$34<>"")*((AN14-基础资料!$AK$5:$AK$34)<=30)*((AN14-基础资料!$AK$5:$AK$34)>=-30)),0)>0),"⚠ 像是在买【基础资料】⑥ 登记的车/设备：类别改成「固定资产购置」，不然成本算两遍",IF(AND(OR(I14="材料费",I14="分包费",I14="机械运输费",I14="其他直接费"),J14="",H14<>"",COUNTIFS(应付登记!$E$5:$E$1004,H14,应付登记!$G$5:$G$1004,-R14)>0),"⚠ 这个项目有同样金额的应付登记：是付那家的，改类别选「付应付款」、改单位选那家（不然成本算两遍）","√")))))))))))))))))))))))))))) -> √ | R14: =ROUND(N(E14)-N(F14),2) -> -20000 | S14: =IF(ISNUMBER(B14),YEAR(B14)*100+MONTH(B14),"") -> 202605 | T14: =IF(N(AK14)=0,"",INDEX(_辅助!$S$1:$S$240,AK14)) | U14: =IF(OR(D14="",R14=0),"",IF(AND(Z14="临时工",R14<0),"临时工工资",IF(AG14="",IF(AA14=1,"工资",IF(Z14="临时工","临时工工资",IF(Z14="甲方/总包","工程款",IF(AND(OR(Z14="材料供应商",Z14="分包",Z14="机械运输"),Y14=1),"付应付款","")))),IF(AND(Y14=1,OR(Z14="材料供应商",Z14="分包",Z14="机械运输",Z14="其他"),OR(AG14="材料费",AG14="分包费",AG14="机械运输费",AG14="其他直接费",AG14="工资",AG14="临时工工资")),"付应付款",AG14)))) -> 业务招待费 | V14: =IF(D14="","",IF(N(AM14)>0,IF(N(AM14)=0,"",INDEX(_辅助!$W$1:$W$900,AM14)),IF(N(AL14)=0,"",INDEX(_辅助!$W$1:$W$900,AL14)))) | W14: =IF(I14="","",IFERROR(INDEX(基础资料!$V$5:$V$64,MATCH(I14,基础资料!$S$5:$S$64,0))&"","？")) -> 公司间接费 | X14: =IF(R14=0,"",IF(OR(I14="",IFERROR(INDEX(基础资料!$U$5:$U$64,MATCH(I14,基础资料!$S$5:$S$64,0))&"","")=""),"待分类",IF(OR(I14="付应付款",IFERROR(INDEX(基础资料!$U$5:$U$64,MATCH(I14,基础资料!$S$5:$S$64,0))&"","")="应付款"),IF(Z14="材料供应商","应付材料款",IF(Z14="分包","应付分包款",IF(Z14="机械运输","应付机械运输费","应付其他款"))),IFERROR(INDEX(基础资料!$U$5:$U$64,MATCH(I14,基础资料!$S$5:$S$64,0))&"","")))) -> 业务招待费 | Y14: =IF(J14="",0,IF(COUNTIF(应付登记!$D$5:$D$1004,J14)+COUNTIF(期初余额!$P$5:$P$204,J14)>0,1,0)) -> 0 | Z14: =IF(J14="","",IFERROR(INDEX(往来单位!$C$4:$C$303,MATCH(J14,往来单位!$B$4:$B$303,0))&"","")) | AA14: =IF(OR(Z14="管理人员",Z14="工人"),1,0) -> 0 | AB14: =IF(ISERROR(FIND("代",D14)),"",IFERROR(MID(D14,FIND("代",D14)+1,FIND("付",D14,FIND("代",D14))-FIND("代",D14)-1),"")) | AC14: =IF(I14<>"账户互转","",IF(J14<>"",IFERROR(INDEX(_辅助!$G$1:$G$40,MATCH(J14,_辅助!$F$1:$F$40,0)),IF(IFERROR(MATCH(1,INDEX(ISNUMBER(SEARCH(_辅助!$Z$1:$Z$40,D14))*(_辅助!$Z$1:$Z$40<>""),0),0),0)=0,"",INDEX(_辅助!$AA$1:$AA$40,IFERROR(MATCH(1,INDEX(ISNUMBER(SEARCH(_辅助!$Z$1:$Z$40,D14))*(_辅助!$Z$1:$Z$40<>""),0),0),0)))),IF(IFERROR(MATCH(1,INDEX(ISNUMBER(SEARCH(_辅助!$Z$1:$Z$40,D14))*(_辅助!$Z$1:$Z$40<>""),0),0),0)=0,"",INDEX(_辅助!$AA$1:$AA$40,IFERROR(MATCH(1,INDEX(ISNUMBER(SEARCH(_辅助!$Z$1:$Z$40,D14))*(_辅助!$Z$1:$Z$40<>""),0),0),0))))) | AD14: =IF(O14<>"",O14,AC14) | AE14: =IF(C14="","",IFERROR(INDEX(基础资料!$H$5:$H$24,MATCH(C14,基础资料!$G$5:$G$24,0))&"","")) -> 银行 | AF14: =IF(AD14="","",IFERROR(INDEX(基础资料!$H$5:$H$24,MATCH(AD14,基础资料!$G$5:$G$24,0))&"","")) | AG14: =IF(OR(D14="",R14=0),"",IFERROR(INDEX(基础资料!$AC$5:$AC$164,IF(IF(F14<>"","支","收")="收",MATCH(1,INDEX(ISNUMBER(SEARCH(_辅助!$AB$1:$AB$160,D14))*(_辅助!$AB$1:$AB$160<>""),0),0),MATCH(1,INDEX(ISNUMBER(SEARCH(_辅助!$AC$1:$AC$160,D14))*(_辅助!$AC$1:$AC$160<>""),0),0)))&"","")) -> 业务招待费 | AH14: =IF(R14=0,"",IF(OR(IFERROR(INDEX(基础资料!$T$5:$T$64,MATCH(I14,基础资料!$S$5:$S$64,0))&"","")="收",IFERROR(INDEX(基础资料!$T$5:$T$64,MATCH(I14,基础资料!$S$5:$S$64,0))&"","")="支"),IFERROR(INDEX(基础资料!$T$5:$T$64,MATCH(I14,基础资料!$S$5:$S$64,0))&"",""),IF(R14>0,"收","支"))) -> 支 | AI14: =IF(N(AK14)=0,"",INDEX(_辅助!$R$1:$R$240,AK14)) | AJ14: =IF(OR(AI14="",L14<>""),0,SUMPRODUCT(ISNUMBER(SEARCH(_辅助!$R$1:$R$240,D14))*(_辅助!$R$1:$R$240<>"")*(1-ISNUMBER(SEARCH(_辅助!$R$1:$R$240,AI14)))*(_辅助!$S$1:$S$240<>T14))) -> 0 | AK14: =IF(D14="",0,IFERROR(MATCH(1,INDEX(ISNUMBER(SEARCH(_辅助!$R$1:$R$240,D14))*(_辅助!$R$1:$R$240<>""),0),0),0)) -> 0 | AL14: =IF(D14="",0,IFERROR(MATCH(1,INDEX(ISNUMBER(SEARCH(_辅助!$V$1:$V$900,D14))*(_辅助!$V$1:$V$900<>""),0),0),0)) -> 0 | AM14: =IF(AB14="",0,IFERROR(MATCH(1,INDEX(ISNUMBER(SEARCH(_辅助!$V$1:$V$900,AB14))*(_辅助!$V$1:$V$900<>""),0),0),0)) -> 0 | AN14: =IF(ISNUMBER(B14),INT(B14),0) -> 46150 | AO14: =IF(AND(X14="应收账款",R14>0,AN14>0,H14<>""),H14&"|"&COUNTIFS(资金流水!$H$6:$H$2005,H14,资金流水!$X$6:$X$2005,"应收账款",资金流水!$R$6:$R$2005,">0",资金流水!$AN$6:$AN$2005,">0",资金流水!$AN$6:$AN$2005,"<="&AN14),"") | AP14: =IF(AND(J14<>"",R14<0,AN14>0),J14&"|"&COUNTIFS(资金流水!$J$6:$J$2005,J14,资金流水!$R$6:$R$2005,"<0",资金流水!$AN$6:$AN$2005,">0",资金流水!$AN$6:$AN$2005,"<="&AN14),"") | AQ14: =IF(AND(X14="其他应收款",AN14>0,J14<>""),J14&"|"&(COUNTIFS(资金流水!$J$6:$J$2005,J14,资金流水!$X$6:$X$2005,"其他应收款",资金流水!$AN$6:$AN$2005,">0",资金流水!$AN$6:$AN$2005,"<"&AN14)+COUNTIFS($J$6:J14,J14,$X$6:X14,"其他应收款",$AN$6:AN14,AN14)),"")
A15: =IF(AND(B15="",D15="",E15="",F15=""),"",ROW()-5) -> 10 | B15: 46155 | C15: 九江银行 | D15: 收到股东借款-聂辉 | E15: 10000 | G15: =IF(C15="","",ROUND(IFERROR(INDEX(基础资料!$K$5:$K$24,MATCH(C15,基础资料!$G$5:$G$24,0)),0)+SUMIFS($R$6:R15,$C$6:C15,C15)-SUMIFS($R$6:R15,$AD$6:AD15,C15,$X$6:X15,"账户互转"),2)) -> -30940 | H15: =IF(L15<>"",L15,T15) | I15: =IF(M15<>"",M15,U15) -> 账户互转 | J15: =IF(N15<>"",N15,V15) -> 聂辉 | K15: =IF(AND(B15="",D15="",E15="",F15=""),"",IF(C15="","✗ 没选账户",IF(AE15="","✗ 账户不在【基础资料】② 里",IF(NOT(ISNUMBER(B15)),"✗ 日期要填成日期（2026/5/1）",IF(AND(ISNUMBER(B15),B15<基础资料!$C$9),"✗ 日期早于建账日期（建账前的放【期初余额】）",IF(AND(N(E15)<>0,N(F15)<>0),"✗ 收入、支出只填一边",IF(R15=0,"✗ 没有金额",IF(I15="","✗ 认不出收支类别：在「改类别」选",IF(W15="？","✗ 收支类别不在【基础资料】③ 里",IF(OR(I15="管理人员工资",I15="折旧费"),"✗ 这一类是自动算的，流水里不能选（发工资选「工资」，买设备选「固定资产购置」）",IF(AND(OR(X15="材料费",X15="人工费",X15="分包费",X15="机械运输费",X15="其他直接费",X15="票据贴息",X15="应收账款"),H15=""),"✗ 这一笔要选项目（摘要里的项目没在【项目档案】的话先去加上）",IF(AND(H15<>"",COUNTIF(项目档案!$B$4:$B$63,H15)=0),"✗ 项目不在【项目档案】里",IF(AND(OR(IFERROR(INDEX(基础资料!$W$5:$W$64,MATCH(I15,基础资料!$S$5:$S$64,0))&"","")="人",IFERROR(INDEX(基础资料!$W$5:$W$64,MATCH(I15,基础资料!$S$5:$S$64,0))&"","")="单位"),J15=""),"✗ 这一笔要选是谁（改单位/人）",IF(AND(I15="付应付款",NOT(OR(Z15="材料供应商",Z15="分包",Z15="机械运输",Z15="其他"))),"✗ 付应付款要选材料商、分包或机械单位",IF(AND(I15="付应付款",Y15=0),"✗ 这家没有应付：先在【应付登记】登记（现买现付的选材料费等）",IF(AND(OR(I15="工资",I15="工资退回"),AA15=0),"✗ 工资要选管理人员或工人（临时工选「临时工工资」）",IF(AND(I15="账户互转",AD15=""),"✗ 账户互转要在「对方账户」选（借款、报销选那个人的个人户）",IF(AND(I15="账户互转",AF15=""),"✗ 对方账户不在【基础资料】② 里",IF(AND(I15="账户互转",AD15=C15),"✗ 对方账户不能是自己",IF(IF(I15="账户互转",COUNTIFS(资金流水!$C$6:$C$2005,AD15,资金流水!$AD$6:$AD$2005,C15,资金流水!$I$6:$I$2005,"账户互转",资金流水!$R$6:$R$2005,-R15)>0,FALSE),"✗ 对方账户那边也记了这笔互转（只记一边：清空其中一行的内容）",IF(AJ15>0,"⚠ 摘要里有两个项目：拆成几行，或在「改项目」选",IF(AND(I15<>"账户互转",O15<>""),"⚠ 填了对方账户但类别不是账户互转（对方账户不起作用）",IF(AND(J15<>"",Z15=""),"⚠ 单位/人没在【往来单位】登记",IF(AND(N(F15)<0,AH15="收"),"⚠ 这是收款，以后请记在收入栏",IF(N(E15)<0,"⚠ 收入填了负数，已按支出算",IF(N(F15)<0,"↩ 冲回（退款）",IF(AND(R15<0,I15<>"固定资产购置",I15<>"付应付款",ISNUMBER(B15),IFERROR(SUMPRODUCT(ISNUMBER(SEARCH(基础资料!$AJ$5:$AJ$34,D15))*(基础资料!$AJ$5:$AJ$34<>"")*((AN15-基础资料!$AK$5:$AK$34)<=30)*((AN15-基础资料!$AK$5:$AK$34)>=-30)),0)>0),"⚠ 像是在买【基础资料】⑥ 登记的车/设备：类别改成「固定资产购置」，不然成本算两遍",IF(AND(OR(I15="材料费",I15="分包费",I15="机械运输费",I15="其他直接费"),J15="",H15<>"",COUNTIFS(应付登记!$E$5:$E$1004,H15,应付登记!$G$5:$G$1004,-R15)>0),"⚠ 这个项目有同样金额的应付登记：是付那家的，改类别选「付应付款」、改单位选那家（不然成本算两遍）","√")))))))))))))))))))))))))))) -> √ | R15: =ROUND(N(E15)-N(F15),2) -> 10000 | S15: =IF(ISNUMBER(B15),YEAR(B15)*100+MONTH(B15),"") -> 202605 | T15: =IF(N(AK15)=0,"",INDEX(_辅助!$S$1:$S$240,AK15)) | U15: =IF(OR(D15="",R15=0),"",IF(AND(Z15="临时工",R15<0),"临时工工资",IF(AG15="",IF(AA15=1,"工资",IF(Z15="临时工","临时工工资",IF(Z15="甲方/总包","工程款",IF(AND(OR(Z15="材料供应商",Z15="分包",Z15="机械运输"),Y15=1),"付应付款","")))),IF(AND(Y15=1,OR(Z15="材料供应商",Z15="分包",Z15="机械运输",Z15="其他"),OR(AG15="材料费",AG15="分包费",AG15="机械运输费",AG15="其他直接费",AG15="工资",AG15="临时工工资")),"付应付款",AG15)))) -> 账户互转 | V15: =IF(D15="","",IF(N(AM15)>0,IF(N(AM15)=0,"",INDEX(_辅助!$W$1:$W$900,AM15)),IF(N(AL15)=0,"",INDEX(_辅助!$W$1:$W$900,AL15)))) -> 聂辉 | W15: =IF(I15="","",IFERROR(INDEX(基础资料!$V$5:$V$64,MATCH(I15,基础资料!$S$5:$S$64,0))&"","？")) -> 不进利润 | X15: =IF(R15=0,"",IF(OR(I15="",IFERROR(INDEX(基础资料!$U$5:$U$64,MATCH(I15,基础资料!$S$5:$S$64,0))&"","")=""),"待分类",IF(OR(I15="付应付款",IFERROR(INDEX(基础资料!$U$5:$U$64,MATCH(I15,基础资料!$S$5:$S$64,0))&"","")="应付款"),IF(Z15="材料供应商","应付材料款",IF(Z15="分包","应付分包款",IF(Z15="机械运输","应付机械运输费","应付其他款"))),IFERROR(INDEX(基础资料!$U$5:$U$64,MATCH(I15,基础资料!$S$5:$S$64,0))&"","")))) -> 账户互转 | Y15: =IF(J15="",0,IF(COUNTIF(应付登记!$D$5:$D$1004,J15)+COUNTIF(期初余额!$P$5:$P$204,J15)>0,1,0)) -> 0 | Z15: =IF(J15="","",IFERROR(INDEX(往来单位!$C$4:$C$303,MATCH(J15,往来单位!$B$4:$B$303,0))&"","")) -> 管理人员 | AA15: =IF(OR(Z15="管理人员",Z15="工人"),1,0) -> 1 | AB15: =IF(ISERROR(FIND("代",D15)),"",IFERROR(MID(D15,FIND("代",D15)+1,FIND("付",D15,FIND("代",D15))-FIND("代",D15)-1),"")) | AC15: =IF(I15<>"账户互转","",IF(J15<>"",IFERROR(INDEX(_辅助!$G$1:$G$40,MATCH(J15,_辅助!$F$1:$F$40,0)),IF(IFERROR(MATCH(1,INDEX(ISNUMBER(SEARCH(_辅助!$Z$1:$Z$40,D15))*(_辅助!$Z$1:$Z$40<>""),0),0),0)=0,"",INDEX(_辅助!$AA$1:$AA$40,IFERROR(MATCH(1,INDEX(ISNUMBER(SEARCH(_辅助!$Z$1:$Z$40,D15))*(_辅助!$Z$1:$Z$40<>""),0),0),0)))),IF(IFERROR(MATCH(1,INDEX(ISNUMBER(SEARCH(_辅助!$Z$1:$Z$40,D15))*(_辅助!$Z$1:$Z$40<>""),0),0),0)=0,"",INDEX(_辅助!$AA$1:$AA$40,IFERROR(MATCH(1,INDEX(ISNUMBER(SEARCH(_辅助!$Z$1:$Z$40,D15))*(_辅助!$Z$1:$Z$40<>""),0),0),0))))) -> 聂辉个人户 | AD15: =IF(O15<>"",O15,AC15) -> 聂辉个人户 | AE15: =IF(C15="","",IFERROR(INDEX(基础资料!$H$5:$H$24,MATCH(C15,基础资料!$G$5:$G$24,0))&"","")) -> 银行 | AF15: =IF(AD15="","",IFERROR(INDEX(基础资料!$H$5:$H$24,MATCH(AD15,基础资料!$G$5:$G$24,0))&"","")) -> 个人户 | AG15: =IF(OR(D15="",R15=0),"",IFERROR(INDEX(基础资料!$AC$5:$AC$164,IF(IF(F15<>"","支","收")="收",MATCH(1,INDEX(ISNUMBER(SEARCH(_辅助!$AB$1:$AB$160,D15))*(_辅助!$AB$1:$AB$160<>""),0),0),MATCH(1,INDEX(ISNUMBER(SEARCH(_辅助!$AC$1:$AC$160,D15))*(_辅助!$AC$1:$AC$160<>""),0),0)))&"","")) -> 账户互转 | AH15: =IF(R15=0,"",IF(OR(IFERROR(INDEX(基础资料!$T$5:$T$64,MATCH(I15,基础资料!$S$5:$S$64,0))&"","")="收",IFERROR(INDEX(基础资料!$T$5:$T$64,MATCH(I15,基础资料!$S$5:$S$64,0))&"","")="支"),IFERROR(INDEX(基础资料!$T$5:$T$64,MATCH(I15,基础资料!$S$5:$S$64,0))&"",""),IF(R15>0,"收","支"))) -> 收 | AI15: =IF(N(AK15)=0,"",INDEX(_辅助!$R$1:$R$240,AK15)) | AJ15: =IF(OR(AI15="",L15<>""),0,SUMPRODUCT(ISNUMBER(SEARCH(_辅助!$R$1:$R$240,D15))*(_辅助!$R$1:$R$240<>"")*(1-ISNUMBER(SEARCH(_辅助!$R$1:$R$240,AI15)))*(_辅助!$S$1:$S$240<>T15))) -> 0 | AK15: =IF(D15="",0,IFERROR(MATCH(1,INDEX(ISNUMBER(SEARCH(_辅助!$R$1:$R$240,D15))*(_辅助!$R$1:$R$240<>""),0),0),0)) -> 0 | AL15: =IF(D15="",0,IFERROR(MATCH(1,INDEX(ISNUMBER(SEARCH(_辅助!$V$1:$V$900,D15))*(_辅助!$V$1:$V$900<>""),0),0),0)) -> 111 | AM15: =IF(AB15="",0,IFERROR(MATCH(1,INDEX(ISNUMBER(SEARCH(_辅助!$V$1:$V$900,AB15))*(_辅助!$V$1:$V$900<>""),0),0),0)) -> 0 | AN15: =IF(ISNUMBER(B15),INT(B15),0) -> 46155 | AO15: =IF(AND(X15="应收账款",R15>0,AN15>0,H15<>""),H15&"|"&COUNTIFS(资金流水!$H$6:$H$2005,H15,资金流水!$X$6:$X$2005,"应收账款",资金流水!$R$6:$R$2005,">0",资金流水!$AN$6:$AN$2005,">0",资金流水!$AN$6:$AN$2005,"<="&AN15),"") | AP15: =IF(AND(J15<>"",R15<0,AN15>0),J15&"|"&COUNTIFS(资金流水!$J$6:$J$2005,J15,资金流水!$R$6:$R$2005,"<0",资金流水!$AN$6:$AN$2005,">0",资金流水!$AN$6:$AN$2005,"<="&AN15),"") | AQ15: =IF(AND(X15="其他应收款",AN15>0,J15<>""),J15&"|"&(COUNTIFS(资金流水!$J$6:$J$2005,J15,资金流水!$X$6:$X$2005,"其他应收款",资金流水!$AN$6:$AN$2005,">0",资金流水!$AN$6:$AN$2005,"<"&AN15)+COUNTIFS($J$6:J15,J15,$X$6:X15,"其他应收款",$AN$6:AN15,AN15)),"")
A16: =IF(AND(B16="",D16="",E16="",F16=""),"",ROW()-5) -> 11 | B16: 46155 | C16: 九江银行 | D16: 支付异地预缴税 | F16: 6467.49 | G16: =IF(C16="","",ROUND(IFERROR(INDEX(基础资料!$K$5:$K$24,MATCH(C16,基础资料!$G$5:$G$24,0)),0)+SUMIFS($R$6:R16,$C$6:C16,C16)-SUMIFS($R$6:R16,$AD$6:AD16,C16,$X$6:X16,"账户互转"),2)) -> -37407.49 | H16: =IF(L16<>"",L16,T16) | I16: =IF(M16<>"",M16,U16) -> 缴增值税及附加 | J16: =IF(N16<>"",N16,V16) | K16: =IF(AND(B16="",D16="",E16="",F16=""),"",IF(C16="","✗ 没选账户",IF(AE16="","✗ 账户不在【基础资料】② 里",IF(NOT(ISNUMBER(B16)),"✗ 日期要填成日期（2026/5/1）",IF(AND(ISNUMBER(B16),B16<基础资料!$C$9),"✗ 日期早于建账日期（建账前的放【期初余额】）",IF(AND(N(E16)<>0,N(F16)<>0),"✗ 收入、支出只填一边",IF(R16=0,"✗ 没有金额",IF(I16="","✗ 认不出收支类别：在「改类别」选",IF(W16="？","✗ 收支类别不在【基础资料】③ 里",IF(OR(I16="管理人员工资",I16="折旧费"),"✗ 这一类是自动算的，流水里不能选（发工资选「工资」，买设备选「固定资产购置」）",IF(AND(OR(X16="材料费",X16="人工费",X16="分包费",X16="机械运输费",X16="其他直接费",X16="票据贴息",X16="应收账款"),H16=""),"✗ 这一笔要选项目（摘要里的项目没在【项目档案】的话先去加上）",IF(AND(H16<>"",COUNTIF(项目档案!$B$4:$B$63,H16)=0),"✗ 项目不在【项目档案】里",IF(AND(OR(IFERROR(INDEX(基础资料!$W$5:$W$64,MATCH(I16,基础资料!$S$5:$S$64,0))&"","")="人",IFERROR(INDEX(基础资料!$W$5:$W$64,MATCH(I16,基础资料!$S$5:$S$64,0))&"","")="单位"),J16=""),"✗ 这一笔要选是谁（改单位/人）",IF(AND(I16="付应付款",NOT(OR(Z16="材料供应商",Z16="分包",Z16="机械运输",Z16="其他"))),"✗ 付应付款要选材料商、分包或机械单位",IF(AND(I16="付应付款",Y16=0),"✗ 这家没有应付：先在【应付登记】登记（现买现付的选材料费等）",IF(AND(OR(I16="工资",I16="工资退回"),AA16=0),"✗ 工资要选管理人员或工人（临时工选「临时工工资」）",IF(AND(I16="账户互转",AD16=""),"✗ 账户互转要在「对方账户」选（借款、报销选那个人的个人户）",IF(AND(I16="账户互转",AF16=""),"✗ 对方账户不在【基础资料】② 里",IF(AND(I16="账户互转",AD16=C16),"✗ 对方账户不能是自己",IF(IF(I16="账户互转",COUNTIFS(资金流水!$C$6:$C$2005,AD16,资金流水!$AD$6:$AD$2005,C16,资金流水!$I$6:$I$2005,"账户互转",资金流水!$R$6:$R$2005,-R16)>0,FALSE),"✗ 对方账户那边也记了这笔互转（只记一边：清空其中一行的内容）",IF(AJ16>0,"⚠ 摘要里有两个项目：拆成几行，或在「改项目」选",IF(AND(I16<>"账户互转",O16<>""),"⚠ 填了对方账户但类别不是账户互转（对方账户不起作用）",IF(AND(J16<>"",Z16=""),"⚠ 单位/人没在【往来单位】登记",IF(AND(N(F16)<0,AH16="收"),"⚠ 这是收款，以后请记在收入栏",IF(N(E16)<0,"⚠ 收入填了负数，已按支出算",IF(N(F16)<0,"↩ 冲回（退款）",IF(AND(R16<0,I16<>"固定资产购置",I16<>"付应付款",ISNUMBER(B16),IFERROR(SUMPRODUCT(ISNUMBER(SEARCH(基础资料!$AJ$5:$AJ$34,D16))*(基础资料!$AJ$5:$AJ$34<>"")*((AN16-基础资料!$AK$5:$AK$34)<=30)*((AN16-基础资料!$AK$5:$AK$34)>=-30)),0)>0),"⚠ 像是在买【基础资料】⑥ 登记的车/设备：类别改成「固定资产购置」，不然成本算两遍",IF(AND(OR(I16="材料费",I16="分包费",I16="机械运输费",I16="其他直接费"),J16="",H16<>"",COUNTIFS(应付登记!$E$5:$E$1004,H16,应付登记!$G$5:$G$1004,-R16)>0),"⚠ 这个项目有同样金额的应付登记：是付那家的，改类别选「付应付款」、改单位选那家（不然成本算两遍）","√")))))))))))))))))))))))))))) -> √ | R16: =ROUND(N(E16)-N(F16),2) -> -6467.49 | S16: =IF(ISNUMBER(B16),YEAR(B16)*100+MONTH(B16),"") -> 202605 | T16: =IF(N(AK16)=0,"",INDEX(_辅助!$S$1:$S$240,AK16)) | U16: =IF(OR(D16="",R16=0),"",IF(AND(Z16="临时工",R16<0),"临时工工资",IF(AG16="",IF(AA16=1,"工资",IF(Z16="临时工","临时工工资",IF(Z16="甲方/总包","工程款",IF(AND(OR(Z16="材料供应商",Z16="分包",Z16="机械运输"),Y16=1),"付应付款","")))),IF(AND(Y16=1,OR(Z16="材料供应商",Z16="分包",Z16="机械运输",Z16="其他"),OR(AG16="材料费",AG16="分包费",AG16="机械运输费",AG16="其他直接费",AG16="工资",AG16="临时工工资")),"付应付款",AG16)))) -> 缴增值税及附加 | V16: =IF(D16="","",IF(N(AM16)>0,IF(N(AM16)=0,"",INDEX(_辅助!$W$1:$W$900,AM16)),IF(N(AL16)=0,"",INDEX(_辅助!$W$1:$W$900,AL16)))) | W16: =IF(I16="","",IFERROR(INDEX(基础资料!$V$5:$V$64,MATCH(I16,基础资料!$S$5:$S$64,0))&"","？")) -> 不进利润 | X16: =IF(R16=0,"",IF(OR(I16="",IFERROR(INDEX(基础资料!$U$5:$U$64,MATCH(I16,基础资料!$S$5:$S$64,0))&"","")=""),"待分类",IF(OR(I16="付应付款",IFERROR(INDEX(基础资料!$U$5:$U$64,MATCH(I16,基础资料!$S$5:$S$64,0))&"","")="应付款"),IF(Z16="材料供应商","应付材料款",IF(Z16="分包","应付分包款",IF(Z16="机械运输","应付机械运输费","应付其他款"))),IFERROR(INDEX(基础资料!$U$5:$U$64,MATCH(I16,基础资料!$S$5:$S$64,0))&"","")))) -> 应交税费 | Y16: =IF(J16="",0,IF(COUNTIF(应付登记!$D$5:$D$1004,J16)+COUNTIF(期初余额!$P$5:$P$204,J16)>0,1,0)) -> 0 | Z16: =IF(J16="","",IFERROR(INDEX(往来单位!$C$4:$C$303,MATCH(J16,往来单位!$B$4:$B$303,0))&"","")) | AA16: =IF(OR(Z16="管理人员",Z16="工人"),1,0) -> 0 | AB16: =IF(ISERROR(FIND("代",D16)),"",IFERROR(MID(D16,FIND("代",D16)+1,FIND("付",D16,FIND("代",D16))-FIND("代",D16)-1),"")) | AC16: =IF(I16<>"账户互转","",IF(J16<>"",IFERROR(INDEX(_辅助!$G$1:$G$40,MATCH(J16,_辅助!$F$1:$F$40,0)),IF(IFERROR(MATCH(1,INDEX(ISNUMBER(SEARCH(_辅助!$Z$1:$Z$40,D16))*(_辅助!$Z$1:$Z$40<>""),0),0),0)=0,"",INDEX(_辅助!$AA$1:$AA$40,IFERROR(MATCH(1,INDEX(ISNUMBER(SEARCH(_辅助!$Z$1:$Z$40,D16))*(_辅助!$Z$1:$Z$40<>""),0),0),0)))),IF(IFERROR(MATCH(1,INDEX(ISNUMBER(SEARCH(_辅助!$Z$1:$Z$40,D16))*(_辅助!$Z$1:$Z$40<>""),0),0),0)=0,"",INDEX(_辅助!$AA$1:$AA$40,IFERROR(MATCH(1,INDEX(ISNUMBER(SEARCH(_辅助!$Z$1:$Z$40,D16))*(_辅助!$Z$1:$Z$40<>""),0),0),0))))) | AD16: =IF(O16<>"",O16,AC16) | AE16: =IF(C16="","",IFERROR(INDEX(基础资料!$H$5:$H$24,MATCH(C16,基础资料!$G$5:$G$24,0))&"","")) -> 银行 | AF16: =IF(AD16="","",IFERROR(INDEX(基础资料!$H$5:$H$24,MATCH(AD16,基础资料!$G$5:$G$24,0))&"","")) | AG16: =IF(OR(D16="",R16=0),"",IFERROR(INDEX(基础资料!$AC$5:$AC$164,IF(IF(F16<>"","支","收")="收",MATCH(1,INDEX(ISNUMBER(SEARCH(_辅助!$AB$1:$AB$160,D16))*(_辅助!$AB$1:$AB$160<>""),0),0),MATCH(1,INDEX(ISNUMBER(SEARCH(_辅助!$AC$1:$AC$160,D16))*(_辅助!$AC$1:$AC$160<>""),0),0)))&"","")) -> 缴增值税及附加 | AH16: =IF(R16=0,"",IF(OR(IFERROR(INDEX(基础资料!$T$5:$T$64,MATCH(I16,基础资料!$S$5:$S$64,0))&"","")="收",IFERROR(INDEX(基础资料!$T$5:$T$64,MATCH(I16,基础资料!$S$5:$S$64,0))&"","")="支"),IFERROR(INDEX(基础资料!$T$5:$T$64,MATCH(I16,基础资料!$S$5:$S$64,0))&"",""),IF(R16>0,"收","支"))) -> 支 | AI16: =IF(N(AK16)=0,"",INDEX(_辅助!$R$1:$R$240,AK16)) | AJ16: =IF(OR(AI16="",L16<>""),0,SUMPRODUCT(ISNUMBER(SEARCH(_辅助!$R$1:$R$240,D16))*(_辅助!$R$1:$R$240<>"")*(1-ISNUMBER(SEARCH(_辅助!$R$1:$R$240,AI16)))*(_辅助!$S$1:$S$240<>T16))) -> 0 | AK16: =IF(D16="",0,IFERROR(MATCH(1,INDEX(ISNUMBER(SEARCH(_辅助!$R$1:$R$240,D16))*(_辅助!$R$1:$R$240<>""),0),0),0)) -> 0 | AL16: =IF(D16="",0,IFERROR(MATCH(1,INDEX(ISNUMBER(SEARCH(_辅助!$V$1:$V$900,D16))*(_辅助!$V$1:$V$900<>""),0),0),0)) -> 0 | AM16: =IF(AB16="",0,IFERROR(MATCH(1,INDEX(ISNUMBER(SEARCH(_辅助!$V$1:$V$900,AB16))*(_辅助!$V$1:$V$900<>""),0),0),0)) -> 0 | AN16: =IF(ISNUMBER(B16),INT(B16),0) -> 46155 | AO16: =IF(AND(X16="应收账款",R16>0,AN16>0,H16<>""),H16&"|"&COUNTIFS(资金流水!$H$6:$H$2005,H16,资金流水!$X$6:$X$2005,"应收账款",资金流水!$R$6:$R$2005,">0",资金流水!$AN$6:$AN$2005,">0",资金流水!$AN$6:$AN$2005,"<="&AN16),"") | AP16: =IF(AND(J16<>"",R16<0,AN16>0),J16&"|"&COUNTIFS(资金流水!$J$6:$J$2005,J16,资金流水!$R$6:$R$2005,"<0",资金流水!$AN$6:$AN$2005,">0",资金流水!$AN$6:$AN$2005,"<="&AN16),"") | AQ16: =IF(AND(X16="其他应收款",AN16>0,J16<>""),J16&"|"&(COUNTIFS(资金流水!$J$6:$J$2005,J16,资金流水!$X$6:$X$2005,"其他应收款",资金流水!$AN$6:$AN$2005,">0",资金流水!$AN$6:$AN$2005,"<"&AN16)+COUNTIFS($J$6:J16,J16,$X$6:X16,"其他应收款",$AN$6:AN16,AN16)),"")
A17: =IF(AND(B17="",D17="",E17="",F17=""),"",ROW()-5) -> 12 | B17: 46155 | C17: 九江银行 | D17: 支付异地预缴税 | F17: 410.63 | G17: =IF(C17="","",ROUND(IFERROR(INDEX(基础资料!$K$5:$K$24,MATCH(C17,基础资料!$G$5:$G$24,0)),0)+SUMIFS($R$6:R17,$C$6:C17,C17)-SUMIFS($R$6:R17,$AD$6:AD17,C17,$X$6:X17,"账户互转"),2)) -> -37818.12 | H17: =IF(L17<>"",L17,T17) | I17: =IF(M17<>"",M17,U17) -> 缴增值税及附加 | J17: =IF(N17<>"",N17,V17) | K17: =IF(AND(B17="",D17="",E17="",F17=""),"",IF(C17="","✗ 没选账户",IF(AE17="","✗ 账户不在【基础资料】② 里",IF(NOT(ISNUMBER(B17)),"✗ 日期要填成日期（2026/5/1）",IF(AND(ISNUMBER(B17),B17<基础资料!$C$9),"✗ 日期早于建账日期（建账前的放【期初余额】）",IF(AND(N(E17)<>0,N(F17)<>0),"✗ 收入、支出只填一边",IF(R17=0,"✗ 没有金额",IF(I17="","✗ 认不出收支类别：在「改类别」选",IF(W17="？","✗ 收支类别不在【基础资料】③ 里",IF(OR(I17="管理人员工资",I17="折旧费"),"✗ 这一类是自动算的，流水里不能选（发工资选「工资」，买设备选「固定资产购置」）",IF(AND(OR(X17="材料费",X17="人工费",X17="分包费",X17="机械运输费",X17="其他直接费",X17="票据贴息",X17="应收账款"),H17=""),"✗ 这一笔要选项目（摘要里的项目没在【项目档案】的话先去加上）",IF(AND(H17<>"",COUNTIF(项目档案!$B$4:$B$63,H17)=0),"✗ 项目不在【项目档案】里",IF(AND(OR(IFERROR(INDEX(基础资料!$W$5:$W$64,MATCH(I17,基础资料!$S$5:$S$64,0))&"","")="人",IFERROR(INDEX(基础资料!$W$5:$W$64,MATCH(I17,基础资料!$S$5:$S$64,0))&"","")="单位"),J17=""),"✗ 这一笔要选是谁（改单位/人）",IF(AND(I17="付应付款",NOT(OR(Z17="材料供应商",Z17="分包",Z17="机械运输",Z17="其他"))),"✗ 付应付款要选材料商、分包或机械单位",IF(AND(I17="付应付款",Y17=0),"✗ 这家没有应付：先在【应付登记】登记（现买现付的选材料费等）",IF(AND(OR(I17="工资",I17="工资退回"),AA17=0),"✗ 工资要选管理人员或工人（临时工选「临时工工资」）",IF(AND(I17="账户互转",AD17=""),"✗ 账户互转要在「对方账户」选（借款、报销选那个人的个人户）",IF(AND(I17="账户互转",AF17=""),"✗ 对方账户不在【基础资料】② 里",IF(AND(I17="账户互转",AD17=C17),"✗ 对方账户不能是自己",IF(IF(I17="账户互转",COUNTIFS(资金流水!$C$6:$C$2005,AD17,资金流水!$AD$6:$AD$2005,C17,资金流水!$I$6:$I$2005,"账户互转",资金流水!$R$6:$R$2005,-R17)>0,FALSE),"✗ 对方账户那边也记了这笔互转（只记一边：清空其中一行的内容）",IF(AJ17>0,"⚠ 摘要里有两个项目：拆成几行，或在「改项目」选",IF(AND(I17<>"账户互转",O17<>""),"⚠ 填了对方账户但类别不是账户互转（对方账户不起作用）",IF(AND(J17<>"",Z17=""),"⚠ 单位/人没在【往来单位】登记",IF(AND(N(F17)<0,AH17="收"),"⚠ 这是收款，以后请记在收入栏",IF(N(E17)<0,"⚠ 收入填了负数，已按支出算",IF(N(F17)<0,"↩ 冲回（退款）",IF(AND(R17<0,I17<>"固定资产购置",I17<>"付应付款",ISNUMBER(B17),IFERROR(SUMPRODUCT(ISNUMBER(SEARCH(基础资料!$AJ$5:$AJ$34,D17))*(基础资料!$AJ$5:$AJ$34<>"")*((AN17-基础资料!$AK$5:$AK$34)<=30)*((AN17-基础资料!$AK$5:$AK$34)>=-30)),0)>0),"⚠ 像是在买【基础资料】⑥ 登记的车/设备：类别改成「固定资产购置」，不然成本算两遍",IF(AND(OR(I17="材料费",I17="分包费",I17="机械运输费",I17="其他直接费"),J17="",H17<>"",COUNTIFS(应付登记!$E$5:$E$1004,H17,应付登记!$G$5:$G$1004,-R17)>0),"⚠ 这个项目有同样金额的应付登记：是付那家的，改类别选「付应付款」、改单位选那家（不然成本算两遍）","√")))))))))))))))))))))))))))) -> √ | R17: =ROUND(N(E17)-N(F17),2) -> -410.63 | S17: =IF(ISNUMBER(B17),YEAR(B17)*100+MONTH(B17),"") -> 202605 | T17: =IF(N(AK17)=0,"",INDEX(_辅助!$S$1:$S$240,AK17)) | U17: =IF(OR(D17="",R17=0),"",IF(AND(Z17="临时工",R17<0),"临时工工资",IF(AG17="",IF(AA17=1,"工资",IF(Z17="临时工","临时工工资",IF(Z17="甲方/总包","工程款",IF(AND(OR(Z17="材料供应商",Z17="分包",Z17="机械运输"),Y17=1),"付应付款","")))),IF(AND(Y17=1,OR(Z17="材料供应商",Z17="分包",Z17="机械运输",Z17="其他"),OR(AG17="材料费",AG17="分包费",AG17="机械运输费",AG17="其他直接费",AG17="工资",AG17="临时工工资")),"付应付款",AG17)))) -> 缴增值税及附加 | V17: =IF(D17="","",IF(N(AM17)>0,IF(N(AM17)=0,"",INDEX(_辅助!$W$1:$W$900,AM17)),IF(N(AL17)=0,"",INDEX(_辅助!$W$1:$W$900,AL17)))) | W17: =IF(I17="","",IFERROR(INDEX(基础资料!$V$5:$V$64,MATCH(I17,基础资料!$S$5:$S$64,0))&"","？")) -> 不进利润 | X17: =IF(R17=0,"",IF(OR(I17="",IFERROR(INDEX(基础资料!$U$5:$U$64,MATCH(I17,基础资料!$S$5:$S$64,0))&"","")=""),"待分类",IF(OR(I17="付应付款",IFERROR(INDEX(基础资料!$U$5:$U$64,MATCH(I17,基础资料!$S$5:$S$64,0))&"","")="应付款"),IF(Z17="材料供应商","应付材料款",IF(Z17="分包","应付分包款",IF(Z17="机械运输","应付机械运输费","应付其他款"))),IFERROR(INDEX(基础资料!$U$5:$U$64,MATCH(I17,基础资料!$S$5:$S$64,0))&"","")))) -> 应交税费 | Y17: =IF(J17="",0,IF(COUNTIF(应付登记!$D$5:$D$1004,J17)+COUNTIF(期初余额!$P$5:$P$204,J17)>0,1,0)) -> 0 | Z17: =IF(J17="","",IFERROR(INDEX(往来单位!$C$4:$C$303,MATCH(J17,往来单位!$B$4:$B$303,0))&"","")) | AA17: =IF(OR(Z17="管理人员",Z17="工人"),1,0) -> 0 | AB17: =IF(ISERROR(FIND("代",D17)),"",IFERROR(MID(D17,FIND("代",D17)+1,FIND("付",D17,FIND("代",D17))-FIND("代",D17)-1),"")) | AC17: =IF(I17<>"账户互转","",IF(J17<>"",IFERROR(INDEX(_辅助!$G$1:$G$40,MATCH(J17,_辅助!$F$1:$F$40,0)),IF(IFERROR(MATCH(1,INDEX(ISNUMBER(SEARCH(_辅助!$Z$1:$Z$40,D17))*(_辅助!$Z$1:$Z$40<>""),0),0),0)=0,"",INDEX(_辅助!$AA$1:$AA$40,IFERROR(MATCH(1,INDEX(ISNUMBER(SEARCH(_辅助!$Z$1:$Z$40,D17))*(_辅助!$Z$1:$Z$40<>""),0),0),0)))),IF(IFERROR(MATCH(1,INDEX(ISNUMBER(SEARCH(_辅助!$Z$1:$Z$40,D17))*(_辅助!$Z$1:$Z$40<>""),0),0),0)=0,"",INDEX(_辅助!$AA$1:$AA$40,IFERROR(MATCH(1,INDEX(ISNUMBER(SEARCH(_辅助!$Z$1:$Z$40,D17))*(_辅助!$Z$1:$Z$40<>""),0),0),0))))) | AD17: =IF(O17<>"",O17,AC17) | AE17: =IF(C17="","",IFERROR(INDEX(基础资料!$H$5:$H$24,MATCH(C17,基础资料!$G$5:$G$24,0))&"","")) -> 银行 | AF17: =IF(AD17="","",IFERROR(INDEX(基础资料!$H$5:$H$24,MATCH(AD17,基础资料!$G$5:$G$24,0))&"","")) | AG17: =IF(OR(D17="",R17=0),"",IFERROR(INDEX(基础资料!$AC$5:$AC$164,IF(IF(F17<>"","支","收")="收",MATCH(1,INDEX(ISNUMBER(SEARCH(_辅助!$AB$1:$AB$160,D17))*(_辅助!$AB$1:$AB$160<>""),0),0),MATCH(1,INDEX(ISNUMBER(SEARCH(_辅助!$AC$1:$AC$160,D17))*(_辅助!$AC$1:$AC$160<>""),0),0)))&"","")) -> 缴增值税及附加 | AH17: =IF(R17=0,"",IF(OR(IFERROR(INDEX(基础资料!$T$5:$T$64,MATCH(I17,基础资料!$S$5:$S$64,0))&"","")="收",IFERROR(INDEX(基础资料!$T$5:$T$64,MATCH(I17,基础资料!$S$5:$S$64,0))&"","")="支"),IFERROR(INDEX(基础资料!$T$5:$T$64,MATCH(I17,基础资料!$S$5:$S$64,0))&"",""),IF(R17>0,"收","支"))) -> 支 | AI17: =IF(N(AK17)=0,"",INDEX(_辅助!$R$1:$R$240,AK17)) | AJ17: =IF(OR(AI17="",L17<>""),0,SUMPRODUCT(ISNUMBER(SEARCH(_辅助!$R$1:$R$240,D17))*(_辅助!$R$1:$R$240<>"")*(1-ISNUMBER(SEARCH(_辅助!$R$1:$R$240,AI17)))*(_辅助!$S$1:$S$240<>T17))) -> 0 | AK17: =IF(D17="",0,IFERROR(MATCH(1,INDEX(ISNUMBER(SEARCH(_辅助!$R$1:$R$240,D17))*(_辅助!$R$1:$R$240<>""),0),0),0)) -> 0 | AL17: =IF(D17="",0,IFERROR(MATCH(1,INDEX(ISNUMBER(SEARCH(_辅助!$V$1:$V$900,D17))*(_辅助!$V$1:$V$900<>""),0),0),0)) -> 0 | AM17: =IF(AB17="",0,IFERROR(MATCH(1,INDEX(ISNUMBER(SEARCH(_辅助!$V$1:$V$900,AB17))*(_辅助!$V$1:$V$900<>""),0),0),0)) -> 0 | AN17: =IF(ISNUMBER(B17),INT(B17),0) -> 46155 | AO17: =IF(AND(X17="应收账款",R17>0,AN17>0,H17<>""),H17&"|"&COUNTIFS(资金流水!$H$6:$H$2005,H17,资金流水!$X$6:$X$2005,"应收账款",资金流水!$R$6:$R$2005,">0",资金流水!$AN$6:$AN$2005,">0",资金流水!$AN$6:$AN$2005,"<="&AN17),"") | AP17: =IF(AND(J17<>"",R17<0,AN17>0),J17&"|"&COUNTIFS(资金流水!$J$6:$J$2005,J17,资金流水!$R$6:$R$2005,"<0",资金流水!$AN$6:$AN$2005,">0",资金流水!$AN$6:$AN$2005,"<="&AN17),"") | AQ17: =IF(AND(X17="其他应收款",AN17>0,J17<>""),J17&"|"&(COUNTIFS(资金流水!$J$6:$J$2005,J17,资金流水!$X$6:$X$2005,"其他应收款",资金流水!$AN$6:$AN$2005,">0",资金流水!$AN$6:$AN$2005,"<"&AN17)+COUNTIFS($J$6:J17,J17,$X$6:X17,"其他应收款",$AN$6:AN17,AN17)),"")
A18: =IF(AND(B18="",D18="",E18="",F18=""),"",ROW()-5) -> 13 | B18: 46155 | C18: 九江银行 | D18: 代扣个税 | F18: 1245.06 | G18: =IF(C18="","",ROUND(IFERROR(INDEX(基础资料!$K$5:$K$24,MATCH(C18,基础资料!$G$5:$G$24,0)),0)+SUMIFS($R$6:R18,$C$6:C18,C18)-SUMIFS($R$6:R18,$AD$6:AD18,C18,$X$6:X18,"账户互转"),2)) -> -39063.18 | H18: =IF(L18<>"",L18,T18) | I18: =IF(M18<>"",M18,U18) -> 代缴个税 | J18: =IF(N18<>"",N18,V18) | K18: =IF(AND(B18="",D18="",E18="",F18=""),"",IF(C18="","✗ 没选账户",IF(AE18="","✗ 账户不在【基础资料】② 里",IF(NOT(ISNUMBER(B18)),"✗ 日期要填成日期（2026/5/1）",IF(AND(ISNUMBER(B18),B18<基础资料!$C$9),"✗ 日期早于建账日期（建账前的放【期初余额】）",IF(AND(N(E18)<>0,N(F18)<>0),"✗ 收入、支出只填一边",IF(R18=0,"✗ 没有金额",IF(I18="","✗ 认不出收支类别：在「改类别」选",IF(W18="？","✗ 收支类别不在【基础资料】③ 里",IF(OR(I18="管理人员工资",I18="折旧费"),"✗ 这一类是自动算的，流水里不能选（发工资选「工资」，买设备选「固定资产购置」）",IF(AND(OR(X18="材料费",X18="人工费",X18="分包费",X18="机械运输费",X18="其他直接费",X18="票据贴息",X18="应收账款"),H18=""),"✗ 这一笔要选项目（摘要里的项目没在【项目档案】的话先去加上）",IF(AND(H18<>"",COUNTIF(项目档案!$B$4:$B$63,H18)=0),"✗ 项目不在【项目档案】里",IF(AND(OR(IFERROR(INDEX(基础资料!$W$5:$W$64,MATCH(I18,基础资料!$S$5:$S$64,0))&"","")="人",IFERROR(INDEX(基础资料!$W$5:$W$64,MATCH(I18,基础资料!$S$5:$S$64,0))&"","")="单位"),J18=""),"✗ 这一笔要选是谁（改单位/人）",IF(AND(I18="付应付款",NOT(OR(Z18="材料供应商",Z18="分包",Z18="机械运输",Z18="其他"))),"✗ 付应付款要选材料商、分包或机械单位",IF(AND(I18="付应付款",Y18=0),"✗ 这家没有应付：先在【应付登记】登记（现买现付的选材料费等）",IF(AND(OR(I18="工资",I18="工资退回"),AA18=0),"✗ 工资要选管理人员或工人（临时工选「临时工工资」）",IF(AND(I18="账户互转",AD18=""),"✗ 账户互转要在「对方账户」选（借款、报销选那个人的个人户）",IF(AND(I18="账户互转",AF18=""),"✗ 对方账户不在【基础资料】② 里",IF(AND(I18="账户互转",AD18=C18),"✗ 对方账户不能是自己",IF(IF(I18="账户互转",COUNTIFS(资金流水!$C$6:$C$2005,AD18,资金流水!$AD$6:$AD$2005,C18,资金流水!$I$6:$I$2005,"账户互转",资金流水!$R$6:$R$2005,-R18)>0,FALSE),"✗ 对方账户那边也记了这笔互转（只记一边：清空其中一行的内容）",IF(AJ18>0,"⚠ 摘要里有两个项目：拆成几行，或在「改项目」选",IF(AND(I18<>"账户互转",O18<>""),"⚠ 填了对方账户但类别不是账户互转（对方账户不起作用）",IF(AND(J18<>"",Z18=""),"⚠ 单位/人没在【往来单位】登记",IF(AND(N(F18)<0,AH18="收"),"⚠ 这是收款，以后请记在收入栏",IF(N(E18)<0,"⚠ 收入填了负数，已按支出算",IF(N(F18)<0,"↩ 冲回（退款）",IF(AND(R18<0,I18<>"固定资产购置",I18<>"付应付款",ISNUMBER(B18),IFERROR(SUMPRODUCT(ISNUMBER(SEARCH(基础资料!$AJ$5:$AJ$34,D18))*(基础资料!$AJ$5:$AJ$34<>"")*((AN18-基础资料!$AK$5:$AK$34)<=30)*((AN18-基础资料!$AK$5:$AK$34)>=-30)),0)>0),"⚠ 像是在买【基础资料】⑥ 登记的车/设备：类别改成「固定资产购置」，不然成本算两遍",IF(AND(OR(I18="材料费",I18="分包费",I18="机械运输费",I18="其他直接费"),J18="",H18<>"",COUNTIFS(应付登记!$E$5:$E$1004,H18,应付登记!$G$5:$G$1004,-R18)>0),"⚠ 这个项目有同样金额的应付登记：是付那家的，改类别选「付应付款」、改单位选那家（不然成本算两遍）","√")))))))))))))))))))))))))))) -> √ | R18: =ROUND(N(E18)-N(F18),2) -> -1245.06 | S18: =IF(ISNUMBER(B18),YEAR(B18)*100+MONTH(B18),"") -> 202605 | T18: =IF(N(AK18)=0,"",INDEX(_辅助!$S$1:$S$240,AK18)) | U18: =IF(OR(D18="",R18=0),"",IF(AND(Z18="临时工",R18<0),"临时工工资",IF(AG18="",IF(AA18=1,"工资",IF(Z18="临时工","临时工工资",IF(Z18="甲方/总包","工程款",IF(AND(OR(Z18="材料供应商",Z18="分包",Z18="机械运输"),Y18=1),"付应付款","")))),IF(AND(Y18=1,OR(Z18="材料供应商",Z18="分包",Z18="机械运输",Z18="其他"),OR(AG18="材料费",AG18="分包费",AG18="机械运输费",AG18="其他直接费",AG18="工资",AG18="临时工工资")),"付应付款",AG18)))) -> 代缴个税 | V18: =IF(D18="","",IF(N(AM18)>0,IF(N(AM18)=0,"",INDEX(_辅助!$W$1:$W$900,AM18)),IF(N(AL18)=0,"",INDEX(_辅助!$W$1:$W$900,AL18)))) | W18: =IF(I18="","",IFERROR(INDEX(基础资料!$V$5:$V$64,MATCH(I18,基础资料!$S$5:$S$64,0))&"","？")) -> 不进利润 | X18: =IF(R18=0,"",IF(OR(I18="",IFERROR(INDEX(基础资料!$U$5:$U$64,MATCH(I18,基础资料!$S$5:$S$64,0))&"","")=""),"待分类",IF(OR(I18="付应付款",IFERROR(INDEX(基础资料!$U$5:$U$64,MATCH(I18,基础资料!$S$5:$S$64,0))&"","")="应付款"),IF(Z18="材料供应商","应付材料款",IF(Z18="分包","应付分包款",IF(Z18="机械运输","应付机械运输费","应付其他款"))),IFERROR(INDEX(基础资料!$U$5:$U$64,MATCH(I18,基础资料!$S$5:$S$64,0))&"","")))) -> 应交税费 | Y18: =IF(J18="",0,IF(COUNTIF(应付登记!$D$5:$D$1004,J18)+COUNTIF(期初余额!$P$5:$P$204,J18)>0,1,0)) -> 0 | Z18: =IF(J18="","",IFERROR(INDEX(往来单位!$C$4:$C$303,MATCH(J18,往来单位!$B$4:$B$303,0))&"","")) | AA18: =IF(OR(Z18="管理人员",Z18="工人"),1,0) -> 0 | AB18: =IF(ISERROR(FIND("代",D18)),"",IFERROR(MID(D18,FIND("代",D18)+1,FIND("付",D18,FIND("代",D18))-FIND("代",D18)-1),"")) | AC18: =IF(I18<>"账户互转","",IF(J18<>"",IFERROR(INDEX(_辅助!$G$1:$G$40,MATCH(J18,_辅助!$F$1:$F$40,0)),IF(IFERROR(MATCH(1,INDEX(ISNUMBER(SEARCH(_辅助!$Z$1:$Z$40,D18))*(_辅助!$Z$1:$Z$40<>""),0),0),0)=0,"",INDEX(_辅助!$AA$1:$AA$40,IFERROR(MATCH(1,INDEX(ISNUMBER(SEARCH(_辅助!$Z$1:$Z$40,D18))*(_辅助!$Z$1:$Z$40<>""),0),0),0)))),IF(IFERROR(MATCH(1,INDEX(ISNUMBER(SEARCH(_辅助!$Z$1:$Z$40,D18))*(_辅助!$Z$1:$Z$40<>""),0),0),0)=0,"",INDEX(_辅助!$AA$1:$AA$40,IFERROR(MATCH(1,INDEX(ISNUMBER(SEARCH(_辅助!$Z$1:$Z$40,D18))*(_辅助!$Z$1:$Z$40<>""),0),0),0))))) | AD18: =IF(O18<>"",O18,AC18) | AE18: =IF(C18="","",IFERROR(INDEX(基础资料!$H$5:$H$24,MATCH(C18,基础资料!$G$5:$G$24,0))&"","")) -> 银行 | AF18: =IF(AD18="","",IFERROR(INDEX(基础资料!$H$5:$H$24,MATCH(AD18,基础资料!$G$5:$G$24,0))&"","")) | AG18: =IF(OR(D18="",R18=0),"",IFERROR(INDEX(基础资料!$AC$5:$AC$164,IF(IF(F18<>"","支","收")="收",MATCH(1,INDEX(ISNUMBER(SEARCH(_辅助!$AB$1:$AB$160,D18))*(_辅助!$AB$1:$AB$160<>""),0),0),MATCH(1,INDEX(ISNUMBER(SEARCH(_辅助!$AC$1:$AC$160,D18))*(_辅助!$AC$1:$AC$160<>""),0),0)))&"","")) -> 代缴个税 | AH18: =IF(R18=0,"",IF(OR(IFERROR(INDEX(基础资料!$T$5:$T$64,MATCH(I18,基础资料!$S$5:$S$64,0))&"","")="收",IFERROR(INDEX(基础资料!$T$5:$T$64,MATCH(I18,基础资料!$S$5:$S$64,0))&"","")="支"),IFERROR(INDEX(基础资料!$T$5:$T$64,MATCH(I18,基础资料!$S$5:$S$64,0))&"",""),IF(R18>0,"收","支"))) -> 支 | AI18: =IF(N(AK18)=0,"",INDEX(_辅助!$R$1:$R$240,AK18)) | AJ18: =IF(OR(AI18="",L18<>""),0,SUMPRODUCT(ISNUMBER(SEARCH(_辅助!$R$1:$R$240,D18))*(_辅助!$R$1:$R$240<>"")*(1-ISNUMBER(SEARCH(_辅助!$R$1:$R$240,AI18)))*(_辅助!$S$1:$S$240<>T18))) -> 0 | AK18: =IF(D18="",0,IFERROR(MATCH(1,INDEX(ISNUMBER(SEARCH(_辅助!$R$1:$R$240,D18))*(_辅助!$R$1:$R$240<>""),0),0),0)) -> 0 | AL18: =IF(D18="",0,IFERROR(MATCH(1,INDEX(ISNUMBER(SEARCH(_辅助!$V$1:$V$900,D18))*(_辅助!$V$1:$V$900<>""),0),0),0)) -> 0 | AM18: =IF(AB18="",0,IFERROR(MATCH(1,INDEX(ISNUMBER(SEARCH(_辅助!$V$1:$V$900,AB18))*(_辅助!$V$1:$V$900<>""),0),0),0)) -> 0 | AN18: =IF(ISNUMBER(B18),INT(B18),0) -> 46155 | AO18: =IF(AND(X18="应收账款",R18>0,AN18>0,H18<>""),H18&"|"&COUNTIFS(资金流水!$H$6:$H$2005,H18,资金流水!$X$6:$X$2005,"应收账款",资金流水!$R$6:$R$2005,">0",资金流水!$AN$6:$AN$2005,">0",资金流水!$AN$6:$AN$2005,"<="&AN18),"") | AP18: =IF(AND(J18<>"",R18<0,AN18>0),J18&"|"&COUNTIFS(资金流水!$J$6:$J$2005,J18,资金流水!$R$6:$R$2005,"<0",资金流水!$AN$6:$AN$2005,">0",资金流水!$AN$6:$AN$2005,"<="&AN18),"") | AQ18: =IF(AND(X18="其他应收款",AN18>0,J18<>""),J18&"|"&(COUNTIFS(资金流水!$J$6:$J$2005,J18,资金流水!$X$6:$X$2005,"其他应收款",资金流水!$AN$6:$AN$2005,">0",资金流水!$AN$6:$AN$2005,"<"&AN18)+COUNTIFS($J$6:J18,J18,$X$6:X18,"其他应收款",$AN$6:AN18,AN18)),"")
A19: =IF(AND(B19="",D19="",E19="",F19=""),"",ROW()-5) -> 14 | B19: 46156 | C19: 九江银行 | D19: 收到股东借款-聂辉 | E19: 40000 | G19: =IF(C19="","",ROUND(IFERROR(INDEX(基础资料!$K$5:$K$24,MATCH(C19,基础资料!$G$5:$G$24,0)),0)+SUMIFS($R$6:R19,$C$6:C19,C19)-SUMIFS($R$6:R19,$AD$6:AD19,C19,$X$6:X19,"账户互转"),2)) -> 936.82 | H19: =IF(L19<>"",L19,T19) | I19: =IF(M19<>"",M19,U19) -> 账户互转 | J19: =IF(N19<>"",N19,V19) -> 聂辉 | K19: =IF(AND(B19="",D19="",E19="",F19=""),"",IF(C19="","✗ 没选账户",IF(AE19="","✗ 账户不在【基础资料】② 里",IF(NOT(ISNUMBER(B19)),"✗ 日期要填成日期（2026/5/1）",IF(AND(ISNUMBER(B19),B19<基础资料!$C$9),"✗ 日期早于建账日期（建账前的放【期初余额】）",IF(AND(N(E19)<>0,N(F19)<>0),"✗ 收入、支出只填一边",IF(R19=0,"✗ 没有金额",IF(I19="","✗ 认不出收支类别：在「改类别」选",IF(W19="？","✗ 收支类别不在【基础资料】③ 里",IF(OR(I19="管理人员工资",I19="折旧费"),"✗ 这一类是自动算的，流水里不能选（发工资选「工资」，买设备选「固定资产购置」）",IF(AND(OR(X19="材料费",X19="人工费",X19="分包费",X19="机械运输费",X19="其他直接费",X19="票据贴息",X19="应收账款"),H19=""),"✗ 这一笔要选项目（摘要里的项目没在【项目档案】的话先去加上）",IF(AND(H19<>"",COUNTIF(项目档案!$B$4:$B$63,H19)=0),"✗ 项目不在【项目档案】里",IF(AND(OR(IFERROR(INDEX(基础资料!$W$5:$W$64,MATCH(I19,基础资料!$S$5:$S$64,0))&"","")="人",IFERROR(INDEX(基础资料!$W$5:$W$64,MATCH(I19,基础资料!$S$5:$S$64,0))&"","")="单位"),J19=""),"✗ 这一笔要选是谁（改单位/人）",IF(AND(I19="付应付款",NOT(OR(Z19="材料供应商",Z19="分包",Z19="机械运输",Z19="其他"))),"✗ 付应付款要选材料商、分包或机械单位",IF(AND(I19="付应付款",Y19=0),"✗ 这家没有应付：先在【应付登记】登记（现买现付的选材料费等）",IF(AND(OR(I19="工资",I19="工资退回"),AA19=0),"✗ 工资要选管理人员或工人（临时工选「临时工工资」）",IF(AND(I19="账户互转",AD19=""),"✗ 账户互转要在「对方账户」选（借款、报销选那个人的个人户）",IF(AND(I19="账户互转",AF19=""),"✗ 对方账户不在【基础资料】② 里",IF(AND(I19="账户互转",AD19=C19),"✗ 对方账户不能是自己",IF(IF(I19="账户互转",COUNTIFS(资金流水!$C$6:$C$2005,AD19,资金流水!$AD$6:$AD$2005,C19,资金流水!$I$6:$I$2005,"账户互转",资金流水!$R$6:$R$2005,-R19)>0,FALSE),"✗ 对方账户那边也记了这笔互转（只记一边：清空其中一行的内容）",IF(AJ19>0,"⚠ 摘要里有两个项目：拆成几行，或在「改项目」选",IF(AND(I19<>"账户互转",O19<>""),"⚠ 填了对方账户但类别不是账户互转（对方账户不起作用）",IF(AND(J19<>"",Z19=""),"⚠ 单位/人没在【往来单位】登记",IF(AND(N(F19)<0,AH19="收"),"⚠ 这是收款，以后请记在收入栏",IF(N(E19)<0,"⚠ 收入填了负数，已按支出算",IF(N(F19)<0,"↩ 冲回（退款）",IF(AND(R19<0,I19<>"固定资产购置",I19<>"付应付款",ISNUMBER(B19),IFERROR(SUMPRODUCT(ISNUMBER(SEARCH(基础资料!$AJ$5:$AJ$34,D19))*(基础资料!$AJ$5:$AJ$34<>"")*((AN19-基础资料!$AK$5:$AK$34)<=30)*((AN19-基础资料!$AK$5:$AK$34)>=-30)),0)>0),"⚠ 像是在买【基础资料】⑥ 登记的车/设备：类别改成「固定资产购置」，不然成本算两遍",IF(AND(OR(I19="材料费",I19="分包费",I19="机械运输费",I19="其他直接费"),J19="",H19<>"",COUNTIFS(应付登记!$E$5:$E$1004,H19,应付登记!$G$5:$G$1004,-R19)>0),"⚠ 这个项目有同样金额的应付登记：是付那家的，改类别选「付应付款」、改单位选那家（不然成本算两遍）","√")))))))))))))))))))))))))))) -> √ | R19: =ROUND(N(E19)-N(F19),2) -> 40000 | S19: =IF(ISNUMBER(B19),YEAR(B19)*100+MONTH(B19),"") -> 202605 | T19: =IF(N(AK19)=0,"",INDEX(_辅助!$S$1:$S$240,AK19)) | U19: =IF(OR(D19="",R19=0),"",IF(AND(Z19="临时工",R19<0),"临时工工资",IF(AG19="",IF(AA19=1,"工资",IF(Z19="临时工","临时工工资",IF(Z19="甲方/总包","工程款",IF(AND(OR(Z19="材料供应商",Z19="分包",Z19="机械运输"),Y19=1),"付应付款","")))),IF(AND(Y19=1,OR(Z19="材料供应商",Z19="分包",Z19="机械运输",Z19="其他"),OR(AG19="材料费",AG19="分包费",AG19="机械运输费",AG19="其他直接费",AG19="工资",AG19="临时工工资")),"付应付款",AG19)))) -> 账户互转 | V19: =IF(D19="","",IF(N(AM19)>0,IF(N(AM19)=0,"",INDEX(_辅助!$W$1:$W$900,AM19)),IF(N(AL19)=0,"",INDEX(_辅助!$W$1:$W$900,AL19)))) -> 聂辉 | W19: =IF(I19="","",IFERROR(INDEX(基础资料!$V$5:$V$64,MATCH(I19,基础资料!$S$5:$S$64,0))&"","？")) -> 不进利润 | X19: =IF(R19=0,"",IF(OR(I19="",IFERROR(INDEX(基础资料!$U$5:$U$64,MATCH(I19,基础资料!$S$5:$S$64,0))&"","")=""),"待分类",IF(OR(I19="付应付款",IFERROR(INDEX(基础资料!$U$5:$U$64,MATCH(I19,基础资料!$S$5:$S$64,0))&"","")="应付款"),IF(Z19="材料供应商","应付材料款",IF(Z19="分包","应付分包款",IF(Z19="机械运输","应付机械运输费","应付其他款"))),IFERROR(INDEX(基础资料!$U$5:$U$64,MATCH(I19,基础资料!$S$5:$S$64,0))&"","")))) -> 账户互转 | Y19: =IF(J19="",0,IF(COUNTIF(应付登记!$D$5:$D$1004,J19)+COUNTIF(期初余额!$P$5:$P$204,J19)>0,1,0)) -> 0 | Z19: =IF(J19="","",IFERROR(INDEX(往来单位!$C$4:$C$303,MATCH(J19,往来单位!$B$4:$B$303,0))&"","")) -> 管理人员 | AA19: =IF(OR(Z19="管理人员",Z19="工人"),1,0) -> 1 | AB19: =IF(ISERROR(FIND("代",D19)),"",IFERROR(MID(D19,FIND("代",D19)+1,FIND("付",D19,FIND("代",D19))-FIND("代",D19)-1),"")) | AC19: =IF(I19<>"账户互转","",IF(J19<>"",IFERROR(INDEX(_辅助!$G$1:$G$40,MATCH(J19,_辅助!$F$1:$F$40,0)),IF(IFERROR(MATCH(1,INDEX(ISNUMBER(SEARCH(_辅助!$Z$1:$Z$40,D19))*(_辅助!$Z$1:$Z$40<>""),0),0),0)=0,"",INDEX(_辅助!$AA$1:$AA$40,IFERROR(MATCH(1,INDEX(ISNUMBER(SEARCH(_辅助!$Z$1:$Z$40,D19))*(_辅助!$Z$1:$Z$40<>""),0),0),0)))),IF(IFERROR(MATCH(1,INDEX(ISNUMBER(SEARCH(_辅助!$Z$1:$Z$40,D19))*(_辅助!$Z$1:$Z$40<>""),0),0),0)=0,"",INDEX(_辅助!$AA$1:$AA$40,IFERROR(MATCH(1,INDEX(ISNUMBER(SEARCH(_辅助!$Z$1:$Z$40,D19))*(_辅助!$Z$1:$Z$40<>""),0),0),0))))) -> 聂辉个人户 | AD19: =IF(O19<>"",O19,AC19) -> 聂辉个人户 | AE19: =IF(C19="","",IFERROR(INDEX(基础资料!$H$5:$H$24,MATCH(C19,基础资料!$G$5:$G$24,0))&"","")) -> 银行 | AF19: =IF(AD19="","",IFERROR(INDEX(基础资料!$H$5:$H$24,MATCH(AD19,基础资料!$G$5:$G$24,0))&"","")) -> 个人户 | AG19: =IF(OR(D19="",R19=0),"",IFERROR(INDEX(基础资料!$AC$5:$AC$164,IF(IF(F19<>"","支","收")="收",MATCH(1,INDEX(ISNUMBER(SEARCH(_辅助!$AB$1:$AB$160,D19))*(_辅助!$AB$1:$AB$160<>""),0),0),MATCH(1,INDEX(ISNUMBER(SEARCH(_辅助!$AC$1:$AC$160,D19))*(_辅助!$AC$1:$AC$160<>""),0),0)))&"","")) -> 账户互转 | AH19: =IF(R19=0,"",IF(OR(IFERROR(INDEX(基础资料!$T$5:$T$64,MATCH(I19,基础资料!$S$5:$S$64,0))&"","")="收",IFERROR(INDEX(基础资料!$T$5:$T$64,MATCH(I19,基础资料!$S$5:$S$64,0))&"","")="支"),IFERROR(INDEX(基础资料!$T$5:$T$64,MATCH(I19,基础资料!$S$5:$S$64,0))&"",""),IF(R19>0,"收","支"))) -> 收 | AI19: =IF(N(AK19)=0,"",INDEX(_辅助!$R$1:$R$240,AK19)) | AJ19: =IF(OR(AI19="",L19<>""),0,SUMPRODUCT(ISNUMBER(SEARCH(_辅助!$R$1:$R$240,D19))*(_辅助!$R$1:$R$240<>"")*(1-ISNUMBER(SEARCH(_辅助!$R$1:$R$240,AI19)))*(_辅助!$S$1:$S$240<>T19))) -> 0 | AK19: =IF(D19="",0,IFERROR(MATCH(1,INDEX(ISNUMBER(SEARCH(_辅助!$R$1:$R$240,D19))*(_辅助!$R$1:$R$240<>""),0),0),0)) -> 0 | AL19: =IF(D19="",0,IFERROR(MATCH(1,INDEX(ISNUMBER(SEARCH(_辅助!$V$1:$V$900,D19))*(_辅助!$V$1:$V$900<>""),0),0),0)) -> 111 | AM19: =IF(AB19="",0,IFERROR(MATCH(1,INDEX(ISNUMBER(SEARCH(_辅助!$V$1:$V$900,AB19))*(_辅助!$V$1:$V$900<>""),0),0),0)) -> 0 | AN19: =IF(ISNUMBER(B19),INT(B19),0) -> 46156 | AO19: =IF(AND(X19="应收账款",R19>0,AN19>0,H19<>""),H19&"|"&COUNTIFS(资金流水!$H$6:$H$2005,H19,资金流水!$X$6:$X$2005,"应收账款",资金流水!$R$6:$R$2005,">0",资金流水!$AN$6:$AN$2005,">0",资金流水!$AN$6:$AN$2005,"<="&AN19),"") | AP19: =IF(AND(J19<>"",R19<0,AN19>0),J19&"|"&COUNTIFS(资金流水!$J$6:$J$2005,J19,资金流水!$R$6:$R$2005,"<0",资金流水!$AN$6:$AN$2005,">0",资金流水!$AN$6:$AN$2005,"<="&AN19),"") | AQ19: =IF(AND(X19="其他应收款",AN19>0,J19<>""),J19&"|"&(COUNTIFS(资金流水!$J$6:$J$2005,J19,资金流水!$X$6:$X$2005,"其他应收款",资金流水!$AN$6:$AN$2005,">0",资金流水!$AN$6:$AN$2005,"<"&AN19)+COUNTIFS($J$6:J19,J19,$X$6:X19,"其他应收款",$AN$6:AN19,AN19)),"")
A20: =IF(AND(B20="",D20="",E20="",F20=""),"",ROW()-5) -> 15 | B20: 46156 | C20: 九江银行 | D20: 付佩力通风材料款（德养） | F20: 7397 | G20: =IF(C20="","",ROUND(IFERROR(INDEX(基础资料!$K$5:$K$24,MATCH(C20,基础资料!$G$5:$G$24,0)),0)+SUMIFS($R$6:R20,$C$6:C20,C20)-SUMIFS($R$6:R20,$AD$6:AD20,C20,$X$6:X20,"账户互转"),2)) -> -6460.18 | H20: =IF(L20<>"",L20,T20) -> 德安养老中心 | I20: =IF(M20<>"",M20,U20) -> 付应付款 | J20: =IF(N20<>"",N20,V20) -> 佩力通风 | K20: =IF(AND(B20="",D20="",E20="",F20=""),"",IF(C20="","✗ 没选账户",IF(AE20="","✗ 账户不在【基础资料】② 里",IF(NOT(ISNUMBER(B20)),"✗ 日期要填成日期（2026/5/1）",IF(AND(ISNUMBER(B20),B20<基础资料!$C$9),"✗ 日期早于建账日期（建账前的放【期初余额】）",IF(AND(N(E20)<>0,N(F20)<>0),"✗ 收入、支出只填一边",IF(R20=0,"✗ 没有金额",IF(I20="","✗ 认不出收支类别：在「改类别」选",IF(W20="？","✗ 收支类别不在【基础资料】③ 里",IF(OR(I20="管理人员工资",I20="折旧费"),"✗ 这一类是自动算的，流水里不能选（发工资选「工资」，买设备选「固定资产购置」）",IF(AND(OR(X20="材料费",X20="人工费",X20="分包费",X20="机械运输费",X20="其他直接费",X20="票据贴息",X20="应收账款"),H20=""),"✗ 这一笔要选项目（摘要里的项目没在【项目档案】的话先去加上）",IF(AND(H20<>"",COUNTIF(项目档案!$B$4:$B$63,H20)=0),"✗ 项目不在【项目档案】里",IF(AND(OR(IFERROR(INDEX(基础资料!$W$5:$W$64,MATCH(I20,基础资料!$S$5:$S$64,0))&"","")="人",IFERROR(INDEX(基础资料!$W$5:$W$64,MATCH(I20,基础资料!$S$5:$S$64,0))&"","")="单位"),J20=""),"✗ 这一笔要选是谁（改单位/人）",IF(AND(I20="付应付款",NOT(OR(Z20="材料供应商",Z20="分包",Z20="机械运输",Z20="其他"))),"✗ 付应付款要选材料商、分包或机械单位",IF(AND(I20="付应付款",Y20=0),"✗ 这家没有应付：先在【应付登记】登记（现买现付的选材料费等）",IF(AND(OR(I20="工资",I20="工资退回"),AA20=0),"✗ 工资要选管理人员或工人（临时工选「临时工工资」）",IF(AND(I20="账户互转",AD20=""),"✗ 账户互转要在「对方账户」选（借款、报销选那个人的个人户）",IF(AND(I20="账户互转",AF20=""),"✗ 对方账户不在【基础资料】② 里",IF(AND(I20="账户互转",AD20=C20),"✗ 对方账户不能是自己",IF(IF(I20="账户互转",COUNTIFS(资金流水!$C$6:$C$2005,AD20,资金流水!$AD$6:$AD$2005,C20,资金流水!$I$6:$I$2005,"账户互转",资金流水!$R$6:$R$2005,-R20)>0,FALSE),"✗ 对方账户那边也记了这笔互转（只记一边：清空其中一行的内容）",IF(AJ20>0,"⚠ 摘要里有两个项目：拆成几行，或在「改项目」选",IF(AND(I20<>"账户互转",O20<>""),"⚠ 填了对方账户但类别不是账户互转（对方账户不起作用）",IF(AND(J20<>"",Z20=""),"⚠ 单位/人没在【往来单位】登记",IF(AND(N(F20)<0,AH20="收"),"⚠ 这是收款，以后请记在收入栏",IF(N(E20)<0,"⚠ 收入填了负数，已按支出算",IF(N(F20)<0,"↩ 冲回（退款）",IF(AND(R20<0,I20<>"固定资产购置",I20<>"付应付款",ISNUMBER(B20),IFERROR(SUMPRODUCT(ISNUMBER(SEARCH(基础资料!$AJ$5:$AJ$34,D20))*(基础资料!$AJ$5:$AJ$34<>"")*((AN20-基础资料!$AK$5:$AK$34)<=30)*((AN20-基础资料!$AK$5:$AK$34)>=-30)),0)>0),"⚠ 像是在买【基础资料】⑥ 登记的车/设备：类别改成「固定资产购置」，不然成本算两遍",IF(AND(OR(I20="材料费",I20="分包费",I20="机械运输费",I20="其他直接费"),J20="",H20<>"",COUNTIFS(应付登记!$E$5:$E$1004,H20,应付登记!$G$5:$G$1004,-R20)>0),"⚠ 这个项目有同样金额的应付登记：是付那家的，改类别选「付应付款」、改单位选那家（不然成本算两遍）","√")))))))))))))))))))))))))))) -> √ | R20: =ROUND(N(E20)-N(F20),2) -> -7397 | S20: =IF(ISNUMBER(B20),YEAR(B20)*100+MONTH(B20),"") -> 202605 | T20: =IF(N(AK20)=0,"",INDEX(_辅助!$S$1:$S$240,AK20)) -> 德安养老中心 | U20: =IF(OR(D20="",R20=0),"",IF(AND(Z20="临时工",R20<0),"临时工工资",IF(AG20="",IF(AA20=1,"工资",IF(Z20="临时工","临时工工资",IF(Z20="甲方/总包","工程款",IF(AND(OR(Z20="材料供应商",Z20="分包",Z20="机械运输"),Y20=1),"付应付款","")))),IF(AND(Y20=1,OR(Z20="材料供应商",Z20="分包",Z20="机械运输",Z20="其他"),OR(AG20="材料费",AG20="分包费",AG20="机械运输费",AG20="其他直接费",AG20="工资",AG20="临时工工资")),"付应付款",AG20)))) -> 付应付款 | V20: =IF(D20="","",IF(N(AM20)>0,IF(N(AM20)=0,"",INDEX(_辅助!$W$1:$W$900,AM20)),IF(N(AL20)=0,"",INDEX(_辅助!$W$1:$W$900,AL20)))) -> 佩力通风 | W20: =IF(I20="","",IFERROR(INDEX(基础资料!$V$5:$V$64,MATCH(I20,基础资料!$S$5:$S$64,0))&"","？")) -> 不进利润 | X20: =IF(R20=0,"",IF(OR(I20="",IFERROR(INDEX(基础资料!$U$5:$U$64,MATCH(I20,基础资料!$S$5:$S$64,0))&"","")=""),"待分类",IF(OR(I20="付应付款",IFERROR(INDEX(基础资料!$U$5:$U$64,MATCH(I20,基础资料!$S$5:$S$64,0))&"","")="应付款"),IF(Z20="材料供应商","应付材料款",IF(Z20="分包","应付分包款",IF(Z20="机械运输","应付机械运输费","应付其他款"))),IFERROR(INDEX(基础资料!$U$5:$U$64,MATCH(I20,基础资料!$S$5:$S$64,0))&"","")))) -> 应付材料款 | Y20: =IF(J20="",0,IF(COUNTIF(应付登记!$D$5:$D$1004,J20)+COUNTIF(期初余额!$P$5:$P$204,J20)>0,1,0)) -> 1 | Z20: =IF(J20="","",IFERROR(INDEX(往来单位!$C$4:$C$303,MATCH(J20,往来单位!$B$4:$B$303,0))&"","")) -> 材料供应商 | AA20: =IF(OR(Z20="管理人员",Z20="工人"),1,0) -> 0 | AB20: =IF(ISERROR(FIND("代",D20)),"",IFERROR(MID(D20,FIND("代",D20)+1,FIND("付",D20,FIND("代",D20))-FIND("代",D20)-1),"")) | AC20: =IF(I20<>"账户互转","",IF(J20<>"",IFERROR(INDEX(_辅助!$G$1:$G$40,MATCH(J20,_辅助!$F$1:$F$40,0)),IF(IFERROR(MATCH(1,INDEX(ISNUMBER(SEARCH(_辅助!$Z$1:$Z$40,D20))*(_辅助!$Z$1:$Z$40<>""),0),0),0)=0,"",INDEX(_辅助!$AA$1:$AA$40,IFERROR(MATCH(1,INDEX(ISNUMBER(SEARCH(_辅助!$Z$1:$Z$40,D20))*(_辅助!$Z$1:$Z$40<>""),0),0),0)))),IF(IFERROR(MATCH(1,INDEX(ISNUMBER(SEARCH(_辅助!$Z$1:$Z$40,D20))*(_辅助!$Z$1:$Z$40<>""),0),0),0)=0,"",INDEX(_辅助!$AA$1:$AA$40,IFERROR(MATCH(1,INDEX(ISNUMBER(SEARCH(_辅助!$Z$1:$Z$40,D20))*(_辅助!$Z$1:$Z$40<>""),0),0),0))))) | AD20: =IF(O20<>"",O20,AC20) | AE20: =IF(C20="","",IFERROR(INDEX(基础资料!$H$5:$H$24,MATCH(C20,基础资料!$G$5:$G$24,0))&"","")) -> 银行 | AF20: =IF(AD20="","",IFERROR(INDEX(基础资料!$H$5:$H$24,MATCH(AD20,基础资料!$G$5:$G$24,0))&"","")) | AG20: =IF(OR(D20="",R20=0),"",IFERROR(INDEX(基础资料!$AC$5:$AC$164,IF(IF(F20<>"","支","收")="收",MATCH(1,INDEX(ISNUMBER(SEARCH(_辅助!$AB$1:$AB$160,D20))*(_辅助!$AB$1:$AB$160<>""),0),0),MATCH(1,INDEX(ISNUMBER(SEARCH(_辅助!$AC$1:$AC$160,D20))*(_辅助!$AC$1:$AC$160<>""),0),0)))&"","")) -> 材料费 | AH20: =IF(R20=0,"",IF(OR(IFERROR(INDEX(基础资料!$T$5:$T$64,MATCH(I20,基础资料!$S$5:$S$64,0))&"","")="收",IFERROR(INDEX(基础资料!$T$5:$T$64,MATCH(I20,基础资料!$S$5:$S$64,0))&"","")="支"),IFERROR(INDEX(基础资料!$T$5:$T$64,MATCH(I20,基础资料!$S$5:$S$64,0))&"",""),IF(R20>0,"收","支"))) -> 支 | AI20: =IF(N(AK20)=0,"",INDEX(_辅助!$R$1:$R$240,AK20)) -> 德养 | AJ20: =IF(OR(AI20="",L20<>""),0,SUMPRODUCT(ISNUMBER(SEARCH(_辅助!$R$1:$R$240,D20))*(_辅助!$R$1:$R$240<>"")*(1-ISNUMBER(SEARCH(_辅助!$R$1:$R$240,AI20)))*(_辅助!$S$1:$S$240<>T20))) -> 0 | AK20: =IF(D20="",0,IFERROR(MATCH(1,INDEX(ISNUMBER(SEARCH(_辅助!$R$1:$R$240,D20))*(_辅助!$R$1:$R$240<>""),0),0),0)) -> 28 | AL20: =IF(D20="",0,IFERROR(MATCH(1,INDEX(ISNUMBER(SEARCH(_辅助!$V$1:$V$900,D20))*(_辅助!$V$1:$V$900<>""),0),0),0)) -> 34 | AM20: =IF(AB20="",0,IFERROR(MATCH(1,INDEX(ISNUMBER(SEARCH(_辅助!$V$1:$V$900,AB20))*(_辅助!$V$1:$V$900<>""),0),0),0)) -> 0 | AN20: =IF(ISNUMBER(B20),INT(B20),0) -> 46156 | AO20: =IF(AND(X20="应收账款",R20>0,AN20>0,H20<>""),H20&"|"&COUNTIFS(资金流水!$H$6:$H$2005,H20,资金流水!$X$6:$X$2005,"应收账款",资金流水!$R$6:$R$2005,">0",资金流水!$AN$6:$AN$2005,">0",资金流水!$AN$6:$AN$2005,"<="&AN20),"") | AP20: =IF(AND(J20<>"",R20<0,AN20>0),J20&"|"&COUNTIFS(资金流水!$J$6:$J$2005,J20,资金流水!$R$6:$R$2005,"<0",资金流水!$AN$6:$AN$2005,">0",资金流水!$AN$6:$AN$2005,"<="&AN20),"") -> 佩力通风|1 | AQ20: =IF(AND(X20="其他应收款",AN20>0,J20<>""),J20&"|"&(COUNTIFS(资金流水!$J$6:$J$2005,J20,资金流水!$X$6:$X$2005,"其他应收款",资金流水!$AN$6:$AN$2005,">0",资金流水!$AN$6:$AN$2005,"<"&AN20)+COUNTIFS($J$6:J20,J20,$X$6:X20,"其他应收款",$AN$6:AN20,AN20)),"")
A21: =IF(AND(B21="",D21="",E21="",F21=""),"",ROW()-5) -> 16 | B21: 46157 | C21: 九江银行 | D21: 代老叶付佩力通风材料款（德养） | F21: 10000 | G21: =IF(C21="","",ROUND(IFERROR(INDEX(基础资料!$K$5:$K$24,MATCH(C21,基础资料!$G$5:$G$24,0)),0)+SUMIFS($R$6:R21,$C$6:C21,C21)-SUMIFS($R$6:R21,$AD$6:AD21,C21,$X$6:X21,"账户互转"),2)) -> -16460.18 | H21: =IF(L21<>"",L21,T21) -> 德安养老中心 | I21: =IF(M21<>"",M21,U21) -> 付应付款 | J21: =IF(N21<>"",N21,V21) -> 恩旗老叶 | K21: =IF(AND(B21="",D21="",E21="",F21=""),"",IF(C21="","✗ 没选账户",IF(AE21="","✗ 账户不在【基础资料】② 里",IF(NOT(ISNUMBER(B21)),"✗ 日期要填成日期（2026/5/1）",IF(AND(ISNUMBER(B21),B21<基础资料!$C$9),"✗ 日期早于建账日期（建账前的放【期初余额】）",IF(AND(N(E21)<>0,N(F21)<>0),"✗ 收入、支出只填一边",IF(R21=0,"✗ 没有金额",IF(I21="","✗ 认不出收支类别：在「改类别」选",IF(W21="？","✗ 收支类别不在【基础资料】③ 里",IF(OR(I21="管理人员工资",I21="折旧费"),"✗ 这一类是自动算的，流水里不能选（发工资选「工资」，买设备选「固定资产购置」）",IF(AND(OR(X21="材料费",X21="人工费",X21="分包费",X21="机械运输费",X21="其他直接费",X21="票据贴息",X21="应收账款"),H21=""),"✗ 这一笔要选项目（摘要里的项目没在【项目档案】的话先去加上）",IF(AND(H21<>"",COUNTIF(项目档案!$B$4:$B$63,H21)=0),"✗ 项目不在【项目档案】里",IF(AND(OR(IFERROR(INDEX(基础资料!$W$5:$W$64,MATCH(I21,基础资料!$S$5:$S$64,0))&"","")="人",IFERROR(INDEX(基础资料!$W$5:$W$64,MATCH(I21,基础资料!$S$5:$S$64,0))&"","")="单位"),J21=""),"✗ 这一笔要选是谁（改单位/人）",IF(AND(I21="付应付款",NOT(OR(Z21="材料供应商",Z21="分包",Z21="机械运输",Z21="其他"))),"✗ 付应付款要选材料商、分包或机械单位",IF(AND(I21="付应付款",Y21=0),"✗ 这家没有应付：先在【应付登记】登记（现买现付的选材料费等）",IF(AND(OR(I21="工资",I21="工资退回"),AA21=0),"✗ 工资要选管理人员或工人（临时工选「临时工工资」）",IF(AND(I21="账户互转",AD21=""),"✗ 账户互转要在「对方账户」选（借款、报销选那个人的个人户）",IF(AND(I21="账户互转",AF21=""),"✗ 对方账户不在【基础资料】② 里",IF(AND(I21="账户互转",AD21=C21),"✗ 对方账户不能是自己",IF(IF(I21="账户互转",COUNTIFS(资金流水!$C$6:$C$2005,AD21,资金流水!$AD$6:$AD$2005,C21,资金流水!$I$6:$I$2005,"账户互转",资金流水!$R$6:$R$2005,-R21)>0,FALSE),"✗ 对方账户那边也记了这笔互转（只记一边：清空其中一行的内容）",IF(AJ21>0,"⚠ 摘要里有两个项目：拆成几行，或在「改项目」选",IF(AND(I21<>"账户互转",O21<>""),"⚠ 填了对方账户但类别不是账户互转（对方账户不起作用）",IF(AND(J21<>"",Z21=""),"⚠ 单位/人没在【往来单位】登记",IF(AND(N(F21)<0,AH21="收"),"⚠ 这是收款，以后请记在收入栏",IF(N(E21)<0,"⚠ 收入填了负数，已按支出算",IF(N(F21)<0,"↩ 冲回（退款）",IF(AND(R21<0,I21<>"固定资产购置",I21<>"付应付款",ISNUMBER(B21),IFERROR(SUMPRODUCT(ISNUMBER(SEARCH(基础资料!$AJ$5:$AJ$34,D21))*(基础资料!$AJ$5:$AJ$34<>"")*((AN21-基础资料!$AK$5:$AK$34)<=30)*((AN21-基础资料!$AK$5:$AK$34)>=-30)),0)>0),"⚠ 像是在买【基础资料】⑥ 登记的车/设备：类别改成「固定资产购置」，不然成本算两遍",IF(AND(OR(I21="材料费",I21="分包费",I21="机械运输费",I21="其他直接费"),J21="",H21<>"",COUNTIFS(应付登记!$E$5:$E$1004,H21,应付登记!$G$5:$G$1004,-R21)>0),"⚠ 这个项目有同样金额的应付登记：是付那家的，改类别选「付应付款」、改单位选那家（不然成本算两遍）","√")))))))))))))))))))))))))))) -> √ | R21: =ROUND(N(E21)-N(F21),2) -> -10000 | S21: =IF(ISNUMBER(B21),YEAR(B21)*100+MONTH(B21),"") -> 202605 | T21: =IF(N(AK21)=0,"",INDEX(_辅助!$S$1:$S$240,AK21)) -> 德安养老中心 | U21: =IF(OR(D21="",R21=0),"",IF(AND(Z21="临时工",R21<0),"临时工工资",IF(AG21="",IF(AA21=1,"工资",IF(Z21="临时工","临时工工资",IF(Z21="甲方/总包","工程款",IF(AND(OR(Z21="材料供应商",Z21="分包",Z21="机械运输"),Y21=1),"付应付款","")))),IF(AND(Y21=1,OR(Z21="材料供应商",Z21="分包",Z21="机械运输",Z21="其他"),OR(AG21="材料费",AG21="分包费",AG21="机械运输费",AG21="其他直接费",AG21="工资",AG21="临时工工资")),"付应付款",AG21)))) -> 付应付款 | V21: =IF(D21="","",IF(N(AM21)>0,IF(N(AM21)=0,"",INDEX(_辅助!$W$1:$W$900,AM21)),IF(N(AL21)=0,"",INDEX(_辅助!$W$1:$W$900,AL21)))) -> 恩旗老叶 | W21: =IF(I21="","",IFERROR(INDEX(基础资料!$V$5:$V$64,MATCH(I21,基础资料!$S$5:$S$64,0))&"","？")) -> 不进利润 | X21: =IF(R21=0,"",IF(OR(I21="",IFERROR(INDEX(基础资料!$U$5:$U$64,MATCH(I21,基础资料!$S$5:$S$64,0))&"","")=""),"待分类",IF(OR(I21="付应付款",IFERROR(INDEX(基础资料!$U$5:$U$64,MATCH(I21,基础资料!$S$5:$S$64,0))&"","")="应付款"),IF(Z21="材料供应商","应付材料款",IF(Z21="分包","应付分包款",IF(Z21="机械运输","应付机械运输费","应付其他款"))),IFERROR(INDEX(基础资料!$U$5:$U$64,MATCH(I21,基础资料!$S$5:$S$64,0))&"","")))) -> 应付分包款 | Y21: =IF(J21="",0,IF(COUNTIF(应付登记!$D$5:$D$1004,J21)+COUNTIF(期初余额!$P$5:$P$204,J21)>0,1,0)) -> 1 | Z21: =IF(J21="","",IFERROR(INDEX(往来单位!$C$4:$C$303,MATCH(J21,往来单位!$B$4:$B$303,0))&"","")) -> 分包 | AA21: =IF(OR(Z21="管理人员",Z21="工人"),1,0) -> 0 | AB21: =IF(ISERROR(FIND("代",D21)),"",IFERROR(MID(D21,FIND("代",D21)+1,FIND("付",D21,FIND("代",D21))-FIND("代",D21)-1),"")) -> 老叶 | AC21: =IF(I21<>"账户互转","",IF(J21<>"",IFERROR(INDEX(_辅助!$G$1:$G$40,MATCH(J21,_辅助!$F$1:$F$40,0)),IF(IFERROR(MATCH(1,INDEX(ISNUMBER(SEARCH(_辅助!$Z$1:$Z$40,D21))*(_辅助!$Z$1:$Z$40<>""),0),0),0)=0,"",INDEX(_辅助!$AA$1:$AA$40,IFERROR(MATCH(1,INDEX(ISNUMBER(SEARCH(_辅助!$Z$1:$Z$40,D21))*(_辅助!$Z$1:$Z$40<>""),0),0),0)))),IF(IFERROR(MATCH(1,INDEX(ISNUMBER(SEARCH(_辅助!$Z$1:$Z$40,D21))*(_辅助!$Z$1:$Z$40<>""),0),0),0)=0,"",INDEX(_辅助!$AA$1:$AA$40,IFERROR(MATCH(1,INDEX(ISNUMBER(SEARCH(_辅助!$Z$1:$Z$40,D21))*(_辅助!$Z$1:$Z$40<>""),0),0),0))))) | AD21: =IF(O21<>"",O21,AC21) | AE21: =IF(C21="","",IFERROR(INDEX(基础资料!$H$5:$H$24,MATCH(C21,基础资料!$G$5:$G$24,0))&"","")) -> 银行 | AF21: =IF(AD21="","",IFERROR(INDEX(基础资料!$H$5:$H$24,MATCH(AD21,基础资料!$G$5:$G$24,0))&"","")) | AG21: =IF(OR(D21="",R21=0),"",IFERROR(INDEX(基础资料!$AC$5:$AC$164,IF(IF(F21<>"","支","收")="收",MATCH(1,INDEX(ISNUMBER(SEARCH(_辅助!$AB$1:$AB$160,D21))*(_辅助!$AB$1:$AB$160<>""),0),0),MATCH(1,INDEX(ISNUMBER(SEARCH(_辅助!$AC$1:$AC$160,D21))*(_辅助!$AC$1:$AC$160<>""),0),0)))&"","")) -> 材料费 | AH21: =IF(R21=0,"",IF(OR(IFERROR(INDEX(基础资料!$T$5:$T$64,MATCH(I21,基础资料!$S$5:$S$64,0))&"","")="收",IFERROR(INDEX(基础资料!$T$5:$T$64,MATCH(I21,基础资料!$S$5:$S$64,0))&"","")="支"),IFERROR(INDEX(基础资料!$T$5:$T$64,MATCH(I21,基础资料!$S$5:$S$64,0))&"",""),IF(R21>0,"收","支"))) -> 支 | AI21: =IF(N(AK21)=0,"",INDEX(_辅助!$R$1:$R$240,AK21)) -> 德养 | AJ21: =IF(OR(AI21="",L21<>""),0,SUMPRODUCT(ISNUMBER(SEARCH(_辅助!$R$1:$R$240,D21))*(_辅助!$R$1:$R$240<>"")*(1-ISNUMBER(SEARCH(_辅助!$R$1:$R$240,AI21)))*(_辅助!$S$1:$S$240<>T21))) -> 0 | AK21: =IF(D21="",0,IFERROR(MATCH(1,INDEX(ISNUMBER(SEARCH(_辅助!$R$1:$R$240,D21))*(_辅助!$R$1:$R$240<>""),0),0),0)) -> 28 | AL21: =IF(D21="",0,IFERROR(MATCH(1,INDEX(ISNUMBER(SEARCH(_辅助!$V$1:$V$900,D21))*(_辅助!$V$1:$V$900<>""),0),0),0)) -> 34 | AM21: =IF(AB21="",0,IFERROR(MATCH(1,INDEX(ISNUMBER(SEARCH(_辅助!$V$1:$V$900,AB21))*(_辅助!$V$1:$V$900<>""),0),0),0)) -> 98 | AN21: =IF(ISNUMBER(B21),INT(B21),0) -> 46157 | AO21: =IF(AND(X21="应收账款",R21>0,AN21>0,H21<>""),H21&"|"&COUNTIFS(资金流水!$H$6:$H$2005,H21,资金流水!$X$6:$X$2005,"应收账款",资金流水!$R$6:$R$2005,">0",资金流水!$AN$6:$AN$2005,">0",资金流水!$AN$6:$AN$2005,"<="&AN21),"") | AP21: =IF(AND(J21<>"",R21<0,AN21>0),J21&"|"&COUNTIFS(资金流水!$J$6:$J$2005,J21,资金流水!$R$6:$R$2005,"<0",资金流水!$AN$6:$AN$2005,">0",资金流水!$AN$6:$AN$2005,"<="&AN21),"") -> 恩旗老叶|2 | AQ21: =IF(AND(X21="其他应收款",AN21>0,J21<>""),J21&"|"&(COUNTIFS(资金流水!$J$6:$J$2005,J21,资金流水!$X$6:$X$2005,"其他应收款",资金流水!$AN$6:$AN$2005,">0",资金流水!$AN$6:$AN$2005,"<"&AN21)+COUNTIFS($J$6:J21,J21,$X$6:X21,"其他应收款",$AN$6:AN21,AN21)),"")
A22: =IF(AND(B22="",D22="",E22="",F22=""),"",ROW()-5) -> 17 | B22: 46158 | C22: 九江银行 | D22: 付沐丰水箱款(邹桥派出所） | F22: 22000 | G22: =IF(C22="","",ROUND(IFERROR(INDEX(基础资料!$K$5:$K$24,MATCH(C22,基础资料!$G$5:$G$24,0)),0)+SUMIFS($R$6:R22,$C$6:C22,C22)-SUMIFS($R$6:R22,$AD$6:AD22,C22,$X$6:X22,"账户互转"),2)) -> -38460.18 | H22: =IF(L22<>"",L22,T22) -> 邹桥派出所 | I22: =IF(M22<>"",M22,U22) -> 付应付款 | J22: =IF(N22<>"",N22,V22) -> 江西沐丰水箱 | K22: =IF(AND(B22="",D22="",E22="",F22=""),"",IF(C22="","✗ 没选账户",IF(AE22="","✗ 账户不在【基础资料】② 里",IF(NOT(ISNUMBER(B22)),"✗ 日期要填成日期（2026/5/1）",IF(AND(ISNUMBER(B22),B22<基础资料!$C$9),"✗ 日期早于建账日期（建账前的放【期初余额】）",IF(AND(N(E22)<>0,N(F22)<>0),"✗ 收入、支出只填一边",IF(R22=0,"✗ 没有金额",IF(I22="","✗ 认不出收支类别：在「改类别」选",IF(W22="？","✗ 收支类别不在【基础资料】③ 里",IF(OR(I22="管理人员工资",I22="折旧费"),"✗ 这一类是自动算的，流水里不能选（发工资选「工资」，买设备选「固定资产购置」）",IF(AND(OR(X22="材料费",X22="人工费",X22="分包费",X22="机械运输费",X22="其他直接费",X22="票据贴息",X22="应收账款"),H22=""),"✗ 这一笔要选项目（摘要里的项目没在【项目档案】的话先去加上）",IF(AND(H22<>"",COUNTIF(项目档案!$B$4:$B$63,H22)=0),"✗ 项目不在【项目档案】里",IF(AND(OR(IFERROR(INDEX(基础资料!$W$5:$W$64,MATCH(I22,基础资料!$S$5:$S$64,0))&"","")="人",IFERROR(INDEX(基础资料!$W$5:$W$64,MATCH(I22,基础资料!$S$5:$S$64,0))&"","")="单位"),J22=""),"✗ 这一笔要选是谁（改单位/人）",IF(AND(I22="付应付款",NOT(OR(Z22="材料供应商",Z22="分包",Z22="机械运输",Z22="其他"))),"✗ 付应付款要选材料商、分包或机械单位",IF(AND(I22="付应付款",Y22=0),"✗ 这家没有应付：先在【应付登记】登记（现买现付的选材料费等）",IF(AND(OR(I22="工资",I22="工资退回"),AA22=0),"✗ 工资要选管理人员或工人（临时工选「临时工工资」）",IF(AND(I22="账户互转",AD22=""),"✗ 账户互转要在「对方账户」选（借款、报销选那个人的个人户）",IF(AND(I22="账户互转",AF22=""),"✗ 对方账户不在【基础资料】② 里",IF(AND(I22="账户互转",AD22=C22),"✗ 对方账户不能是自己",IF(IF(I22="账户互转",COUNTIFS(资金流水!$C$6:$C$2005,AD22,资金流水!$AD$6:$AD$2005,C22,资金流水!$I$6:$I$2005,"账户互转",资金流水!$R$6:$R$2005,-R22)>0,FALSE),"✗ 对方账户那边也记了这笔互转（只记一边：清空其中一行的内容）",IF(AJ22>0,"⚠ 摘要里有两个项目：拆成几行，或在「改项目」选",IF(AND(I22<>"账户互转",O22<>""),"⚠ 填了对方账户但类别不是账户互转（对方账户不起作用）",IF(AND(J22<>"",Z22=""),"⚠ 单位/人没在【往来单位】登记",IF(AND(N(F22)<0,AH22="收"),"⚠ 这是收款，以后请记在收入栏",IF(N(E22)<0,"⚠ 收入填了负数，已按支出算",IF(N(F22)<0,"↩ 冲回（退款）",IF(AND(R22<0,I22<>"固定资产购置",I22<>"付应付款",ISNUMBER(B22),IFERROR(SUMPRODUCT(ISNUMBER(SEARCH(基础资料!$AJ$5:$AJ$34,D22))*(基础资料!$AJ$5:$AJ$34<>"")*((AN22-基础资料!$AK$5:$AK$34)<=30)*((AN22-基础资料!$AK$5:$AK$34)>=-30)),0)>0),"⚠ 像是在买【基础资料】⑥ 登记的车/设备：类别改成「固定资产购置」，不然成本算两遍",IF(AND(OR(I22="材料费",I22="分包费",I22="机械运输费",I22="其他直接费"),J22="",H22<>"",COUNTIFS(应付登记!$E$5:$E$1004,H22,应付登记!$G$5:$G$1004,-R22)>0),"⚠ 这个项目有同样金额的应付登记：是付那家的，改类别选「付应付款」、改单位选那家（不然成本算两遍）","√")))))))))))))))))))))))))))) -> √ | R22: =ROUND(N(E22)-N(F22),2) -> -22000 | S22: =IF(ISNUMBER(B22),YEAR(B22)*100+MONTH(B22),"") -> 202605 | T22: =IF(N(AK22)=0,"",INDEX(_辅助!$S$1:$S$240,AK22)) -> 邹桥派出所 | U22: =IF(OR(D22="",R22=0),"",IF(AND(Z22="临时工",R22<0),"临时工工资",IF(AG22="",IF(AA22=1,"工资",IF(Z22="临时工","临时工工资",IF(Z22="甲方/总包","工程款",IF(AND(OR(Z22="材料供应商",Z22="分包",Z22="机械运输"),Y22=1),"付应付款","")))),IF(AND(Y22=1,OR(Z22="材料供应商",Z22="分包",Z22="机械运输",Z22="其他"),OR(AG22="材料费",AG22="分包费",AG22="机械运输费",AG22="其他直接费",AG22="工资",AG22="临时工工资")),"付应付款",AG22)))) -> 付应付款 | V22: =IF(D22="","",IF(N(AM22)>0,IF(N(AM22)=0,"",INDEX(_辅助!$W$1:$W$900,AM22)),IF(N(AL22)=0,"",INDEX(_辅助!$W$1:$W$900,AL22)))) -> 江西沐丰水箱 | W22: =IF(I22="","",IFERROR(INDEX(基础资料!$V$5:$V$64,MATCH(I22,基础资料!$S$5:$S$64,0))&"","？")) -> 不进利润 | X22: =IF(R22=0,"",IF(OR(I22="",IFERROR(INDEX(基础资料!$U$5:$U$64,MATCH(I22,基础资料!$S$5:$S$64,0))&"","")=""),"待分类",IF(OR(I22="付应付款",IFERROR(INDEX(基础资料!$U$5:$U$64,MATCH(I22,基础资料!$S$5:$S$64,0))&"","")="应付款"),IF(Z22="材料供应商","应付材料款",IF(Z22="分包","应付分包款",IF(Z22="机械运输","应付机械运输费","应付其他款"))),IFERROR(INDEX(基础资料!$U$5:$U$64,MATCH(I22,基础资料!$S$5:$S$64,0))&"","")))) -> 应付材料款 | Y22: =IF(J22="",0,IF(COUNTIF(应付登记!$D$5:$D$1004,J22)+COUNTIF(期初余额!$P$5:$P$204,J22)>0,1,0)) -> 1 | Z22: =IF(J22="","",IFERROR(INDEX(往来单位!$C$4:$C$303,MATCH(J22,往来单位!$B$4:$B$303,0))&"","")) -> 材料供应商 | AA22: =IF(OR(Z22="管理人员",Z22="工人"),1,0) -> 0 | AB22: =IF(ISERROR(FIND("代",D22)),"",IFERROR(MID(D22,FIND("代",D22)+1,FIND("付",D22,FIND("代",D22))-FIND("代",D22)-1),"")) | AC22: =IF(I22<>"账户互转","",IF(J22<>"",IFERROR(INDEX(_辅助!$G$1:$G$40,MATCH(J22,_辅助!$F$1:$F$40,0)),IF(IFERROR(MATCH(1,INDEX(ISNUMBER(SEARCH(_辅助!$Z$1:$Z$40,D22))*(_辅助!$Z$1:$Z$40<>""),0),0),0)=0,"",INDEX(_辅助!$AA$1:$AA$40,IFERROR(MATCH(1,INDEX(ISNUMBER(SEARCH(_辅助!$Z$1:$Z$40,D22))*(_辅助!$Z$1:$Z$40<>""),0),0),0)))),IF(IFERROR(MATCH(1,INDEX(ISNUMBER(SEARCH(_辅助!$Z$1:$Z$40,D22))*(_辅助!$Z$1:$Z$40<>""),0),0),0)=0,"",INDEX(_辅助!$AA$1:$AA$40,IFERROR(MATCH(1,INDEX(ISNUMBER(SEARCH(_辅助!$Z$1:$Z$40,D22))*(_辅助!$Z$1:$Z$40<>""),0),0),0))))) | AD22: =IF(O22<>"",O22,AC22) | AE22: =IF(C22="","",IFERROR(INDEX(基础资料!$H$5:$H$24,MATCH(C22,基础资料!$G$5:$G$24,0))&"","")) -> 银行 | AF22: =IF(AD22="","",IFERROR(INDEX(基础资料!$H$5:$H$24,MATCH(AD22,基础资料!$G$5:$G$24,0))&"","")) | AG22: =IF(OR(D22="",R22=0),"",IFERROR(INDEX(基础资料!$AC$5:$AC$164,IF(IF(F22<>"","支","收")="收",MATCH(1,INDEX(ISNUMBER(SEARCH(_辅助!$AB$1:$AB$160,D22))*(_辅助!$AB$1:$AB$160<>""),0),0),MATCH(1,INDEX(ISNUMBER(SEARCH(_辅助!$AC$1:$AC$160,D22))*(_辅助!$AC$1:$AC$160<>""),0),0)))&"","")) -> 材料费 | AH22: =IF(R22=0,"",IF(OR(IFERROR(INDEX(基础资料!$T$5:$T$64,MATCH(I22,基础资料!$S$5:$S$64,0))&"","")="收",IFERROR(INDEX(基础资料!$T$5:$T$64,MATCH(I22,基础资料!$S$5:$S$64,0))&"","")="支"),IFERROR(INDEX(基础资料!$T$5:$T$64,MATCH(I22,基础资料!$S$5:$S$64,0))&"",""),IF(R22>0,"收","支"))) -> 支 | AI22: =IF(N(AK22)=0,"",INDEX(_辅助!$R$1:$R$240,AK22)) -> 邹桥派出所 | AJ22: =IF(OR(AI22="",L22<>""),0,SUMPRODUCT(ISNUMBER(SEARCH(_辅助!$R$1:$R$240,D22))*(_辅助!$R$1:$R$240<>"")*(1-ISNUMBER(SEARCH(_辅助!$R$1:$R$240,AI22)))*(_辅助!$S$1:$S$240<>T22))) -> 0 | AK22: =IF(D22="",0,IFERROR(MATCH(1,INDEX(ISNUMBER(SEARCH(_辅助!$R$1:$R$240,D22))*(_辅助!$R$1:$R$240<>""),0),0),0)) -> 7 | AL22: =IF(D22="",0,IFERROR(MATCH(1,INDEX(ISNUMBER(SEARCH(_辅助!$V$1:$V$900,D22))*(_辅助!$V$1:$V$900<>""),0),0),0)) -> 90 | AM22: =IF(AB22="",0,IFERROR(MATCH(1,INDEX(ISNUMBER(SEARCH(_辅助!$V$1:$V$900,AB22))*(_辅助!$V$1:$V$900<>""),0),0),0)) -> 0 | AN22: =IF(ISNUMBER(B22),INT(B22),0) -> 46158 | AO22: =IF(AND(X22="应收账款",R22>0,AN22>0,H22<>""),H22&"|"&COUNTIFS(资金流水!$H$6:$H$2005,H22,资金流水!$X$6:$X$2005,"应收账款",资金流水!$R$6:$R$2005,">0",资金流水!$AN$6:$AN$2005,">0",资金流水!$AN$6:$AN$2005,"<="&AN22),"") | AP22: =IF(AND(J22<>"",R22<0,AN22>0),J22&"|"&COUNTIFS(资金流水!$J$6:$J$2005,J22,资金流水!$R$6:$R$2005,"<0",资金流水!$AN$6:$AN$2005,">0",资金流水!$AN$6:$AN$2005,"<="&AN22),"") -> 江西沐丰水箱|1 | AQ22: =IF(AND(X22="其他应收款",AN22>0,J22<>""),J22&"|"&(COUNTIFS(资金流水!$J$6:$J$2005,J22,资金流水!$X$6:$X$2005,"其他应收款",资金流水!$AN$6:$AN$2005,">0",资金流水!$AN$6:$AN$2005,"<"&AN22)+COUNTIFS($J$6:J22,J22,$X$6:X22,"其他应收款",$AN$6:AN22,AN22)),"")
A23: =IF(AND(B23="",D23="",E23="",F23=""),"",ROW()-5) -> 18 | B23: 46161 | C23: 九江银行 | D23: 收到股东借款-聂辉 | E23: 90000 | G23: =IF(C23="","",ROUND(IFERROR(INDEX(基础资料!$K$5:$K$24,MATCH(C23,基础资料!$G$5:$G$24,0)),0)+SUMIFS($R$6:R23,$C$6:C23,C23)-SUMIFS($R$6:R23,$AD$6:AD23,C23,$X$6:X23,"账户互转"),2)) -> 51539.82 | H23: =IF(L23<>"",L23,T23) | I23: =IF(M23<>"",M23,U23) -> 账户互转 | J23: =IF(N23<>"",N23,V23) -> 聂辉 | K23: =IF(AND(B23="",D23="",E23="",F23=""),"",IF(C23="","✗ 没选账户",IF(AE23="","✗ 账户不在【基础资料】② 里",IF(NOT(ISNUMBER(B23)),"✗ 日期要填成日期（2026/5/1）",IF(AND(ISNUMBER(B23),B23<基础资料!$C$9),"✗ 日期早于建账日期（建账前的放【期初余额】）",IF(AND(N(E23)<>0,N(F23)<>0),"✗ 收入、支出只填一边",IF(R23=0,"✗ 没有金额",IF(I23="","✗ 认不出收支类别：在「改类别」选",IF(W23="？","✗ 收支类别不在【基础资料】③ 里",IF(OR(I23="管理人员工资",I23="折旧费"),"✗ 这一类是自动算的，流水里不能选（发工资选「工资」，买设备选「固定资产购置」）",IF(AND(OR(X23="材料费",X23="人工费",X23="分包费",X23="机械运输费",X23="其他直接费",X23="票据贴息",X23="应收账款"),H23=""),"✗ 这一笔要选项目（摘要里的项目没在【项目档案】的话先去加上）",IF(AND(H23<>"",COUNTIF(项目档案!$B$4:$B$63,H23)=0),"✗ 项目不在【项目档案】里",IF(AND(OR(IFERROR(INDEX(基础资料!$W$5:$W$64,MATCH(I23,基础资料!$S$5:$S$64,0))&"","")="人",IFERROR(INDEX(基础资料!$W$5:$W$64,MATCH(I23,基础资料!$S$5:$S$64,0))&"","")="单位"),J23=""),"✗ 这一笔要选是谁（改单位/人）",IF(AND(I23="付应付款",NOT(OR(Z23="材料供应商",Z23="分包",Z23="机械运输",Z23="其他"))),"✗ 付应付款要选材料商、分包或机械单位",IF(AND(I23="付应付款",Y23=0),"✗ 这家没有应付：先在【应付登记】登记（现买现付的选材料费等）",IF(AND(OR(I23="工资",I23="工资退回"),AA23=0),"✗ 工资要选管理人员或工人（临时工选「临时工工资」）",IF(AND(I23="账户互转",AD23=""),"✗ 账户互转要在「对方账户」选（借款、报销选那个人的个人户）",IF(AND(I23="账户互转",AF23=""),"✗ 对方账户不在【基础资料】② 里",IF(AND(I23="账户互转",AD23=C23),"✗ 对方账户不能是自己",IF(IF(I23="账户互转",COUNTIFS(资金流水!$C$6:$C$2005,AD23,资金流水!$AD$6:$AD$2005,C23,资金流水!$I$6:$I$2005,"账户互转",资金流水!$R$6:$R$2005,-R23)>0,FALSE),"✗ 对方账户那边也记了这笔互转（只记一边：清空其中一行的内容）",IF(AJ23>0,"⚠ 摘要里有两个项目：拆成几行，或在「改项目」选",IF(AND(I23<>"账户互转",O23<>""),"⚠ 填了对方账户但类别不是账户互转（对方账户不起作用）",IF(AND(J23<>"",Z23=""),"⚠ 单位/人没在【往来单位】登记",IF(AND(N(F23)<0,AH23="收"),"⚠ 这是收款，以后请记在收入栏",IF(N(E23)<0,"⚠ 收入填了负数，已按支出算",IF(N(F23)<0,"↩ 冲回（退款）",IF(AND(R23<0,I23<>"固定资产购置",I23<>"付应付款",ISNUMBER(B23),IFERROR(SUMPRODUCT(ISNUMBER(SEARCH(基础资料!$AJ$5:$AJ$34,D23))*(基础资料!$AJ$5:$AJ$34<>"")*((AN23-基础资料!$AK$5:$AK$34)<=30)*((AN23-基础资料!$AK$5:$AK$34)>=-30)),0)>0),"⚠ 像是在买【基础资料】⑥ 登记的车/设备：类别改成「固定资产购置」，不然成本算两遍",IF(AND(OR(I23="材料费",I23="分包费",I23="机械运输费",I23="其他直接费"),J23="",H23<>"",COUNTIFS(应付登记!$E$5:$E$1004,H23,应付登记!$G$5:$G$1004,-R23)>0),"⚠ 这个项目有同样金额的应付登记：是付那家的，改类别选「付应付款」、改单位选那家（不然成本算两遍）","√")))))))))))))))))))))))))))) -> √ | R23: =ROUND(N(E23)-N(F23),2) -> 90000 | S23: =IF(ISNUMBER(B23),YEAR(B23)*100+MONTH(B23),"") -> 202605 | T23: =IF(N(AK23)=0,"",INDEX(_辅助!$S$1:$S$240,AK23)) | U23: =IF(OR(D23="",R23=0),"",IF(AND(Z23="临时工",R23<0),"临时工工资",IF(AG23="",IF(AA23=1,"工资",IF(Z23="临时工","临时工工资",IF(Z23="甲方/总包","工程款",IF(AND(OR(Z23="材料供应商",Z23="分包",Z23="机械运输"),Y23=1),"付应付款","")))),IF(AND(Y23=1,OR(Z23="材料供应商",Z23="分包",Z23="机械运输",Z23="其他"),OR(AG23="材料费",AG23="分包费",AG23="机械运输费",AG23="其他直接费",AG23="工资",AG23="临时工工资")),"付应付款",AG23)))) -> 账户互转 | V23: =IF(D23="","",IF(N(AM23)>0,IF(N(AM23)=0,"",INDEX(_辅助!$W$1:$W$900,AM23)),IF(N(AL23)=0,"",INDEX(_辅助!$W$1:$W$900,AL23)))) -> 聂辉 | W23: =IF(I23="","",IFERROR(INDEX(基础资料!$V$5:$V$64,MATCH(I23,基础资料!$S$5:$S$64,0))&"","？")) -> 不进利润 | X23: =IF(R23=0,"",IF(OR(I23="",IFERROR(INDEX(基础资料!$U$5:$U$64,MATCH(I23,基础资料!$S$5:$S$64,0))&"","")=""),"待分类",IF(OR(I23="付应付款",IFERROR(INDEX(基础资料!$U$5:$U$64,MATCH(I23,基础资料!$S$5:$S$64,0))&"","")="应付款"),IF(Z23="材料供应商","应付材料款",IF(Z23="分包","应付分包款",IF(Z23="机械运输","应付机械运输费","应付其他款"))),IFERROR(INDEX(基础资料!$U$5:$U$64,MATCH(I23,基础资料!$S$5:$S$64,0))&"","")))) -> 账户互转 | Y23: =IF(J23="",0,IF(COUNTIF(应付登记!$D$5:$D$1004,J23)+COUNTIF(期初余额!$P$5:$P$204,J23)>0,1,0)) -> 0 | Z23: =IF(J23="","",IFERROR(INDEX(往来单位!$C$4:$C$303,MATCH(J23,往来单位!$B$4:$B$303,0))&"","")) -> 管理人员 | AA23: =IF(OR(Z23="管理人员",Z23="工人"),1,0) -> 1 | AB23: =IF(ISERROR(FIND("代",D23)),"",IFERROR(MID(D23,FIND("代",D23)+1,FIND("付",D23,FIND("代",D23))-FIND("代",D23)-1),"")) | AC23: =IF(I23<>"账户互转","",IF(J23<>"",IFERROR(INDEX(_辅助!$G$1:$G$40,MATCH(J23,_辅助!$F$1:$F$40,0)),IF(IFERROR(MATCH(1,INDEX(ISNUMBER(SEARCH(_辅助!$Z$1:$Z$40,D23))*(_辅助!$Z$1:$Z$40<>""),0),0),0)=0,"",INDEX(_辅助!$AA$1:$AA$40,IFERROR(MATCH(1,INDEX(ISNUMBER(SEARCH(_辅助!$Z$1:$Z$40,D23))*(_辅助!$Z$1:$Z$40<>""),0),0),0)))),IF(IFERROR(MATCH(1,INDEX(ISNUMBER(SEARCH(_辅助!$Z$1:$Z$40,D23))*(_辅助!$Z$1:$Z$40<>""),0),0),0)=0,"",INDEX(_辅助!$AA$1:$AA$40,IFERROR(MATCH(1,INDEX(ISNUMBER(SEARCH(_辅助!$Z$1:$Z$40,D23))*(_辅助!$Z$1:$Z$40<>""),0),0),0))))) -> 聂辉个人户 | AD23: =IF(O23<>"",O23,AC23) -> 聂辉个人户 | AE23: =IF(C23="","",IFERROR(INDEX(基础资料!$H$5:$H$24,MATCH(C23,基础资料!$G$5:$G$24,0))&"","")) -> 银行 | AF23: =IF(AD23="","",IFERROR(INDEX(基础资料!$H$5:$H$24,MATCH(AD23,基础资料!$G$5:$G$24,0))&"","")) -> 个人户 | AG23: =IF(OR(D23="",R23=0),"",IFERROR(INDEX(基础资料!$AC$5:$AC$164,IF(IF(F23<>"","支","收")="收",MATCH(1,INDEX(ISNUMBER(SEARCH(_辅助!$AB$1:$AB$160,D23))*(_辅助!$AB$1:$AB$160<>""),0),0),MATCH(1,INDEX(ISNUMBER(SEARCH(_辅助!$AC$1:$AC$160,D23))*(_辅助!$AC$1:$AC$160<>""),0),0)))&"","")) -> 账户互转 | AH23: =IF(R23=0,"",IF(OR(IFERROR(INDEX(基础资料!$T$5:$T$64,MATCH(I23,基础资料!$S$5:$S$64,0))&"","")="收",IFERROR(INDEX(基础资料!$T$5:$T$64,MATCH(I23,基础资料!$S$5:$S$64,0))&"","")="支"),IFERROR(INDEX(基础资料!$T$5:$T$64,MATCH(I23,基础资料!$S$5:$S$64,0))&"",""),IF(R23>0,"收","支"))) -> 收 | AI23: =IF(N(AK23)=0,"",INDEX(_辅助!$R$1:$R$240,AK23)) | AJ23: =IF(OR(AI23="",L23<>""),0,SUMPRODUCT(ISNUMBER(SEARCH(_辅助!$R$1:$R$240,D23))*(_辅助!$R$1:$R$240<>"")*(1-ISNUMBER(SEARCH(_辅助!$R$1:$R$240,AI23)))*(_辅助!$S$1:$S$240<>T23))) -> 0 | AK23: =IF(D23="",0,IFERROR(MATCH(1,INDEX(ISNUMBER(SEARCH(_辅助!$R$1:$R$240,D23))*(_辅助!$R$1:$R$240<>""),0),0),0)) -> 0 | AL23: =IF(D23="",0,IFERROR(MATCH(1,INDEX(ISNUMBER(SEARCH(_辅助!$V$1:$V$900,D23))*(_辅助!$V$1:$V$900<>""),0),0),0)) -> 111 | AM23: =IF(AB23="",0,IFERROR(MATCH(1,INDEX(ISNUMBER(SEARCH(_辅助!$V$1:$V$900,AB23))*(_辅助!$V$1:$V$900<>""),0),0),0)) -> 0 | AN23: =IF(ISNUMBER(B23),INT(B23),0) -> 46161 | AO23: =IF(AND(X23="应收账款",R23>0,AN23>0,H23<>""),H23&"|"&COUNTIFS(资金流水!$H$6:$H$2005,H23,资金流水!$X$6:$X$2005,"应收账款",资金流水!$R$6:$R$2005,">0",资金流水!$AN$6:$AN$2005,">0",资金流水!$AN$6:$AN$2005,"<="&AN23),"") | AP23: =IF(AND(J23<>"",R23<0,AN23>0),J23&"|"&COUNTIFS(资金流水!$J$6:$J$2005,J23,资金流水!$R$6:$R$2005,"<0",资金流水!$AN$6:$AN$2005,">0",资金流水!$AN$6:$AN$2005,"<="&AN23),"") | AQ23: =IF(AND(X23="其他应收款",AN23>0,J23<>""),J23&"|"&(COUNTIFS(资金流水!$J$6:$J$2005,J23,资金流水!$X$6:$X$2005,"其他应收款",资金流水!$AN$6:$AN$2005,">0",资金流水!$AN$6:$AN$2005,"<"&AN23)+COUNTIFS($J$6:J23,J23,$X$6:X23,"其他应收款",$AN$6:AN23,AN23)),"")
A24: =IF(AND(B24="",D24="",E24="",F24=""),"",ROW()-5) -> 19 | B24: 46161 | C24: 九江银行 | D24: 支付食品厂投标保证金 | F24: 90000 | G24: =IF(C24="","",ROUND(IFERROR(INDEX(基础资料!$K$5:$K$24,MATCH(C24,基础资料!$G$5:$G$24,0)),0)+SUMIFS($R$6:R24,$C$6:C24,C24)-SUMIFS($R$6:R24,$AD$6:AD24,C24,$X$6:X24,"账户互转"),2)) -> -38460.18 | H24: =IF(L24<>"",L24,T24) | I24: =IF(M24<>"",M24,U24) -> 保证金押金 | J24: =IF(N24<>"",N24,V24) | K24: =IF(AND(B24="",D24="",E24="",F24=""),"",IF(C24="","✗ 没选账户",IF(AE24="","✗ 账户不在【基础资料】② 里",IF(NOT(ISNUMBER(B24)),"✗ 日期要填成日期（2026/5/1）",IF(AND(ISNUMBER(B24),B24<基础资料!$C$9),"✗ 日期早于建账日期（建账前的放【期初余额】）",IF(AND(N(E24)<>0,N(F24)<>0),"✗ 收入、支出只填一边",IF(R24=0,"✗ 没有金额",IF(I24="","✗ 认不出收支类别：在「改类别」选",IF(W24="？","✗ 收支类别不在【基础资料】③ 里",IF(OR(I24="管理人员工资",I24="折旧费"),"✗ 这一类是自动算的，流水里不能选（发工资选「工资」，买设备选「固定资产购置」）",IF(AND(OR(X24="材料费",X24="人工费",X24="分包费",X24="机械运输费",X24="其他直接费",X24="票据贴息",X24="应收账款"),H24=""),"✗ 这一笔要选项目（摘要里的项目没在【项目档案】的话先去加上）",IF(AND(H24<>"",COUNTIF(项目档案!$B$4:$B$63,H24)=0),"✗ 项目不在【项目档案】里",IF(AND(OR(IFERROR(INDEX(基础资料!$W$5:$W$64,MATCH(I24,基础资料!$S$5:$S$64,0))&"","")="人",IFERROR(INDEX(基础资料!$W$5:$W$64,MATCH(I24,基础资料!$S$5:$S$64,0))&"","")="单位"),J24=""),"✗ 这一笔要选是谁（改单位/人）",IF(AND(I24="付应付款",NOT(OR(Z24="材料供应商",Z24="分包",Z24="机械运输",Z24="其他"))),"✗ 付应付款要选材料商、分包或机械单位",IF(AND(I24="付应付款",Y24=0),"✗ 这家没有应付：先在【应付登记】登记（现买现付的选材料费等）",IF(AND(OR(I24="工资",I24="工资退回"),AA24=0),"✗ 工资要选管理人员或工人（临时工选「临时工工资」）",IF(AND(I24="账户互转",AD24=""),"✗ 账户互转要在「对方账户」选（借款、报销选那个人的个人户）",IF(AND(I24="账户互转",AF24=""),"✗ 对方账户不在【基础资料】② 里",IF(AND(I24="账户互转",AD24=C24),"✗ 对方账户不能是自己",IF(IF(I24="账户互转",COUNTIFS(资金流水!$C$6:$C$2005,AD24,资金流水!$AD$6:$AD$2005,C24,资金流水!$I$6:$I$2005,"账户互转",资金流水!$R$6:$R$2005,-R24)>0,FALSE),"✗ 对方账户那边也记了这笔互转（只记一边：清空其中一行的内容）",IF(AJ24>0,"⚠ 摘要里有两个项目：拆成几行，或在「改项目」选",IF(AND(I24<>"账户互转",O24<>""),"⚠ 填了对方账户但类别不是账户互转（对方账户不起作用）",IF(AND(J24<>"",Z24=""),"⚠ 单位/人没在【往来单位】登记",IF(AND(N(F24)<0,AH24="收"),"⚠ 这是收款，以后请记在收入栏",IF(N(E24)<0,"⚠ 收入填了负数，已按支出算",IF(N(F24)<0,"↩ 冲回（退款）",IF(AND(R24<0,I24<>"固定资产购置",I24<>"付应付款",ISNUMBER(B24),IFERROR(SUMPRODUCT(ISNUMBER(SEARCH(基础资料!$AJ$5:$AJ$34,D24))*(基础资料!$AJ$5:$AJ$34<>"")*((AN24-基础资料!$AK$5:$AK$34)<=30)*((AN24-基础资料!$AK$5:$AK$34)>=-30)),0)>0),"⚠ 像是在买【基础资料】⑥ 登记的车/设备：类别改成「固定资产购置」，不然成本算两遍",IF(AND(OR(I24="材料费",I24="分包费",I24="机械运输费",I24="其他直接费"),J24="",H24<>"",COUNTIFS(应付登记!$E$5:$E$1004,H24,应付登记!$G$5:$G$1004,-R24)>0),"⚠ 这个项目有同样金额的应付登记：是付那家的，改类别选「付应付款」、改单位选那家（不然成本算两遍）","√")))))))))))))))))))))))))))) -> √ | R24: =ROUND(N(E24)-N(F24),2) -> -90000 | S24: =IF(ISNUMBER(B24),YEAR(B24)*100+MONTH(B24),"") -> 202605 | T24: =IF(N(AK24)=0,"",INDEX(_辅助!$S$1:$S$240,AK24)) | U24: =IF(OR(D24="",R24=0),"",IF(AND(Z24="临时工",R24<0),"临时工工资",IF(AG24="",IF(AA24=1,"工资",IF(Z24="临时工","临时工工资",IF(Z24="甲方/总包","工程款",IF(AND(OR(Z24="材料供应商",Z24="分包",Z24="机械运输"),Y24=1),"付应付款","")))),IF(AND(Y24=1,OR(Z24="材料供应商",Z24="分包",Z24="机械运输",Z24="其他"),OR(AG24="材料费",AG24="分包费",AG24="机械运输费",AG24="其他直接费",AG24="工资",AG24="临时工工资")),"付应付款",AG24)))) -> 保证金押金 | V24: =IF(D24="","",IF(N(AM24)>0,IF(N(AM24)=0,"",INDEX(_辅助!$W$1:$W$900,AM24)),IF(N(AL24)=0,"",INDEX(_辅助!$W$1:$W$900,AL24)))) | W24: =IF(I24="","",IFERROR(INDEX(基础资料!$V$5:$V$64,MATCH(I24,基础资料!$S$5:$S$64,0))&"","？")) -> 不进利润 | X24: =IF(R24=0,"",IF(OR(I24="",IFERROR(INDEX(基础资料!$U$5:$U$64,MATCH(I24,基础资料!$S$5:$S$64,0))&"","")=""),"待分类",IF(OR(I24="付应付款",IFERROR(INDEX(基础资料!$U$5:$U$64,MATCH(I24,基础资料!$S$5:$S$64,0))&"","")="应付款"),IF(Z24="材料供应商","应付材料款",IF(Z24="分包","应付分包款",IF(Z24="机械运输","应付机械运输费","应付其他款"))),IFERROR(INDEX(基础资料!$U$5:$U$64,MATCH(I24,基础资料!$S$5:$S$64,0))&"","")))) -> 其他应收款 | Y24: =IF(J24="",0,IF(COUNTIF(应付登记!$D$5:$D$1004,J24)+COUNTIF(期初余额!$P$5:$P$204,J24)>0,1,0)) -> 0 | Z24: =IF(J24="","",IFERROR(INDEX(往来单位!$C$4:$C$303,MATCH(J24,往来单位!$B$4:$B$303,0))&"","")) | AA24: =IF(OR(Z24="管理人员",Z24="工人"),1,0) -> 0 | AB24: =IF(ISERROR(FIND("代",D24)),"",IFERROR(MID(D24,FIND("代",D24)+1,FIND("付",D24,FIND("代",D24))-FIND("代",D24)-1),"")) | AC24: =IF(I24<>"账户互转","",IF(J24<>"",IFERROR(INDEX(_辅助!$G$1:$G$40,MATCH(J24,_辅助!$F$1:$F$40,0)),IF(IFERROR(MATCH(1,INDEX(ISNUMBER(SEARCH(_辅助!$Z$1:$Z$40,D24))*(_辅助!$Z$1:$Z$40<>""),0),0),0)=0,"",INDEX(_辅助!$AA$1:$AA$40,IFERROR(MATCH(1,INDEX(ISNUMBER(SEARCH(_辅助!$Z$1:$Z$40,D24))*(_辅助!$Z$1:$Z$40<>""),0),0),0)))),IF(IFERROR(MATCH(1,INDEX(ISNUMBER(SEARCH(_辅助!$Z$1:$Z$40,D24))*(_辅助!$Z$1:$Z$40<>""),0),0),0)=0,"",INDEX(_辅助!$AA$1:$AA$40,IFERROR(MATCH(1,INDEX(ISNUMBER(SEARCH(_辅助!$Z$1:$Z$40,D24))*(_辅助!$Z$1:$Z$40<>""),0),0),0))))) | AD24: =IF(O24<>"",O24,AC24) | AE24: =IF(C24="","",IFERROR(INDEX(基础资料!$H$5:$H$24,MATCH(C24,基础资料!$G$5:$G$24,0))&"","")) -> 银行 | AF24: =IF(AD24="","",IFERROR(INDEX(基础资料!$H$5:$H$24,MATCH(AD24,基础资料!$G$5:$G$24,0))&"","")) | AG24: =IF(OR(D24="",R24=0),"",IFERROR(INDEX(基础资料!$AC$5:$AC$164,IF(IF(F24<>"","支","收")="收",MATCH(1,INDEX(ISNUMBER(SEARCH(_辅助!$AB$1:$AB$160,D24))*(_辅助!$AB$1:$AB$160<>""),0),0),MATCH(1,INDEX(ISNUMBER(SEARCH(_辅助!$AC$1:$AC$160,D24))*(_辅助!$AC$1:$AC$160<>""),0),0)))&"","")) -> 保证金押金 | AH24: =IF(R24=0,"",IF(OR(IFERROR(INDEX(基础资料!$T$5:$T$64,MATCH(I24,基础资料!$S$5:$S$64,0))&"","")="收",IFERROR(INDEX(基础资料!$T$5:$T$64,MATCH(I24,基础资料!$S$5:$S$64,0))&"","")="支"),IFERROR(INDEX(基础资料!$T$5:$T$64,MATCH(I24,基础资料!$S$5:$S$64,0))&"",""),IF(R24>0,"收","支"))) -> 支 | AI24: =IF(N(AK24)=0,"",INDEX(_辅助!$R$1:$R$240,AK24)) | AJ24: =IF(OR(AI24="",L24<>""),0,SUMPRODUCT(ISNUMBER(SEARCH(_辅助!$R$1:$R$240,D24))*(_辅助!$R$1:$R$240<>"")*(1-ISNUMBER(SEARCH(_辅助!$R$1:$R$240,AI24)))*(_辅助!$S$1:$S$240<>T24))) -> 0 | AK24: =IF(D24="",0,IFERROR(MATCH(1,INDEX(ISNUMBER(SEARCH(_辅助!$R$1:$R$240,D24))*(_辅助!$R$1:$R$240<>""),0),0),0)) -> 0 | AL24: =IF(D24="",0,IFERROR(MATCH(1,INDEX(ISNUMBER(SEARCH(_辅助!$V$1:$V$900,D24))*(_辅助!$V$1:$V$900<>""),0),0),0)) -> 0 | AM24: =IF(AB24="",0,IFERROR(MATCH(1,INDEX(ISNUMBER(SEARCH(_辅助!$V$1:$V$900,AB24))*(_辅助!$V$1:$V$900<>""),0),0),0)) -> 0 | AN24: =IF(ISNUMBER(B24),INT(B24),0) -> 46161 | AO24: =IF(AND(X24="应收账款",R24>0,AN24>0,H24<>""),H24&"|"&COUNTIFS(资金流水!$H$6:$H$2005,H24,资金流水!$X$6:$X$2005,"应收账款",资金流水!$R$6:$R$2005,">0",资金流水!$AN$6:$AN$2005,">0",资金流水!$AN$6:$AN$2005,"<="&AN24),"") | AP24: =IF(AND(J24<>"",R24<0,AN24>0),J24&"|"&COUNTIFS(资金流水!$J$6:$J$2005,J24,资金流水!$R$6:$R$2005,"<0",资金流水!$AN$6:$AN$2005,">0",资金流水!$AN$6:$AN$2005,"<="&AN24),"") | AQ24: =IF(AND(X24="其他应收款",AN24>0,J24<>""),J24&"|"&(COUNTIFS(资金流水!$J$6:$J$2005,J24,资金流水!$X$6:$X$2005,"其他应收款",资金流水!$AN$6:$AN$2005,">0",资金流水!$AN$6:$AN$2005,"<"&AN24)+COUNTIFS($J$6:J24,J24,$X$6:X24,"其他应收款",$AN$6:AN24,AN24)),"")
A25: =IF(AND(B25="",D25="",E25="",F25=""),"",ROW()-5) -> 20 | B25: 46163 | C25: 九江银行 | D25: 收江西赣粤高速公路工程款 | E25: 14502.87 | G25: =IF(C25="","",ROUND(IFERROR(INDEX(基础资料!$K$5:$K$24,MATCH(C25,基础资料!$G$5:$G$24,0)),0)+SUMIFS($R$6:R25,$C$6:C25,C25)-SUMIFS($R$6:R25,$AD$6:AD25,C25,$X$6:X25,"账户互转"),2)) -> -23957.31 | H25: =IF(L25<>"",L25,T25) -> 赣粤高速 | I25: =IF(M25<>"",M25,U25) -> 工程款 | J25: =IF(N25<>"",N25,V25) -> 江西赣粤高速 | K25: =IF(AND(B25="",D25="",E25="",F25=""),"",IF(C25="","✗ 没选账户",IF(AE25="","✗ 账户不在【基础资料】② 里",IF(NOT(ISNUMBER(B25)),"✗ 日期要填成日期（2026/5/1）",IF(AND(ISNUMBER(B25),B25<基础资料!$C$9),"✗ 日期早于建账日期（建账前的放【期初余额】）",IF(AND(N(E25)<>0,N(F25)<>0),"✗ 收入、支出只填一边",IF(R25=0,"✗ 没有金额",IF(I25="","✗ 认不出收支类别：在「改类别」选",IF(W25="？","✗ 收支类别不在【基础资料】③ 里",IF(OR(I25="管理人员工资",I25="折旧费"),"✗ 这一类是自动算的，流水里不能选（发工资选「工资」，买设备选「固定资产购置」）",IF(AND(OR(X25="材料费",X25="人工费",X25="分包费",X25="机械运输费",X25="其他直接费",X25="票据贴息",X25="应收账款"),H25=""),"✗ 这一笔要选项目（摘要里的项目没在【项目档案】的话先去加上）",IF(AND(H25<>"",COUNTIF(项目档案!$B$4:$B$63,H25)=0),"✗ 项目不在【项目档案】里",IF(AND(OR(IFERROR(INDEX(基础资料!$W$5:$W$64,MATCH(I25,基础资料!$S$5:$S$64,0))&"","")="人",IFERROR(INDEX(基础资料!$W$5:$W$64,MATCH(I25,基础资料!$S$5:$S$64,0))&"","")="单位"),J25=""),"✗ 这一笔要选是谁（改单位/人）",IF(AND(I25="付应付款",NOT(OR(Z25="材料供应商",Z25="分包",Z25="机械运输",Z25="其他"))),"✗ 付应付款要选材料商、分包或机械单位",IF(AND(I25="付应付款",Y25=0),"✗ 这家没有应付：先在【应付登记】登记（现买现付的选材料费等）",IF(AND(OR(I25="工资",I25="工资退回"),AA25=0),"✗ 工资要选管理人员或工人（临时工选「临时工工资」）",IF(AND(I25="账户互转",AD25=""),"✗ 账户互转要在「对方账户」选（借款、报销选那个人的个人户）",IF(AND(I25="账户互转",AF25=""),"✗ 对方账户不在【基础资料】② 里",IF(AND(I25="账户互转",AD25=C25),"✗ 对方账户不能是自己",IF(IF(I25="账户互转",COUNTIFS(资金流水!$C$6:$C$2005,AD25,资金流水!$AD$6:$AD$2005,C25,资金流水!$I$6:$I$2005,"账户互转",资金流水!$R$6:$R$2005,-R25)>0,FALSE),"✗ 对方账户那边也记了这笔互转（只记一边：清空其中一行的内容）",IF(AJ25>0,"⚠ 摘要里有两个项目：拆成几行，或在「改项目」选",IF(AND(I25<>"账户互转",O25<>""),"⚠ 填了对方账户但类别不是账户互转（对方账户不起作用）",IF(AND(J25<>"",Z25=""),"⚠ 单位/人没在【往来单位】登记",IF(AND(N(F25)<0,AH25="收"),"⚠ 这是收款，以后请记在收入栏",IF(N(E25)<0,"⚠ 收入填了负数，已按支出算",IF(N(F25)<0,"↩ 冲回（退款）",IF(AND(R25<0,I25<>"固定资产购置",I25<>"付应付款",ISNUMBER(B25),IFERROR(SUMPRODUCT(ISNUMBER(SEARCH(基础资料!$AJ$5:$AJ$34,D25))*(基础资料!$AJ$5:$AJ$34<>"")*((AN25-基础资料!$AK$5:$AK$34)<=30)*((AN25-基础资料!$AK$5:$AK$34)>=-30)),0)>0),"⚠ 像是在买【基础资料】⑥ 登记的车/设备：类别改成「固定资产购置」，不然成本算两遍",IF(AND(OR(I25="材料费",I25="分包费",I25="机械运输费",I25="其他直接费"),J25="",H25<>"",COUNTIFS(应付登记!$E$5:$E$1004,H25,应付登记!$G$5:$G$1004,-R25)>0),"⚠ 这个项目有同样金额的应付登记：是付那家的，改类别选「付应付款」、改单位选那家（不然成本算两遍）","√")))))))))))))))))))))))))))) -> √ | R25: =ROUND(N(E25)-N(F25),2) -> 14502.87 | S25: =IF(ISNUMBER(B25),YEAR(B25)*100+MONTH(B25),"") -> 202605 | T25: =IF(N(AK25)=0,"",INDEX(_辅助!$S$1:$S$240,AK25)) -> 赣粤高速 | U25: =IF(OR(D25="",R25=0),"",IF(AND(Z25="临时工",R25<0),"临时工工资",IF(AG25="",IF(AA25=1,"工资",IF(Z25="临时工","临时工工资",IF(Z25="甲方/总包","工程款",IF(AND(OR(Z25="材料供应商",Z25="分包",Z25="机械运输"),Y25=1),"付应付款","")))),IF(AND(Y25=1,OR(Z25="材料供应商",Z25="分包",Z25="机械运输",Z25="其他"),OR(AG25="材料费",AG25="分包费",AG25="机械运输费",AG25="其他直接费",AG25="工资",AG25="临时工工资")),"付应付款",AG25)))) -> 工程款 | V25: =IF(D25="","",IF(N(AM25)>0,IF(N(AM25)=0,"",INDEX(_辅助!$W$1:$W$900,AM25)),IF(N(AL25)=0,"",INDEX(_辅助!$W$1:$W$900,AL25)))) -> 江西赣粤高速 | W25: =IF(I25="","",IFERROR(INDEX(基础资料!$V$5:$V$64,MATCH(I25,基础资料!$S$5:$S$64,0))&"","？")) -> 不进利润 | X25: =IF(R25=0,"",IF(OR(I25="",IFERROR(INDEX(基础资料!$U$5:$U$64,MATCH(I25,基础资料!$S$5:$S$64,0))&"","")=""),"待分类",IF(OR(I25="付应付款",IFERROR(INDEX(基础资料!$U$5:$U$64,MATCH(I25,基础资料!$S$5:$S$64,0))&"","")="应付款"),IF(Z25="材料供应商","应付材料款",IF(Z25="分包","应付分包款",IF(Z25="机械运输","应付机械运输费","应付其他款"))),IFERROR(INDEX(基础资料!$U$5:$U$64,MATCH(I25,基础资料!$S$5:$S$64,0))&"","")))) -> 应收账款 | Y25: =IF(J25="",0,IF(COUNTIF(应付登记!$D$5:$D$1004,J25)+COUNTIF(期初余额!$P$5:$P$204,J25)>0,1,0)) -> 0 | Z25: =IF(J25="","",IFERROR(INDEX(往来单位!$C$4:$C$303,MATCH(J25,往来单位!$B$4:$B$303,0))&"","")) -> 甲方/总包 | AA25: =IF(OR(Z25="管理人员",Z25="工人"),1,0) -> 0 | AB25: =IF(ISERROR(FIND("代",D25)),"",IFERROR(MID(D25,FIND("代",D25)+1,FIND("付",D25,FIND("代",D25))-FIND("代",D25)-1),"")) | AC25: =IF(I25<>"账户互转","",IF(J25<>"",IFERROR(INDEX(_辅助!$G$1:$G$40,MATCH(J25,_辅助!$F$1:$F$40,0)),IF(IFERROR(MATCH(1,INDEX(ISNUMBER(SEARCH(_辅助!$Z$1:$Z$40,D25))*(_辅助!$Z$1:$Z$40<>""),0),0),0)=0,"",INDEX(_辅助!$AA$1:$AA$40,IFERROR(MATCH(1,INDEX(ISNUMBER(SEARCH(_辅助!$Z$1:$Z$40,D25))*(_辅助!$Z$1:$Z$40<>""),0),0),0)))),IF(IFERROR(MATCH(1,INDEX(ISNUMBER(SEARCH(_辅助!$Z$1:$Z$40,D25))*(_辅助!$Z$1:$Z$40<>""),0),0),0)=0,"",INDEX(_辅助!$AA$1:$AA$40,IFERROR(MATCH(1,INDEX(ISNUMBER(SEARCH(_辅助!$Z$1:$Z$40,D25))*(_辅助!$Z$1:$Z$40<>""),0),0),0))))) | AD25: =IF(O25<>"",O25,AC25) | AE25: =IF(C25="","",IFERROR(INDEX(基础资料!$H$5:$H$24,MATCH(C25,基础资料!$G$5:$G$24,0))&"","")) -> 银行 | AF25: =IF(AD25="","",IFERROR(INDEX(基础资料!$H$5:$H$24,MATCH(AD25,基础资料!$G$5:$G$24,0))&"","")) | AG25: =IF(OR(D25="",R25=0),"",IFERROR(INDEX(基础资料!$AC$5:$AC$164,IF(IF(F25<>"","支","收")="收",MATCH(1,INDEX(ISNUMBER(SEARCH(_辅助!$AB$1:$AB$160,D25))*(_辅助!$AB$1:$AB$160<>""),0),0),MATCH(1,INDEX(ISNUMBER(SEARCH(_辅助!$AC$1:$AC$160,D25))*(_辅助!$AC$1:$AC$160<>""),0),0)))&"","")) -> 工程款 | AH25: =IF(R25=0,"",IF(OR(IFERROR(INDEX(基础资料!$T$5:$T$64,MATCH(I25,基础资料!$S$5:$S$64,0))&"","")="收",IFERROR(INDEX(基础资料!$T$5:$T$64,MATCH(I25,基础资料!$S$5:$S$64,0))&"","")="支"),IFERROR(INDEX(基础资料!$T$5:$T$64,MATCH(I25,基础资料!$S$5:$S$64,0))&"",""),IF(R25>0,"收","支"))) -> 收 | AI25: =IF(N(AK25)=0,"",INDEX(_辅助!$R$1:$R$240,AK25)) -> 赣粤高速 | AJ25: =IF(OR(AI25="",L25<>""),0,SUMPRODUCT(ISNUMBER(SEARCH(_辅助!$R$1:$R$240,D25))*(_辅助!$R$1:$R$240<>"")*(1-ISNUMBER(SEARCH(_辅助!$R$1:$R$240,AI25)))*(_辅助!$S$1:$S$240<>T25))) -> 0 | AK25: =IF(D25="",0,IFERROR(MATCH(1,INDEX(ISNUMBER(SEARCH(_辅助!$R$1:$R$240,D25))*(_辅助!$R$1:$R$240<>""),0),0),0)) -> 20 | AL25: =IF(D25="",0,IFERROR(MATCH(1,INDEX(ISNUMBER(SEARCH(_辅助!$V$1:$V$900,D25))*(_辅助!$V$1:$V$900<>""),0),0),0)) -> 13 | AM25: =IF(AB25="",0,IFERROR(MATCH(1,INDEX(ISNUMBER(SEARCH(_辅助!$V$1:$V$900,AB25))*(_辅助!$V$1:$V$900<>""),0),0),0)) -> 0 | AN25: =IF(ISNUMBER(B25),INT(B25),0) -> 46163 | AO25: =IF(AND(X25="应收账款",R25>0,AN25>0,H25<>""),H25&"|"&COUNTIFS(资金流水!$H$6:$H$2005,H25,资金流水!$X$6:$X$2005,"应收账款",资金流水!$R$6:$R$2005,">0",资金流水!$AN$6:$AN$2005,">0",资金流水!$AN$6:$AN$2005,"<="&AN25),"") -> 赣粤高速|1 | AP25: =IF(AND(J25<>"",R25<0,AN25>0),J25&"|"&COUNTIFS(资金流水!$J$6:$J$2005,J25,资金流水!$R$6:$R$2005,"<0",资金流水!$AN$6:$AN$2005,">0",资金流水!$AN$6:$AN$2005,"<="&AN25),"") | AQ25: =IF(AND(X25="其他应收款",AN25>0,J25<>""),J25&"|"&(COUNTIFS(资金流水!$J$6:$J$2005,J25,资金流水!$X$6:$X$2005,"其他应收款",资金流水!$AN$6:$AN$2005,">0",资金流水!$AN$6:$AN$2005,"<"&AN25)+COUNTIFS($J$6:J25,J25,$X$6:X25,"其他应收款",$AN$6:AN25,AN25)),"")
A26: =IF(AND(B26="",D26="",E26="",F26=""),"",ROW()-5) -> 21 | B26: 46164 | C26: 九江银行 | D26: 食品厂投标保证金退回 | E26: 90000 | G26: =IF(C26="","",ROUND(IFERROR(INDEX(基础资料!$K$5:$K$24,MATCH(C26,基础资料!$G$5:$G$24,0)),0)+SUMIFS($R$6:R26,$C$6:C26,C26)-SUMIFS($R$6:R26,$AD$6:AD26,C26,$X$6:X26,"账户互转"),2)) -> 66042.69 | H26: =IF(L26<>"",L26,T26) | I26: =IF(M26<>"",M26,U26) -> 保证金押金 | J26: =IF(N26<>"",N26,V26) | K26: =IF(AND(B26="",D26="",E26="",F26=""),"",IF(C26="","✗ 没选账户",IF(AE26="","✗ 账户不在【基础资料】② 里",IF(NOT(ISNUMBER(B26)),"✗ 日期要填成日期（2026/5/1）",IF(AND(ISNUMBER(B26),B26<基础资料!$C$9),"✗ 日期早于建账日期（建账前的放【期初余额】）",IF(AND(N(E26)<>0,N(F26)<>0),"✗ 收入、支出只填一边",IF(R26=0,"✗ 没有金额",IF(I26="","✗ 认不出收支类别：在「改类别」选",IF(W26="？","✗ 收支类别不在【基础资料】③ 里",IF(OR(I26="管理人员工资",I26="折旧费"),"✗ 这一类是自动算的，流水里不能选（发工资选「工资」，买设备选「固定资产购置」）",IF(AND(OR(X26="材料费",X26="人工费",X26="分包费",X26="机械运输费",X26="其他直接费",X26="票据贴息",X26="应收账款"),H26=""),"✗ 这一笔要选项目（摘要里的项目没在【项目档案】的话先去加上）",IF(AND(H26<>"",COUNTIF(项目档案!$B$4:$B$63,H26)=0),"✗ 项目不在【项目档案】里",IF(AND(OR(IFERROR(INDEX(基础资料!$W$5:$W$64,MATCH(I26,基础资料!$S$5:$S$64,0))&"","")="人",IFERROR(INDEX(基础资料!$W$5:$W$64,MATCH(I26,基础资料!$S$5:$S$64,0))&"","")="单位"),J26=""),"✗ 这一笔要选是谁（改单位/人）",IF(AND(I26="付应付款",NOT(OR(Z26="材料供应商",Z26="分包",Z26="机械运输",Z26="其他"))),"✗ 付应付款要选材料商、分包或机械单位",IF(AND(I26="付应付款",Y26=0),"✗ 这家没有应付：先在【应付登记】登记（现买现付的选材料费等）",IF(AND(OR(I26="工资",I26="工资退回"),AA26=0),"✗ 工资要选管理人员或工人（临时工选「临时工工资」）",IF(AND(I26="账户互转",AD26=""),"✗ 账户互转要在「对方账户」选（借款、报销选那个人的个人户）",IF(AND(I26="账户互转",AF26=""),"✗ 对方账户不在【基础资料】② 里",IF(AND(I26="账户互转",AD26=C26),"✗ 对方账户不能是自己",IF(IF(I26="账户互转",COUNTIFS(资金流水!$C$6:$C$2005,AD26,资金流水!$AD$6:$AD$2005,C26,资金流水!$I$6:$I$2005,"账户互转",资金流水!$R$6:$R$2005,-R26)>0,FALSE),"✗ 对方账户那边也记了这笔互转（只记一边：清空其中一行的内容）",IF(AJ26>0,"⚠ 摘要里有两个项目：拆成几行，或在「改项目」选",IF(AND(I26<>"账户互转",O26<>""),"⚠ 填了对方账户但类别不是账户互转（对方账户不起作用）",IF(AND(J26<>"",Z26=""),"⚠ 单位/人没在【往来单位】登记",IF(AND(N(F26)<0,AH26="收"),"⚠ 这是收款，以后请记在收入栏",IF(N(E26)<0,"⚠ 收入填了负数，已按支出算",IF(N(F26)<0,"↩ 冲回（退款）",IF(AND(R26<0,I26<>"固定资产购置",I26<>"付应付款",ISNUMBER(B26),IFERROR(SUMPRODUCT(ISNUMBER(SEARCH(基础资料!$AJ$5:$AJ$34,D26))*(基础资料!$AJ$5:$AJ$34<>"")*((AN26-基础资料!$AK$5:$AK$34)<=30)*((AN26-基础资料!$AK$5:$AK$34)>=-30)),0)>0),"⚠ 像是在买【基础资料】⑥ 登记的车/设备：类别改成「固定资产购置」，不然成本算两遍",IF(AND(OR(I26="材料费",I26="分包费",I26="机械运输费",I26="其他直接费"),J26="",H26<>"",COUNTIFS(应付登记!$E$5:$E$1004,H26,应付登记!$G$5:$G$1004,-R26)>0),"⚠ 这个项目有同样金额的应付登记：是付那家的，改类别选「付应付款」、改单位选那家（不然成本算两遍）","√")))))))))))))))))))))))))))) -> √ | R26: =ROUND(N(E26)-N(F26),2) -> 90000 | S26: =IF(ISNUMBER(B26),YEAR(B26)*100+MONTH(B26),"") -> 202605 | T26: =IF(N(AK26)=0,"",INDEX(_辅助!$S$1:$S$240,AK26)) | U26: =IF(OR(D26="",R26=0),"",IF(AND(Z26="临时工",R26<0),"临时工工资",IF(AG26="",IF(AA26=1,"工资",IF(Z26="临时工","临时工工资",IF(Z26="甲方/总包","工程款",IF(AND(OR(Z26="材料供应商",Z26="分包",Z26="机械运输"),Y26=1),"付应付款","")))),IF(AND(Y26=1,OR(Z26="材料供应商",Z26="分包",Z26="机械运输",Z26="其他"),OR(AG26="材料费",AG26="分包费",AG26="机械运输费",AG26="其他直接费",AG26="工资",AG26="临时工工资")),"付应付款",AG26)))) -> 保证金押金 | V26: =IF(D26="","",IF(N(AM26)>0,IF(N(AM26)=0,"",INDEX(_辅助!$W$1:$W$900,AM26)),IF(N(AL26)=0,"",INDEX(_辅助!$W$1:$W$900,AL26)))) | W26: =IF(I26="","",IFERROR(INDEX(基础资料!$V$5:$V$64,MATCH(I26,基础资料!$S$5:$S$64,0))&"","？")) -> 不进利润 | X26: =IF(R26=0,"",IF(OR(I26="",IFERROR(INDEX(基础资料!$U$5:$U$64,MATCH(I26,基础资料!$S$5:$S$64,0))&"","")=""),"待分类",IF(OR(I26="付应付款",IFERROR(INDEX(基础资料!$U$5:$U$64,MATCH(I26,基础资料!$S$5:$S$64,0))&"","")="应付款"),IF(Z26="材料供应商","应付材料款",IF(Z26="分包","应付分包款",IF(Z26="机械运输","应付机械运输费","应付其他款"))),IFERROR(INDEX(基础资料!$U$5:$U$64,MATCH(I26,基础资料!$S$5:$S$64,0))&"","")))) -> 其他应收款 | Y26: =IF(J26="",0,IF(COUNTIF(应付登记!$D$5:$D$1004,J26)+COUNTIF(期初余额!$P$5:$P$204,J26)>0,1,0)) -> 0 | Z26: =IF(J26="","",IFERROR(INDEX(往来单位!$C$4:$C$303,MATCH(J26,往来单位!$B$4:$B$303,0))&"","")) | AA26: =IF(OR(Z26="管理人员",Z26="工人"),1,0) -> 0 | AB26: =IF(ISERROR(FIND("代",D26)),"",IFERROR(MID(D26,FIND("代",D26)+1,FIND("付",D26,FIND("代",D26))-FIND("代",D26)-1),"")) | AC26: =IF(I26<>"账户互转","",IF(J26<>"",IFERROR(INDEX(_辅助!$G$1:$G$40,MATCH(J26,_辅助!$F$1:$F$40,0)),IF(IFERROR(MATCH(1,INDEX(ISNUMBER(SEARCH(_辅助!$Z$1:$Z$40,D26))*(_辅助!$Z$1:$Z$40<>""),0),0),0)=0,"",INDEX(_辅助!$AA$1:$AA$40,IFERROR(MATCH(1,INDEX(ISNUMBER(SEARCH(_辅助!$Z$1:$Z$40,D26))*(_辅助!$Z$1:$Z$40<>""),0),0),0)))),IF(IFERROR(MATCH(1,INDEX(ISNUMBER(SEARCH(_辅助!$Z$1:$Z$40,D26))*(_辅助!$Z$1:$Z$40<>""),0),0),0)=0,"",INDEX(_辅助!$AA$1:$AA$40,IFERROR(MATCH(1,INDEX(ISNUMBER(SEARCH(_辅助!$Z$1:$Z$40,D26))*(_辅助!$Z$1:$Z$40<>""),0),0),0))))) | AD26: =IF(O26<>"",O26,AC26) | AE26: =IF(C26="","",IFERROR(INDEX(基础资料!$H$5:$H$24,MATCH(C26,基础资料!$G$5:$G$24,0))&"","")) -> 银行 | AF26: =IF(AD26="","",IFERROR(INDEX(基础资料!$H$5:$H$24,MATCH(AD26,基础资料!$G$5:$G$24,0))&"","")) | AG26: =IF(OR(D26="",R26=0),"",IFERROR(INDEX(基础资料!$AC$5:$AC$164,IF(IF(F26<>"","支","收")="收",MATCH(1,INDEX(ISNUMBER(SEARCH(_辅助!$AB$1:$AB$160,D26))*(_辅助!$AB$1:$AB$160<>""),0),0),MATCH(1,INDEX(ISNUMBER(SEARCH(_辅助!$AC$1:$AC$160,D26))*(_辅助!$AC$1:$AC$160<>""),0),0)))&"","")) -> 保证金押金 | AH26: =IF(R26=0,"",IF(OR(IFERROR(INDEX(基础资料!$T$5:$T$64,MATCH(I26,基础资料!$S$5:$S$64,0))&"","")="收",IFERROR(INDEX(基础资料!$T$5:$T$64,MATCH(I26,基础资料!$S$5:$S$64,0))&"","")="支"),IFERROR(INDEX(基础资料!$T$5:$T$64,MATCH(I26,基础资料!$S$5:$S$64,0))&"",""),IF(R26>0,"收","支"))) -> 收 | AI26: =IF(N(AK26)=0,"",INDEX(_辅助!$R$1:$R$240,AK26)) | AJ26: =IF(OR(AI26="",L26<>""),0,SUMPRODUCT(ISNUMBER(SEARCH(_辅助!$R$1:$R$240,D26))*(_辅助!$R$1:$R$240<>"")*(1-ISNUMBER(SEARCH(_辅助!$R$1:$R$240,AI26)))*(_辅助!$S$1:$S$240<>T26))) -> 0 | AK26: =IF(D26="",0,IFERROR(MATCH(1,INDEX(ISNUMBER(SEARCH(_辅助!$R$1:$R$240,D26))*(_辅助!$R$1:$R$240<>""),0),0),0)) -> 0 | AL26: =IF(D26="",0,IFERROR(MATCH(1,INDEX(ISNUMBER(SEARCH(_辅助!$V$1:$V$900,D26))*(_辅助!$V$1:$V$900<>""),0),0),0)) -> 0 | AM26: =IF(AB26="",0,IFERROR(MATCH(1,INDEX(ISNUMBER(SEARCH(_辅助!$V$1:$V$900,AB26))*(_辅助!$V$1:$V$900<>""),0),0),0)) -> 0 | AN26: =IF(ISNUMBER(B26),INT(B26),0) -> 46164 | AO26: =IF(AND(X26="应收账款",R26>0,AN26>0,H26<>""),H26&"|"&COUNTIFS(资金流水!$H$6:$H$2005,H26,资金流水!$X$6:$X$2005,"应收账款",资金流水!$R$6:$R$2005,">0",资金流水!$AN$6:$AN$2005,">0",资金流水!$AN$6:$AN$2005,"<="&AN26),"") | AP26: =IF(AND(J26<>"",R26<0,AN26>0),J26&"|"&COUNTIFS(资金流水!$J$6:$J$2005,J26,资金流水!$R$6:$R$2005,"<0",资金流水!$AN$6:$AN$2005,">0",资金流水!$AN$6:$AN$2005,"<="&AN26),"") | AQ26: =IF(AND(X26="其他应收款",AN26>0,J26<>""),J26&"|"&(COUNTIFS(资金流水!$J$6:$J$2005,J26,资金流水!$X$6:$X$2005,"其他应收款",资金流水!$AN$6:$AN$2005,">0",资金流水!$AN$6:$AN$2005,"<"&AN26)+COUNTIFS($J$6:J26,J26,$X$6:X26,"其他应收款",$AN$6:AN26,AN26)),"")
A27: =IF(AND(B27="",D27="",E27="",F27=""),"",ROW()-5) -> 22 | B27: 46165 | C27: 九江银行 | D27: 归还股东个人借款-聂辉 | F27: 10000 | G27: =IF(C27="","",ROUND(IFERROR(INDEX(基础资料!$K$5:$K$24,MATCH(C27,基础资料!$G$5:$G$24,0)),0)+SUMIFS($R$6:R27,$C$6:C27,C27)-SUMIFS($R$6:R27,$AD$6:AD27,C27,$X$6:X27,"账户互转"),2)) -> 56042.69 | H27: =IF(L27<>"",L27,T27) | I27: =IF(M27<>"",M27,U27) -> 账户互转 | J27: =IF(N27<>"",N27,V27) -> 聂辉 | K27: =IF(AND(B27="",D27="",E27="",F27=""),"",IF(C27="","✗ 没选账户",IF(AE27="","✗ 账户不在【基础资料】② 里",IF(NOT(ISNUMBER(B27)),"✗ 日期要填成日期（2026/5/1）",IF(AND(ISNUMBER(B27),B27<基础资料!$C$9),"✗ 日期早于建账日期（建账前的放【期初余额】）",IF(AND(N(E27)<>0,N(F27)<>0),"✗ 收入、支出只填一边",IF(R27=0,"✗ 没有金额",IF(I27="","✗ 认不出收支类别：在「改类别」选",IF(W27="？","✗ 收支类别不在【基础资料】③ 里",IF(OR(I27="管理人员工资",I27="折旧费"),"✗ 这一类是自动算的，流水里不能选（发工资选「工资」，买设备选「固定资产购置」）",IF(AND(OR(X27="材料费",X27="人工费",X27="分包费",X27="机械运输费",X27="其他直接费",X27="票据贴息",X27="应收账款"),H27=""),"✗ 这一笔要选项目（摘要里的项目没在【项目档案】的话先去加上）",IF(AND(H27<>"",COUNTIF(项目档案!$B$4:$B$63,H27)=0),"✗ 项目不在【项目档案】里",IF(AND(OR(IFERROR(INDEX(基础资料!$W$5:$W$64,MATCH(I27,基础资料!$S$5:$S$64,0))&"","")="人",IFERROR(INDEX(基础资料!$W$5:$W$64,MATCH(I27,基础资料!$S$5:$S$64,0))&"","")="单位"),J27=""),"✗ 这一笔要选是谁（改单位/人）",IF(AND(I27="付应付款",NOT(OR(Z27="材料供应商",Z27="分包",Z27="机械运输",Z27="其他"))),"✗ 付应付款要选材料商、分包或机械单位",IF(AND(I27="付应付款",Y27=0),"✗ 这家没有应付：先在【应付登记】登记（现买现付的选材料费等）",IF(AND(OR(I27="工资",I27="工资退回"),AA27=0),"✗ 工资要选管理人员或工人（临时工选「临时工工资」）",IF(AND(I27="账户互转",AD27=""),"✗ 账户互转要在「对方账户」选（借款、报销选那个人的个人户）",IF(AND(I27="账户互转",AF27=""),"✗ 对方账户不在【基础资料】② 里",IF(AND(I27="账户互转",AD27=C27),"✗ 对方账户不能是自己",IF(IF(I27="账户互转",COUNTIFS(资金流水!$C$6:$C$2005,AD27,资金流水!$AD$6:$AD$2005,C27,资金流水!$I$6:$I$2005,"账户互转",资金流水!$R$6:$R$2005,-R27)>0,FALSE),"✗ 对方账户那边也记了这笔互转（只记一边：清空其中一行的内容）",IF(AJ27>0,"⚠ 摘要里有两个项目：拆成几行，或在「改项目」选",IF(AND(I27<>"账户互转",O27<>""),"⚠ 填了对方账户但类别不是账户互转（对方账户不起作用）",IF(AND(J27<>"",Z27=""),"⚠ 单位/人没在【往来单位】登记",IF(AND(N(F27)<0,AH27="收"),"⚠ 这是收款，以后请记在收入栏",IF(N(E27)<0,"⚠ 收入填了负数，已按支出算",IF(N(F27)<0,"↩ 冲回（退款）",IF(AND(R27<0,I27<>"固定资产购置",I27<>"付应付款",ISNUMBER(B27),IFERROR(SUMPRODUCT(ISNUMBER(SEARCH(基础资料!$AJ$5:$AJ$34,D27))*(基础资料!$AJ$5:$AJ$34<>"")*((AN27-基础资料!$AK$5:$AK$34)<=30)*((AN27-基础资料!$AK$5:$AK$34)>=-30)),0)>0),"⚠ 像是在买【基础资料】⑥ 登记的车/设备：类别改成「固定资产购置」，不然成本算两遍",IF(AND(OR(I27="材料费",I27="分包费",I27="机械运输费",I27="其他直接费"),J27="",H27<>"",COUNTIFS(应付登记!$E$5:$E$1004,H27,应付登记!$G$5:$G$1004,-R27)>0),"⚠ 这个项目有同样金额的应付登记：是付那家的，改类别选「付应付款」、改单位选那家（不然成本算两遍）","√")))))))))))))))))))))))))))) -> √ | R27: =ROUND(N(E27)-N(F27),2) -> -10000 | S27: =IF(ISNUMBER(B27),YEAR(B27)*100+MONTH(B27),"") -> 202605 | T27: =IF(N(AK27)=0,"",INDEX(_辅助!$S$1:$S$240,AK27)) | U27: =IF(OR(D27="",R27=0),"",IF(AND(Z27="临时工",R27<0),"临时工工资",IF(AG27="",IF(AA27=1,"工资",IF(Z27="临时工","临时工工资",IF(Z27="甲方/总包","工程款",IF(AND(OR(Z27="材料供应商",Z27="分包",Z27="机械运输"),Y27=1),"付应付款","")))),IF(AND(Y27=1,OR(Z27="材料供应商",Z27="分包",Z27="机械运输",Z27="其他"),OR(AG27="材料费",AG27="分包费",AG27="机械运输费",AG27="其他直接费",AG27="工资",AG27="临时工工资")),"付应付款",AG27)))) -> 账户互转 | V27: =IF(D27="","",IF(N(AM27)>0,IF(N(AM27)=0,"",INDEX(_辅助!$W$1:$W$900,AM27)),IF(N(AL27)=0,"",INDEX(_辅助!$W$1:$W$900,AL27)))) -> 聂辉 | W27: =IF(I27="","",IFERROR(INDEX(基础资料!$V$5:$V$64,MATCH(I27,基础资料!$S$5:$S$64,0))&"","？")) -> 不进利润 | X27: =IF(R27=0,"",IF(OR(I27="",IFERROR(INDEX(基础资料!$U$5:$U$64,MATCH(I27,基础资料!$S$5:$S$64,0))&"","")=""),"待分类",IF(OR(I27="付应付款",IFERROR(INDEX(基础资料!$U$5:$U$64,MATCH(I27,基础资料!$S$5:$S$64,0))&"","")="应付款"),IF(Z27="材料供应商","应付材料款",IF(Z27="分包","应付分包款",IF(Z27="机械运输","应付机械运输费","应付其他款"))),IFERROR(INDEX(基础资料!$U$5:$U$64,MATCH(I27,基础资料!$S$5:$S$64,0))&"","")))) -> 账户互转 | Y27: =IF(J27="",0,IF(COUNTIF(应付登记!$D$5:$D$1004,J27)+COUNTIF(期初余额!$P$5:$P$204,J27)>0,1,0)) -> 0 | Z27: =IF(J27="","",IFERROR(INDEX(往来单位!$C$4:$C$303,MATCH(J27,往来单位!$B$4:$B$303,0))&"","")) -> 管理人员 | AA27: =IF(OR(Z27="管理人员",Z27="工人"),1,0) -> 1 | AB27: =IF(ISERROR(FIND("代",D27)),"",IFERROR(MID(D27,FIND("代",D27)+1,FIND("付",D27,FIND("代",D27))-FIND("代",D27)-1),"")) | AC27: =IF(I27<>"账户互转","",IF(J27<>"",IFERROR(INDEX(_辅助!$G$1:$G$40,MATCH(J27,_辅助!$F$1:$F$40,0)),IF(IFERROR(MATCH(1,INDEX(ISNUMBER(SEARCH(_辅助!$Z$1:$Z$40,D27))*(_辅助!$Z$1:$Z$40<>""),0),0),0)=0,"",INDEX(_辅助!$AA$1:$AA$40,IFERROR(MATCH(1,INDEX(ISNUMBER(SEARCH(_辅助!$Z$1:$Z$40,D27))*(_辅助!$Z$1:$Z$40<>""),0),0),0)))),IF(IFERROR(MATCH(1,INDEX(ISNUMBER(SEARCH(_辅助!$Z$1:$Z$40,D27))*(_辅助!$Z$1:$Z$40<>""),0),0),0)=0,"",INDEX(_辅助!$AA$1:$AA$40,IFERROR(MATCH(1,INDEX(ISNUMBER(SEARCH(_辅助!$Z$1:$Z$40,D27))*(_辅助!$Z$1:$Z$40<>""),0),0),0))))) -> 聂辉个人户 | AD27: =IF(O27<>"",O27,AC27) -> 聂辉个人户 | AE27: =IF(C27="","",IFERROR(INDEX(基础资料!$H$5:$H$24,MATCH(C27,基础资料!$G$5:$G$24,0))&"","")) -> 银行 | AF27: =IF(AD27="","",IFERROR(INDEX(基础资料!$H$5:$H$24,MATCH(AD27,基础资料!$G$5:$G$24,0))&"","")) -> 个人户 | AG27: =IF(OR(D27="",R27=0),"",IFERROR(INDEX(基础资料!$AC$5:$AC$164,IF(IF(F27<>"","支","收")="收",MATCH(1,INDEX(ISNUMBER(SEARCH(_辅助!$AB$1:$AB$160,D27))*(_辅助!$AB$1:$AB$160<>""),0),0),MATCH(1,INDEX(ISNUMBER(SEARCH(_辅助!$AC$1:$AC$160,D27))*(_辅助!$AC$1:$AC$160<>""),0),0)))&"","")) -> 账户互转 | AH27: =IF(R27=0,"",IF(OR(IFERROR(INDEX(基础资料!$T$5:$T$64,MATCH(I27,基础资料!$S$5:$S$64,0))&"","")="收",IFERROR(INDEX(基础资料!$T$5:$T$64,MATCH(I27,基础资料!$S$5:$S$64,0))&"","")="支"),IFERROR(INDEX(基础资料!$T$5:$T$64,MATCH(I27,基础资料!$S$5:$S$64,0))&"",""),IF(R27>0,"收","支"))) -> 支 | AI27: =IF(N(AK27)=0,"",INDEX(_辅助!$R$1:$R$240,AK27)) | AJ27: =IF(OR(AI27="",L27<>""),0,SUMPRODUCT(ISNUMBER(SEARCH(_辅助!$R$1:$R$240,D27))*(_辅助!$R$1:$R$240<>"")*(1-ISNUMBER(SEARCH(_辅助!$R$1:$R$240,AI27)))*(_辅助!$S$1:$S$240<>T27))) -> 0 | AK27: =IF(D27="",0,IFERROR(MATCH(1,INDEX(ISNUMBER(SEARCH(_辅助!$R$1:$R$240,D27))*(_辅助!$R$1:$R$240<>""),0),0),0)) -> 0 | AL27: =IF(D27="",0,IFERROR(MATCH(1,INDEX(ISNUMBER(SEARCH(_辅助!$V$1:$V$900,D27))*(_辅助!$V$1:$V$900<>""),0),0),0)) -> 111 | AM27: =IF(AB27="",0,IFERROR(MATCH(1,INDEX(ISNUMBER(SEARCH(_辅助!$V$1:$V$900,AB27))*(_辅助!$V$1:$V$900<>""),0),0),0)) -> 0 | AN27: =IF(ISNUMBER(B27),INT(B27),0) -> 46165 | AO27: =IF(AND(X27="应收账款",R27>0,AN27>0,H27<>""),H27&"|"&COUNTIFS(资金流水!$H$6:$H$2005,H27,资金流水!$X$6:$X$2005,"应收账款",资金流水!$R$6:$R$2005,">0",资金流水!$AN$6:$AN$2005,">0",资金流水!$AN$6:$AN$2005,"<="&AN27),"") | AP27: =IF(AND(J27<>"",R27<0,AN27>0),J27&"|"&COUNTIFS(资金流水!$J$6:$J$2005,J27,资金流水!$R$6:$R$2005,"<0",资金流水!$AN$6:$AN$2005,">0",资金流水!$AN$6:$AN$2005,"<="&AN27),"") -> 聂辉|2 | AQ27: =IF(AND(X27="其他应收款",AN27>0,J27<>""),J27&"|"&(COUNTIFS(资金流水!$J$6:$J$2005,J27,资金流水!$X$6:$X$2005,"其他应收款",资金流水!$AN$6:$AN$2005,">0",资金流水!$AN$6:$AN$2005,"<"&AN27)+COUNTIFS($J$6:J27,J27,$X$6:X27,"其他应收款",$AN$6:AN27,AN27)),"")
A28: =IF(AND(B28="",D28="",E28="",F28=""),"",ROW()-5) -> 23 | B28: 46165 | C28: 九江银行 | D28: 归还股东个人借款-聂辉 | F28: 80000 | G28: =IF(C28="","",ROUND(IFERROR(INDEX(基础资料!$K$5:$K$24,MATCH(C28,基础资料!$G$5:$G$24,0)),0)+SUMIFS($R$6:R28,$C$6:C28,C28)-SUMIFS($R$6:R28,$AD$6:AD28,C28,$X$6:X28,"账户互转"),2)) -> -23957.31 | H28: =IF(L28<>"",L28,T28) | I28: =IF(M28<>"",M28,U28) -> 账户互转 | J28: =IF(N28<>"",N28,V28) -> 聂辉 | K28: =IF(AND(B28="",D28="",E28="",F28=""),"",IF(C28="","✗ 没选账户",IF(AE28="","✗ 账户不在【基础资料】② 里",IF(NOT(ISNUMBER(B28)),"✗ 日期要填成日期（2026/5/1）",IF(AND(ISNUMBER(B28),B28<基础资料!$C$9),"✗ 日期早于建账日期（建账前的放【期初余额】）",IF(AND(N(E28)<>0,N(F28)<>0),"✗ 收入、支出只填一边",IF(R28=0,"✗ 没有金额",IF(I28="","✗ 认不出收支类别：在「改类别」选",IF(W28="？","✗ 收支类别不在【基础资料】③ 里",IF(OR(I28="管理人员工资",I28="折旧费"),"✗ 这一类是自动算的，流水里不能选（发工资选「工资」，买设备选「固定资产购置」）",IF(AND(OR(X28="材料费",X28="人工费",X28="分包费",X28="机械运输费",X28="其他直接费",X28="票据贴息",X28="应收账款"),H28=""),"✗ 这一笔要选项目（摘要里的项目没在【项目档案】的话先去加上）",IF(AND(H28<>"",COUNTIF(项目档案!$B$4:$B$63,H28)=0),"✗ 项目不在【项目档案】里",IF(AND(OR(IFERROR(INDEX(基础资料!$W$5:$W$64,MATCH(I28,基础资料!$S$5:$S$64,0))&"","")="人",IFERROR(INDEX(基础资料!$W$5:$W$64,MATCH(I28,基础资料!$S$5:$S$64,0))&"","")="单位"),J28=""),"✗ 这一笔要选是谁（改单位/人）",IF(AND(I28="付应付款",NOT(OR(Z28="材料供应商",Z28="分包",Z28="机械运输",Z28="其他"))),"✗ 付应付款要选材料商、分包或机械单位",IF(AND(I28="付应付款",Y28=0),"✗ 这家没有应付：先在【应付登记】登记（现买现付的选材料费等）",IF(AND(OR(I28="工资",I28="工资退回"),AA28=0),"✗ 工资要选管理人员或工人（临时工选「临时工工资」）",IF(AND(I28="账户互转",AD28=""),"✗ 账户互转要在「对方账户」选（借款、报销选那个人的个人户）",IF(AND(I28="账户互转",AF28=""),"✗ 对方账户不在【基础资料】② 里",IF(AND(I28="账户互转",AD28=C28),"✗ 对方账户不能是自己",IF(IF(I28="账户互转",COUNTIFS(资金流水!$C$6:$C$2005,AD28,资金流水!$AD$6:$AD$2005,C28,资金流水!$I$6:$I$2005,"账户互转",资金流水!$R$6:$R$2005,-R28)>0,FALSE),"✗ 对方账户那边也记了这笔互转（只记一边：清空其中一行的内容）",IF(AJ28>0,"⚠ 摘要里有两个项目：拆成几行，或在「改项目」选",IF(AND(I28<>"账户互转",O28<>""),"⚠ 填了对方账户但类别不是账户互转（对方账户不起作用）",IF(AND(J28<>"",Z28=""),"⚠ 单位/人没在【往来单位】登记",IF(AND(N(F28)<0,AH28="收"),"⚠ 这是收款，以后请记在收入栏",IF(N(E28)<0,"⚠ 收入填了负数，已按支出算",IF(N(F28)<0,"↩ 冲回（退款）",IF(AND(R28<0,I28<>"固定资产购置",I28<>"付应付款",ISNUMBER(B28),IFERROR(SUMPRODUCT(ISNUMBER(SEARCH(基础资料!$AJ$5:$AJ$34,D28))*(基础资料!$AJ$5:$AJ$34<>"")*((AN28-基础资料!$AK$5:$AK$34)<=30)*((AN28-基础资料!$AK$5:$AK$34)>=-30)),0)>0),"⚠ 像是在买【基础资料】⑥ 登记的车/设备：类别改成「固定资产购置」，不然成本算两遍",IF(AND(OR(I28="材料费",I28="分包费",I28="机械运输费",I28="其他直接费"),J28="",H28<>"",COUNTIFS(应付登记!$E$5:$E$1004,H28,应付登记!$G$5:$G$1004,-R28)>0),"⚠ 这个项目有同样金额的应付登记：是付那家的，改类别选「付应付款」、改单位选那家（不然成本算两遍）","√")))))))))))))))))))))))))))) -> √ | R28: =ROUND(N(E28)-N(F28),2) -> -80000 | S28: =IF(ISNUMBER(B28),YEAR(B28)*100+MONTH(B28),"") -> 202605 | T28: =IF(N(AK28)=0,"",INDEX(_辅助!$S$1:$S$240,AK28)) | U28: =IF(OR(D28="",R28=0),"",IF(AND(Z28="临时工",R28<0),"临时工工资",IF(AG28="",IF(AA28=1,"工资",IF(Z28="临时工","临时工工资",IF(Z28="甲方/总包","工程款",IF(AND(OR(Z28="材料供应商",Z28="分包",Z28="机械运输"),Y28=1),"付应付款","")))),IF(AND(Y28=1,OR(Z28="材料供应商",Z28="分包",Z28="机械运输",Z28="其他"),OR(AG28="材料费",AG28="分包费",AG28="机械运输费",AG28="其他直接费",AG28="工资",AG28="临时工工资")),"付应付款",AG28)))) -> 账户互转 | V28: =IF(D28="","",IF(N(AM28)>0,IF(N(AM28)=0,"",INDEX(_辅助!$W$1:$W$900,AM28)),IF(N(AL28)=0,"",INDEX(_辅助!$W$1:$W$900,AL28)))) -> 聂辉 | W28: =IF(I28="","",IFERROR(INDEX(基础资料!$V$5:$V$64,MATCH(I28,基础资料!$S$5:$S$64,0))&"","？")) -> 不进利润 | X28: =IF(R28=0,"",IF(OR(I28="",IFERROR(INDEX(基础资料!$U$5:$U$64,MATCH(I28,基础资料!$S$5:$S$64,0))&"","")=""),"待分类",IF(OR(I28="付应付款",IFERROR(INDEX(基础资料!$U$5:$U$64,MATCH(I28,基础资料!$S$5:$S$64,0))&"","")="应付款"),IF(Z28="材料供应商","应付材料款",IF(Z28="分包","应付分包款",IF(Z28="机械运输","应付机械运输费","应付其他款"))),IFERROR(INDEX(基础资料!$U$5:$U$64,MATCH(I28,基础资料!$S$5:$S$64,0))&"","")))) -> 账户互转 | Y28: =IF(J28="",0,IF(COUNTIF(应付登记!$D$5:$D$1004,J28)+COUNTIF(期初余额!$P$5:$P$204,J28)>0,1,0)) -> 0 | Z28: =IF(J28="","",IFERROR(INDEX(往来单位!$C$4:$C$303,MATCH(J28,往来单位!$B$4:$B$303,0))&"","")) -> 管理人员 | AA28: =IF(OR(Z28="管理人员",Z28="工人"),1,0) -> 1 | AB28: =IF(ISERROR(FIND("代",D28)),"",IFERROR(MID(D28,FIND("代",D28)+1,FIND("付",D28,FIND("代",D28))-FIND("代",D28)-1),"")) | AC28: =IF(I28<>"账户互转","",IF(J28<>"",IFERROR(INDEX(_辅助!$G$1:$G$40,MATCH(J28,_辅助!$F$1:$F$40,0)),IF(IFERROR(MATCH(1,INDEX(ISNUMBER(SEARCH(_辅助!$Z$1:$Z$40,D28))*(_辅助!$Z$1:$Z$40<>""),0),0),0)=0,"",INDEX(_辅助!$AA$1:$AA$40,IFERROR(MATCH(1,INDEX(ISNUMBER(SEARCH(_辅助!$Z$1:$Z$40,D28))*(_辅助!$Z$1:$Z$40<>""),0),0),0)))),IF(IFERROR(MATCH(1,INDEX(ISNUMBER(SEARCH(_辅助!$Z$1:$Z$40,D28))*(_辅助!$Z$1:$Z$40<>""),0),0),0)=0,"",INDEX(_辅助!$AA$1:$AA$40,IFERROR(MATCH(1,INDEX(ISNUMBER(SEARCH(_辅助!$Z$1:$Z$40,D28))*(_辅助!$Z$1:$Z$40<>""),0),0),0))))) -> 聂辉个人户 | AD28: =IF(O28<>"",O28,AC28) -> 聂辉个人户 | AE28: =IF(C28="","",IFERROR(INDEX(基础资料!$H$5:$H$24,MATCH(C28,基础资料!$G$5:$G$24,0))&"","")) -> 银行 | AF28: =IF(AD28="","",IFERROR(INDEX(基础资料!$H$5:$H$24,MATCH(AD28,基础资料!$G$5:$G$24,0))&"","")) -> 个人户 | AG28: =IF(OR(D28="",R28=0),"",IFERROR(INDEX(基础资料!$AC$5:$AC$164,IF(IF(F28<>"","支","收")="收",MATCH(1,INDEX(ISNUMBER(SEARCH(_辅助!$AB$1:$AB$160,D28))*(_辅助!$AB$1:$AB$160<>""),0),0),MATCH(1,INDEX(ISNUMBER(SEARCH(_辅助!$AC$1:$AC$160,D28))*(_辅助!$AC$1:$AC$160<>""),0),0)))&"","")) -> 账户互转 | AH28: =IF(R28=0,"",IF(OR(IFERROR(INDEX(基础资料!$T$5:$T$64,MATCH(I28,基础资料!$S$5:$S$64,0))&"","")="收",IFERROR(INDEX(基础资料!$T$5:$T$64,MATCH(I28,基础资料!$S$5:$S$64,0))&"","")="支"),IFERROR(INDEX(基础资料!$T$5:$T$64,MATCH(I28,基础资料!$S$5:$S$64,0))&"",""),IF(R28>0,"收","支"))) -> 支 | AI28: =IF(N(AK28)=0,"",INDEX(_辅助!$R$1:$R$240,AK28)) | AJ28: =IF(OR(AI28="",L28<>""),0,SUMPRODUCT(ISNUMBER(SEARCH(_辅助!$R$1:$R$240,D28))*(_辅助!$R$1:$R$240<>"")*(1-ISNUMBER(SEARCH(_辅助!$R$1:$R$240,AI28)))*(_辅助!$S$1:$S$240<>T28))) -> 0 | AK28: =IF(D28="",0,IFERROR(MATCH(1,INDEX(ISNUMBER(SEARCH(_辅助!$R$1:$R$240,D28))*(_辅助!$R$1:$R$240<>""),0),0),0)) -> 0 | AL28: =IF(D28="",0,IFERROR(MATCH(1,INDEX(ISNUMBER(SEARCH(_辅助!$V$1:$V$900,D28))*(_辅助!$V$1:$V$900<>""),0),0),0)) -> 111 | AM28: =IF(AB28="",0,IFERROR(MATCH(1,INDEX(ISNUMBER(SEARCH(_辅助!$V$1:$V$900,AB28))*(_辅助!$V$1:$V$900<>""),0),0),0)) -> 0 | AN28: =IF(ISNUMBER(B28),INT(B28),0) -> 46165 | AO28: =IF(AND(X28="应收账款",R28>0,AN28>0,H28<>""),H28&"|"&COUNTIFS(资金流水!$H$6:$H$2005,H28,资金流水!$X$6:$X$2005,"应收账款",资金流水!$R$6:$R$2005,">0",资金流水!$AN$6:$AN$2005,">0",资金流水!$AN$6:$AN$2005,"<="&AN28),"") | AP28: =IF(AND(J28<>"",R28<0,AN28>0),J28&"|"&COUNTIFS(资金流水!$J$6:$J$2005,J28,资金流水!$R$6:$R$2005,"<0",资金流水!$AN$6:$AN$2005,">0",资金流水!$AN$6:$AN$2005,"<="&AN28),"") -> 聂辉|2 | AQ28: =IF(AND(X28="其他应收款",AN28>0,J28<>""),J28&"|"&(COUNTIFS(资金流水!$J$6:$J$2005,J28,资金流水!$X$6:$X$2005,"其他应收款",资金流水!$AN$6:$AN$2005,">0",资金流水!$AN$6:$AN$2005,"<"&AN28)+COUNTIFS($J$6:J28,J28,$X$6:X28,"其他应收款",$AN$6:AN28,AN28)),"")
A29: =IF(AND(B29="",D29="",E29="",F29=""),"",ROW()-5) -> 24 | B29: 46167 | C29: 九江银行 | D29: 支付社保费 | F29: 30.54 | G29: =IF(C29="","",ROUND(IFERROR(INDEX(基础资料!$K$5:$K$24,MATCH(C29,基础资料!$G$5:$G$24,0)),0)+SUMIFS($R$6:R29,$C$6:C29,C29)-SUMIFS($R$6:R29,$AD$6:AD29,C29,$X$6:X29,"账户互转"),2)) -> -23987.85 | H29: =IF(L29<>"",L29,T29) | I29: =IF(M29<>"",M29,U29) -> 社保费 | J29: =IF(N29<>"",N29,V29) | K29: =IF(AND(B29="",D29="",E29="",F29=""),"",IF(C29="","✗ 没选账户",IF(AE29="","✗ 账户不在【基础资料】② 里",IF(NOT(ISNUMBER(B29)),"✗ 日期要填成日期（2026/5/1）",IF(AND(ISNUMBER(B29),B29<基础资料!$C$9),"✗ 日期早于建账日期（建账前的放【期初余额】）",IF(AND(N(E29)<>0,N(F29)<>0),"✗ 收入、支出只填一边",IF(R29=0,"✗ 没有金额",IF(I29="","✗ 认不出收支类别：在「改类别」选",IF(W29="？","✗ 收支类别不在【基础资料】③ 里",IF(OR(I29="管理人员工资",I29="折旧费"),"✗ 这一类是自动算的，流水里不能选（发工资选「工资」，买设备选「固定资产购置」）",IF(AND(OR(X29="材料费",X29="人工费",X29="分包费",X29="机械运输费",X29="其他直接费",X29="票据贴息",X29="应收账款"),H29=""),"✗ 这一笔要选项目（摘要里的项目没在【项目档案】的话先去加上）",IF(AND(H29<>"",COUNTIF(项目档案!$B$4:$B$63,H29)=0),"✗ 项目不在【项目档案】里",IF(AND(OR(IFERROR(INDEX(基础资料!$W$5:$W$64,MATCH(I29,基础资料!$S$5:$S$64,0))&"","")="人",IFERROR(INDEX(基础资料!$W$5:$W$64,MATCH(I29,基础资料!$S$5:$S$64,0))&"","")="单位"),J29=""),"✗ 这一笔要选是谁（改单位/人）",IF(AND(I29="付应付款",NOT(OR(Z29="材料供应商",Z29="分包",Z29="机械运输",Z29="其他"))),"✗ 付应付款要选材料商、分包或机械单位",IF(AND(I29="付应付款",Y29=0),"✗ 这家没有应付：先在【应付登记】登记（现买现付的选材料费等）",IF(AND(OR(I29="工资",I29="工资退回"),AA29=0),"✗ 工资要选管理人员或工人（临时工选「临时工工资」）",IF(AND(I29="账户互转",AD29=""),"✗ 账户互转要在「对方账户」选（借款、报销选那个人的个人户）",IF(AND(I29="账户互转",AF29=""),"✗ 对方账户不在【基础资料】② 里",IF(AND(I29="账户互转",AD29=C29),"✗ 对方账户不能是自己",IF(IF(I29="账户互转",COUNTIFS(资金流水!$C$6:$C$2005,AD29,资金流水!$AD$6:$AD$2005,C29,资金流水!$I$6:$I$2005,"账户互转",资金流水!$R$6:$R$2005,-R29)>0,FALSE),"✗ 对方账户那边也记了这笔互转（只记一边：清空其中一行的内容）",IF(AJ29>0,"⚠ 摘要里有两个项目：拆成几行，或在「改项目」选",IF(AND(I29<>"账户互转",O29<>""),"⚠ 填了对方账户但类别不是账户互转（对方账户不起作用）",IF(AND(J29<>"",Z29=""),"⚠ 单位/人没在【往来单位】登记",IF(AND(N(F29)<0,AH29="收"),"⚠ 这是收款，以后请记在收入栏",IF(N(E29)<0,"⚠ 收入填了负数，已按支出算",IF(N(F29)<0,"↩ 冲回（退款）",IF(AND(R29<0,I29<>"固定资产购置",I29<>"付应付款",ISNUMBER(B29),IFERROR(SUMPRODUCT(ISNUMBER(SEARCH(基础资料!$AJ$5:$AJ$34,D29))*(基础资料!$AJ$5:$AJ$34<>"")*((AN29-基础资料!$AK$5:$AK$34)<=30)*((AN29-基础资料!$AK$5:$AK$34)>=-30)),0)>0),"⚠ 像是在买【基础资料】⑥ 登记的车/设备：类别改成「固定资产购置」，不然成本算两遍",IF(AND(OR(I29="材料费",I29="分包费",I29="机械运输费",I29="其他直接费"),J29="",H29<>"",COUNTIFS(应付登记!$E$5:$E$1004,H29,应付登记!$G$5:$G$1004,-R29)>0),"⚠ 这个项目有同样金额的应付登记：是付那家的，改类别选「付应付款」、改单位选那家（不然成本算两遍）","√")))))))))))))))))))))))))))) -> √ | R29: =ROUND(N(E29)-N(F29),2) -> -30.54 | S29: =IF(ISNUMBER(B29),YEAR(B29)*100+MONTH(B29),"") -> 202605 | T29: =IF(N(AK29)=0,"",INDEX(_辅助!$S$1:$S$240,AK29)) | U29: =IF(OR(D29="",R29=0),"",IF(AND(Z29="临时工",R29<0),"临时工工资",IF(AG29="",IF(AA29=1,"工资",IF(Z29="临时工","临时工工资",IF(Z29="甲方/总包","工程款",IF(AND(OR(Z29="材料供应商",Z29="分包",Z29="机械运输"),Y29=1),"付应付款","")))),IF(AND(Y29=1,OR(Z29="材料供应商",Z29="分包",Z29="机械运输",Z29="其他"),OR(AG29="材料费",AG29="分包费",AG29="机械运输费",AG29="其他直接费",AG29="工资",AG29="临时工工资")),"付应付款",AG29)))) -> 社保费 | V29: =IF(D29="","",IF(N(AM29)>0,IF(N(AM29)=0,"",INDEX(_辅助!$W$1:$W$900,AM29)),IF(N(AL29)=0,"",INDEX(_辅助!$W$1:$W$900,AL29)))) | W29: =IF(I29="","",IFERROR(INDEX(基础资料!$V$5:$V$64,MATCH(I29,基础资料!$S$5:$S$64,0))&"","？")) -> 公司间接费 | X29: =IF(R29=0,"",IF(OR(I29="",IFERROR(INDEX(基础资料!$U$5:$U$64,MATCH(I29,基础资料!$S$5:$S$64,0))&"","")=""),"待分类",IF(OR(I29="付应付款",IFERROR(INDEX(基础资料!$U$5:$U$64,MATCH(I29,基础资料!$S$5:$S$64,0))&"","")="应付款"),IF(Z29="材料供应商","应付材料款",IF(Z29="分包","应付分包款",IF(Z29="机械运输","应付机械运输费","应付其他款"))),IFERROR(INDEX(基础资料!$U$5:$U$64,MATCH(I29,基础资料!$S$5:$S$64,0))&"","")))) -> 社保费 | Y29: =IF(J29="",0,IF(COUNTIF(应付登记!$D$5:$D$1004,J29)+COUNTIF(期初余额!$P$5:$P$204,J29)>0,1,0)) -> 0 | Z29: =IF(J29="","",IFERROR(INDEX(往来单位!$C$4:$C$303,MATCH(J29,往来单位!$B$4:$B$303,0))&"","")) | AA29: =IF(OR(Z29="管理人员",Z29="工人"),1,0) -> 0 | AB29: =IF(ISERROR(FIND("代",D29)),"",IFERROR(MID(D29,FIND("代",D29)+1,FIND("付",D29,FIND("代",D29))-FIND("代",D29)-1),"")) | AC29: =IF(I29<>"账户互转","",IF(J29<>"",IFERROR(INDEX(_辅助!$G$1:$G$40,MATCH(J29,_辅助!$F$1:$F$40,0)),IF(IFERROR(MATCH(1,INDEX(ISNUMBER(SEARCH(_辅助!$Z$1:$Z$40,D29))*(_辅助!$Z$1:$Z$40<>""),0),0),0)=0,"",INDEX(_辅助!$AA$1:$AA$40,IFERROR(MATCH(1,INDEX(ISNUMBER(SEARCH(_辅助!$Z$1:$Z$40,D29))*(_辅助!$Z$1:$Z$40<>""),0),0),0)))),IF(IFERROR(MATCH(1,INDEX(ISNUMBER(SEARCH(_辅助!$Z$1:$Z$40,D29))*(_辅助!$Z$1:$Z$40<>""),0),0),0)=0,"",INDEX(_辅助!$AA$1:$AA$40,IFERROR(MATCH(1,INDEX(ISNUMBER(SEARCH(_辅助!$Z$1:$Z$40,D29))*(_辅助!$Z$1:$Z$40<>""),0),0),0))))) | AD29: =IF(O29<>"",O29,AC29) | AE29: =IF(C29="","",IFERROR(INDEX(基础资料!$H$5:$H$24,MATCH(C29,基础资料!$G$5:$G$24,0))&"","")) -> 银行 | AF29: =IF(AD29="","",IFERROR(INDEX(基础资料!$H$5:$H$24,MATCH(AD29,基础资料!$G$5:$G$24,0))&"","")) | AG29: =IF(OR(D29="",R29=0),"",IFERROR(INDEX(基础资料!$AC$5:$AC$164,IF(IF(F29<>"","支","收")="收",MATCH(1,INDEX(ISNUMBER(SEARCH(_辅助!$AB$1:$AB$160,D29))*(_辅助!$AB$1:$AB$160<>""),0),0),MATCH(1,INDEX(ISNUMBER(SEARCH(_辅助!$AC$1:$AC$160,D29))*(_辅助!$AC$1:$AC$160<>""),0),0)))&"","")) -> 社保费 | AH29: =IF(R29=0,"",IF(OR(IFERROR(INDEX(基础资料!$T$5:$T$64,MATCH(I29,基础资料!$S$5:$S$64,0))&"","")="收",IFERROR(INDEX(基础资料!$T$5:$T$64,MATCH(I29,基础资料!$S$5:$S$64,0))&"","")="支"),IFERROR(INDEX(基础资料!$T$5:$T$64,MATCH(I29,基础资料!$S$5:$S$64,0))&"",""),IF(R29>0,"收","支"))) -> 支 | AI29: =IF(N(AK29)=0,"",INDEX(_辅助!$R$1:$R$240,AK29)) | AJ29: =IF(OR(AI29="",L29<>""),0,SUMPRODUCT(ISNUMBER(SEARCH(_辅助!$R$1:$R$240,D29))*(_辅助!$R$1:$R$240<>"")*(1-ISNUMBER(SEARCH(_辅助!$R$1:$R$240,AI29)))*(_辅助!$S$1:$S$240<>T29))) -> 0 | AK29: =IF(D29="",0,IFERROR(MATCH(1,INDEX(ISNUMBER(SEARCH(_辅助!$R$1:$R$240,D29))*(_辅助!$R$1:$R$240<>""),0),0),0)) -> 0 | AL29: =IF(D29="",0,IFERROR(MATCH(1,INDEX(ISNUMBER(SEARCH(_辅助!$V$1:$V$900,D29))*(_辅助!$V$1:$V$900<>""),0),0),0)) -> 0 | AM29: =IF(AB29="",0,IFERROR(MATCH(1,INDEX(ISNUMBER(SEARCH(_辅助!$V$1:$V$900,AB29))*(_辅助!$V$1:$V$900<>""),0),0),0)) -> 0 | AN29: =IF(ISNUMBER(B29),INT(B29),0) -> 46167 | AO29: =IF(AND(X29="应收账款",R29>0,AN29>0,H29<>""),H29&"|"&COUNTIFS(资金流水!$H$6:$H$2005,H29,资金流水!$X$6:$X$2005,"应收账款",资金流水!$R$6:$R$2005,">0",资金流水!$AN$6:$AN$2005,">0",资金流水!$AN$6:$AN$2005,"<="&AN29),"") | AP29: =IF(AND(J29<>"",R29<0,AN29>0),J29&"|"&COUNTIFS(资金流水!$J$6:$J$2005,J29,资金流水!$R$6:$R$2005,"<0",资金流水!$AN$6:$AN$2005,">0",资金流水!$AN$6:$AN$2005,"<="&AN29),"") | AQ29: =IF(AND(X29="其他应收款",AN29>0,J29<>""),J29&"|"&(COUNTIFS(资金流水!$J$6:$J$2005,J29,资金流水!$X$6:$X$2005,"其他应收款",资金流水!$AN$6:$AN$2005,">0",资金流水!$AN$6:$AN$2005,"<"&AN29)+COUNTIFS($J$6:J29,J29,$X$6:X29,"其他应收款",$AN$6:AN29,AN29)),"")
A30: =IF(AND(B30="",D30="",E30="",F30=""),"",ROW()-5) -> 25 | B30: 46167 | C30: 九江银行 | D30: 支付社保费 | F30: 2008.42 | G30: =IF(C30="","",ROUND(IFERROR(INDEX(基础资料!$K$5:$K$24,MATCH(C30,基础资料!$G$5:$G$24,0)),0)+SUMIFS($R$6:R30,$C$6:C30,C30)-SUMIFS($R$6:R30,$AD$6:AD30,C30,$X$6:X30,"账户互转"),2)) -> -25996.27 | H30: =IF(L30<>"",L30,T30) | I30: =IF(M30<>"",M30,U30) -> 社保费 | J30: =IF(N30<>"",N30,V30) | K30: =IF(AND(B30="",D30="",E30="",F30=""),"",IF(C30="","✗ 没选账户",IF(AE30="","✗ 账户不在【基础资料】② 里",IF(NOT(ISNUMBER(B30)),"✗ 日期要填成日期（2026/5/1）",IF(AND(ISNUMBER(B30),B30<基础资料!$C$9),"✗ 日期早于建账日期（建账前的放【期初余额】）",IF(AND(N(E30)<>0,N(F30)<>0),"✗ 收入、支出只填一边",IF(R30=0,"✗ 没有金额",IF(I30="","✗ 认不出收支类别：在「改类别」选",IF(W30="？","✗ 收支类别不在【基础资料】③ 里",IF(OR(I30="管理人员工资",I30="折旧费"),"✗ 这一类是自动算的，流水里不能选（发工资选「工资」，买设备选「固定资产购置」）",IF(AND(OR(X30="材料费",X30="人工费",X30="分包费",X30="机械运输费",X30="其他直接费",X30="票据贴息",X30="应收账款"),H30=""),"✗ 这一笔要选项目（摘要里的项目没在【项目档案】的话先去加上）",IF(AND(H30<>"",COUNTIF(项目档案!$B$4:$B$63,H30)=0),"✗ 项目不在【项目档案】里",IF(AND(OR(IFERROR(INDEX(基础资料!$W$5:$W$64,MATCH(I30,基础资料!$S$5:$S$64,0))&"","")="人",IFERROR(INDEX(基础资料!$W$5:$W$64,MATCH(I30,基础资料!$S$5:$S$64,0))&"","")="单位"),J30=""),"✗ 这一笔要选是谁（改单位/人）",IF(AND(I30="付应付款",NOT(OR(Z30="材料供应商",Z30="分包",Z30="机械运输",Z30="其他"))),"✗ 付应付款要选材料商、分包或机械单位",IF(AND(I30="付应付款",Y30=0),"✗ 这家没有应付：先在【应付登记】登记（现买现付的选材料费等）",IF(AND(OR(I30="工资",I30="工资退回"),AA30=0),"✗ 工资要选管理人员或工人（临时工选「临时工工资」）",IF(AND(I30="账户互转",AD30=""),"✗ 账户互转要在「对方账户」选（借款、报销选那个人的个人户）",IF(AND(I30="账户互转",AF30=""),"✗ 对方账户不在【基础资料】② 里",IF(AND(I30="账户互转",AD30=C30),"✗ 对方账户不能是自己",IF(IF(I30="账户互转",COUNTIFS(资金流水!$C$6:$C$2005,AD30,资金流水!$AD$6:$AD$2005,C30,资金流水!$I$6:$I$2005,"账户互转",资金流水!$R$6:$R$2005,-R30)>0,FALSE),"✗ 对方账户那边也记了这笔互转（只记一边：清空其中一行的内容）",IF(AJ30>0,"⚠ 摘要里有两个项目：拆成几行，或在「改项目」选",IF(AND(I30<>"账户互转",O30<>""),"⚠ 填了对方账户但类别不是账户互转（对方账户不起作用）",IF(AND(J30<>"",Z30=""),"⚠ 单位/人没在【往来单位】登记",IF(AND(N(F30)<0,AH30="收"),"⚠ 这是收款，以后请记在收入栏",IF(N(E30)<0,"⚠ 收入填了负数，已按支出算",IF(N(F30)<0,"↩ 冲回（退款）",IF(AND(R30<0,I30<>"固定资产购置",I30<>"付应付款",ISNUMBER(B30),IFERROR(SUMPRODUCT(ISNUMBER(SEARCH(基础资料!$AJ$5:$AJ$34,D30))*(基础资料!$AJ$5:$AJ$34<>"")*((AN30-基础资料!$AK$5:$AK$34)<=30)*((AN30-基础资料!$AK$5:$AK$34)>=-30)),0)>0),"⚠ 像是在买【基础资料】⑥ 登记的车/设备：类别改成「固定资产购置」，不然成本算两遍",IF(AND(OR(I30="材料费",I30="分包费",I30="机械运输费",I30="其他直接费"),J30="",H30<>"",COUNTIFS(应付登记!$E$5:$E$1004,H30,应付登记!$G$5:$G$1004,-R30)>0),"⚠ 这个项目有同样金额的应付登记：是付那家的，改类别选「付应付款」、改单位选那家（不然成本算两遍）","√")))))))))))))))))))))))))))) -> √ | R30: =ROUND(N(E30)-N(F30),2) -> -2008.42 | S30: =IF(ISNUMBER(B30),YEAR(B30)*100+MONTH(B30),"") -> 202605 | T30: =IF(N(AK30)=0,"",INDEX(_辅助!$S$1:$S$240,AK30)) | U30: =IF(OR(D30="",R30=0),"",IF(AND(Z30="临时工",R30<0),"临时工工资",IF(AG30="",IF(AA30=1,"工资",IF(Z30="临时工","临时工工资",IF(Z30="甲方/总包","工程款",IF(AND(OR(Z30="材料供应商",Z30="分包",Z30="机械运输"),Y30=1),"付应付款","")))),IF(AND(Y30=1,OR(Z30="材料供应商",Z30="分包",Z30="机械运输",Z30="其他"),OR(AG30="材料费",AG30="分包费",AG30="机械运输费",AG30="其他直接费",AG30="工资",AG30="临时工工资")),"付应付款",AG30)))) -> 社保费 | V30: =IF(D30="","",IF(N(AM30)>0,IF(N(AM30)=0,"",INDEX(_辅助!$W$1:$W$900,AM30)),IF(N(AL30)=0,"",INDEX(_辅助!$W$1:$W$900,AL30)))) | W30: =IF(I30="","",IFERROR(INDEX(基础资料!$V$5:$V$64,MATCH(I30,基础资料!$S$5:$S$64,0))&"","？")) -> 公司间接费 | X30: =IF(R30=0,"",IF(OR(I30="",IFERROR(INDEX(基础资料!$U$5:$U$64,MATCH(I30,基础资料!$S$5:$S$64,0))&"","")=""),"待分类",IF(OR(I30="付应付款",IFERROR(INDEX(基础资料!$U$5:$U$64,MATCH(I30,基础资料!$S$5:$S$64,0))&"","")="应付款"),IF(Z30="材料供应商","应付材料款",IF(Z30="分包","应付分包款",IF(Z30="机械运输","应付机械运输费","应付其他款"))),IFERROR(INDEX(基础资料!$U$5:$U$64,MATCH(I30,基础资料!$S$5:$S$64,0))&"","")))) -> 社保费 | Y30: =IF(J30="",0,IF(COUNTIF(应付登记!$D$5:$D$1004,J30)+COUNTIF(期初余额!$P$5:$P$204,J30)>0,1,0)) -> 0 | Z30: =IF(J30="","",IFERROR(INDEX(往来单位!$C$4:$C$303,MATCH(J30,往来单位!$B$4:$B$303,0))&"","")) | AA30: =IF(OR(Z30="管理人员",Z30="工人"),1,0) -> 0 | AB30: =IF(ISERROR(FIND("代",D30)),"",IFERROR(MID(D30,FIND("代",D30)+1,FIND("付",D30,FIND("代",D30))-FIND("代",D30)-1),"")) | AC30: =IF(I30<>"账户互转","",IF(J30<>"",IFERROR(INDEX(_辅助!$G$1:$G$40,MATCH(J30,_辅助!$F$1:$F$40,0)),IF(IFERROR(MATCH(1,INDEX(ISNUMBER(SEARCH(_辅助!$Z$1:$Z$40,D30))*(_辅助!$Z$1:$Z$40<>""),0),0),0)=0,"",INDEX(_辅助!$AA$1:$AA$40,IFERROR(MATCH(1,INDEX(ISNUMBER(SEARCH(_辅助!$Z$1:$Z$40,D30))*(_辅助!$Z$1:$Z$40<>""),0),0),0)))),IF(IFERROR(MATCH(1,INDEX(ISNUMBER(SEARCH(_辅助!$Z$1:$Z$40,D30))*(_辅助!$Z$1:$Z$40<>""),0),0),0)=0,"",INDEX(_辅助!$AA$1:$AA$40,IFERROR(MATCH(1,INDEX(ISNUMBER(SEARCH(_辅助!$Z$1:$Z$40,D30))*(_辅助!$Z$1:$Z$40<>""),0),0),0))))) | AD30: =IF(O30<>"",O30,AC30) | AE30: =IF(C30="","",IFERROR(INDEX(基础资料!$H$5:$H$24,MATCH(C30,基础资料!$G$5:$G$24,0))&"","")) -> 银行 | AF30: =IF(AD30="","",IFERROR(INDEX(基础资料!$H$5:$H$24,MATCH(AD30,基础资料!$G$5:$G$24,0))&"","")) | AG30: =IF(OR(D30="",R30=0),"",IFERROR(INDEX(基础资料!$AC$5:$AC$164,IF(IF(F30<>"","支","收")="收",MATCH(1,INDEX(ISNUMBER(SEARCH(_辅助!$AB$1:$AB$160,D30))*(_辅助!$AB$1:$AB$160<>""),0),0),MATCH(1,INDEX(ISNUMBER(SEARCH(_辅助!$AC$1:$AC$160,D30))*(_辅助!$AC$1:$AC$160<>""),0),0)))&"","")) -> 社保费 | AH30: =IF(R30=0,"",IF(OR(IFERROR(INDEX(基础资料!$T$5:$T$64,MATCH(I30,基础资料!$S$5:$S$64,0))&"","")="收",IFERROR(INDEX(基础资料!$T$5:$T$64,MATCH(I30,基础资料!$S$5:$S$64,0))&"","")="支"),IFERROR(INDEX(基础资料!$T$5:$T$64,MATCH(I30,基础资料!$S$5:$S$64,0))&"",""),IF(R30>0,"收","支"))) -> 支 | AI30: =IF(N(AK30)=0,"",INDEX(_辅助!$R$1:$R$240,AK30)) | AJ30: =IF(OR(AI30="",L30<>""),0,SUMPRODUCT(ISNUMBER(SEARCH(_辅助!$R$1:$R$240,D30))*(_辅助!$R$1:$R$240<>"")*(1-ISNUMBER(SEARCH(_辅助!$R$1:$R$240,AI30)))*(_辅助!$S$1:$S$240<>T30))) -> 0 | AK30: =IF(D30="",0,IFERROR(MATCH(1,INDEX(ISNUMBER(SEARCH(_辅助!$R$1:$R$240,D30))*(_辅助!$R$1:$R$240<>""),0),0),0)) -> 0 | AL30: =IF(D30="",0,IFERROR(MATCH(1,INDEX(ISNUMBER(SEARCH(_辅助!$V$1:$V$900,D30))*(_辅助!$V$1:$V$900<>""),0),0),0)) -> 0 | AM30: =IF(AB30="",0,IFERROR(MATCH(1,INDEX(ISNUMBER(SEARCH(_辅助!$V$1:$V$900,AB30))*(_辅助!$V$1:$V$900<>""),0),0),0)) -> 0 | AN30: =IF(ISNUMBER(B30),INT(B30),0) -> 46167 | AO30: =IF(AND(X30="应收账款",R30>0,AN30>0,H30<>""),H30&"|"&COUNTIFS(资金流水!$H$6:$H$2005,H30,资金流水!$X$6:$X$2005,"应收账款",资金流水!$R$6:$R$2005,">0",资金流水!$AN$6:$AN$2005,">0",资金流水!$AN$6:$AN$2005,"<="&AN30),"") | AP30: =IF(AND(J30<>"",R30<0,AN30>0),J30&"|"&COUNTIFS(资金流水!$J$6:$J$2005,J30,资金流水!$R$6:$R$2005,"<0",资金流水!$AN$6:$AN$2005,">0",资金流水!$AN$6:$AN$2005,"<="&AN30),"") | AQ30: =IF(AND(X30="其他应收款",AN30>0,J30<>""),J30&"|"&(COUNTIFS(资金流水!$J$6:$J$2005,J30,资金流水!$X$6:$X$2005,"其他应收款",资金流水!$AN$6:$AN$2005,">0",资金流水!$AN$6:$AN$2005,"<"&AN30)+COUNTIFS($J$6:J30,J30,$X$6:X30,"其他应收款",$AN$6:AN30,AN30)),"")
A31: =IF(AND(B31="",D31="",E31="",F31=""),"",ROW()-5) -> 26 | B31: 46170 | C31: 九江银行 | D31: 付代账公司费用 | F31: 1000 | G31: =IF(C31="","",ROUND(IFERROR(INDEX(基础资料!$K$5:$K$24,MATCH(C31,基础资料!$G$5:$G$24,0)),0)+SUMIFS($R$6:R31,$C$6:C31,C31)-SUMIFS($R$6:R31,$AD$6:AD31,C31,$X$6:X31,"账户互转"),2)) -> -26996.27 | H31: =IF(L31<>"",L31,T31) | I31: =IF(M31<>"",M31,U31) -> 办公费 | J31: =IF(N31<>"",N31,V31) | K31: =IF(AND(B31="",D31="",E31="",F31=""),"",IF(C31="","✗ 没选账户",IF(AE31="","✗ 账户不在【基础资料】② 里",IF(NOT(ISNUMBER(B31)),"✗ 日期要填成日期（2026/5/1）",IF(AND(ISNUMBER(B31),B31<基础资料!$C$9),"✗ 日期早于建账日期（建账前的放【期初余额】）",IF(AND(N(E31)<>0,N(F31)<>0),"✗ 收入、支出只填一边",IF(R31=0,"✗ 没有金额",IF(I31="","✗ 认不出收支类别：在「改类别」选",IF(W31="？","✗ 收支类别不在【基础资料】③ 里",IF(OR(I31="管理人员工资",I31="折旧费"),"✗ 这一类是自动算的，流水里不能选（发工资选「工资」，买设备选「固定资产购置」）",IF(AND(OR(X31="材料费",X31="人工费",X31="分包费",X31="机械运输费",X31="其他直接费",X31="票据贴息",X31="应收账款"),H31=""),"✗ 这一笔要选项目（摘要里的项目没在【项目档案】的话先去加上）",IF(AND(H31<>"",COUNTIF(项目档案!$B$4:$B$63,H31)=0),"✗ 项目不在【项目档案】里",IF(AND(OR(IFERROR(INDEX(基础资料!$W$5:$W$64,MATCH(I31,基础资料!$S$5:$S$64,0))&"","")="人",IFERROR(INDEX(基础资料!$W$5:$W$64,MATCH(I31,基础资料!$S$5:$S$64,0))&"","")="单位"),J31=""),"✗ 这一笔要选是谁（改单位/人）",IF(AND(I31="付应付款",NOT(OR(Z31="材料供应商",Z31="分包",Z31="机械运输",Z31="其他"))),"✗ 付应付款要选材料商、分包或机械单位",IF(AND(I31="付应付款",Y31=0),"✗ 这家没有应付：先在【应付登记】登记（现买现付的选材料费等）",IF(AND(OR(I31="工资",I31="工资退回"),AA31=0),"✗ 工资要选管理人员或工人（临时工选「临时工工资」）",IF(AND(I31="账户互转",AD31=""),"✗ 账户互转要在「对方账户」选（借款、报销选那个人的个人户）",IF(AND(I31="账户互转",AF31=""),"✗ 对方账户不在【基础资料】② 里",IF(AND(I31="账户互转",AD31=C31),"✗ 对方账户不能是自己",IF(IF(I31="账户互转",COUNTIFS(资金流水!$C$6:$C$2005,AD31,资金流水!$AD$6:$AD$2005,C31,资金流水!$I$6:$I$2005,"账户互转",资金流水!$R$6:$R$2005,-R31)>0,FALSE),"✗ 对方账户那边也记了这笔互转（只记一边：清空其中一行的内容）",IF(AJ31>0,"⚠ 摘要里有两个项目：拆成几行，或在「改项目」选",IF(AND(I31<>"账户互转",O31<>""),"⚠ 填了对方账户但类别不是账户互转（对方账户不起作用）",IF(AND(J31<>"",Z31=""),"⚠ 单位/人没在【往来单位】登记",IF(AND(N(F31)<0,AH31="收"),"⚠ 这是收款，以后请记在收入栏",IF(N(E31)<0,"⚠ 收入填了负数，已按支出算",IF(N(F31)<0,"↩ 冲回（退款）",IF(AND(R31<0,I31<>"固定资产购置",I31<>"付应付款",ISNUMBER(B31),IFERROR(SUMPRODUCT(ISNUMBER(SEARCH(基础资料!$AJ$5:$AJ$34,D31))*(基础资料!$AJ$5:$AJ$34<>"")*((AN31-基础资料!$AK$5:$AK$34)<=30)*((AN31-基础资料!$AK$5:$AK$34)>=-30)),0)>0),"⚠ 像是在买【基础资料】⑥ 登记的车/设备：类别改成「固定资产购置」，不然成本算两遍",IF(AND(OR(I31="材料费",I31="分包费",I31="机械运输费",I31="其他直接费"),J31="",H31<>"",COUNTIFS(应付登记!$E$5:$E$1004,H31,应付登记!$G$5:$G$1004,-R31)>0),"⚠ 这个项目有同样金额的应付登记：是付那家的，改类别选「付应付款」、改单位选那家（不然成本算两遍）","√")))))))))))))))))))))))))))) -> √ | R31: =ROUND(N(E31)-N(F31),2) -> -1000 | S31: =IF(ISNUMBER(B31),YEAR(B31)*100+MONTH(B31),"") -> 202605 | T31: =IF(N(AK31)=0,"",INDEX(_辅助!$S$1:$S$240,AK31)) | U31: =IF(OR(D31="",R31=0),"",IF(AND(Z31="临时工",R31<0),"临时工工资",IF(AG31="",IF(AA31=1,"工资",IF(Z31="临时工","临时工工资",IF(Z31="甲方/总包","工程款",IF(AND(OR(Z31="材料供应商",Z31="分包",Z31="机械运输"),Y31=1),"付应付款","")))),IF(AND(Y31=1,OR(Z31="材料供应商",Z31="分包",Z31="机械运输",Z31="其他"),OR(AG31="材料费",AG31="分包费",AG31="机械运输费",AG31="其他直接费",AG31="工资",AG31="临时工工资")),"付应付款",AG31)))) -> 办公费 | V31: =IF(D31="","",IF(N(AM31)>0,IF(N(AM31)=0,"",INDEX(_辅助!$W$1:$W$900,AM31)),IF(N(AL31)=0,"",INDEX(_辅助!$W$1:$W$900,AL31)))) | W31: =IF(I31="","",IFERROR(INDEX(基础资料!$V$5:$V$64,MATCH(I31,基础资料!$S$5:$S$64,0))&"","？")) -> 公司间接费 | X31: =IF(R31=0,"",IF(OR(I31="",IFERROR(INDEX(基础资料!$U$5:$U$64,MATCH(I31,基础资料!$S$5:$S$64,0))&"","")=""),"待分类",IF(OR(I31="付应付款",IFERROR(INDEX(基础资料!$U$5:$U$64,MATCH(I31,基础资料!$S$5:$S$64,0))&"","")="应付款"),IF(Z31="材料供应商","应付材料款",IF(Z31="分包","应付分包款",IF(Z31="机械运输","应付机械运输费","应付其他款"))),IFERROR(INDEX(基础资料!$U$5:$U$64,MATCH(I31,基础资料!$S$5:$S$64,0))&"","")))) -> 办公费 | Y31: =IF(J31="",0,IF(COUNTIF(应付登记!$D$5:$D$1004,J31)+COUNTIF(期初余额!$P$5:$P$204,J31)>0,1,0)) -> 0 | Z31: =IF(J31="","",IFERROR(INDEX(往来单位!$C$4:$C$303,MATCH(J31,往来单位!$B$4:$B$303,0))&"","")) | AA31: =IF(OR(Z31="管理人员",Z31="工人"),1,0) -> 0 | AB31: =IF(ISERROR(FIND("代",D31)),"",IFERROR(MID(D31,FIND("代",D31)+1,FIND("付",D31,FIND("代",D31))-FIND("代",D31)-1),"")) | AC31: =IF(I31<>"账户互转","",IF(J31<>"",IFERROR(INDEX(_辅助!$G$1:$G$40,MATCH(J31,_辅助!$F$1:$F$40,0)),IF(IFERROR(MATCH(1,INDEX(ISNUMBER(SEARCH(_辅助!$Z$1:$Z$40,D31))*(_辅助!$Z$1:$Z$40<>""),0),0),0)=0,"",INDEX(_辅助!$AA$1:$AA$40,IFERROR(MATCH(1,INDEX(ISNUMBER(SEARCH(_辅助!$Z$1:$Z$40,D31))*(_辅助!$Z$1:$Z$40<>""),0),0),0)))),IF(IFERROR(MATCH(1,INDEX(ISNUMBER(SEARCH(_辅助!$Z$1:$Z$40,D31))*(_辅助!$Z$1:$Z$40<>""),0),0),0)=0,"",INDEX(_辅助!$AA$1:$AA$40,IFERROR(MATCH(1,INDEX(ISNUMBER(SEARCH(_辅助!$Z$1:$Z$40,D31))*(_辅助!$Z$1:$Z$40<>""),0),0),0))))) | AD31: =IF(O31<>"",O31,AC31) | AE31: =IF(C31="","",IFERROR(INDEX(基础资料!$H$5:$H$24,MATCH(C31,基础资料!$G$5:$G$24,0))&"","")) -> 银行 | AF31: =IF(AD31="","",IFERROR(INDEX(基础资料!$H$5:$H$24,MATCH(AD31,基础资料!$G$5:$G$24,0))&"","")) | AG31: =IF(OR(D31="",R31=0),"",IFERROR(INDEX(基础资料!$AC$5:$AC$164,IF(IF(F31<>"","支","收")="收",MATCH(1,INDEX(ISNUMBER(SEARCH(_辅助!$AB$1:$AB$160,D31))*(_辅助!$AB$1:$AB$160<>""),0),0),MATCH(1,INDEX(ISNUMBER(SEARCH(_辅助!$AC$1:$AC$160,D31))*(_辅助!$AC$1:$AC$160<>""),0),0)))&"","")) -> 办公费 | AH31: =IF(R31=0,"",IF(OR(IFERROR(INDEX(基础资料!$T$5:$T$64,MATCH(I31,基础资料!$S$5:$S$64,0))&"","")="收",IFERROR(INDEX(基础资料!$T$5:$T$64,MATCH(I31,基础资料!$S$5:$S$64,0))&"","")="支"),IFERROR(INDEX(基础资料!$T$5:$T$64,MATCH(I31,基础资料!$S$5:$S$64,0))&"",""),IF(R31>0,"收","支"))) -> 支 | AI31: =IF(N(AK31)=0,"",INDEX(_辅助!$R$1:$R$240,AK31)) | AJ31: =IF(OR(AI31="",L31<>""),0,SUMPRODUCT(ISNUMBER(SEARCH(_辅助!$R$1:$R$240,D31))*(_辅助!$R$1:$R$240<>"")*(1-ISNUMBER(SEARCH(_辅助!$R$1:$R$240,AI31)))*(_辅助!$S$1:$S$240<>T31))) -> 0 | AK31: =IF(D31="",0,IFERROR(MATCH(1,INDEX(ISNUMBER(SEARCH(_辅助!$R$1:$R$240,D31))*(_辅助!$R$1:$R$240<>""),0),0),0)) -> 0 | AL31: =IF(D31="",0,IFERROR(MATCH(1,INDEX(ISNUMBER(SEARCH(_辅助!$V$1:$V$900,D31))*(_辅助!$V$1:$V$900<>""),0),0),0)) -> 0 | AM31: =IF(AB31="",0,IFERROR(MATCH(1,INDEX(ISNUMBER(SEARCH(_辅助!$V$1:$V$900,AB31))*(_辅助!$V$1:$V$900<>""),0),0),0)) -> 0 | AN31: =IF(ISNUMBER(B31),INT(B31),0) -> 46170 | AO31: =IF(AND(X31="应收账款",R31>0,AN31>0,H31<>""),H31&"|"&COUNTIFS(资金流水!$H$6:$H$2005,H31,资金流水!$X$6:$X$2005,"应收账款",资金流水!$R$6:$R$2005,">0",资金流水!$AN$6:$AN$2005,">0",资金流水!$AN$6:$AN$2005,"<="&AN31),"") | AP31: =IF(AND(J31<>"",R31<0,AN31>0),J31&"|"&COUNTIFS(资金流水!$J$6:$J$2005,J31,资金流水!$R$6:$R$2005,"<0",资金流水!$AN$6:$AN$2005,">0",资金流水!$AN$6:$AN$2005,"<="&AN31),"") | AQ31: =IF(AND(X31="其他应收款",AN31>0,J31<>""),J31&"|"&(COUNTIFS(资金流水!$J$6:$J$2005,J31,资金流水!$X$6:$X$2005,"其他应收款",资金流水!$AN$6:$AN$2005,">0",资金流水!$AN$6:$AN$2005,"<"&AN31)+COUNTIFS($J$6:J31,J31,$X$6:X31,"其他应收款",$AN$6:AN31,AN31)),"")
A32: =IF(AND(B32="",D32="",E32="",F32=""),"",ROW()-5) -> 27 | B32: 46145 | C32: 王伟个人户 | D32: 支付顺丰快递费 | F32: 23 | G32: =IF(C32="","",ROUND(IFERROR(INDEX(基础资料!$K$5:$K$24,MATCH(C32,基础资料!$G$5:$G$24,0)),0)+SUMIFS($R$6:R32,$C$6:C32,C32)-SUMIFS($R$6:R32,$AD$6:AD32,C32,$X$6:X32,"账户互转"),2)) -> -190023 | H32: =IF(L32<>"",L32,T32) | I32: =IF(M32<>"",M32,U32) -> 办公费 | J32: =IF(N32<>"",N32,V32) | K32: =IF(AND(B32="",D32="",E32="",F32=""),"",IF(C32="","✗ 没选账户",IF(AE32="","✗ 账户不在【基础资料】② 里",IF(NOT(ISNUMBER(B32)),"✗ 日期要填成日期（2026/5/1）",IF(AND(ISNUMBER(B32),B32<基础资料!$C$9),"✗ 日期早于建账日期（建账前的放【期初余额】）",IF(AND(N(E32)<>0,N(F32)<>0),"✗ 收入、支出只填一边",IF(R32=0,"✗ 没有金额",IF(I32="","✗ 认不出收支类别：在「改类别」选",IF(W32="？","✗ 收支类别不在【基础资料】③ 里",IF(OR(I32="管理人员工资",I32="折旧费"),"✗ 这一类是自动算的，流水里不能选（发工资选「工资」，买设备选「固定资产购置」）",IF(AND(OR(X32="材料费",X32="人工费",X32="分包费",X32="机械运输费",X32="其他直接费",X32="票据贴息",X32="应收账款"),H32=""),"✗ 这一笔要选项目（摘要里的项目没在【项目档案】的话先去加上）",IF(AND(H32<>"",COUNTIF(项目档案!$B$4:$B$63,H32)=0),"✗ 项目不在【项目档案】里",IF(AND(OR(IFERROR(INDEX(基础资料!$W$5:$W$64,MATCH(I32,基础资料!$S$5:$S$64,0))&"","")="人",IFERROR(INDEX(基础资料!$W$5:$W$64,MATCH(I32,基础资料!$S$5:$S$64,0))&"","")="单位"),J32=""),"✗ 这一笔要选是谁（改单位/人）",IF(AND(I32="付应付款",NOT(OR(Z32="材料供应商",Z32="分包",Z32="机械运输",Z32="其他"))),"✗ 付应付款要选材料商、分包或机械单位",IF(AND(I32="付应付款",Y32=0),"✗ 这家没有应付：先在【应付登记】登记（现买现付的选材料费等）",IF(AND(OR(I32="工资",I32="工资退回"),AA32=0),"✗ 工资要选管理人员或工人（临时工选「临时工工资」）",IF(AND(I32="账户互转",AD32=""),"✗ 账户互转要在「对方账户」选（借款、报销选那个人的个人户）",IF(AND(I32="账户互转",AF32=""),"✗ 对方账户不在【基础资料】② 里",IF(AND(I32="账户互转",AD32=C32),"✗ 对方账户不能是自己",IF(IF(I32="账户互转",COUNTIFS(资金流水!$C$6:$C$2005,AD32,资金流水!$AD$6:$AD$2005,C32,资金流水!$I$6:$I$2005,"账户互转",资金流水!$R$6:$R$2005,-R32)>0,FALSE),"✗ 对方账户那边也记了这笔互转（只记一边：清空其中一行的内容）",IF(AJ32>0,"⚠ 摘要里有两个项目：拆成几行，或在「改项目」选",IF(AND(I32<>"账户互转",O32<>""),"⚠ 填了对方账户但类别不是账户互转（对方账户不起作用）",IF(AND(J32<>"",Z32=""),"⚠ 单位/人没在【往来单位】登记",IF(AND(N(F32)<0,AH32="收"),"⚠ 这是收款，以后请记在收入栏",IF(N(E32)<0,"⚠ 收入填了负数，已按支出算",IF(N(F32)<0,"↩ 冲回（退款）",IF(AND(R32<0,I32<>"固定资产购置",I32<>"付应付款",ISNUMBER(B32),IFERROR(SUMPRODUCT(ISNUMBER(SEARCH(基础资料!$AJ$5:$AJ$34,D32))*(基础资料!$AJ$5:$AJ$34<>"")*((AN32-基础资料!$AK$5:$AK$34)<=30)*((AN32-基础资料!$AK$5:$AK$34)>=-30)),0)>0),"⚠ 像是在买【基础资料】⑥ 登记的车/设备：类别改成「固定资产购置」，不然成本算两遍",IF(AND(OR(I32="材料费",I32="分包费",I32="机械运输费",I32="其他直接费"),J32="",H32<>"",COUNTIFS(应付登记!$E$5:$E$1004,H32,应付登记!$G$5:$G$1004,-R32)>0),"⚠ 这个项目有同样金额的应付登记：是付那家的，改类别选「付应付款」、改单位选那家（不然成本算两遍）","√")))))))))))))))))))))))))))) -> √ | R32: =ROUND(N(E32)-N(F32),2) -> -23 | S32: =IF(ISNUMBER(B32),YEAR(B32)*100+MONTH(B32),"") -> 202605 | T32: =IF(N(AK32)=0,"",INDEX(_辅助!$S$1:$S$240,AK32)) | U32: =IF(OR(D32="",R32=0),"",IF(AND(Z32="临时工",R32<0),"临时工工资",IF(AG32="",IF(AA32=1,"工资",IF(Z32="临时工","临时工工资",IF(Z32="甲方/总包","工程款",IF(AND(OR(Z32="材料供应商",Z32="分包",Z32="机械运输"),Y32=1),"付应付款","")))),IF(AND(Y32=1,OR(Z32="材料供应商",Z32="分包",Z32="机械运输",Z32="其他"),OR(AG32="材料费",AG32="分包费",AG32="机械运输费",AG32="其他直接费",AG32="工资",AG32="临时工工资")),"付应付款",AG32)))) -> 办公费 | V32: =IF(D32="","",IF(N(AM32)>0,IF(N(AM32)=0,"",INDEX(_辅助!$W$1:$W$900,AM32)),IF(N(AL32)=0,"",INDEX(_辅助!$W$1:$W$900,AL32)))) | W32: =IF(I32="","",IFERROR(INDEX(基础资料!$V$5:$V$64,MATCH(I32,基础资料!$S$5:$S$64,0))&"","？")) -> 公司间接费 | X32: =IF(R32=0,"",IF(OR(I32="",IFERROR(INDEX(基础资料!$U$5:$U$64,MATCH(I32,基础资料!$S$5:$S$64,0))&"","")=""),"待分类",IF(OR(I32="付应付款",IFERROR(INDEX(基础资料!$U$5:$U$64,MATCH(I32,基础资料!$S$5:$S$64,0))&"","")="应付款"),IF(Z32="材料供应商","应付材料款",IF(Z32="分包","应付分包款",IF(Z32="机械运输","应付机械运输费","应付其他款"))),IFERROR(INDEX(基础资料!$U$5:$U$64,MATCH(I32,基础资料!$S$5:$S$64,0))&"","")))) -> 办公费 | Y32: =IF(J32="",0,IF(COUNTIF(应付登记!$D$5:$D$1004,J32)+COUNTIF(期初余额!$P$5:$P$204,J32)>0,1,0)) -> 0 | Z32: =IF(J32="","",IFERROR(INDEX(往来单位!$C$4:$C$303,MATCH(J32,往来单位!$B$4:$B$303,0))&"","")) | AA32: =IF(OR(Z32="管理人员",Z32="工人"),1,0) -> 0 | AB32: =IF(ISERROR(FIND("代",D32)),"",IFERROR(MID(D32,FIND("代",D32)+1,FIND("付",D32,FIND("代",D32))-FIND("代",D32)-1),"")) | AC32: =IF(I32<>"账户互转","",IF(J32<>"",IFERROR(INDEX(_辅助!$G$1:$G$40,MATCH(J32,_辅助!$F$1:$F$40,0)),IF(IFERROR(MATCH(1,INDEX(ISNUMBER(SEARCH(_辅助!$Z$1:$Z$40,D32))*(_辅助!$Z$1:$Z$40<>""),0),0),0)=0,"",INDEX(_辅助!$AA$1:$AA$40,IFERROR(MATCH(1,INDEX(ISNUMBER(SEARCH(_辅助!$Z$1:$Z$40,D32))*(_辅助!$Z$1:$Z$40<>""),0),0),0)))),IF(IFERROR(MATCH(1,INDEX(ISNUMBER(SEARCH(_辅助!$Z$1:$Z$40,D32))*(_辅助!$Z$1:$Z$40<>""),0),0),0)=0,"",INDEX(_辅助!$AA$1:$AA$40,IFERROR(MATCH(1,INDEX(ISNUMBER(SEARCH(_辅助!$Z$1:$Z$40,D32))*(_辅助!$Z$1:$Z$40<>""),0),0),0))))) | AD32: =IF(O32<>"",O32,AC32) | AE32: =IF(C32="","",IFERROR(INDEX(基础资料!$H$5:$H$24,MATCH(C32,基础资料!$G$5:$G$24,0))&"","")) -> 个人户 | AF32: =IF(AD32="","",IFERROR(INDEX(基础资料!$H$5:$H$24,MATCH(AD32,基础资料!$G$5:$G$24,0))&"","")) | AG32: =IF(OR(D32="",R32=0),"",IFERROR(INDEX(基础资料!$AC$5:$AC$164,IF(IF(F32<>"","支","收")="收",MATCH(1,INDEX(ISNUMBER(SEARCH(_辅助!$AB$1:$AB$160,D32))*(_辅助!$AB$1:$AB$160<>""),0),0),MATCH(1,INDEX(ISNUMBER(SEARCH(_辅助!$AC$1:$AC$160,D32))*(_辅助!$AC$1:$AC$160<>""),0),0)))&"","")) -> 办公费 | AH32: =IF(R32=0,"",IF(OR(IFERROR(INDEX(基础资料!$T$5:$T$64,MATCH(I32,基础资料!$S$5:$S$64,0))&"","")="收",IFERROR(INDEX(基础资料!$T$5:$T$64,MATCH(I32,基础资料!$S$5:$S$64,0))&"","")="支"),IFERROR(INDEX(基础资料!$T$5:$T$64,MATCH(I32,基础资料!$S$5:$S$64,0))&"",""),IF(R32>0,"收","支"))) -> 支 | AI32: =IF(N(AK32)=0,"",INDEX(_辅助!$R$1:$R$240,AK32)) | AJ32: =IF(OR(AI32="",L32<>""),0,SUMPRODUCT(ISNUMBER(SEARCH(_辅助!$R$1:$R$240,D32))*(_辅助!$R$1:$R$240<>"")*(1-ISNUMBER(SEARCH(_辅助!$R$1:$R$240,AI32)))*(_辅助!$S$1:$S$240<>T32))) -> 0 | AK32: =IF(D32="",0,IFERROR(MATCH(1,INDEX(ISNUMBER(SEARCH(_辅助!$R$1:$R$240,D32))*(_辅助!$R$1:$R$240<>""),0),0),0)) -> 0 | AL32: =IF(D32="",0,IFERROR(MATCH(1,INDEX(ISNUMBER(SEARCH(_辅助!$V$1:$V$900,D32))*(_辅助!$V$1:$V$900<>""),0),0),0)) -> 0 | AM32: =IF(AB32="",0,IFERROR(MATCH(1,INDEX(ISNUMBER(SEARCH(_辅助!$V$1:$V$900,AB32))*(_辅助!$V$1:$V$900<>""),0),0),0)) -> 0 | AN32: =IF(ISNUMBER(B32),INT(B32),0) -> 46145 | AO32: =IF(AND(X32="应收账款",R32>0,AN32>0,H32<>""),H32&"|"&COUNTIFS(资金流水!$H$6:$H$2005,H32,资金流水!$X$6:$X$2005,"应收账款",资金流水!$R$6:$R$2005,">0",资金流水!$AN$6:$AN$2005,">0",资金流水!$AN$6:$AN$2005,"<="&AN32),"") | AP32: =IF(AND(J32<>"",R32<0,AN32>0),J32&"|"&COUNTIFS(资金流水!$J$6:$J$2005,J32,资金流水!$R$6:$R$2005,"<0",资金流水!$AN$6:$AN$2005,">0",资金流水!$AN$6:$AN$2005,"<="&AN32),"") | AQ32: =IF(AND(X32="其他应收款",AN32>0,J32<>""),J32&"|"&(COUNTIFS(资金流水!$J$6:$J$2005,J32,资金流水!$X$6:$X$2005,"其他应收款",资金流水!$AN$6:$AN$2005,">0",资金流水!$AN$6:$AN$2005,"<"&AN32)+COUNTIFS($J$6:J32,J32,$X$6:X32,"其他应收款",$AN$6:AN32,AN32)),"")
