Workbook
Name 年度: 基础资料!$B$5
Name 年初日: 基础资料!$B$7
Name 年末日: 基础资料!$B$8
Name 客户列表: OFFSET(总览汇总!$B$5,0,0,MAX(1,COUNTA(总览汇总!$B$5:$B$304)),1)
Name 商品列表: OFFSET(基础资料!$E$5,0,0,MAX(1,COUNTA(基础资料!$E$5:$E$104)),1)
Name 供应商列表: OFFSET(基础资料!$Q$5,0,0,MAX(1,COUNTA(基础资料!$Q$5:$Q$54)),1)
Name 账户列表: OFFSET(基础资料!$W$5,0,0,MAX(1,COUNTA(基础资料!$W$5:$W$24)),1)
Name 收支项目列表: OFFSET(基础资料!$AC$5,0,0,MAX(1,COUNTA(基础资料!$AC$5:$AC$34)),1)
Name 费用项目列表: OFFSET(基础资料!$AI$5,0,0,MAX(1,COUNTA(基础资料!$AI$5:$AI$54)),1)

Sheet 首页
A1: =IF(基础资料!B6="","饮料经销财务模板",基础资料!B6)&" · "&年度&"年度账" -> 饮料经销财务模板 · 2026年度账
A2: 💡 日常只录四张表：资金台帐（收钱付钱）、出库明细（送货）、存条明细（客户存条）、采购进货（进货）；报损照原来每月一张。其余全部自动：总览、库存、收付款明细、对账单、利润表、资产负债表。淡黄/白格子手填，灰格子别动。
A4: 关键数（截至今天录入的数据）
A5: 本年销售额 | B5: 本年毛利 | C5: 本年净利润 | D5: 当前资金余额 | E5: 客户欠我们 | F5: 客户存条/预存 | G5: 欠厂家货款 | H5: 数据校验待改项
A6: =利润表!Q7 -> 1707307.7 | B6: =利润表!Q12 -> 571498.93 | C6: =利润表!Q24 -> 553843.71 | D6: =基础资料!Y25 -> 3869309.7 | E6: =SUMIF(总览汇总!$G$5:$G$304,">0") -> 61456.5 | F6: =-SUMIF(总览汇总!$G$5:$G$304,"<0") -> 2223458.5 | G6: =SUMIF(_辅助!$K$5:$K$54,">0") -> 0 | H6: =数据校验!$C$32 -> 1
A7: 「欠厂家货款」按资产负债表选定月份月底算；其余是全年/当前数。
A9: 表格导航（点表名直接跳过去）
A10: 表名 | B10: 干什么的 | D10: 你要做什么
A11: 资金台帐 | B11: 收支混合录入，逐笔出账户余额和总余额 | D11: ★ 每收/付一笔钱记一行；收客户的选客户，付厂家的选供应商，花钱的选费用项目
A12: 出库明细 | B12: （原表）客户领货/送货 | D12: ★ 每次送货记一行
A13: 存条明细 | B13: （原表）客户存条（预付的货） | D13: ★ 客户存条时记，一个商品一行
A14: 采购进货 | B14: （新）从厂家进货 | D14: ★ 每张进货单记，厂家搭赠填赠品数量
A15: 2026年9月报损 | B15: （原表）每月过期报损 | D15: ★ 每月一张，照原来的填；新月份复制上月的表，并在基础资料登记表名
A16: 基础资料 | B16: 商品、供应商、资金账户、收支项目、费用项目 | D16: 新商品/新账户先在这里加；商品的参考进价要填
A17: 总览汇总 | B17: （原表）客户存条&货款总览——客户名单也在这 | D17: 新客户在 B 列加；已付款自动从资金台帐取
A18: 商品库存 | B18: （原表）每个客户每个商品的存条库存 | D18: 全自动
A19: 收付款明细 | B19: （原表）收付款明细 | D19: 全自动，从资金台帐提取
A20: 客户查询 | B20: （原表）客户快速查询 | D20: 选客户看
A21: 收付款汇总 | B21: 按月收付、按客户/供应商汇总 | D21: 全自动
... A29: 数据校验 | B29: 所有数据问题一表列出 | D29: 有 ✗ 就按提示改
A31: 钱和货是怎么流的
A32: 1. 客户付存条款/货款 → 资金台帐（选客户）→ 总览汇总「已付款」、收付款明细、客户对账单
A33: 2. 客户领货 → 出库明细 → 总览汇总「已领用」、商品库存、利润表「主营业务收入」、公司库存「出库」
A34: 3. 从厂家进货 → 采购进货 → 公司库存、成本计算（加权平均进价）、供应商对账单「进货」
A35: 4. 付厂家货款 → 资金台帐（选供应商）→ 供应商对账单「付款」、资产负债表「应付账款」
A36: 5. 各项开支 → 资金台帐（选费用项目）→ 费用汇总 → 利润表
A37: 6. 过期报损 → 各月报损表 → 报损汇总一览、利润表「商品报损损失」、公司库存「报损」
A39: 颜色
B40: 淡黄：手填的格子 | D40: 淡灰：公式自动算，别改 | F40: 亮黄：查询/报表的选择格 | H40: 淡红：校验发现的问题

Sheet 基础资料
A1: 基础资料（参数 · 商品 · 供应商 · 资金账户 · 收支项目 · 费用项目 · 报损月表）
A2: 💡 淡黄格子手填，灰格子自动。这里的清单就是各录入表的下拉内容——清单里没有的先在这里加一行，再去录。客户名单还在【总览汇总】B 列（跟原来一样，新客户在那里加）。不要插入或删除行，直接往下面的空行里填。
A3: 参数 | D3: 商品档案（出库 / 存条 / 采购 的「商品品类」都从这里选） | P3: 供应商档案 | V3: 资金账户（资金台帐「账户」下拉） | AB3: 收支项目（资金台帐「收支项目」下拉；前 6 个名称别改，公式按名字认） | AH3: 费用项目（资金台帐「费用项目」下拉） | AM3: 报损月表清单（几月的报损记在哪张表）
A4: 项目 | B4: 值 | D4: 序号 | E4: 商品名称 | F4: 供应商 (所属公司) | G4: 报损表品名 | H4: 规格 | I4: 每件 瓶数 | J4: 参考进价 (元/件) | K4: 参考售价 (元/件) | L4: 期初库存 (件) | M4: 期初单价 (元/件) | N4: 期初金额 (元) | P4: 序号 | Q4: 供应商名称 | R4: 年初应付(元) 正=我欠他 负=预付 | S4: 联系人/电话 | T4: 备注 | V4: 序号 | W4: 账户名称 | X4: 年初余额(元) | Y4: 当前余额(元) 自动 | Z4: 备注 | AB4: 序号 | AC4: 收支项目 | AD4: 方向 | AE4: 去向 | AF4: 说明 | AH4: 序号 | AI4: 费用项目 | AJ4: 利润表归类 | AK4: 说明 | AM4: 月份 | AN4: 报损表名 | AO4: 说明
A5: 会计年度 | B5: 2026 | D5: =IF(E5="","",ROW()-4) -> 1 | E5: 大东鹏 | F5: 东鹏公司 | G5: 东鹏500ML特饮 | H5: 1*24 | I5: 24 | J5: 77.52 | K5: 90 | N5: =IF(N(L5)=0,"",L5*N(M5)) | P5: =IF(Q5="","",ROW()-4) -> 1 | Q5: 东鹏公司 | T5: 东鹏特饮、补水啦、果之茶、大咖等 | V5: =IF(W5="","",ROW()-4) -> 1 | W5: 收款码 | Y5: =IF(W5="","",N(X5)+SUMIF(资金台帐!$C$7:$C$3006,W5,资金台帐!$F$7:$F$3006)-SUMIF(资金台帐!$C$7:$C$3006,W5,资金台帐!$G$7:$G$3006)) -> 3857959.7 | Z5: 原收付款明细的「收款码」 | AB5: =IF(AC5="","",ROW()-4) -> 1 | AC5: 客户回款 | AD5: 收 | AE5: 应收 | AF5: 客户付货款、存条款。要选【客户】，自动冲减他在总览汇总的未付货款 | AH5: =IF(AI5="","",ROW()-4) -> 1 | AI5: 工资 | AJ5: 销售费用 | AK5: 司机、业务员、装卸工工资 | AM5: 1 | AO5: =IF(AN5="","（这个月没有报损表）",IF(ISREF(INDIRECT("'"&AN5&"'!A1")),"√ 找到这张表","✗ 没有叫这个名字的表")) -> （这个月没有报损表）
A6: 公司名称 | D6: =IF(E6="","",ROW()-4) -> 2 | E6: 小东鹏 | F6: 东鹏公司 | G6: 东鹏250ML特饮 | H6: 1*24 | I6: 24 | J6: 37.92 | K6: 50 | N6: =IF(N(L6)=0,"",L6*N(M6)) | P6: =IF(Q6="","",ROW()-4) -> 2 | Q6: 农夫山泉公司 | T6: 农夫饮料、水 | V6: =IF(W6="","",ROW()-4) -> 2 | W6: 农业工账 | Y6: =IF(W6="","",N(X6)+SUMIF(资金台帐!$C$7:$C$3006,W6,资金台帐!$F$7:$F$3006)-SUMIF(资金台帐!$C$7:$C$3006,W6,资金台帐!$G$7:$G$3006)) -> 11350 | Z6: 原收付款明细第 39 行（阳光超市 11,350）用的账户 | AB6: =IF(AC6="","",ROW()-4) -> 2 | AC6: 客户退款 | AD6: 支 | AE6: 应收 | AF6: 退钱给客户。要选【客户】 | AH6: =IF(AI6="","",ROW()-4) -> 2 | AI6: 提成奖金 | AJ6: 销售费用 | AM6: 2 | AO6: =IF(AN6="","（这个月没有报损表）",IF(ISREF(INDIRECT("'"&AN6&"'!A1")),"√ 找到这张表","✗ 没有叫这个名字的表")) -> （这个月没有报损表）
A7: 年初日 | B7: =DATE(B5,1,1) -> 46023 | D7: =IF(E7="","",ROW()-4) -> 3 | E7: 555补水 | F7: 东鹏公司 | G7: 东鹏555补水 | H7: 1*24 | I7: 24 | J7: 54.816 | K7: 65 | N7: =IF(N(L7)=0,"",L7*N(M7)) | P7: =IF(Q7="","",ROW()-4) -> 3 | Q7: 青岛公司 | T7: 青岛啤酒 | V7: =IF(W7="","",ROW()-4) -> 3 | W7: 现金 | Y7: =IF(W7="","",N(X7)+SUMIF(资金台帐!$C$7:$C$3006,W7,资金台帐!$F$7:$F$3006)-SUMIF(资金台帐!$C$7:$C$3006,W7,资金台帐!$G$7:$G$3006)) -> 0 | AB7: =IF(AC7="","",ROW()-4) -> 3 | AC7: 供应商付款 | AD7: 支 | AE7: 应付 | AF7: 付厂家/供应商货款。要选【供应商】，自动冲减应付 | AH7: =IF(AI7="","",ROW()-4) -> 3 | AI7: 运费油费 | AJ7: 销售费用 | AK7: 送货油费、过路费、外请运输 | AM7: 3 | AO7: =IF(AN7="","（这个月没有报损表）",IF(ISREF(INDIRECT("'"&AN7&"'!A1")),"√ 找到这张表","✗ 没有叫这个名字的表")) -> （这个月没有报损表）
A8: 年末日 | B8: =DATE(B5,12,31) -> 46387 | D8: =IF(E8="","",ROW()-4) -> 4 | E8: 1L补水 | F8: 东鹏公司 | G8: 东鹏1L补水 | H8: 1*12 | I8: 12 | J8: 43.2696 | K8: 55 | N8: =IF(N(L8)=0,"",L8*N(M8)) | P8: =IF(Q8="","",ROW()-4) -> 4 | Q8: 其他公司 | T8: 艾精隆瓜子花生等 | V8: =IF(W8="","",ROW()-4) -> 4 | W8: 微信 | Y8: =IF(W8="","",N(X8)+SUMIF(资金台帐!$C$7:$C$3006,W8,资金台帐!$F$7:$F$3006)-SUMIF(资金台帐!$C$7:$C$3006,W8,资金台帐!$G$7:$G$3006)) -> 0 | AB8: =IF(AC8="","",ROW()-4) -> 4 | AC8: 供应商退款 | AD8: 收 | AE8: 应付 | AF8: 厂家退回来的货款。要选【供应商】 | AH8: =IF(AI8="","",ROW()-4) -> 4 | AI8: 车辆费用 | AJ8: 销售费用 | AK8: 车辆保养维修、保险、年检 | AM8: 4 | AO8: =IF(AN8="","（这个月没有报损表）",IF(ISREF(INDIRECT("'"&AN8&"'!A1")),"√ 找到这张表","✗ 没有叫这个名字的表")) -> （这个月没有报损表）
A9: 年初借款余额 | B9: 0 | D9: =IF(E9="","",ROW()-4) -> 5 | E9: 小果之茶 | F9: 东鹏公司 | G9: 东鹏小果茶 | H9: 1*24 | I9: 24 | K9: 47 | N9: =IF(N(L9)=0,"",L9*N(M9)) | P9: =IF(Q9="","",ROW()-4) | V9: =IF(W9="","",ROW()-4) -> 5 | W9: 支付宝 | Y9: =IF(W9="","",N(X9)+SUMIF(资金台帐!$C$7:$C$3006,W9,资金台帐!$F$7:$F$3006)-SUMIF(资金台帐!$C$7:$C$3006,W9,资金台帐!$G$7:$G$3006)) -> 0 | AB9: =IF(AC9="","",ROW()-4) -> 5 | AC9: 厂家返利 | AD9: 收 | AE9: 返利收入 | AF9: 返利、陈列补贴、报损补偿等厂家给的钱，建议选上【供应商】 | AH9: =IF(AI9="","",ROW()-4) -> 5 | AI9: 装卸费 | AJ9: 销售费用 | AM9: 5 | AO9: =IF(AN9="","（这个月没有报损表）",IF(ISREF(INDIRECT("'"&AN9&"'!A1")),"√ 找到这张表","✗ 没有叫这个名字的表")) -> （这个月没有报损表）
A10: 年初其他应收(+)/应付(-) | B10: 0 | D10: =IF(E10="","",ROW()-4) -> 6 | E10: 1L果之茶 | F10: 东鹏公司 | G10: 东鹏1L果之茶 | H10: 1*12 | I10: 12 | K10: 43 | N10: =IF(N(L10)=0,"",L10*N(M10)) | P10: =IF(Q10="","",ROW()-4) | V10: =IF(W10="","",ROW()-4) -> 6 | W10: 银行卡 | Y10: =IF(W10="","",N(X10)+SUMIF(资金台帐!$C$7:$C$3006,W10,资金台帐!$F$7:$F$3006)-SUMIF(资金台帐!$C$7:$C$3006,W10,资金台帐!$G$7:$G$3006)) -> 0 | AB10: =IF(AC10="","",ROW()-4) -> 6 | AC10: 费用支出 | AD10: 支 | AE10: 费用 | AF10: 工资、运费、房租……要选【费用项目】 | AH10: =IF(AI10="","",ROW()-4) -> 6 | AI10: 促销陈列费 | AJ10: 销售费用 | AK10: 给店里的陈列费、促销品（厂家报销的记厂家返利） | AM10: 6 | AN10: 报损明细台账 | AO10: =IF(AN10="","（这个月没有报损表）",IF(ISREF(INDIRECT("'"&AN10&"'!A1")),"√ 找到这张表","✗ 没有叫这个名字的表")) -> √ 找到这张表
D11: =IF(E11="","",ROW()-4) -> 7 | E11: 港式奶茶 | F11: 东鹏公司 | G11: 东鹏港式奶茶 | H11: 1*24 | I11: 24 | K11: 69 | N11: =IF(N(L11)=0,"",L11*N(M11)) | P11: =IF(Q11="","",ROW()-4) | V11: =IF(W11="","",ROW()-4) | Y11: =IF(W11="","",N(X11)+SUMIF(资金台帐!$C$7:$C$3006,W11,资金台帐!$F$7:$F$3006)-SUMIF(资金台帐!$C$7:$C$3006,W11,资金台帐!$G$7:$G$3006)) | AB11: =IF(AC11="","",ROW()-4) -> 7 | AC11: 其他收入 | AD11: 收 | AE11: 其他收入 | AF11: 卖废品/空箱、利息等零星收入 | AH11: =IF(AI11="","",ROW()-4) -> 7 | AI11: 业务招待费 | AJ11: 管理费用 | AM11: 7 | AN11: 2026年7月报损 | AO11: =IF(AN11="","（这个月没有报损表）",IF(ISREF(INDIRECT("'"&AN11&"'!A1")),"√ 找到这张表","✗ 没有叫这个名字的表")) -> √ 找到这张表
A12: 「去向」说明（收支项目落到报表哪一行） | D12: =IF(E12="","",ROW()-4) -> 8 | E12: 大咖 | F12: 东鹏公司 | G12: 东鹏500大咖 | H12: 1*15 | I12: 15 | J12: 73.08 | K12: 83 | N12: =IF(N(L12)=0,"",L12*N(M12)) | P12: =IF(Q12="","",ROW()-4) | V12: =IF(W12="","",ROW()-4) | Y12: =IF(W12="","",N(X12)+SUMIF(资金台帐!$C$7:$C$3006,W12,资金台帐!$F$7:$F$3006)-SUMIF(资金台帐!$C$7:$C$3006,W12,资金台帐!$G$7:$G$3006)) | AB12: =IF(AC12="","",ROW()-4) -> 8 | AC12: 股东投入 | AD12: 收 | AE12: 投入 | AF12: 老板往账上投钱 | AH12: =IF(AI12="","",ROW()-4) -> 8 | AI12: 管理人员工资 | AJ12: 管理费用 | AM12: 8 | AN12: 2026年8月报损 | AO12: =IF(AN12="","（这个月没有报损表）",IF(ISREF(INDIRECT("'"&AN12&"'!A1")),"√ 找到这张表","✗ 没有叫这个名字的表")) -> √ 找到这张表
A13: 应收 | B13: 冲减客户未付货款（总览汇总·已付款） | D13: =IF(E13="","",ROW()-4) -> 9 | E13: 330大咖 | F13: 东鹏公司 | K13: 90 | N13: =IF(N(L13)=0,"",L13*N(M13)) | P13: =IF(Q13="","",ROW()-4) | V13: =IF(W13="","",ROW()-4) | Y13: =IF(W13="","",N(X13)+SUMIF(资金台帐!$C$7:$C$3006,W13,资金台帐!$F$7:$F$3006)-SUMIF(资金台帐!$C$7:$C$3006,W13,资金台帐!$G$7:$G$3006)) | AB13: =IF(AC13="","",ROW()-4) -> 9 | AC13: 股东提取 | AD13: 支 | AE13: 提取 | AF13: 老板从账上拿钱自用 | AH13: =IF(AI13="","",ROW()-4) -> 9 | AI13: 仓库租金 | AJ13: 管理费用 | AM13: 9 | AN13: 2026年9月报损 | AO13: =IF(AN13="","（这个月没有报损表）",IF(ISREF(INDIRECT("'"&AN13&"'!A1")),"√ 找到这张表","✗ 没有叫这个名字的表")) -> √ 找到这张表
A14: 应付 | B14: 冲减欠供应商的货款 | D14: =IF(E14="","",ROW()-4) -> 10 | E14: 小咖 | F14: 东鹏公司 | K14: 90 | N14: =IF(N(L14)=0,"",L14*N(M14)) | P14: =IF(Q14="","",ROW()-4) | V14: =IF(W14="","",ROW()-4) | Y14: =IF(W14="","",N(X14)+SUMIF(资金台帐!$C$7:$C$3006,W14,资金台帐!$F$7:$F$3006)-SUMIF(资金台帐!$C$7:$C$3006,W14,资金台帐!$G$7:$G$3006)) | AB14: =IF(AC14="","",ROW()-4) -> 10 | AC14: 借入款项 | AD14: 收 | AE14: 借款 | AF14: 借进来的钱 | AH14: =IF(AI14="","",ROW()-4) -> 10 | AI14: 水电费 | AJ14: 管理费用 | AM14: 10 | AO14: =IF(AN14="","（这个月没有报损表）",IF(ISREF(INDIRECT("'"&AN14&"'!A1")),"√ 找到这张表","✗ 没有叫这个名字的表")) -> （这个月没有报损表）
A15: 费用 | B15: 按费用项目进利润表 | D15: =IF(E15="","",ROW()-4) -> 11 | E15: 小海岛椰 | F15: 东鹏公司 | G15: 东鹏小海岛椰 | H15: 1*12 | I15: 12 | J15: 29.52 | K15: 32 | N15: =IF(N(L15)=0,"",L15*N(M15)) | P15: =IF(Q15="","",ROW()-4) | V15: =IF(W15="","",ROW()-4) | Y15: =IF(W15="","",N(X15)+SUMIF(资金台帐!$C$7:$C$3006,W15,资金台帐!$F$7:$F$3006)-SUMIF(资金台帐!$C$7:$C$3006,W15,资金台帐!$G$7:$G$3006)) | AB15: =IF(AC15="","",ROW()-4) -> 11 | AC15: 归还借款 | AD15: 支 | AE15: 借款 | AF15: 还借款本金（利息记「费用支出·利息支出」） | AH15: =IF(AI15="","",ROW()-4) -> 11 | AI15: 通讯费 | AJ15: 管理费用 | AM15: 11 | AO15: =IF(AN15="","（这个月没有报损表）",IF(ISREF(INDIRECT("'"&AN15&"'!A1")),"√ 找到这张表","✗ 没有叫这个名字的表")) -> （这个月没有报损表）
A16: 返利收入 | B16: 利润表·其他业务收入 | D16: =IF(E16="","",ROW()-4) -> 12 | E16: 330海岛椰 | F16: 东鹏公司 | K16: 36 | N16: =IF(N(L16)=0,"",L16*N(M16)) | P16: =IF(Q16="","",ROW()-4) | V16: =IF(W16="","",ROW()-4) | Y16: =IF(W16="","",N(X16)+SUMIF(资金台帐!$C$7:$C$3006,W16,资金台帐!$F$7:$F$3006)-SUMIF(资金台帐!$C$7:$C$3006,W16,资金台帐!$G$7:$G$3006)) | AB16: =IF(AC16="","",ROW()-4) -> 12 | AC16: 内部转账 | AD16: 收支 | AE16: 转账 | AF16: 账户之间互转：转出账户记一行支出、转入账户记一行收入，两行都选这个 | AH16: =IF(AI16="","",ROW()-4) -> 12 | AI16: 办公费 | AJ16: 管理费用 | AM16: 12 | AO16: =IF(AN16="","（这个月没有报损表）",IF(ISREF(INDIRECT("'"&AN16&"'!A1")),"√ 找到这张表","✗ 没有叫这个名字的表")) -> （这个月没有报损表）
A17: 其他收入 | B17: 利润表·营业外收入 | D17: =IF(E17="","",ROW()-4) -> 13 | E17: 1.25海岛椰 | F17: 东鹏公司 | G17: 东鹏1.25L海岛椰 | H17: 1*6 | I17: 6 | K17: 51 | N17: =IF(N(L17)=0,"",L17*N(M17)) | P17: =IF(Q17="","",ROW()-4) | V17: =IF(W17="","",ROW()-4) | Y17: =IF(W17="","",N(X17)+SUMIF(资金台帐!$C$7:$C$3006,W17,资金台帐!$F$7:$F$3006)-SUMIF(资金台帐!$C$7:$C$3006,W17,资金台帐!$G$7:$G$3006)) | AB17: =IF(AC17="","",ROW()-4) -> 13 | AC17: 其他往来 | AD17: 收支 | AE17: 其他往来 | AF17: 押金、代收代付等以后要收回/付出的钱 | AH17: =IF(AI17="","",ROW()-4) -> 13 | AI17: 其他费用 | AJ17: 管理费用
A18: 投入 | B18: 资产负债表·股东投入 | D18: =IF(E18="","",ROW()-4) -> 14 | E18: 东鹏椰子水 | F18: 东鹏公司 | K18: 90 | N18: =IF(N(L18)=0,"",L18*N(M18)) | P18: =IF(Q18="","",ROW()-4) | V18: =IF(W18="","",ROW()-4) | Y18: =IF(W18="","",N(X18)+SUMIF(资金台帐!$C$7:$C$3006,W18,资金台帐!$F$7:$F$3006)-SUMIF(资金台帐!$C$7:$C$3006,W18,资金台帐!$G$7:$G$3006)) | AB18: =IF(AC18="","",ROW()-4) | AH18: =IF(AI18="","",ROW()-4) -> 14 | AI18: 手续费 | AJ18: 财务费用 | AK18: 收款码/银行手续费 | AM18: 新的一个月：右键上个月的报损表→移动或复制→建立副本，改成「2026年10月报损」这样的表名，清掉数量，再回这里填上表名。
A19: 提取 | B19: 资产负债表·股东提取 | D19: =IF(E19="","",ROW()-4) -> 15 | E19: 555椰子水 | F19: 东鹏公司 | K19: 93 | N19: =IF(N(L19)=0,"",L19*N(M19)) | P19: =IF(Q19="","",ROW()-4) | V19: =IF(W19="","",ROW()-4) | Y19: =IF(W19="","",N(X19)+SUMIF(资金台帐!$C$7:$C$3006,W19,资金台帐!$F$7:$F$3006)-SUMIF(资金台帐!$C$7:$C$3006,W19,资金台帐!$G$7:$G$3006)) | AB19: =IF(AC19="","",ROW()-4) | AH19: =IF(AI19="","",ROW()-4) -> 15 | AI19: 利息支出 | AJ19: 财务费用
A20: 借款 | B20: 资产负债表·短期借款 | D20: =IF(E20="","",ROW()-4) -> 16 | E20: 菊花茶 | F20: 东鹏公司 | G20: 东鹏菊花茶 | H20: 1*24 | I20: 24 | J20: 59.616 | N20: =IF(N(L20)=0,"",L20*N(M20)) | P20: =IF(Q20="","",ROW()-4) | V20: =IF(W20="","",ROW()-4) | Y20: =IF(W20="","",N(X20)+SUMIF(资金台帐!$C$7:$C$3006,W20,资金台帐!$F$7:$F$3006)-SUMIF(资金台帐!$C$7:$C$3006,W20,资金台帐!$G$7:$G$3006)) | AB20: =IF(AC20="","",ROW()-4) | AH20: =IF(AI20="","",ROW()-4) -> 16 | AI20: 税费 | AJ20: 税金及附加 | AK20: 按实际交的钱计
A21: 转账 | B21: 账户互转，不进报表（收支要成对） | D21: =IF(E21="","",ROW()-4) -> 17 | E21: 九制陈皮 | K21: 47 | N21: =IF(N(L21)=0,"",L21*N(M21)) | P21: =IF(Q21="","",ROW()-4) | V21: =IF(W21="","",ROW()-4) | Y21: =IF(W21="","",N(X21)+SUMIF(资金台帐!$C$7:$C$3006,W21,资金台帐!$F$7:$F$3006)-SUMIF(资金台帐!$C$7:$C$3006,W21,资金台帐!$G$7:$G$3006)) | AB21: =IF(AC21="","",ROW()-4) | AH21: =IF(AI21="","",ROW()-4) -> 17 | AI21: 罚款赔偿 | AJ21: 营业外支出
A22: 其他往来 | B22: 其他应收 / 其他应付（押金等） | D22: =IF(E22="","",ROW()-4) -> 18 | E22: 小焙好茶 | K22: 48 | N22: =IF(N(L22)=0,"",L22*N(M22)) | P22: =IF(Q22="","",ROW()-4) | V22: =IF(W22="","",ROW()-4) | Y22: =IF(W22="","",N(X22)+SUMIF(资金台帐!$C$7:$C$3006,W22,资金台帐!$F$7:$F$3006)-SUMIF(资金台帐!$C$7:$C$3006,W22,资金台帐!$G$7:$G$3006)) | AB22: =IF(AC22="","",ROW()-4) | AH22: =IF(AI22="","",ROW()-4) -> 18 | AI22: 所得税 | AJ22: 所得税费用
D23: =IF(E23="","",ROW()-4) -> 19 | E23: 1L焙好茶 | K23: 46 | N23: =IF(N(L23)=0,"",L23*N(M23)) | P23: =IF(Q23="","",ROW()-4) | V23: =IF(W23="","",ROW()-4) | Y23: =IF(W23="","",N(X23)+SUMIF(资金台帐!$C$7:$C$3006,W23,资金台帐!$F$7:$F$3006)-SUMIF(资金台帐!$C$7:$C$3006,W23,资金台帐!$G$7:$G$3006)) | AB23: =IF(AC23="","",ROW()-4) | AH23: =IF(AI23="","",ROW()-4)
D24: =IF(E24="","",ROW()-4) -> 20 | E24: 大鹏 | K24: 86 | N24: =IF(N(L24)=0,"",L24*N(M24)) | P24: =IF(Q24="","",ROW()-4) | V24: =IF(W24="","",ROW()-4) | Y24: =IF(W24="","",N(X24)+SUMIF(资金台帐!$C$7:$C$3006,W24,资金台帐!$F$7:$F$3006)-SUMIF(资金台帐!$C$7:$C$3006,W24,资金台帐!$G$7:$G$3006)) | AB24: =IF(AC24="","",ROW()-4) | AH24: =IF(AI24="","",ROW()-4)
D25: =IF(E25="","",ROW()-4) -> 21 | E25: 500农夫饮料 | F25: 农夫山泉公司 | G25: 农夫500ML饮料 | H25: 1*15 | I25: 15 | J25: 46.005 | K25: 52 | N25: =IF(N(L25)=0,"",L25*N(M25)) | P25: =IF(Q25="","",ROW()-4) | W25: 合计 | X25: =SUM(X5:X24) -> 0 | Y25: =SUM(Y5:Y24) -> 3869309.7 | AB25: =IF(AC25="","",ROW()-4) | AH25: =IF(AI25="","",ROW()-4)
D26: =IF(E26="","",ROW()-4) -> 22 | E26: 900农夫饮料 | F26: 农夫山泉公司 | G26: 农夫900ML饮料 | H26: 1*12 | I26: 12 | J26: 50.04 | K26: 62 | N26: =IF(N(L26)=0,"",L26*N(M26)) | P26: =IF(Q26="","",ROW()-4) | AB26: =IF(AC26="","",ROW()-4) | AH26: =IF(AI26="","",ROW()-4)
D27: =IF(E27="","",ROW()-4) -> 23 | E27: 550农夫水 | F27: 农夫山泉公司 | G27: 农夫550ML水 | H27: 1*24 | I27: 24 | J27: 20.016 | K27: 20 | N27: =IF(N(L27)=0,"",L27*N(M27)) | P27: =IF(Q27="","",ROW()-4) | AB27: =IF(AC27="","",ROW()-4) | AH27: =IF(AI27="","",ROW()-4)
D28: =IF(E28="","",ROW()-4) -> 24 | E28: 550农夫纯净水 | F28: 农夫山泉公司 | G28: 农夫550ML纯净水 | H28: 1*24 | I28: 24 | J28: 15 | K28: 14 | N28: =IF(N(L28)=0,"",L28*N(M28)) | P28: =IF(Q28="","",ROW()-4) | AB28: =IF(AC28="","",ROW()-4) | AH28: =IF(AI28="","",ROW()-4)
D29: =IF(E29="","",ROW()-4) -> 25 | E29: 550纯净水12入 | F29: 农夫山泉公司 | H29: 1*12 | I29: 12 | J29: 7.5 | K29: 7.6 | N29: =IF(N(L29)=0,"",L29*N(M29)) | P29: =IF(Q29="","",ROW()-4) | AB29: =IF(AC29="","",ROW()-4) | AH29: =IF(AI29="","",ROW()-4)
D30: =IF(E30="","",ROW()-4) -> 26 | E30: 1.5L水 | F30: 农夫山泉公司 | G30: 农夫1.5L水 | H30: 1*12 | I30: 12 | J30: 20.004 | K30: 25 | N30: =IF(N(L30)=0,"",L30*N(M30)) | P30: =IF(Q30="","",ROW()-4) | AB30: =IF(AC30="","",ROW()-4) | AH30: =IF(AI30="","",ROW()-4)
D31: =IF(E31="","",ROW()-4) -> 27 | E31: 农夫苏打水 | F31: 农夫山泉公司 | G31: 农夫苏打水 | H31: 1*15 | I31: 15 | J31: 34.05 | N31: =IF(N(L31)=0,"",L31*N(M31)) | P31: =IF(Q31="","",ROW()-4) | AB31: =IF(AC31="","",ROW()-4) | AH31: =IF(AI31="","",ROW()-4)
D32: =IF(E32="","",ROW()-4) -> 28 | E32: 农夫2L水 | F32: 农夫山泉公司 | G32: 农夫2L水 | H32: 1*8 | I32: 8 | J32: 18 | N32: =IF(N(L32)=0,"",L32*N(M32)) | P32: =IF(Q32="","",ROW()-4) | AB32: =IF(AC32="","",ROW()-4) | AH32: =IF(AI32="","",ROW()-4)
D33: =IF(E33="","",ROW()-4) -> 29 | E33: 农夫5L水 | F33: 农夫山泉公司 | G33: 农夫5L水 | H33: 1*4 | I33: 4 | N33: =IF(N(L33)=0,"",L33*N(M33)) | P33: =IF(Q33="","",ROW()-4) | AB33: =IF(AC33="","",ROW()-4) | AH33: =IF(AI33="","",ROW()-4)
D34: =IF(E34="","",ROW()-4) -> 30 | E34: 农夫12.9L水 | F34: 农夫山泉公司 | G34: 农夫12.9L水 | N34: =IF(N(L34)=0,"",L34*N(M34)) | P34: =IF(Q34="","",ROW()-4) | AB34: =IF(AC34="","",ROW()-4) | AH34: =IF(AI34="","",ROW()-4)
D35: =IF(E35="","",ROW()-4) -> 31 | E35: 农夫1.25L果园 | F35: 农夫山泉公司 | G35: 农夫1.25L果园 | H35: 1*6 | I35: 6 | J35: 38.5 | N35: =IF(N(L35)=0,"",L35*N(M35)) | P35: =IF(Q35="","",ROW()-4) | AH35: =IF(AI35="","",ROW()-4)
D36: =IF(E36="","",ROW()-4) -> 32 | E36: 农夫1.5L东方树叶 | F36: 农夫山泉公司 | G36: 农夫1.5L东方树叶 | H36: 1*6 | I36: 6 | J36: 42 | N36: =IF(N(L36)=0,"",L36*N(M36)) | P36: =IF(Q36="","",ROW()-4) | AH36: =IF(AI36="","",ROW()-4)
D37: =IF(E37="","",ROW()-4) -> 33 | E37: 清爽 | F37: 青岛公司 | G37: 青岛清爽8 | H37: 1*12 | I37: 12 | J37: 35.28 | K37: 42 | N37: =IF(N(L37)=0,"",L37*N(M37)) | P37: =IF(Q37="","",ROW()-4) | AH37: =IF(AI37="","",ROW()-4)
D38: =IF(E38="","",ROW()-4) -> 34 | E38: 青岛清爽8奖盖过期 | F38: 青岛公司 | G38: 青岛清爽8奖盖过期 | H38: 1*12 | I38: 12 | J38: 35.28 | N38: =IF(N(L38)=0,"",L38*N(M38)) | P38: =IF(Q38="","",ROW()-4) | AH38: =IF(AI38="","",ROW()-4)
D39: =IF(E39="","",ROW()-4) -> 35 | E39: 青岛经典 | F39: 青岛公司 | G39: 青岛经典 | H39: 1*12 | I39: 12 | J39: 50.04 | N39: =IF(N(L39)=0,"",L39*N(M39)) | P39: =IF(Q39="","",ROW()-4) | AH39: =IF(AI39="","",ROW()-4)
D40: =IF(E40="","",ROW()-4) -> 36 | E40: 青岛崂山 | F40: 青岛公司 | G40: 青岛崂山 | H40: 1*12 | I40: 12 | J40: 24 | N40: =IF(N(L40)=0,"",L40*N(M40)) | P40: =IF(Q40="","",ROW()-4) | AH40: =IF(AI40="","",ROW()-4)
D41: =IF(E41="","",ROW()-4) -> 37 | E41: 青岛白啤 | F41: 青岛公司 | G41: 青岛白啤 | H41: 1*12 | I41: 12 | J41: 62.04 | N41: =IF(N(L41)=0,"",L41*N(M41)) | P41: =IF(Q41="","",ROW()-4) | AH41: =IF(AI41="","",ROW()-4)
D42: =IF(E42="","",ROW()-4) -> 38 | E42: 艾精隆155克瓜子 | F42: 其他公司 | G42: 艾精隆155克瓜子 | H42: 1*30 | I42: 30 | J42: 96 | N42: =IF(N(L42)=0,"",L42*N(M42)) | P42: =IF(Q42="","",ROW()-4) | AH42: =IF(AI42="","",ROW()-4)
D43: =IF(E43="","",ROW()-4) -> 39 | E43: 艾精隆60克香瓜子 | F43: 其他公司 | G43: 艾精隆60克香瓜子 | H43: 1*40 | I43: 40 | J43: 48 | N43: =IF(N(L43)=0,"",L43*N(M43)) | P43: =IF(Q43="","",ROW()-4) | AH43: =IF(AI43="","",ROW()-4)
D44: =IF(E44="","",ROW()-4) -> 40 | E44: 艾精隆60克原味瓜子 | F44: 其他公司 | G44: 艾精隆60克原味瓜子 | H44: 1*35 | I44: 35 | J44: 43.9985 | N44: =IF(N(L44)=0,"",L44*N(M44)) | P44: =IF(Q44="","",ROW()-4) | AH44: =IF(AI44="","",ROW()-4)
D45: =IF(E45="","",ROW()-4) -> 41 | E45: 艾精隆208克花生 | F45: 其他公司 | G45: 艾精隆208克花生 | H45: 1*30 | I45: 30 | J45: 96 | N45: =IF(N(L45)=0,"",L45*N(M45)) | P45: =IF(Q45="","",ROW()-4) | AH45: =IF(AI45="","",ROW()-4)
D46: =IF(E46="","",ROW()-4) -> 42 | E46: 艾精隆500克多味 | F46: 其他公司 | G46: 艾精隆500克多味 | H46: 1*20 | I46: 20 | J46: 220 | N46: =IF(N(L46)=0,"",L46*N(M46)) | P46: =IF(Q46="","",ROW()-4) | AH46: =IF(AI46="","",ROW()-4)
D47: =IF(E47="","",ROW()-4) -> 43 | E47: 艾精隆110克瓜子 | F47: 其他公司 | G47: 艾精隆110克瓜子 | H47: 1*40 | I47: 40 | J47: 128 | N47: =IF(N(L47)=0,"",L47*N(M47)) | P47: =IF(Q47="","",ROW()-4) | AH47: =IF(AI47="","",ROW()-4)
D48: =IF(E48="","",ROW()-4) -> 44 | E48: 艾精隆多味葵 | F48: 其他公司 | G48: 艾精隆多味葵 | H48: 1*10 | I48: 10 | N48: =IF(N(L48)=0,"",L48*N(M48)) | P48: =IF(Q48="","",ROW()-4) | AH48: =IF(AI48="","",ROW()-4)
D49: =IF(E49="","",ROW()-4) | N49: =IF(N(L49)=0,"",L49*N(M49)) | P49: =IF(Q49="","",ROW()-4) | AH49: =IF(AI49="","",ROW()-4)
D50: =IF(E50="","",ROW()-4) | N50: =IF(N(L50)=0,"",L50*N(M50)) | P50: =IF(Q50="","",ROW()-4) | AH50: =IF(AI50="","",ROW()-4)
D51: =IF(E51="","",ROW()-4) | N51: =IF(N(L51)=0,"",L51*N(M51)) | P51: =IF(Q51="","",ROW()-4) | AH51: =IF(AI51="","",ROW()-4)
D52: =IF(E52="","",ROW()-4) | N52: =IF(N(L52)=0,"",L52*N(M52)) | P52: =IF(Q52="","",ROW()-4) | AH52: =IF(AI52="","",ROW()-4)
D53: =IF(E53="","",ROW()-4) | N53: =IF(N(L53)=0,"",L53*N(M53)) | P53: =IF(Q53="","",ROW()-4) | AH53: =IF(AI53="","",ROW()-4)
D54: =IF(E54="","",ROW()-4) | N54: =IF(N(L54)=0,"",L54*N(M54)) | P54: =IF(Q54="","",ROW()-4) | AH54: =IF(AI54="","",ROW()-4)
D55: =IF(E55="","",ROW()-4) | N55: =IF(N(L55)=0,"",L55*N(M55))
D56: =IF(E56="","",ROW()-4) | N56: =IF(N(L56)=0,"",L56*N(M56))
D57: =IF(E57="","",ROW()-4) | N57: =IF(N(L57)=0,"",L57*N(M57))
D58: =IF(E58="","",ROW()-4) | N58: =IF(N(L58)=0,"",L58*N(M58))
D59: =IF(E59="","",ROW()-4) | N59: =IF(N(L59)=0,"",L59*N(M59))
D60: =IF(E60="","",ROW()-4) | N60: =IF(N(L60)=0,"",L60*N(M60))
D61: =IF(E61="","",ROW()-4) | N61: =IF(N(L61)=0,"",L61*N(M61))
D62: =IF(E62="","",ROW()-4) | N62: =IF(N(L62)=0,"",L62*N(M62))
D63: =IF(E63="","",ROW()-4) | N63: =IF(N(L63)=0,"",L63*N(M63))
D64: =IF(E64="","",ROW()-4) | N64: =IF(N(L64)=0,"",L64*N(M64))
D65: =IF(E65="","",ROW()-4) | N65: =IF(N(L65)=0,"",L65*N(M65))
D66: =IF(E66="","",ROW()-4) | N66: =IF(N(L66)=0,"",L66*N(M66))
... D104: =IF(E104="","",ROW()-4) | N104: =IF(N(L104)=0,"",L104*N(M104))

Sheet 资金台帐
A1: 资金台帐（收支混合录入 · 即时余额）
A2: 💡 一笔一行，按发生顺序往下记：收钱填【收入金额】，付钱填【支出金额】，右边【账户余额】【总余额】自动滚出来。收客户的钱选【客户】、付厂家货款选【供应商】、花钱选【费用项目】——总览汇总、收付款明细、对账单、利润表都从这里自动取数。选了客户/供应商/费用项目的，【收支项目】可以不选，会自动认。
A3: 月份： | B3: 9 | C3: 本月收入： | D3: =SUMIFS($F$7:$F$3006,$B$7:$B$3006,">="&DATE(年度,$B$3,1),$B$7:$B$3006,"<"&DATE(年度,$B$3+1,1),$P$7:$P$3006,"<>转账") -> 2700 | E3: 本月支出： | F3: =SUMIFS($G$7:$G$3006,$B$7:$B$3006,">="&DATE(年度,$B$3,1),$B$7:$B$3006,"<"&DATE(年度,$B$3+1,1),$P$7:$P$3006,"<>转账") -> 0 | G3: 上月结余： | H3: =SUM(基础资料!$X$5:$X$24)+SUMIFS($F$7:$F$3006,$B$7:$B$3006,">="&年初日,$B$7:$B$3006,"<"&DATE(年度,$B$3,1))-SUMIFS($G$7:$G$3006,$B$7:$B$3006,">="&年初日,$B$7:$B$3006,"<"&DATE(年度,$B$3,1)) -> 3866609.7 | I3: 本月结余： | J3: =SUM(基础资料!$X$5:$X$24)+SUMIFS($F$7:$F$3006,$B$7:$B$3006,">="&年初日,$B$7:$B$3006,"<"&DATE(年度,$B$3+1,1))-SUMIFS($G$7:$G$3006,$B$7:$B$3006,">="&年初日,$B$7:$B$3006,"<"&DATE(年度,$B$3+1,1)) -> 3869309.7 | K3: 当前总余额： | L3: =SUM(基础资料!$X$5:$X$24)+SUM($F$7:$F$3006)-SUM($G$7:$G$3006) -> 3869309.7 | M3: 按日期统计，本月收入/支出不含内部转账
A5: 登 记 信 息 | F5: ＋ 收 入 | G5: ＋ 支 出 | H5: 即时余额（自动） | J5: 往来 / 费用（筛选列） | M5: 备注 / 校验
A6: 序号 | B6: 日期 | C6: 账户 | D6: 收支项目 | E6: 摘要 | F6: 收入金额 | G6: 支出金额 | H6: 账户余额 | I6: 总余额 | J6: 客户 | K6: 供应商 | L6: 费用项目 | M6: 备注 | N6: 校验 | O6: 实际项目 | P6: 去向 | Q6: 客户收款序 | R6: 供应商付款序 | S6: 净额
A7: =IF(AND(F7="",G7=""),"",ROW()-6) -> 1 | B7: 46156 | C7: 收款码 | D7: 客户回款 | E7: 收货款 | F7: 100000 | H7: =IF(OR(C7="",AND(F7="",G7="")),"",SUMIF(基础资料!$W$5:$W$24,C7,基础资料!$X$5:$X$24)+SUMIF(C$7:C7,C7,F$7:F7)-SUMIF(C$7:C7,C7,G$7:G7)) -> 100000 | I7: =IF(AND(F7="",G7=""),"",SUM(基础资料!$X$5:$X$24)+SUM(F$7:F7)-SUM(G$7:G7)) -> 100000 | J7: 鼎龙陈财超市 | N7: =IF(AND(AND(F7="",G7=""),B7="",C7="",D7="",J7="",K7="",L7=""),"",IF(AND(F7="",G7=""),"✗ 没填金额",IF(AND(N(F7)<>0,N(G7)<>0),"✗ 收入、支出只能填一边",IF(NOT(ISNUMBER(B7)),"✗ 日期不是真日期（要像 2026/9/25 这样填）",IF(OR(B7<年初日,B7>年末日),"✗ 日期不在本会计年度",IF(C7="","✗ 没选账户",IF(COUNTIF(基础资料!$W$5:$W$24,C7)=0,"✗ 账户不在基础资料里",IF(O7="","✗ 没选收支项目",IF(P7="未知","✗ 收支项目不在基础资料里",IF(AND(P7="应收",J7=""),"✗ 这笔要选客户",IF(AND(P7="应收",COUNTIF(总览汇总!$B$5:$B$304,J7)=0),"✗ 客户不在总览汇总名单里",IF(AND(P7="应付",K7=""),"✗ 这笔要选供应商",IF(AND(P7="应付",COUNTIF(基础资料!$Q$5:$Q$54,K7)=0),"✗ 供应商不在基础资料里",IF(AND(P7="费用",L7=""),"✗ 费用支出要选费用项目",IF(AND(L7<>"",COUNTIF(基础资料!$AI$5:$AI$54,L7)=0),"✗ 费用项目不在基础资料里",IF(AND(IFERROR(INDEX(基础资料!$AD$5:$AD$34,MATCH(O7,基础资料!$AC$5:$AC$34,0)),"")="收",N(G7)<>0),"✗ 这类是收款，金额填到收入列",IF(AND(IFERROR(INDEX(基础资料!$AD$5:$AD$34,MATCH(O7,基础资料!$AC$5:$AC$34,0)),"")="支",N(F7)<>0),"✗ 这类是付款，金额填到支出列",IF(N(H7)<0,"⚠ 账户余额成负数了，核对一下","√")))))))))))))))))) -> √ | O7: =IF(D7<>"",D7,IF(AND(F7="",G7=""),"",IF(J7<>"",IF(N(F7)>0,"客户回款","客户退款"),IF(K7<>"",IF(N(G7)>0,"供应商付款","供应商退款"),IF(L7<>"","费用支出",""))))) -> 客户回款 | P7: =IF(O7="","",IFERROR(INDEX(基础资料!$AE$5:$AE$34,MATCH(O7,基础资料!$AC$5:$AC$34,0)),"未知")) -> 应收 | Q7: =IF(P7="应收",COUNTIF(P$7:P7,"应收"),"") -> 1 | R7: =IF(P7="应付",COUNTIF(P$7:P7,"应付"),"") | S7: =N(F7)-N(G7) -> 100000
A8: =IF(AND(F8="",G8=""),"",ROW()-6) -> 2 | B8: 46198 | C8: 收款码 | D8: 客户回款 | E8: 收货款 | F8: 39547 | H8: =IF(OR(C8="",AND(F8="",G8="")),"",SUMIF(基础资料!$W$5:$W$24,C8,基础资料!$X$5:$X$24)+SUMIF(C$7:C8,C8,F$7:F8)-SUMIF(C$7:C8,C8,G$7:G8)) -> 139547 | I8: =IF(AND(F8="",G8=""),"",SUM(基础资料!$X$5:$X$24)+SUM(F$7:F8)-SUM(G$7:G8)) -> 139547 | J8: 星海超市 | N8: =IF(AND(AND(F8="",G8=""),B8="",C8="",D8="",J8="",K8="",L8=""),"",IF(AND(F8="",G8=""),"✗ 没填金额",IF(AND(N(F8)<>0,N(G8)<>0),"✗ 收入、支出只能填一边",IF(NOT(ISNUMBER(B8)),"✗ 日期不是真日期（要像 2026/9/25 这样填）",IF(OR(B8<年初日,B8>年末日),"✗ 日期不在本会计年度",IF(C8="","✗ 没选账户",IF(COUNTIF(基础资料!$W$5:$W$24,C8)=0,"✗ 账户不在基础资料里",IF(O8="","✗ 没选收支项目",IF(P8="未知","✗ 收支项目不在基础资料里",IF(AND(P8="应收",J8=""),"✗ 这笔要选客户",IF(AND(P8="应收",COUNTIF(总览汇总!$B$5:$B$304,J8)=0),"✗ 客户不在总览汇总名单里",IF(AND(P8="应付",K8=""),"✗ 这笔要选供应商",IF(AND(P8="应付",COUNTIF(基础资料!$Q$5:$Q$54,K8)=0),"✗ 供应商不在基础资料里",IF(AND(P8="费用",L8=""),"✗ 费用支出要选费用项目",IF(AND(L8<>"",COUNTIF(基础资料!$AI$5:$AI$54,L8)=0),"✗ 费用项目不在基础资料里",IF(AND(IFERROR(INDEX(基础资料!$AD$5:$AD$34,MATCH(O8,基础资料!$AC$5:$AC$34,0)),"")="收",N(G8)<>0),"✗ 这类是收款，金额填到收入列",IF(AND(IFERROR(INDEX(基础资料!$AD$5:$AD$34,MATCH(O8,基础资料!$AC$5:$AC$34,0)),"")="支",N(F8)<>0),"✗ 这类是付款，金额填到支出列",IF(N(H8)<0,"⚠ 账户余额成负数了，核对一下","√")))))))))))))))))) -> √ | O8: =IF(D8<>"",D8,IF(AND(F8="",G8=""),"",IF(J8<>"",IF(N(F8)>0,"客户回款","客户退款"),IF(K8<>"",IF(N(G8)>0,"供应商付款","供应商退款"),IF(L8<>"","费用支出",""))))) -> 客户回款 | P8: =IF(O8="","",IFERROR(INDEX(基础资料!$AE$5:$AE$34,MATCH(O8,基础资料!$AC$5:$AC$34,0)),"未知")) -> 应收 | Q8: =IF(P8="应收",COUNTIF(P$7:P8,"应收"),"") -> 2 | R8: =IF(P8="应付",COUNTIF(P$7:P8,"应付"),"") | S8: =N(F8)-N(G8) -> 39547
A9: =IF(AND(F9="",G9=""),"",ROW()-6) -> 3 | B9: 46198 | C9: 收款码 | D9: 客户回款 | E9: 收货款 | F9: 99000 | H9: =IF(OR(C9="",AND(F9="",G9="")),"",SUMIF(基础资料!$W$5:$W$24,C9,基础资料!$X$5:$X$24)+SUMIF(C$7:C9,C9,F$7:F9)-SUMIF(C$7:C9,C9,G$7:G9)) -> 238547 | I9: =IF(AND(F9="",G9=""),"",SUM(基础资料!$X$5:$X$24)+SUM(F$7:F9)-SUM(G$7:G9)) -> 238547 | J9: 王玉琴 | N9: =IF(AND(AND(F9="",G9=""),B9="",C9="",D9="",J9="",K9="",L9=""),"",IF(AND(F9="",G9=""),"✗ 没填金额",IF(AND(N(F9)<>0,N(G9)<>0),"✗ 收入、支出只能填一边",IF(NOT(ISNUMBER(B9)),"✗ 日期不是真日期（要像 2026/9/25 这样填）",IF(OR(B9<年初日,B9>年末日),"✗ 日期不在本会计年度",IF(C9="","✗ 没选账户",IF(COUNTIF(基础资料!$W$5:$W$24,C9)=0,"✗ 账户不在基础资料里",IF(O9="","✗ 没选收支项目",IF(P9="未知","✗ 收支项目不在基础资料里",IF(AND(P9="应收",J9=""),"✗ 这笔要选客户",IF(AND(P9="应收",COUNTIF(总览汇总!$B$5:$B$304,J9)=0),"✗ 客户不在总览汇总名单里",IF(AND(P9="应付",K9=""),"✗ 这笔要选供应商",IF(AND(P9="应付",COUNTIF(基础资料!$Q$5:$Q$54,K9)=0),"✗ 供应商不在基础资料里",IF(AND(P9="费用",L9=""),"✗ 费用支出要选费用项目",IF(AND(L9<>"",COUNTIF(基础资料!$AI$5:$AI$54,L9)=0),"✗ 费用项目不在基础资料里",IF(AND(IFERROR(INDEX(基础资料!$AD$5:$AD$34,MATCH(O9,基础资料!$AC$5:$AC$34,0)),"")="收",N(G9)<>0),"✗ 这类是收款，金额填到收入列",IF(AND(IFERROR(INDEX(基础资料!$AD$5:$AD$34,MATCH(O9,基础资料!$AC$5:$AC$34,0)),"")="支",N(F9)<>0),"✗ 这类是付款，金额填到支出列",IF(N(H9)<0,"⚠ 账户余额成负数了，核对一下","√")))))))))))))))))) -> √ | O9: =IF(D9<>"",D9,IF(AND(F9="",G9=""),"",IF(J9<>"",IF(N(F9)>0,"客户回款","客户退款"),IF(K9<>"",IF(N(G9)>0,"供应商付款","供应商退款"),IF(L9<>"","费用支出",""))))) -> 客户回款 | P9: =IF(O9="","",IFERROR(INDEX(基础资料!$AE$5:$AE$34,MATCH(O9,基础资料!$AC$5:$AC$34,0)),"未知")) -> 应收 | Q9: =IF(P9="应收",COUNTIF(P$7:P9,"应收"),"") -> 3 | R9: =IF(P9="应付",COUNTIF(P$7:P9,"应付"),"") | S9: =N(F9)-N(G9) -> 99000
A10: =IF(AND(F10="",G10=""),"",ROW()-6) -> 4 | B10: 46198 | C10: 收款码 | D10: 客户回款 | E10: 还差我46313元 | F10: 700231.47 | H10: =IF(OR(C10="",AND(F10="",G10="")),"",SUMIF(基础资料!$W$5:$W$24,C10,基础资料!$X$5:$X$24)+SUMIF(C$7:C10,C10,F$7:F10)-SUMIF(C$7:C10,C10,G$7:G10)) -> 938778.47 | I10: =IF(AND(F10="",G10=""),"",SUM(基础资料!$X$5:$X$24)+SUM(F$7:F10)-SUM(G$7:G10)) -> 938778.47 | J10: 桐心源 | N10: =IF(AND(AND(F10="",G10=""),B10="",C10="",D10="",J10="",K10="",L10=""),"",IF(AND(F10="",G10=""),"✗ 没填金额",IF(AND(N(F10)<>0,N(G10)<>0),"✗ 收入、支出只能填一边",IF(NOT(ISNUMBER(B10)),"✗ 日期不是真日期（要像 2026/9/25 这样填）",IF(OR(B10<年初日,B10>年末日),"✗ 日期不在本会计年度",IF(C10="","✗ 没选账户",IF(COUNTIF(基础资料!$W$5:$W$24,C10)=0,"✗ 账户不在基础资料里",IF(O10="","✗ 没选收支项目",IF(P10="未知","✗ 收支项目不在基础资料里",IF(AND(P10="应收",J10=""),"✗ 这笔要选客户",IF(AND(P10="应收",COUNTIF(总览汇总!$B$5:$B$304,J10)=0),"✗ 客户不在总览汇总名单里",IF(AND(P10="应付",K10=""),"✗ 这笔要选供应商",IF(AND(P10="应付",COUNTIF(基础资料!$Q$5:$Q$54,K10)=0),"✗ 供应商不在基础资料里",IF(AND(P10="费用",L10=""),"✗ 费用支出要选费用项目",IF(AND(L10<>"",COUNTIF(基础资料!$AI$5:$AI$54,L10)=0),"✗ 费用项目不在基础资料里",IF(AND(IFERROR(INDEX(基础资料!$AD$5:$AD$34,MATCH(O10,基础资料!$AC$5:$AC$34,0)),"")="收",N(G10)<>0),"✗ 这类是收款，金额填到收入列",IF(AND(IFERROR(INDEX(基础资料!$AD$5:$AD$34,MATCH(O10,基础资料!$AC$5:$AC$34,0)),"")="支",N(F10)<>0),"✗ 这类是付款，金额填到支出列",IF(N(H10)<0,"⚠ 账户余额成负数了，核对一下","√")))))))))))))))))) -> √ | O10: =IF(D10<>"",D10,IF(AND(F10="",G10=""),"",IF(J10<>"",IF(N(F10)>0,"客户回款","客户退款"),IF(K10<>"",IF(N(G10)>0,"供应商付款","供应商退款"),IF(L10<>"","费用支出",""))))) -> 客户回款 | P10: =IF(O10="","",IFERROR(INDEX(基础资料!$AE$5:$AE$34,MATCH(O10,基础资料!$AC$5:$AC$34,0)),"未知")) -> 应收 | Q10: =IF(P10="应收",COUNTIF(P$7:P10,"应收"),"") -> 4 | R10: =IF(P10="应付",COUNTIF(P$7:P10,"应付"),"") | S10: =N(F10)-N(G10) -> 700231.47
A11: =IF(AND(F11="",G11=""),"",ROW()-6) -> 5 | B11: 46198 | C11: 收款码 | D11: 客户回款 | E11: 农夫饮料 | F11: 46360 | H11: =IF(OR(C11="",AND(F11="",G11="")),"",SUMIF(基础资料!$W$5:$W$24,C11,基础资料!$X$5:$X$24)+SUMIF(C$7:C11,C11,F$7:F11)-SUMIF(C$7:C11,C11,G$7:G11)) -> 985138.47 | I11: =IF(AND(F11="",G11=""),"",SUM(基础资料!$X$5:$X$24)+SUM(F$7:F11)-SUM(G$7:G11)) -> 985138.47 | J11: 桐心源 | N11: =IF(AND(AND(F11="",G11=""),B11="",C11="",D11="",J11="",K11="",L11=""),"",IF(AND(F11="",G11=""),"✗ 没填金额",IF(AND(N(F11)<>0,N(G11)<>0),"✗ 收入、支出只能填一边",IF(NOT(ISNUMBER(B11)),"✗ 日期不是真日期（要像 2026/9/25 这样填）",IF(OR(B11<年初日,B11>年末日),"✗ 日期不在本会计年度",IF(C11="","✗ 没选账户",IF(COUNTIF(基础资料!$W$5:$W$24,C11)=0,"✗ 账户不在基础资料里",IF(O11="","✗ 没选收支项目",IF(P11="未知","✗ 收支项目不在基础资料里",IF(AND(P11="应收",J11=""),"✗ 这笔要选客户",IF(AND(P11="应收",COUNTIF(总览汇总!$B$5:$B$304,J11)=0),"✗ 客户不在总览汇总名单里",IF(AND(P11="应付",K11=""),"✗ 这笔要选供应商",IF(AND(P11="应付",COUNTIF(基础资料!$Q$5:$Q$54,K11)=0),"✗ 供应商不在基础资料里",IF(AND(P11="费用",L11=""),"✗ 费用支出要选费用项目",IF(AND(L11<>"",COUNTIF(基础资料!$AI$5:$AI$54,L11)=0),"✗ 费用项目不在基础资料里",IF(AND(IFERROR(INDEX(基础资料!$AD$5:$AD$34,MATCH(O11,基础资料!$AC$5:$AC$34,0)),"")="收",N(G11)<>0),"✗ 这类是收款，金额填到收入列",IF(AND(IFERROR(INDEX(基础资料!$AD$5:$AD$34,MATCH(O11,基础资料!$AC$5:$AC$34,0)),"")="支",N(F11)<>0),"✗ 这类是付款，金额填到支出列",IF(N(H11)<0,"⚠ 账户余额成负数了，核对一下","√")))))))))))))))))) -> √ | O11: =IF(D11<>"",D11,IF(AND(F11="",G11=""),"",IF(J11<>"",IF(N(F11)>0,"客户回款","客户退款"),IF(K11<>"",IF(N(G11)>0,"供应商付款","供应商退款"),IF(L11<>"","费用支出",""))))) -> 客户回款 | P11: =IF(O11="","",IFERROR(INDEX(基础资料!$AE$5:$AE$34,MATCH(O11,基础资料!$AC$5:$AC$34,0)),"未知")) -> 应收 | Q11: =IF(P11="应收",COUNTIF(P$7:P11,"应收"),"") -> 5 | R11: =IF(P11="应付",COUNTIF(P$7:P11,"应付"),"") | S11: =N(F11)-N(G11) -> 46360
A12: =IF(AND(F12="",G12=""),"",ROW()-6) -> 6 | B12: 46198 | C12: 收款码 | D12: 客户回款 | E12: 还差我37433元 | F12: 570147.22 | H12: =IF(OR(C12="",AND(F12="",G12="")),"",SUMIF(基础资料!$W$5:$W$24,C12,基础资料!$X$5:$X$24)+SUMIF(C$7:C12,C12,F$7:F12)-SUMIF(C$7:C12,C12,G$7:G12)) -> 1555285.7 | I12: =IF(AND(F12="",G12=""),"",SUM(基础资料!$X$5:$X$24)+SUM(F$7:F12)-SUM(G$7:G12)) -> 1555285.7 | J12: 阿东副食 | N12: =IF(AND(AND(F12="",G12=""),B12="",C12="",D12="",J12="",K12="",L12=""),"",IF(AND(F12="",G12=""),"✗ 没填金额",IF(AND(N(F12)<>0,N(G12)<>0),"✗ 收入、支出只能填一边",IF(NOT(ISNUMBER(B12)),"✗ 日期不是真日期（要像 2026/9/25 这样填）",IF(OR(B12<年初日,B12>年末日),"✗ 日期不在本会计年度",IF(C12="","✗ 没选账户",IF(COUNTIF(基础资料!$W$5:$W$24,C12)=0,"✗ 账户不在基础资料里",IF(O12="","✗ 没选收支项目",IF(P12="未知","✗ 收支项目不在基础资料里",IF(AND(P12="应收",J12=""),"✗ 这笔要选客户",IF(AND(P12="应收",COUNTIF(总览汇总!$B$5:$B$304,J12)=0),"✗ 客户不在总览汇总名单里",IF(AND(P12="应付",K12=""),"✗ 这笔要选供应商",IF(AND(P12="应付",COUNTIF(基础资料!$Q$5:$Q$54,K12)=0),"✗ 供应商不在基础资料里",IF(AND(P12="费用",L12=""),"✗ 费用支出要选费用项目",IF(AND(L12<>"",COUNTIF(基础资料!$AI$5:$AI$54,L12)=0),"✗ 费用项目不在基础资料里",IF(AND(IFERROR(INDEX(基础资料!$AD$5:$AD$34,MATCH(O12,基础资料!$AC$5:$AC$34,0)),"")="收",N(G12)<>0),"✗ 这类是收款，金额填到收入列",IF(AND(IFERROR(INDEX(基础资料!$AD$5:$AD$34,MATCH(O12,基础资料!$AC$5:$AC$34,0)),"")="支",N(F12)<>0),"✗ 这类是付款，金额填到支出列",IF(N(H12)<0,"⚠ 账户余额成负数了，核对一下","√")))))))))))))))))) -> √ | O12: =IF(D12<>"",D12,IF(AND(F12="",G12=""),"",IF(J12<>"",IF(N(F12)>0,"客户回款","客户退款"),IF(K12<>"",IF(N(G12)>0,"供应商付款","供应商退款"),IF(L12<>"","费用支出",""))))) -> 客户回款 | P12: =IF(O12="","",IFERROR(INDEX(基础资料!$AE$5:$AE$34,MATCH(O12,基础资料!$AC$5:$AC$34,0)),"未知")) -> 应收 | Q12: =IF(P12="应收",COUNTIF(P$7:P12,"应收"),"") -> 6 | R12: =IF(P12="应付",COUNTIF(P$7:P12,"应付"),"") | S12: =N(F12)-N(G12) -> 570147.22
A13: =IF(AND(F13="",G13=""),"",ROW()-6) -> 7 | B13: 46199 | C13: 收款码 | D13: 客户回款 | E13: 收货款 | F13: 8950 | H13: =IF(OR(C13="",AND(F13="",G13="")),"",SUMIF(基础资料!$W$5:$W$24,C13,基础资料!$X$5:$X$24)+SUMIF(C$7:C13,C13,F$7:F13)-SUMIF(C$7:C13,C13,G$7:G13)) -> 1564235.7 | I13: =IF(AND(F13="",G13=""),"",SUM(基础资料!$X$5:$X$24)+SUM(F$7:F13)-SUM(G$7:G13)) -> 1564235.7 | J13: 金凤副食 | N13: =IF(AND(AND(F13="",G13=""),B13="",C13="",D13="",J13="",K13="",L13=""),"",IF(AND(F13="",G13=""),"✗ 没填金额",IF(AND(N(F13)<>0,N(G13)<>0),"✗ 收入、支出只能填一边",IF(NOT(ISNUMBER(B13)),"✗ 日期不是真日期（要像 2026/9/25 这样填）",IF(OR(B13<年初日,B13>年末日),"✗ 日期不在本会计年度",IF(C13="","✗ 没选账户",IF(COUNTIF(基础资料!$W$5:$W$24,C13)=0,"✗ 账户不在基础资料里",IF(O13="","✗ 没选收支项目",IF(P13="未知","✗ 收支项目不在基础资料里",IF(AND(P13="应收",J13=""),"✗ 这笔要选客户",IF(AND(P13="应收",COUNTIF(总览汇总!$B$5:$B$304,J13)=0),"✗ 客户不在总览汇总名单里",IF(AND(P13="应付",K13=""),"✗ 这笔要选供应商",IF(AND(P13="应付",COUNTIF(基础资料!$Q$5:$Q$54,K13)=0),"✗ 供应商不在基础资料里",IF(AND(P13="费用",L13=""),"✗ 费用支出要选费用项目",IF(AND(L13<>"",COUNTIF(基础资料!$AI$5:$AI$54,L13)=0),"✗ 费用项目不在基础资料里",IF(AND(IFERROR(INDEX(基础资料!$AD$5:$AD$34,MATCH(O13,基础资料!$AC$5:$AC$34,0)),"")="收",N(G13)<>0),"✗ 这类是收款，金额填到收入列",IF(AND(IFERROR(INDEX(基础资料!$AD$5:$AD$34,MATCH(O13,基础资料!$AC$5:$AC$34,0)),"")="支",N(F13)<>0),"✗ 这类是付款，金额填到支出列",IF(N(H13)<0,"⚠ 账户余额成负数了，核对一下","√")))))))))))))))))) -> √ | O13: =IF(D13<>"",D13,IF(AND(F13="",G13=""),"",IF(J13<>"",IF(N(F13)>0,"客户回款","客户退款"),IF(K13<>"",IF(N(G13)>0,"供应商付款","供应商退款"),IF(L13<>"","费用支出",""))))) -> 客户回款 | P13: =IF(O13="","",IFERROR(INDEX(基础资料!$AE$5:$AE$34,MATCH(O13,基础资料!$AC$5:$AC$34,0)),"未知")) -> 应收 | Q13: =IF(P13="应收",COUNTIF(P$7:P13,"应收"),"") -> 7 | R13: =IF(P13="应付",COUNTIF(P$7:P13,"应付"),"") | S13: =N(F13)-N(G13) -> 8950
A14: =IF(AND(F14="",G14=""),"",ROW()-6) -> 8 | B14: 46199 | C14: 收款码 | D14: 客户回款 | E14: 收货款 | F14: 437965 | H14: =IF(OR(C14="",AND(F14="",G14="")),"",SUMIF(基础资料!$W$5:$W$24,C14,基础资料!$X$5:$X$24)+SUMIF(C$7:C14,C14,F$7:F14)-SUMIF(C$7:C14,C14,G$7:G14)) -> 2002200.7 | I14: =IF(AND(F14="",G14=""),"",SUM(基础资料!$X$5:$X$24)+SUM(F$7:F14)-SUM(G$7:G14)) -> 2002200.7 | J14: 致发商行 | N14: =IF(AND(AND(F14="",G14=""),B14="",C14="",D14="",J14="",K14="",L14=""),"",IF(AND(F14="",G14=""),"✗ 没填金额",IF(AND(N(F14)<>0,N(G14)<>0),"✗ 收入、支出只能填一边",IF(NOT(ISNUMBER(B14)),"✗ 日期不是真日期（要像 2026/9/25 这样填）",IF(OR(B14<年初日,B14>年末日),"✗ 日期不在本会计年度",IF(C14="","✗ 没选账户",IF(COUNTIF(基础资料!$W$5:$W$24,C14)=0,"✗ 账户不在基础资料里",IF(O14="","✗ 没选收支项目",IF(P14="未知","✗ 收支项目不在基础资料里",IF(AND(P14="应收",J14=""),"✗ 这笔要选客户",IF(AND(P14="应收",COUNTIF(总览汇总!$B$5:$B$304,J14)=0),"✗ 客户不在总览汇总名单里",IF(AND(P14="应付",K14=""),"✗ 这笔要选供应商",IF(AND(P14="应付",COUNTIF(基础资料!$Q$5:$Q$54,K14)=0),"✗ 供应商不在基础资料里",IF(AND(P14="费用",L14=""),"✗ 费用支出要选费用项目",IF(AND(L14<>"",COUNTIF(基础资料!$AI$5:$AI$54,L14)=0),"✗ 费用项目不在基础资料里",IF(AND(IFERROR(INDEX(基础资料!$AD$5:$AD$34,MATCH(O14,基础资料!$AC$5:$AC$34,0)),"")="收",N(G14)<>0),"✗ 这类是收款，金额填到收入列",IF(AND(IFERROR(INDEX(基础资料!$AD$5:$AD$34,MATCH(O14,基础资料!$AC$5:$AC$34,0)),"")="支",N(F14)<>0),"✗ 这类是付款，金额填到支出列",IF(N(H14)<0,"⚠ 账户余额成负数了，核对一下","√")))))))))))))))))) -> √ | O14: =IF(D14<>"",D14,IF(AND(F14="",G14=""),"",IF(J14<>"",IF(N(F14)>0,"客户回款","客户退款"),IF(K14<>"",IF(N(G14)>0,"供应商付款","供应商退款"),IF(L14<>"","费用支出",""))))) -> 客户回款 | P14: =IF(O14="","",IFERROR(INDEX(基础资料!$AE$5:$AE$34,MATCH(O14,基础资料!$AC$5:$AC$34,0)),"未知")) -> 应收 | Q14: =IF(P14="应收",COUNTIF(P$7:P14,"应收"),"") -> 8 | R14: =IF(P14="应付",COUNTIF(P$7:P14,"应付"),"") | S14: =N(F14)-N(G14) -> 437965
A15: =IF(AND(F15="",G15=""),"",ROW()-6) -> 9 | B15: 46199 | C15: 收款码 | D15: 客户回款 | E15: 收货款 | F15: 18000 | H15: =IF(OR(C15="",AND(F15="",G15="")),"",SUMIF(基础资料!$W$5:$W$24,C15,基础资料!$X$5:$X$24)+SUMIF(C$7:C15,C15,F$7:F15)-SUMIF(C$7:C15,C15,G$7:G15)) -> 2020200.7 | I15: =IF(AND(F15="",G15=""),"",SUM(基础资料!$X$5:$X$24)+SUM(F$7:F15)-SUM(G$7:G15)) -> 2020200.7 | J15: 通达商行 | N15: =IF(AND(AND(F15="",G15=""),B15="",C15="",D15="",J15="",K15="",L15=""),"",IF(AND(F15="",G15=""),"✗ 没填金额",IF(AND(N(F15)<>0,N(G15)<>0),"✗ 收入、支出只能填一边",IF(NOT(ISNUMBER(B15)),"✗ 日期不是真日期（要像 2026/9/25 这样填）",IF(OR(B15<年初日,B15>年末日),"✗ 日期不在本会计年度",IF(C15="","✗ 没选账户",IF(COUNTIF(基础资料!$W$5:$W$24,C15)=0,"✗ 账户不在基础资料里",IF(O15="","✗ 没选收支项目",IF(P15="未知","✗ 收支项目不在基础资料里",IF(AND(P15="应收",J15=""),"✗ 这笔要选客户",IF(AND(P15="应收",COUNTIF(总览汇总!$B$5:$B$304,J15)=0),"✗ 客户不在总览汇总名单里",IF(AND(P15="应付",K15=""),"✗ 这笔要选供应商",IF(AND(P15="应付",COUNTIF(基础资料!$Q$5:$Q$54,K15)=0),"✗ 供应商不在基础资料里",IF(AND(P15="费用",L15=""),"✗ 费用支出要选费用项目",IF(AND(L15<>"",COUNTIF(基础资料!$AI$5:$AI$54,L15)=0),"✗ 费用项目不在基础资料里",IF(AND(IFERROR(INDEX(基础资料!$AD$5:$AD$34,MATCH(O15,基础资料!$AC$5:$AC$34,0)),"")="收",N(G15)<>0),"✗ 这类是收款，金额填到收入列",IF(AND(IFERROR(INDEX(基础资料!$AD$5:$AD$34,MATCH(O15,基础资料!$AC$5:$AC$34,0)),"")="支",N(F15)<>0),"✗ 这类是付款，金额填到支出列",IF(N(H15)<0,"⚠ 账户余额成负数了，核对一下","√")))))))))))))))))) -> √ | O15: =IF(D15<>"",D15,IF(AND(F15="",G15=""),"",IF(J15<>"",IF(N(F15)>0,"客户回款","客户退款"),IF(K15<>"",IF(N(G15)>0,"供应商付款","供应商退款"),IF(L15<>"","费用支出",""))))) -> 客户回款 | P15: =IF(O15="","",IFERROR(INDEX(基础资料!$AE$5:$AE$34,MATCH(O15,基础资料!$AC$5:$AC$34,0)),"未知")) -> 应收 | Q15: =IF(P15="应收",COUNTIF(P$7:P15,"应收"),"") -> 9 | R15: =IF(P15="应付",COUNTIF(P$7:P15,"应付"),"") | S15: =N(F15)-N(G15) -> 18000
A16: =IF(AND(F16="",G16=""),"",ROW()-6) -> 10 | B16: 46199 | C16: 收款码 | D16: 客户回款 | E16: 收货款 | F16: 54000 | H16: =IF(OR(C16="",AND(F16="",G16="")),"",SUMIF(基础资料!$W$5:$W$24,C16,基础资料!$X$5:$X$24)+SUMIF(C$7:C16,C16,F$7:F16)-SUMIF(C$7:C16,C16,G$7:G16)) -> 2074200.7 | I16: =IF(AND(F16="",G16=""),"",SUM(基础资料!$X$5:$X$24)+SUM(F$7:F16)-SUM(G$7:G16)) -> 2074200.7 | J16: 宜兴粮油 | N16: =IF(AND(AND(F16="",G16=""),B16="",C16="",D16="",J16="",K16="",L16=""),"",IF(AND(F16="",G16=""),"✗ 没填金额",IF(AND(N(F16)<>0,N(G16)<>0),"✗ 收入、支出只能填一边",IF(NOT(ISNUMBER(B16)),"✗ 日期不是真日期（要像 2026/9/25 这样填）",IF(OR(B16<年初日,B16>年末日),"✗ 日期不在本会计年度",IF(C16="","✗ 没选账户",IF(COUNTIF(基础资料!$W$5:$W$24,C16)=0,"✗ 账户不在基础资料里",IF(O16="","✗ 没选收支项目",IF(P16="未知","✗ 收支项目不在基础资料里",IF(AND(P16="应收",J16=""),"✗ 这笔要选客户",IF(AND(P16="应收",COUNTIF(总览汇总!$B$5:$B$304,J16)=0),"✗ 客户不在总览汇总名单里",IF(AND(P16="应付",K16=""),"✗ 这笔要选供应商",IF(AND(P16="应付",COUNTIF(基础资料!$Q$5:$Q$54,K16)=0),"✗ 供应商不在基础资料里",IF(AND(P16="费用",L16=""),"✗ 费用支出要选费用项目",IF(AND(L16<>"",COUNTIF(基础资料!$AI$5:$AI$54,L16)=0),"✗ 费用项目不在基础资料里",IF(AND(IFERROR(INDEX(基础资料!$AD$5:$AD$34,MATCH(O16,基础资料!$AC$5:$AC$34,0)),"")="收",N(G16)<>0),"✗ 这类是收款，金额填到收入列",IF(AND(IFERROR(INDEX(基础资料!$AD$5:$AD$34,MATCH(O16,基础资料!$AC$5:$AC$34,0)),"")="支",N(F16)<>0),"✗ 这类是付款，金额填到支出列",IF(N(H16)<0,"⚠ 账户余额成负数了，核对一下","√")))))))))))))))))) -> √ | O16: =IF(D16<>"",D16,IF(AND(F16="",G16=""),"",IF(J16<>"",IF(N(F16)>0,"客户回款","客户退款"),IF(K16<>"",IF(N(G16)>0,"供应商付款","供应商退款"),IF(L16<>"","费用支出",""))))) -> 客户回款 | P16: =IF(O16="","",IFERROR(INDEX(基础资料!$AE$5:$AE$34,MATCH(O16,基础资料!$AC$5:$AC$34,0)),"未知")) -> 应收 | Q16: =IF(P16="应收",COUNTIF(P$7:P16,"应收"),"") -> 10 | R16: =IF(P16="应付",COUNTIF(P$7:P16,"应付"),"") | S16: =N(F16)-N(G16) -> 54000
A17: =IF(AND(F17="",G17=""),"",ROW()-6) -> 11 | B17: 46200 | C17: 收款码 | D17: 客户回款 | E17: 东鹏新品订货款 | F17: 840 | H17: =IF(OR(C17="",AND(F17="",G17="")),"",SUMIF(基础资料!$W$5:$W$24,C17,基础资料!$X$5:$X$24)+SUMIF(C$7:C17,C17,F$7:F17)-SUMIF(C$7:C17,C17,G$7:G17)) -> 2075040.7 | I17: =IF(AND(F17="",G17=""),"",SUM(基础资料!$X$5:$X$24)+SUM(F$7:F17)-SUM(G$7:G17)) -> 2075040.7 | J17: 马路下小卖部 | N17: =IF(AND(AND(F17="",G17=""),B17="",C17="",D17="",J17="",K17="",L17=""),"",IF(AND(F17="",G17=""),"✗ 没填金额",IF(AND(N(F17)<>0,N(G17)<>0),"✗ 收入、支出只能填一边",IF(NOT(ISNUMBER(B17)),"✗ 日期不是真日期（要像 2026/9/25 这样填）",IF(OR(B17<年初日,B17>年末日),"✗ 日期不在本会计年度",IF(C17="","✗ 没选账户",IF(COUNTIF(基础资料!$W$5:$W$24,C17)=0,"✗ 账户不在基础资料里",IF(O17="","✗ 没选收支项目",IF(P17="未知","✗ 收支项目不在基础资料里",IF(AND(P17="应收",J17=""),"✗ 这笔要选客户",IF(AND(P17="应收",COUNTIF(总览汇总!$B$5:$B$304,J17)=0),"✗ 客户不在总览汇总名单里",IF(AND(P17="应付",K17=""),"✗ 这笔要选供应商",IF(AND(P17="应付",COUNTIF(基础资料!$Q$5:$Q$54,K17)=0),"✗ 供应商不在基础资料里",IF(AND(P17="费用",L17=""),"✗ 费用支出要选费用项目",IF(AND(L17<>"",COUNTIF(基础资料!$AI$5:$AI$54,L17)=0),"✗ 费用项目不在基础资料里",IF(AND(IFERROR(INDEX(基础资料!$AD$5:$AD$34,MATCH(O17,基础资料!$AC$5:$AC$34,0)),"")="收",N(G17)<>0),"✗ 这类是收款，金额填到收入列",IF(AND(IFERROR(INDEX(基础资料!$AD$5:$AD$34,MATCH(O17,基础资料!$AC$5:$AC$34,0)),"")="支",N(F17)<>0),"✗ 这类是付款，金额填到支出列",IF(N(H17)<0,"⚠ 账户余额成负数了，核对一下","√")))))))))))))))))) -> √ | O17: =IF(D17<>"",D17,IF(AND(F17="",G17=""),"",IF(J17<>"",IF(N(F17)>0,"客户回款","客户退款"),IF(K17<>"",IF(N(G17)>0,"供应商付款","供应商退款"),IF(L17<>"","费用支出",""))))) -> 客户回款 | P17: =IF(O17="","",IFERROR(INDEX(基础资料!$AE$5:$AE$34,MATCH(O17,基础资料!$AC$5:$AC$34,0)),"未知")) -> 应收 | Q17: =IF(P17="应收",COUNTIF(P$7:P17,"应收"),"") -> 11 | R17: =IF(P17="应付",COUNTIF(P$7:P17,"应付"),"") | S17: =N(F17)-N(G17) -> 840
A18: =IF(AND(F18="",G18=""),"",ROW()-6) -> 12 | B18: 46200 | C18: 收款码 | D18: 客户回款 | E18: 收货款 | F18: 30043 | H18: =IF(OR(C18="",AND(F18="",G18="")),"",SUMIF(基础资料!$W$5:$W$24,C18,基础资料!$X$5:$X$24)+SUMIF(C$7:C18,C18,F$7:F18)-SUMIF(C$7:C18,C18,G$7:G18)) -> 2105083.7 | I18: =IF(AND(F18="",G18=""),"",SUM(基础资料!$X$5:$X$24)+SUM(F$7:F18)-SUM(G$7:G18)) -> 2105083.7 | J18: 兴莲隆兴商行 | N18: =IF(AND(AND(F18="",G18=""),B18="",C18="",D18="",J18="",K18="",L18=""),"",IF(AND(F18="",G18=""),"✗ 没填金额",IF(AND(N(F18)<>0,N(G18)<>0),"✗ 收入、支出只能填一边",IF(NOT(ISNUMBER(B18)),"✗ 日期不是真日期（要像 2026/9/25 这样填）",IF(OR(B18<年初日,B18>年末日),"✗ 日期不在本会计年度",IF(C18="","✗ 没选账户",IF(COUNTIF(基础资料!$W$5:$W$24,C18)=0,"✗ 账户不在基础资料里",IF(O18="","✗ 没选收支项目",IF(P18="未知","✗ 收支项目不在基础资料里",IF(AND(P18="应收",J18=""),"✗ 这笔要选客户",IF(AND(P18="应收",COUNTIF(总览汇总!$B$5:$B$304,J18)=0),"✗ 客户不在总览汇总名单里",IF(AND(P18="应付",K18=""),"✗ 这笔要选供应商",IF(AND(P18="应付",COUNTIF(基础资料!$Q$5:$Q$54,K18)=0),"✗ 供应商不在基础资料里",IF(AND(P18="费用",L18=""),"✗ 费用支出要选费用项目",IF(AND(L18<>"",COUNTIF(基础资料!$AI$5:$AI$54,L18)=0),"✗ 费用项目不在基础资料里",IF(AND(IFERROR(INDEX(基础资料!$AD$5:$AD$34,MATCH(O18,基础资料!$AC$5:$AC$34,0)),"")="收",N(G18)<>0),"✗ 这类是收款，金额填到收入列",IF(AND(IFERROR(INDEX(基础资料!$AD$5:$AD$34,MATCH(O18,基础资料!$AC$5:$AC$34,0)),"")="支",N(F18)<>0),"✗ 这类是付款，金额填到支出列",IF(N(H18)<0,"⚠ 账户余额成负数了，核对一下","√")))))))))))))))))) -> √ | O18: =IF(D18<>"",D18,IF(AND(F18="",G18=""),"",IF(J18<>"",IF(N(F18)>0,"客户回款","客户退款"),IF(K18<>"",IF(N(G18)>0,"供应商付款","供应商退款"),IF(L18<>"","费用支出",""))))) -> 客户回款 | P18: =IF(O18="","",IFERROR(INDEX(基础资料!$AE$5:$AE$34,MATCH(O18,基础资料!$AC$5:$AC$34,0)),"未知")) -> 应收 | Q18: =IF(P18="应收",COUNTIF(P$7:P18,"应收"),"") -> 12 | R18: =IF(P18="应付",COUNTIF(P$7:P18,"应付"),"") | S18: =N(F18)-N(G18) -> 30043
... A123: =IF(AND(F123="",G123=""),"",ROW()-6) -> 117 | B123: 46270 | C123: 收款码 | D123: 客户回款 | E123: 收货款 | F123: 2700 | H123: =IF(OR(C123="",AND(F123="",G123="")),"",SUMIF(基础资料!$W$5:$W$24,C123,基础资料!$X$5:$X$24)+SUMIF(C$7:C123,C123,F$7:F123)-SUMIF(C$7:C123,C123,G$7:G123)) -> 3857959.7 | I123: =IF(AND(F123="",G123=""),"",SUM(基础资料!$X$5:$X$24)+SUM(F$7:F123)-SUM(G$7:G123)) -> 3869309.7 | J123: 城岗老石商行 | N123: =IF(AND(AND(F123="",G123=""),B123="",C123="",D123="",J123="",K123="",L123=""),"",IF(AND(F123="",G123=""),"✗ 没填金额",IF(AND(N(F123)<>0,N(G123)<>0),"✗ 收入、支出只能填一边",IF(NOT(ISNUMBER(B123)),"✗ 日期不是真日期（要像 2026/9/25 这样填）",IF(OR(B123<年初日,B123>年末日),"✗ 日期不在本会计年度",IF(C123="","✗ 没选账户",IF(COUNTIF(基础资料!$W$5:$W$24,C123)=0,"✗ 账户不在基础资料里",IF(O123="","✗ 没选收支项目",IF(P123="未知","✗ 收支项目不在基础资料里",IF(AND(P123="应收",J123=""),"✗ 这笔要选客户",IF(AND(P123="应收",COUNTIF(总览汇总!$B$5:$B$304,J123)=0),"✗ 客户不在总览汇总名单里",IF(AND(P123="应付",K123=""),"✗ 这笔要选供应商",IF(AND(P123="应付",COUNTIF(基础资料!$Q$5:$Q$54,K123)=0),"✗ 供应商不在基础资料里",IF(AND(P123="费用",L123=""),"✗ 费用支出要选费用项目",IF(AND(L123<>"",COUNTIF(基础资料!$AI$5:$AI$54,L123)=0),"✗ 费用项目不在基础资料里",IF(AND(IFERROR(INDEX(基础资料!$AD$5:$AD$34,MATCH(O123,基础资料!$AC$5:$AC$34,0)),"")="收",N(G123)<>0),"✗ 这类是收款，金额填到收入列",IF(AND(IFERROR(INDEX(基础资料!$AD$5:$AD$34,MATCH(O123,基础资料!$AC$5:$AC$34,0)),"")="支",N(F123)<>0),"✗ 这类是付款，金额填到支出列",IF(N(H123)<0,"⚠ 账户余额成负数了，核对一下","√")))))))))))))))))) -> √ | O123: =IF(D123<>"",D123,IF(AND(F123="",G123=""),"",IF(J123<>"",IF(N(F123)>0,"客户回款","客户退款"),IF(K123<>"",IF(N(G123)>0,"供应商付款","供应商退款"),IF(L123<>"","费用支出",""))))) -> 客户回款 | P123: =IF(O123="","",IFERROR(INDEX(基础资料!$AE$5:$AE$34,MATCH(O123,基础资料!$AC$5:$AC$34,0)),"未知")) -> 应收 | Q123: =IF(P123="应收",COUNTIF(P$7:P123,"应收"),"") -> 117 | R123: =IF(P123="应付",COUNTIF(P$7:P123,"应付"),"") | S123: =N(F123)-N(G123) -> 2700
A124: =IF(AND(F124="",G124=""),"",ROW()-6) | H124: =IF(OR(C124="",AND(F124="",G124="")),"",SUMIF(基础资料!$W$5:$W$24,C124,基础资料!$X$5:$X$24)+SUMIF(C$7:C124,C124,F$7:F124)-SUMIF(C$7:C124,C124,G$7:G124)) | I124: =IF(AND(F124="",G124=""),"",SUM(基础资料!$X$5:$X$24)+SUM(F$7:F124)-SUM(G$7:G124)) | N124: =IF(AND(AND(F124="",G124=""),B124="",C124="",D124="",J124="",K124="",L124=""),"",IF(AND(F124="",G124=""),"✗ 没填金额",IF(AND(N(F124)<>0,N(G124)<>0),"✗ 收入、支出只能填一边",IF(NOT(ISNUMBER(B124)),"✗ 日期不是真日期（要像 2026/9/25 这样填）",IF(OR(B124<年初日,B124>年末日),"✗ 日期不在本会计年度",IF(C124="","✗ 没选账户",IF(COUNTIF(基础资料!$W$5:$W$24,C124)=0,"✗ 账户不在基础资料里",IF(O124="","✗ 没选收支项目",IF(P124="未知","✗ 收支项目不在基础资料里",IF(AND(P124="应收",J124=""),"✗ 这笔要选客户",IF(AND(P124="应收",COUNTIF(总览汇总!$B$5:$B$304,J124)=0),"✗ 客户不在总览汇总名单里",IF(AND(P124="应付",K124=""),"✗ 这笔要选供应商",IF(AND(P124="应付",COUNTIF(基础资料!$Q$5:$Q$54,K124)=0),"✗ 供应商不在基础资料里",IF(AND(P124="费用",L124=""),"✗ 费用支出要选费用项目",IF(AND(L124<>"",COUNTIF(基础资料!$AI$5:$AI$54,L124)=0),"✗ 费用项目不在基础资料里",IF(AND(IFERROR(INDEX(基础资料!$AD$5:$AD$34,MATCH(O124,基础资料!$AC$5:$AC$34,0)),"")="收",N(G124)<>0),"✗ 这类是收款，金额填到收入列",IF(AND(IFERROR(INDEX(基础资料!$AD$5:$AD$34,MATCH(O124,基础资料!$AC$5:$AC$34,0)),"")="支",N(F124)<>0),"✗ 这类是付款，金额填到支出列",IF(N(H124)<0,"⚠ 账户余额成负数了，核对一下","√")))))))))))))))))) | O124: =IF(D124<>"",D124,IF(AND(F124="",G124=""),"",IF(J124<>"",IF(N(F124)>0,"客户回款","客户退款"),IF(K124<>"",IF(N(G124)>0,"供应商付款","供应商退款"),IF(L124<>"","费用支出",""))))) | P124: =IF(O124="","",IFERROR(INDEX(基础资料!$AE$5:$AE$34,MATCH(O124,基础资料!$AC$5:$AC$34,0)),"未知")) | Q124: =IF(P124="应收",COUNTIF(P$7:P124,"应收"),"") | R124: =IF(P124="应付",COUNTIF(P$7:P124,"应付"),"") | S124: =N(F124)-N(G124) -> 0
A125: =IF(AND(F125="",G125=""),"",ROW()-6) | H125: =IF(OR(C125="",AND(F125="",G125="")),"",SUMIF(基础资料!$W$5:$W$24,C125,基础资料!$X$5:$X$24)+SUMIF(C$7:C125,C125,F$7:F125)-SUMIF(C$7:C125,C125,G$7:G125)) | I125: =IF(AND(F125="",G125=""),"",SUM(基础资料!$X$5:$X$24)+SUM(F$7:F125)-SUM(G$7:G125)) | N125: =IF(AND(AND(F125="",G125=""),B125="",C125="",D125="",J125="",K125="",L125=""),"",IF(AND(F125="",G125=""),"✗ 没填金额",IF(AND(N(F125)<>0,N(G125)<>0),"✗ 收入、支出只能填一边",IF(NOT(ISNUMBER(B125)),"✗ 日期不是真日期（要像 2026/9/25 这样填）",IF(OR(B125<年初日,B125>年末日),"✗ 日期不在本会计年度",IF(C125="","✗ 没选账户",IF(COUNTIF(基础资料!$W$5:$W$24,C125)=0,"✗ 账户不在基础资料里",IF(O125="","✗ 没选收支项目",IF(P125="未知","✗ 收支项目不在基础资料里",IF(AND(P125="应收",J125=""),"✗ 这笔要选客户",IF(AND(P125="应收",COUNTIF(总览汇总!$B$5:$B$304,J125)=0),"✗ 客户不在总览汇总名单里",IF(AND(P125="应付",K125=""),"✗ 这笔要选供应商",IF(AND(P125="应付",COUNTIF(基础资料!$Q$5:$Q$54,K125)=0),"✗ 供应商不在基础资料里",IF(AND(P125="费用",L125=""),"✗ 费用支出要选费用项目",IF(AND(L125<>"",COUNTIF(基础资料!$AI$5:$AI$54,L125)=0),"✗ 费用项目不在基础资料里",IF(AND(IFERROR(INDEX(基础资料!$AD$5:$AD$34,MATCH(O125,基础资料!$AC$5:$AC$34,0)),"")="收",N(G125)<>0),"✗ 这类是收款，金额填到收入列",IF(AND(IFERROR(INDEX(基础资料!$AD$5:$AD$34,MATCH(O125,基础资料!$AC$5:$AC$34,0)),"")="支",N(F125)<>0),"✗ 这类是付款，金额填到支出列",IF(N(H125)<0,"⚠ 账户余额成负数了，核对一下","√")))))))))))))))))) | O125: =IF(D125<>"",D125,IF(AND(F125="",G125=""),"",IF(J125<>"",IF(N(F125)>0,"客户回款","客户退款"),IF(K125<>"",IF(N(G125)>0,"供应商付款","供应商退款"),IF(L125<>"","费用支出",""))))) | P125: =IF(O125="","",IFERROR(INDEX(基础资料!$AE$5:$AE$34,MATCH(O125,基础资料!$AC$5:$AC$34,0)),"未知")) | Q125: =IF(P125="应收",COUNTIF(P$7:P125,"应收"),"") | R125: =IF(P125="应付",COUNTIF(P$7:P125,"应付"),"") | S125: =N(F125)-N(G125) -> 0
A126: =IF(AND(F126="",G126=""),"",ROW()-6) | H126: =IF(OR(C126="",AND(F126="",G126="")),"",SUMIF(基础资料!$W$5:$W$24,C126,基础资料!$X$5:$X$24)+SUMIF(C$7:C126,C126,F$7:F126)-SUMIF(C$7:C126,C126,G$7:G126)) | I126: =IF(AND(F126="",G126=""),"",SUM(基础资料!$X$5:$X$24)+SUM(F$7:F126)-SUM(G$7:G126)) | N126: =IF(AND(AND(F126="",G126=""),B126="",C126="",D126="",J126="",K126="",L126=""),"",IF(AND(F126="",G126=""),"✗ 没填金额",IF(AND(N(F126)<>0,N(G126)<>0),"✗ 收入、支出只能填一边",IF(NOT(ISNUMBER(B126)),"✗ 日期不是真日期（要像 2026/9/25 这样填）",IF(OR(B126<年初日,B126>年末日),"✗ 日期不在本会计年度",IF(C126="","✗ 没选账户",IF(COUNTIF(基础资料!$W$5:$W$24,C126)=0,"✗ 账户不在基础资料里",IF(O126="","✗ 没选收支项目",IF(P126="未知","✗ 收支项目不在基础资料里",IF(AND(P126="应收",J126=""),"✗ 这笔要选客户",IF(AND(P126="应收",COUNTIF(总览汇总!$B$5:$B$304,J126)=0),"✗ 客户不在总览汇总名单里",IF(AND(P126="应付",K126=""),"✗ 这笔要选供应商",IF(AND(P126="应付",COUNTIF(基础资料!$Q$5:$Q$54,K126)=0),"✗ 供应商不在基础资料里",IF(AND(P126="费用",L126=""),"✗ 费用支出要选费用项目",IF(AND(L126<>"",COUNTIF(基础资料!$AI$5:$AI$54,L126)=0),"✗ 费用项目不在基础资料里",IF(AND(IFERROR(INDEX(基础资料!$AD$5:$AD$34,MATCH(O126,基础资料!$AC$5:$AC$34,0)),"")="收",N(G126)<>0),"✗ 这类是收款，金额填到收入列",IF(AND(IFERROR(INDEX(基础资料!$AD$5:$AD$34,MATCH(O126,基础资料!$AC$5:$AC$34,0)),"")="支",N(F126)<>0),"✗ 这类是付款，金额填到支出列",IF(N(H126)<0,"⚠ 账户余额成负数了，核对一下","√")))))))))))))))))) | O126: =IF(D126<>"",D126,IF(AND(F126="",G126=""),"",IF(J126<>"",IF(N(F126)>0,"客户回款","客户退款"),IF(K126<>"",IF(N(G126)>0,"供应商付款","供应商退款"),IF(L126<>"","费用支出",""))))) | P126: =IF(O126="","",IFERROR(INDEX(基础资料!$AE$5:$AE$34,MATCH(O126,基础资料!$AC$5:$AC$34,0)),"未知")) | Q126: =IF(P126="应收",COUNTIF(P$7:P126,"应收"),"") | R126: =IF(P126="应付",COUNTIF(P$7:P126,"应付"),"") | S126: =N(F126)-N(G126) -> 0
A127: =IF(AND(F127="",G127=""),"",ROW()-6) | H127: =IF(OR(C127="",AND(F127="",G127="")),"",SUMIF(基础资料!$W$5:$W$24,C127,基础资料!$X$5:$X$24)+SUMIF(C$7:C127,C127,F$7:F127)-SUMIF(C$7:C127,C127,G$7:G127)) | I127: =IF(AND(F127="",G127=""),"",SUM(基础资料!$X$5:$X$24)+SUM(F$7:F127)-SUM(G$7:G127)) | N127: =IF(AND(AND(F127="",G127=""),B127="",C127="",D127="",J127="",K127="",L127=""),"",IF(AND(F127="",G127=""),"✗ 没填金额",IF(AND(N(F127)<>0,N(G127)<>0),"✗ 收入、支出只能填一边",IF(NOT(ISNUMBER(B127)),"✗ 日期不是真日期（要像 2026/9/25 这样填）",IF(OR(B127<年初日,B127>年末日),"✗ 日期不在本会计年度",IF(C127="","✗ 没选账户",IF(COUNTIF(基础资料!$W$5:$W$24,C127)=0,"✗ 账户不在基础资料里",IF(O127="","✗ 没选收支项目",IF(P127="未知","✗ 收支项目不在基础资料里",IF(AND(P127="应收",J127=""),"✗ 这笔要选客户",IF(AND(P127="应收",COUNTIF(总览汇总!$B$5:$B$304,J127)=0),"✗ 客户不在总览汇总名单里",IF(AND(P127="应付",K127=""),"✗ 这笔要选供应商",IF(AND(P127="应付",COUNTIF(基础资料!$Q$5:$Q$54,K127)=0),"✗ 供应商不在基础资料里",IF(AND(P127="费用",L127=""),"✗ 费用支出要选费用项目",IF(AND(L127<>"",COUNTIF(基础资料!$AI$5:$AI$54,L127)=0),"✗ 费用项目不在基础资料里",IF(AND(IFERROR(INDEX(基础资料!$AD$5:$AD$34,MATCH(O127,基础资料!$AC$5:$AC$34,0)),"")="收",N(G127)<>0),"✗ 这类是收款，金额填到收入列",IF(AND(IFERROR(INDEX(基础资料!$AD$5:$AD$34,MATCH(O127,基础资料!$AC$5:$AC$34,0)),"")="支",N(F127)<>0),"✗ 这类是付款，金额填到支出列",IF(N(H127)<0,"⚠ 账户余额成负数了，核对一下","√")))))))))))))))))) | O127: =IF(D127<>"",D127,IF(AND(F127="",G127=""),"",IF(J127<>"",IF(N(F127)>0,"客户回款","客户退款"),IF(K127<>"",IF(N(G127)>0,"供应商付款","供应商退款"),IF(L127<>"","费用支出",""))))) | P127: =IF(O127="","",IFERROR(INDEX(基础资料!$AE$5:$AE$34,MATCH(O127,基础资料!$AC$5:$AC$34,0)),"未知")) | Q127: =IF(P127="应收",COUNTIF(P$7:P127,"应收"),"") | R127: =IF(P127="应付",COUNTIF(P$7:P127,"应付"),"") | S127: =N(F127)-N(G127) -> 0
A128: =IF(AND(F128="",G128=""),"",ROW()-6) | H128: =IF(OR(C128="",AND(F128="",G128="")),"",SUMIF(基础资料!$W$5:$W$24,C128,基础资料!$X$5:$X$24)+SUMIF(C$7:C128,C128,F$7:F128)-SUMIF(C$7:C128,C128,G$7:G128)) | I128: =IF(AND(F128="",G128=""),"",SUM(基础资料!$X$5:$X$24)+SUM(F$7:F128)-SUM(G$7:G128)) | N128: =IF(AND(AND(F128="",G128=""),B128="",C128="",D128="",J128="",K128="",L128=""),"",IF(AND(F128="",G128=""),"✗ 没填金额",IF(AND(N(F128)<>0,N(G128)<>0),"✗ 收入、支出只能填一边",IF(NOT(ISNUMBER(B128)),"✗ 日期不是真日期（要像 2026/9/25 这样填）",IF(OR(B128<年初日,B128>年末日),"✗ 日期不在本会计年度",IF(C128="","✗ 没选账户",IF(COUNTIF(基础资料!$W$5:$W$24,C128)=0,"✗ 账户不在基础资料里",IF(O128="","✗ 没选收支项目",IF(P128="未知","✗ 收支项目不在基础资料里",IF(AND(P128="应收",J128=""),"✗ 这笔要选客户",IF(AND(P128="应收",COUNTIF(总览汇总!$B$5:$B$304,J128)=0),"✗ 客户不在总览汇总名单里",IF(AND(P128="应付",K128=""),"✗ 这笔要选供应商",IF(AND(P128="应付",COUNTIF(基础资料!$Q$5:$Q$54,K128)=0),"✗ 供应商不在基础资料里",IF(AND(P128="费用",L128=""),"✗ 费用支出要选费用项目",IF(AND(L128<>"",COUNTIF(基础资料!$AI$5:$AI$54,L128)=0),"✗ 费用项目不在基础资料里",IF(AND(IFERROR(INDEX(基础资料!$AD$5:$AD$34,MATCH(O128,基础资料!$AC$5:$AC$34,0)),"")="收",N(G128)<>0),"✗ 这类是收款，金额填到收入列",IF(AND(IFERROR(INDEX(基础资料!$AD$5:$AD$34,MATCH(O128,基础资料!$AC$5:$AC$34,0)),"")="支",N(F128)<>0),"✗ 这类是付款，金额填到支出列",IF(N(H128)<0,"⚠ 账户余额成负数了，核对一下","√")))))))))))))))))) | O128: =IF(D128<>"",D128,IF(AND(F128="",G128=""),"",IF(J128<>"",IF(N(F128)>0,"客户回款","客户退款"),IF(K128<>"",IF(N(G128)>0,"供应商付款","供应商退款"),IF(L128<>"","费用支出",""))))) | P128: =IF(O128="","",IFERROR(INDEX(基础资料!$AE$5:$AE$34,MATCH(O128,基础资料!$AC$5:$AC$34,0)),"未知")) | Q128: =IF(P128="应收",COUNTIF(P$7:P128,"应收"),"") | R128: =IF(P128="应付",COUNTIF(P$7:P128,"应付"),"") | S128: =N(F128)-N(G128) -> 0
A129: =IF(AND(F129="",G129=""),"",ROW()-6) | H129: =IF(OR(C129="",AND(F129="",G129="")),"",SUMIF(基础资料!$W$5:$W$24,C129,基础资料!$X$5:$X$24)+SUMIF(C$7:C129,C129,F$7:F129)-SUMIF(C$7:C129,C129,G$7:G129)) | I129: =IF(AND(F129="",G129=""),"",SUM(基础资料!$X$5:$X$24)+SUM(F$7:F129)-SUM(G$7:G129)) | N129: =IF(AND(AND(F129="",G129=""),B129="",C129="",D129="",J129="",K129="",L129=""),"",IF(AND(F129="",G129=""),"✗ 没填金额",IF(AND(N(F129)<>0,N(G129)<>0),"✗ 收入、支出只能填一边",IF(NOT(ISNUMBER(B129)),"✗ 日期不是真日期（要像 2026/9/25 这样填）",IF(OR(B129<年初日,B129>年末日),"✗ 日期不在本会计年度",IF(C129="","✗ 没选账户",IF(COUNTIF(基础资料!$W$5:$W$24,C129)=0,"✗ 账户不在基础资料里",IF(O129="","✗ 没选收支项目",IF(P129="未知","✗ 收支项目不在基础资料里",IF(AND(P129="应收",J129=""),"✗ 这笔要选客户",IF(AND(P129="应收",COUNTIF(总览汇总!$B$5:$B$304,J129)=0),"✗ 客户不在总览汇总名单里",IF(AND(P129="应付",K129=""),"✗ 这笔要选供应商",IF(AND(P129="应付",COUNTIF(基础资料!$Q$5:$Q$54,K129)=0),"✗ 供应商不在基础资料里",IF(AND(P129="费用",L129=""),"✗ 费用支出要选费用项目",IF(AND(L129<>"",COUNTIF(基础资料!$AI$5:$AI$54,L129)=0),"✗ 费用项目不在基础资料里",IF(AND(IFERROR(INDEX(基础资料!$AD$5:$AD$34,MATCH(O129,基础资料!$AC$5:$AC$34,0)),"")="收",N(G129)<>0),"✗ 这类是收款，金额填到收入列",IF(AND(IFERROR(INDEX(基础资料!$AD$5:$AD$34,MATCH(O129,基础资料!$AC$5:$AC$34,0)),"")="支",N(F129)<>0),"✗ 这类是付款，金额填到支出列",IF(N(H129)<0,"⚠ 账户余额成负数了，核对一下","√")))))))))))))))))) | O129: =IF(D129<>"",D129,IF(AND(F129="",G129=""),"",IF(J129<>"",IF(N(F129)>0,"客户回款","客户退款"),IF(K129<>"",IF(N(G129)>0,"供应商付款","供应商退款"),IF(L129<>"","费用支出",""))))) | P129: =IF(O129="","",IFERROR(INDEX(基础资料!$AE$5:$AE$34,MATCH(O129,基础资料!$AC$5:$AC$34,0)),"未知")) | Q129: =IF(P129="应收",COUNTIF(P$7:P129,"应收"),"") | R129: =IF(P129="应付",COUNTIF(P$7:P129,"应付"),"") | S129: =N(F129)-N(G129) -> 0
A130: =IF(AND(F130="",G130=""),"",ROW()-6) | H130: =IF(OR(C130="",AND(F130="",G130="")),"",SUMIF(基础资料!$W$5:$W$24,C130,基础资料!$X$5:$X$24)+SUMIF(C$7:C130,C130,F$7:F130)-SUMIF(C$7:C130,C130,G$7:G130)) | I130: =IF(AND(F130="",G130=""),"",SUM(基础资料!$X$5:$X$24)+SUM(F$7:F130)-SUM(G$7:G130)) | N130: =IF(AND(AND(F130="",G130=""),B130="",C130="",D130="",J130="",K130="",L130=""),"",IF(AND(F130="",G130=""),"✗ 没填金额",IF(AND(N(F130)<>0,N(G130)<>0),"✗ 收入、支出只能填一边",IF(NOT(ISNUMBER(B130)),"✗ 日期不是真日期（要像 2026/9/25 这样填）",IF(OR(B130<年初日,B130>年末日),"✗ 日期不在本会计年度",IF(C130="","✗ 没选账户",IF(COUNTIF(基础资料!$W$5:$W$24,C130)=0,"✗ 账户不在基础资料里",IF(O130="","✗ 没选收支项目",IF(P130="未知","✗ 收支项目不在基础资料里",IF(AND(P130="应收",J130=""),"✗ 这笔要选客户",IF(AND(P130="应收",COUNTIF(总览汇总!$B$5:$B$304,J130)=0),"✗ 客户不在总览汇总名单里",IF(AND(P130="应付",K130=""),"✗ 这笔要选供应商",IF(AND(P130="应付",COUNTIF(基础资料!$Q$5:$Q$54,K130)=0),"✗ 供应商不在基础资料里",IF(AND(P130="费用",L130=""),"✗ 费用支出要选费用项目",IF(AND(L130<>"",COUNTIF(基础资料!$AI$5:$AI$54,L130)=0),"✗ 费用项目不在基础资料里",IF(AND(IFERROR(INDEX(基础资料!$AD$5:$AD$34,MATCH(O130,基础资料!$AC$5:$AC$34,0)),"")="收",N(G130)<>0),"✗ 这类是收款，金额填到收入列",IF(AND(IFERROR(INDEX(基础资料!$AD$5:$AD$34,MATCH(O130,基础资料!$AC$5:$AC$34,0)),"")="支",N(F130)<>0),"✗ 这类是付款，金额填到支出列",IF(N(H130)<0,"⚠ 账户余额成负数了，核对一下","√")))))))))))))))))) | O130: =IF(D130<>"",D130,IF(AND(F130="",G130=""),"",IF(J130<>"",IF(N(F130)>0,"客户回款","客户退款"),IF(K130<>"",IF(N(G130)>0,"供应商付款","供应商退款"),IF(L130<>"","费用支出",""))))) | P130: =IF(O130="","",IFERROR(INDEX(基础资料!$AE$5:$AE$34,MATCH(O130,基础资料!$AC$5:$AC$34,0)),"未知")) | Q130: =IF(P130="应收",COUNTIF(P$7:P130,"应收"),"") | R130: =IF(P130="应付",COUNTIF(P$7:P130,"应付"),"") | S130: =N(F130)-N(G130) -> 0
A131: =IF(AND(F131="",G131=""),"",ROW()-6) | H131: =IF(OR(C131="",AND(F131="",G131="")),"",SUMIF(基础资料!$W$5:$W$24,C131,基础资料!$X$5:$X$24)+SUMIF(C$7:C131,C131,F$7:F131)-SUMIF(C$7:C131,C131,G$7:G131)) | I131: =IF(AND(F131="",G131=""),"",SUM(基础资料!$X$5:$X$24)+SUM(F$7:F131)-SUM(G$7:G131)) | N131: =IF(AND(AND(F131="",G131=""),B131="",C131="",D131="",J131="",K131="",L131=""),"",IF(AND(F131="",G131=""),"✗ 没填金额",IF(AND(N(F131)<>0,N(G131)<>0),"✗ 收入、支出只能填一边",IF(NOT(ISNUMBER(B131)),"✗ 日期不是真日期（要像 2026/9/25 这样填）",IF(OR(B131<年初日,B131>年末日),"✗ 日期不在本会计年度",IF(C131="","✗ 没选账户",IF(COUNTIF(基础资料!$W$5:$W$24,C131)=0,"✗ 账户不在基础资料里",IF(O131="","✗ 没选收支项目",IF(P131="未知","✗ 收支项目不在基础资料里",IF(AND(P131="应收",J131=""),"✗ 这笔要选客户",IF(AND(P131="应收",COUNTIF(总览汇总!$B$5:$B$304,J131)=0),"✗ 客户不在总览汇总名单里",IF(AND(P131="应付",K131=""),"✗ 这笔要选供应商",IF(AND(P131="应付",COUNTIF(基础资料!$Q$5:$Q$54,K131)=0),"✗ 供应商不在基础资料里",IF(AND(P131="费用",L131=""),"✗ 费用支出要选费用项目",IF(AND(L131<>"",COUNTIF(基础资料!$AI$5:$AI$54,L131)=0),"✗ 费用项目不在基础资料里",IF(AND(IFERROR(INDEX(基础资料!$AD$5:$AD$34,MATCH(O131,基础资料!$AC$5:$AC$34,0)),"")="收",N(G131)<>0),"✗ 这类是收款，金额填到收入列",IF(AND(IFERROR(INDEX(基础资料!$AD$5:$AD$34,MATCH(O131,基础资料!$AC$5:$AC$34,0)),"")="支",N(F131)<>0),"✗ 这类是付款，金额填到支出列",IF(N(H131)<0,"⚠ 账户余额成负数了，核对一下","√")))))))))))))))))) | O131: =IF(D131<>"",D131,IF(AND(F131="",G131=""),"",IF(J131<>"",IF(N(F131)>0,"客户回款","客户退款"),IF(K131<>"",IF(N(G131)>0,"供应商付款","供应商退款"),IF(L131<>"","费用支出",""))))) | P131: =IF(O131="","",IFERROR(INDEX(基础资料!$AE$5:$AE$34,MATCH(O131,基础资料!$AC$5:$AC$34,0)),"未知")) | Q131: =IF(P131="应收",COUNTIF(P$7:P131,"应收"),"") | R131: =IF(P131="应付",COUNTIF(P$7:P131,"应付"),"") | S131: =N(F131)-N(G131) -> 0
A132: =IF(AND(F132="",G132=""),"",ROW()-6) | H132: =IF(OR(C132="",AND(F132="",G132="")),"",SUMIF(基础资料!$W$5:$W$24,C132,基础资料!$X$5:$X$24)+SUMIF(C$7:C132,C132,F$7:F132)-SUMIF(C$7:C132,C132,G$7:G132)) | I132: =IF(AND(F132="",G132=""),"",SUM(基础资料!$X$5:$X$24)+SUM(F$7:F132)-SUM(G$7:G132)) | N132: =IF(AND(AND(F132="",G132=""),B132="",C132="",D132="",J132="",K132="",L132=""),"",IF(AND(F132="",G132=""),"✗ 没填金额",IF(AND(N(F132)<>0,N(G132)<>0),"✗ 收入、支出只能填一边",IF(NOT(ISNUMBER(B132)),"✗ 日期不是真日期（要像 2026/9/25 这样填）",IF(OR(B132<年初日,B132>年末日),"✗ 日期不在本会计年度",IF(C132="","✗ 没选账户",IF(COUNTIF(基础资料!$W$5:$W$24,C132)=0,"✗ 账户不在基础资料里",IF(O132="","✗ 没选收支项目",IF(P132="未知","✗ 收支项目不在基础资料里",IF(AND(P132="应收",J132=""),"✗ 这笔要选客户",IF(AND(P132="应收",COUNTIF(总览汇总!$B$5:$B$304,J132)=0),"✗ 客户不在总览汇总名单里",IF(AND(P132="应付",K132=""),"✗ 这笔要选供应商",IF(AND(P132="应付",COUNTIF(基础资料!$Q$5:$Q$54,K132)=0),"✗ 供应商不在基础资料里",IF(AND(P132="费用",L132=""),"✗ 费用支出要选费用项目",IF(AND(L132<>"",COUNTIF(基础资料!$AI$5:$AI$54,L132)=0),"✗ 费用项目不在基础资料里",IF(AND(IFERROR(INDEX(基础资料!$AD$5:$AD$34,MATCH(O132,基础资料!$AC$5:$AC$34,0)),"")="收",N(G132)<>0),"✗ 这类是收款，金额填到收入列",IF(AND(IFERROR(INDEX(基础资料!$AD$5:$AD$34,MATCH(O132,基础资料!$AC$5:$AC$34,0)),"")="支",N(F132)<>0),"✗ 这类是付款，金额填到支出列",IF(N(H132)<0,"⚠ 账户余额成负数了，核对一下","√")))))))))))))))))) | O132: =IF(D132<>"",D132,IF(AND(F132="",G132=""),"",IF(J132<>"",IF(N(F132)>0,"客户回款","客户退款"),IF(K132<>"",IF(N(G132)>0,"供应商付款","供应商退款"),IF(L132<>"","费用支出",""))))) | P132: =IF(O132="","",IFERROR(INDEX(基础资料!$AE$5:$AE$34,MATCH(O132,基础资料!$AC$5:$AC$34,0)),"未知")) | Q132: =IF(P132="应收",COUNTIF(P$7:P132,"应收"),"") | R132: =IF(P132="应付",COUNTIF(P$7:P132,"应付"),"") | S132: =N(F132)-N(G132) -> 0
A133: =IF(AND(F133="",G133=""),"",ROW()-6) | H133: =IF(OR(C133="",AND(F133="",G133="")),"",SUMIF(基础资料!$W$5:$W$24,C133,基础资料!$X$5:$X$24)+SUMIF(C$7:C133,C133,F$7:F133)-SUMIF(C$7:C133,C133,G$7:G133)) | I133: =IF(AND(F133="",G133=""),"",SUM(基础资料!$X$5:$X$24)+SUM(F$7:F133)-SUM(G$7:G133)) | N133: =IF(AND(AND(F133="",G133=""),B133="",C133="",D133="",J133="",K133="",L133=""),"",IF(AND(F133="",G133=""),"✗ 没填金额",IF(AND(N(F133)<>0,N(G133)<>0),"✗ 收入、支出只能填一边",IF(NOT(ISNUMBER(B133)),"✗ 日期不是真日期（要像 2026/9/25 这样填）",IF(OR(B133<年初日,B133>年末日),"✗ 日期不在本会计年度",IF(C133="","✗ 没选账户",IF(COUNTIF(基础资料!$W$5:$W$24,C133)=0,"✗ 账户不在基础资料里",IF(O133="","✗ 没选收支项目",IF(P133="未知","✗ 收支项目不在基础资料里",IF(AND(P133="应收",J133=""),"✗ 这笔要选客户",IF(AND(P133="应收",COUNTIF(总览汇总!$B$5:$B$304,J133)=0),"✗ 客户不在总览汇总名单里",IF(AND(P133="应付",K133=""),"✗ 这笔要选供应商",IF(AND(P133="应付",COUNTIF(基础资料!$Q$5:$Q$54,K133)=0),"✗ 供应商不在基础资料里",IF(AND(P133="费用",L133=""),"✗ 费用支出要选费用项目",IF(AND(L133<>"",COUNTIF(基础资料!$AI$5:$AI$54,L133)=0),"✗ 费用项目不在基础资料里",IF(AND(IFERROR(INDEX(基础资料!$AD$5:$AD$34,MATCH(O133,基础资料!$AC$5:$AC$34,0)),"")="收",N(G133)<>0),"✗ 这类是收款，金额填到收入列",IF(AND(IFERROR(INDEX(基础资料!$AD$5:$AD$34,MATCH(O133,基础资料!$AC$5:$AC$34,0)),"")="支",N(F133)<>0),"✗ 这类是付款，金额填到支出列",IF(N(H133)<0,"⚠ 账户余额成负数了，核对一下","√")))))))))))))))))) | O133: =IF(D133<>"",D133,IF(AND(F133="",G133=""),"",IF(J133<>"",IF(N(F133)>0,"客户回款","客户退款"),IF(K133<>"",IF(N(G133)>0,"供应商付款","供应商退款"),IF(L133<>"","费用支出",""))))) | P133: =IF(O133="","",IFERROR(INDEX(基础资料!$AE$5:$AE$34,MATCH(O133,基础资料!$AC$5:$AC$34,0)),"未知")) | Q133: =IF(P133="应收",COUNTIF(P$7:P133,"应收"),"") | R133: =IF(P133="应付",COUNTIF(P$7:P133,"应付"),"") | S133: =N(F133)-N(G133) -> 0
A134: =IF(AND(F134="",G134=""),"",ROW()-6) | H134: =IF(OR(C134="",AND(F134="",G134="")),"",SUMIF(基础资料!$W$5:$W$24,C134,基础资料!$X$5:$X$24)+SUMIF(C$7:C134,C134,F$7:F134)-SUMIF(C$7:C134,C134,G$7:G134)) | I134: =IF(AND(F134="",G134=""),"",SUM(基础资料!$X$5:$X$24)+SUM(F$7:F134)-SUM(G$7:G134)) | N134: =IF(AND(AND(F134="",G134=""),B134="",C134="",D134="",J134="",K134="",L134=""),"",IF(AND(F134="",G134=""),"✗ 没填金额",IF(AND(N(F134)<>0,N(G134)<>0),"✗ 收入、支出只能填一边",IF(NOT(ISNUMBER(B134)),"✗ 日期不是真日期（要像 2026/9/25 这样填）",IF(OR(B134<年初日,B134>年末日),"✗ 日期不在本会计年度",IF(C134="","✗ 没选账户",IF(COUNTIF(基础资料!$W$5:$W$24,C134)=0,"✗ 账户不在基础资料里",IF(O134="","✗ 没选收支项目",IF(P134="未知","✗ 收支项目不在基础资料里",IF(AND(P134="应收",J134=""),"✗ 这笔要选客户",IF(AND(P134="应收",COUNTIF(总览汇总!$B$5:$B$304,J134)=0),"✗ 客户不在总览汇总名单里",IF(AND(P134="应付",K134=""),"✗ 这笔要选供应商",IF(AND(P134="应付",COUNTIF(基础资料!$Q$5:$Q$54,K134)=0),"✗ 供应商不在基础资料里",IF(AND(P134="费用",L134=""),"✗ 费用支出要选费用项目",IF(AND(L134<>"",COUNTIF(基础资料!$AI$5:$AI$54,L134)=0),"✗ 费用项目不在基础资料里",IF(AND(IFERROR(INDEX(基础资料!$AD$5:$AD$34,MATCH(O134,基础资料!$AC$5:$AC$34,0)),"")="收",N(G134)<>0),"✗ 这类是收款，金额填到收入列",IF(AND(IFERROR(INDEX(基础资料!$AD$5:$AD$34,MATCH(O134,基础资料!$AC$5:$AC$34,0)),"")="支",N(F134)<>0),"✗ 这类是付款，金额填到支出列",IF(N(H134)<0,"⚠ 账户余额成负数了，核对一下","√")))))))))))))))))) | O134: =IF(D134<>"",D134,IF(AND(F134="",G134=""),"",IF(J134<>"",IF(N(F134)>0,"客户回款","客户退款"),IF(K134<>"",IF(N(G134)>0,"供应商付款","供应商退款"),IF(L134<>"","费用支出",""))))) | P134: =IF(O134="","",IFERROR(INDEX(基础资料!$AE$5:$AE$34,MATCH(O134,基础资料!$AC$5:$AC$34,0)),"未知")) | Q134: =IF(P134="应收",COUNTIF(P$7:P134,"应收"),"") | R134: =IF(P134="应付",COUNTIF(P$7:P134,"应付"),"") | S134: =N(F134)-N(G134) -> 0
A135: =IF(AND(F135="",G135=""),"",ROW()-6) | H135: =IF(OR(C135="",AND(F135="",G135="")),"",SUMIF(基础资料!$W$5:$W$24,C135,基础资料!$X$5:$X$24)+SUMIF(C$7:C135,C135,F$7:F135)-SUMIF(C$7:C135,C135,G$7:G135)) | I135: =IF(AND(F135="",G135=""),"",SUM(基础资料!$X$5:$X$24)+SUM(F$7:F135)-SUM(G$7:G135)) | N135: =IF(AND(AND(F135="",G135=""),B135="",C135="",D135="",J135="",K135="",L135=""),"",IF(AND(F135="",G135=""),"✗ 没填金额",IF(AND(N(F135)<>0,N(G135)<>0),"✗ 收入、支出只能填一边",IF(NOT(ISNUMBER(B135)),"✗ 日期不是真日期（要像 2026/9/25 这样填）",IF(OR(B135<年初日,B135>年末日),"✗ 日期不在本会计年度",IF(C135="","✗ 没选账户",IF(COUNTIF(基础资料!$W$5:$W$24,C135)=0,"✗ 账户不在基础资料里",IF(O135="","✗ 没选收支项目",IF(P135="未知","✗ 收支项目不在基础资料里",IF(AND(P135="应收",J135=""),"✗ 这笔要选客户",IF(AND(P135="应收",COUNTIF(总览汇总!$B$5:$B$304,J135)=0),"✗ 客户不在总览汇总名单里",IF(AND(P135="应付",K135=""),"✗ 这笔要选供应商",IF(AND(P135="应付",COUNTIF(基础资料!$Q$5:$Q$54,K135)=0),"✗ 供应商不在基础资料里",IF(AND(P135="费用",L135=""),"✗ 费用支出要选费用项目",IF(AND(L135<>"",COUNTIF(基础资料!$AI$5:$AI$54,L135)=0),"✗ 费用项目不在基础资料里",IF(AND(IFERROR(INDEX(基础资料!$AD$5:$AD$34,MATCH(O135,基础资料!$AC$5:$AC$34,0)),"")="收",N(G135)<>0),"✗ 这类是收款，金额填到收入列",IF(AND(IFERROR(INDEX(基础资料!$AD$5:$AD$34,MATCH(O135,基础资料!$AC$5:$AC$34,0)),"")="支",N(F135)<>0),"✗ 这类是付款，金额填到支出列",IF(N(H135)<0,"⚠ 账户余额成负数了，核对一下","√")))))))))))))))))) | O135: =IF(D135<>"",D135,IF(AND(F135="",G135=""),"",IF(J135<>"",IF(N(F135)>0,"客户回款","客户退款"),IF(K135<>"",IF(N(G135)>0,"供应商付款","供应商退款"),IF(L135<>"","费用支出",""))))) | P135: =IF(O135="","",IFERROR(INDEX(基础资料!$AE$5:$AE$34,MATCH(O135,基础资料!$AC$5:$AC$34,0)),"未知")) | Q135: =IF(P135="应收",COUNTIF(P$7:P135,"应收"),"") | R135: =IF(P135="应付",COUNTIF(P$7:P135,"应付"),"") | S135: =N(F135)-N(G135) -> 0
... A3006: =IF(AND(F3006="",G3006=""),"",ROW()-6) | H3006: =IF(OR(C3006="",AND(F3006="",G3006="")),"",SUMIF(基础资料!$W$5:$W$24,C3006,基础资料!$X$5:$X$24)+SUMIF(C$7:C3006,C3006,F$7:F3006)-SUMIF(C$7:C3006,C3006,G$7:G3006)) | I3006: =IF(AND(F3006="",G3006=""),"",SUM(基础资料!$X$5:$X$24)+SUM(F$7:F3006)-SUM(G$7:G3006)) | N3006: =IF(AND(AND(F3006="",G3006=""),B3006="",C3006="",D3006="",J3006="",K3006="",L3006=""),"",IF(AND(F3006="",G3006=""),"✗ 没填金额",IF(AND(N(F3006)<>0,N(G3006)<>0),"✗ 收入、支出只能填一边",IF(NOT(ISNUMBER(B3006)),"✗ 日期不是真日期（要像 2026/9/25 这样填）",IF(OR(B3006<年初日,B3006>年末日),"✗ 日期不在本会计年度",IF(C3006="","✗ 没选账户",IF(COUNTIF(基础资料!$W$5:$W$24,C3006)=0,"✗ 账户不在基础资料里",IF(O3006="","✗ 没选收支项目",IF(P3006="未知","✗ 收支项目不在基础资料里",IF(AND(P3006="应收",J3006=""),"✗ 这笔要选客户",IF(AND(P3006="应收",COUNTIF(总览汇总!$B$5:$B$304,J3006)=0),"✗ 客户不在总览汇总名单里",IF(AND(P3006="应付",K3006=""),"✗ 这笔要选供应商",IF(AND(P3006="应付",COUNTIF(基础资料!$Q$5:$Q$54,K3006)=0),"✗ 供应商不在基础资料里",IF(AND(P3006="费用",L3006=""),"✗ 费用支出要选费用项目",IF(AND(L3006<>"",COUNTIF(基础资料!$AI$5:$AI$54,L3006)=0),"✗ 费用项目不在基础资料里",IF(AND(IFERROR(INDEX(基础资料!$AD$5:$AD$34,MATCH(O3006,基础资料!$AC$5:$AC$34,0)),"")="收",N(G3006)<>0),"✗ 这类是收款，金额填到收入列",IF(AND(IFERROR(INDEX(基础资料!$AD$5:$AD$34,MATCH(O3006,基础资料!$AC$5:$AC$34,0)),"")="支",N(F3006)<>0),"✗ 这类是付款，金额填到支出列",IF(N(H3006)<0,"⚠ 账户余额成负数了，核对一下","√")))))))))))))))))) | O3006: =IF(D3006<>"",D3006,IF(AND(F3006="",G3006=""),"",IF(J3006<>"",IF(N(F3006)>0,"客户回款","客户退款"),IF(K3006<>"",IF(N(G3006)>0,"供应商付款","供应商退款"),IF(L3006<>"","费用支出",""))))) | P3006: =IF(O3006="","",IFERROR(INDEX(基础资料!$AE$5:$AE$34,MATCH(O3006,基础资料!$AC$5:$AC$34,0)),"未知")) | Q3006: =IF(P3006="应收",COUNTIF(P$7:P3006,"应收"),"") | R3006: =IF(P3006="应付",COUNTIF(P$7:P3006,"应付"),"") | S3006: =N(F3006)-N(G3006) -> 0

Sheet 采购进货
A1: 采购进货明细台账
A2: 💡 从厂家/供应商进货在这里登记，一个商品一行：数量×进价自动出金额；厂家搭赠的货填「赠品数量」，只加库存不加货款；退货数量填负数。付货款去【资金台帐】记一笔并选供应商。公司库存、成本、利润表、供应商对账单都从这里取数。
A3: 序号 | B3: 日期 | C3: 供应商 | D3: 商品品类 | E3: 数量(件) | F3: 进价(元/件) | G3: 金额(元) | H3: 赠品数量(件) | I3: 备注 | J3: 校验
A4: =IF(AND(C4="",D4=""),"",ROW()-3) | G4: =IF(AND(E4<>"",F4<>""),E4*F4,"") | J4: =IF(AND(B4="",C4="",D4="",E4="",F4="",H4=""),"",IF(NOT(ISNUMBER(B4)),"✗ 日期不是真日期",IF(OR(B4<年初日,B4>年末日),"✗ 日期不在本年度",IF(C4="","✗ 没选供应商",IF(COUNTIF(基础资料!$Q$5:$Q$54,C4)=0,"✗ 供应商不在基础资料里",IF(D4="","✗ 没选商品",IF(COUNTIF(基础资料!$E$5:$E$104,D4)=0,"✗ 商品不在商品档案里",IF(AND(E4="",H4=""),"✗ 没填数量",IF(AND(N(E4)<>0,F4=""),"✗ 没填进价","√")))))))))
A5: =IF(AND(C5="",D5=""),"",ROW()-3) | G5: =IF(AND(E5<>"",F5<>""),E5*F5,"") | J5: =IF(AND(B5="",C5="",D5="",E5="",F5="",H5=""),"",IF(NOT(ISNUMBER(B5)),"✗ 日期不是真日期",IF(OR(B5<年初日,B5>年末日),"✗ 日期不在本年度",IF(C5="","✗ 没选供应商",IF(COUNTIF(基础资料!$Q$5:$Q$54,C5)=0,"✗ 供应商不在基础资料里",IF(D5="","✗ 没选商品",IF(COUNTIF(基础资料!$E$5:$E$104,D5)=0,"✗ 商品不在商品档案里",IF(AND(E5="",H5=""),"✗ 没填数量",IF(AND(N(E5)<>0,F5=""),"✗ 没填进价","√")))))))))
A6: =IF(AND(C6="",D6=""),"",ROW()-3) | G6: =IF(AND(E6<>"",F6<>""),E6*F6,"") | J6: =IF(AND(B6="",C6="",D6="",E6="",F6="",H6=""),"",IF(NOT(ISNUMBER(B6)),"✗ 日期不是真日期",IF(OR(B6<年初日,B6>年末日),"✗ 日期不在本年度",IF(C6="","✗ 没选供应商",IF(COUNTIF(基础资料!$Q$5:$Q$54,C6)=0,"✗ 供应商不在基础资料里",IF(D6="","✗ 没选商品",IF(COUNTIF(基础资料!$E$5:$E$104,D6)=0,"✗ 商品不在商品档案里",IF(AND(E6="",H6=""),"✗ 没填数量",IF(AND(N(E6)<>0,F6=""),"✗ 没填进价","√")))))))))
A7: =IF(AND(C7="",D7=""),"",ROW()-3) | G7: =IF(AND(E7<>"",F7<>""),E7*F7,"") | J7: =IF(AND(B7="",C7="",D7="",E7="",F7="",H7=""),"",IF(NOT(ISNUMBER(B7)),"✗ 日期不是真日期",IF(OR(B7<年初日,B7>年末日),"✗ 日期不在本年度",IF(C7="","✗ 没选供应商",IF(COUNTIF(基础资料!$Q$5:$Q$54,C7)=0,"✗ 供应商不在基础资料里",IF(D7="","✗ 没选商品",IF(COUNTIF(基础资料!$E$5:$E$104,D7)=0,"✗ 商品不在商品档案里",IF(AND(E7="",H7=""),"✗ 没填数量",IF(AND(N(E7)<>0,F7=""),"✗ 没填进价","√")))))))))
A8: =IF(AND(C8="",D8=""),"",ROW()-3) | G8: =IF(AND(E8<>"",F8<>""),E8*F8,"") | J8: =IF(AND(B8="",C8="",D8="",E8="",F8="",H8=""),"",IF(NOT(ISNUMBER(B8)),"✗ 日期不是真日期",IF(OR(B8<年初日,B8>年末日),"✗ 日期不在本年度",IF(C8="","✗ 没选供应商",IF(COUNTIF(基础资料!$Q$5:$Q$54,C8)=0,"✗ 供应商不在基础资料里",IF(D8="","✗ 没选商品",IF(COUNTIF(基础资料!$E$5:$E$104,D8)=0,"✗ 商品不在商品档案里",IF(AND(E8="",H8=""),"✗ 没填数量",IF(AND(N(E8)<>0,F8=""),"✗ 没填进价","√")))))))))
A9: =IF(AND(C9="",D9=""),"",ROW()-3) | G9: =IF(AND(E9<>"",F9<>""),E9*F9,"") | J9: =IF(AND(B9="",C9="",D9="",E9="",F9="",H9=""),"",IF(NOT(ISNUMBER(B9)),"✗ 日期不是真日期",IF(OR(B9<年初日,B9>年末日),"✗ 日期不在本年度",IF(C9="","✗ 没选供应商",IF(COUNTIF(基础资料!$Q$5:$Q$54,C9)=0,"✗ 供应商不在基础资料里",IF(D9="","✗ 没选商品",IF(COUNTIF(基础资料!$E$5:$E$104,D9)=0,"✗ 商品不在商品档案里",IF(AND(E9="",H9=""),"✗ 没填数量",IF(AND(N(E9)<>0,F9=""),"✗ 没填进价","√")))))))))
A10: =IF(AND(C10="",D10=""),"",ROW()-3) | G10: =IF(AND(E10<>"",F10<>""),E10*F10,"") | J10: =IF(AND(B10="",C10="",D10="",E10="",F10="",H10=""),"",IF(NOT(ISNUMBER(B10)),"✗ 日期不是真日期",IF(OR(B10<年初日,B10>年末日),"✗ 日期不在本年度",IF(C10="","✗ 没选供应商",IF(COUNTIF(基础资料!$Q$5:$Q$54,C10)=0,"✗ 供应商不在基础资料里",IF(D10="","✗ 没选商品",IF(COUNTIF(基础资料!$E$5:$E$104,D10)=0,"✗ 商品不在商品档案里",IF(AND(E10="",H10=""),"✗ 没填数量",IF(AND(N(E10)<>0,F10=""),"✗ 没填进价","√")))))))))
A11: =IF(AND(C11="",D11=""),"",ROW()-3) | G11: =IF(AND(E11<>"",F11<>""),E11*F11,"") | J11: =IF(AND(B11="",C11="",D11="",E11="",F11="",H11=""),"",IF(NOT(ISNUMBER(B11)),"✗ 日期不是真日期",IF(OR(B11<年初日,B11>年末日),"✗ 日期不在本年度",IF(C11="","✗ 没选供应商",IF(COUNTIF(基础资料!$Q$5:$Q$54,C11)=0,"✗ 供应商不在基础资料里",IF(D11="","✗ 没选商品",IF(COUNTIF(基础资料!$E$5:$E$104,D11)=0,"✗ 商品不在商品档案里",IF(AND(E11="",H11=""),"✗ 没填数量",IF(AND(N(E11)<>0,F11=""),"✗ 没填进价","√")))))))))
A12: =IF(AND(C12="",D12=""),"",ROW()-3) | G12: =IF(AND(E12<>"",F12<>""),E12*F12,"") | J12: =IF(AND(B12="",C12="",D12="",E12="",F12="",H12=""),"",IF(NOT(ISNUMBER(B12)),"✗ 日期不是真日期",IF(OR(B12<年初日,B12>年末日),"✗ 日期不在本年度",IF(C12="","✗ 没选供应商",IF(COUNTIF(基础资料!$Q$5:$Q$54,C12)=0,"✗ 供应商不在基础资料里",IF(D12="","✗ 没选商品",IF(COUNTIF(基础资料!$E$5:$E$104,D12)=0,"✗ 商品不在商品档案里",IF(AND(E12="",H12=""),"✗ 没填数量",IF(AND(N(E12)<>0,F12=""),"✗ 没填进价","√")))))))))
A13: =IF(AND(C13="",D13=""),"",ROW()-3) | G13: =IF(AND(E13<>"",F13<>""),E13*F13,"") | J13: =IF(AND(B13="",C13="",D13="",E13="",F13="",H13=""),"",IF(NOT(ISNUMBER(B13)),"✗ 日期不是真日期",IF(OR(B13<年初日,B13>年末日),"✗ 日期不在本年度",IF(C13="","✗ 没选供应商",IF(COUNTIF(基础资料!$Q$5:$Q$54,C13)=0,"✗ 供应商不在基础资料里",IF(D13="","✗ 没选商品",IF(COUNTIF(基础资料!$E$5:$E$104,D13)=0,"✗ 商品不在商品档案里",IF(AND(E13="",H13=""),"✗ 没填数量",IF(AND(N(E13)<>0,F13=""),"✗ 没填进价","√")))))))))
A14: =IF(AND(C14="",D14=""),"",ROW()-3) | G14: =IF(AND(E14<>"",F14<>""),E14*F14,"") | J14: =IF(AND(B14="",C14="",D14="",E14="",F14="",H14=""),"",IF(NOT(ISNUMBER(B14)),"✗ 日期不是真日期",IF(OR(B14<年初日,B14>年末日),"✗ 日期不在本年度",IF(C14="","✗ 没选供应商",IF(COUNTIF(基础资料!$Q$5:$Q$54,C14)=0,"✗ 供应商不在基础资料里",IF(D14="","✗ 没选商品",IF(COUNTIF(基础资料!$E$5:$E$104,D14)=0,"✗ 商品不在商品档案里",IF(AND(E14="",H14=""),"✗ 没填数量",IF(AND(N(E14)<>0,F14=""),"✗ 没填进价","√")))))))))
A15: =IF(AND(C15="",D15=""),"",ROW()-3) | G15: =IF(AND(E15<>"",F15<>""),E15*F15,"") | J15: =IF(AND(B15="",C15="",D15="",E15="",F15="",H15=""),"",IF(NOT(ISNUMBER(B15)),"✗ 日期不是真日期",IF(OR(B15<年初日,B15>年末日),"✗ 日期不在本年度",IF(C15="","✗ 没选供应商",IF(COUNTIF(基础资料!$Q$5:$Q$54,C15)=0,"✗ 供应商不在基础资料里",IF(D15="","✗ 没选商品",IF(COUNTIF(基础资料!$E$5:$E$104,D15)=0,"✗ 商品不在商品档案里",IF(AND(E15="",H15=""),"✗ 没填数量",IF(AND(N(E15)<>0,F15=""),"✗ 没填进价","√")))))))))
... A1503: =IF(AND(C1503="",D1503=""),"",ROW()-3) | G1503: =IF(AND(E1503<>"",F1503<>""),E1503*F1503,"") | J1503: =IF(AND(B1503="",C1503="",D1503="",E1503="",F1503="",H1503=""),"",IF(NOT(ISNUMBER(B1503)),"✗ 日期不是真日期",IF(OR(B1503<年初日,B1503>年末日),"✗ 日期不在本年度",IF(C1503="","✗ 没选供应商",IF(COUNTIF(基础资料!$Q$5:$Q$54,C1503)=0,"✗ 供应商不在基础资料里",IF(D1503="","✗ 没选商品",IF(COUNTIF(基础资料!$E$5:$E$104,D1503)=0,"✗ 商品不在商品档案里",IF(AND(E1503="",H1503=""),"✗ 没填数量",IF(AND(N(E1503)<>0,F1503=""),"✗ 没填进价","√")))))))))

Sheet 总览汇总
A1: 客户存条&货款总览汇总表
A2: 💡 一篮子查看所有客户情况：新增客户在 B 列往下接着填（C 列填初始存条金额，K 列填上年结转过来的欠款）；领用记【出库明细】、收款记【资金台帐】并选客户，数据自动更新
A3: 序号 | B3: 客户名称 | C3: 初始存条金额(元) | D3: 已领用金额(元) | E3: 剩余存条金额(元) | F3: 已付款金额(元) | G3: 未付货款(元) | H3: 状态 | I3: 库存总结余数量(件) | J3: 库存总结余金额(元) | K3: 期初欠款(元)
B4: 合计 | C4: =C305 -> 3138507.2 | D4: =D305 -> 1707307.7 | E4: =E305 -> 1446536 | F4: =F305 -> 3869309.7 | G4: =G305 -> -2162002 | I4: =I305 -> 25340 | J4: =J305 -> 1993075.8 | K4: =K305 -> 0
A5: =IF(B5="","",COUNTA($B$5:B5)) -> 1 | B5: 星海超市 | C5: 39547 | D5: =IF(B5<>"",SUMIF(出库明细!C:C,B5,出库明细!G:G),"") -> 77322 | E5: =IF(AND(C5<>"",D5<>""),C5-D5,"") -> -37775 | F5: =IF(B5<>"",SUMIFS(资金台帐!$S:$S,资金台帐!$J:$J,B5,资金台帐!$P:$P,"应收"),"") -> 148067 | G5: =IF(B5="","",N(K5)+N(D5)-N(F5)) -> -70745 | H5: =IF(B5="","",IF(G5=0,"已结清",IF(G5>0,"有欠款","预存款"))) -> 预存款 | I5: =IFERROR(SUMIF(商品库存!B:B,B5,商品库存!I:I),0) -> 1167 | J5: =IFERROR(SUMIF(商品库存!B:B,B5,商品库存!J:J),0) -> 73781
A6: =IF(B6="","",COUNTA($B$5:B6)) -> 2 | B6: 王玉琴 | C6: 99000 | D6: =IF(B6<>"",SUMIF(出库明细!C:C,B6,出库明细!G:G),"") -> 54172.5 | E6: =IF(AND(C6<>"",D6<>""),C6-D6,"") -> 44827.5 | F6: =IF(B6<>"",SUMIFS(资金台帐!$S:$S,资金台帐!$J:$J,B6,资金台帐!$P:$P,"应收"),"") -> 106697 | G6: =IF(B6="","",N(K6)+N(D6)-N(F6)) -> -52524.5 | H6: =IF(B6="","",IF(G6=0,"已结清",IF(G6>0,"有欠款","预存款"))) -> 预存款 | I6: =IFERROR(SUMIF(商品库存!B:B,B6,商品库存!I:I),0) -> 462.5 | J6: =IFERROR(SUMIF(商品库存!B:B,B6,商品库存!J:J),0) -> 44827.5
A7: =IF(B7="","",COUNTA($B$5:B7)) -> 3 | B7: 桐心源 | C7: 700231.47 | D7: =IF(B7<>"",SUMIF(出库明细!C:C,B7,出库明细!G:G),"") -> 416695 | E7: =IF(AND(C7<>"",D7<>""),C7-D7,"") -> 283536.47 | F7: =IF(B7<>"",SUMIFS(资金台帐!$S:$S,资金台帐!$J:$J,B7,资金台帐!$P:$P,"应收"),"") -> 868551.47 | G7: =IF(B7="","",N(K7)+N(D7)-N(F7)) -> -451856.47 | H7: =IF(B7="","",IF(G7=0,"已结清",IF(G7>0,"有欠款","预存款"))) -> 预存款 | I7: =IFERROR(SUMIF(商品库存!B:B,B7,商品库存!I:I),0) -> 5560 | J7: =IFERROR(SUMIF(商品库存!B:B,B7,商品库存!J:J),0) -> 469317
A8: =IF(B8="","",COUNTA($B$5:B8)) -> 4 | B8: 阿东副食 | C8: 570147.22 | D8: =IF(B8<>"",SUMIF(出库明细!C:C,B8,出库明细!G:G),"") -> 184072 | E8: =IF(AND(C8<>"",D8<>""),C8-D8,"") -> 386075.22 | F8: =IF(B8<>"",SUMIFS(资金台帐!$S:$S,资金台帐!$J:$J,B8,资金台帐!$P:$P,"应收"),"") -> 649147.22 | G8: =IF(B8="","",N(K8)+N(D8)-N(F8)) -> -465075.22 | H8: =IF(B8="","",IF(G8=0,"已结清",IF(G8>0,"有欠款","预存款"))) -> 预存款 | I8: =IFERROR(SUMIF(商品库存!B:B,B8,商品库存!I:I),0) -> 6575 | J8: =IFERROR(SUMIF(商品库存!B:B,B8,商品库存!J:J),0) -> 511410
A9: =IF(B9="","",COUNTA($B$5:B9)) -> 5 | B9: 金凤副食 | C9: 8950 | D9: =IF(B9<>"",SUMIF(出库明细!C:C,B9,出库明细!G:G),"") -> 47079.2 | E9: =IF(AND(C9<>"",D9<>""),C9-D9,"") -> -38129.2 | F9: =IF(B9<>"",SUMIFS(资金台帐!$S:$S,资金台帐!$J:$J,B9,资金台帐!$P:$P,"应收"),"") -> 56950 | G9: =IF(B9="","",N(K9)+N(D9)-N(F9)) -> -9870.8 | H9: =IF(B9="","",IF(G9=0,"已结清",IF(G9>0,"有欠款","预存款"))) -> 预存款 | I9: =IFERROR(SUMIF(商品库存!B:B,B9,商品库存!I:I),0) -> -690 | J9: =IFERROR(SUMIF(商品库存!B:B,B9,商品库存!J:J),0) -> -38129.2
A10: =IF(B10="","",COUNTA($B$5:B10)) -> 6 | B10: 致发商行 | C10: 437965 | D10: =IF(B10<>"",SUMIF(出库明细!C:C,B10,出库明细!G:G),"") -> 164100 | E10: =IF(AND(C10<>"",D10<>""),C10-D10,"") -> 273865 | F10: =IF(B10<>"",SUMIFS(资金台帐!$S:$S,资金台帐!$J:$J,B10,资金台帐!$P:$P,"应收"),"") -> 437965 | G10: =IF(B10="","",N(K10)+N(D10)-N(F10)) -> -273865 | H10: =IF(B10="","",IF(G10=0,"已结清",IF(G10>0,"有欠款","预存款"))) -> 预存款 | I10: =IFERROR(SUMIF(商品库存!B:B,B10,商品库存!I:I),0) -> 3165 | J10: =IFERROR(SUMIF(商品库存!B:B,B10,商品库存!J:J),0) -> 273865
A11: =IF(B11="","",COUNTA($B$5:B11)) -> 7 | B11: 家家兴超市 | D11: =IF(B11<>"",SUMIF(出库明细!C:C,B11,出库明细!G:G),"") -> 14616.5 | E11: =IF(AND(C11<>"",D11<>""),C11-D11,"") | F11: =IF(B11<>"",SUMIFS(资金台帐!$S:$S,资金台帐!$J:$J,B11,资金台帐!$P:$P,"应收"),"") -> 12579 | G11: =IF(B11="","",N(K11)+N(D11)-N(F11)) -> 2037.5 | H11: =IF(B11="","",IF(G11=0,"已结清",IF(G11>0,"有欠款","预存款"))) -> 有欠款 | I11: =IFERROR(SUMIF(商品库存!B:B,B11,商品库存!I:I),0) -> -233 | J11: =IFERROR(SUMIF(商品库存!B:B,B11,商品库存!J:J),0) -> -14616.5
A12: =IF(B12="","",COUNTA($B$5:B12)) -> 8 | B12: 通达商行 | C12: 18000 | D12: =IF(B12<>"",SUMIF(出库明细!C:C,B12,出库明细!G:G),"") -> 18000 | E12: =IF(AND(C12<>"",D12<>""),C12-D12,"") -> 0 | F12: =IF(B12<>"",SUMIFS(资金台帐!$S:$S,资金台帐!$J:$J,B12,资金台帐!$P:$P,"应收"),"") -> 18000 | G12: =IF(B12="","",N(K12)+N(D12)-N(F12)) -> 0 | H12: =IF(B12="","",IF(G12=0,"已结清",IF(G12>0,"有欠款","预存款"))) -> 已结清 | I12: =IFERROR(SUMIF(商品库存!B:B,B12,商品库存!I:I),0) -> 0 | J12: =IFERROR(SUMIF(商品库存!B:B,B12,商品库存!J:J),0) -> 0
A13: =IF(B13="","",COUNTA($B$5:B13)) -> 9 | B13: 宜兴粮油 | C13: 54000 | D13: =IF(B13<>"",SUMIF(出库明细!C:C,B13,出库明细!G:G),"") -> 64943.5 | E13: =IF(AND(C13<>"",D13<>""),C13-D13,"") -> -10943.5 | F13: =IF(B13<>"",SUMIFS(资金台帐!$S:$S,资金台帐!$J:$J,B13,资金台帐!$P:$P,"应收"),"") -> 66416.5 | G13: =IF(B13="","",N(K13)+N(D13)-N(F13)) -> -1473 | H13: =IF(B13="","",IF(G13=0,"已结清",IF(G13>0,"有欠款","预存款"))) -> 预存款 | I13: =IFERROR(SUMIF(商品库存!B:B,B13,商品库存!I:I),0) -> 45 | J13: =IFERROR(SUMIF(商品库存!B:B,B13,商品库存!J:J),0) -> 1473
A14: =IF(B14="","",COUNTA($B$5:B14)) -> 10 | B14: 马路下小卖部 | C14: 19440 | D14: =IF(B14<>"",SUMIF(出库明细!C:C,B14,出库明细!G:G),"") -> 4986 | E14: =IF(AND(C14<>"",D14<>""),C14-D14,"") -> 14454 | F14: =IF(B14<>"",SUMIFS(资金台帐!$S:$S,资金台帐!$J:$J,B14,资金台帐!$P:$P,"应收"),"") -> 19440 | G14: =IF(B14="","",N(K14)+N(D14)-N(F14)) -> -14454 | H14: =IF(B14="","",IF(G14=0,"已结清",IF(G14>0,"有欠款","预存款"))) -> 预存款 | I14: =IFERROR(SUMIF(商品库存!B:B,B14,商品库存!I:I),0) -> 144 | J14: =IFERROR(SUMIF(商品库存!B:B,B14,商品库存!J:J),0) -> 13614
A15: =IF(B15="","",COUNTA($B$5:B15)) -> 11 | B15: 兴莲隆兴商行 | C15: 30043 | D15: =IF(B15<>"",SUMIF(出库明细!C:C,B15,出库明细!G:G),"") -> 27050 | E15: =IF(AND(C15<>"",D15<>""),C15-D15,"") -> 2993 | F15: =IF(B15<>"",SUMIFS(资金台帐!$S:$S,资金台帐!$J:$J,B15,资金台帐!$P:$P,"应收"),"") -> 39043 | G15: =IF(B15="","",N(K15)+N(D15)-N(F15)) -> -11993 | H15: =IF(B15="","",IF(G15=0,"已结清",IF(G15>0,"有欠款","预存款"))) -> 预存款 | I15: =IFERROR(SUMIF(商品库存!B:B,B15,商品库存!I:I),0) -> -106 | J15: =IFERROR(SUMIF(商品库存!B:B,B15,商品库存!J:J),0) -> -3307
A16: =IF(B16="","",COUNTA($B$5:B16)) -> 12 | B16: 诚信粮油 | C16: 29565 | D16: =IF(B16<>"",SUMIF(出库明细!C:C,B16,出库明细!G:G),"") -> 29900 | E16: =IF(AND(C16<>"",D16<>""),C16-D16,"") -> -335 | F16: =IF(B16<>"",SUMIFS(资金台帐!$S:$S,资金台帐!$J:$J,B16,资金台帐!$P:$P,"应收"),"") -> 79565 | G16: =IF(B16="","",N(K16)+N(D16)-N(F16)) -> -49665 | H16: =IF(B16="","",IF(G16=0,"已结清",IF(G16>0,"有欠款","预存款"))) -> 预存款 | I16: =IFERROR(SUMIF(商品库存!B:B,B16,商品库存!I:I),0) -> -50 | J16: =IFERROR(SUMIF(商品库存!B:B,B16,商品库存!J:J),0) -> -2900
A17: =IF(B17="","",COUNTA($B$5:B17)) -> 13 | B17: 李记副食 | C17: 6930 | D17: =IF(B17<>"",SUMIF(出库明细!C:C,B17,出库明细!G:G),"") -> 6562.5 | E17: =IF(AND(C17<>"",D17<>""),C17-D17,"") -> 367.5 | F17: =IF(B17<>"",SUMIFS(资金台帐!$S:$S,资金台帐!$J:$J,B17,资金台帐!$P:$P,"应收"),"") -> 6930 | G17: =IF(B17="","",N(K17)+N(D17)-N(F17)) -> -367.5 | H17: =IF(B17="","",IF(G17=0,"已结清",IF(G17>0,"有欠款","预存款"))) -> 预存款 | I17: =IFERROR(SUMIF(商品库存!B:B,B17,商品库存!I:I),0) -> -80.5 | J17: =IFERROR(SUMIF(商品库存!B:B,B17,商品库存!J:J),0) -> -6562.5
A18: =IF(B18="","",COUNTA($B$5:B18)) -> 14 | B18: 吕维春 | C18: 32440 | D18: =IF(B18<>"",SUMIF(出库明细!C:C,B18,出库明细!G:G),"") -> 16400 | E18: =IF(AND(C18<>"",D18<>""),C18-D18,"") -> 16040 | F18: =IF(B18<>"",SUMIFS(资金台帐!$S:$S,资金台帐!$J:$J,B18,资金台帐!$P:$P,"应收"),"") -> 62440 | G18: =IF(B18="","",N(K18)+N(D18)-N(F18)) -> -46040 | H18: =IF(B18="","",IF(G18=0,"已结清",IF(G18>0,"有欠款","预存款"))) -> 预存款 | I18: =IFERROR(SUMIF(商品库存!B:B,B18,商品库存!I:I),0) -> 200 | J18: =IFERROR(SUMIF(商品库存!B:B,B18,商品库存!J:J),0) -> 16040
A19: =IF(B19="","",COUNTA($B$5:B19)) -> 15 | B19: 兴发商行 | C19: 15300 | D19: =IF(B19<>"",SUMIF(出库明细!C:C,B19,出库明细!G:G),"") -> 9270 | E19: =IF(AND(C19<>"",D19<>""),C19-D19,"") -> 6030 | F19: =IF(B19<>"",SUMIFS(资金台帐!$S:$S,资金台帐!$J:$J,B19,资金台帐!$P:$P,"应收"),"") -> 16437.5 | G19: =IF(B19="","",N(K19)+N(D19)-N(F19)) -> -7167.5 | H19: =IF(B19="","",IF(G19=0,"已结清",IF(G19>0,"有欠款","预存款"))) -> 预存款 | I19: =IFERROR(SUMIF(商品库存!B:B,B19,商品库存!I:I),0) -> 80 | J19: =IFERROR(SUMIF(商品库存!B:B,B19,商品库存!J:J),0) -> 7167.5
A20: =IF(B20="","",COUNTA($B$5:B20)) -> 16 | B20: 城岗日日升超市 | C20: 36895 | D20: =IF(B20<>"",SUMIF(出库明细!C:C,B20,出库明细!G:G),"") -> 38496.5 | E20: =IF(AND(C20<>"",D20<>""),C20-D20,"") -> -1601.5 | F20: =IF(B20<>"",SUMIFS(资金台帐!$S:$S,资金台帐!$J:$J,B20,资金台帐!$P:$P,"应收"),"") -> 63895 | G20: =IF(B20="","",N(K20)+N(D20)-N(F20)) -> -25398.5 | H20: =IF(B20="","",IF(G20=0,"已结清",IF(G20>0,"有欠款","预存款"))) -> 预存款 | I20: =IFERROR(SUMIF(商品库存!B:B,B20,商品库存!I:I),0) -> 545 | J20: =IFERROR(SUMIF(商品库存!B:B,B20,商品库存!J:J),0) -> 25398.5
A21: =IF(B21="","",COUNTA($B$5:B21)) -> 17 | B21: 江背久明商行 | C21: 21620 | D21: =IF(B21<>"",SUMIF(出库明细!C:C,B21,出库明细!G:G),"") -> 56620 | E21: =IF(AND(C21<>"",D21<>""),C21-D21,"") -> -35000 | F21: =IF(B21<>"",SUMIFS(资金台帐!$S:$S,资金台帐!$J:$J,B21,资金台帐!$P:$P,"应收"),"") -> 21620 | G21: =IF(B21="","",N(K21)+N(D21)-N(F21)) -> 35000 | H21: =IF(B21="","",IF(G21=0,"已结清",IF(G21>0,"有欠款","预存款"))) -> 有欠款 | I21: =IFERROR(SUMIF(商品库存!B:B,B21,商品库存!I:I),0) -> 0 | J21: =IFERROR(SUMIF(商品库存!B:B,B21,商品库存!J:J),0) -> 0
A22: =IF(B22="","",COUNTA($B$5:B22)) -> 18 | B22: 社富丽华超市 | C22: 8100 | D22: =IF(B22<>"",SUMIF(出库明细!C:C,B22,出库明细!G:G),"") -> 0 | E22: =IF(AND(C22<>"",D22<>""),C22-D22,"") -> 8100 | F22: =IF(B22<>"",SUMIFS(资金台帐!$S:$S,资金台帐!$J:$J,B22,资金台帐!$P:$P,"应收"),"") -> 8100 | G22: =IF(B22="","",N(K22)+N(D22)-N(F22)) -> -8100 | H22: =IF(B22="","",IF(G22=0,"已结清",IF(G22>0,"有欠款","预存款"))) -> 预存款 | I22: =IFERROR(SUMIF(商品库存!B:B,B22,商品库存!I:I),0) -> 90 | J22: =IFERROR(SUMIF(商品库存!B:B,B22,商品库存!J:J),0) -> 8100
A23: =IF(B23="","",COUNTA($B$5:B23)) -> 19 | B23: 九鑫粮油 | C23: 3150 | D23: =IF(B23<>"",SUMIF(出库明细!C:C,B23,出库明细!G:G),"") -> 6030 | E23: =IF(AND(C23<>"",D23<>""),C23-D23,"") -> -2880 | F23: =IF(B23<>"",SUMIFS(资金台帐!$S:$S,资金台帐!$J:$J,B23,资金台帐!$P:$P,"应收"),"") -> 13150 | G23: =IF(B23="","",N(K23)+N(D23)-N(F23)) -> -7120 | H23: =IF(B23="","",IF(G23=0,"已结清",IF(G23>0,"有欠款","预存款"))) -> 预存款 | I23: =IFERROR(SUMIF(商品库存!B:B,B23,商品库存!I:I),0) -> -32 | J23: =IFERROR(SUMIF(商品库存!B:B,B23,商品库存!J:J),0) -> -2880
... A48: =IF(B48="","",COUNTA($B$5:B48)) -> 44 | B48: 好帮手 | C48: 12000 | D48: =IF(B48<>"",SUMIF(出库明细!C:C,B48,出库明细!G:G),"") -> 12327.5 | E48: =IF(AND(C48<>"",D48<>""),C48-D48,"") -> -327.5 | F48: =IF(B48<>"",SUMIFS(资金台帐!$S:$S,资金台帐!$J:$J,B48,资金台帐!$P:$P,"应收"),"") -> 12327.5 | G48: =IF(B48="","",N(K48)+N(D48)-N(F48)) -> 0 | H48: =IF(B48="","",IF(G48=0,"已结清",IF(G48>0,"有欠款","预存款"))) -> 已结清 | I48: =IFERROR(SUMIF(商品库存!B:B,B48,商品库存!I:I),0) -> -162.5 | J48: =IFERROR(SUMIF(商品库存!B:B,B48,商品库存!J:J),0) -> -12327.5
A49: =IF(B49="","",COUNTA($B$5:B49)) -> 45 | B49: 优生副食 | D49: =IF(B49<>"",SUMIF(出库明细!C:C,B49,出库明细!G:G),"") -> 720 | E49: =IF(AND(C49<>"",D49<>""),C49-D49,"") | F49: =IF(B49<>"",SUMIFS(资金台帐!$S:$S,资金台帐!$J:$J,B49,资金台帐!$P:$P,"应收"),"") -> 0 | G49: =IF(B49="","",N(K49)+N(D49)-N(F49)) -> 720 | H49: =IF(B49="","",IF(G49=0,"已结清",IF(G49>0,"有欠款","预存款"))) -> 有欠款 | I49: =IFERROR(SUMIF(商品库存!B:B,B49,商品库存!I:I),0) -> -12 | J49: =IFERROR(SUMIF(商品库存!B:B,B49,商品库存!J:J),0) -> -720
A50: =IF(B50="","",COUNTA($B$5:B50)) -> 46 | B50: 龙岗好又全超市 | C50: 137732 | D50: =IF(B50<>"",SUMIF(出库明细!C:C,B50,出库明细!G:G),"") -> 24252 | E50: =IF(AND(C50<>"",D50<>""),C50-D50,"") -> 113480 | F50: =IF(B50<>"",SUMIFS(资金台帐!$S:$S,资金台帐!$J:$J,B50,资金台帐!$P:$P,"应收"),"") -> 152732 | G50: =IF(B50="","",N(K50)+N(D50)-N(F50)) -> -128480 | H50: =IF(B50="","",IF(G50=0,"已结清",IF(G50>0,"有欠款","预存款"))) -> 预存款 | I50: =IFERROR(SUMIF(商品库存!B:B,B50,商品库存!I:I),0) -> 1573 | J50: =IFERROR(SUMIF(商品库存!B:B,B50,商品库存!J:J),0) -> 113480
A51: =IF(B51="","",COUNTA($B$5:B51)) -> 47 | B51: 友兰商行 | C51: 602 | D51: =IF(B51<>"",SUMIF(出库明细!C:C,B51,出库明细!G:G),"") -> 5252 | E51: =IF(AND(C51<>"",D51<>""),C51-D51,"") -> -4650 | F51: =IF(B51<>"",SUMIFS(资金台帐!$S:$S,资金台帐!$J:$J,B51,资金台帐!$P:$P,"应收"),"") -> 5252 | G51: =IF(B51="","",N(K51)+N(D51)-N(F51)) -> 0 | H51: =IF(B51="","",IF(G51=0,"已结清",IF(G51>0,"有欠款","预存款"))) -> 已结清 | I51: =IFERROR(SUMIF(商品库存!B:B,B51,商品库存!I:I),0) -> 0 | J51: =IFERROR(SUMIF(商品库存!B:B,B51,商品库存!J:J),0) -> 0
A52: =IF(B52="","",COUNTA($B$5:B52)) -> 48 | B52: 隆坪美林副食 | C52: 5386 | D52: =IF(B52<>"",SUMIF(出库明细!C:C,B52,出库明细!G:G),"") -> 2833 | E52: =IF(AND(C52<>"",D52<>""),C52-D52,"") -> 2553 | F52: =IF(B52<>"",SUMIFS(资金台帐!$S:$S,资金台帐!$J:$J,B52,资金台帐!$P:$P,"应收"),"") -> 5386 | G52: =IF(B52="","",N(K52)+N(D52)-N(F52)) -> -2553 | H52: =IF(B52="","",IF(G52=0,"已结清",IF(G52>0,"有欠款","预存款"))) -> 预存款 | I52: =IFERROR(SUMIF(商品库存!B:B,B52,商品库存!I:I),0) -> -50 | J52: =IFERROR(SUMIF(商品库存!B:B,B52,商品库存!J:J),0) -> -2833
A53: =IF(B53="","",COUNTA($B$5:B53)) -> 49 | B53: 高兴四季春副食 | C53: 2697 | D53: =IF(B53<>"",SUMIF(出库明细!C:C,B53,出库明细!G:G),"") -> 24180 | E53: =IF(AND(C53<>"",D53<>""),C53-D53,"") -> -21483 | F53: =IF(B53<>"",SUMIFS(资金台帐!$S:$S,资金台帐!$J:$J,B53,资金台帐!$P:$P,"应收"),"") -> 2697 | G53: =IF(B53="","",N(K53)+N(D53)-N(F53)) -> 21483 | H53: =IF(B53="","",IF(G53=0,"已结清",IF(G53>0,"有欠款","预存款"))) -> 有欠款 | I53: =IFERROR(SUMIF(商品库存!B:B,B53,商品库存!I:I),0) -> 10 | J53: =IFERROR(SUMIF(商品库存!B:B,B53,商品库存!J:J),0) -> -21483
A54: =IF(B54="","",COUNTA($B$5:B54)) -> 50 | B54: 崇贤高平副食 | C54: 2325 | D54: =IF(B54<>"",SUMIF(出库明细!C:C,B54,出库明细!G:G),"") -> 1395 | E54: =IF(AND(C54<>"",D54<>""),C54-D54,"") -> 930 | F54: =IF(B54<>"",SUMIFS(资金台帐!$S:$S,资金台帐!$J:$J,B54,资金台帐!$P:$P,"应收"),"") -> 2325 | G54: =IF(B54="","",N(K54)+N(D54)-N(F54)) -> -930 | H54: =IF(B54="","",IF(G54=0,"已结清",IF(G54>0,"有欠款","预存款"))) -> 预存款 | I54: =IFERROR(SUMIF(商品库存!B:B,B54,商品库存!I:I),0) -> 10 | J54: =IFERROR(SUMIF(商品库存!B:B,B54,商品库存!J:J),0) -> 930
A55: =IF(B55="","",COUNTA($B$5:B55)) -> 51 | B55: 高兴张声英 | C55: 2325 | D55: =IF(B55<>"",SUMIF(出库明细!C:C,B55,出库明细!G:G),"") -> 0 | E55: =IF(AND(C55<>"",D55<>""),C55-D55,"") -> 2325 | F55: =IF(B55<>"",SUMIFS(资金台帐!$S:$S,资金台帐!$J:$J,B55,资金台帐!$P:$P,"应收"),"") -> 2325 | G55: =IF(B55="","",N(K55)+N(D55)-N(F55)) -> -2325 | H55: =IF(B55="","",IF(G55=0,"已结清",IF(G55>0,"有欠款","预存款"))) -> 预存款 | I55: =IFERROR(SUMIF(商品库存!B:B,B55,商品库存!I:I),0) -> 25 | J55: =IFERROR(SUMIF(商品库存!B:B,B55,商品库存!J:J),0) -> 2325
A56: =IF(B56="","",COUNTA($B$5:B56)) -> 52 | B56: 崇贤粤客隆 | C56: 2325 | D56: =IF(B56<>"",SUMIF(出库明细!C:C,B56,出库明细!G:G),"") -> 2325 | E56: =IF(AND(C56<>"",D56<>""),C56-D56,"") -> 0 | F56: =IF(B56<>"",SUMIFS(资金台帐!$S:$S,资金台帐!$J:$J,B56,资金台帐!$P:$P,"应收"),"") -> 2325 | G56: =IF(B56="","",N(K56)+N(D56)-N(F56)) -> 0 | H56: =IF(B56="","",IF(G56=0,"已结清",IF(G56>0,"有欠款","预存款"))) -> 已结清 | I56: =IFERROR(SUMIF(商品库存!B:B,B56,商品库存!I:I),0) -> 0 | J56: =IFERROR(SUMIF(商品库存!B:B,B56,商品库存!J:J),0) -> 0
A57: =IF(B57="","",COUNTA($B$5:B57)) -> 53 | B57: 火车站关新平 | C57: 5330 | D57: =IF(B57<>"",SUMIF(出库明细!C:C,B57,出库明细!G:G),"") -> 3470 | E57: =IF(AND(C57<>"",D57<>""),C57-D57,"") -> 1860 | F57: =IF(B57<>"",SUMIFS(资金台帐!$S:$S,资金台帐!$J:$J,B57,资金台帐!$P:$P,"应收"),"") -> 5330 | G57: =IF(B57="","",N(K57)+N(D57)-N(F57)) -> -1860 | H57: =IF(B57="","",IF(G57=0,"已结清",IF(G57>0,"有欠款","预存款"))) -> 预存款 | I57: =IFERROR(SUMIF(商品库存!B:B,B57,商品库存!I:I),0) -> 20 | J57: =IFERROR(SUMIF(商品库存!B:B,B57,商品库存!J:J),0) -> 1860
A58: =IF(B58="","",COUNTA($B$5:B58)) -> 54 | B58: 洪门五香副食 | C58: 930 | D58: =IF(B58<>"",SUMIF(出库明细!C:C,B58,出库明细!G:G),"") -> 0 | E58: =IF(AND(C58<>"",D58<>""),C58-D58,"") -> 930 | F58: =IF(B58<>"",SUMIFS(资金台帐!$S:$S,资金台帐!$J:$J,B58,资金台帐!$P:$P,"应收"),"") -> 930 | G58: =IF(B58="","",N(K58)+N(D58)-N(F58)) -> -930 | H58: =IF(B58="","",IF(G58=0,"已结清",IF(G58>0,"有欠款","预存款"))) -> 预存款 | I58: =IFERROR(SUMIF(商品库存!B:B,B58,商品库存!I:I),0) -> 10 | J58: =IFERROR(SUMIF(商品库存!B:B,B58,商品库存!J:J),0) -> 930
A59: =IF(B59="","",COUNTA($B$5:B59)) -> 55 | B59: 良村万家欢超市 | C59: 1395 | D59: =IF(B59<>"",SUMIF(出库明细!C:C,B59,出库明细!G:G),"") -> 1395 | E59: =IF(AND(C59<>"",D59<>""),C59-D59,"") -> 0 | F59: =IF(B59<>"",SUMIFS(资金台帐!$S:$S,资金台帐!$J:$J,B59,资金台帐!$P:$P,"应收"),"") -> 1395 | G59: =IF(B59="","",N(K59)+N(D59)-N(F59)) -> 0 | H59: =IF(B59="","",IF(G59=0,"已结清",IF(G59>0,"有欠款","预存款"))) -> 已结清 | I59: =IFERROR(SUMIF(商品库存!B:B,B59,商品库存!I:I),0) -> 0 | J59: =IFERROR(SUMIF(商品库存!B:B,B59,商品库存!J:J),0) -> 0
A60: =IF(B60="","",COUNTA($B$5:B60)) -> 56 | B60: 滨江路小红花便利店 | C60: 3200 | D60: =IF(B60<>"",SUMIF(出库明细!C:C,B60,出库明细!G:G),"") -> 2426 | E60: =IF(AND(C60<>"",D60<>""),C60-D60,"") -> 774 | F60: =IF(B60<>"",SUMIFS(资金台帐!$S:$S,资金台帐!$J:$J,B60,资金台帐!$P:$P,"应收"),"") -> 3200 | G60: =IF(B60="","",N(K60)+N(D60)-N(F60)) -> -774 | H60: =IF(B60="","",IF(G60=0,"已结清",IF(G60>0,"有欠款","预存款"))) -> 预存款 | I60: =IFERROR(SUMIF(商品库存!B:B,B60,商品库存!I:I),0) -> 16 | J60: =IFERROR(SUMIF(商品库存!B:B,B60,商品库存!J:J),0) -> 774
A61: =IF(B61="","",COUNTA($B$5:B61)) -> 57 | B61: 滨江荣香副食 | C61: 3380 | D61: =IF(B61<>"",SUMIF(出库明细!C:C,B61,出库明细!G:G),"") -> 1932 | E61: =IF(AND(C61<>"",D61<>""),C61-D61,"") -> 1448 | F61: =IF(B61<>"",SUMIFS(资金台帐!$S:$S,资金台帐!$J:$J,B61,资金台帐!$P:$P,"应收"),"") -> 3380 | G61: =IF(B61="","",N(K61)+N(D61)-N(F61)) -> -1448 | H61: =IF(B61="","",IF(G61=0,"已结清",IF(G61>0,"有欠款","预存款"))) -> 预存款 | I61: =IFERROR(SUMIF(商品库存!B:B,B61,商品库存!I:I),0) -> 29 | J61: =IFERROR(SUMIF(商品库存!B:B,B61,商品库存!J:J),0) -> 1448
... A82: =IF(B82="","",COUNTA($B$5:B82)) -> 78 | B82: 埠头万客欢 | C82: 2750 | D82: =IF(B82<>"",SUMIF(出库明细!C:C,B82,出库明细!G:G),"") -> 0 | E82: =IF(AND(C82<>"",D82<>""),C82-D82,"") -> 2750 | F82: =IF(B82<>"",SUMIFS(资金台帐!$S:$S,资金台帐!$J:$J,B82,资金台帐!$P:$P,"应收"),"") -> 2750 | G82: =IF(B82="","",N(K82)+N(D82)-N(F82)) -> -2750 | H82: =IF(B82="","",IF(G82=0,"已结清",IF(G82>0,"有欠款","预存款"))) -> 预存款 | I82: =IFERROR(SUMIF(商品库存!B:B,B82,商品库存!I:I),0) -> 250 | J82: =IFERROR(SUMIF(商品库存!B:B,B82,商品库存!J:J),0) -> 1900
A83: =IF(B83="","",COUNTA($B$5:B83)) -> 79 | B83: 阳光超市 | D83: =IF(B83<>"",SUMIF(出库明细!C:C,B83,出库明细!G:G),"") -> 0 | E83: =IF(AND(C83<>"",D83<>""),C83-D83,"") | F83: =IF(B83<>"",SUMIFS(资金台帐!$S:$S,资金台帐!$J:$J,B83,资金台帐!$P:$P,"应收"),"") -> 11350 | G83: =IF(B83="","",N(K83)+N(D83)-N(F83)) -> -11350 | H83: =IF(B83="","",IF(G83=0,"已结清",IF(G83>0,"有欠款","预存款"))) -> 预存款 | I83: =IFERROR(SUMIF(商品库存!B:B,B83,商品库存!I:I),0) -> 0 | J83: =IFERROR(SUMIF(商品库存!B:B,B83,商品库存!J:J),0) -> 0
A84: =IF(B84="","",COUNTA($B$5:B84)) -> 80 | B84: 竹坝鸿禄食品 | D84: =IF(B84<>"",SUMIF(出库明细!C:C,B84,出库明细!G:G),"") -> 0 | E84: =IF(AND(C84<>"",D84<>""),C84-D84,"") | F84: =IF(B84<>"",SUMIFS(资金台帐!$S:$S,资金台帐!$J:$J,B84,资金台帐!$P:$P,"应收"),"") -> 0 | G84: =IF(B84="","",N(K84)+N(D84)-N(F84)) -> 0 | H84: =IF(B84="","",IF(G84=0,"已结清",IF(G84>0,"有欠款","预存款"))) -> 已结清 | I84: =IFERROR(SUMIF(商品库存!B:B,B84,商品库存!I:I),0) -> 120 | J84: =IFERROR(SUMIF(商品库存!B:B,B84,商品库存!J:J),0) -> 10100
A85: =IF(B85="","",COUNTA($B$5:B85)) -> 81 | B85: 长岗万家欢 | D85: =IF(B85<>"",SUMIF(出库明细!C:C,B85,出库明细!G:G),"") -> 0 | E85: =IF(AND(C85<>"",D85<>""),C85-D85,"") | F85: =IF(B85<>"",SUMIFS(资金台帐!$S:$S,资金台帐!$J:$J,B85,资金台帐!$P:$P,"应收"),"") -> 3000 | G85: =IF(B85="","",N(K85)+N(D85)-N(F85)) -> -3000 | H85: =IF(B85="","",IF(G85=0,"已结清",IF(G85>0,"有欠款","预存款"))) -> 预存款 | I85: =IFERROR(SUMIF(商品库存!B:B,B85,商品库存!I:I),0) -> 0 | J85: =IFERROR(SUMIF(商品库存!B:B,B85,商品库存!J:J),0) -> 0
A86: =IF(B86="","",COUNTA($B$5:B86)) | D86: =IF(B86<>"",SUMIF(出库明细!C:C,B86,出库明细!G:G),"") | E86: =IF(AND(C86<>"",D86<>""),C86-D86,"") | F86: =IF(B86<>"",SUMIFS(资金台帐!$S:$S,资金台帐!$J:$J,B86,资金台帐!$P:$P,"应收"),"") | G86: =IF(B86="","",N(K86)+N(D86)-N(F86)) | H86: =IF(B86="","",IF(G86=0,"已结清",IF(G86>0,"有欠款","预存款"))) | I86: =IFERROR(SUMIF(商品库存!B:B,B86,商品库存!I:I),0) -> 0 | J86: =IFERROR(SUMIF(商品库存!B:B,B86,商品库存!J:J),0) -> 0
A87: =IF(B87="","",COUNTA($B$5:B87)) | D87: =IF(B87<>"",SUMIF(出库明细!C:C,B87,出库明细!G:G),"") | E87: =IF(AND(C87<>"",D87<>""),C87-D87,"") | F87: =IF(B87<>"",SUMIFS(资金台帐!$S:$S,资金台帐!$J:$J,B87,资金台帐!$P:$P,"应收"),"") | G87: =IF(B87="","",N(K87)+N(D87)-N(F87)) | H87: =IF(B87="","",IF(G87=0,"已结清",IF(G87>0,"有欠款","预存款"))) | I87: =IFERROR(SUMIF(商品库存!B:B,B87,商品库存!I:I),0) -> 0 | J87: =IFERROR(SUMIF(商品库存!B:B,B87,商品库存!J:J),0) -> 0
A88: =IF(B88="","",COUNTA($B$5:B88)) | D88: =IF(B88<>"",SUMIF(出库明细!C:C,B88,出库明细!G:G),"") | E88: =IF(AND(C88<>"",D88<>""),C88-D88,"") | F88: =IF(B88<>"",SUMIFS(资金台帐!$S:$S,资金台帐!$J:$J,B88,资金台帐!$P:$P,"应收"),"") | G88: =IF(B88="","",N(K88)+N(D88)-N(F88)) | H88: =IF(B88="","",IF(G88=0,"已结清",IF(G88>0,"有欠款","预存款"))) | I88: =IFERROR(SUMIF(商品库存!B:B,B88,商品库存!I:I),0) -> 0 | J88: =IFERROR(SUMIF(商品库存!B:B,B88,商品库存!J:J),0) -> 0
A89: =IF(B89="","",COUNTA($B$5:B89)) | D89: =IF(B89<>"",SUMIF(出库明细!C:C,B89,出库明细!G:G),"") | E89: =IF(AND(C89<>"",D89<>""),C89-D89,"") | F89: =IF(B89<>"",SUMIFS(资金台帐!$S:$S,资金台帐!$J:$J,B89,资金台帐!$P:$P,"应收"),"") | G89: =IF(B89="","",N(K89)+N(D89)-N(F89)) | H89: =IF(B89="","",IF(G89=0,"已结清",IF(G89>0,"有欠款","预存款"))) | I89: =IFERROR(SUMIF(商品库存!B:B,B89,商品库存!I:I),0) -> 0 | J89: =IFERROR(SUMIF(商品库存!B:B,B89,商品库存!J:J),0) -> 0
A90: =IF(B90="","",COUNTA($B$5:B90)) | D90: =IF(B90<>"",SUMIF(出库明细!C:C,B90,出库明细!G:G),"") | E90: =IF(AND(C90<>"",D90<>""),C90-D90,"") | F90: =IF(B90<>"",SUMIFS(资金台帐!$S:$S,资金台帐!$J:$J,B90,资金台帐!$P:$P,"应收"),"") | G90: =IF(B90="","",N(K90)+N(D90)-N(F90)) | H90: =IF(B90="","",IF(G90=0,"已结清",IF(G90>0,"有欠款","预存款"))) | I90: =IFERROR(SUMIF(商品库存!B:B,B90,商品库存!I:I),0) -> 0 | J90: =IFERROR(SUMIF(商品库存!B:B,B90,商品库存!J:J),0) -> 0
A91: =IF(B91="","",COUNTA($B$5:B91)) | D91: =IF(B91<>"",SUMIF(出库明细!C:C,B91,出库明细!G:G),"") | E91: =IF(AND(C91<>"",D91<>""),C91-D91,"") | F91: =IF(B91<>"",SUMIFS(资金台帐!$S:$S,资金台帐!$J:$J,B91,资金台帐!$P:$P,"应收"),"") | G91: =IF(B91="","",N(K91)+N(D91)-N(F91)) | H91: =IF(B91="","",IF(G91=0,"已结清",IF(G91>0,"有欠款","预存款"))) | I91: =IFERROR(SUMIF(商品库存!B:B,B91,商品库存!I:I),0) -> 0 | J91: =IFERROR(SUMIF(商品库存!B:B,B91,商品库存!J:J),0) -> 0
A92: =IF(B92="","",COUNTA($B$5:B92)) | D92: =IF(B92<>"",SUMIF(出库明细!C:C,B92,出库明细!G:G),"") | E92: =IF(AND(C92<>"",D92<>""),C92-D92,"") | F92: =IF(B92<>"",SUMIFS(资金台帐!$S:$S,资金台帐!$J:$J,B92,资金台帐!$P:$P,"应收"),"") | G92: =IF(B92="","",N(K92)+N(D92)-N(F92)) | H92: =IF(B92="","",IF(G92=0,"已结清",IF(G92>0,"有欠款","预存款"))) | I92: =IFERROR(SUMIF(商品库存!B:B,B92,商品库存!I:I),0) -> 0 | J92: =IFERROR(SUMIF(商品库存!B:B,B92,商品库存!J:J),0) -> 0
A93: =IF(B93="","",COUNTA($B$5:B93)) | D93: =IF(B93<>"",SUMIF(出库明细!C:C,B93,出库明细!G:G),"") | E93: =IF(AND(C93<>"",D93<>""),C93-D93,"") | F93: =IF(B93<>"",SUMIFS(资金台帐!$S:$S,资金台帐!$J:$J,B93,资金台帐!$P:$P,"应收"),"") | G93: =IF(B93="","",N(K93)+N(D93)-N(F93)) | H93: =IF(B93="","",IF(G93=0,"已结清",IF(G93>0,"有欠款","预存款"))) | I93: =IFERROR(SUMIF(商品库存!B:B,B93,商品库存!I:I),0) -> 0 | J93: =IFERROR(SUMIF(商品库存!B:B,B93,商品库存!J:J),0) -> 0
A94: =IF(B94="","",COUNTA($B$5:B94)) | D94: =IF(B94<>"",SUMIF(出库明细!C:C,B94,出库明细!G:G),"") | E94: =IF(AND(C94<>"",D94<>""),C94-D94,"") | F94: =IF(B94<>"",SUMIFS(资金台帐!$S:$S,资金台帐!$J:$J,B94,资金台帐!$P:$P,"应收"),"") | G94: =IF(B94="","",N(K94)+N(D94)-N(F94)) | H94: =IF(B94="","",IF(G94=0,"已结清",IF(G94>0,"有欠款","预存款"))) | I94: =IFERROR(SUMIF(商品库存!B:B,B94,商品库存!I:I),0) -> 0 | J94: =IFERROR(SUMIF(商品库存!B:B,B94,商品库存!J:J),0) -> 0
A95: =IF(B95="","",COUNTA($B$5:B95)) | D95: =IF(B95<>"",SUMIF(出库明细!C:C,B95,出库明细!G:G),"") | E95: =IF(AND(C95<>"",D95<>""),C95-D95,"") | F95: =IF(B95<>"",SUMIFS(资金台帐!$S:$S,资金台帐!$J:$J,B95,资金台帐!$P:$P,"应收"),"") | G95: =IF(B95="","",N(K95)+N(D95)-N(F95)) | H95: =IF(B95="","",IF(G95=0,"已结清",IF(G95>0,"有欠款","预存款"))) | I95: =IFERROR(SUMIF(商品库存!B:B,B95,商品库存!I:I),0) -> 0 | J95: =IFERROR(SUMIF(商品库存!B:B,B95,商品库存!J:J),0) -> 0
A96: =IF(B96="","",COUNTA($B$5:B96)) | D96: =IF(B96<>"",SUMIF(出库明细!C:C,B96,出库明细!G:G),"") | E96: =IF(AND(C96<>"",D96<>""),C96-D96,"") | F96: =IF(B96<>"",SUMIFS(资金台帐!$S:$S,资金台帐!$J:$J,B96,资金台帐!$P:$P,"应收"),"") | G96: =IF(B96="","",N(K96)+N(D96)-N(F96)) | H96: =IF(B96="","",IF(G96=0,"已结清",IF(G96>0,"有欠款","预存款"))) | I96: =IFERROR(SUMIF(商品库存!B:B,B96,商品库存!I:I),0) -> 0 | J96: =IFERROR(SUMIF(商品库存!B:B,B96,商品库存!J:J),0) -> 0
A97: =IF(B97="","",COUNTA($B$5:B97)) | D97: =IF(B97<>"",SUMIF(出库明细!C:C,B97,出库明细!G:G),"") | E97: =IF(AND(C97<>"",D97<>""),C97-D97,"") | F97: =IF(B97<>"",SUMIFS(资金台帐!$S:$S,资金台帐!$J:$J,B97,资金台帐!$P:$P,"应收"),"") | G97: =IF(B97="","",N(K97)+N(D97)-N(F97)) | H97: =IF(B97="","",IF(G97=0,"已结清",IF(G97>0,"有欠款","预存款"))) | I97: =IFERROR(SUMIF(商品库存!B:B,B97,商品库存!I:I),0) -> 0 | J97: =IFERROR(SUMIF(商品库存!B:B,B97,商品库存!J:J),0) -> 0
... A304: =IF(B304="","",COUNTA($B$5:B304)) | D304: =IF(B304<>"",SUMIF(出库明细!C:C,B304,出库明细!G:G),"") | E304: =IF(AND(C304<>"",D304<>""),C304-D304,"") | F304: =IF(B304<>"",SUMIFS(资金台帐!$S:$S,资金台帐!$J:$J,B304,资金台帐!$P:$P,"应收"),"") | G304: =IF(B304="","",N(K304)+N(D304)-N(F304)) | H304: =IF(B304="","",IF(G304=0,"已结清",IF(G304>0,"有欠款","预存款"))) | I304: =IFERROR(SUMIF(商品库存!B:B,B304,商品库存!I:I),0) -> 0 | J304: =IFERROR(SUMIF(商品库存!B:B,B304,商品库存!J:J),0) -> 0
A305: 合计 | C305: =SUM(C5:C304) -> 3138507.2 | D305: =SUM(D5:D304) -> 1707307.7 | E305: =SUM(E5:E304) -> 1446536 | F305: =SUM(F5:F304) -> 3869309.7 | G305: =SUM(G5:G304) -> -2162002 | I305: =SUM(I5:I304) -> 25340 | J305: =SUM(J5:J304) -> 1993075.8 | K305: =SUM(K5:K304) -> 0

Sheet 出库明细
A1: 商品领用明细台账
A2: 💡 每次送货/拣货在此登记（客户、商品从下拉选），总览表、商品库存、利润表、对账单自动更新。金额＝数量×单价自动算；赠品没单价的照样登记数量，成本会算进去。
A3: 序号 | B3: 日期 | C3: 客户名称 | D3: 商品品类 | E3: 领用数量(件) | F3: 单价(元/件) | G3: 本次领用金额(元) | H3: 备注
A4: 1 | B4: 46202 | C4: 阿东副食 | D4: 555补水 | E4: 11 | F4: 65 | G4: =IF(AND(E4<>"",F4<>""),E4*F4,"") -> 715
A5: 2 | B5: 46202 | C5: 阿东副食 | D5: 小焙好茶 | E5: 20 | F5: 48 | G5: =IF(AND(E5<>"",F5<>""),E5*F5,"") -> 960
A6: 3 | B6: 46203 | C6: 阿东副食 | D6: 小果之茶 | E6: 166 | F6: 47 | G6: =IF(AND(E6<>"",F6<>""),E6*F6,"") -> 7802
A7: 4 | B7: 46210 | C7: 阿东副食 | D7: 555补水 | E7: 80 | F7: 65 | G7: =IF(AND(E7<>"",F7<>""),E7*F7,"") -> 5200
A8: 5 | B8: 46210 | C8: 阿东副食 | D8: 1L补水 | E8: 50 | F8: 55 | G8: =IF(AND(E8<>"",F8<>""),E8*F8,"") -> 2750
A9: 6 | B9: 46220 | C9: 阿东副食 | D9: 1L果之茶 | E9: 90 | F9: 43 | G9: =IF(AND(E9<>"",F9<>""),E9*F9,"") -> 3870
A10: 7 | B10: 46220 | C10: 阿东副食 | D10: 小焙好茶 | E10: 20 | F10: 48 | G10: =IF(AND(E10<>"",F10<>""),E10*F10,"") -> 960
A11: 8 | B11: 46220 | C11: 阿东副食 | D11: 555补水 | E11: 25 | F11: 65 | G11: =IF(AND(E11<>"",F11<>""),E11*F11,"") -> 1625
A12: 9 | B12: 46220 | C12: 阿东副食 | D12: 小果之茶 | E12: 50 | F12: 47 | G12: =IF(AND(E12<>"",F12<>""),E12*F12,"") -> 2350
A13: 10 | B13: 46227 | C13: 阿东副食 | D13: 大咖 | E13: 50 | F13: 83 | G13: =IF(AND(E13<>"",F13<>""),E13*F13,"") -> 4150
A14: 11 | B14: 46225 | C14: 阿东副食 | D14: 330大咖 | E14: 20 | F14: 90 | G14: =IF(AND(E14<>"",F14<>""),E14*F14,"") -> 1800
A15: 12 | B15: 46225 | C15: 阿东副食 | D15: 555补水 | E15: 30 | F15: 65 | G15: =IF(AND(E15<>"",F15<>""),E15*F15,"") -> 1950
... A25: 22 | B25: 46230 | C25: 诚信粮油 | D25: 大东鹏 | E25: 100 | F25: 90 | G25: =IF(AND(E25<>"",F25<>""),E25*F25,"") -> 9000
A26: 23 | B26: 46214 | C26: 城北街隆兴商行 | D26: 大东鹏 | E26: 1 | G26: =IF(AND(E26<>"",F26<>""),E26*F26,"")
A27: 24 | B27: 46214 | C27: 城北街隆兴商行 | D27: 555补水 | E27: 3 | F27: 68 | G27: =IF(AND(E27<>"",F27<>""),E27*F27,"") -> 204
A28: 25 | B28: 46214 | C28: 城北街隆兴商行 | D28: 555补水 | E28: 1 | G28: =IF(AND(E28<>"",F28<>""),E28*F28,"")
A29: 26 | B29: 46221 | C29: 崇贤三角超市 | D29: 1L补水 | E29: 5 | F29: 58 | G29: =IF(AND(E29<>"",F29<>""),E29*F29,"") -> 290
A30: 27 | B30: 46197 | C30: 枫边德华超市 | D30: 555补水 | E30: 30 | F30: 65 | G30: =IF(AND(E30<>"",F30<>""),E30*F30,"") -> 1950
A31: 28 | B31: 46221 | C31: 枫边德华超市 | D31: 大东鹏 | E31: 100 | F31: 90 | G31: =IF(AND(E31<>"",F31<>""),E31*F31,"") -> 9000
A32: 29 | B32: 46213 | C32: 福旺家优购 | D32: 大东鹏 | E32: 20 | F32: 93 | G32: =IF(AND(E32<>"",F32<>""),E32*F32,"") -> 1860
A33: 30 | B33: 46213 | C33: 福旺家优购 | D33: 小果之茶 | E33: 5 | F33: 50 | G33: =IF(AND(E33<>"",F33<>""),E33*F33,"") -> 250
A34: 31 | B34: 46213 | C34: 福旺家优购 | D34: 555补水 | E34: 3 | F34: 68 | G34: =IF(AND(E34<>"",F34<>""),E34*F34,"") -> 204
A35: 32 | B35: 46213 | C35: 福旺家优购 | D35: 1L补水 | E35: 3 | F35: 58 | G35: =IF(AND(E35<>"",F35<>""),E35*F35,"") -> 174
A36: 33 | B36: 46222 | C36: 福旺家优购 | D36: 1L补水 | E36: 12 | F36: 58 | G36: =IF(AND(E36<>"",F36<>""),E36*F36,"") -> 696
A37: 34 | B37: 46222 | C37: 福旺家优购 | D37: 1L果之茶 | E37: 10 | F37: 46 | G37: =IF(AND(E37<>"",F37<>""),E37*F37,"") -> 460
A38: 35 | B38: 46219 | C38: 福旺家优购 | D38: 大东鹏 | E38: 25 | F38: 93 | G38: =IF(AND(E38<>"",F38<>""),E38*F38,"") -> 2325
A39: 36 | B39: 46219 | C39: 福旺家优购 | D39: 555补水 | E39: 11 | F39: 68 | G39: =IF(AND(E39<>"",F39<>""),E39*F39,"") -> 748
A40: 37 | B40: 46219 | C40: 福旺家优购 | D40: 港式奶茶 | E40: 2 | F40: 72 | G40: =IF(AND(E40<>"",F40<>""),E40*F40,"") -> 144
... A61: 58 | B61: 46230 | C61: 洪门兴诚超市 | D61: 大东鹏 | E61: 100 | F61: 90 | G61: =IF(AND(E61<>"",F61<>""),E61*F61,"") -> 9000
A62: 59 | B62: 46195 | C62: 家家兴超市 | D62: 500农夫饮料 | E62: 4 | F62: 54 | G62: =IF(AND(E62<>"",F62<>""),E62*F62,"") -> 216 | H62: 高兴店
A63: 60 | B63: 46195 | C63: 家家兴超市 | D63: 500农夫饮料 | E63: 5 | F63: 54 | G63: =IF(AND(E63<>"",F63<>""),E63*F63,"") -> 270 | H63: 城岗店
A64: 61 | B64: 46200 | C64: 家家兴超市 | D64: 500农夫饮料 | E64: 6 | F64: 54 | G64: =IF(AND(E64<>"",F64<>""),E64*F64,"") -> 324 | H64: 龙岗店
A65: 62 | B65: 46203 | C65: 家家兴超市 | D65: 500农夫饮料 | E65: 10 | F65: 54 | G65: =IF(AND(E65<>"",F65<>""),E65*F65,"") -> 540 | H65: 模范城
A66: 63 | B66: 46203 | C66: 家家兴超市 | D66: 1.5L水 | E66: 2 | F66: 25 | G66: =IF(AND(E66<>"",F66<>""),E66*F66,"") -> 50
A67: 64 | B67: 46204 | C67: 家家兴超市 | D67: 500农夫饮料 | E67: 2 | F67: 54 | G67: =IF(AND(E67<>"",F67<>""),E67*F67,"") -> 108 | H67: 梅窖
A68: 65 | B68: 46204 | C68: 家家兴超市 | D68: 550农夫纯净水 | E68: 50 | F68: 14 | G68: =IF(AND(E68<>"",F68<>""),E68*F68,"") -> 700 | H68: 梅窖
A69: 66 | B69: 46204 | C69: 家家兴超市 | D69: 550农夫纯净水 | E69: -6.5 | F69: 14 | G69: =IF(AND(E69<>"",F69<>""),E69*F69,"") -> -91
A70: 67 | B70: 46205 | C70: 家家兴超市 | D70: 500农夫饮料 | E70: 2 | F70: 54 | G70: =IF(AND(E70<>"",F70<>""),E70*F70,"") -> 108 | H70: 高兴店
A71: 68 | B71: 46206 | C71: 家家兴超市 | D71: 500农夫饮料 | E71: 7 | F71: 54 | G71: =IF(AND(E71<>"",F71<>""),E71*F71,"") -> 378 | H71: 龙岗爱客来
A72: 69 | B72: 46206 | C72: 家家兴超市 | D72: 900农夫饮料 | E72: 2 | F72: 65 | G72: =IF(AND(E72<>"",F72<>""),E72*F72,"") -> 130
A73: 70 | B73: 46206 | C73: 家家兴超市 | D73: 500农夫饮料 | E73: 4 | F73: 54 | G73: =IF(AND(E73<>"",F73<>""),E73*F73,"") -> 216 | H73: 长岗爱客来
A74: 71 | B74: 46207 | C74: 家家兴超市 | D74: 大东鹏 | E74: 100 | F74: 95 | G74: =IF(AND(E74<>"",F74<>""),E74*F74,"") -> 9500 | H74: 火车站家家兴
A75: 72 | B75: 46210 | C75: 家家兴超市 | D75: 900农夫饮料 | E75: 2 | F75: 65 | G75: =IF(AND(E75<>"",F75<>""),E75*F75,"") -> 130 | H75: 梅窖
A76: 73 | B76: 46217 | C76: 家家兴超市 | D76: 500农夫饮料 | E76: 2 | F76: 54 | G76: =IF(AND(E76<>"",F76<>""),E76*F76,"") -> 108
A77: 74 | B77: 46218 | C77: 家家兴超市 | D77: 500农夫饮料 | E77: 5 | F77: 54 | G77: =IF(AND(E77<>"",F77<>""),E77*F77,"") -> 270
A78: 75 | B78: 46218 | C78: 家家兴超市 | D78: 550农夫水 | E78: 3.5 | F78: 25 | G78: =IF(AND(E78<>"",F78<>""),E78*F78,"") -> 87.5
A79: 76 | B79: 46219 | C79: 家家兴超市 | D79: 500农夫饮料 | E79: 3 | F79: 54 | G79: =IF(AND(E79<>"",F79<>""),E79*F79,"") -> 162
A80: 77 | B80: 46211 | C80: 江背久明商行 | D80: 大东鹏 | E80: 300 | F80: 90 | G80: =IF(AND(E80<>"",F80<>""),E80*F80,"") -> 27000
A81: 78 | B81: 46211 | C81: 江背久明商行 | D81: 小果之茶 | E81: 30 | F81: 47 | G81: =IF(AND(E81<>"",F81<>""),E81*F81,"") -> 1410
A82: 79 | B82: 46226 | C82: 江背久明商行 | D82: 大咖 | E82: 80 | F82: 83 | G82: =IF(AND(E82<>"",F82<>""),E82*F82,"") -> 6640
A83: 80 | B83: 46219 | C83: 金凤副食 | D83: 大东鹏 | E83: 50 | F83: 90 | G83: =IF(AND(E83<>"",F83<>""),E83*F83,"") -> 4500
A84: 81 | B84: 46221 | C84: 九鑫粮油 | D84: 大东鹏 | E84: 35 | F84: 90 | G84: =IF(AND(E84<>"",F84<>""),E84*F84,"") -> 3150 | H84: 存条已清
A85: 82 | B85: 46202 | C85: 李记副食 | D85: 555补水 | E85: 4 | F85: 65 | G85: =IF(AND(E85<>"",F85<>""),E85*F85,"") -> 260
A86: 83 | B86: 46209 | C86: 李记副食 | D86: 555补水 | E86: 16.5 | F86: 65 | G86: =IF(AND(E86<>"",F86<>""),E86*F86,"") -> 1072.5
A87: 84 | B87: 46226 | C87: 李记副食 | D87: 小东鹏 | E87: 5 | F87: 51 | G87: =IF(AND(E87<>"",F87<>""),E87*F87,"") -> 255
A88: 85 | B88: 46227 | C88: 龙岗好又全超市 | D88: 555补水 | E88: 50 | F88: 65 | G88: =IF(AND(E88<>"",F88<>""),E88*F88,"") -> 3250
A89: 86 | B89: 46227 | C89: 龙岗好又全超市 | D89: 1L补水 | E89: 50 | F89: 55 | G89: =IF(AND(E89<>"",F89<>""),E89*F89,"") -> 2750
A90: 87 | B90: 46227 | C90: 龙岗好又全超市 | D90: 1L果之茶 | E90: 50 | F90: 43 | G90: =IF(AND(E90<>"",F90<>""),E90*F90,"") -> 2150
A91: 88 | B91: 46227 | C91: 龙岗好又全超市 | D91: 大咖 | E91: 14 | F91: 83 | G91: =IF(AND(E91<>"",F91<>""),E91*F91,"") -> 1162
A92: 89 | B92: 46227 | C92: 隆坪美林副食 | D92: 小果之茶 | E92: 6 | F92: 50 | G92: =IF(AND(E92<>"",F92<>""),E92*F92,"") -> 300
A93: 90 | B93: 46227 | C93: 隆坪美林副食 | D93: 1L焙好茶 | E93: 1 | F93: 46 | G93: =IF(AND(E93<>"",F93<>""),E93*F93,"") -> 46
A94: 91 | B94: 46219 | C94: 隆坪美林副食 | D94: 1L补水 | E94: 4 | F94: 58 | G94: =IF(AND(E94<>"",F94<>""),E94*F94,"") -> 232
A95: 92 | B95: 46219 | C95: 隆坪美林副食 | D95: 555补水 | E95: 11 | F95: 68 | G95: 680
A96: 93 | B96: 46219 | C96: 隆坪美林副食 | D96: 小果之茶 | E96: 3 | F96: 50 | G96: =IF(AND(E96<>"",F96<>""),E96*F96,"") -> 150
A97: 94 | B97: 46219 | C97: 隆坪美林副食 | D97: 1L果之茶 | E97: 6 | F97: 46 | G97: =IF(AND(E97<>"",F97<>""),E97*F97,"") -> 276
A98: 95 | B98: 46213 | C98: 吕维春 | D98: 大东鹏 | E98: 50 | F98: 90 | G98: =IF(AND(E98<>"",F98<>""),E98*F98,"") -> 4500
A99: 96 | B99: 46200 | C99: 马路下小卖部 | D99: 小果之茶 | E99: 2 | F99: 50 | G99: =IF(AND(E99<>"",F99<>""),E99*F99,"") -> 100
A100: 97 | B100: 46210 | C100: 马路下小卖部 | D100: 555补水 | E100: 2 | F100: 68 | G100: =IF(AND(E100<>"",F100<>""),E100*F100,"") -> 136
A101: 98 | B101: 46210 | C101: 马路下小卖部 | D101: 小果之茶 | E101: 2 | F101: 50 | G101: =IF(AND(E101<>"",F101<>""),E101*F101,"") -> 100
A102: 99 | B102: 46204 | C102: 梅窖建军批发 | D102: 555补水 | E102: 10 | F102: 65 | G102: =IF(AND(E102<>"",F102<>""),E102*F102,"") -> 650
A103: 100 | B103: 46213 | C103: 梅窖建军批发 | D103: 555补水 | E103: 20 | F103: 65 | G103: =IF(AND(E103<>"",F103<>""),E103*F103,"") -> 1300
A104: 101 | B104: 46213 | C104: 梅窖建军批发 | D104: 1L补水 | E104: 20 | F104: 55 | G104: =IF(AND(E104<>"",F104<>""),E104*F104,"") -> 1100
A105: 102 | B105: 46222 | C105: 梅窖建军批发 | D105: 1L果之茶 | E105: 20 | F105: 43 | G105: =IF(AND(E105<>"",F105<>""),E105*F105,"") -> 860
A106: 103 | B106: 46216 | C106: 通达商行 | D106: 大东鹏 | E106: 100 | F106: 90 | G106: =IF(AND(E106<>"",F106<>""),E106*F106,"") -> 9000
A107: 104 | B107: 46197 | C107: 桐心源 | D107: 500农夫饮料 | E107: 5 | F107: 52 | G107: =IF(AND(E107<>"",F107<>""),E107*F107,"") -> 260
... A144: 141 | B144: 46221 | C144: 桐心源 | D144: 东鹏椰子水 | E144: 50 | F144: 90 | G144: =IF(AND(E144<>"",F144<>""),E144*F144,"") -> 4500
A145: 142 | B145: 46221 | C145: 桐心源 | D145: 东鹏椰子水 | E145: 4 | G145: =IF(AND(E145<>"",F145<>""),E145*F145,"")
A146: 143 | B146: 46231 | C146: 桐心源 | D146: 小果之茶 | E146: 200 | F146: 47 | G146: =IF(AND(E146<>"",F146<>""),E146*F146,"") -> 9400
A147: 144 | B147: 46231 | C147: 桐心源 | D147: 555补水 | E147: 100 | F147: 65 | G147: =IF(AND(E147<>"",F147<>""),E147*F147,"") -> 6500
A148: 145 | B148: 46201 | C148: 王玉琴 | D148: 1L果之茶 | E148: 17.5 | F148: 43 | G148: =IF(AND(E148<>"",F148<>""),E148*F148,"") -> 752.5 | H148: 送半件
A149: 146 | B149: 46206 | C149: 王玉琴 | D149: 大东鹏 | E149: 95 | F149: 90 | G149: =IF(AND(E149<>"",F149<>""),E149*F149,"") -> 8550
A150: 147 | B150: 46208 | C150: 王玉琴 | D150: 小果之茶 | E150: 17.5 | F150: 47 | G150: =IF(AND(E150<>"",F150<>""),E150*F150,"") -> 822.5
A151: 148 | B151: 46213 | C151: 王玉琴 | D151: 大东鹏 | E151: 50 | F151: 90 | G151: =IF(AND(E151<>"",F151<>""),E151*F151,"") -> 4500
A152: 149 | B152: 46221 | C152: 王玉琴 | D152: 小果之茶 | E152: 17.5 | F152: 47 | G152: =IF(AND(E152<>"",F152<>""),E152*F152,"") -> 822.5
A153: 150 | B153: 46222 | C153: 王玉琴 | D153: 555补水 | E153: 17.5 | F153: 65 | G153: =IF(AND(E153<>"",F153<>""),E153*F153,"") -> 1137.5
A154: 151 | B154: 46209 | C154: 小梅商行 | D154: 大东鹏 | E154: 300 | F154: 90 | G154: =IF(AND(E154<>"",F154<>""),E154*F154,"") -> 27000
A155: 152 | B155: 46230 | C155: 小梅商行 | D155: 大东鹏 | E155: 100 | F155: 90 | G155: =IF(AND(E155<>"",F155<>""),E155*F155,"") -> 9000
A156: 153 | B156: 46200 | C156: 星海超市 | D156: 小焙好茶 | E156: 20 | F156: 48 | G156: =IF(AND(E156<>"",F156<>""),E156*F156,"") -> 960
A157: 154 | B157: 46200 | C157: 星海超市 | D157: 大咖 | E157: 10 | F157: 83 | G157: =IF(AND(E157<>"",F157<>""),E157*F157,"") -> 830
A158: 155 | B158: 46225 | C158: 星海超市 | D158: 1L补水 | E158: 90 | F158: 55 | G158: =IF(AND(E158<>"",F158<>""),E158*F158,"") -> 4950
A159: 156 | B159: 46225 | C159: 星海超市 | D159: 555补水 | E159: 100 | F159: 65 | G159: =IF(AND(E159<>"",F159<>""),E159*F159,"") -> 6500
A160: 157 | B160: 46225 | C160: 星海超市 | D160: 1L果之茶 | E160: 50 | F160: 43 | G160: =IF(AND(E160<>"",F160<>""),E160*F160,"") -> 2150
... A169: 166 | B169: 46227 | C169: 宜兴粮油 | D169: 大东鹏 | E169: 115 | F169: 87.8 | G169: =IF(AND(E169<>"",F169<>""),E169*F169,"") -> 10097
A170: 167 | B170: 46227 | C170: 宜兴粮油 | D170: 555补水 | E170: 10 | G170: =IF(AND(E170<>"",F170<>""),E170*F170,"")
A171: 168 | B171: 46217 | C171: 宜兴粮油 | D171: 555补水 | E171: 60 | F171: 65 | G171: =IF(AND(E171<>"",F171<>""),E171*F171,"") -> 3900
A172: 169 | B172: 46217 | C172: 宜兴粮油 | D172: 555补水 | E172: 6 | G172: =IF(AND(E172<>"",F172<>""),E172*F172,"")
A173: 170 | B173: 46217 | C173: 宜兴粮油 | D173: 小果之茶 | E173: 35 | F173: 47 | G173: =IF(AND(E173<>"",F173<>""),E173*F173,"") -> 1645
...

Sheet 收付款明细
A1: 收付款明细台账（自动从资金台帐提取） | I1: 供应商付款明细（自动从资金台帐提取）
A2: 💡 不用再手工登记了：在【资金台帐】记收款并选上客户，这里自动逐笔列出，总览汇总的「已付款金额」、对账单一起跟着变。付厂家的钱列在右边。 | I2: 💡 资金台帐里选了「供应商」的付款（和退款）自动列在这里，冲减欠厂家的货款。
A3: 序号 | B3: 日期 | C3: 客户名称 | D3: 收款金额(元) | E3: 付款方式 | F3: 备注 | G3: 行号 | I3: 序号 | J3: 日期 | K3: 供应商 | L3: 付款金额(元) | M3: 付款方式 | N3: 摘要 | O3: 行号
A4: =IF($G4="","",1) -> 1 | B4: =IF($G4="","",INDEX(资金台帐!$B$7:$B$3006,$G4)) -> 46156 | C4: =IF($G4="","",INDEX(资金台帐!$J$7:$J$3006,$G4)) -> 鼎龙陈财超市 | D4: =IF($G4="","",INDEX(资金台帐!$S$7:$S$3006,$G4)) -> 100000 | E4: =IF($G4="","",INDEX(资金台帐!$C$7:$C$3006,$G4)) -> 收款码 | F4: =IF($G4="","",INDEX(资金台帐!$E$7:$E$3006,$G4)&IF(INDEX(资金台帐!$M$7:$M$3006,$G4)="","","；"&INDEX(资金台帐!$M$7:$M$3006,$G4))) -> 收货款 | G4: =IFERROR(MATCH(1,资金台帐!$Q$7:$Q$3006,0),"") -> 1 | I4: =IF($O4="","",1) | J4: =IF($O4="","",INDEX(资金台帐!$B$7:$B$3006,$O4)) | K4: =IF($O4="","",INDEX(资金台帐!$K$7:$K$3006,$O4)) | L4: =IF($O4="","",-INDEX(资金台帐!$S$7:$S$3006,$O4)) | M4: =IF($O4="","",INDEX(资金台帐!$C$7:$C$3006,$O4)) | N4: =IF($O4="","",INDEX(资金台帐!$E$7:$E$3006,$O4)) | O4: =IFERROR(MATCH(1,资金台帐!$R$7:$R$3006,0),"")
A5: =IF($G5="","",2) -> 2 | B5: =IF($G5="","",INDEX(资金台帐!$B$7:$B$3006,$G5)) -> 46198 | C5: =IF($G5="","",INDEX(资金台帐!$J$7:$J$3006,$G5)) -> 星海超市 | D5: =IF($G5="","",INDEX(资金台帐!$S$7:$S$3006,$G5)) -> 39547 | E5: =IF($G5="","",INDEX(资金台帐!$C$7:$C$3006,$G5)) -> 收款码 | F5: =IF($G5="","",INDEX(资金台帐!$E$7:$E$3006,$G5)&IF(INDEX(资金台帐!$M$7:$M$3006,$G5)="","","；"&INDEX(资金台帐!$M$7:$M$3006,$G5))) -> 收货款 | G5: =IFERROR(MATCH(2,资金台帐!$Q$7:$Q$3006,0),"") -> 2 | I5: =IF($O5="","",2) | J5: =IF($O5="","",INDEX(资金台帐!$B$7:$B$3006,$O5)) | K5: =IF($O5="","",INDEX(资金台帐!$K$7:$K$3006,$O5)) | L5: =IF($O5="","",-INDEX(资金台帐!$S$7:$S$3006,$O5)) | M5: =IF($O5="","",INDEX(资金台帐!$C$7:$C$3006,$O5)) | N5: =IF($O5="","",INDEX(资金台帐!$E$7:$E$3006,$O5)) | O5: =IFERROR(MATCH(2,资金台帐!$R$7:$R$3006,0),"")
A6: =IF($G6="","",3) -> 3 | B6: =IF($G6="","",INDEX(资金台帐!$B$7:$B$3006,$G6)) -> 46198 | C6: =IF($G6="","",INDEX(资金台帐!$J$7:$J$3006,$G6)) -> 王玉琴 | D6: =IF($G6="","",INDEX(资金台帐!$S$7:$S$3006,$G6)) -> 99000 | E6: =IF($G6="","",INDEX(资金台帐!$C$7:$C$3006,$G6)) -> 收款码 | F6: =IF($G6="","",INDEX(资金台帐!$E$7:$E$3006,$G6)&IF(INDEX(资金台帐!$M$7:$M$3006,$G6)="","","；"&INDEX(资金台帐!$M$7:$M$3006,$G6))) -> 收货款 | G6: =IFERROR(MATCH(3,资金台帐!$Q$7:$Q$3006,0),"") -> 3 | I6: =IF($O6="","",3) | J6: =IF($O6="","",INDEX(资金台帐!$B$7:$B$3006,$O6)) | K6: =IF($O6="","",INDEX(资金台帐!$K$7:$K$3006,$O6)) | L6: =IF($O6="","",-INDEX(资金台帐!$S$7:$S$3006,$O6)) | M6: =IF($O6="","",INDEX(资金台帐!$C$7:$C$3006,$O6)) | N6: =IF($O6="","",INDEX(资金台帐!$E$7:$E$3006,$O6)) | O6: =IFERROR(MATCH(3,资金台帐!$R$7:$R$3006,0),"")
A7: =IF($G7="","",4) -> 4 | B7: =IF($G7="","",INDEX(资金台帐!$B$7:$B$3006,$G7)) -> 46198 | C7: =IF($G7="","",INDEX(资金台帐!$J$7:$J$3006,$G7)) -> 桐心源 | D7: =IF($G7="","",INDEX(资金台帐!$S$7:$S$3006,$G7)) -> 700231.47 | E7: =IF($G7="","",INDEX(资金台帐!$C$7:$C$3006,$G7)) -> 收款码 | F7: =IF($G7="","",INDEX(资金台帐!$E$7:$E$3006,$G7)&IF(INDEX(资金台帐!$M$7:$M$3006,$G7)="","","；"&INDEX(资金台帐!$M$7:$M$3006,$G7))) -> 还差我46313元 | G7: =IFERROR(MATCH(4,资金台帐!$Q$7:$Q$3006,0),"") -> 4 | I7: =IF($O7="","",4) | J7: =IF($O7="","",INDEX(资金台帐!$B$7:$B$3006,$O7)) | K7: =IF($O7="","",INDEX(资金台帐!$K$7:$K$3006,$O7)) | L7: =IF($O7="","",-INDEX(资金台帐!$S$7:$S$3006,$O7)) | M7: =IF($O7="","",INDEX(资金台帐!$C$7:$C$3006,$O7)) | N7: =IF($O7="","",INDEX(资金台帐!$E$7:$E$3006,$O7)) | O7: =IFERROR(MATCH(4,资金台帐!$R$7:$R$3006,0),"")
A8: =IF($G8="","",5) -> 5 | B8: =IF($G8="","",INDEX(资金台帐!$B$7:$B$3006,$G8)) -> 46198 | C8: =IF($G8="","",INDEX(资金台帐!$J$7:$J$3006,$G8)) -> 桐心源 | D8: =IF($G8="","",INDEX(资金台帐!$S$7:$S$3006,$G8)) -> 46360 | E8: =IF($G8="","",INDEX(资金台帐!$C$7:$C$3006,$G8)) -> 收款码 | F8: =IF($G8="","",INDEX(资金台帐!$E$7:$E$3006,$G8)&IF(INDEX(资金台帐!$M$7:$M$3006,$G8)="","","；"&INDEX(资金台帐!$M$7:$M$3006,$G8))) -> 农夫饮料 | G8: =IFERROR(MATCH(5,资金台帐!$Q$7:$Q$3006,0),"") -> 5 | I8: =IF($O8="","",5) | J8: =IF($O8="","",INDEX(资金台帐!$B$7:$B$3006,$O8)) | K8: =IF($O8="","",INDEX(资金台帐!$K$7:$K$3006,$O8)) | L8: =IF($O8="","",-INDEX(资金台帐!$S$7:$S$3006,$O8)) | M8: =IF($O8="","",INDEX(资金台帐!$C$7:$C$3006,$O8)) | N8: =IF($O8="","",INDEX(资金台帐!$E$7:$E$3006,$O8)) | O8: =IFERROR(MATCH(5,资金台帐!$R$7:$R$3006,0),"")
A9: =IF($G9="","",6) -> 6 | B9: =IF($G9="","",INDEX(资金台帐!$B$7:$B$3006,$G9)) -> 46198 | C9: =IF($G9="","",INDEX(资金台帐!$J$7:$J$3006,$G9)) -> 阿东副食 | D9: =IF($G9="","",INDEX(资金台帐!$S$7:$S$3006,$G9)) -> 570147.22 | E9: =IF($G9="","",INDEX(资金台帐!$C$7:$C$3006,$G9)) -> 收款码 | F9: =IF($G9="","",INDEX(资金台帐!$E$7:$E$3006,$G9)&IF(INDEX(资金台帐!$M$7:$M$3006,$G9)="","","；"&INDEX(资金台帐!$M$7:$M$3006,$G9))) -> 还差我37433元 | G9: =IFERROR(MATCH(6,资金台帐!$Q$7:$Q$3006,0),"") -> 6 | I9: =IF($O9="","",6) | J9: =IF($O9="","",INDEX(资金台帐!$B$7:$B$3006,$O9)) | K9: =IF($O9="","",INDEX(资金台帐!$K$7:$K$3006,$O9)) | L9: =IF($O9="","",-INDEX(资金台帐!$S$7:$S$3006,$O9)) | M9: =IF($O9="","",INDEX(资金台帐!$C$7:$C$3006,$O9)) | N9: =IF($O9="","",INDEX(资金台帐!$E$7:$E$3006,$O9)) | O9: =IFERROR(MATCH(6,资金台帐!$R$7:$R$3006,0),"")
A10: =IF($G10="","",7) -> 7 | B10: =IF($G10="","",INDEX(资金台帐!$B$7:$B$3006,$G10)) -> 46199 | C10: =IF($G10="","",INDEX(资金台帐!$J$7:$J$3006,$G10)) -> 金凤副食 | D10: =IF($G10="","",INDEX(资金台帐!$S$7:$S$3006,$G10)) -> 8950 | E10: =IF($G10="","",INDEX(资金台帐!$C$7:$C$3006,$G10)) -> 收款码 | F10: =IF($G10="","",INDEX(资金台帐!$E$7:$E$3006,$G10)&IF(INDEX(资金台帐!$M$7:$M$3006,$G10)="","","；"&INDEX(资金台帐!$M$7:$M$3006,$G10))) -> 收货款 | G10: =IFERROR(MATCH(7,资金台帐!$Q$7:$Q$3006,0),"") -> 7 | I10: =IF($O10="","",7) | J10: =IF($O10="","",INDEX(资金台帐!$B$7:$B$3006,$O10)) | K10: =IF($O10="","",INDEX(资金台帐!$K$7:$K$3006,$O10)) | L10: =IF($O10="","",-INDEX(资金台帐!$S$7:$S$3006,$O10)) | M10: =IF($O10="","",INDEX(资金台帐!$C$7:$C$3006,$O10)) | N10: =IF($O10="","",INDEX(资金台帐!$E$7:$E$3006,$O10)) | O10: =IFERROR(MATCH(7,资金台帐!$R$7:$R$3006,0),"")
A11: =IF($G11="","",8) -> 8 | B11: =IF($G11="","",INDEX(资金台帐!$B$7:$B$3006,$G11)) -> 46199 | C11: =IF($G11="","",INDEX(资金台帐!$J$7:$J$3006,$G11)) -> 致发商行 | D11: =IF($G11="","",INDEX(资金台帐!$S$7:$S$3006,$G11)) -> 437965 | E11: =IF($G11="","",INDEX(资金台帐!$C$7:$C$3006,$G11)) -> 收款码 | F11: =IF($G11="","",INDEX(资金台帐!$E$7:$E$3006,$G11)&IF(INDEX(资金台帐!$M$7:$M$3006,$G11)="","","；"&INDEX(资金台帐!$M$7:$M$3006,$G11))) -> 收货款 | G11: =IFERROR(MATCH(8,资金台帐!$Q$7:$Q$3006,0),"") -> 8 | I11: =IF($O11="","",8) | J11: =IF($O11="","",INDEX(资金台帐!$B$7:$B$3006,$O11)) | K11: =IF($O11="","",INDEX(资金台帐!$K$7:$K$3006,$O11)) | L11: =IF($O11="","",-INDEX(资金台帐!$S$7:$S$3006,$O11)) | M11: =IF($O11="","",INDEX(资金台帐!$C$7:$C$3006,$O11)) | N11: =IF($O11="","",INDEX(资金台帐!$E$7:$E$3006,$O11)) | O11: =IFERROR(MATCH(8,资金台帐!$R$7:$R$3006,0),"")
A12: =IF($G12="","",9) -> 9 | B12: =IF($G12="","",INDEX(资金台帐!$B$7:$B$3006,$G12)) -> 46199 | C12: =IF($G12="","",INDEX(资金台帐!$J$7:$J$3006,$G12)) -> 通达商行 | D12: =IF($G12="","",INDEX(资金台帐!$S$7:$S$3006,$G12)) -> 18000 | E12: =IF($G12="","",INDEX(资金台帐!$C$7:$C$3006,$G12)) -> 收款码 | F12: =IF($G12="","",INDEX(资金台帐!$E$7:$E$3006,$G12)&IF(INDEX(资金台帐!$M$7:$M$3006,$G12)="","","；"&INDEX(资金台帐!$M$7:$M$3006,$G12))) -> 收货款 | G12: =IFERROR(MATCH(9,资金台帐!$Q$7:$Q$3006,0),"") -> 9 | I12: =IF($O12="","",9) | J12: =IF($O12="","",INDEX(资金台帐!$B$7:$B$3006,$O12)) | K12: =IF($O12="","",INDEX(资金台帐!$K$7:$K$3006,$O12)) | L12: =IF($O12="","",-INDEX(资金台帐!$S$7:$S$3006,$O12)) | M12: =IF($O12="","",INDEX(资金台帐!$C$7:$C$3006,$O12)) | N12: =IF($O12="","",INDEX(资金台帐!$E$7:$E$3006,$O12)) | O12: =IFERROR(MATCH(9,资金台帐!$R$7:$R$3006,0),"")
A13: =IF($G13="","",10) -> 10 | B13: =IF($G13="","",INDEX(资金台帐!$B$7:$B$3006,$G13)) -> 46199 | C13: =IF($G13="","",INDEX(资金台帐!$J$7:$J$3006,$G13)) -> 宜兴粮油 | D13: =IF($G13="","",INDEX(资金台帐!$S$7:$S$3006,$G13)) -> 54000 | E13: =IF($G13="","",INDEX(资金台帐!$C$7:$C$3006,$G13)) -> 收款码 | F13: =IF($G13="","",INDEX(资金台帐!$E$7:$E$3006,$G13)&IF(INDEX(资金台帐!$M$7:$M$3006,$G13)="","","；"&INDEX(资金台帐!$M$7:$M$3006,$G13))) -> 收货款 | G13: =IFERROR(MATCH(10,资金台帐!$Q$7:$Q$3006,0),"") -> 10 | I13: =IF($O13="","",10) | J13: =IF($O13="","",INDEX(资金台帐!$B$7:$B$3006,$O13)) | K13: =IF($O13="","",INDEX(资金台帐!$K$7:$K$3006,$O13)) | L13: =IF($O13="","",-INDEX(资金台帐!$S$7:$S$3006,$O13)) | M13: =IF($O13="","",INDEX(资金台帐!$C$7:$C$3006,$O13)) | N13: =IF($O13="","",INDEX(资金台帐!$E$7:$E$3006,$O13)) | O13: =IFERROR(MATCH(10,资金台帐!$R$7:$R$3006,0),"")
A14: =IF($G14="","",11) -> 11 | B14: =IF($G14="","",INDEX(资金台帐!$B$7:$B$3006,$G14)) -> 46200 | C14: =IF($G14="","",INDEX(资金台帐!$J$7:$J$3006,$G14)) -> 马路下小卖部 | D14: =IF($G14="","",INDEX(资金台帐!$S$7:$S$3006,$G14)) -> 840 | E14: =IF($G14="","",INDEX(资金台帐!$C$7:$C$3006,$G14)) -> 收款码 | F14: =IF($G14="","",INDEX(资金台帐!$E$7:$E$3006,$G14)&IF(INDEX(资金台帐!$M$7:$M$3006,$G14)="","","；"&INDEX(资金台帐!$M$7:$M$3006,$G14))) -> 东鹏新品订货款 | G14: =IFERROR(MATCH(11,资金台帐!$Q$7:$Q$3006,0),"") -> 11 | I14: =IF($O14="","",11) | J14: =IF($O14="","",INDEX(资金台帐!$B$7:$B$3006,$O14)) | K14: =IF($O14="","",INDEX(资金台帐!$K$7:$K$3006,$O14)) | L14: =IF($O14="","",-INDEX(资金台帐!$S$7:$S$3006,$O14)) | M14: =IF($O14="","",INDEX(资金台帐!$C$7:$C$3006,$O14)) | N14: =IF($O14="","",INDEX(资金台帐!$E$7:$E$3006,$O14)) | O14: =IFERROR(MATCH(11,资金台帐!$R$7:$R$3006,0),"")
A15: =IF($G15="","",12) -> 12 | B15: =IF($G15="","",INDEX(资金台帐!$B$7:$B$3006,$G15)) -> 46200 | C15: =IF($G15="","",INDEX(资金台帐!$J$7:$J$3006,$G15)) -> 兴莲隆兴商行 | D15: =IF($G15="","",INDEX(资金台帐!$S$7:$S$3006,$G15)) -> 30043 | E15: =IF($G15="","",INDEX(资金台帐!$C$7:$C$3006,$G15)) -> 收款码 | F15: =IF($G15="","",INDEX(资金台帐!$E$7:$E$3006,$G15)&IF(INDEX(资金台帐!$M$7:$M$3006,$G15)="","","；"&INDEX(资金台帐!$M$7:$M$3006,$G15))) -> 收货款 | G15: =IFERROR(MATCH(12,资金台帐!$Q$7:$Q$3006,0),"") -> 12 | I15: =IF($O15="","",12) | J15: =IF($O15="","",INDEX(资金台帐!$B$7:$B$3006,$O15)) | K15: =IF($O15="","",INDEX(资金台帐!$K$7:$K$3006,$O15)) | L15: =IF($O15="","",-INDEX(资金台帐!$S$7:$S$3006,$O15)) | M15: =IF($O15="","",INDEX(资金台帐!$C$7:$C$3006,$O15)) | N15: =IF($O15="","",INDEX(资金台帐!$E$7:$E$3006,$O15)) | O15: =IFERROR(MATCH(12,资金台帐!$R$7:$R$3006,0),"")
A16: =IF($G16="","",13) -> 13 | B16: =IF($G16="","",INDEX(资金台帐!$B$7:$B$3006,$G16)) -> 46200 | C16: =IF($G16="","",INDEX(资金台帐!$J$7:$J$3006,$G16)) -> 诚信粮油 | D16: =IF($G16="","",INDEX(资金台帐!$S$7:$S$3006,$G16)) -> 27000 | E16: =IF($G16="","",INDEX(资金台帐!$C$7:$C$3006,$G16)) -> 收款码 | F16: =IF($G16="","",INDEX(资金台帐!$E$7:$E$3006,$G16)&IF(INDEX(资金台帐!$M$7:$M$3006,$G16)="","","；"&INDEX(资金台帐!$M$7:$M$3006,$G16))) -> 收货款 | G16: =IFERROR(MATCH(13,资金台帐!$Q$7:$Q$3006,0),"") -> 13 | I16: =IF($O16="","",13) | J16: =IF($O16="","",INDEX(资金台帐!$B$7:$B$3006,$O16)) | K16: =IF($O16="","",INDEX(资金台帐!$K$7:$K$3006,$O16)) | L16: =IF($O16="","",-INDEX(资金台帐!$S$7:$S$3006,$O16)) | M16: =IF($O16="","",INDEX(资金台帐!$C$7:$C$3006,$O16)) | N16: =IF($O16="","",INDEX(资金台帐!$E$7:$E$3006,$O16)) | O16: =IFERROR(MATCH(13,资金台帐!$R$7:$R$3006,0),"")
A17: =IF($G17="","",14) -> 14 | B17: =IF($G17="","",INDEX(资金台帐!$B$7:$B$3006,$G17)) -> 46200 | C17: =IF($G17="","",INDEX(资金台帐!$J$7:$J$3006,$G17)) -> 诚信粮油 | D17: =IF($G17="","",INDEX(资金台帐!$S$7:$S$3006,$G17)) -> 2565 | E17: =IF($G17="","",INDEX(资金台帐!$C$7:$C$3006,$G17)) -> 收款码 | F17: =IF($G17="","",INDEX(资金台帐!$E$7:$E$3006,$G17)&IF(INDEX(资金台帐!$M$7:$M$3006,$G17)="","","；"&INDEX(资金台帐!$M$7:$M$3006,$G17))) -> 东鹏新品订货款 | G17: =IFERROR(MATCH(14,资金台帐!$Q$7:$Q$3006,0),"") -> 14 | I17: =IF($O17="","",14) | J17: =IF($O17="","",INDEX(资金台帐!$B$7:$B$3006,$O17)) | K17: =IF($O17="","",INDEX(资金台帐!$K$7:$K$3006,$O17)) | L17: =IF($O17="","",-INDEX(资金台帐!$S$7:$S$3006,$O17)) | M17: =IF($O17="","",INDEX(资金台帐!$C$7:$C$3006,$O17)) | N17: =IF($O17="","",INDEX(资金台帐!$E$7:$E$3006,$O17)) | O17: =IFERROR(MATCH(14,资金台帐!$R$7:$R$3006,0),"")
A18: =IF($G18="","",15) -> 15 | B18: =IF($G18="","",INDEX(资金台帐!$B$7:$B$3006,$G18)) -> 46200 | C18: =IF($G18="","",INDEX(资金台帐!$J$7:$J$3006,$G18)) -> 李记副食 | D18: =IF($G18="","",INDEX(资金台帐!$S$7:$S$3006,$G18)) -> 6930 | E18: =IF($G18="","",INDEX(资金台帐!$C$7:$C$3006,$G18)) -> 收款码 | F18: =IF($G18="","",INDEX(资金台帐!$E$7:$E$3006,$G18)&IF(INDEX(资金台帐!$M$7:$M$3006,$G18)="","","；"&INDEX(资金台帐!$M$7:$M$3006,$G18))) -> 东鹏新品订货款 | G18: =IFERROR(MATCH(15,资金台帐!$Q$7:$Q$3006,0),"") -> 15 | I18: =IF($O18="","",15) | J18: =IF($O18="","",INDEX(资金台帐!$B$7:$B$3006,$O18)) | K18: =IF($O18="","",INDEX(资金台帐!$K$7:$K$3006,$O18)) | L18: =IF($O18="","",-INDEX(资金台帐!$S$7:$S$3006,$O18)) | M18: =IF($O18="","",INDEX(资金台帐!$C$7:$C$3006,$O18)) | N18: =IF($O18="","",INDEX(资金台帐!$E$7:$E$3006,$O18)) | O18: =IFERROR(MATCH(15,资金台帐!$R$7:$R$3006,0),"")
A19: =IF($G19="","",16) -> 16 | B19: =IF($G19="","",INDEX(资金台帐!$B$7:$B$3006,$G19)) -> 46200 | C19: =IF($G19="","",INDEX(资金台帐!$J$7:$J$3006,$G19)) -> 吕维春 | D19: =IF($G19="","",INDEX(资金台帐!$S$7:$S$3006,$G19)) -> 32440 | E19: =IF($G19="","",INDEX(资金台帐!$C$7:$C$3006,$G19)) -> 收款码 | F19: =IF($G19="","",INDEX(资金台帐!$E$7:$E$3006,$G19)&IF(INDEX(资金台帐!$M$7:$M$3006,$G19)="","","；"&INDEX(资金台帐!$M$7:$M$3006,$G19))) -> 收货款 | G19: =IFERROR(MATCH(16,资金台帐!$Q$7:$Q$3006,0),"") -> 16 | I19: =IF($O19="","",16) | J19: =IF($O19="","",INDEX(资金台帐!$B$7:$B$3006,$O19)) | K19: =IF($O19="","",INDEX(资金台帐!$K$7:$K$3006,$O19)) | L19: =IF($O19="","",-INDEX(资金台帐!$S$7:$S$3006,$O19)) | M19: =IF($O19="","",INDEX(资金台帐!$C$7:$C$3006,$O19)) | N19: =IF($O19="","",INDEX(资金台帐!$E$7:$E$3006,$O19)) | O19: =IFERROR(MATCH(16,资金台帐!$R$7:$R$3006,0),"")
A20: =IF($G20="","",17) -> 17 | B20: =IF($G20="","",INDEX(资金台帐!$B$7:$B$3006,$G20)) -> 46200 | C20: =IF($G20="","",INDEX(资金台帐!$J$7:$J$3006,$G20)) -> 兴发商行 | D20: =IF($G20="","",INDEX(资金台帐!$S$7:$S$3006,$G20)) -> 15300 | E20: =IF($G20="","",INDEX(资金台帐!$C$7:$C$3006,$G20)) -> 收款码 | F20: =IF($G20="","",INDEX(资金台帐!$E$7:$E$3006,$G20)&IF(INDEX(资金台帐!$M$7:$M$3006,$G20)="","","；"&INDEX(资金台帐!$M$7:$M$3006,$G20))) -> 收货款 | G20: =IFERROR(MATCH(17,资金台帐!$Q$7:$Q$3006,0),"") -> 17 | I20: =IF($O20="","",17) | J20: =IF($O20="","",INDEX(资金台帐!$B$7:$B$3006,$O20)) | K20: =IF($O20="","",INDEX(资金台帐!$K$7:$K$3006,$O20)) | L20: =IF($O20="","",-INDEX(资金台帐!$S$7:$S$3006,$O20)) | M20: =IF($O20="","",INDEX(资金台帐!$C$7:$C$3006,$O20)) | N20: =IF($O20="","",INDEX(资金台帐!$E$7:$E$3006,$O20)) | O20: =IFERROR(MATCH(17,资金台帐!$R$7:$R$3006,0),"")
A21: =IF($G21="","",18) -> 18 | B21: =IF($G21="","",INDEX(资金台帐!$B$7:$B$3006,$G21)) -> 46200 | C21: =IF($G21="","",INDEX(资金台帐!$J$7:$J$3006,$G21)) -> 城岗日日升超市 | D21: =IF($G21="","",INDEX(资金台帐!$S$7:$S$3006,$G21)) -> 36895 | E21: =IF($G21="","",INDEX(资金台帐!$C$7:$C$3006,$G21)) -> 收款码 | F21: =IF($G21="","",INDEX(资金台帐!$E$7:$E$3006,$G21)&IF(INDEX(资金台帐!$M$7:$M$3006,$G21)="","","；"&INDEX(资金台帐!$M$7:$M$3006,$G21))) -> 收货款 | G21: =IFERROR(MATCH(18,资金台帐!$Q$7:$Q$3006,0),"") -> 18 | I21: =IF($O21="","",18) | J21: =IF($O21="","",INDEX(资金台帐!$B$7:$B$3006,$O21)) | K21: =IF($O21="","",INDEX(资金台帐!$K$7:$K$3006,$O21)) | L21: =IF($O21="","",-INDEX(资金台帐!$S$7:$S$3006,$O21)) | M21: =IF($O21="","",INDEX(资金台帐!$C$7:$C$3006,$O21)) | N21: =IF($O21="","",INDEX(资金台帐!$E$7:$E$3006,$O21)) | O21: =IFERROR(MATCH(18,资金台帐!$R$7:$R$3006,0),"")
A22: =IF($G22="","",19) -> 19 | B22: =IF($G22="","",INDEX(资金台帐!$B$7:$B$3006,$G22)) -> 46200 | C22: =IF($G22="","",INDEX(资金台帐!$J$7:$J$3006,$G22)) -> 江背久明商行 | D22: =IF($G22="","",INDEX(资金台帐!$S$7:$S$3006,$G22)) -> 21620 | E22: =IF($G22="","",INDEX(资金台帐!$C$7:$C$3006,$G22)) -> 收款码 | F22: =IF($G22="","",INDEX(资金台帐!$E$7:$E$3006,$G22)&IF(INDEX(资金台帐!$M$7:$M$3006,$G22)="","","；"&INDEX(资金台帐!$M$7:$M$3006,$G22))) -> 收货款 | G22: =IFERROR(MATCH(19,资金台帐!$Q$7:$Q$3006,0),"") -> 19 | I22: =IF($O22="","",19) | J22: =IF($O22="","",INDEX(资金台帐!$B$7:$B$3006,$O22)) | K22: =IF($O22="","",INDEX(资金台帐!$K$7:$K$3006,$O22)) | L22: =IF($O22="","",-INDEX(资金台帐!$S$7:$S$3006,$O22)) | M22: =IF($O22="","",INDEX(资金台帐!$C$7:$C$3006,$O22)) | N22: =IF($O22="","",INDEX(资金台帐!$E$7:$E$3006,$O22)) | O22: =IFERROR(MATCH(19,资金台帐!$R$7:$R$3006,0),"")
A23: =IF($G23="","",20) -> 20 | B23: =IF($G23="","",INDEX(资金台帐!$B$7:$B$3006,$G23)) -> 46200 | C23: =IF($G23="","",INDEX(资金台帐!$J$7:$J$3006,$G23)) -> 龙岗好又全超市 | D23: =IF($G23="","",INDEX(资金台帐!$S$7:$S$3006,$G23)) -> 137732 | E23: =IF($G23="","",INDEX(资金台帐!$C$7:$C$3006,$G23)) -> 收款码 | F23: =IF($G23="","",INDEX(资金台帐!$E$7:$E$3006,$G23)&IF(INDEX(资金台帐!$M$7:$M$3006,$G23)="","","；"&INDEX(资金台帐!$M$7:$M$3006,$G23))) -> 收货款 | G23: =IFERROR(MATCH(20,资金台帐!$Q$7:$Q$3006,0),"") -> 20 | I23: =IF($O23="","",20) | J23: =IF($O23="","",INDEX(资金台帐!$B$7:$B$3006,$O23)) | K23: =IF($O23="","",INDEX(资金台帐!$K$7:$K$3006,$O23)) | L23: =IF($O23="","",-INDEX(资金台帐!$S$7:$S$3006,$O23)) | M23: =IF($O23="","",INDEX(资金台帐!$C$7:$C$3006,$O23)) | N23: =IF($O23="","",INDEX(资金台帐!$E$7:$E$3006,$O23)) | O23: =IFERROR(MATCH(20,资金台帐!$R$7:$R$3006,0),"")
A24: =IF($G24="","",21) -> 21 | B24: =IF($G24="","",INDEX(资金台帐!$B$7:$B$3006,$G24)) -> 46200 | C24: =IF($G24="","",INDEX(资金台帐!$J$7:$J$3006,$G24)) -> 社富丽华超市 | D24: =IF($G24="","",INDEX(资金台帐!$S$7:$S$3006,$G24)) -> 8100 | E24: =IF($G24="","",INDEX(资金台帐!$C$7:$C$3006,$G24)) -> 收款码 | F24: =IF($G24="","",INDEX(资金台帐!$E$7:$E$3006,$G24)&IF(INDEX(资金台帐!$M$7:$M$3006,$G24)="","","；"&INDEX(资金台帐!$M$7:$M$3006,$G24))) -> 收货款 | G24: =IFERROR(MATCH(21,资金台帐!$Q$7:$Q$3006,0),"") -> 21 | I24: =IF($O24="","",21) | J24: =IF($O24="","",INDEX(资金台帐!$B$7:$B$3006,$O24)) | K24: =IF($O24="","",INDEX(资金台帐!$K$7:$K$3006,$O24)) | L24: =IF($O24="","",-INDEX(资金台帐!$S$7:$S$3006,$O24)) | M24: =IF($O24="","",INDEX(资金台帐!$C$7:$C$3006,$O24)) | N24: =IF($O24="","",INDEX(资金台帐!$E$7:$E$3006,$O24)) | O24: =IFERROR(MATCH(21,资金台帐!$R$7:$R$3006,0),"")
A25: =IF($G25="","",22) -> 22 | B25: =IF($G25="","",INDEX(资金台帐!$B$7:$B$3006,$G25)) -> 46200 | C25: =IF($G25="","",INDEX(资金台帐!$J$7:$J$3006,$G25)) -> 九鑫粮油 | D25: =IF($G25="","",INDEX(资金台帐!$S$7:$S$3006,$G25)) -> 3150 | E25: =IF($G25="","",INDEX(资金台帐!$C$7:$C$3006,$G25)) -> 收款码 | F25: =IF($G25="","",INDEX(资金台帐!$E$7:$E$3006,$G25)&IF(INDEX(资金台帐!$M$7:$M$3006,$G25)="","","；"&INDEX(资金台帐!$M$7:$M$3006,$G25))) -> 收货款 | G25: =IFERROR(MATCH(22,资金台帐!$Q$7:$Q$3006,0),"") -> 22 | I25: =IF($O25="","",22) | J25: =IF($O25="","",INDEX(资金台帐!$B$7:$B$3006,$O25)) | K25: =IF($O25="","",INDEX(资金台帐!$K$7:$K$3006,$O25)) | L25: =IF($O25="","",-INDEX(资金台帐!$S$7:$S$3006,$O25)) | M25: =IF($O25="","",INDEX(资金台帐!$C$7:$C$3006,$O25)) | N25: =IF($O25="","",INDEX(资金台帐!$E$7:$E$3006,$O25)) | O25: =IFERROR(MATCH(22,资金台帐!$R$7:$R$3006,0),"")
A26: =IF($G26="","",23) -> 23 | B26: =IF($G26="","",INDEX(资金台帐!$B$7:$B$3006,$G26)) -> 46200 | C26: =IF($G26="","",INDEX(资金台帐!$J$7:$J$3006,$G26)) -> 鼎龙陈财超市 | D26: =IF($G26="","",INDEX(资金台帐!$S$7:$S$3006,$G26)) -> 77682.5 | E26: =IF($G26="","",INDEX(资金台帐!$C$7:$C$3006,$G26)) -> 收款码 | F26: =IF($G26="","",INDEX(资金台帐!$E$7:$E$3006,$G26)&IF(INDEX(资金台帐!$M$7:$M$3006,$G26)="","","；"&INDEX(资金台帐!$M$7:$M$3006,$G26))) -> 还欠2400元 | G26: =IFERROR(MATCH(23,资金台帐!$Q$7:$Q$3006,0),"") -> 23 | I26: =IF($O26="","",23) | J26: =IF($O26="","",INDEX(资金台帐!$B$7:$B$3006,$O26)) | K26: =IF($O26="","",INDEX(资金台帐!$K$7:$K$3006,$O26)) | L26: =IF($O26="","",-INDEX(资金台帐!$S$7:$S$3006,$O26)) | M26: =IF($O26="","",INDEX(资金台帐!$C$7:$C$3006,$O26)) | N26: =IF($O26="","",INDEX(资金台帐!$E$7:$E$3006,$O26)) | O26: =IFERROR(MATCH(23,资金台帐!$R$7:$R$3006,0),"")
A27: =IF($G27="","",24) -> 24 | B27: =IF($G27="","",INDEX(资金台帐!$B$7:$B$3006,$G27)) -> 46200 | C27: =IF($G27="","",INDEX(资金台帐!$J$7:$J$3006,$G27)) -> 洪门美群商行 | D27: =IF($G27="","",INDEX(资金台帐!$S$7:$S$3006,$G27)) -> 4500 | E27: =IF($G27="","",INDEX(资金台帐!$C$7:$C$3006,$G27)) -> 收款码 | F27: =IF($G27="","",INDEX(资金台帐!$E$7:$E$3006,$G27)&IF(INDEX(资金台帐!$M$7:$M$3006,$G27)="","","；"&INDEX(资金台帐!$M$7:$M$3006,$G27))) -> 收货款 | G27: =IFERROR(MATCH(24,资金台帐!$Q$7:$Q$3006,0),"") -> 24 | I27: =IF($O27="","",24) | J27: =IF($O27="","",INDEX(资金台帐!$B$7:$B$3006,$O27)) | K27: =IF($O27="","",INDEX(资金台帐!$K$7:$K$3006,$O27)) | L27: =IF($O27="","",-INDEX(资金台帐!$S$7:$S$3006,$O27)) | M27: =IF($O27="","",INDEX(资金台帐!$C$7:$C$3006,$O27)) | N27: =IF($O27="","",INDEX(资金台帐!$E$7:$E$3006,$O27)) | O27: =IFERROR(MATCH(24,资金台帐!$R$7:$R$3006,0),"")
A28: =IF($G28="","",25) -> 25 | B28: =IF($G28="","",INDEX(资金台帐!$B$7:$B$3006,$G28)) -> 46200 | C28: =IF($G28="","",INDEX(资金台帐!$J$7:$J$3006,$G28)) -> 兴江家源超市 | D28: =IF($G28="","",INDEX(资金台帐!$S$7:$S$3006,$G28)) -> 1800 | E28: =IF($G28="","",INDEX(资金台帐!$C$7:$C$3006,$G28)) -> 收款码 | F28: =IF($G28="","",INDEX(资金台帐!$E$7:$E$3006,$G28)&IF(INDEX(资金台帐!$M$7:$M$3006,$G28)="","","；"&INDEX(资金台帐!$M$7:$M$3006,$G28))) -> 收货款 | G28: =IFERROR(MATCH(25,资金台帐!$Q$7:$Q$3006,0),"") -> 25 | I28: =IF($O28="","",25) | J28: =IF($O28="","",INDEX(资金台帐!$B$7:$B$3006,$O28)) | K28: =IF($O28="","",INDEX(资金台帐!$K$7:$K$3006,$O28)) | L28: =IF($O28="","",-INDEX(资金台帐!$S$7:$S$3006,$O28)) | M28: =IF($O28="","",INDEX(资金台帐!$C$7:$C$3006,$O28)) | N28: =IF($O28="","",INDEX(资金台帐!$E$7:$E$3006,$O28)) | O28: =IFERROR(MATCH(25,资金台帐!$R$7:$R$3006,0),"")
A29: =IF($G29="","",26) -> 26 | B29: =IF($G29="","",INDEX(资金台帐!$B$7:$B$3006,$G29)) -> 46200 | C29: =IF($G29="","",INDEX(资金台帐!$J$7:$J$3006,$G29)) -> 永丰橙丰购物 | D29: =IF($G29="","",INDEX(资金台帐!$S$7:$S$3006,$G29)) -> 1067 | E29: =IF($G29="","",INDEX(资金台帐!$C$7:$C$3006,$G29)) -> 收款码 | F29: =IF($G29="","",INDEX(资金台帐!$E$7:$E$3006,$G29)&IF(INDEX(资金台帐!$M$7:$M$3006,$G29)="","","；"&INDEX(资金台帐!$M$7:$M$3006,$G29))) -> 东鹏新品订货款 | G29: =IFERROR(MATCH(26,资金台帐!$Q$7:$Q$3006,0),"") -> 26 | I29: =IF($O29="","",26) | J29: =IF($O29="","",INDEX(资金台帐!$B$7:$B$3006,$O29)) | K29: =IF($O29="","",INDEX(资金台帐!$K$7:$K$3006,$O29)) | L29: =IF($O29="","",-INDEX(资金台帐!$S$7:$S$3006,$O29)) | M29: =IF($O29="","",INDEX(资金台帐!$C$7:$C$3006,$O29)) | N29: =IF($O29="","",INDEX(资金台帐!$E$7:$E$3006,$O29)) | O29: =IFERROR(MATCH(26,资金台帐!$R$7:$R$3006,0),"")
A30: =IF($G30="","",27) -> 27 | B30: =IF($G30="","",INDEX(资金台帐!$B$7:$B$3006,$G30)) -> 46200 | C30: =IF($G30="","",INDEX(资金台帐!$J$7:$J$3006,$G30)) -> 枫边德华超市 | D30: =IF($G30="","",INDEX(资金台帐!$S$7:$S$3006,$G30)) -> 38440 | E30: =IF($G30="","",INDEX(资金台帐!$C$7:$C$3006,$G30)) -> 收款码 | F30: =IF($G30="","",INDEX(资金台帐!$E$7:$E$3006,$G30)&IF(INDEX(资金台帐!$M$7:$M$3006,$G30)="","","；"&INDEX(资金台帐!$M$7:$M$3006,$G30))) -> 收货款 | G30: =IFERROR(MATCH(27,资金台帐!$Q$7:$Q$3006,0),"") -> 27 | I30: =IF($O30="","",27) | J30: =IF($O30="","",INDEX(资金台帐!$B$7:$B$3006,$O30)) | K30: =IF($O30="","",INDEX(资金台帐!$K$7:$K$3006,$O30)) | L30: =IF($O30="","",-INDEX(资金台帐!$S$7:$S$3006,$O30)) | M30: =IF($O30="","",INDEX(资金台帐!$C$7:$C$3006,$O30)) | N30: =IF($O30="","",INDEX(资金台帐!$E$7:$E$3006,$O30)) | O30: =IFERROR(MATCH(27,资金台帐!$R$7:$R$3006,0),"")
A31: =IF($G31="","",28) -> 28 | B31: =IF($G31="","",INDEX(资金台帐!$B$7:$B$3006,$G31)) -> 46200 | C31: =IF($G31="","",INDEX(资金台帐!$J$7:$J$3006,$G31)) -> 梅窖建军批发 | D31: =IF($G31="","",INDEX(资金台帐!$S$7:$S$3006,$G31)) -> 11740 | E31: =IF($G31="","",INDEX(资金台帐!$C$7:$C$3006,$G31)) -> 收款码 | F31: =IF($G31="","",INDEX(资金台帐!$E$7:$E$3006,$G31)&IF(INDEX(资金台帐!$M$7:$M$3006,$G31)="","","；"&INDEX(资金台帐!$M$7:$M$3006,$G31))) -> 收货款 | G31: =IFERROR(MATCH(28,资金台帐!$Q$7:$Q$3006,0),"") -> 28 | I31: =IF($O31="","",28) | J31: =IF($O31="","",INDEX(资金台帐!$B$7:$B$3006,$O31)) | K31: =IF($O31="","",INDEX(资金台帐!$K$7:$K$3006,$O31)) | L31: =IF($O31="","",-INDEX(资金台帐!$S$7:$S$3006,$O31)) | M31: =IF($O31="","",INDEX(资金台帐!$C$7:$C$3006,$O31)) | N31: =IF($O31="","",INDEX(资金台帐!$E$7:$E$3006,$O31)) | O31: =IFERROR(MATCH(28,资金台帐!$R$7:$R$3006,0),"")
A32: =IF($G32="","",29) -> 29 | B32: =IF($G32="","",INDEX(资金台帐!$B$7:$B$3006,$G32)) -> 46200 | C32: =IF($G32="","",INDEX(资金台帐!$J$7:$J$3006,$G32)) -> 高兴美宜佳 | D32: =IF($G32="","",INDEX(资金台帐!$S$7:$S$3006,$G32)) -> 704 | E32: =IF($G32="","",INDEX(资金台帐!$C$7:$C$3006,$G32)) -> 收款码 | F32: =IF($G32="","",INDEX(资金台帐!$E$7:$E$3006,$G32)&IF(INDEX(资金台帐!$M$7:$M$3006,$G32)="","","；"&INDEX(资金台帐!$M$7:$M$3006,$G32))) -> 东鹏新品订货款 | G32: =IFERROR(MATCH(29,资金台帐!$Q$7:$Q$3006,0),"") -> 29 | I32: =IF($O32="","",29) | J32: =IF($O32="","",INDEX(资金台帐!$B$7:$B$3006,$O32)) | K32: =IF($O32="","",INDEX(资金台帐!$K$7:$K$3006,$O32)) | L32: =IF($O32="","",-INDEX(资金台帐!$S$7:$S$3006,$O32)) | M32: =IF($O32="","",INDEX(资金台帐!$C$7:$C$3006,$O32)) | N32: =IF($O32="","",INDEX(资金台帐!$E$7:$E$3006,$O32)) | O32: =IFERROR(MATCH(29,资金台帐!$R$7:$R$3006,0),"")
A33: =IF($G33="","",30) -> 30 | B33: =IF($G33="","",INDEX(资金台帐!$B$7:$B$3006,$G33)) -> 46200 | C33: =IF($G33="","",INDEX(资金台帐!$J$7:$J$3006,$G33)) -> 永丰焦溪兰兰副食 | D33: =IF($G33="","",INDEX(资金台帐!$S$7:$S$3006,$G33)) -> 3244 | E33: =IF($G33="","",INDEX(资金台帐!$C$7:$C$3006,$G33)) -> 收款码 | F33: =IF($G33="","",INDEX(资金台帐!$E$7:$E$3006,$G33)&IF(INDEX(资金台帐!$M$7:$M$3006,$G33)="","","；"&INDEX(资金台帐!$M$7:$M$3006,$G33))) -> 东鹏新品订货款 | G33: =IFERROR(MATCH(30,资金台帐!$Q$7:$Q$3006,0),"") -> 30 | I33: =IF($O33="","",30) | J33: =IF($O33="","",INDEX(资金台帐!$B$7:$B$3006,$O33)) | K33: =IF($O33="","",INDEX(资金台帐!$K$7:$K$3006,$O33)) | L33: =IF($O33="","",-INDEX(资金台帐!$S$7:$S$3006,$O33)) | M33: =IF($O33="","",INDEX(资金台帐!$C$7:$C$3006,$O33)) | N33: =IF($O33="","",INDEX(资金台帐!$E$7:$E$3006,$O33)) | O33: =IFERROR(MATCH(30,资金台帐!$R$7:$R$3006,0),"")
A34: =IF($G34="","",31) -> 31 | B34: =IF($G34="","",INDEX(资金台帐!$B$7:$B$3006,$G34)) -> 46200 | C34: =IF($G34="","",INDEX(资金台帐!$J$7:$J$3006,$G34)) -> 高兴枫树平价超市 | D34: =IF($G34="","",INDEX(资金台帐!$S$7:$S$3006,$G34)) -> 1126 | E34: =IF($G34="","",INDEX(资金台帐!$C$7:$C$3006,$G34)) -> 收款码 | F34: =IF($G34="","",INDEX(资金台帐!$E$7:$E$3006,$G34)&IF(INDEX(资金台帐!$M$7:$M$3006,$G34)="","","；"&INDEX(资金台帐!$M$7:$M$3006,$G34))) -> 东鹏新品订货款 | G34: =IFERROR(MATCH(31,资金台帐!$Q$7:$Q$3006,0),"") -> 31 | I34: =IF($O34="","",31) | J34: =IF($O34="","",INDEX(资金台帐!$B$7:$B$3006,$O34)) | K34: =IF($O34="","",INDEX(资金台帐!$K$7:$K$3006,$O34)) | L34: =IF($O34="","",-INDEX(资金台帐!$S$7:$S$3006,$O34)) | M34: =IF($O34="","",INDEX(资金台帐!$C$7:$C$3006,$O34)) | N34: =IF($O34="","",INDEX(资金台帐!$E$7:$E$3006,$O34)) | O34: =IFERROR(MATCH(31,资金台帐!$R$7:$R$3006,0),"")
A35: =IF($G35="","",32) -> 32 | B35: =IF($G35="","",INDEX(资金台帐!$B$7:$B$3006,$G35)) -> 46200 | C35: =IF($G35="","",INDEX(资金台帐!$J$7:$J$3006,$G35)) -> 鼎龙众家乐超市 | D35: =IF($G35="","",INDEX(资金台帐!$S$7:$S$3006,$G35)) -> 2182 | E35: =IF($G35="","",INDEX(资金台帐!$C$7:$C$3006,$G35)) -> 收款码 | F35: =IF($G35="","",INDEX(资金台帐!$E$7:$E$3006,$G35)&IF(INDEX(资金台帐!$M$7:$M$3006,$G35)="","","；"&INDEX(资金台帐!$M$7:$M$3006,$G35))) -> 东鹏新品订货款 | G35: =IFERROR(MATCH(32,资金台帐!$Q$7:$Q$3006,0),"") -> 32 | I35: =IF($O35="","",32) | J35: =IF($O35="","",INDEX(资金台帐!$B$7:$B$3006,$O35)) | K35: =IF($O35="","",INDEX(资金台帐!$K$7:$K$3006,$O35)) | L35: =IF($O35="","",-INDEX(资金台帐!$S$7:$S$3006,$O35)) | M35: =IF($O35="","",INDEX(资金台帐!$C$7:$C$3006,$O35)) | N35: =IF($O35="","",INDEX(资金台帐!$E$7:$E$3006,$O35)) | O35: =IFERROR(MATCH(32,资金台帐!$R$7:$R$3006,0),"")
A36: =IF($G36="","",33) -> 33 | B36: =IF($G36="","",INDEX(资金台帐!$B$7:$B$3006,$G36)) -> 46200 | C36: =IF($G36="","",INDEX(资金台帐!$J$7:$J$3006,$G36)) -> 洪门兴诚超市 | D36: =IF($G36="","",INDEX(资金台帐!$S$7:$S$3006,$G36)) -> 45000 | E36: =IF($G36="","",INDEX(资金台帐!$C$7:$C$3006,$G36)) -> 收款码 | F36: =IF($G36="","",INDEX(资金台帐!$E$7:$E$3006,$G36)&IF(INDEX(资金台帐!$M$7:$M$3006,$G36)="","","；"&INDEX(资金台帐!$M$7:$M$3006,$G36))) -> 收货款 | G36: =IFERROR(MATCH(33,资金台帐!$Q$7:$Q$3006,0),"") -> 33 | I36: =IF($O36="","",33) | J36: =IF($O36="","",INDEX(资金台帐!$B$7:$B$3006,$O36)) | K36: =IF($O36="","",INDEX(资金台帐!$K$7:$K$3006,$O36)) | L36: =IF($O36="","",-INDEX(资金台帐!$S$7:$S$3006,$O36)) | M36: =IF($O36="","",INDEX(资金台帐!$C$7:$C$3006,$O36)) | N36: =IF($O36="","",INDEX(资金台帐!$E$7:$E$3006,$O36)) | O36: =IFERROR(MATCH(33,资金台帐!$R$7:$R$3006,0),"")
A37: =IF($G37="","",34) -> 34 | B37: =IF($G37="","",INDEX(资金台帐!$B$7:$B$3006,$G37)) -> 46201 | C37: =IF($G37="","",INDEX(资金台帐!$J$7:$J$3006,$G37)) -> 王玉琴 | D37: =IF($G37="","",INDEX(资金台帐!$S$7:$S$3006,$G37)) -> 7697 | E37: =IF($G37="","",INDEX(资金台帐!$C$7:$C$3006,$G37)) -> 收款码 | F37: =IF($G37="","",INDEX(资金台帐!$E$7:$E$3006,$G37)&IF(INDEX(资金台帐!$M$7:$M$3006,$G37)="","","；"&INDEX(资金台帐!$M$7:$M$3006,$G37))) -> 收货款 | G37: =IFERROR(MATCH(34,资金台帐!$Q$7:$Q$3006,0),"") -> 34 | I37: =IF($O37="","",34) | J37: =IF($O37="","",INDEX(资金台帐!$B$7:$B$3006,$O37)) | K37: =IF($O37="","",INDEX(资金台帐!$K$7:$K$3006,$O37)) | L37: =IF($O37="","",-INDEX(资金台帐!$S$7:$S$3006,$O37)) | M37: =IF($O37="","",INDEX(资金台帐!$C$7:$C$3006,$O37)) | N37: =IF($O37="","",INDEX(资金台帐!$E$7:$E$3006,$O37)) | O37: =IFERROR(MATCH(34,资金台帐!$R$7:$R$3006,0),"")
A38: =IF($G38="","",35) -> 35 | B38: =IF($G38="","",INDEX(资金台帐!$B$7:$B$3006,$G38)) -> 46202 | C38: =IF($G38="","",INDEX(资金台帐!$J$7:$J$3006,$G38)) -> 兴江吴辉明 | D38: =IF($G38="","",INDEX(资金台帐!$S$7:$S$3006,$G38)) -> 21135 | E38: =IF($G38="","",INDEX(资金台帐!$C$7:$C$3006,$G38)) -> 收款码 | F38: =IF($G38="","",INDEX(资金台帐!$E$7:$E$3006,$G38)&IF(INDEX(资金台帐!$M$7:$M$3006,$G38)="","","；"&INDEX(资金台帐!$M$7:$M$3006,$G38))) -> 收货款 | G38: =IFERROR(MATCH(35,资金台帐!$Q$7:$Q$3006,0),"") -> 35 | I38: =IF($O38="","",35) | J38: =IF($O38="","",INDEX(资金台帐!$B$7:$B$3006,$O38)) | K38: =IF($O38="","",INDEX(资金台帐!$K$7:$K$3006,$O38)) | L38: =IF($O38="","",-INDEX(资金台帐!$S$7:$S$3006,$O38)) | M38: =IF($O38="","",INDEX(资金台帐!$C$7:$C$3006,$O38)) | N38: =IF($O38="","",INDEX(资金台帐!$E$7:$E$3006,$O38)) | O38: =IFERROR(MATCH(35,资金台帐!$R$7:$R$3006,0),"")
A39: =IF($G39="","",36) -> 36 | B39: =IF($G39="","",INDEX(资金台帐!$B$7:$B$3006,$G39)) -> 46202 | C39: =IF($G39="","",INDEX(资金台帐!$J$7:$J$3006,$G39)) -> 和睦公园百顺 | D39: =IF($G39="","",INDEX(资金台帐!$S$7:$S$3006,$G39)) -> 27000 | E39: =IF($G39="","",INDEX(资金台帐!$C$7:$C$3006,$G39)) -> 收款码 | F39: =IF($G39="","",INDEX(资金台帐!$E$7:$E$3006,$G39)&IF(INDEX(资金台帐!$M$7:$M$3006,$G39)="","","；"&INDEX(资金台帐!$M$7:$M$3006,$G39))) -> 收货款 | G39: =IFERROR(MATCH(36,资金台帐!$Q$7:$Q$3006,0),"") -> 36 | I39: =IF($O39="","",36) | J39: =IF($O39="","",INDEX(资金台帐!$B$7:$B$3006,$O39)) | K39: =IF($O39="","",INDEX(资金台帐!$K$7:$K$3006,$O39)) | L39: =IF($O39="","",-INDEX(资金台帐!$S$7:$S$3006,$O39)) | M39: =IF($O39="","",INDEX(资金台帐!$C$7:$C$3006,$O39)) | N39: =IF($O39="","",INDEX(资金台帐!$E$7:$E$3006,$O39)) | O39: =IFERROR(MATCH(36,资金台帐!$R$7:$R$3006,0),"")
A40: =IF($G40="","",37) -> 37 | B40: =IF($G40="","",INDEX(资金台帐!$B$7:$B$3006,$G40)) -> 46204 | C40: =IF($G40="","",INDEX(资金台帐!$J$7:$J$3006,$G40)) -> 阳光超市 | D40: =IF($G40="","",INDEX(资金台帐!$S$7:$S$3006,$G40)) -> 11350 | E40: =IF($G40="","",INDEX(资金台帐!$C$7:$C$3006,$G40)) -> 农业工账 | F40: =IF($G40="","",INDEX(资金台帐!$E$7:$E$3006,$G40)&IF(INDEX(资金台帐!$M$7:$M$3006,$G40)="","","；"&INDEX(资金台帐!$M$7:$M$3006,$G40))) -> 收货款 | G40: =IFERROR(MATCH(37,资金台帐!$Q$7:$Q$3006,0),"") -> 37 | I40: =IF($O40="","",37) | J40: =IF($O40="","",INDEX(资金台帐!$B$7:$B$3006,$O40)) | K40: =IF($O40="","",INDEX(资金台帐!$K$7:$K$3006,$O40)) | L40: =IF($O40="","",-INDEX(资金台帐!$S$7:$S$3006,$O40)) | M40: =IF($O40="","",INDEX(资金台帐!$C$7:$C$3006,$O40)) | N40: =IF($O40="","",INDEX(资金台帐!$E$7:$E$3006,$O40)) | O40: =IFERROR(MATCH(37,资金台帐!$R$7:$R$3006,0),"")
A41: =IF($G41="","",38) -> 38 | B41: =IF($G41="","",INDEX(资金台帐!$B$7:$B$3006,$G41)) -> 46204 | C41: =IF($G41="","",INDEX(资金台帐!$J$7:$J$3006,$G41)) -> 红军路怡品折扣店 | D41: =IF($G41="","",INDEX(资金台帐!$S$7:$S$3006,$G41)) -> 5400 | E41: =IF($G41="","",INDEX(资金台帐!$C$7:$C$3006,$G41)) -> 收款码 | F41: =IF($G41="","",INDEX(资金台帐!$E$7:$E$3006,$G41)&IF(INDEX(资金台帐!$M$7:$M$3006,$G41)="","","；"&INDEX(资金台帐!$M$7:$M$3006,$G41))) -> 收货款 | G41: =IFERROR(MATCH(38,资金台帐!$Q$7:$Q$3006,0),"") -> 38 | I41: =IF($O41="","",38) | J41: =IF($O41="","",INDEX(资金台帐!$B$7:$B$3006,$O41)) | K41: =IF($O41="","",INDEX(资金台帐!$K$7:$K$3006,$O41)) | L41: =IF($O41="","",-INDEX(资金台帐!$S$7:$S$3006,$O41)) | M41: =IF($O41="","",INDEX(资金台帐!$C$7:$C$3006,$O41)) | N41: =IF($O41="","",INDEX(资金台帐!$E$7:$E$3006,$O41)) | O41: =IFERROR(MATCH(38,资金台帐!$R$7:$R$3006,0),"")
A42: =IF($G42="","",39) -> 39 | B42: =IF($G42="","",INDEX(资金台帐!$B$7:$B$3006,$G42)) -> 46204 | C42: =IF($G42="","",INDEX(资金台帐!$J$7:$J$3006,$G42)) -> 家家兴超市 | D42: =IF($G42="","",INDEX(资金台帐!$S$7:$S$3006,$G42)) -> 2579 | E42: =IF($G42="","",INDEX(资金台帐!$C$7:$C$3006,$G42)) -> 收款码 | F42: =IF($G42="","",INDEX(资金台帐!$E$7:$E$3006,$G42)&IF(INDEX(资金台帐!$M$7:$M$3006,$G42)="","","；"&INDEX(资金台帐!$M$7:$M$3006,$G42))) -> 收货款 | G42: =IFERROR(MATCH(39,资金台帐!$Q$7:$Q$3006,0),"") -> 39 | I42: =IF($O42="","",39) | J42: =IF($O42="","",INDEX(资金台帐!$B$7:$B$3006,$O42)) | K42: =IF($O42="","",INDEX(资金台帐!$K$7:$K$3006,$O42)) | L42: =IF($O42="","",-INDEX(资金台帐!$S$7:$S$3006,$O42)) | M42: =IF($O42="","",INDEX(资金台帐!$C$7:$C$3006,$O42)) | N42: =IF($O42="","",INDEX(资金台帐!$E$7:$E$3006,$O42)) | O42: =IFERROR(MATCH(39,资金台帐!$R$7:$R$3006,0),"")
A43: =IF($G43="","",40) -> 40 | B43: =IF($G43="","",INDEX(资金台帐!$B$7:$B$3006,$G43)) -> 46204 | C43: =IF($G43="","",INDEX(资金台帐!$J$7:$J$3006,$G43)) -> 小梅商行 | D43: =IF($G43="","",INDEX(资金台帐!$S$7:$S$3006,$G43)) -> 360000 | E43: =IF($G43="","",INDEX(资金台帐!$C$7:$C$3006,$G43)) -> 收款码 | F43: =IF($G43="","",INDEX(资金台帐!$E$7:$E$3006,$G43)&IF(INDEX(资金台帐!$M$7:$M$3006,$G43)="","","；"&INDEX(资金台帐!$M$7:$M$3006,$G43))) -> 收货款 | G43: =IFERROR(MATCH(40,资金台帐!$Q$7:$Q$3006,0),"") -> 40 | I43: =IF($O43="","",40) | J43: =IF($O43="","",INDEX(资金台帐!$B$7:$B$3006,$O43)) | K43: =IF($O43="","",INDEX(资金台帐!$K$7:$K$3006,$O43)) | L43: =IF($O43="","",-INDEX(资金台帐!$S$7:$S$3006,$O43)) | M43: =IF($O43="","",INDEX(资金台帐!$C$7:$C$3006,$O43)) | N43: =IF($O43="","",INDEX(资金台帐!$E$7:$E$3006,$O43)) | O43: =IFERROR(MATCH(40,资金台帐!$R$7:$R$3006,0),"")
A44: =IF($G44="","",41) -> 41 | B44: =IF($G44="","",INDEX(资金台帐!$B$7:$B$3006,$G44)) -> 46205 | C44: =IF($G44="","",INDEX(资金台帐!$J$7:$J$3006,$G44)) -> 家家兴超市 | D44: =IF($G44="","",INDEX(资金台帐!$S$7:$S$3006,$G44)) -> 10000 | E44: =IF($G44="","",INDEX(资金台帐!$C$7:$C$3006,$G44)) -> 收款码 | F44: =IF($G44="","",INDEX(资金台帐!$E$7:$E$3006,$G44)&IF(INDEX(资金台帐!$M$7:$M$3006,$G44)="","","；"&INDEX(资金台帐!$M$7:$M$3006,$G44))) -> 收货款 | G44: =IFERROR(MATCH(41,资金台帐!$Q$7:$Q$3006,0),"") -> 41 | I44: =IF($O44="","",41) | J44: =IF($O44="","",INDEX(资金台帐!$B$7:$B$3006,$O44)) | K44: =IF($O44="","",INDEX(资金台帐!$K$7:$K$3006,$O44)) | L44: =IF($O44="","",-INDEX(资金台帐!$S$7:$S$3006,$O44)) | M44: =IF($O44="","",INDEX(资金台帐!$C$7:$C$3006,$O44)) | N44: =IF($O44="","",INDEX(资金台帐!$E$7:$E$3006,$O44)) | O44: =IFERROR(MATCH(41,资金台帐!$R$7:$R$3006,0),"")
A45: =IF($G45="","",42) -> 42 | B45: =IF($G45="","",INDEX(资金台帐!$B$7:$B$3006,$G45)) -> 46207 | C45: =IF($G45="","",INDEX(资金台帐!$J$7:$J$3006,$G45)) -> 均村桃姐水果店 | D45: =IF($G45="","",INDEX(资金台帐!$S$7:$S$3006,$G45)) -> 2325 | E45: =IF($G45="","",INDEX(资金台帐!$C$7:$C$3006,$G45)) -> 收款码 | F45: =IF($G45="","",INDEX(资金台帐!$E$7:$E$3006,$G45)&IF(INDEX(资金台帐!$M$7:$M$3006,$G45)="","","；"&INDEX(资金台帐!$M$7:$M$3006,$G45))) -> 收货款 | G45: =IFERROR(MATCH(42,资金台帐!$Q$7:$Q$3006,0),"") -> 42 | I45: =IF($O45="","",42) | J45: =IF($O45="","",INDEX(资金台帐!$B$7:$B$3006,$O45)) | K45: =IF($O45="","",INDEX(资金台帐!$K$7:$K$3006,$O45)) | L45: =IF($O45="","",-INDEX(资金台帐!$S$7:$S$3006,$O45)) | M45: =IF($O45="","",INDEX(资金台帐!$C$7:$C$3006,$O45)) | N45: =IF($O45="","",INDEX(资金台帐!$E$7:$E$3006,$O45)) | O45: =IFERROR(MATCH(42,资金台帐!$R$7:$R$3006,0),"")
A46: =IF($G46="","",43) -> 43 | B46: =IF($G46="","",INDEX(资金台帐!$B$7:$B$3006,$G46)) -> 46209 | C46: =IF($G46="","",INDEX(资金台帐!$J$7:$J$3006,$G46)) -> 贸易广场老吴副食 | D46: =IF($G46="","",INDEX(资金台帐!$S$7:$S$3006,$G46)) -> 4500 | E46: =IF($G46="","",INDEX(资金台帐!$C$7:$C$3006,$G46)) -> 收款码 | F46: =IF($G46="","",INDEX(资金台帐!$E$7:$E$3006,$G46)&IF(INDEX(资金台帐!$M$7:$M$3006,$G46)="","","；"&INDEX(资金台帐!$M$7:$M$3006,$G46))) -> 收货款 | G46: =IFERROR(MATCH(43,资金台帐!$Q$7:$Q$3006,0),"") -> 43 | I46: =IF($O46="","",43) | J46: =IF($O46="","",INDEX(资金台帐!$B$7:$B$3006,$O46)) | K46: =IF($O46="","",INDEX(资金台帐!$K$7:$K$3006,$O46)) | L46: =IF($O46="","",-INDEX(资金台帐!$S$7:$S$3006,$O46)) | M46: =IF($O46="","",INDEX(资金台帐!$C$7:$C$3006,$O46)) | N46: =IF($O46="","",INDEX(资金台帐!$E$7:$E$3006,$O46)) | O46: =IFERROR(MATCH(43,资金台帐!$R$7:$R$3006,0),"")
A47: =IF($G47="","",44) -> 44 | B47: =IF($G47="","",INDEX(资金台帐!$B$7:$B$3006,$G47)) -> 46210 | C47: =IF($G47="","",INDEX(资金台帐!$J$7:$J$3006,$G47)) -> 友兰商行 | D47: =IF($G47="","",INDEX(资金台帐!$S$7:$S$3006,$G47)) -> 4650 | E47: =IF($G47="","",INDEX(资金台帐!$C$7:$C$3006,$G47)) -> 收款码 | F47: =IF($G47="","",INDEX(资金台帐!$E$7:$E$3006,$G47)&IF(INDEX(资金台帐!$M$7:$M$3006,$G47)="","","；"&INDEX(资金台帐!$M$7:$M$3006,$G47))) -> 收货款 | G47: =IFERROR(MATCH(44,资金台帐!$Q$7:$Q$3006,0),"") -> 44 | I47: =IF($O47="","",44) | J47: =IF($O47="","",INDEX(资金台帐!$B$7:$B$3006,$O47)) | K47: =IF($O47="","",INDEX(资金台帐!$K$7:$K$3006,$O47)) | L47: =IF($O47="","",-INDEX(资金台帐!$S$7:$S$3006,$O47)) | M47: =IF($O47="","",INDEX(资金台帐!$C$7:$C$3006,$O47)) | N47: =IF($O47="","",INDEX(资金台帐!$E$7:$E$3006,$O47)) | O47: =IFERROR(MATCH(44,资金台帐!$R$7:$R$3006,0),"")
A48: =IF($G48="","",45) -> 45 | B48: =IF($G48="","",INDEX(资金台帐!$B$7:$B$3006,$G48)) -> 46211 | C48: =IF($G48="","",INDEX(资金台帐!$J$7:$J$3006,$G48)) -> 崇贤高平副食 | D48: =IF($G48="","",INDEX(资金台帐!$S$7:$S$3006,$G48)) -> 2325 | E48: =IF($G48="","",INDEX(资金台帐!$C$7:$C$3006,$G48)) -> 收款码 | F48: =IF($G48="","",INDEX(资金台帐!$E$7:$E$3006,$G48)&IF(INDEX(资金台帐!$M$7:$M$3006,$G48)="","","；"&INDEX(资金台帐!$M$7:$M$3006,$G48))) -> 收货款 | G48: =IFERROR(MATCH(45,资金台帐!$Q$7:$Q$3006,0),"") -> 45 | I48: =IF($O48="","",45) | J48: =IF($O48="","",INDEX(资金台帐!$B$7:$B$3006,$O48)) | K48: =IF($O48="","",INDEX(资金台帐!$K$7:$K$3006,$O48)) | L48: =IF($O48="","",-INDEX(资金台帐!$S$7:$S$3006,$O48)) | M48: =IF($O48="","",INDEX(资金台帐!$C$7:$C$3006,$O48)) | N48: =IF($O48="","",INDEX(资金台帐!$E$7:$E$3006,$O48)) | O48: =IFERROR(MATCH(45,资金台帐!$R$7:$R$3006,0),"")
A49: =IF($G49="","",46) -> 46 | B49: =IF($G49="","",INDEX(资金台帐!$B$7:$B$3006,$G49)) -> 46211 | C49: =IF($G49="","",INDEX(资金台帐!$J$7:$J$3006,$G49)) -> 高兴张声英 | D49: =IF($G49="","",INDEX(资金台帐!$S$7:$S$3006,$G49)) -> 2325 | E49: =IF($G49="","",INDEX(资金台帐!$C$7:$C$3006,$G49)) -> 收款码 | F49: =IF($G49="","",INDEX(资金台帐!$E$7:$E$3006,$G49)&IF(INDEX(资金台帐!$M$7:$M$3006,$G49)="","","；"&INDEX(资金台帐!$M$7:$M$3006,$G49))) -> 收货款 | G49: =IFERROR(MATCH(46,资金台帐!$Q$7:$Q$3006,0),"") -> 46 | I49: =IF($O49="","",46) | J49: =IF($O49="","",INDEX(资金台帐!$B$7:$B$3006,$O49)) | K49: =IF($O49="","",INDEX(资金台帐!$K$7:$K$3006,$O49)) | L49: =IF($O49="","",-INDEX(资金台帐!$S$7:$S$3006,$O49)) | M49: =IF($O49="","",INDEX(资金台帐!$C$7:$C$3006,$O49)) | N49: =IF($O49="","",INDEX(资金台帐!$E$7:$E$3006,$O49)) | O49: =IFERROR(MATCH(46,资金台帐!$R$7:$R$3006,0),"")
A50: =IF($G50="","",47) -> 47 | B50: =IF($G50="","",INDEX(资金台帐!$B$7:$B$3006,$G50)) -> 46211 | C50: =IF($G50="","",INDEX(资金台帐!$J$7:$J$3006,$G50)) -> 崇贤粤客隆 | D50: =IF($G50="","",INDEX(资金台帐!$S$7:$S$3006,$G50)) -> 2325 | E50: =IF($G50="","",INDEX(资金台帐!$C$7:$C$3006,$G50)) -> 收款码 | F50: =IF($G50="","",INDEX(资金台帐!$E$7:$E$3006,$G50)&IF(INDEX(资金台帐!$M$7:$M$3006,$G50)="","","；"&INDEX(资金台帐!$M$7:$M$3006,$G50))) -> 收货款 | G50: =IFERROR(MATCH(47,资金台帐!$Q$7:$Q$3006,0),"") -> 47 | I50: =IF($O50="","",47) | J50: =IF($O50="","",INDEX(资金台帐!$B$7:$B$3006,$O50)) | K50: =IF($O50="","",INDEX(资金台帐!$K$7:$K$3006,$O50)) | L50: =IF($O50="","",-INDEX(资金台帐!$S$7:$S$3006,$O50)) | M50: =IF($O50="","",INDEX(资金台帐!$C$7:$C$3006,$O50)) | N50: =IF($O50="","",INDEX(资金台帐!$E$7:$E$3006,$O50)) | O50: =IFERROR(MATCH(47,资金台帐!$R$7:$R$3006,0),"")
A51: =IF($G51="","",48) -> 48 | B51: =IF($G51="","",INDEX(资金台帐!$B$7:$B$3006,$G51)) -> 46211 | C51: =IF($G51="","",INDEX(资金台帐!$J$7:$J$3006,$G51)) -> 火车站关新平 | D51: =IF($G51="","",INDEX(资金台帐!$S$7:$S$3006,$G51)) -> 5330 | E51: =IF($G51="","",INDEX(资金台帐!$C$7:$C$3006,$G51)) -> 收款码 | F51: =IF($G51="","",INDEX(资金台帐!$E$7:$E$3006,$G51)&IF(INDEX(资金台帐!$M$7:$M$3006,$G51)="","","；"&INDEX(资金台帐!$M$7:$M$3006,$G51))) -> 收货款 | G51: =IFERROR(MATCH(48,资金台帐!$Q$7:$Q$3006,0),"") -> 48 | I51: =IF($O51="","",48) | J51: =IF($O51="","",INDEX(资金台帐!$B$7:$B$3006,$O51)) | K51: =IF($O51="","",INDEX(资金台帐!$K$7:$K$3006,$O51)) | L51: =IF($O51="","",-INDEX(资金台帐!$S$7:$S$3006,$O51)) | M51: =IF($O51="","",INDEX(资金台帐!$C$7:$C$3006,$O51)) | N51: =IF($O51="","",INDEX(资金台帐!$E$7:$E$3006,$O51)) | O51: =IFERROR(MATCH(48,资金台帐!$R$7:$R$3006,0),"")
A52: =IF($G52="","",49) -> 49 | B52: =IF($G52="","",INDEX(资金台帐!$B$7:$B$3006,$G52)) -> 46211 | C52: =IF($G52="","",INDEX(资金台帐!$J$7:$J$3006,$G52)) -> 洪门五香副食 | D52: =IF($G52="","",INDEX(资金台帐!$S$7:$S$3006,$G52)) -> 930 | E52: =IF($G52="","",INDEX(资金台帐!$C$7:$C$3006,$G52)) -> 收款码 | F52: =IF($G52="","",INDEX(资金台帐!$E$7:$E$3006,$G52)&IF(INDEX(资金台帐!$M$7:$M$3006,$G52)="","","；"&INDEX(资金台帐!$M$7:$M$3006,$G52))) -> 收货款 | G52: =IFERROR(MATCH(49,资金台帐!$Q$7:$Q$3006,0),"") -> 49 | I52: =IF($O52="","",49) | J52: =IF($O52="","",INDEX(资金台帐!$B$7:$B$3006,$O52)) | K52: =IF($O52="","",INDEX(资金台帐!$K$7:$K$3006,$O52)) | L52: =IF($O52="","",-INDEX(资金台帐!$S$7:$S$3006,$O52)) | M52: =IF($O52="","",INDEX(资金台帐!$C$7:$C$3006,$O52)) | N52: =IF($O52="","",INDEX(资金台帐!$E$7:$E$3006,$O52)) | O52: =IFERROR(MATCH(49,资金台帐!$R$7:$R$3006,0),"")
A53: =IF($G53="","",50) -> 50 | B53: =IF($G53="","",INDEX(资金台帐!$B$7:$B$3006,$G53)) -> 46212 | C53: =IF($G53="","",INDEX(资金台帐!$J$7:$J$3006,$G53)) -> 长岗愉清副食 | D53: =IF($G53="","",INDEX(资金台帐!$S$7:$S$3006,$G53)) -> 3035 | E53: =IF($G53="","",INDEX(资金台帐!$C$7:$C$3006,$G53)) -> 收款码 | F53: =IF($G53="","",INDEX(资金台帐!$E$7:$E$3006,$G53)&IF(INDEX(资金台帐!$M$7:$M$3006,$G53)="","","；"&INDEX(资金台帐!$M$7:$M$3006,$G53))) -> 收货款 | G53: =IFERROR(MATCH(50,资金台帐!$Q$7:$Q$3006,0),"") -> 50 | I53: =IF($O53="","",50) | J53: =IF($O53="","",INDEX(资金台帐!$B$7:$B$3006,$O53)) | K53: =IF($O53="","",INDEX(资金台帐!$K$7:$K$3006,$O53)) | L53: =IF($O53="","",-INDEX(资金台帐!$S$7:$S$3006,$O53)) | M53: =IF($O53="","",INDEX(资金台帐!$C$7:$C$3006,$O53)) | N53: =IF($O53="","",INDEX(资金台帐!$E$7:$E$3006,$O53)) | O53: =IFERROR(MATCH(50,资金台帐!$R$7:$R$3006,0),"")
A54: =IF($G54="","",51) -> 51 | B54: =IF($G54="","",INDEX(资金台帐!$B$7:$B$3006,$G54)) -> 46212 | C54: =IF($G54="","",INDEX(资金台帐!$J$7:$J$3006,$G54)) -> 高兴小春王均平 | D54: =IF($G54="","",INDEX(资金台帐!$S$7:$S$3006,$G54)) -> 2907 | E54: =IF($G54="","",INDEX(资金台帐!$C$7:$C$3006,$G54)) -> 收款码 | F54: =IF($G54="","",INDEX(资金台帐!$E$7:$E$3006,$G54)&IF(INDEX(资金台帐!$M$7:$M$3006,$G54)="","","；"&INDEX(资金台帐!$M$7:$M$3006,$G54))) -> 收货款 | G54: =IFERROR(MATCH(51,资金台帐!$Q$7:$Q$3006,0),"") -> 51 | I54: =IF($O54="","",51) | J54: =IF($O54="","",INDEX(资金台帐!$B$7:$B$3006,$O54)) | K54: =IF($O54="","",INDEX(资金台帐!$K$7:$K$3006,$O54)) | L54: =IF($O54="","",-INDEX(资金台帐!$S$7:$S$3006,$O54)) | M54: =IF($O54="","",INDEX(资金台帐!$C$7:$C$3006,$O54)) | N54: =IF($O54="","",INDEX(资金台帐!$E$7:$E$3006,$O54)) | O54: =IFERROR(MATCH(51,资金台帐!$R$7:$R$3006,0),"")
A55: =IF($G55="","",52) -> 52 | B55: =IF($G55="","",INDEX(资金台帐!$B$7:$B$3006,$G55)) -> 46212 | C55: =IF($G55="","",INDEX(资金台帐!$J$7:$J$3006,$G55)) -> 高兴蒙山超市 | D55: =IF($G55="","",INDEX(资金台帐!$S$7:$S$3006,$G55)) -> 1567 | E55: =IF($G55="","",INDEX(资金台帐!$C$7:$C$3006,$G55)) -> 收款码 | F55: =IF($G55="","",INDEX(资金台帐!$E$7:$E$3006,$G55)&IF(INDEX(资金台帐!$M$7:$M$3006,$G55)="","","；"&INDEX(资金台帐!$M$7:$M$3006,$G55))) -> 收货款 | G55: =IFERROR(MATCH(52,资金台帐!$Q$7:$Q$3006,0),"") -> 52 | I55: =IF($O55="","",52) | J55: =IF($O55="","",INDEX(资金台帐!$B$7:$B$3006,$O55)) | K55: =IF($O55="","",INDEX(资金台帐!$K$7:$K$3006,$O55)) | L55: =IF($O55="","",-INDEX(资金台帐!$S$7:$S$3006,$O55)) | M55: =IF($O55="","",INDEX(资金台帐!$C$7:$C$3006,$O55)) | N55: =IF($O55="","",INDEX(资金台帐!$E$7:$E$3006,$O55)) | O55: =IFERROR(MATCH(52,资金台帐!$R$7:$R$3006,0),"")
A56: =IF($G56="","",53) -> 53 | B56: =IF($G56="","",INDEX(资金台帐!$B$7:$B$3006,$G56)) -> 46213 | C56: =IF($G56="","",INDEX(资金台帐!$J$7:$J$3006,$G56)) -> 财源批发 | D56: =IF($G56="","",INDEX(资金台帐!$S$7:$S$3006,$G56)) -> 4500 | E56: =IF($G56="","",INDEX(资金台帐!$C$7:$C$3006,$G56)) -> 收款码 | F56: =IF($G56="","",INDEX(资金台帐!$E$7:$E$3006,$G56)&IF(INDEX(资金台帐!$M$7:$M$3006,$G56)="","","；"&INDEX(资金台帐!$M$7:$M$3006,$G56))) -> 收货款 | G56: =IFERROR(MATCH(53,资金台帐!$Q$7:$Q$3006,0),"") -> 53 | I56: =IF($O56="","",53) | J56: =IF($O56="","",INDEX(资金台帐!$B$7:$B$3006,$O56)) | K56: =IF($O56="","",INDEX(资金台帐!$K$7:$K$3006,$O56)) | L56: =IF($O56="","",-INDEX(资金台帐!$S$7:$S$3006,$O56)) | M56: =IF($O56="","",INDEX(资金台帐!$C$7:$C$3006,$O56)) | N56: =IF($O56="","",INDEX(资金台帐!$E$7:$E$3006,$O56)) | O56: =IFERROR(MATCH(53,资金台帐!$R$7:$R$3006,0),"")
A57: =IF($G57="","",54) -> 54 | B57: =IF($G57="","",INDEX(资金台帐!$B$7:$B$3006,$G57)) -> 46213 | C57: =IF($G57="","",INDEX(资金台帐!$J$7:$J$3006,$G57)) -> 均村好惠多超市 | D57: =IF($G57="","",INDEX(资金台帐!$S$7:$S$3006,$G57)) -> 1395 | E57: =IF($G57="","",INDEX(资金台帐!$C$7:$C$3006,$G57)) -> 收款码 | F57: =IF($G57="","",INDEX(资金台帐!$E$7:$E$3006,$G57)&IF(INDEX(资金台帐!$M$7:$M$3006,$G57)="","","；"&INDEX(资金台帐!$M$7:$M$3006,$G57))) -> 收货款 | G57: =IFERROR(MATCH(54,资金台帐!$Q$7:$Q$3006,0),"") -> 54 | I57: =IF($O57="","",54) | J57: =IF($O57="","",INDEX(资金台帐!$B$7:$B$3006,$O57)) | K57: =IF($O57="","",INDEX(资金台帐!$K$7:$K$3006,$O57)) | L57: =IF($O57="","",-INDEX(资金台帐!$S$7:$S$3006,$O57)) | M57: =IF($O57="","",INDEX(资金台帐!$C$7:$C$3006,$O57)) | N57: =IF($O57="","",INDEX(资金台帐!$E$7:$E$3006,$O57)) | O57: =IFERROR(MATCH(54,资金台帐!$R$7:$R$3006,0),"")
A58: =IF($G58="","",55) -> 55 | B58: =IF($G58="","",INDEX(资金台帐!$B$7:$B$3006,$G58)) -> 46213 | C58: =IF($G58="","",INDEX(资金台帐!$J$7:$J$3006,$G58)) -> 龙口利客副食 | D58: =IF($G58="","",INDEX(资金台帐!$S$7:$S$3006,$G58)) -> 2325 | E58: =IF($G58="","",INDEX(资金台帐!$C$7:$C$3006,$G58)) -> 收款码 | F58: =IF($G58="","",INDEX(资金台帐!$E$7:$E$3006,$G58)&IF(INDEX(资金台帐!$M$7:$M$3006,$G58)="","","；"&INDEX(资金台帐!$M$7:$M$3006,$G58))) -> 收货款 | G58: =IFERROR(MATCH(55,资金台帐!$Q$7:$Q$3006,0),"") -> 55 | I58: =IF($O58="","",55) | J58: =IF($O58="","",INDEX(资金台帐!$B$7:$B$3006,$O58)) | K58: =IF($O58="","",INDEX(资金台帐!$K$7:$K$3006,$O58)) | L58: =IF($O58="","",-INDEX(资金台帐!$S$7:$S$3006,$O58)) | M58: =IF($O58="","",INDEX(资金台帐!$C$7:$C$3006,$O58)) | N58: =IF($O58="","",INDEX(资金台帐!$E$7:$E$3006,$O58)) | O58: =IFERROR(MATCH(55,资金台帐!$R$7:$R$3006,0),"")
A59: =IF($G59="","",56) -> 56 | B59: =IF($G59="","",INDEX(资金台帐!$B$7:$B$3006,$G59)) -> 46215 | C59: =IF($G59="","",INDEX(资金台帐!$J$7:$J$3006,$G59)) -> 崇贤三角超市 | D59: =IF($G59="","",INDEX(资金台帐!$S$7:$S$3006,$G59)) -> 2955 | E59: =IF($G59="","",INDEX(资金台帐!$C$7:$C$3006,$G59)) -> 收款码 | F59: =IF($G59="","",INDEX(资金台帐!$E$7:$E$3006,$G59)&IF(INDEX(资金台帐!$M$7:$M$3006,$G59)="","","；"&INDEX(资金台帐!$M$7:$M$3006,$G59))) -> 收货款 | G59: =IFERROR(MATCH(56,资金台帐!$Q$7:$Q$3006,0),"") -> 56 | I59: =IF($O59="","",56) | J59: =IF($O59="","",INDEX(资金台帐!$B$7:$B$3006,$O59)) | K59: =IF($O59="","",INDEX(资金台帐!$K$7:$K$3006,$O59)) | L59: =IF($O59="","",-INDEX(资金台帐!$S$7:$S$3006,$O59)) | M59: =IF($O59="","",INDEX(资金台帐!$C$7:$C$3006,$O59)) | N59: =IF($O59="","",INDEX(资金台帐!$E$7:$E$3006,$O59)) | O59: =IFERROR(MATCH(56,资金台帐!$R$7:$R$3006,0),"")
A60: =IF($G60="","",57) -> 57 | B60: =IF($G60="","",INDEX(资金台帐!$B$7:$B$3006,$G60)) -> 46215 | C60: =IF($G60="","",INDEX(资金台帐!$J$7:$J$3006,$G60)) -> 方太青华百货 | D60: =IF($G60="","",INDEX(资金台帐!$S$7:$S$3006,$G60)) -> 1395 | E60: =IF($G60="","",INDEX(资金台帐!$C$7:$C$3006,$G60)) -> 收款码 | F60: =IF($G60="","",INDEX(资金台帐!$E$7:$E$3006,$G60)&IF(INDEX(资金台帐!$M$7:$M$3006,$G60)="","","；"&INDEX(资金台帐!$M$7:$M$3006,$G60))) -> 收货款 | G60: =IFERROR(MATCH(57,资金台帐!$Q$7:$Q$3006,0),"") -> 57 | I60: =IF($O60="","",57) | J60: =IF($O60="","",INDEX(资金台帐!$B$7:$B$3006,$O60)) | K60: =IF($O60="","",INDEX(资金台帐!$K$7:$K$3006,$O60)) | L60: =IF($O60="","",-INDEX(资金台帐!$S$7:$S$3006,$O60)) | M60: =IF($O60="","",INDEX(资金台帐!$C$7:$C$3006,$O60)) | N60: =IF($O60="","",INDEX(资金台帐!$E$7:$E$3006,$O60)) | O60: =IFERROR(MATCH(57,资金台帐!$R$7:$R$3006,0),"")
A61: =IF($G61="","",58) -> 58 | B61: =IF($G61="","",INDEX(资金台帐!$B$7:$B$3006,$G61)) -> 46215 | C61: =IF($G61="","",INDEX(资金台帐!$J$7:$J$3006,$G61)) -> 城北街隆兴商行 | D61: =IF($G61="","",INDEX(资金台帐!$S$7:$S$3006,$G61)) -> 3005 | E61: =IF($G61="","",INDEX(资金台帐!$C$7:$C$3006,$G61)) -> 收款码 | F61: =IF($G61="","",INDEX(资金台帐!$E$7:$E$3006,$G61)&IF(INDEX(资金台帐!$M$7:$M$3006,$G61)="","","；"&INDEX(资金台帐!$M$7:$M$3006,$G61))) -> 收货款 | G61: =IFERROR(MATCH(58,资金台帐!$Q$7:$Q$3006,0),"") -> 58 | I61: =IF($O61="","",58) | J61: =IF($O61="","",INDEX(资金台帐!$B$7:$B$3006,$O61)) | K61: =IF($O61="","",INDEX(资金台帐!$K$7:$K$3006,$O61)) | L61: =IF($O61="","",-INDEX(资金台帐!$S$7:$S$3006,$O61)) | M61: =IF($O61="","",INDEX(资金台帐!$C$7:$C$3006,$O61)) | N61: =IF($O61="","",INDEX(资金台帐!$E$7:$E$3006,$O61)) | O61: =IFERROR(MATCH(58,资金台帐!$R$7:$R$3006,0),"")
A62: =IF($G62="","",59) -> 59 | B62: =IF($G62="","",INDEX(资金台帐!$B$7:$B$3006,$G62)) -> 46217 | C62: =IF($G62="","",INDEX(资金台帐!$J$7:$J$3006,$G62)) -> 埠头凤岗万家乐超市 | D62: =IF($G62="","",INDEX(资金台帐!$S$7:$S$3006,$G62)) -> 930 | E62: =IF($G62="","",INDEX(资金台帐!$C$7:$C$3006,$G62)) -> 收款码 | F62: =IF($G62="","",INDEX(资金台帐!$E$7:$E$3006,$G62)&IF(INDEX(资金台帐!$M$7:$M$3006,$G62)="","","；"&INDEX(资金台帐!$M$7:$M$3006,$G62))) -> 收货款 | G62: =IFERROR(MATCH(59,资金台帐!$Q$7:$Q$3006,0),"") -> 59 | I62: =IF($O62="","",59) | J62: =IF($O62="","",INDEX(资金台帐!$B$7:$B$3006,$O62)) | K62: =IF($O62="","",INDEX(资金台帐!$K$7:$K$3006,$O62)) | L62: =IF($O62="","",-INDEX(资金台帐!$S$7:$S$3006,$O62)) | M62: =IF($O62="","",INDEX(资金台帐!$C$7:$C$3006,$O62)) | N62: =IF($O62="","",INDEX(资金台帐!$E$7:$E$3006,$O62)) | O62: =IFERROR(MATCH(59,资金台帐!$R$7:$R$3006,0),"")
A63: =IF($G63="","",60) -> 60 | B63: =IF($G63="","",INDEX(资金台帐!$B$7:$B$3006,$G63)) -> 46218 | C63: =IF($G63="","",INDEX(资金台帐!$J$7:$J$3006,$G63)) -> 良村万家欢超市 | D63: =IF($G63="","",INDEX(资金台帐!$S$7:$S$3006,$G63)) -> 1395 | E63: =IF($G63="","",INDEX(资金台帐!$C$7:$C$3006,$G63)) -> 收款码 | F63: =IF($G63="","",INDEX(资金台帐!$E$7:$E$3006,$G63)&IF(INDEX(资金台帐!$M$7:$M$3006,$G63)="","","；"&INDEX(资金台帐!$M$7:$M$3006,$G63))) -> 收货款 | G63: =IFERROR(MATCH(60,资金台帐!$Q$7:$Q$3006,0),"") -> 60 | I63: =IF($O63="","",60) | J63: =IF($O63="","",INDEX(资金台帐!$B$7:$B$3006,$O63)) | K63: =IF($O63="","",INDEX(资金台帐!$K$7:$K$3006,$O63)) | L63: =IF($O63="","",-INDEX(资金台帐!$S$7:$S$3006,$O63)) | M63: =IF($O63="","",INDEX(资金台帐!$C$7:$C$3006,$O63)) | N63: =IF($O63="","",INDEX(资金台帐!$E$7:$E$3006,$O63)) | O63: =IFERROR(MATCH(60,资金台帐!$R$7:$R$3006,0),"")
A64: =IF($G64="","",61) -> 61 | B64: =IF($G64="","",INDEX(资金台帐!$B$7:$B$3006,$G64)) -> 46218 | C64: =IF($G64="","",INDEX(资金台帐!$J$7:$J$3006,$G64)) -> 滨江荣香副食 | D64: =IF($G64="","",INDEX(资金台帐!$S$7:$S$3006,$G64)) -> 3380 | E64: =IF($G64="","",INDEX(资金台帐!$C$7:$C$3006,$G64)) -> 收款码 | F64: =IF($G64="","",INDEX(资金台帐!$E$7:$E$3006,$G64)&IF(INDEX(资金台帐!$M$7:$M$3006,$G64)="","","；"&INDEX(资金台帐!$M$7:$M$3006,$G64))) -> 收货款 | G64: =IFERROR(MATCH(61,资金台帐!$Q$7:$Q$3006,0),"") -> 61 | I64: =IF($O64="","",61) | J64: =IF($O64="","",INDEX(资金台帐!$B$7:$B$3006,$O64)) | K64: =IF($O64="","",INDEX(资金台帐!$K$7:$K$3006,$O64)) | L64: =IF($O64="","",-INDEX(资金台帐!$S$7:$S$3006,$O64)) | M64: =IF($O64="","",INDEX(资金台帐!$C$7:$C$3006,$O64)) | N64: =IF($O64="","",INDEX(资金台帐!$E$7:$E$3006,$O64)) | O64: =IFERROR(MATCH(61,资金台帐!$R$7:$R$3006,0),"")
A65: =IF($G65="","",62) -> 62 | B65: =IF($G65="","",INDEX(资金台帐!$B$7:$B$3006,$G65)) -> 46218 | C65: =IF($G65="","",INDEX(资金台帐!$J$7:$J$3006,$G65)) -> 宜兴粮油 | D65: =IF($G65="","",INDEX(资金台帐!$S$7:$S$3006,$G65)) -> 12416.5 | E65: =IF($G65="","",INDEX(资金台帐!$C$7:$C$3006,$G65)) -> 收款码 | F65: =IF($G65="","",INDEX(资金台帐!$E$7:$E$3006,$G65)&IF(INDEX(资金台帐!$M$7:$M$3006,$G65)="","","；"&INDEX(资金台帐!$M$7:$M$3006,$G65))) -> 收货款 | G65: =IFERROR(MATCH(62,资金台帐!$Q$7:$Q$3006,0),"") -> 62 | I65: =IF($O65="","",62) | J65: =IF($O65="","",INDEX(资金台帐!$B$7:$B$3006,$O65)) | K65: =IF($O65="","",INDEX(资金台帐!$K$7:$K$3006,$O65)) | L65: =IF($O65="","",-INDEX(资金台帐!$S$7:$S$3006,$O65)) | M65: =IF($O65="","",INDEX(资金台帐!$C$7:$C$3006,$O65)) | N65: =IF($O65="","",INDEX(资金台帐!$E$7:$E$3006,$O65)) | O65: =IFERROR(MATCH(62,资金台帐!$R$7:$R$3006,0),"")
A66: =IF($G66="","",63) -> 63 | B66: =IF($G66="","",INDEX(资金台帐!$B$7:$B$3006,$G66)) -> 46219 | C66: =IF($G66="","",INDEX(资金台帐!$J$7:$J$3006,$G66)) -> 福旺家优购 | D66: =IF($G66="","",INDEX(资金台帐!$S$7:$S$3006,$G66)) -> 27220 | E66: =IF($G66="","",INDEX(资金台帐!$C$7:$C$3006,$G66)) -> 收款码 | F66: =IF($G66="","",INDEX(资金台帐!$E$7:$E$3006,$G66)&IF(INDEX(资金台帐!$M$7:$M$3006,$G66)="","","；"&INDEX(资金台帐!$M$7:$M$3006,$G66))) -> 收货款 | G66: =IFERROR(MATCH(63,资金台帐!$Q$7:$Q$3006,0),"") -> 63 | I66: =IF($O66="","",63) | J66: =IF($O66="","",INDEX(资金台帐!$B$7:$B$3006,$O66)) | K66: =IF($O66="","",INDEX(资金台帐!$K$7:$K$3006,$O66)) | L66: =IF($O66="","",-INDEX(资金台帐!$S$7:$S$3006,$O66)) | M66: =IF($O66="","",INDEX(资金台帐!$C$7:$C$3006,$O66)) | N66: =IF($O66="","",INDEX(资金台帐!$E$7:$E$3006,$O66)) | O66: =IFERROR(MATCH(63,资金台帐!$R$7:$R$3006,0),"")
A67: =IF($G67="","",64) -> 64 | B67: =IF($G67="","",INDEX(资金台帐!$B$7:$B$3006,$G67)) -> 46219 | C67: =IF($G67="","",INDEX(资金台帐!$J$7:$J$3006,$G67)) -> 阿东副食 | D67: =IF($G67="","",INDEX(资金台帐!$S$7:$S$3006,$G67)) -> 9000 | E67: =IF($G67="","",INDEX(资金台帐!$C$7:$C$3006,$G67)) -> 收款码 | F67: =IF($G67="","",INDEX(资金台帐!$E$7:$E$3006,$G67)&IF(INDEX(资金台帐!$M$7:$M$3006,$G67)="","","；"&INDEX(资金台帐!$M$7:$M$3006,$G67))) -> 收货款 | G67: =IFERROR(MATCH(64,资金台帐!$Q$7:$Q$3006,0),"") -> 64 | I67: =IF($O67="","",64) | J67: =IF($O67="","",INDEX(资金台帐!$B$7:$B$3006,$O67)) | K67: =IF($O67="","",INDEX(资金台帐!$K$7:$K$3006,$O67)) | L67: =IF($O67="","",-INDEX(资金台帐!$S$7:$S$3006,$O67)) | M67: =IF($O67="","",INDEX(资金台帐!$C$7:$C$3006,$O67)) | N67: =IF($O67="","",INDEX(资金台帐!$E$7:$E$3006,$O67)) | O67: =IFERROR(MATCH(64,资金台帐!$R$7:$R$3006,0),"")
A68: =IF($G68="","",65) -> 65 | B68: =IF($G68="","",INDEX(资金台帐!$B$7:$B$3006,$G68)) -> 46219 | C68: =IF($G68="","",INDEX(资金台帐!$J$7:$J$3006,$G68)) -> 隆坪美林副食 | D68: =IF($G68="","",INDEX(资金台帐!$S$7:$S$3006,$G68)) -> 3000 | E68: =IF($G68="","",INDEX(资金台帐!$C$7:$C$3006,$G68)) -> 收款码 | F68: =IF($G68="","",INDEX(资金台帐!$E$7:$E$3006,$G68)&IF(INDEX(资金台帐!$M$7:$M$3006,$G68)="","","；"&INDEX(资金台帐!$M$7:$M$3006,$G68))) -> 收货款 | G68: =IFERROR(MATCH(65,资金台帐!$Q$7:$Q$3006,0),"") -> 65 | I68: =IF($O68="","",65) | J68: =IF($O68="","",INDEX(资金台帐!$B$7:$B$3006,$O68)) | K68: =IF($O68="","",INDEX(资金台帐!$K$7:$K$3006,$O68)) | L68: =IF($O68="","",-INDEX(资金台帐!$S$7:$S$3006,$O68)) | M68: =IF($O68="","",INDEX(资金台帐!$C$7:$C$3006,$O68)) | N68: =IF($O68="","",INDEX(资金台帐!$E$7:$E$3006,$O68)) | O68: =IFERROR(MATCH(65,资金台帐!$R$7:$R$3006,0),"")
A69: =IF($G69="","",66) -> 66 | B69: =IF($G69="","",INDEX(资金台帐!$B$7:$B$3006,$G69)) -> 46219 | C69: =IF($G69="","",INDEX(资金台帐!$J$7:$J$3006,$G69)) -> 金凤副食 | D69: =IF($G69="","",INDEX(资金台帐!$S$7:$S$3006,$G69)) -> 48000 | E69: =IF($G69="","",INDEX(资金台帐!$C$7:$C$3006,$G69)) -> 收款码 | F69: =IF($G69="","",INDEX(资金台帐!$E$7:$E$3006,$G69)&IF(INDEX(资金台帐!$M$7:$M$3006,$G69)="","","；"&INDEX(资金台帐!$M$7:$M$3006,$G69))) -> 收货款 | G69: =IFERROR(MATCH(66,资金台帐!$Q$7:$Q$3006,0),"") -> 66 | I69: =IF($O69="","",66) | J69: =IF($O69="","",INDEX(资金台帐!$B$7:$B$3006,$O69)) | K69: =IF($O69="","",INDEX(资金台帐!$K$7:$K$3006,$O69)) | L69: =IF($O69="","",-INDEX(资金台帐!$S$7:$S$3006,$O69)) | M69: =IF($O69="","",INDEX(资金台帐!$C$7:$C$3006,$O69)) | N69: =IF($O69="","",INDEX(资金台帐!$E$7:$E$3006,$O69)) | O69: =IFERROR(MATCH(66,资金台帐!$R$7:$R$3006,0),"")
A70: =IF($G70="","",67) -> 67 | B70: =IF($G70="","",INDEX(资金台帐!$B$7:$B$3006,$G70)) -> 46220 | C70: =IF($G70="","",INDEX(资金台帐!$J$7:$J$3006,$G70)) -> 桐心源 | D70: =IF($G70="","",INDEX(资金台帐!$S$7:$S$3006,$G70)) -> 9000 | E70: =IF($G70="","",INDEX(资金台帐!$C$7:$C$3006,$G70)) -> 收款码 | F70: =IF($G70="","",INDEX(资金台帐!$E$7:$E$3006,$G70)&IF(INDEX(资金台帐!$M$7:$M$3006,$G70)="","","；"&INDEX(资金台帐!$M$7:$M$3006,$G70))) -> 收货款 | G70: =IFERROR(MATCH(67,资金台帐!$Q$7:$Q$3006,0),"") -> 67 | I70: =IF($O70="","",67) | J70: =IF($O70="","",INDEX(资金台帐!$B$7:$B$3006,$O70)) | K70: =IF($O70="","",INDEX(资金台帐!$K$7:$K$3006,$O70)) | L70: =IF($O70="","",-INDEX(资金台帐!$S$7:$S$3006,$O70)) | M70: =IF($O70="","",INDEX(资金台帐!$C$7:$C$3006,$O70)) | N70: =IF($O70="","",INDEX(资金台帐!$E$7:$E$3006,$O70)) | O70: =IFERROR(MATCH(67,资金台帐!$R$7:$R$3006,0),"")
A71: =IF($G71="","",68) -> 68 | B71: =IF($G71="","",INDEX(资金台帐!$B$7:$B$3006,$G71)) -> 46220 | C71: =IF($G71="","",INDEX(资金台帐!$J$7:$J$3006,$G71)) -> 高兴美宜佳 | D71: =IF($G71="","",INDEX(资金台帐!$S$7:$S$3006,$G71)) -> 9000 | E71: =IF($G71="","",INDEX(资金台帐!$C$7:$C$3006,$G71)) -> 收款码 | F71: =IF($G71="","",INDEX(资金台帐!$E$7:$E$3006,$G71)&IF(INDEX(资金台帐!$M$7:$M$3006,$G71)="","","；"&INDEX(资金台帐!$M$7:$M$3006,$G71))) -> 收货款 | G71: =IFERROR(MATCH(68,资金台帐!$Q$7:$Q$3006,0),"") -> 68 | I71: =IF($O71="","",68) | J71: =IF($O71="","",INDEX(资金台帐!$B$7:$B$3006,$O71)) | K71: =IF($O71="","",INDEX(资金台帐!$K$7:$K$3006,$O71)) | L71: =IF($O71="","",-INDEX(资金台帐!$S$7:$S$3006,$O71)) | M71: =IF($O71="","",INDEX(资金台帐!$C$7:$C$3006,$O71)) | N71: =IF($O71="","",INDEX(资金台帐!$E$7:$E$3006,$O71)) | O71: =IFERROR(MATCH(68,资金台帐!$R$7:$R$3006,0),"")
A72: =IF($G72="","",69) -> 69 | B72: =IF($G72="","",INDEX(资金台帐!$B$7:$B$3006,$G72)) -> 46220 | C72: =IF($G72="","",INDEX(资金台帐!$J$7:$J$3006,$G72)) -> 滨江路小红花便利店 | D72: =IF($G72="","",INDEX(资金台帐!$S$7:$S$3006,$G72)) -> 3200 | E72: =IF($G72="","",INDEX(资金台帐!$C$7:$C$3006,$G72)) -> 收款码 | F72: =IF($G72="","",INDEX(资金台帐!$E$7:$E$3006,$G72)&IF(INDEX(资金台帐!$M$7:$M$3006,$G72)="","","；"&INDEX(资金台帐!$M$7:$M$3006,$G72))) -> 收货款 | G72: =IFERROR(MATCH(69,资金台帐!$Q$7:$Q$3006,0),"") -> 69 | I72: =IF($O72="","",69) | J72: =IF($O72="","",INDEX(资金台帐!$B$7:$B$3006,$O72)) | K72: =IF($O72="","",INDEX(资金台帐!$K$7:$K$3006,$O72)) | L72: =IF($O72="","",-INDEX(资金台帐!$S$7:$S$3006,$O72)) | M72: =IF($O72="","",INDEX(资金台帐!$C$7:$C$3006,$O72)) | N72: =IF($O72="","",INDEX(资金台帐!$E$7:$E$3006,$O72)) | O72: =IFERROR(MATCH(69,资金台帐!$R$7:$R$3006,0),"")
A73: =IF($G73="","",70) -> 70 | B73: =IF($G73="","",INDEX(资金台帐!$B$7:$B$3006,$G73)) -> 46221 | C73: =IF($G73="","",INDEX(资金台帐!$J$7:$J$3006,$G73)) -> 标哥副食 | D73: =IF($G73="","",INDEX(资金台帐!$S$7:$S$3006,$G73)) -> 2526.5 | E73: =IF($G73="","",INDEX(资金台帐!$C$7:$C$3006,$G73)) -> 收款码 | F73: =IF($G73="","",INDEX(资金台帐!$E$7:$E$3006,$G73)&IF(INDEX(资金台帐!$M$7:$M$3006,$G73)="","","；"&INDEX(资金台帐!$M$7:$M$3006,$G73))) -> 收货款 | G73: =IFERROR(MATCH(70,资金台帐!$Q$7:$Q$3006,0),"") -> 70 | I73: =IF($O73="","",70) | J73: =IF($O73="","",INDEX(资金台帐!$B$7:$B$3006,$O73)) | K73: =IF($O73="","",INDEX(资金台帐!$K$7:$K$3006,$O73)) | L73: =IF($O73="","",-INDEX(资金台帐!$S$7:$S$3006,$O73)) | M73: =IF($O73="","",INDEX(资金台帐!$C$7:$C$3006,$O73)) | N73: =IF($O73="","",INDEX(资金台帐!$E$7:$E$3006,$O73)) | O73: =IFERROR(MATCH(70,资金台帐!$R$7:$R$3006,0),"")
A74: =IF($G74="","",71) -> 71 | B74: =IF($G74="","",INDEX(资金台帐!$B$7:$B$3006,$G74)) -> 46221 | C74: =IF($G74="","",INDEX(资金台帐!$J$7:$J$3006,$G74)) -> 星海超市 | D74: =IF($G74="","",INDEX(资金台帐!$S$7:$S$3006,$G74)) -> 50000 | E74: =IF($G74="","",INDEX(资金台帐!$C$7:$C$3006,$G74)) -> 收款码 | F74: =IF($G74="","",INDEX(资金台帐!$E$7:$E$3006,$G74)&IF(INDEX(资金台帐!$M$7:$M$3006,$G74)="","","；"&INDEX(资金台帐!$M$7:$M$3006,$G74))) -> 收货款 | G74: =IFERROR(MATCH(71,资金台帐!$Q$7:$Q$3006,0),"") -> 71 | I74: =IF($O74="","",71) | J74: =IF($O74="","",INDEX(资金台帐!$B$7:$B$3006,$O74)) | K74: =IF($O74="","",INDEX(资金台帐!$K$7:$K$3006,$O74)) | L74: =IF($O74="","",-INDEX(资金台帐!$S$7:$S$3006,$O74)) | M74: =IF($O74="","",INDEX(资金台帐!$C$7:$C$3006,$O74)) | N74: =IF($O74="","",INDEX(资金台帐!$E$7:$E$3006,$O74)) | O74: =IFERROR(MATCH(71,资金台帐!$R$7:$R$3006,0),"")
A75: =IF($G75="","",72) -> 72 | B75: =IF($G75="","",INDEX(资金台帐!$B$7:$B$3006,$G75)) -> 46223 | C75: =IF($G75="","",INDEX(资金台帐!$J$7:$J$3006,$G75)) -> 良村小杜批发 | D75: =IF($G75="","",INDEX(资金台帐!$S$7:$S$3006,$G75)) -> 4500 | E75: =IF($G75="","",INDEX(资金台帐!$C$7:$C$3006,$G75)) -> 收款码 | F75: =IF($G75="","",INDEX(资金台帐!$E$7:$E$3006,$G75)&IF(INDEX(资金台帐!$M$7:$M$3006,$G75)="","","；"&INDEX(资金台帐!$M$7:$M$3006,$G75))) -> 收货款 | G75: =IFERROR(MATCH(72,资金台帐!$Q$7:$Q$3006,0),"") -> 72 | I75: =IF($O75="","",72) | J75: =IF($O75="","",INDEX(资金台帐!$B$7:$B$3006,$O75)) | K75: =IF($O75="","",INDEX(资金台帐!$K$7:$K$3006,$O75)) | L75: =IF($O75="","",-INDEX(资金台帐!$S$7:$S$3006,$O75)) | M75: =IF($O75="","",INDEX(资金台帐!$C$7:$C$3006,$O75)) | N75: =IF($O75="","",INDEX(资金台帐!$E$7:$E$3006,$O75)) | O75: =IFERROR(MATCH(72,资金台帐!$R$7:$R$3006,0),"")
A76: =IF($G76="","",73) -> 73 | B76: =IF($G76="","",INDEX(资金台帐!$B$7:$B$3006,$G76)) -> 46224 | C76: =IF($G76="","",INDEX(资金台帐!$J$7:$J$3006,$G76)) -> 高兴四季春副食 | D76: =IF($G76="","",INDEX(资金台帐!$S$7:$S$3006,$G76)) -> 2697 | E76: =IF($G76="","",INDEX(资金台帐!$C$7:$C$3006,$G76)) -> 收款码 | F76: =IF($G76="","",INDEX(资金台帐!$E$7:$E$3006,$G76)&IF(INDEX(资金台帐!$M$7:$M$3006,$G76)="","","；"&INDEX(资金台帐!$M$7:$M$3006,$G76))) -> 收货款 | G76: =IFERROR(MATCH(73,资金台帐!$Q$7:$Q$3006,0),"") -> 73 | I76: =IF($O76="","",73) | J76: =IF($O76="","",INDEX(资金台帐!$B$7:$B$3006,$O76)) | K76: =IF($O76="","",INDEX(资金台帐!$K$7:$K$3006,$O76)) | L76: =IF($O76="","",-INDEX(资金台帐!$S$7:$S$3006,$O76)) | M76: =IF($O76="","",INDEX(资金台帐!$C$7:$C$3006,$O76)) | N76: =IF($O76="","",INDEX(资金台帐!$E$7:$E$3006,$O76)) | O76: =IFERROR(MATCH(73,资金台帐!$R$7:$R$3006,0),"")
A77: =IF($G77="","",74) -> 74 | B77: =IF($G77="","",INDEX(资金台帐!$B$7:$B$3006,$G77)) -> 46225 | C77: =IF($G77="","",INDEX(资金台帐!$J$7:$J$3006,$G77)) -> 友兰商行 | D77: =IF($G77="","",INDEX(资金台帐!$S$7:$S$3006,$G77)) -> 602 | E77: =IF($G77="","",INDEX(资金台帐!$C$7:$C$3006,$G77)) -> 收款码 | F77: =IF($G77="","",INDEX(资金台帐!$E$7:$E$3006,$G77)&IF(INDEX(资金台帐!$M$7:$M$3006,$G77)="","","；"&INDEX(资金台帐!$M$7:$M$3006,$G77))) -> 收货款 | G77: =IFERROR(MATCH(74,资金台帐!$Q$7:$Q$3006,0),"") -> 74 | I77: =IF($O77="","",74) | J77: =IF($O77="","",INDEX(资金台帐!$B$7:$B$3006,$O77)) | K77: =IF($O77="","",INDEX(资金台帐!$K$7:$K$3006,$O77)) | L77: =IF($O77="","",-INDEX(资金台帐!$S$7:$S$3006,$O77)) | M77: =IF($O77="","",INDEX(资金台帐!$C$7:$C$3006,$O77)) | N77: =IF($O77="","",INDEX(资金台帐!$E$7:$E$3006,$O77)) | O77: =IFERROR(MATCH(74,资金台帐!$R$7:$R$3006,0),"")
A78: =IF($G78="","",75) -> 75 | B78: =IF($G78="","",INDEX(资金台帐!$B$7:$B$3006,$G78)) -> 46226 | C78: =IF($G78="","",INDEX(资金台帐!$J$7:$J$3006,$G78)) -> 好帮手 | D78: =IF($G78="","",INDEX(资金台帐!$S$7:$S$3006,$G78)) -> 12000 | E78: =IF($G78="","",INDEX(资金台帐!$C$7:$C$3006,$G78)) -> 收款码 | F78: =IF($G78="","",INDEX(资金台帐!$E$7:$E$3006,$G78)&IF(INDEX(资金台帐!$M$7:$M$3006,$G78)="","","；"&INDEX(资金台帐!$M$7:$M$3006,$G78))) -> 收货款 | G78: =IFERROR(MATCH(75,资金台帐!$Q$7:$Q$3006,0),"") -> 75 | I78: =IF($O78="","",75) | J78: =IF($O78="","",INDEX(资金台帐!$B$7:$B$3006,$O78)) | K78: =IF($O78="","",INDEX(资金台帐!$K$7:$K$3006,$O78)) | L78: =IF($O78="","",-INDEX(资金台帐!$S$7:$S$3006,$O78)) | M78: =IF($O78="","",INDEX(资金台帐!$C$7:$C$3006,$O78)) | N78: =IF($O78="","",INDEX(资金台帐!$E$7:$E$3006,$O78)) | O78: =IFERROR(MATCH(75,资金台帐!$R$7:$R$3006,0),"")
A79: =IF($G79="","",76) -> 76 | B79: =IF($G79="","",INDEX(资金台帐!$B$7:$B$3006,$G79)) -> 46226 | C79: =IF($G79="","",INDEX(资金台帐!$J$7:$J$3006,$G79)) -> 洪门C区李记商行 | D79: =IF($G79="","",INDEX(资金台帐!$S$7:$S$3006,$G79)) -> 9000 | E79: =IF($G79="","",INDEX(资金台帐!$C$7:$C$3006,$G79)) -> 收款码 | F79: =IF($G79="","",INDEX(资金台帐!$E$7:$E$3006,$G79)&IF(INDEX(资金台帐!$M$7:$M$3006,$G79)="","","；"&INDEX(资金台帐!$M$7:$M$3006,$G79))) -> 收货款 | G79: =IFERROR(MATCH(76,资金台帐!$Q$7:$Q$3006,0),"") -> 76 | I79: =IF($O79="","",76) | J79: =IF($O79="","",INDEX(资金台帐!$B$7:$B$3006,$O79)) | K79: =IF($O79="","",INDEX(资金台帐!$K$7:$K$3006,$O79)) | L79: =IF($O79="","",-INDEX(资金台帐!$S$7:$S$3006,$O79)) | M79: =IF($O79="","",INDEX(资金台帐!$C$7:$C$3006,$O79)) | N79: =IF($O79="","",INDEX(资金台帐!$E$7:$E$3006,$O79)) | O79: =IFERROR(MATCH(76,资金台帐!$R$7:$R$3006,0),"")
A80: =IF($G80="","",77) -> 77 | B80: =IF($G80="","",INDEX(资金台帐!$B$7:$B$3006,$G80)) -> 46227 | C80: =IF($G80="","",INDEX(资金台帐!$J$7:$J$3006,$G80)) -> 洪门兴诚超市 | D80: =IF($G80="","",INDEX(资金台帐!$S$7:$S$3006,$G80)) -> 6000 | E80: =IF($G80="","",INDEX(资金台帐!$C$7:$C$3006,$G80)) -> 收款码 | F80: =IF($G80="","",INDEX(资金台帐!$E$7:$E$3006,$G80)&IF(INDEX(资金台帐!$M$7:$M$3006,$G80)="","","；"&INDEX(资金台帐!$M$7:$M$3006,$G80))) -> 收货款 | G80: =IFERROR(MATCH(77,资金台帐!$Q$7:$Q$3006,0),"") -> 77 | I80: =IF($O80="","",77) | J80: =IF($O80="","",INDEX(资金台帐!$B$7:$B$3006,$O80)) | K80: =IF($O80="","",INDEX(资金台帐!$K$7:$K$3006,$O80)) | L80: =IF($O80="","",-INDEX(资金台帐!$S$7:$S$3006,$O80)) | M80: =IF($O80="","",INDEX(资金台帐!$C$7:$C$3006,$O80)) | N80: =IF($O80="","",INDEX(资金台帐!$E$7:$E$3006,$O80)) | O80: =IFERROR(MATCH(77,资金台帐!$R$7:$R$3006,0),"")
A81: =IF($G81="","",78) -> 78 | B81: =IF($G81="","",INDEX(资金台帐!$B$7:$B$3006,$G81)) -> 46227 | C81: =IF($G81="","",INDEX(资金台帐!$J$7:$J$3006,$G81)) -> 城西街福临门超市 | D81: =IF($G81="","",INDEX(资金台帐!$S$7:$S$3006,$G81)) -> 2046 | E81: =IF($G81="","",INDEX(资金台帐!$C$7:$C$3006,$G81)) -> 收款码 | F81: =IF($G81="","",INDEX(资金台帐!$E$7:$E$3006,$G81)&IF(INDEX(资金台帐!$M$7:$M$3006,$G81)="","","；"&INDEX(资金台帐!$M$7:$M$3006,$G81))) -> 订3017元 | G81: =IFERROR(MATCH(78,资金台帐!$Q$7:$Q$3006,0),"") -> 78 | I81: =IF($O81="","",78) | J81: =IF($O81="","",INDEX(资金台帐!$B$7:$B$3006,$O81)) | K81: =IF($O81="","",INDEX(资金台帐!$K$7:$K$3006,$O81)) | L81: =IF($O81="","",-INDEX(资金台帐!$S$7:$S$3006,$O81)) | M81: =IF($O81="","",INDEX(资金台帐!$C$7:$C$3006,$O81)) | N81: =IF($O81="","",INDEX(资金台帐!$E$7:$E$3006,$O81)) | O81: =IFERROR(MATCH(78,资金台帐!$R$7:$R$3006,0),"")
A82: =IF($G82="","",79) -> 79 | B82: =IF($G82="","",INDEX(资金台帐!$B$7:$B$3006,$G82)) -> 46227 | C82: =IF($G82="","",INDEX(资金台帐!$J$7:$J$3006,$G82)) -> 滨江路莲花便利店 | D82: =IF($G82="","",INDEX(资金台帐!$S$7:$S$3006,$G82)) -> 1582 | E82: =IF($G82="","",INDEX(资金台帐!$C$7:$C$3006,$G82)) -> 收款码 | F82: =IF($G82="","",INDEX(资金台帐!$E$7:$E$3006,$G82)&IF(INDEX(资金台帐!$M$7:$M$3006,$G82)="","","；"&INDEX(资金台帐!$M$7:$M$3006,$G82))) -> 订3004元 | G82: =IFERROR(MATCH(79,资金台帐!$Q$7:$Q$3006,0),"") -> 79 | I82: =IF($O82="","",79) | J82: =IF($O82="","",INDEX(资金台帐!$B$7:$B$3006,$O82)) | K82: =IF($O82="","",INDEX(资金台帐!$K$7:$K$3006,$O82)) | L82: =IF($O82="","",-INDEX(资金台帐!$S$7:$S$3006,$O82)) | M82: =IF($O82="","",INDEX(资金台帐!$C$7:$C$3006,$O82)) | N82: =IF($O82="","",INDEX(资金台帐!$E$7:$E$3006,$O82)) | O82: =IFERROR(MATCH(79,资金台帐!$R$7:$R$3006,0),"")
A83: =IF($G83="","",80) -> 80 | B83: =IF($G83="","",INDEX(资金台帐!$B$7:$B$3006,$G83)) -> 46227 | C83: =IF($G83="","",INDEX(资金台帐!$J$7:$J$3006,$G83)) -> 马路下小卖部 | D83: =IF($G83="","",INDEX(资金台帐!$S$7:$S$3006,$G83)) -> 18600 | E83: =IF($G83="","",INDEX(资金台帐!$C$7:$C$3006,$G83)) -> 收款码 | F83: =IF($G83="","",INDEX(资金台帐!$E$7:$E$3006,$G83)&IF(INDEX(资金台帐!$M$7:$M$3006,$G83)="","","；"&INDEX(资金台帐!$M$7:$M$3006,$G83))) -> 收货款 | G83: =IFERROR(MATCH(80,资金台帐!$Q$7:$Q$3006,0),"") -> 80 | I83: =IF($O83="","",80) | J83: =IF($O83="","",INDEX(资金台帐!$B$7:$B$3006,$O83)) | K83: =IF($O83="","",INDEX(资金台帐!$K$7:$K$3006,$O83)) | L83: =IF($O83="","",-INDEX(资金台帐!$S$7:$S$3006,$O83)) | M83: =IF($O83="","",INDEX(资金台帐!$C$7:$C$3006,$O83)) | N83: =IF($O83="","",INDEX(资金台帐!$E$7:$E$3006,$O83)) | O83: =IFERROR(MATCH(80,资金台帐!$R$7:$R$3006,0),"")
A84: =IF($G84="","",81) -> 81 | B84: =IF($G84="","",INDEX(资金台帐!$B$7:$B$3006,$G84)) -> 46227 | C84: =IF($G84="","",INDEX(资金台帐!$J$7:$J$3006,$G84)) -> 城岗日日升超市 | D84: =IF($G84="","",INDEX(资金台帐!$S$7:$S$3006,$G84)) -> 27000 | E84: =IF($G84="","",INDEX(资金台帐!$C$7:$C$3006,$G84)) -> 收款码 | F84: =IF($G84="","",INDEX(资金台帐!$E$7:$E$3006,$G84)&IF(INDEX(资金台帐!$M$7:$M$3006,$G84)="","","；"&INDEX(资金台帐!$M$7:$M$3006,$G84))) -> 收货款 | G84: =IFERROR(MATCH(81,资金台帐!$Q$7:$Q$3006,0),"") -> 81 | I84: =IF($O84="","",81) | J84: =IF($O84="","",INDEX(资金台帐!$B$7:$B$3006,$O84)) | K84: =IF($O84="","",INDEX(资金台帐!$K$7:$K$3006,$O84)) | L84: =IF($O84="","",-INDEX(资金台帐!$S$7:$S$3006,$O84)) | M84: =IF($O84="","",INDEX(资金台帐!$C$7:$C$3006,$O84)) | N84: =IF($O84="","",INDEX(资金台帐!$E$7:$E$3006,$O84)) | O84: =IFERROR(MATCH(81,资金台帐!$R$7:$R$3006,0),"")
A85: =IF($G85="","",82) -> 82 | B85: =IF($G85="","",INDEX(资金台帐!$B$7:$B$3006,$G85)) -> 46227 | C85: =IF($G85="","",INDEX(资金台帐!$J$7:$J$3006,$G85)) -> 隆坪美林副食 | D85: =IF($G85="","",INDEX(资金台帐!$S$7:$S$3006,$G85)) -> 2386 | E85: =IF($G85="","",INDEX(资金台帐!$C$7:$C$3006,$G85)) -> 收款码 | F85: =IF($G85="","",INDEX(资金台帐!$E$7:$E$3006,$G85)&IF(INDEX(资金台帐!$M$7:$M$3006,$G85)="","","；"&INDEX(资金台帐!$M$7:$M$3006,$G85))) -> 收货款 | G85: =IFERROR(MATCH(82,资金台帐!$Q$7:$Q$3006,0),"") -> 82 | I85: =IF($O85="","",82) | J85: =IF($O85="","",INDEX(资金台帐!$B$7:$B$3006,$O85)) | K85: =IF($O85="","",INDEX(资金台帐!$K$7:$K$3006,$O85)) | L85: =IF($O85="","",-INDEX(资金台帐!$S$7:$S$3006,$O85)) | M85: =IF($O85="","",INDEX(资金台帐!$C$7:$C$3006,$O85)) | N85: =IF($O85="","",INDEX(资金台帐!$E$7:$E$3006,$O85)) | O85: =IFERROR(MATCH(82,资金台帐!$R$7:$R$3006,0),"")
A86: =IF($G86="","",83) -> 83 | B86: =IF($G86="","",INDEX(资金台帐!$B$7:$B$3006,$G86)) -> 46227 | C86: =IF($G86="","",INDEX(资金台帐!$J$7:$J$3006,$G86)) -> 埠头鑫鑫文具 | D86: =IF($G86="","",INDEX(资金台帐!$S$7:$S$3006,$G86)) -> 2325 | E86: =IF($G86="","",INDEX(资金台帐!$C$7:$C$3006,$G86)) -> 收款码 | F86: =IF($G86="","",INDEX(资金台帐!$E$7:$E$3006,$G86)&IF(INDEX(资金台帐!$M$7:$M$3006,$G86)="","","；"&INDEX(资金台帐!$M$7:$M$3006,$G86))) -> 收货款 | G86: =IFERROR(MATCH(83,资金台帐!$Q$7:$Q$3006,0),"") -> 83 | I86: =IF($O86="","",83) | J86: =IF($O86="","",INDEX(资金台帐!$B$7:$B$3006,$O86)) | K86: =IF($O86="","",INDEX(资金台帐!$K$7:$K$3006,$O86)) | L86: =IF($O86="","",-INDEX(资金台帐!$S$7:$S$3006,$O86)) | M86: =IF($O86="","",INDEX(资金台帐!$C$7:$C$3006,$O86)) | N86: =IF($O86="","",INDEX(资金台帐!$E$7:$E$3006,$O86)) | O86: =IFERROR(MATCH(83,资金台帐!$R$7:$R$3006,0),"")
A87: =IF($G87="","",84) -> 84 | B87: =IF($G87="","",INDEX(资金台帐!$B$7:$B$3006,$G87)) -> 46228 | C87: =IF($G87="","",INDEX(资金台帐!$J$7:$J$3006,$G87)) -> 春萌副食 | D87: =IF($G87="","",INDEX(资金台帐!$S$7:$S$3006,$G87)) -> 2325 | E87: =IF($G87="","",INDEX(资金台帐!$C$7:$C$3006,$G87)) -> 收款码 | F87: =IF($G87="","",INDEX(资金台帐!$E$7:$E$3006,$G87)&IF(INDEX(资金台帐!$M$7:$M$3006,$G87)="","","；"&INDEX(资金台帐!$M$7:$M$3006,$G87))) -> 收货款 | G87: =IFERROR(MATCH(84,资金台帐!$Q$7:$Q$3006,0),"") -> 84 | I87: =IF($O87="","",84) | J87: =IF($O87="","",INDEX(资金台帐!$B$7:$B$3006,$O87)) | K87: =IF($O87="","",INDEX(资金台帐!$K$7:$K$3006,$O87)) | L87: =IF($O87="","",-INDEX(资金台帐!$S$7:$S$3006,$O87)) | M87: =IF($O87="","",INDEX(资金台帐!$C$7:$C$3006,$O87)) | N87: =IF($O87="","",INDEX(资金台帐!$E$7:$E$3006,$O87)) | O87: =IFERROR(MATCH(84,资金台帐!$R$7:$R$3006,0),"")
A88: =IF($G88="","",85) -> 85 | B88: =IF($G88="","",INDEX(资金台帐!$B$7:$B$3006,$G88)) -> 46229 | C88: =IF($G88="","",INDEX(资金台帐!$J$7:$J$3006,$G88)) -> 星海超市 | D88: =IF($G88="","",INDEX(资金台帐!$S$7:$S$3006,$G88)) -> 40000 | E88: =IF($G88="","",INDEX(资金台帐!$C$7:$C$3006,$G88)) -> 收款码 | F88: =IF($G88="","",INDEX(资金台帐!$E$7:$E$3006,$G88)&IF(INDEX(资金台帐!$M$7:$M$3006,$G88)="","","；"&INDEX(资金台帐!$M$7:$M$3006,$G88))) -> 收货款 | G88: =IFERROR(MATCH(85,资金台帐!$Q$7:$Q$3006,0),"") -> 85 | I88: =IF($O88="","",85) | J88: =IF($O88="","",INDEX(资金台帐!$B$7:$B$3006,$O88)) | K88: =IF($O88="","",INDEX(资金台帐!$K$7:$K$3006,$O88)) | L88: =IF($O88="","",-INDEX(资金台帐!$S$7:$S$3006,$O88)) | M88: =IF($O88="","",INDEX(资金台帐!$C$7:$C$3006,$O88)) | N88: =IF($O88="","",INDEX(资金台帐!$E$7:$E$3006,$O88)) | O88: =IFERROR(MATCH(85,资金台帐!$R$7:$R$3006,0),"")
A89: =IF($G89="","",86) -> 86 | B89: =IF($G89="","",INDEX(资金台帐!$B$7:$B$3006,$G89)) -> 46230 | C89: =IF($G89="","",INDEX(资金台帐!$J$7:$J$3006,$G89)) -> 和睦公园百顺 | D89: =IF($G89="","",INDEX(资金台帐!$S$7:$S$3006,$G89)) -> 11705 | E89: =IF($G89="","",INDEX(资金台帐!$C$7:$C$3006,$G89)) -> 收款码 | F89: =IF($G89="","",INDEX(资金台帐!$E$7:$E$3006,$G89)&IF(INDEX(资金台帐!$M$7:$M$3006,$G89)="","","；"&INDEX(资金台帐!$M$7:$M$3006,$G89))) -> 收货款 | G89: =IFERROR(MATCH(86,资金台帐!$Q$7:$Q$3006,0),"") -> 86 | I89: =IF($O89="","",86) | J89: =IF($O89="","",INDEX(资金台帐!$B$7:$B$3006,$O89)) | K89: =IF($O89="","",INDEX(资金台帐!$K$7:$K$3006,$O89)) | L89: =IF($O89="","",-INDEX(资金台帐!$S$7:$S$3006,$O89)) | M89: =IF($O89="","",INDEX(资金台帐!$C$7:$C$3006,$O89)) | N89: =IF($O89="","",INDEX(资金台帐!$E$7:$E$3006,$O89)) | O89: =IFERROR(MATCH(86,资金台帐!$R$7:$R$3006,0),"")
A90: =IF($G90="","",87) -> 87 | B90: =IF($G90="","",INDEX(资金台帐!$B$7:$B$3006,$G90)) -> 46230 | C90: =IF($G90="","",INDEX(资金台帐!$J$7:$J$3006,$G90)) -> 南区长裕商行 | D90: =IF($G90="","",INDEX(资金台帐!$S$7:$S$3006,$G90)) -> 1860 | E90: =IF($G90="","",INDEX(资金台帐!$C$7:$C$3006,$G90)) -> 收款码 | F90: =IF($G90="","",INDEX(资金台帐!$E$7:$E$3006,$G90)&IF(INDEX(资金台帐!$M$7:$M$3006,$G90)="","","；"&INDEX(资金台帐!$M$7:$M$3006,$G90))) -> 收货款 | G90: =IFERROR(MATCH(87,资金台帐!$Q$7:$Q$3006,0),"") -> 87 | I90: =IF($O90="","",87) | J90: =IF($O90="","",INDEX(资金台帐!$B$7:$B$3006,$O90)) | K90: =IF($O90="","",INDEX(资金台帐!$K$7:$K$3006,$O90)) | L90: =IF($O90="","",-INDEX(资金台帐!$S$7:$S$3006,$O90)) | M90: =IF($O90="","",INDEX(资金台帐!$C$7:$C$3006,$O90)) | N90: =IF($O90="","",INDEX(资金台帐!$E$7:$E$3006,$O90)) | O90: =IFERROR(MATCH(87,资金台帐!$R$7:$R$3006,0),"")
A91: =IF($G91="","",88) -> 88 | B91: =IF($G91="","",INDEX(资金台帐!$B$7:$B$3006,$G91)) -> 46231 | C91: =IF($G91="","",INDEX(资金台帐!$J$7:$J$3006,$G91)) -> 桐心源 | D91: =IF($G91="","",INDEX(资金台帐!$S$7:$S$3006,$G91)) -> 22000 | E91: =IF($G91="","",INDEX(资金台帐!$C$7:$C$3006,$G91)) -> 收款码 | F91: =IF($G91="","",INDEX(资金台帐!$E$7:$E$3006,$G91)&IF(INDEX(资金台帐!$M$7:$M$3006,$G91)="","","；"&INDEX(资金台帐!$M$7:$M$3006,$G91))) -> 77900-22000 | G91: =IFERROR(MATCH(88,资金台帐!$Q$7:$Q$3006,0),"") -> 88 | I91: =IF($O91="","",88) | J91: =IF($O91="","",INDEX(资金台帐!$B$7:$B$3006,$O91)) | K91: =IF($O91="","",INDEX(资金台帐!$K$7:$K$3006,$O91)) | L91: =IF($O91="","",-INDEX(资金台帐!$S$7:$S$3006,$O91)) | M91: =IF($O91="","",INDEX(资金台帐!$C$7:$C$3006,$O91)) | N91: =IF($O91="","",INDEX(资金台帐!$E$7:$E$3006,$O91)) | O91: =IFERROR(MATCH(88,资金台帐!$R$7:$R$3006,0),"")
A92: =IF($G92="","",89) -> 89 | B92: =IF($G92="","",INDEX(资金台帐!$B$7:$B$3006,$G92)) -> 46231 | C92: =IF($G92="","",INDEX(资金台帐!$J$7:$J$3006,$G92)) -> 桐心源 | D92: =IF($G92="","",INDEX(资金台帐!$S$7:$S$3006,$G92)) -> 13000 | E92: =IF($G92="","",INDEX(资金台帐!$C$7:$C$3006,$G92)) -> 收款码 | F92: =IF($G92="","",INDEX(资金台帐!$E$7:$E$3006,$G92)&IF(INDEX(资金台帐!$M$7:$M$3006,$G92)="","","；"&INDEX(资金台帐!$M$7:$M$3006,$G92))) -> 55900-13000 | G92: =IFERROR(MATCH(89,资金台帐!$Q$7:$Q$3006,0),"") -> 89 | I92: =IF($O92="","",89) | J92: =IF($O92="","",INDEX(资金台帐!$B$7:$B$3006,$O92)) | K92: =IF($O92="","",INDEX(资金台帐!$K$7:$K$3006,$O92)) | L92: =IF($O92="","",-INDEX(资金台帐!$S$7:$S$3006,$O92)) | M92: =IF($O92="","",INDEX(资金台帐!$C$7:$C$3006,$O92)) | N92: =IF($O92="","",INDEX(资金台帐!$E$7:$E$3006,$O92)) | O92: =IFERROR(MATCH(89,资金台帐!$R$7:$R$3006,0),"")
A93: =IF($G93="","",90) -> 90 | B93: =IF($G93="","",INDEX(资金台帐!$B$7:$B$3006,$G93)) -> 46231 | C93: =IF($G93="","",INDEX(资金台帐!$J$7:$J$3006,$G93)) -> 桐心源 | D93: =IF($G93="","",INDEX(资金台帐!$S$7:$S$3006,$G93)) -> 77960 | E93: =IF($G93="","",INDEX(资金台帐!$C$7:$C$3006,$G93)) -> 收款码 | F93: =IF($G93="","",INDEX(资金台帐!$E$7:$E$3006,$G93)&IF(INDEX(资金台帐!$M$7:$M$3006,$G93)="","","；"&INDEX(资金台帐!$M$7:$M$3006,$G93))) -> 收货款 | G93: =IFERROR(MATCH(90,资金台帐!$Q$7:$Q$3006,0),"") -> 90 | I93: =IF($O93="","",90) | J93: =IF($O93="","",INDEX(资金台帐!$B$7:$B$3006,$O93)) | K93: =IF($O93="","",INDEX(资金台帐!$K$7:$K$3006,$O93)) | L93: =IF($O93="","",-INDEX(资金台帐!$S$7:$S$3006,$O93)) | M93: =IF($O93="","",INDEX(资金台帐!$C$7:$C$3006,$O93)) | N93: =IF($O93="","",INDEX(资金台帐!$E$7:$E$3006,$O93)) | O93: =IFERROR(MATCH(90,资金台帐!$R$7:$R$3006,0),"")
A94: =IF($G94="","",91) -> 91 | B94: =IF($G94="","",INDEX(资金台帐!$B$7:$B$3006,$G94)) -> 46232 | C94: =IF($G94="","",INDEX(资金台帐!$J$7:$J$3006,$G94)) -> 星海超市 | D94: =IF($G94="","",INDEX(资金台帐!$S$7:$S$3006,$G94)) -> 9860 | E94: =IF($G94="","",INDEX(资金台帐!$C$7:$C$3006,$G94)) -> 收款码 | F94: =IF($G94="","",INDEX(资金台帐!$E$7:$E$3006,$G94)&IF(INDEX(资金台帐!$M$7:$M$3006,$G94)="","","；"&INDEX(资金台帐!$M$7:$M$3006,$G94))) -> 收货款 | G94: =IFERROR(MATCH(91,资金台帐!$Q$7:$Q$3006,0),"") -> 91 | I94: =IF($O94="","",91) | J94: =IF($O94="","",INDEX(资金台帐!$B$7:$B$3006,$O94)) | K94: =IF($O94="","",INDEX(资金台帐!$K$7:$K$3006,$O94)) | L94: =IF($O94="","",-INDEX(资金台帐!$S$7:$S$3006,$O94)) | M94: =IF($O94="","",INDEX(资金台帐!$C$7:$C$3006,$O94)) | N94: =IF($O94="","",INDEX(资金台帐!$E$7:$E$3006,$O94)) | O94: =IFERROR(MATCH(91,资金台帐!$R$7:$R$3006,0),"")
A95: =IF($G95="","",92) -> 92 | B95: =IF($G95="","",INDEX(资金台帐!$B$7:$B$3006,$G95)) -> 46232 | C95: =IF($G95="","",INDEX(资金台帐!$J$7:$J$3006,$G95)) -> 洪门永信商行 | D95: =IF($G95="","",INDEX(资金台帐!$S$7:$S$3006,$G95)) -> 4500 | E95: =IF($G95="","",INDEX(资金台帐!$C$7:$C$3006,$G95)) -> 收款码 | F95: =IF($G95="","",INDEX(资金台帐!$E$7:$E$3006,$G95)&IF(INDEX(资金台帐!$M$7:$M$3006,$G95)="","","；"&INDEX(资金台帐!$M$7:$M$3006,$G95))) -> 收货款 | G95: =IFERROR(MATCH(92,资金台帐!$Q$7:$Q$3006,0),"") -> 92 | I95: =IF($O95="","",92) | J95: =IF($O95="","",INDEX(资金台帐!$B$7:$B$3006,$O95)) | K95: =IF($O95="","",INDEX(资金台帐!$K$7:$K$3006,$O95)) | L95: =IF($O95="","",-INDEX(资金台帐!$S$7:$S$3006,$O95)) | M95: =IF($O95="","",INDEX(资金台帐!$C$7:$C$3006,$O95)) | N95: =IF($O95="","",INDEX(资金台帐!$E$7:$E$3006,$O95)) | O95: =IFERROR(MATCH(92,资金台帐!$R$7:$R$3006,0),"")
A96: =IF($G96="","",93) -> 93 | B96: =IF($G96="","",INDEX(资金台帐!$B$7:$B$3006,$G96)) -> 46234 | C96: =IF($G96="","",INDEX(资金台帐!$J$7:$J$3006,$G96)) -> 星海超市 | D96: =IF($G96="","",INDEX(资金台帐!$S$7:$S$3006,$G96)) -> 8660 | E96: =IF($G96="","",INDEX(资金台帐!$C$7:$C$3006,$G96)) -> 收款码 | F96: =IF($G96="","",INDEX(资金台帐!$E$7:$E$3006,$G96)&IF(INDEX(资金台帐!$M$7:$M$3006,$G96)="","","；"&INDEX(资金台帐!$M$7:$M$3006,$G96))) -> 收货款 | G96: =IFERROR(MATCH(93,资金台帐!$Q$7:$Q$3006,0),"") -> 93 | I96: =IF($O96="","",93) | J96: =IF($O96="","",INDEX(资金台帐!$B$7:$B$3006,$O96)) | K96: =IF($O96="","",INDEX(资金台帐!$K$7:$K$3006,$O96)) | L96: =IF($O96="","",-INDEX(资金台帐!$S$7:$S$3006,$O96)) | M96: =IF($O96="","",INDEX(资金台帐!$C$7:$C$3006,$O96)) | N96: =IF($O96="","",INDEX(资金台帐!$E$7:$E$3006,$O96)) | O96: =IFERROR(MATCH(93,资金台帐!$R$7:$R$3006,0),"")
A97: =IF($G97="","",94) -> 94 | B97: =IF($G97="","",INDEX(资金台帐!$B$7:$B$3006,$G97)) -> 46234 | C97: =IF($G97="","",INDEX(资金台帐!$J$7:$J$3006,$G97)) -> 吕维春 | D97: =IF($G97="","",INDEX(资金台帐!$S$7:$S$3006,$G97)) -> 30000 | E97: =IF($G97="","",INDEX(资金台帐!$C$7:$C$3006,$G97)) -> 收款码 | F97: =IF($G97="","",INDEX(资金台帐!$E$7:$E$3006,$G97)&IF(INDEX(资金台帐!$M$7:$M$3006,$G97)="","","；"&INDEX(资金台帐!$M$7:$M$3006,$G97))) -> 收货款 | G97: =IFERROR(MATCH(94,资金台帐!$Q$7:$Q$3006,0),"") -> 94 | I97: =IF($O97="","",94) | J97: =IF($O97="","",INDEX(资金台帐!$B$7:$B$3006,$O97)) | K97: =IF($O97="","",INDEX(资金台帐!$K$7:$K$3006,$O97)) | L97: =IF($O97="","",-INDEX(资金台帐!$S$7:$S$3006,$O97)) | M97: =IF($O97="","",INDEX(资金台帐!$C$7:$C$3006,$O97)) | N97: =IF($O97="","",INDEX(资金台帐!$E$7:$E$3006,$O97)) | O97: =IFERROR(MATCH(94,资金台帐!$R$7:$R$3006,0),"")
A98: =IF($G98="","",95) -> 95 | B98: =IF($G98="","",INDEX(资金台帐!$B$7:$B$3006,$G98)) -> 46235 | C98: =IF($G98="","",INDEX(资金台帐!$J$7:$J$3006,$G98)) -> 阿东副食 | D98: =IF($G98="","",INDEX(资金台帐!$S$7:$S$3006,$G98)) -> 67900 | E98: =IF($G98="","",INDEX(资金台帐!$C$7:$C$3006,$G98)) -> 收款码 | F98: =IF($G98="","",INDEX(资金台帐!$E$7:$E$3006,$G98)&IF(INDEX(资金台帐!$M$7:$M$3006,$G98)="","","；"&INDEX(资金台帐!$M$7:$M$3006,$G98))) -> 收货款 | G98: =IFERROR(MATCH(95,资金台帐!$Q$7:$Q$3006,0),"") -> 95 | I98: =IF($O98="","",95) | J98: =IF($O98="","",INDEX(资金台帐!$B$7:$B$3006,$O98)) | K98: =IF($O98="","",INDEX(资金台帐!$K$7:$K$3006,$O98)) | L98: =IF($O98="","",-INDEX(资金台帐!$S$7:$S$3006,$O98)) | M98: =IF($O98="","",INDEX(资金台帐!$C$7:$C$3006,$O98)) | N98: =IF($O98="","",INDEX(资金台帐!$E$7:$E$3006,$O98)) | O98: =IFERROR(MATCH(95,资金台帐!$R$7:$R$3006,0),"")
A99: =IF($G99="","",96) -> 96 | B99: =IF($G99="","",INDEX(资金台帐!$B$7:$B$3006,$G99)) -> 46235 | C99: =IF($G99="","",INDEX(资金台帐!$J$7:$J$3006,$G99)) -> 小陈副食 | D99: =IF($G99="","",INDEX(资金台帐!$S$7:$S$3006,$G99)) -> 12000 | E99: =IF($G99="","",INDEX(资金台帐!$C$7:$C$3006,$G99)) -> 收款码 | F99: =IF($G99="","",INDEX(资金台帐!$E$7:$E$3006,$G99)&IF(INDEX(资金台帐!$M$7:$M$3006,$G99)="","","；"&INDEX(资金台帐!$M$7:$M$3006,$G99))) -> 收货款 | G99: =IFERROR(MATCH(96,资金台帐!$Q$7:$Q$3006,0),"") -> 96 | I99: =IF($O99="","",96) | J99: =IF($O99="","",INDEX(资金台帐!$B$7:$B$3006,$O99)) | K99: =IF($O99="","",INDEX(资金台帐!$K$7:$K$3006,$O99)) | L99: =IF($O99="","",-INDEX(资金台帐!$S$7:$S$3006,$O99)) | M99: =IF($O99="","",INDEX(资金台帐!$C$7:$C$3006,$O99)) | N99: =IF($O99="","",INDEX(资金台帐!$E$7:$E$3006,$O99)) | O99: =IFERROR(MATCH(96,资金台帐!$R$7:$R$3006,0),"")
A100: =IF($G100="","",97) -> 97 | B100: =IF($G100="","",INDEX(资金台帐!$B$7:$B$3006,$G100)) -> 46241 | C100: =IF($G100="","",INDEX(资金台帐!$J$7:$J$3006,$G100)) -> 阿东副食 | D100: =IF($G100="","",INDEX(资金台帐!$S$7:$S$3006,$G100)) -> 2100 | E100: =IF($G100="","",INDEX(资金台帐!$C$7:$C$3006,$G100)) -> 收款码 | F100: =IF($G100="","",INDEX(资金台帐!$E$7:$E$3006,$G100)&IF(INDEX(资金台帐!$M$7:$M$3006,$G100)="","","；"&INDEX(资金台帐!$M$7:$M$3006,$G100))) -> 收货款 | G100: =IFERROR(MATCH(97,资金台帐!$Q$7:$Q$3006,0),"") -> 97 | I100: =IF($O100="","",97) | J100: =IF($O100="","",INDEX(资金台帐!$B$7:$B$3006,$O100)) | K100: =IF($O100="","",INDEX(资金台帐!$K$7:$K$3006,$O100)) | L100: =IF($O100="","",-INDEX(资金台帐!$S$7:$S$3006,$O100)) | M100: =IF($O100="","",INDEX(资金台帐!$C$7:$C$3006,$O100)) | N100: =IF($O100="","",INDEX(资金台帐!$E$7:$E$3006,$O100)) | O100: =IFERROR(MATCH(97,资金台帐!$R$7:$R$3006,0),"")
...

Sheet 存条明细
A1: 商品入库明细台账
A2: 💡 客户存条（预付的货）在此登记，一个商品一行；商品库存表按「客户+商品」自动汇总、自动累加，领用记【出库明细】自动扣减。客户付的存条款记【资金台帐】并选客户。
A3: 序号 | B3: 入库日期 | C3: 客户名称 | D3: 商品品类 | E3: 入库数量(件) | F3: 入库单价(元/件) | G3: 本次入库总金额(元) | H3: 备注
A4: 1 | B4: 46198 | C4: 星海超市 | D4: 小东鹏 | E4: 282 | F4: 50 | G4: =IF(AND(E4<>"",F4<>""),E4*F4,"") -> 14100
A5: 2 | B5: 46198 | C5: 星海超市 | D5: 555补水 | E5: 83 | F5: 65 | G5: =IF(AND(E5<>"",F5<>""),E5*F5,"") -> 5395
A6: 3 | B6: 46198 | C6: 星海超市 | D6: 1L补水 | E6: 142 | F6: 55 | G6: =IF(AND(E6<>"",F6<>""),E6*F6,"") -> 7810
A7: 4 | B7: 46198 | C7: 星海超市 | D7: 1L果之茶 | E7: 118 | F7: 43 | G7: =IF(AND(E7<>"",F7<>""),E7*F7,"") -> 5074
A8: 5 | B8: 46198 | C8: 星海超市 | D8: 港式奶茶 | E8: 96 | F8: 69 | G8: =IF(AND(E8<>"",F8<>""),E8*F8,"") -> 6624
A9: 6 | B9: 46198 | C9: 王玉琴 | D9: 大东鹏 | E9: 1100 | F9: 90 | G9: =IF(AND(E9<>"",F9<>""),E9*F9,"") -> 99000
A10: 7 | B10: 46198 | C10: 桐心源 | D10: 大东鹏 | E10: 6531 | F10: 90 | G10: =IF(AND(E10<>"",F10<>""),E10*F10,"") -> 587790
A11: 8 | B11: 46198 | C11: 桐心源 | D11: 1L补水 | E11: 625 | F11: 55 | G11: =IF(AND(E11<>"",F11<>""),E11*F11,"") -> 34375
A12: 9 | B12: 46198 | C12: 桐心源 | D12: 555补水 | E12: 604 | F12: 65 | G12: =IF(AND(E12<>"",F12<>""),E12*F12,"") -> 39260
A13: 10 | B13: 46198 | C13: 桐心源 | D13: 小果之茶 | E13: 906 | F13: 47 | G13: =IF(AND(E13<>"",F13<>""),E13*F13,"") -> 42582
A14: 11 | B14: 46198 | C14: 桐心源 | D14: 大咖 | E14: 236 | F14: 83 | G14: =IF(AND(E14<>"",F14<>""),E14*F14,"") -> 19588
A15: 12 | B15: 46198 | C15: 桐心源 | D15: 港式奶茶 | E15: 152 | F15: 69 | G15: =IF(AND(E15<>"",F15<>""),E15*F15,"") -> 10488
... A43: 40 | B43: 46199 | C43: 致发商行 | D43: 大东鹏 | E43: 2300 | F43: 90 | G43: =IF(AND(E43<>"",F43<>""),E43*F43,"") -> 207000
A44: 41 | B44: 46199 | C44: 致发商行 | D44: 小果之茶 | E44: 1040 | F44: 47 | G44: 47000
A45: 42 | B45: 46199 | C45: 致发商行 | D45: 大咖 | E45: 208 | F45: 86 | G45: 16600
A46: 43 | B46: 46199 | C46: 致发商行 | D46: 1L果之茶 | E46: 208 | F46: 43 | G46: 8600
A47: 44 | B47: 46199 | C47: 通达商行 | D47: 大东鹏 | E47: 200 | F47: 90 | G47: =IF(AND(E47<>"",F47<>""),E47*F47,"") -> 18000
A48: 45 | B48: 46199 | C48: 宜兴粮油 | D48: 大东鹏 | E48: 615 | F48: 87.8 | G48: 54000
A49: 46 | B49: 46199 | C49: 宜兴粮油 | D49: 555补水 | E49: 5 | F49: 0 | G49: =IF(AND(E49<>"",F49<>""),E49*F49,"") -> 0
A50: 47 | B50: 46200 | C50: 兴莲隆兴商行 | D50: 大东鹏 | E50: 162 | F50: 90 | G50: =IF(AND(E50<>"",F50<>""),E50*F50,"") -> 14580
A51: 48 | B51: 46200 | C51: 兴莲隆兴商行 | D51: 1L补水 | E51: 23 | F51: 55 | G51: =IF(AND(E51<>"",F51<>""),E51*F51,"") -> 1265
A52: 49 | B52: 46200 | C52: 兴莲隆兴商行 | D52: 555补水 | E52: 23 | F52: 65 | G52: =IF(AND(E52<>"",F52<>""),E52*F52,"") -> 1495
A53: 50 | B53: 46200 | C53: 兴莲隆兴商行 | D53: 大咖 | E53: 68 | F53: 83 | G53: =IF(AND(E53<>"",F53<>""),E53*F53,"") -> 5644
A54: 51 | B54: 46200 | C54: 兴莲隆兴商行 | D54: 港式奶茶 | E54: 11 | F54: 69 | G54: =IF(AND(E54<>"",F54<>""),E54*F54,"") -> 759
A55: 52 | B55: 46200 | C55: 诚信粮油 | D55: 大东鹏 | E55: 300 | F55: 90 | G55: =IF(AND(E55<>"",F55<>""),E55*F55,"") -> 27000
A56: 53 | B56: 46200 | C56: 吕维春 | D56: 大东鹏 | E56: 250 | F56: 90 | G56: =IF(AND(E56<>"",F56<>""),E56*F56,"") -> 22500
A57: 54 | B57: 46200 | C57: 吕维春 | D57: 1L补水 | E57: 150 | F57: 55 | G57: =IF(AND(E57<>"",F57<>""),E57*F57,"") -> 8250
A58: 55 | B58: 46200 | C58: 吕维春 | D58: 1L果之茶 | E58: 20 | F58: 43 | G58: =IF(AND(E58<>"",F58<>""),E58*F58,"") -> 860
A59: 56 | B59: 46200 | C59: 吕维春 | D59: 大咖 | E59: 10 | F59: 83 | G59: =IF(AND(E59<>"",F59<>""),E59*F59,"") -> 830
A60: 57 | B60: 46200 | C60: 兴发商行 | D60: 大东鹏 | E60: 170 | F60: 90 | G60: =IF(AND(E60<>"",F60<>""),E60*F60,"") -> 15300
... A89: 86 | B89: 46200 | C89: 洪门美群商行 | D89: 大东鹏 | E89: 50 | F89: 90 | G89: =IF(AND(E89<>"",F89<>""),E89*F89,"") -> 4500
A90: 87 | B90: 46200 | C90: 兴江家源超市 | D90: 大东鹏 | E90: 20 | F90: 90 | G90: =IF(AND(E90<>"",F90<>""),E90*F90,"") -> 1800 | H90: 2024年7月5日存条
A91: 88 | B91: 46200 | C91: 枫边德华超市 | D91: 大东鹏 | E91: 100 | F91: 90 | G91: =IF(AND(E91<>"",F91<>""),E91*F91,"") -> 9000
A92: 89 | B92: 46200 | C92: 枫边德华超市 | D92: 555补水 | E92: 80 | F92: 65 | G92: =IF(AND(E92<>"",F92<>""),E92*F92,"") -> 5200
A93: 90 | B93: 46200 | C93: 枫边德华超市 | D93: 1L补水 | E93: 80 | F93: 55 | G93: =IF(AND(E93<>"",F93<>""),E93*F93,"") -> 4400
A94: 91 | B94: 46200 | C94: 枫边德华超市 | D94: 港式奶茶 | E94: 80 | F94: 69 | G94: =IF(AND(E94<>"",F94<>""),E94*F94,"") -> 5520
A95: 92 | B95: 46200 | C95: 枫边德华超市 | D95: 1L果之茶 | E95: 80 | F95: 46 | G95: =IF(AND(E95<>"",F95<>""),E95*F95,"") -> 3680
A96: 93 | B96: 46200 | C96: 枫边德华超市 | D96: 九制陈皮 | E96: 40 | F96: 47 | G96: =IF(AND(E96<>"",F96<>""),E96*F96,"") -> 1880
A97: 94 | B97: 46200 | C97: 枫边德华超市 | D97: 小果之茶 | E97: 40 | F97: 47 | G97: =IF(AND(E97<>"",F97<>""),E97*F97,"") -> 1880
A98: 95 | B98: 46200 | C98: 枫边德华超市 | D98: 大咖 | E98: 80 | F98: 86 | G98: =IF(AND(E98<>"",F98<>""),E98*F98,"") -> 6880
A99: 96 | B99: 46200 | C99: 梅窖建军批发 | D99: 1L补水 | E99: 80 | F99: 55 | G99: =IF(AND(E99<>"",F99<>""),E99*F99,"") -> 4400
A100: 97 | B100: 46200 | C100: 梅窖建军批发 | D100: 555补水 | E100: 60 | F100: 65 | G100: =IF(AND(E100<>"",F100<>""),E100*F100,"") -> 3900
A101: 98 | B101: 46200 | C101: 梅窖建军批发 | D101: 1L果之茶 | E101: 80 | F101: 43 | G101: =IF(AND(E101<>"",F101<>""),E101*F101,"") -> 3440
A102: 99 | B102: 46200 | C102: 洪门兴诚超市 | D102: 大东鹏 | E102: 500 | F102: 90 | G102: =IF(AND(E102<>"",F102<>""),E102*F102,"") -> 45000
... A120: 118 | B120: 46221 | C120: 标哥副食 | D120: 小果之茶 | E120: 1 | F120: 50 | G120: =IF(AND(E120<>"",F120<>""),E120*F120,"") -> 50
A121: 119 | B121: 46156 | C121: 鼎龙陈财超市 | D121: 大东鹏 | E121: 1200 | F121: 80 | G121: 108000
A122: 120 | B122: 46228 | C122: 春萌副食 | D122: 大东鹏 | E122: 25 | F122: 93 | G122: =IF(AND(E122<>"",F122<>""),E122*F122,"") -> 2325
A123: 121 | B123: 46226 | C123: 城西街福临门超市 | D123: 大东鹏 | E123: 22 | F123: 93 | G123: =IF(AND(E123<>"",F123<>""),E123*F123,"") -> 2046
A124: 122 | B124: 46227 | C124: 滨江路莲花便利店 | D124: 小果之茶 | E124: 23 | F124: 50 | G124: =IF(AND(E124<>"",F124<>""),E124*F124,"") -> 1150
A125: 123 | B125: 46227 | C125: 滨江路莲花便利店 | D125: 大咖 | E125: 3 | F125: 86 | G125: =IF(AND(E125<>"",F125<>""),E125*F125,"") -> 258
A126: 124 | B126: 46227 | C126: 滨江路莲花便利店 | D126: 1L补水 | E126: 3 | F126: 58 | G126: =IF(AND(E126<>"",F126<>""),E126*F126,"") -> 174
A127: 22 | B127: 46226 | C127: 马路下小卖部 | D127: 大东鹏 | E127: 200 | F127: 93 | G127: =IF(AND(E127<>"",F127<>""),E127*F127,"") -> 18600
A128: 23 | B128: 46227 | C128: 小梅商行 | D128: 大东鹏 | E128: 4000 | F128: 90 | G128: =IF(AND(E128<>"",F128<>""),E128*F128,"") -> 360000
A129: 24 | B129: 46228 | C129: 星海超市 | D129: 小果之茶 | E129: 400 | F129: 47 | G129: =IF(AND(E129<>"",F129<>""),E129*F129,"") -> 18800
A130: 25 | B130: 46228 | C130: 星海超市 | D130: 小果之茶 | E130: 16 | G130: =IF(AND(E130<>"",F130<>""),E130*F130,"")
A131: 26 | B131: 46228 | C131: 星海超市 | D131: 大咖 | E131: 100 | F131: 83 | G131: =IF(AND(E131<>"",F131<>""),E131*F131,"") -> 8300
A132: 27 | B132: 46228 | C132: 星海超市 | D132: 大咖 | E132: 4 | G132: =IF(AND(E132<>"",F132<>""),E132*F132,"")
A133: 28 | B133: 46228 | C133: 星海超市 | D133: 555补水 | E133: 200 | F133: 65 | G133: =IF(AND(E133<>"",F133<>""),E133*F133,"") -> 13000
A134: 29 | B134: 46228 | C134: 星海超市 | D134: 555补水 | E134: 20 | G134: =IF(AND(E134<>"",F134<>""),E134*F134,"")
A135: 30 | B135: 46228 | C135: 星海超市 | D135: 大东鹏 | E135: 800 | F135: 90 | G135: =IF(AND(E135<>"",F135<>""),E135*F135,"") -> 72000
A136: 31 | B136: 46228 | C136: 星海超市 | D136: 大东鹏 | E136: 8 | G136: =IF(AND(E136<>"",F136<>""),E136*F136,"")
A137: 32 | B137: 46224 | C137: 城岗日日升超市 | D137: 大东鹏 | E137: 300 | F137: 90 | G137: =IF(AND(E137<>"",F137<>""),E137*F137,"") -> 27000
A138: 33 | B138: 46218 | C138: 福旺家优购 | D138: 大东鹏 | E138: 250 | F138: 90 | G138: =IF(AND(E138<>"",F138<>""),E138*F138,"") -> 22500
A139: 34 | B139: 46218 | C139: 福旺家优购 | D139: 大东鹏 | E139: 5 | G139: =IF(AND(E139<>"",F139<>""),E139*F139,"")
A140: 35 | B140: 46218 | C140: 福旺家优购 | D140: 555补水 | E140: 20 | F140: 68 | G140: =IF(AND(E140<>"",F140<>""),E140*F140,"") -> 1360
A141: 36 | B141: 46218 | C141: 福旺家优购 | D141: 555补水 | E141: 2 | G141: =IF(AND(E141<>"",F141<>""),E141*F141,"")
A142: 37 | B142: 46218 | C142: 福旺家优购 | D142: 小果之茶 | E142: 15 | F142: 50 | G142: =IF(AND(E142<>"",F142<>""),E142*F142,"") -> 750
A143: 38 | B143: 46218 | C143: 福旺家优购 | D143: 1L果之茶 | E143: 10 | F143: 46 | G143: =IF(AND(E143<>"",F143<>""),E143*F143,"") -> 460
A144: 39 | B144: 46218 | C144: 福旺家优购 | D144: 小果之茶 | E144: 2 | G144: =IF(AND(E144<>"",F144<>""),E144*F144,"")
A145: 40 | B145: 46218 | C145: 福旺家优购 | D145: 1L补水 | E145: 15 | F145: 58 | G145: =IF(AND(E145<>"",F145<>""),E145*F145,"") -> 870
A146: 41 | B146: 46218 | C146: 福旺家优购 | D146: 港式奶茶 | E146: 2 | F146: 72 | G146: =IF(AND(E146<>"",F146<>""),E146*F146,"") -> 144
A147: 42 | B147: 46218 | C147: 福旺家优购 | D147: 九制陈皮 | E147: 2 | F147: 50 | G147: =IF(AND(E147<>"",F147<>""),E147*F147,"") -> 100
A148: 43 | B148: 46218 | C148: 福旺家优购 | D148: 1L焙好茶 | E148: 4 | F148: 46 | G148: =IF(AND(E148<>"",F148<>""),E148*F148,"") -> 184
A149: 44 | B149: 46218 | C149: 福旺家优购 | D149: 小焙好茶 | E149: 2 | F149: 51 | G149: =IF(AND(E149<>"",F149<>""),E149*F149,"") -> 102
A150: 45 | B150: 46225 | C150: 友兰商行 | D150: 大咖 | E150: 7 | F150: 86 | G150: =IF(AND(E150<>"",F150<>""),E150*F150,"") -> 602
A151: 46 | B151: 46211 | C151: 友兰商行 | D151: 大东鹏 | E151: 50 | F151: 93 | G151: =IF(AND(E151<>"",F151<>""),E151*F151,"") -> 4650
A152: 47 | B152: 46220 | C152: 阿东副食 | D152: 东鹏椰子水 | E152: 100 | F152: 90 | G152: =IF(AND(E152<>"",F152<>""),E152*F152,"") -> 9000
A153: 48 | B153: 46220 | C153: 阿东副食 | D153: 东鹏椰子水 | E153: 4 | G153: =IF(AND(E153<>"",F153<>""),E153*F153,"")
A154: 49 | B154: 46220 | C154: 桐心源 | D154: 东鹏椰子水 | E154: 100 | F154: 90 | G154: =IF(AND(E154<>"",F154<>""),E154*F154,"") -> 9000
A155: 50 | B155: 46220 | C155: 桐心源 | D155: 东鹏椰子水 | E155: 4 | G155: =IF(AND(E155<>"",F155<>""),E155*F155,"")
A156: 51 | B156: 46223 | C156: 高兴四季春副食 | D156: 大东鹏 | E156: 25 | F156: 93 | G156: =IF(AND(E156<>"",F156<>""),E156*F156,"") -> 2325
A157: 52 | B157: 46223 | C157: 高兴四季春副食 | D157: 大东鹏 | E157: 1 | G157: =IF(AND(E157<>"",F157<>""),E157*F157,"")
A158: 53 | B158: 46223 | C158: 高兴四季春副食 | D158: 大咖 | E158: 2 | F158: 86 | G158: =IF(AND(E158<>"",F158<>""),E158*F158,"") -> 172
A159: 54 | B159: 46223 | C159: 高兴四季春副食 | D159: 小果之茶 | E159: 4 | F159: 50 | G159: =IF(AND(E159<>"",F159<>""),E159*F159,"") -> 200
A160: 55 | B160: 46211 | C160: 崇贤高平副食 | D160: 大东鹏 | E160: 25 | F160: 93 | G160: =IF(AND(E160<>"",F160<>""),E160*F160,"") -> 2325
A161: 56 | B161: 46211 | C161: 高兴张声英 | D161: 大东鹏 | E161: 25 | F161: 93 | G161: =IF(AND(E161<>"",F161<>""),E161*F161,"") -> 2325
A162: 57 | B162: 46211 | C162: 崇贤粤客隆 | D162: 大东鹏 | E162: 25 | F162: 93 | G162: =IF(AND(E162<>"",F162<>""),E162*F162,"") -> 2325
A163: 58 | B163: 46211 | C163: 火车站关新平 | D163: 大东鹏 | E163: 50 | F163: 93 | G163: =IF(AND(E163<>"",F163<>""),E163*F163,"") -> 4650
A164: 59 | B164: 46211 | C164: 火车站关新平 | D164: 555补水 | E164: 10 | F164: 68 | G164: =IF(AND(E164<>"",F164<>""),E164*F164,"") -> 680
A165: 60 | B165: 46220 | C165: 洪门五香副食 | D165: 大东鹏 | E165: 10 | F165: 93 | G165: =IF(AND(E165<>"",F165<>""),E165*F165,"") -> 930
A166: 61 | B166: 46220 | C166: 高兴美宜佳 | D166: 大东鹏 | E166: 100 | F166: 90 | G166: =IF(AND(E166<>"",F166<>""),E166*F166,"") -> 9000
A167: 62 | B167: 46218 | C167: 良村万家欢超市 | D167: 大东鹏 | E167: 15 | F167: 93 | G167: =IF(AND(E167<>"",F167<>""),E167*F167,"") -> 1395
A168: 63 | B168: 46220 | C168: 滨江路小红花便利店 | D168: 555补水 | E168: 10 | F168: 68 | G168: =IF(AND(E168<>"",F168<>""),E168*F168,"") -> 680
A169: 64 | B169: 46220 | C169: 滨江路小红花便利店 | D169: 555补水 | E169: 1 | G169: =IF(AND(E169<>"",F169<>""),E169*F169,"")
A170: 65 | B170: 46220 | C170: 滨江路小红花便利店 | D170: 小果之茶 | E170: 25 | F170: 50 | G170: =IF(AND(E170<>"",F170<>""),E170*F170,"") -> 1250
A171: 66 | B171: 46220 | C171: 滨江路小红花便利店 | D171: 小果之茶 | E171: 2 | G171: =IF(AND(E171<>"",F171<>""),E171*F171,"")
A172: 67 | B172: 46220 | C172: 滨江路小红花便利店 | D172: 1L补水 | E172: 10 | F172: 58 | G172: =IF(AND(E172<>"",F172<>""),E172*F172,"") -> 580
...

Sheet 商品库存
A1: 商品库存明细（按客户+商品）
A2: 💡 每个客户每个商品的存条库存：全自动，不用手工加行——【存条明细】或【出库明细】里出现新的「客户+商品」，这里自动多一行（按总览汇总的客户顺序排）。剩余＝累计入库−已领用。
A3: 序号 | B3: 客户名称 | C3: 商品品类 | D3: 累计入库数量(件) | E3: 入库单价(元) | F3: 累计入库总金额(元) | G3: 已领用数量(件) | H3: 已领用金额(元) | I3: 剩余数量(件) | J3: 剩余金额(元) | K3: 最后更新日期
A4: =IF(B4="","",ROW()-3) -> 1 | B4: =IF(_辅助!$B4="","",IF(_辅助!$B4<=1000,INDEX(存条明细!$C$4:$C$1003,_辅助!$B4),INDEX(出库明细!$C$4:$C$3003,_辅助!$B4-1000))) -> 星海超市 | C4: =IF(_辅助!$B4="","",IF(_辅助!$B4<=1000,INDEX(存条明细!$D$4:$D$1003,_辅助!$B4),INDEX(出库明细!$D$4:$D$3003,_辅助!$B4-1000))) -> 大东鹏 | D4: =IF($B4="","",IFERROR(SUMIFS(存条明细!E:E,存条明细!C:C,$B4,存条明细!D:D,$C4),0)) -> 808 | E4: =IF(OR($B4="",N(D4)=0),"",ROUND(F4/D4,2)) -> 89.11 | F4: =IF($B4="","",IFERROR(SUMIFS(存条明细!G:G,存条明细!C:C,$B4,存条明细!D:D,$C4),0)) -> 72000 | G4: =IF($B4="","",IFERROR(SUMIFS(出库明细!E:E,出库明细!C:C,$B4,出库明细!D:D,$C4),0)) -> 500 | H4: =IF($B4="","",IFERROR(SUMIFS(出库明细!G:G,出库明细!C:C,$B4,出库明细!D:D,$C4),0)) -> 45000 | I4: =IF($B4="","",D4-G4) -> 308 | J4: =IF($B4="","",F4-H4) -> 27000 | K4: =IF($B4="","",MAX(_xlfn.MAXIFS(存条明细!B:B,存条明细!C:C,$B4,存条明细!D:D,$C4),_xlfn.MAXIFS(出库明细!B:B,出库明细!C:C,$B4,出库明细!D:D,$C4))) -> 46256
A5: =IF(B5="","",ROW()-3) -> 2 | B5: =IF(_辅助!$B5="","",IF(_辅助!$B5<=1000,INDEX(存条明细!$C$4:$C$1003,_辅助!$B5),INDEX(出库明细!$C$4:$C$3003,_辅助!$B5-1000))) -> 星海超市 | C5: =IF(_辅助!$B5="","",IF(_辅助!$B5<=1000,INDEX(存条明细!$D$4:$D$1003,_辅助!$B5),INDEX(出库明细!$D$4:$D$3003,_辅助!$B5-1000))) -> 小东鹏 | D5: =IF($B5="","",IFERROR(SUMIFS(存条明细!E:E,存条明细!C:C,$B5,存条明细!D:D,$C5),0)) -> 282 | E5: =IF(OR($B5="",N(D5)=0),"",ROUND(F5/D5,2)) -> 50 | F5: =IF($B5="","",IFERROR(SUMIFS(存条明细!G:G,存条明细!C:C,$B5,存条明细!D:D,$C5),0)) -> 14100 | G5: =IF($B5="","",IFERROR(SUMIFS(出库明细!E:E,出库明细!C:C,$B5,出库明细!D:D,$C5),0)) -> 182 | H5: =IF($B5="","",IFERROR(SUMIFS(出库明细!G:G,出库明细!C:C,$B5,出库明细!D:D,$C5),0)) -> 9282 | I5: =IF($B5="","",D5-G5) -> 100 | J5: =IF($B5="","",F5-H5) -> 4818 | K5: =IF($B5="","",MAX(_xlfn.MAXIFS(存条明细!B:B,存条明细!C:C,$B5,存条明细!D:D,$C5),_xlfn.MAXIFS(出库明细!B:B,出库明细!C:C,$B5,出库明细!D:D,$C5))) -> 46237
