Workbook

Sheet 项目汇总情况
A1: 项目名称 | B1: 甲方 | C1: 乙方 | D1: 合同金额 | E1: 质保金 | F1: 回款金额 | G1: 未收款 | H1: 收款比例 | I1: 已开票金额 | J1: 税率 | K1: 未开票金额
A2: 农村商业银行股份有限公司德安县总部室外消防栓改造 | B2: 银行 | C2: 竣辉 | D2: 8992 | E2: 0 | F2: 0 | G2: =D2+E2-F2 -> 8992 | H2: =F2/D2 -> 0 | I2: 8992 | J2: 0.09 | K2: =D2-I2 -> 0

Sheet 应付汇总
B1: 名称（材料） | C1: 摘要 | D1: 应付金额/合同金额 | E1: 已支付 | F1: 已付合计 | G1: 未付金额 | H1: 已开发票金额 | I1: 税率 | J1: 税额 | K1: 欠发票金额
B2: 江西筑强建材有限公司 | C2: 消防器材 | D2: 546.94 | E2: 546.94 | F2: =SUM(E2:E2) -> 546.94 | G2: =D2-F2 -> 0 | H2: 546.94 | I2: 0.13 | J2: =H2/(1+I2)*I2 -> 62.922301 | K2: =D2-H2 -> 0
B3: 德安草坪基地 | C3: 草皮 | D3: 50 | E3: 50 | F3: =SUM(E3:E3) -> 50 | G3: =D3-F3 -> 0 | I3: % | J3: =G3/1.01*0.01 -> 0 | K3: =D3-H3 -> 50
B4: 稻花香(树苗供应商） | C4: 树苗 | D4: 70 | E4: 70 | F4: =SUM(E4:E4) -> 70 | G4: =D4-F4 -> 0 | I4: % | K4: =D4-H4 -> 70
F5: =SUM(E5:E5) -> 0 | G5: =D5-F5 -> 0 | I5: % | K5: =D5-H5 -> 0
F6: =SUM(E6:E6) -> 0 | G6: =D6-F6 -> 0 | K6: =D6-H6 -> 0
F7: =SUM(E7:E7) -> 0 | G7: =D7-F7 -> 0 | K7: =D7-H7 -> 0
F8: =SUM(E8:E8) -> 0 | G8: =D8-F8 -> 0 | K8: =D8-H8 -> 0
F9: =SUM(E9:E9) -> 0 | G9: =D9-F9 -> 0 | K9: =D9-H9 -> 0
F10: =SUM(E10:E10) -> 0 | G10: =D10-F10 -> 0 | K10: =D10-H10 -> 0
F11: =SUM(E11:E11) -> 0 | G11: =D11-F11 -> 0 | K11: =D11-H11 -> 0
B12: 名称（人工） | C12: 摘要 | D12: 应付金额 | E12: 已支付 | F12: 已付合计 | G12: 未付金额 | H12: 已开发票金额 | I12: 税率 | J12: 税额 | K12: 欠发票金额
B13: 项目-劳务费 | C13: 农民工工资 | D13: 1820 | E13: 1820 | F13: =SUM(E13:E13) -> 1820 | G13: =D13-F13 -> 0 | K13: =D13-H13 -> 1820
B14: 临时工工资 | C14: 王伟现金付 | D14: 360 | E14: 360 | F14: =SUM(E14:E14) -> 360 | G14: =D14-F14 -> 0 | K14: =D14-H14 -> 360
F15: =SUM(E15:E15) -> 0 | G15: =D15-F15 -> 0 | K15: =D15-H15 -> 0 | N15: 1820
F16: =SUM(E16:E16) -> 0 | G16: =D16-F16 -> 0 | K16: =D16-H16 -> 0 | N16: 800
B17: 名称（间接） | C17: 摘要 | D17: 应付金额 | E17: 已支付 | F17: 已付合计 | G17: 未付金额 | H17: 已开发票金额 | I17: 税率 | J17: 税额 | K17: 欠发票金额
B18: 项目-期间费-机械费 | C18: 挖机费用 | D18: 800 | E18: 800 | F18: =SUM(E18:E18) -> 800 | G18: =D18-F18 -> 0 | H18: 800 | I18: 0.01 | J18: =H18/(1+I18)*I18 -> 7.9207921
F19: =SUM(E19:E19) -> 0 | G19: =D19-F19 -> 0
F20: =SUM(E20:E20) -> 0 | G20: =D20-F20 -> 0
F21: =SUM(E21:E21) -> 0 | G21: =D21-F21 -> 0 | K21: =E21-H21 -> 0
F22: =SUM(E22:E22) -> 0 | G22: =D22-F22 -> 0 | K22: =E22-H22 -> 0
F23: =SUM(E23:E23) -> 0 | G23: =D23-F23 -> 0 | K23: =E23-H23 -> 0
F24: =SUM(E24:E24) -> 0 | G24: =D24-F24 -> 0 | K24: =E24-H24 -> 0
F25: =SUM(E25:E25) -> 0 | G25: =D25-F25 -> 0 | K25: =E25-H25 -> 0
F26: =SUM(E26:E26) -> 0 | G26: =D26-F26 -> 0 | K26: =E26-H26 -> 0
F27: =SUM(E27:E27) -> 0 | G27: =D27-F27 -> 0 | K27: =E27-H27 -> 0
F28: =SUM(E28:E28) -> 0 | G28: =D28-F28 -> 0 | K28: =E28-H28 -> 0
F29: =SUM(E29:E29) -> 0 | G29: =D29-F29 -> 0 | K29: =E29-H29 -> 0

Sheet 利润表
A1: 德安农商行总部利润表
B2: 项目 | C2: 金额 | D2: 百分比
A3: 收入项目 | B3: 工程款 | C3: =项目汇总情况!D2 -> 8992 | D3: 1
B5: {=IFERROR(OFFSET($X$1,SMALL(IF(($X$1:$X$111)<>"",ROW($X$1:$X$111),""),ROW(#REF!))-ROW($X$1),0),"")} | C5: =IF(B5="","",IF(#REF!="",SUMIFS([1]收支登记表!$J:$J,[1]收支登记表!$D:$D,">="&$L$2,[1]收支登记表!$D:$D,"<="&$N$2,[1]收支登记表!$H:$H,[1]利润表!$G29),SUMIFS([1]收支登记表!$J:$J,[1]收支登记表!$D:$D,">="&$L$2,[1]收支登记表!$D:$D,"<="&$N$2,[1]收支登记表!$H:$H,[1]利润表!$G29,[1]收支登记表!$M:$M,[1]利润表!$L$3))) | D5: =IFERROR(C5/#REF!,"")
A6: 总收入 | C6: =C3 -> 8992 | D6: =IFERROR(C6/#REF!,"")
A7: 支出项目 | B7: 项目-材料费 | C7: =SUM(应付汇总!D2:D11) -> 666.94 | D7: =C7/C6 -> 0.074170374
B8: 项目-劳务费 | C8: =SUM(应付汇总!D13:D16) -> 2180 | D8: =C8/C6 -> 0.24243772
D9: =C9/C6 -> 0
B10: 项目-期间费 | C10: =SUM(应付汇总!D18:D30) -> 800 | D10: =C10/C6 -> 0.088967972
B11: 分摊费用 | C11: =待摊费用!D11 -> 636.70495 | D11: =C11/C6 -> 0.070807935
D12: =C12/C6 -> 0
D13: =C13/C6 -> 0
B14: {=IFERROR(OFFSET($Y$1,SMALL(IF(($Y$1:$Y$111)<>"",ROW($Y$1:$Y$111),""),ROW(#REF!))-ROW($Y$1),0),"")} | C14: =IF(B14="","",IF(#REF!="",SUMIFS([1]收支登记表!$K:$K,[1]收支登记表!$D:$D,">="&$L$2,[1]收支登记表!$D:$D,"<="&$N$2,[1]收支登记表!$H:$H,[1]利润表!$G103),SUMIFS([1]收支登记表!$K:$K,[1]收支登记表!$D:$D,">="&$L$2,[1]收支登记表!$D:$D,"<="&$N$2,[1]收支登记表!$H:$H,[1]利润表!$G103,[1]收支登记表!$M:$M,[1]利润表!$L$3))) | D14: =IFERROR(C14/$H$17,"")
B15: {=IFERROR(OFFSET($Y$1,SMALL(IF(($Y$1:$Y$111)<>"",ROW($Y$1:$Y$111),""),ROW(#REF!))-ROW($Y$1),0),"")} | C15: =IF(B15="","",IF(#REF!="",SUMIFS([1]收支登记表!$K:$K,[1]收支登记表!$D:$D,">="&$L$2,[1]收支登记表!$D:$D,"<="&$N$2,[1]收支登记表!$H:$H,[1]利润表!$G104),SUMIFS([1]收支登记表!$K:$K,[1]收支登记表!$D:$D,">="&$L$2,[1]收支登记表!$D:$D,"<="&$N$2,[1]收支登记表!$H:$H,[1]利润表!$G104,[1]收支登记表!$M:$M,[1]利润表!$L$3))) | D15: =IFERROR(C15/$H$17,"")
A16: 总支出 | C16: =SUM(C7:C15) -> 4283.645 | D16: =IFERROR(C16/$H$17,"")
A17: 利 润 | C17: =SUM(C6-C16) -> 4708.355 | D17: 0

Sheet 待摊费用
A1: 工程款合计 | B1: =SUBTOTAL(9,B3:B100) -> 9649368.9 | H1: 25-26合计 | I1: =H16+J16 -> 683251.89
A2: 项目名称 | B2: 工程款 | C2: 比例 | D2: 待摊费用 | G2: 25年 | H2: 2025年待摊费用 | I2: 26年 | J2: 2026年待摊费用
A3: 九安架空层 | B3: 1500000 | C3: =B3/B1 -> 0.15545058 | D3: =I1*C3 -> 106211.9 | G3: 办公费 | H3: 63079.24 | I3: 办公费 | J3: 48775.98
A4: 德安养老中心 | B4: 4362576.5 | C4: =B4/B1 -> 0.45211003 | D4: =C4*I1 -> 308905.03 | G4: 张滨、王伟报销 | H4: 59850 | I4: 贷款利息 | J4: 5755.94
A5: 科创中心 | B5: 1641809 | C5: =B5/B1 -> 0.17014677 | D5: =C5*I1 -> 116253.11 | G5: 本地税费 | H5: 7366.32 | I5: 朱博文社保 | J5: 6132.15
A6: 数字产业园 | B6: 325612.18 | C6: =B6/B1 -> 0.033744401 | D6: =C6*I1 -> 23055.926 | G6: 办公室工资 | H6: 144850 | I6: 本地税款 | J6: 11442.26
A7: 邹桥派出所 | B7: 91006.56 | C7: =B7/B1 -> 0.0094313484 | D7: =C7*I1 -> 6443.9866 | I7: 聂辉工资 | J7: 120000
A8: 抚州1号楼 | B8: 695372.72 | C8: =B8/B1 -> 0.072064062 | D8: =C8*I1 -> 49237.906 | I8: 王伟工资 | J8: 120000
A9: 抚州2号楼 | B9: 64000 | C9: =B9/B1 -> 0.0066325581 | D9: =C9*I1 -> 4531.7078 | I9: 张滨工资 | J9: 96000
A10: 抚州8号楼 | B10: 960000 | C10: =B10/B1 -> 0.099488371 | D10: =C10*I1 -> 67975.618 | I10: 聂辉报销款
A11: 共青农商行 | B11: 8992 | C11: =B11/B1 -> 0.00093187441 | D11: =C11*I1 -> 636.70495 | I11: 王伟报销款
I12: 张滨报销款
G16: 25年合计： | H16: =SUM(H3:OFFSET(H16,-1,0)) -> 275145.56 | I16: 26年合计： | J16: =SUM(J3:OFFSET(J16,-1,0)) -> 408106.33

Sheet 销售发票的明细
A1: 销售发票及回款
A2: 收款日期 | B2: 收款金额 | C2: 开票日期 | D2: 开票金额 | E2: 备注
B10: =SUM(B3:B9) -> 0 | C10: =SUM(C3:C9) -> 0 | D10: =SUM(D3:D9) -> 0

Sheet 项目的税负表
A1: xxxxxxx项目税负表 | K1: 扣款明细
A2: 名称 | B2: 含税金额 | C2: 不含税金额 | D2: 税额 | E2: 比例 | F2: 备注 | G2: 已回票 | H2: 差票 | K2: 费用 | L2: 金额 | M2: 费率
A3: 工程款9% | B3: 8992 | C3: =B3/1.09 -> 8249.5413 | D3: =C3*0.09 -> 742.45872 | K3: 增值税 | L3: =C3*0.02 -> 164.99083 | M3: =L3/B3 -> 0.018348624
A4: 0.13 | B4: =C4+D4 -> 5019.5286 | C4: =D4/0.13 -> 4442.0607 | D4: =D3-D5-D6 -> 577.46789 | E4: =B4/B3 -> 0.55822159 | F4: 材料专票 | G4: 546.94 | H4: =B4-G4 -> 4472.5886 | K4: 附加税 | L4: =L3*0.12 -> 19.798899 | M4: =L4/B3 -> 0.0022018349
A5: 0.03 | C5: =B5/1.03 -> 0 | D5: =C5*0.03 -> 0 | E5: =B5/B3 -> 0 | F5: 劳务及其他 | K5: 印花税 | L5: =B3*0.0006 -> 5.3952 | M5: =L5/B3 -> 0.0006
A6: 普通 | B6: =B3-B4-B5-B7 -> 3773.2945 | C6: =B6 -> 3773.2945 | D6: =L3 -> 164.99083 | E6: =B6/B3 -> 0.41962795 | F6: 劳务及其他 | G6: 2620 | H6: =B6-G6 -> 1153.2945 | K6: 企业所得税 | L6: =B3*0.001 -> 8.992 | M6: =L6/B3 -> 0.001
A7: 扣款 | B7: =L7 -> 199.17692 | K7: 合计 | L7: =SUM(L3:L6) -> 199.17692
K8: 税负 | L8: =L7/B3 -> 0.022150459 | M8: =SUM(M3:M7) -> 0.022150459
