Workbook

Sheet 首页
A1: A076 拼多多电脑电商财务帐套 · 首页（报表本）
A2: 录入本连接： | B2: =IF(ISERROR(COUNTIF('[1]基础资料'!$A$4:$A$5,"?*")),"请先打开 A076-1_录入本.xlsx，再在这本按 F9／更新","录入本已连上（数取自 A076-1_录入本.xlsx）") -> 录入本已连上（数取自 A076-1_录入本.xlsx）
A3: 用法：先开录入本（记账、粘管家婆和拼多多导出都在那本），再开这本看报表。两本放同一个文件夹，文件名别改。下面年份、月份可以改（淡黄格）。
A4: 年份 | B4: 2026 | D4: 月份（本月） | E4: 9
A6: 资金账户 | B6: 当前余额 | D6: 本月（见上面月份） | E6: 金额
A7: =IF('[1]基础资料'!$A$5="","",'[1]基础资料'!$A$5) -> 招商银行 | B7: =IF(A7="","",'[1]基础资料'!$D$5) -> 100000 | D7: 资金台帐收入（不含内部转账） | E7: =SUMIFS('[1]资金台帐'!$G$4:$G$3003,'[1]资金台帐'!$N$4:$N$3003,'首页'!$B$4*100+'首页'!$E$4,'[1]资金台帐'!$M$4:$M$3003,"<>内部转账") -> 0
A8: =IF('[1]基础资料'!$A$6="","",'[1]基础资料'!$A$6) -> 微信 | B8: =IF(A8="","",'[1]基础资料'!$D$6) -> 0 | D8: 资金台帐支出（不含内部转账） | E8: =SUMIFS('[1]资金台帐'!$H$4:$H$3003,'[1]资金台帐'!$N$4:$N$3003,'首页'!$B$4*100+'首页'!$E$4,'[1]资金台帐'!$M$4:$M$3003,"<>内部转账") -> 0
A9: =IF('[1]基础资料'!$A$7="","",'[1]基础资料'!$A$7) -> 支付宝 | B9: =IF(A9="","",'[1]基础资料'!$D$7) -> 0 | D9: 销售收入（管家婆） | E9: =INDEX('利润表'!$C$7:$N$7,'首页'!$E$4) -> 2807123
A10: =IF('[1]基础资料'!$A$8="","",'[1]基础资料'!$A$8) -> 拼多多店铺余额 | B10: =IF(A10="","",'[1]基础资料'!$D$8) -> 61390.86 | C10: 含平台账务明细 | D10: 销售成本 | E10: =INDEX('利润表'!$C$8:$N$8,'首页'!$E$4) -> 2698448.2
A11: =IF('[1]基础资料'!$A$9="","",'[1]基础资料'!$A$9) | B11: =IF(A11="","",'[1]基础资料'!$D$9) | D11: 毛利 | E11: =INDEX('利润表'!$C$9:$N$9,'首页'!$E$4) -> 108674.77
A12: =IF('[1]基础资料'!$A$10="","",'[1]基础资料'!$A$10) | B12: =IF(A12="","",'[1]基础资料'!$D$10) | D12: 净利润（简易） | E12: =INDEX('利润表'!$C$17:$N$17,'首页'!$E$4) -> 114126.63
A13: 合计 | B13: =SUM(B7:B12) -> 161390.86
A15: 拼多多对账提示 | B15: 笔数／单数 | C15: 金额 | D15: 看哪里／怎么处理
A16: 本月店铺净额 跟账务明细「#总计」差 | C16: =INDEX('拼多多对账'!$C$24:$N$24,'首页'!$E$4) -> 0 | D16: 拼多多对账「一」；应为 0
A17: 本月月末店铺余额（期初＋净额） | C17: =INDEX('拼多多对账'!$C$26:$N$26,'首页'!$E$4) -> 61390.86 | D17: 期初在录入本基础资料第 8 行
A18: 本月提现没记进资金台帐的差额 | C18: =INDEX('拼多多对账'!$C$28:$N$28,'首页'!$E$4) -> 0 | D18: 应为 0；提现在资金台帐记内部转账
A19: 到账批次：对账单里没有明细的 | B19: =COUNTIF('拼多多对账'!$J$32:$J$91,"对账单里没有*") -> 6 | C19: =SUMIFS('拼多多对账'!$E$32:$E$91,'拼多多对账'!$J$32:$J$91,"对账单里没有*") -> 3991.59 | D19: 按批次号去后台下载这几批的对账单明细，粘进录入本
A20: 对账单批次：账务明细还没到账的 | B20: =COUNTIF('拼多多对账'!$I$95:$I$134,"账务明细里还没到账*") -> 3 | C20: =SUMIFS('拼多多对账'!$F$95:$F$134,'拼多多对账'!$I$95:$I$134,"账务明细里还没到账*") -> 1320 | D20: 看结算时间，粘那个月的账务明细再看
A21: 营销活动逐单不一致 | B21: ='拼多多对账'!$I$138 -> 0 | D21: 拼多多对账「三」
A22: 百亿补贴技术服务费 扣了还没返 | B22: ='技术服务费核对'!$H$10 -> 40 | C22: ='技术服务费核对'!$H$11 -> 2183.3 | D22: 技术服务费核对「三」；超过 30 天没返问客服
A23: 返还账单里在账务明细找不到这单 | B23: ='技术服务费核对'!$C$10 -> 64 | C23: ='技术服务费核对'!$C$11 -> 4637.2 | D23: 扣费在更早月份，把那个月账务明细也粘上
A24: 返了又扣回（-t01） | B24: ='技术服务费核对'!$C$7 -> 1 | C24: ='技术服务费核对'!$C$8 -> -50.39 | D24: 技术服务费核对「二」，问客服扣回原因
A27: 跳转
A28: → 拼多多对账 | D28: → 打开录入本 A076-1_录入本.xlsx（同一文件夹）
A29: → 技术服务费核对
A30: → 库存
A31: → 往来
A32: → 费用统计
A33: → 利润表
A34: → 使用说明

Sheet 拼多多对账
A1: A076 拼多多对账（店铺余额·批次·营销活动）
A2: 怎么核才准：① 先看「一」每月净额跟账务明细最后一行「#总计」对上没有；② 补贴汇入、技术服务费返还在账务明细里只有一笔总数，备注里有批次号——拿批次号去对账单里找同批次的明细，合计要等于到账金额（「二」）；③ 营销活动逐单：应结＝报名价－活动价＋补贴券（「三」）；④ 技术服务费逐单在「技术服务费核对」表。对账单是按结算时间出的，账务明细是按到账月份出的，月份不一样就会「对不上」，要按批次号对。
A4: 一、按月店铺余额（年份见首页；单位：元，收入正、支出负）
A5: 账务类型 | B5: 利润表归类 | C5: 1 | D5: 2 | E5: 3 | F5: 4 | G5: 5 | H5: 6 | I5: 7 | J5: 8 | K5: 9 | L5: 10 | M5: 11 | N5: 12 | O5: 全年合计
A6: =IF('[1]基础资料'!$B$47="","",'[1]基础资料'!$B$47) -> 订单收入 | B6: =IF(A6="","",'[1]基础资料'!$C$47) -> 店铺回款 | C6: =IF($A6="",0,SUMIFS('[1]粘贴_账务明细'!$K$4:$K$3003,'[1]粘贴_账务明细'!$L$4:$L$3003,$A6,'[1]粘贴_账务明细'!$I$4:$I$3003,'首页'!$B$4*100+C$5)) -> 0 | D6: =IF($A6="",0,SUMIFS('[1]粘贴_账务明细'!$K$4:$K$3003,'[1]粘贴_账务明细'!$L$4:$L$3003,$A6,'[1]粘贴_账务明细'!$I$4:$I$3003,'首页'!$B$4*100+D$5)) -> 0 | E6: =IF($A6="",0,SUMIFS('[1]粘贴_账务明细'!$K$4:$K$3003,'[1]粘贴_账务明细'!$L$4:$L$3003,$A6,'[1]粘贴_账务明细'!$I$4:$I$3003,'首页'!$B$4*100+E$5)) -> 0 | F6: =IF($A6="",0,SUMIFS('[1]粘贴_账务明细'!$K$4:$K$3003,'[1]粘贴_账务明细'!$L$4:$L$3003,$A6,'[1]粘贴_账务明细'!$I$4:$I$3003,'首页'!$B$4*100+F$5)) -> 0 | G6: =IF($A6="",0,SUMIFS('[1]粘贴_账务明细'!$K$4:$K$3003,'[1]粘贴_账务明细'!$L$4:$L$3003,$A6,'[1]粘贴_账务明细'!$I$4:$I$3003,'首页'!$B$4*100+G$5)) -> 0 | H6: =IF($A6="",0,SUMIFS('[1]粘贴_账务明细'!$K$4:$K$3003,'[1]粘贴_账务明细'!$L$4:$L$3003,$A6,'[1]粘贴_账务明细'!$I$4:$I$3003,'首页'!$B$4*100+H$5)) -> 0 | I6: =IF($A6="",0,SUMIFS('[1]粘贴_账务明细'!$K$4:$K$3003,'[1]粘贴_账务明细'!$L$4:$L$3003,$A6,'[1]粘贴_账务明细'!$I$4:$I$3003,'首页'!$B$4*100+I$5)) -> 0 | J6: =IF($A6="",0,SUMIFS('[1]粘贴_账务明细'!$K$4:$K$3003,'[1]粘贴_账务明细'!$L$4:$L$3003,$A6,'[1]粘贴_账务明细'!$I$4:$I$3003,'首页'!$B$4*100+J$5)) -> 0 | ... N6: =IF($A6="",0,SUMIFS('[1]粘贴_账务明细'!$K$4:$K$3003,'[1]粘贴_账务明细'!$L$4:$L$3003,$A6,'[1]粘贴_账务明细'!$I$4:$I$3003,'首页'!$B$4*100+N$5)) -> 0 | O6: =SUM(C6:N6) -> 303943
A7: =IF('[1]基础资料'!$B$48="","",'[1]基础资料'!$B$48) -> 优惠券结算 | B7: =IF(A7="","",'[1]基础资料'!$C$48) -> 店铺回款 | C7: =IF($A7="",0,SUMIFS('[1]粘贴_账务明细'!$K$4:$K$3003,'[1]粘贴_账务明细'!$L$4:$L$3003,$A7,'[1]粘贴_账务明细'!$I$4:$I$3003,'首页'!$B$4*100+C$5)) -> 0 | D7: =IF($A7="",0,SUMIFS('[1]粘贴_账务明细'!$K$4:$K$3003,'[1]粘贴_账务明细'!$L$4:$L$3003,$A7,'[1]粘贴_账务明细'!$I$4:$I$3003,'首页'!$B$4*100+D$5)) -> 0 | E7: =IF($A7="",0,SUMIFS('[1]粘贴_账务明细'!$K$4:$K$3003,'[1]粘贴_账务明细'!$L$4:$L$3003,$A7,'[1]粘贴_账务明细'!$I$4:$I$3003,'首页'!$B$4*100+E$5)) -> 0 | F7: =IF($A7="",0,SUMIFS('[1]粘贴_账务明细'!$K$4:$K$3003,'[1]粘贴_账务明细'!$L$4:$L$3003,$A7,'[1]粘贴_账务明细'!$I$4:$I$3003,'首页'!$B$4*100+F$5)) -> 0 | G7: =IF($A7="",0,SUMIFS('[1]粘贴_账务明细'!$K$4:$K$3003,'[1]粘贴_账务明细'!$L$4:$L$3003,$A7,'[1]粘贴_账务明细'!$I$4:$I$3003,'首页'!$B$4*100+G$5)) -> 0 | H7: =IF($A7="",0,SUMIFS('[1]粘贴_账务明细'!$K$4:$K$3003,'[1]粘贴_账务明细'!$L$4:$L$3003,$A7,'[1]粘贴_账务明细'!$I$4:$I$3003,'首页'!$B$4*100+H$5)) -> 0 | I7: =IF($A7="",0,SUMIFS('[1]粘贴_账务明细'!$K$4:$K$3003,'[1]粘贴_账务明细'!$L$4:$L$3003,$A7,'[1]粘贴_账务明细'!$I$4:$I$3003,'首页'!$B$4*100+I$5)) -> 0 | J7: =IF($A7="",0,SUMIFS('[1]粘贴_账务明细'!$K$4:$K$3003,'[1]粘贴_账务明细'!$L$4:$L$3003,$A7,'[1]粘贴_账务明细'!$I$4:$I$3003,'首页'!$B$4*100+J$5)) -> 0 | ... N7: =IF($A7="",0,SUMIFS('[1]粘贴_账务明细'!$K$4:$K$3003,'[1]粘贴_账务明细'!$L$4:$L$3003,$A7,'[1]粘贴_账务明细'!$I$4:$I$3003,'首页'!$B$4*100+N$5)) -> 0 | O7: =SUM(C7:N7) -> 7172
A8: =IF('[1]基础资料'!$B$49="","",'[1]基础资料'!$B$49) -> 交易退款 | B8: =IF(A8="","",'[1]基础资料'!$C$49) -> 店铺回款 | C8: =IF($A8="",0,SUMIFS('[1]粘贴_账务明细'!$K$4:$K$3003,'[1]粘贴_账务明细'!$L$4:$L$3003,$A8,'[1]粘贴_账务明细'!$I$4:$I$3003,'首页'!$B$4*100+C$5)) -> 0 | D8: =IF($A8="",0,SUMIFS('[1]粘贴_账务明细'!$K$4:$K$3003,'[1]粘贴_账务明细'!$L$4:$L$3003,$A8,'[1]粘贴_账务明细'!$I$4:$I$3003,'首页'!$B$4*100+D$5)) -> 0 | E8: =IF($A8="",0,SUMIFS('[1]粘贴_账务明细'!$K$4:$K$3003,'[1]粘贴_账务明细'!$L$4:$L$3003,$A8,'[1]粘贴_账务明细'!$I$4:$I$3003,'首页'!$B$4*100+E$5)) -> 0 | F8: =IF($A8="",0,SUMIFS('[1]粘贴_账务明细'!$K$4:$K$3003,'[1]粘贴_账务明细'!$L$4:$L$3003,$A8,'[1]粘贴_账务明细'!$I$4:$I$3003,'首页'!$B$4*100+F$5)) -> 0 | G8: =IF($A8="",0,SUMIFS('[1]粘贴_账务明细'!$K$4:$K$3003,'[1]粘贴_账务明细'!$L$4:$L$3003,$A8,'[1]粘贴_账务明细'!$I$4:$I$3003,'首页'!$B$4*100+G$5)) -> 0 | H8: =IF($A8="",0,SUMIFS('[1]粘贴_账务明细'!$K$4:$K$3003,'[1]粘贴_账务明细'!$L$4:$L$3003,$A8,'[1]粘贴_账务明细'!$I$4:$I$3003,'首页'!$B$4*100+H$5)) -> 0 | I8: =IF($A8="",0,SUMIFS('[1]粘贴_账务明细'!$K$4:$K$3003,'[1]粘贴_账务明细'!$L$4:$L$3003,$A8,'[1]粘贴_账务明细'!$I$4:$I$3003,'首页'!$B$4*100+I$5)) -> 0 | J8: =IF($A8="",0,SUMIFS('[1]粘贴_账务明细'!$K$4:$K$3003,'[1]粘贴_账务明细'!$L$4:$L$3003,$A8,'[1]粘贴_账务明细'!$I$4:$I$3003,'首页'!$B$4*100+J$5)) -> 0 | ... N8: =IF($A8="",0,SUMIFS('[1]粘贴_账务明细'!$K$4:$K$3003,'[1]粘贴_账务明细'!$L$4:$L$3003,$A8,'[1]粘贴_账务明细'!$I$4:$I$3003,'首页'!$B$4*100+N$5)) -> 0 | O8: =SUM(C8:N8) -> -151906
A9: =IF('[1]基础资料'!$B$50="","",'[1]基础资料'!$B$50) -> 退款扣优惠券 | B9: =IF(A9="","",'[1]基础资料'!$C$50) -> 店铺回款 | C9: =IF($A9="",0,SUMIFS('[1]粘贴_账务明细'!$K$4:$K$3003,'[1]粘贴_账务明细'!$L$4:$L$3003,$A9,'[1]粘贴_账务明细'!$I$4:$I$3003,'首页'!$B$4*100+C$5)) -> 0 | D9: =IF($A9="",0,SUMIFS('[1]粘贴_账务明细'!$K$4:$K$3003,'[1]粘贴_账务明细'!$L$4:$L$3003,$A9,'[1]粘贴_账务明细'!$I$4:$I$3003,'首页'!$B$4*100+D$5)) -> 0 | E9: =IF($A9="",0,SUMIFS('[1]粘贴_账务明细'!$K$4:$K$3003,'[1]粘贴_账务明细'!$L$4:$L$3003,$A9,'[1]粘贴_账务明细'!$I$4:$I$3003,'首页'!$B$4*100+E$5)) -> 0 | F9: =IF($A9="",0,SUMIFS('[1]粘贴_账务明细'!$K$4:$K$3003,'[1]粘贴_账务明细'!$L$4:$L$3003,$A9,'[1]粘贴_账务明细'!$I$4:$I$3003,'首页'!$B$4*100+F$5)) -> 0 | G9: =IF($A9="",0,SUMIFS('[1]粘贴_账务明细'!$K$4:$K$3003,'[1]粘贴_账务明细'!$L$4:$L$3003,$A9,'[1]粘贴_账务明细'!$I$4:$I$3003,'首页'!$B$4*100+G$5)) -> 0 | H9: =IF($A9="",0,SUMIFS('[1]粘贴_账务明细'!$K$4:$K$3003,'[1]粘贴_账务明细'!$L$4:$L$3003,$A9,'[1]粘贴_账务明细'!$I$4:$I$3003,'首页'!$B$4*100+H$5)) -> 0 | I9: =IF($A9="",0,SUMIFS('[1]粘贴_账务明细'!$K$4:$K$3003,'[1]粘贴_账务明细'!$L$4:$L$3003,$A9,'[1]粘贴_账务明细'!$I$4:$I$3003,'首页'!$B$4*100+I$5)) -> 0 | J9: =IF($A9="",0,SUMIFS('[1]粘贴_账务明细'!$K$4:$K$3003,'[1]粘贴_账务明细'!$L$4:$L$3003,$A9,'[1]粘贴_账务明细'!$I$4:$I$3003,'首页'!$B$4*100+J$5)) -> 0 | ... N9: =IF($A9="",0,SUMIFS('[1]粘贴_账务明细'!$K$4:$K$3003,'[1]粘贴_账务明细'!$L$4:$L$3003,$A9,'[1]粘贴_账务明细'!$I$4:$I$3003,'首页'!$B$4*100+N$5)) -> 0 | O9: =SUM(C9:N9) -> -3270
A10: =IF('[1]基础资料'!$B$51="","",'[1]基础资料'!$B$51) -> 基础技术服务费 | B10: =IF(A10="","",'[1]基础资料'!$C$51) -> 技术服务费 | C10: =IF($A10="",0,SUMIFS('[1]粘贴_账务明细'!$K$4:$K$3003,'[1]粘贴_账务明细'!$L$4:$L$3003,$A10,'[1]粘贴_账务明细'!$I$4:$I$3003,'首页'!$B$4*100+C$5)) -> 0 | D10: =IF($A10="",0,SUMIFS('[1]粘贴_账务明细'!$K$4:$K$3003,'[1]粘贴_账务明细'!$L$4:$L$3003,$A10,'[1]粘贴_账务明细'!$I$4:$I$3003,'首页'!$B$4*100+D$5)) -> 0 | E10: =IF($A10="",0,SUMIFS('[1]粘贴_账务明细'!$K$4:$K$3003,'[1]粘贴_账务明细'!$L$4:$L$3003,$A10,'[1]粘贴_账务明细'!$I$4:$I$3003,'首页'!$B$4*100+E$5)) -> 0 | F10: =IF($A10="",0,SUMIFS('[1]粘贴_账务明细'!$K$4:$K$3003,'[1]粘贴_账务明细'!$L$4:$L$3003,$A10,'[1]粘贴_账务明细'!$I$4:$I$3003,'首页'!$B$4*100+F$5)) -> 0 | G10: =IF($A10="",0,SUMIFS('[1]粘贴_账务明细'!$K$4:$K$3003,'[1]粘贴_账务明细'!$L$4:$L$3003,$A10,'[1]粘贴_账务明细'!$I$4:$I$3003,'首页'!$B$4*100+G$5)) -> 0 | H10: =IF($A10="",0,SUMIFS('[1]粘贴_账务明细'!$K$4:$K$3003,'[1]粘贴_账务明细'!$L$4:$L$3003,$A10,'[1]粘贴_账务明细'!$I$4:$I$3003,'首页'!$B$4*100+H$5)) -> 0 | I10: =IF($A10="",0,SUMIFS('[1]粘贴_账务明细'!$K$4:$K$3003,'[1]粘贴_账务明细'!$L$4:$L$3003,$A10,'[1]粘贴_账务明细'!$I$4:$I$3003,'首页'!$B$4*100+I$5)) -> 0 | J10: =IF($A10="",0,SUMIFS('[1]粘贴_账务明细'!$K$4:$K$3003,'[1]粘贴_账务明细'!$L$4:$L$3003,$A10,'[1]粘贴_账务明细'!$I$4:$I$3003,'首页'!$B$4*100+J$5)) -> 0 | ... N10: =IF($A10="",0,SUMIFS('[1]粘贴_账务明细'!$K$4:$K$3003,'[1]粘贴_账务明细'!$L$4:$L$3003,$A10,'[1]粘贴_账务明细'!$I$4:$I$3003,'首页'!$B$4*100+N$5)) -> 0 | O10: =SUM(C10:N10) -> -956.47
A11: =IF('[1]基础资料'!$B$52="","",'[1]基础资料'!$B$52) -> 百亿补贴技术服务费 | B11: =IF(A11="","",'[1]基础资料'!$C$52) -> 技术服务费 | C11: =IF($A11="",0,SUMIFS('[1]粘贴_账务明细'!$K$4:$K$3003,'[1]粘贴_账务明细'!$L$4:$L$3003,$A11,'[1]粘贴_账务明细'!$I$4:$I$3003,'首页'!$B$4*100+C$5)) -> 0 | D11: =IF($A11="",0,SUMIFS('[1]粘贴_账务明细'!$K$4:$K$3003,'[1]粘贴_账务明细'!$L$4:$L$3003,$A11,'[1]粘贴_账务明细'!$I$4:$I$3003,'首页'!$B$4*100+D$5)) -> 0 | E11: =IF($A11="",0,SUMIFS('[1]粘贴_账务明细'!$K$4:$K$3003,'[1]粘贴_账务明细'!$L$4:$L$3003,$A11,'[1]粘贴_账务明细'!$I$4:$I$3003,'首页'!$B$4*100+E$5)) -> 0 | F11: =IF($A11="",0,SUMIFS('[1]粘贴_账务明细'!$K$4:$K$3003,'[1]粘贴_账务明细'!$L$4:$L$3003,$A11,'[1]粘贴_账务明细'!$I$4:$I$3003,'首页'!$B$4*100+F$5)) -> 0 | G11: =IF($A11="",0,SUMIFS('[1]粘贴_账务明细'!$K$4:$K$3003,'[1]粘贴_账务明细'!$L$4:$L$3003,$A11,'[1]粘贴_账务明细'!$I$4:$I$3003,'首页'!$B$4*100+G$5)) -> 0 | H11: =IF($A11="",0,SUMIFS('[1]粘贴_账务明细'!$K$4:$K$3003,'[1]粘贴_账务明细'!$L$4:$L$3003,$A11,'[1]粘贴_账务明细'!$I$4:$I$3003,'首页'!$B$4*100+H$5)) -> 0 | I11: =IF($A11="",0,SUMIFS('[1]粘贴_账务明细'!$K$4:$K$3003,'[1]粘贴_账务明细'!$L$4:$L$3003,$A11,'[1]粘贴_账务明细'!$I$4:$I$3003,'首页'!$B$4*100+I$5)) -> 0 | J11: =IF($A11="",0,SUMIFS('[1]粘贴_账务明细'!$K$4:$K$3003,'[1]粘贴_账务明细'!$L$4:$L$3003,$A11,'[1]粘贴_账务明细'!$I$4:$I$3003,'首页'!$B$4*100+J$5)) -> 0 | ... N11: =IF($A11="",0,SUMIFS('[1]粘贴_账务明细'!$K$4:$K$3003,'[1]粘贴_账务明细'!$L$4:$L$3003,$A11,'[1]粘贴_账务明细'!$I$4:$I$3003,'首页'!$B$4*100+N$5)) -> 0 | O11: =SUM(C11:N11) -> -2183.3
A12: =IF('[1]基础资料'!$B$53="","",'[1]基础资料'!$B$53) -> 技术服务费返还 | B12: =IF(A12="","",'[1]基础资料'!$C$53) -> 技术服务费 | C12: =IF($A12="",0,SUMIFS('[1]粘贴_账务明细'!$K$4:$K$3003,'[1]粘贴_账务明细'!$L$4:$L$3003,$A12,'[1]粘贴_账务明细'!$I$4:$I$3003,'首页'!$B$4*100+C$5)) -> 0 | D12: =IF($A12="",0,SUMIFS('[1]粘贴_账务明细'!$K$4:$K$3003,'[1]粘贴_账务明细'!$L$4:$L$3003,$A12,'[1]粘贴_账务明细'!$I$4:$I$3003,'首页'!$B$4*100+D$5)) -> 0 | E12: =IF($A12="",0,SUMIFS('[1]粘贴_账务明细'!$K$4:$K$3003,'[1]粘贴_账务明细'!$L$4:$L$3003,$A12,'[1]粘贴_账务明细'!$I$4:$I$3003,'首页'!$B$4*100+E$5)) -> 0 | F12: =IF($A12="",0,SUMIFS('[1]粘贴_账务明细'!$K$4:$K$3003,'[1]粘贴_账务明细'!$L$4:$L$3003,$A12,'[1]粘贴_账务明细'!$I$4:$I$3003,'首页'!$B$4*100+F$5)) -> 0 | G12: =IF($A12="",0,SUMIFS('[1]粘贴_账务明细'!$K$4:$K$3003,'[1]粘贴_账务明细'!$L$4:$L$3003,$A12,'[1]粘贴_账务明细'!$I$4:$I$3003,'首页'!$B$4*100+G$5)) -> 0 | H12: =IF($A12="",0,SUMIFS('[1]粘贴_账务明细'!$K$4:$K$3003,'[1]粘贴_账务明细'!$L$4:$L$3003,$A12,'[1]粘贴_账务明细'!$I$4:$I$3003,'首页'!$B$4*100+H$5)) -> 0 | I12: =IF($A12="",0,SUMIFS('[1]粘贴_账务明细'!$K$4:$K$3003,'[1]粘贴_账务明细'!$L$4:$L$3003,$A12,'[1]粘贴_账务明细'!$I$4:$I$3003,'首页'!$B$4*100+I$5)) -> 0 | J12: =IF($A12="",0,SUMIFS('[1]粘贴_账务明细'!$K$4:$K$3003,'[1]粘贴_账务明细'!$L$4:$L$3003,$A12,'[1]粘贴_账务明细'!$I$4:$I$3003,'首页'!$B$4*100+J$5)) -> 0 | ... N12: =IF($A12="",0,SUMIFS('[1]粘贴_账务明细'!$K$4:$K$3003,'[1]粘贴_账务明细'!$L$4:$L$3003,$A12,'[1]粘贴_账务明细'!$I$4:$I$3003,'首页'!$B$4*100+N$5)) -> 0 | O12: =SUM(C12:N12) -> 4608.4
A13: =IF('[1]基础资料'!$B$54="","",'[1]基础资料'!$B$54) -> 补贴汇入 | B13: =IF(A13="","",'[1]基础资料'!$C$54) -> 平台补贴 | C13: =IF($A13="",0,SUMIFS('[1]粘贴_账务明细'!$K$4:$K$3003,'[1]粘贴_账务明细'!$L$4:$L$3003,$A13,'[1]粘贴_账务明细'!$I$4:$I$3003,'首页'!$B$4*100+C$5)) -> 0 | D13: =IF($A13="",0,SUMIFS('[1]粘贴_账务明细'!$K$4:$K$3003,'[1]粘贴_账务明细'!$L$4:$L$3003,$A13,'[1]粘贴_账务明细'!$I$4:$I$3003,'首页'!$B$4*100+D$5)) -> 0 | E13: =IF($A13="",0,SUMIFS('[1]粘贴_账务明细'!$K$4:$K$3003,'[1]粘贴_账务明细'!$L$4:$L$3003,$A13,'[1]粘贴_账务明细'!$I$4:$I$3003,'首页'!$B$4*100+E$5)) -> 0 | F13: =IF($A13="",0,SUMIFS('[1]粘贴_账务明细'!$K$4:$K$3003,'[1]粘贴_账务明细'!$L$4:$L$3003,$A13,'[1]粘贴_账务明细'!$I$4:$I$3003,'首页'!$B$4*100+F$5)) -> 0 | G13: =IF($A13="",0,SUMIFS('[1]粘贴_账务明细'!$K$4:$K$3003,'[1]粘贴_账务明细'!$L$4:$L$3003,$A13,'[1]粘贴_账务明细'!$I$4:$I$3003,'首页'!$B$4*100+G$5)) -> 0 | H13: =IF($A13="",0,SUMIFS('[1]粘贴_账务明细'!$K$4:$K$3003,'[1]粘贴_账务明细'!$L$4:$L$3003,$A13,'[1]粘贴_账务明细'!$I$4:$I$3003,'首页'!$B$4*100+H$5)) -> 0 | I13: =IF($A13="",0,SUMIFS('[1]粘贴_账务明细'!$K$4:$K$3003,'[1]粘贴_账务明细'!$L$4:$L$3003,$A13,'[1]粘贴_账务明细'!$I$4:$I$3003,'首页'!$B$4*100+I$5)) -> 0 | J13: =IF($A13="",0,SUMIFS('[1]粘贴_账务明细'!$K$4:$K$3003,'[1]粘贴_账务明细'!$L$4:$L$3003,$A13,'[1]粘贴_账务明细'!$I$4:$I$3003,'首页'!$B$4*100+J$5)) -> 0 | ... N13: =IF($A13="",0,SUMIFS('[1]粘贴_账务明细'!$K$4:$K$3003,'[1]粘贴_账务明细'!$L$4:$L$3003,$A13,'[1]粘贴_账务明细'!$I$4:$I$3003,'首页'!$B$4*100+N$5)) -> 0 | O13: =SUM(C13:N13) -> 3970
A14: =IF('[1]基础资料'!$B$55="","",'[1]基础资料'!$B$55) -> 消费者体验提升计划 | B14: =IF(A14="","",'[1]基础资料'!$C$55) -> 体验计划 | C14: =IF($A14="",0,SUMIFS('[1]粘贴_账务明细'!$K$4:$K$3003,'[1]粘贴_账务明细'!$L$4:$L$3003,$A14,'[1]粘贴_账务明细'!$I$4:$I$3003,'首页'!$B$4*100+C$5)) -> 0 | D14: =IF($A14="",0,SUMIFS('[1]粘贴_账务明细'!$K$4:$K$3003,'[1]粘贴_账务明细'!$L$4:$L$3003,$A14,'[1]粘贴_账务明细'!$I$4:$I$3003,'首页'!$B$4*100+D$5)) -> 0 | E14: =IF($A14="",0,SUMIFS('[1]粘贴_账务明细'!$K$4:$K$3003,'[1]粘贴_账务明细'!$L$4:$L$3003,$A14,'[1]粘贴_账务明细'!$I$4:$I$3003,'首页'!$B$4*100+E$5)) -> 0 | F14: =IF($A14="",0,SUMIFS('[1]粘贴_账务明细'!$K$4:$K$3003,'[1]粘贴_账务明细'!$L$4:$L$3003,$A14,'[1]粘贴_账务明细'!$I$4:$I$3003,'首页'!$B$4*100+F$5)) -> 0 | G14: =IF($A14="",0,SUMIFS('[1]粘贴_账务明细'!$K$4:$K$3003,'[1]粘贴_账务明细'!$L$4:$L$3003,$A14,'[1]粘贴_账务明细'!$I$4:$I$3003,'首页'!$B$4*100+G$5)) -> 0 | H14: =IF($A14="",0,SUMIFS('[1]粘贴_账务明细'!$K$4:$K$3003,'[1]粘贴_账务明细'!$L$4:$L$3003,$A14,'[1]粘贴_账务明细'!$I$4:$I$3003,'首页'!$B$4*100+H$5)) -> 0 | I14: =IF($A14="",0,SUMIFS('[1]粘贴_账务明细'!$K$4:$K$3003,'[1]粘贴_账务明细'!$L$4:$L$3003,$A14,'[1]粘贴_账务明细'!$I$4:$I$3003,'首页'!$B$4*100+I$5)) -> 0 | J14: =IF($A14="",0,SUMIFS('[1]粘贴_账务明细'!$K$4:$K$3003,'[1]粘贴_账务明细'!$L$4:$L$3003,$A14,'[1]粘贴_账务明细'!$I$4:$I$3003,'首页'!$B$4*100+J$5)) -> 0 | ... N14: =IF($A14="",0,SUMIFS('[1]粘贴_账务明细'!$K$4:$K$3003,'[1]粘贴_账务明细'!$L$4:$L$3003,$A14,'[1]粘贴_账务明细'!$I$4:$I$3003,'首页'!$B$4*100+N$5)) -> 0 | O14: =SUM(C14:N14) -> -9.77
A15: =IF('[1]基础资料'!$B$56="","",'[1]基础资料'!$B$56) -> 售后补偿 | B15: =IF(A15="","",'[1]基础资料'!$C$56) -> 售后补偿 | C15: =IF($A15="",0,SUMIFS('[1]粘贴_账务明细'!$K$4:$K$3003,'[1]粘贴_账务明细'!$L$4:$L$3003,$A15,'[1]粘贴_账务明细'!$I$4:$I$3003,'首页'!$B$4*100+C$5)) -> 0 | D15: =IF($A15="",0,SUMIFS('[1]粘贴_账务明细'!$K$4:$K$3003,'[1]粘贴_账务明细'!$L$4:$L$3003,$A15,'[1]粘贴_账务明细'!$I$4:$I$3003,'首页'!$B$4*100+D$5)) -> 0 | E15: =IF($A15="",0,SUMIFS('[1]粘贴_账务明细'!$K$4:$K$3003,'[1]粘贴_账务明细'!$L$4:$L$3003,$A15,'[1]粘贴_账务明细'!$I$4:$I$3003,'首页'!$B$4*100+E$5)) -> 0 | F15: =IF($A15="",0,SUMIFS('[1]粘贴_账务明细'!$K$4:$K$3003,'[1]粘贴_账务明细'!$L$4:$L$3003,$A15,'[1]粘贴_账务明细'!$I$4:$I$3003,'首页'!$B$4*100+F$5)) -> 0 | G15: =IF($A15="",0,SUMIFS('[1]粘贴_账务明细'!$K$4:$K$3003,'[1]粘贴_账务明细'!$L$4:$L$3003,$A15,'[1]粘贴_账务明细'!$I$4:$I$3003,'首页'!$B$4*100+G$5)) -> 0 | H15: =IF($A15="",0,SUMIFS('[1]粘贴_账务明细'!$K$4:$K$3003,'[1]粘贴_账务明细'!$L$4:$L$3003,$A15,'[1]粘贴_账务明细'!$I$4:$I$3003,'首页'!$B$4*100+H$5)) -> 0 | I15: =IF($A15="",0,SUMIFS('[1]粘贴_账务明细'!$K$4:$K$3003,'[1]粘贴_账务明细'!$L$4:$L$3003,$A15,'[1]粘贴_账务明细'!$I$4:$I$3003,'首页'!$B$4*100+I$5)) -> 0 | J15: =IF($A15="",0,SUMIFS('[1]粘贴_账务明细'!$K$4:$K$3003,'[1]粘贴_账务明细'!$L$4:$L$3003,$A15,'[1]粘贴_账务明细'!$I$4:$I$3003,'首页'!$B$4*100+J$5)) -> 0 | ... N15: =IF($A15="",0,SUMIFS('[1]粘贴_账务明细'!$K$4:$K$3003,'[1]粘贴_账务明细'!$L$4:$L$3003,$A15,'[1]粘贴_账务明细'!$I$4:$I$3003,'首页'!$B$4*100+N$5)) -> 0 | O15: =SUM(C15:N15) -> -103
A16: =IF('[1]基础资料'!$B$57="","",'[1]基础资料'!$B$57) -> 申诉补回 | B16: =IF(A16="","",'[1]基础资料'!$C$57) -> 售后补偿 | C16: =IF($A16="",0,SUMIFS('[1]粘贴_账务明细'!$K$4:$K$3003,'[1]粘贴_账务明细'!$L$4:$L$3003,$A16,'[1]粘贴_账务明细'!$I$4:$I$3003,'首页'!$B$4*100+C$5)) -> 0 | D16: =IF($A16="",0,SUMIFS('[1]粘贴_账务明细'!$K$4:$K$3003,'[1]粘贴_账务明细'!$L$4:$L$3003,$A16,'[1]粘贴_账务明细'!$I$4:$I$3003,'首页'!$B$4*100+D$5)) -> 0 | E16: =IF($A16="",0,SUMIFS('[1]粘贴_账务明细'!$K$4:$K$3003,'[1]粘贴_账务明细'!$L$4:$L$3003,$A16,'[1]粘贴_账务明细'!$I$4:$I$3003,'首页'!$B$4*100+E$5)) -> 0 | F16: =IF($A16="",0,SUMIFS('[1]粘贴_账务明细'!$K$4:$K$3003,'[1]粘贴_账务明细'!$L$4:$L$3003,$A16,'[1]粘贴_账务明细'!$I$4:$I$3003,'首页'!$B$4*100+F$5)) -> 0 | G16: =IF($A16="",0,SUMIFS('[1]粘贴_账务明细'!$K$4:$K$3003,'[1]粘贴_账务明细'!$L$4:$L$3003,$A16,'[1]粘贴_账务明细'!$I$4:$I$3003,'首页'!$B$4*100+G$5)) -> 0 | H16: =IF($A16="",0,SUMIFS('[1]粘贴_账务明细'!$K$4:$K$3003,'[1]粘贴_账务明细'!$L$4:$L$3003,$A16,'[1]粘贴_账务明细'!$I$4:$I$3003,'首页'!$B$4*100+H$5)) -> 0 | I16: =IF($A16="",0,SUMIFS('[1]粘贴_账务明细'!$K$4:$K$3003,'[1]粘贴_账务明细'!$L$4:$L$3003,$A16,'[1]粘贴_账务明细'!$I$4:$I$3003,'首页'!$B$4*100+I$5)) -> 0 | J16: =IF($A16="",0,SUMIFS('[1]粘贴_账务明细'!$K$4:$K$3003,'[1]粘贴_账务明细'!$L$4:$L$3003,$A16,'[1]粘贴_账务明细'!$I$4:$I$3003,'首页'!$B$4*100+J$5)) -> 0 | ... N16: =IF($A16="",0,SUMIFS('[1]粘贴_账务明细'!$K$4:$K$3003,'[1]粘贴_账务明细'!$L$4:$L$3003,$A16,'[1]粘贴_账务明细'!$I$4:$I$3003,'首页'!$B$4*100+N$5)) -> 0 | O16: =SUM(C16:N16) -> 126
A17: =IF('[1]基础资料'!$B$58="","",'[1]基础资料'!$B$58) -> 提现 | B17: =IF(A17="","",'[1]基础资料'!$C$58) -> 提现 | C17: =IF($A17="",0,SUMIFS('[1]粘贴_账务明细'!$K$4:$K$3003,'[1]粘贴_账务明细'!$L$4:$L$3003,$A17,'[1]粘贴_账务明细'!$I$4:$I$3003,'首页'!$B$4*100+C$5)) -> 0 | D17: =IF($A17="",0,SUMIFS('[1]粘贴_账务明细'!$K$4:$K$3003,'[1]粘贴_账务明细'!$L$4:$L$3003,$A17,'[1]粘贴_账务明细'!$I$4:$I$3003,'首页'!$B$4*100+D$5)) -> 0 | E17: =IF($A17="",0,SUMIFS('[1]粘贴_账务明细'!$K$4:$K$3003,'[1]粘贴_账务明细'!$L$4:$L$3003,$A17,'[1]粘贴_账务明细'!$I$4:$I$3003,'首页'!$B$4*100+E$5)) -> 0 | F17: =IF($A17="",0,SUMIFS('[1]粘贴_账务明细'!$K$4:$K$3003,'[1]粘贴_账务明细'!$L$4:$L$3003,$A17,'[1]粘贴_账务明细'!$I$4:$I$3003,'首页'!$B$4*100+F$5)) -> 0 | G17: =IF($A17="",0,SUMIFS('[1]粘贴_账务明细'!$K$4:$K$3003,'[1]粘贴_账务明细'!$L$4:$L$3003,$A17,'[1]粘贴_账务明细'!$I$4:$I$3003,'首页'!$B$4*100+G$5)) -> 0 | H17: =IF($A17="",0,SUMIFS('[1]粘贴_账务明细'!$K$4:$K$3003,'[1]粘贴_账务明细'!$L$4:$L$3003,$A17,'[1]粘贴_账务明细'!$I$4:$I$3003,'首页'!$B$4*100+H$5)) -> 0 | I17: =IF($A17="",0,SUMIFS('[1]粘贴_账务明细'!$K$4:$K$3003,'[1]粘贴_账务明细'!$L$4:$L$3003,$A17,'[1]粘贴_账务明细'!$I$4:$I$3003,'首页'!$B$4*100+I$5)) -> 0 | J17: =IF($A17="",0,SUMIFS('[1]粘贴_账务明细'!$K$4:$K$3003,'[1]粘贴_账务明细'!$L$4:$L$3003,$A17,'[1]粘贴_账务明细'!$I$4:$I$3003,'首页'!$B$4*100+J$5)) -> 0 | ... N17: =IF($A17="",0,SUMIFS('[1]粘贴_账务明细'!$K$4:$K$3003,'[1]粘贴_账务明细'!$L$4:$L$3003,$A17,'[1]粘贴_账务明细'!$I$4:$I$3003,'首页'!$B$4*100+N$5)) -> 0 | O17: =SUM(C17:N17) -> -100000
A18: =IF('[1]基础资料'!$B$59="","",'[1]基础资料'!$B$59) | B18: =IF(A18="","",'[1]基础资料'!$C$59) | C18: =IF($A18="",0,SUMIFS('[1]粘贴_账务明细'!$K$4:$K$3003,'[1]粘贴_账务明细'!$L$4:$L$3003,$A18,'[1]粘贴_账务明细'!$I$4:$I$3003,'首页'!$B$4*100+C$5)) -> 0 | D18: =IF($A18="",0,SUMIFS('[1]粘贴_账务明细'!$K$4:$K$3003,'[1]粘贴_账务明细'!$L$4:$L$3003,$A18,'[1]粘贴_账务明细'!$I$4:$I$3003,'首页'!$B$4*100+D$5)) -> 0 | E18: =IF($A18="",0,SUMIFS('[1]粘贴_账务明细'!$K$4:$K$3003,'[1]粘贴_账务明细'!$L$4:$L$3003,$A18,'[1]粘贴_账务明细'!$I$4:$I$3003,'首页'!$B$4*100+E$5)) -> 0 | F18: =IF($A18="",0,SUMIFS('[1]粘贴_账务明细'!$K$4:$K$3003,'[1]粘贴_账务明细'!$L$4:$L$3003,$A18,'[1]粘贴_账务明细'!$I$4:$I$3003,'首页'!$B$4*100+F$5)) -> 0 | G18: =IF($A18="",0,SUMIFS('[1]粘贴_账务明细'!$K$4:$K$3003,'[1]粘贴_账务明细'!$L$4:$L$3003,$A18,'[1]粘贴_账务明细'!$I$4:$I$3003,'首页'!$B$4*100+G$5)) -> 0 | H18: =IF($A18="",0,SUMIFS('[1]粘贴_账务明细'!$K$4:$K$3003,'[1]粘贴_账务明细'!$L$4:$L$3003,$A18,'[1]粘贴_账务明细'!$I$4:$I$3003,'首页'!$B$4*100+H$5)) -> 0 | I18: =IF($A18="",0,SUMIFS('[1]粘贴_账务明细'!$K$4:$K$3003,'[1]粘贴_账务明细'!$L$4:$L$3003,$A18,'[1]粘贴_账务明细'!$I$4:$I$3003,'首页'!$B$4*100+I$5)) -> 0 | J18: =IF($A18="",0,SUMIFS('[1]粘贴_账务明细'!$K$4:$K$3003,'[1]粘贴_账务明细'!$L$4:$L$3003,$A18,'[1]粘贴_账务明细'!$I$4:$I$3003,'首页'!$B$4*100+J$5)) -> 0 | ... N18: =IF($A18="",0,SUMIFS('[1]粘贴_账务明细'!$K$4:$K$3003,'[1]粘贴_账务明细'!$L$4:$L$3003,$A18,'[1]粘贴_账务明细'!$I$4:$I$3003,'首页'!$B$4*100+N$5)) -> 0 | O18: =SUM(C18:N18) -> 0
A19: =IF('[1]基础资料'!$B$60="","",'[1]基础资料'!$B$60) | B19: =IF(A19="","",'[1]基础资料'!$C$60) | C19: =IF($A19="",0,SUMIFS('[1]粘贴_账务明细'!$K$4:$K$3003,'[1]粘贴_账务明细'!$L$4:$L$3003,$A19,'[1]粘贴_账务明细'!$I$4:$I$3003,'首页'!$B$4*100+C$5)) -> 0 | D19: =IF($A19="",0,SUMIFS('[1]粘贴_账务明细'!$K$4:$K$3003,'[1]粘贴_账务明细'!$L$4:$L$3003,$A19,'[1]粘贴_账务明细'!$I$4:$I$3003,'首页'!$B$4*100+D$5)) -> 0 | E19: =IF($A19="",0,SUMIFS('[1]粘贴_账务明细'!$K$4:$K$3003,'[1]粘贴_账务明细'!$L$4:$L$3003,$A19,'[1]粘贴_账务明细'!$I$4:$I$3003,'首页'!$B$4*100+E$5)) -> 0 | F19: =IF($A19="",0,SUMIFS('[1]粘贴_账务明细'!$K$4:$K$3003,'[1]粘贴_账务明细'!$L$4:$L$3003,$A19,'[1]粘贴_账务明细'!$I$4:$I$3003,'首页'!$B$4*100+F$5)) -> 0 | G19: =IF($A19="",0,SUMIFS('[1]粘贴_账务明细'!$K$4:$K$3003,'[1]粘贴_账务明细'!$L$4:$L$3003,$A19,'[1]粘贴_账务明细'!$I$4:$I$3003,'首页'!$B$4*100+G$5)) -> 0 | H19: =IF($A19="",0,SUMIFS('[1]粘贴_账务明细'!$K$4:$K$3003,'[1]粘贴_账务明细'!$L$4:$L$3003,$A19,'[1]粘贴_账务明细'!$I$4:$I$3003,'首页'!$B$4*100+H$5)) -> 0 | I19: =IF($A19="",0,SUMIFS('[1]粘贴_账务明细'!$K$4:$K$3003,'[1]粘贴_账务明细'!$L$4:$L$3003,$A19,'[1]粘贴_账务明细'!$I$4:$I$3003,'首页'!$B$4*100+I$5)) -> 0 | J19: =IF($A19="",0,SUMIFS('[1]粘贴_账务明细'!$K$4:$K$3003,'[1]粘贴_账务明细'!$L$4:$L$3003,$A19,'[1]粘贴_账务明细'!$I$4:$I$3003,'首页'!$B$4*100+J$5)) -> 0 | ... N19: =IF($A19="",0,SUMIFS('[1]粘贴_账务明细'!$K$4:$K$3003,'[1]粘贴_账务明细'!$L$4:$L$3003,$A19,'[1]粘贴_账务明细'!$I$4:$I$3003,'首页'!$B$4*100+N$5)) -> 0 | O19: =SUM(C19:N19) -> 0
A20: =IF('[1]基础资料'!$B$61="","",'[1]基础资料'!$B$61) | B20: =IF(A20="","",'[1]基础资料'!$C$61) | C20: =IF($A20="",0,SUMIFS('[1]粘贴_账务明细'!$K$4:$K$3003,'[1]粘贴_账务明细'!$L$4:$L$3003,$A20,'[1]粘贴_账务明细'!$I$4:$I$3003,'首页'!$B$4*100+C$5)) -> 0 | D20: =IF($A20="",0,SUMIFS('[1]粘贴_账务明细'!$K$4:$K$3003,'[1]粘贴_账务明细'!$L$4:$L$3003,$A20,'[1]粘贴_账务明细'!$I$4:$I$3003,'首页'!$B$4*100+D$5)) -> 0 | E20: =IF($A20="",0,SUMIFS('[1]粘贴_账务明细'!$K$4:$K$3003,'[1]粘贴_账务明细'!$L$4:$L$3003,$A20,'[1]粘贴_账务明细'!$I$4:$I$3003,'首页'!$B$4*100+E$5)) -> 0 | F20: =IF($A20="",0,SUMIFS('[1]粘贴_账务明细'!$K$4:$K$3003,'[1]粘贴_账务明细'!$L$4:$L$3003,$A20,'[1]粘贴_账务明细'!$I$4:$I$3003,'首页'!$B$4*100+F$5)) -> 0 | G20: =IF($A20="",0,SUMIFS('[1]粘贴_账务明细'!$K$4:$K$3003,'[1]粘贴_账务明细'!$L$4:$L$3003,$A20,'[1]粘贴_账务明细'!$I$4:$I$3003,'首页'!$B$4*100+G$5)) -> 0 | H20: =IF($A20="",0,SUMIFS('[1]粘贴_账务明细'!$K$4:$K$3003,'[1]粘贴_账务明细'!$L$4:$L$3003,$A20,'[1]粘贴_账务明细'!$I$4:$I$3003,'首页'!$B$4*100+H$5)) -> 0 | I20: =IF($A20="",0,SUMIFS('[1]粘贴_账务明细'!$K$4:$K$3003,'[1]粘贴_账务明细'!$L$4:$L$3003,$A20,'[1]粘贴_账务明细'!$I$4:$I$3003,'首页'!$B$4*100+I$5)) -> 0 | J20: =IF($A20="",0,SUMIFS('[1]粘贴_账务明细'!$K$4:$K$3003,'[1]粘贴_账务明细'!$L$4:$L$3003,$A20,'[1]粘贴_账务明细'!$I$4:$I$3003,'首页'!$B$4*100+J$5)) -> 0 | ... N20: =IF($A20="",0,SUMIFS('[1]粘贴_账务明细'!$K$4:$K$3003,'[1]粘贴_账务明细'!$L$4:$L$3003,$A20,'[1]粘贴_账务明细'!$I$4:$I$3003,'首页'!$B$4*100+N$5)) -> 0 | O20: =SUM(C20:N20) -> 0
A21: 其他未归类 | B21: 其他费用 | C21: =IF($A21="",0,SUMIFS('[1]粘贴_账务明细'!$K$4:$K$3003,'[1]粘贴_账务明细'!$L$4:$L$3003,$A21,'[1]粘贴_账务明细'!$I$4:$I$3003,'首页'!$B$4*100+C$5)) -> 0 | D21: =IF($A21="",0,SUMIFS('[1]粘贴_账务明细'!$K$4:$K$3003,'[1]粘贴_账务明细'!$L$4:$L$3003,$A21,'[1]粘贴_账务明细'!$I$4:$I$3003,'首页'!$B$4*100+D$5)) -> 0 | E21: =IF($A21="",0,SUMIFS('[1]粘贴_账务明细'!$K$4:$K$3003,'[1]粘贴_账务明细'!$L$4:$L$3003,$A21,'[1]粘贴_账务明细'!$I$4:$I$3003,'首页'!$B$4*100+E$5)) -> 0 | F21: =IF($A21="",0,SUMIFS('[1]粘贴_账务明细'!$K$4:$K$3003,'[1]粘贴_账务明细'!$L$4:$L$3003,$A21,'[1]粘贴_账务明细'!$I$4:$I$3003,'首页'!$B$4*100+F$5)) -> 0 | G21: =IF($A21="",0,SUMIFS('[1]粘贴_账务明细'!$K$4:$K$3003,'[1]粘贴_账务明细'!$L$4:$L$3003,$A21,'[1]粘贴_账务明细'!$I$4:$I$3003,'首页'!$B$4*100+G$5)) -> 0 | H21: =IF($A21="",0,SUMIFS('[1]粘贴_账务明细'!$K$4:$K$3003,'[1]粘贴_账务明细'!$L$4:$L$3003,$A21,'[1]粘贴_账务明细'!$I$4:$I$3003,'首页'!$B$4*100+H$5)) -> 0 | I21: =IF($A21="",0,SUMIFS('[1]粘贴_账务明细'!$K$4:$K$3003,'[1]粘贴_账务明细'!$L$4:$L$3003,$A21,'[1]粘贴_账务明细'!$I$4:$I$3003,'首页'!$B$4*100+I$5)) -> 0 | J21: =IF($A21="",0,SUMIFS('[1]粘贴_账务明细'!$K$4:$K$3003,'[1]粘贴_账务明细'!$L$4:$L$3003,$A21,'[1]粘贴_账务明细'!$I$4:$I$3003,'首页'!$B$4*100+J$5)) -> 0 | ... N21: =IF($A21="",0,SUMIFS('[1]粘贴_账务明细'!$K$4:$K$3003,'[1]粘贴_账务明细'!$L$4:$L$3003,$A21,'[1]粘贴_账务明细'!$I$4:$I$3003,'首页'!$B$4*100+N$5)) -> 0 | O21: =SUM(C21:N21) -> 0
A22: 本月净额（上面合计） | C22: =SUM(C6:C21) -> 0 | D22: =SUM(D6:D21) -> 0 | E22: =SUM(E6:E21) -> 0 | F22: =SUM(F6:F21) -> 0 | G22: =SUM(G6:G21) -> 0 | H22: =SUM(H6:H21) -> 0 | I22: =SUM(I6:I21) -> 0 | J22: =SUM(J6:J21) -> 0 | ... N22: =SUM(N6:N21) -> 0 | O22: =SUM(C22:N22) -> 61390.86
A23: 账务明细「#总计」 | C23: =IF(COUNTIFS('[1]粘贴_账务明细'!$J$4:$J$3003,">-9E+99",'[1]粘贴_账务明细'!$I$4:$I$3003,'首页'!$B$4*100+C$5)=0,"",SUMIFS('[1]粘贴_账务明细'!$J$4:$J$3003,'[1]粘贴_账务明细'!$I$4:$I$3003,'首页'!$B$4*100+C$5)) | D23: =IF(COUNTIFS('[1]粘贴_账务明细'!$J$4:$J$3003,">-9E+99",'[1]粘贴_账务明细'!$I$4:$I$3003,'首页'!$B$4*100+D$5)=0,"",SUMIFS('[1]粘贴_账务明细'!$J$4:$J$3003,'[1]粘贴_账务明细'!$I$4:$I$3003,'首页'!$B$4*100+D$5)) | E23: =IF(COUNTIFS('[1]粘贴_账务明细'!$J$4:$J$3003,">-9E+99",'[1]粘贴_账务明细'!$I$4:$I$3003,'首页'!$B$4*100+E$5)=0,"",SUMIFS('[1]粘贴_账务明细'!$J$4:$J$3003,'[1]粘贴_账务明细'!$I$4:$I$3003,'首页'!$B$4*100+E$5)) | F23: =IF(COUNTIFS('[1]粘贴_账务明细'!$J$4:$J$3003,">-9E+99",'[1]粘贴_账务明细'!$I$4:$I$3003,'首页'!$B$4*100+F$5)=0,"",SUMIFS('[1]粘贴_账务明细'!$J$4:$J$3003,'[1]粘贴_账务明细'!$I$4:$I$3003,'首页'!$B$4*100+F$5)) | G23: =IF(COUNTIFS('[1]粘贴_账务明细'!$J$4:$J$3003,">-9E+99",'[1]粘贴_账务明细'!$I$4:$I$3003,'首页'!$B$4*100+G$5)=0,"",SUMIFS('[1]粘贴_账务明细'!$J$4:$J$3003,'[1]粘贴_账务明细'!$I$4:$I$3003,'首页'!$B$4*100+G$5)) | H23: =IF(COUNTIFS('[1]粘贴_账务明细'!$J$4:$J$3003,">-9E+99",'[1]粘贴_账务明细'!$I$4:$I$3003,'首页'!$B$4*100+H$5)=0,"",SUMIFS('[1]粘贴_账务明细'!$J$4:$J$3003,'[1]粘贴_账务明细'!$I$4:$I$3003,'首页'!$B$4*100+H$5)) | I23: =IF(COUNTIFS('[1]粘贴_账务明细'!$J$4:$J$3003,">-9E+99",'[1]粘贴_账务明细'!$I$4:$I$3003,'首页'!$B$4*100+I$5)=0,"",SUMIFS('[1]粘贴_账务明细'!$J$4:$J$3003,'[1]粘贴_账务明细'!$I$4:$I$3003,'首页'!$B$4*100+I$5)) | J23: =IF(COUNTIFS('[1]粘贴_账务明细'!$J$4:$J$3003,">-9E+99",'[1]粘贴_账务明细'!$I$4:$I$3003,'首页'!$B$4*100+J$5)=0,"",SUMIFS('[1]粘贴_账务明细'!$J$4:$J$3003,'[1]粘贴_账务明细'!$I$4:$I$3003,'首页'!$B$4*100+J$5)) | ... N23: =IF(COUNTIFS('[1]粘贴_账务明细'!$J$4:$J$3003,">-9E+99",'[1]粘贴_账务明细'!$I$4:$I$3003,'首页'!$B$4*100+N$5)=0,"",SUMIFS('[1]粘贴_账务明细'!$J$4:$J$3003,'[1]粘贴_账务明细'!$I$4:$I$3003,'首页'!$B$4*100+N$5))
A24: 差异（应为 0） | C24: =IF(C23="","没粘#总计",ROUND(C22-C23,2)) -> 没粘#总计 | D24: =IF(D23="","没粘#总计",ROUND(D22-D23,2)) -> 没粘#总计 | E24: =IF(E23="","没粘#总计",ROUND(E22-E23,2)) -> 没粘#总计 | F24: =IF(F23="","没粘#总计",ROUND(F22-F23,2)) -> 没粘#总计 | G24: =IF(G23="","没粘#总计",ROUND(G22-G23,2)) -> 没粘#总计 | H24: =IF(H23="","没粘#总计",ROUND(H22-H23,2)) -> 没粘#总计 | I24: =IF(I23="","没粘#总计",ROUND(I22-I23,2)) -> 没粘#总计 | J24: =IF(J23="","没粘#总计",ROUND(J22-J23,2)) -> 没粘#总计 | ... N24: =IF(N23="","没粘#总计",ROUND(N22-N23,2)) -> 没粘#总计
A25: 月初店铺余额 | C25: =N('[1]基础资料'!$C$8) -> 0 | D25: =C26 -> 0 | E25: =D26 -> 0 | F25: =E26 -> 0 | G25: =F26 -> 0 | H25: =G26 -> 0 | I25: =H26 -> 0 | J25: =I26 -> 0 | K25: =J26 -> 0 | ... N25: =M26 -> 61390.86
A26: 月末店铺余额 | C26: =C25+C22 -> 0 | D26: =D25+D22 -> 0 | E26: =E25+E22 -> 0 | F26: =F25+F22 -> 0 | G26: =G25+G22 -> 0 | H26: =H25+H22 -> 0 | I26: =I25+I22 -> 0 | J26: =J25+J22 -> 0 | ... N26: =N25+N22 -> 61390.86
A27: 资金台帐记的提现 | C27: =SUMIFS('[1]资金台帐'!$H$4:$H$3003,'[1]资金台帐'!$B$4:$B$3003,'[1]基础资料'!$A$8,'[1]资金台帐'!$M$4:$M$3003,"内部转账",'[1]资金台帐'!$N$4:$N$3003,'首页'!$B$4*100+C$5)-SUMIFS('[1]资金台帐'!$G$4:$G$3003,'[1]资金台帐'!$B$4:$B$3003,'[1]基础资料'!$A$8,'[1]资金台帐'!$M$4:$M$3003,"内部转账",'[1]资金台帐'!$N$4:$N$3003,'首页'!$B$4*100+C$5)+SUMIFS('[1]资金台帐'!$G$4:$G$3003,'[1]资金台帐'!$I$4:$I$3003,'[1]基础资料'!$A$8,'[1]资金台帐'!$M$4:$M$3003,"内部转账",'[1]资金台帐'!$N$4:$N$3003,'首页'!$B$4*100+C$5)-SUMIFS('[1]资金台帐'!$H$4:$H$3003,'[1]资金台帐'!$I$4:$I$3003,'[1]基础资料'!$A$8,'[1]资金台帐'!$M$4:$M$3003,"内部转账",'[1]资金台帐'!$N$4:$N$3003,'首页'!$B$4*100+C$5) -> 0 | D27: =SUMIFS('[1]资金台帐'!$H$4:$H$3003,'[1]资金台帐'!$B$4:$B$3003,'[1]基础资料'!$A$8,'[1]资金台帐'!$M$4:$M$3003,"内部转账",'[1]资金台帐'!$N$4:$N$3003,'首页'!$B$4*100+D$5)-SUMIFS('[1]资金台帐'!$G$4:$G$3003,'[1]资金台帐'!$B$4:$B$3003,'[1]基础资料'!$A$8,'[1]资金台帐'!$M$4:$M$3003,"内部转账",'[1]资金台帐'!$N$4:$N$3003,'首页'!$B$4*100+D$5)+SUMIFS('[1]资金台帐'!$G$4:$G$3003,'[1]资金台帐'!$I$4:$I$3003,'[1]基础资料'!$A$8,'[1]资金台帐'!$M$4:$M$3003,"内部转账",'[1]资金台帐'!$N$4:$N$3003,'首页'!$B$4*100+D$5)-SUMIFS('[1]资金台帐'!$H$4:$H$3003,'[1]资金台帐'!$I$4:$I$3003,'[1]基础资料'!$A$8,'[1]资金台帐'!$M$4:$M$3003,"内部转账",'[1]资金台帐'!$N$4:$N$3003,'首页'!$B$4*100+D$5) -> 0 | E27: =SUMIFS('[1]资金台帐'!$H$4:$H$3003,'[1]资金台帐'!$B$4:$B$3003,'[1]基础资料'!$A$8,'[1]资金台帐'!$M$4:$M$3003,"内部转账",'[1]资金台帐'!$N$4:$N$3003,'首页'!$B$4*100+E$5)-SUMIFS('[1]资金台帐'!$G$4:$G$3003,'[1]资金台帐'!$B$4:$B$3003,'[1]基础资料'!$A$8,'[1]资金台帐'!$M$4:$M$3003,"内部转账",'[1]资金台帐'!$N$4:$N$3003,'首页'!$B$4*100+E$5)+SUMIFS('[1]资金台帐'!$G$4:$G$3003,'[1]资金台帐'!$I$4:$I$3003,'[1]基础资料'!$A$8,'[1]资金台帐'!$M$4:$M$3003,"内部转账",'[1]资金台帐'!$N$4:$N$3003,'首页'!$B$4*100+E$5)-SUMIFS('[1]资金台帐'!$H$4:$H$3003,'[1]资金台帐'!$I$4:$I$3003,'[1]基础资料'!$A$8,'[1]资金台帐'!$M$4:$M$3003,"内部转账",'[1]资金台帐'!$N$4:$N$3003,'首页'!$B$4*100+E$5) -> 0 | F27: =SUMIFS('[1]资金台帐'!$H$4:$H$3003,'[1]资金台帐'!$B$4:$B$3003,'[1]基础资料'!$A$8,'[1]资金台帐'!$M$4:$M$3003,"内部转账",'[1]资金台帐'!$N$4:$N$3003,'首页'!$B$4*100+F$5)-SUMIFS('[1]资金台帐'!$G$4:$G$3003,'[1]资金台帐'!$B$4:$B$3003,'[1]基础资料'!$A$8,'[1]资金台帐'!$M$4:$M$3003,"内部转账",'[1]资金台帐'!$N$4:$N$3003,'首页'!$B$4*100+F$5)+SUMIFS('[1]资金台帐'!$G$4:$G$3003,'[1]资金台帐'!$I$4:$I$3003,'[1]基础资料'!$A$8,'[1]资金台帐'!$M$4:$M$3003,"内部转账",'[1]资金台帐'!$N$4:$N$3003,'首页'!$B$4*100+F$5)-SUMIFS('[1]资金台帐'!$H$4:$H$3003,'[1]资金台帐'!$I$4:$I$3003,'[1]基础资料'!$A$8,'[1]资金台帐'!$M$4:$M$3003,"内部转账",'[1]资金台帐'!$N$4:$N$3003,'首页'!$B$4*100+F$5) -> 0 | G27: =SUMIFS('[1]资金台帐'!$H$4:$H$3003,'[1]资金台帐'!$B$4:$B$3003,'[1]基础资料'!$A$8,'[1]资金台帐'!$M$4:$M$3003,"内部转账",'[1]资金台帐'!$N$4:$N$3003,'首页'!$B$4*100+G$5)-SUMIFS('[1]资金台帐'!$G$4:$G$3003,'[1]资金台帐'!$B$4:$B$3003,'[1]基础资料'!$A$8,'[1]资金台帐'!$M$4:$M$3003,"内部转账",'[1]资金台帐'!$N$4:$N$3003,'首页'!$B$4*100+G$5)+SUMIFS('[1]资金台帐'!$G$4:$G$3003,'[1]资金台帐'!$I$4:$I$3003,'[1]基础资料'!$A$8,'[1]资金台帐'!$M$4:$M$3003,"内部转账",'[1]资金台帐'!$N$4:$N$3003,'首页'!$B$4*100+G$5)-SUMIFS('[1]资金台帐'!$H$4:$H$3003,'[1]资金台帐'!$I$4:$I$3003,'[1]基础资料'!$A$8,'[1]资金台帐'!$M$4:$M$3003,"内部转账",'[1]资金台帐'!$N$4:$N$3003,'首页'!$B$4*100+G$5) -> 0 | H27: =SUMIFS('[1]资金台帐'!$H$4:$H$3003,'[1]资金台帐'!$B$4:$B$3003,'[1]基础资料'!$A$8,'[1]资金台帐'!$M$4:$M$3003,"内部转账",'[1]资金台帐'!$N$4:$N$3003,'首页'!$B$4*100+H$5)-SUMIFS('[1]资金台帐'!$G$4:$G$3003,'[1]资金台帐'!$B$4:$B$3003,'[1]基础资料'!$A$8,'[1]资金台帐'!$M$4:$M$3003,"内部转账",'[1]资金台帐'!$N$4:$N$3003,'首页'!$B$4*100+H$5)+SUMIFS('[1]资金台帐'!$G$4:$G$3003,'[1]资金台帐'!$I$4:$I$3003,'[1]基础资料'!$A$8,'[1]资金台帐'!$M$4:$M$3003,"内部转账",'[1]资金台帐'!$N$4:$N$3003,'首页'!$B$4*100+H$5)-SUMIFS('[1]资金台帐'!$H$4:$H$3003,'[1]资金台帐'!$I$4:$I$3003,'[1]基础资料'!$A$8,'[1]资金台帐'!$M$4:$M$3003,"内部转账",'[1]资金台帐'!$N$4:$N$3003,'首页'!$B$4*100+H$5) -> 0 | I27: =SUMIFS('[1]资金台帐'!$H$4:$H$3003,'[1]资金台帐'!$B$4:$B$3003,'[1]基础资料'!$A$8,'[1]资金台帐'!$M$4:$M$3003,"内部转账",'[1]资金台帐'!$N$4:$N$3003,'首页'!$B$4*100+I$5)-SUMIFS('[1]资金台帐'!$G$4:$G$3003,'[1]资金台帐'!$B$4:$B$3003,'[1]基础资料'!$A$8,'[1]资金台帐'!$M$4:$M$3003,"内部转账",'[1]资金台帐'!$N$4:$N$3003,'首页'!$B$4*100+I$5)+SUMIFS('[1]资金台帐'!$G$4:$G$3003,'[1]资金台帐'!$I$4:$I$3003,'[1]基础资料'!$A$8,'[1]资金台帐'!$M$4:$M$3003,"内部转账",'[1]资金台帐'!$N$4:$N$3003,'首页'!$B$4*100+I$5)-SUMIFS('[1]资金台帐'!$H$4:$H$3003,'[1]资金台帐'!$I$4:$I$3003,'[1]基础资料'!$A$8,'[1]资金台帐'!$M$4:$M$3003,"内部转账",'[1]资金台帐'!$N$4:$N$3003,'首页'!$B$4*100+I$5) -> 0 | J27: =SUMIFS('[1]资金台帐'!$H$4:$H$3003,'[1]资金台帐'!$B$4:$B$3003,'[1]基础资料'!$A$8,'[1]资金台帐'!$M$4:$M$3003,"内部转账",'[1]资金台帐'!$N$4:$N$3003,'首页'!$B$4*100+J$5)-SUMIFS('[1]资金台帐'!$G$4:$G$3003,'[1]资金台帐'!$B$4:$B$3003,'[1]基础资料'!$A$8,'[1]资金台帐'!$M$4:$M$3003,"内部转账",'[1]资金台帐'!$N$4:$N$3003,'首页'!$B$4*100+J$5)+SUMIFS('[1]资金台帐'!$G$4:$G$3003,'[1]资金台帐'!$I$4:$I$3003,'[1]基础资料'!$A$8,'[1]资金台帐'!$M$4:$M$3003,"内部转账",'[1]资金台帐'!$N$4:$N$3003,'首页'!$B$4*100+J$5)-SUMIFS('[1]资金台帐'!$H$4:$H$3003,'[1]资金台帐'!$I$4:$I$3003,'[1]基础资料'!$A$8,'[1]资金台帐'!$M$4:$M$3003,"内部转账",'[1]资金台帐'!$N$4:$N$3003,'首页'!$B$4*100+J$5) -> 0 | ... N27: =SUMIFS('[1]资金台帐'!$H$4:$H$3003,'[1]资金台帐'!$B$4:$B$3003,'[1]基础资料'!$A$8,'[1]资金台帐'!$M$4:$M$3003,"内部转账",'[1]资金台帐'!$N$4:$N$3003,'首页'!$B$4*100+N$5)-SUMIFS('[1]资金台帐'!$G$4:$G$3003,'[1]资金台帐'!$B$4:$B$3003,'[1]基础资料'!$A$8,'[1]资金台帐'!$M$4:$M$3003,"内部转账",'[1]资金台帐'!$N$4:$N$3003,'首页'!$B$4*100+N$5)+SUMIFS('[1]资金台帐'!$G$4:$G$3003,'[1]资金台帐'!$I$4:$I$3003,'[1]基础资料'!$A$8,'[1]资金台帐'!$M$4:$M$3003,"内部转账",'[1]资金台帐'!$N$4:$N$3003,'首页'!$B$4*100+N$5)-SUMIFS('[1]资金台帐'!$H$4:$H$3003,'[1]资金台帐'!$I$4:$I$3003,'[1]基础资料'!$A$8,'[1]资金台帐'!$M$4:$M$3003,"内部转账",'[1]资金台帐'!$N$4:$N$3003,'首页'!$B$4*100+N$5) -> 0 | O27: =SUM(C27:N27) -> 100000
A28: 提现差异（台帐－账务明细） | C28: =ROUND(C27+SUMIFS('[1]粘贴_账务明细'!$K$4:$K$3003,'[1]粘贴_账务明细'!$L$4:$L$3003,"提现",'[1]粘贴_账务明细'!$I$4:$I$3003,'首页'!$B$4*100+C$5),2) -> 0 | D28: =ROUND(D27+SUMIFS('[1]粘贴_账务明细'!$K$4:$K$3003,'[1]粘贴_账务明细'!$L$4:$L$3003,"提现",'[1]粘贴_账务明细'!$I$4:$I$3003,'首页'!$B$4*100+D$5),2) -> 0 | E28: =ROUND(E27+SUMIFS('[1]粘贴_账务明细'!$K$4:$K$3003,'[1]粘贴_账务明细'!$L$4:$L$3003,"提现",'[1]粘贴_账务明细'!$I$4:$I$3003,'首页'!$B$4*100+E$5),2) -> 0 | F28: =ROUND(F27+SUMIFS('[1]粘贴_账务明细'!$K$4:$K$3003,'[1]粘贴_账务明细'!$L$4:$L$3003,"提现",'[1]粘贴_账务明细'!$I$4:$I$3003,'首页'!$B$4*100+F$5),2) -> 0 | G28: =ROUND(G27+SUMIFS('[1]粘贴_账务明细'!$K$4:$K$3003,'[1]粘贴_账务明细'!$L$4:$L$3003,"提现",'[1]粘贴_账务明细'!$I$4:$I$3003,'首页'!$B$4*100+G$5),2) -> 0 | H28: =ROUND(H27+SUMIFS('[1]粘贴_账务明细'!$K$4:$K$3003,'[1]粘贴_账务明细'!$L$4:$L$3003,"提现",'[1]粘贴_账务明细'!$I$4:$I$3003,'首页'!$B$4*100+H$5),2) -> 0 | I28: =ROUND(I27+SUMIFS('[1]粘贴_账务明细'!$K$4:$K$3003,'[1]粘贴_账务明细'!$L$4:$L$3003,"提现",'[1]粘贴_账务明细'!$I$4:$I$3003,'首页'!$B$4*100+I$5),2) -> 0 | J28: =ROUND(J27+SUMIFS('[1]粘贴_账务明细'!$K$4:$K$3003,'[1]粘贴_账务明细'!$L$4:$L$3003,"提现",'[1]粘贴_账务明细'!$I$4:$I$3003,'首页'!$B$4*100+J$5),2) -> 0 | ... N28: =ROUND(N27+SUMIFS('[1]粘贴_账务明细'!$K$4:$K$3003,'[1]粘贴_账务明细'!$L$4:$L$3003,"提现",'[1]粘贴_账务明细'!$I$4:$I$3003,'首页'!$B$4*100+N$5),2) -> 0 | O28: =SUM(C28:N28) -> 0
A30: 二、批次核对 A. 账务明细里到账的批次（补贴汇入／技术服务费返还）→ 对账单里同一批次号的合计 | P30: ='[1]粘贴_账务明细'!$N$3003 -> 7 | Q30: ← 批数
A31: 序 | B31: 到账时间 | C31: 类型 | D31: 批次号 | E31: 到账金额 | F31: 营销活动对账单 | G31: 服务费返还账单 | H31: 对账单笔数 | I31: 差额 | J31: 结论 | P31: (位置)
A32: 1 | B32: =IF($P32="","",INDEX('[1]粘贴_账务明细'!$H$4:$H$3003,$P32)) -> 46289.375 | C32: =IF($P32="","",INDEX('[1]粘贴_账务明细'!$L$4:$L$3003,$P32)) -> 技术服务费返还 | D32: =IF($P32="","",INDEX('[1]粘贴_账务明细'!$M$4:$M$3003,$P32)) -> BO260915078057502 | E32: =IF($P32="","",INDEX('[1]粘贴_账务明细'!$K$4:$K$3003,$P32)) -> 4586.81 | F32: =IF($P32="","",SUMIFS('[1]粘贴_营销活动'!$M$4:$M$3003,'[1]粘贴_营销活动'!$I$4:$I$3003,$D32)) -> 0 | G32: =IF($P32="","",SUMIFS('[1]粘贴_服务费返还'!$M$4:$M$3003,'[1]粘贴_服务费返还'!$I$4:$I$3003,$D32)) -> 4586.81 | H32: =IF($P32="","",COUNTIFS('[1]粘贴_营销活动'!$I$4:$I$3003,$D32)+COUNTIFS('[1]粘贴_服务费返还'!$I$4:$I$3003,$D32)) -> 65 | I32: =IF($P32="","",ROUND(E32-F32-G32,2)) -> 0 | J32: =IF($P32="","",IF(H32=0,"对账单里没有这批明细",IF(ABS(I32)<0.01,"对上","差 "&TEXT(I32,"0.00")))) -> 对上 | P32: =IF(A32>$P$30,"",MATCH(A32,'[1]粘贴_账务明细'!$N$4:$N$3003,0)) -> 93
A33: 2 | B33: =IF($P33="","",INDEX('[1]粘贴_账务明细'!$H$4:$H$3003,$P33)) -> 46280.006 | C33: =IF($P33="","",INDEX('[1]粘贴_账务明细'!$L$4:$L$3003,$P33)) -> 补贴汇入 | D33: =IF($P33="","",INDEX('[1]粘贴_账务明细'!$M$4:$M$3003,$P33)) -> BO260825067002610 | E33: =IF($P33="","",INDEX('[1]粘贴_账务明细'!$K$4:$K$3003,$P33)) -> 690 | F33: =IF($P33="","",SUMIFS('[1]粘贴_营销活动'!$M$4:$M$3003,'[1]粘贴_营销活动'!$I$4:$I$3003,$D33)) -> 0 | G33: =IF($P33="","",SUMIFS('[1]粘贴_服务费返还'!$M$4:$M$3003,'[1]粘贴_服务费返还'!$I$4:$I$3003,$D33)) -> 0 | H33: =IF($P33="","",COUNTIFS('[1]粘贴_营销活动'!$I$4:$I$3003,$D33)+COUNTIFS('[1]粘贴_服务费返还'!$I$4:$I$3003,$D33)) -> 0 | I33: =IF($P33="","",ROUND(E33-F33-G33,2)) -> 690 | J33: =IF($P33="","",IF(H33=0,"对账单里没有这批明细",IF(ABS(I33)<0.01,"对上","差 "&TEXT(I33,"0.00")))) -> 对账单里没有这批明细 | P33: =IF(A33>$P$30,"",MATCH(A33,'[1]粘贴_账务明细'!$N$4:$N$3003,0)) -> 239
A34: 3 | B34: =IF($P34="","",INDEX('[1]粘贴_账务明细'!$H$4:$H$3003,$P34)) -> 46280.006 | C34: =IF($P34="","",INDEX('[1]粘贴_账务明细'!$L$4:$L$3003,$P34)) -> 补贴汇入 | D34: =IF($P34="","",INDEX('[1]粘贴_账务明细'!$M$4:$M$3003,$P34)) -> BO260904188542622 | E34: =IF($P34="","",INDEX('[1]粘贴_账务明细'!$K$4:$K$3003,$P34)) -> 310 | F34: =IF($P34="","",SUMIFS('[1]粘贴_营销活动'!$M$4:$M$3003,'[1]粘贴_营销活动'!$I$4:$I$3003,$D34)) -> 0 | G34: =IF($P34="","",SUMIFS('[1]粘贴_服务费返还'!$M$4:$M$3003,'[1]粘贴_服务费返还'!$I$4:$I$3003,$D34)) -> 0 | H34: =IF($P34="","",COUNTIFS('[1]粘贴_营销活动'!$I$4:$I$3003,$D34)+COUNTIFS('[1]粘贴_服务费返还'!$I$4:$I$3003,$D34)) -> 0 | I34: =IF($P34="","",ROUND(E34-F34-G34,2)) -> 310 | J34: =IF($P34="","",IF(H34=0,"对账单里没有这批明细",IF(ABS(I34)<0.01,"对上","差 "&TEXT(I34,"0.00")))) -> 对账单里没有这批明细 | P34: =IF(A34>$P$30,"",MATCH(A34,'[1]粘贴_账务明细'!$N$4:$N$3003,0)) -> 240
A35: 4 | B35: =IF($P35="","",INDEX('[1]粘贴_账务明细'!$H$4:$H$3003,$P35)) -> 46280.005 | C35: =IF($P35="","",INDEX('[1]粘贴_账务明细'!$L$4:$L$3003,$P35)) -> 补贴汇入 | D35: =IF($P35="","",INDEX('[1]粘贴_账务明细'!$M$4:$M$3003,$P35)) -> BO260828184556094 | E35: =IF($P35="","",INDEX('[1]粘贴_账务明细'!$K$4:$K$3003,$P35)) -> 600 | F35: =IF($P35="","",SUMIFS('[1]粘贴_营销活动'!$M$4:$M$3003,'[1]粘贴_营销活动'!$I$4:$I$3003,$D35)) -> 0 | G35: =IF($P35="","",SUMIFS('[1]粘贴_服务费返还'!$M$4:$M$3003,'[1]粘贴_服务费返还'!$I$4:$I$3003,$D35)) -> 0 | H35: =IF($P35="","",COUNTIFS('[1]粘贴_营销活动'!$I$4:$I$3003,$D35)+COUNTIFS('[1]粘贴_服务费返还'!$I$4:$I$3003,$D35)) -> 0 | I35: =IF($P35="","",ROUND(E35-F35-G35,2)) -> 600 | J35: =IF($P35="","",IF(H35=0,"对账单里没有这批明细",IF(ABS(I35)<0.01,"对上","差 "&TEXT(I35,"0.00")))) -> 对账单里没有这批明细 | P35: =IF(A35>$P$30,"",MATCH(A35,'[1]粘贴_账务明细'!$N$4:$N$3003,0)) -> 241
A36: 5 | B36: =IF($P36="","",INDEX('[1]粘贴_账务明细'!$H$4:$H$3003,$P36)) -> 46280.005 | C36: =IF($P36="","",INDEX('[1]粘贴_账务明细'!$L$4:$L$3003,$P36)) -> 补贴汇入 | D36: =IF($P36="","",INDEX('[1]粘贴_账务明细'!$M$4:$M$3003,$P36)) -> BO260904071810200 | E36: =IF($P36="","",INDEX('[1]粘贴_账务明细'!$K$4:$K$3003,$P36)) -> 660 | F36: =IF($P36="","",SUMIFS('[1]粘贴_营销活动'!$M$4:$M$3003,'[1]粘贴_营销活动'!$I$4:$I$3003,$D36)) -> 0 | G36: =IF($P36="","",SUMIFS('[1]粘贴_服务费返还'!$M$4:$M$3003,'[1]粘贴_服务费返还'!$I$4:$I$3003,$D36)) -> 0 | H36: =IF($P36="","",COUNTIFS('[1]粘贴_营销活动'!$I$4:$I$3003,$D36)+COUNTIFS('[1]粘贴_服务费返还'!$I$4:$I$3003,$D36)) -> 0 | I36: =IF($P36="","",ROUND(E36-F36-G36,2)) -> 660 | J36: =IF($P36="","",IF(H36=0,"对账单里没有这批明细",IF(ABS(I36)<0.01,"对上","差 "&TEXT(I36,"0.00")))) -> 对账单里没有这批明细 | P36: =IF(A36>$P$30,"",MATCH(A36,'[1]粘贴_账务明细'!$N$4:$N$3003,0)) -> 242
A37: 6 | B37: =IF($P37="","",INDEX('[1]粘贴_账务明细'!$H$4:$H$3003,$P37)) -> 46280.005 | C37: =IF($P37="","",INDEX('[1]粘贴_账务明细'!$L$4:$L$3003,$P37)) -> 补贴汇入 | D37: =IF($P37="","",INDEX('[1]粘贴_账务明细'!$M$4:$M$3003,$P37)) -> BO260828184181181 | E37: =IF($P37="","",INDEX('[1]粘贴_账务明细'!$K$4:$K$3003,$P37)) -> 1710 | F37: =IF($P37="","",SUMIFS('[1]粘贴_营销活动'!$M$4:$M$3003,'[1]粘贴_营销活动'!$I$4:$I$3003,$D37)) -> 0 | G37: =IF($P37="","",SUMIFS('[1]粘贴_服务费返还'!$M$4:$M$3003,'[1]粘贴_服务费返还'!$I$4:$I$3003,$D37)) -> 0 | H37: =IF($P37="","",COUNTIFS('[1]粘贴_营销活动'!$I$4:$I$3003,$D37)+COUNTIFS('[1]粘贴_服务费返还'!$I$4:$I$3003,$D37)) -> 0 | I37: =IF($P37="","",ROUND(E37-F37-G37,2)) -> 1710 | J37: =IF($P37="","",IF(H37=0,"对账单里没有这批明细",IF(ABS(I37)<0.01,"对上","差 "&TEXT(I37,"0.00")))) -> 对账单里没有这批明细 | P37: =IF(A37>$P$30,"",MATCH(A37,'[1]粘贴_账务明细'!$N$4:$N$3003,0)) -> 243
A38: 7 | B38: =IF($P38="","",INDEX('[1]粘贴_账务明细'!$H$4:$H$3003,$P38)) -> 46273.4 | C38: =IF($P38="","",INDEX('[1]粘贴_账务明细'!$L$4:$L$3003,$P38)) -> 技术服务费返还 | D38: =IF($P38="","",INDEX('[1]粘贴_账务明细'!$M$4:$M$3003,$P38)) -> BO260904188278880 | E38: =IF($P38="","",INDEX('[1]粘贴_账务明细'!$K$4:$K$3003,$P38)) -> 21.59 | F38: =IF($P38="","",SUMIFS('[1]粘贴_营销活动'!$M$4:$M$3003,'[1]粘贴_营销活动'!$I$4:$I$3003,$D38)) -> 0 | G38: =IF($P38="","",SUMIFS('[1]粘贴_服务费返还'!$M$4:$M$3003,'[1]粘贴_服务费返还'!$I$4:$I$3003,$D38)) -> 0 | H38: =IF($P38="","",COUNTIFS('[1]粘贴_营销活动'!$I$4:$I$3003,$D38)+COUNTIFS('[1]粘贴_服务费返还'!$I$4:$I$3003,$D38)) -> 0 | I38: =IF($P38="","",ROUND(E38-F38-G38,2)) -> 21.59 | J38: =IF($P38="","",IF(H38=0,"对账单里没有这批明细",IF(ABS(I38)<0.01,"对上","差 "&TEXT(I38,"0.00")))) -> 对账单里没有这批明细 | P38: =IF(A38>$P$30,"",MATCH(A38,'[1]粘贴_账务明细'!$N$4:$N$3003,0)) -> 292
A39: 8 | B39: =IF($P39="","",INDEX('[1]粘贴_账务明细'!$H$4:$H$3003,$P39)) | C39: =IF($P39="","",INDEX('[1]粘贴_账务明细'!$L$4:$L$3003,$P39)) | D39: =IF($P39="","",INDEX('[1]粘贴_账务明细'!$M$4:$M$3003,$P39)) | E39: =IF($P39="","",INDEX('[1]粘贴_账务明细'!$K$4:$K$3003,$P39)) | F39: =IF($P39="","",SUMIFS('[1]粘贴_营销活动'!$M$4:$M$3003,'[1]粘贴_营销活动'!$I$4:$I$3003,$D39)) | G39: =IF($P39="","",SUMIFS('[1]粘贴_服务费返还'!$M$4:$M$3003,'[1]粘贴_服务费返还'!$I$4:$I$3003,$D39)) | H39: =IF($P39="","",COUNTIFS('[1]粘贴_营销活动'!$I$4:$I$3003,$D39)+COUNTIFS('[1]粘贴_服务费返还'!$I$4:$I$3003,$D39)) | I39: =IF($P39="","",ROUND(E39-F39-G39,2)) | J39: =IF($P39="","",IF(H39=0,"对账单里没有这批明细",IF(ABS(I39)<0.01,"对上","差 "&TEXT(I39,"0.00")))) | P39: =IF(A39>$P$30,"",MATCH(A39,'[1]粘贴_账务明细'!$N$4:$N$3003,0))
A40: 9 | B40: =IF($P40="","",INDEX('[1]粘贴_账务明细'!$H$4:$H$3003,$P40)) | C40: =IF($P40="","",INDEX('[1]粘贴_账务明细'!$L$4:$L$3003,$P40)) | D40: =IF($P40="","",INDEX('[1]粘贴_账务明细'!$M$4:$M$3003,$P40)) | E40: =IF($P40="","",INDEX('[1]粘贴_账务明细'!$K$4:$K$3003,$P40)) | F40: =IF($P40="","",SUMIFS('[1]粘贴_营销活动'!$M$4:$M$3003,'[1]粘贴_营销活动'!$I$4:$I$3003,$D40)) | G40: =IF($P40="","",SUMIFS('[1]粘贴_服务费返还'!$M$4:$M$3003,'[1]粘贴_服务费返还'!$I$4:$I$3003,$D40)) | H40: =IF($P40="","",COUNTIFS('[1]粘贴_营销活动'!$I$4:$I$3003,$D40)+COUNTIFS('[1]粘贴_服务费返还'!$I$4:$I$3003,$D40)) | I40: =IF($P40="","",ROUND(E40-F40-G40,2)) | J40: =IF($P40="","",IF(H40=0,"对账单里没有这批明细",IF(ABS(I40)<0.01,"对上","差 "&TEXT(I40,"0.00")))) | P40: =IF(A40>$P$30,"",MATCH(A40,'[1]粘贴_账务明细'!$N$4:$N$3003,0))
A41: 10 | B41: =IF($P41="","",INDEX('[1]粘贴_账务明细'!$H$4:$H$3003,$P41)) | C41: =IF($P41="","",INDEX('[1]粘贴_账务明细'!$L$4:$L$3003,$P41)) | D41: =IF($P41="","",INDEX('[1]粘贴_账务明细'!$M$4:$M$3003,$P41)) | E41: =IF($P41="","",INDEX('[1]粘贴_账务明细'!$K$4:$K$3003,$P41)) | F41: =IF($P41="","",SUMIFS('[1]粘贴_营销活动'!$M$4:$M$3003,'[1]粘贴_营销活动'!$I$4:$I$3003,$D41)) | G41: =IF($P41="","",SUMIFS('[1]粘贴_服务费返还'!$M$4:$M$3003,'[1]粘贴_服务费返还'!$I$4:$I$3003,$D41)) | H41: =IF($P41="","",COUNTIFS('[1]粘贴_营销活动'!$I$4:$I$3003,$D41)+COUNTIFS('[1]粘贴_服务费返还'!$I$4:$I$3003,$D41)) | I41: =IF($P41="","",ROUND(E41-F41-G41,2)) | J41: =IF($P41="","",IF(H41=0,"对账单里没有这批明细",IF(ABS(I41)<0.01,"对上","差 "&TEXT(I41,"0.00")))) | P41: =IF(A41>$P$30,"",MATCH(A41,'[1]粘贴_账务明细'!$N$4:$N$3003,0))
A42: 11 | B42: =IF($P42="","",INDEX('[1]粘贴_账务明细'!$H$4:$H$3003,$P42)) | C42: =IF($P42="","",INDEX('[1]粘贴_账务明细'!$L$4:$L$3003,$P42)) | D42: =IF($P42="","",INDEX('[1]粘贴_账务明细'!$M$4:$M$3003,$P42)) | E42: =IF($P42="","",INDEX('[1]粘贴_账务明细'!$K$4:$K$3003,$P42)) | F42: =IF($P42="","",SUMIFS('[1]粘贴_营销活动'!$M$4:$M$3003,'[1]粘贴_营销活动'!$I$4:$I$3003,$D42)) | G42: =IF($P42="","",SUMIFS('[1]粘贴_服务费返还'!$M$4:$M$3003,'[1]粘贴_服务费返还'!$I$4:$I$3003,$D42)) | H42: =IF($P42="","",COUNTIFS('[1]粘贴_营销活动'!$I$4:$I$3003,$D42)+COUNTIFS('[1]粘贴_服务费返还'!$I$4:$I$3003,$D42)) | I42: =IF($P42="","",ROUND(E42-F42-G42,2)) | J42: =IF($P42="","",IF(H42=0,"对账单里没有这批明细",IF(ABS(I42)<0.01,"对上","差 "&TEXT(I42,"0.00")))) | P42: =IF(A42>$P$30,"",MATCH(A42,'[1]粘贴_账务明细'!$N$4:$N$3003,0))
A43: 12 | B43: =IF($P43="","",INDEX('[1]粘贴_账务明细'!$H$4:$H$3003,$P43)) | C43: =IF($P43="","",INDEX('[1]粘贴_账务明细'!$L$4:$L$3003,$P43)) | D43: =IF($P43="","",INDEX('[1]粘贴_账务明细'!$M$4:$M$3003,$P43)) | E43: =IF($P43="","",INDEX('[1]粘贴_账务明细'!$K$4:$K$3003,$P43)) | F43: =IF($P43="","",SUMIFS('[1]粘贴_营销活动'!$M$4:$M$3003,'[1]粘贴_营销活动'!$I$4:$I$3003,$D43)) | G43: =IF($P43="","",SUMIFS('[1]粘贴_服务费返还'!$M$4:$M$3003,'[1]粘贴_服务费返还'!$I$4:$I$3003,$D43)) | H43: =IF($P43="","",COUNTIFS('[1]粘贴_营销活动'!$I$4:$I$3003,$D43)+COUNTIFS('[1]粘贴_服务费返还'!$I$4:$I$3003,$D43)) | I43: =IF($P43="","",ROUND(E43-F43-G43,2)) | J43: =IF($P43="","",IF(H43=0,"对账单里没有这批明细",IF(ABS(I43)<0.01,"对上","差 "&TEXT(I43,"0.00")))) | P43: =IF(A43>$P$30,"",MATCH(A43,'[1]粘贴_账务明细'!$N$4:$N$3003,0))
... A91: 60 | B91: =IF($P91="","",INDEX('[1]粘贴_账务明细'!$H$4:$H$3003,$P91)) | C91: =IF($P91="","",INDEX('[1]粘贴_账务明细'!$L$4:$L$3003,$P91)) | D91: =IF($P91="","",INDEX('[1]粘贴_账务明细'!$M$4:$M$3003,$P91)) | E91: =IF($P91="","",INDEX('[1]粘贴_账务明细'!$K$4:$K$3003,$P91)) | F91: =IF($P91="","",SUMIFS('[1]粘贴_营销活动'!$M$4:$M$3003,'[1]粘贴_营销活动'!$I$4:$I$3003,$D91)) | G91: =IF($P91="","",SUMIFS('[1]粘贴_服务费返还'!$M$4:$M$3003,'[1]粘贴_服务费返还'!$I$4:$I$3003,$D91)) | H91: =IF($P91="","",COUNTIFS('[1]粘贴_营销活动'!$I$4:$I$3003,$D91)+COUNTIFS('[1]粘贴_服务费返还'!$I$4:$I$3003,$D91)) | I91: =IF($P91="","",ROUND(E91-F91-G91,2)) | J91: =IF($P91="","",IF(H91=0,"对账单里没有这批明细",IF(ABS(I91)<0.01,"对上","差 "&TEXT(I91,"0.00")))) | P91: =IF(A91>$P$30,"",MATCH(A91,'[1]粘贴_账务明细'!$N$4:$N$3003,0))
A93: B. 对账单里的批次 → 账务明细里到账了没有 | P93: ='[1]粘贴_营销活动'!$R$3003 -> 3 | Q93: ='[1]粘贴_服务费返还'!$R$3003 -> 1 | R93: ← 营销活动批数、服务费返还批数
A94: 序 | B94: 来源 | C94: 批次号 | D94: 结算时间 | E94: 笔数 | F94: 对账单合计 | G94: 账务明细到账 | H94: 差额 | I94: 结论 | P94: (位置)
A95: 1 | B95: =IF(A95<=$P$93,"营销活动",IF(A95<=$P$93+$Q$93,"服务费返还","")) -> 营销活动 | C95: =IF($P95="","",IF($B95="营销活动",INDEX('[1]粘贴_营销活动'!$I$4:$I$3003,$P95),INDEX('[1]粘贴_服务费返还'!$I$4:$I$3003,$P95))) -> BO260913194135449 | D95: =IF($P95="","",IF($B95="营销活动",INDEX('[1]粘贴_营销活动'!$K$4:$K$3003,$P95),INDEX('[1]粘贴_服务费返还'!$K$4:$K$3003,$P95))) -> 2026-10-12 17:10:05 | E95: =IF($P95="","",COUNTIFS('[1]粘贴_营销活动'!$I$4:$I$3003,$C95)+COUNTIFS('[1]粘贴_服务费返还'!$I$4:$I$3003,$C95)) -> 1 | F95: =IF($P95="","",SUMIFS('[1]粘贴_营销活动'!$M$4:$M$3003,'[1]粘贴_营销活动'!$I$4:$I$3003,$C95)+SUMIFS('[1]粘贴_服务费返还'!$M$4:$M$3003,'[1]粘贴_服务费返还'!$I$4:$I$3003,$C95)) -> 110 | G95: =IF($P95="","",SUMIFS('[1]粘贴_账务明细'!$K$4:$K$3003,'[1]粘贴_账务明细'!$M$4:$M$3003,$C95)) -> 0 | H95: =IF($P95="","",ROUND(G95-F95,2)) -> -110 | I95: =IF($P95="","",IF(G95=0,"账务明细里还没到账（看结算时间，粘那个月的账务明细）",IF(ABS(H95)<0.01,"对上","差 "&TEXT(H95,"0.00")))) -> 账务明细里还没到账（看结算时间，粘那个月的账务明细） | P95: =IF(B95="营销活动",MATCH(A95,'[1]粘贴_营销活动'!$R$4:$R$3003,0),IF(B95="服务费返还",MATCH(A95-$P$93,'[1]粘贴_服务费返还'!$R$4:$R$3003,0),"")) -> 1
A96: 2 | B96: =IF(A96<=$P$93,"营销活动",IF(A96<=$P$93+$Q$93,"服务费返还","")) -> 营销活动 | C96: =IF($P96="","",IF($B96="营销活动",INDEX('[1]粘贴_营销活动'!$I$4:$I$3003,$P96),INDEX('[1]粘贴_服务费返还'!$I$4:$I$3003,$P96))) -> BO260919079963782 | D96: =IF($P96="","",IF($B96="营销活动",INDEX('[1]粘贴_营销活动'!$K$4:$K$3003,$P96),INDEX('[1]粘贴_服务费返还'!$K$4:$K$3003,$P96))) -> 2026-10-12 17:07:42 | E96: =IF($P96="","",COUNTIFS('[1]粘贴_营销活动'!$I$4:$I$3003,$C96)+COUNTIFS('[1]粘贴_服务费返还'!$I$4:$I$3003,$C96)) -> 2 | F96: =IF($P96="","",SUMIFS('[1]粘贴_营销活动'!$M$4:$M$3003,'[1]粘贴_营销活动'!$I$4:$I$3003,$C96)+SUMIFS('[1]粘贴_服务费返还'!$M$4:$M$3003,'[1]粘贴_服务费返还'!$I$4:$I$3003,$C96)) -> 560 | G96: =IF($P96="","",SUMIFS('[1]粘贴_账务明细'!$K$4:$K$3003,'[1]粘贴_账务明细'!$M$4:$M$3003,$C96)) -> 0 | H96: =IF($P96="","",ROUND(G96-F96,2)) -> -560 | I96: =IF($P96="","",IF(G96=0,"账务明细里还没到账（看结算时间，粘那个月的账务明细）",IF(ABS(H96)<0.01,"对上","差 "&TEXT(H96,"0.00")))) -> 账务明细里还没到账（看结算时间，粘那个月的账务明细） | P96: =IF(B96="营销活动",MATCH(A96,'[1]粘贴_营销活动'!$R$4:$R$3003,0),IF(B96="服务费返还",MATCH(A96-$P$93,'[1]粘贴_服务费返还'!$R$4:$R$3003,0),"")) -> 2
A97: 3 | B97: =IF(A97<=$P$93,"营销活动",IF(A97<=$P$93+$Q$93,"服务费返还","")) -> 营销活动 | C97: =IF($P97="","",IF($B97="营销活动",INDEX('[1]粘贴_营销活动'!$I$4:$I$3003,$P97),INDEX('[1]粘贴_服务费返还'!$I$4:$I$3003,$P97))) -> BO260925082890891 | D97: =IF($P97="","",IF($B97="营销活动",INDEX('[1]粘贴_营销活动'!$K$4:$K$3003,$P97),INDEX('[1]粘贴_服务费返还'!$K$4:$K$3003,$P97))) -> 2026-10-12 17:07:47 | E97: =IF($P97="","",COUNTIFS('[1]粘贴_营销活动'!$I$4:$I$3003,$C97)+COUNTIFS('[1]粘贴_服务费返还'!$I$4:$I$3003,$C97)) -> 1 | F97: =IF($P97="","",SUMIFS('[1]粘贴_营销活动'!$M$4:$M$3003,'[1]粘贴_营销活动'!$I$4:$I$3003,$C97)+SUMIFS('[1]粘贴_服务费返还'!$M$4:$M$3003,'[1]粘贴_服务费返还'!$I$4:$I$3003,$C97)) -> 650 | G97: =IF($P97="","",SUMIFS('[1]粘贴_账务明细'!$K$4:$K$3003,'[1]粘贴_账务明细'!$M$4:$M$3003,$C97)) -> 0 | H97: =IF($P97="","",ROUND(G97-F97,2)) -> -650 | I97: =IF($P97="","",IF(G97=0,"账务明细里还没到账（看结算时间，粘那个月的账务明细）",IF(ABS(H97)<0.01,"对上","差 "&TEXT(H97,"0.00")))) -> 账务明细里还没到账（看结算时间，粘那个月的账务明细） | P97: =IF(B97="营销活动",MATCH(A97,'[1]粘贴_营销活动'!$R$4:$R$3003,0),IF(B97="服务费返还",MATCH(A97-$P$93,'[1]粘贴_服务费返还'!$R$4:$R$3003,0),"")) -> 4
A98: 4 | B98: =IF(A98<=$P$93,"营销活动",IF(A98<=$P$93+$Q$93,"服务费返还","")) -> 服务费返还 | C98: =IF($P98="","",IF($B98="营销活动",INDEX('[1]粘贴_营销活动'!$I$4:$I$3003,$P98),INDEX('[1]粘贴_服务费返还'!$I$4:$I$3003,$P98))) -> BO260915078057502 | D98: =IF($P98="","",IF($B98="营销活动",INDEX('[1]粘贴_营销活动'!$K$4:$K$3003,$P98),INDEX('[1]粘贴_服务费返还'!$K$4:$K$3003,$P98))) -> 2026-09-24 08:59:43 | E98: =IF($P98="","",COUNTIFS('[1]粘贴_营销活动'!$I$4:$I$3003,$C98)+COUNTIFS('[1]粘贴_服务费返还'!$I$4:$I$3003,$C98)) -> 65 | F98: =IF($P98="","",SUMIFS('[1]粘贴_营销活动'!$M$4:$M$3003,'[1]粘贴_营销活动'!$I$4:$I$3003,$C98)+SUMIFS('[1]粘贴_服务费返还'!$M$4:$M$3003,'[1]粘贴_服务费返还'!$I$4:$I$3003,$C98)) -> 4586.81 | G98: =IF($P98="","",SUMIFS('[1]粘贴_账务明细'!$K$4:$K$3003,'[1]粘贴_账务明细'!$M$4:$M$3003,$C98)) -> 4586.81 | H98: =IF($P98="","",ROUND(G98-F98,2)) -> 0 | I98: =IF($P98="","",IF(G98=0,"账务明细里还没到账（看结算时间，粘那个月的账务明细）",IF(ABS(H98)<0.01,"对上","差 "&TEXT(H98,"0.00")))) -> 对上 | P98: =IF(B98="营销活动",MATCH(A98,'[1]粘贴_营销活动'!$R$4:$R$3003,0),IF(B98="服务费返还",MATCH(A98-$P$93,'[1]粘贴_服务费返还'!$R$4:$R$3003,0),"")) -> 1
A99: 5 | B99: =IF(A99<=$P$93,"营销活动",IF(A99<=$P$93+$Q$93,"服务费返还","")) | C99: =IF($P99="","",IF($B99="营销活动",INDEX('[1]粘贴_营销活动'!$I$4:$I$3003,$P99),INDEX('[1]粘贴_服务费返还'!$I$4:$I$3003,$P99))) | D99: =IF($P99="","",IF($B99="营销活动",INDEX('[1]粘贴_营销活动'!$K$4:$K$3003,$P99),INDEX('[1]粘贴_服务费返还'!$K$4:$K$3003,$P99))) | E99: =IF($P99="","",COUNTIFS('[1]粘贴_营销活动'!$I$4:$I$3003,$C99)+COUNTIFS('[1]粘贴_服务费返还'!$I$4:$I$3003,$C99)) | F99: =IF($P99="","",SUMIFS('[1]粘贴_营销活动'!$M$4:$M$3003,'[1]粘贴_营销活动'!$I$4:$I$3003,$C99)+SUMIFS('[1]粘贴_服务费返还'!$M$4:$M$3003,'[1]粘贴_服务费返还'!$I$4:$I$3003,$C99)) | G99: =IF($P99="","",SUMIFS('[1]粘贴_账务明细'!$K$4:$K$3003,'[1]粘贴_账务明细'!$M$4:$M$3003,$C99)) | H99: =IF($P99="","",ROUND(G99-F99,2)) | I99: =IF($P99="","",IF(G99=0,"账务明细里还没到账（看结算时间，粘那个月的账务明细）",IF(ABS(H99)<0.01,"对上","差 "&TEXT(H99,"0.00")))) | P99: =IF(B99="营销活动",MATCH(A99,'[1]粘贴_营销活动'!$R$4:$R$3003,0),IF(B99="服务费返还",MATCH(A99-$P$93,'[1]粘贴_服务费返还'!$R$4:$R$3003,0),""))
A100: 6 | B100: =IF(A100<=$P$93,"营销活动",IF(A100<=$P$93+$Q$93,"服务费返还","")) | C100: =IF($P100="","",IF($B100="营销活动",INDEX('[1]粘贴_营销活动'!$I$4:$I$3003,$P100),INDEX('[1]粘贴_服务费返还'!$I$4:$I$3003,$P100))) | D100: =IF($P100="","",IF($B100="营销活动",INDEX('[1]粘贴_营销活动'!$K$4:$K$3003,$P100),INDEX('[1]粘贴_服务费返还'!$K$4:$K$3003,$P100))) | E100: =IF($P100="","",COUNTIFS('[1]粘贴_营销活动'!$I$4:$I$3003,$C100)+COUNTIFS('[1]粘贴_服务费返还'!$I$4:$I$3003,$C100)) | F100: =IF($P100="","",SUMIFS('[1]粘贴_营销活动'!$M$4:$M$3003,'[1]粘贴_营销活动'!$I$4:$I$3003,$C100)+SUMIFS('[1]粘贴_服务费返还'!$M$4:$M$3003,'[1]粘贴_服务费返还'!$I$4:$I$3003,$C100)) | G100: =IF($P100="","",SUMIFS('[1]粘贴_账务明细'!$K$4:$K$3003,'[1]粘贴_账务明细'!$M$4:$M$3003,$C100)) | H100: =IF($P100="","",ROUND(G100-F100,2)) | I100: =IF($P100="","",IF(G100=0,"账务明细里还没到账（看结算时间，粘那个月的账务明细）",IF(ABS(H100)<0.01,"对上","差 "&TEXT(H100,"0.00")))) | P100: =IF(B100="营销活动",MATCH(A100,'[1]粘贴_营销活动'!$R$4:$R$3003,0),IF(B100="服务费返还",MATCH(A100-$P$93,'[1]粘贴_服务费返还'!$R$4:$R$3003,0),""))
A101: 7 | B101: =IF(A101<=$P$93,"营销活动",IF(A101<=$P$93+$Q$93,"服务费返还","")) | C101: =IF($P101="","",IF($B101="营销活动",INDEX('[1]粘贴_营销活动'!$I$4:$I$3003,$P101),INDEX('[1]粘贴_服务费返还'!$I$4:$I$3003,$P101))) | D101: =IF($P101="","",IF($B101="营销活动",INDEX('[1]粘贴_营销活动'!$K$4:$K$3003,$P101),INDEX('[1]粘贴_服务费返还'!$K$4:$K$3003,$P101))) | E101: =IF($P101="","",COUNTIFS('[1]粘贴_营销活动'!$I$4:$I$3003,$C101)+COUNTIFS('[1]粘贴_服务费返还'!$I$4:$I$3003,$C101)) | F101: =IF($P101="","",SUMIFS('[1]粘贴_营销活动'!$M$4:$M$3003,'[1]粘贴_营销活动'!$I$4:$I$3003,$C101)+SUMIFS('[1]粘贴_服务费返还'!$M$4:$M$3003,'[1]粘贴_服务费返还'!$I$4:$I$3003,$C101)) | G101: =IF($P101="","",SUMIFS('[1]粘贴_账务明细'!$K$4:$K$3003,'[1]粘贴_账务明细'!$M$4:$M$3003,$C101)) | H101: =IF($P101="","",ROUND(G101-F101,2)) | I101: =IF($P101="","",IF(G101=0,"账务明细里还没到账（看结算时间，粘那个月的账务明细）",IF(ABS(H101)<0.01,"对上","差 "&TEXT(H101,"0.00")))) | P101: =IF(B101="营销活动",MATCH(A101,'[1]粘贴_营销活动'!$R$4:$R$3003,0),IF(B101="服务费返还",MATCH(A101-$P$93,'[1]粘贴_服务费返还'!$R$4:$R$3003,0),""))
A102: 8 | B102: =IF(A102<=$P$93,"营销活动",IF(A102<=$P$93+$Q$93,"服务费返还","")) | C102: =IF($P102="","",IF($B102="营销活动",INDEX('[1]粘贴_营销活动'!$I$4:$I$3003,$P102),INDEX('[1]粘贴_服务费返还'!$I$4:$I$3003,$P102))) | D102: =IF($P102="","",IF($B102="营销活动",INDEX('[1]粘贴_营销活动'!$K$4:$K$3003,$P102),INDEX('[1]粘贴_服务费返还'!$K$4:$K$3003,$P102))) | E102: =IF($P102="","",COUNTIFS('[1]粘贴_营销活动'!$I$4:$I$3003,$C102)+COUNTIFS('[1]粘贴_服务费返还'!$I$4:$I$3003,$C102)) | F102: =IF($P102="","",SUMIFS('[1]粘贴_营销活动'!$M$4:$M$3003,'[1]粘贴_营销活动'!$I$4:$I$3003,$C102)+SUMIFS('[1]粘贴_服务费返还'!$M$4:$M$3003,'[1]粘贴_服务费返还'!$I$4:$I$3003,$C102)) | G102: =IF($P102="","",SUMIFS('[1]粘贴_账务明细'!$K$4:$K$3003,'[1]粘贴_账务明细'!$M$4:$M$3003,$C102)) | H102: =IF($P102="","",ROUND(G102-F102,2)) | I102: =IF($P102="","",IF(G102=0,"账务明细里还没到账（看结算时间，粘那个月的账务明细）",IF(ABS(H102)<0.01,"对上","差 "&TEXT(H102,"0.00")))) | P102: =IF(B102="营销活动",MATCH(A102,'[1]粘贴_营销活动'!$R$4:$R$3003,0),IF(B102="服务费返还",MATCH(A102-$P$93,'[1]粘贴_服务费返还'!$R$4:$R$3003,0),""))
A103: 9 | B103: =IF(A103<=$P$93,"营销活动",IF(A103<=$P$93+$Q$93,"服务费返还","")) | C103: =IF($P103="","",IF($B103="营销活动",INDEX('[1]粘贴_营销活动'!$I$4:$I$3003,$P103),INDEX('[1]粘贴_服务费返还'!$I$4:$I$3003,$P103))) | D103: =IF($P103="","",IF($B103="营销活动",INDEX('[1]粘贴_营销活动'!$K$4:$K$3003,$P103),INDEX('[1]粘贴_服务费返还'!$K$4:$K$3003,$P103))) | E103: =IF($P103="","",COUNTIFS('[1]粘贴_营销活动'!$I$4:$I$3003,$C103)+COUNTIFS('[1]粘贴_服务费返还'!$I$4:$I$3003,$C103)) | F103: =IF($P103="","",SUMIFS('[1]粘贴_营销活动'!$M$4:$M$3003,'[1]粘贴_营销活动'!$I$4:$I$3003,$C103)+SUMIFS('[1]粘贴_服务费返还'!$M$4:$M$3003,'[1]粘贴_服务费返还'!$I$4:$I$3003,$C103)) | G103: =IF($P103="","",SUMIFS('[1]粘贴_账务明细'!$K$4:$K$3003,'[1]粘贴_账务明细'!$M$4:$M$3003,$C103)) | H103: =IF($P103="","",ROUND(G103-F103,2)) | I103: =IF($P103="","",IF(G103=0,"账务明细里还没到账（看结算时间，粘那个月的账务明细）",IF(ABS(H103)<0.01,"对上","差 "&TEXT(H103,"0.00")))) | P103: =IF(B103="营销活动",MATCH(A103,'[1]粘贴_营销活动'!$R$4:$R$3003,0),IF(B103="服务费返还",MATCH(A103-$P$93,'[1]粘贴_服务费返还'!$R$4:$R$3003,0),""))
A104: 10 | B104: =IF(A104<=$P$93,"营销活动",IF(A104<=$P$93+$Q$93,"服务费返还","")) | C104: =IF($P104="","",IF($B104="营销活动",INDEX('[1]粘贴_营销活动'!$I$4:$I$3003,$P104),INDEX('[1]粘贴_服务费返还'!$I$4:$I$3003,$P104))) | D104: =IF($P104="","",IF($B104="营销活动",INDEX('[1]粘贴_营销活动'!$K$4:$K$3003,$P104),INDEX('[1]粘贴_服务费返还'!$K$4:$K$3003,$P104))) | E104: =IF($P104="","",COUNTIFS('[1]粘贴_营销活动'!$I$4:$I$3003,$C104)+COUNTIFS('[1]粘贴_服务费返还'!$I$4:$I$3003,$C104)) | F104: =IF($P104="","",SUMIFS('[1]粘贴_营销活动'!$M$4:$M$3003,'[1]粘贴_营销活动'!$I$4:$I$3003,$C104)+SUMIFS('[1]粘贴_服务费返还'!$M$4:$M$3003,'[1]粘贴_服务费返还'!$I$4:$I$3003,$C104)) | G104: =IF($P104="","",SUMIFS('[1]粘贴_账务明细'!$K$4:$K$3003,'[1]粘贴_账务明细'!$M$4:$M$3003,$C104)) | H104: =IF($P104="","",ROUND(G104-F104,2)) | I104: =IF($P104="","",IF(G104=0,"账务明细里还没到账（看结算时间，粘那个月的账务明细）",IF(ABS(H104)<0.01,"对上","差 "&TEXT(H104,"0.00")))) | P104: =IF(B104="营销活动",MATCH(A104,'[1]粘贴_营销活动'!$R$4:$R$3003,0),IF(B104="服务费返还",MATCH(A104-$P$93,'[1]粘贴_服务费返还'!$R$4:$R$3003,0),""))
A105: 11 | B105: =IF(A105<=$P$93,"营销活动",IF(A105<=$P$93+$Q$93,"服务费返还","")) | C105: =IF($P105="","",IF($B105="营销活动",INDEX('[1]粘贴_营销活动'!$I$4:$I$3003,$P105),INDEX('[1]粘贴_服务费返还'!$I$4:$I$3003,$P105))) | D105: =IF($P105="","",IF($B105="营销活动",INDEX('[1]粘贴_营销活动'!$K$4:$K$3003,$P105),INDEX('[1]粘贴_服务费返还'!$K$4:$K$3003,$P105))) | E105: =IF($P105="","",COUNTIFS('[1]粘贴_营销活动'!$I$4:$I$3003,$C105)+COUNTIFS('[1]粘贴_服务费返还'!$I$4:$I$3003,$C105)) | F105: =IF($P105="","",SUMIFS('[1]粘贴_营销活动'!$M$4:$M$3003,'[1]粘贴_营销活动'!$I$4:$I$3003,$C105)+SUMIFS('[1]粘贴_服务费返还'!$M$4:$M$3003,'[1]粘贴_服务费返还'!$I$4:$I$3003,$C105)) | G105: =IF($P105="","",SUMIFS('[1]粘贴_账务明细'!$K$4:$K$3003,'[1]粘贴_账务明细'!$M$4:$M$3003,$C105)) | H105: =IF($P105="","",ROUND(G105-F105,2)) | I105: =IF($P105="","",IF(G105=0,"账务明细里还没到账（看结算时间，粘那个月的账务明细）",IF(ABS(H105)<0.01,"对上","差 "&TEXT(H105,"0.00")))) | P105: =IF(B105="营销活动",MATCH(A105,'[1]粘贴_营销活动'!$R$4:$R$3003,0),IF(B105="服务费返还",MATCH(A105-$P$93,'[1]粘贴_服务费返还'!$R$4:$R$3003,0),""))
A106: 12 | B106: =IF(A106<=$P$93,"营销活动",IF(A106<=$P$93+$Q$93,"服务费返还","")) | C106: =IF($P106="","",IF($B106="营销活动",INDEX('[1]粘贴_营销活动'!$I$4:$I$3003,$P106),INDEX('[1]粘贴_服务费返还'!$I$4:$I$3003,$P106))) | D106: =IF($P106="","",IF($B106="营销活动",INDEX('[1]粘贴_营销活动'!$K$4:$K$3003,$P106),INDEX('[1]粘贴_服务费返还'!$K$4:$K$3003,$P106))) | E106: =IF($P106="","",COUNTIFS('[1]粘贴_营销活动'!$I$4:$I$3003,$C106)+COUNTIFS('[1]粘贴_服务费返还'!$I$4:$I$3003,$C106)) | F106: =IF($P106="","",SUMIFS('[1]粘贴_营销活动'!$M$4:$M$3003,'[1]粘贴_营销活动'!$I$4:$I$3003,$C106)+SUMIFS('[1]粘贴_服务费返还'!$M$4:$M$3003,'[1]粘贴_服务费返还'!$I$4:$I$3003,$C106)) | G106: =IF($P106="","",SUMIFS('[1]粘贴_账务明细'!$K$4:$K$3003,'[1]粘贴_账务明细'!$M$4:$M$3003,$C106)) | H106: =IF($P106="","",ROUND(G106-F106,2)) | I106: =IF($P106="","",IF(G106=0,"账务明细里还没到账（看结算时间，粘那个月的账务明细）",IF(ABS(H106)<0.01,"对上","差 "&TEXT(H106,"0.00")))) | P106: =IF(B106="营销活动",MATCH(A106,'[1]粘贴_营销活动'!$R$4:$R$3003,0),IF(B106="服务费返还",MATCH(A106-$P$93,'[1]粘贴_服务费返还'!$R$4:$R$3003,0),""))
... A134: 40 | B134: =IF(A134<=$P$93,"营销活动",IF(A134<=$P$93+$Q$93,"服务费返还","")) | C134: =IF($P134="","",IF($B134="营销活动",INDEX('[1]粘贴_营销活动'!$I$4:$I$3003,$P134),INDEX('[1]粘贴_服务费返还'!$I$4:$I$3003,$P134))) | D134: =IF($P134="","",IF($B134="营销活动",INDEX('[1]粘贴_营销活动'!$K$4:$K$3003,$P134),INDEX('[1]粘贴_服务费返还'!$K$4:$K$3003,$P134))) | E134: =IF($P134="","",COUNTIFS('[1]粘贴_营销活动'!$I$4:$I$3003,$C134)+COUNTIFS('[1]粘贴_服务费返还'!$I$4:$I$3003,$C134)) | F134: =IF($P134="","",SUMIFS('[1]粘贴_营销活动'!$M$4:$M$3003,'[1]粘贴_营销活动'!$I$4:$I$3003,$C134)+SUMIFS('[1]粘贴_服务费返还'!$M$4:$M$3003,'[1]粘贴_服务费返还'!$I$4:$I$3003,$C134)) | G134: =IF($P134="","",SUMIFS('[1]粘贴_账务明细'!$K$4:$K$3003,'[1]粘贴_账务明细'!$M$4:$M$3003,$C134)) | H134: =IF($P134="","",ROUND(G134-F134,2)) | I134: =IF($P134="","",IF(G134=0,"账务明细里还没到账（看结算时间，粘那个月的账务明细）",IF(ABS(H134)<0.01,"对上","差 "&TEXT(H134,"0.00")))) | P134: =IF(B134="营销活动",MATCH(A134,'[1]粘贴_营销活动'!$R$4:$R$3003,0),IF(B134="服务费返还",MATCH(A134-$P$93,'[1]粘贴_服务费返还'!$R$4:$R$3003,0),""))
A136: 三、营销活动逐单核对：应结＝成本金额（报名价）－商品售价（活动价）＋备注里的补贴优惠券，跟结算总金额比
A137: 对账单笔数 | C137: 应结合计 | E137: 结算合计 | G137: 补贴券合计 | I137: 不一致笔数
A138: =COUNT('[1]粘贴_营销活动'!$M$4:$M$3003) -> 4 | C138: =SUM('[1]粘贴_营销活动'!$O$4:$O$3003) -> 1320 | E138: =SUM('[1]粘贴_营销活动'!$M$4:$M$3003) -> 1320 | G138: =SUM('[1]粘贴_营销活动'!$N$4:$N$3003) -> 600 | I138: =COUNTIFS('[1]粘贴_营销活动'!$Q$4:$Q$3003,"不一致") -> 0
A139: 不一致的单（最多列 20 笔，全部的去「粘贴_营销活动」按「结论」筛选）
A140: 序 | B140: 订单号 | C140: 商品名称 | D140: 活动价 | E140: 报名价 | F140: 补贴券 | G140: 应结 | H140: 结算总金额 | I140: 差额 | J140: 批次号 | P140: (位置)
A141: 1 | B141: =IF($P141="","",INDEX('[1]粘贴_营销活动'!$A$4:$A$3003,$P141)) | C141: =IF($P141="","",INDEX('[1]粘贴_营销活动'!$E$4:$E$3003,$P141)) | D141: =IF($P141="","",INDEX('[1]粘贴_营销活动'!$F$4:$F$3003,$P141)) | E141: =IF($P141="","",INDEX('[1]粘贴_营销活动'!$G$4:$G$3003,$P141)) | F141: =IF($P141="","",INDEX('[1]粘贴_营销活动'!$N$4:$N$3003,$P141)) | G141: =IF($P141="","",INDEX('[1]粘贴_营销活动'!$O$4:$O$3003,$P141)) | H141: =IF($P141="","",INDEX('[1]粘贴_营销活动'!$M$4:$M$3003,$P141)) | I141: =IF($P141="","",INDEX('[1]粘贴_营销活动'!$P$4:$P$3003,$P141)) | J141: =IF($P141="","",INDEX('[1]粘贴_营销活动'!$I$4:$I$3003,$P141)) | P141: =IFERROR(MATCH(A141,'[1]粘贴_营销活动'!$S$4:$S$3003,0),"")
A142: 2 | B142: =IF($P142="","",INDEX('[1]粘贴_营销活动'!$A$4:$A$3003,$P142)) | C142: =IF($P142="","",INDEX('[1]粘贴_营销活动'!$E$4:$E$3003,$P142)) | D142: =IF($P142="","",INDEX('[1]粘贴_营销活动'!$F$4:$F$3003,$P142)) | E142: =IF($P142="","",INDEX('[1]粘贴_营销活动'!$G$4:$G$3003,$P142)) | F142: =IF($P142="","",INDEX('[1]粘贴_营销活动'!$N$4:$N$3003,$P142)) | G142: =IF($P142="","",INDEX('[1]粘贴_营销活动'!$O$4:$O$3003,$P142)) | H142: =IF($P142="","",INDEX('[1]粘贴_营销活动'!$M$4:$M$3003,$P142)) | I142: =IF($P142="","",INDEX('[1]粘贴_营销活动'!$P$4:$P$3003,$P142)) | J142: =IF($P142="","",INDEX('[1]粘贴_营销活动'!$I$4:$I$3003,$P142)) | P142: =IFERROR(MATCH(A142,'[1]粘贴_营销活动'!$S$4:$S$3003,0),"")
A143: 3 | B143: =IF($P143="","",INDEX('[1]粘贴_营销活动'!$A$4:$A$3003,$P143)) | C143: =IF($P143="","",INDEX('[1]粘贴_营销活动'!$E$4:$E$3003,$P143)) | D143: =IF($P143="","",INDEX('[1]粘贴_营销活动'!$F$4:$F$3003,$P143)) | E143: =IF($P143="","",INDEX('[1]粘贴_营销活动'!$G$4:$G$3003,$P143)) | F143: =IF($P143="","",INDEX('[1]粘贴_营销活动'!$N$4:$N$3003,$P143)) | G143: =IF($P143="","",INDEX('[1]粘贴_营销活动'!$O$4:$O$3003,$P143)) | H143: =IF($P143="","",INDEX('[1]粘贴_营销活动'!$M$4:$M$3003,$P143)) | I143: =IF($P143="","",INDEX('[1]粘贴_营销活动'!$P$4:$P$3003,$P143)) | J143: =IF($P143="","",INDEX('[1]粘贴_营销活动'!$I$4:$I$3003,$P143)) | P143: =IFERROR(MATCH(A143,'[1]粘贴_营销活动'!$S$4:$S$3003,0),"")
A144: 4 | B144: =IF($P144="","",INDEX('[1]粘贴_营销活动'!$A$4:$A$3003,$P144)) | C144: =IF($P144="","",INDEX('[1]粘贴_营销活动'!$E$4:$E$3003,$P144)) | D144: =IF($P144="","",INDEX('[1]粘贴_营销活动'!$F$4:$F$3003,$P144)) | E144: =IF($P144="","",INDEX('[1]粘贴_营销活动'!$G$4:$G$3003,$P144)) | F144: =IF($P144="","",INDEX('[1]粘贴_营销活动'!$N$4:$N$3003,$P144)) | G144: =IF($P144="","",INDEX('[1]粘贴_营销活动'!$O$4:$O$3003,$P144)) | H144: =IF($P144="","",INDEX('[1]粘贴_营销活动'!$M$4:$M$3003,$P144)) | I144: =IF($P144="","",INDEX('[1]粘贴_营销活动'!$P$4:$P$3003,$P144)) | J144: =IF($P144="","",INDEX('[1]粘贴_营销活动'!$I$4:$I$3003,$P144)) | P144: =IFERROR(MATCH(A144,'[1]粘贴_营销活动'!$S$4:$S$3003,0),"")
A145: 5 | B145: =IF($P145="","",INDEX('[1]粘贴_营销活动'!$A$4:$A$3003,$P145)) | C145: =IF($P145="","",INDEX('[1]粘贴_营销活动'!$E$4:$E$3003,$P145)) | D145: =IF($P145="","",INDEX('[1]粘贴_营销活动'!$F$4:$F$3003,$P145)) | E145: =IF($P145="","",INDEX('[1]粘贴_营销活动'!$G$4:$G$3003,$P145)) | F145: =IF($P145="","",INDEX('[1]粘贴_营销活动'!$N$4:$N$3003,$P145)) | G145: =IF($P145="","",INDEX('[1]粘贴_营销活动'!$O$4:$O$3003,$P145)) | H145: =IF($P145="","",INDEX('[1]粘贴_营销活动'!$M$4:$M$3003,$P145)) | I145: =IF($P145="","",INDEX('[1]粘贴_营销活动'!$P$4:$P$3003,$P145)) | J145: =IF($P145="","",INDEX('[1]粘贴_营销活动'!$I$4:$I$3003,$P145)) | P145: =IFERROR(MATCH(A145,'[1]粘贴_营销活动'!$S$4:$S$3003,0),"")
A146: 6 | B146: =IF($P146="","",INDEX('[1]粘贴_营销活动'!$A$4:$A$3003,$P146)) | C146: =IF($P146="","",INDEX('[1]粘贴_营销活动'!$E$4:$E$3003,$P146)) | D146: =IF($P146="","",INDEX('[1]粘贴_营销活动'!$F$4:$F$3003,$P146)) | E146: =IF($P146="","",INDEX('[1]粘贴_营销活动'!$G$4:$G$3003,$P146)) | F146: =IF($P146="","",INDEX('[1]粘贴_营销活动'!$N$4:$N$3003,$P146)) | G146: =IF($P146="","",INDEX('[1]粘贴_营销活动'!$O$4:$O$3003,$P146)) | H146: =IF($P146="","",INDEX('[1]粘贴_营销活动'!$M$4:$M$3003,$P146)) | I146: =IF($P146="","",INDEX('[1]粘贴_营销活动'!$P$4:$P$3003,$P146)) | J146: =IF($P146="","",INDEX('[1]粘贴_营销活动'!$I$4:$I$3003,$P146)) | P146: =IFERROR(MATCH(A146,'[1]粘贴_营销活动'!$S$4:$S$3003,0),"")
A147: 7 | B147: =IF($P147="","",INDEX('[1]粘贴_营销活动'!$A$4:$A$3003,$P147)) | C147: =IF($P147="","",INDEX('[1]粘贴_营销活动'!$E$4:$E$3003,$P147)) | D147: =IF($P147="","",INDEX('[1]粘贴_营销活动'!$F$4:$F$3003,$P147)) | E147: =IF($P147="","",INDEX('[1]粘贴_营销活动'!$G$4:$G$3003,$P147)) | F147: =IF($P147="","",INDEX('[1]粘贴_营销活动'!$N$4:$N$3003,$P147)) | G147: =IF($P147="","",INDEX('[1]粘贴_营销活动'!$O$4:$O$3003,$P147)) | H147: =IF($P147="","",INDEX('[1]粘贴_营销活动'!$M$4:$M$3003,$P147)) | I147: =IF($P147="","",INDEX('[1]粘贴_营销活动'!$P$4:$P$3003,$P147)) | J147: =IF($P147="","",INDEX('[1]粘贴_营销活动'!$I$4:$I$3003,$P147)) | P147: =IFERROR(MATCH(A147,'[1]粘贴_营销活动'!$S$4:$S$3003,0),"")
A148: 8 | B148: =IF($P148="","",INDEX('[1]粘贴_营销活动'!$A$4:$A$3003,$P148)) | C148: =IF($P148="","",INDEX('[1]粘贴_营销活动'!$E$4:$E$3003,$P148)) | D148: =IF($P148="","",INDEX('[1]粘贴_营销活动'!$F$4:$F$3003,$P148)) | E148: =IF($P148="","",INDEX('[1]粘贴_营销活动'!$G$4:$G$3003,$P148)) | F148: =IF($P148="","",INDEX('[1]粘贴_营销活动'!$N$4:$N$3003,$P148)) | G148: =IF($P148="","",INDEX('[1]粘贴_营销活动'!$O$4:$O$3003,$P148)) | H148: =IF($P148="","",INDEX('[1]粘贴_营销活动'!$M$4:$M$3003,$P148)) | I148: =IF($P148="","",INDEX('[1]粘贴_营销活动'!$P$4:$P$3003,$P148)) | J148: =IF($P148="","",INDEX('[1]粘贴_营销活动'!$I$4:$I$3003,$P148)) | P148: =IFERROR(MATCH(A148,'[1]粘贴_营销活动'!$S$4:$S$3003,0),"")
A149: 9 | B149: =IF($P149="","",INDEX('[1]粘贴_营销活动'!$A$4:$A$3003,$P149)) | C149: =IF($P149="","",INDEX('[1]粘贴_营销活动'!$E$4:$E$3003,$P149)) | D149: =IF($P149="","",INDEX('[1]粘贴_营销活动'!$F$4:$F$3003,$P149)) | E149: =IF($P149="","",INDEX('[1]粘贴_营销活动'!$G$4:$G$3003,$P149)) | F149: =IF($P149="","",INDEX('[1]粘贴_营销活动'!$N$4:$N$3003,$P149)) | G149: =IF($P149="","",INDEX('[1]粘贴_营销活动'!$O$4:$O$3003,$P149)) | H149: =IF($P149="","",INDEX('[1]粘贴_营销活动'!$M$4:$M$3003,$P149)) | I149: =IF($P149="","",INDEX('[1]粘贴_营销活动'!$P$4:$P$3003,$P149)) | J149: =IF($P149="","",INDEX('[1]粘贴_营销活动'!$I$4:$I$3003,$P149)) | P149: =IFERROR(MATCH(A149,'[1]粘贴_营销活动'!$S$4:$S$3003,0),"")
A150: 10 | B150: =IF($P150="","",INDEX('[1]粘贴_营销活动'!$A$4:$A$3003,$P150)) | C150: =IF($P150="","",INDEX('[1]粘贴_营销活动'!$E$4:$E$3003,$P150)) | D150: =IF($P150="","",INDEX('[1]粘贴_营销活动'!$F$4:$F$3003,$P150)) | E150: =IF($P150="","",INDEX('[1]粘贴_营销活动'!$G$4:$G$3003,$P150)) | F150: =IF($P150="","",INDEX('[1]粘贴_营销活动'!$N$4:$N$3003,$P150)) | G150: =IF($P150="","",INDEX('[1]粘贴_营销活动'!$O$4:$O$3003,$P150)) | H150: =IF($P150="","",INDEX('[1]粘贴_营销活动'!$M$4:$M$3003,$P150)) | I150: =IF($P150="","",INDEX('[1]粘贴_营销活动'!$P$4:$P$3003,$P150)) | J150: =IF($P150="","",INDEX('[1]粘贴_营销活动'!$I$4:$I$3003,$P150)) | P150: =IFERROR(MATCH(A150,'[1]粘贴_营销活动'!$S$4:$S$3003,0),"")
A151: 11 | B151: =IF($P151="","",INDEX('[1]粘贴_营销活动'!$A$4:$A$3003,$P151)) | C151: =IF($P151="","",INDEX('[1]粘贴_营销活动'!$E$4:$E$3003,$P151)) | D151: =IF($P151="","",INDEX('[1]粘贴_营销活动'!$F$4:$F$3003,$P151)) | E151: =IF($P151="","",INDEX('[1]粘贴_营销活动'!$G$4:$G$3003,$P151)) | F151: =IF($P151="","",INDEX('[1]粘贴_营销活动'!$N$4:$N$3003,$P151)) | G151: =IF($P151="","",INDEX('[1]粘贴_营销活动'!$O$4:$O$3003,$P151)) | H151: =IF($P151="","",INDEX('[1]粘贴_营销活动'!$M$4:$M$3003,$P151)) | I151: =IF($P151="","",INDEX('[1]粘贴_营销活动'!$P$4:$P$3003,$P151)) | J151: =IF($P151="","",INDEX('[1]粘贴_营销活动'!$I$4:$I$3003,$P151)) | P151: =IFERROR(MATCH(A151,'[1]粘贴_营销活动'!$S$4:$S$3003,0),"")
A152: 12 | B152: =IF($P152="","",INDEX('[1]粘贴_营销活动'!$A$4:$A$3003,$P152)) | C152: =IF($P152="","",INDEX('[1]粘贴_营销活动'!$E$4:$E$3003,$P152)) | D152: =IF($P152="","",INDEX('[1]粘贴_营销活动'!$F$4:$F$3003,$P152)) | E152: =IF($P152="","",INDEX('[1]粘贴_营销活动'!$G$4:$G$3003,$P152)) | F152: =IF($P152="","",INDEX('[1]粘贴_营销活动'!$N$4:$N$3003,$P152)) | G152: =IF($P152="","",INDEX('[1]粘贴_营销活动'!$O$4:$O$3003,$P152)) | H152: =IF($P152="","",INDEX('[1]粘贴_营销活动'!$M$4:$M$3003,$P152)) | I152: =IF($P152="","",INDEX('[1]粘贴_营销活动'!$P$4:$P$3003,$P152)) | J152: =IF($P152="","",INDEX('[1]粘贴_营销活动'!$I$4:$I$3003,$P152)) | P152: =IFERROR(MATCH(A152,'[1]粘贴_营销活动'!$S$4:$S$3003,0),"")
... A160: 20 | B160: =IF($P160="","",INDEX('[1]粘贴_营销活动'!$A$4:$A$3003,$P160)) | C160: =IF($P160="","",INDEX('[1]粘贴_营销活动'!$E$4:$E$3003,$P160)) | D160: =IF($P160="","",INDEX('[1]粘贴_营销活动'!$F$4:$F$3003,$P160)) | E160: =IF($P160="","",INDEX('[1]粘贴_营销活动'!$G$4:$G$3003,$P160)) | F160: =IF($P160="","",INDEX('[1]粘贴_营销活动'!$N$4:$N$3003,$P160)) | G160: =IF($P160="","",INDEX('[1]粘贴_营销活动'!$O$4:$O$3003,$P160)) | H160: =IF($P160="","",INDEX('[1]粘贴_营销活动'!$M$4:$M$3003,$P160)) | I160: =IF($P160="","",INDEX('[1]粘贴_营销活动'!$P$4:$P$3003,$P160)) | J160: =IF($P160="","",INDEX('[1]粘贴_营销活动'!$I$4:$I$3003,$P160)) | P160: =IFERROR(MATCH(A160,'[1]粘贴_营销活动'!$S$4:$S$3003,0),"")

Sheet 技术服务费核对
A1: A076 技术服务费核对（百亿补贴技术服务费 1.4% 返还，逐单）
A2: 百亿补贴的单，确认收货时账务明细扣「基础技术服务费 0.6%」＋「百亿补贴技术服务费 1.4%」；1.4% 这部分平台过后按批次返还（返还账单一单一行，账务明细里只有一笔批次总额）。下面「三」逐单看：扣了多少、返了多少、有没有返了又扣回（订单号带 -t01）。返还一般晚一个月左右，所以要把扣费那个月和返还那个月的账务明细都粘进录入本。
A4: 一、汇总
B5: 返还账单：返还笔数 | C5: =COUNTIFS('[1]粘贴_服务费返还'!$O$4:$O$3003,"返还") -> 64 | E5: 账务明细：扣了百亿费的订单数 | H5: ='[1]粘贴_账务明细'!$O$3003 -> 84 | J5: 账务明细最后一天
B6: 返还合计 | C6: =SUMIFS('[1]粘贴_服务费返还'!$M$4:$M$3003,'[1]粘贴_服务费返还'!$O$4:$O$3003,"返还") -> 4637.2 | E6: 实扣百亿费合计 | H6: =SUM(F29:F428) -> 2183.3 | J6: =MAX('[1]粘贴_账务明细'!$H$4:$H$3003) -> 46295.446
B7: 扣回笔数（-t01） | C7: =COUNTIFS('[1]粘贴_服务费返还'!$O$4:$O$3003,"扣回") -> 1 | E7: 订单已退款、不用返（单） | H7: =COUNTIF(J29:J428,"订单已退款*") -> 44
B8: 扣回合计 | C8: =SUMIFS('[1]粘贴_服务费返还'!$M$4:$M$3003,'[1]粘贴_服务费返还'!$O$4:$O$3003,"扣回") -> -50.39 | E8: 已返还（单） | H8: =COUNTIF(J29:J428,"已返还") -> 0
B9: 净返还 | C9: =C6+C8 -> 4586.81 | E9: 已返还金额 | H9: =SUMIFS(G29:G428,J29:J428,"已返还") -> 0
B10: 账务明细里找不到这单（笔） | C10: =COUNTIFS('[1]粘贴_服务费返还'!$P$4:$P$3003,"没有",'[1]粘贴_服务费返还'!$O$4:$O$3003,"返还") -> 64 | E10: 扣了还没返（单） | H10: =COUNTIF(J29:J428,"扣了还没返") -> 40
B11: 金额（扣费在更早月份） | C11: =SUMIFS('[1]粘贴_服务费返还'!$M$4:$M$3003,'[1]粘贴_服务费返还'!$P$4:$P$3003,"没有",'[1]粘贴_服务费返还'!$O$4:$O$3003,"返还") -> 4637.2 | E11: 扣了还没返金额 | H11: =SUMIFS(I29:I428,J29:J428,"扣了还没返") -> 2183.3
E12: 少返／返了又扣回（单） | H12: =COUNTIF(J29:J428,"少返*")+COUNTIF(J29:J428,"返了又扣回*") -> 0
A15: 二、返了又扣回（返还账单里订单号带 -t01 的负数行）
A16: 序 | B16: 账单订单号 | C16: 原订单号 | D16: 金额 | E16: 批次号 | F16: 结算时间 | L16: (位置)
A17: 1 | B17: =IF($L17="","",INDEX('[1]粘贴_服务费返还'!$A$4:$A$3003,$L17)) -> 260819-158733494712735-t01 | C17: =IF($L17="","",INDEX('[1]粘贴_服务费返还'!$N$4:$N$3003,$L17)) -> 260819-158733494712735 | D17: =IF($L17="","",INDEX('[1]粘贴_服务费返还'!$M$4:$M$3003,$L17)) -> -50.39 | E17: =IF($L17="","",INDEX('[1]粘贴_服务费返还'!$I$4:$I$3003,$L17)) -> BO260915078057502 | F17: =IF($L17="","",INDEX('[1]粘贴_服务费返还'!$K$4:$K$3003,$L17)) -> 2026-09-24 08:59:43 | L17: =IFERROR(MATCH(A17,'[1]粘贴_服务费返还'!$S$4:$S$3003,0),"") -> 35
A18: 2 | B18: =IF($L18="","",INDEX('[1]粘贴_服务费返还'!$A$4:$A$3003,$L18)) | C18: =IF($L18="","",INDEX('[1]粘贴_服务费返还'!$N$4:$N$3003,$L18)) | D18: =IF($L18="","",INDEX('[1]粘贴_服务费返还'!$M$4:$M$3003,$L18)) | E18: =IF($L18="","",INDEX('[1]粘贴_服务费返还'!$I$4:$I$3003,$L18)) | F18: =IF($L18="","",INDEX('[1]粘贴_服务费返还'!$K$4:$K$3003,$L18)) | L18: =IFERROR(MATCH(A18,'[1]粘贴_服务费返还'!$S$4:$S$3003,0),"")
A19: 3 | B19: =IF($L19="","",INDEX('[1]粘贴_服务费返还'!$A$4:$A$3003,$L19)) | C19: =IF($L19="","",INDEX('[1]粘贴_服务费返还'!$N$4:$N$3003,$L19)) | D19: =IF($L19="","",INDEX('[1]粘贴_服务费返还'!$M$4:$M$3003,$L19)) | E19: =IF($L19="","",INDEX('[1]粘贴_服务费返还'!$I$4:$I$3003,$L19)) | F19: =IF($L19="","",INDEX('[1]粘贴_服务费返还'!$K$4:$K$3003,$L19)) | L19: =IFERROR(MATCH(A19,'[1]粘贴_服务费返还'!$S$4:$S$3003,0),"")
A20: 4 | B20: =IF($L20="","",INDEX('[1]粘贴_服务费返还'!$A$4:$A$3003,$L20)) | C20: =IF($L20="","",INDEX('[1]粘贴_服务费返还'!$N$4:$N$3003,$L20)) | D20: =IF($L20="","",INDEX('[1]粘贴_服务费返还'!$M$4:$M$3003,$L20)) | E20: =IF($L20="","",INDEX('[1]粘贴_服务费返还'!$I$4:$I$3003,$L20)) | F20: =IF($L20="","",INDEX('[1]粘贴_服务费返还'!$K$4:$K$3003,$L20)) | L20: =IFERROR(MATCH(A20,'[1]粘贴_服务费返还'!$S$4:$S$3003,0),"")
A21: 5 | B21: =IF($L21="","",INDEX('[1]粘贴_服务费返还'!$A$4:$A$3003,$L21)) | C21: =IF($L21="","",INDEX('[1]粘贴_服务费返还'!$N$4:$N$3003,$L21)) | D21: =IF($L21="","",INDEX('[1]粘贴_服务费返还'!$M$4:$M$3003,$L21)) | E21: =IF($L21="","",INDEX('[1]粘贴_服务费返还'!$I$4:$I$3003,$L21)) | F21: =IF($L21="","",INDEX('[1]粘贴_服务费返还'!$K$4:$K$3003,$L21)) | L21: =IFERROR(MATCH(A21,'[1]粘贴_服务费返还'!$S$4:$S$3003,0),"")
A22: 6 | B22: =IF($L22="","",INDEX('[1]粘贴_服务费返还'!$A$4:$A$3003,$L22)) | C22: =IF($L22="","",INDEX('[1]粘贴_服务费返还'!$N$4:$N$3003,$L22)) | D22: =IF($L22="","",INDEX('[1]粘贴_服务费返还'!$M$4:$M$3003,$L22)) | E22: =IF($L22="","",INDEX('[1]粘贴_服务费返还'!$I$4:$I$3003,$L22)) | F22: =IF($L22="","",INDEX('[1]粘贴_服务费返还'!$K$4:$K$3003,$L22)) | L22: =IFERROR(MATCH(A22,'[1]粘贴_服务费返还'!$S$4:$S$3003,0),"")
A23: 7 | B23: =IF($L23="","",INDEX('[1]粘贴_服务费返还'!$A$4:$A$3003,$L23)) | C23: =IF($L23="","",INDEX('[1]粘贴_服务费返还'!$N$4:$N$3003,$L23)) | D23: =IF($L23="","",INDEX('[1]粘贴_服务费返还'!$M$4:$M$3003,$L23)) | E23: =IF($L23="","",INDEX('[1]粘贴_服务费返还'!$I$4:$I$3003,$L23)) | F23: =IF($L23="","",INDEX('[1]粘贴_服务费返还'!$K$4:$K$3003,$L23)) | L23: =IFERROR(MATCH(A23,'[1]粘贴_服务费返还'!$S$4:$S$3003,0),"")
A24: 8 | B24: =IF($L24="","",INDEX('[1]粘贴_服务费返还'!$A$4:$A$3003,$L24)) | C24: =IF($L24="","",INDEX('[1]粘贴_服务费返还'!$N$4:$N$3003,$L24)) | D24: =IF($L24="","",INDEX('[1]粘贴_服务费返还'!$M$4:$M$3003,$L24)) | E24: =IF($L24="","",INDEX('[1]粘贴_服务费返还'!$I$4:$I$3003,$L24)) | F24: =IF($L24="","",INDEX('[1]粘贴_服务费返还'!$K$4:$K$3003,$L24)) | L24: =IFERROR(MATCH(A24,'[1]粘贴_服务费返还'!$S$4:$S$3003,0),"")
A27: 三、逐单：账务明细里扣了「百亿补贴技术服务费」的订单（最多 400 单）
A28: 序 | B28: 订单号 | C28: 扣费时间 | D28: 订单价 | E28: 应返(1.4%) | F28: 实扣百亿费 | G28: 已返还 | H28: 扣回 | I28: 待返 | J28: 状态 | K28: 距账务明细 最后一天(天) | L28: (位置)
A29: 1 | B29: =IF($L29="","",INDEX('[1]粘贴_账务明细'!$A$4:$A$3003,$L29)) -> 260925-191061040790069 | C29: =IF($L29="","",INDEX('[1]粘贴_账务明细'!$H$4:$H$3003,$L29)) -> 46294.771 | D29: =IF($L29="","",SUMIFS('[1]粘贴_账务明细'!$K$4:$K$3003,'[1]粘贴_账务明细'!$A$4:$A$3003,$B29,'[1]粘贴_账务明细'!$L$4:$L$3003,"订单收入")+SUMIFS('[1]粘贴_账务明细'!$K$4:$K$3003,'[1]粘贴_账务明细'!$A$4:$A$3003,$B29,'[1]粘贴_账务明细'!$L$4:$L$3003,"优惠券结算")) -> 3499 | E29: =IF($L29="","",ROUND(D29*0.014,2)) -> 48.99 | F29: =IF($L29="","",-SUMIFS('[1]粘贴_账务明细'!$K$4:$K$3003,'[1]粘贴_账务明细'!$A$4:$A$3003,$B29,'[1]粘贴_账务明细'!$L$4:$L$3003,"百亿补贴技术服务费")) -> 48.99 | G29: =IF($L29="","",SUMIFS('[1]粘贴_服务费返还'!$M$4:$M$3003,'[1]粘贴_服务费返还'!$N$4:$N$3003,$B29,'[1]粘贴_服务费返还'!$O$4:$O$3003,"返还")) -> 0 | H29: =IF($L29="","",SUMIFS('[1]粘贴_服务费返还'!$M$4:$M$3003,'[1]粘贴_服务费返还'!$N$4:$N$3003,$B29,'[1]粘贴_服务费返还'!$O$4:$O$3003,"扣回")) -> 0 | I29: =IF($L29="","",ROUND(F29-G29-H29,2)) -> 48.99 | J29: =IF($L29="","",IF(F29<0.005,"订单已退款，百亿费已原路退回，不用返",IF(G29+H29>=F29-0.01,"已返还",IF(H29<0,"返了又扣回(-t01)，问客服",IF(G29>0,"少返 "&TEXT(I29,"0.00"),"扣了还没返"))))) -> 扣了还没返 | K29: =IF($L29="","",INT($J$6)-INT(C29)) -> 1 | L29: =IF(A29>$H$5,"",MATCH(A29,'[1]粘贴_账务明细'!$O$4:$O$3003,0)) -> 5
A30: 2 | B30: =IF($L30="","",INDEX('[1]粘贴_账务明细'!$A$4:$A$3003,$L30)) -> 260926-409783560592068 | C30: =IF($L30="","",INDEX('[1]粘贴_账务明细'!$H$4:$H$3003,$L30)) -> 46294.706 | D30: =IF($L30="","",SUMIFS('[1]粘贴_账务明细'!$K$4:$K$3003,'[1]粘贴_账务明细'!$A$4:$A$3003,$B30,'[1]粘贴_账务明细'!$L$4:$L$3003,"订单收入")+SUMIFS('[1]粘贴_账务明细'!$K$4:$K$3003,'[1]粘贴_账务明细'!$A$4:$A$3003,$B30,'[1]粘贴_账务明细'!$L$4:$L$3003,"优惠券结算")) -> 3169 | E30: =IF($L30="","",ROUND(D30*0.014,2)) -> 44.37 | F30: =IF($L30="","",-SUMIFS('[1]粘贴_账务明细'!$K$4:$K$3003,'[1]粘贴_账务明细'!$A$4:$A$3003,$B30,'[1]粘贴_账务明细'!$L$4:$L$3003,"百亿补贴技术服务费")) -> 44.37 | G30: =IF($L30="","",SUMIFS('[1]粘贴_服务费返还'!$M$4:$M$3003,'[1]粘贴_服务费返还'!$N$4:$N$3003,$B30,'[1]粘贴_服务费返还'!$O$4:$O$3003,"返还")) -> 0 | H30: =IF($L30="","",SUMIFS('[1]粘贴_服务费返还'!$M$4:$M$3003,'[1]粘贴_服务费返还'!$N$4:$N$3003,$B30,'[1]粘贴_服务费返还'!$O$4:$O$3003,"扣回")) -> 0 | I30: =IF($L30="","",ROUND(F30-G30-H30,2)) -> 44.37 | J30: =IF($L30="","",IF(F30<0.005,"订单已退款，百亿费已原路退回，不用返",IF(G30+H30>=F30-0.01,"已返还",IF(H30<0,"返了又扣回(-t01)，问客服",IF(G30>0,"少返 "&TEXT(I30,"0.00"),"扣了还没返"))))) -> 扣了还没返 | K30: =IF($L30="","",INT($J$6)-INT(C30)) -> 1 | L30: =IF(A30>$H$5,"",MATCH(A30,'[1]粘贴_账务明细'!$O$4:$O$3003,0)) -> 6
A31: 3 | B31: =IF($L31="","",INDEX('[1]粘贴_账务明细'!$A$4:$A$3003,$L31)) -> 260922-289307420991455 | C31: =IF($L31="","",INDEX('[1]粘贴_账务明细'!$H$4:$H$3003,$L31)) -> 46294.671 | D31: =IF($L31="","",SUMIFS('[1]粘贴_账务明细'!$K$4:$K$3003,'[1]粘贴_账务明细'!$A$4:$A$3003,$B31,'[1]粘贴_账务明细'!$L$4:$L$3003,"订单收入")+SUMIFS('[1]粘贴_账务明细'!$K$4:$K$3003,'[1]粘贴_账务明细'!$A$4:$A$3003,$B31,'[1]粘贴_账务明细'!$L$4:$L$3003,"优惠券结算")) -> 3589 | E31: =IF($L31="","",ROUND(D31*0.014,2)) -> 50.25 | F31: =IF($L31="","",-SUMIFS('[1]粘贴_账务明细'!$K$4:$K$3003,'[1]粘贴_账务明细'!$A$4:$A$3003,$B31,'[1]粘贴_账务明细'!$L$4:$L$3003,"百亿补贴技术服务费")) -> 50.25 | G31: =IF($L31="","",SUMIFS('[1]粘贴_服务费返还'!$M$4:$M$3003,'[1]粘贴_服务费返还'!$N$4:$N$3003,$B31,'[1]粘贴_服务费返还'!$O$4:$O$3003,"返还")) -> 0 | H31: =IF($L31="","",SUMIFS('[1]粘贴_服务费返还'!$M$4:$M$3003,'[1]粘贴_服务费返还'!$N$4:$N$3003,$B31,'[1]粘贴_服务费返还'!$O$4:$O$3003,"扣回")) -> 0 | I31: =IF($L31="","",ROUND(F31-G31-H31,2)) -> 50.25 | J31: =IF($L31="","",IF(F31<0.005,"订单已退款，百亿费已原路退回，不用返",IF(G31+H31>=F31-0.01,"已返还",IF(H31<0,"返了又扣回(-t01)，问客服",IF(G31>0,"少返 "&TEXT(I31,"0.00"),"扣了还没返"))))) -> 扣了还没返 | K31: =IF($L31="","",INT($J$6)-INT(C31)) -> 1 | L31: =IF(A31>$H$5,"",MATCH(A31,'[1]粘贴_账务明细'!$O$4:$O$3003,0)) -> 9
A32: 4 | B32: =IF($L32="","",INDEX('[1]粘贴_账务明细'!$A$4:$A$3003,$L32)) -> 260926-467518103081461 | C32: =IF($L32="","",INDEX('[1]粘贴_账务明细'!$H$4:$H$3003,$L32)) -> 46294.435 | D32: =IF($L32="","",SUMIFS('[1]粘贴_账务明细'!$K$4:$K$3003,'[1]粘贴_账务明细'!$A$4:$A$3003,$B32,'[1]粘贴_账务明细'!$L$4:$L$3003,"订单收入")+SUMIFS('[1]粘贴_账务明细'!$K$4:$K$3003,'[1]粘贴_账务明细'!$A$4:$A$3003,$B32,'[1]粘贴_账务明细'!$L$4:$L$3003,"优惠券结算")) -> 3589 | E32: =IF($L32="","",ROUND(D32*0.014,2)) -> 50.25 | F32: =IF($L32="","",-SUMIFS('[1]粘贴_账务明细'!$K$4:$K$3003,'[1]粘贴_账务明细'!$A$4:$A$3003,$B32,'[1]粘贴_账务明细'!$L$4:$L$3003,"百亿补贴技术服务费")) -> 50.25 | G32: =IF($L32="","",SUMIFS('[1]粘贴_服务费返还'!$M$4:$M$3003,'[1]粘贴_服务费返还'!$N$4:$N$3003,$B32,'[1]粘贴_服务费返还'!$O$4:$O$3003,"返还")) -> 0 | H32: =IF($L32="","",SUMIFS('[1]粘贴_服务费返还'!$M$4:$M$3003,'[1]粘贴_服务费返还'!$N$4:$N$3003,$B32,'[1]粘贴_服务费返还'!$O$4:$O$3003,"扣回")) -> 0 | I32: =IF($L32="","",ROUND(F32-G32-H32,2)) -> 50.25 | J32: =IF($L32="","",IF(F32<0.005,"订单已退款，百亿费已原路退回，不用返",IF(G32+H32>=F32-0.01,"已返还",IF(H32<0,"返了又扣回(-t01)，问客服",IF(G32>0,"少返 "&TEXT(I32,"0.00"),"扣了还没返"))))) -> 扣了还没返 | K32: =IF($L32="","",INT($J$6)-INT(C32)) -> 1 | L32: =IF(A32>$H$5,"",MATCH(A32,'[1]粘贴_账务明细'!$O$4:$O$3003,0)) -> 15
A33: 5 | B33: =IF($L33="","",INDEX('[1]粘贴_账务明细'!$A$4:$A$3003,$L33)) -> 260924-421034770800999 | C33: =IF($L33="","",INDEX('[1]粘贴_账务明细'!$H$4:$H$3003,$L33)) -> 46294.021 | D33: =IF($L33="","",SUMIFS('[1]粘贴_账务明细'!$K$4:$K$3003,'[1]粘贴_账务明细'!$A$4:$A$3003,$B33,'[1]粘贴_账务明细'!$L$4:$L$3003,"订单收入")+SUMIFS('[1]粘贴_账务明细'!$K$4:$K$3003,'[1]粘贴_账务明细'!$A$4:$A$3003,$B33,'[1]粘贴_账务明细'!$L$4:$L$3003,"优惠券结算")) -> 3589 | E33: =IF($L33="","",ROUND(D33*0.014,2)) -> 50.25 | F33: =IF($L33="","",-SUMIFS('[1]粘贴_账务明细'!$K$4:$K$3003,'[1]粘贴_账务明细'!$A$4:$A$3003,$B33,'[1]粘贴_账务明细'!$L$4:$L$3003,"百亿补贴技术服务费")) -> 50.25 | G33: =IF($L33="","",SUMIFS('[1]粘贴_服务费返还'!$M$4:$M$3003,'[1]粘贴_服务费返还'!$N$4:$N$3003,$B33,'[1]粘贴_服务费返还'!$O$4:$O$3003,"返还")) -> 0 | H33: =IF($L33="","",SUMIFS('[1]粘贴_服务费返还'!$M$4:$M$3003,'[1]粘贴_服务费返还'!$N$4:$N$3003,$B33,'[1]粘贴_服务费返还'!$O$4:$O$3003,"扣回")) -> 0 | I33: =IF($L33="","",ROUND(F33-G33-H33,2)) -> 50.25 | J33: =IF($L33="","",IF(F33<0.005,"订单已退款，百亿费已原路退回，不用返",IF(G33+H33>=F33-0.01,"已返还",IF(H33<0,"返了又扣回(-t01)，问客服",IF(G33>0,"少返 "&TEXT(I33,"0.00"),"扣了还没返"))))) -> 扣了还没返 | K33: =IF($L33="","",INT($J$6)-INT(C33)) -> 1 | L33: =IF(A33>$H$5,"",MATCH(A33,'[1]粘贴_账务明细'!$O$4:$O$3003,0)) -> 18
A34: 6 | B34: =IF($L34="","",INDEX('[1]粘贴_账务明细'!$A$4:$A$3003,$L34)) -> 260928-546318641462943 | C34: =IF($L34="","",INDEX('[1]粘贴_账务明细'!$H$4:$H$3003,$L34)) -> 46293.692 | D34: =IF($L34="","",SUMIFS('[1]粘贴_账务明细'!$K$4:$K$3003,'[1]粘贴_账务明细'!$A$4:$A$3003,$B34,'[1]粘贴_账务明细'!$L$4:$L$3003,"订单收入")+SUMIFS('[1]粘贴_账务明细'!$K$4:$K$3003,'[1]粘贴_账务明细'!$A$4:$A$3003,$B34,'[1]粘贴_账务明细'!$L$4:$L$3003,"优惠券结算")) -> 3019 | E34: =IF($L34="","",ROUND(D34*0.014,2)) -> 42.27 | F34: =IF($L34="","",-SUMIFS('[1]粘贴_账务明细'!$K$4:$K$3003,'[1]粘贴_账务明细'!$A$4:$A$3003,$B34,'[1]粘贴_账务明细'!$L$4:$L$3003,"百亿补贴技术服务费")) -> 0 | G34: =IF($L34="","",SUMIFS('[1]粘贴_服务费返还'!$M$4:$M$3003,'[1]粘贴_服务费返还'!$N$4:$N$3003,$B34,'[1]粘贴_服务费返还'!$O$4:$O$3003,"返还")) -> 0 | H34: =IF($L34="","",SUMIFS('[1]粘贴_服务费返还'!$M$4:$M$3003,'[1]粘贴_服务费返还'!$N$4:$N$3003,$B34,'[1]粘贴_服务费返还'!$O$4:$O$3003,"扣回")) -> 0 | I34: =IF($L34="","",ROUND(F34-G34-H34,2)) -> 0 | J34: =IF($L34="","",IF(F34<0.005,"订单已退款，百亿费已原路退回，不用返",IF(G34+H34>=F34-0.01,"已返还",IF(H34<0,"返了又扣回(-t01)，问客服",IF(G34>0,"少返 "&TEXT(I34,"0.00"),"扣了还没返"))))) -> 订单已退款，百亿费已原路退回，不用返 | K34: =IF($L34="","",INT($J$6)-INT(C34)) -> 2 | L34: =IF(A34>$H$5,"",MATCH(A34,'[1]粘贴_账务明细'!$O$4:$O$3003,0)) -> 23
A35: 7 | B35: =IF($L35="","",INDEX('[1]粘贴_账务明细'!$A$4:$A$3003,$L35)) -> 260925-504543394092041 | C35: =IF($L35="","",INDEX('[1]粘贴_账务明细'!$H$4:$H$3003,$L35)) -> 46292.546 | D35: =IF($L35="","",SUMIFS('[1]粘贴_账务明细'!$K$4:$K$3003,'[1]粘贴_账务明细'!$A$4:$A$3003,$B35,'[1]粘贴_账务明细'!$L$4:$L$3003,"订单收入")+SUMIFS('[1]粘贴_账务明细'!$K$4:$K$3003,'[1]粘贴_账务明细'!$A$4:$A$3003,$B35,'[1]粘贴_账务明细'!$L$4:$L$3003,"优惠券结算")) -> 3499 | E35: =IF($L35="","",ROUND(D35*0.014,2)) -> 48.99 | F35: =IF($L35="","",-SUMIFS('[1]粘贴_账务明细'!$K$4:$K$3003,'[1]粘贴_账务明细'!$A$4:$A$3003,$B35,'[1]粘贴_账务明细'!$L$4:$L$3003,"百亿补贴技术服务费")) -> 48.99 | G35: =IF($L35="","",SUMIFS('[1]粘贴_服务费返还'!$M$4:$M$3003,'[1]粘贴_服务费返还'!$N$4:$N$3003,$B35,'[1]粘贴_服务费返还'!$O$4:$O$3003,"返还")) -> 0 | H35: =IF($L35="","",SUMIFS('[1]粘贴_服务费返还'!$M$4:$M$3003,'[1]粘贴_服务费返还'!$N$4:$N$3003,$B35,'[1]粘贴_服务费返还'!$O$4:$O$3003,"扣回")) -> 0 | I35: =IF($L35="","",ROUND(F35-G35-H35,2)) -> 48.99 | J35: =IF($L35="","",IF(F35<0.005,"订单已退款，百亿费已原路退回，不用返",IF(G35+H35>=F35-0.01,"已返还",IF(H35<0,"返了又扣回(-t01)，问客服",IF(G35>0,"少返 "&TEXT(I35,"0.00"),"扣了还没返"))))) -> 扣了还没返 | K35: =IF($L35="","",INT($J$6)-INT(C35)) -> 3 | L35: =IF(A35>$H$5,"",MATCH(A35,'[1]粘贴_账务明细'!$O$4:$O$3003,0)) -> 29
A36: 8 | B36: =IF($L36="","",INDEX('[1]粘贴_账务明细'!$A$4:$A$3003,$L36)) -> 260926-645083962921461 | C36: =IF($L36="","",INDEX('[1]粘贴_账务明细'!$H$4:$H$3003,$L36)) -> 46291.823 | D36: =IF($L36="","",SUMIFS('[1]粘贴_账务明细'!$K$4:$K$3003,'[1]粘贴_账务明细'!$A$4:$A$3003,$B36,'[1]粘贴_账务明细'!$L$4:$L$3003,"订单收入")+SUMIFS('[1]粘贴_账务明细'!$K$4:$K$3003,'[1]粘贴_账务明细'!$A$4:$A$3003,$B36,'[1]粘贴_账务明细'!$L$4:$L$3003,"优惠券结算")) -> 3589 | E36: =IF($L36="","",ROUND(D36*0.014,2)) -> 50.25 | F36: =IF($L36="","",-SUMIFS('[1]粘贴_账务明细'!$K$4:$K$3003,'[1]粘贴_账务明细'!$A$4:$A$3003,$B36,'[1]粘贴_账务明细'!$L$4:$L$3003,"百亿补贴技术服务费")) -> 0 | G36: =IF($L36="","",SUMIFS('[1]粘贴_服务费返还'!$M$4:$M$3003,'[1]粘贴_服务费返还'!$N$4:$N$3003,$B36,'[1]粘贴_服务费返还'!$O$4:$O$3003,"返还")) -> 0 | H36: =IF($L36="","",SUMIFS('[1]粘贴_服务费返还'!$M$4:$M$3003,'[1]粘贴_服务费返还'!$N$4:$N$3003,$B36,'[1]粘贴_服务费返还'!$O$4:$O$3003,"扣回")) -> 0 | I36: =IF($L36="","",ROUND(F36-G36-H36,2)) -> 0 | J36: =IF($L36="","",IF(F36<0.005,"订单已退款，百亿费已原路退回，不用返",IF(G36+H36>=F36-0.01,"已返还",IF(H36<0,"返了又扣回(-t01)，问客服",IF(G36>0,"少返 "&TEXT(I36,"0.00"),"扣了还没返"))))) -> 订单已退款，百亿费已原路退回，不用返 | K36: =IF($L36="","",INT($J$6)-INT(C36)) -> 4 | L36: =IF(A36>$H$5,"",MATCH(A36,'[1]粘贴_账务明细'!$O$4:$O$3003,0)) -> 34
A37: 9 | B37: =IF($L37="","",INDEX('[1]粘贴_账务明细'!$A$4:$A$3003,$L37)) -> 260924-102770983250639 | C37: =IF($L37="","",INDEX('[1]粘贴_账务明细'!$H$4:$H$3003,$L37)) -> 46291.803 | D37: =IF($L37="","",SUMIFS('[1]粘贴_账务明细'!$K$4:$K$3003,'[1]粘贴_账务明细'!$A$4:$A$3003,$B37,'[1]粘贴_账务明细'!$L$4:$L$3003,"订单收入")+SUMIFS('[1]粘贴_账务明细'!$K$4:$K$3003,'[1]粘贴_账务明细'!$A$4:$A$3003,$B37,'[1]粘贴_账务明细'!$L$4:$L$3003,"优惠券结算")) -> 3499 | E37: =IF($L37="","",ROUND(D37*0.014,2)) -> 48.99 | F37: =IF($L37="","",-SUMIFS('[1]粘贴_账务明细'!$K$4:$K$3003,'[1]粘贴_账务明细'!$A$4:$A$3003,$B37,'[1]粘贴_账务明细'!$L$4:$L$3003,"百亿补贴技术服务费")) -> 48.99 | G37: =IF($L37="","",SUMIFS('[1]粘贴_服务费返还'!$M$4:$M$3003,'[1]粘贴_服务费返还'!$N$4:$N$3003,$B37,'[1]粘贴_服务费返还'!$O$4:$O$3003,"返还")) -> 0 | H37: =IF($L37="","",SUMIFS('[1]粘贴_服务费返还'!$M$4:$M$3003,'[1]粘贴_服务费返还'!$N$4:$N$3003,$B37,'[1]粘贴_服务费返还'!$O$4:$O$3003,"扣回")) -> 0 | I37: =IF($L37="","",ROUND(F37-G37-H37,2)) -> 48.99 | J37: =IF($L37="","",IF(F37<0.005,"订单已退款，百亿费已原路退回，不用返",IF(G37+H37>=F37-0.01,"已返还",IF(H37<0,"返了又扣回(-t01)，问客服",IF(G37>0,"少返 "&TEXT(I37,"0.00"),"扣了还没返"))))) -> 扣了还没返 | K37: =IF($L37="","",INT($J$6)-INT(C37)) -> 4 | L37: =IF(A37>$H$5,"",MATCH(A37,'[1]粘贴_账务明细'!$O$4:$O$3003,0)) -> 39
A38: 10 | B38: =IF($L38="","",INDEX('[1]粘贴_账务明细'!$A$4:$A$3003,$L38)) -> 260924-347508652384062 | C38: =IF($L38="","",INDEX('[1]粘贴_账务明细'!$H$4:$H$3003,$L38)) -> 46291.695 | D38: =IF($L38="","",SUMIFS('[1]粘贴_账务明细'!$K$4:$K$3003,'[1]粘贴_账务明细'!$A$4:$A$3003,$B38,'[1]粘贴_账务明细'!$L$4:$L$3003,"订单收入")+SUMIFS('[1]粘贴_账务明细'!$K$4:$K$3003,'[1]粘贴_账务明细'!$A$4:$A$3003,$B38,'[1]粘贴_账务明细'!$L$4:$L$3003,"优惠券结算")) -> 3499 | E38: =IF($L38="","",ROUND(D38*0.014,2)) -> 48.99 | F38: =IF($L38="","",-SUMIFS('[1]粘贴_账务明细'!$K$4:$K$3003,'[1]粘贴_账务明细'!$A$4:$A$3003,$B38,'[1]粘贴_账务明细'!$L$4:$L$3003,"百亿补贴技术服务费")) -> 48.99 | G38: =IF($L38="","",SUMIFS('[1]粘贴_服务费返还'!$M$4:$M$3003,'[1]粘贴_服务费返还'!$N$4:$N$3003,$B38,'[1]粘贴_服务费返还'!$O$4:$O$3003,"返还")) -> 0 | H38: =IF($L38="","",SUMIFS('[1]粘贴_服务费返还'!$M$4:$M$3003,'[1]粘贴_服务费返还'!$N$4:$N$3003,$B38,'[1]粘贴_服务费返还'!$O$4:$O$3003,"扣回")) -> 0 | I38: =IF($L38="","",ROUND(F38-G38-H38,2)) -> 48.99 | J38: =IF($L38="","",IF(F38<0.005,"订单已退款，百亿费已原路退回，不用返",IF(G38+H38>=F38-0.01,"已返还",IF(H38<0,"返了又扣回(-t01)，问客服",IF(G38>0,"少返 "&TEXT(I38,"0.00"),"扣了还没返"))))) -> 扣了还没返 | K38: =IF($L38="","",INT($J$6)-INT(C38)) -> 4 | L38: =IF(A38>$H$5,"",MATCH(A38,'[1]粘贴_账务明细'!$O$4:$O$3003,0)) -> 43
A39: 11 | B39: =IF($L39="","",INDEX('[1]粘贴_账务明细'!$A$4:$A$3003,$L39)) -> 260923-040139507320110 | C39: =IF($L39="","",INDEX('[1]粘贴_账务明细'!$H$4:$H$3003,$L39)) -> 46291.525 | D39: =IF($L39="","",SUMIFS('[1]粘贴_账务明细'!$K$4:$K$3003,'[1]粘贴_账务明细'!$A$4:$A$3003,$B39,'[1]粘贴_账务明细'!$L$4:$L$3003,"订单收入")+SUMIFS('[1]粘贴_账务明细'!$K$4:$K$3003,'[1]粘贴_账务明细'!$A$4:$A$3003,$B39,'[1]粘贴_账务明细'!$L$4:$L$3003,"优惠券结算")) -> 3499 | E39: =IF($L39="","",ROUND(D39*0.014,2)) -> 48.99 | F39: =IF($L39="","",-SUMIFS('[1]粘贴_账务明细'!$K$4:$K$3003,'[1]粘贴_账务明细'!$A$4:$A$3003,$B39,'[1]粘贴_账务明细'!$L$4:$L$3003,"百亿补贴技术服务费")) -> 0 | G39: =IF($L39="","",SUMIFS('[1]粘贴_服务费返还'!$M$4:$M$3003,'[1]粘贴_服务费返还'!$N$4:$N$3003,$B39,'[1]粘贴_服务费返还'!$O$4:$O$3003,"返还")) -> 0 | H39: =IF($L39="","",SUMIFS('[1]粘贴_服务费返还'!$M$4:$M$3003,'[1]粘贴_服务费返还'!$N$4:$N$3003,$B39,'[1]粘贴_服务费返还'!$O$4:$O$3003,"扣回")) -> 0 | I39: =IF($L39="","",ROUND(F39-G39-H39,2)) -> 0 | J39: =IF($L39="","",IF(F39<0.005,"订单已退款，百亿费已原路退回，不用返",IF(G39+H39>=F39-0.01,"已返还",IF(H39<0,"返了又扣回(-t01)，问客服",IF(G39>0,"少返 "&TEXT(I39,"0.00"),"扣了还没返"))))) -> 订单已退款，百亿费已原路退回，不用返 | K39: =IF($L39="","",INT($J$6)-INT(C39)) -> 4 | L39: =IF(A39>$H$5,"",MATCH(A39,'[1]粘贴_账务明细'!$O$4:$O$3003,0)) -> 48
A40: 12 | B40: =IF($L40="","",INDEX('[1]粘贴_账务明细'!$A$4:$A$3003,$L40)) -> 260926-177765127802385 | C40: =IF($L40="","",INDEX('[1]粘贴_账务明细'!$H$4:$H$3003,$L40)) -> 46291.1 | D40: =IF($L40="","",SUMIFS('[1]粘贴_账务明细'!$K$4:$K$3003,'[1]粘贴_账务明细'!$A$4:$A$3003,$B40,'[1]粘贴_账务明细'!$L$4:$L$3003,"订单收入")+SUMIFS('[1]粘贴_账务明细'!$K$4:$K$3003,'[1]粘贴_账务明细'!$A$4:$A$3003,$B40,'[1]粘贴_账务明细'!$L$4:$L$3003,"优惠券结算")) -> 3069 | E40: =IF($L40="","",ROUND(D40*0.014,2)) -> 42.97 | F40: =IF($L40="","",-SUMIFS('[1]粘贴_账务明细'!$K$4:$K$3003,'[1]粘贴_账务明细'!$A$4:$A$3003,$B40,'[1]粘贴_账务明细'!$L$4:$L$3003,"百亿补贴技术服务费")) -> 0 | G40: =IF($L40="","",SUMIFS('[1]粘贴_服务费返还'!$M$4:$M$3003,'[1]粘贴_服务费返还'!$N$4:$N$3003,$B40,'[1]粘贴_服务费返还'!$O$4:$O$3003,"返还")) -> 0 | H40: =IF($L40="","",SUMIFS('[1]粘贴_服务费返还'!$M$4:$M$3003,'[1]粘贴_服务费返还'!$N$4:$N$3003,$B40,'[1]粘贴_服务费返还'!$O$4:$O$3003,"扣回")) -> 0 | I40: =IF($L40="","",ROUND(F40-G40-H40,2)) -> 0 | J40: =IF($L40="","",IF(F40<0.005,"订单已退款，百亿费已原路退回，不用返",IF(G40+H40>=F40-0.01,"已返还",IF(H40<0,"返了又扣回(-t01)，问客服",IF(G40>0,"少返 "&TEXT(I40,"0.00"),"扣了还没返"))))) -> 订单已退款，百亿费已原路退回，不用返 | K40: =IF($L40="","",INT($J$6)-INT(C40)) -> 4 | L40: =IF(A40>$H$5,"",MATCH(A40,'[1]粘贴_账务明细'!$O$4:$O$3003,0)) -> 54
... A428: 400 | B428: =IF($L428="","",INDEX('[1]粘贴_账务明细'!$A$4:$A$3003,$L428)) | C428: =IF($L428="","",INDEX('[1]粘贴_账务明细'!$H$4:$H$3003,$L428)) | D428: =IF($L428="","",SUMIFS('[1]粘贴_账务明细'!$K$4:$K$3003,'[1]粘贴_账务明细'!$A$4:$A$3003,$B428,'[1]粘贴_账务明细'!$L$4:$L$3003,"订单收入")+SUMIFS('[1]粘贴_账务明细'!$K$4:$K$3003,'[1]粘贴_账务明细'!$A$4:$A$3003,$B428,'[1]粘贴_账务明细'!$L$4:$L$3003,"优惠券结算")) | E428: =IF($L428="","",ROUND(D428*0.014,2)) | F428: =IF($L428="","",-SUMIFS('[1]粘贴_账务明细'!$K$4:$K$3003,'[1]粘贴_账务明细'!$A$4:$A$3003,$B428,'[1]粘贴_账务明细'!$L$4:$L$3003,"百亿补贴技术服务费")) | G428: =IF($L428="","",SUMIFS('[1]粘贴_服务费返还'!$M$4:$M$3003,'[1]粘贴_服务费返还'!$N$4:$N$3003,$B428,'[1]粘贴_服务费返还'!$O$4:$O$3003,"返还")) | H428: =IF($L428="","",SUMIFS('[1]粘贴_服务费返还'!$M$4:$M$3003,'[1]粘贴_服务费返还'!$N$4:$N$3003,$B428,'[1]粘贴_服务费返还'!$O$4:$O$3003,"扣回")) | I428: =IF($L428="","",ROUND(F428-G428-H428,2)) | J428: =IF($L428="","",IF(F428<0.005,"订单已退款，百亿费已原路退回，不用返",IF(G428+H428>=F428-0.01,"已返还",IF(H428<0,"返了又扣回(-t01)，问客服",IF(G428>0,"少返 "&TEXT(I428,"0.00"),"扣了还没返"))))) | K428: =IF($L428="","",INT($J$6)-INT(C428)) | L428: =IF(A428>$H$5,"",MATCH(A428,'[1]粘贴_账务明细'!$O$4:$O$3003,0))

Sheet 库存
A1: A076 库存（期初＋采购－销售＝结存）
A2: 成本算法：全期一次加权平均——每个商品 加权单价＝（期初金额＋采购金额）÷（期初数量＋采购数量），销售成本＝销售数量×加权单价。期初取的是上传的管家婆库存表（你说不太准），盘点后到录入本「基础资料」改期初数量、单价。右边 12 列是年份内各月销售数量（利润表算各月成本用）。采购、销售都是全部明细（不按年份截）；建议一年一套录入本，年底把结存抄成下一年期初。
A4: 商品名称 | B4: 品牌 | C4: 期初数量 | D4: 期初金额 | E4: 采购数量 | F4: 采购金额 | G4: 销售数量 | H4: 加权单价 | I4: 销售成本 | J4: 结存数量 | K4: 结存金额 | L4: 提示 | M4: 1 | N4: 2 | O4: 3 | P4: 4 | Q4: 5 | R4: 6 | S4: 7 | T4: 8 | U4: 9 | V4: 10 | W4: 11 | X4: 12
A5: 合计 | C5: =SUM(C6:C305) -> 5081 | D5: =SUM(D6:D305) -> 12275944 | E5: =SUM(E6:E305) -> 2584302.5 | F5: =SUM(F6:F305) -> 2813917.8 | G5: =SUM(G6:G305) -> 2584260.5 | I5: =SUM(I6:I305) -> 3234755.8 | J5: =SUM(J6:J305) -> 5123 | K5: =SUM(K6:K305) -> 11855106 | L5: =IF(ROUND(SUM('[1]销售出库'!$R$4:$R$2003)-G5,2)<>0,"有 "&ROUND(SUM('[1]销售出库'!$R$4:$R$2003)-G5,2)&" 个销售数量的商品不在基础资料","")&IF(ROUND(SUM('[1]采购入库'!$U$4:$U$2003)-E5,2)<>0,"；采购有 "&ROUND(SUM('[1]采购入库'!$U$4:$U$2003)-E5,2)&" 个不在基础资料","") | M5: =SUM(M6:M305) -> 0 | N5: =SUM(N6:N305) -> 0 | O5: =SUM(O6:O305) -> 0 | P5: =SUM(P6:P305) -> 0 | Q5: =SUM(Q6:Q305) -> 0 | R5: =SUM(R6:R305) -> 0 | S5: =SUM(S6:S305) -> 0 | T5: =SUM(T6:T305) -> 0 | ... X5: =SUM(X6:X305) -> 0
A6: =IF('[1]基础资料'!$P$5="","",'[1]基础资料'!$P$5) -> 华硕无双M3452UA8845 16+512银色（原封） | B6: =IF(A6="","",'[1]基础资料'!$Q$5&"") -> 华硕 | C6: =IF(A6="",0,N('[1]基础资料'!$S$5)) -> 8 | D6: =IF(A6="",0,N('[1]基础资料'!$U$5)) -> 36560 | E6: =IF(A6="",0,SUMIFS('[1]采购入库'!$U$4:$U$2003,'[1]采购入库'!$I$4:$I$2003,$A6)) -> 42 | F6: =IF(A6="",0,SUMIFS('[1]采购入库'!$V$4:$V$2003,'[1]采购入库'!$I$4:$I$2003,$A6)) -> 191940 | G6: =IF(A6="",0,SUMIFS('[1]销售出库'!$R$4:$R$2003,'[1]销售出库'!$H$4:$H$2003,$A6)) -> 34 | H6: =IF(C6+E6>0,ROUND((D6+F6)/(C6+E6),4),0) -> 4570 | I6: =ROUND(G6*H6,2) -> 155380 | J6: =C6+E6-G6 -> 16 | K6: =ROUND(D6+F6-I6,2) -> 73120 | L6: =IF(A6="","",IF(J6<0,"负库存：漏记采购或期初不准",IF(AND(G6>0,C6+E6=0),"没进货就卖了",""))) | M6: =IF($A6="",0,SUMIFS('[1]销售出库'!$R$4:$R$2003,'[1]销售出库'!$H$4:$H$2003,$A6,'[1]销售出库'!$Q$4:$Q$2003,'首页'!$B$4*100+M$4)) -> 0 | N6: =IF($A6="",0,SUMIFS('[1]销售出库'!$R$4:$R$2003,'[1]销售出库'!$H$4:$H$2003,$A6,'[1]销售出库'!$Q$4:$Q$2003,'首页'!$B$4*100+N$4)) -> 0 | O6: =IF($A6="",0,SUMIFS('[1]销售出库'!$R$4:$R$2003,'[1]销售出库'!$H$4:$H$2003,$A6,'[1]销售出库'!$Q$4:$Q$2003,'首页'!$B$4*100+O$4)) -> 0 | P6: =IF($A6="",0,SUMIFS('[1]销售出库'!$R$4:$R$2003,'[1]销售出库'!$H$4:$H$2003,$A6,'[1]销售出库'!$Q$4:$Q$2003,'首页'!$B$4*100+P$4)) -> 0 | Q6: =IF($A6="",0,SUMIFS('[1]销售出库'!$R$4:$R$2003,'[1]销售出库'!$H$4:$H$2003,$A6,'[1]销售出库'!$Q$4:$Q$2003,'首页'!$B$4*100+Q$4)) -> 0 | R6: =IF($A6="",0,SUMIFS('[1]销售出库'!$R$4:$R$2003,'[1]销售出库'!$H$4:$H$2003,$A6,'[1]销售出库'!$Q$4:$Q$2003,'首页'!$B$4*100+R$4)) -> 0 | S6: =IF($A6="",0,SUMIFS('[1]销售出库'!$R$4:$R$2003,'[1]销售出库'!$H$4:$H$2003,$A6,'[1]销售出库'!$Q$4:$Q$2003,'首页'!$B$4*100+S$4)) -> 0 | T6: =IF($A6="",0,SUMIFS('[1]销售出库'!$R$4:$R$2003,'[1]销售出库'!$H$4:$H$2003,$A6,'[1]销售出库'!$Q$4:$Q$2003,'首页'!$B$4*100+T$4)) -> 0 | ... X6: =IF($A6="",0,SUMIFS('[1]销售出库'!$R$4:$R$2003,'[1]销售出库'!$H$4:$H$2003,$A6,'[1]销售出库'!$Q$4:$Q$2003,'首页'!$B$4*100+X$4)) -> 0
A7: =IF('[1]基础资料'!$P$6="","",'[1]基础资料'!$P$6) -> S3652AA325 U5-325H 16 512 银-无畏16 | B7: =IF(A7="","",'[1]基础资料'!$Q$6&"") -> 华硕 | C7: =IF(A7="",0,N('[1]基础资料'!$S$6)) -> 20 | D7: =IF(A7="",0,N('[1]基础资料'!$U$6)) -> 104000 | E7: =IF(A7="",0,SUMIFS('[1]采购入库'!$U$4:$U$2003,'[1]采购入库'!$I$4:$I$2003,$A7)) -> 0 | F7: =IF(A7="",0,SUMIFS('[1]采购入库'!$V$4:$V$2003,'[1]采购入库'!$I$4:$I$2003,$A7)) -> 0 | G7: =IF(A7="",0,SUMIFS('[1]销售出库'!$R$4:$R$2003,'[1]销售出库'!$H$4:$H$2003,$A7)) -> 0 | H7: =IF(C7+E7>0,ROUND((D7+F7)/(C7+E7),4),0) -> 5200 | I7: =ROUND(G7*H7,2) -> 0 | J7: =C7+E7-G7 -> 20 | K7: =ROUND(D7+F7-I7,2) -> 104000 | L7: =IF(A7="","",IF(J7<0,"负库存：漏记采购或期初不准",IF(AND(G7>0,C7+E7=0),"没进货就卖了",""))) | M7: =IF($A7="",0,SUMIFS('[1]销售出库'!$R$4:$R$2003,'[1]销售出库'!$H$4:$H$2003,$A7,'[1]销售出库'!$Q$4:$Q$2003,'首页'!$B$4*100+M$4)) -> 0 | N7: =IF($A7="",0,SUMIFS('[1]销售出库'!$R$4:$R$2003,'[1]销售出库'!$H$4:$H$2003,$A7,'[1]销售出库'!$Q$4:$Q$2003,'首页'!$B$4*100+N$4)) -> 0 | O7: =IF($A7="",0,SUMIFS('[1]销售出库'!$R$4:$R$2003,'[1]销售出库'!$H$4:$H$2003,$A7,'[1]销售出库'!$Q$4:$Q$2003,'首页'!$B$4*100+O$4)) -> 0 | P7: =IF($A7="",0,SUMIFS('[1]销售出库'!$R$4:$R$2003,'[1]销售出库'!$H$4:$H$2003,$A7,'[1]销售出库'!$Q$4:$Q$2003,'首页'!$B$4*100+P$4)) -> 0 | Q7: =IF($A7="",0,SUMIFS('[1]销售出库'!$R$4:$R$2003,'[1]销售出库'!$H$4:$H$2003,$A7,'[1]销售出库'!$Q$4:$Q$2003,'首页'!$B$4*100+Q$4)) -> 0 | R7: =IF($A7="",0,SUMIFS('[1]销售出库'!$R$4:$R$2003,'[1]销售出库'!$H$4:$H$2003,$A7,'[1]销售出库'!$Q$4:$Q$2003,'首页'!$B$4*100+R$4)) -> 0 | S7: =IF($A7="",0,SUMIFS('[1]销售出库'!$R$4:$R$2003,'[1]销售出库'!$H$4:$H$2003,$A7,'[1]销售出库'!$Q$4:$Q$2003,'首页'!$B$4*100+S$4)) -> 0 | T7: =IF($A7="",0,SUMIFS('[1]销售出库'!$R$4:$R$2003,'[1]销售出库'!$H$4:$H$2003,$A7,'[1]销售出库'!$Q$4:$Q$2003,'首页'!$B$4*100+T$4)) -> 0 | ... X7: =IF($A7="",0,SUMIFS('[1]销售出库'!$R$4:$R$2003,'[1]销售出库'!$H$4:$H$2003,$A7,'[1]销售出库'!$Q$4:$Q$2003,'首页'!$B$4*100+X$4)) -> 0
A8: =IF('[1]基础资料'!$P$7="","",'[1]基础资料'!$P$7) -> 联想小新Pro 16GT U5 338H 32+1T 灰 | B8: =IF(A8="","",'[1]基础资料'!$Q$7&"") -> 联想 | C8: =IF(A8="",0,N('[1]基础资料'!$S$7)) -> 18 | D8: =IF(A8="",0,N('[1]基础资料'!$U$7)) -> 162104.21 | E8: =IF(A8="",0,SUMIFS('[1]采购入库'!$U$4:$U$2003,'[1]采购入库'!$I$4:$I$2003,$A8)) -> 17 | F8: =IF(A8="",0,SUMIFS('[1]采购入库'!$V$4:$V$2003,'[1]采购入库'!$I$4:$I$2003,$A8)) -> 152750 | G8: =IF(A8="",0,SUMIFS('[1]销售出库'!$R$4:$R$2003,'[1]销售出库'!$H$4:$H$2003,$A8)) -> 1 | H8: =IF(C8+E8>0,ROUND((D8+F8)/(C8+E8),4),0) -> 8995.8346 | I8: =ROUND(G8*H8,2) -> 8995.83 | J8: =C8+E8-G8 -> 34 | K8: =ROUND(D8+F8-I8,2) -> 305858.38 | L8: =IF(A8="","",IF(J8<0,"负库存：漏记采购或期初不准",IF(AND(G8>0,C8+E8=0),"没进货就卖了",""))) | M8: =IF($A8="",0,SUMIFS('[1]销售出库'!$R$4:$R$2003,'[1]销售出库'!$H$4:$H$2003,$A8,'[1]销售出库'!$Q$4:$Q$2003,'首页'!$B$4*100+M$4)) -> 0 | N8: =IF($A8="",0,SUMIFS('[1]销售出库'!$R$4:$R$2003,'[1]销售出库'!$H$4:$H$2003,$A8,'[1]销售出库'!$Q$4:$Q$2003,'首页'!$B$4*100+N$4)) -> 0 | O8: =IF($A8="",0,SUMIFS('[1]销售出库'!$R$4:$R$2003,'[1]销售出库'!$H$4:$H$2003,$A8,'[1]销售出库'!$Q$4:$Q$2003,'首页'!$B$4*100+O$4)) -> 0 | P8: =IF($A8="",0,SUMIFS('[1]销售出库'!$R$4:$R$2003,'[1]销售出库'!$H$4:$H$2003,$A8,'[1]销售出库'!$Q$4:$Q$2003,'首页'!$B$4*100+P$4)) -> 0 | Q8: =IF($A8="",0,SUMIFS('[1]销售出库'!$R$4:$R$2003,'[1]销售出库'!$H$4:$H$2003,$A8,'[1]销售出库'!$Q$4:$Q$2003,'首页'!$B$4*100+Q$4)) -> 0 | R8: =IF($A8="",0,SUMIFS('[1]销售出库'!$R$4:$R$2003,'[1]销售出库'!$H$4:$H$2003,$A8,'[1]销售出库'!$Q$4:$Q$2003,'首页'!$B$4*100+R$4)) -> 0 | S8: =IF($A8="",0,SUMIFS('[1]销售出库'!$R$4:$R$2003,'[1]销售出库'!$H$4:$H$2003,$A8,'[1]销售出库'!$Q$4:$Q$2003,'首页'!$B$4*100+S$4)) -> 0 | T8: =IF($A8="",0,SUMIFS('[1]销售出库'!$R$4:$R$2003,'[1]销售出库'!$H$4:$H$2003,$A8,'[1]销售出库'!$Q$4:$Q$2003,'首页'!$B$4*100+T$4)) -> 0 | ... X8: =IF($A8="",0,SUMIFS('[1]销售出库'!$R$4:$R$2003,'[1]销售出库'!$H$4:$H$2003,$A8,'[1]销售出库'!$Q$4:$Q$2003,'首页'!$B$4*100+X$4)) -> 0
A9: =IF('[1]基础资料'!$P$8="","",'[1]基础资料'!$P$8) -> 联想平板拯救者Y700 五代 24G+1TB碳晶黑WIFI | B9: =IF(A9="","",'[1]基础资料'!$Q$8&"") -> 平板 | C9: =IF(A9="",0,N('[1]基础资料'!$S$8)) -> 80 | D9: =IF(A9="",0,N('[1]基础资料'!$U$8)) -> 396195.12 | E9: =IF(A9="",0,SUMIFS('[1]采购入库'!$U$4:$U$2003,'[1]采购入库'!$I$4:$I$2003,$A9)) -> 0 | F9: =IF(A9="",0,SUMIFS('[1]采购入库'!$V$4:$V$2003,'[1]采购入库'!$I$4:$I$2003,$A9)) -> 0 | G9: =IF(A9="",0,SUMIFS('[1]销售出库'!$R$4:$R$2003,'[1]销售出库'!$H$4:$H$2003,$A9)) -> 2 | H9: =IF(C9+E9>0,ROUND((D9+F9)/(C9+E9),4),0) -> 4952.439 | I9: =ROUND(G9*H9,2) -> 9904.88 | J9: =C9+E9-G9 -> 78 | K9: =ROUND(D9+F9-I9,2) -> 386290.24 | L9: =IF(A9="","",IF(J9<0,"负库存：漏记采购或期初不准",IF(AND(G9>0,C9+E9=0),"没进货就卖了",""))) | M9: =IF($A9="",0,SUMIFS('[1]销售出库'!$R$4:$R$2003,'[1]销售出库'!$H$4:$H$2003,$A9,'[1]销售出库'!$Q$4:$Q$2003,'首页'!$B$4*100+M$4)) -> 0 | N9: =IF($A9="",0,SUMIFS('[1]销售出库'!$R$4:$R$2003,'[1]销售出库'!$H$4:$H$2003,$A9,'[1]销售出库'!$Q$4:$Q$2003,'首页'!$B$4*100+N$4)) -> 0 | O9: =IF($A9="",0,SUMIFS('[1]销售出库'!$R$4:$R$2003,'[1]销售出库'!$H$4:$H$2003,$A9,'[1]销售出库'!$Q$4:$Q$2003,'首页'!$B$4*100+O$4)) -> 0 | P9: =IF($A9="",0,SUMIFS('[1]销售出库'!$R$4:$R$2003,'[1]销售出库'!$H$4:$H$2003,$A9,'[1]销售出库'!$Q$4:$Q$2003,'首页'!$B$4*100+P$4)) -> 0 | Q9: =IF($A9="",0,SUMIFS('[1]销售出库'!$R$4:$R$2003,'[1]销售出库'!$H$4:$H$2003,$A9,'[1]销售出库'!$Q$4:$Q$2003,'首页'!$B$4*100+Q$4)) -> 0 | R9: =IF($A9="",0,SUMIFS('[1]销售出库'!$R$4:$R$2003,'[1]销售出库'!$H$4:$H$2003,$A9,'[1]销售出库'!$Q$4:$Q$2003,'首页'!$B$4*100+R$4)) -> 0 | S9: =IF($A9="",0,SUMIFS('[1]销售出库'!$R$4:$R$2003,'[1]销售出库'!$H$4:$H$2003,$A9,'[1]销售出库'!$Q$4:$Q$2003,'首页'!$B$4*100+S$4)) -> 0 | T9: =IF($A9="",0,SUMIFS('[1]销售出库'!$R$4:$R$2003,'[1]销售出库'!$H$4:$H$2003,$A9,'[1]销售出库'!$Q$4:$Q$2003,'首页'!$B$4*100+T$4)) -> 0 | ... X9: =IF($A9="",0,SUMIFS('[1]销售出库'!$R$4:$R$2003,'[1]销售出库'!$H$4:$H$2003,$A9,'[1]销售出库'!$Q$4:$Q$2003,'首页'!$B$4*100+X$4)) -> 0
A10: =IF('[1]基础资料'!$P$9="","",'[1]基础资料'!$P$9) -> 小新Pro16 2026 Ultra7-356H/32GB/1TB | B10: =IF(A10="","",'[1]基础资料'!$Q$9&"") -> 联想 | C10: =IF(A10="",0,N('[1]基础资料'!$S$9)) -> 63 | D10: =IF(A10="",0,N('[1]基础资料'!$U$9)) -> 512575.08 | E10: =IF(A10="",0,SUMIFS('[1]采购入库'!$U$4:$U$2003,'[1]采购入库'!$I$4:$I$2003,$A10)) -> 9 | F10: =IF(A10="",0,SUMIFS('[1]采购入库'!$V$4:$V$2003,'[1]采购入库'!$I$4:$I$2003,$A10)) -> 75040 | G10: =IF(A10="",0,SUMIFS('[1]销售出库'!$R$4:$R$2003,'[1]销售出库'!$H$4:$H$2003,$A10)) -> 1 | H10: =IF(C10+E10>0,ROUND((D10+F10)/(C10+E10),4),0) -> 8161.3206 | I10: =ROUND(G10*H10,2) -> 8161.32 | J10: =C10+E10-G10 -> 71 | K10: =ROUND(D10+F10-I10,2) -> 579453.76 | L10: =IF(A10="","",IF(J10<0,"负库存：漏记采购或期初不准",IF(AND(G10>0,C10+E10=0),"没进货就卖了",""))) | M10: =IF($A10="",0,SUMIFS('[1]销售出库'!$R$4:$R$2003,'[1]销售出库'!$H$4:$H$2003,$A10,'[1]销售出库'!$Q$4:$Q$2003,'首页'!$B$4*100+M$4)) -> 0 | N10: =IF($A10="",0,SUMIFS('[1]销售出库'!$R$4:$R$2003,'[1]销售出库'!$H$4:$H$2003,$A10,'[1]销售出库'!$Q$4:$Q$2003,'首页'!$B$4*100+N$4)) -> 0 | O10: =IF($A10="",0,SUMIFS('[1]销售出库'!$R$4:$R$2003,'[1]销售出库'!$H$4:$H$2003,$A10,'[1]销售出库'!$Q$4:$Q$2003,'首页'!$B$4*100+O$4)) -> 0 | P10: =IF($A10="",0,SUMIFS('[1]销售出库'!$R$4:$R$2003,'[1]销售出库'!$H$4:$H$2003,$A10,'[1]销售出库'!$Q$4:$Q$2003,'首页'!$B$4*100+P$4)) -> 0 | Q10: =IF($A10="",0,SUMIFS('[1]销售出库'!$R$4:$R$2003,'[1]销售出库'!$H$4:$H$2003,$A10,'[1]销售出库'!$Q$4:$Q$2003,'首页'!$B$4*100+Q$4)) -> 0 | R10: =IF($A10="",0,SUMIFS('[1]销售出库'!$R$4:$R$2003,'[1]销售出库'!$H$4:$H$2003,$A10,'[1]销售出库'!$Q$4:$Q$2003,'首页'!$B$4*100+R$4)) -> 0 | S10: =IF($A10="",0,SUMIFS('[1]销售出库'!$R$4:$R$2003,'[1]销售出库'!$H$4:$H$2003,$A10,'[1]销售出库'!$Q$4:$Q$2003,'首页'!$B$4*100+S$4)) -> 0 | T10: =IF($A10="",0,SUMIFS('[1]销售出库'!$R$4:$R$2003,'[1]销售出库'!$H$4:$H$2003,$A10,'[1]销售出库'!$Q$4:$Q$2003,'首页'!$B$4*100+T$4)) -> 0 | ... X10: =IF($A10="",0,SUMIFS('[1]销售出库'!$R$4:$R$2003,'[1]销售出库'!$H$4:$H$2003,$A10,'[1]销售出库'!$Q$4:$Q$2003,'首页'!$B$4*100+X$4)) -> 0
A11: =IF('[1]基础资料'!$P$10="","",'[1]基础资料'!$P$10) -> 联想平板 拯救者Y900 13 极光紫16+512wifi | B11: =IF(A11="","",'[1]基础资料'!$Q$10&"") -> 平板 | C11: =IF(A11="",0,N('[1]基础资料'!$S$10)) -> 32 | D11: =IF(A11="",0,N('[1]基础资料'!$U$10)) -> 106370.72 | E11: =IF(A11="",0,SUMIFS('[1]采购入库'!$U$4:$U$2003,'[1]采购入库'!$I$4:$I$2003,$A11)) -> 30 | F11: =IF(A11="",0,SUMIFS('[1]采购入库'!$V$4:$V$2003,'[1]采购入库'!$I$4:$I$2003,$A11)) -> 93570 | G11: =IF(A11="",0,SUMIFS('[1]销售出库'!$R$4:$R$2003,'[1]销售出库'!$H$4:$H$2003,$A11)) -> 38 | H11: =IF(C11+E11>0,ROUND((D11+F11)/(C11+E11),4),0) -> 3224.8503 | I11: =ROUND(G11*H11,2) -> 122544.31 | J11: =C11+E11-G11 -> 24 | K11: =ROUND(D11+F11-I11,2) -> 77396.41 | L11: =IF(A11="","",IF(J11<0,"负库存：漏记采购或期初不准",IF(AND(G11>0,C11+E11=0),"没进货就卖了",""))) | M11: =IF($A11="",0,SUMIFS('[1]销售出库'!$R$4:$R$2003,'[1]销售出库'!$H$4:$H$2003,$A11,'[1]销售出库'!$Q$4:$Q$2003,'首页'!$B$4*100+M$4)) -> 0 | N11: =IF($A11="",0,SUMIFS('[1]销售出库'!$R$4:$R$2003,'[1]销售出库'!$H$4:$H$2003,$A11,'[1]销售出库'!$Q$4:$Q$2003,'首页'!$B$4*100+N$4)) -> 0 | O11: =IF($A11="",0,SUMIFS('[1]销售出库'!$R$4:$R$2003,'[1]销售出库'!$H$4:$H$2003,$A11,'[1]销售出库'!$Q$4:$Q$2003,'首页'!$B$4*100+O$4)) -> 0 | P11: =IF($A11="",0,SUMIFS('[1]销售出库'!$R$4:$R$2003,'[1]销售出库'!$H$4:$H$2003,$A11,'[1]销售出库'!$Q$4:$Q$2003,'首页'!$B$4*100+P$4)) -> 0 | Q11: =IF($A11="",0,SUMIFS('[1]销售出库'!$R$4:$R$2003,'[1]销售出库'!$H$4:$H$2003,$A11,'[1]销售出库'!$Q$4:$Q$2003,'首页'!$B$4*100+Q$4)) -> 0 | R11: =IF($A11="",0,SUMIFS('[1]销售出库'!$R$4:$R$2003,'[1]销售出库'!$H$4:$H$2003,$A11,'[1]销售出库'!$Q$4:$Q$2003,'首页'!$B$4*100+R$4)) -> 0 | S11: =IF($A11="",0,SUMIFS('[1]销售出库'!$R$4:$R$2003,'[1]销售出库'!$H$4:$H$2003,$A11,'[1]销售出库'!$Q$4:$Q$2003,'首页'!$B$4*100+S$4)) -> 0 | T11: =IF($A11="",0,SUMIFS('[1]销售出库'!$R$4:$R$2003,'[1]销售出库'!$H$4:$H$2003,$A11,'[1]销售出库'!$Q$4:$Q$2003,'首页'!$B$4*100+T$4)) -> 0 | ... X11: =IF($A11="",0,SUMIFS('[1]销售出库'!$R$4:$R$2003,'[1]销售出库'!$H$4:$H$2003,$A11,'[1]销售出库'!$Q$4:$Q$2003,'首页'!$B$4*100+X$4)) -> 0
A12: =IF('[1]基础资料'!$P$11="","",'[1]基础资料'!$P$11) -> 联想拯救者Y900 11 8+128WIFI碳晶黑 | B12: =IF(A12="","",'[1]基础资料'!$Q$11&"") -> 平板 | C12: =IF(A12="",0,N('[1]基础资料'!$S$11)) -> 96 | D12: =IF(A12="",0,N('[1]基础资料'!$U$11)) -> 181264.62 | E12: =IF(A12="",0,SUMIFS('[1]采购入库'!$U$4:$U$2003,'[1]采购入库'!$I$4:$I$2003,$A12)) -> 7 | F12: =IF(A12="",0,SUMIFS('[1]采购入库'!$V$4:$V$2003,'[1]采购入库'!$I$4:$I$2003,$A12)) -> 11660 | G12: =IF(A12="",0,SUMIFS('[1]销售出库'!$R$4:$R$2003,'[1]销售出库'!$H$4:$H$2003,$A12)) -> 8 | H12: =IF(C12+E12>0,ROUND((D12+F12)/(C12+E12),4),0) -> 1873.0546 | I12: =ROUND(G12*H12,2) -> 14984.44 | J12: =C12+E12-G12 -> 95 | K12: =ROUND(D12+F12-I12,2) -> 177940.18 | L12: =IF(A12="","",IF(J12<0,"负库存：漏记采购或期初不准",IF(AND(G12>0,C12+E12=0),"没进货就卖了",""))) | M12: =IF($A12="",0,SUMIFS('[1]销售出库'!$R$4:$R$2003,'[1]销售出库'!$H$4:$H$2003,$A12,'[1]销售出库'!$Q$4:$Q$2003,'首页'!$B$4*100+M$4)) -> 0 | N12: =IF($A12="",0,SUMIFS('[1]销售出库'!$R$4:$R$2003,'[1]销售出库'!$H$4:$H$2003,$A12,'[1]销售出库'!$Q$4:$Q$2003,'首页'!$B$4*100+N$4)) -> 0 | O12: =IF($A12="",0,SUMIFS('[1]销售出库'!$R$4:$R$2003,'[1]销售出库'!$H$4:$H$2003,$A12,'[1]销售出库'!$Q$4:$Q$2003,'首页'!$B$4*100+O$4)) -> 0 | P12: =IF($A12="",0,SUMIFS('[1]销售出库'!$R$4:$R$2003,'[1]销售出库'!$H$4:$H$2003,$A12,'[1]销售出库'!$Q$4:$Q$2003,'首页'!$B$4*100+P$4)) -> 0 | Q12: =IF($A12="",0,SUMIFS('[1]销售出库'!$R$4:$R$2003,'[1]销售出库'!$H$4:$H$2003,$A12,'[1]销售出库'!$Q$4:$Q$2003,'首页'!$B$4*100+Q$4)) -> 0 | R12: =IF($A12="",0,SUMIFS('[1]销售出库'!$R$4:$R$2003,'[1]销售出库'!$H$4:$H$2003,$A12,'[1]销售出库'!$Q$4:$Q$2003,'首页'!$B$4*100+R$4)) -> 0 | S12: =IF($A12="",0,SUMIFS('[1]销售出库'!$R$4:$R$2003,'[1]销售出库'!$H$4:$H$2003,$A12,'[1]销售出库'!$Q$4:$Q$2003,'首页'!$B$4*100+S$4)) -> 0 | T12: =IF($A12="",0,SUMIFS('[1]销售出库'!$R$4:$R$2003,'[1]销售出库'!$H$4:$H$2003,$A12,'[1]销售出库'!$Q$4:$Q$2003,'首页'!$B$4*100+T$4)) -> 0 | ... X12: =IF($A12="",0,SUMIFS('[1]销售出库'!$R$4:$R$2003,'[1]销售出库'!$H$4:$H$2003,$A12,'[1]销售出库'!$Q$4:$Q$2003,'首页'!$B$4*100+X$4)) -> 0
A13: =IF('[1]基础资料'!$P$12="","",'[1]基础资料'!$P$12) -> 小新Pro16 Ultra5 135H 24GB 1TB | B13: =IF(A13="","",'[1]基础资料'!$Q$12&"") -> 联想 | C13: =IF(A13="",0,N('[1]基础资料'!$S$12)) -> 14 | D13: =IF(A13="",0,N('[1]基础资料'!$U$12)) -> 88669 | E13: =IF(A13="",0,SUMIFS('[1]采购入库'!$U$4:$U$2003,'[1]采购入库'!$I$4:$I$2003,$A13)) -> 0 | F13: =IF(A13="",0,SUMIFS('[1]采购入库'!$V$4:$V$2003,'[1]采购入库'!$I$4:$I$2003,$A13)) -> 0 | G13: =IF(A13="",0,SUMIFS('[1]销售出库'!$R$4:$R$2003,'[1]销售出库'!$H$4:$H$2003,$A13)) -> 6 | H13: =IF(C13+E13>0,ROUND((D13+F13)/(C13+E13),4),0) -> 6333.5 | I13: =ROUND(G13*H13,2) -> 38001 | J13: =C13+E13-G13 -> 8 | K13: =ROUND(D13+F13-I13,2) -> 50668 | L13: =IF(A13="","",IF(J13<0,"负库存：漏记采购或期初不准",IF(AND(G13>0,C13+E13=0),"没进货就卖了",""))) | M13: =IF($A13="",0,SUMIFS('[1]销售出库'!$R$4:$R$2003,'[1]销售出库'!$H$4:$H$2003,$A13,'[1]销售出库'!$Q$4:$Q$2003,'首页'!$B$4*100+M$4)) -> 0 | N13: =IF($A13="",0,SUMIFS('[1]销售出库'!$R$4:$R$2003,'[1]销售出库'!$H$4:$H$2003,$A13,'[1]销售出库'!$Q$4:$Q$2003,'首页'!$B$4*100+N$4)) -> 0 | O13: =IF($A13="",0,SUMIFS('[1]销售出库'!$R$4:$R$2003,'[1]销售出库'!$H$4:$H$2003,$A13,'[1]销售出库'!$Q$4:$Q$2003,'首页'!$B$4*100+O$4)) -> 0 | P13: =IF($A13="",0,SUMIFS('[1]销售出库'!$R$4:$R$2003,'[1]销售出库'!$H$4:$H$2003,$A13,'[1]销售出库'!$Q$4:$Q$2003,'首页'!$B$4*100+P$4)) -> 0 | Q13: =IF($A13="",0,SUMIFS('[1]销售出库'!$R$4:$R$2003,'[1]销售出库'!$H$4:$H$2003,$A13,'[1]销售出库'!$Q$4:$Q$2003,'首页'!$B$4*100+Q$4)) -> 0 | R13: =IF($A13="",0,SUMIFS('[1]销售出库'!$R$4:$R$2003,'[1]销售出库'!$H$4:$H$2003,$A13,'[1]销售出库'!$Q$4:$Q$2003,'首页'!$B$4*100+R$4)) -> 0 | S13: =IF($A13="",0,SUMIFS('[1]销售出库'!$R$4:$R$2003,'[1]销售出库'!$H$4:$H$2003,$A13,'[1]销售出库'!$Q$4:$Q$2003,'首页'!$B$4*100+S$4)) -> 0 | T13: =IF($A13="",0,SUMIFS('[1]销售出库'!$R$4:$R$2003,'[1]销售出库'!$H$4:$H$2003,$A13,'[1]销售出库'!$Q$4:$Q$2003,'首页'!$B$4*100+T$4)) -> 0 | ... X13: =IF($A13="",0,SUMIFS('[1]销售出库'!$R$4:$R$2003,'[1]销售出库'!$H$4:$H$2003,$A13,'[1]销售出库'!$Q$4:$Q$2003,'首页'!$B$4*100+X$4)) -> 0
A14: =IF('[1]基础资料'!$P$13="","",'[1]基础资料'!$P$13) -> 联想Y900 11 12+512黑色WIFI | B14: =IF(A14="","",'[1]基础资料'!$Q$13&"") -> 平板 | C14: =IF(A14="",0,N('[1]基础资料'!$S$13)) -> 8 | D14: =IF(A14="",0,N('[1]基础资料'!$U$13)) -> 19600 | E14: =IF(A14="",0,SUMIFS('[1]采购入库'!$U$4:$U$2003,'[1]采购入库'!$I$4:$I$2003,$A14)) -> 20 | F14: =IF(A14="",0,SUMIFS('[1]采购入库'!$V$4:$V$2003,'[1]采购入库'!$I$4:$I$2003,$A14)) -> 49000 | G14: =IF(A14="",0,SUMIFS('[1]销售出库'!$R$4:$R$2003,'[1]销售出库'!$H$4:$H$2003,$A14)) -> 13 | H14: =IF(C14+E14>0,ROUND((D14+F14)/(C14+E14),4),0) -> 2450 | I14: =ROUND(G14*H14,2) -> 31850 | J14: =C14+E14-G14 -> 15 | K14: =ROUND(D14+F14-I14,2) -> 36750 | L14: =IF(A14="","",IF(J14<0,"负库存：漏记采购或期初不准",IF(AND(G14>0,C14+E14=0),"没进货就卖了",""))) | M14: =IF($A14="",0,SUMIFS('[1]销售出库'!$R$4:$R$2003,'[1]销售出库'!$H$4:$H$2003,$A14,'[1]销售出库'!$Q$4:$Q$2003,'首页'!$B$4*100+M$4)) -> 0 | N14: =IF($A14="",0,SUMIFS('[1]销售出库'!$R$4:$R$2003,'[1]销售出库'!$H$4:$H$2003,$A14,'[1]销售出库'!$Q$4:$Q$2003,'首页'!$B$4*100+N$4)) -> 0 | O14: =IF($A14="",0,SUMIFS('[1]销售出库'!$R$4:$R$2003,'[1]销售出库'!$H$4:$H$2003,$A14,'[1]销售出库'!$Q$4:$Q$2003,'首页'!$B$4*100+O$4)) -> 0 | P14: =IF($A14="",0,SUMIFS('[1]销售出库'!$R$4:$R$2003,'[1]销售出库'!$H$4:$H$2003,$A14,'[1]销售出库'!$Q$4:$Q$2003,'首页'!$B$4*100+P$4)) -> 0 | Q14: =IF($A14="",0,SUMIFS('[1]销售出库'!$R$4:$R$2003,'[1]销售出库'!$H$4:$H$2003,$A14,'[1]销售出库'!$Q$4:$Q$2003,'首页'!$B$4*100+Q$4)) -> 0 | R14: =IF($A14="",0,SUMIFS('[1]销售出库'!$R$4:$R$2003,'[1]销售出库'!$H$4:$H$2003,$A14,'[1]销售出库'!$Q$4:$Q$2003,'首页'!$B$4*100+R$4)) -> 0 | S14: =IF($A14="",0,SUMIFS('[1]销售出库'!$R$4:$R$2003,'[1]销售出库'!$H$4:$H$2003,$A14,'[1]销售出库'!$Q$4:$Q$2003,'首页'!$B$4*100+S$4)) -> 0 | T14: =IF($A14="",0,SUMIFS('[1]销售出库'!$R$4:$R$2003,'[1]销售出库'!$H$4:$H$2003,$A14,'[1]销售出库'!$Q$4:$Q$2003,'首页'!$B$4*100+T$4)) -> 0 | ... X14: =IF($A14="",0,SUMIFS('[1]销售出库'!$R$4:$R$2003,'[1]销售出库'!$H$4:$H$2003,$A14,'[1]销售出库'!$Q$4:$Q$2003,'首页'!$B$4*100+X$4)) -> 0
A15: =IF('[1]基础资料'!$P$14="","",'[1]基础资料'!$P$14) -> 联想拯救者Y700 五代 12+512 WIFI碳晶黑 | B15: =IF(A15="","",'[1]基础资料'!$Q$14&"") -> 平板 | C15: =IF(A15="",0,N('[1]基础资料'!$S$14)) -> 80 | D15: =IF(A15="",0,N('[1]基础资料'!$U$14)) -> 272120 | E15: =IF(A15="",0,SUMIFS('[1]采购入库'!$U$4:$U$2003,'[1]采购入库'!$I$4:$I$2003,$A15)) -> 6 | F15: =IF(A15="",0,SUMIFS('[1]采购入库'!$V$4:$V$2003,'[1]采购入库'!$I$4:$I$2003,$A15)) -> 20520 | G15: =IF(A15="",0,SUMIFS('[1]销售出库'!$R$4:$R$2003,'[1]销售出库'!$H$4:$H$2003,$A15)) -> 0 | H15: =IF(C15+E15>0,ROUND((D15+F15)/(C15+E15),4),0) -> 3402.7907 | I15: =ROUND(G15*H15,2) -> 0 | J15: =C15+E15-G15 -> 86 | K15: =ROUND(D15+F15-I15,2) -> 292640 | L15: =IF(A15="","",IF(J15<0,"负库存：漏记采购或期初不准",IF(AND(G15>0,C15+E15=0),"没进货就卖了",""))) | M15: =IF($A15="",0,SUMIFS('[1]销售出库'!$R$4:$R$2003,'[1]销售出库'!$H$4:$H$2003,$A15,'[1]销售出库'!$Q$4:$Q$2003,'首页'!$B$4*100+M$4)) -> 0 | N15: =IF($A15="",0,SUMIFS('[1]销售出库'!$R$4:$R$2003,'[1]销售出库'!$H$4:$H$2003,$A15,'[1]销售出库'!$Q$4:$Q$2003,'首页'!$B$4*100+N$4)) -> 0 | O15: =IF($A15="",0,SUMIFS('[1]销售出库'!$R$4:$R$2003,'[1]销售出库'!$H$4:$H$2003,$A15,'[1]销售出库'!$Q$4:$Q$2003,'首页'!$B$4*100+O$4)) -> 0 | P15: =IF($A15="",0,SUMIFS('[1]销售出库'!$R$4:$R$2003,'[1]销售出库'!$H$4:$H$2003,$A15,'[1]销售出库'!$Q$4:$Q$2003,'首页'!$B$4*100+P$4)) -> 0 | Q15: =IF($A15="",0,SUMIFS('[1]销售出库'!$R$4:$R$2003,'[1]销售出库'!$H$4:$H$2003,$A15,'[1]销售出库'!$Q$4:$Q$2003,'首页'!$B$4*100+Q$4)) -> 0 | R15: =IF($A15="",0,SUMIFS('[1]销售出库'!$R$4:$R$2003,'[1]销售出库'!$H$4:$H$2003,$A15,'[1]销售出库'!$Q$4:$Q$2003,'首页'!$B$4*100+R$4)) -> 0 | S15: =IF($A15="",0,SUMIFS('[1]销售出库'!$R$4:$R$2003,'[1]销售出库'!$H$4:$H$2003,$A15,'[1]销售出库'!$Q$4:$Q$2003,'首页'!$B$4*100+S$4)) -> 0 | T15: =IF($A15="",0,SUMIFS('[1]销售出库'!$R$4:$R$2003,'[1]销售出库'!$H$4:$H$2003,$A15,'[1]销售出库'!$Q$4:$Q$2003,'首页'!$B$4*100+T$4)) -> 0 | ... X15: =IF($A15="",0,SUMIFS('[1]销售出库'!$R$4:$R$2003,'[1]销售出库'!$H$4:$H$2003,$A15,'[1]销售出库'!$Q$4:$Q$2003,'首页'!$B$4*100+X$4)) -> 0
A16: =IF('[1]基础资料'!$P$15="","",'[1]基础资料'!$P$15) -> iPhone 17 Pro Max 256GB 星宇橙色 | B16: =IF(A16="","",'[1]基础资料'!$Q$15&"") -> 苹果 | C16: =IF(A16="",0,N('[1]基础资料'!$S$15)) -> 120 | D16: =IF(A16="",0,N('[1]基础资料'!$U$15)) -> 1068535 | E16: =IF(A16="",0,SUMIFS('[1]采购入库'!$U$4:$U$2003,'[1]采购入库'!$I$4:$I$2003,$A16)) -> 0 | F16: =IF(A16="",0,SUMIFS('[1]采购入库'!$V$4:$V$2003,'[1]采购入库'!$I$4:$I$2003,$A16)) -> 0 | G16: =IF(A16="",0,SUMIFS('[1]销售出库'!$R$4:$R$2003,'[1]销售出库'!$H$4:$H$2003,$A16)) -> 0 | H16: =IF(C16+E16>0,ROUND((D16+F16)/(C16+E16),4),0) -> 8904.4583 | I16: =ROUND(G16*H16,2) -> 0 | J16: =C16+E16-G16 -> 120 | K16: =ROUND(D16+F16-I16,2) -> 1068535 | L16: =IF(A16="","",IF(J16<0,"负库存：漏记采购或期初不准",IF(AND(G16>0,C16+E16=0),"没进货就卖了",""))) | M16: =IF($A16="",0,SUMIFS('[1]销售出库'!$R$4:$R$2003,'[1]销售出库'!$H$4:$H$2003,$A16,'[1]销售出库'!$Q$4:$Q$2003,'首页'!$B$4*100+M$4)) -> 0 | N16: =IF($A16="",0,SUMIFS('[1]销售出库'!$R$4:$R$2003,'[1]销售出库'!$H$4:$H$2003,$A16,'[1]销售出库'!$Q$4:$Q$2003,'首页'!$B$4*100+N$4)) -> 0 | O16: =IF($A16="",0,SUMIFS('[1]销售出库'!$R$4:$R$2003,'[1]销售出库'!$H$4:$H$2003,$A16,'[1]销售出库'!$Q$4:$Q$2003,'首页'!$B$4*100+O$4)) -> 0 | P16: =IF($A16="",0,SUMIFS('[1]销售出库'!$R$4:$R$2003,'[1]销售出库'!$H$4:$H$2003,$A16,'[1]销售出库'!$Q$4:$Q$2003,'首页'!$B$4*100+P$4)) -> 0 | Q16: =IF($A16="",0,SUMIFS('[1]销售出库'!$R$4:$R$2003,'[1]销售出库'!$H$4:$H$2003,$A16,'[1]销售出库'!$Q$4:$Q$2003,'首页'!$B$4*100+Q$4)) -> 0 | R16: =IF($A16="",0,SUMIFS('[1]销售出库'!$R$4:$R$2003,'[1]销售出库'!$H$4:$H$2003,$A16,'[1]销售出库'!$Q$4:$Q$2003,'首页'!$B$4*100+R$4)) -> 0 | S16: =IF($A16="",0,SUMIFS('[1]销售出库'!$R$4:$R$2003,'[1]销售出库'!$H$4:$H$2003,$A16,'[1]销售出库'!$Q$4:$Q$2003,'首页'!$B$4*100+S$4)) -> 0 | T16: =IF($A16="",0,SUMIFS('[1]销售出库'!$R$4:$R$2003,'[1]销售出库'!$H$4:$H$2003,$A16,'[1]销售出库'!$Q$4:$Q$2003,'首页'!$B$4*100+T$4)) -> 0 | ... X16: =IF($A16="",0,SUMIFS('[1]销售出库'!$R$4:$R$2003,'[1]销售出库'!$H$4:$H$2003,$A16,'[1]销售出库'!$Q$4:$Q$2003,'首页'!$B$4*100+X$4)) -> 0
A17: =IF('[1]基础资料'!$P$16="","",'[1]基础资料'!$P$16) -> iPhone17 Pro Max 512GB星宇橙色 | B17: =IF(A17="","",'[1]基础资料'!$Q$16&"") -> 苹果 | C17: =IF(A17="",0,N('[1]基础资料'!$S$16)) -> 10 | D17: =IF(A17="",0,N('[1]基础资料'!$U$16)) -> 106000 | E17: =IF(A17="",0,SUMIFS('[1]采购入库'!$U$4:$U$2003,'[1]采购入库'!$I$4:$I$2003,$A17)) -> 0 | F17: =IF(A17="",0,SUMIFS('[1]采购入库'!$V$4:$V$2003,'[1]采购入库'!$I$4:$I$2003,$A17)) -> 0 | G17: =IF(A17="",0,SUMIFS('[1]销售出库'!$R$4:$R$2003,'[1]销售出库'!$H$4:$H$2003,$A17)) -> 0 | H17: =IF(C17+E17>0,ROUND((D17+F17)/(C17+E17),4),0) -> 10600 | I17: =ROUND(G17*H17,2) -> 0 | J17: =C17+E17-G17 -> 10 | K17: =ROUND(D17+F17-I17,2) -> 106000 | L17: =IF(A17="","",IF(J17<0,"负库存：漏记采购或期初不准",IF(AND(G17>0,C17+E17=0),"没进货就卖了",""))) | M17: =IF($A17="",0,SUMIFS('[1]销售出库'!$R$4:$R$2003,'[1]销售出库'!$H$4:$H$2003,$A17,'[1]销售出库'!$Q$4:$Q$2003,'首页'!$B$4*100+M$4)) -> 0 | N17: =IF($A17="",0,SUMIFS('[1]销售出库'!$R$4:$R$2003,'[1]销售出库'!$H$4:$H$2003,$A17,'[1]销售出库'!$Q$4:$Q$2003,'首页'!$B$4*100+N$4)) -> 0 | O17: =IF($A17="",0,SUMIFS('[1]销售出库'!$R$4:$R$2003,'[1]销售出库'!$H$4:$H$2003,$A17,'[1]销售出库'!$Q$4:$Q$2003,'首页'!$B$4*100+O$4)) -> 0 | P17: =IF($A17="",0,SUMIFS('[1]销售出库'!$R$4:$R$2003,'[1]销售出库'!$H$4:$H$2003,$A17,'[1]销售出库'!$Q$4:$Q$2003,'首页'!$B$4*100+P$4)) -> 0 | Q17: =IF($A17="",0,SUMIFS('[1]销售出库'!$R$4:$R$2003,'[1]销售出库'!$H$4:$H$2003,$A17,'[1]销售出库'!$Q$4:$Q$2003,'首页'!$B$4*100+Q$4)) -> 0 | R17: =IF($A17="",0,SUMIFS('[1]销售出库'!$R$4:$R$2003,'[1]销售出库'!$H$4:$H$2003,$A17,'[1]销售出库'!$Q$4:$Q$2003,'首页'!$B$4*100+R$4)) -> 0 | S17: =IF($A17="",0,SUMIFS('[1]销售出库'!$R$4:$R$2003,'[1]销售出库'!$H$4:$H$2003,$A17,'[1]销售出库'!$Q$4:$Q$2003,'首页'!$B$4*100+S$4)) -> 0 | T17: =IF($A17="",0,SUMIFS('[1]销售出库'!$R$4:$R$2003,'[1]销售出库'!$H$4:$H$2003,$A17,'[1]销售出库'!$Q$4:$Q$2003,'首页'!$B$4*100+T$4)) -> 0 | ... X17: =IF($A17="",0,SUMIFS('[1]销售出库'!$R$4:$R$2003,'[1]销售出库'!$H$4:$H$2003,$A17,'[1]销售出库'!$Q$4:$Q$2003,'首页'!$B$4*100+X$4)) -> 0
A18: =IF('[1]基础资料'!$P$17="","",'[1]基础资料'!$P$17) -> iPhone 17 Pro 256GB 银色 | B18: =IF(A18="","",'[1]基础资料'!$Q$17&"") -> 苹果 | C18: =IF(A18="",0,N('[1]基础资料'!$S$17)) -> 10 | D18: =IF(A18="",0,N('[1]基础资料'!$U$17)) -> 78700 | E18: =IF(A18="",0,SUMIFS('[1]采购入库'!$U$4:$U$2003,'[1]采购入库'!$I$4:$I$2003,$A18)) -> 0 | F18: =IF(A18="",0,SUMIFS('[1]采购入库'!$V$4:$V$2003,'[1]采购入库'!$I$4:$I$2003,$A18)) -> 0 | G18: =IF(A18="",0,SUMIFS('[1]销售出库'!$R$4:$R$2003,'[1]销售出库'!$H$4:$H$2003,$A18)) -> 0 | H18: =IF(C18+E18>0,ROUND((D18+F18)/(C18+E18),4),0) -> 7870 | I18: =ROUND(G18*H18,2) -> 0 | J18: =C18+E18-G18 -> 10 | K18: =ROUND(D18+F18-I18,2) -> 78700 | L18: =IF(A18="","",IF(J18<0,"负库存：漏记采购或期初不准",IF(AND(G18>0,C18+E18=0),"没进货就卖了",""))) | M18: =IF($A18="",0,SUMIFS('[1]销售出库'!$R$4:$R$2003,'[1]销售出库'!$H$4:$H$2003,$A18,'[1]销售出库'!$Q$4:$Q$2003,'首页'!$B$4*100+M$4)) -> 0 | N18: =IF($A18="",0,SUMIFS('[1]销售出库'!$R$4:$R$2003,'[1]销售出库'!$H$4:$H$2003,$A18,'[1]销售出库'!$Q$4:$Q$2003,'首页'!$B$4*100+N$4)) -> 0 | O18: =IF($A18="",0,SUMIFS('[1]销售出库'!$R$4:$R$2003,'[1]销售出库'!$H$4:$H$2003,$A18,'[1]销售出库'!$Q$4:$Q$2003,'首页'!$B$4*100+O$4)) -> 0 | P18: =IF($A18="",0,SUMIFS('[1]销售出库'!$R$4:$R$2003,'[1]销售出库'!$H$4:$H$2003,$A18,'[1]销售出库'!$Q$4:$Q$2003,'首页'!$B$4*100+P$4)) -> 0 | Q18: =IF($A18="",0,SUMIFS('[1]销售出库'!$R$4:$R$2003,'[1]销售出库'!$H$4:$H$2003,$A18,'[1]销售出库'!$Q$4:$Q$2003,'首页'!$B$4*100+Q$4)) -> 0 | R18: =IF($A18="",0,SUMIFS('[1]销售出库'!$R$4:$R$2003,'[1]销售出库'!$H$4:$H$2003,$A18,'[1]销售出库'!$Q$4:$Q$2003,'首页'!$B$4*100+R$4)) -> 0 | S18: =IF($A18="",0,SUMIFS('[1]销售出库'!$R$4:$R$2003,'[1]销售出库'!$H$4:$H$2003,$A18,'[1]销售出库'!$Q$4:$Q$2003,'首页'!$B$4*100+S$4)) -> 0 | T18: =IF($A18="",0,SUMIFS('[1]销售出库'!$R$4:$R$2003,'[1]销售出库'!$H$4:$H$2003,$A18,'[1]销售出库'!$Q$4:$Q$2003,'首页'!$B$4*100+T$4)) -> 0 | ... X18: =IF($A18="",0,SUMIFS('[1]销售出库'!$R$4:$R$2003,'[1]销售出库'!$H$4:$H$2003,$A18,'[1]销售出库'!$Q$4:$Q$2003,'首页'!$B$4*100+X$4)) -> 0
A19: =IF('[1]基础资料'!$P$18="","",'[1]基础资料'!$P$18) -> iPhone 17 Pro 256GB星宇橙色 | B19: =IF(A19="","",'[1]基础资料'!$Q$18&"") -> 苹果 | C19: =IF(A19="",0,N('[1]基础资料'!$S$18)) -> 2 | D19: =IF(A19="",0,N('[1]基础资料'!$U$18)) -> 15410 | E19: =IF(A19="",0,SUMIFS('[1]采购入库'!$U$4:$U$2003,'[1]采购入库'!$I$4:$I$2003,$A19)) -> 0 | F19: =IF(A19="",0,SUMIFS('[1]采购入库'!$V$4:$V$2003,'[1]采购入库'!$I$4:$I$2003,$A19)) -> 0 | G19: =IF(A19="",0,SUMIFS('[1]销售出库'!$R$4:$R$2003,'[1]销售出库'!$H$4:$H$2003,$A19)) -> 0 | H19: =IF(C19+E19>0,ROUND((D19+F19)/(C19+E19),4),0) -> 7705 | I19: =ROUND(G19*H19,2) -> 0 | J19: =C19+E19-G19 -> 2 | K19: =ROUND(D19+F19-I19,2) -> 15410 | L19: =IF(A19="","",IF(J19<0,"负库存：漏记采购或期初不准",IF(AND(G19>0,C19+E19=0),"没进货就卖了",""))) | M19: =IF($A19="",0,SUMIFS('[1]销售出库'!$R$4:$R$2003,'[1]销售出库'!$H$4:$H$2003,$A19,'[1]销售出库'!$Q$4:$Q$2003,'首页'!$B$4*100+M$4)) -> 0 | N19: =IF($A19="",0,SUMIFS('[1]销售出库'!$R$4:$R$2003,'[1]销售出库'!$H$4:$H$2003,$A19,'[1]销售出库'!$Q$4:$Q$2003,'首页'!$B$4*100+N$4)) -> 0 | O19: =IF($A19="",0,SUMIFS('[1]销售出库'!$R$4:$R$2003,'[1]销售出库'!$H$4:$H$2003,$A19,'[1]销售出库'!$Q$4:$Q$2003,'首页'!$B$4*100+O$4)) -> 0 | P19: =IF($A19="",0,SUMIFS('[1]销售出库'!$R$4:$R$2003,'[1]销售出库'!$H$4:$H$2003,$A19,'[1]销售出库'!$Q$4:$Q$2003,'首页'!$B$4*100+P$4)) -> 0 | Q19: =IF($A19="",0,SUMIFS('[1]销售出库'!$R$4:$R$2003,'[1]销售出库'!$H$4:$H$2003,$A19,'[1]销售出库'!$Q$4:$Q$2003,'首页'!$B$4*100+Q$4)) -> 0 | R19: =IF($A19="",0,SUMIFS('[1]销售出库'!$R$4:$R$2003,'[1]销售出库'!$H$4:$H$2003,$A19,'[1]销售出库'!$Q$4:$Q$2003,'首页'!$B$4*100+R$4)) -> 0 | S19: =IF($A19="",0,SUMIFS('[1]销售出库'!$R$4:$R$2003,'[1]销售出库'!$H$4:$H$2003,$A19,'[1]销售出库'!$Q$4:$Q$2003,'首页'!$B$4*100+S$4)) -> 0 | T19: =IF($A19="",0,SUMIFS('[1]销售出库'!$R$4:$R$2003,'[1]销售出库'!$H$4:$H$2003,$A19,'[1]销售出库'!$Q$4:$Q$2003,'首页'!$B$4*100+T$4)) -> 0 | ... X19: =IF($A19="",0,SUMIFS('[1]销售出库'!$R$4:$R$2003,'[1]销售出库'!$H$4:$H$2003,$A19,'[1]销售出库'!$Q$4:$Q$2003,'首页'!$B$4*100+X$4)) -> 0
A20: =IF('[1]基础资料'!$P$19="","",'[1]基础资料'!$P$19) -> iPhone 17 Pro Max 256GB 银色 | B20: =IF(A20="","",'[1]基础资料'!$Q$19&"") -> 苹果 | C20: =IF(A20="",0,N('[1]基础资料'!$S$19)) -> 35 | D20: =IF(A20="",0,N('[1]基础资料'!$U$19)) -> 312830 | E20: =IF(A20="",0,SUMIFS('[1]采购入库'!$U$4:$U$2003,'[1]采购入库'!$I$4:$I$2003,$A20)) -> 0 | F20: =IF(A20="",0,SUMIFS('[1]采购入库'!$V$4:$V$2003,'[1]采购入库'!$I$4:$I$2003,$A20)) -> 0 | G20: =IF(A20="",0,SUMIFS('[1]销售出库'!$R$4:$R$2003,'[1]销售出库'!$H$4:$H$2003,$A20)) -> 0 | H20: =IF(C20+E20>0,ROUND((D20+F20)/(C20+E20),4),0) -> 8938 | I20: =ROUND(G20*H20,2) -> 0 | J20: =C20+E20-G20 -> 35 | K20: =ROUND(D20+F20-I20,2) -> 312830 | L20: =IF(A20="","",IF(J20<0,"负库存：漏记采购或期初不准",IF(AND(G20>0,C20+E20=0),"没进货就卖了",""))) | M20: =IF($A20="",0,SUMIFS('[1]销售出库'!$R$4:$R$2003,'[1]销售出库'!$H$4:$H$2003,$A20,'[1]销售出库'!$Q$4:$Q$2003,'首页'!$B$4*100+M$4)) -> 0 | N20: =IF($A20="",0,SUMIFS('[1]销售出库'!$R$4:$R$2003,'[1]销售出库'!$H$4:$H$2003,$A20,'[1]销售出库'!$Q$4:$Q$2003,'首页'!$B$4*100+N$4)) -> 0 | O20: =IF($A20="",0,SUMIFS('[1]销售出库'!$R$4:$R$2003,'[1]销售出库'!$H$4:$H$2003,$A20,'[1]销售出库'!$Q$4:$Q$2003,'首页'!$B$4*100+O$4)) -> 0 | P20: =IF($A20="",0,SUMIFS('[1]销售出库'!$R$4:$R$2003,'[1]销售出库'!$H$4:$H$2003,$A20,'[1]销售出库'!$Q$4:$Q$2003,'首页'!$B$4*100+P$4)) -> 0 | Q20: =IF($A20="",0,SUMIFS('[1]销售出库'!$R$4:$R$2003,'[1]销售出库'!$H$4:$H$2003,$A20,'[1]销售出库'!$Q$4:$Q$2003,'首页'!$B$4*100+Q$4)) -> 0 | R20: =IF($A20="",0,SUMIFS('[1]销售出库'!$R$4:$R$2003,'[1]销售出库'!$H$4:$H$2003,$A20,'[1]销售出库'!$Q$4:$Q$2003,'首页'!$B$4*100+R$4)) -> 0 | S20: =IF($A20="",0,SUMIFS('[1]销售出库'!$R$4:$R$2003,'[1]销售出库'!$H$4:$H$2003,$A20,'[1]销售出库'!$Q$4:$Q$2003,'首页'!$B$4*100+S$4)) -> 0 | T20: =IF($A20="",0,SUMIFS('[1]销售出库'!$R$4:$R$2003,'[1]销售出库'!$H$4:$H$2003,$A20,'[1]销售出库'!$Q$4:$Q$2003,'首页'!$B$4*100+T$4)) -> 0 | ... X20: =IF($A20="",0,SUMIFS('[1]销售出库'!$R$4:$R$2003,'[1]销售出库'!$H$4:$H$2003,$A20,'[1]销售出库'!$Q$4:$Q$2003,'首页'!$B$4*100+X$4)) -> 0
A21: =IF('[1]基础资料'!$P$20="","",'[1]基础资料'!$P$20) -> 荣耀平板X10 NDL2W09 6+128星空灰 | B21: =IF(A21="","",'[1]基础资料'!$Q$20&"") -> 平板 | C21: =IF(A21="",0,N('[1]基础资料'!$S$20)) -> 30 | D21: =IF(A21="",0,N('[1]基础资料'!$U$20)) -> 31392.29 | E21: =IF(A21="",0,SUMIFS('[1]采购入库'!$U$4:$U$2003,'[1]采购入库'!$I$4:$I$2003,$A21)) -> 0 | F21: =IF(A21="",0,SUMIFS('[1]采购入库'!$V$4:$V$2003,'[1]采购入库'!$I$4:$I$2003,$A21)) -> 0 | G21: =IF(A21="",0,SUMIFS('[1]销售出库'!$R$4:$R$2003,'[1]销售出库'!$H$4:$H$2003,$A21)) -> 10 | H21: =IF(C21+E21>0,ROUND((D21+F21)/(C21+E21),4),0) -> 1046.4097 | I21: =ROUND(G21*H21,2) -> 10464.1 | J21: =C21+E21-G21 -> 20 | K21: =ROUND(D21+F21-I21,2) -> 20928.19 | L21: =IF(A21="","",IF(J21<0,"负库存：漏记采购或期初不准",IF(AND(G21>0,C21+E21=0),"没进货就卖了",""))) | M21: =IF($A21="",0,SUMIFS('[1]销售出库'!$R$4:$R$2003,'[1]销售出库'!$H$4:$H$2003,$A21,'[1]销售出库'!$Q$4:$Q$2003,'首页'!$B$4*100+M$4)) -> 0 | N21: =IF($A21="",0,SUMIFS('[1]销售出库'!$R$4:$R$2003,'[1]销售出库'!$H$4:$H$2003,$A21,'[1]销售出库'!$Q$4:$Q$2003,'首页'!$B$4*100+N$4)) -> 0 | O21: =IF($A21="",0,SUMIFS('[1]销售出库'!$R$4:$R$2003,'[1]销售出库'!$H$4:$H$2003,$A21,'[1]销售出库'!$Q$4:$Q$2003,'首页'!$B$4*100+O$4)) -> 0 | P21: =IF($A21="",0,SUMIFS('[1]销售出库'!$R$4:$R$2003,'[1]销售出库'!$H$4:$H$2003,$A21,'[1]销售出库'!$Q$4:$Q$2003,'首页'!$B$4*100+P$4)) -> 0 | Q21: =IF($A21="",0,SUMIFS('[1]销售出库'!$R$4:$R$2003,'[1]销售出库'!$H$4:$H$2003,$A21,'[1]销售出库'!$Q$4:$Q$2003,'首页'!$B$4*100+Q$4)) -> 0 | R21: =IF($A21="",0,SUMIFS('[1]销售出库'!$R$4:$R$2003,'[1]销售出库'!$H$4:$H$2003,$A21,'[1]销售出库'!$Q$4:$Q$2003,'首页'!$B$4*100+R$4)) -> 0 | S21: =IF($A21="",0,SUMIFS('[1]销售出库'!$R$4:$R$2003,'[1]销售出库'!$H$4:$H$2003,$A21,'[1]销售出库'!$Q$4:$Q$2003,'首页'!$B$4*100+S$4)) -> 0 | T21: =IF($A21="",0,SUMIFS('[1]销售出库'!$R$4:$R$2003,'[1]销售出库'!$H$4:$H$2003,$A21,'[1]销售出库'!$Q$4:$Q$2003,'首页'!$B$4*100+T$4)) -> 0 | ... X21: =IF($A21="",0,SUMIFS('[1]销售出库'!$R$4:$R$2003,'[1]销售出库'!$H$4:$H$2003,$A21,'[1]销售出库'!$Q$4:$Q$2003,'首页'!$B$4*100+X$4)) -> 0
A22: =IF('[1]基础资料'!$P$21="","",'[1]基础资料'!$P$21) -> 联想平板拯救者Y700 五代 12+256 星光紫WIFI | B22: =IF(A22="","",'[1]基础资料'!$Q$21&"") -> 联想 | C22: =IF(A22="",0,N('[1]基础资料'!$S$21)) -> 57 | D22: =IF(A22="",0,N('[1]基础资料'!$U$21)) -> 171427.5 | E22: =IF(A22="",0,SUMIFS('[1]采购入库'!$U$4:$U$2003,'[1]采购入库'!$I$4:$I$2003,$A22)) -> 20 | F22: =IF(A22="",0,SUMIFS('[1]采购入库'!$V$4:$V$2003,'[1]采购入库'!$I$4:$I$2003,$A22)) -> 61000 | G22: =IF(A22="",0,SUMIFS('[1]销售出库'!$R$4:$R$2003,'[1]销售出库'!$H$4:$H$2003,$A22)) -> 23 | H22: =IF(C22+E22>0,ROUND((D22+F22)/(C22+E22),4),0) -> 3018.539 | I22: =ROUND(G22*H22,2) -> 69426.4 | J22: =C22+E22-G22 -> 54 | K22: =ROUND(D22+F22-I22,2) -> 163001.1 | L22: =IF(A22="","",IF(J22<0,"负库存：漏记采购或期初不准",IF(AND(G22>0,C22+E22=0),"没进货就卖了",""))) | M22: =IF($A22="",0,SUMIFS('[1]销售出库'!$R$4:$R$2003,'[1]销售出库'!$H$4:$H$2003,$A22,'[1]销售出库'!$Q$4:$Q$2003,'首页'!$B$4*100+M$4)) -> 0 | N22: =IF($A22="",0,SUMIFS('[1]销售出库'!$R$4:$R$2003,'[1]销售出库'!$H$4:$H$2003,$A22,'[1]销售出库'!$Q$4:$Q$2003,'首页'!$B$4*100+N$4)) -> 0 | O22: =IF($A22="",0,SUMIFS('[1]销售出库'!$R$4:$R$2003,'[1]销售出库'!$H$4:$H$2003,$A22,'[1]销售出库'!$Q$4:$Q$2003,'首页'!$B$4*100+O$4)) -> 0 | P22: =IF($A22="",0,SUMIFS('[1]销售出库'!$R$4:$R$2003,'[1]销售出库'!$H$4:$H$2003,$A22,'[1]销售出库'!$Q$4:$Q$2003,'首页'!$B$4*100+P$4)) -> 0 | Q22: =IF($A22="",0,SUMIFS('[1]销售出库'!$R$4:$R$2003,'[1]销售出库'!$H$4:$H$2003,$A22,'[1]销售出库'!$Q$4:$Q$2003,'首页'!$B$4*100+Q$4)) -> 0 | R22: =IF($A22="",0,SUMIFS('[1]销售出库'!$R$4:$R$2003,'[1]销售出库'!$H$4:$H$2003,$A22,'[1]销售出库'!$Q$4:$Q$2003,'首页'!$B$4*100+R$4)) -> 0 | S22: =IF($A22="",0,SUMIFS('[1]销售出库'!$R$4:$R$2003,'[1]销售出库'!$H$4:$H$2003,$A22,'[1]销售出库'!$Q$4:$Q$2003,'首页'!$B$4*100+S$4)) -> 0 | T22: =IF($A22="",0,SUMIFS('[1]销售出库'!$R$4:$R$2003,'[1]销售出库'!$H$4:$H$2003,$A22,'[1]销售出库'!$Q$4:$Q$2003,'首页'!$B$4*100+T$4)) -> 0 | ... X22: =IF($A22="",0,SUMIFS('[1]销售出库'!$R$4:$R$2003,'[1]销售出库'!$H$4:$H$2003,$A22,'[1]销售出库'!$Q$4:$Q$2003,'首页'!$B$4*100+X$4)) -> 0
A23: =IF('[1]基础资料'!$P$22="","",'[1]基础资料'!$P$22) -> 联想平板拯救者Y700 五代 16+512 星光紫WIFI | B23: =IF(A23="","",'[1]基础资料'!$Q$22&"") -> 联想 | C23: =IF(A23="",0,N('[1]基础资料'!$S$22)) -> 20 | D23: =IF(A23="",0,N('[1]基础资料'!$U$22)) -> 72600 | E23: =IF(A23="",0,SUMIFS('[1]采购入库'!$U$4:$U$2003,'[1]采购入库'!$I$4:$I$2003,$A23)) -> 0 | F23: =IF(A23="",0,SUMIFS('[1]采购入库'!$V$4:$V$2003,'[1]采购入库'!$I$4:$I$2003,$A23)) -> 0 | G23: =IF(A23="",0,SUMIFS('[1]销售出库'!$R$4:$R$2003,'[1]销售出库'!$H$4:$H$2003,$A23)) -> 0 | H23: =IF(C23+E23>0,ROUND((D23+F23)/(C23+E23),4),0) -> 3630 | I23: =ROUND(G23*H23,2) -> 0 | J23: =C23+E23-G23 -> 20 | K23: =ROUND(D23+F23-I23,2) -> 72600 | L23: =IF(A23="","",IF(J23<0,"负库存：漏记采购或期初不准",IF(AND(G23>0,C23+E23=0),"没进货就卖了",""))) | M23: =IF($A23="",0,SUMIFS('[1]销售出库'!$R$4:$R$2003,'[1]销售出库'!$H$4:$H$2003,$A23,'[1]销售出库'!$Q$4:$Q$2003,'首页'!$B$4*100+M$4)) -> 0 | N23: =IF($A23="",0,SUMIFS('[1]销售出库'!$R$4:$R$2003,'[1]销售出库'!$H$4:$H$2003,$A23,'[1]销售出库'!$Q$4:$Q$2003,'首页'!$B$4*100+N$4)) -> 0 | O23: =IF($A23="",0,SUMIFS('[1]销售出库'!$R$4:$R$2003,'[1]销售出库'!$H$4:$H$2003,$A23,'[1]销售出库'!$Q$4:$Q$2003,'首页'!$B$4*100+O$4)) -> 0 | P23: =IF($A23="",0,SUMIFS('[1]销售出库'!$R$4:$R$2003,'[1]销售出库'!$H$4:$H$2003,$A23,'[1]销售出库'!$Q$4:$Q$2003,'首页'!$B$4*100+P$4)) -> 0 | Q23: =IF($A23="",0,SUMIFS('[1]销售出库'!$R$4:$R$2003,'[1]销售出库'!$H$4:$H$2003,$A23,'[1]销售出库'!$Q$4:$Q$2003,'首页'!$B$4*100+Q$4)) -> 0 | R23: =IF($A23="",0,SUMIFS('[1]销售出库'!$R$4:$R$2003,'[1]销售出库'!$H$4:$H$2003,$A23,'[1]销售出库'!$Q$4:$Q$2003,'首页'!$B$4*100+R$4)) -> 0 | S23: =IF($A23="",0,SUMIFS('[1]销售出库'!$R$4:$R$2003,'[1]销售出库'!$H$4:$H$2003,$A23,'[1]销售出库'!$Q$4:$Q$2003,'首页'!$B$4*100+S$4)) -> 0 | T23: =IF($A23="",0,SUMIFS('[1]销售出库'!$R$4:$R$2003,'[1]销售出库'!$H$4:$H$2003,$A23,'[1]销售出库'!$Q$4:$Q$2003,'首页'!$B$4*100+T$4)) -> 0 | ... X23: =IF($A23="",0,SUMIFS('[1]销售出库'!$R$4:$R$2003,'[1]销售出库'!$H$4:$H$2003,$A23,'[1]销售出库'!$Q$4:$Q$2003,'首页'!$B$4*100+X$4)) -> 0
A24: =IF('[1]基础资料'!$P$23="","",'[1]基础资料'!$P$23) -> 联想平板拯救者Y700 五代世界杯 12+256 莱茵绿WIFI | B24: =IF(A24="","",'[1]基础资料'!$Q$23&"") -> 联想 | C24: =IF(A24="",0,N('[1]基础资料'!$S$23)) -> 87 | D24: =IF(A24="",0,N('[1]基础资料'!$U$23)) -> 287100 | E24: =IF(A24="",0,SUMIFS('[1]采购入库'!$U$4:$U$2003,'[1]采购入库'!$I$4:$I$2003,$A24)) -> 0 | F24: =IF(A24="",0,SUMIFS('[1]采购入库'!$V$4:$V$2003,'[1]采购入库'!$I$4:$I$2003,$A24)) -> 0 | G24: =IF(A24="",0,SUMIFS('[1]销售出库'!$R$4:$R$2003,'[1]销售出库'!$H$4:$H$2003,$A24)) -> 0 | H24: =IF(C24+E24>0,ROUND((D24+F24)/(C24+E24),4),0) -> 3300 | I24: =ROUND(G24*H24,2) -> 0 | J24: =C24+E24-G24 -> 87 | K24: =ROUND(D24+F24-I24,2) -> 287100 | L24: =IF(A24="","",IF(J24<0,"负库存：漏记采购或期初不准",IF(AND(G24>0,C24+E24=0),"没进货就卖了",""))) | M24: =IF($A24="",0,SUMIFS('[1]销售出库'!$R$4:$R$2003,'[1]销售出库'!$H$4:$H$2003,$A24,'[1]销售出库'!$Q$4:$Q$2003,'首页'!$B$4*100+M$4)) -> 0 | N24: =IF($A24="",0,SUMIFS('[1]销售出库'!$R$4:$R$2003,'[1]销售出库'!$H$4:$H$2003,$A24,'[1]销售出库'!$Q$4:$Q$2003,'首页'!$B$4*100+N$4)) -> 0 | O24: =IF($A24="",0,SUMIFS('[1]销售出库'!$R$4:$R$2003,'[1]销售出库'!$H$4:$H$2003,$A24,'[1]销售出库'!$Q$4:$Q$2003,'首页'!$B$4*100+O$4)) -> 0 | P24: =IF($A24="",0,SUMIFS('[1]销售出库'!$R$4:$R$2003,'[1]销售出库'!$H$4:$H$2003,$A24,'[1]销售出库'!$Q$4:$Q$2003,'首页'!$B$4*100+P$4)) -> 0 | Q24: =IF($A24="",0,SUMIFS('[1]销售出库'!$R$4:$R$2003,'[1]销售出库'!$H$4:$H$2003,$A24,'[1]销售出库'!$Q$4:$Q$2003,'首页'!$B$4*100+Q$4)) -> 0 | R24: =IF($A24="",0,SUMIFS('[1]销售出库'!$R$4:$R$2003,'[1]销售出库'!$H$4:$H$2003,$A24,'[1]销售出库'!$Q$4:$Q$2003,'首页'!$B$4*100+R$4)) -> 0 | S24: =IF($A24="",0,SUMIFS('[1]销售出库'!$R$4:$R$2003,'[1]销售出库'!$H$4:$H$2003,$A24,'[1]销售出库'!$Q$4:$Q$2003,'首页'!$B$4*100+S$4)) -> 0 | T24: =IF($A24="",0,SUMIFS('[1]销售出库'!$R$4:$R$2003,'[1]销售出库'!$H$4:$H$2003,$A24,'[1]销售出库'!$Q$4:$Q$2003,'首页'!$B$4*100+T$4)) -> 0 | ... X24: =IF($A24="",0,SUMIFS('[1]销售出库'!$R$4:$R$2003,'[1]销售出库'!$H$4:$H$2003,$A24,'[1]销售出库'!$Q$4:$Q$2003,'首页'!$B$4*100+X$4)) -> 0
A25: =IF('[1]基础资料'!$P$24="","",'[1]基础资料'!$P$24) -> 联想平板拯救者Y700 DNF手游勇士版12+512 | B25: =IF(A25="","",'[1]基础资料'!$Q$24&"") -> 联想 | C25: =IF(A25="",0,N('[1]基础资料'!$S$24)) -> 75 | D25: =IF(A25="",0,N('[1]基础资料'!$U$24)) -> 257700 | E25: =IF(A25="",0,SUMIFS('[1]采购入库'!$U$4:$U$2003,'[1]采购入库'!$I$4:$I$2003,$A25)) -> 0 | F25: =IF(A25="",0,SUMIFS('[1]采购入库'!$V$4:$V$2003,'[1]采购入库'!$I$4:$I$2003,$A25)) -> 0 | G25: =IF(A25="",0,SUMIFS('[1]销售出库'!$R$4:$R$2003,'[1]销售出库'!$H$4:$H$2003,$A25)) -> 0 | H25: =IF(C25+E25>0,ROUND((D25+F25)/(C25+E25),4),0) -> 3436 | I25: =ROUND(G25*H25,2) -> 0 | J25: =C25+E25-G25 -> 75 | K25: =ROUND(D25+F25-I25,2) -> 257700 | L25: =IF(A25="","",IF(J25<0,"负库存：漏记采购或期初不准",IF(AND(G25>0,C25+E25=0),"没进货就卖了",""))) | M25: =IF($A25="",0,SUMIFS('[1]销售出库'!$R$4:$R$2003,'[1]销售出库'!$H$4:$H$2003,$A25,'[1]销售出库'!$Q$4:$Q$2003,'首页'!$B$4*100+M$4)) -> 0 | N25: =IF($A25="",0,SUMIFS('[1]销售出库'!$R$4:$R$2003,'[1]销售出库'!$H$4:$H$2003,$A25,'[1]销售出库'!$Q$4:$Q$2003,'首页'!$B$4*100+N$4)) -> 0 | O25: =IF($A25="",0,SUMIFS('[1]销售出库'!$R$4:$R$2003,'[1]销售出库'!$H$4:$H$2003,$A25,'[1]销售出库'!$Q$4:$Q$2003,'首页'!$B$4*100+O$4)) -> 0 | P25: =IF($A25="",0,SUMIFS('[1]销售出库'!$R$4:$R$2003,'[1]销售出库'!$H$4:$H$2003,$A25,'[1]销售出库'!$Q$4:$Q$2003,'首页'!$B$4*100+P$4)) -> 0 | Q25: =IF($A25="",0,SUMIFS('[1]销售出库'!$R$4:$R$2003,'[1]销售出库'!$H$4:$H$2003,$A25,'[1]销售出库'!$Q$4:$Q$2003,'首页'!$B$4*100+Q$4)) -> 0 | R25: =IF($A25="",0,SUMIFS('[1]销售出库'!$R$4:$R$2003,'[1]销售出库'!$H$4:$H$2003,$A25,'[1]销售出库'!$Q$4:$Q$2003,'首页'!$B$4*100+R$4)) -> 0 | S25: =IF($A25="",0,SUMIFS('[1]销售出库'!$R$4:$R$2003,'[1]销售出库'!$H$4:$H$2003,$A25,'[1]销售出库'!$Q$4:$Q$2003,'首页'!$B$4*100+S$4)) -> 0 | T25: =IF($A25="",0,SUMIFS('[1]销售出库'!$R$4:$R$2003,'[1]销售出库'!$H$4:$H$2003,$A25,'[1]销售出库'!$Q$4:$Q$2003,'首页'!$B$4*100+T$4)) -> 0 | ... X25: =IF($A25="",0,SUMIFS('[1]销售出库'!$R$4:$R$2003,'[1]销售出库'!$H$4:$H$2003,$A25,'[1]销售出库'!$Q$4:$Q$2003,'首页'!$B$4*100+X$4)) -> 0
A26: =IF('[1]基础资料'!$P$25="","",'[1]基础资料'!$P$25) -> 联想平板拯救者Y700 五代世界杯 16+512 莱茵绿WIFI | B26: =IF(A26="","",'[1]基础资料'!$Q$25&"") -> 联想 | C26: =IF(A26="",0,N('[1]基础资料'!$S$25)) -> 85 | D26: =IF(A26="",0,N('[1]基础资料'!$U$25)) -> 327250 | E26: =IF(A26="",0,SUMIFS('[1]采购入库'!$U$4:$U$2003,'[1]采购入库'!$I$4:$I$2003,$A26)) -> 0 | F26: =IF(A26="",0,SUMIFS('[1]采购入库'!$V$4:$V$2003,'[1]采购入库'!$I$4:$I$2003,$A26)) -> 0 | G26: =IF(A26="",0,SUMIFS('[1]销售出库'!$R$4:$R$2003,'[1]销售出库'!$H$4:$H$2003,$A26)) -> 0 | H26: =IF(C26+E26>0,ROUND((D26+F26)/(C26+E26),4),0) -> 3850 | I26: =ROUND(G26*H26,2) -> 0 | J26: =C26+E26-G26 -> 85 | K26: =ROUND(D26+F26-I26,2) -> 327250 | L26: =IF(A26="","",IF(J26<0,"负库存：漏记采购或期初不准",IF(AND(G26>0,C26+E26=0),"没进货就卖了",""))) | M26: =IF($A26="",0,SUMIFS('[1]销售出库'!$R$4:$R$2003,'[1]销售出库'!$H$4:$H$2003,$A26,'[1]销售出库'!$Q$4:$Q$2003,'首页'!$B$4*100+M$4)) -> 0 | N26: =IF($A26="",0,SUMIFS('[1]销售出库'!$R$4:$R$2003,'[1]销售出库'!$H$4:$H$2003,$A26,'[1]销售出库'!$Q$4:$Q$2003,'首页'!$B$4*100+N$4)) -> 0 | O26: =IF($A26="",0,SUMIFS('[1]销售出库'!$R$4:$R$2003,'[1]销售出库'!$H$4:$H$2003,$A26,'[1]销售出库'!$Q$4:$Q$2003,'首页'!$B$4*100+O$4)) -> 0 | P26: =IF($A26="",0,SUMIFS('[1]销售出库'!$R$4:$R$2003,'[1]销售出库'!$H$4:$H$2003,$A26,'[1]销售出库'!$Q$4:$Q$2003,'首页'!$B$4*100+P$4)) -> 0 | Q26: =IF($A26="",0,SUMIFS('[1]销售出库'!$R$4:$R$2003,'[1]销售出库'!$H$4:$H$2003,$A26,'[1]销售出库'!$Q$4:$Q$2003,'首页'!$B$4*100+Q$4)) -> 0 | R26: =IF($A26="",0,SUMIFS('[1]销售出库'!$R$4:$R$2003,'[1]销售出库'!$H$4:$H$2003,$A26,'[1]销售出库'!$Q$4:$Q$2003,'首页'!$B$4*100+R$4)) -> 0 | S26: =IF($A26="",0,SUMIFS('[1]销售出库'!$R$4:$R$2003,'[1]销售出库'!$H$4:$H$2003,$A26,'[1]销售出库'!$Q$4:$Q$2003,'首页'!$B$4*100+S$4)) -> 0 | T26: =IF($A26="",0,SUMIFS('[1]销售出库'!$R$4:$R$2003,'[1]销售出库'!$H$4:$H$2003,$A26,'[1]销售出库'!$Q$4:$Q$2003,'首页'!$B$4*100+T$4)) -> 0 | ... X26: =IF($A26="",0,SUMIFS('[1]销售出库'!$R$4:$R$2003,'[1]销售出库'!$H$4:$H$2003,$A26,'[1]销售出库'!$Q$4:$Q$2003,'首页'!$B$4*100+X$4)) -> 0
A27: =IF('[1]基础资料'!$P$26="","",'[1]基础资料'!$P$26) -> 联想平板拯救者Y900 11+手写笔+键盘套装12+512白色 | B27: =IF(A27="","",'[1]基础资料'!$Q$26&"") -> 联想 | C27: =IF(A27="",0,N('[1]基础资料'!$S$26)) -> 21 | D27: =IF(A27="",0,N('[1]基础资料'!$U$26)) -> 68599.99 | E27: =IF(A27="",0,SUMIFS('[1]采购入库'!$U$4:$U$2003,'[1]采购入库'!$I$4:$I$2003,$A27)) -> 0 | F27: =IF(A27="",0,SUMIFS('[1]采购入库'!$V$4:$V$2003,'[1]采购入库'!$I$4:$I$2003,$A27)) -> 0 | G27: =IF(A27="",0,SUMIFS('[1]销售出库'!$R$4:$R$2003,'[1]销售出库'!$H$4:$H$2003,$A27)) -> 9 | H27: =IF(C27+E27>0,ROUND((D27+F27)/(C27+E27),4),0) -> 3266.6662 | I27: =ROUND(G27*H27,2) -> 29400 | J27: =C27+E27-G27 -> 12 | K27: =ROUND(D27+F27-I27,2) -> 39199.99 | L27: =IF(A27="","",IF(J27<0,"负库存：漏记采购或期初不准",IF(AND(G27>0,C27+E27=0),"没进货就卖了",""))) | M27: =IF($A27="",0,SUMIFS('[1]销售出库'!$R$4:$R$2003,'[1]销售出库'!$H$4:$H$2003,$A27,'[1]销售出库'!$Q$4:$Q$2003,'首页'!$B$4*100+M$4)) -> 0 | N27: =IF($A27="",0,SUMIFS('[1]销售出库'!$R$4:$R$2003,'[1]销售出库'!$H$4:$H$2003,$A27,'[1]销售出库'!$Q$4:$Q$2003,'首页'!$B$4*100+N$4)) -> 0 | O27: =IF($A27="",0,SUMIFS('[1]销售出库'!$R$4:$R$2003,'[1]销售出库'!$H$4:$H$2003,$A27,'[1]销售出库'!$Q$4:$Q$2003,'首页'!$B$4*100+O$4)) -> 0 | P27: =IF($A27="",0,SUMIFS('[1]销售出库'!$R$4:$R$2003,'[1]销售出库'!$H$4:$H$2003,$A27,'[1]销售出库'!$Q$4:$Q$2003,'首页'!$B$4*100+P$4)) -> 0 | Q27: =IF($A27="",0,SUMIFS('[1]销售出库'!$R$4:$R$2003,'[1]销售出库'!$H$4:$H$2003,$A27,'[1]销售出库'!$Q$4:$Q$2003,'首页'!$B$4*100+Q$4)) -> 0 | R27: =IF($A27="",0,SUMIFS('[1]销售出库'!$R$4:$R$2003,'[1]销售出库'!$H$4:$H$2003,$A27,'[1]销售出库'!$Q$4:$Q$2003,'首页'!$B$4*100+R$4)) -> 0 | S27: =IF($A27="",0,SUMIFS('[1]销售出库'!$R$4:$R$2003,'[1]销售出库'!$H$4:$H$2003,$A27,'[1]销售出库'!$Q$4:$Q$2003,'首页'!$B$4*100+S$4)) -> 0 | T27: =IF($A27="",0,SUMIFS('[1]销售出库'!$R$4:$R$2003,'[1]销售出库'!$H$4:$H$2003,$A27,'[1]销售出库'!$Q$4:$Q$2003,'首页'!$B$4*100+T$4)) -> 0 | ... X27: =IF($A27="",0,SUMIFS('[1]销售出库'!$R$4:$R$2003,'[1]销售出库'!$H$4:$H$2003,$A27,'[1]销售出库'!$Q$4:$Q$2003,'首页'!$B$4*100+X$4)) -> 0
A28: =IF('[1]基础资料'!$P$27="","",'[1]基础资料'!$P$27) -> 联想平板拯救者Y900 11+手写笔+键盘套装12+512黑色 | B28: =IF(A28="","",'[1]基础资料'!$Q$27&"") -> 联想 | C28: =IF(A28="",0,N('[1]基础资料'!$S$27)) -> 40 | D28: =IF(A28="",0,N('[1]基础资料'!$U$27)) -> 130558.14 | E28: =IF(A28="",0,SUMIFS('[1]采购入库'!$U$4:$U$2003,'[1]采购入库'!$I$4:$I$2003,$A28)) -> 0 | F28: =IF(A28="",0,SUMIFS('[1]采购入库'!$V$4:$V$2003,'[1]采购入库'!$I$4:$I$2003,$A28)) -> 0 | G28: =IF(A28="",0,SUMIFS('[1]销售出库'!$R$4:$R$2003,'[1]销售出库'!$H$4:$H$2003,$A28)) -> 3 | H28: =IF(C28+E28>0,ROUND((D28+F28)/(C28+E28),4),0) -> 3263.9535 | I28: =ROUND(G28*H28,2) -> 9791.86 | J28: =C28+E28-G28 -> 37 | K28: =ROUND(D28+F28-I28,2) -> 120766.28 | L28: =IF(A28="","",IF(J28<0,"负库存：漏记采购或期初不准",IF(AND(G28>0,C28+E28=0),"没进货就卖了",""))) | M28: =IF($A28="",0,SUMIFS('[1]销售出库'!$R$4:$R$2003,'[1]销售出库'!$H$4:$H$2003,$A28,'[1]销售出库'!$Q$4:$Q$2003,'首页'!$B$4*100+M$4)) -> 0 | N28: =IF($A28="",0,SUMIFS('[1]销售出库'!$R$4:$R$2003,'[1]销售出库'!$H$4:$H$2003,$A28,'[1]销售出库'!$Q$4:$Q$2003,'首页'!$B$4*100+N$4)) -> 0 | O28: =IF($A28="",0,SUMIFS('[1]销售出库'!$R$4:$R$2003,'[1]销售出库'!$H$4:$H$2003,$A28,'[1]销售出库'!$Q$4:$Q$2003,'首页'!$B$4*100+O$4)) -> 0 | P28: =IF($A28="",0,SUMIFS('[1]销售出库'!$R$4:$R$2003,'[1]销售出库'!$H$4:$H$2003,$A28,'[1]销售出库'!$Q$4:$Q$2003,'首页'!$B$4*100+P$4)) -> 0 | Q28: =IF($A28="",0,SUMIFS('[1]销售出库'!$R$4:$R$2003,'[1]销售出库'!$H$4:$H$2003,$A28,'[1]销售出库'!$Q$4:$Q$2003,'首页'!$B$4*100+Q$4)) -> 0 | R28: =IF($A28="",0,SUMIFS('[1]销售出库'!$R$4:$R$2003,'[1]销售出库'!$H$4:$H$2003,$A28,'[1]销售出库'!$Q$4:$Q$2003,'首页'!$B$4*100+R$4)) -> 0 | S28: =IF($A28="",0,SUMIFS('[1]销售出库'!$R$4:$R$2003,'[1]销售出库'!$H$4:$H$2003,$A28,'[1]销售出库'!$Q$4:$Q$2003,'首页'!$B$4*100+S$4)) -> 0 | T28: =IF($A28="",0,SUMIFS('[1]销售出库'!$R$4:$R$2003,'[1]销售出库'!$H$4:$H$2003,$A28,'[1]销售出库'!$Q$4:$Q$2003,'首页'!$B$4*100+T$4)) -> 0 | ... X28: =IF($A28="",0,SUMIFS('[1]销售出库'!$R$4:$R$2003,'[1]销售出库'!$H$4:$H$2003,$A28,'[1]销售出库'!$Q$4:$Q$2003,'首页'!$B$4*100+X$4)) -> 0
A29: =IF('[1]基础资料'!$P$28="","",'[1]基础资料'!$P$28) -> 联想平板拯救者Y900 11+手写笔+键盘套装12+256白色 WIFI | B29: =IF(A29="","",'[1]基础资料'!$Q$28&"") -> 联想 | C29: =IF(A29="",0,N('[1]基础资料'!$S$28)) -> 32 | D29: =IF(A29="",0,N('[1]基础资料'!$U$28)) -> 92160 | E29: =IF(A29="",0,SUMIFS('[1]采购入库'!$U$4:$U$2003,'[1]采购入库'!$I$4:$I$2003,$A29)) -> 0 | F29: =IF(A29="",0,SUMIFS('[1]采购入库'!$V$4:$V$2003,'[1]采购入库'!$I$4:$I$2003,$A29)) -> 0 | G29: =IF(A29="",0,SUMIFS('[1]销售出库'!$R$4:$R$2003,'[1]销售出库'!$H$4:$H$2003,$A29)) -> 0 | H29: =IF(C29+E29>0,ROUND((D29+F29)/(C29+E29),4),0) -> 2880 | I29: =ROUND(G29*H29,2) -> 0 | J29: =C29+E29-G29 -> 32 | K29: =ROUND(D29+F29-I29,2) -> 92160 | L29: =IF(A29="","",IF(J29<0,"负库存：漏记采购或期初不准",IF(AND(G29>0,C29+E29=0),"没进货就卖了",""))) | M29: =IF($A29="",0,SUMIFS('[1]销售出库'!$R$4:$R$2003,'[1]销售出库'!$H$4:$H$2003,$A29,'[1]销售出库'!$Q$4:$Q$2003,'首页'!$B$4*100+M$4)) -> 0 | N29: =IF($A29="",0,SUMIFS('[1]销售出库'!$R$4:$R$2003,'[1]销售出库'!$H$4:$H$2003,$A29,'[1]销售出库'!$Q$4:$Q$2003,'首页'!$B$4*100+N$4)) -> 0 | O29: =IF($A29="",0,SUMIFS('[1]销售出库'!$R$4:$R$2003,'[1]销售出库'!$H$4:$H$2003,$A29,'[1]销售出库'!$Q$4:$Q$2003,'首页'!$B$4*100+O$4)) -> 0 | P29: =IF($A29="",0,SUMIFS('[1]销售出库'!$R$4:$R$2003,'[1]销售出库'!$H$4:$H$2003,$A29,'[1]销售出库'!$Q$4:$Q$2003,'首页'!$B$4*100+P$4)) -> 0 | Q29: =IF($A29="",0,SUMIFS('[1]销售出库'!$R$4:$R$2003,'[1]销售出库'!$H$4:$H$2003,$A29,'[1]销售出库'!$Q$4:$Q$2003,'首页'!$B$4*100+Q$4)) -> 0 | R29: =IF($A29="",0,SUMIFS('[1]销售出库'!$R$4:$R$2003,'[1]销售出库'!$H$4:$H$2003,$A29,'[1]销售出库'!$Q$4:$Q$2003,'首页'!$B$4*100+R$4)) -> 0 | S29: =IF($A29="",0,SUMIFS('[1]销售出库'!$R$4:$R$2003,'[1]销售出库'!$H$4:$H$2003,$A29,'[1]销售出库'!$Q$4:$Q$2003,'首页'!$B$4*100+S$4)) -> 0 | T29: =IF($A29="",0,SUMIFS('[1]销售出库'!$R$4:$R$2003,'[1]销售出库'!$H$4:$H$2003,$A29,'[1]销售出库'!$Q$4:$Q$2003,'首页'!$B$4*100+T$4)) -> 0 | ... X29: =IF($A29="",0,SUMIFS('[1]销售出库'!$R$4:$R$2003,'[1]销售出库'!$H$4:$H$2003,$A29,'[1]销售出库'!$Q$4:$Q$2003,'首页'!$B$4*100+X$4)) -> 0
A30: =IF('[1]基础资料'!$P$29="","",'[1]基础资料'!$P$29) -> 联想平板拯救者Y900 11+手写笔+键盘套装12+256碳晶黑 WIFI | B30: =IF(A30="","",'[1]基础资料'!$Q$29&"") -> 联想 | C30: =IF(A30="",0,N('[1]基础资料'!$S$29)) -> 48 | D30: =IF(A30="",0,N('[1]基础资料'!$U$29)) -> 138240 | E30: =IF(A30="",0,SUMIFS('[1]采购入库'!$U$4:$U$2003,'[1]采购入库'!$I$4:$I$2003,$A30)) -> 0 | F30: =IF(A30="",0,SUMIFS('[1]采购入库'!$V$4:$V$2003,'[1]采购入库'!$I$4:$I$2003,$A30)) -> 0 | G30: =IF(A30="",0,SUMIFS('[1]销售出库'!$R$4:$R$2003,'[1]销售出库'!$H$4:$H$2003,$A30)) -> 0 | H30: =IF(C30+E30>0,ROUND((D30+F30)/(C30+E30),4),0) -> 2880 | I30: =ROUND(G30*H30,2) -> 0 | J30: =C30+E30-G30 -> 48 | K30: =ROUND(D30+F30-I30,2) -> 138240 | L30: =IF(A30="","",IF(J30<0,"负库存：漏记采购或期初不准",IF(AND(G30>0,C30+E30=0),"没进货就卖了",""))) | M30: =IF($A30="",0,SUMIFS('[1]销售出库'!$R$4:$R$2003,'[1]销售出库'!$H$4:$H$2003,$A30,'[1]销售出库'!$Q$4:$Q$2003,'首页'!$B$4*100+M$4)) -> 0 | N30: =IF($A30="",0,SUMIFS('[1]销售出库'!$R$4:$R$2003,'[1]销售出库'!$H$4:$H$2003,$A30,'[1]销售出库'!$Q$4:$Q$2003,'首页'!$B$4*100+N$4)) -> 0 | O30: =IF($A30="",0,SUMIFS('[1]销售出库'!$R$4:$R$2003,'[1]销售出库'!$H$4:$H$2003,$A30,'[1]销售出库'!$Q$4:$Q$2003,'首页'!$B$4*100+O$4)) -> 0 | P30: =IF($A30="",0,SUMIFS('[1]销售出库'!$R$4:$R$2003,'[1]销售出库'!$H$4:$H$2003,$A30,'[1]销售出库'!$Q$4:$Q$2003,'首页'!$B$4*100+P$4)) -> 0 | Q30: =IF($A30="",0,SUMIFS('[1]销售出库'!$R$4:$R$2003,'[1]销售出库'!$H$4:$H$2003,$A30,'[1]销售出库'!$Q$4:$Q$2003,'首页'!$B$4*100+Q$4)) -> 0 | R30: =IF($A30="",0,SUMIFS('[1]销售出库'!$R$4:$R$2003,'[1]销售出库'!$H$4:$H$2003,$A30,'[1]销售出库'!$Q$4:$Q$2003,'首页'!$B$4*100+R$4)) -> 0 | S30: =IF($A30="",0,SUMIFS('[1]销售出库'!$R$4:$R$2003,'[1]销售出库'!$H$4:$H$2003,$A30,'[1]销售出库'!$Q$4:$Q$2003,'首页'!$B$4*100+S$4)) -> 0 | T30: =IF($A30="",0,SUMIFS('[1]销售出库'!$R$4:$R$2003,'[1]销售出库'!$H$4:$H$2003,$A30,'[1]销售出库'!$Q$4:$Q$2003,'首页'!$B$4*100+T$4)) -> 0 | ... X30: =IF($A30="",0,SUMIFS('[1]销售出库'!$R$4:$R$2003,'[1]销售出库'!$H$4:$H$2003,$A30,'[1]销售出库'!$Q$4:$Q$2003,'首页'!$B$4*100+X$4)) -> 0
A31: =IF('[1]基础资料'!$P$30="","",'[1]基础资料'!$P$30) -> 联想平板 拯救者Y900 13 16+512白 WIFI | B31: =IF(A31="","",'[1]基础资料'!$Q$30&"") -> 联想 | C31: =IF(A31="",0,N('[1]基础资料'!$S$30)) -> 53 | D31: =IF(A31="",0,N('[1]基础资料'!$U$30)) -> 179140 | E31: =IF(A31="",0,SUMIFS('[1]采购入库'!$U$4:$U$2003,'[1]采购入库'!$I$4:$I$2003,$A31)) -> 0 | F31: =IF(A31="",0,SUMIFS('[1]采购入库'!$V$4:$V$2003,'[1]采购入库'!$I$4:$I$2003,$A31)) -> 0 | G31: =IF(A31="",0,SUMIFS('[1]销售出库'!$R$4:$R$2003,'[1]销售出库'!$H$4:$H$2003,$A31)) -> 0 | H31: =IF(C31+E31>0,ROUND((D31+F31)/(C31+E31),4),0) -> 3380 | I31: =ROUND(G31*H31,2) -> 0 | J31: =C31+E31-G31 -> 53 | K31: =ROUND(D31+F31-I31,2) -> 179140 | L31: =IF(A31="","",IF(J31<0,"负库存：漏记采购或期初不准",IF(AND(G31>0,C31+E31=0),"没进货就卖了",""))) | M31: =IF($A31="",0,SUMIFS('[1]销售出库'!$R$4:$R$2003,'[1]销售出库'!$H$4:$H$2003,$A31,'[1]销售出库'!$Q$4:$Q$2003,'首页'!$B$4*100+M$4)) -> 0 | N31: =IF($A31="",0,SUMIFS('[1]销售出库'!$R$4:$R$2003,'[1]销售出库'!$H$4:$H$2003,$A31,'[1]销售出库'!$Q$4:$Q$2003,'首页'!$B$4*100+N$4)) -> 0 | O31: =IF($A31="",0,SUMIFS('[1]销售出库'!$R$4:$R$2003,'[1]销售出库'!$H$4:$H$2003,$A31,'[1]销售出库'!$Q$4:$Q$2003,'首页'!$B$4*100+O$4)) -> 0 | P31: =IF($A31="",0,SUMIFS('[1]销售出库'!$R$4:$R$2003,'[1]销售出库'!$H$4:$H$2003,$A31,'[1]销售出库'!$Q$4:$Q$2003,'首页'!$B$4*100+P$4)) -> 0 | Q31: =IF($A31="",0,SUMIFS('[1]销售出库'!$R$4:$R$2003,'[1]销售出库'!$H$4:$H$2003,$A31,'[1]销售出库'!$Q$4:$Q$2003,'首页'!$B$4*100+Q$4)) -> 0 | R31: =IF($A31="",0,SUMIFS('[1]销售出库'!$R$4:$R$2003,'[1]销售出库'!$H$4:$H$2003,$A31,'[1]销售出库'!$Q$4:$Q$2003,'首页'!$B$4*100+R$4)) -> 0 | S31: =IF($A31="",0,SUMIFS('[1]销售出库'!$R$4:$R$2003,'[1]销售出库'!$H$4:$H$2003,$A31,'[1]销售出库'!$Q$4:$Q$2003,'首页'!$B$4*100+S$4)) -> 0 | T31: =IF($A31="",0,SUMIFS('[1]销售出库'!$R$4:$R$2003,'[1]销售出库'!$H$4:$H$2003,$A31,'[1]销售出库'!$Q$4:$Q$2003,'首页'!$B$4*100+T$4)) -> 0 | ... X31: =IF($A31="",0,SUMIFS('[1]销售出库'!$R$4:$R$2003,'[1]销售出库'!$H$4:$H$2003,$A31,'[1]销售出库'!$Q$4:$Q$2003,'首页'!$B$4*100+X$4)) -> 0
A32: =IF('[1]基础资料'!$P$31="","",'[1]基础资料'!$P$31) -> 联想拯救者Y900 11 8+128WIFI白色 | B32: =IF(A32="","",'[1]基础资料'!$Q$31&"") -> 平板 | C32: =IF(A32="",0,N('[1]基础资料'!$S$31)) -> 76 | D32: =IF(A32="",0,N('[1]基础资料'!$U$31)) -> 143848.05 | E32: =IF(A32="",0,SUMIFS('[1]采购入库'!$U$4:$U$2003,'[1]采购入库'!$I$4:$I$2003,$A32)) -> 0 | F32: =IF(A32="",0,SUMIFS('[1]采购入库'!$V$4:$V$2003,'[1]采购入库'!$I$4:$I$2003,$A32)) -> 0 | G32: =IF(A32="",0,SUMIFS('[1]销售出库'!$R$4:$R$2003,'[1]销售出库'!$H$4:$H$2003,$A32)) -> 4 | H32: =IF(C32+E32>0,ROUND((D32+F32)/(C32+E32),4),0) -> 1892.7375 | I32: =ROUND(G32*H32,2) -> 7570.95 | J32: =C32+E32-G32 -> 72 | K32: =ROUND(D32+F32-I32,2) -> 136277.1 | L32: =IF(A32="","",IF(J32<0,"负库存：漏记采购或期初不准",IF(AND(G32>0,C32+E32=0),"没进货就卖了",""))) | M32: =IF($A32="",0,SUMIFS('[1]销售出库'!$R$4:$R$2003,'[1]销售出库'!$H$4:$H$2003,$A32,'[1]销售出库'!$Q$4:$Q$2003,'首页'!$B$4*100+M$4)) -> 0 | N32: =IF($A32="",0,SUMIFS('[1]销售出库'!$R$4:$R$2003,'[1]销售出库'!$H$4:$H$2003,$A32,'[1]销售出库'!$Q$4:$Q$2003,'首页'!$B$4*100+N$4)) -> 0 | O32: =IF($A32="",0,SUMIFS('[1]销售出库'!$R$4:$R$2003,'[1]销售出库'!$H$4:$H$2003,$A32,'[1]销售出库'!$Q$4:$Q$2003,'首页'!$B$4*100+O$4)) -> 0 | P32: =IF($A32="",0,SUMIFS('[1]销售出库'!$R$4:$R$2003,'[1]销售出库'!$H$4:$H$2003,$A32,'[1]销售出库'!$Q$4:$Q$2003,'首页'!$B$4*100+P$4)) -> 0 | Q32: =IF($A32="",0,SUMIFS('[1]销售出库'!$R$4:$R$2003,'[1]销售出库'!$H$4:$H$2003,$A32,'[1]销售出库'!$Q$4:$Q$2003,'首页'!$B$4*100+Q$4)) -> 0 | R32: =IF($A32="",0,SUMIFS('[1]销售出库'!$R$4:$R$2003,'[1]销售出库'!$H$4:$H$2003,$A32,'[1]销售出库'!$Q$4:$Q$2003,'首页'!$B$4*100+R$4)) -> 0 | S32: =IF($A32="",0,SUMIFS('[1]销售出库'!$R$4:$R$2003,'[1]销售出库'!$H$4:$H$2003,$A32,'[1]销售出库'!$Q$4:$Q$2003,'首页'!$B$4*100+S$4)) -> 0 | T32: =IF($A32="",0,SUMIFS('[1]销售出库'!$R$4:$R$2003,'[1]销售出库'!$H$4:$H$2003,$A32,'[1]销售出库'!$Q$4:$Q$2003,'首页'!$B$4*100+T$4)) -> 0 | ... X32: =IF($A32="",0,SUMIFS('[1]销售出库'!$R$4:$R$2003,'[1]销售出库'!$H$4:$H$2003,$A32,'[1]销售出库'!$Q$4:$Q$2003,'首页'!$B$4*100+X$4)) -> 0
A33: =IF('[1]基础资料'!$P$32="","",'[1]基础资料'!$P$32) -> 联想小新Pad Pro（二代）8+128灰色 | B33: =IF(A33="","",'[1]基础资料'!$Q$32&"") -> 联想 | C33: =IF(A33="",0,N('[1]基础资料'!$S$32)) -> 4 | D33: =IF(A33="",0,N('[1]基础资料'!$U$32)) -> 4860 | E33: =IF(A33="",0,SUMIFS('[1]采购入库'!$U$4:$U$2003,'[1]采购入库'!$I$4:$I$2003,$A33)) -> 0 | F33: =IF(A33="",0,SUMIFS('[1]采购入库'!$V$4:$V$2003,'[1]采购入库'!$I$4:$I$2003,$A33)) -> 0 | G33: =IF(A33="",0,SUMIFS('[1]销售出库'!$R$4:$R$2003,'[1]销售出库'!$H$4:$H$2003,$A33)) -> 0 | H33: =IF(C33+E33>0,ROUND((D33+F33)/(C33+E33),4),0) -> 1215 | I33: =ROUND(G33*H33,2) -> 0 | J33: =C33+E33-G33 -> 4 | K33: =ROUND(D33+F33-I33,2) -> 4860 | L33: =IF(A33="","",IF(J33<0,"负库存：漏记采购或期初不准",IF(AND(G33>0,C33+E33=0),"没进货就卖了",""))) | M33: =IF($A33="",0,SUMIFS('[1]销售出库'!$R$4:$R$2003,'[1]销售出库'!$H$4:$H$2003,$A33,'[1]销售出库'!$Q$4:$Q$2003,'首页'!$B$4*100+M$4)) -> 0 | N33: =IF($A33="",0,SUMIFS('[1]销售出库'!$R$4:$R$2003,'[1]销售出库'!$H$4:$H$2003,$A33,'[1]销售出库'!$Q$4:$Q$2003,'首页'!$B$4*100+N$4)) -> 0 | O33: =IF($A33="",0,SUMIFS('[1]销售出库'!$R$4:$R$2003,'[1]销售出库'!$H$4:$H$2003,$A33,'[1]销售出库'!$Q$4:$Q$2003,'首页'!$B$4*100+O$4)) -> 0 | P33: =IF($A33="",0,SUMIFS('[1]销售出库'!$R$4:$R$2003,'[1]销售出库'!$H$4:$H$2003,$A33,'[1]销售出库'!$Q$4:$Q$2003,'首页'!$B$4*100+P$4)) -> 0 | Q33: =IF($A33="",0,SUMIFS('[1]销售出库'!$R$4:$R$2003,'[1]销售出库'!$H$4:$H$2003,$A33,'[1]销售出库'!$Q$4:$Q$2003,'首页'!$B$4*100+Q$4)) -> 0 | R33: =IF($A33="",0,SUMIFS('[1]销售出库'!$R$4:$R$2003,'[1]销售出库'!$H$4:$H$2003,$A33,'[1]销售出库'!$Q$4:$Q$2003,'首页'!$B$4*100+R$4)) -> 0 | S33: =IF($A33="",0,SUMIFS('[1]销售出库'!$R$4:$R$2003,'[1]销售出库'!$H$4:$H$2003,$A33,'[1]销售出库'!$Q$4:$Q$2003,'首页'!$B$4*100+S$4)) -> 0 | T33: =IF($A33="",0,SUMIFS('[1]销售出库'!$R$4:$R$2003,'[1]销售出库'!$H$4:$H$2003,$A33,'[1]销售出库'!$Q$4:$Q$2003,'首页'!$B$4*100+T$4)) -> 0 | ... X33: =IF($A33="",0,SUMIFS('[1]销售出库'!$R$4:$R$2003,'[1]销售出库'!$H$4:$H$2003,$A33,'[1]销售出库'!$Q$4:$Q$2003,'首页'!$B$4*100+X$4)) -> 0
A34: =IF('[1]基础资料'!$P$33="","",'[1]基础资料'!$P$33) -> 联想拯救者Y700平板五代碳晶黑,12GB+256GB,Wifi版 | B34: =IF(A34="","",'[1]基础资料'!$Q$33&"") -> 平板 | C34: =IF(A34="",0,N('[1]基础资料'!$S$33)) -> 288 | D34: =IF(A34="",0,N('[1]基础资料'!$U$33)) -> 858119.56 | E34: =IF(A34="",0,SUMIFS('[1]采购入库'!$U$4:$U$2003,'[1]采购入库'!$I$4:$I$2003,$A34)) -> 1 | F34: =IF(A34="",0,SUMIFS('[1]采购入库'!$V$4:$V$2003,'[1]采购入库'!$I$4:$I$2003,$A34)) -> 3080 | G34: =IF(A34="",0,SUMIFS('[1]销售出库'!$R$4:$R$2003,'[1]销售出库'!$H$4:$H$2003,$A34)) -> 0 | H34: =IF(C34+E34>0,ROUND((D34+F34)/(C34+E34),4),0) -> 2979.9293 | I34: =ROUND(G34*H34,2) -> 0 | J34: =C34+E34-G34 -> 289 | K34: =ROUND(D34+F34-I34,2) -> 861199.56 | L34: =IF(A34="","",IF(J34<0,"负库存：漏记采购或期初不准",IF(AND(G34>0,C34+E34=0),"没进货就卖了",""))) | M34: =IF($A34="",0,SUMIFS('[1]销售出库'!$R$4:$R$2003,'[1]销售出库'!$H$4:$H$2003,$A34,'[1]销售出库'!$Q$4:$Q$2003,'首页'!$B$4*100+M$4)) -> 0 | N34: =IF($A34="",0,SUMIFS('[1]销售出库'!$R$4:$R$2003,'[1]销售出库'!$H$4:$H$2003,$A34,'[1]销售出库'!$Q$4:$Q$2003,'首页'!$B$4*100+N$4)) -> 0 | O34: =IF($A34="",0,SUMIFS('[1]销售出库'!$R$4:$R$2003,'[1]销售出库'!$H$4:$H$2003,$A34,'[1]销售出库'!$Q$4:$Q$2003,'首页'!$B$4*100+O$4)) -> 0 | P34: =IF($A34="",0,SUMIFS('[1]销售出库'!$R$4:$R$2003,'[1]销售出库'!$H$4:$H$2003,$A34,'[1]销售出库'!$Q$4:$Q$2003,'首页'!$B$4*100+P$4)) -> 0 | Q34: =IF($A34="",0,SUMIFS('[1]销售出库'!$R$4:$R$2003,'[1]销售出库'!$H$4:$H$2003,$A34,'[1]销售出库'!$Q$4:$Q$2003,'首页'!$B$4*100+Q$4)) -> 0 | R34: =IF($A34="",0,SUMIFS('[1]销售出库'!$R$4:$R$2003,'[1]销售出库'!$H$4:$H$2003,$A34,'[1]销售出库'!$Q$4:$Q$2003,'首页'!$B$4*100+R$4)) -> 0 | S34: =IF($A34="",0,SUMIFS('[1]销售出库'!$R$4:$R$2003,'[1]销售出库'!$H$4:$H$2003,$A34,'[1]销售出库'!$Q$4:$Q$2003,'首页'!$B$4*100+S$4)) -> 0 | T34: =IF($A34="",0,SUMIFS('[1]销售出库'!$R$4:$R$2003,'[1]销售出库'!$H$4:$H$2003,$A34,'[1]销售出库'!$Q$4:$Q$2003,'首页'!$B$4*100+T$4)) -> 0 | ... X34: =IF($A34="",0,SUMIFS('[1]销售出库'!$R$4:$R$2003,'[1]销售出库'!$H$4:$H$2003,$A34,'[1]销售出库'!$Q$4:$Q$2003,'首页'!$B$4*100+X$4)) -> 0
A35: =IF('[1]基础资料'!$P$34="","",'[1]基础资料'!$P$34) -> 联想拯救者Y900电竞平板旗舰版白色 冰魄白,8GB+256GB,Wifi版 | B35: =IF(A35="","",'[1]基础资料'!$Q$34&"") -> 平板 | C35: =IF(A35="",0,N('[1]基础资料'!$S$34)) -> 25 | D35: =IF(A35="",0,N('[1]基础资料'!$U$34)) -> 60516.8 | E35: =IF(A35="",0,SUMIFS('[1]采购入库'!$U$4:$U$2003,'[1]采购入库'!$I$4:$I$2003,$A35)) -> 0 | F35: =IF(A35="",0,SUMIFS('[1]采购入库'!$V$4:$V$2003,'[1]采购入库'!$I$4:$I$2003,$A35)) -> 0 | G35: =IF(A35="",0,SUMIFS('[1]销售出库'!$R$4:$R$2003,'[1]销售出库'!$H$4:$H$2003,$A35)) -> 0 | H35: =IF(C35+E35>0,ROUND((D35+F35)/(C35+E35),4),0) -> 2420.672 | I35: =ROUND(G35*H35,2) -> 0 | J35: =C35+E35-G35 -> 25 | K35: =ROUND(D35+F35-I35,2) -> 60516.8 | L35: =IF(A35="","",IF(J35<0,"负库存：漏记采购或期初不准",IF(AND(G35>0,C35+E35=0),"没进货就卖了",""))) | M35: =IF($A35="",0,SUMIFS('[1]销售出库'!$R$4:$R$2003,'[1]销售出库'!$H$4:$H$2003,$A35,'[1]销售出库'!$Q$4:$Q$2003,'首页'!$B$4*100+M$4)) -> 0 | N35: =IF($A35="",0,SUMIFS('[1]销售出库'!$R$4:$R$2003,'[1]销售出库'!$H$4:$H$2003,$A35,'[1]销售出库'!$Q$4:$Q$2003,'首页'!$B$4*100+N$4)) -> 0 | O35: =IF($A35="",0,SUMIFS('[1]销售出库'!$R$4:$R$2003,'[1]销售出库'!$H$4:$H$2003,$A35,'[1]销售出库'!$Q$4:$Q$2003,'首页'!$B$4*100+O$4)) -> 0 | P35: =IF($A35="",0,SUMIFS('[1]销售出库'!$R$4:$R$2003,'[1]销售出库'!$H$4:$H$2003,$A35,'[1]销售出库'!$Q$4:$Q$2003,'首页'!$B$4*100+P$4)) -> 0 | Q35: =IF($A35="",0,SUMIFS('[1]销售出库'!$R$4:$R$2003,'[1]销售出库'!$H$4:$H$2003,$A35,'[1]销售出库'!$Q$4:$Q$2003,'首页'!$B$4*100+Q$4)) -> 0 | R35: =IF($A35="",0,SUMIFS('[1]销售出库'!$R$4:$R$2003,'[1]销售出库'!$H$4:$H$2003,$A35,'[1]销售出库'!$Q$4:$Q$2003,'首页'!$B$4*100+R$4)) -> 0 | S35: =IF($A35="",0,SUMIFS('[1]销售出库'!$R$4:$R$2003,'[1]销售出库'!$H$4:$H$2003,$A35,'[1]销售出库'!$Q$4:$Q$2003,'首页'!$B$4*100+S$4)) -> 0 | T35: =IF($A35="",0,SUMIFS('[1]销售出库'!$R$4:$R$2003,'[1]销售出库'!$H$4:$H$2003,$A35,'[1]销售出库'!$Q$4:$Q$2003,'首页'!$B$4*100+T$4)) -> 0 | ... X35: =IF($A35="",0,SUMIFS('[1]销售出库'!$R$4:$R$2003,'[1]销售出库'!$H$4:$H$2003,$A35,'[1]销售出库'!$Q$4:$Q$2003,'首页'!$B$4*100+X$4)) -> 0
A36: =IF('[1]基础资料'!$P$35="","",'[1]基础资料'!$P$35) -> 联想拯救者Y900电竞平板旗舰版深灰色 碳晶黑,8GB+256GB,Wifi版 | B36: =IF(A36="","",'[1]基础资料'!$Q$35&"") -> 平板 | C36: =IF(A36="",0,N('[1]基础资料'!$S$35)) -> 16 | D36: =IF(A36="",0,N('[1]基础资料'!$U$35)) -> 38778.18 | E36: =IF(A36="",0,SUMIFS('[1]采购入库'!$U$4:$U$2003,'[1]采购入库'!$I$4:$I$2003,$A36)) -> 0 | F36: =IF(A36="",0,SUMIFS('[1]采购入库'!$V$4:$V$2003,'[1]采购入库'!$I$4:$I$2003,$A36)) -> 0 | G36: =IF(A36="",0,SUMIFS('[1]销售出库'!$R$4:$R$2003,'[1]销售出库'!$H$4:$H$2003,$A36)) -> 0 | H36: =IF(C36+E36>0,ROUND((D36+F36)/(C36+E36),4),0) -> 2423.6363 | I36: =ROUND(G36*H36,2) -> 0 | J36: =C36+E36-G36 -> 16 | K36: =ROUND(D36+F36-I36,2) -> 38778.18 | L36: =IF(A36="","",IF(J36<0,"负库存：漏记采购或期初不准",IF(AND(G36>0,C36+E36=0),"没进货就卖了",""))) | M36: =IF($A36="",0,SUMIFS('[1]销售出库'!$R$4:$R$2003,'[1]销售出库'!$H$4:$H$2003,$A36,'[1]销售出库'!$Q$4:$Q$2003,'首页'!$B$4*100+M$4)) -> 0 | N36: =IF($A36="",0,SUMIFS('[1]销售出库'!$R$4:$R$2003,'[1]销售出库'!$H$4:$H$2003,$A36,'[1]销售出库'!$Q$4:$Q$2003,'首页'!$B$4*100+N$4)) -> 0 | O36: =IF($A36="",0,SUMIFS('[1]销售出库'!$R$4:$R$2003,'[1]销售出库'!$H$4:$H$2003,$A36,'[1]销售出库'!$Q$4:$Q$2003,'首页'!$B$4*100+O$4)) -> 0 | P36: =IF($A36="",0,SUMIFS('[1]销售出库'!$R$4:$R$2003,'[1]销售出库'!$H$4:$H$2003,$A36,'[1]销售出库'!$Q$4:$Q$2003,'首页'!$B$4*100+P$4)) -> 0 | Q36: =IF($A36="",0,SUMIFS('[1]销售出库'!$R$4:$R$2003,'[1]销售出库'!$H$4:$H$2003,$A36,'[1]销售出库'!$Q$4:$Q$2003,'首页'!$B$4*100+Q$4)) -> 0 | R36: =IF($A36="",0,SUMIFS('[1]销售出库'!$R$4:$R$2003,'[1]销售出库'!$H$4:$H$2003,$A36,'[1]销售出库'!$Q$4:$Q$2003,'首页'!$B$4*100+R$4)) -> 0 | S36: =IF($A36="",0,SUMIFS('[1]销售出库'!$R$4:$R$2003,'[1]销售出库'!$H$4:$H$2003,$A36,'[1]销售出库'!$Q$4:$Q$2003,'首页'!$B$4*100+S$4)) -> 0 | T36: =IF($A36="",0,SUMIFS('[1]销售出库'!$R$4:$R$2003,'[1]销售出库'!$H$4:$H$2003,$A36,'[1]销售出库'!$Q$4:$Q$2003,'首页'!$B$4*100+T$4)) -> 0 | ... X36: =IF($A36="",0,SUMIFS('[1]销售出库'!$R$4:$R$2003,'[1]销售出库'!$H$4:$H$2003,$A36,'[1]销售出库'!$Q$4:$Q$2003,'首页'!$B$4*100+X$4)) -> 0
A37: =IF('[1]基础资料'!$P$36="","",'[1]基础资料'!$P$36) -> 联想拯救者Y700四代 8.8英寸AI游戏平板 骁龙8至尊版碳晶黑,16GB+512GB,Wifi版 | B37: =IF(A37="","",'[1]基础资料'!$Q$36&"") -> 联想 | C37: =IF(A37="",0,N('[1]基础资料'!$S$36)) -> 116 | D37: =IF(A37="",0,N('[1]基础资料'!$U$36)) -> 314472.71 | E37: =IF(A37="",0,SUMIFS('[1]采购入库'!$U$4:$U$2003,'[1]采购入库'!$I$4:$I$2003,$A37)) -> 0 | F37: =IF(A37="",0,SUMIFS('[1]采购入库'!$V$4:$V$2003,'[1]采购入库'!$I$4:$I$2003,$A37)) -> 0 | G37: =IF(A37="",0,SUMIFS('[1]销售出库'!$R$4:$R$2003,'[1]销售出库'!$H$4:$H$2003,$A37)) -> 0 | H37: =IF(C37+E37>0,ROUND((D37+F37)/(C37+E37),4),0) -> 2710.9716 | I37: =ROUND(G37*H37,2) -> 0 | J37: =C37+E37-G37 -> 116 | K37: =ROUND(D37+F37-I37,2) -> 314472.71 | L37: =IF(A37="","",IF(J37<0,"负库存：漏记采购或期初不准",IF(AND(G37>0,C37+E37=0),"没进货就卖了",""))) | M37: =IF($A37="",0,SUMIFS('[1]销售出库'!$R$4:$R$2003,'[1]销售出库'!$H$4:$H$2003,$A37,'[1]销售出库'!$Q$4:$Q$2003,'首页'!$B$4*100+M$4)) -> 0 | N37: =IF($A37="",0,SUMIFS('[1]销售出库'!$R$4:$R$2003,'[1]销售出库'!$H$4:$H$2003,$A37,'[1]销售出库'!$Q$4:$Q$2003,'首页'!$B$4*100+N$4)) -> 0 | O37: =IF($A37="",0,SUMIFS('[1]销售出库'!$R$4:$R$2003,'[1]销售出库'!$H$4:$H$2003,$A37,'[1]销售出库'!$Q$4:$Q$2003,'首页'!$B$4*100+O$4)) -> 0 | P37: =IF($A37="",0,SUMIFS('[1]销售出库'!$R$4:$R$2003,'[1]销售出库'!$H$4:$H$2003,$A37,'[1]销售出库'!$Q$4:$Q$2003,'首页'!$B$4*100+P$4)) -> 0 | Q37: =IF($A37="",0,SUMIFS('[1]销售出库'!$R$4:$R$2003,'[1]销售出库'!$H$4:$H$2003,$A37,'[1]销售出库'!$Q$4:$Q$2003,'首页'!$B$4*100+Q$4)) -> 0 | R37: =IF($A37="",0,SUMIFS('[1]销售出库'!$R$4:$R$2003,'[1]销售出库'!$H$4:$H$2003,$A37,'[1]销售出库'!$Q$4:$Q$2003,'首页'!$B$4*100+R$4)) -> 0 | S37: =IF($A37="",0,SUMIFS('[1]销售出库'!$R$4:$R$2003,'[1]销售出库'!$H$4:$H$2003,$A37,'[1]销售出库'!$Q$4:$Q$2003,'首页'!$B$4*100+S$4)) -> 0 | T37: =IF($A37="",0,SUMIFS('[1]销售出库'!$R$4:$R$2003,'[1]销售出库'!$H$4:$H$2003,$A37,'[1]销售出库'!$Q$4:$Q$2003,'首页'!$B$4*100+T$4)) -> 0 | ... X37: =IF($A37="",0,SUMIFS('[1]销售出库'!$R$4:$R$2003,'[1]销售出库'!$H$4:$H$2003,$A37,'[1]销售出库'!$Q$4:$Q$2003,'首页'!$B$4*100+X$4)) -> 0
A38: =IF('[1]基础资料'!$P$37="","",'[1]基础资料'!$P$37) -> 联想拯救者Y700四代 8.8英寸AI游戏平板 骁龙8至尊版冰魄白,16GB+512GB,Wifi版 | B38: =IF(A38="","",'[1]基础资料'!$Q$37&"") -> 平板 | C38: =IF(A38="",0,N('[1]基础资料'!$S$37)) -> 119 | D38: =IF(A38="",0,N('[1]基础资料'!$U$37)) -> 319730.29 | E38: =IF(A38="",0,SUMIFS('[1]采购入库'!$U$4:$U$2003,'[1]采购入库'!$I$4:$I$2003,$A38)) -> 0 | F38: =IF(A38="",0,SUMIFS('[1]采购入库'!$V$4:$V$2003,'[1]采购入库'!$I$4:$I$2003,$A38)) -> 0 | G38: =IF(A38="",0,SUMIFS('[1]销售出库'!$R$4:$R$2003,'[1]销售出库'!$H$4:$H$2003,$A38)) -> 0 | H38: =IF(C38+E38>0,ROUND((D38+F38)/(C38+E38),4),0) -> 2686.8092 | I38: =ROUND(G38*H38,2) -> 0 | J38: =C38+E38-G38 -> 119 | K38: =ROUND(D38+F38-I38,2) -> 319730.29 | L38: =IF(A38="","",IF(J38<0,"负库存：漏记采购或期初不准",IF(AND(G38>0,C38+E38=0),"没进货就卖了",""))) | M38: =IF($A38="",0,SUMIFS('[1]销售出库'!$R$4:$R$2003,'[1]销售出库'!$H$4:$H$2003,$A38,'[1]销售出库'!$Q$4:$Q$2003,'首页'!$B$4*100+M$4)) -> 0 | N38: =IF($A38="",0,SUMIFS('[1]销售出库'!$R$4:$R$2003,'[1]销售出库'!$H$4:$H$2003,$A38,'[1]销售出库'!$Q$4:$Q$2003,'首页'!$B$4*100+N$4)) -> 0 | O38: =IF($A38="",0,SUMIFS('[1]销售出库'!$R$4:$R$2003,'[1]销售出库'!$H$4:$H$2003,$A38,'[1]销售出库'!$Q$4:$Q$2003,'首页'!$B$4*100+O$4)) -> 0 | P38: =IF($A38="",0,SUMIFS('[1]销售出库'!$R$4:$R$2003,'[1]销售出库'!$H$4:$H$2003,$A38,'[1]销售出库'!$Q$4:$Q$2003,'首页'!$B$4*100+P$4)) -> 0 | Q38: =IF($A38="",0,SUMIFS('[1]销售出库'!$R$4:$R$2003,'[1]销售出库'!$H$4:$H$2003,$A38,'[1]销售出库'!$Q$4:$Q$2003,'首页'!$B$4*100+Q$4)) -> 0 | R38: =IF($A38="",0,SUMIFS('[1]销售出库'!$R$4:$R$2003,'[1]销售出库'!$H$4:$H$2003,$A38,'[1]销售出库'!$Q$4:$Q$2003,'首页'!$B$4*100+R$4)) -> 0 | S38: =IF($A38="",0,SUMIFS('[1]销售出库'!$R$4:$R$2003,'[1]销售出库'!$H$4:$H$2003,$A38,'[1]销售出库'!$Q$4:$Q$2003,'首页'!$B$4*100+S$4)) -> 0 | T38: =IF($A38="",0,SUMIFS('[1]销售出库'!$R$4:$R$2003,'[1]销售出库'!$H$4:$H$2003,$A38,'[1]销售出库'!$Q$4:$Q$2003,'首页'!$B$4*100+T$4)) -> 0 | ... X38: =IF($A38="",0,SUMIFS('[1]销售出库'!$R$4:$R$2003,'[1]销售出库'!$H$4:$H$2003,$A38,'[1]销售出库'!$Q$4:$Q$2003,'首页'!$B$4*100+X$4)) -> 0
A39: =IF('[1]基础资料'!$P$38="","",'[1]基础资料'!$P$38) -> 联想拯救Y700五代第五代骁龙8.8英寸16+512白wifi | B39: =IF(A39="","",'[1]基础资料'!$Q$38&"") -> 平板 | C39: =IF(A39="",0,N('[1]基础资料'!$S$38)) -> 28 | D39: =IF(A39="",0,N('[1]基础资料'!$U$38)) -> 104160 | E39: =IF(A39="",0,SUMIFS('[1]采购入库'!$U$4:$U$2003,'[1]采购入库'!$I$4:$I$2003,$A39)) -> 0 | F39: =IF(A39="",0,SUMIFS('[1]采购入库'!$V$4:$V$2003,'[1]采购入库'!$I$4:$I$2003,$A39)) -> 0 | G39: =IF(A39="",0,SUMIFS('[1]销售出库'!$R$4:$R$2003,'[1]销售出库'!$H$4:$H$2003,$A39)) -> 0 | H39: =IF(C39+E39>0,ROUND((D39+F39)/(C39+E39),4),0) -> 3720 | I39: =ROUND(G39*H39,2) -> 0 | J39: =C39+E39-G39 -> 28 | K39: =ROUND(D39+F39-I39,2) -> 104160 | L39: =IF(A39="","",IF(J39<0,"负库存：漏记采购或期初不准",IF(AND(G39>0,C39+E39=0),"没进货就卖了",""))) | M39: =IF($A39="",0,SUMIFS('[1]销售出库'!$R$4:$R$2003,'[1]销售出库'!$H$4:$H$2003,$A39,'[1]销售出库'!$Q$4:$Q$2003,'首页'!$B$4*100+M$4)) -> 0 | N39: =IF($A39="",0,SUMIFS('[1]销售出库'!$R$4:$R$2003,'[1]销售出库'!$H$4:$H$2003,$A39,'[1]销售出库'!$Q$4:$Q$2003,'首页'!$B$4*100+N$4)) -> 0 | O39: =IF($A39="",0,SUMIFS('[1]销售出库'!$R$4:$R$2003,'[1]销售出库'!$H$4:$H$2003,$A39,'[1]销售出库'!$Q$4:$Q$2003,'首页'!$B$4*100+O$4)) -> 0 | P39: =IF($A39="",0,SUMIFS('[1]销售出库'!$R$4:$R$2003,'[1]销售出库'!$H$4:$H$2003,$A39,'[1]销售出库'!$Q$4:$Q$2003,'首页'!$B$4*100+P$4)) -> 0 | Q39: =IF($A39="",0,SUMIFS('[1]销售出库'!$R$4:$R$2003,'[1]销售出库'!$H$4:$H$2003,$A39,'[1]销售出库'!$Q$4:$Q$2003,'首页'!$B$4*100+Q$4)) -> 0 | R39: =IF($A39="",0,SUMIFS('[1]销售出库'!$R$4:$R$2003,'[1]销售出库'!$H$4:$H$2003,$A39,'[1]销售出库'!$Q$4:$Q$2003,'首页'!$B$4*100+R$4)) -> 0 | S39: =IF($A39="",0,SUMIFS('[1]销售出库'!$R$4:$R$2003,'[1]销售出库'!$H$4:$H$2003,$A39,'[1]销售出库'!$Q$4:$Q$2003,'首页'!$B$4*100+S$4)) -> 0 | T39: =IF($A39="",0,SUMIFS('[1]销售出库'!$R$4:$R$2003,'[1]销售出库'!$H$4:$H$2003,$A39,'[1]销售出库'!$Q$4:$Q$2003,'首页'!$B$4*100+T$4)) -> 0 | ... X39: =IF($A39="",0,SUMIFS('[1]销售出库'!$R$4:$R$2003,'[1]销售出库'!$H$4:$H$2003,$A39,'[1]销售出库'!$Q$4:$Q$2003,'首页'!$B$4*100+X$4)) -> 0
A40: =IF('[1]基础资料'!$P$39="","",'[1]基础资料'!$P$39) -> 联想拯救Y700五代第五代骁龙8.8英寸12+256白wifi | B40: =IF(A40="","",'[1]基础资料'!$Q$39&"") -> 平板 | C40: =IF(A40="",0,N('[1]基础资料'!$S$39)) -> 101 | D40: =IF(A40="",0,N('[1]基础资料'!$U$39)) -> 294263.14 | E40: =IF(A40="",0,SUMIFS('[1]采购入库'!$U$4:$U$2003,'[1]采购入库'!$I$4:$I$2003,$A40)) -> 0 | F40: =IF(A40="",0,SUMIFS('[1]采购入库'!$V$4:$V$2003,'[1]采购入库'!$I$4:$I$2003,$A40)) -> 0 | G40: =IF(A40="",0,SUMIFS('[1]销售出库'!$R$4:$R$2003,'[1]销售出库'!$H$4:$H$2003,$A40)) -> 0 | H40: =IF(C40+E40>0,ROUND((D40+F40)/(C40+E40),4),0) -> 2913.4964 | I40: =ROUND(G40*H40,2) -> 0 | J40: =C40+E40-G40 -> 101 | K40: =ROUND(D40+F40-I40,2) -> 294263.14 | L40: =IF(A40="","",IF(J40<0,"负库存：漏记采购或期初不准",IF(AND(G40>0,C40+E40=0),"没进货就卖了",""))) | M40: =IF($A40="",0,SUMIFS('[1]销售出库'!$R$4:$R$2003,'[1]销售出库'!$H$4:$H$2003,$A40,'[1]销售出库'!$Q$4:$Q$2003,'首页'!$B$4*100+M$4)) -> 0 | N40: =IF($A40="",0,SUMIFS('[1]销售出库'!$R$4:$R$2003,'[1]销售出库'!$H$4:$H$2003,$A40,'[1]销售出库'!$Q$4:$Q$2003,'首页'!$B$4*100+N$4)) -> 0 | O40: =IF($A40="",0,SUMIFS('[1]销售出库'!$R$4:$R$2003,'[1]销售出库'!$H$4:$H$2003,$A40,'[1]销售出库'!$Q$4:$Q$2003,'首页'!$B$4*100+O$4)) -> 0 | P40: =IF($A40="",0,SUMIFS('[1]销售出库'!$R$4:$R$2003,'[1]销售出库'!$H$4:$H$2003,$A40,'[1]销售出库'!$Q$4:$Q$2003,'首页'!$B$4*100+P$4)) -> 0 | Q40: =IF($A40="",0,SUMIFS('[1]销售出库'!$R$4:$R$2003,'[1]销售出库'!$H$4:$H$2003,$A40,'[1]销售出库'!$Q$4:$Q$2003,'首页'!$B$4*100+Q$4)) -> 0 | R40: =IF($A40="",0,SUMIFS('[1]销售出库'!$R$4:$R$2003,'[1]销售出库'!$H$4:$H$2003,$A40,'[1]销售出库'!$Q$4:$Q$2003,'首页'!$B$4*100+R$4)) -> 0 | S40: =IF($A40="",0,SUMIFS('[1]销售出库'!$R$4:$R$2003,'[1]销售出库'!$H$4:$H$2003,$A40,'[1]销售出库'!$Q$4:$Q$2003,'首页'!$B$4*100+S$4)) -> 0 | T40: =IF($A40="",0,SUMIFS('[1]销售出库'!$R$4:$R$2003,'[1]销售出库'!$H$4:$H$2003,$A40,'[1]销售出库'!$Q$4:$Q$2003,'首页'!$B$4*100+T$4)) -> 0 | ... X40: =IF($A40="",0,SUMIFS('[1]销售出库'!$R$4:$R$2003,'[1]销售出库'!$H$4:$H$2003,$A40,'[1]销售出库'!$Q$4:$Q$2003,'首页'!$B$4*100+X$4)) -> 0
A41: =IF('[1]基础资料'!$P$40="","",'[1]基础资料'!$P$40) -> 联想手写笔Pro（第二代）AP602U | B41: =IF(A41="","",'[1]基础资料'!$Q$40&"") -> 配件 | C41: =IF(A41="",0,N('[1]基础资料'!$S$40)) -> 196 | D41: =IF(A41="",0,N('[1]基础资料'!$U$40)) -> 51719.52 | E41: =IF(A41="",0,SUMIFS('[1]采购入库'!$U$4:$U$2003,'[1]采购入库'!$I$4:$I$2003,$A41)) -> 301 | F41: =IF(A41="",0,SUMIFS('[1]采购入库'!$V$4:$V$2003,'[1]采购入库'!$I$4:$I$2003,$A41)) -> 80066 | G41: =IF(A41="",0,SUMIFS('[1]销售出库'!$R$4:$R$2003,'[1]销售出库'!$H$4:$H$2003,$A41)) -> 105 | H41: =IF(C41+E41>0,ROUND((D41+F41)/(C41+E41),4),0) -> 265.162 | I41: =ROUND(G41*H41,2) -> 27842.01 | J41: =C41+E41-G41 -> 392 | K41: =ROUND(D41+F41-I41,2) -> 103943.51 | L41: =IF(A41="","",IF(J41<0,"负库存：漏记采购或期初不准",IF(AND(G41>0,C41+E41=0),"没进货就卖了",""))) | M41: =IF($A41="",0,SUMIFS('[1]销售出库'!$R$4:$R$2003,'[1]销售出库'!$H$4:$H$2003,$A41,'[1]销售出库'!$Q$4:$Q$2003,'首页'!$B$4*100+M$4)) -> 0 | N41: =IF($A41="",0,SUMIFS('[1]销售出库'!$R$4:$R$2003,'[1]销售出库'!$H$4:$H$2003,$A41,'[1]销售出库'!$Q$4:$Q$2003,'首页'!$B$4*100+N$4)) -> 0 | O41: =IF($A41="",0,SUMIFS('[1]销售出库'!$R$4:$R$2003,'[1]销售出库'!$H$4:$H$2003,$A41,'[1]销售出库'!$Q$4:$Q$2003,'首页'!$B$4*100+O$4)) -> 0 | P41: =IF($A41="",0,SUMIFS('[1]销售出库'!$R$4:$R$2003,'[1]销售出库'!$H$4:$H$2003,$A41,'[1]销售出库'!$Q$4:$Q$2003,'首页'!$B$4*100+P$4)) -> 0 | Q41: =IF($A41="",0,SUMIFS('[1]销售出库'!$R$4:$R$2003,'[1]销售出库'!$H$4:$H$2003,$A41,'[1]销售出库'!$Q$4:$Q$2003,'首页'!$B$4*100+Q$4)) -> 0 | R41: =IF($A41="",0,SUMIFS('[1]销售出库'!$R$4:$R$2003,'[1]销售出库'!$H$4:$H$2003,$A41,'[1]销售出库'!$Q$4:$Q$2003,'首页'!$B$4*100+R$4)) -> 0 | S41: =IF($A41="",0,SUMIFS('[1]销售出库'!$R$4:$R$2003,'[1]销售出库'!$H$4:$H$2003,$A41,'[1]销售出库'!$Q$4:$Q$2003,'首页'!$B$4*100+S$4)) -> 0 | T41: =IF($A41="",0,SUMIFS('[1]销售出库'!$R$4:$R$2003,'[1]销售出库'!$H$4:$H$2003,$A41,'[1]销售出库'!$Q$4:$Q$2003,'首页'!$B$4*100+T$4)) -> 0 | ... X41: =IF($A41="",0,SUMIFS('[1]销售出库'!$R$4:$R$2003,'[1]销售出库'!$H$4:$H$2003,$A41,'[1]销售出库'!$Q$4:$Q$2003,'首页'!$B$4*100+X$4)) -> 0
A42: =IF('[1]基础资料'!$P$41="","",'[1]基础资料'!$P$41) -> 华硕主机内存条32G | B42: =IF(A42="","",'[1]基础资料'!$Q$41&"") -> 配件 | C42: =IF(A42="",0,N('[1]基础资料'!$S$41)) -> 4 | D42: =IF(A42="",0,N('[1]基础资料'!$U$41)) -> 9200 | E42: =IF(A42="",0,SUMIFS('[1]采购入库'!$U$4:$U$2003,'[1]采购入库'!$I$4:$I$2003,$A42)) -> 0 | F42: =IF(A42="",0,SUMIFS('[1]采购入库'!$V$4:$V$2003,'[1]采购入库'!$I$4:$I$2003,$A42)) -> 0 | G42: =IF(A42="",0,SUMIFS('[1]销售出库'!$R$4:$R$2003,'[1]销售出库'!$H$4:$H$2003,$A42)) -> 0 | H42: =IF(C42+E42>0,ROUND((D42+F42)/(C42+E42),4),0) -> 2300 | I42: =ROUND(G42*H42,2) -> 0 | J42: =C42+E42-G42 -> 4 | K42: =ROUND(D42+F42-I42,2) -> 9200 | L42: =IF(A42="","",IF(J42<0,"负库存：漏记采购或期初不准",IF(AND(G42>0,C42+E42=0),"没进货就卖了",""))) | M42: =IF($A42="",0,SUMIFS('[1]销售出库'!$R$4:$R$2003,'[1]销售出库'!$H$4:$H$2003,$A42,'[1]销售出库'!$Q$4:$Q$2003,'首页'!$B$4*100+M$4)) -> 0 | N42: =IF($A42="",0,SUMIFS('[1]销售出库'!$R$4:$R$2003,'[1]销售出库'!$H$4:$H$2003,$A42,'[1]销售出库'!$Q$4:$Q$2003,'首页'!$B$4*100+N$4)) -> 0 | O42: =IF($A42="",0,SUMIFS('[1]销售出库'!$R$4:$R$2003,'[1]销售出库'!$H$4:$H$2003,$A42,'[1]销售出库'!$Q$4:$Q$2003,'首页'!$B$4*100+O$4)) -> 0 | P42: =IF($A42="",0,SUMIFS('[1]销售出库'!$R$4:$R$2003,'[1]销售出库'!$H$4:$H$2003,$A42,'[1]销售出库'!$Q$4:$Q$2003,'首页'!$B$4*100+P$4)) -> 0 | Q42: =IF($A42="",0,SUMIFS('[1]销售出库'!$R$4:$R$2003,'[1]销售出库'!$H$4:$H$2003,$A42,'[1]销售出库'!$Q$4:$Q$2003,'首页'!$B$4*100+Q$4)) -> 0 | R42: =IF($A42="",0,SUMIFS('[1]销售出库'!$R$4:$R$2003,'[1]销售出库'!$H$4:$H$2003,$A42,'[1]销售出库'!$Q$4:$Q$2003,'首页'!$B$4*100+R$4)) -> 0 | S42: =IF($A42="",0,SUMIFS('[1]销售出库'!$R$4:$R$2003,'[1]销售出库'!$H$4:$H$2003,$A42,'[1]销售出库'!$Q$4:$Q$2003,'首页'!$B$4*100+S$4)) -> 0 | T42: =IF($A42="",0,SUMIFS('[1]销售出库'!$R$4:$R$2003,'[1]销售出库'!$H$4:$H$2003,$A42,'[1]销售出库'!$Q$4:$Q$2003,'首页'!$B$4*100+T$4)) -> 0 | ... X42: =IF($A42="",0,SUMIFS('[1]销售出库'!$R$4:$R$2003,'[1]销售出库'!$H$4:$H$2003,$A42,'[1]销售出库'!$Q$4:$Q$2003,'首页'!$B$4*100+X$4)) -> 0
A43: =IF('[1]基础资料'!$P$42="","",'[1]基础资料'!$P$42) -> 华硕主机内存条16G | B43: =IF(A43="","",'[1]基础资料'!$Q$42&"") -> 配件 | C43: =IF(A43="",0,N('[1]基础资料'!$S$42)) -> 279 | D43: =IF(A43="",0,N('[1]基础资料'!$U$42)) -> 320850 | E43: =IF(A43="",0,SUMIFS('[1]采购入库'!$U$4:$U$2003,'[1]采购入库'!$I$4:$I$2003,$A43)) -> 0 | F43: =IF(A43="",0,SUMIFS('[1]采购入库'!$V$4:$V$2003,'[1]采购入库'!$I$4:$I$2003,$A43)) -> 0 | G43: =IF(A43="",0,SUMIFS('[1]销售出库'!$R$4:$R$2003,'[1]销售出库'!$H$4:$H$2003,$A43)) -> 0 | H43: =IF(C43+E43>0,ROUND((D43+F43)/(C43+E43),4),0) -> 1150 | I43: =ROUND(G43*H43,2) -> 0 | J43: =C43+E43-G43 -> 279 | K43: =ROUND(D43+F43-I43,2) -> 320850 | L43: =IF(A43="","",IF(J43<0,"负库存：漏记采购或期初不准",IF(AND(G43>0,C43+E43=0),"没进货就卖了",""))) | M43: =IF($A43="",0,SUMIFS('[1]销售出库'!$R$4:$R$2003,'[1]销售出库'!$H$4:$H$2003,$A43,'[1]销售出库'!$Q$4:$Q$2003,'首页'!$B$4*100+M$4)) -> 0 | N43: =IF($A43="",0,SUMIFS('[1]销售出库'!$R$4:$R$2003,'[1]销售出库'!$H$4:$H$2003,$A43,'[1]销售出库'!$Q$4:$Q$2003,'首页'!$B$4*100+N$4)) -> 0 | O43: =IF($A43="",0,SUMIFS('[1]销售出库'!$R$4:$R$2003,'[1]销售出库'!$H$4:$H$2003,$A43,'[1]销售出库'!$Q$4:$Q$2003,'首页'!$B$4*100+O$4)) -> 0 | P43: =IF($A43="",0,SUMIFS('[1]销售出库'!$R$4:$R$2003,'[1]销售出库'!$H$4:$H$2003,$A43,'[1]销售出库'!$Q$4:$Q$2003,'首页'!$B$4*100+P$4)) -> 0 | Q43: =IF($A43="",0,SUMIFS('[1]销售出库'!$R$4:$R$2003,'[1]销售出库'!$H$4:$H$2003,$A43,'[1]销售出库'!$Q$4:$Q$2003,'首页'!$B$4*100+Q$4)) -> 0 | R43: =IF($A43="",0,SUMIFS('[1]销售出库'!$R$4:$R$2003,'[1]销售出库'!$H$4:$H$2003,$A43,'[1]销售出库'!$Q$4:$Q$2003,'首页'!$B$4*100+R$4)) -> 0 | S43: =IF($A43="",0,SUMIFS('[1]销售出库'!$R$4:$R$2003,'[1]销售出库'!$H$4:$H$2003,$A43,'[1]销售出库'!$Q$4:$Q$2003,'首页'!$B$4*100+S$4)) -> 0 | T43: =IF($A43="",0,SUMIFS('[1]销售出库'!$R$4:$R$2003,'[1]销售出库'!$H$4:$H$2003,$A43,'[1]销售出库'!$Q$4:$Q$2003,'首页'!$B$4*100+T$4)) -> 0 | ... X43: =IF($A43="",0,SUMIFS('[1]销售出库'!$R$4:$R$2003,'[1]销售出库'!$H$4:$H$2003,$A43,'[1]销售出库'!$Q$4:$Q$2003,'首页'!$B$4*100+X$4)) -> 0
A44: =IF('[1]基础资料'!$P$43="","",'[1]基础资料'!$P$43) -> 华硕主机破晓6X-S501SER | B44: =IF(A44="","",'[1]基础资料'!$Q$43&"") -> 华硕 | C44: =IF(A44="",0,N('[1]基础资料'!$S$43)) -> 147 | D44: =IF(A44="",0,N('[1]基础资料'!$U$43)) -> 102900 | E44: =IF(A44="",0,SUMIFS('[1]采购入库'!$U$4:$U$2003,'[1]采购入库'!$I$4:$I$2003,$A44)) -> 0 | F44: =IF(A44="",0,SUMIFS('[1]采购入库'!$V$4:$V$2003,'[1]采购入库'!$I$4:$I$2003,$A44)) -> 0 | G44: =IF(A44="",0,SUMIFS('[1]销售出库'!$R$4:$R$2003,'[1]销售出库'!$H$4:$H$2003,$A44)) -> 0 | H44: =IF(C44+E44>0,ROUND((D44+F44)/(C44+E44),4),0) -> 700 | I44: =ROUND(G44*H44,2) -> 0 | J44: =C44+E44-G44 -> 147 | K44: =ROUND(D44+F44-I44,2) -> 102900 | L44: =IF(A44="","",IF(J44<0,"负库存：漏记采购或期初不准",IF(AND(G44>0,C44+E44=0),"没进货就卖了",""))) | M44: =IF($A44="",0,SUMIFS('[1]销售出库'!$R$4:$R$2003,'[1]销售出库'!$H$4:$H$2003,$A44,'[1]销售出库'!$Q$4:$Q$2003,'首页'!$B$4*100+M$4)) -> 0 | N44: =IF($A44="",0,SUMIFS('[1]销售出库'!$R$4:$R$2003,'[1]销售出库'!$H$4:$H$2003,$A44,'[1]销售出库'!$Q$4:$Q$2003,'首页'!$B$4*100+N$4)) -> 0 | O44: =IF($A44="",0,SUMIFS('[1]销售出库'!$R$4:$R$2003,'[1]销售出库'!$H$4:$H$2003,$A44,'[1]销售出库'!$Q$4:$Q$2003,'首页'!$B$4*100+O$4)) -> 0 | P44: =IF($A44="",0,SUMIFS('[1]销售出库'!$R$4:$R$2003,'[1]销售出库'!$H$4:$H$2003,$A44,'[1]销售出库'!$Q$4:$Q$2003,'首页'!$B$4*100+P$4)) -> 0 | Q44: =IF($A44="",0,SUMIFS('[1]销售出库'!$R$4:$R$2003,'[1]销售出库'!$H$4:$H$2003,$A44,'[1]销售出库'!$Q$4:$Q$2003,'首页'!$B$4*100+Q$4)) -> 0 | R44: =IF($A44="",0,SUMIFS('[1]销售出库'!$R$4:$R$2003,'[1]销售出库'!$H$4:$H$2003,$A44,'[1]销售出库'!$Q$4:$Q$2003,'首页'!$B$4*100+R$4)) -> 0 | S44: =IF($A44="",0,SUMIFS('[1]销售出库'!$R$4:$R$2003,'[1]销售出库'!$H$4:$H$2003,$A44,'[1]销售出库'!$Q$4:$Q$2003,'首页'!$B$4*100+S$4)) -> 0 | T44: =IF($A44="",0,SUMIFS('[1]销售出库'!$R$4:$R$2003,'[1]销售出库'!$H$4:$H$2003,$A44,'[1]销售出库'!$Q$4:$Q$2003,'首页'!$B$4*100+T$4)) -> 0 | ... X44: =IF($A44="",0,SUMIFS('[1]销售出库'!$R$4:$R$2003,'[1]销售出库'!$H$4:$H$2003,$A44,'[1]销售出库'!$Q$4:$Q$2003,'首页'!$B$4*100+X$4)) -> 0
A45: =IF('[1]基础资料'!$P$44="","",'[1]基础资料'!$P$44) -> 天选6Pro FX608LM235 U5-235HX-16G-512G-RTX5060-高色域1K屏幕-青 | B45: =IF(A45="","",'[1]基础资料'!$Q$44&"") -> 华硕 | C45: =IF(A45="",0,N('[1]基础资料'!$S$44)) -> 72 | D45: =IF(A45="",0,N('[1]基础资料'!$U$44)) -> 514781.13 | E45: =IF(A45="",0,SUMIFS('[1]采购入库'!$U$4:$U$2003,'[1]采购入库'!$I$4:$I$2003,$A45)) -> 0 | F45: =IF(A45="",0,SUMIFS('[1]采购入库'!$V$4:$V$2003,'[1]采购入库'!$I$4:$I$2003,$A45)) -> 0 | G45: =IF(A45="",0,SUMIFS('[1]销售出库'!$R$4:$R$2003,'[1]销售出库'!$H$4:$H$2003,$A45)) -> 0 | H45: =IF(C45+E45>0,ROUND((D45+F45)/(C45+E45),4),0) -> 7149.7379 | I45: =ROUND(G45*H45,2) -> 0 | J45: =C45+E45-G45 -> 72 | K45: =ROUND(D45+F45-I45,2) -> 514781.13 | L45: =IF(A45="","",IF(J45<0,"负库存：漏记采购或期初不准",IF(AND(G45>0,C45+E45=0),"没进货就卖了",""))) | M45: =IF($A45="",0,SUMIFS('[1]销售出库'!$R$4:$R$2003,'[1]销售出库'!$H$4:$H$2003,$A45,'[1]销售出库'!$Q$4:$Q$2003,'首页'!$B$4*100+M$4)) -> 0 | N45: =IF($A45="",0,SUMIFS('[1]销售出库'!$R$4:$R$2003,'[1]销售出库'!$H$4:$H$2003,$A45,'[1]销售出库'!$Q$4:$Q$2003,'首页'!$B$4*100+N$4)) -> 0 | O45: =IF($A45="",0,SUMIFS('[1]销售出库'!$R$4:$R$2003,'[1]销售出库'!$H$4:$H$2003,$A45,'[1]销售出库'!$Q$4:$Q$2003,'首页'!$B$4*100+O$4)) -> 0 | P45: =IF($A45="",0,SUMIFS('[1]销售出库'!$R$4:$R$2003,'[1]销售出库'!$H$4:$H$2003,$A45,'[1]销售出库'!$Q$4:$Q$2003,'首页'!$B$4*100+P$4)) -> 0 | Q45: =IF($A45="",0,SUMIFS('[1]销售出库'!$R$4:$R$2003,'[1]销售出库'!$H$4:$H$2003,$A45,'[1]销售出库'!$Q$4:$Q$2003,'首页'!$B$4*100+Q$4)) -> 0 | R45: =IF($A45="",0,SUMIFS('[1]销售出库'!$R$4:$R$2003,'[1]销售出库'!$H$4:$H$2003,$A45,'[1]销售出库'!$Q$4:$Q$2003,'首页'!$B$4*100+R$4)) -> 0 | S45: =IF($A45="",0,SUMIFS('[1]销售出库'!$R$4:$R$2003,'[1]销售出库'!$H$4:$H$2003,$A45,'[1]销售出库'!$Q$4:$Q$2003,'首页'!$B$4*100+S$4)) -> 0 | T45: =IF($A45="",0,SUMIFS('[1]销售出库'!$R$4:$R$2003,'[1]销售出库'!$H$4:$H$2003,$A45,'[1]销售出库'!$Q$4:$Q$2003,'首页'!$B$4*100+T$4)) -> 0 | ... X45: =IF($A45="",0,SUMIFS('[1]销售出库'!$R$4:$R$2003,'[1]销售出库'!$H$4:$H$2003,$A45,'[1]销售出库'!$Q$4:$Q$2003,'首页'!$B$4*100+X$4)) -> 0
A46: =IF('[1]基础资料'!$P$45="","",'[1]基础资料'!$P$45) -> 天选6Pro FX608LM235 U5-235HX-16G-512G-RTX5060-2.5K-灰 | B46: =IF(A46="","",'[1]基础资料'!$Q$45&"") -> 华硕 | C46: =IF(A46="",0,N('[1]基础资料'!$S$45)) -> 8 | D46: =IF(A46="",0,N('[1]基础资料'!$U$45)) -> 63950.4 | E46: =IF(A46="",0,SUMIFS('[1]采购入库'!$U$4:$U$2003,'[1]采购入库'!$I$4:$I$2003,$A46)) -> 0 | F46: =IF(A46="",0,SUMIFS('[1]采购入库'!$V$4:$V$2003,'[1]采购入库'!$I$4:$I$2003,$A46)) -> 0 | G46: =IF(A46="",0,SUMIFS('[1]销售出库'!$R$4:$R$2003,'[1]销售出库'!$H$4:$H$2003,$A46)) -> 0 | H46: =IF(C46+E46>0,ROUND((D46+F46)/(C46+E46),4),0) -> 7993.8 | I46: =ROUND(G46*H46,2) -> 0 | J46: =C46+E46-G46 -> 8 | K46: =ROUND(D46+F46-I46,2) -> 63950.4 | L46: =IF(A46="","",IF(J46<0,"负库存：漏记采购或期初不准",IF(AND(G46>0,C46+E46=0),"没进货就卖了",""))) | M46: =IF($A46="",0,SUMIFS('[1]销售出库'!$R$4:$R$2003,'[1]销售出库'!$H$4:$H$2003,$A46,'[1]销售出库'!$Q$4:$Q$2003,'首页'!$B$4*100+M$4)) -> 0 | N46: =IF($A46="",0,SUMIFS('[1]销售出库'!$R$4:$R$2003,'[1]销售出库'!$H$4:$H$2003,$A46,'[1]销售出库'!$Q$4:$Q$2003,'首页'!$B$4*100+N$4)) -> 0 | O46: =IF($A46="",0,SUMIFS('[1]销售出库'!$R$4:$R$2003,'[1]销售出库'!$H$4:$H$2003,$A46,'[1]销售出库'!$Q$4:$Q$2003,'首页'!$B$4*100+O$4)) -> 0 | P46: =IF($A46="",0,SUMIFS('[1]销售出库'!$R$4:$R$2003,'[1]销售出库'!$H$4:$H$2003,$A46,'[1]销售出库'!$Q$4:$Q$2003,'首页'!$B$4*100+P$4)) -> 0 | Q46: =IF($A46="",0,SUMIFS('[1]销售出库'!$R$4:$R$2003,'[1]销售出库'!$H$4:$H$2003,$A46,'[1]销售出库'!$Q$4:$Q$2003,'首页'!$B$4*100+Q$4)) -> 0 | R46: =IF($A46="",0,SUMIFS('[1]销售出库'!$R$4:$R$2003,'[1]销售出库'!$H$4:$H$2003,$A46,'[1]销售出库'!$Q$4:$Q$2003,'首页'!$B$4*100+R$4)) -> 0 | S46: =IF($A46="",0,SUMIFS('[1]销售出库'!$R$4:$R$2003,'[1]销售出库'!$H$4:$H$2003,$A46,'[1]销售出库'!$Q$4:$Q$2003,'首页'!$B$4*100+S$4)) -> 0 | T46: =IF($A46="",0,SUMIFS('[1]销售出库'!$R$4:$R$2003,'[1]销售出库'!$H$4:$H$2003,$A46,'[1]销售出库'!$Q$4:$Q$2003,'首页'!$B$4*100+T$4)) -> 0 | ... X46: =IF($A46="",0,SUMIFS('[1]销售出库'!$R$4:$R$2003,'[1]销售出库'!$H$4:$H$2003,$A46,'[1]销售出库'!$Q$4:$Q$2003,'首页'!$B$4*100+X$4)) -> 0
A47: =IF('[1]基础资料'!$P$46="","",'[1]基础资料'!$P$46) -> DJI OSMO MOBILE 7P 手机云台 | B47: =IF(A47="","",'[1]基础资料'!$Q$46&"") -> 大疆 | C47: =IF(A47="",0,N('[1]基础资料'!$S$46)) -> 1944 | D47: =IF(A47="",0,N('[1]基础资料'!$U$46)) -> 985192.57 | E47: =IF(A47="",0,SUMIFS('[1]采购入库'!$U$4:$U$2003,'[1]采购入库'!$I$4:$I$2003,$A47)) -> 0 | F47: =IF(A47="",0,SUMIFS('[1]采购入库'!$V$4:$V$2003,'[1]采购入库'!$I$4:$I$2003,$A47)) -> 0 | G47: =IF(A47="",0,SUMIFS('[1]销售出库'!$R$4:$R$2003,'[1]销售出库'!$H$4:$H$2003,$A47)) -> 21 | H47: =IF(C47+E47>0,ROUND((D47+F47)/(C47+E47),4),0) -> 506.7863 | I47: =ROUND(G47*H47,2) -> 10642.51 | J47: =C47+E47-G47 -> 1923 | K47: =ROUND(D47+F47-I47,2) -> 974550.06 | L47: =IF(A47="","",IF(J47<0,"负库存：漏记采购或期初不准",IF(AND(G47>0,C47+E47=0),"没进货就卖了",""))) | M47: =IF($A47="",0,SUMIFS('[1]销售出库'!$R$4:$R$2003,'[1]销售出库'!$H$4:$H$2003,$A47,'[1]销售出库'!$Q$4:$Q$2003,'首页'!$B$4*100+M$4)) -> 0 | N47: =IF($A47="",0,SUMIFS('[1]销售出库'!$R$4:$R$2003,'[1]销售出库'!$H$4:$H$2003,$A47,'[1]销售出库'!$Q$4:$Q$2003,'首页'!$B$4*100+N$4)) -> 0 | O47: =IF($A47="",0,SUMIFS('[1]销售出库'!$R$4:$R$2003,'[1]销售出库'!$H$4:$H$2003,$A47,'[1]销售出库'!$Q$4:$Q$2003,'首页'!$B$4*100+O$4)) -> 0 | P47: =IF($A47="",0,SUMIFS('[1]销售出库'!$R$4:$R$2003,'[1]销售出库'!$H$4:$H$2003,$A47,'[1]销售出库'!$Q$4:$Q$2003,'首页'!$B$4*100+P$4)) -> 0 | Q47: =IF($A47="",0,SUMIFS('[1]销售出库'!$R$4:$R$2003,'[1]销售出库'!$H$4:$H$2003,$A47,'[1]销售出库'!$Q$4:$Q$2003,'首页'!$B$4*100+Q$4)) -> 0 | R47: =IF($A47="",0,SUMIFS('[1]销售出库'!$R$4:$R$2003,'[1]销售出库'!$H$4:$H$2003,$A47,'[1]销售出库'!$Q$4:$Q$2003,'首页'!$B$4*100+R$4)) -> 0 | S47: =IF($A47="",0,SUMIFS('[1]销售出库'!$R$4:$R$2003,'[1]销售出库'!$H$4:$H$2003,$A47,'[1]销售出库'!$Q$4:$Q$2003,'首页'!$B$4*100+S$4)) -> 0 | T47: =IF($A47="",0,SUMIFS('[1]销售出库'!$R$4:$R$2003,'[1]销售出库'!$H$4:$H$2003,$A47,'[1]销售出库'!$Q$4:$Q$2003,'首页'!$B$4*100+T$4)) -> 0 | ... X47: =IF($A47="",0,SUMIFS('[1]销售出库'!$R$4:$R$2003,'[1]销售出库'!$H$4:$H$2003,$A47,'[1]销售出库'!$Q$4:$Q$2003,'首页'!$B$4*100+X$4)) -> 0
A48: =IF('[1]基础资料'!$P$47="","",'[1]基础资料'!$P$47) -> 华硕无畏16SE 2026款 C5-320-16+512 1K 144hz 2.5k银 | B48: =IF(A48="","",'[1]基础资料'!$Q$47&"") -> 华硕 | C48: =IF(A48="",0,N('[1]基础资料'!$S$47)) -> 3 | D48: =IF(A48="",0,N('[1]基础资料'!$U$47)) -> 13890 | E48: =IF(A48="",0,SUMIFS('[1]采购入库'!$U$4:$U$2003,'[1]采购入库'!$I$4:$I$2003,$A48)) -> 3 | F48: =IF(A48="",0,SUMIFS('[1]采购入库'!$V$4:$V$2003,'[1]采购入库'!$I$4:$I$2003,$A48)) -> 13890 | G48: =IF(A48="",0,SUMIFS('[1]销售出库'!$R$4:$R$2003,'[1]销售出库'!$H$4:$H$2003,$A48)) -> 0 | H48: =IF(C48+E48>0,ROUND((D48+F48)/(C48+E48),4),0) -> 4630 | I48: =ROUND(G48*H48,2) -> 0 | J48: =C48+E48-G48 -> 6 | K48: =ROUND(D48+F48-I48,2) -> 27780 | L48: =IF(A48="","",IF(J48<0,"负库存：漏记采购或期初不准",IF(AND(G48>0,C48+E48=0),"没进货就卖了",""))) | M48: =IF($A48="",0,SUMIFS('[1]销售出库'!$R$4:$R$2003,'[1]销售出库'!$H$4:$H$2003,$A48,'[1]销售出库'!$Q$4:$Q$2003,'首页'!$B$4*100+M$4)) -> 0 | N48: =IF($A48="",0,SUMIFS('[1]销售出库'!$R$4:$R$2003,'[1]销售出库'!$H$4:$H$2003,$A48,'[1]销售出库'!$Q$4:$Q$2003,'首页'!$B$4*100+N$4)) -> 0 | O48: =IF($A48="",0,SUMIFS('[1]销售出库'!$R$4:$R$2003,'[1]销售出库'!$H$4:$H$2003,$A48,'[1]销售出库'!$Q$4:$Q$2003,'首页'!$B$4*100+O$4)) -> 0 | P48: =IF($A48="",0,SUMIFS('[1]销售出库'!$R$4:$R$2003,'[1]销售出库'!$H$4:$H$2003,$A48,'[1]销售出库'!$Q$4:$Q$2003,'首页'!$B$4*100+P$4)) -> 0 | Q48: =IF($A48="",0,SUMIFS('[1]销售出库'!$R$4:$R$2003,'[1]销售出库'!$H$4:$H$2003,$A48,'[1]销售出库'!$Q$4:$Q$2003,'首页'!$B$4*100+Q$4)) -> 0 | R48: =IF($A48="",0,SUMIFS('[1]销售出库'!$R$4:$R$2003,'[1]销售出库'!$H$4:$H$2003,$A48,'[1]销售出库'!$Q$4:$Q$2003,'首页'!$B$4*100+R$4)) -> 0 | S48: =IF($A48="",0,SUMIFS('[1]销售出库'!$R$4:$R$2003,'[1]销售出库'!$H$4:$H$2003,$A48,'[1]销售出库'!$Q$4:$Q$2003,'首页'!$B$4*100+S$4)) -> 0 | T48: =IF($A48="",0,SUMIFS('[1]销售出库'!$R$4:$R$2003,'[1]销售出库'!$H$4:$H$2003,$A48,'[1]销售出库'!$Q$4:$Q$2003,'首页'!$B$4*100+T$4)) -> 0 | ... X48: =IF($A48="",0,SUMIFS('[1]销售出库'!$R$4:$R$2003,'[1]销售出库'!$H$4:$H$2003,$A48,'[1]销售出库'!$Q$4:$Q$2003,'首页'!$B$4*100+X$4)) -> 0
A49: =IF('[1]基础资料'!$P$48="","",'[1]基础资料'!$P$48) -> 联想小新Air15 2026 Core5 320/16GB/512GB灰色 | B49: =IF(A49="","",'[1]基础资料'!$Q$48&"") -> 联想 | C49: =IF(A49="",0,N('[1]基础资料'!$S$48)) -> 19 | D49: =IF(A49="",0,N('[1]基础资料'!$U$48)) -> 87970 | E49: =IF(A49="",0,SUMIFS('[1]采购入库'!$U$4:$U$2003,'[1]采购入库'!$I$4:$I$2003,$A49)) -> 0 | F49: =IF(A49="",0,SUMIFS('[1]采购入库'!$V$4:$V$2003,'[1]采购入库'!$I$4:$I$2003,$A49)) -> 0 | G49: =IF(A49="",0,SUMIFS('[1]销售出库'!$R$4:$R$2003,'[1]销售出库'!$H$4:$H$2003,$A49)) -> 0 | H49: =IF(C49+E49>0,ROUND((D49+F49)/(C49+E49),4),0) -> 4630 | I49: =ROUND(G49*H49,2) -> 0 | J49: =C49+E49-G49 -> 19 | K49: =ROUND(D49+F49-I49,2) -> 87970 | L49: =IF(A49="","",IF(J49<0,"负库存：漏记采购或期初不准",IF(AND(G49>0,C49+E49=0),"没进货就卖了",""))) | M49: =IF($A49="",0,SUMIFS('[1]销售出库'!$R$4:$R$2003,'[1]销售出库'!$H$4:$H$2003,$A49,'[1]销售出库'!$Q$4:$Q$2003,'首页'!$B$4*100+M$4)) -> 0 | N49: =IF($A49="",0,SUMIFS('[1]销售出库'!$R$4:$R$2003,'[1]销售出库'!$H$4:$H$2003,$A49,'[1]销售出库'!$Q$4:$Q$2003,'首页'!$B$4*100+N$4)) -> 0 | O49: =IF($A49="",0,SUMIFS('[1]销售出库'!$R$4:$R$2003,'[1]销售出库'!$H$4:$H$2003,$A49,'[1]销售出库'!$Q$4:$Q$2003,'首页'!$B$4*100+O$4)) -> 0 | P49: =IF($A49="",0,SUMIFS('[1]销售出库'!$R$4:$R$2003,'[1]销售出库'!$H$4:$H$2003,$A49,'[1]销售出库'!$Q$4:$Q$2003,'首页'!$B$4*100+P$4)) -> 0 | Q49: =IF($A49="",0,SUMIFS('[1]销售出库'!$R$4:$R$2003,'[1]销售出库'!$H$4:$H$2003,$A49,'[1]销售出库'!$Q$4:$Q$2003,'首页'!$B$4*100+Q$4)) -> 0 | R49: =IF($A49="",0,SUMIFS('[1]销售出库'!$R$4:$R$2003,'[1]销售出库'!$H$4:$H$2003,$A49,'[1]销售出库'!$Q$4:$Q$2003,'首页'!$B$4*100+R$4)) -> 0 | S49: =IF($A49="",0,SUMIFS('[1]销售出库'!$R$4:$R$2003,'[1]销售出库'!$H$4:$H$2003,$A49,'[1]销售出库'!$Q$4:$Q$2003,'首页'!$B$4*100+S$4)) -> 0 | T49: =IF($A49="",0,SUMIFS('[1]销售出库'!$R$4:$R$2003,'[1]销售出库'!$H$4:$H$2003,$A49,'[1]销售出库'!$Q$4:$Q$2003,'首页'!$B$4*100+T$4)) -> 0 | ... X49: =IF($A49="",0,SUMIFS('[1]销售出库'!$R$4:$R$2003,'[1]销售出库'!$H$4:$H$2003,$A49,'[1]销售出库'!$Q$4:$Q$2003,'首页'!$B$4*100+X$4)) -> 0
A50: =IF('[1]基础资料'!$P$49="","",'[1]基础资料'!$P$49) -> 联想小新16 R7-255 16G 512 120Hz | B50: =IF(A50="","",'[1]基础资料'!$Q$49&"") -> 联想 | C50: =IF(A50="",0,N('[1]基础资料'!$S$49)) -> 31 | D50: =IF(A50="",0,N('[1]基础资料'!$U$49)) -> 141812.42 | E50: =IF(A50="",0,SUMIFS('[1]采购入库'!$U$4:$U$2003,'[1]采购入库'!$I$4:$I$2003,$A50)) -> 3 | F50: =IF(A50="",0,SUMIFS('[1]采购入库'!$V$4:$V$2003,'[1]采购入库'!$I$4:$I$2003,$A50)) -> 15626 | G50: =IF(A50="",0,SUMIFS('[1]销售出库'!$R$4:$R$2003,'[1]销售出库'!$H$4:$H$2003,$A50)) -> 3 | H50: =IF(C50+E50>0,ROUND((D50+F50)/(C50+E50),4),0) -> 4630.5418 | I50: =ROUND(G50*H50,2) -> 13891.63 | J50: =C50+E50-G50 -> 31 | K50: =ROUND(D50+F50-I50,2) -> 143546.79 | L50: =IF(A50="","",IF(J50<0,"负库存：漏记采购或期初不准",IF(AND(G50>0,C50+E50=0),"没进货就卖了",""))) | M50: =IF($A50="",0,SUMIFS('[1]销售出库'!$R$4:$R$2003,'[1]销售出库'!$H$4:$H$2003,$A50,'[1]销售出库'!$Q$4:$Q$2003,'首页'!$B$4*100+M$4)) -> 0 | N50: =IF($A50="",0,SUMIFS('[1]销售出库'!$R$4:$R$2003,'[1]销售出库'!$H$4:$H$2003,$A50,'[1]销售出库'!$Q$4:$Q$2003,'首页'!$B$4*100+N$4)) -> 0 | O50: =IF($A50="",0,SUMIFS('[1]销售出库'!$R$4:$R$2003,'[1]销售出库'!$H$4:$H$2003,$A50,'[1]销售出库'!$Q$4:$Q$2003,'首页'!$B$4*100+O$4)) -> 0 | P50: =IF($A50="",0,SUMIFS('[1]销售出库'!$R$4:$R$2003,'[1]销售出库'!$H$4:$H$2003,$A50,'[1]销售出库'!$Q$4:$Q$2003,'首页'!$B$4*100+P$4)) -> 0 | Q50: =IF($A50="",0,SUMIFS('[1]销售出库'!$R$4:$R$2003,'[1]销售出库'!$H$4:$H$2003,$A50,'[1]销售出库'!$Q$4:$Q$2003,'首页'!$B$4*100+Q$4)) -> 0 | R50: =IF($A50="",0,SUMIFS('[1]销售出库'!$R$4:$R$2003,'[1]销售出库'!$H$4:$H$2003,$A50,'[1]销售出库'!$Q$4:$Q$2003,'首页'!$B$4*100+R$4)) -> 0 | S50: =IF($A50="",0,SUMIFS('[1]销售出库'!$R$4:$R$2003,'[1]销售出库'!$H$4:$H$2003,$A50,'[1]销售出库'!$Q$4:$Q$2003,'首页'!$B$4*100+S$4)) -> 0 | T50: =IF($A50="",0,SUMIFS('[1]销售出库'!$R$4:$R$2003,'[1]销售出库'!$H$4:$H$2003,$A50,'[1]销售出库'!$Q$4:$Q$2003,'首页'!$B$4*100+T$4)) -> 0 | ... X50: =IF($A50="",0,SUMIFS('[1]销售出库'!$R$4:$R$2003,'[1]销售出库'!$H$4:$H$2003,$A50,'[1]销售出库'!$Q$4:$Q$2003,'首页'!$B$4*100+X$4)) -> 0
A51: =IF('[1]基础资料'!$P$50="","",'[1]基础资料'!$P$50) -> 联想小新16 R7-255 16G 512 60Hz | B51: =IF(A51="","",'[1]基础资料'!$Q$50&"") -> 联想 | C51: =IF(A51="",0,N('[1]基础资料'!$S$50)) -> 43 | D51: =IF(A51="",0,N('[1]基础资料'!$U$50)) -> 166054.43 | E51: =IF(A51="",0,SUMIFS('[1]采购入库'!$U$4:$U$2003,'[1]采购入库'!$I$4:$I$2003,$A51)) -> 0 | F51: =IF(A51="",0,SUMIFS('[1]采购入库'!$V$4:$V$2003,'[1]采购入库'!$I$4:$I$2003,$A51)) -> 0 | G51: =IF(A51="",0,SUMIFS('[1]销售出库'!$R$4:$R$2003,'[1]销售出库'!$H$4:$H$2003,$A51)) -> 0 | H51: =IF(C51+E51>0,ROUND((D51+F51)/(C51+E51),4),0) -> 3861.7309 | I51: =ROUND(G51*H51,2) -> 0 | J51: =C51+E51-G51 -> 43 | K51: =ROUND(D51+F51-I51,2) -> 166054.43 | L51: =IF(A51="","",IF(J51<0,"负库存：漏记采购或期初不准",IF(AND(G51>0,C51+E51=0),"没进货就卖了",""))) | M51: =IF($A51="",0,SUMIFS('[1]销售出库'!$R$4:$R$2003,'[1]销售出库'!$H$4:$H$2003,$A51,'[1]销售出库'!$Q$4:$Q$2003,'首页'!$B$4*100+M$4)) -> 0 | N51: =IF($A51="",0,SUMIFS('[1]销售出库'!$R$4:$R$2003,'[1]销售出库'!$H$4:$H$2003,$A51,'[1]销售出库'!$Q$4:$Q$2003,'首页'!$B$4*100+N$4)) -> 0 | O51: =IF($A51="",0,SUMIFS('[1]销售出库'!$R$4:$R$2003,'[1]销售出库'!$H$4:$H$2003,$A51,'[1]销售出库'!$Q$4:$Q$2003,'首页'!$B$4*100+O$4)) -> 0 | P51: =IF($A51="",0,SUMIFS('[1]销售出库'!$R$4:$R$2003,'[1]销售出库'!$H$4:$H$2003,$A51,'[1]销售出库'!$Q$4:$Q$2003,'首页'!$B$4*100+P$4)) -> 0 | Q51: =IF($A51="",0,SUMIFS('[1]销售出库'!$R$4:$R$2003,'[1]销售出库'!$H$4:$H$2003,$A51,'[1]销售出库'!$Q$4:$Q$2003,'首页'!$B$4*100+Q$4)) -> 0 | R51: =IF($A51="",0,SUMIFS('[1]销售出库'!$R$4:$R$2003,'[1]销售出库'!$H$4:$H$2003,$A51,'[1]销售出库'!$Q$4:$Q$2003,'首页'!$B$4*100+R$4)) -> 0 | S51: =IF($A51="",0,SUMIFS('[1]销售出库'!$R$4:$R$2003,'[1]销售出库'!$H$4:$H$2003,$A51,'[1]销售出库'!$Q$4:$Q$2003,'首页'!$B$4*100+S$4)) -> 0 | T51: =IF($A51="",0,SUMIFS('[1]销售出库'!$R$4:$R$2003,'[1]销售出库'!$H$4:$H$2003,$A51,'[1]销售出库'!$Q$4:$Q$2003,'首页'!$B$4*100+T$4)) -> 0 | ... X51: =IF($A51="",0,SUMIFS('[1]销售出库'!$R$4:$R$2003,'[1]销售出库'!$H$4:$H$2003,$A51,'[1]销售出库'!$Q$4:$Q$2003,'首页'!$B$4*100+X$4)) -> 0
A52: =IF('[1]基础资料'!$P$51="","",'[1]基础资料'!$P$51) -> 联想小新16C R7-8745Hs 16 512 灰色 | B52: =IF(A52="","",'[1]基础资料'!$Q$51&"") -> 联想 | C52: =IF(A52="",0,N('[1]基础资料'!$S$51)) -> 7 | D52: =IF(A52="",0,N('[1]基础资料'!$U$51)) -> 30180 | E52: =IF(A52="",0,SUMIFS('[1]采购入库'!$U$4:$U$2003,'[1]采购入库'!$I$4:$I$2003,$A52)) -> 0 | F52: =IF(A52="",0,SUMIFS('[1]采购入库'!$V$4:$V$2003,'[1]采购入库'!$I$4:$I$2003,$A52)) -> 0 | G52: =IF(A52="",0,SUMIFS('[1]销售出库'!$R$4:$R$2003,'[1]销售出库'!$H$4:$H$2003,$A52)) -> 0 | H52: =IF(C52+E52>0,ROUND((D52+F52)/(C52+E52),4),0) -> 4311.4286 | I52: =ROUND(G52*H52,2) -> 0 | J52: =C52+E52-G52 -> 7 | K52: =ROUND(D52+F52-I52,2) -> 30180 | L52: =IF(A52="","",IF(J52<0,"负库存：漏记采购或期初不准",IF(AND(G52>0,C52+E52=0),"没进货就卖了",""))) | M52: =IF($A52="",0,SUMIFS('[1]销售出库'!$R$4:$R$2003,'[1]销售出库'!$H$4:$H$2003,$A52,'[1]销售出库'!$Q$4:$Q$2003,'首页'!$B$4*100+M$4)) -> 0 | N52: =IF($A52="",0,SUMIFS('[1]销售出库'!$R$4:$R$2003,'[1]销售出库'!$H$4:$H$2003,$A52,'[1]销售出库'!$Q$4:$Q$2003,'首页'!$B$4*100+N$4)) -> 0 | O52: =IF($A52="",0,SUMIFS('[1]销售出库'!$R$4:$R$2003,'[1]销售出库'!$H$4:$H$2003,$A52,'[1]销售出库'!$Q$4:$Q$2003,'首页'!$B$4*100+O$4)) -> 0 | P52: =IF($A52="",0,SUMIFS('[1]销售出库'!$R$4:$R$2003,'[1]销售出库'!$H$4:$H$2003,$A52,'[1]销售出库'!$Q$4:$Q$2003,'首页'!$B$4*100+P$4)) -> 0 | Q52: =IF($A52="",0,SUMIFS('[1]销售出库'!$R$4:$R$2003,'[1]销售出库'!$H$4:$H$2003,$A52,'[1]销售出库'!$Q$4:$Q$2003,'首页'!$B$4*100+Q$4)) -> 0 | R52: =IF($A52="",0,SUMIFS('[1]销售出库'!$R$4:$R$2003,'[1]销售出库'!$H$4:$H$2003,$A52,'[1]销售出库'!$Q$4:$Q$2003,'首页'!$B$4*100+R$4)) -> 0 | S52: =IF($A52="",0,SUMIFS('[1]销售出库'!$R$4:$R$2003,'[1]销售出库'!$H$4:$H$2003,$A52,'[1]销售出库'!$Q$4:$Q$2003,'首页'!$B$4*100+S$4)) -> 0 | T52: =IF($A52="",0,SUMIFS('[1]销售出库'!$R$4:$R$2003,'[1]销售出库'!$H$4:$H$2003,$A52,'[1]销售出库'!$Q$4:$Q$2003,'首页'!$B$4*100+T$4)) -> 0 | ... X52: =IF($A52="",0,SUMIFS('[1]销售出库'!$R$4:$R$2003,'[1]销售出库'!$H$4:$H$2003,$A52,'[1]销售出库'!$Q$4:$Q$2003,'首页'!$B$4*100+X$4)) -> 0
A53: =IF('[1]基础资料'!$P$52="","",'[1]基础资料'!$P$52) -> 联想小新Air14Ultra5-228V 120Hz 灰色,32GB,1TB SSD,官方标配 | B53: =IF(A53="","",'[1]基础资料'!$Q$52&"") -> 联想 | C53: =IF(A53="",0,N('[1]基础资料'!$S$52)) -> 18 | D53: =IF(A53="",0,N('[1]基础资料'!$U$52)) -> 124656 | E53: =IF(A53="",0,SUMIFS('[1]采购入库'!$U$4:$U$2003,'[1]采购入库'!$I$4:$I$2003,$A53)) -> 5 | F53: =IF(A53="",0,SUMIFS('[1]采购入库'!$V$4:$V$2003,'[1]采购入库'!$I$4:$I$2003,$A53)) -> 36440 | G53: =IF(A53="",0,SUMIFS('[1]销售出库'!$R$4:$R$2003,'[1]销售出库'!$H$4:$H$2003,$A53)) -> 0 | H53: =IF(C53+E53>0,ROUND((D53+F53)/(C53+E53),4),0) -> 7004.1739 | I53: =ROUND(G53*H53,2) -> 0 | J53: =C53+E53-G53 -> 23 | K53: =ROUND(D53+F53-I53,2) -> 161096 | L53: =IF(A53="","",IF(J53<0,"负库存：漏记采购或期初不准",IF(AND(G53>0,C53+E53=0),"没进货就卖了",""))) | M53: =IF($A53="",0,SUMIFS('[1]销售出库'!$R$4:$R$2003,'[1]销售出库'!$H$4:$H$2003,$A53,'[1]销售出库'!$Q$4:$Q$2003,'首页'!$B$4*100+M$4)) -> 0 | N53: =IF($A53="",0,SUMIFS('[1]销售出库'!$R$4:$R$2003,'[1]销售出库'!$H$4:$H$2003,$A53,'[1]销售出库'!$Q$4:$Q$2003,'首页'!$B$4*100+N$4)) -> 0 | O53: =IF($A53="",0,SUMIFS('[1]销售出库'!$R$4:$R$2003,'[1]销售出库'!$H$4:$H$2003,$A53,'[1]销售出库'!$Q$4:$Q$2003,'首页'!$B$4*100+O$4)) -> 0 | P53: =IF($A53="",0,SUMIFS('[1]销售出库'!$R$4:$R$2003,'[1]销售出库'!$H$4:$H$2003,$A53,'[1]销售出库'!$Q$4:$Q$2003,'首页'!$B$4*100+P$4)) -> 0 | Q53: =IF($A53="",0,SUMIFS('[1]销售出库'!$R$4:$R$2003,'[1]销售出库'!$H$4:$H$2003,$A53,'[1]销售出库'!$Q$4:$Q$2003,'首页'!$B$4*100+Q$4)) -> 0 | R53: =IF($A53="",0,SUMIFS('[1]销售出库'!$R$4:$R$2003,'[1]销售出库'!$H$4:$H$2003,$A53,'[1]销售出库'!$Q$4:$Q$2003,'首页'!$B$4*100+R$4)) -> 0 | S53: =IF($A53="",0,SUMIFS('[1]销售出库'!$R$4:$R$2003,'[1]销售出库'!$H$4:$H$2003,$A53,'[1]销售出库'!$Q$4:$Q$2003,'首页'!$B$4*100+S$4)) -> 0 | T53: =IF($A53="",0,SUMIFS('[1]销售出库'!$R$4:$R$2003,'[1]销售出库'!$H$4:$H$2003,$A53,'[1]销售出库'!$Q$4:$Q$2003,'首页'!$B$4*100+T$4)) -> 0 | ... X53: =IF($A53="",0,SUMIFS('[1]销售出库'!$R$4:$R$2003,'[1]销售出库'!$H$4:$H$2003,$A53,'[1]销售出库'!$Q$4:$Q$2003,'首页'!$B$4*100+X$4)) -> 0
A54: =IF('[1]基础资料'!$P$53="","",'[1]基础资料'!$P$53) -> 联想小新Pro14 Ultra5-336H/32GB/1TB/集显 | B54: =IF(A54="","",'[1]基础资料'!$Q$53&"") -> 联想 | C54: =IF(A54="",0,N('[1]基础资料'!$S$53)) -> 8 | D54: =IF(A54="",0,N('[1]基础资料'!$U$53)) -> 58600 | E54: =IF(A54="",0,SUMIFS('[1]采购入库'!$U$4:$U$2003,'[1]采购入库'!$I$4:$I$2003,$A54)) -> 0 | F54: =IF(A54="",0,SUMIFS('[1]采购入库'!$V$4:$V$2003,'[1]采购入库'!$I$4:$I$2003,$A54)) -> 0 | G54: =IF(A54="",0,SUMIFS('[1]销售出库'!$R$4:$R$2003,'[1]销售出库'!$H$4:$H$2003,$A54)) -> 0 | H54: =IF(C54+E54>0,ROUND((D54+F54)/(C54+E54),4),0) -> 7325 | I54: =ROUND(G54*H54,2) -> 0 | J54: =C54+E54-G54 -> 8 | K54: =ROUND(D54+F54-I54,2) -> 58600 | L54: =IF(A54="","",IF(J54<0,"负库存：漏记采购或期初不准",IF(AND(G54>0,C54+E54=0),"没进货就卖了",""))) | M54: =IF($A54="",0,SUMIFS('[1]销售出库'!$R$4:$R$2003,'[1]销售出库'!$H$4:$H$2003,$A54,'[1]销售出库'!$Q$4:$Q$2003,'首页'!$B$4*100+M$4)) -> 0 | N54: =IF($A54="",0,SUMIFS('[1]销售出库'!$R$4:$R$2003,'[1]销售出库'!$H$4:$H$2003,$A54,'[1]销售出库'!$Q$4:$Q$2003,'首页'!$B$4*100+N$4)) -> 0 | O54: =IF($A54="",0,SUMIFS('[1]销售出库'!$R$4:$R$2003,'[1]销售出库'!$H$4:$H$2003,$A54,'[1]销售出库'!$Q$4:$Q$2003,'首页'!$B$4*100+O$4)) -> 0 | P54: =IF($A54="",0,SUMIFS('[1]销售出库'!$R$4:$R$2003,'[1]销售出库'!$H$4:$H$2003,$A54,'[1]销售出库'!$Q$4:$Q$2003,'首页'!$B$4*100+P$4)) -> 0 | Q54: =IF($A54="",0,SUMIFS('[1]销售出库'!$R$4:$R$2003,'[1]销售出库'!$H$4:$H$2003,$A54,'[1]销售出库'!$Q$4:$Q$2003,'首页'!$B$4*100+Q$4)) -> 0 | R54: =IF($A54="",0,SUMIFS('[1]销售出库'!$R$4:$R$2003,'[1]销售出库'!$H$4:$H$2003,$A54,'[1]销售出库'!$Q$4:$Q$2003,'首页'!$B$4*100+R$4)) -> 0 | S54: =IF($A54="",0,SUMIFS('[1]销售出库'!$R$4:$R$2003,'[1]销售出库'!$H$4:$H$2003,$A54,'[1]销售出库'!$Q$4:$Q$2003,'首页'!$B$4*100+S$4)) -> 0 | T54: =IF($A54="",0,SUMIFS('[1]销售出库'!$R$4:$R$2003,'[1]销售出库'!$H$4:$H$2003,$A54,'[1]销售出库'!$Q$4:$Q$2003,'首页'!$B$4*100+T$4)) -> 0 | ... X54: =IF($A54="",0,SUMIFS('[1]销售出库'!$R$4:$R$2003,'[1]销售出库'!$H$4:$H$2003,$A54,'[1]销售出库'!$Q$4:$Q$2003,'首页'!$B$4*100+X$4)) -> 0
A55: =IF('[1]基础资料'!$P$54="","",'[1]基础资料'!$P$54) -> 小新14C R7-8745Hs-16G-512G-灰色 | B55: =IF(A55="","",'[1]基础资料'!$Q$54&"") -> 联想 | C55: =IF(A55="",0,N('[1]基础资料'!$S$54)) -> 15 | D55: =IF(A55="",0,N('[1]基础资料'!$U$54)) -> 60707.14 | E55: =IF(A55="",0,SUMIFS('[1]采购入库'!$U$4:$U$2003,'[1]采购入库'!$I$4:$I$2003,$A55)) -> 0 | F55: =IF(A55="",0,SUMIFS('[1]采购入库'!$V$4:$V$2003,'[1]采购入库'!$I$4:$I$2003,$A55)) -> 0 | G55: =IF(A55="",0,SUMIFS('[1]销售出库'!$R$4:$R$2003,'[1]销售出库'!$H$4:$H$2003,$A55)) -> 5 | H55: =IF(C55+E55>0,ROUND((D55+F55)/(C55+E55),4),0) -> 4047.1427 | I55: =ROUND(G55*H55,2) -> 20235.71 | J55: =C55+E55-G55 -> 10 | K55: =ROUND(D55+F55-I55,2) -> 40471.43 | L55: =IF(A55="","",IF(J55<0,"负库存：漏记采购或期初不准",IF(AND(G55>0,C55+E55=0),"没进货就卖了",""))) | M55: =IF($A55="",0,SUMIFS('[1]销售出库'!$R$4:$R$2003,'[1]销售出库'!$H$4:$H$2003,$A55,'[1]销售出库'!$Q$4:$Q$2003,'首页'!$B$4*100+M$4)) -> 0 | N55: =IF($A55="",0,SUMIFS('[1]销售出库'!$R$4:$R$2003,'[1]销售出库'!$H$4:$H$2003,$A55,'[1]销售出库'!$Q$4:$Q$2003,'首页'!$B$4*100+N$4)) -> 0 | O55: =IF($A55="",0,SUMIFS('[1]销售出库'!$R$4:$R$2003,'[1]销售出库'!$H$4:$H$2003,$A55,'[1]销售出库'!$Q$4:$Q$2003,'首页'!$B$4*100+O$4)) -> 0 | P55: =IF($A55="",0,SUMIFS('[1]销售出库'!$R$4:$R$2003,'[1]销售出库'!$H$4:$H$2003,$A55,'[1]销售出库'!$Q$4:$Q$2003,'首页'!$B$4*100+P$4)) -> 0 | Q55: =IF($A55="",0,SUMIFS('[1]销售出库'!$R$4:$R$2003,'[1]销售出库'!$H$4:$H$2003,$A55,'[1]销售出库'!$Q$4:$Q$2003,'首页'!$B$4*100+Q$4)) -> 0 | R55: =IF($A55="",0,SUMIFS('[1]销售出库'!$R$4:$R$2003,'[1]销售出库'!$H$4:$H$2003,$A55,'[1]销售出库'!$Q$4:$Q$2003,'首页'!$B$4*100+R$4)) -> 0 | S55: =IF($A55="",0,SUMIFS('[1]销售出库'!$R$4:$R$2003,'[1]销售出库'!$H$4:$H$2003,$A55,'[1]销售出库'!$Q$4:$Q$2003,'首页'!$B$4*100+S$4)) -> 0 | T55: =IF($A55="",0,SUMIFS('[1]销售出库'!$R$4:$R$2003,'[1]销售出库'!$H$4:$H$2003,$A55,'[1]销售出库'!$Q$4:$Q$2003,'首页'!$B$4*100+T$4)) -> 0 | ... X55: =IF($A55="",0,SUMIFS('[1]销售出库'!$R$4:$R$2003,'[1]销售出库'!$H$4:$H$2003,$A55,'[1]销售出库'!$Q$4:$Q$2003,'首页'!$B$4*100+X$4)) -> 0
A56: =IF('[1]基础资料'!$P$55="","",'[1]基础资料'!$P$55) -> 华硕主机固态硬盘1T | B56: =IF(A56="","",'[1]基础资料'!$Q$55&"") -> 配件 | C56: =IF(A56="",0,N('[1]基础资料'!$S$55)) -> 70 | D56: =IF(A56="",0,N('[1]基础资料'!$U$55)) -> 61600 | E56: =IF(A56="",0,SUMIFS('[1]采购入库'!$U$4:$U$2003,'[1]采购入库'!$I$4:$I$2003,$A56)) -> 0 | F56: =IF(A56="",0,SUMIFS('[1]采购入库'!$V$4:$V$2003,'[1]采购入库'!$I$4:$I$2003,$A56)) -> 0 | G56: =IF(A56="",0,SUMIFS('[1]销售出库'!$R$4:$R$2003,'[1]销售出库'!$H$4:$H$2003,$A56)) -> 0 | H56: =IF(C56+E56>0,ROUND((D56+F56)/(C56+E56),4),0) -> 880 | I56: =ROUND(G56*H56,2) -> 0 | J56: =C56+E56-G56 -> 70 | K56: =ROUND(D56+F56-I56,2) -> 61600 | L56: =IF(A56="","",IF(J56<0,"负库存：漏记采购或期初不准",IF(AND(G56>0,C56+E56=0),"没进货就卖了",""))) | M56: =IF($A56="",0,SUMIFS('[1]销售出库'!$R$4:$R$2003,'[1]销售出库'!$H$4:$H$2003,$A56,'[1]销售出库'!$Q$4:$Q$2003,'首页'!$B$4*100+M$4)) -> 0 | N56: =IF($A56="",0,SUMIFS('[1]销售出库'!$R$4:$R$2003,'[1]销售出库'!$H$4:$H$2003,$A56,'[1]销售出库'!$Q$4:$Q$2003,'首页'!$B$4*100+N$4)) -> 0 | O56: =IF($A56="",0,SUMIFS('[1]销售出库'!$R$4:$R$2003,'[1]销售出库'!$H$4:$H$2003,$A56,'[1]销售出库'!$Q$4:$Q$2003,'首页'!$B$4*100+O$4)) -> 0 | P56: =IF($A56="",0,SUMIFS('[1]销售出库'!$R$4:$R$2003,'[1]销售出库'!$H$4:$H$2003,$A56,'[1]销售出库'!$Q$4:$Q$2003,'首页'!$B$4*100+P$4)) -> 0 | Q56: =IF($A56="",0,SUMIFS('[1]销售出库'!$R$4:$R$2003,'[1]销售出库'!$H$4:$H$2003,$A56,'[1]销售出库'!$Q$4:$Q$2003,'首页'!$B$4*100+Q$4)) -> 0 | R56: =IF($A56="",0,SUMIFS('[1]销售出库'!$R$4:$R$2003,'[1]销售出库'!$H$4:$H$2003,$A56,'[1]销售出库'!$Q$4:$Q$2003,'首页'!$B$4*100+R$4)) -> 0 | S56: =IF($A56="",0,SUMIFS('[1]销售出库'!$R$4:$R$2003,'[1]销售出库'!$H$4:$H$2003,$A56,'[1]销售出库'!$Q$4:$Q$2003,'首页'!$B$4*100+S$4)) -> 0 | T56: =IF($A56="",0,SUMIFS('[1]销售出库'!$R$4:$R$2003,'[1]销售出库'!$H$4:$H$2003,$A56,'[1]销售出库'!$Q$4:$Q$2003,'首页'!$B$4*100+T$4)) -> 0 | ... X56: =IF($A56="",0,SUMIFS('[1]销售出库'!$R$4:$R$2003,'[1]销售出库'!$H$4:$H$2003,$A56,'[1]销售出库'!$Q$4:$Q$2003,'首页'!$B$4*100+X$4)) -> 0
A57: =IF('[1]基础资料'!$P$56="","",'[1]基础资料'!$P$56) -> 联想小新Pro16 GT 酷睿版 Ultra5 225H 32GB+1TB | B57: =IF(A57="","",'[1]基础资料'!$Q$56&"") -> 联想 | C57: =IF(A57="",0,N('[1]基础资料'!$S$56)) -> 18 | D57: =IF(A57="",0,N('[1]基础资料'!$U$56)) -> 131324.21 | E57: =IF(A57="",0,SUMIFS('[1]采购入库'!$U$4:$U$2003,'[1]采购入库'!$I$4:$I$2003,$A57)) -> 0 | F57: =IF(A57="",0,SUMIFS('[1]采购入库'!$V$4:$V$2003,'[1]采购入库'!$I$4:$I$2003,$A57)) -> 0 | G57: =IF(A57="",0,SUMIFS('[1]销售出库'!$R$4:$R$2003,'[1]销售出库'!$H$4:$H$2003,$A57)) -> 0 | H57: =IF(C57+E57>0,ROUND((D57+F57)/(C57+E57),4),0) -> 7295.7894 | I57: =ROUND(G57*H57,2) -> 0 | J57: =C57+E57-G57 -> 18 | K57: =ROUND(D57+F57-I57,2) -> 131324.21 | L57: =IF(A57="","",IF(J57<0,"负库存：漏记采购或期初不准",IF(AND(G57>0,C57+E57=0),"没进货就卖了",""))) | M57: =IF($A57="",0,SUMIFS('[1]销售出库'!$R$4:$R$2003,'[1]销售出库'!$H$4:$H$2003,$A57,'[1]销售出库'!$Q$4:$Q$2003,'首页'!$B$4*100+M$4)) -> 0 | N57: =IF($A57="",0,SUMIFS('[1]销售出库'!$R$4:$R$2003,'[1]销售出库'!$H$4:$H$2003,$A57,'[1]销售出库'!$Q$4:$Q$2003,'首页'!$B$4*100+N$4)) -> 0 | O57: =IF($A57="",0,SUMIFS('[1]销售出库'!$R$4:$R$2003,'[1]销售出库'!$H$4:$H$2003,$A57,'[1]销售出库'!$Q$4:$Q$2003,'首页'!$B$4*100+O$4)) -> 0 | P57: =IF($A57="",0,SUMIFS('[1]销售出库'!$R$4:$R$2003,'[1]销售出库'!$H$4:$H$2003,$A57,'[1]销售出库'!$Q$4:$Q$2003,'首页'!$B$4*100+P$4)) -> 0 | Q57: =IF($A57="",0,SUMIFS('[1]销售出库'!$R$4:$R$2003,'[1]销售出库'!$H$4:$H$2003,$A57,'[1]销售出库'!$Q$4:$Q$2003,'首页'!$B$4*100+Q$4)) -> 0 | R57: =IF($A57="",0,SUMIFS('[1]销售出库'!$R$4:$R$2003,'[1]销售出库'!$H$4:$H$2003,$A57,'[1]销售出库'!$Q$4:$Q$2003,'首页'!$B$4*100+R$4)) -> 0 | S57: =IF($A57="",0,SUMIFS('[1]销售出库'!$R$4:$R$2003,'[1]销售出库'!$H$4:$H$2003,$A57,'[1]销售出库'!$Q$4:$Q$2003,'首页'!$B$4*100+S$4)) -> 0 | T57: =IF($A57="",0,SUMIFS('[1]销售出库'!$R$4:$R$2003,'[1]销售出库'!$H$4:$H$2003,$A57,'[1]销售出库'!$Q$4:$Q$2003,'首页'!$B$4*100+T$4)) -> 0 | ... X57: =IF($A57="",0,SUMIFS('[1]销售出库'!$R$4:$R$2003,'[1]销售出库'!$H$4:$H$2003,$A57,'[1]销售出库'!$Q$4:$Q$2003,'首页'!$B$4*100+X$4)) -> 0
A58: =IF('[1]基础资料'!$P$57="","",'[1]基础资料'!$P$57) -> 天选6 FA608UH260-锐龙7H260-16G-1T-RTX5050-青 | B58: =IF(A58="","",'[1]基础资料'!$Q$57&"") -> 华硕 | C58: =IF(A58="",0,N('[1]基础资料'!$S$57)) -> 35 | D58: =IF(A58="",0,N('[1]基础资料'!$U$57)) -> 231623.17 | E58: =IF(A58="",0,SUMIFS('[1]采购入库'!$U$4:$U$2003,'[1]采购入库'!$I$4:$I$2003,$A58)) -> 0 | F58: =IF(A58="",0,SUMIFS('[1]采购入库'!$V$4:$V$2003,'[1]采购入库'!$I$4:$I$2003,$A58)) -> 0 | G58: =IF(A58="",0,SUMIFS('[1]销售出库'!$R$4:$R$2003,'[1]销售出库'!$H$4:$H$2003,$A58)) -> 0 | H58: =IF(C58+E58>0,ROUND((D58+F58)/(C58+E58),4),0) -> 6617.8049 | I58: =ROUND(G58*H58,2) -> 0 | J58: =C58+E58-G58 -> 35 | K58: =ROUND(D58+F58-I58,2) -> 231623.17 | L58: =IF(A58="","",IF(J58<0,"负库存：漏记采购或期初不准",IF(AND(G58>0,C58+E58=0),"没进货就卖了",""))) | M58: =IF($A58="",0,SUMIFS('[1]销售出库'!$R$4:$R$2003,'[1]销售出库'!$H$4:$H$2003,$A58,'[1]销售出库'!$Q$4:$Q$2003,'首页'!$B$4*100+M$4)) -> 0 | N58: =IF($A58="",0,SUMIFS('[1]销售出库'!$R$4:$R$2003,'[1]销售出库'!$H$4:$H$2003,$A58,'[1]销售出库'!$Q$4:$Q$2003,'首页'!$B$4*100+N$4)) -> 0 | O58: =IF($A58="",0,SUMIFS('[1]销售出库'!$R$4:$R$2003,'[1]销售出库'!$H$4:$H$2003,$A58,'[1]销售出库'!$Q$4:$Q$2003,'首页'!$B$4*100+O$4)) -> 0 | P58: =IF($A58="",0,SUMIFS('[1]销售出库'!$R$4:$R$2003,'[1]销售出库'!$H$4:$H$2003,$A58,'[1]销售出库'!$Q$4:$Q$2003,'首页'!$B$4*100+P$4)) -> 0 | Q58: =IF($A58="",0,SUMIFS('[1]销售出库'!$R$4:$R$2003,'[1]销售出库'!$H$4:$H$2003,$A58,'[1]销售出库'!$Q$4:$Q$2003,'首页'!$B$4*100+Q$4)) -> 0 | R58: =IF($A58="",0,SUMIFS('[1]销售出库'!$R$4:$R$2003,'[1]销售出库'!$H$4:$H$2003,$A58,'[1]销售出库'!$Q$4:$Q$2003,'首页'!$B$4*100+R$4)) -> 0 | S58: =IF($A58="",0,SUMIFS('[1]销售出库'!$R$4:$R$2003,'[1]销售出库'!$H$4:$H$2003,$A58,'[1]销售出库'!$Q$4:$Q$2003,'首页'!$B$4*100+S$4)) -> 0 | T58: =IF($A58="",0,SUMIFS('[1]销售出库'!$R$4:$R$2003,'[1]销售出库'!$H$4:$H$2003,$A58,'[1]销售出库'!$Q$4:$Q$2003,'首页'!$B$4*100+T$4)) -> 0 | ... X58: =IF($A58="",0,SUMIFS('[1]销售出库'!$R$4:$R$2003,'[1]销售出库'!$H$4:$H$2003,$A58,'[1]销售出库'!$Q$4:$Q$2003,'首页'!$B$4*100+X$4)) -> 0
A59: =IF('[1]基础资料'!$P$58="","",'[1]基础资料'!$P$58) -> 天选6Pro FA608PM8940-锐龙9 R9-8940HX-16G-1T-RTX5060-2.5K-青 | B59: =IF(A59="","",'[1]基础资料'!$Q$58&"") -> 华硕 | C59: =IF(A59="",0,N('[1]基础资料'!$S$58)) -> 136 | D59: =IF(A59="",0,N('[1]基础资料'!$U$58)) -> 1037909.8 | E59: =IF(A59="",0,SUMIFS('[1]采购入库'!$U$4:$U$2003,'[1]采购入库'!$I$4:$I$2003,$A59)) -> 0 | F59: =IF(A59="",0,SUMIFS('[1]采购入库'!$V$4:$V$2003,'[1]采购入库'!$I$4:$I$2003,$A59)) -> 0 | G59: =IF(A59="",0,SUMIFS('[1]销售出库'!$R$4:$R$2003,'[1]销售出库'!$H$4:$H$2003,$A59)) -> 0 | H59: =IF(C59+E59>0,ROUND((D59+F59)/(C59+E59),4),0) -> 7631.6896 | I59: =ROUND(G59*H59,2) -> 0 | J59: =C59+E59-G59 -> 136 | K59: =ROUND(D59+F59-I59,2) -> 1037909.8 | L59: =IF(A59="","",IF(J59<0,"负库存：漏记采购或期初不准",IF(AND(G59>0,C59+E59=0),"没进货就卖了",""))) | M59: =IF($A59="",0,SUMIFS('[1]销售出库'!$R$4:$R$2003,'[1]销售出库'!$H$4:$H$2003,$A59,'[1]销售出库'!$Q$4:$Q$2003,'首页'!$B$4*100+M$4)) -> 0 | N59: =IF($A59="",0,SUMIFS('[1]销售出库'!$R$4:$R$2003,'[1]销售出库'!$H$4:$H$2003,$A59,'[1]销售出库'!$Q$4:$Q$2003,'首页'!$B$4*100+N$4)) -> 0 | O59: =IF($A59="",0,SUMIFS('[1]销售出库'!$R$4:$R$2003,'[1]销售出库'!$H$4:$H$2003,$A59,'[1]销售出库'!$Q$4:$Q$2003,'首页'!$B$4*100+O$4)) -> 0 | P59: =IF($A59="",0,SUMIFS('[1]销售出库'!$R$4:$R$2003,'[1]销售出库'!$H$4:$H$2003,$A59,'[1]销售出库'!$Q$4:$Q$2003,'首页'!$B$4*100+P$4)) -> 0 | Q59: =IF($A59="",0,SUMIFS('[1]销售出库'!$R$4:$R$2003,'[1]销售出库'!$H$4:$H$2003,$A59,'[1]销售出库'!$Q$4:$Q$2003,'首页'!$B$4*100+Q$4)) -> 0 | R59: =IF($A59="",0,SUMIFS('[1]销售出库'!$R$4:$R$2003,'[1]销售出库'!$H$4:$H$2003,$A59,'[1]销售出库'!$Q$4:$Q$2003,'首页'!$B$4*100+R$4)) -> 0 | S59: =IF($A59="",0,SUMIFS('[1]销售出库'!$R$4:$R$2003,'[1]销售出库'!$H$4:$H$2003,$A59,'[1]销售出库'!$Q$4:$Q$2003,'首页'!$B$4*100+S$4)) -> 0 | T59: =IF($A59="",0,SUMIFS('[1]销售出库'!$R$4:$R$2003,'[1]销售出库'!$H$4:$H$2003,$A59,'[1]销售出库'!$Q$4:$Q$2003,'首页'!$B$4*100+T$4)) -> 0 | ... X59: =IF($A59="",0,SUMIFS('[1]销售出库'!$R$4:$R$2003,'[1]销售出库'!$H$4:$H$2003,$A59,'[1]销售出库'!$Q$4:$Q$2003,'首页'!$B$4*100+X$4)) -> 0
A60: =IF('[1]基础资料'!$P$59="","",'[1]基础资料'!$P$59) -> 天选6Pro FX608JP13650 I7-13650HX-16G-1TB-5070-8G-灰165Hz | B60: =IF(A60="","",'[1]基础资料'!$Q$59&"") -> 华硕 | C60: =IF(A60="",0,N('[1]基础资料'!$S$59)) -> 16 | D60: =IF(A60="",0,N('[1]基础资料'!$U$59)) -> 133543.53 | E60: =IF(A60="",0,SUMIFS('[1]采购入库'!$U$4:$U$2003,'[1]采购入库'!$I$4:$I$2003,$A60)) -> 0 | F60: =IF(A60="",0,SUMIFS('[1]采购入库'!$V$4:$V$2003,'[1]采购入库'!$I$4:$I$2003,$A60)) -> 0 | G60: =IF(A60="",0,SUMIFS('[1]销售出库'!$R$4:$R$2003,'[1]销售出库'!$H$4:$H$2003,$A60)) -> 0 | H60: =IF(C60+E60>0,ROUND((D60+F60)/(C60+E60),4),0) -> 8346.4706 | I60: =ROUND(G60*H60,2) -> 0 | J60: =C60+E60-G60 -> 16 | K60: =ROUND(D60+F60-I60,2) -> 133543.53 | L60: =IF(A60="","",IF(J60<0,"负库存：漏记采购或期初不准",IF(AND(G60>0,C60+E60=0),"没进货就卖了",""))) | M60: =IF($A60="",0,SUMIFS('[1]销售出库'!$R$4:$R$2003,'[1]销售出库'!$H$4:$H$2003,$A60,'[1]销售出库'!$Q$4:$Q$2003,'首页'!$B$4*100+M$4)) -> 0 | N60: =IF($A60="",0,SUMIFS('[1]销售出库'!$R$4:$R$2003,'[1]销售出库'!$H$4:$H$2003,$A60,'[1]销售出库'!$Q$4:$Q$2003,'首页'!$B$4*100+N$4)) -> 0 | O60: =IF($A60="",0,SUMIFS('[1]销售出库'!$R$4:$R$2003,'[1]销售出库'!$H$4:$H$2003,$A60,'[1]销售出库'!$Q$4:$Q$2003,'首页'!$B$4*100+O$4)) -> 0 | P60: =IF($A60="",0,SUMIFS('[1]销售出库'!$R$4:$R$2003,'[1]销售出库'!$H$4:$H$2003,$A60,'[1]销售出库'!$Q$4:$Q$2003,'首页'!$B$4*100+P$4)) -> 0 | Q60: =IF($A60="",0,SUMIFS('[1]销售出库'!$R$4:$R$2003,'[1]销售出库'!$H$4:$H$2003,$A60,'[1]销售出库'!$Q$4:$Q$2003,'首页'!$B$4*100+Q$4)) -> 0 | R60: =IF($A60="",0,SUMIFS('[1]销售出库'!$R$4:$R$2003,'[1]销售出库'!$H$4:$H$2003,$A60,'[1]销售出库'!$Q$4:$Q$2003,'首页'!$B$4*100+R$4)) -> 0 | S60: =IF($A60="",0,SUMIFS('[1]销售出库'!$R$4:$R$2003,'[1]销售出库'!$H$4:$H$2003,$A60,'[1]销售出库'!$Q$4:$Q$2003,'首页'!$B$4*100+S$4)) -> 0 | T60: =IF($A60="",0,SUMIFS('[1]销售出库'!$R$4:$R$2003,'[1]销售出库'!$H$4:$H$2003,$A60,'[1]销售出库'!$Q$4:$Q$2003,'首页'!$B$4*100+T$4)) -> 0 | ... X60: =IF($A60="",0,SUMIFS('[1]销售出库'!$R$4:$R$2003,'[1]销售出库'!$H$4:$H$2003,$A60,'[1]销售出库'!$Q$4:$Q$2003,'首页'!$B$4*100+X$4)) -> 0
A61: =IF('[1]基础资料'!$P$60="","",'[1]基础资料'!$P$60) -> 天选6 FA608UH260-锐龙7-16G-512G-RTX5050-高色域-灰 | B61: =IF(A61="","",'[1]基础资料'!$Q$60&"") -> 华硕 | C61: =IF(A61="",0,N('[1]基础资料'!$S$60)) -> 87 | D61: =IF(A61="",0,N('[1]基础资料'!$U$60)) -> 523018.92 | E61: =IF(A61="",0,SUMIFS('[1]采购入库'!$U$4:$U$2003,'[1]采购入库'!$I$4:$I$2003,$A61)) -> 0 | F61: =IF(A61="",0,SUMIFS('[1]采购入库'!$V$4:$V$2003,'[1]采购入库'!$I$4:$I$2003,$A61)) -> 0 | G61: =IF(A61="",0,SUMIFS('[1]销售出库'!$R$4:$R$2003,'[1]销售出库'!$H$4:$H$2003,$A61)) -> 0 | H61: =IF(C61+E61>0,ROUND((D61+F61)/(C61+E61),4),0) -> 6011.7117 | I61: =ROUND(G61*H61,2) -> 0 | J61: =C61+E61-G61 -> 87 | K61: =ROUND(D61+F61-I61,2) -> 523018.92 | L61: =IF(A61="","",IF(J61<0,"负库存：漏记采购或期初不准",IF(AND(G61>0,C61+E61=0),"没进货就卖了",""))) | M61: =IF($A61="",0,SUMIFS('[1]销售出库'!$R$4:$R$2003,'[1]销售出库'!$H$4:$H$2003,$A61,'[1]销售出库'!$Q$4:$Q$2003,'首页'!$B$4*100+M$4)) -> 0 | N61: =IF($A61="",0,SUMIFS('[1]销售出库'!$R$4:$R$2003,'[1]销售出库'!$H$4:$H$2003,$A61,'[1]销售出库'!$Q$4:$Q$2003,'首页'!$B$4*100+N$4)) -> 0 | O61: =IF($A61="",0,SUMIFS('[1]销售出库'!$R$4:$R$2003,'[1]销售出库'!$H$4:$H$2003,$A61,'[1]销售出库'!$Q$4:$Q$2003,'首页'!$B$4*100+O$4)) -> 0 | P61: =IF($A61="",0,SUMIFS('[1]销售出库'!$R$4:$R$2003,'[1]销售出库'!$H$4:$H$2003,$A61,'[1]销售出库'!$Q$4:$Q$2003,'首页'!$B$4*100+P$4)) -> 0 | Q61: =IF($A61="",0,SUMIFS('[1]销售出库'!$R$4:$R$2003,'[1]销售出库'!$H$4:$H$2003,$A61,'[1]销售出库'!$Q$4:$Q$2003,'首页'!$B$4*100+Q$4)) -> 0 | R61: =IF($A61="",0,SUMIFS('[1]销售出库'!$R$4:$R$2003,'[1]销售出库'!$H$4:$H$2003,$A61,'[1]销售出库'!$Q$4:$Q$2003,'首页'!$B$4*100+R$4)) -> 0 | S61: =IF($A61="",0,SUMIFS('[1]销售出库'!$R$4:$R$2003,'[1]销售出库'!$H$4:$H$2003,$A61,'[1]销售出库'!$Q$4:$Q$2003,'首页'!$B$4*100+S$4)) -> 0 | T61: =IF($A61="",0,SUMIFS('[1]销售出库'!$R$4:$R$2003,'[1]销售出库'!$H$4:$H$2003,$A61,'[1]销售出库'!$Q$4:$Q$2003,'首页'!$B$4*100+T$4)) -> 0 | ... X61: =IF($A61="",0,SUMIFS('[1]销售出库'!$R$4:$R$2003,'[1]销售出库'!$H$4:$H$2003,$A61,'[1]销售出库'!$Q$4:$Q$2003,'首页'!$B$4*100+X$4)) -> 0
A62: =IF('[1]基础资料'!$P$61="","",'[1]基础资料'!$P$61) -> 来酷斗战者-战7000P 锐龙9 R9-8940HX-16G-512G-RTX5060 | B62: =IF(A62="","",'[1]基础资料'!$Q$61&"") -> 联想 | C62: =IF(A62="",0,N('[1]基础资料'!$S$61)) -> 8 | D62: =IF(A62="",0,N('[1]基础资料'!$U$61)) -> 68610 | E62: =IF(A62="",0,SUMIFS('[1]采购入库'!$U$4:$U$2003,'[1]采购入库'!$I$4:$I$2003,$A62)) -> 0 | F62: =IF(A62="",0,SUMIFS('[1]采购入库'!$V$4:$V$2003,'[1]采购入库'!$I$4:$I$2003,$A62)) -> 0 | G62: =IF(A62="",0,SUMIFS('[1]销售出库'!$R$4:$R$2003,'[1]销售出库'!$H$4:$H$2003,$A62)) -> 0 | H62: =IF(C62+E62>0,ROUND((D62+F62)/(C62+E62),4),0) -> 8576.25 | I62: =ROUND(G62*H62,2) -> 0 | J62: =C62+E62-G62 -> 8 | K62: =ROUND(D62+F62-I62,2) -> 68610 | L62: =IF(A62="","",IF(J62<0,"负库存：漏记采购或期初不准",IF(AND(G62>0,C62+E62=0),"没进货就卖了",""))) | M62: =IF($A62="",0,SUMIFS('[1]销售出库'!$R$4:$R$2003,'[1]销售出库'!$H$4:$H$2003,$A62,'[1]销售出库'!$Q$4:$Q$2003,'首页'!$B$4*100+M$4)) -> 0 | N62: =IF($A62="",0,SUMIFS('[1]销售出库'!$R$4:$R$2003,'[1]销售出库'!$H$4:$H$2003,$A62,'[1]销售出库'!$Q$4:$Q$2003,'首页'!$B$4*100+N$4)) -> 0 | O62: =IF($A62="",0,SUMIFS('[1]销售出库'!$R$4:$R$2003,'[1]销售出库'!$H$4:$H$2003,$A62,'[1]销售出库'!$Q$4:$Q$2003,'首页'!$B$4*100+O$4)) -> 0 | P62: =IF($A62="",0,SUMIFS('[1]销售出库'!$R$4:$R$2003,'[1]销售出库'!$H$4:$H$2003,$A62,'[1]销售出库'!$Q$4:$Q$2003,'首页'!$B$4*100+P$4)) -> 0 | Q62: =IF($A62="",0,SUMIFS('[1]销售出库'!$R$4:$R$2003,'[1]销售出库'!$H$4:$H$2003,$A62,'[1]销售出库'!$Q$4:$Q$2003,'首页'!$B$4*100+Q$4)) -> 0 | R62: =IF($A62="",0,SUMIFS('[1]销售出库'!$R$4:$R$2003,'[1]销售出库'!$H$4:$H$2003,$A62,'[1]销售出库'!$Q$4:$Q$2003,'首页'!$B$4*100+R$4)) -> 0 | S62: =IF($A62="",0,SUMIFS('[1]销售出库'!$R$4:$R$2003,'[1]销售出库'!$H$4:$H$2003,$A62,'[1]销售出库'!$Q$4:$Q$2003,'首页'!$B$4*100+S$4)) -> 0 | T62: =IF($A62="",0,SUMIFS('[1]销售出库'!$R$4:$R$2003,'[1]销售出库'!$H$4:$H$2003,$A62,'[1]销售出库'!$Q$4:$Q$2003,'首页'!$B$4*100+T$4)) -> 0 | ... X62: =IF($A62="",0,SUMIFS('[1]销售出库'!$R$4:$R$2003,'[1]销售出库'!$H$4:$H$2003,$A62,'[1]销售出库'!$Q$4:$Q$2003,'首页'!$B$4*100+X$4)) -> 0
A63: =IF('[1]基础资料'!$P$62="","",'[1]基础资料'!$P$62) -> 电脑配件 | B63: =IF(A63="","",'[1]基础资料'!$Q$62&"") | C63: =IF(A63="",0,N('[1]基础资料'!$S$62)) -> 0 | D63: =IF(A63="",0,N('[1]基础资料'!$U$62)) -> 0 | E63: =IF(A63="",0,SUMIFS('[1]采购入库'!$U$4:$U$2003,'[1]采购入库'!$I$4:$I$2003,$A63)) -> 2583464.5 | F63: =IF(A63="",0,SUMIFS('[1]采购入库'!$V$4:$V$2003,'[1]采购入库'!$I$4:$I$2003,$A63)) -> 27321.65 | G63: =IF(A63="",0,SUMIFS('[1]销售出库'!$R$4:$R$2003,'[1]销售出库'!$H$4:$H$2003,$A63)) -> 2583464.5 | H63: =IF(C63+E63>0,ROUND((D63+F63)/(C63+E63),4),0) -> 0.0106 | I63: =ROUND(G63*H63,2) -> 27384.72 | J63: =C63+E63-G63 -> 0 | K63: =ROUND(D63+F63-I63,2) -> -63.07 | L63: =IF(A63="","",IF(J63<0,"负库存：漏记采购或期初不准",IF(AND(G63>0,C63+E63=0),"没进货就卖了",""))) | M63: =IF($A63="",0,SUMIFS('[1]销售出库'!$R$4:$R$2003,'[1]销售出库'!$H$4:$H$2003,$A63,'[1]销售出库'!$Q$4:$Q$2003,'首页'!$B$4*100+M$4)) -> 0 | N63: =IF($A63="",0,SUMIFS('[1]销售出库'!$R$4:$R$2003,'[1]销售出库'!$H$4:$H$2003,$A63,'[1]销售出库'!$Q$4:$Q$2003,'首页'!$B$4*100+N$4)) -> 0 | O63: =IF($A63="",0,SUMIFS('[1]销售出库'!$R$4:$R$2003,'[1]销售出库'!$H$4:$H$2003,$A63,'[1]销售出库'!$Q$4:$Q$2003,'首页'!$B$4*100+O$4)) -> 0 | P63: =IF($A63="",0,SUMIFS('[1]销售出库'!$R$4:$R$2003,'[1]销售出库'!$H$4:$H$2003,$A63,'[1]销售出库'!$Q$4:$Q$2003,'首页'!$B$4*100+P$4)) -> 0 | Q63: =IF($A63="",0,SUMIFS('[1]销售出库'!$R$4:$R$2003,'[1]销售出库'!$H$4:$H$2003,$A63,'[1]销售出库'!$Q$4:$Q$2003,'首页'!$B$4*100+Q$4)) -> 0 | R63: =IF($A63="",0,SUMIFS('[1]销售出库'!$R$4:$R$2003,'[1]销售出库'!$H$4:$H$2003,$A63,'[1]销售出库'!$Q$4:$Q$2003,'首页'!$B$4*100+R$4)) -> 0 | S63: =IF($A63="",0,SUMIFS('[1]销售出库'!$R$4:$R$2003,'[1]销售出库'!$H$4:$H$2003,$A63,'[1]销售出库'!$Q$4:$Q$2003,'首页'!$B$4*100+S$4)) -> 0 | T63: =IF($A63="",0,SUMIFS('[1]销售出库'!$R$4:$R$2003,'[1]销售出库'!$H$4:$H$2003,$A63,'[1]销售出库'!$Q$4:$Q$2003,'首页'!$B$4*100+T$4)) -> 0 | ... X63: =IF($A63="",0,SUMIFS('[1]销售出库'!$R$4:$R$2003,'[1]销售出库'!$H$4:$H$2003,$A63,'[1]销售出库'!$Q$4:$Q$2003,'首页'!$B$4*100+X$4)) -> 0
A64: =IF('[1]基础资料'!$P$63="","",'[1]基础资料'!$P$63) -> 联想小新16c I5-13420H 16+512灰 | B64: =IF(A64="","",'[1]基础资料'!$Q$63&"") -> 联想 | C64: =IF(A64="",0,N('[1]基础资料'!$S$63)) -> 0 | D64: =IF(A64="",0,N('[1]基础资料'!$U$63)) -> 0 | E64: =IF(A64="",0,SUMIFS('[1]采购入库'!$U$4:$U$2003,'[1]采购入库'!$I$4:$I$2003,$A64)) -> 59 | F64: =IF(A64="",0,SUMIFS('[1]采购入库'!$V$4:$V$2003,'[1]采购入库'!$I$4:$I$2003,$A64)) -> 295590 | G64: =IF(A64="",0,SUMIFS('[1]销售出库'!$R$4:$R$2003,'[1]销售出库'!$H$4:$H$2003,$A64)) -> 186 | H64: =IF(C64+E64>0,ROUND((D64+F64)/(C64+E64),4),0) -> 5010 | I64: =ROUND(G64*H64,2) -> 931860 | J64: =C64+E64-G64 -> -127 | K64: =ROUND(D64+F64-I64,2) -> -636270 | L64: =IF(A64="","",IF(J64<0,"负库存：漏记采购或期初不准",IF(AND(G64>0,C64+E64=0),"没进货就卖了",""))) -> 负库存：漏记采购或期初不准 | M64: =IF($A64="",0,SUMIFS('[1]销售出库'!$R$4:$R$2003,'[1]销售出库'!$H$4:$H$2003,$A64,'[1]销售出库'!$Q$4:$Q$2003,'首页'!$B$4*100+M$4)) -> 0 | N64: =IF($A64="",0,SUMIFS('[1]销售出库'!$R$4:$R$2003,'[1]销售出库'!$H$4:$H$2003,$A64,'[1]销售出库'!$Q$4:$Q$2003,'首页'!$B$4*100+N$4)) -> 0 | O64: =IF($A64="",0,SUMIFS('[1]销售出库'!$R$4:$R$2003,'[1]销售出库'!$H$4:$H$2003,$A64,'[1]销售出库'!$Q$4:$Q$2003,'首页'!$B$4*100+O$4)) -> 0 | P64: =IF($A64="",0,SUMIFS('[1]销售出库'!$R$4:$R$2003,'[1]销售出库'!$H$4:$H$2003,$A64,'[1]销售出库'!$Q$4:$Q$2003,'首页'!$B$4*100+P$4)) -> 0 | Q64: =IF($A64="",0,SUMIFS('[1]销售出库'!$R$4:$R$2003,'[1]销售出库'!$H$4:$H$2003,$A64,'[1]销售出库'!$Q$4:$Q$2003,'首页'!$B$4*100+Q$4)) -> 0 | R64: =IF($A64="",0,SUMIFS('[1]销售出库'!$R$4:$R$2003,'[1]销售出库'!$H$4:$H$2003,$A64,'[1]销售出库'!$Q$4:$Q$2003,'首页'!$B$4*100+R$4)) -> 0 | S64: =IF($A64="",0,SUMIFS('[1]销售出库'!$R$4:$R$2003,'[1]销售出库'!$H$4:$H$2003,$A64,'[1]销售出库'!$Q$4:$Q$2003,'首页'!$B$4*100+S$4)) -> 0 | T64: =IF($A64="",0,SUMIFS('[1]销售出库'!$R$4:$R$2003,'[1]销售出库'!$H$4:$H$2003,$A64,'[1]销售出库'!$Q$4:$Q$2003,'首页'!$B$4*100+T$4)) -> 0 | ... X64: =IF($A64="",0,SUMIFS('[1]销售出库'!$R$4:$R$2003,'[1]销售出库'!$H$4:$H$2003,$A64,'[1]销售出库'!$Q$4:$Q$2003,'首页'!$B$4*100+X$4)) -> 0
A65: =IF('[1]基础资料'!$P$64="","",'[1]基础资料'!$P$64) -> 联想Y7000P U7-255H-16G-1T-RTX5060黑色（一手） | B65: =IF(A65="","",'[1]基础资料'!$Q$64&"") -> 联想 | C65: =IF(A65="",0,N('[1]基础资料'!$S$64)) -> 0 | D65: =IF(A65="",0,N('[1]基础资料'!$U$64)) -> 0 | E65: =IF(A65="",0,SUMIFS('[1]采购入库'!$U$4:$U$2003,'[1]采购入库'!$I$4:$I$2003,$A65)) -> 53 | F65: =IF(A65="",0,SUMIFS('[1]采购入库'!$V$4:$V$2003,'[1]采购入库'!$I$4:$I$2003,$A65)) -> 694300 | G65: =IF(A65="",0,SUMIFS('[1]销售出库'!$R$4:$R$2003,'[1]销售出库'!$H$4:$H$2003,$A65)) -> 53 | H65: =IF(C65+E65>0,ROUND((D65+F65)/(C65+E65),4),0) -> 13100 | I65: =ROUND(G65*H65,2) -> 694300 | J65: =C65+E65-G65 -> 0 | K65: =ROUND(D65+F65-I65,2) -> 0 | L65: =IF(A65="","",IF(J65<0,"负库存：漏记采购或期初不准",IF(AND(G65>0,C65+E65=0),"没进货就卖了",""))) | M65: =IF($A65="",0,SUMIFS('[1]销售出库'!$R$4:$R$2003,'[1]销售出库'!$H$4:$H$2003,$A65,'[1]销售出库'!$Q$4:$Q$2003,'首页'!$B$4*100+M$4)) -> 0 | N65: =IF($A65="",0,SUMIFS('[1]销售出库'!$R$4:$R$2003,'[1]销售出库'!$H$4:$H$2003,$A65,'[1]销售出库'!$Q$4:$Q$2003,'首页'!$B$4*100+N$4)) -> 0 | O65: =IF($A65="",0,SUMIFS('[1]销售出库'!$R$4:$R$2003,'[1]销售出库'!$H$4:$H$2003,$A65,'[1]销售出库'!$Q$4:$Q$2003,'首页'!$B$4*100+O$4)) -> 0 | P65: =IF($A65="",0,SUMIFS('[1]销售出库'!$R$4:$R$2003,'[1]销售出库'!$H$4:$H$2003,$A65,'[1]销售出库'!$Q$4:$Q$2003,'首页'!$B$4*100+P$4)) -> 0 | Q65: =IF($A65="",0,SUMIFS('[1]销售出库'!$R$4:$R$2003,'[1]销售出库'!$H$4:$H$2003,$A65,'[1]销售出库'!$Q$4:$Q$2003,'首页'!$B$4*100+Q$4)) -> 0 | R65: =IF($A65="",0,SUMIFS('[1]销售出库'!$R$4:$R$2003,'[1]销售出库'!$H$4:$H$2003,$A65,'[1]销售出库'!$Q$4:$Q$2003,'首页'!$B$4*100+R$4)) -> 0 | S65: =IF($A65="",0,SUMIFS('[1]销售出库'!$R$4:$R$2003,'[1]销售出库'!$H$4:$H$2003,$A65,'[1]销售出库'!$Q$4:$Q$2003,'首页'!$B$4*100+S$4)) -> 0 | T65: =IF($A65="",0,SUMIFS('[1]销售出库'!$R$4:$R$2003,'[1]销售出库'!$H$4:$H$2003,$A65,'[1]销售出库'!$Q$4:$Q$2003,'首页'!$B$4*100+T$4)) -> 0 | ... X65: =IF($A65="",0,SUMIFS('[1]销售出库'!$R$4:$R$2003,'[1]销售出库'!$H$4:$H$2003,$A65,'[1]销售出库'!$Q$4:$Q$2003,'首页'!$B$4*100+X$4)) -> 0
